{
  "type": "Feature",
  "properties": {
    "addr:full":"30 W Main St Marianna AR 72360",
    "addr:housenumber":"30",
    "addr:postcode":"72360",
    "addr:street":"W Main St",
    "iso:country":"US",
    "sg:address":"30 W Main St",
    "sg:city":"Marianna",
    "sg:classifiers":[
        {
            "category":"Social Services",
            "type":"Services"
        }
    ],
    "sg:phone":"+1 870 295 5195",
    "sg:postcode":"72360",
    "sg:province":"AR",
    "wof:name":"Counsling Cons After Schl Prog",
    "wof:placetype":"venue"
},
  "geometry": {"coordinates":[-90.758233,34.773589],"type":"Point"}
}