{
  "type": "Feature",
  "properties": {
    "iso:country":"US",
    "sg:address":"165 Highland Dr",
    "sg:city":"Mountain View",
    "sg:classifiers":[
        {
            "category":"Home & Garden",
            "subcategory":"Household Appliances",
            "type":"Retail Goods"
        }
    ],
    "sg:phone":"+1 870 269 4530",
    "sg:postcode":"72560",
    "sg:province":"AR",
    "sg:tags":[
        "machine",
        "sewing"
    ],
    "wof:name":"Janome New Home",
    "wof:placetype":"venue"
},
  "geometry": {"coordinates":[-92.102775,35.893287],"type":"Point"}
}