{
  "type": "Feature",
  "properties": {
    "addr:full":"30 Acres Cir Greenbrier AR 72058",
    "addr:housenumber":"30",
    "addr:postcode":"72058",
    "addr:street":"Acres Cir",
    "iso:country":"US",
    "sg:address":"30 Acres Cir",
    "sg:city":"Greenbrier",
    "sg:classifiers":[
        {
            "category":"Retail",
            "subcategory":"Auto Repair",
            "type":"Services"
        }
    ],
    "sg:phone":"+1 501 679 4428",
    "sg:postcode":"72058",
    "sg:province":"AR",
    "wof:name":"Acre Farm Equipment",
    "wof:placetype":"venue"
},
  "geometry": {"coordinates":[-92.425338,35.288166],"type":"Point"}
}