{
  "type": "Feature",
  "properties": {
    "iso:country":"US",
    "sg:address":"1705 S State Line Ave",
    "sg:city":"Texarkana",
    "sg:classifiers":[
        {
            "category":"Building & Trades",
            "subcategory":"Construction",
            "type":"Services"
        }
    ],
    "sg:phone":"+1 870 772 1462",
    "sg:postcode":"71854",
    "sg:province":"AR",
    "sg:tags":[
        "painter"
    ],
    "wof:name":"Jones WJ Painting Contr",
    "wof:placetype":"venue"
},
  "geometry": {"coordinates":[-94.043029,33.405483],"type":"Point"}
}