{
  "type": "Feature",
  "properties": {
    "addr:full":"809 S Gutensohn Rd Springdale AR 72762",
    "addr:housenumber":"809",
    "addr:postcode":"72762",
    "addr:street":"S Gutensohn Rd",
    "iso:country":"US",
    "sg:address":"809 S Gutensohn Rd",
    "sg:city":"Springdale",
    "sg:classifiers":[
        {
            "category":"Professional",
            "subcategory":"Art Services",
            "type":"Services"
        }
    ],
    "sg:phone":"+1 479 750 2575",
    "sg:postcode":"72762",
    "sg:province":"AR",
    "sg:tags":[
        "photography",
        "commercial"
    ],
    "wof:name":"Hartsock Photography",
    "wof:placetype":"venue"
},
  "geometry": {"coordinates":[-94.16127299999999,36.178822],"type":"Point"}
}