{
  "type": "Feature",
  "properties": {
    "iso:country":"US",
    "sg:address":"4000 W 13th St",
    "sg:city":"Little Rock",
    "sg:classifiers":[
        {
            "category":"Organizations",
            "subcategory":"Religious Organization",
            "type":"Services"
        },
        {
            "category":"Health Services",
            "subcategory":"Clinic",
            "type":"Services"
        }
    ],
    "sg:phone":"+1 501 663 9621",
    "sg:postcode":"72204",
    "sg:province":"AR",
    "sg:tags":[
        "church",
        "aids",
        "testing",
        "information"
    ],
    "wof:name":"Black Community Development",
    "wof:placetype":"venue"
},
  "geometry": {"coordinates":[-92.31904,34.739639],"type":"Point"}
}