{
  "type": "Feature",
  "properties": {
    "iso:country":"US",
    "sg:address":"79 Spout Springs Dr",
    "sg:city":"Batesville",
    "sg:classifiers":[
        {
            "category":"Shopping",
            "subcategory":"Crafts & Fabrics",
            "type":"Retail Goods"
        }
    ],
    "sg:phone":"+1 870 251 3333",
    "sg:postcode":"72501",
    "sg:province":"AR",
    "sg:tags":[
        "monogram"
    ],
    "wof:name":"Cummings & Cummings",
    "wof:placetype":"venue"
},
  "geometry": {"coordinates":[-91.596132,35.688293],"type":"Point"}
}