{
  "type": "Feature",
  "properties": {
    "iso:country":"US",
    "sg:address":"1831 Butterfield Coach Rd",
    "sg:city":"Springdale",
    "sg:classifiers":[
        {
            "category":"Retail",
            "subcategory":"Auto Repair",
            "type":"Services"
        }
    ],
    "sg:phone":"+1 479 756 9302",
    "sg:postcode":"72764",
    "sg:province":"AR",
    "sg:tags":[
        "repairing",
        "automobile"
    ],
    "wof:name":"Sid's Auto Svc",
    "wof:placetype":"venue"
},
  "geometry": {"coordinates":[-94.094327,36.167744],"type":"Point"}
}