{
  "type": "Feature",
  "properties": {
    "addr:full":"3668 State Hwy 367 Searcy AR 72143",
    "addr:housenumber":"3668",
    "addr:postcode":"72143",
    "addr:street":"State Hwy 367",
    "iso:country":"US",
    "sg:address":"3668 State Hwy 367",
    "sg:city":"Searcy",
    "sg:classifiers":[
        {
            "category":"Autos & Motor Vehicles",
            "subcategory":"Automobile Sales",
            "type":"Retail Goods"
        }
    ],
    "sg:phone":"+1 501 268 0658",
    "sg:postcode":"72143",
    "sg:province":"AR",
    "sg:tags":[
        "car",
        "used",
        "dealer"
    ],
    "wof:name":"Marple Auto Sales Inc",
    "wof:placetype":"venue"
},
  "geometry": {"coordinates":[-91.73751300000001,35.178915],"type":"Point"}
}