{
  "type": "Feature",
  "properties": {
    "iso:country":"US",
    "sg:address":"804 Front St",
    "sg:city":"Conway",
    "sg:classifiers":[
        {
            "category":"Shopping",
            "subcategory":"Jewelry",
            "type":"Retail Goods"
        }
    ],
    "sg:phone":"+1 501 329 6332",
    "sg:postcode":"72032",
    "sg:province":"AR",
    "wof:name":"Dayer Jewelers",
    "wof:placetype":"venue"
},
  "geometry": {"coordinates":[-92.440749,35.090582],"type":"Point"}
}