{
  "type": "Feature",
  "properties": {
    "addr:full":"1500 Richard Prewitt Dr Osceola AR 72370",
    "addr:housenumber":"1500",
    "addr:postcode":"72370",
    "addr:street":"Richard Prewitt Dr",
    "iso:country":"US",
    "sg:address":"1500 Richard Prewitt Dr",
    "sg:city":"Osceola",
    "sg:classifiers":[
        {
            "category":"Manufacturing",
            "subcategory":"Rubber & Plastics",
            "type":"Manufacturing & Wholesale Goods"
        }
    ],
    "sg:phone":"+1 870 563 1600",
    "sg:postcode":"72370",
    "sg:province":"AR",
    "sg:tags":[
        "product",
        "plastics-finished-wholesale",
        "manufacturer"
    ],
    "wof:name":"Evonik Cyro",
    "wof:placetype":"venue"
},
  "geometry": {"coordinates":[-89.981689,35.68758],"type":"Point"}
}