{
  "type": "Feature",
  "properties": {
    "iso:country":"US",
    "sg:address":"3862 State Hwy 7",
    "sg:city":"Harrison",
    "sg:classifiers":[
        {
            "category":"Shopping",
            "subcategory":"Clothing, Apparel, & Fashions",
            "type":"Retail Goods"
        }
    ],
    "sg:phone":"+1 870 741 9413",
    "sg:postcode":"72601",
    "sg:province":"AR",
    "wof:name":"Holt Leather Co",
    "wof:placetype":"venue"
},
  "geometry": {"coordinates":[-93.121604,36.210593],"type":"Point"}
}