{
  "type": "Feature",
  "properties": {
    "iso:country":"US",
    "sg:address":"3841 State Hwy 83",
    "sg:city":"Star City",
    "sg:classifiers":[
        {
            "category":"Manufacturing",
            "subcategory":"Lumber",
            "type":"Manufacturing & Wholesale Goods"
        }
    ],
    "sg:phone":"+1 870 367 8051",
    "sg:postcode":"71655",
    "sg:province":"AR",
    "sg:tags":[
        "operator",
        "logging",
        "local",
        "trucking"
    ],
    "wof:name":"Strickland Bros Timber Contrs",
    "wof:placetype":"venue"
},
  "geometry": {"coordinates":[-91.75055,33.788281],"type":"Point"}
}