{
  "type": "Feature",
  "properties": {
    "addr:full":"1320 W Walnut St Rogers AR 72756",
    "addr:housenumber":"1320",
    "addr:postcode":"72756",
    "addr:street":"W Walnut St",
    "iso:country":"US",
    "sg:address":"1320 W Walnut St",
    "sg:city":"Rogers",
    "sg:classifiers":[
        {
            "category":"Shopping",
            "subcategory":"Photographic Equipment",
            "type":"Retail Goods"
        }
    ],
    "sg:phone":"+1 479 636 2424",
    "sg:postcode":"72756",
    "sg:province":"AR",
    "sg:tags":[
        "photography",
        "store",
        "supply"
    ],
    "sg:website":"www.bedfords.com",
    "wof:name":"Bedford Camera & Video",
    "wof:placetype":"venue"
},
  "geometry": {"coordinates":[-94.135902,36.3339],"type":"Point"}
}