{
  "type": "Feature",
  "properties": {
    "iso:country":"US",
    "sg:address":"268 Oak Ave",
    "sg:city":"Decatur",
    "sg:classifiers":[
        {
            "category":"Shopping",
            "type":"Retail Goods"
        }
    ],
    "sg:phone":"+1 479 426 7145",
    "sg:postcode":"72722",
    "sg:province":"AR",
    "sg:tags":[
        "merchandise"
    ],
    "wof:name":"Cosy Little Shop",
    "wof:placetype":"venue"
},
  "geometry": {"coordinates":[-94.462487,36.331771],"type":"Point"}
}