{
  "type": "Feature",
  "properties": {
    "addr:full":"806 North St Ward AR 72176",
    "addr:housenumber":"806",
    "addr:postcode":"72176",
    "addr:street":"North St",
    "iso:country":"US",
    "sg:address":"806 North St",
    "sg:city":"Ward",
    "sg:classifiers":[
        {
            "category":"Restaurant",
            "type":"Food & Drink"
        }
    ],
    "sg:phone":"+1 501 941 2688",
    "sg:postcode":"72176",
    "sg:province":"AR",
    "wof:name":"North St Diner",
    "wof:placetype":"venue"
},
  "geometry": {"coordinates":[-91.95654,35.03335],"type":"Point"}
}