{
  "type": "Feature",
  "properties": {
    "iso:country":"US",
    "sg:address":"151 Agee Ave SW",
    "sg:city":"Camden",
    "sg:classifiers":[
        {
            "category":"Building & Trades",
            "subcategory":"Construction",
            "type":"Services"
        }
    ],
    "sg:phone":"+1 870 836 2814",
    "sg:postcode":"71701",
    "sg:province":"AR",
    "sg:tags":[
        "repairing",
        "remodeling",
        "contractor"
    ],
    "wof:name":"Handy Man",
    "wof:placetype":"venue"
},
  "geometry": {"coordinates":[-92.843185,33.583707],"type":"Point"}
}