{
  "type": "Feature",
  "properties": {
    "addr:full":"18 E Township St Fayetteville AR 72703",
    "addr:housenumber":"18",
    "addr:postcode":"72703",
    "addr:street":"E Township St",
    "iso:country":"US",
    "sg:address":"18 E Township St",
    "sg:city":"Fayetteville",
    "sg:classifiers":[
        {
            "category":"Health Services",
            "subcategory":"Chiropractor",
            "type":"Services"
        }
    ],
    "sg:phone":"+1 479 444 9988",
    "sg:postcode":"72703",
    "sg:province":"AR",
    "wof:name":"Agape Chiropractic",
    "wof:placetype":"venue"
},
  "geometry": {"coordinates":[-94.156711,36.095347],"type":"Point"}
}