{
  "type": "Feature",
  "properties": {
    "iso:country":"US",
    "sg:address":"3200 Baseline Rd",
    "sg:city":"Little Rock",
    "sg:classifiers":[
        {
            "category":"Building & Trades",
            "subcategory":"Plumbing",
            "type":"Services"
        }
    ],
    "sg:phone":"+1 501 565 5988",
    "sg:postcode":"72209",
    "sg:province":"AR",
    "sg:tags":[
        "conditioning",
        "air",
        "system",
        "contractor"
    ],
    "wof:name":"Tropical Breeze Cooling & Htg",
    "wof:placetype":"venue"
},
  "geometry": {"coordinates":[-92.310511,34.667559],"type":"Point"}
}