{
  "type": "Feature",
  "properties": {
    "iso:country":"US",
    "sg:address":"627 Main St",
    "sg:city":"Bauxite",
    "sg:classifiers":[
        {
            "category":"Professional",
            "type":"Services"
        }
    ],
    "sg:phone":"+1 501 557 2884",
    "sg:postcode":"72011",
    "sg:province":"AR",
    "wof:name":"Robert Anderson",
    "wof:placetype":"venue"
},
  "geometry": {"coordinates":[-92.523734,34.55579],"type":"Point"}
}