{
  "type": "Feature",
  "properties": {
    "iso:country":"US",
    "sg:address":"231 W Dent St",
    "sg:city":"Eudora",
    "sg:classifiers":[
        {
            "category":"Health Services",
            "subcategory":"Doctor",
            "type":"Services"
        }
    ],
    "sg:phone":"+1 870 355 2300",
    "sg:postcode":"71640",
    "sg:province":"AR",
    "sg:tags":[
        "medical"
    ],
    "wof:name":"Eudora Medical Clinic",
    "wof:placetype":"venue"
},
  "geometry": {"coordinates":[-91.263864,33.115035],"type":"Point"}
}