{
  "type": "Feature",
  "properties": {
    "addr:full":"18323 Philis Dr Hensley AR 72065",
    "addr:postcode":"18323;72065",
    "addr:street":"Philis Dr",
    "iso:country":"US",
    "sg:address":"18323 Philis Dr",
    "sg:city":"Hensley",
    "sg:classifiers":[
        {
            "category":"Autos & Motor Vehicles",
            "subcategory":"Auto Supplies",
            "type":"Retail Goods"
        },
        {
            "category":"Retail",
            "subcategory":"Auto Repair",
            "type":"Services"
        },
        {
            "category":"Sports & Exercise",
            "subcategory":"Race Track",
            "type":"Entertainment"
        }
    ],
    "sg:phone":"+1 501 888 5256",
    "sg:postcode":"72065",
    "sg:province":"AR",
    "sg:tags":[
        "engine",
        "rebuilding",
        "exchange",
        "automobile",
        "equipment",
        "car",
        "performance",
        "racing",
        "engines-rebuild"
    ],
    "wof:name":"Jim's Engine Service",
    "wof:placetype":"venue"
},
  "geometry": {"coordinates":[-92.287944,34.559641],"type":"Point"}
}