{
  "type": "Feature",
  "properties": {
    "iso:country":"US",
    "sg:address":"1930 Co Rd 422",
    "sg:city":"Berryville",
    "sg:classifiers":[
        {
            "category":"Farming",
            "subcategory":"Livestock Farm",
            "type":"Manufacturing & Wholesale Goods"
        }
    ],
    "sg:phone":"+1 870 749 2789",
    "sg:postcode":"72616",
    "sg:province":"AR",
    "wof:name":"High Farms",
    "wof:placetype":"venue"
},
  "geometry": {"coordinates":[-93.532903,36.473319],"type":"Point"}
}