{
  "type": "Feature",
  "properties": {
    "addr:full":"1805 Bond St Little Rock AR 72206",
    "addr:housenumber":"1805",
    "addr:postcode":"72206",
    "addr:street":"Bond St",
    "iso:country":"US",
    "sg:address":"1805 Bond St",
    "sg:city":"Little Rock",
    "sg:classifiers":[
        {
            "category":"Building & Trades",
            "subcategory":"Plumbing",
            "type":"Services"
        }
    ],
    "sg:phone":"+1 501 663 5676",
    "sg:postcode":"72206",
    "sg:province":"AR",
    "sg:tags":[
        "conditioning",
        "air",
        "system",
        "contractor"
    ],
    "wof:name":"Carrier Commercial Svc",
    "wof:placetype":"venue"
},
  "geometry": {"coordinates":[-92.24299600000001,34.72749],"type":"Point"}
}