{
  "type": "Feature",
  "properties": {
    "iso:country":"US",
    "sg:address":"1100 48th Pl",
    "sg:city":"Springdale",
    "sg:classifiers":[
        {
            "category":"Restaurant",
            "type":"Food & Drink"
        }
    ],
    "sg:phone":"+1 479 872 6464",
    "sg:postcode":"72762",
    "sg:province":"AR",
    "wof:name":"Osegueras",
    "wof:placetype":"venue"
},
  "geometry": {"coordinates":[-94.183632,36.175964],"type":"Point"}
}