{
  "type": "Feature",
  "properties": {
    "iso:country":"US",
    "sg:address":"1432 Braden St",
    "sg:city":"Jacksonville",
    "sg:classifiers":[
        {
            "category":"Health Services",
            "subcategory":"Doctor",
            "type":"Services"
        }
    ],
    "sg:phone":"+1 501 985 1323",
    "sg:postcode":"72076",
    "sg:province":"AR",
    "sg:tags":[
        "physician",
        "surgeon"
    ],
    "wof:name":"Jacksonville Neurology",
    "wof:placetype":"venue"
},
  "geometry": {"coordinates":[-92.123734,34.872429],"type":"Point"}
}