{
  "type": "Feature",
  "properties": {
    "addr:full":"303 N Main St Harrison AR 72601",
    "addr:housenumber":"303",
    "addr:postcode":"72601",
    "addr:street":"N Main St",
    "iso:country":"US",
    "sg:address":"303 N Main St",
    "sg:city":"Harrison",
    "sg:classifiers":[
        {
            "category":"Social Services",
            "type":"Services"
        }
    ],
    "sg:phone":"+1 870 743 2827",
    "sg:postcode":"72601",
    "sg:province":"AR",
    "sg:tags":[
        "organization",
        "welfare"
    ],
    "wof:name":"United Cerebral Palsy",
    "wof:placetype":"venue"
},
  "geometry": {"coordinates":[-93.10717,36.233151],"type":"Point"}
}