{
  "type": "Feature",
  "properties": {
    "addr:full":"506 W Main St El Dorado AR 71730",
    "addr:housenumber":"506",
    "addr:postcode":"71730",
    "addr:street":"W Main St",
    "iso:country":"US",
    "sg:address":"506 W Main St",
    "sg:city":"El Dorado",
    "sg:classifiers":[
        {
            "category":"Insurance",
            "subcategory":"Insurance Agent",
            "type":"Services"
        }
    ],
    "sg:phone":"+1 870 862 2252",
    "sg:postcode":"71730",
    "sg:province":"AR",
    "wof:name":"Jay G Johnston Inc",
    "wof:placetype":"venue"
},
  "geometry": {"coordinates":[-92.66956399999999,33.211956],"type":"Point"}
}