{
  "type": "Feature",
  "properties": {
    "iso:country":"US",
    "sg:address":"2200 Airport Rd",
    "sg:city":"Hot Springs",
    "sg:classifiers":[
        {
            "category":"Building & Trades",
            "subcategory":"Construction",
            "type":"Services"
        }
    ],
    "sg:phone":"+1 501 622 9047",
    "sg:postcode":"71913",
    "sg:province":"AR",
    "sg:tags":[
        "repairing",
        "nonresidential",
        "remodeling",
        "contractor"
    ],
    "wof:name":"Home Care Specialist",
    "wof:placetype":"venue"
},
  "geometry": {"coordinates":[-93.16057000000001,34.456225],"type":"Point"}
}