{
  "type": "Feature",
  "properties": {
    "iso:country":"US",
    "sg:address":"513 Ashley Road 20",
    "sg:city":"Crossett",
    "sg:classifiers":[
        {
            "category":"Building & Trades",
            "subcategory":"Construction",
            "type":"Services"
        }
    ],
    "sg:phone":"+1 870 364 5915",
    "sg:postcode":"71635",
    "sg:province":"AR",
    "sg:tags":[
        "house"
    ],
    "wof:name":"Sooner Construction Inc",
    "wof:placetype":"venue"
},
  "geometry": {"coordinates":[-91.912791,33.158146],"type":"Point"}
}