{
  "type": "Feature",
  "properties": {
    "iso:country":"US",
    "sg:address":"22500 Highway 107",
    "sg:city":"Jacksonville",
    "sg:classifiers":[
        {
            "category":"Autos & Motor Vehicles",
            "subcategory":"Automobile Sales",
            "type":"Retail Goods"
        }
    ],
    "sg:phone":"+1 501 988 0990",
    "sg:postcode":"72076",
    "sg:province":"AR",
    "sg:tags":[
        "dealers-used",
        "car",
        "used",
        "cars-wholesale"
    ],
    "wof:name":"Highway 107 Wholesale",
    "wof:placetype":"venue"
},
  "geometry": {"coordinates":[-92.168548,34.91828],"type":"Point"}
}