{
  "type": "Feature",
  "properties": {
    "iso:country":"US",
    "sg:address":"2050 John Harden Dr",
    "sg:city":"Jacksonville",
    "sg:classifiers":[
        {
            "category":"Wholesale",
            "subcategory":"Toys & Hobbies",
            "type":"Manufacturing & Wholesale Goods"
        }
    ],
    "sg:phone":"+1 501 457 5106",
    "sg:postcode":"72076",
    "sg:province":"AR",
    "wof:name":"Gamz For Less",
    "wof:placetype":"venue"
},
  "geometry": {"coordinates":[-92.111109,34.883069],"type":"Point"}
}