{
  "type": "Feature",
  "properties": {
    "iso:country":"US",
    "sg:address":"214 Sylamore Ave",
    "sg:city":"Mountain View",
    "sg:classifiers":[
        {
            "category":"Travel",
            "subcategory":"Campground",
            "type":"Entertainment"
        }
    ],
    "sg:phone":"+1 870 585 2326",
    "sg:postcode":"72560",
    "sg:province":"AR",
    "wof:name":"Sylamore Creek Camp",
    "wof:placetype":"venue"
},
  "geometry": {"coordinates":[-92.10799,35.865459],"type":"Point"}
}