{
  "type": "Feature",
  "properties": {
    "addr:full":"2010 W Main St Blytheville AR 72315",
    "addr:housenumber":"2010",
    "addr:postcode":"72315",
    "addr:street":"W Main St",
    "iso:country":"US",
    "sg:address":"2010 W Main St",
    "sg:city":"Blytheville",
    "sg:classifiers":[
        {
            "category":"Retail",
            "subcategory":"Laundry & Dry Cleaning",
            "type":"Services"
        }
    ],
    "sg:phone":"+1 870 762 2408",
    "sg:postcode":"72315",
    "sg:province":"AR",
    "sg:tags":[
        "drycleaning",
        "plant",
        "power"
    ],
    "wof:name":"Bestway Cleaners",
    "wof:placetype":"venue"
},
  "geometry": {"coordinates":[-89.927673,35.927521],"type":"Point"}
}