{
  "type": "Feature",
  "properties": {
    "iso:country":"US",
    "sg:address":"3400 Baseline Rd",
    "sg:city":"Little Rock",
    "sg:classifiers":[
        {
            "category":"Shopping",
            "subcategory":"Used Merchandise",
            "type":"Retail Goods"
        }
    ],
    "sg:phone":"+1 501 570 0570",
    "sg:postcode":"72209",
    "sg:province":"AR",
    "wof:name":"Baseline Pawn Shop",
    "wof:placetype":"venue"
},
  "geometry": {"coordinates":[-92.31714599999999,34.667891],"type":"Point"}
}