{
  "type": "Feature",
  "properties": {
    "iso:country":"US",
    "sg:address":"239 S Main St",
    "sg:city":"Jonesboro",
    "sg:classifiers":[
        {
            "category":"Shopping",
            "subcategory":"Shoes",
            "type":"Retail Goods"
        }
    ],
    "sg:phone":"+1 870 268 9600",
    "sg:postcode":"72401",
    "sg:province":"AR",
    "wof:name":"Posh",
    "wof:placetype":"venue"
},
  "geometry": {"coordinates":[-90.704972,35.841407],"type":"Point"}
}