{
  "type": "Feature",
  "properties": {
    "iso:country":"US",
    "sg:address":"1014 W 3rd St",
    "sg:city":"Imboden",
    "sg:classifiers":[
        {
            "category":"Retail",
            "subcategory":"Repair Shop",
            "type":"Services"
        }
    ],
    "sg:phone":"+1 870 869 1010",
    "sg:postcode":"72434",
    "sg:province":"AR",
    "sg:tags":[
        "taxidermist"
    ],
    "wof:name":"Archer's Taxidermy Studio",
    "wof:placetype":"venue"
},
  "geometry": {"coordinates":[-91.18659,36.203929],"type":"Point"}
}