{
  "type": "Feature",
  "properties": {
    "iso:country":"US",
    "sg:address":"5 Powder Cv",
    "sg:city":"Maumelle",
    "sg:classifiers":[
        {
            "category":"Place Of Worship",
            "subcategory":"Church",
            "type":"Public Place"
        }
    ],
    "sg:phone":"+1 501 868 5786",
    "sg:postcode":"72113",
    "sg:province":"AR",
    "sg:tags":[
        "churches-jehovah's",
        "witness"
    ],
    "wof:name":"Northwest Congregation Of",
    "wof:placetype":"venue"
},
  "geometry": {"coordinates":[-92.407107,34.837001],"type":"Point"}
}