{
  "type": "Feature",
  "properties": {
    "addr:full":"133 N 21st St Arkadelphia AR 71923",
    "addr:housenumber":"133",
    "addr:postcode":"71923",
    "addr:street":"N 21St St",
    "iso:country":"US",
    "sg:address":"133 N 21st St",
    "sg:city":"Arkadelphia",
    "sg:classifiers":[
        {
            "category":"Shopping",
            "subcategory":"Florist",
            "type":"Retail Goods"
        }
    ],
    "sg:phone":"+1 870 230 5104",
    "sg:postcode":"71923",
    "sg:province":"AR",
    "wof:name":"Kaye S Florist",
    "wof:placetype":"venue"
},
  "geometry": {"coordinates":[-93.075063,34.121891],"type":"Point"}
}