{
  "type": "Feature",
  "properties": {
    "iso:country":"US",
    "sg:address":"410 Commerce Rd",
    "sg:city":"Conway",
    "sg:classifiers":[
        {
            "category":"Manufacturing",
            "subcategory":"Paper Products",
            "type":"Manufacturing & Wholesale Goods"
        }
    ],
    "sg:phone":"+1 501 327 3847",
    "sg:postcode":"72032",
    "sg:province":"AR",
    "sg:tags":[
        "corrugated",
        "solid",
        "fiber",
        "box"
    ],
    "sg:website":"www.ageindustries.com",
    "wof:name":"Age Industries LTD",
    "wof:placetype":"venue"
},
  "geometry": {"coordinates":[-92.424206,35.071528],"type":"Point"}
}