{
  "type": "Feature",
  "properties": {
    "iso:country":"US",
    "sg:address":"800 Carlton St",
    "sg:city":"Springdale",
    "sg:classifiers":[
        {
            "category":"Shopping",
            "type":"Retail Goods"
        }
    ],
    "sg:phone":"+1 479 872 2242",
    "sg:postcode":"72762",
    "sg:province":"AR",
    "sg:tags":[
        "merchandise"
    ],
    "wof:name":"Peterson Orignials",
    "wof:placetype":"venue"
},
  "geometry": {"coordinates":[-94.152861,36.174804],"type":"Point"}
}