{
  "type": "Feature",
  "properties": {
    "iso:country":"US",
    "sg:address":"3304 Willow Pond",
    "sg:city":"White Hall",
    "sg:classifiers":[
        {
            "category":"Professional",
            "type":"Services"
        }
    ],
    "sg:phone":"+1 870 247 9294",
    "sg:postcode":"71602",
    "sg:province":"AR",
    "wof:name":"Geneva C Wilkerson",
    "wof:placetype":"venue"
},
  "geometry": {"coordinates":[-92.122858,34.326939],"type":"Point"}
}