{
  "type": "Feature",
  "properties": {
    "addr:full":"3104 S Catalpa St Pine Bluff AR 71603",
    "addr:housenumber":"3104",
    "addr:postcode":"71603",
    "addr:street":"S Catalpa St",
    "iso:country":"US",
    "sg:address":"3104 S Catalpa St",
    "sg:city":"Pine Bluff",
    "sg:classifiers":[
        {
            "category":"Insurance",
            "subcategory":"Insurance Agent",
            "type":"Services"
        }
    ],
    "sg:phone":"+1 870 536 7137",
    "sg:postcode":"71603",
    "sg:province":"AR",
    "wof:name":"Bruce Insurance",
    "wof:placetype":"venue"
},
  "geometry": {"coordinates":[-92.033669,34.197723],"type":"Point"}
}