{
  "type": "Feature",
  "properties": {
    "iso:country":"US",
    "sg:address":"312 N Durango Pl",
    "sg:city":"Fayetteville",
    "sg:classifiers":[
        {
            "category":"Professional",
            "subcategory":"Business Services",
            "type":"Services"
        }
    ],
    "sg:phone":"+1 479 442 4349",
    "sg:postcode":"72704",
    "sg:province":"AR",
    "sg:tags":[
        "inspection"
    ],
    "wof:name":"Home Inspection Service",
    "wof:placetype":"venue"
},
  "geometry": {"coordinates":[-94.25699400000001,36.068584],"type":"Point"}
}