{
  "type": "Feature",
  "properties": {
    "iso:country":"US",
    "sg:address":"8203 Rogers Ave",
    "sg:city":"Fort Smith",
    "sg:classifiers":[
        {
            "category":"Restaurant",
            "type":"Food & Drink"
        }
    ],
    "sg:phone":"+1 479 478 6006",
    "sg:postcode":"72903",
    "sg:province":"AR",
    "sg:tags":[
        "eating"
    ],
    "wof:name":"Mi Casita Mexican Restaurant",
    "wof:placetype":"venue"
},
  "geometry": {"coordinates":[-94.342619,35.349388],"type":"Point"}
}