{
  "type": "Feature",
  "properties": {
    "iso:country":"US",
    "sg:address":"1110 N 26th St",
    "sg:city":"Van Buren",
    "sg:classifiers":[
        {
            "category":"Freight",
            "type":"Transportation"
        }
    ],
    "sg:phone":"+1 479 474 9792",
    "sg:postcode":"72956",
    "sg:province":"AR",
    "sg:tags":[
        "operator",
        "trucking",
        "local",
        "help",
        "supply"
    ],
    "wof:name":"Taft Trucking Services Inc",
    "wof:placetype":"venue"
},
  "geometry": {"coordinates":[-94.33097600000001,35.450263],"type":"Point"}
}