{
  "type": "Feature",
  "properties": {
    "iso:country":"US",
    "sg:address":"6700 McKennon Blvd",
    "sg:city":"Fort Smith",
    "sg:classifiers":[
        {
            "category":"Parking",
            "type":"Transportation"
        }
    ],
    "sg:phone":"+1 479 478 9499",
    "sg:postcode":"72903",
    "sg:province":"AR",
    "sg:tags":[
        "garage"
    ],
    "wof:name":"Air Terminal Parking Co",
    "wof:placetype":"venue"
},
  "geometry": {"coordinates":[-94.360511,35.342534],"type":"Point"}
}