{
  "type": "Feature",
  "properties": {
    "iso:country":"US",
    "sg:address":"7022 W Sunset Ave",
    "sg:city":"Springdale",
    "sg:classifiers":[
        {
            "category":"Fast Food",
            "type":"Food & Drink"
        },
        {
            "category":"Restaurant",
            "type":"Food & Drink"
        },
        {
            "category":"Food & Beverages",
            "subcategory":"Groceries & Convenience Stores",
            "type":"Retail Goods"
        }
    ],
    "sg:phone":"+1 479 717 2020",
    "sg:postcode":"72762",
    "sg:province":"AR",
    "sg:tags":[
        "shop",
        "american",
        "sandwich",
        "take"
    ],
    "sg:website":"http://www.quiznos.com",
    "wof:name":"Quiznos Classic Subs",
    "wof:placetype":"venue"
},
  "geometry": {"coordinates":[-94.208578,36.17579],"type":"Point"}
}