{
  "type": "Feature",
  "properties": {
    "addr:full":"1015 Main St Earle AR 72331",
    "addr:housenumber":"1015",
    "addr:postcode":"72331",
    "addr:street":"Main St",
    "iso:country":"US",
    "sg:address":"1015 Main St",
    "sg:city":"Earle",
    "sg:classifiers":[
        {
            "category":"Shopping",
            "subcategory":"Department Store",
            "type":"Retail Goods"
        }
    ],
    "sg:phone":"+1 870 792 8680",
    "sg:postcode":"72331",
    "sg:province":"AR",
    "sg:tags":[
        "shop"
    ],
    "wof:name":"Wooten Bargain Store",
    "wof:placetype":"venue"
},
  "geometry": {"coordinates":[-90.463993,35.270054],"type":"Point"}
}