{
  "type": "Feature",
  "properties": {
    "iso:country":"US",
    "sg:address":"17115 Raines Rd",
    "sg:city":"Little Rock",
    "sg:classifiers":[
        {
            "category":"Building & Trades",
            "subcategory":"Plumbing",
            "type":"Services"
        }
    ],
    "sg:phone":"+1 501 455 0601",
    "sg:postcode":"72210",
    "sg:province":"AR",
    "sg:tags":[
        "plumbing",
        "contractor",
        "heating",
        "electric",
        "except"
    ],
    "wof:name":"Rays Plumbing & Heating Co",
    "wof:placetype":"venue"
},
  "geometry": {"coordinates":[-92.45706,34.68698],"type":"Point"}
}