{
  "type": "Feature",
  "properties": {
    "addr:full":"604 S Sawmill Rd Searcy AR 72143",
    "addr:housenumber":"604",
    "addr:postcode":"72143",
    "addr:street":"S Sawmill Rd",
    "iso:country":"US",
    "sg:address":"604 S Sawmill Rd",
    "sg:city":"Searcy",
    "sg:classifiers":[
        {
            "category":"Professional",
            "type":"Services"
        }
    ],
    "sg:phone":"+1 501 268 2563",
    "sg:postcode":"72143",
    "sg:province":"AR",
    "wof:name":"Judy Pennington",
    "wof:placetype":"venue"
},
  "geometry": {"coordinates":[-91.76591000000001,35.2411],"type":"Point"}
}