{
  "type": "Feature",
  "properties": {
    "addr:full":"114 W Eden Park Rd Searcy AR 72143",
    "addr:housenumber":"114",
    "addr:postcode":"72143",
    "addr:street":"W Eden Park Rd",
    "iso:country":"US",
    "sg:address":"114 W Eden Park Rd",
    "sg:city":"Searcy",
    "sg:classifiers":[
        {
            "category":"Professional",
            "subcategory":"Business Services",
            "type":"Services"
        }
    ],
    "sg:phone":"+1 501 279 9469",
    "sg:postcode":"72143",
    "sg:province":"AR",
    "sg:tags":[
        "consultant",
        "coach"
    ],
    "wof:name":"Caliber Associates",
    "wof:placetype":"venue"
},
  "geometry": {"coordinates":[-91.80783700000001,35.254857],"type":"Point"}
}