{
  "type": "Feature",
  "properties": {
    "addr:full":"122 Buena Vista Rd Hot Springs AR 71913",
    "addr:housenumber":"122",
    "addr:postcode":"71913",
    "addr:street":"Buena Vista Rd",
    "iso:country":"US",
    "sg:address":"122 Buena Vista Rd",
    "sg:city":"Hot Springs",
    "sg:classifiers":[
        {
            "category":"Insurance",
            "subcategory":"Insurance Agent",
            "type":"Services"
        }
    ],
    "sg:phone":"+1 501 525 0033",
    "sg:postcode":"71913",
    "sg:province":"AR",
    "wof:name":"Allstate Insurance",
    "wof:placetype":"venue"
},
  "geometry": {"coordinates":[-93.061661,34.456525],"type":"Point"}
}