{
  "type": "Feature",
  "properties": {
    "iso:country":"US",
    "sg:address":"105 W Poplar St",
    "sg:city":"Fayetteville",
    "sg:classifiers":[
        {
            "category":"Recreation",
            "type":"Entertainment"
        }
    ],
    "sg:phone":"+1 479 633 0141",
    "sg:postcode":"72703",
    "sg:province":"AR",
    "sg:tags":[
        "club",
        "membership"
    ],
    "wof:name":"Club Frisco",
    "wof:placetype":"venue"
},
  "geometry": {"coordinates":[-94.160586,36.088596],"type":"Point"}
}