{
  "type": "Feature",
  "properties": {
    "iso:country":"US",
    "sg:address":"1318 Pine St",
    "sg:city":"Arkadelphia",
    "sg:classifiers":[
        {
            "category":"Building & Trades",
            "subcategory":"Plumbing",
            "type":"Services"
        }
    ],
    "sg:phone":"+1 870 246 2599",
    "sg:postcode":"71923",
    "sg:province":"AR",
    "sg:tags":[
        "conditioning",
        "air",
        "system",
        "contractor"
    ],
    "wof:name":"Service Experts Arkansas",
    "wof:placetype":"venue"
},
  "geometry": {"coordinates":[-93.06272800000001,34.122661],"type":"Point"}
}