{
  "type": "Feature",
  "properties": {
    "iso:country":"US",
    "sg:address":"113 S 2nd St",
    "sg:city":"Rogers",
    "sg:classifiers":[
        {
            "category":"Professional",
            "type":"Services"
        }
    ],
    "sg:phone":"+1 479 636 5140",
    "sg:postcode":"72756",
    "sg:province":"AR",
    "sg:tags":[
        "establishment"
    ],
    "wof:name":"Regina Marie's Custom Designs",
    "wof:placetype":"venue"
},
  "geometry": {"coordinates":[-94.117423,36.332194],"type":"Point"}
}