{
  "type": "Feature",
  "properties": {
    "iso:country":"US",
    "sg:address":"297 Walker Cutoff",
    "sg:city":"Malvern",
    "sg:classifiers":[
        {
            "category":"Organizations",
            "subcategory":"Religious Organization",
            "type":"Services"
        }
    ],
    "sg:phone":"+1 501 337 4329",
    "sg:postcode":"72104",
    "sg:province":"AR",
    "sg:tags":[
        "church"
    ],
    "wof:name":"Oachita Missionary Baptist Ch",
    "wof:placetype":"venue"
},
  "geometry": {"coordinates":[-92.89649,34.2295],"type":"Point"}
}