{
  "type": "Feature",
  "properties": {
    "iso:country":"US",
    "sg:address":"28000 Akin Ln",
    "sg:city":"Redfield",
    "sg:classifiers":[
        {
            "category":"Place Of Worship",
            "subcategory":"Church",
            "type":"Public Place"
        },
        {
            "category":"Place Of Worship",
            "type":"Public Place"
        }
    ],
    "sg:phone":"+1 501 397 5642",
    "sg:postcode":"72132",
    "sg:province":"AR",
    "sg:tags":[
        "churches-baptist-general",
        "churches-baptist"
    ],
    "wof:name":"Orion Missionary Bapt Chu",
    "wof:placetype":"venue"
},
  "geometry": {"coordinates":[-92.216103,34.49144],"type":"Point"}
}