{
  "type": "Feature",
  "properties": {
    "iso:country":"US",
    "sg:address":"702 W Center Ave",
    "sg:city":"Searcy",
    "sg:classifiers":[
        {
            "category":"Organizations",
            "subcategory":"Religious Organization",
            "type":"Services"
        }
    ],
    "sg:phone":"+1 501 268 2951",
    "sg:postcode":"72143",
    "sg:province":"AR",
    "sg:website":"www.wschurch.net",
    "wof:name":"Church Of Christ",
    "wof:placetype":"venue"
},
  "geometry": {"coordinates":[-91.74413,35.24883],"type":"Point"}
}