{
  "type": "Feature",
  "properties": {
    "iso:country":"US",
    "sg:address":"651 Spring St",
    "sg:city":"Winthrop",
    "sg:classifiers":[
        {
            "category":"Social Services",
            "subcategory":"Child Care",
            "type":"Services"
        }
    ],
    "sg:phone":"+1 870 881 7529",
    "sg:postcode":"71866",
    "sg:province":"AR",
    "sg:tags":[
        "kindergarten",
        "academic",
        "school"
    ],
    "wof:name":"Winthrop Pre-School",
    "wof:placetype":"venue"
},
  "geometry": {"coordinates":[-94.354308,33.830225],"type":"Point"}
}