{
  "type": "Feature",
  "properties": {
    "iso:country":"US",
    "sg:address":"225 N Gee St",
    "sg:city":"Jonesboro",
    "sg:classifiers":[
        {
            "category":"Professional",
            "subcategory":"Art Services",
            "type":"Services"
        }
    ],
    "sg:phone":"+1 870 935 1371",
    "sg:postcode":"72401",
    "sg:province":"AR",
    "sg:tags":[
        "taxidermist"
    ],
    "wof:name":"Kaiser's Taxidermy",
    "wof:placetype":"venue"
},
  "geometry": {"coordinates":[-90.725658,35.840731],"type":"Point"}
}