{
  "type": "Feature",
  "properties": {
    "iso:country":"US",
    "sg:address":"1521 Malvern Ave",
    "sg:city":"Hot Springs National",
    "sg:classifiers":[
        {
            "category":"Restaurant",
            "type":"Food & Drink"
        }
    ],
    "sg:phone":"+1 501 525 8420",
    "sg:postcode":"71901",
    "sg:province":"AR",
    "sg:tags":[
        "eating"
    ],
    "wof:name":"Baby Boommers",
    "wof:placetype":"venue"
},
  "geometry": {"coordinates":[-93.038247,34.495824],"type":"Point"}
}