{
  "type": "Feature",
  "properties": {
    "iso:country":"US",
    "sg:address":"504 S Main St",
    "sg:city":"Searcy",
    "sg:classifiers":[
        {
            "category":"Autos & Motor Vehicles",
            "subcategory":"Automobile Sales",
            "type":"Retail Goods"
        }
    ],
    "sg:phone":"+1 501 268 2950",
    "sg:postcode":"72143",
    "sg:province":"AR",
    "sg:tags":[
        "car",
        "dealer"
    ],
    "wof:name":"Patrick's Auto Sales",
    "wof:placetype":"venue"
},
  "geometry": {"coordinates":[-91.73634300000001,35.245126],"type":"Point"}
}