{
  "type": "Feature",
  "properties": {
    "iso:country":"US",
    "sg:address":"7509 Pontiac Dr",
    "sg:city":"N Little Rock",
    "sg:classifiers":[
        {
            "category":"Personal",
            "type":"Services"
        }
    ],
    "sg:phone":"+1 501 833 3314",
    "sg:postcode":"72116",
    "sg:province":"AR",
    "sg:tags":[
        "control",
        "weight"
    ],
    "wof:name":"Herbalife Distributor",
    "wof:placetype":"venue"
},
  "geometry": {"coordinates":[-92.24640599999999,34.824283],"type":"Point"}
}