{
  "type": "Feature",
  "properties": {
    "addr:full":"5105 Kensington Dr Benton AR 72019",
    "addr:housenumber":"5105",
    "addr:postcode":"72019",
    "addr:street":"Kensington Dr",
    "iso:country":"US",
    "sg:address":"5105 Kensington Dr",
    "sg:city":"Benton",
    "sg:classifiers":[
        {
            "category":"Professional",
            "subcategory":"Business Services",
            "type":"Services"
        }
    ],
    "sg:phone":"+1 501 847 9322",
    "sg:postcode":"72019",
    "sg:province":"AR",
    "sg:tags":[
        "consultant",
        "coach"
    ],
    "wof:name":"Jreynolds Consulting Inc",
    "wof:placetype":"venue"
},
  "geometry": {"coordinates":[-92.526134,34.624679],"type":"Point"}
}