{
  "type": "Feature",
  "properties": {
    "iso:country":"US",
    "sg:address":"37 Cattail Rd",
    "sg:city":"Searcy",
    "sg:classifiers":[
        {
            "category":"Banks & Credit Unions",
            "subcategory":"Financial Services",
            "type":"Services"
        }
    ],
    "sg:phone":"+1 501 268 1343",
    "sg:postcode":"72143",
    "sg:province":"AR",
    "sg:tags":[
        "investor"
    ],
    "wof:name":"Fuller Investments Inc",
    "wof:placetype":"venue"
},
  "geometry": {"coordinates":[-91.76293099999999,35.243908],"type":"Point"}
}