{
  "type": "Feature",
  "properties": {
    "iso:country":"US",
    "sg:address":"423 Rogers Ave",
    "sg:city":"Fort Smith",
    "sg:classifiers":[
        {
            "category":"Professional",
            "subcategory":"Lawyer & Legal Services",
            "type":"Services"
        }
    ],
    "sg:phone":"+1 479 782 6400",
    "sg:postcode":"72901",
    "sg:province":"AR",
    "sg:tags":[
        "attorney"
    ],
    "wof:name":"Barham Law Office Pa",
    "wof:placetype":"venue"
},
  "geometry": {"coordinates":[-94.42715099999999,35.387202],"type":"Point"}
}