{
  "type": "Feature",
  "properties": {
    "iso:country":"US",
    "sg:address":"1615 Rebsamen Park Rd",
    "sg:city":"Little Rock",
    "sg:classifiers":[
        {
            "category":"Restaurant",
            "type":"Food & Drink"
        }
    ],
    "sg:phone":"+1 501 660 4200",
    "sg:postcode":"72202",
    "sg:province":"AR",
    "wof:name":"Bubba & Garcia's Restaurant",
    "wof:placetype":"venue"
},
  "geometry": {"coordinates":[-92.310048,34.764926],"type":"Point"}
}