{
  "type": "Feature",
  "properties": {
    "iso:country":"US",
    "sg:address":"121 N Tyler St",
    "sg:city":"De Witt",
    "sg:classifiers":[
        {
            "category":"Building & Trades",
            "subcategory":"Plumbing",
            "type":"Services"
        }
    ],
    "sg:phone":"+1 870 946 3142",
    "sg:postcode":"72042",
    "sg:province":"AR",
    "sg:tags":[
        "air",
        "heating",
        "conditioning",
        "contractor"
    ],
    "wof:name":"Lynch Air Conditioning & Htg",
    "wof:placetype":"venue"
},
  "geometry": {"coordinates":[-91.344886,34.296533],"type":"Point"}
}