{
  "type": "Feature",
  "properties": {
    "iso:country":"US",
    "sg:address":"2209 Wildrose Ln",
    "sg:city":"Paragould",
    "sg:classifiers":[
        {
            "category":"Building & Trades",
            "subcategory":"Construction",
            "type":"Services"
        }
    ],
    "sg:phone":"+1 870 236 7234",
    "sg:postcode":"72450",
    "sg:province":"AR",
    "sg:tags":[
        "general",
        "contractor"
    ],
    "wof:name":"Rawls Inc",
    "wof:placetype":"venue"
},
  "geometry": {"coordinates":[-90.515169,36.029141],"type":"Point"}
}