{
  "type": "Feature",
  "properties": {
    "addr:full":"202 Shannon Rd Grady AR 71644",
    "addr:housenumber":"202",
    "addr:postcode":"71644",
    "addr:street":"Shannon Rd",
    "iso:country":"US",
    "sg:address":"202 Shannon Rd",
    "sg:city":"Grady",
    "sg:classifiers":[
        {
            "category":"Real Estate",
            "subcategory":"Real Estate Operator",
            "type":"Services"
        }
    ],
    "sg:phone":"+1 870 479 3300",
    "sg:postcode":"71644",
    "sg:province":"AR",
    "sg:tags":[
        "apartment"
    ],
    "wof:name":"Westridge Apartments",
    "wof:placetype":"venue"
},
  "geometry": {"coordinates":[-91.700248,34.068727],"type":"Point"}
}