{
  "type": "Feature",
  "properties": {
    "iso:country":"US",
    "sg:address":"406 W Emma Ave",
    "sg:city":"Springdale",
    "sg:classifiers":[
        {
            "category":"Health Services",
            "subcategory":"Doctor",
            "type":"Services"
        }
    ],
    "sg:phone":"+1 479 751 3461",
    "sg:postcode":"72764",
    "sg:province":"AR",
    "wof:name":"Springdale Allergy & Asthma Center",
    "wof:placetype":"venue"
},
  "geometry": {"coordinates":[-94.134843,36.185277],"type":"Point"}
}