{
  "type": "Feature",
  "properties": {
    "iso:country":"US",
    "sg:address":"16026 Greasy Valley Rd",
    "sg:city":"Prairie Grove",
    "sg:classifiers":[
        {
            "category":"Retail",
            "subcategory":"Repair Shop",
            "type":"Services"
        }
    ],
    "sg:phone":"+1 479 848 3308",
    "sg:postcode":"72753",
    "sg:province":"AR",
    "sg:tags":[
        "sharpening"
    ],
    "wof:name":"Circle V Sharpening Service",
    "wof:placetype":"venue"
},
  "geometry": {"coordinates":[-94.37893200000001,35.877705],"type":"Point"}
}