{
  "type": "Feature",
  "properties": {
    "iso:country":"US",
    "sg:address":"202 S 1st St",
    "sg:city":"Rogers",
    "sg:classifiers":[
        {
            "category":"Personal",
            "subcategory":"Beauty Salon",
            "type":"Services"
        }
    ],
    "sg:phone":"+1 479 621 1002",
    "sg:postcode":"72756",
    "sg:province":"AR",
    "sg:tags":[
        "shop"
    ],
    "wof:name":"Salon Cheveux LLC",
    "wof:placetype":"venue"
},
  "geometry": {"coordinates":[-94.11644099999999,36.330926],"type":"Point"}
}