{
  "type": "Feature",
  "properties": {
    "addr:full":"709 Golf Links Dr Blytheville AR 72315",
    "addr:housenumber":"709",
    "addr:postcode":"72315",
    "addr:street":"Golf Links Dr",
    "iso:country":"US",
    "sg:address":"709 Golf Links Dr",
    "sg:city":"Blytheville",
    "sg:classifiers":[
        {
            "category":"Professional",
            "subcategory":"Accounting & Tax Preparation",
            "type":"Services"
        }
    ],
    "sg:phone":"+1 870 762 6512",
    "sg:postcode":"72315",
    "sg:province":"AR",
    "sg:tags":[
        "accountant"
    ],
    "wof:name":"S Don Ray CPA",
    "wof:placetype":"venue"
},
  "geometry": {"coordinates":[-89.91368900000001,35.956877],"type":"Point"}
}