{
  "type": "Feature",
  "properties": {
    "addr:full":"650 S Shackleford Rd Little Rock AR 72211",
    "addr:housenumber":"650",
    "addr:postcode":"72211",
    "addr:street":"S Shackleford Rd",
    "iso:country":"US",
    "sg:address":"650 S Shackleford Rd",
    "sg:city":"Little Rock",
    "sg:classifiers":[
        {
            "category":"Real Estate",
            "subcategory":"Real Estate Services",
            "type":"Services"
        }
    ],
    "sg:phone":"+1 501 227 4646",
    "sg:postcode":"72211",
    "sg:province":"AR",
    "sg:tags":[
        "company",
        "title"
    ],
    "wof:name":"Land America Lawyers Title",
    "wof:placetype":"venue"
},
  "geometry": {"coordinates":[-92.394059,34.748025],"type":"Point"}
}