{
  "type": "Feature",
  "properties": {
    "iso:country":"US",
    "sg:address":"3000 Moberly Ln",
    "sg:city":"Bentonville",
    "sg:classifiers":[
        {
            "category":"Autos & Motor Vehicles",
            "subcategory":"Automobile Sales",
            "type":"Retail Goods"
        }
    ],
    "sg:phone":"+1 479 696 0800",
    "sg:postcode":"72712",
    "sg:province":"AR",
    "sg:tags":[
        "new",
        "car"
    ],
    "sg:website":"http://www.hyundaiofbentonville.com/",
    "wof:name":"Hyundai Of Bentonville",
    "wof:placetype":"venue"
},
  "geometry": {"coordinates":[-94.183937,36.337206],"type":"Point"}
}