{
  "type": "Feature",
  "properties": {
    "iso:country":"US",
    "sg:address":"212 N Marr St",
    "sg:city":"Pocahontas",
    "sg:classifiers":[
        {
            "category":"Professional",
            "type":"Services"
        }
    ],
    "sg:phone":"+1 870 892 9046",
    "sg:postcode":"72455",
    "sg:province":"AR",
    "wof:name":"Pocahontas Day Svc Ctr Inc",
    "wof:placetype":"venue"
},
  "geometry": {"coordinates":[-90.970153,36.261829],"type":"Point"}
}