{
  "type": "Feature",
  "properties": {
    "iso:country":"US",
    "sg:address":"2585 Donaghey Ave",
    "sg:city":"Conway",
    "sg:classifiers":[
        {
            "category":"Recreation",
            "type":"Entertainment"
        }
    ],
    "sg:phone":"+1 501 932 0303",
    "sg:postcode":"72032",
    "sg:province":"AR",
    "sg:tags":[
        "instruction",
        "yoga"
    ],
    "wof:name":"Kinetic Potential PLC",
    "wof:placetype":"venue"
},
  "geometry": {"coordinates":[-92.44883,35.112146],"type":"Point"}
}