{
  "type": "Feature",
  "properties": {
    "addr:full":"10 Cherry Valley Dr Little Rock AR 72211",
    "addr:housenumber":"10",
    "addr:postcode":"72211",
    "addr:street":"Cherry Valley Dr",
    "iso:country":"US",
    "sg:address":"10 Cherry Valley Dr",
    "sg:city":"Little Rock",
    "sg:classifiers":[
        {
            "category":"Restaurant",
            "type":"Food & Drink"
        }
    ],
    "sg:phone":"+1 501 562 5266",
    "sg:postcode":"72211",
    "sg:province":"AR",
    "wof:name":"Wafie's Pizza & Pita",
    "wof:placetype":"venue"
},
  "geometry": {"coordinates":[-92.39218099999999,34.767087],"type":"Point"}
}