{
  "type": "Feature",
  "properties": {
    "iso:country":"US",
    "sg:address":"1558 Airport Rd",
    "sg:city":"Hot Springs National Park",
    "sg:classifiers":[
        {
            "category":"Retail",
            "subcategory":"Repair Shop",
            "type":"Services"
        }
    ],
    "sg:phone":"+1 501 623 3001",
    "sg:postcode":"71913",
    "sg:province":"AR",
    "wof:name":"A Bonded Locksmith Service",
    "wof:placetype":"venue"
},
  "geometry": {"coordinates":[-93.13888300000001,34.468515],"type":"Point"}
}