{
  "type": "Feature",
  "properties": {
    "addr:full":"104 King Richard Ct Dierks AR 71833",
    "addr:housenumber":"104",
    "addr:postcode":"71833",
    "addr:street":"King Richard Ct",
    "iso:country":"US",
    "sg:address":"104 King Richard Ct",
    "sg:city":"Dierks",
    "sg:classifiers":[
        {
            "category":"Manufacturing",
            "subcategory":"Printing",
            "type":"Manufacturing & Wholesale Goods"
        }
    ],
    "sg:phone":"+1 870 286 3318",
    "sg:postcode":"71833",
    "sg:province":"AR",
    "sg:tags":[
        "lithographic",
        "commercial"
    ],
    "wof:name":"B & B Printing & Copying",
    "wof:placetype":"venue"
},
  "geometry": {"coordinates":[-94.017172,34.102519],"type":"Point"}
}