{
  "type": "Feature",
  "properties": {
    "iso:country":"US",
    "sg:address":"200 L H Polk Dr",
    "sg:city":"Marion",
    "sg:classifiers":[
        {
            "category":"Organizations",
            "subcategory":"Religious Organization",
            "type":"Services"
        }
    ],
    "sg:phone":"+1 870 739 2106",
    "sg:postcode":"72364",
    "sg:province":"AR",
    "wof:name":"Im A Part Missionary Baptis T",
    "wof:placetype":"venue"
},
  "geometry": {"coordinates":[-90.192934,35.19741],"type":"Point"}
}