{
  "type": "Feature",
  "properties": {
    "iso:country":"US",
    "sg:address":"2744 E Millennium Pl",
    "sg:city":"Fayetteville",
    "sg:classifiers":[
        {
            "category":"Real Estate",
            "subcategory":"Real Estate Agent",
            "type":"Services"
        }
    ],
    "sg:phone":"+1 479 973 0808",
    "sg:postcode":"72703",
    "sg:province":"AR",
    "wof:name":"Metro Area Board Of Realtors",
    "wof:placetype":"venue"
},
  "geometry": {"coordinates":[-94.120213,36.121164],"type":"Point"}
}