{
  "type": "Feature",
  "properties": {
    "iso:country":"US",
    "sg:address":"810 W Faulkner St",
    "sg:city":"El Dorado",
    "sg:classifiers":[
        {
            "category":"Restaurant",
            "type":"Food & Drink"
        }
    ],
    "sg:phone":"+1 870 863 9914",
    "sg:postcode":"71730",
    "sg:province":"AR",
    "sg:tags":[
        "eating"
    ],
    "wof:name":"Spudnut Shop Corp",
    "wof:placetype":"venue"
},
  "geometry": {"coordinates":[-92.674195,33.214831],"type":"Point"}
}