{
  "type": "Feature",
  "properties": {
    "addr:full":"11711 Bethel Rd Dardanelle AR 72834",
    "addr:housenumber":"11711",
    "addr:postcode":"72834",
    "addr:street":"Bethel Rd",
    "iso:country":"US",
    "sg:address":"11711 Bethel Rd",
    "sg:city":"Dardanelle",
    "sg:classifiers":[
        {
            "category":"Building & Trades",
            "subcategory":"Construction",
            "type":"Services"
        }
    ],
    "sg:phone":"+1 479 229 2964",
    "sg:postcode":"72834",
    "sg:province":"AR",
    "sg:tags":[
        "mason",
        "masonry",
        "industrial",
        "contractors-commercial",
        "contractor"
    ],
    "wof:name":"Lonnie Crowell Masonry, Inc",
    "wof:placetype":"venue"
},
  "geometry": {"coordinates":[-93.221046,35.218772],"type":"Point"}
}