{
  "type": "Feature",
  "properties": {
    "addr:full":"809 Mena St Mena AR 71953",
    "addr:housenumber":"809",
    "addr:postcode":"71953",
    "addr:street":"Mena St",
    "iso:country":"US",
    "sg:address":"809 Mena St",
    "sg:city":"Mena",
    "sg:classifiers":[
        {
            "category":"Personal",
            "subcategory":"Beauty Salon",
            "type":"Services"
        }
    ],
    "sg:phone":"+1 479 243 2090",
    "sg:postcode":"71953",
    "sg:province":"AR",
    "sg:tags":[
        "manicuring"
    ],
    "wof:name":"Mena Nails",
    "wof:placetype":"venue"
},
  "geometry": {"coordinates":[-94.235669,34.583353],"type":"Point"}
}