{
  "type": "Feature",
  "properties": {
    "iso:country":"US",
    "sg:address":"10120 Ironton Rd",
    "sg:city":"Little Rock",
    "sg:classifiers":[
        {
            "category":"Building & Trades",
            "subcategory":"Construction",
            "type":"Services"
        }
    ],
    "sg:phone":"+1 501 888 2696",
    "sg:postcode":"72206",
    "sg:province":"AR",
    "sg:tags":[
        "dry wall",
        "contractor"
    ],
    "wof:name":"Central Acoustical & Drywall",
    "wof:placetype":"venue"
},
  "geometry": {"coordinates":[-92.270931,34.661219],"type":"Point"}
}