{
  "type": "Feature",
  "properties": {
    "iso:country":"US",
    "sg:address":"822 Mellon St",
    "sg:city":"Little Rock",
    "sg:classifiers":[
        {
            "category":"Real Estate",
            "subcategory":"Real Estate Agent",
            "type":"Services"
        }
    ],
    "sg:phone":"+1 501 413 7454",
    "sg:postcode":"72205",
    "sg:province":"AR",
    "wof:name":"Harley Realty",
    "wof:placetype":"venue"
},
  "geometry": {"coordinates":[-92.352138,34.756854],"type":"Point"}
}