{
  "type": "Feature",
  "properties": {
    "iso:country":"US",
    "sg:address":"3999 Acorn Dr",
    "sg:city":"Harrison",
    "sg:classifiers":[
        {
            "category":"Building & Trades",
            "subcategory":"Construction",
            "type":"Services"
        }
    ],
    "sg:phone":"+1 870 743 5511",
    "sg:postcode":"72601",
    "sg:province":"AR",
    "sg:tags":[
        "hanging",
        "contractor"
    ],
    "wof:name":"D R Painting",
    "wof:placetype":"venue"
},
  "geometry": {"coordinates":[-93.173405,36.237499],"type":"Point"}
}