{
  "type": "Feature",
  "properties": {
    "iso:country":"US",
    "sg:address":"15886 Vesper Ln",
    "sg:city":"Gravette",
    "sg:classifiers":[
        {
            "category":"Real Estate",
            "subcategory":"Real Estate Agent",
            "type":"Services"
        }
    ],
    "sg:phone":"+1 479 787 6861",
    "sg:postcode":"72736",
    "sg:province":"AR",
    "sg:tags":[
        "inspection"
    ],
    "wof:name":"A Better Home Inspection",
    "wof:placetype":"venue"
},
  "geometry": {"coordinates":[-94.375802,36.390042],"type":"Point"}
}