{
  "type": "Feature",
  "properties": {
    "iso:country":"US",
    "sg:address":"500 S Main St",
    "sg:city":"Searcy",
    "sg:classifiers":[
        {
            "category":"Building & Trades",
            "subcategory":"Plumbing",
            "type":"Services"
        }
    ],
    "sg:phone":"+1 501 268 2303",
    "sg:postcode":"72143",
    "sg:province":"AR",
    "sg:tags":[
        "air",
        "work",
        "conditioning",
        "heating"
    ],
    "wof:name":"A A C O Heat & Air",
    "wof:placetype":"venue"
},
  "geometry": {"coordinates":[-91.736418,35.245169],"type":"Point"}
}