{
  "type": "Feature",
  "properties": {
    "iso:country":"US",
    "sg:address":"7 S Adair St",
    "sg:city":"Greenwood",
    "sg:classifiers":[
        {
            "category":"Organizations",
            "subcategory":"Religious Organization",
            "type":"Services"
        }
    ],
    "sg:phone":"+1 479 996 7966",
    "sg:postcode":"72936",
    "sg:province":"AR",
    "wof:name":"Temple Calvary United Pen",
    "wof:placetype":"venue"
},
  "geometry": {"coordinates":[-94.257023,35.211907],"type":"Point"}
}