{
  "type": "Feature",
  "properties": {
    "addr:full":"6152 State Hwy 101 Gamaliel AR 72537",
    "addr:housenumber":"6152",
    "addr:postcode":"72537",
    "addr:street":"State Hwy 101",
    "iso:country":"US",
    "sg:address":"6152 State Hwy 101",
    "sg:city":"Gamaliel",
    "sg:classifiers":[
        {
            "category":"Building & Trades",
            "subcategory":"Electrical",
            "type":"Services"
        }
    ],
    "sg:phone":"+1 870 467 5751",
    "sg:postcode":"72537",
    "sg:province":"AR",
    "sg:tags":[
        "electric",
        "contractor"
    ],
    "wof:name":"Master Electric",
    "wof:placetype":"venue"
},
  "geometry": {"coordinates":[-92.250361,36.439335],"type":"Point"}
}