{
  "type": "Feature",
  "properties": {
    "addr:full":"1002 McClain Rd Bentonville AR 72712",
    "addr:housenumber":"1002",
    "addr:postcode":"72712",
    "addr:street":"Mcclain Rd",
    "iso:country":"US",
    "sg:address":"1002 McClain Rd",
    "sg:city":"Bentonville",
    "sg:classifiers":[
        {
            "category":"Wholesale",
            "subcategory":"Meat",
            "type":"Manufacturing & Wholesale Goods"
        }
    ],
    "sg:phone":"+1 479 271 6030",
    "sg:postcode":"72712",
    "sg:province":"AR",
    "wof:name":"Con Agra Foods",
    "wof:placetype":"venue"
},
  "geometry": {"coordinates":[-94.17065700000001,36.379502],"type":"Point"}
}