{
  "type": "Feature",
  "properties": {
    "addr:full":"1 Lile Ct Little Rock AR 72205",
    "addr:housenumber":"1",
    "addr:postcode":"72205",
    "addr:street":"Lile Ct",
    "iso:country":"US",
    "sg:address":"1 Lile Ct",
    "sg:city":"Little Rock",
    "sg:classifiers":[
        {
            "category":"Health Services",
            "subcategory":"Doctor",
            "type":"Services"
        }
    ],
    "sg:phone":"+1 501 663 9600",
    "sg:postcode":"72205",
    "sg:province":"AR",
    "sg:tags":[
        "physician",
        "surgeon"
    ],
    "wof:name":"James C Wellborn Jr MD",
    "wof:placetype":"venue"
},
  "geometry": {"coordinates":[-92.37787899999999,34.745655],"type":"Point"}
}