{
  "type": "Feature",
  "properties": {
    "iso:country":"US",
    "sg:address":"248 Violet St",
    "sg:city":"Batesville",
    "sg:classifiers":[
        {
            "category":"Organizations",
            "subcategory":"Membership Organization",
            "type":"Services"
        }
    ],
    "sg:phone":"+1 870 793 5508",
    "sg:postcode":"72501",
    "sg:province":"AR",
    "wof:name":"M A D D Independence - C A T",
    "wof:placetype":"venue"
},
  "geometry": {"coordinates":[-91.592141,35.811059],"type":"Point"}
}