{
  "type": "Feature",
  "properties": {
    "addr:full":"5102 Timber Creek Dr North Little Rock AR 72116",
    "addr:housenumber":"5102",
    "addr:postcode":"72116",
    "addr:street":"Timber Creek Dr",
    "iso:country":"US",
    "sg:address":"5102 Timber Creek Dr",
    "sg:city":"North Little Rock",
    "sg:classifiers":[
        {
            "category":"Professional",
            "subcategory":"Business Services",
            "type":"Services"
        }
    ],
    "sg:phone":"+1 501 812 0044",
    "sg:postcode":"72116",
    "sg:province":"AR",
    "wof:name":"Pericles Group Ltd Co",
    "wof:placetype":"venue"
},
  "geometry": {"coordinates":[-92.23206999999999,34.802712],"type":"Point"}
}