{
  "type": "Feature",
  "properties": {
    "addr:full":"274 N Broadway Ave Booneville AR 72927",
    "addr:housenumber":"274",
    "addr:postcode":"72927",
    "addr:street":"N Broadway Ave",
    "iso:country":"US",
    "sg:address":"274 N Broadway Ave",
    "sg:city":"Booneville",
    "sg:classifiers":[
        {
            "category":"Shopping",
            "type":"Retail Goods"
        }
    ],
    "sg:phone":"+1 479 675 2848",
    "sg:postcode":"72927",
    "sg:province":"AR",
    "sg:tags":[
        "cosmetic",
        "perfume"
    ],
    "wof:name":"Merle Norman Cosmetics",
    "wof:placetype":"venue"
},
  "geometry": {"coordinates":[-93.921846,35.139424],"type":"Point"}
}