{
  "type": "Feature",
  "properties": {
    "iso:country":"US",
    "sg:address":"2825 State Hwy 96",
    "sg:city":"Hartford",
    "sg:classifiers":[
        {
            "category":"Professional",
            "type":"Services"
        }
    ],
    "sg:phone":"+1 479 928 5691",
    "sg:postcode":"72938",
    "sg:province":"AR",
    "wof:name":"Marc Reano",
    "wof:placetype":"venue"
},
  "geometry": {"coordinates":[-94.301816,35.039289],"type":"Point"}
}