{
  "type": "Feature",
  "properties": {
    "addr:full":"218 W Oliver Ave West Memphis AR 72301",
    "addr:housenumber":"218",
    "addr:postcode":"72301",
    "addr:street":"W Oliver Ave",
    "iso:country":"US",
    "sg:address":"218 W Oliver Ave",
    "sg:city":"West Memphis",
    "sg:classifiers":[
        {
            "category":"Building & Trades",
            "subcategory":"Landscaping Services",
            "type":"Services"
        }
    ],
    "sg:phone":"+1 870 735 6337",
    "sg:postcode":"72301",
    "sg:province":"AR",
    "sg:tags":[
        "tree"
    ],
    "wof:name":"Sampley's Tree Svc",
    "wof:placetype":"venue"
},
  "geometry": {"coordinates":[-90.18809899999999,35.149157],"type":"Point"}
}