{
  "type": "Feature",
  "properties": {
    "iso:country":"US",
    "sg:address":"382 Clara M Ct",
    "sg:city":"Royal",
    "sg:classifiers":[
        {
            "category":"Building & Trades",
            "subcategory":"Plumbing",
            "type":"Services"
        }
    ],
    "sg:phone":"+1 501 767 5719",
    "sg:postcode":"71968",
    "sg:province":"AR",
    "sg:tags":[
        "septic"
    ],
    "wof:name":"A-1 Septic Tank Svc",
    "wof:placetype":"venue"
},
  "geometry": {"coordinates":[-93.281842,34.499697],"type":"Point"}
}