{
  "type": "Feature",
  "properties": {
    "iso:country":"US",
    "sg:address":"1101 W Elm St Ste A",
    "sg:city":"Cabot",
    "sg:classifiers":[
        {
            "category":"Social Services",
            "subcategory":"Child Care",
            "type":"Services"
        }
    ],
    "sg:phone":"+1 501 605 0095",
    "sg:postcode":"72023",
    "sg:province":"AR",
    "sg:tags":[
        "nursery",
        "day"
    ],
    "wof:name":"Kids & Co Child Development Ctr",
    "wof:placetype":"venue"
},
  "geometry": {"coordinates":[-92.028052,34.973972],"type":"Point"}
}