{
  "type": "Feature",
  "properties": {
    "iso:country":"US",
    "sg:address":"1101 S Old Missouri Rd",
    "sg:city":"Springdale",
    "sg:classifiers":[
        {
            "category":"Real Estate",
            "subcategory":"Real Estate Operator",
            "type":"Services"
        }
    ],
    "sg:phone":"+1 479 751 9081",
    "sg:postcode":"72764",
    "sg:province":"AR",
    "sg:tags":[
        "mobile",
        "home",
        "community"
    ],
    "wof:name":"Whisler Rv Park",
    "wof:placetype":"venue"
},
  "geometry": {"coordinates":[-94.116247,36.180636],"type":"Point"}
}