{
  "type": "Feature",
  "properties": {
    "iso:country":"US",
    "sg:address":"4124 Hwy 70 W",
    "sg:city":"Forrest City",
    "sg:classifiers":[
        {
            "category":"Wholesale",
            "subcategory":"Machinery & Supplies",
            "type":"Manufacturing & Wholesale Goods"
        }
    ],
    "sg:phone":"+1 870 633 1645",
    "sg:postcode":"72335",
    "sg:province":"AR",
    "sg:tags":[
        "farm",
        "equipment"
    ],
    "wof:name":"Producers Tractor Co Inc",
    "wof:placetype":"venue"
},
  "geometry": {"coordinates":[-90.84656,34.985776],"type":"Point"}
}