{
  "type": "Feature",
  "properties": {
    "iso:country":"US",
    "sg:address":"575 Cagle Rock Rd",
    "sg:city":"Russellville",
    "sg:classifiers":[
        {
            "category":"Building & Trades",
            "subcategory":"Construction",
            "type":"Services"
        }
    ],
    "sg:phone":"+1 479 880 1906",
    "sg:postcode":"72802",
    "sg:province":"AR",
    "sg:tags":[
        "cabinet",
        "carpentry",
        "maker",
        "contractor"
    ],
    "wof:name":"Collins Cabinets Inc",
    "wof:placetype":"venue"
},
  "geometry": {"coordinates":[-93.087307,35.313062],"type":"Point"}
}