{
  "type": "Feature",
  "properties": {
    "addr:full":"658 Old Strong Hwy Strong AR 71765",
    "addr:housenumber":"658",
    "addr:postcode":"71765",
    "addr:street":"Old Strong Hwy",
    "iso:country":"US",
    "sg:address":"658 Old Strong Hwy",
    "sg:city":"Strong",
    "sg:classifiers":[
        {
            "category":"Organizations",
            "subcategory":"Religious Organization",
            "type":"Services"
        }
    ],
    "sg:phone":"+1 870 862 3840",
    "sg:postcode":"71765",
    "sg:province":"AR",
    "sg:tags":[
        "clergy"
    ],
    "wof:name":"Eddie L Mabry",
    "wof:placetype":"venue"
},
  "geometry": {"coordinates":[-92.44087,33.133323],"type":"Point"}
}