{
  "type": "Feature",
  "properties": {
    "addr:full":"3100B Honeysuckle Ln Rogers AR 72758",
    "addr:housenumber":"3100b",
    "addr:postcode":"72758",
    "addr:street":"Honeysuckle Ln",
    "iso:country":"US",
    "sg:address":"3100B Honeysuckle Ln",
    "sg:city":"Rogers",
    "sg:classifiers":[
        {
            "category":"Professional",
            "subcategory":"Engineering",
            "type":"Services"
        }
    ],
    "sg:phone":"+1 479 986 9675",
    "sg:postcode":"72758",
    "sg:province":"AR",
    "sg:tags":[
        "system",
        "equipment",
        "air conditioning"
    ],
    "wof:name":"Hawkins Co Inc",
    "wof:placetype":"venue"
},
  "geometry": {"coordinates":[-94.12696200000001,36.288402],"type":"Point"}
}