{
  "type": "Feature",
  "properties": {
    "iso:country":"US",
    "sg:address":"221 W Capitol Ave",
    "sg:city":"Little Rock",
    "sg:classifiers":[
        {
            "category":"Shopping",
            "subcategory":"Discount & Variety Stores",
            "type":"Retail Goods"
        }
    ],
    "sg:phone":"+1 501 375 8181",
    "sg:postcode":"72201",
    "sg:province":"AR",
    "sg:website":"www.duckwall.com",
    "wof:name":"Duckwall Variety Store",
    "wof:placetype":"venue"
},
  "geometry": {"coordinates":[-92.273295,34.744376],"type":"Point"}
}