{
  "type": "Feature",
  "properties": {
    "addr:full":"92 Co Rd 234 Cherry Valley AR 72324",
    "addr:housenumber":"92;234",
    "addr:postcode":"72324",
    "addr:street":"Co Rd",
    "iso:country":"US",
    "sg:address":"92 Co Rd 234",
    "sg:city":"Cherry Valley",
    "sg:classifiers":[
        {
            "category":"Retail",
            "subcategory":"Auto Repair",
            "type":"Services"
        }
    ],
    "sg:phone":"+1 870 238 8897",
    "sg:postcode":"72324",
    "sg:province":"AR",
    "sg:tags":[
        "automotive"
    ],
    "wof:name":"D & J Electric",
    "wof:placetype":"venue"
},
  "geometry": {"coordinates":[-90.80731,35.32751],"type":"Point"}
}