{
  "type": "Feature",
  "properties": {
    "addr:full":"1925 Easy St Benton AR 72019",
    "addr:housenumber":"1925",
    "addr:postcode":"72019",
    "addr:street":"Easy St",
    "iso:country":"US",
    "sg:address":"1925 Easy St",
    "sg:city":"Benton",
    "sg:classifiers":[
        {
            "category":"Real Estate",
            "subcategory":"Real Estate Agent",
            "type":"Services"
        }
    ],
    "sg:phone":"+1 501 315 1099",
    "sg:postcode":"72019",
    "sg:province":"AR",
    "wof:name":"Double W Rental",
    "wof:placetype":"venue"
},
  "geometry": {"coordinates":[-92.62311800000001,34.581525],"type":"Point"}
}