{
  "type": "Feature",
  "properties": {
    "iso:country":"US",
    "sg:address":"1006 S Mill St",
    "sg:city":"Grove",
    "sg:classifiers":[
        {
            "category":"Real Estate",
            "subcategory":"Real Estate Agent",
            "type":"Services"
        }
    ],
    "sg:phone":"+1 918 787 2425",
    "sg:postcode":"74344",
    "sg:province":"OK",
    "wof:name":"W. O. Investments, Inc.",
    "wof:placetype":"venue"
},
  "geometry": {"coordinates":[-94.766638,36.587149],"type":"Point"}
}