{
  "type": "Feature",
  "properties": {
    "addr:full":"413 Park Ave Hot Springs National AR 71901",
    "addr:housenumber":"413",
    "addr:postcode":"71901",
    "addr:street":"Park Ave",
    "iso:country":"US",
    "sg:address":"413 Park Ave",
    "sg:city":"Hot Springs National",
    "sg:classifiers":[
        {
            "category":"Personal",
            "type":"Services"
        }
    ],
    "sg:phone":"+1 501 623 4744",
    "sg:postcode":"71901",
    "sg:province":"AR",
    "wof:name":"Redberds Living Canvas Tattoos",
    "wof:placetype":"venue"
},
  "geometry": {"coordinates":[-93.05418,34.523037],"type":"Point"}
}