{
  "type": "Feature",
  "properties": {
    "iso:country":"US",
    "sg:address":"5161 Highway 243 N",
    "sg:city":"Marvell",
    "sg:classifiers":[
        {
            "category":"Farming",
            "subcategory":"Farm",
            "type":"Manufacturing & Wholesale Goods"
        }
    ],
    "sg:phone":"+1 870 829 2210",
    "sg:postcode":"72366",
    "sg:province":"AR",
    "sg:website":"http://www.doublehfarms.com",
    "wof:name":"Double H Farms",
    "wof:placetype":"venue"
},
  "geometry": {"coordinates":[-90.900726,34.616143],"type":"Point"}
}