{
  "type": "Feature",
  "properties": {
    "iso:country":"US",
    "sg:address":"4716 Baseline Rd",
    "sg:city":"Little Rock",
    "sg:classifiers":[
        {
            "category":"Social Services",
            "subcategory":"Child Care",
            "type":"Services"
        }
    ],
    "sg:phone":"+1 501 562 6286",
    "sg:postcode":"72209",
    "sg:province":"AR",
    "sg:tags":[
        "day"
    ],
    "wof:name":"Granny's Den Learning Academy",
    "wof:placetype":"venue"
},
  "geometry": {"coordinates":[-92.33007600000001,34.668517],"type":"Point"}
}