{
  "type": "Feature",
  "properties": {
    "addr:full":"105 Barber Rd Bald Knob AR 72010",
    "addr:housenumber":"105",
    "addr:postcode":"72010",
    "addr:street":"Barber Rd",
    "iso:country":"US",
    "sg:address":"105 Barber Rd",
    "sg:city":"Bald Knob",
    "sg:classifiers":[
        {
            "category":"Freight",
            "type":"Transportation"
        }
    ],
    "sg:phone":"+1 501 207 1272",
    "sg:postcode":"72010",
    "sg:province":"AR",
    "sg:tags":[
        "operator",
        "local",
        "trucking"
    ],
    "wof:name":"Burns Trucking",
    "wof:placetype":"venue"
},
  "geometry": {"coordinates":[-91.572221,35.405222],"type":"Point"}
}