{
  "type": "Feature",
  "properties": {
    "addr:full":"2009 N Buerkle St Stuttgart AR 72160",
    "addr:housenumber":"2009",
    "addr:postcode":"72160",
    "addr:street":"N Buerkle St",
    "iso:country":"US",
    "sg:address":"2009 N Buerkle St",
    "sg:city":"Stuttgart",
    "sg:classifiers":[
        {
            "category":"Place Of Worship",
            "subcategory":"Church",
            "type":"Public Place"
        },
        {
            "category":"Place Of Worship",
            "type":"Public Place"
        },
        {
            "category":"Organizations",
            "subcategory":"Religious Organization",
            "type":"Services"
        }
    ],
    "sg:phone":"+1 870 673 2293",
    "sg:postcode":"72160",
    "sg:province":"AR",
    "sg:tags":[
        "churches-interdenominational",
        "churches-various",
        "denomination"
    ],
    "wof:name":"Central Christian Church",
    "wof:placetype":"venue"
},
  "geometry": {"coordinates":[-91.557429,34.522275],"type":"Point"}
}