{
  "type": "Feature",
  "properties": {
    "iso:country":"US",
    "sg:address":"14637 Daniels Rd",
    "sg:city":"Bentonville",
    "sg:classifiers":[
        {
            "category":"Recreation",
            "type":"Entertainment"
        }
    ],
    "sg:phone":"+1 479 795 0570",
    "sg:postcode":"72712",
    "sg:province":"AR",
    "sg:tags":[
        "riding",
        "academy"
    ],
    "wof:name":"Rocky Creek Riding Ctr",
    "wof:placetype":"venue"
},
  "geometry": {"coordinates":[-94.35396,36.308669],"type":"Point"}
}