{
  "type": "Feature",
  "properties": {
    "iso:country":"US",
    "sg:address":"2221 Biscayne Dr",
    "sg:city":"Little Rock",
    "sg:classifiers":[
        {
            "category":"Professional",
            "subcategory":"Business Services",
            "type":"Services"
        }
    ],
    "sg:phone":"+1 501 223 9099",
    "sg:postcode":"72227",
    "sg:province":"AR",
    "wof:name":"Lease Technology",
    "wof:placetype":"venue"
},
  "geometry": {"coordinates":[-92.363102,34.773696],"type":"Point"}
}