{
  "type": "Feature",
  "properties": {
    "iso:country":"US",
    "sg:address":"1410 Kavanaugh Blvd",
    "sg:city":"Little Rock",
    "sg:classifiers":[
        {
            "category":"Professional",
            "subcategory":"Art Services",
            "type":"Services"
        }
    ],
    "sg:phone":"+1 501 661 9002",
    "sg:postcode":"72205",
    "sg:province":"AR",
    "sg:tags":[
        "photography",
        "commercial"
    ],
    "wof:name":"Louis Tobian Photography",
    "wof:placetype":"venue"
},
  "geometry": {"coordinates":[-92.307518,34.754875],"type":"Point"}
}