{
  "type": "Feature",
  "properties": {
    "addr:full":"62 Sidlaw Hills Dr Bella Vista AR 72715",
    "addr:housenumber":"62",
    "addr:postcode":"72715",
    "addr:street":"Sidlaw Hills Dr",
    "iso:country":"US",
    "sg:address":"62 Sidlaw Hills Dr",
    "sg:city":"Bella Vista",
    "sg:classifiers":[
        {
            "category":"Real Estate",
            "subcategory":"Real Estate Agent",
            "type":"Services"
        }
    ],
    "sg:phone":"+1 479 876 2520",
    "sg:postcode":"72715",
    "sg:province":"AR",
    "wof:name":"Woodys Real Estate",
    "wof:placetype":"venue"
},
  "geometry": {"coordinates":[-94.31011700000001,36.484946],"type":"Point"}
}