{
  "type": "Feature",
  "properties": {
    "iso:country":"US",
    "sg:address":"50 Ranch Ridge Rd",
    "sg:city":"Little Rock",
    "sg:classifiers":[
        {
            "category":"Real Estate",
            "subcategory":"Real Estate Operator",
            "type":"Services"
        }
    ],
    "sg:phone":"+1 501 223 3730",
    "sg:postcode":"72223",
    "sg:province":"AR",
    "sg:tags":[
        "building",
        "nonresidential"
    ],
    "wof:name":"Dso Properties LLC",
    "wof:placetype":"venue"
},
  "geometry": {"coordinates":[-92.458326,34.810935],"type":"Point"}
}