{
  "type": "Feature",
  "properties": {
    "iso:country":"US",
    "sg:address":"561 Madison 6400",
    "sg:city":"Elkins",
    "sg:classifiers":[
        {
            "category":"Manufacturing",
            "subcategory":"Buildings",
            "type":"Manufacturing & Wholesale Goods"
        },
        {
            "category":"Building & Trades",
            "subcategory":"Construction",
            "type":"Services"
        }
    ],
    "sg:phone":"+1 479 463 2808",
    "sg:postcode":"72727",
    "sg:province":"AR",
    "sg:tags":[
        "home",
        "builder",
        "contractor"
    ],
    "wof:name":"Tnp Construction Company",
    "wof:placetype":"venue"
},
  "geometry": {"coordinates":[-93.926974,35.978124],"type":"Point"}
}