{
  "type": "Feature",
  "properties": {
    "iso:country":"US",
    "sg:address":"1801 Moberly Ln",
    "sg:city":"Bentonville",
    "sg:classifiers":[
        {
            "category":"Professional",
            "subcategory":"Computer Services",
            "type":"Services"
        }
    ],
    "sg:phone":"+1 479 464 9109",
    "sg:postcode":"72712",
    "sg:province":"AR",
    "sg:tags":[
        "repair"
    ],
    "wof:name":"Need A Geek",
    "wof:placetype":"venue"
},
  "geometry": {"coordinates":[-94.183516,36.35206],"type":"Point"}
}