{
  "type": "Feature",
  "properties": {
    "iso:country":"US",
    "sg:address":"421 N Main St",
    "sg:city":"Nashville",
    "sg:classifiers":[
        {
            "category":"Government",
            "subcategory":"Office",
            "type":"Public Place"
        }
    ],
    "sg:phone":"+1 870 845 7511",
    "sg:postcode":"71852",
    "sg:province":"AR",
    "wof:name":"Howard County Assessor's Ofc",
    "wof:placetype":"venue"
},
  "geometry": {"coordinates":[-93.847033,33.947562],"type":"Point"}
}