{
  "type": "Feature",
  "properties": {
    "iso:country":"US",
    "sg:address":"511 W Tulsa St",
    "sg:city":"Siloam Springs",
    "sg:classifiers":[
        {
            "category":"Professional",
            "type":"Services"
        }
    ],
    "sg:phone":"+1 479 736 5439",
    "sg:postcode":"72761",
    "sg:province":"OK",
    "sg:tags":[
        "establishment"
    ],
    "wof:name":"A King Midas Touch",
    "wof:placetype":"venue"
},
  "geometry": {"coordinates":[-94.545828,36.178123],"type":"Point"}
}