{
  "type": "Feature",
  "properties": {
    "addr:full":"305 N 24th St Rogers AR 72756",
    "addr:housenumber":"305",
    "addr:postcode":"72756",
    "addr:street":"N 24Th St",
    "iso:country":"US",
    "sg:address":"305 N 24th St",
    "sg:city":"Rogers",
    "sg:classifiers":[
        {
            "category":"Health Services",
            "subcategory":"Chiropractor",
            "type":"Services"
        }
    ],
    "sg:phone":"+1 479 636 3021",
    "sg:postcode":"72756",
    "sg:province":"AR",
    "wof:name":"Hines Teri L DC",
    "wof:placetype":"venue"
},
  "geometry": {"coordinates":[-94.151717,36.336397],"type":"Point"}
}