{
  "type": "Feature",
  "properties": {
    "iso:country":"US",
    "sg:address":"220 Cooper St",
    "sg:city":"Hot Springs National Park",
    "sg:classifiers":[
        {
            "category":"Professional",
            "type":"Services"
        }
    ],
    "sg:phone":"+1 501 624 5072",
    "sg:postcode":"71913",
    "sg:province":"AR",
    "wof:name":"Steve P Uher",
    "wof:placetype":"venue"
},
  "geometry": {"coordinates":[-93.082693,34.494177],"type":"Point"}
}