{
  "type": "Feature",
  "properties": {
    "iso:country":"US",
    "sg:address":"221 Cain Rd",
    "sg:city":"Hot Springs",
    "sg:classifiers":[
        {
            "category":"Personal",
            "type":"Services"
        }
    ],
    "sg:phone":"+1 501 767 1805",
    "sg:postcode":"71913",
    "sg:province":"AR",
    "sg:tags":[
        "therapist",
        "massage"
    ],
    "wof:name":"Massage Therapy Clinic",
    "wof:placetype":"venue"
},
  "geometry": {"coordinates":[-93.137279,34.467435],"type":"Point"}
}