{
  "type": "Feature",
  "properties": {
    "iso:country":"US",
    "sg:address":"928 Sidney St",
    "sg:city":"Batesville",
    "sg:classifiers":[
        {
            "category":"Manufacturing",
            "subcategory":"Food",
            "type":"Manufacturing & Wholesale Goods"
        },
        {
            "category":"Food & Beverages",
            "subcategory":"Bakery",
            "type":"Retail Goods"
        }
    ],
    "sg:phone":"+1 870 793 6279",
    "sg:postcode":"72501",
    "sg:province":"AR",
    "sg:tags":[
        "product",
        "doughnut",
        "mfg"
    ],
    "wof:name":"Kay's Donut Shop",
    "wof:placetype":"venue"
},
  "geometry": {"coordinates":[-91.636945,35.770305],"type":"Point"}
}