{
  "type": "Feature",
  "properties": {
    "addr:full":"1243 S Paradise Dr Fayetteville AR 72701",
    "addr:housenumber":"1243",
    "addr:postcode":"72701",
    "addr:street":"S Paradise Dr",
    "iso:country":"US",
    "sg:address":"1243 S Paradise Dr",
    "sg:city":"Fayetteville",
    "sg:classifiers":[
        {
            "category":"Professional",
            "type":"Services"
        }
    ],
    "sg:phone":"+1 479 443 2834",
    "sg:postcode":"72701",
    "sg:province":"AR",
    "sg:tags":[
        "establishment"
    ],
    "wof:name":"L L & Alpha",
    "wof:placetype":"venue"
},
  "geometry": {"coordinates":[-94.09155,36.048342],"type":"Point"}
}