{
  "type": "Feature",
  "properties": {
    "iso:country":"US",
    "sg:address":"6241 Highway 62 W",
    "sg:city":"Pocahontas",
    "sg:classifiers":[
        {
            "category":"Retail",
            "subcategory":"Storage",
            "type":"Services"
        }
    ],
    "sg:phone":"+1 870 378 7575",
    "sg:postcode":"72455",
    "sg:province":"AR",
    "sg:tags":[
        "self"
    ],
    "sg:website":"http://www.ashlandaussies.com",
    "wof:name":"Ashland Mini Aussies Australian Shepherd Breeder and Sales",
    "wof:placetype":"venue"
},
  "geometry": {"coordinates":[-91.06112400000001,36.247147],"type":"Point"}
}