{
  "type": "Feature",
  "properties": {
    "iso:country":"US",
    "sg:address":"709 N Timberlane Dr",
    "sg:city":"El Dorado",
    "sg:classifiers":[
        {
            "category":"Building & Trades",
            "subcategory":"Landscaping Services",
            "type":"Services"
        }
    ],
    "sg:phone":"+1 870 862 1301",
    "sg:postcode":"71730",
    "sg:province":"AR",
    "wof:name":"Diversified Services",
    "wof:placetype":"venue"
},
  "geometry": {"coordinates":[-92.686636,33.215341],"type":"Point"}
}