{
  "type": "Feature",
  "properties": {
    "iso:country":"US",
    "sg:address":"702 Hornbeck Ave",
    "sg:city":"Mena",
    "sg:classifiers":[
        {
            "category":"Social Services",
            "subcategory":"Adult Care",
            "type":"Services"
        }
    ],
    "sg:phone":"+1 479 394 3433",
    "sg:postcode":"71953",
    "sg:province":"AR",
    "sg:tags":[
        "residential",
        "aged",
        "homes-institutional"
    ],
    "wof:name":"In Home Service",
    "wof:placetype":"venue"
},
  "geometry": {"coordinates":[-94.224851,34.58298],"type":"Point"}
}