{
  "type": "Feature",
  "properties": {
    "iso:country":"US",
    "sg:address":"807 W Bailey Ave Apt A",
    "sg:city":"Springdale",
    "sg:classifiers":[
        {
            "category":"Shopping",
            "subcategory":"Gifts & Souvenirs",
            "type":"Retail Goods"
        }
    ],
    "sg:phone":"+1 479 751 5849",
    "sg:postcode":"72764",
    "sg:province":"AR",
    "sg:tags":[
        "greeting",
        "card"
    ],
    "wof:name":"Stokes Phone Cards",
    "wof:placetype":"venue"
},
  "geometry": {"coordinates":[-94.135254,36.198952],"type":"Point"}
}