{
  "type": "Feature",
  "properties": {
    "iso:country":"US",
    "sg:address":"921 W Vine St",
    "sg:city":"Sheridan",
    "sg:classifiers":[
        {
            "category":"Organizations",
            "subcategory":"Religious Organization",
            "type":"Services"
        }
    ],
    "sg:phone":"+1 870 942 4532",
    "sg:postcode":"72150",
    "sg:province":"AR",
    "sg:tags":[
        "church"
    ],
    "wof:name":"Holy Cross Catholic Church",
    "wof:placetype":"venue"
},
  "geometry": {"coordinates":[-92.410988,34.31113],"type":"Point"}
}