{
  "type": "Feature",
  "properties": {
    "iso:country":"US",
    "sg:address":"4621 S Caraway Rd",
    "sg:city":"Jonesboro",
    "sg:classifiers":[
        {
            "category":"Personal",
            "type":"Services"
        }
    ],
    "sg:phone":"+1 870 931 9369",
    "sg:postcode":"72404",
    "sg:province":"AR",
    "sg:tags":[
        "control",
        "weight"
    ],
    "wof:name":"Nutri System Direct Ind Rep",
    "wof:placetype":"venue"
},
  "geometry": {"coordinates":[-90.678969,35.781313],"type":"Point"}
}