{
  "type": "Feature",
  "properties": {
    "addr:full":"58 W Main St Marianna AR 72360",
    "addr:housenumber":"58",
    "addr:postcode":"72360",
    "addr:street":"W Main St",
    "iso:country":"US",
    "sg:address":"58 W Main St",
    "sg:city":"Marianna",
    "sg:classifiers":[
        {
            "category":"Social Services",
            "subcategory":"Job Training",
            "type":"Services"
        }
    ],
    "sg:phone":"+1 870 295 9529",
    "sg:postcode":"72360",
    "sg:province":"AR",
    "sg:tags":[
        "rehab",
        "government"
    ],
    "wof:name":"Work Force Inc",
    "wof:placetype":"venue"
},
  "geometry": {"coordinates":[-90.759079,34.77357],"type":"Point"}
}