{
  "type": "Feature",
  "properties": {
    "iso:country":"US",
    "sg:address":"11221 Oak Hill Rd",
    "sg:city":"Little Rock",
    "sg:classifiers":[
        {
            "category":"Building & Trades",
            "subcategory":"Electrical",
            "type":"Services"
        }
    ],
    "sg:phone":"+1 501 541 5772",
    "sg:postcode":"72206",
    "sg:province":"AR",
    "sg:tags":[
        "electrical",
        "contractor"
    ],
    "wof:name":"Ebco Electrical Inc",
    "wof:placetype":"venue"
},
  "geometry": {"coordinates":[-92.276641,34.64503],"type":"Point"}
}