{
  "type": "Feature",
  "properties": {
    "iso:country":"US",
    "sg:address":"1001 N Vine",
    "sg:city":"Magnolia",
    "sg:classifiers":[
        {
            "category":"Travel",
            "subcategory":"Hotels & Motels",
            "type":"Entertainment"
        }
    ],
    "sg:phone":"+1 870 234 4252",
    "sg:postcode":"71753",
    "sg:province":"AR",
    "wof:name":"Flamingo Motel",
    "wof:placetype":"venue"
},
  "geometry": {"coordinates":[-93.243797,33.27549],"type":"Point"}
}