{
  "type": "Feature",
  "properties": {
    "iso:country":"US",
    "sg:address":"3501 N Main St",
    "sg:city":"Newport",
    "sg:classifiers":[
        {
            "category":"Freight",
            "type":"Transportation"
        }
    ],
    "sg:phone":"+1 870 523 8085",
    "sg:postcode":"72112",
    "sg:province":"AR",
    "sg:tags":[
        "grain",
        "elevator"
    ],
    "wof:name":"Mc Neil Grain Co",
    "wof:placetype":"venue"
},
  "geometry": {"coordinates":[-91.265125,35.647611],"type":"Point"}
}