{
  "type": "Feature",
  "properties": {
    "iso:country":"US",
    "sg:address":"3310 Country Club Rd",
    "sg:city":"Arkadelphia",
    "sg:classifiers":[
        {
            "category":"Manufacturing",
            "subcategory":"Lumber",
            "type":"Manufacturing & Wholesale Goods"
        }
    ],
    "sg:phone":"+1 870 246 2603",
    "sg:postcode":"71923",
    "sg:province":"AR",
    "sg:tags":[
        "operation",
        "timber",
        "tract"
    ],
    "wof:name":"Larry Poarch",
    "wof:placetype":"venue"
},
  "geometry": {"coordinates":[-93.093136,34.138087],"type":"Point"}
}