{
  "type": "Feature",
  "properties": {
    "iso:country":"US",
    "sg:address":"200 W Walnut St",
    "sg:city":"Blytheville",
    "sg:classifiers":[
        {
            "category":"Government",
            "subcategory":"Court House",
            "type":"Public Place"
        }
    ],
    "sg:phone":"+1 870 763 1621",
    "sg:postcode":"72315",
    "sg:province":"AR",
    "sg:tags":[
        "county",
        "judges"
    ],
    "wof:name":"Mississippi County Judges Off",
    "wof:placetype":"venue"
},
  "geometry": {"coordinates":[-89.905414,35.928481],"type":"Point"}
}