{
  "type": "Feature",
  "properties": {
    "iso:country":"US",
    "sg:address":"3111 E 19th St",
    "sg:city":"Texarkana",
    "sg:classifiers":[
        {
            "category":"Freight",
            "type":"Transportation"
        }
    ],
    "sg:phone":"+1 870 773 9239",
    "sg:postcode":"71854",
    "sg:province":"TX",
    "sg:tags":[
        "general"
    ],
    "wof:name":"C&C Tye Mini Storage",
    "wof:placetype":"venue"
},
  "geometry": {"coordinates":[-94.008986,33.440658],"type":"Point"}
}