{
  "type": "Feature",
  "properties": {
    "iso:country":"US",
    "sg:address":"1408 W Vine Ave",
    "sg:city":"Searcy",
    "sg:classifiers":[
        {
            "category":"Professional",
            "type":"Services"
        }
    ],
    "sg:phone":"+1 501 268 4166",
    "sg:postcode":"72143",
    "sg:province":"AR",
    "wof:name":"Jek Inc",
    "wof:placetype":"venue"
},
  "geometry": {"coordinates":[-91.752791,35.252115],"type":"Point"}
}