{
  "type": "Feature",
  "properties": {
    "addr:full":"1307 Maplewood Rd Harrison AR 72601",
    "addr:housenumber":"1307",
    "addr:postcode":"72601",
    "addr:street":"Maplewood Rd",
    "iso:country":"US",
    "sg:address":"1307 Maplewood Rd",
    "sg:city":"Harrison",
    "sg:classifiers":[
        {
            "category":"Education",
            "subcategory":"School",
            "type":"Public Place"
        }
    ],
    "sg:phone":"+1 870 741 0944",
    "sg:postcode":"72601",
    "sg:province":"AR",
    "wof:name":"Christian Hillcrest School",
    "wof:placetype":"venue"
},
  "geometry": {"coordinates":[-93.10388399999999,36.245511],"type":"Point"}
}