{
  "type": "Feature",
  "properties": {
    "iso:country":"US",
    "sg:address":"201 Joe Brady Dr",
    "sg:city":"Helena",
    "sg:classifiers":[
        {
            "category":"Organizations",
            "subcategory":"Religious Organization",
            "type":"Services"
        }
    ],
    "sg:phone":"+1 870 817 0678",
    "sg:postcode":"72342",
    "sg:province":"AR",
    "sg:tags":[
        "church"
    ],
    "wof:name":"New Jerusalem Outreach Mnstrs",
    "wof:placetype":"venue"
},
  "geometry": {"coordinates":[-90.597679,34.511238],"type":"Point"}
}