{
  "type": "Feature",
  "properties": {
    "iso:country":"US",
    "sg:address":"309 Morrow St S",
    "sg:city":"Mena",
    "sg:classifiers":[
        {
            "category":"Health Services",
            "subcategory":"Doctor",
            "type":"Services"
        }
    ],
    "sg:phone":"+1 479 394 6596",
    "sg:postcode":"71953",
    "sg:province":"AR",
    "sg:tags":[
        "dentist"
    ],
    "wof:name":"David Van Winkle DDS",
    "wof:placetype":"venue"
},
  "geometry": {"coordinates":[-94.222598,34.584708],"type":"Point"}
}