{
  "type": "Feature",
  "properties": {
    "addr:full":"6417 N Lakewood Dr Van Buren AR 72956",
    "addr:housenumber":"6417",
    "addr:postcode":"72956",
    "addr:street":"N Lakewood Dr",
    "iso:country":"US",
    "sg:address":"6417 N Lakewood Dr",
    "sg:city":"Van Buren",
    "sg:classifiers":[
        {
            "category":"Professional",
            "type":"Services"
        }
    ],
    "sg:phone":"+1 479 474 9427",
    "sg:postcode":"72956",
    "sg:province":"AR",
    "wof:name":"James K Vaughan",
    "wof:placetype":"venue"
},
  "geometry": {"coordinates":[-94.36480400000001,35.532831],"type":"Point"}
}