{
  "type": "Feature",
  "properties": {
    "iso:country":"US",
    "sg:address":"713 S 1st St",
    "sg:city":"Jacksonville",
    "sg:classifiers":[
        {
            "category":"Autos & Motor Vehicles",
            "subcategory":"Fuel & Gas Station",
            "type":"Retail Goods"
        }
    ],
    "sg:phone":"+1 501 982 8200",
    "sg:postcode":"72076",
    "sg:province":"AR",
    "sg:tags":[
        "grocery",
        "station",
        "gasoline"
    ],
    "wof:name":"Coastal Market",
    "wof:placetype":"venue"
},
  "geometry": {"coordinates":[-92.11672900000001,34.859593],"type":"Point"}
}