{
  "type": "Feature",
  "properties": {
    "iso:country":"US",
    "sg:address":"401 E Maryland Ave",
    "sg:city":"Sherwood",
    "sg:classifiers":[
        {
            "category":"Organizations",
            "subcategory":"Professional Association",
            "type":"Services"
        }
    ],
    "sg:phone":"+1 501 834 2443",
    "sg:postcode":"72120",
    "sg:province":"AR",
    "wof:name":"Native American Coalition",
    "wof:placetype":"venue"
},
  "geometry": {"coordinates":[-92.23063,34.840506],"type":"Point"}
}