{
  "type": "Feature",
  "properties": {
    "iso:country":"US",
    "sg:address":"101 N Main St",
    "sg:city":"North Little Rock",
    "sg:classifiers":[
        {
            "category":"Food & Beverages",
            "subcategory":"Bakery",
            "type":"Retail Goods"
        }
    ],
    "sg:phone":"+1 501 372 7322",
    "sg:postcode":"72114",
    "sg:province":"AR",
    "wof:name":"Sfbc",
    "wof:placetype":"venue"
},
  "geometry": {"coordinates":[-92.267821,34.754723],"type":"Point"}
}