{
  "type": "Feature",
  "properties": {
    "addr:full":"110 W Industrial Park Rd Harrison AR 72601",
    "addr:housenumber":"110",
    "addr:postcode":"72601",
    "addr:street":"W Industrial Park Rd",
    "iso:country":"US",
    "sg:address":"110 W Industrial Park Rd",
    "sg:city":"Harrison",
    "sg:classifiers":[
        {
            "category":"Insurance",
            "subcategory":"Hazard Insurance",
            "type":"Services"
        },
        {
            "category":"Banks & Credit Unions",
            "subcategory":"Financial Services",
            "type":"Services"
        }
    ],
    "sg:phone":"+1 870 741 3488",
    "sg:postcode":"72601",
    "sg:province":"AR",
    "sg:tags":[
        "planning",
        "sharing",
        "business",
        "profit",
        "annuity",
        "commercial",
        "retirement",
        "plan",
        "pension"
    ],
    "wof:name":"Farm Bureau Insurance",
    "wof:placetype":"venue"
},
  "geometry": {"coordinates":[-93.11914299999999,36.24981],"type":"Point"}
}