{
  "type": "Feature",
  "properties": {
    "iso:country":"US",
    "sg:address":"1 Choctaw Dr",
    "sg:city":"Cherokee Village",
    "sg:classifiers":[
        {
            "category":"Shopping",
            "subcategory":"Pharmacy",
            "type":"Retail Goods"
        },
        {
            "category":"Manufacturing",
            "subcategory":"Chemicals & Compounds",
            "type":"Manufacturing & Wholesale Goods"
        }
    ],
    "sg:phone":"+1 870 856 4696",
    "sg:postcode":"72529",
    "sg:province":"AR",
    "sg:tags":[
        "pharmaceutical"
    ],
    "wof:name":"Econo-Med Pharmacy Inc",
    "wof:placetype":"venue"
},
  "geometry": {"coordinates":[-91.51512,36.30515],"type":"Point"}
}