{
  "type": "Feature",
  "properties": {
    "addr:full":"1400 W Dewitt Henry Dr Beebe AR 72012",
    "addr:housenumber":"1400",
    "addr:postcode":"72012",
    "addr:street":"W;Henry Dr",
    "iso:country":"US",
    "sg:address":"1400 W Dewitt Henry Dr",
    "sg:city":"Beebe",
    "sg:classifiers":[
        {
            "category":"Autos & Motor Vehicles",
            "subcategory":"Auto Supplies",
            "type":"Retail Goods"
        }
    ],
    "sg:phone":"+1 501 882 5571",
    "sg:postcode":"72012",
    "sg:province":"AR",
    "sg:tags":[
        "automobile",
        "parts"
    ],
    "wof:name":"NAPA Auto Parts",
    "wof:placetype":"venue"
},
  "geometry": {"coordinates":[-91.89961099999999,35.074836],"type":"Point"}
}