{
  "type": "Feature",
  "properties": {
    "iso:country":"US",
    "sg:address":"1887 State Hwy 193",
    "sg:city":"Wynne",
    "sg:phone":"+1 870 238 2933",
    "sg:postcode":"72396",
    "sg:province":"AR",
    "sg:tags":[
        "farm",
        "rice",
        "wheat",
        "soybean"
    ],
    "wof:name":"Donald Davis",
    "wof:placetype":"venue"
},
  "geometry": {"coordinates":[-90.915916,35.265887],"type":"Point"}
}