{
  "type": "Feature",
  "properties": {
    "iso:country":"US",
    "sg:address":"3 Tyler St",
    "sg:city":"Greenbrier",
    "sg:classifiers":[
        {
            "category":"Retail",
            "subcategory":"Auto Repair",
            "type":"Services"
        }
    ],
    "sg:phone":"+1 501 679 4933",
    "sg:postcode":"72058",
    "sg:province":"AR",
    "sg:tags":[
        "automotive",
        "general"
    ],
    "wof:name":"Hargroves Auto Service",
    "wof:placetype":"venue"
},
  "geometry": {"coordinates":[-92.388364,35.211586],"type":"Point"}
}