{
  "type": "Feature",
  "properties": {
    "iso:country":"US",
    "sg:address":"21941 I- 30",
    "sg:city":"Bryant",
    "sg:classifiers":[
        {
            "category":"Professional",
            "type":"Services"
        }
    ],
    "sg:phone":"+1 501 847 2946",
    "sg:postcode":"72022",
    "sg:province":"AR",
    "wof:name":"Technology Services America",
    "wof:placetype":"venue"
},
  "geometry": {"coordinates":[-92.510842,34.613101],"type":"Point"}
}