{
  "type": "Feature",
  "properties": {
    "addr:full":"782 Foster Chapel Rd Searcy AR 72143",
    "addr:housenumber":"782",
    "addr:postcode":"72143",
    "addr:street":"Foster Chapel Rd",
    "iso:country":"US",
    "sg:address":"782 Foster Chapel Rd",
    "sg:city":"Searcy",
    "sg:classifiers":[
        {
            "category":"Building & Trades",
            "subcategory":"Construction",
            "type":"Services"
        }
    ],
    "sg:phone":"+1 501 279 2963",
    "sg:postcode":"72143",
    "sg:province":"AR",
    "sg:tags":[
        "painter"
    ],
    "wof:name":"Superior Painting & Drywall",
    "wof:placetype":"venue"
},
  "geometry": {"coordinates":[-91.832855,35.284705],"type":"Point"}
}