{
  "type": "Feature",
  "properties": {
    "iso:country":"US",
    "sg:address":"1804 Eastern Ave",
    "sg:city":"Newport",
    "sg:classifiers":[
        {
            "category":"Manufacturing",
            "subcategory":"Food",
            "type":"Manufacturing & Wholesale Goods"
        }
    ],
    "sg:phone":"+1 870 523 6033",
    "sg:postcode":"72112",
    "sg:province":"AR",
    "sg:tags":[
        "product"
    ],
    "wof:name":"Malcolm Haigwood",
    "wof:placetype":"venue"
},
  "geometry": {"coordinates":[-91.247322,35.622334],"type":"Point"}
}