{
  "type": "Feature",
  "properties": {
    "addr:full":"151 Cottondale Rd Pine Bluff AR 71601",
    "addr:housenumber":"151",
    "addr:postcode":"71601",
    "addr:street":"Cottondale Rd",
    "iso:country":"US",
    "sg:address":"151 Cottondale Rd",
    "sg:city":"Pine Bluff",
    "sg:phone":"+1 870 534 4221",
    "sg:postcode":"71601",
    "sg:province":"AR",
    "sg:tags":[
        "farm",
        "crop"
    ],
    "wof:name":"D & N Ward Farms",
    "wof:placetype":"venue"
},
  "geometry": {"coordinates":[-91.852788,34.179215],"type":"Point"}
}