{
  "type": "Feature",
  "properties": {
    "iso:country":"US",
    "sg:address":"8138 Burton Ln",
    "sg:city":"Rogers",
    "sg:classifiers":[
        {
            "category":"Restaurant",
            "type":"Food & Drink"
        }
    ],
    "sg:phone":"+1 479 359 0059",
    "sg:postcode":"72758",
    "sg:province":"AR",
    "wof:name":"Mesquite Tree Grill",
    "wof:placetype":"venue"
},
  "geometry": {"coordinates":[-94.204193,36.28831],"type":"Point"}
}