{
  "type": "Feature",
  "properties": {
    "iso:country":"US",
    "sg:address":"700 W Pridemore Dr",
    "sg:city":"Lincoln",
    "sg:classifiers":[
        {
            "category":"Home & Garden",
            "subcategory":"Building Materials",
            "type":"Retail Goods"
        }
    ],
    "sg:phone":"+1 479 824 3292",
    "sg:postcode":"72744",
    "sg:province":"AR",
    "sg:tags":[
        "lumber"
    ],
    "wof:name":"Carrington Lumber & Hdwr Co",
    "wof:placetype":"venue"
},
  "geometry": {"coordinates":[-94.431505,35.950987],"type":"Point"}
}