{
  "type": "Feature",
  "properties": {
    "addr:full":"733 US Hwy 64 Wynne AR 72396",
    "addr:housenumber":"733",
    "addr:postcode":"72396",
    "addr:street":"Us Hwy 64",
    "iso:country":"US",
    "sg:address":"733 US Hwy 64",
    "sg:city":"Wynne",
    "sg:classifiers":[
        {
            "category":"Government",
            "subcategory":"Office",
            "type":"Public Place"
        }
    ],
    "sg:phone":"+1 870 238 5541",
    "sg:postcode":"72396",
    "sg:province":"AR",
    "sg:tags":[
        "county"
    ],
    "wof:name":"Cross County Material",
    "wof:placetype":"venue"
},
  "geometry": {"coordinates":[-90.975176,35.251453],"type":"Point"}
}