{
  "type": "Feature",
  "properties": {
    "iso:country":"US",
    "sg:address":"701 SE J St",
    "sg:city":"Bentonville",
    "sg:classifiers":[
        {
            "category":"Wholesale",
            "subcategory":"Durable Goods & Equipment",
            "type":"Manufacturing & Wholesale Goods"
        }
    ],
    "sg:phone":"+1 479 271 8282",
    "sg:postcode":"72712",
    "sg:province":"AR",
    "sg:tags":[
        "importer"
    ],
    "wof:name":"Test Rite Products Corp",
    "wof:placetype":"venue"
},
  "geometry": {"coordinates":[-94.196671,36.364968],"type":"Point"}
}