{
  "type": "Feature",
  "properties": {
    "iso:country":"US",
    "sg:address":"1301 N Hervey St",
    "sg:city":"Hope",
    "sg:classifiers":[
        {
            "category":"Shopping",
            "subcategory":"Jewelry",
            "type":"Retail Goods"
        }
    ],
    "sg:phone":"+1 870 722 5411",
    "sg:postcode":"71801",
    "sg:province":"AR",
    "sg:tags":[
        "jeweler"
    ],
    "wof:name":"Friedman's",
    "wof:placetype":"venue"
},
  "geometry": {"coordinates":[-93.6026,33.678858],"type":"Point"}
}