{
  "type": "Feature",
  "properties": {
    "iso:country":"US",
    "sg:address":"1304 N Thompson St",
    "sg:city":"Springdale",
    "sg:classifiers":[
        {
            "category":"Banks & Credit Unions",
            "subcategory":"Bank",
            "type":"Services"
        }
    ],
    "sg:phone":"+1 479 927 2615",
    "sg:postcode":"72764",
    "sg:province":"AR",
    "sg:tags":[
        "depository",
        "banking",
        "check",
        "cashing"
    ],
    "wof:name":"First American Cash Advance",
    "wof:placetype":"venue"
},
  "geometry": {"coordinates":[-94.138328,36.197749],"type":"Point"}
}