{
  "type": "Feature",
  "properties": {
    "addr:full":"214 River Ridge Pt Little Rock AR 72227",
    "addr:housenumber":"214",
    "addr:postcode":"72227",
    "addr:street":"River Ridge Pt",
    "iso:country":"US",
    "sg:address":"214 River Ridge Pt",
    "sg:city":"Little Rock",
    "sg:classifiers":[
        {
            "category":"Real Estate",
            "subcategory":"Real Estate Operator",
            "type":"Services"
        }
    ],
    "sg:phone":"+1 501 562 1124",
    "sg:postcode":"72227",
    "sg:province":"AR",
    "sg:tags":[
        "building",
        "nonresidential"
    ],
    "wof:name":"ML Properties Corp",
    "wof:placetype":"venue"
},
  "geometry": {"coordinates":[-92.385201,34.792529],"type":"Point"}
}