{
  "type": "Feature",
  "properties": {
    "iso:country":"US",
    "sg:address":"2509 Brasco Rd",
    "sg:city":"Jacksonville",
    "sg:classifiers":[
        {
            "category":"Wholesale",
            "subcategory":"Vending Machines",
            "type":"Manufacturing & Wholesale Goods"
        }
    ],
    "sg:phone":"+1 501 988 0003",
    "sg:postcode":"72076",
    "sg:province":"AR",
    "sg:tags":[
        "operator"
    ],
    "wof:name":"Sherrys Vending",
    "wof:placetype":"venue"
},
  "geometry": {"coordinates":[-92.133301,34.950631],"type":"Point"}
}