{
  "type": "Feature",
  "properties": {
    "addr:full":"401 High School Dr Arkadelphia AR 71923",
    "addr:housenumber":"401",
    "addr:postcode":"71923",
    "addr:street":"High School Dr",
    "iso:country":"US",
    "sg:address":"401 High School Dr",
    "sg:city":"Arkadelphia",
    "sg:classifiers":[
        {
            "category":"Education",
            "subcategory":"School",
            "type":"Public Place"
        }
    ],
    "sg:phone":"+1 870 246 7373",
    "sg:postcode":"71923",
    "sg:province":"AR",
    "wof:name":"Arkadelphia High School",
    "wof:placetype":"venue"
},
  "geometry": {"coordinates":[-93.097677,34.122856],"type":"Point"}
}