{
  "type": "Feature",
  "properties": {
    "iso:country":"US",
    "sg:address":"2101 Congo Rd",
    "sg:city":"Benton",
    "sg:classifiers":[
        {
            "category":"Utilities",
            "subcategory":"Mobile Phone",
            "type":"Services"
        }
    ],
    "sg:phone":"+1 501 315 3265",
    "sg:postcode":"72015",
    "sg:province":"AR",
    "sg:tags":[
        "telephone",
        "cellular"
    ],
    "wof:name":"Landers Wireless Svc",
    "wof:placetype":"venue"
},
  "geometry": {"coordinates":[-92.572269,34.583835],"type":"Point"}
}