{
  "type": "Feature",
  "properties": {
    "iso:country":"US",
    "sg:address":"2525 Harper Rd",
    "sg:city":"Benton",
    "sg:classifiers":[
        {
            "category":"Building & Trades",
            "subcategory":"Cleaning & Sanitation",
            "type":"Services"
        }
    ],
    "sg:phone":"+1 501 778 9324",
    "sg:postcode":"72015",
    "sg:province":"AR",
    "sg:tags":[
        "maintenance"
    ],
    "wof:name":"Picture Perfect Floor Care",
    "wof:placetype":"venue"
},
  "geometry": {"coordinates":[-92.546043,34.587115],"type":"Point"}
}