{
  "type": "Feature",
  "properties": {
    "iso:country":"US",
    "sg:address":"1 E 1st St",
    "sg:city":"Mountain Home",
    "sg:classifiers":[
        {
            "category":"Government",
            "subcategory":"Court House",
            "type":"Public Place"
        }
    ],
    "sg:phone":"+1 870 425 3475",
    "sg:postcode":"72653",
    "sg:province":"AR",
    "wof:name":"Baxter County Clerks Office",
    "wof:placetype":"venue"
},
  "geometry": {"coordinates":[-92.38369,36.34017],"type":"Point"}
}