{
  "type": "Feature",
  "properties": {
    "iso:country":"US",
    "sg:address":"1710 E Main St",
    "sg:city":"Russellville",
    "sg:classifiers":[
        {
            "category":"Building & Trades",
            "subcategory":"Construction",
            "type":"Services"
        }
    ],
    "sg:phone":"+1 479 967 1249",
    "sg:postcode":"72801",
    "sg:province":"AR",
    "sg:tags":[
        "roofing",
        "consultant",
        "contractor"
    ],
    "sg:website":"http://www.uhaul.com/Locations/Rentals-near-Russellville-AR-72801/028155",
    "wof:name":"U-Haul Neighborhood Dealer - Motley Crew Roofing & Const",
    "wof:placetype":"venue"
},
  "geometry": {"coordinates":[-93.113312,35.278318],"type":"Point"}
}