{
  "type": "Feature",
  "properties": {
    "addr:full":"4903 Central Ave Hot Springs AR 71913",
    "addr:housenumber":"4903",
    "addr:postcode":"71913",
    "addr:street":"Central Ave",
    "iso:country":"US",
    "sg:address":"4903 Central Ave",
    "sg:city":"Hot Springs",
    "sg:classifiers":[
        {
            "category":"Autos & Motor Vehicles",
            "subcategory":"Boat Sales",
            "type":"Retail Goods"
        }
    ],
    "sg:phone":"+1 501 525 1166",
    "sg:postcode":"71913",
    "sg:province":"AR",
    "sg:tags":[
        "dealer",
        "sales"
    ],
    "sg:website":"www.powerboatsinc.com",
    "wof:name":"Power Boats Inc",
    "wof:placetype":"venue"
},
  "geometry": {"coordinates":[-93.08834899999999,34.439386],"type":"Point"}
}