{
  "type": "Feature",
  "properties": {
    "addr:full":"1811 N Rock St Sheridan AR 72150",
    "addr:housenumber":"1811",
    "addr:postcode":"72150",
    "addr:street":"N Rock St",
    "iso:country":"US",
    "sg:address":"1811 N Rock St",
    "sg:city":"Sheridan",
    "sg:classifiers":[
        {
            "category":"Wholesale",
            "subcategory":"Durable Goods & Equipment",
            "type":"Manufacturing & Wholesale Goods"
        }
    ],
    "sg:phone":"+1 870 942 8500",
    "sg:postcode":"72150",
    "sg:province":"AR",
    "sg:tags":[
        "exporter"
    ],
    "sg:website":"www.centria.com",
    "wof:name":"CENTRIA",
    "wof:placetype":"venue"
},
  "geometry": {"coordinates":[-92.395568,34.320843],"type":"Point"}
}