{
  "type": "Feature",
  "properties": {
    "addr:full":"183 Utley Rd Dover AR 72837",
    "addr:housenumber":"183",
    "addr:postcode":"72837",
    "addr:street":"Utley Rd",
    "iso:country":"US",
    "sg:address":"183 Utley Rd",
    "sg:city":"Dover",
    "sg:classifiers":[
        {
            "category":"Building & Trades",
            "subcategory":"Plumbing",
            "type":"Services"
        },
        {
            "category":"Home & Garden",
            "subcategory":"Hardware",
            "type":"Retail Goods"
        }
    ],
    "sg:phone":"+1 479 331 0315",
    "sg:postcode":"72837",
    "sg:province":"AR",
    "sg:tags":[
        "filtration",
        "supply",
        "work",
        "purification",
        "water",
        "equipment"
    ],
    "wof:name":"Smart Connections",
    "wof:placetype":"venue"
},
  "geometry": {"coordinates":[-93.07535300000001,35.37406],"type":"Point"}
}