{
  "type": "Feature",
  "properties": {
    "iso:country":"US",
    "sg:address":"1924 Marion St",
    "sg:city":"N Little Rock",
    "sg:classifiers":[
        {
            "category":"Health Services",
            "subcategory":"Hospital",
            "type":"Services"
        }
    ],
    "sg:phone":"+1 501 812 0633",
    "sg:postcode":"72114",
    "sg:province":"AR",
    "sg:tags":[
        "mental"
    ],
    "wof:name":"Arkansas Counseling Assoc",
    "wof:placetype":"venue"
},
  "geometry": {"coordinates":[-92.276178,34.773823],"type":"Point"}
}