{
  "type": "Feature",
  "properties": {
    "iso:country":"US",
    "sg:address":"250 Bucher Dr",
    "sg:city":"Mountain Home",
    "sg:classifiers":[
        {
            "category":"Health Services",
            "subcategory":"Doctor",
            "type":"Services"
        }
    ],
    "sg:phone":"+1 870 425 9323",
    "sg:postcode":"72653",
    "sg:province":"AR",
    "sg:tags":[
        "dentist"
    ],
    "wof:name":"Family Dental Ctr",
    "wof:placetype":"venue"
},
  "geometry": {"coordinates":[-92.396485,36.339734],"type":"Point"}
}