{
  "type": "Feature",
  "properties": {
    "iso:country":"US",
    "sg:address":"1314 Holmes Rd",
    "sg:city":"Searcy",
    "sg:classifiers":[
        {
            "category":"Freight",
            "type":"Transportation"
        }
    ],
    "sg:phone":"+1 501 305 4310",
    "sg:postcode":"72143",
    "sg:province":"AR",
    "sg:tags":[
        "fixed",
        "motor",
        "facility"
    ],
    "wof:name":"Barker Assoc LLC",
    "wof:placetype":"venue"
},
  "geometry": {"coordinates":[-91.749358,35.261038],"type":"Point"}
}