{
  "type": "Feature",
  "properties": {
    "iso:country":"US",
    "sg:address":"163 Rock Creek Rd Cut Off",
    "sg:city":"Glenwood",
    "sg:classifiers":[
        {
            "category":"Manufacturing",
            "subcategory":"Lumber",
            "type":"Manufacturing & Wholesale Goods"
        }
    ],
    "sg:phone":"+1 870 356 3900",
    "sg:postcode":"71943",
    "sg:province":"AR",
    "sg:tags":[
        "logging"
    ],
    "wof:name":"Markham & Sons Logging",
    "wof:placetype":"venue"
},
  "geometry": {"coordinates":[-93.55047399999999,34.310505],"type":"Point"}
}