{
  "type": "Feature",
  "properties": {
    "addr:full":"809 S Main St Searcy AR 72143",
    "addr:housenumber":"809",
    "addr:postcode":"72143",
    "addr:street":"S Main St",
    "iso:country":"US",
    "sg:address":"809 S Main St",
    "sg:city":"Searcy",
    "sg:classifiers":[
        {
            "category":"Restaurant",
            "type":"Food & Drink"
        }
    ],
    "sg:phone":"+1 501 279 7771",
    "sg:postcode":"72143",
    "sg:province":"AR",
    "wof:name":"Charley's Pizza",
    "wof:placetype":"venue"
},
  "geometry": {"coordinates":[-91.73654000000001,35.24213],"type":"Point"}
}