{
  "type": "Feature",
  "properties": {
    "iso:country":"US",
    "sg:address":"8405 Woodson Lateral Rd",
    "sg:city":"Hensley",
    "sg:classifiers":[
        {
            "category":"Place Of Worship",
            "subcategory":"Church",
            "type":"Public Place"
        },
        {
            "category":"Place Of Worship",
            "type":"Public Place"
        },
        {
            "category":"Organizations",
            "subcategory":"Religious Organization",
            "type":"Services"
        }
    ],
    "sg:phone":"+1 501 397 2140",
    "sg:postcode":"72065",
    "sg:province":"AR",
    "sg:tags":[
        "churches-baptist-general",
        "churches-baptist"
    ],
    "wof:name":"Woodson Baptist Church",
    "wof:placetype":"venue"
},
  "geometry": {"coordinates":[-92.21286499999999,34.529249],"type":"Point"}
}