{
  "type": "Feature",
  "properties": {
    "iso:country":"US",
    "sg:address":"17 Hwy 63 N",
    "sg:city":"Mammoth Spring",
    "sg:classifiers":[
        {
            "category":"Recreation",
            "type":"Entertainment"
        }
    ],
    "sg:phone":"+1 870 625 7364",
    "sg:postcode":"72554",
    "sg:province":"AR",
    "sg:tags":[
        "parks"
    ],
    "sg:website":"www.arkansasstateparks.com",
    "wof:name":"Mammoth Spring State Park",
    "wof:placetype":"venue"
},
  "geometry": {"coordinates":[-91.53655500000001,36.495872],"type":"Point"}
}