{
  "type": "Feature",
  "properties": {
    "addr:full":"5411 Pinnacle Ponte Dr Rogers AR 72758",
    "addr:housenumber":"5411",
    "addr:postcode":"72758",
    "addr:street":"Pinnacle Ponte Dr",
    "iso:country":"US",
    "sg:address":"5411 Pinnacle Ponte Dr",
    "sg:city":"Rogers",
    "sg:classifiers":[
        {
            "category":"Retail",
            "subcategory":"Laundry & Dry Cleaning",
            "type":"Services"
        }
    ],
    "sg:phone":"+1 479 464 8876",
    "sg:postcode":"72758",
    "sg:province":"AR",
    "sg:tags":[
        "drycleaning",
        "plant"
    ],
    "wof:name":"Old Town Dry Cleaners",
    "wof:placetype":"venue"
},
  "geometry": {"coordinates":[-94.187286,36.312044],"type":"Point"}
}