{
  "type": "Feature",
  "properties": {
    "iso:country":"US",
    "sg:address":"2272 Highway 62 412",
    "sg:city":"Highland",
    "sg:classifiers":[
        {
            "category":"Autos & Motor Vehicles",
            "subcategory":"Auto Supplies",
            "type":"Retail Goods"
        },
        {
            "category":"Manufacturing",
            "subcategory":"Glass & Minerals",
            "type":"Manufacturing & Wholesale Goods"
        },
        {
            "category":"Retail",
            "subcategory":"Auto Repair",
            "type":"Services"
        }
    ],
    "sg:phone":"+1 870 856 3566",
    "sg:postcode":"72542",
    "sg:province":"AR",
    "sg:tags":[
        "plate",
        "coating",
        "window",
        "tinting",
        "glass-wholesale",
        "glass-auto",
        "shape",
        "circle",
        "windshield",
        "special",
        "manufacturer"
    ],
    "wof:name":"All Pro Glass Inc",
    "wof:placetype":"venue"
},
  "geometry": {"coordinates":[-91.503114,36.30182],"type":"Point"}
}