{
  "type": "Feature",
  "properties": {
    "addr:full":"1416 Fayetteville Rd Van Buren AR 72956",
    "addr:housenumber":"1416",
    "addr:postcode":"72956",
    "addr:street":"Fayetteville Rd",
    "iso:country":"US",
    "sg:address":"1416 Fayetteville Rd",
    "sg:city":"Van Buren",
    "sg:classifiers":[
        {
            "category":"Insurance",
            "subcategory":"Insurance Agent",
            "type":"Services"
        }
    ],
    "sg:phone":"+1 479 471 1000",
    "sg:postcode":"72956",
    "sg:province":"AR",
    "wof:name":"Farmers Insurance Group",
    "wof:placetype":"venue"
},
  "geometry": {"coordinates":[-94.3566,35.454664],"type":"Point"}
}