{
  "type": "Feature",
  "properties": {
    "iso:country":"US",
    "sg:address":"209 Wolfe St",
    "sg:city":"Forrest City",
    "sg:classifiers":[
        {
            "category":"Building & Trades",
            "subcategory":"Construction",
            "type":"Services"
        }
    ],
    "sg:phone":"+1 870 633 4736",
    "sg:postcode":"72335",
    "sg:province":"AR",
    "sg:tags":[
        "house"
    ],
    "wof:name":"Sykes Brother Construction",
    "wof:placetype":"venue"
},
  "geometry": {"coordinates":[-90.776785,35.012854],"type":"Point"}
}