{
  "type": "Feature",
  "properties": {
    "iso:country":"US",
    "sg:address":"702 S Thompson St",
    "sg:city":"Springdale",
    "sg:classifiers":[
        {
            "category":"Organizations",
            "subcategory":"Non-profit Organization",
            "type":"Services"
        }
    ],
    "sg:phone":"+1 479 756 8717",
    "sg:postcode":"72764",
    "sg:province":"AR",
    "sg:tags":[
        "info",
        "addiction",
        "abuse",
        "treatment",
        "drug"
    ],
    "wof:name":"NWA Methadone Treatment Ctr",
    "wof:placetype":"venue"
},
  "geometry": {"coordinates":[-94.138971,36.178174],"type":"Point"}
}