{
  "type": "Feature",
  "properties": {
    "iso:country":"US",
    "sg:address":"213 Co Rd 960",
    "sg:city":"Brookland",
    "sg:classifiers":[
        {
            "category":"Farming",
            "subcategory":"Livestock Farm",
            "type":"Manufacturing & Wholesale Goods"
        }
    ],
    "sg:phone":"+1 870 932 9439",
    "sg:postcode":"72417",
    "sg:province":"AR",
    "sg:tags":[
        "beef",
        "feedlot",
        "cattle"
    ],
    "wof:name":"Robert Robinson",
    "wof:placetype":"venue"
},
  "geometry": {"coordinates":[-90.570948,35.951063],"type":"Point"}
}