{
  "type": "Feature",
  "properties": {
    "addr:full":"910 E Oak Pl Ashdown AR 71822",
    "addr:housenumber":"910",
    "addr:postcode":"71822",
    "addr:street":"E Oak Pl",
    "iso:country":"US",
    "sg:address":"910 E Oak Pl",
    "sg:city":"Ashdown",
    "sg:classifiers":[
        {
            "category":"Building & Trades",
            "subcategory":"Landscaping Services",
            "type":"Services"
        }
    ],
    "sg:phone":"+1 870 898 3234",
    "sg:postcode":"71822",
    "sg:province":"AR",
    "wof:name":"Woodruff Lawn and Small E",
    "wof:placetype":"venue"
},
  "geometry": {"coordinates":[-94.118315,33.668188],"type":"Point"}
}