{
  "type": "Feature",
  "properties": {
    "iso:country":"US",
    "sg:address":"130 S 16th St",
    "sg:city":"West Memphis",
    "sg:classifiers":[
        {
            "category":"Social Services",
            "subcategory":"Child Care",
            "type":"Services"
        }
    ],
    "sg:phone":"+1 870 733 0407",
    "sg:postcode":"72301",
    "sg:province":"AR",
    "wof:name":"Primary Learning Academy",
    "wof:placetype":"venue"
},
  "geometry": {"coordinates":[-90.16530899999999,35.145912],"type":"Point"}
}