{
  "type": "Feature",
  "properties": {
    "iso:country":"US",
    "sg:address":"907 E 3rd St",
    "sg:city":"Hope",
    "sg:classifiers":[
        {
            "category":"Retail",
            "subcategory":"Repair Shop",
            "type":"Services"
        }
    ],
    "sg:phone":"+1 870 777 0110",
    "sg:postcode":"71801",
    "sg:province":"AR",
    "sg:tags":[
        "related"
    ],
    "wof:name":"Truck & Trailer Robert's",
    "wof:placetype":"venue"
},
  "geometry": {"coordinates":[-93.581158,33.668223],"type":"Point"}
}