{
  "type": "Feature",
  "properties": {
    "addr:full":"75 Stephenwood Dr Arkadelphia AR 71923",
    "addr:housenumber":"75",
    "addr:postcode":"71923",
    "addr:street":"Stephenwood Dr",
    "iso:country":"US",
    "sg:address":"75 Stephenwood Dr",
    "sg:city":"Arkadelphia",
    "sg:classifiers":[
        {
            "category":"Professional",
            "subcategory":"Management & Consulting",
            "type":"Services"
        }
    ],
    "sg:phone":"+1 870 245 2299",
    "sg:postcode":"71923",
    "sg:province":"AR",
    "sg:tags":[
        "consultant",
        "business"
    ],
    "wof:name":"First Choice Account Mgmt",
    "wof:placetype":"venue"
},
  "geometry": {"coordinates":[-93.097605,34.120796],"type":"Point"}
}