{
  "type": "Feature",
  "properties": {
    "iso:country":"US",
    "sg:address":"1811 Junction City Rd",
    "sg:city":"El Dorado",
    "sg:classifiers":[
        {
            "category":"Autos & Motor Vehicles",
            "subcategory":"Automobile Sales",
            "type":"Retail Goods"
        }
    ],
    "sg:phone":"+1 870 864 4700",
    "sg:postcode":"71730",
    "sg:province":"AR",
    "wof:name":"Murphy Nissan",
    "wof:placetype":"venue"
},
  "geometry": {"coordinates":[-92.64551400000001,33.203018],"type":"Point"}
}