{
  "type": "Feature",
  "properties": {
    "iso:country":"US",
    "sg:address":"119 Crooked Creek Ct",
    "sg:city":"North Little Rock",
    "sg:classifiers":[
        {
            "category":"Real Estate",
            "subcategory":"Real Estate Agent",
            "type":"Services"
        }
    ],
    "sg:phone":"+1 501 834 8671",
    "sg:postcode":"72116",
    "sg:province":"AR",
    "wof:name":"SMC Property Development",
    "wof:placetype":"venue"
},
  "geometry": {"coordinates":[-92.232567,34.809424],"type":"Point"}
}