{
  "type": "Feature",
  "properties": {
    "iso:country":"US",
    "sg:address":"200 Central Ave",
    "sg:city":"Bay",
    "sg:classifiers":[
        {
            "category":"Organizations",
            "subcategory":"Religious Organization",
            "type":"Services"
        }
    ],
    "sg:phone":"+1 870 781 3269",
    "sg:postcode":"72411",
    "sg:province":"AR",
    "sg:tags":[
        "church"
    ],
    "wof:name":"First Baptist Church",
    "wof:placetype":"venue"
},
  "geometry": {"coordinates":[-90.562857,35.745548],"type":"Point"}
}