{
  "type": "Feature",
  "properties": {
    "iso:country":"US",
    "sg:address":"4103 State Hwy 36",
    "sg:city":"Searcy",
    "sg:classifiers":[
        {
            "category":"Wholesale",
            "subcategory":"Office Equipment",
            "type":"Manufacturing & Wholesale Goods"
        },
        {
            "category":"Home & Garden",
            "subcategory":"Furniture",
            "type":"Retail Goods"
        }
    ],
    "sg:phone":"+1 501 368 8324",
    "sg:postcode":"72143",
    "sg:province":"AR",
    "sg:tags":[
        "machine",
        "duplicating",
        "copying",
        "supply"
    ],
    "wof:name":"Superior Office Solutions",
    "wof:placetype":"venue"
},
  "geometry": {"coordinates":[-91.914658,35.271267],"type":"Point"}
}