{
  "type": "Feature",
  "properties": {
    "iso:country":"US",
    "sg:address":"115 W Industrial Park Rd Ste 5",
    "sg:city":"Harrison",
    "sg:classifiers":[
        {
            "category":"Shopping",
            "subcategory":"Jewelry",
            "type":"Retail Goods"
        },
        {
            "category":"Manufacturing",
            "subcategory":"Jewelry",
            "type":"Manufacturing & Wholesale Goods"
        },
        {
            "category":"Retail",
            "subcategory":"Repair Shop",
            "type":"Services"
        }
    ],
    "sg:phone":"+1 870 741 8150",
    "sg:postcode":"72601",
    "sg:province":"AR",
    "sg:tags":[
        "repairing",
        "stone",
        "designer",
        "jewelers-wholesale",
        "clock",
        "jeweler",
        "precious",
        "semi-precious",
        "manufacturer"
    ],
    "wof:name":"Dey Gem Jewelry",
    "wof:placetype":"venue"
},
  "geometry": {"coordinates":[-93.119181,36.249826],"type":"Point"}
}