{
  "type": "Feature",
  "properties": {
    "iso:country":"US",
    "sg:address":"202 Commercial Ave E",
    "sg:city":"Wynne",
    "sg:classifiers":[
        {
            "category":"Health Services",
            "subcategory":"Doctor",
            "type":"Services"
        },
        {
            "category":"Social Services",
            "type":"Services"
        },
        {
            "category":"Personal",
            "type":"Services"
        }
    ],
    "sg:phone":"+1 870 238 4329",
    "sg:postcode":"72396",
    "sg:province":"AR",
    "sg:tags":[
        "family",
        "professional",
        "counselors-licensed",
        "psychologist",
        "individual",
        "marriage",
        "child",
        "counseling",
        "counselor"
    ],
    "sg:website":"http://www.conceptsoftruth.org",
    "wof:name":"Concepts Of Truth Inc",
    "wof:placetype":"venue"
},
  "geometry": {"coordinates":[-90.79123300000001,35.224988],"type":"Point"}
}