{
  "type": "Feature",
  "properties": {
    "iso:country":"US",
    "sg:address":"696 W Clay St",
    "sg:city":"Piggott",
    "sg:classifiers":[
        {
            "category":"Building & Trades",
            "subcategory":"Construction",
            "type":"Services"
        }
    ],
    "sg:phone":"+1 870 598 2980",
    "sg:postcode":"72454",
    "sg:province":"AR",
    "sg:tags":[
        "contractor"
    ],
    "wof:name":"Moores Welding",
    "wof:placetype":"venue"
},
  "geometry": {"coordinates":[-90.196276,36.381933],"type":"Point"}
}