{
  "type": "Feature",
  "properties": {
    "addr:full":"1502 Lois Pl Searcy AR 72143",
    "addr:housenumber":"1502",
    "addr:postcode":"72143",
    "addr:street":"Lois Pl",
    "iso:country":"US",
    "sg:address":"1502 Lois Pl",
    "sg:city":"Searcy",
    "sg:classifiers":[
        {
            "category":"Professional",
            "subcategory":"Art Services",
            "type":"Services"
        }
    ],
    "sg:phone":"+1 501 278 4910",
    "sg:postcode":"72143",
    "sg:province":"AR",
    "sg:tags":[
        "commercial",
        "design"
    ],
    "wof:name":"Business Images & Graphics",
    "wof:placetype":"venue"
},
  "geometry": {"coordinates":[-91.748468,35.230773],"type":"Point"}
}