{
  "type": "Feature",
  "properties": {
    "iso:country":"US",
    "sg:address":"273 Repop Pl",
    "sg:city":"Pearcy",
    "sg:classifiers":[
        {
            "category":"Manufacturing",
            "subcategory":"Motor Vehicles & Parts",
            "type":"Manufacturing & Wholesale Goods"
        }
    ],
    "sg:phone":"+1 501 767 4440",
    "sg:postcode":"71964",
    "sg:province":"AR",
    "sg:tags":[
        "automobile",
        "supply"
    ],
    "wof:name":"Clark Industries Inc",
    "wof:placetype":"venue"
},
  "geometry": {"coordinates":[-93.278573,34.433422],"type":"Point"}
}