{
  "type": "Feature",
  "properties": {
    "iso:country":"US",
    "sg:address":"2970 E Moore Ave",
    "sg:city":"Searcy",
    "sg:classifiers":[
        {
            "category":"Banks & Credit Unions",
            "subcategory":"Investment Brokerage",
            "type":"Services"
        },
        {
            "category":"Professional",
            "subcategory":"Business Services",
            "type":"Services"
        }
    ],
    "sg:phone":"+1 501 368 0043",
    "sg:postcode":"72143",
    "sg:province":"AR",
    "sg:tags":[
        "advisory",
        "financial"
    ],
    "wof:name":"Curbo Financial Solutions Inc",
    "wof:placetype":"venue"
},
  "geometry": {"coordinates":[-91.700534,35.253851],"type":"Point"}
}