{
  "type": "Feature",
  "properties": {
    "addr:full":"108 N 2nd St Dardanelle AR 72834",
    "addr:housenumber":"108",
    "addr:postcode":"72834",
    "addr:street":"N 2Nd St",
    "iso:country":"US",
    "sg:address":"108 N 2nd St",
    "sg:city":"Dardanelle",
    "sg:classifiers":[
        {
            "category":"Farming",
            "subcategory":"Farm",
            "type":"Manufacturing & Wholesale Goods"
        }
    ],
    "sg:phone":"+1 479 229 1531",
    "sg:postcode":"72834",
    "sg:province":"AR",
    "sg:tags":[
        "crop",
        "general"
    ],
    "wof:name":"Baker Fullerton Farms Inc",
    "wof:placetype":"venue"
},
  "geometry": {"coordinates":[-93.15500400000001,35.220699],"type":"Point"}
}