{
  "type": "Feature",
  "properties": {
    "iso:country":"US",
    "sg:address":"111 S 5th St",
    "sg:city":"West Memphis",
    "sg:classifiers":[
        {
            "category":"Retail",
            "subcategory":"Auto Repair",
            "type":"Services"
        }
    ],
    "sg:phone":"+1 870 733 9299",
    "sg:postcode":"72301",
    "sg:province":"AR",
    "sg:tags":[
        "repairing",
        "automobile",
        "transmission"
    ],
    "wof:name":"H & W Automotive",
    "wof:placetype":"venue"
},
  "geometry": {"coordinates":[-90.179906,35.146383],"type":"Point"}
}