{
  "type": "Feature",
  "properties": {
    "iso:country":"US",
    "sg:address":"600 E Main St",
    "sg:city":"Magnolia",
    "sg:classifiers":[
        {
            "category":"Retail",
            "subcategory":"Auto Repair",
            "type":"Services"
        }
    ],
    "sg:phone":"+1 870 234 1640",
    "sg:postcode":"71753",
    "sg:province":"AR",
    "sg:tags":[
        "glass",
        "towing",
        "recovery",
        "replacement"
    ],
    "wof:name":"Linkous Auto Glass",
    "wof:placetype":"venue"
},
  "geometry": {"coordinates":[-93.232857,33.266996],"type":"Point"}
}