{
  "type": "Feature",
  "properties": {
    "iso:country":"US",
    "sg:address":"3612 Hwy 367 N",
    "sg:city":"Bald Knob",
    "sg:classifiers":[
        {
            "category":"Personal",
            "subcategory":"Tanning Parlor",
            "type":"Services"
        }
    ],
    "sg:phone":"+1 501 724 3445",
    "sg:postcode":"72010",
    "sg:province":"AR",
    "sg:tags":[
        "salon"
    ],
    "wof:name":"Bald Knob Nu Weigh",
    "wof:placetype":"venue"
},
  "geometry": {"coordinates":[-91.487038,35.382633],"type":"Point"}
}