{
  "type": "Feature",
  "properties": {
    "iso:country":"US",
    "sg:address":"3900 John Barrow Rd",
    "sg:city":"Little Rock",
    "sg:classifiers":[
        {
            "category":"Insurance",
            "subcategory":"Insurance Agent",
            "type":"Services"
        }
    ],
    "sg:phone":"+1 501 565 0992",
    "sg:postcode":"72204",
    "sg:province":"AR",
    "wof:name":"Steven L Phillips Ins & Fnncl",
    "wof:placetype":"venue"
},
  "geometry": {"coordinates":[-92.373167,34.718923],"type":"Point"}
}