{
  "type": "Feature",
  "properties": {
    "iso:country":"US",
    "sg:address":"55 Sugar Pine Pl",
    "sg:city":"Farmington",
    "sg:classifiers":[
        {
            "category":"Structure",
            "subcategory":"Office Building",
            "type":"Public Place"
        }
    ],
    "sg:phone":"+1 479 267 5042",
    "sg:postcode":"72730",
    "sg:province":"AR",
    "sg:tags":[
        "park"
    ],
    "wof:name":"Tooley Properties",
    "wof:placetype":"venue"
},
  "geometry": {"coordinates":[-94.256272,36.045037],"type":"Point"}
}