{
  "type": "Feature",
  "properties": {
    "iso:country":"US",
    "sg:address":"17386 Martin Pedro Rd",
    "sg:city":"Siloam Springs",
    "sg:classifiers":[
        {
            "category":"Professional",
            "type":"Services"
        }
    ],
    "sg:phone":"+1 479 238 1138",
    "sg:postcode":"72761",
    "sg:province":"OK",
    "wof:name":"John Acord",
    "wof:placetype":"venue"
},
  "geometry": {"coordinates":[-94.405954,36.153765],"type":"Point"}
}