{
  "type": "Feature",
  "properties": {
    "addr:full":"100 Morgan Keegan Dr Little Rock AR 72202",
    "addr:housenumber":"100",
    "addr:postcode":"72202",
    "addr:street":"Morgan Keegan Dr",
    "iso:country":"US",
    "sg:address":"100 Morgan Keegan Dr",
    "sg:city":"Little Rock",
    "sg:classifiers":[
        {
            "category":"Professional",
            "subcategory":"Lawyer & Legal Services",
            "type":"Services"
        }
    ],
    "sg:phone":"+1 501 280 0100",
    "sg:postcode":"72202",
    "sg:province":"AR",
    "sg:tags":[
        "attorney"
    ],
    "sg:website":"www.armstrongallen.com",
    "wof:name":"Armstrong Allen",
    "wof:placetype":"venue"
},
  "geometry": {"coordinates":[-92.30552900000001,34.770672],"type":"Point"}
}