{
  "type": "Feature",
  "properties": {
    "addr:full":"108 E Erie St Harrison AR 72601",
    "addr:housenumber":"108",
    "addr:postcode":"72601",
    "addr:street":"E Erie St",
    "iso:country":"US",
    "sg:address":"108 E Erie St",
    "sg:city":"Harrison",
    "sg:classifiers":[
        {
            "category":"Manufacturing",
            "subcategory":"Signs",
            "type":"Manufacturing & Wholesale Goods"
        }
    ],
    "sg:phone":"+1 870 743 1757",
    "sg:postcode":"72601",
    "sg:province":"AR",
    "sg:tags":[
        "specialty",
        "mfg"
    ],
    "wof:name":"Gary S Signs",
    "wof:placetype":"venue"
},
  "geometry": {"coordinates":[-93.106511,36.234269],"type":"Point"}
}