{
  "type": "Feature",
  "properties": {
    "addr:full":"201 S Denver Ave Russellville AR 72801",
    "addr:housenumber":"201",
    "addr:postcode":"72801",
    "addr:street":"S Denver Ave",
    "iso:country":"US",
    "sg:address":"201 S Denver Ave",
    "sg:city":"Russellville",
    "sg:classifiers":[
        {
            "category":"Professional",
            "subcategory":"Lawyer & Legal Services",
            "type":"Services"
        }
    ],
    "sg:phone":"+1 479 880 8842",
    "sg:postcode":"72801",
    "sg:province":"AR",
    "sg:tags":[
        "attorney"
    ],
    "wof:name":"Williams & Anderson",
    "wof:placetype":"venue"
},
  "geometry": {"coordinates":[-93.136589,35.277915],"type":"Point"}
}