{
  "type": "Feature",
  "properties": {
    "addr:full":"327 Front St Forrest City AR 72335",
    "addr:housenumber":"327",
    "addr:postcode":"72335",
    "addr:street":"Front St",
    "iso:country":"US",
    "sg:address":"327 Front St",
    "sg:city":"Forrest City",
    "sg:classifiers":[
        {
            "category":"Home & Garden",
            "subcategory":"Building Materials",
            "type":"Retail Goods"
        }
    ],
    "sg:phone":"+1 870 633 1141",
    "sg:postcode":"72335",
    "sg:province":"AR",
    "sg:tags":[
        "lumber"
    ],
    "wof:name":"Vaccaro Lumber & Hardware Co",
    "wof:placetype":"venue"
},
  "geometry": {"coordinates":[-90.786784,35.007862],"type":"Point"}
}