{
  "type": "Feature",
  "properties": {
    "addr:full":"1122 Main St Vilonia AR 72173",
    "addr:housenumber":"1122",
    "addr:postcode":"72173",
    "addr:street":"Main St",
    "iso:country":"US",
    "sg:address":"1122 Main St",
    "sg:city":"Vilonia",
    "sg:classifiers":[
        {
            "category":"Shopping",
            "subcategory":"Clothing, Apparel, & Fashions",
            "type":"Retail Goods"
        }
    ],
    "sg:phone":"+1 501 796 3556",
    "sg:postcode":"72173",
    "sg:province":"AR",
    "sg:tags":[
        "sporting",
        "family"
    ],
    "wof:name":"V-Town TS",
    "wof:placetype":"venue"
},
  "geometry": {"coordinates":[-92.20460799999999,35.08408],"type":"Point"}
}