{
  "type": "Feature",
  "properties": {
    "addr:full":"285 Westinghouse Dr Hot Springs National AR 71901",
    "addr:housenumber":"285",
    "addr:postcode":"71901",
    "addr:street":"Westinghouse Dr",
    "iso:country":"US",
    "sg:address":"285 Westinghouse Dr",
    "sg:city":"Hot Springs National",
    "sg:classifiers":[
        {
            "category":"Building & Trades",
            "subcategory":"Construction",
            "type":"Services"
        }
    ],
    "sg:phone":"+1 501 262 5490",
    "sg:postcode":"71901",
    "sg:province":"AR",
    "sg:tags":[
        "contractor"
    ],
    "wof:name":"Advanced Applicators LLC",
    "wof:placetype":"venue"
},
  "geometry": {"coordinates":[-92.985107,34.49943],"type":"Point"}
}