{
  "type": "Feature",
  "properties": {
    "addr:full":"132 Eagle St Marmaduke AR 72443",
    "addr:housenumber":"132",
    "addr:postcode":"72443",
    "addr:street":"Eagle St",
    "iso:country":"US",
    "sg:address":"132 Eagle St",
    "sg:city":"Marmaduke",
    "sg:classifiers":[
        {
            "category":"Retail",
            "subcategory":"Auto Repair",
            "type":"Services"
        }
    ],
    "sg:phone":"+1 870 586 0817",
    "sg:postcode":"72443",
    "sg:province":"AR",
    "sg:tags":[
        "wrecker"
    ],
    "wof:name":"Harris Towing & Recovery",
    "wof:placetype":"venue"
},
  "geometry": {"coordinates":[-90.493061,36.207739],"type":"Point"}
}