{
  "type": "Feature",
  "properties": {
    "iso:country":"US",
    "sg:address":"251 Holiday Island Dr",
    "sg:city":"Eureka Springs",
    "sg:classifiers":[
        {
            "category":"Government",
            "subcategory":"Office",
            "type":"Public Place"
        },
        {
            "category":"Government",
            "subcategory":"Fire Station",
            "type":"Public Place"
        }
    ],
    "sg:phone":"+1 479 253 8397",
    "sg:postcode":"72631",
    "sg:province":"AR",
    "sg:tags":[
        "department",
        "commissioner"
    ],
    "wof:name":"Holiday Island Fire Dept",
    "wof:placetype":"venue"
},
  "geometry": {"coordinates":[-93.750851,36.479584],"type":"Point"}
}