{
  "type": "Feature",
  "properties": {
    "iso:country":"US",
    "sg:address":"1475 Hogan Ln",
    "sg:city":"Conway",
    "sg:classifiers":[
        {
            "category":"Restaurant",
            "type":"Food & Drink"
        }
    ],
    "sg:phone":"+1 501 336 9100",
    "sg:postcode":"72034",
    "sg:province":"AR",
    "wof:name":"Brick Oven Pizza Co",
    "wof:placetype":"venue"
},
  "geometry": {"coordinates":[-92.497645,35.098297],"type":"Point"}
}