{
  "type": "Feature",
  "properties": {
    "addr:full":"402 N 15th St Arkadelphia AR 71923",
    "addr:housenumber":"402",
    "addr:postcode":"71923",
    "addr:street":"N 15Th St",
    "iso:country":"US",
    "sg:address":"402 N 15th St",
    "sg:city":"Arkadelphia",
    "sg:classifiers":[
        {
            "category":"Social Services",
            "subcategory":"Child Care",
            "type":"Services"
        }
    ],
    "sg:phone":"+1 870 246 3246",
    "sg:postcode":"71923",
    "sg:province":"AR",
    "wof:name":"Apple Den",
    "wof:placetype":"venue"
},
  "geometry": {"coordinates":[-93.06489999999999,34.126529],"type":"Point"}
}