{
  "type": "Feature",
  "properties": {
    "addr:full":"119 N Broadway Ave Booneville AR 72927",
    "addr:housenumber":"119",
    "addr:postcode":"72927",
    "addr:street":"N Broadway Ave",
    "iso:country":"US",
    "sg:address":"119 N Broadway Ave",
    "sg:city":"Booneville",
    "sg:classifiers":[
        {
            "category":"Insurance",
            "subcategory":"Hazard Insurance",
            "type":"Services"
        }
    ],
    "sg:phone":"+1 479 675 2855",
    "sg:postcode":"72927",
    "sg:province":"AR",
    "sg:website":"http://statefarm.mqgroup.com/url.asp?usr=041573",
    "wof:name":"State Farm Insurance Agent-Ross A Kent",
    "wof:placetype":"venue"
},
  "geometry": {"coordinates":[-93.921988,35.13869],"type":"Point"}
}