{
  "type": "Feature",
  "properties": {
    "addr:full":"8622 Chicot Rd Little Rock AR 72209",
    "addr:housenumber":"8622",
    "addr:postcode":"72209",
    "addr:street":"Chicot Rd",
    "iso:country":"US",
    "sg:address":"8622 Chicot Rd",
    "sg:city":"Little Rock",
    "sg:classifiers":[
        {
            "category":"Food & Beverages",
            "subcategory":"Bakery",
            "type":"Retail Goods"
        }
    ],
    "sg:phone":"+1 501 565 0266",
    "sg:postcode":"72209",
    "sg:province":"AR",
    "sg:tags":[
        "baker"
    ],
    "wof:name":"Panaderia Taqueria Las America",
    "wof:placetype":"venue"
},
  "geometry": {"coordinates":[-92.36176399999999,34.671322],"type":"Point"}
}