{
  "type": "Feature",
  "properties": {
    "iso:country":"US",
    "sg:address":"1401 S Blake St",
    "sg:city":"Pine Bluff",
    "sg:classifiers":[
        {
            "category":"Retail",
            "subcategory":"Laundry & Dry Cleaning",
            "type":"Services"
        }
    ],
    "sg:phone":"+1 870 536 8131",
    "sg:postcode":"71603",
    "sg:province":"AR",
    "sg:tags":[
        "cleaners"
    ],
    "wof:name":"Flash Cleaners",
    "wof:placetype":"venue"
},
  "geometry": {"coordinates":[-92.043394,34.214774],"type":"Point"}
}