{
  "type": "Feature",
  "properties": {
    "iso:country":"US",
    "sg:address":"372 Co Rd 468",
    "sg:city":"Jonesboro",
    "sg:classifiers":[
        {
            "category":"Social Services",
            "type":"Services"
        }
    ],
    "sg:phone":"+1 870 268 8222",
    "sg:postcode":"72404",
    "sg:province":"AR",
    "sg:tags":[
        "organization",
        "welfare"
    ],
    "wof:name":"Special Olympics",
    "wof:placetype":"venue"
},
  "geometry": {"coordinates":[-90.664732,35.730396],"type":"Point"}
}