{
  "type": "Feature",
  "properties": {
    "addr:full":"179 County Road 5550 Ozone AR 72854",
    "addr:housenumber":"179",
    "addr:postcode":"5550;72854",
    "addr:street":"County Road",
    "iso:country":"US",
    "sg:address":"179 County Road 5550",
    "sg:city":"Ozone",
    "sg:classifiers":[
        {
            "category":"Building & Trades",
            "subcategory":"Construction",
            "type":"Services"
        }
    ],
    "sg:phone":"+1 479 292 3339",
    "sg:postcode":"72854",
    "sg:province":"AR",
    "sg:tags":[
        "roofing",
        "industrial",
        "contractors-commercial",
        "contractor"
    ],
    "wof:name":"Justice Roofing Service I",
    "wof:placetype":"venue"
},
  "geometry": {"coordinates":[-93.412209,35.690268],"type":"Point"}
}