{
  "type": "Feature",
  "properties": {
    "iso:country":"US",
    "sg:address":"200 W Locust",
    "sg:city":"El Dorado",
    "sg:classifiers":[
        {
            "category":"Building & Trades",
            "subcategory":"Plumbing",
            "type":"Services"
        }
    ],
    "sg:phone":"+1 870 862 6571",
    "sg:postcode":"71730",
    "sg:province":"AR",
    "sg:tags":[
        "conditioning",
        "air",
        "system",
        "contractor"
    ],
    "wof:name":"Dixie Air Corp",
    "wof:placetype":"venue"
},
  "geometry": {"coordinates":[-92.665458,33.21045],"type":"Point"}
}