{
  "type": "Feature",
  "properties": {
    "iso:country":"US",
    "sg:address":"10116 W Steele Rd",
    "sg:city":"Springdale",
    "sg:classifiers":[
        {
            "category":"Farming",
            "subcategory":"Livestock Farm",
            "type":"Manufacturing & Wholesale Goods"
        },
        {
            "category":"Farming",
            "subcategory":"Farm",
            "type":"Manufacturing & Wholesale Goods"
        }
    ],
    "sg:phone":"+1 479 361 2894",
    "sg:postcode":"72762",
    "sg:province":"AR",
    "sg:tags":[
        "beef",
        "feedlot",
        "cattle"
    ],
    "wof:name":"Inlow Farms",
    "wof:placetype":"venue"
},
  "geometry": {"coordinates":[-94.213932,36.140418],"type":"Point"}
}