{
  "type": "Feature",
  "properties": {
    "iso:country":"US",
    "sg:address":"219 W Main St",
    "sg:city":"Ozark",
    "sg:classifiers":[
        {
            "category":"Government",
            "subcategory":"Office",
            "type":"Public Place"
        }
    ],
    "sg:phone":"+1 479 667 2415",
    "sg:postcode":"72949",
    "sg:province":"AR",
    "wof:name":"Franklin County Assessor's Ofc",
    "wof:placetype":"venue"
},
  "geometry": {"coordinates":[-93.82722699999999,35.486062],"type":"Point"}
}