{
  "type": "Feature",
  "properties": {
    "iso:country":"US",
    "sg:address":"1901 Love St",
    "sg:city":"Pocola",
    "sg:classifiers":[
        {
            "category":"Professional",
            "subcategory":"Management & Consulting",
            "type":"Services"
        }
    ],
    "sg:phone":"+1 918 436 1915",
    "sg:postcode":"74902",
    "sg:province":"OK",
    "sg:tags":[
        "business"
    ],
    "wof:name":"D & H Consulting",
    "wof:placetype":"venue"
},
  "geometry": {"coordinates":[-94.478169,35.231678],"type":"Point"}
}