{
  "type": "Feature",
  "properties": {
    "addr:full":"2807 N Arkansas Ave Russellville AR 72802",
    "addr:housenumber":"2807",
    "addr:postcode":"72802",
    "addr:street":"N Arkansas Ave",
    "iso:country":"US",
    "sg:address":"2807 N Arkansas Ave",
    "sg:city":"Russellville",
    "sg:classifiers":[
        {
            "category":"Restaurant",
            "type":"Food & Drink"
        }
    ],
    "sg:phone":"+1 479 968 2111",
    "sg:postcode":"72802",
    "sg:province":"AR",
    "wof:name":"Seven Forty Supper Club",
    "wof:placetype":"venue"
},
  "geometry": {"coordinates":[-93.138763,35.308477],"type":"Point"}
}