{
  "type": "Feature",
  "properties": {
    "iso:country":"US",
    "sg:address":"308 E Main St",
    "sg:city":"Batesville",
    "sg:classifiers":[
        {
            "category":"Wholesale",
            "subcategory":"Furniture",
            "type":"Manufacturing & Wholesale Goods"
        }
    ],
    "sg:phone":"+1 870 698 1557",
    "sg:postcode":"72501",
    "sg:province":"AR",
    "sg:website":"www.schweg.com",
    "wof:name":"Schwegman Office Supply Inc",
    "wof:placetype":"venue"
},
  "geometry": {"coordinates":[-91.65124400000001,35.77163],"type":"Point"}
}