{
  "type": "Feature",
  "properties": {
    "iso:country":"US",
    "sg:address":"1021 N Constitution Ave",
    "sg:city":"Ashdown",
    "sg:classifiers":[
        {
            "category":"Professional",
            "subcategory":"Business Services",
            "type":"Services"
        }
    ],
    "sg:phone":"+1 870 898 3051",
    "sg:postcode":"71822",
    "sg:province":"AR",
    "sg:tags":[
        "water",
        "conservation"
    ],
    "wof:name":"Little River Conservation Dist",
    "wof:placetype":"venue"
},
  "geometry": {"coordinates":[-94.13527,33.681717],"type":"Point"}
}