{
  "type": "Feature",
  "properties": {
    "iso:country":"US",
    "sg:address":"4835 Gander Ln",
    "sg:city":"Harrison",
    "sg:classifiers":[
        {
            "category":"Building & Trades",
            "subcategory":"Plumbing",
            "type":"Services"
        }
    ],
    "sg:phone":"+1 870 743 6221",
    "sg:postcode":"72601",
    "sg:province":"AR",
    "sg:tags":[
        "tank",
        "septic"
    ],
    "wof:name":"Reliable Septic Tank Svc",
    "wof:placetype":"venue"
},
  "geometry": {"coordinates":[-93.03911600000001,36.165272],"type":"Point"}
}