{
  "type": "Feature",
  "properties": {
    "iso:country":"US",
    "sg:address":"2607 Stadium Blvd",
    "sg:city":"Jonesboro",
    "sg:classifiers":[
        {
            "category":"Food & Beverages",
            "subcategory":"Groceries & Convenience Stores",
            "type":"Retail Goods"
        }
    ],
    "sg:phone":"+1 870 972 6286",
    "sg:postcode":"72401",
    "sg:province":"AR",
    "wof:name":"Bullets Resturant",
    "wof:placetype":"venue"
},
  "geometry": {"coordinates":[-90.66909200000001,35.813884],"type":"Point"}
}