{
  "type": "Feature",
  "properties": {
    "iso:country":"US",
    "sg:address":"3200 S Battery St",
    "sg:city":"Little Rock",
    "sg:classifiers":[
        {
            "category":"Organizations",
            "subcategory":"Religious Organization",
            "type":"Services"
        }
    ],
    "sg:phone":"+1 501 244 2027",
    "sg:postcode":"72206",
    "sg:province":"AR",
    "sg:tags":[
        "church"
    ],
    "wof:name":"New Light Baptist Church Annex",
    "wof:placetype":"venue"
},
  "geometry": {"coordinates":[-92.294855,34.717732],"type":"Point"}
}