{
  "type": "Feature",
  "properties": {
    "iso:country":"US",
    "sg:address":"209 E F Ave",
    "sg:city":"N Little Rock",
    "sg:classifiers":[
        {
            "category":"Building & Trades",
            "subcategory":"Equipment Rental",
            "type":"Services"
        }
    ],
    "sg:phone":"+1 501 753 7878",
    "sg:postcode":"72116",
    "sg:province":"AR",
    "sg:tags":[
        "party",
        "supply"
    ],
    "wof:name":"Space Jump",
    "wof:placetype":"venue"
},
  "geometry": {"coordinates":[-92.257099,34.788058],"type":"Point"}
}