{
  "type": "Feature",
  "properties": {
    "iso:country":"US",
    "sg:address":"123 Moccasin Ln",
    "sg:city":"Bismarck",
    "sg:classifiers":[
        {
            "category":"Farming",
            "subcategory":"Farm",
            "type":"Manufacturing & Wholesale Goods"
        }
    ],
    "sg:phone":"+1 501 865 2216",
    "sg:postcode":"71929",
    "sg:province":"AR",
    "wof:name":"Rhein O Ranch",
    "wof:placetype":"venue"
},
  "geometry": {"coordinates":[-93.154979,34.321936],"type":"Point"}
}