{
  "type": "Feature",
  "properties": {
    "iso:country":"US",
    "sg:address":"1400 Marsha Dr",
    "sg:city":"Jacksonville",
    "sg:classifiers":[
        {
            "category":"Professional",
            "subcategory":"Business Services",
            "type":"Services"
        }
    ],
    "sg:phone":"+1 501 374 5324",
    "sg:postcode":"72076",
    "sg:province":"AR",
    "sg:tags":[
        "organizing",
        "services-household"
    ],
    "wof:name":"Herny Management",
    "wof:placetype":"venue"
},
  "geometry": {"coordinates":[-92.147278,34.879791],"type":"Point"}
}