{
  "type": "Feature",
  "properties": {
    "iso:country":"US",
    "sg:address":"108 N Pecan St",
    "sg:city":"Searcy",
    "sg:classifiers":[
        {
            "category":"Insurance",
            "subcategory":"Insurance Agent",
            "type":"Services"
        }
    ],
    "sg:phone":"+1 501 268 0888",
    "sg:postcode":"72143",
    "sg:province":"AR",
    "wof:name":"Insurance Warehouse Corp",
    "wof:placetype":"venue"
},
  "geometry": {"coordinates":[-91.744003,35.250005],"type":"Point"}
}