{
  "type": "Feature",
  "properties": {
    "iso:country":"US",
    "sg:address":"118 Co Rd 947",
    "sg:city":"Brookland",
    "sg:classifiers":[
        {
            "category":"Retail",
            "subcategory":"Auto Repair",
            "type":"Services"
        }
    ],
    "sg:phone":"+1 870 935 7193",
    "sg:postcode":"72417",
    "sg:province":"AR",
    "sg:tags":[
        "body",
        "automobile",
        "painting"
    ],
    "wof:name":"Bob's Auto Painting",
    "wof:placetype":"venue"
},
  "geometry": {"coordinates":[-90.536108,35.892676],"type":"Point"}
}