{
  "type": "Feature",
  "properties": {
    "iso:country":"US",
    "sg:address":"624 S Main St",
    "sg:city":"Jonesboro",
    "sg:classifiers":[
        {
            "category":"Professional",
            "subcategory":"Lawyer & Legal Services",
            "type":"Services"
        }
    ],
    "sg:phone":"+1 870 932 8686",
    "sg:postcode":"72401",
    "sg:province":"AR",
    "sg:tags":[
        "attorney"
    ],
    "wof:name":"Drummond Law Firm",
    "wof:placetype":"venue"
},
  "geometry": {"coordinates":[-90.704988,35.837502],"type":"Point"}
}