{
  "type": "Feature",
  "properties": {
    "addr:full":"809 9th Ave Conway AR 72032",
    "addr:housenumber":"809",
    "addr:postcode":"72032",
    "addr:street":"9Th Ave",
    "iso:country":"US",
    "sg:address":"809 9th Ave",
    "sg:city":"Conway",
    "sg:classifiers":[
        {
            "category":"Building & Trades",
            "subcategory":"Plumbing",
            "type":"Services"
        }
    ],
    "sg:phone":"+1 501 548 3535",
    "sg:postcode":"72032",
    "sg:province":"AR",
    "sg:tags":[
        "plumbing",
        "contractor"
    ],
    "wof:name":"Bruce Rogers Co Plbg Fixt",
    "wof:placetype":"venue"
},
  "geometry": {"coordinates":[-92.41561900000001,35.083422],"type":"Point"}
}