{
  "type": "Feature",
  "properties": {
    "addr:full":"409 N Rosser St Forrest City AR 72335",
    "addr:housenumber":"409",
    "addr:postcode":"72335",
    "addr:street":"N Rosser St",
    "iso:country":"US",
    "sg:address":"409 N Rosser St",
    "sg:city":"Forrest City",
    "sg:classifiers":[
        {
            "category":"Social Services",
            "type":"Services"
        }
    ],
    "sg:phone":"+1 870 633 6653",
    "sg:postcode":"72335",
    "sg:province":"AR",
    "sg:tags":[
        "probation"
    ],
    "wof:name":"Parole Area Office",
    "wof:placetype":"venue"
},
  "geometry": {"coordinates":[-90.787888,35.012354],"type":"Point"}
}