{
  "type": "Feature",
  "properties": {
    "iso:country":"US",
    "sg:address":"125 E 12th Ave",
    "sg:city":"Pine Bluff",
    "sg:classifiers":[
        {
            "category":"Professional",
            "subcategory":"Computer Services",
            "type":"Services"
        }
    ],
    "sg:phone":"+1 870 534 2565",
    "sg:postcode":"71601",
    "sg:province":"AR",
    "sg:tags":[
        "repair"
    ],
    "wof:name":"Just Us 4 Electronics & Tech",
    "wof:placetype":"venue"
},
  "geometry": {"coordinates":[-92.001408,34.217686],"type":"Point"}
}