{
  "type": "Feature",
  "properties": {
    "iso:country":"US",
    "sg:address":"17324 Dyer Rd",
    "sg:city":"Little Rock",
    "sg:classifiers":[
        {
            "category":"Building & Trades",
            "subcategory":"Cleaning & Sanitation",
            "type":"Services"
        }
    ],
    "sg:phone":"+1 501 868 4828",
    "sg:postcode":"72223",
    "sg:province":"AR",
    "sg:tags":[
        "maintenance"
    ],
    "wof:name":"Appleberry Hw Maintenance",
    "wof:placetype":"venue"
},
  "geometry": {"coordinates":[-92.458524,34.828599],"type":"Point"}
}