{
  "type": "Feature",
  "properties": {
    "iso:country":"US",
    "sg:address":"69605 E 300 Rd",
    "sg:city":"Grove",
    "sg:classifiers":[
        {
            "category":"Food & Beverages",
            "subcategory":"Groceries & Convenience Stores",
            "type":"Retail Goods"
        }
    ],
    "sg:phone":"+1 918 791 0010",
    "sg:postcode":"74344",
    "sg:province":"OK",
    "sg:tags":[
        "product"
    ],
    "wof:name":"Simmons Foods",
    "wof:placetype":"venue"
},
  "geometry": {"coordinates":[-94.64373000000001,36.583197],"type":"Point"}
}