{
  "type": "Feature",
  "properties": {
    "iso:country":"US",
    "sg:address":"608 Warner Ave",
    "sg:city":"Jonesboro",
    "sg:classifiers":[
        {
            "category":"Manufacturing",
            "subcategory":"Watercraft",
            "type":"Manufacturing & Wholesale Goods"
        }
    ],
    "sg:phone":"+1 870 972 6893",
    "sg:postcode":"72401",
    "sg:province":"AR",
    "wof:name":"Halfacre Arbile",
    "wof:placetype":"venue"
},
  "geometry": {"coordinates":[-90.711344,35.834935],"type":"Point"}
}