{
  "type": "Feature",
  "properties": {
    "iso:country":"US",
    "sg:address":"3610 West St",
    "sg:city":"Little Rock",
    "sg:classifiers":[
        {
            "category":"Retail",
            "subcategory":"Portrait Studio",
            "type":"Services"
        }
    ],
    "sg:phone":"+1 501 312 8427",
    "sg:postcode":"72204",
    "sg:province":"AR",
    "sg:tags":[
        "photographer"
    ],
    "wof:name":"Victor's Photography",
    "wof:placetype":"venue"
},
  "geometry": {"coordinates":[-92.38202699999999,34.719221],"type":"Point"}
}