{
  "type": "Feature",
  "properties": {
    "addr:full":"208 N Arkansas St Crossett AR 71635",
    "addr:housenumber":"208",
    "addr:postcode":"71635",
    "addr:street":"N Arkansas St",
    "iso:country":"US",
    "sg:address":"208 N Arkansas St",
    "sg:city":"Crossett",
    "sg:classifiers":[
        {
            "category":"Organizations",
            "subcategory":"Non-profit Organization",
            "type":"Services"
        }
    ],
    "sg:phone":"+1 870 364 2535",
    "sg:postcode":"71635",
    "sg:province":"AR",
    "sg:tags":[
        "disability"
    ],
    "wof:name":"Sheltered Workshop-Ashley",
    "wof:placetype":"venue"
},
  "geometry": {"coordinates":[-91.964311,33.133706],"type":"Point"}
}