{
  "type": "Feature",
  "properties": {
    "iso:country":"US",
    "sg:address":"11 River Rd",
    "sg:city":"Mayflower",
    "sg:classifiers":[
        {
            "category":"Wholesale",
            "subcategory":"Machinery & Supplies",
            "type":"Manufacturing & Wholesale Goods"
        }
    ],
    "sg:phone":"+1 501 803 0916",
    "sg:postcode":"72106",
    "sg:province":"AR",
    "sg:tags":[
        "gage"
    ],
    "wof:name":"Industrial Material & Svc Inc",
    "wof:placetype":"venue"
},
  "geometry": {"coordinates":[-92.449238,34.912296],"type":"Point"}
}