{
  "type": "Feature",
  "properties": {
    "iso:country":"US",
    "sg:address":"222 E 1st St N",
    "sg:city":"Prescott",
    "sg:classifiers":[
        {
            "category":"Manufacturing",
            "subcategory":"Furniture",
            "type":"Manufacturing & Wholesale Goods"
        }
    ],
    "sg:phone":"+1 870 887 1947",
    "sg:postcode":"71857",
    "sg:province":"AR",
    "sg:tags":[
        "household",
        "wood",
        "mfg"
    ],
    "wof:name":"Funshine Furniture",
    "wof:placetype":"venue"
},
  "geometry": {"coordinates":[-93.379408,33.802865],"type":"Point"}
}