{
  "type": "Feature",
  "properties": {
    "addr:full":"720 Allen Dr Monticello AR 71655",
    "addr:housenumber":"720",
    "addr:postcode":"71655",
    "addr:street":"Allen Dr",
    "iso:country":"US",
    "sg:address":"720 Allen Dr",
    "sg:city":"Monticello",
    "sg:classifiers":[
        {
            "category":"Banks & Credit Unions",
            "subcategory":"Financial Services",
            "type":"Services"
        }
    ],
    "sg:phone":"+1 870 367 6689",
    "sg:postcode":"71655",
    "sg:province":"AR",
    "sg:tags":[
        "trust",
        "investment",
        "real estate"
    ],
    "wof:name":"Allen Drive LP",
    "wof:placetype":"venue"
},
  "geometry": {"coordinates":[-91.80390800000001,33.655955],"type":"Point"}
}