{
  "type": "Feature",
  "properties": {
    "addr:full":"2030 N Jackson Magnolia AR 71753",
    "addr:housenumber":"2030",
    "addr:postcode":"71753",
    "addr:street":"N Jackson Magnolia",
    "iso:country":"US",
    "sg:address":"2030 N Jackson",
    "sg:city":"Magnolia",
    "sg:classifiers":[
        {
            "category":"Personal",
            "type":"Services"
        },
        {
            "category":"Sports & Exercise",
            "subcategory":"Gym",
            "type":"Entertainment"
        },
        {
            "category":"Health Services",
            "subcategory":"Health Practitioner",
            "type":"Services"
        },
        {
            "category":"Arena",
            "subcategory":"Sports Club",
            "type":"Entertainment"
        }
    ],
    "sg:phone":"+1 800 615 7352",
    "sg:postcode":"71753",
    "sg:province":"AR",
    "sg:tags":[
        "control",
        "trainer",
        "weight",
        "consultant",
        "program",
        "fitness",
        "physical"
    ],
    "sg:website":"http://national.citysearch.com/profile/external/41534919/magnolia_ar/curves.html?publisher=yellowpages&reference_id=1&placement=ypwebsitemip",
    "wof:name":"Curves",
    "wof:placetype":"venue"
},
  "geometry": {"coordinates":[-93.23505900000001,33.285222],"type":"Point"}
}