{
  "type": "Feature",
  "properties": {
    "iso:country":"US",
    "sg:address":"1008 Grim St",
    "sg:city":"Texarkana",
    "sg:classifiers":[
        {
            "category":"Building & Trades",
            "subcategory":"Construction",
            "type":"Services"
        },
        {
            "category":"Building & Trades",
            "subcategory":"Electrical",
            "type":"Services"
        }
    ],
    "sg:phone":"+1 870 773 4884",
    "sg:postcode":"71854",
    "sg:province":"AR",
    "sg:tags":[
        "altering",
        "remodeling",
        "electrician",
        "contractor"
    ],
    "wof:name":"R P Elecric",
    "wof:placetype":"venue"
},
  "geometry": {"coordinates":[-94.033525,33.411796],"type":"Point"}
}