{
  "type": "Feature",
  "properties": {
    "addr:full":"28114 S Springlake Rd Hensley AR 72065",
    "addr:housenumber":"28114",
    "addr:postcode":"72065",
    "addr:street":"S Springlake Rd",
    "iso:country":"US",
    "sg:address":"28114 S Springlake Rd",
    "sg:city":"Hensley",
    "sg:classifiers":[
        {
            "category":"Autos & Motor Vehicles",
            "subcategory":"Fuel & Gas Station",
            "type":"Retail Goods"
        }
    ],
    "sg:phone":"+1 501 888 1107",
    "sg:postcode":"72065",
    "sg:province":"AR",
    "sg:tags":[
        "operator",
        "station",
        "gasoline",
        "trucking"
    ],
    "wof:name":"Associated Mobile Home Movers",
    "wof:placetype":"venue"
},
  "geometry": {"coordinates":[-92.298461,34.509448],"type":"Point"}
}