{
  "type": "Feature",
  "properties": {
    "iso:country":"US",
    "sg:address":"8505 Doyle Springs Rd",
    "sg:city":"Little Rock",
    "sg:classifiers":[
        {
            "category":"Organizations",
            "subcategory":"Community Association",
            "type":"Services"
        }
    ],
    "sg:phone":"+1 501 562 4002",
    "sg:postcode":"72209",
    "sg:province":"AR",
    "sg:tags":[
        "fraternal"
    ],
    "wof:name":"Fraternal Order Of Police",
    "wof:placetype":"venue"
},
  "geometry": {"coordinates":[-92.328604,34.672563],"type":"Point"}
}