{
  "type": "Feature",
  "properties": {
    "iso:country":"US",
    "sg:address":"10700 Kanis Rd",
    "sg:city":"Little Rock",
    "sg:classifiers":[
        {
            "category":"Social Services",
            "subcategory":"Child Care",
            "type":"Services"
        }
    ],
    "sg:phone":"+1 501 223 3337",
    "sg:postcode":"72211",
    "sg:province":"AR",
    "sg:website":"www.kidcoearlyed.com",
    "wof:name":"Kidco Early Education Ctr",
    "wof:placetype":"venue"
},
  "geometry": {"coordinates":[-92.392747,34.743108],"type":"Point"}
}