{
  "type": "Feature",
  "properties": {
    "iso:country":"US",
    "sg:address":"56 Cherokee Acres Dr",
    "sg:city":"Cherokee Village",
    "sg:classifiers":[
        {
            "category":"Professional",
            "subcategory":"Secretarial Services",
            "type":"Services"
        }
    ],
    "sg:phone":"+1 870 257 2322",
    "sg:postcode":"72529",
    "sg:province":"AR",
    "sg:tags":[
        "editing"
    ],
    "wof:name":"Barry Bowman",
    "wof:placetype":"venue"
},
  "geometry": {"coordinates":[-91.57037099999999,36.285768],"type":"Point"}
}