{
  "type": "Feature",
  "properties": {
    "addr:full":"5606 John F Kennedy Blvd N Little Rock AR 72116",
    "addr:housenumber":"5606",
    "addr:postcode":"72116",
    "addr:street":"John F Kennedy Blvd N",
    "iso:country":"US",
    "sg:address":"5606 John F Kennedy Blvd",
    "sg:city":"N Little Rock",
    "sg:classifiers":[
        {
            "category":"Building & Trades",
            "subcategory":"Plumbing",
            "type":"Services"
        }
    ],
    "sg:phone":"+1 501 753 1515",
    "sg:postcode":"72116",
    "sg:province":"AR",
    "sg:tags":[
        "plumbing",
        "contractor"
    ],
    "wof:name":"Ray Lusk Plumbing",
    "wof:placetype":"venue"
},
  "geometry": {"coordinates":[-92.250157,34.80709],"type":"Point"}
}