{
  "type": "Feature",
  "properties": {
    "iso:country":"US",
    "sg:address":"3115 Pyburn Ext",
    "sg:city":"Pocahontas",
    "sg:classifiers":[
        {
            "category":"Organizations",
            "subcategory":"Religious Organization",
            "type":"Services"
        }
    ],
    "sg:phone":"+1 870 892 9473",
    "sg:postcode":"72455",
    "sg:province":"AR",
    "sg:website":"http://www.corneliushouse.com",
    "wof:name":"Cornelius House Inc",
    "wof:placetype":"venue"
},
  "geometry": {"coordinates":[-90.996759,36.273671],"type":"Point"}
}