{
  "type": "Feature",
  "properties": {
    "addr:full":"2600 W Hillsboro St El Dorado AR 71730",
    "addr:housenumber":"2600",
    "addr:postcode":"71730",
    "addr:street":"W Hillsboro St",
    "iso:country":"US",
    "sg:address":"2600 W Hillsboro St",
    "sg:city":"El Dorado",
    "sg:classifiers":[
        {
            "category":"Government",
            "subcategory":"Office",
            "type":"Public Place"
        }
    ],
    "sg:phone":"+1 870 862 5788",
    "sg:postcode":"71730",
    "sg:province":"AR",
    "sg:tags":[
        "federal",
        "human"
    ],
    "sg:website":"www.ssa.gov",
    "wof:name":"US Social Security Admin",
    "wof:placetype":"venue"
},
  "geometry": {"coordinates":[-92.69509600000001,33.207798],"type":"Point"}
}