{
  "type": "Feature",
  "properties": {
    "iso:country":"US",
    "sg:address":"920 Cherry Ln",
    "sg:city":"Malvern",
    "sg:classifiers":[
        {
            "category":"Organizations",
            "subcategory":"Religious Organization",
            "type":"Services"
        }
    ],
    "sg:phone":"+1 501 332 2384",
    "sg:postcode":"72104",
    "sg:province":"AR",
    "wof:name":"Rose Sharon Baptist Church",
    "wof:placetype":"venue"
},
  "geometry": {"coordinates":[-92.797375,34.360389],"type":"Point"}
}