{
  "type": "Feature",
  "properties": {
    "iso:country":"US",
    "sg:address":"1336 W Central St",
    "sg:city":"Warren",
    "sg:classifiers":[
        {
            "category":"Home & Garden",
            "subcategory":"Household Appliances",
            "type":"Retail Goods"
        }
    ],
    "sg:phone":"+1 870 226 3283",
    "sg:postcode":"71671",
    "sg:province":"AR",
    "wof:name":"Southern LP Gas Inc",
    "wof:placetype":"venue"
},
  "geometry": {"coordinates":[-92.088635,33.609812],"type":"Point"}
}