{
  "type": "Feature",
  "properties": {
    "addr:full":"1497 Lincoln St Lonoke AR 72086",
    "addr:housenumber":"1497",
    "addr:postcode":"72086",
    "addr:street":"Lincoln St",
    "iso:country":"US",
    "sg:address":"1497 Lincoln St",
    "sg:city":"Lonoke",
    "sg:classifiers":[
        {
            "category":"Social Services",
            "subcategory":"Adult Care",
            "type":"Services"
        }
    ],
    "sg:phone":"+1 501 676 6200",
    "sg:postcode":"72086",
    "sg:province":"AR",
    "sg:tags":[
        "living",
        "assisted",
        "facility",
        "residential"
    ],
    "wof:name":"Renaissance Assisted Living The",
    "wof:placetype":"venue"
},
  "geometry": {"coordinates":[-91.909277,34.771446],"type":"Point"}
}