{
  "type": "Feature",
  "properties": {
    "iso:country":"US",
    "sg:address":"2199 Indian Valley Dr",
    "sg:city":"Benton",
    "sg:classifiers":[
        {
            "category":"Health Services",
            "subcategory":"Doctor",
            "type":"Services"
        }
    ],
    "sg:phone":"+1 501 316 3256",
    "sg:postcode":"72019",
    "sg:province":"AR",
    "sg:tags":[
        "physician",
        "surgeon"
    ],
    "wof:name":"Lendall Shell",
    "wof:placetype":"venue"
},
  "geometry": {"coordinates":[-92.609839,34.621482],"type":"Point"}
}