{
  "type": "Feature",
  "properties": {
    "addr:full":"1942 Mill Creek Rd Hot Springs AR 71901",
    "addr:housenumber":"1942",
    "addr:postcode":"71901",
    "addr:street":"Mill Creek Rd",
    "iso:country":"US",
    "sg:address":"1942 Mill Creek Rd",
    "sg:city":"Hot Springs",
    "sg:classifiers":[
        {
            "category":"Recreation",
            "type":"Entertainment"
        }
    ],
    "sg:phone":"+1 501 623 5556",
    "sg:postcode":"71901",
    "sg:province":"AR",
    "sg:tags":[
        "stable"
    ],
    "sg:website":"www.panthervalleyranch.com",
    "wof:name":"Panther Valley Ranch Inc",
    "wof:placetype":"venue"
},
  "geometry": {"coordinates":[-93.00838299999999,34.515738],"type":"Point"}
}