{
  "type": "Feature",
  "properties": {
    "iso:country":"US",
    "sg:address":"7412 N Hills Blvd",
    "sg:city":"N Little Rock",
    "sg:classifiers":[
        {
            "category":"Restaurant",
            "type":"Food & Drink"
        }
    ],
    "sg:phone":"+1 501 833 3040",
    "sg:postcode":"72116",
    "sg:province":"AR",
    "sg:tags":[
        "pizza"
    ],
    "wof:name":"Jim's Razorback Pizza",
    "wof:placetype":"venue"
},
  "geometry": {"coordinates":[-92.2363,34.821626],"type":"Point"}
}