{
  "type": "Feature",
  "properties": {
    "addr:full":"1208 S Rogers St Clarksville AR 72830",
    "addr:housenumber":"1208",
    "addr:postcode":"72830",
    "addr:street":"S Rogers St",
    "iso:country":"US",
    "sg:address":"1208 S Rogers St",
    "sg:city":"Clarksville",
    "sg:classifiers":[
        {
            "category":"Real Estate",
            "subcategory":"Real Estate Agent",
            "type":"Services"
        }
    ],
    "sg:phone":"+1 479 705 7587",
    "sg:postcode":"72830",
    "sg:province":"AR",
    "wof:name":"Re Max Plus",
    "wof:placetype":"venue"
},
  "geometry": {"coordinates":[-93.460042,35.459833],"type":"Point"}
}