{
  "type": "Feature",
  "properties": {
    "iso:country":"US",
    "sg:address":"101 E Capitol Ave",
    "sg:city":"Little Rock",
    "sg:classifiers":[
        {
            "category":"Government",
            "subcategory":"Office",
            "type":"Public Place"
        }
    ],
    "sg:phone":"+1 501 682 2952",
    "sg:postcode":"72201",
    "sg:province":"AR",
    "sg:website":"www.asla.info",
    "wof:name":"Student Loan Authority",
    "wof:placetype":"venue"
},
  "geometry": {"coordinates":[-92.270474,34.744071],"type":"Point"}
}