{
  "type": "Feature",
  "properties": {
    "iso:country":"US",
    "sg:address":"964 State Hwy 1",
    "sg:city":"De Witt",
    "sg:classifiers":[
        {
            "category":"Freight",
            "type":"Transportation"
        }
    ],
    "sg:phone":"+1 870 946 2154",
    "sg:postcode":"72042",
    "sg:province":"AR",
    "sg:tags":[
        "operator",
        "trucking"
    ],
    "wof:name":"Ron Cat Services",
    "wof:placetype":"venue"
},
  "geometry": {"coordinates":[-91.224764,34.370082],"type":"Point"}
}