{
  "type": "Feature",
  "properties": {
    "addr:full":"80 Court St Marion AR 72364",
    "addr:housenumber":"80",
    "addr:postcode":"72364",
    "addr:street":"Court St",
    "iso:country":"US",
    "sg:address":"80 Court St",
    "sg:city":"Marion",
    "sg:classifiers":[
        {
            "category":"Insurance",
            "subcategory":"Hazard Insurance",
            "type":"Services"
        }
    ],
    "sg:phone":"+1 870 739 2212",
    "sg:postcode":"72364",
    "sg:province":"AR",
    "sg:tags":[
        "skip",
        "tracing",
        "bond"
    ],
    "wof:name":"A-1 Bail Bond Co.",
    "wof:placetype":"venue"
},
  "geometry": {"coordinates":[-90.196759,35.214819],"type":"Point"}
}