{
  "type": "Feature",
  "properties": {
    "addr:full":"100 S 30th St Ozark AR 72949",
    "addr:housenumber":"100",
    "addr:postcode":"72949",
    "addr:street":"S 30Th St",
    "iso:country":"US",
    "sg:address":"100 S 30th St",
    "sg:city":"Ozark",
    "sg:classifiers":[
        {
            "category":"Personal",
            "subcategory":"Beauty Salon",
            "type":"Services"
        }
    ],
    "sg:phone":"+1 479 667 5484",
    "sg:postcode":"72949",
    "sg:province":"AR",
    "sg:tags":[
        "shop"
    ],
    "wof:name":"Sophisticuts Salon & Spa",
    "wof:placetype":"venue"
},
  "geometry": {"coordinates":[-93.85890999999999,35.49023],"type":"Point"}
}