{
  "type": "Feature",
  "properties": {
    "addr:full":"2323 N Poplar St N Little Rock AR 72114",
    "addr:housenumber":"2323",
    "addr:postcode":"72114",
    "addr:street":"N Poplar St N",
    "iso:country":"US",
    "sg:address":"2323 N Poplar St",
    "sg:city":"N Little Rock",
    "sg:classifiers":[
        {
            "category":"Shopping",
            "subcategory":"Bicycles & Sporting Goods",
            "type":"Retail Goods"
        }
    ],
    "sg:phone":"+1 501 753 6004",
    "sg:postcode":"72114",
    "sg:province":"AR",
    "sg:tags":[
        "equipment",
        "diver",
        "supply"
    ],
    "sg:website":"www.ricksdivecenter.com",
    "wof:name":"Rick's Dive 'n Travel Ctr",
    "wof:placetype":"venue"
},
  "geometry": {"coordinates":[-92.26522300000001,34.777301],"type":"Point"}
}