{
  "type": "Feature",
  "properties": {
    "iso:country":"US",
    "sg:address":"513 N Missouri St",
    "sg:city":"West Memphis",
    "sg:classifiers":[
        {
            "category":"Organizations",
            "subcategory":"Religious Organization",
            "type":"Services"
        }
    ],
    "sg:phone":"+1 870 735 1907",
    "sg:postcode":"72301",
    "sg:province":"AR",
    "sg:tags":[
        "church"
    ],
    "wof:name":"First Assembly Of God",
    "wof:placetype":"venue"
},
  "geometry": {"coordinates":[-90.184698,35.151808],"type":"Point"}
}