{
  "type": "Feature",
  "properties": {
    "iso:country":"US",
    "sg:address":"8553 Raybourn Rd",
    "sg:city":"Weiner",
    "sg:classifiers":[
        {
            "category":"Manufacturing",
            "subcategory":"Pet Food",
            "type":"Manufacturing & Wholesale Goods"
        }
    ],
    "sg:phone":"+1 870 684 2354",
    "sg:postcode":"72479",
    "sg:province":"AR",
    "sg:tags":[
        "rice",
        "mills"
    ],
    "sg:website":"www.southernbrownrice.com",
    "wof:name":"Southern Brown Rice",
    "wof:placetype":"venue"
},
  "geometry": {"coordinates":[-90.88187,35.637477],"type":"Point"}
}