{
  "type": "Feature",
  "properties": {
    "iso:country":"US",
    "sg:address":"6601 Euper Ln",
    "sg:city":"Fort Smith",
    "sg:classifiers":[
        {
            "category":"Education",
            "subcategory":"School",
            "type":"Public Place"
        }
    ],
    "sg:phone":"+1 479 452 2601",
    "sg:postcode":"72903",
    "sg:province":"AR",
    "wof:name":"Euper Lane Elementary School",
    "wof:placetype":"venue"
},
  "geometry": {"coordinates":[-94.356768,35.363085],"type":"Point"}
}