{
  "type": "Feature",
  "properties": {
    "addr:full":"2315 Aaron Rd Beebe AR 72012",
    "addr:housenumber":"2315",
    "addr:postcode":"72012",
    "addr:street":"Aaron Rd",
    "iso:country":"US",
    "sg:address":"2315 Aaron Rd",
    "sg:city":"Beebe",
    "sg:classifiers":[
        {
            "category":"Professional",
            "type":"Services"
        }
    ],
    "sg:phone":"+1 501 882 2185",
    "sg:postcode":"72012",
    "sg:province":"AR",
    "wof:name":"Mary Nell Sparks",
    "wof:placetype":"venue"
},
  "geometry": {"coordinates":[-91.920625,35.07025],"type":"Point"}
}