{
  "type": "Feature",
  "properties": {
    "iso:country":"US",
    "sg:address":"1300 Westpark Dr",
    "sg:city":"Little Rock",
    "sg:classifiers":[
        {
            "category":"Professional",
            "subcategory":"Business Services",
            "type":"Services"
        }
    ],
    "sg:phone":"+1 501 663 7054",
    "sg:postcode":"72204",
    "sg:province":"AR",
    "wof:name":"Cbm Appraisals",
    "wof:placetype":"venue"
},
  "geometry": {"coordinates":[-92.351705,34.738198],"type":"Point"}
}