{
  "type": "Feature",
  "properties": {
    "iso:country":"US",
    "sg:address":"501 N Hervey St",
    "sg:city":"Hope",
    "sg:classifiers":[
        {
            "category":"Health Services",
            "subcategory":"Health Practitioner",
            "type":"Services"
        }
    ],
    "sg:phone":"+1 870 777 6798",
    "sg:postcode":"71801",
    "sg:province":"AR",
    "sg:tags":[
        "therapist",
        "physical"
    ],
    "wof:name":"Haynes Sports Therapy & Rehab",
    "wof:placetype":"venue"
},
  "geometry": {"coordinates":[-93.59862699999999,33.673069],"type":"Point"}
}