{
  "type": "Feature",
  "properties": {
    "addr:full":"851 W Semmes Ave Osceola AR 72370",
    "addr:housenumber":"851",
    "addr:postcode":"72370",
    "addr:street":"W Semmes Ave",
    "iso:country":"US",
    "sg:address":"851 W Semmes Ave",
    "sg:city":"Osceola",
    "sg:classifiers":[
        {
            "category":"Professional",
            "type":"Services"
        }
    ],
    "sg:phone":"+1 870 563 5582",
    "sg:postcode":"72370",
    "sg:province":"AR",
    "wof:name":"Ralph Wilson Jr",
    "wof:placetype":"venue"
},
  "geometry": {"coordinates":[-89.98133900000001,35.704932],"type":"Point"}
}