{
  "type": "Feature",
  "properties": {
    "iso:country":"US",
    "sg:address":"732 N Main St",
    "sg:city":"Decatur",
    "sg:classifiers":[
        {
            "category":"Organizations",
            "subcategory":"Religious Organization",
            "type":"Services"
        }
    ],
    "sg:phone":"+1 479 752 3230",
    "sg:postcode":"72722",
    "sg:province":"AR",
    "sg:tags":[
        "church"
    ],
    "wof:name":"Assembly Of God Church",
    "wof:placetype":"venue"
},
  "geometry": {"coordinates":[-94.46042799999999,36.342672],"type":"Point"}
}