{
  "type": "Feature",
  "properties": {
    "iso:country":"US",
    "sg:address":"121 Central Ave",
    "sg:city":"Hot Springs National",
    "sg:classifiers":[
        {
            "category":"Shopping",
            "subcategory":"Gifts & Souvenirs",
            "type":"Retail Goods"
        }
    ],
    "sg:phone":"+1 501 623 5966",
    "sg:postcode":"71901",
    "sg:province":"AR",
    "wof:name":"Gift Tree",
    "wof:placetype":"venue"
},
  "geometry": {"coordinates":[-93.055622,34.51853],"type":"Point"}
}