{
  "type": "Feature",
  "properties": {
    "iso:country":"US",
    "sg:address":"2420 Walnut Grove Rd",
    "sg:city":"Newark",
    "sg:classifiers":[
        {
            "category":"Building & Trades",
            "subcategory":"Construction",
            "type":"Services"
        }
    ],
    "sg:phone":"+1 870 799 8204",
    "sg:postcode":"72562",
    "sg:province":"AR",
    "sg:tags":[
        "nonresidential"
    ],
    "wof:name":"Rudd Construction",
    "wof:placetype":"venue"
},
  "geometry": {"coordinates":[-91.42927299999999,35.768868],"type":"Point"}
}