{
  "type": "Feature",
  "properties": {
    "addr:full":"14 Rolling Pines Cove Conway AR 72034",
    "addr:housenumber":"14",
    "addr:postcode":"72034",
    "addr:street":"Rolling Pines Cove",
    "iso:country":"US",
    "sg:address":"14 Rolling Pines Cove",
    "sg:city":"Conway",
    "sg:classifiers":[
        {
            "category":"Communications",
            "subcategory":"Film & Video Production",
            "type":"Services"
        }
    ],
    "sg:phone":"+1 501 470 1202",
    "sg:postcode":"72034",
    "sg:province":"AR",
    "sg:tags":[
        "motion"
    ],
    "wof:name":"Solid Rock Audio Inc",
    "wof:placetype":"venue"
},
  "geometry": {"coordinates":[-92.427086,35.024464],"type":"Point"}
}