{
  "type": "Feature",
  "properties": {
    "addr:full":"300 Parker Ave Fort Smith AR 72901",
    "addr:housenumber":"300",
    "addr:postcode":"72901",
    "addr:street":"Parker Ave",
    "iso:country":"US",
    "sg:address":"300 Parker Ave",
    "sg:city":"Fort Smith",
    "sg:classifiers":[
        {
            "category":"Professional",
            "type":"Services"
        }
    ],
    "sg:phone":"+1 479 424 1888",
    "sg:postcode":"72901",
    "sg:province":"AR",
    "sg:tags":[
        "establishment"
    ],
    "wof:name":"Phones & Data Quality Svc",
    "wof:placetype":"venue"
},
  "geometry": {"coordinates":[-94.42875600000001,35.386815],"type":"Point"}
}