{
  "type": "Feature",
  "properties": {
    "addr:full":"2907 Lakewood Village Dr N Little Rock AR 72116",
    "addr:housenumber":"2907",
    "addr:postcode":"72116",
    "addr:street":"Lakewood Village Dr N",
    "iso:country":"US",
    "sg:address":"2907 Lakewood Village Dr",
    "sg:city":"N Little Rock",
    "sg:classifiers":[
        {
            "category":"Restaurant",
            "type":"Food & Drink"
        }
    ],
    "sg:phone":"+1 501 812 9888",
    "sg:postcode":"72116",
    "sg:province":"AR",
    "wof:name":"Crazy Hibachi Co",
    "wof:placetype":"venue"
},
  "geometry": {"coordinates":[-92.23181099999999,34.796798],"type":"Point"}
}