{
  "type": "Feature",
  "properties": {
    "addr:full":"1510 Highway 71 N Mena AR 71953",
    "addr:housenumber":"1510",
    "addr:postcode":"71953",
    "addr:street":"Highway 71 N",
    "iso:country":"US",
    "sg:address":"1510 Highway 71 N",
    "sg:city":"Mena",
    "sg:classifiers":[
        {
            "category":"Shopping",
            "subcategory":"Pets & Pet Supplies",
            "type":"Retail Goods"
        },
        {
            "category":"Retail",
            "subcategory":"Animal Services",
            "type":"Services"
        }
    ],
    "sg:phone":"+1 479 394 1418",
    "sg:postcode":"71953",
    "sg:province":"AR",
    "sg:tags":[
        "grooming",
        "furnishing",
        "dog",
        "store",
        "cat"
    ],
    "wof:name":"Custom Critter Cuts",
    "wof:placetype":"venue"
},
  "geometry": {"coordinates":[-94.204009,34.636678],"type":"Point"}
}