{
  "type": "Feature",
  "properties": {
    "addr:full":"1903 E Main St Russellville AR 72801",
    "addr:housenumber":"1903",
    "addr:postcode":"72801",
    "addr:street":"E Main St",
    "iso:country":"US",
    "sg:address":"1903 E Main St",
    "sg:city":"Russellville",
    "sg:classifiers":[
        {
            "category":"Shopping",
            "subcategory":"Clothing, Apparel, & Fashions",
            "type":"Retail Goods"
        }
    ],
    "sg:phone":"+1 479 890 9567",
    "sg:postcode":"72801",
    "sg:province":"AR",
    "wof:name":"Whitneys Bridal",
    "wof:placetype":"venue"
},
  "geometry": {"coordinates":[-93.111411,35.278363],"type":"Point"}
}