{
  "type": "Feature",
  "properties": {
    "iso:country":"US",
    "sg:address":"1015 State Hwy 44",
    "sg:city":"Tichnor",
    "sg:classifiers":[
        {
            "category":"Government",
            "subcategory":"Post Office",
            "type":"Public Place"
        }
    ],
    "sg:phone":"+1 870 548 2888",
    "sg:postcode":"72166",
    "sg:province":"AR",
    "wof:name":"US Post Office",
    "wof:placetype":"venue"
},
  "geometry": {"coordinates":[-91.26600999999999,34.134769],"type":"Point"}
}