{
  "type": "Feature",
  "properties": {
    "addr:full":"5651 Wesson Rd Junction City AR 71749",
    "addr:housenumber":"5651",
    "addr:postcode":"71749",
    "addr:street":"Wesson Rd",
    "iso:country":"US",
    "sg:address":"5651 Wesson Rd",
    "sg:city":"Junction City",
    "sg:classifiers":[
        {
            "category":"Farming",
            "subcategory":"Farm",
            "type":"Manufacturing & Wholesale Goods"
        }
    ],
    "sg:phone":"+1 870 862 0139",
    "sg:postcode":"71749",
    "sg:province":"AR",
    "sg:tags":[
        "crop",
        "general"
    ],
    "wof:name":"Charles R Orr",
    "wof:placetype":"venue"
},
  "geometry": {"coordinates":[-92.76835699999999,33.124512],"type":"Point"}
}