{
  "type": "Feature",
  "properties": {
    "addr:full":"3847 Madison 2545 Huntsville AR 72740",
    "addr:housenumber":"3847",
    "addr:postcode":"2545;72740",
    "addr:street":"Madison",
    "iso:country":"US",
    "sg:address":"3847 Madison 2545",
    "sg:city":"Huntsville",
    "sg:classifiers":[
        {
            "category":"Personal",
            "subcategory":"Beauty Salon",
            "type":"Services"
        }
    ],
    "sg:phone":"+1 479 665 2793",
    "sg:postcode":"72740",
    "sg:province":"AR",
    "sg:tags":[
        "shop"
    ],
    "wof:name":"Lindas Style Spot",
    "wof:placetype":"venue"
},
  "geometry": {"coordinates":[-93.543424,36.055173],"type":"Point"}
}