{
  "type": "Feature",
  "properties": {
    "iso:country":"US",
    "sg:address":"2036 Lake Fort Smith Rd",
    "sg:city":"Mountainburg",
    "sg:classifiers":[
        {
            "category":"Manufacturing",
            "subcategory":"Buildings",
            "type":"Manufacturing & Wholesale Goods"
        },
        {
            "category":"Building & Trades",
            "subcategory":"Construction",
            "type":"Services"
        }
    ],
    "sg:phone":"+1 479 662 6090",
    "sg:postcode":"72946",
    "sg:province":"AR",
    "sg:tags":[
        "home",
        "builder",
        "contractor"
    ],
    "wof:name":"Crossland Construction",
    "wof:placetype":"venue"
},
  "geometry": {"coordinates":[-94.157213,35.649704],"type":"Point"}
}