{
  "type": "Feature",
  "properties": {
    "addr:full":"2218 Cantrell Rd Little Rock AR 72202",
    "addr:housenumber":"2218",
    "addr:postcode":"72202",
    "addr:street":"Cantrell Rd",
    "iso:country":"US",
    "sg:address":"2218 Cantrell Rd",
    "sg:city":"Little Rock",
    "sg:classifiers":[
        {
            "category":"Wholesale",
            "subcategory":"Electrical",
            "type":"Manufacturing & Wholesale Goods"
        }
    ],
    "sg:phone":"+1 501 375 1171",
    "sg:postcode":"72202",
    "sg:province":"AR",
    "sg:tags":[
        "control"
    ],
    "wof:name":"WACO Distributing Co",
    "wof:placetype":"venue"
},
  "geometry": {"coordinates":[-92.299494,34.756555],"type":"Point"}
}