{
  "type": "Feature",
  "properties": {
    "addr:full":"209 E Collin Raye Dr De Queen AR 71832",
    "addr:housenumber":"209",
    "addr:postcode":"71832",
    "addr:street":"E Collin Raye Dr De Queen",
    "iso:country":"US",
    "sg:address":"209 E Collin Raye Dr",
    "sg:city":"De Queen",
    "sg:classifiers":[
        {
            "category":"Cinema",
            "subcategory":"Movie Rental",
            "type":"Entertainment"
        }
    ],
    "sg:phone":"+1 870 642 2696",
    "sg:postcode":"71832",
    "sg:province":"AR",
    "sg:tags":[
        "leasing",
        "video",
        "disc",
        "tape"
    ],
    "wof:name":"Home Entertainment",
    "wof:placetype":"venue"
},
  "geometry": {"coordinates":[-94.33388100000001,34.045569],"type":"Point"}
}