{
  "type": "Feature",
  "properties": {
    "addr:full":"105 Coy Cv Harrison AR 72601",
    "addr:housenumber":"105",
    "addr:postcode":"72601",
    "addr:street":"Coy Cv",
    "iso:country":"US",
    "sg:address":"105 Coy Cv",
    "sg:city":"Harrison",
    "sg:classifiers":[
        {
            "category":"Personal",
            "subcategory":"Beauty Salon",
            "type":"Services"
        }
    ],
    "sg:phone":"+1 870 743 3914",
    "sg:postcode":"72601",
    "sg:province":"AR",
    "wof:name":"Tim Jackson Hair Salon",
    "wof:placetype":"venue"
},
  "geometry": {"coordinates":[-93.07249400000001,36.214983],"type":"Point"}
}