{
  "type": "Feature",
  "properties": {
    "addr:full":"513 Porter St Helena AR 72342",
    "addr:housenumber":"513",
    "addr:postcode":"72342",
    "addr:street":"Porter St",
    "iso:country":"US",
    "sg:address":"513 Porter St",
    "sg:city":"Helena",
    "sg:classifiers":[
        {
            "category":"Health Services",
            "subcategory":"Doctor",
            "type":"Services"
        }
    ],
    "sg:phone":"+1 870 338 7401",
    "sg:postcode":"72342",
    "sg:province":"AR",
    "sg:tags":[
        "medical"
    ],
    "wof:name":"Johnny R Paine MD",
    "wof:placetype":"venue"
},
  "geometry": {"coordinates":[-90.589112,34.527993],"type":"Point"}
}