{
  "type": "Feature",
  "properties": {
    "iso:country":"US",
    "sg:address":"517 Olvey Rd",
    "sg:city":"Harrison",
    "sg:classifiers":[
        {
            "category":"Restaurant",
            "type":"Food & Drink"
        }
    ],
    "sg:phone":"+1 870 743 3843",
    "sg:postcode":"72601",
    "sg:province":"AR",
    "sg:tags":[
        "eating"
    ],
    "wof:name":"Pizza Pro Inc",
    "wof:placetype":"venue"
},
  "geometry": {"coordinates":[-92.965695,36.192947],"type":"Point"}
}