{
  "type": "Feature",
  "properties": {
    "addr:full":"7301 Zero St Fort Smith AR 72903",
    "addr:housenumber":"7301",
    "addr:postcode":"72903",
    "addr:street":"Zero St",
    "iso:country":"US",
    "sg:address":"7301 Zero St",
    "sg:city":"Fort Smith",
    "sg:classifiers":[
        {
            "category":"Autos & Motor Vehicles",
            "subcategory":"Automobile Sales",
            "type":"Retail Goods"
        }
    ],
    "sg:phone":"+1 479 452 2767",
    "sg:postcode":"72903",
    "sg:province":"AR",
    "sg:tags":[
        "car",
        "dealer"
    ],
    "wof:name":"A & R Auto Sales II",
    "wof:placetype":"venue"
},
  "geometry": {"coordinates":[-94.353409,35.326027],"type":"Point"}
}