{
  "type": "Feature",
  "properties": {
    "addr:full":"141 State Hwy 355 Hope AR 71801",
    "addr:housenumber":"141",
    "addr:postcode":"71801",
    "addr:street":"State Hwy 355",
    "iso:country":"US",
    "sg:address":"141 State Hwy 355",
    "sg:city":"Hope",
    "sg:classifiers":[
        {
            "category":"Farming",
            "subcategory":"Livestock Farm",
            "type":"Manufacturing & Wholesale Goods"
        }
    ],
    "sg:phone":"+1 870 777 0509",
    "sg:postcode":"71801",
    "sg:province":"AR",
    "sg:tags":[
        "animal",
        "general"
    ],
    "wof:name":"280 Hunting Club",
    "wof:placetype":"venue"
},
  "geometry": {"coordinates":[-93.616089,33.574961],"type":"Point"}
}