{
  "type": "Feature",
  "properties": {
    "addr:full":"811 Old Hwy 7 S Dardanelle AR 72834",
    "addr:housenumber":"811",
    "addr:postcode":"72834",
    "addr:street":"Old Hwy 7 S",
    "iso:country":"US",
    "sg:address":"811 Old Hwy 7 S",
    "sg:city":"Dardanelle",
    "sg:classifiers":[
        {
            "category":"Personal",
            "subcategory":"Beauty Salon",
            "type":"Services"
        }
    ],
    "sg:phone":"+1 479 229 3788",
    "sg:postcode":"72834",
    "sg:province":"AR",
    "sg:tags":[
        "shop"
    ],
    "wof:name":"Mane Attraction Salon",
    "wof:placetype":"venue"
},
  "geometry": {"coordinates":[-93.15104599999999,35.211438],"type":"Point"}
}