{
  "type": "Feature",
  "properties": {
    "iso:country":"US",
    "sg:address":"202 N 2nd St",
    "sg:city":"Glenwood",
    "sg:classifiers":[
        {
            "category":"Insurance",
            "subcategory":"Insurance Agent",
            "type":"Services"
        }
    ],
    "sg:phone":"+1 870 356 4111",
    "sg:postcode":"71943",
    "sg:province":"AR",
    "wof:name":"Allstate Insurance Co",
    "wof:placetype":"venue"
},
  "geometry": {"coordinates":[-93.55136400000001,34.32751],"type":"Point"}
}