{
  "type": "Feature",
  "properties": {
    "iso:country":"US",
    "sg:address":"1320 Gober Rd",
    "sg:city":"Fordyce",
    "sg:classifiers":[
        {
            "category":"Freight",
            "type":"Transportation"
        }
    ],
    "sg:phone":"+1 870 352 2286",
    "sg:postcode":"71742",
    "sg:province":"AR",
    "sg:tags":[
        "hauling",
        "trucking"
    ],
    "wof:name":"Garland Raney & Sons Trucking",
    "wof:placetype":"venue"
},
  "geometry": {"coordinates":[-92.397752,33.833635],"type":"Point"}
}