{
  "type": "Feature",
  "properties": {
    "iso:country":"US",
    "sg:address":"1125 N College Ave",
    "sg:city":"Fayetteville",
    "sg:classifiers":[
        {
            "category":"Professional",
            "type":"Services"
        }
    ],
    "sg:phone":"+1 479 442 9063",
    "sg:postcode":"72703",
    "sg:province":"AR",
    "sg:tags":[
        "establishment"
    ],
    "wof:name":"Interfaith Volunteer Crgvrs",
    "wof:placetype":"venue"
},
  "geometry": {"coordinates":[-94.157076,36.078385],"type":"Point"}
}