{
  "type": "Feature",
  "properties": {
    "iso:country":"US",
    "sg:address":"208 N Rosser St",
    "sg:city":"Forrest City",
    "sg:classifiers":[
        {
            "category":"Retail",
            "subcategory":"Laundry & Dry Cleaning",
            "type":"Services"
        }
    ],
    "sg:phone":"+1 870 633 6628",
    "sg:postcode":"72335",
    "sg:province":"AR",
    "sg:tags":[
        "drycleaning",
        "plant",
        "agent",
        "w",
        "garment"
    ],
    "wof:name":"Nuway Cleaners & Laundry",
    "wof:placetype":"venue"
},
  "geometry": {"coordinates":[-90.78698300000001,35.010631],"type":"Point"}
}