{
  "type": "Feature",
  "properties": {
    "addr:full":"31804 Highway 84 Malvern AR 72104",
    "addr:housenumber":"31804",
    "addr:postcode":"72104",
    "addr:street":"Highway 84",
    "iso:country":"US",
    "sg:address":"31804 Highway 84",
    "sg:city":"Malvern",
    "sg:classifiers":[
        {
            "category":"Manufacturing",
            "subcategory":"Buildings",
            "type":"Manufacturing & Wholesale Goods"
        },
        {
            "category":"Building & Trades",
            "subcategory":"Construction",
            "type":"Services"
        }
    ],
    "sg:phone":"+1 501 337 0677",
    "sg:postcode":"72104",
    "sg:province":"AR",
    "sg:tags":[
        "home",
        "builder",
        "industrial",
        "contractors-commercial",
        "contractor"
    ],
    "wof:name":"Mid State Construction",
    "wof:placetype":"venue"
},
  "geometry": {"coordinates":[-93.115157,34.326834],"type":"Point"}
}