{
  "type": "Feature",
  "properties": {
    "addr:full":"3200 Porter Jasper Rd Crossett AR 71635",
    "addr:housenumber":"3200",
    "addr:postcode":"71635",
    "addr:street":"Porter Jasper Rd",
    "iso:country":"US",
    "sg:address":"3200 Porter Jasper Rd",
    "sg:city":"Crossett",
    "sg:classifiers":[
        {
            "category":"Professional",
            "subcategory":"Detective & Security Services",
            "type":"Services"
        }
    ],
    "sg:phone":"+1 870 305 1130",
    "sg:postcode":"71635",
    "sg:province":"AR",
    "sg:tags":[
        "information",
        "bureau"
    ],
    "wof:name":"4 Wright's Catering Service",
    "wof:placetype":"venue"
},
  "geometry": {"coordinates":[-91.996391,33.144588],"type":"Point"}
}