{
  "type": "Feature",
  "properties": {
    "iso:country":"US",
    "sg:address":"64100 E. 290 Rd",
    "sg:city":"Grove",
    "sg:classifiers":[
        {
            "category":"Autos & Motor Vehicles",
            "subcategory":"Auto Supplies",
            "type":"Retail Goods"
        },
        {
            "category":"Retail",
            "subcategory":"Auto Repair",
            "type":"Services"
        }
    ],
    "sg:phone":"+1 918 791 4365",
    "sg:postcode":"74344",
    "sg:province":"OK",
    "sg:tags":[
        "tire",
        "automobile",
        "brake",
        "equipment-service",
        "diagnostic",
        "air conditioning"
    ],
    "wof:name":"Matt's Auto Clinic",
    "wof:placetype":"venue"
},
  "geometry": {"coordinates":[-94.812729,36.598024],"type":"Point"}
}