{
  "type": "Feature",
  "properties": {
    "iso:country":"US",
    "sg:address":"1605 N Cedar St",
    "sg:city":"N Little Rock",
    "sg:classifiers":[
        {
            "category":"Wholesale",
            "subcategory":"Machinery & Supplies",
            "type":"Manufacturing & Wholesale Goods"
        },
        {
            "category":"Shopping",
            "type":"Retail Goods"
        }
    ],
    "sg:phone":"+1 501 372 4270",
    "sg:postcode":"72114",
    "sg:province":"AR",
    "sg:tags":[
        "equipment",
        "establishment",
        "cosmetic",
        "perfume"
    ],
    "wof:name":"Ann's Beauty Supplies",
    "wof:placetype":"venue"
},
  "geometry": {"coordinates":[-92.257741,34.769603],"type":"Point"}
}