{
  "type": "Feature",
  "properties": {
    "addr:full":"2609 S Greenwood Ave Fort Smith AR 72901",
    "addr:housenumber":"2609",
    "addr:postcode":"72901",
    "addr:street":"S Greenwood Ave",
    "iso:country":"US",
    "sg:address":"2609 S Greenwood Ave",
    "sg:city":"Fort Smith",
    "sg:classifiers":[
        {
            "category":"Building & Trades",
            "subcategory":"Construction",
            "type":"Services"
        }
    ],
    "sg:phone":"+1 479 782 9945",
    "sg:postcode":"72901",
    "sg:province":"AR",
    "sg:tags":[
        "concrete",
        "contractor"
    ],
    "wof:name":"Hawley Concrete Construction",
    "wof:placetype":"venue"
},
  "geometry": {"coordinates":[-94.404083,35.358717],"type":"Point"}
}