{
  "type": "Feature",
  "properties": {
    "iso:country":"US",
    "sg:address":"198 W Main St",
    "sg:city":"West Fork",
    "sg:classifiers":[
        {
            "category":"Education",
            "subcategory":"Library",
            "type":"Public Place"
        }
    ],
    "sg:phone":"+1 479 839 2626",
    "sg:postcode":"72774",
    "sg:province":"AR",
    "wof:name":"West Fork Library",
    "wof:placetype":"venue"
},
  "geometry": {"coordinates":[-94.185526,35.926682],"type":"Point"}
}