{
  "type": "Feature",
  "properties": {
    "iso:country":"US",
    "sg:address":"387 Blue Springs Rd",
    "sg:city":"Fayetteville",
    "sg:classifiers":[
        {
            "category":"Professional",
            "subcategory":"Management & Consulting",
            "type":"Services"
        }
    ],
    "sg:phone":"+1 479 571 1633",
    "sg:postcode":"72703",
    "sg:province":"AR",
    "sg:tags":[
        "engineering",
        "business"
    ],
    "wof:name":"Power Science Inc",
    "wof:placetype":"venue"
},
  "geometry": {"coordinates":[-94.000215,36.105058],"type":"Point"}
}