{
  "type": "Feature",
  "properties": {
    "addr:full":"1806 E 50th St Texarkana AR 71854",
    "addr:housenumber":"1806",
    "addr:postcode":"71854",
    "addr:street":"E 50Th St",
    "iso:country":"US",
    "sg:address":"1806 E 50th St",
    "sg:city":"Texarkana",
    "sg:classifiers":[
        {
            "category":"Arts & Performance",
            "subcategory":"Dance",
            "type":"Entertainment"
        }
    ],
    "sg:phone":"+1 870 772 1921",
    "sg:postcode":"71854",
    "sg:province":"AR",
    "sg:tags":[
        "instruction",
        "dancing"
    ],
    "wof:name":"Arkansas Academy Of Dance",
    "wof:placetype":"venue"
},
  "geometry": {"coordinates":[-94.02767299999999,33.470521],"type":"Point"}
}