{
  "type": "Feature",
  "properties": {
    "iso:country":"US",
    "sg:address":"5320 W Sunset Ave",
    "sg:city":"Springdale",
    "sg:classifiers":[
        {
            "category":"Home & Garden",
            "subcategory":"Carpets & Floor Coverings",
            "type":"Retail Goods"
        }
    ],
    "sg:phone":"+1 479 751 1120",
    "sg:postcode":"72762",
    "sg:province":"AR",
    "sg:tags":[
        "rug"
    ],
    "wof:name":"Carpet Smart Smart",
    "wof:placetype":"venue"
},
  "geometry": {"coordinates":[-94.191764,36.175534],"type":"Point"}
}