{
  "type": "Feature",
  "properties": {
    "iso:country":"US",
    "sg:address":"4408 W Hepburn St",
    "sg:city":"Pine Bluff",
    "sg:classifiers":[
        {
            "category":"Building & Trades",
            "subcategory":"Plumbing",
            "type":"Services"
        }
    ],
    "sg:phone":"+1 870 536 5217",
    "sg:postcode":"71603",
    "sg:province":"AR",
    "sg:tags":[
        "plumbing",
        "contractor"
    ],
    "wof:name":"J J's Plumbing Of Pine Bluff",
    "wof:placetype":"venue"
},
  "geometry": {"coordinates":[-92.051088,34.218082],"type":"Point"}
}