{
  "type": "Feature",
  "properties": {
    "iso:country":"US",
    "sg:address":"17200 Chenal Pkwy",
    "sg:city":"Little Rock",
    "sg:classifiers":[
        {
            "category":"Building & Trades",
            "subcategory":"Construction",
            "type":"Services"
        }
    ],
    "sg:phone":"+1 501 951 3361",
    "sg:postcode":"72223",
    "sg:province":"AR",
    "sg:tags":[
        "handyman"
    ],
    "wof:name":"Home Handyman",
    "wof:placetype":"venue"
},
  "geometry": {"coordinates":[-92.462909,34.777364],"type":"Point"}
}