{
  "type": "Feature",
  "properties": {
    "iso:country":"US",
    "sg:address":"4137 John F Kennedy Blvd",
    "sg:city":"Sherwood",
    "sg:classifiers":[
        {
            "category":"Health Services",
            "subcategory":"Doctor",
            "type":"Services"
        }
    ],
    "sg:phone":"+1 501 753 2700",
    "sg:postcode":"72116",
    "sg:province":"AR",
    "sg:tags":[
        "dentist"
    ],
    "wof:name":"Danny R Cook DDS",
    "wof:placetype":"venue"
},
  "geometry": {"coordinates":[-92.257954,34.793639],"type":"Point"}
}