{
  "type": "Feature",
  "properties": {
    "addr:full":"3606 Southview Dr Fort Smith AR 72903",
    "addr:housenumber":"3606",
    "addr:postcode":"72903",
    "addr:street":"Southview Dr",
    "iso:country":"US",
    "sg:address":"3606 Southview Dr",
    "sg:city":"Fort Smith",
    "sg:classifiers":[
        {
            "category":"Social Services",
            "type":"Services"
        }
    ],
    "sg:phone":"+1 479 782 8823",
    "sg:postcode":"72903",
    "sg:province":"AR",
    "sg:tags":[
        "counselor",
        "marriage",
        "family"
    ],
    "wof:name":"Hagemeier Family Counseling",
    "wof:placetype":"venue"
},
  "geometry": {"coordinates":[-94.397397,35.34039],"type":"Point"}
}