{
  "type": "Feature",
  "properties": {
    "addr:full":"100 S 2nd St Ozark AR 72949",
    "addr:housenumber":"100",
    "addr:postcode":"72949",
    "addr:street":"S 2Nd St",
    "iso:country":"US",
    "sg:address":"100 S 2nd St",
    "sg:city":"Ozark",
    "sg:classifiers":[
        {
            "category":"Professional",
            "type":"Services"
        }
    ],
    "sg:phone":"+1 479 667 3474",
    "sg:postcode":"72949",
    "sg:province":"AR",
    "wof:name":"Satellites & More",
    "wof:placetype":"venue"
},
  "geometry": {"coordinates":[-93.82638,35.48605],"type":"Point"}
}