{
  "type": "Feature",
  "properties": {
    "iso:country":"US",
    "sg:address":"51 Old Hwy 25",
    "sg:city":"Tumbling Shoals",
    "sg:classifiers":[
        {
            "category":"Banks & Credit Unions",
            "subcategory":"Financial Services",
            "type":"Services"
        }
    ],
    "sg:phone":"+1 501 250 1460",
    "sg:postcode":"72581",
    "sg:province":"AR",
    "sg:tags":[
        "investor"
    ],
    "wof:name":"Lake Area Investments LLC",
    "wof:placetype":"venue"
},
  "geometry": {"coordinates":[-91.983088,35.546045],"type":"Point"}
}