{
  "type": "Feature",
  "properties": {
    "iso:country":"US",
    "sg:address":"116 S 2nd St",
    "sg:city":"Ozark",
    "sg:classifiers":[
        {
            "category":"Government",
            "subcategory":"Court House",
            "type":"Public Place"
        }
    ],
    "sg:phone":"+1 479 667 4808",
    "sg:postcode":"72949",
    "sg:province":"AR",
    "sg:tags":[
        "city"
    ],
    "wof:name":"Ozark District Court",
    "wof:placetype":"venue"
},
  "geometry": {"coordinates":[-93.826289,35.486156],"type":"Point"}
}