{
  "type": "Feature",
  "properties": {
    "iso:country":"US",
    "sg:address":"4622 Camp Robinson Rd",
    "sg:city":"N Little Rock",
    "sg:classifiers":[
        {
            "category":"Autos & Motor Vehicles",
            "subcategory":"Fuel & Gas Station",
            "type":"Retail Goods"
        }
    ],
    "sg:phone":"+1 501 753 5221",
    "sg:postcode":"72118",
    "sg:province":"AR",
    "sg:tags":[
        "oil"
    ],
    "wof:name":"Shell Superstop",
    "wof:placetype":"venue"
},
  "geometry": {"coordinates":[-92.270956,34.79537],"type":"Point"}
}