{
  "type": "Feature",
  "properties": {
    "iso:country":"US",
    "sg:address":"9381 State Hwy 135",
    "sg:city":"Caraway",
    "sg:classifiers":[
        {
            "category":"Autos & Motor Vehicles",
            "subcategory":"Automobile Sales",
            "type":"Retail Goods"
        }
    ],
    "sg:phone":"+1 870 482 3097",
    "sg:postcode":"72419",
    "sg:province":"AR",
    "sg:tags":[
        "car",
        "used",
        "dealer"
    ],
    "wof:name":"Austin Auto Sales & Salvage",
    "wof:placetype":"venue"
},
  "geometry": {"coordinates":[-90.3404,35.712738],"type":"Point"}
}