{
  "type": "Feature",
  "properties": {
    "iso:country":"US",
    "sg:address":"1410 Lindberg St",
    "sg:city":"Texarkana",
    "sg:classifiers":[
        {
            "category":"Professional",
            "type":"Services"
        }
    ],
    "sg:phone":"+1 870 772 7577",
    "sg:postcode":"71854",
    "sg:province":"AR",
    "wof:name":"Samantha Davis",
    "wof:placetype":"venue"
},
  "geometry": {"coordinates":[-94.04146299999999,33.408501],"type":"Point"}
}