{
  "type": "Feature",
  "properties": {
    "iso:country":"US",
    "sg:address":"119 Summer Leigh St",
    "sg:city":"Bay",
    "sg:classifiers":[
        {
            "category":"Organizations",
            "subcategory":"Religious Organization",
            "type":"Services"
        }
    ],
    "sg:phone":"+1 870 781 3721",
    "sg:postcode":"72411",
    "sg:province":"AR",
    "sg:tags":[
        "church"
    ],
    "wof:name":"Broadway Baptist Church",
    "wof:placetype":"venue"
},
  "geometry": {"coordinates":[-90.563574,35.740678],"type":"Point"}
}