{
  "type": "Feature",
  "properties": {
    "addr:full":"1327 E Main St Russellville AR 72801",
    "addr:housenumber":"1327",
    "addr:postcode":"72801",
    "addr:street":"E Main St",
    "iso:country":"US",
    "sg:address":"1327 E Main St",
    "sg:city":"Russellville",
    "sg:classifiers":[
        {
            "category":"Autos & Motor Vehicles",
            "subcategory":"Automobile Sales",
            "type":"Retail Goods"
        }
    ],
    "sg:phone":"+1 479 967 0850",
    "sg:postcode":"72801",
    "sg:province":"AR",
    "sg:tags":[
        "car",
        "used",
        "dealer"
    ],
    "wof:name":"Hunnicutt's Auto Sales",
    "wof:placetype":"venue"
},
  "geometry": {"coordinates":[-93.11742700000001,35.278483],"type":"Point"}
}