{
  "type": "Feature",
  "properties": {
    "addr:full":"7340 Amelia Rd Benton AR 72015",
    "addr:housenumber":"7340",
    "addr:postcode":"72015",
    "addr:street":"Amelia Rd",
    "iso:country":"US",
    "sg:address":"7340 Amelia Rd",
    "sg:city":"Benton",
    "sg:classifiers":[
        {
            "category":"Professional",
            "type":"Services"
        }
    ],
    "sg:phone":"+1 501 316 1971",
    "sg:postcode":"72015",
    "sg:province":"AR",
    "wof:name":"Designed Events Inc",
    "wof:placetype":"venue"
},
  "geometry": {"coordinates":[-92.568146,34.631712],"type":"Point"}
}