{
  "type": "Feature",
  "properties": {
    "addr:full":"5512 S 66th St Fort Smith AR 72903",
    "addr:housenumber":"5512",
    "addr:postcode":"72903",
    "addr:street":"S 66Th St",
    "iso:country":"US",
    "sg:address":"5512 S 66th St",
    "sg:city":"Fort Smith",
    "sg:classifiers":[
        {
            "category":"Wholesale",
            "subcategory":"Metals & Minerals",
            "type":"Manufacturing & Wholesale Goods"
        }
    ],
    "sg:phone":"+1 479 646 9274",
    "sg:postcode":"72903",
    "sg:province":"AR",
    "sg:tags":[
        "copper",
        "product"
    ],
    "wof:name":"Copperfab",
    "wof:placetype":"venue"
},
  "geometry": {"coordinates":[-94.36076799999999,35.328111],"type":"Point"}
}