{
  "type": "Feature",
  "properties": {
    "iso:country":"US",
    "sg:address":"419 W Rock St",
    "sg:city":"Fayetteville",
    "sg:classifiers":[
        {
            "category":"Organizations",
            "subcategory":"Non-profit Organization",
            "type":"Services"
        }
    ],
    "sg:phone":"+1 479 575 9696",
    "sg:postcode":"72701",
    "sg:province":"AR",
    "wof:name":"Habitat For Humanity",
    "wof:placetype":"venue"
},
  "geometry": {"coordinates":[-94.165395,36.060901],"type":"Point"}
}