{
  "type": "Feature",
  "properties": {
    "addr:full":"2225 Springview Rd Pocahontas AR 72455",
    "addr:housenumber":"2225",
    "addr:postcode":"72455",
    "addr:street":"Springview Rd",
    "iso:country":"US",
    "sg:address":"2225 Springview Rd",
    "sg:city":"Pocahontas",
    "sg:classifiers":[
        {
            "category":"Building & Trades",
            "subcategory":"Construction",
            "type":"Services"
        }
    ],
    "sg:phone":"+1 870 892 9136",
    "sg:postcode":"72455",
    "sg:province":"AR",
    "sg:tags":[
        "house"
    ],
    "wof:name":"Jansens Home Improvements",
    "wof:placetype":"venue"
},
  "geometry": {"coordinates":[-91.014211,36.321982],"type":"Point"}
}