{
  "type": "Feature",
  "properties": {
    "iso:country":"US",
    "sg:address":"426 Polk St N",
    "sg:city":"Mena",
    "sg:classifiers":[
        {
            "category":"Wholesale",
            "subcategory":"Auto Parts",
            "type":"Manufacturing & Wholesale Goods"
        }
    ],
    "sg:phone":"+1 479 394 1918",
    "sg:postcode":"71953",
    "sg:province":"AR",
    "wof:name":"Many Supplies",
    "wof:placetype":"venue"
},
  "geometry": {"coordinates":[-94.251396,34.590729],"type":"Point"}
}