{
  "type": "Feature",
  "properties": {
    "iso:country":"US",
    "sg:address":"3809 W Stagecoach Rd",
    "sg:city":"Jefferson",
    "sg:classifiers":[
        {
            "category":"Building & Trades",
            "subcategory":"Landscaping Services",
            "type":"Services"
        }
    ],
    "sg:phone":"+1 501 397 5182",
    "sg:postcode":"72079",
    "sg:province":"AR",
    "sg:tags":[
        "landscape",
        "contractor"
    ],
    "wof:name":"Arkansas Native Stone",
    "wof:placetype":"venue"
},
  "geometry": {"coordinates":[-92.174572,34.38027],"type":"Point"}
}