{
  "type": "Feature",
  "properties": {
    "iso:country":"US",
    "sg:address":"94 State Hwy 109",
    "sg:city":"Magazine",
    "sg:classifiers":[
        {
            "category":"Wholesale",
            "subcategory":"Electrical",
            "type":"Manufacturing & Wholesale Goods"
        }
    ],
    "sg:phone":"+1 479 969 6178",
    "sg:postcode":"72943",
    "sg:province":"AR",
    "sg:tags":[
        "electric",
        "motor"
    ],
    "wof:name":"Jernie Motor Co",
    "wof:placetype":"venue"
},
  "geometry": {"coordinates":[-93.80613,35.149896],"type":"Point"}
}