{
  "type": "Feature",
  "properties": {
    "addr:full":"1104 Jones Rd Booneville AR 72927",
    "addr:housenumber":"1104",
    "addr:postcode":"72927",
    "addr:street":"Jones Rd",
    "iso:country":"US",
    "sg:address":"1104 Jones Rd",
    "sg:city":"Booneville",
    "sg:classifiers":[
        {
            "category":"Professional",
            "subcategory":"Engineering",
            "type":"Services"
        }
    ],
    "sg:phone":"+1 870 236 5736",
    "sg:postcode":"72927",
    "sg:province":"AR",
    "sg:tags":[
        "engineer"
    ],
    "wof:name":"Centex Engineering & Constr",
    "wof:placetype":"venue"
},
  "geometry": {"coordinates":[-93.945046,35.149439],"type":"Point"}
}