{
  "type": "Feature",
  "properties": {
    "addr:full":"421 Lee Road 159 Moro AR 72368",
    "addr:housenumber":"421",
    "addr:postcode":"72368",
    "addr:street":"Lee Road 159 Moro",
    "iso:country":"US",
    "sg:address":"421 Lee Road 159",
    "sg:city":"Moro",
    "sg:classifiers":[
        {
            "category":"Farming",
            "subcategory":"Farm",
            "type":"Manufacturing & Wholesale Goods"
        }
    ],
    "sg:phone":"+1 870 768 4292",
    "sg:postcode":"72368",
    "sg:province":"AR",
    "sg:tags":[
        "crop",
        "general"
    ],
    "wof:name":"Black Swamp Farms Inc",
    "wof:placetype":"venue"
},
  "geometry": {"coordinates":[-90.953208,34.745184],"type":"Point"}
}