{
  "type": "Feature",
  "properties": {
    "iso:country":"US",
    "sg:address":"201 US Hwy 64 Bus",
    "sg:city":"Alma",
    "sg:classifiers":[
        {
            "category":"Wholesale",
            "subcategory":"Hardware",
            "type":"Manufacturing & Wholesale Goods"
        }
    ],
    "sg:phone":"+1 479 632 4313",
    "sg:postcode":"72921",
    "sg:province":"AR",
    "sg:tags":[
        "plumbing",
        "fixture",
        "supply"
    ],
    "wof:name":"Triangle Supply Co",
    "wof:placetype":"venue"
},
  "geometry": {"coordinates":[-94.224176,35.480591],"type":"Point"}
}