{
  "type": "Feature",
  "properties": {
    "iso:country":"US",
    "sg:address":"1609 East St",
    "sg:city":"Texarkana",
    "sg:classifiers":[
        {
            "category":"Autos & Motor Vehicles",
            "subcategory":"Auto Supplies",
            "type":"Retail Goods"
        },
        {
            "category":"Wholesale",
            "subcategory":"Auto Parts",
            "type":"Manufacturing & Wholesale Goods"
        }
    ],
    "sg:phone":"+1 870 774 7313",
    "sg:postcode":"71854",
    "sg:province":"TX",
    "sg:tags":[
        "tire"
    ],
    "wof:name":"Dave's Used Tires",
    "wof:placetype":"venue"
},
  "geometry": {"coordinates":[-94.030392,33.406553],"type":"Point"}
}