{
  "type": "Feature",
  "properties": {
    "addr:full":"1106 Walnut St Van Buren AR 72956",
    "addr:housenumber":"1106",
    "addr:postcode":"72956",
    "addr:street":"Walnut St",
    "iso:country":"US",
    "sg:address":"1106 Walnut St",
    "sg:city":"Van Buren",
    "sg:classifiers":[
        {
            "category":"Home & Garden",
            "subcategory":"Furniture",
            "type":"Retail Goods"
        }
    ],
    "sg:phone":"+1 479 410 1970",
    "sg:postcode":"72956",
    "sg:province":"AR",
    "wof:name":"Odom Jim Furniture",
    "wof:placetype":"venue"
},
  "geometry": {"coordinates":[-94.347092,35.435623],"type":"Point"}
}