{
  "type": "Feature",
  "properties": {
    "iso:country":"US",
    "sg:address":"7217 Ohio St",
    "sg:city":"Little Rock",
    "sg:classifiers":[
        {
            "category":"Education",
            "subcategory":"School",
            "type":"Public Place"
        }
    ],
    "sg:phone":"+1 501 663 6631",
    "sg:postcode":"72207",
    "sg:province":"AR",
    "wof:name":"Montessori School Tanglewood",
    "wof:placetype":"venue"
},
  "geometry": {"coordinates":[-92.35589899999999,34.768988],"type":"Point"}
}