{
  "type": "Feature",
  "properties": {
    "iso:country":"US",
    "sg:address":"212 Main St",
    "sg:city":"Traskwood",
    "sg:classifiers":[
        {
            "category":"Government",
            "subcategory":"Office",
            "type":"Public Place"
        }
    ],
    "sg:phone":"+1 501 860 6277",
    "sg:postcode":"72167",
    "sg:province":"AR",
    "sg:tags":[
        "city"
    ],
    "wof:name":"Traskwood City Hall",
    "wof:placetype":"venue"
},
  "geometry": {"coordinates":[-92.653879,34.449178],"type":"Point"}
}