{
  "type": "Feature",
  "properties": {
    "iso:country":"US",
    "sg:address":"415 W 12th St",
    "sg:city":"Little Rock",
    "sg:classifiers":[
        {
            "category":"Organizations",
            "subcategory":"Labor Organization",
            "type":"Services"
        }
    ],
    "sg:phone":"+1 501 372 5150",
    "sg:postcode":"72202",
    "sg:province":"AR",
    "wof:name":"Sheet Metal Workers",
    "wof:placetype":"venue"
},
  "geometry": {"coordinates":[-92.276488,34.737761],"type":"Point"}
}