{
  "type": "Feature",
  "properties": {
    "addr:full":"1606 War Eagle Dr Pine Bluff AR 71603",
    "addr:housenumber":"1606",
    "addr:postcode":"71603",
    "addr:street":"War Eagle Dr",
    "iso:country":"US",
    "sg:address":"1606 War Eagle Dr",
    "sg:city":"Pine Bluff",
    "sg:classifiers":[
        {
            "category":"Retail",
            "subcategory":"Laundry & Dry Cleaning",
            "type":"Services"
        }
    ],
    "sg:phone":"+1 870 534 2929",
    "sg:postcode":"71603",
    "sg:province":"AR",
    "sg:tags":[
        "cleaners",
        "rug",
        "carpet"
    ],
    "wof:name":"Promarc Carpet Care Inc",
    "wof:placetype":"venue"
},
  "geometry": {"coordinates":[-92.021399,34.158608],"type":"Point"}
}