{
  "type": "Feature",
  "properties": {
    "iso:country":"US",
    "sg:address":"322 State Hwy 18",
    "sg:city":"Manila",
    "sg:classifiers":[
        {
            "category":"Health Services",
            "subcategory":"Doctor",
            "type":"Services"
        }
    ],
    "sg:phone":"+1 870 561 4400",
    "sg:postcode":"72442",
    "sg:province":"AR",
    "sg:tags":[
        "dentist"
    ],
    "wof:name":"Bruce T Wilson DDS",
    "wof:placetype":"venue"
},
  "geometry": {"coordinates":[-90.16990699999999,35.872854],"type":"Point"}
}