{
  "type": "Feature",
  "properties": {
    "iso:country":"US",
    "sg:address":"1090 Hwy 65 N",
    "sg:city":"Conway",
    "sg:classifiers":[
        {
            "category":"Restaurant",
            "type":"Food & Drink"
        }
    ],
    "sg:phone":"+1 501 697 3885",
    "sg:postcode":"72032",
    "sg:province":"AR",
    "sg:tags":[
        "caterer"
    ],
    "wof:name":"Your Place Catering",
    "wof:placetype":"venue"
},
  "geometry": {"coordinates":[-92.439264,35.1111],"type":"Point"}
}