{
  "type": "Feature",
  "properties": {
    "iso:country":"US",
    "sg:address":"516 N Boyd St",
    "sg:city":"Monticello",
    "sg:classifiers":[
        {
            "category":"Insurance",
            "subcategory":"Hazard Insurance",
            "type":"Services"
        }
    ],
    "sg:phone":"+1 870 367 9424",
    "sg:postcode":"71655",
    "sg:province":"AR",
    "wof:name":"Sandra Parker Davis",
    "wof:placetype":"venue"
},
  "geometry": {"coordinates":[-91.794239,33.631288],"type":"Point"}
}