{
  "type": "Feature",
  "properties": {
    "addr:full":"10201 W Markham St Little Rock AR 72205",
    "addr:housenumber":"10201",
    "addr:postcode":"72205",
    "addr:street":"W Markham St",
    "iso:country":"US",
    "sg:address":"10201 W Markham St",
    "sg:city":"Little Rock",
    "sg:classifiers":[
        {
            "category":"Wholesale",
            "subcategory":"Electrical",
            "type":"Manufacturing & Wholesale Goods"
        }
    ],
    "sg:phone":"+1 501 954 7233",
    "sg:postcode":"72205",
    "sg:province":"AR",
    "sg:tags":[
        "fire",
        "equipment",
        "protection"
    ],
    "wof:name":"Safety Professional Inc",
    "wof:placetype":"venue"
},
  "geometry": {"coordinates":[-92.387998,34.753709],"type":"Point"}
}