{
  "type": "Feature",
  "properties": {
    "addr:full":"210 E 39th St Russellville AR 72802",
    "addr:housenumber":"210",
    "addr:postcode":"72802",
    "addr:street":"E 39Th St",
    "iso:country":"US",
    "sg:address":"210 E 39th St",
    "sg:city":"Russellville",
    "sg:classifiers":[
        {
            "category":"Manufacturing",
            "subcategory":"Metals",
            "type":"Manufacturing & Wholesale Goods"
        }
    ],
    "sg:phone":"+1 479 967 6008",
    "sg:postcode":"72802",
    "sg:province":"AR",
    "sg:tags":[
        "metal-wholesale",
        "manufacturer"
    ],
    "wof:name":"Phoenix Metals Company",
    "wof:placetype":"venue"
},
  "geometry": {"coordinates":[-93.136087,35.237855],"type":"Point"}
}