{
  "type": "Feature",
  "properties": {
    "addr:full":"1575 Grays Ave Batesville AR 72501",
    "addr:housenumber":"1575",
    "addr:postcode":"72501",
    "addr:street":"Grays Ave",
    "iso:country":"US",
    "sg:address":"1575 Grays Ave",
    "sg:city":"Batesville",
    "sg:classifiers":[
        {
            "category":"Real Estate",
            "subcategory":"Developer",
            "type":"Services"
        }
    ],
    "sg:phone":"+1 870 698 2432",
    "sg:postcode":"72501",
    "sg:province":"AR",
    "sg:tags":[
        "cemetery"
    ],
    "wof:name":"Cemetery Maintenance Shop",
    "wof:placetype":"venue"
},
  "geometry": {"coordinates":[-91.637643,35.765594],"type":"Point"}
}