{
  "type": "Feature",
  "properties": {
    "addr:full":"13521 Degraff Rd Rogers AR 72756",
    "addr:housenumber":"13521",
    "addr:postcode":"72756",
    "addr:street":"Degraff Rd",
    "iso:country":"US",
    "sg:address":"13521 Degraff Rd",
    "sg:city":"Rogers",
    "sg:classifiers":[
        {
            "category":"Communications",
            "type":"Services"
        }
    ],
    "sg:phone":"+1 479 451 8836",
    "sg:postcode":"72756",
    "sg:province":"AR",
    "sg:tags":[
        "communication"
    ],
    "wof:name":"Thunderlink Communications",
    "wof:placetype":"venue"
},
  "geometry": {"coordinates":[-94.061615,36.429077],"type":"Point"}
}