{
  "type": "Feature",
  "properties": {
    "iso:country":"US",
    "sg:address":"1500 Dodson Ave",
    "sg:city":"Fort Smith",
    "sg:classifiers":[
        {
            "category":"Health Services",
            "subcategory":"Medical Lab",
            "type":"Services"
        }
    ],
    "sg:phone":"+1 479 784 6607",
    "sg:postcode":"72901",
    "sg:province":"AR",
    "sg:tags":[
        "laboratory"
    ],
    "wof:name":"Quest Diagnostics",
    "wof:placetype":"venue"
},
  "geometry": {"coordinates":[-94.416659,35.372433],"type":"Point"}
}