{
  "type": "Feature",
  "properties": {
    "iso:country":"US",
    "sg:address":"1072 Bluegrass Dr",
    "sg:city":"Benton",
    "sg:classifiers":[
        {
            "category":"Building & Trades",
            "subcategory":"Plumbing",
            "type":"Services"
        }
    ],
    "sg:phone":"+1 501 316 1502",
    "sg:postcode":"72015",
    "sg:province":"AR",
    "sg:tags":[
        "plumbing",
        "contractor"
    ],
    "wof:name":"Tim Griggs Plumbing Company",
    "wof:placetype":"venue"
},
  "geometry": {"coordinates":[-92.693771,34.609892],"type":"Point"}
}