{
  "type": "Feature",
  "properties": {
    "addr:full":"2200 S 13th St Rogers AR 72758",
    "addr:housenumber":"2200",
    "addr:postcode":"72758",
    "addr:street":"S 13Th St",
    "iso:country":"US",
    "sg:address":"2200 S 13th St",
    "sg:city":"Rogers",
    "sg:classifiers":[
        {
            "category":"Organizations",
            "subcategory":"Religious Organization",
            "type":"Services"
        }
    ],
    "sg:phone":"+1 479 636 5889",
    "sg:postcode":"72758",
    "sg:province":"AR",
    "sg:tags":[
        "church"
    ],
    "sg:website":"www.rogersupc.org",
    "wof:name":"First United Pentecostal Chr",
    "wof:placetype":"venue"
},
  "geometry": {"coordinates":[-94.135571,36.303907],"type":"Point"}
}