{
  "type": "Feature",
  "properties": {
    "addr:full":"278 Jacoway Ln Hot Springs National Park AR 71913",
    "addr:housenumber":"278",
    "addr:postcode":"71913",
    "addr:street":"Jacoway Ln",
    "iso:country":"US",
    "sg:address":"278 Jacoway Ln",
    "sg:city":"Hot Springs National Park",
    "sg:classifiers":[
        {
            "category":"Professional",
            "type":"Services"
        }
    ],
    "sg:phone":"+1 501 767 2909",
    "sg:postcode":"71913",
    "sg:province":"AR",
    "wof:name":"Susie Foiles",
    "wof:placetype":"venue"
},
  "geometry": {"coordinates":[-93.180502,34.515294],"type":"Point"}
}