{
  "type": "Feature",
  "properties": {
    "iso:country":"US",
    "sg:address":"101 Glenridge Ct",
    "sg:city":"Hot Springs National",
    "sg:classifiers":[
        {
            "category":"Real Estate",
            "subcategory":"Real Estate Agent",
            "type":"Services"
        }
    ],
    "sg:phone":"+1 501 624 3621",
    "sg:postcode":"71901",
    "sg:province":"AR",
    "wof:name":"Bbk Properties Inc",
    "wof:placetype":"venue"
},
  "geometry": {"coordinates":[-93.02739,34.468921],"type":"Point"}
}