{
  "type": "Feature",
  "properties": {
    "iso:country":"US",
    "sg:address":"4782 Hwy 232",
    "sg:city":"England",
    "sg:classifiers":[
        {
            "category":"Farming",
            "subcategory":"Farm",
            "type":"Manufacturing & Wholesale Goods"
        }
    ],
    "sg:phone":"+1 501 676 5918",
    "sg:postcode":"72046",
    "sg:province":"AR",
    "sg:tags":[
        "livestock",
        "crop",
        "general"
    ],
    "wof:name":"Silver Lease Plantation",
    "wof:placetype":"venue"
},
  "geometry": {"coordinates":[-91.811256,34.601321],"type":"Point"}
}