{
  "type": "Feature",
  "properties": {
    "addr:full":"128 S Hervey St Hope AR 71801",
    "addr:housenumber":"128",
    "addr:postcode":"71801",
    "addr:street":"S Hervey St",
    "iso:country":"US",
    "sg:address":"128 S Hervey St",
    "sg:city":"Hope",
    "sg:classifiers":[
        {
            "category":"Restaurant",
            "type":"Food & Drink"
        }
    ],
    "sg:menulink":"http://www.allmenus.com/ar/de-roan/231688-sonic/menu/",
    "sg:phone":"+1 870 777 4205",
    "sg:postcode":"71801",
    "sg:province":"AR",
    "sg:tags":[
        "burger",
        "american"
    ],
    "wof:name":"Sonic",
    "wof:placetype":"venue"
},
  "geometry": {"coordinates":[-93.596737,33.667517],"type":"Point"}
}