{
  "type": "Feature",
  "properties": {
    "addr:full":"1700 N Locust St N Little Rock AR 72114",
    "addr:housenumber":"1700",
    "addr:postcode":"72114",
    "addr:street":"N Locust St N",
    "iso:country":"US",
    "sg:address":"1700 N Locust St",
    "sg:city":"N Little Rock",
    "sg:classifiers":[
        {
            "category":"Social Services",
            "subcategory":"Child Care",
            "type":"Services"
        }
    ],
    "sg:phone":"+1 501 791 9655",
    "sg:postcode":"72114",
    "sg:province":"AR",
    "sg:tags":[
        "day"
    ],
    "wof:name":"Not Home Alone Daycare",
    "wof:placetype":"venue"
},
  "geometry": {"coordinates":[-92.261178,34.771854],"type":"Point"}
}