{
  "type": "Feature",
  "properties": {
    "addr:full":"8885 US Hwy 79 Pine Bluff AR 71603",
    "addr:housenumber":"8885",
    "addr:postcode":"71603",
    "addr:street":"Us Hwy 79",
    "iso:country":"US",
    "sg:address":"8885 US Hwy 79",
    "sg:city":"Pine Bluff",
    "sg:classifiers":[
        {
            "category":"Food & Beverages",
            "subcategory":"Groceries & Convenience Stores",
            "type":"Retail Goods"
        }
    ],
    "sg:phone":"+1 870 879 3571",
    "sg:postcode":"71603",
    "sg:province":"AR",
    "sg:tags":[
        "station",
        "gasoline"
    ],
    "wof:name":"D J's One Stop",
    "wof:placetype":"venue"
},
  "geometry": {"coordinates":[-92.12460900000001,34.125517],"type":"Point"}
}