{
  "type": "Feature",
  "properties": {
    "iso:country":"US",
    "sg:address":"117 N 9th St",
    "sg:city":"Rogers",
    "sg:classifiers":[
        {
            "category":"Personal",
            "subcategory":"Beauty Salon",
            "type":"Services"
        }
    ],
    "sg:phone":"+1 479 636 5336",
    "sg:postcode":"72756",
    "sg:province":"AR",
    "sg:tags":[
        "shop"
    ],
    "wof:name":"Elegante Hair Unlimited",
    "wof:placetype":"venue"
},
  "geometry": {"coordinates":[-94.126878,36.334288],"type":"Point"}
}