{
  "type": "Feature",
  "properties": {
    "iso:country":"US",
    "sg:address":"189 Lee Ln",
    "sg:city":"De Queen",
    "sg:classifiers":[
        {
            "category":"Farming",
            "subcategory":"Farm",
            "type":"Manufacturing & Wholesale Goods"
        }
    ],
    "sg:phone":"+1 870 642 3428",
    "sg:postcode":"71832",
    "sg:province":"AR",
    "sg:tags":[
        "crop",
        "general"
    ],
    "wof:name":"Charles & Sandra Lee",
    "wof:placetype":"venue"
},
  "geometry": {"coordinates":[-94.31683099999999,34.104346],"type":"Point"}
}