{
  "type": "Feature",
  "properties": {
    "iso:country":"US",
    "sg:address":"5823 Oakbrook Rd",
    "sg:city":"Alexander",
    "sg:classifiers":[
        {
            "category":"Building & Trades",
            "subcategory":"Cleaning & Sanitation",
            "type":"Services"
        }
    ],
    "sg:phone":"+1 501 847 0733",
    "sg:postcode":"72002",
    "sg:province":"AR",
    "sg:tags":[
        "ceiling"
    ],
    "wof:name":"Kimarc Ceiling Inc",
    "wof:placetype":"venue"
},
  "geometry": {"coordinates":[-92.487138,34.646329],"type":"Point"}
}