{
  "type": "Feature",
  "properties": {
    "iso:country":"US",
    "sg:address":"2213 N Reynolds Rd",
    "sg:city":"Bryant",
    "sg:classifiers":[
        {
            "category":"Wholesale",
            "subcategory":"Machinery & Supplies",
            "type":"Manufacturing & Wholesale Goods"
        }
    ],
    "sg:phone":"+1 501 653 2884",
    "sg:postcode":"72022",
    "sg:province":"AR",
    "sg:tags":[
        "compressor",
        "industrial",
        "gas",
        "equipment"
    ],
    "wof:name":"Kitchens Industrial Equipment",
    "wof:placetype":"venue"
},
  "geometry": {"coordinates":[-92.495834,34.611609],"type":"Point"}
}