{
  "type": "Feature",
  "properties": {
    "iso:country":"US",
    "sg:address":"204 S Main St",
    "sg:city":"Leachville",
    "sg:classifiers":[
        {
            "category":"Insurance",
            "subcategory":"Insurance Agent",
            "type":"Services"
        }
    ],
    "sg:phone":"+1 870 539 6403",
    "sg:postcode":"72438",
    "sg:province":"AR",
    "wof:name":"General Insurance",
    "wof:placetype":"venue"
},
  "geometry": {"coordinates":[-90.257976,35.936647],"type":"Point"}
}