{
  "type": "Feature",
  "properties": {
    "iso:country":"US",
    "sg:address":"505 S Cleveland St",
    "sg:city":"Wynne",
    "sg:classifiers":[
        {
            "category":"Building & Trades",
            "subcategory":"Pest Control",
            "type":"Services"
        }
    ],
    "sg:phone":"+1 870 238 2144",
    "sg:postcode":"72396",
    "sg:province":"AR",
    "wof:name":"Will-Kill Termite & Pest Cntrl",
    "wof:placetype":"venue"
},
  "geometry": {"coordinates":[-90.791487,35.220778],"type":"Point"}
}