{
  "type": "Feature",
  "properties": {
    "addr:full":"701 Green Mountain Dr Little Rock AR 72211",
    "addr:housenumber":"701",
    "addr:postcode":"72211",
    "addr:street":"Green Mountain Dr",
    "iso:country":"US",
    "sg:address":"701 Green Mountain Dr",
    "sg:city":"Little Rock",
    "sg:classifiers":[
        {
            "category":"Professional",
            "subcategory":"Computer Services",
            "type":"Services"
        }
    ],
    "sg:phone":"+1 501 228 5249",
    "sg:postcode":"72211",
    "sg:province":"AR",
    "sg:tags":[
        "prepackaged",
        "software"
    ],
    "wof:name":"Bw Software LLC",
    "wof:placetype":"venue"
},
  "geometry": {"coordinates":[-92.401366,34.759866],"type":"Point"}
}