{
  "type": "Feature",
  "properties": {
    "iso:country":"US",
    "sg:address":"1226 Laura Ave",
    "sg:city":"Berryville",
    "sg:classifiers":[
        {
            "category":"Autos & Motor Vehicles",
            "subcategory":"Automobile Sales",
            "type":"Retail Goods"
        }
    ],
    "sg:phone":"+1 870 423 3697",
    "sg:postcode":"72616",
    "sg:province":"AR",
    "wof:name":"Merriman Motors Co",
    "wof:placetype":"venue"
},
  "geometry": {"coordinates":[-93.55080599999999,36.367595],"type":"Point"}
}