{
  "type": "Feature",
  "properties": {
    "addr:full":"401 President Clinton Ave Little Rock AR 72201",
    "addr:housenumber":"401",
    "addr:postcode":"72201",
    "addr:street":"President Clinton Ave",
    "iso:country":"US",
    "sg:address":"401 President Clinton Ave",
    "sg:city":"Little Rock",
    "sg:classifiers":[
        {
            "category":"Restaurant",
            "type":"Food & Drink"
        },
        {
            "category":"Food & Beverages",
            "subcategory":"Meat & Fish",
            "type":"Retail Goods"
        }
    ],
    "sg:menulink":"http://www.allmenus.com/ar/little-rock/255128-shaka-smoke-lodge/menu/",
    "sg:phone":"+1 501 372 7756",
    "sg:postcode":"72201",
    "sg:province":"AR",
    "sg:tags":[
        "american"
    ],
    "wof:name":"Shaka Smoke Lodge",
    "wof:placetype":"venue"
},
  "geometry": {"coordinates":[-92.266671,34.747604],"type":"Point"}
}