{
  "type": "Feature",
  "properties": {
    "iso:country":"US",
    "sg:address":"207 S Knoxville Ave",
    "sg:city":"Russellville",
    "sg:classifiers":[
        {
            "category":"Wholesale",
            "subcategory":"Farm Supplies",
            "type":"Manufacturing & Wholesale Goods"
        }
    ],
    "sg:phone":"+1 479 968 1662",
    "sg:postcode":"72802",
    "sg:province":"AR",
    "sg:tags":[
        "feed"
    ],
    "wof:name":"Price Milling Co",
    "wof:placetype":"venue"
},
  "geometry": {"coordinates":[-93.120398,35.277069],"type":"Point"}
}