{
  "type": "Feature",
  "properties": {
    "iso:country":"US",
    "sg:address":"12166 US Hwy 62 Scn",
    "sg:city":"Farmington",
    "sg:classifiers":[
        {
            "category":"Autos & Motor Vehicles",
            "subcategory":"Automobile Sales",
            "type":"Retail Goods"
        }
    ],
    "sg:phone":"+1 479 267 3500",
    "sg:postcode":"72730",
    "sg:province":"AR",
    "sg:tags":[
        "car",
        "dealer"
    ],
    "wof:name":"Hedgehogs Auto World",
    "wof:placetype":"venue"
},
  "geometry": {"coordinates":[-94.263041,36.033614],"type":"Point"}
}