{
  "type": "Feature",
  "properties": {
    "addr:full":"381 Pippin Cir Conway AR 72034",
    "addr:housenumber":"381",
    "addr:postcode":"72034",
    "addr:street":"Pippin Cir",
    "iso:country":"US",
    "sg:address":"381 Pippin Cir",
    "sg:city":"Conway",
    "sg:classifiers":[
        {
            "category":"Farming",
            "subcategory":"Farm",
            "type":"Manufacturing & Wholesale Goods"
        }
    ],
    "sg:phone":"+1 501 336 0138",
    "sg:postcode":"72034",
    "sg:province":"AR",
    "sg:tags":[
        "crop"
    ],
    "wof:name":"Mark Schnarr",
    "wof:placetype":"venue"
},
  "geometry": {"coordinates":[-92.474733,35.075767],"type":"Point"}
}