{
  "type": "Feature",
  "properties": {
    "iso:country":"US",
    "sg:address":"204 E Elm St",
    "sg:city":"Earle",
    "sg:classifiers":[
        {
            "category":"Freight",
            "type":"Transportation"
        }
    ],
    "sg:phone":"+1 870 792 7101",
    "sg:postcode":"72331",
    "sg:province":"AR",
    "sg:tags":[
        "local",
        "without",
        "storage",
        "trucking"
    ],
    "wof:name":"Richard Jackson Trucking",
    "wof:placetype":"venue"
},
  "geometry": {"coordinates":[-90.475381,35.262864],"type":"Point"}
}