{
  "type": "Feature",
  "properties": {
    "iso:country":"US",
    "sg:address":"108 Bellaire Dr",
    "sg:city":"Hot Springs",
    "sg:classifiers":[
        {
            "category":"Shopping",
            "subcategory":"Crafts & Fabrics",
            "type":"Retail Goods"
        }
    ],
    "sg:phone":"+1 501 321 4717",
    "sg:postcode":"71901",
    "sg:province":"AR",
    "sg:tags":[
        "monogram"
    ],
    "wof:name":"Monograms N More",
    "wof:placetype":"venue"
},
  "geometry": {"coordinates":[-93.029313,34.483145],"type":"Point"}
}