{
  "type": "Feature",
  "properties": {
    "addr:full":"302 N 6th St Fort Smith AR 72901",
    "addr:housenumber":"302",
    "addr:postcode":"72901",
    "addr:street":"N 6Th St",
    "iso:country":"US",
    "sg:address":"302 N 6th St",
    "sg:city":"Fort Smith",
    "sg:classifiers":[
        {
            "category":"Real Estate",
            "subcategory":"Architect",
            "type":"Services"
        }
    ],
    "sg:phone":"+1 479 782 1051",
    "sg:postcode":"72901",
    "sg:province":"AR",
    "sg:website":"www.mahgarch.com",
    "wof:name":"Mahg Architecture Inc",
    "wof:placetype":"venue"
},
  "geometry": {"coordinates":[-94.422223,35.390274],"type":"Point"}
}