{
  "type": "Feature",
  "properties": {
    "iso:country":"US",
    "sg:address":"1315 S 11th St",
    "sg:city":"Fort Smith",
    "sg:classifiers":[
        {
            "category":"Building & Trades",
            "subcategory":"Electrical",
            "type":"Services"
        }
    ],
    "sg:phone":"+1 479 782 1064",
    "sg:postcode":"72901",
    "sg:province":"AR",
    "sg:tags":[
        "electric",
        "contractor"
    ],
    "wof:name":"Khilco Industrial Electric Inc",
    "wof:placetype":"venue"
},
  "geometry": {"coordinates":[-94.422613,35.370277],"type":"Point"}
}