{
  "type": "Feature",
  "properties": {
    "iso:country":"US",
    "sg:address":"3562 Evergreen Ln",
    "sg:city":"Harrison",
    "sg:classifiers":[
        {
            "category":"Building & Trades",
            "subcategory":"Construction",
            "type":"Services"
        }
    ],
    "sg:phone":"+1 870 743 2583",
    "sg:postcode":"72601",
    "sg:province":"AR",
    "sg:tags":[
        "house"
    ],
    "wof:name":"Stanley Home Improvement",
    "wof:placetype":"venue"
},
  "geometry": {"coordinates":[-93.112053,36.290796],"type":"Point"}
}