{
  "type": "Feature",
  "properties": {
    "addr:full":"9748 Maumelle Blvd N Little Rock AR 72113",
    "addr:housenumber":"9748",
    "addr:postcode":"72113",
    "addr:street":"Maumelle Blvd N",
    "iso:country":"US",
    "sg:address":"9748 Maumelle Blvd",
    "sg:city":"N Little Rock",
    "sg:classifiers":[
        {
            "category":"Shopping",
            "subcategory":"Computers & Home Electronics",
            "type":"Retail Goods"
        }
    ],
    "sg:phone":"+1 501 771 0079",
    "sg:postcode":"72113",
    "sg:province":"AR",
    "sg:tags":[
        "equipment",
        "satellite",
        "system"
    ],
    "wof:name":"Today's Satellite",
    "wof:placetype":"venue"
},
  "geometry": {"coordinates":[-92.364631,34.817819],"type":"Point"}
}