{
  "type": "Feature",
  "properties": {
    "addr:full":"10816 Executive Center Dr Little Rock AR 72211",
    "addr:housenumber":"10816",
    "addr:postcode":"72211",
    "addr:street":"Executive Center Dr",
    "iso:country":"US",
    "sg:address":"10816 Executive Center Dr",
    "sg:city":"Little Rock",
    "sg:classifiers":[
        {
            "category":"Insurance",
            "subcategory":"Life Insurance",
            "type":"Services"
        }
    ],
    "sg:phone":"+1 501 219 8787",
    "sg:postcode":"72211",
    "sg:province":"AR",
    "wof:name":"Guardian The",
    "wof:placetype":"venue"
},
  "geometry": {"coordinates":[-92.395877,34.739344],"type":"Point"}
}