{
  "type": "Feature",
  "properties": {
    "iso:country":"US",
    "sg:address":"206 S Main St",
    "sg:city":"Stuttgart",
    "sg:classifiers":[
        {
            "category":"Personal",
            "subcategory":"Nail Salon",
            "type":"Services"
        }
    ],
    "sg:phone":"+1 870 673 0227",
    "sg:postcode":"72160",
    "sg:province":"AR",
    "wof:name":"L A Nail",
    "wof:placetype":"venue"
},
  "geometry": {"coordinates":[-91.552545,34.501149],"type":"Point"}
}