{
  "type": "Feature",
  "properties": {
    "addr:full":"1600 Browns Lane Access Rd Jonesboro AR 72401",
    "addr:housenumber":"1600",
    "addr:postcode":"72401",
    "addr:street":"Browns Lane Access Rd",
    "iso:country":"US",
    "sg:address":"1600 Browns Lane Access Rd",
    "sg:city":"Jonesboro",
    "sg:classifiers":[
        {
            "category":"Home & Garden",
            "subcategory":"Furniture",
            "type":"Retail Goods"
        }
    ],
    "sg:phone":"+1 870 972 0180",
    "sg:postcode":"72401",
    "sg:province":"AR",
    "wof:name":"Martin David Inc",
    "wof:placetype":"venue"
},
  "geometry": {"coordinates":[-90.68586999999999,35.8075],"type":"Point"}
}