{
  "type": "Feature",
  "properties": {
    "iso:country":"US",
    "sg:address":"596 Sturgeon Cir",
    "sg:city":"Russellville",
    "sg:classifiers":[
        {
            "category":"Building & Trades",
            "subcategory":"Construction",
            "type":"Services"
        }
    ],
    "sg:phone":"+1 479 967 8523",
    "sg:postcode":"72802",
    "sg:province":"AR",
    "sg:tags":[
        "nonresidential"
    ],
    "wof:name":"Nelsons Construction",
    "wof:placetype":"venue"
},
  "geometry": {"coordinates":[-93.065653,35.292821],"type":"Point"}
}