{
  "type": "Feature",
  "properties": {
    "iso:country":"US",
    "sg:address":"823 E O St",
    "sg:city":"Russellville",
    "sg:classifiers":[
        {
            "category":"Real Estate",
            "subcategory":"Real Estate Operator",
            "type":"Services"
        }
    ],
    "sg:phone":"+1 479 890 4744",
    "sg:postcode":"72801",
    "sg:province":"AR",
    "sg:tags":[
        "apartment"
    ],
    "wof:name":"Duvall Apartments",
    "wof:placetype":"venue"
},
  "geometry": {"coordinates":[-93.123735,35.293079],"type":"Point"}
}