{
  "type": "Feature",
  "properties": {
    "iso:country":"US",
    "sg:address":"506 W Court St",
    "sg:city":"Paragould",
    "sg:classifiers":[
        {
            "category":"Government",
            "subcategory":"Office",
            "type":"Public Place"
        }
    ],
    "sg:phone":"+1 870 446 6022",
    "sg:postcode":"72450",
    "sg:province":"AR",
    "wof:name":"Newton Co Tobacco Ed Group",
    "wof:placetype":"venue"
},
  "geometry": {"coordinates":[-90.491433,36.056147],"type":"Point"}
}