{
  "type": "Feature",
  "properties": {
    "addr:full":"810 Bella Vista Rd Bentonville AR 72712",
    "addr:housenumber":"810",
    "addr:postcode":"72712",
    "addr:street":"Bella Vista Rd",
    "iso:country":"US",
    "sg:address":"810 Bella Vista Rd",
    "sg:city":"Bentonville",
    "sg:classifiers":[
        {
            "category":"Education",
            "subcategory":"School",
            "type":"Public Place"
        }
    ],
    "sg:phone":"+1 479 254 5860",
    "sg:postcode":"72712",
    "sg:province":"AR",
    "sg:website":"www.bentonville.k12.ar.us",
    "wof:name":"Thomas Jefferson Elementary",
    "wof:placetype":"venue"
},
  "geometry": {"coordinates":[-94.21723,36.381334],"type":"Point"}
}