{
  "type": "Feature",
  "properties": {
    "iso:country":"US",
    "sg:address":"800 N Roseville St",
    "sg:city":"Altus",
    "sg:classifiers":[
        {
            "category":"Organizations",
            "subcategory":"Membership Organization",
            "type":"Services"
        }
    ],
    "sg:phone":"+1 479 468 2131",
    "sg:postcode":"72821",
    "sg:province":"AR",
    "sg:tags":[
        "fraternal"
    ],
    "sg:website":"http://www.foe.com/",
    "wof:name":"Foe 3455",
    "wof:placetype":"venue"
},
  "geometry": {"coordinates":[-93.761413,35.439259],"type":"Point"}
}