{
  "type": "Feature",
  "properties": {
    "iso:country":"US",
    "sg:address":"14 Stevenson Ln",
    "sg:city":"Conway",
    "sg:classifiers":[
        {
            "category":"Shopping",
            "subcategory":"Books",
            "type":"Retail Goods"
        }
    ],
    "sg:phone":"+1 501 849 3517",
    "sg:postcode":"72032",
    "sg:province":"AR",
    "wof:name":"Clint R Reed Drycln Cnsulting",
    "wof:placetype":"venue"
},
  "geometry": {"coordinates":[-92.274642,35.146282],"type":"Point"}
}