{
  "type": "Feature",
  "properties": {
    "iso:country":"US",
    "sg:address":"6401 W 12th St",
    "sg:city":"Little Rock",
    "sg:classifiers":[
        {
            "category":"Organizations",
            "subcategory":"Religious Organization",
            "type":"Services"
        }
    ],
    "sg:phone":"+1 501 835 4399",
    "sg:postcode":"72204",
    "sg:province":"AR",
    "wof:name":"In Light of Truth Ministries",
    "wof:placetype":"venue"
},
  "geometry": {"coordinates":[-92.34428,34.741373],"type":"Point"}
}