{
  "type": "Feature",
  "properties": {
    "iso:country":"US",
    "sg:address":"7510 Hwy 5 N",
    "sg:city":"Alexander",
    "sg:classifiers":[
        {
            "category":"Wholesale",
            "subcategory":"Medical Equipment & Supplies",
            "type":"Manufacturing & Wholesale Goods"
        }
    ],
    "sg:phone":"+1 501 847 2332",
    "sg:postcode":"72002",
    "sg:province":"AR",
    "sg:tags":[
        "physician",
        "surgeon"
    ],
    "sg:website":"www.boothmed.com",
    "wof:name":"Booths Medical Equipment Co",
    "wof:placetype":"venue"
},
  "geometry": {"coordinates":[-92.470512,34.636496],"type":"Point"}
}