{
  "type": "Feature",
  "properties": {
    "addr:full":"225 Co Rd 730 Mountain Home AR 72653",
    "addr:housenumber":"225;730",
    "addr:postcode":"72653",
    "addr:street":"Co Rd",
    "iso:country":"US",
    "sg:address":"225 Co Rd 730",
    "sg:city":"Mountain Home",
    "sg:classifiers":[
        {
            "category":"Building & Trades",
            "subcategory":"Construction",
            "type":"Services"
        }
    ],
    "sg:phone":"+1 870 424 6862",
    "sg:postcode":"72653",
    "sg:province":"AR",
    "sg:tags":[
        "general",
        "contractor"
    ],
    "wof:name":"Snodgrass Construction",
    "wof:placetype":"venue"
},
  "geometry": {"coordinates":[-92.42231099999999,36.337047],"type":"Point"}
}