{
  "type": "Feature",
  "properties": {
    "iso:country":"US",
    "sg:address":"1210 Gavin Ln",
    "sg:city":"Rison",
    "sg:classifiers":[
        {
            "category":"Building & Trades",
            "subcategory":"Construction",
            "type":"Services"
        }
    ],
    "sg:phone":"+1 870 357 2961",
    "sg:postcode":"71665",
    "sg:province":"AR",
    "sg:tags":[
        "maker",
        "cabinet"
    ],
    "wof:name":"Nelson Cabinet Shop",
    "wof:placetype":"venue"
},
  "geometry": {"coordinates":[-92.01469,33.77274],"type":"Point"}
}