{
  "type": "Feature",
  "properties": {
    "addr:full":"152 Legion Rd West Memphis AR 72301",
    "addr:housenumber":"152",
    "addr:postcode":"72301",
    "addr:street":"Legion Rd",
    "iso:country":"US",
    "sg:address":"152 Legion Rd",
    "sg:city":"West Memphis",
    "sg:classifiers":[
        {
            "category":"Organizations",
            "subcategory":"Community Association",
            "type":"Services"
        }
    ],
    "sg:phone":"+1 870 735 0866",
    "sg:postcode":"72301",
    "sg:province":"AR",
    "sg:tags":[
        "business",
        "fraternal"
    ],
    "wof:name":"Forty & Eight Inc",
    "wof:placetype":"venue"
},
  "geometry": {"coordinates":[-90.133955,35.142499],"type":"Point"}
}