{
  "type": "Feature",
  "properties": {
    "addr:full":"200 E Ridge Ave Harrison AR 72601",
    "addr:housenumber":"200",
    "addr:postcode":"72601",
    "addr:street":"E Ridge Ave",
    "iso:country":"US",
    "sg:address":"200 E Ridge Ave",
    "sg:city":"Harrison",
    "sg:classifiers":[
        {
            "category":"Real Estate",
            "subcategory":"Real Estate Services",
            "type":"Services"
        },
        {
            "category":"Banks & Credit Unions",
            "subcategory":"Bank",
            "type":"Services"
        },
        {
            "category":"Banks & Credit Unions",
            "subcategory":"Financial Services",
            "type":"Services"
        }
    ],
    "sg:phone":"+1 870 391 8000",
    "sg:postcode":"72601",
    "sg:province":"AR",
    "sg:tags":[
        "commercial",
        "loan",
        "saving"
    ],
    "sg:website":"http://www.communityfirstbank.com",
    "wof:name":"Comunity First Bank Shares",
    "wof:placetype":"venue"
},
  "geometry": {"coordinates":[-93.106003,36.232033],"type":"Point"}
}