{
  "type": "Feature",
  "properties": {
    "iso:country":"US",
    "sg:address":"2303 Washington Ave",
    "sg:city":"Conway",
    "sg:classifiers":[
        {
            "category":"Personal",
            "subcategory":"Beauty Salon",
            "type":"Services"
        }
    ],
    "sg:phone":"+1 501 327 1695",
    "sg:postcode":"72032",
    "sg:province":"AR",
    "sg:tags":[
        "shop"
    ],
    "wof:name":"Hair One Studio",
    "wof:placetype":"venue"
},
  "geometry": {"coordinates":[-92.44566500000001,35.109285],"type":"Point"}
}