{
  "type": "Feature",
  "properties": {
    "iso:country":"US",
    "sg:address":"30 Cloverleaf Plz",
    "sg:city":"Van Buren",
    "sg:classifiers":[
        {
            "category":"Health Services",
            "subcategory":"Optometrist",
            "type":"Services"
        }
    ],
    "sg:phone":"+1 479 474 7878",
    "sg:postcode":"72956",
    "sg:province":"AR",
    "wof:name":"Graham Optical",
    "wof:placetype":"venue"
},
  "geometry": {"coordinates":[-94.32410900000001,35.443266],"type":"Point"}
}