{
  "type": "Feature",
  "properties": {
    "iso:country":"US",
    "sg:address":"3515 Gate Nine Rd",
    "sg:city":"Greenwood",
    "sg:classifiers":[
        {
            "category":"Organizations",
            "subcategory":"Religious Organization",
            "type":"Services"
        }
    ],
    "sg:phone":"+1 479 996 2496",
    "sg:postcode":"72936",
    "sg:province":"AR",
    "sg:tags":[
        "church"
    ],
    "wof:name":"Howard Hill Assembly-God Chr",
    "wof:placetype":"venue"
},
  "geometry": {"coordinates":[-94.30943000000001,35.265517],"type":"Point"}
}