{
  "type": "Feature",
  "properties": {
    "iso:country":"US",
    "sg:address":"518 S Thompson St",
    "sg:city":"Springdale",
    "sg:classifiers":[
        {
            "category":"Personal",
            "subcategory":"Beauty Salon",
            "type":"Services"
        }
    ],
    "sg:phone":"+1 479 756 2008",
    "sg:postcode":"72764",
    "sg:province":"AR",
    "sg:tags":[
        "hair",
        "shop",
        "stylist"
    ],
    "sg:website":"http://www.campphil.com",
    "wof:name":"Hair Design 2000",
    "wof:placetype":"venue"
},
  "geometry": {"coordinates":[-94.138741,36.180729],"type":"Point"}
}