{
  "type": "Feature",
  "properties": {
    "addr:full":"5400 Lock and Dam Rd Ozark AR 72949",
    "addr:postcode":"5400;72949",
    "addr:street":"Dam Rd",
    "iso:country":"US",
    "sg:address":"5400 Lock and Dam Rd",
    "sg:city":"Ozark",
    "sg:classifiers":[
        {
            "category":"Government",
            "subcategory":"Office",
            "type":"Public Place"
        }
    ],
    "sg:phone":"+1 479 667 2120",
    "sg:postcode":"72949",
    "sg:province":"AR",
    "sg:tags":[
        "federal"
    ],
    "wof:name":"US Army Corps Of Engineers",
    "wof:placetype":"venue"
},
  "geometry": {"coordinates":[-93.81222,35.47269],"type":"Point"}
}