{
  "type": "Feature",
  "properties": {
    "addr:full":"1911 Timberline Dr Texarkana AR 71854",
    "addr:housenumber":"1911",
    "addr:postcode":"71854",
    "addr:street":"Timberline Dr",
    "iso:country":"US",
    "sg:address":"1911 Timberline Dr",
    "sg:city":"Texarkana",
    "sg:classifiers":[
        {
            "category":"Building & Trades",
            "subcategory":"Landscaping Services",
            "type":"Services"
        }
    ],
    "sg:phone":"+1 870 216 1995",
    "sg:postcode":"71854",
    "sg:province":"AR",
    "sg:tags":[
        "landscape",
        "contractor"
    ],
    "wof:name":"Greenskeepers LLC",
    "wof:placetype":"venue"
},
  "geometry": {"coordinates":[-94.02220699999999,33.465097],"type":"Point"}
}