{
  "type": "Feature",
  "properties": {
    "iso:country":"US",
    "sg:address":"100 E Huntington Ave",
    "sg:city":"Jonesboro",
    "sg:classifiers":[
        {
            "category":"Health Services",
            "subcategory":"Health Practitioner",
            "type":"Services"
        }
    ],
    "sg:phone":"+1 870 932 0260",
    "sg:postcode":"72401",
    "sg:province":"AR",
    "wof:name":"Professional Counseling & Cnsl",
    "wof:placetype":"venue"
},
  "geometry": {"coordinates":[-90.704933,35.84034],"type":"Point"}
}