{
  "type": "Feature",
  "properties": {
    "addr:full":"278 Co Rd 178 Success AR 72470",
    "addr:housenumber":"278;178",
    "addr:postcode":"72470",
    "addr:street":"Co Rd",
    "iso:country":"US",
    "sg:address":"278 Co Rd 178",
    "sg:city":"Success",
    "sg:classifiers":[
        {
            "category":"Professional",
            "type":"Services"
        }
    ],
    "sg:phone":"+1 870 276 5023",
    "sg:postcode":"72470",
    "sg:province":"AR",
    "wof:name":"Todd Smith",
    "wof:placetype":"venue"
},
  "geometry": {"coordinates":[-90.69923300000001,36.463853],"type":"Point"}
}