{
  "type": "Feature",
  "properties": {
    "iso:country":"US",
    "sg:address":"1300 Falls Blvd N",
    "sg:city":"Wynne",
    "sg:classifiers":[
        {
            "category":"Education",
            "subcategory":"School",
            "type":"Public Place"
        }
    ],
    "sg:phone":"+1 870 238 5000",
    "sg:postcode":"72396",
    "sg:province":"AR",
    "wof:name":"Wynne Public Schools",
    "wof:placetype":"venue"
},
  "geometry": {"coordinates":[-90.784476,35.234522],"type":"Point"}
}