{
  "type": "Feature",
  "properties": {
    "iso:country":"US",
    "sg:address":"100 E Villena Dr",
    "sg:city":"Hot Springs Vlg",
    "sg:classifiers":[
        {
            "category":"Organizations",
            "subcategory":"Religious Organization",
            "type":"Services"
        }
    ],
    "sg:phone":"+1 501 922 1722",
    "sg:postcode":"71909",
    "sg:province":"AR",
    "sg:tags":[
        "church"
    ],
    "wof:name":"First Baptist Church",
    "wof:placetype":"venue"
},
  "geometry": {"coordinates":[-93.0343,34.66402],"type":"Point"}
}