{
  "type": "Feature",
  "properties": {
    "addr:full":"1849 McRay Ave Springdale AR 72762",
    "addr:housenumber":"1849",
    "addr:postcode":"72762",
    "addr:street":"Mcray Ave",
    "iso:country":"US",
    "sg:address":"1849 McRay Ave",
    "sg:city":"Springdale",
    "sg:classifiers":[
        {
            "category":"Organizations",
            "subcategory":"Religious Organization",
            "type":"Services"
        }
    ],
    "sg:phone":"+1 479 751 3530",
    "sg:postcode":"72762",
    "sg:province":"AR",
    "sg:tags":[
        "church"
    ],
    "wof:name":"Iglesia De Cristo Palabra De R",
    "wof:placetype":"venue"
},
  "geometry": {"coordinates":[-94.14926,36.181608],"type":"Point"}
}