{
  "type": "Feature",
  "properties": {
    "iso:country":"US",
    "sg:address":"2192 New London Rd",
    "sg:city":"Strong",
    "sg:classifiers":[
        {
            "category":"Professional",
            "type":"Services"
        }
    ],
    "sg:phone":"+1 870 797 7508",
    "sg:postcode":"71765",
    "sg:province":"AR",
    "wof:name":"James P Fife",
    "wof:placetype":"venue"
},
  "geometry": {"coordinates":[-92.33884500000001,33.161247],"type":"Point"}
}