{
  "type": "Feature",
  "properties": {
    "addr:full":"231 N Walton Blvd Bentonville AR 72712",
    "addr:housenumber":"231",
    "addr:postcode":"72712",
    "addr:street":"N Walton Blvd",
    "iso:country":"US",
    "sg:address":"231 N Walton Blvd",
    "sg:city":"Bentonville",
    "sg:classifiers":[
        {
            "category":"Restaurant",
            "type":"Food & Drink"
        }
    ],
    "sg:menulink":"http://www.allmenus.com/ar/centerton/90762-wingstop/menu/",
    "sg:phone":"+1 479 271 8833",
    "sg:postcode":"72712",
    "sg:province":"AR",
    "sg:tags":[
        "american",
        "wing"
    ],
    "wof:name":"Wingstop",
    "wof:placetype":"venue"
},
  "geometry": {"coordinates":[-94.221403,36.373798],"type":"Point"}
}