{
  "type": "Feature",
  "properties": {
    "addr:full":"1401 W Rock St Morrilton AR 72110",
    "addr:housenumber":"1401",
    "addr:postcode":"72110",
    "addr:street":"W Rock St",
    "iso:country":"US",
    "sg:address":"1401 W Rock St",
    "sg:city":"Morrilton",
    "sg:classifiers":[
        {
            "category":"Wholesale",
            "subcategory":"Auto Parts",
            "type":"Manufacturing & Wholesale Goods"
        }
    ],
    "sg:phone":"+1 501 354 2621",
    "sg:postcode":"72110",
    "sg:province":"AR",
    "sg:tags":[
        "automobile",
        "rebuilt"
    ],
    "wof:name":"Gibby's Auto Sales & Parts",
    "wof:placetype":"venue"
},
  "geometry": {"coordinates":[-92.76246399999999,35.158738],"type":"Point"}
}