{
  "type": "Feature",
  "properties": {
    "iso:country":"US",
    "sg:address":"2107 Pin Oak Dr",
    "sg:city":"Springdale",
    "sg:classifiers":[
        {
            "category":"Education",
            "subcategory":"Dance Studio",
            "type":"Public Place"
        }
    ],
    "sg:phone":"+1 479 756 6191",
    "sg:postcode":"72762",
    "sg:province":"AR",
    "wof:name":"New Moves Cheer & Dance Studio",
    "wof:placetype":"venue"
},
  "geometry": {"coordinates":[-94.161259,36.178033],"type":"Point"}
}