{
  "type": "Feature",
  "properties": {
    "iso:country":"US",
    "sg:address":"1079 Velvet Ridge Rd",
    "sg:city":"Bradford",
    "sg:classifiers":[
        {
            "category":"Organizations",
            "subcategory":"Religious Organization",
            "type":"Services"
        }
    ],
    "sg:phone":"+1 501 344 2764",
    "sg:postcode":"72020",
    "sg:province":"AR",
    "sg:tags":[
        "church"
    ],
    "wof:name":"Trinity Baptist Church",
    "wof:placetype":"venue"
},
  "geometry": {"coordinates":[-91.484567,35.425622],"type":"Point"}
}