{
  "type": "Feature",
  "properties": {
    "iso:country":"US",
    "sg:address":"3450 Greene Rd 839",
    "sg:city":"Paragould",
    "sg:phone":"+1 870 239 3821",
    "sg:postcode":"72450",
    "sg:province":"AR",
    "sg:tags":[
        "farm",
        "cotton"
    ],
    "wof:name":"Tommy Hester Farms",
    "wof:placetype":"venue"
},
  "geometry": {"coordinates":[-90.301908,36.124527],"type":"Point"}
}