{
  "type": "Feature",
  "properties": {
    "iso:country":"US",
    "sg:address":"107 Main St",
    "sg:city":"Arkoma",
    "sg:classifiers":[
        {
            "category":"Transit Center",
            "subcategory":"Freight",
            "type":"Transportation"
        },
        {
            "category":"Freight",
            "type":"Transportation"
        }
    ],
    "sg:phone":"+1 918 875 2339",
    "sg:postcode":"74901",
    "sg:province":"OK",
    "sg:tags":[
        "trucking-motor",
        "trucking"
    ],
    "wof:name":"National Hot Shop Svc",
    "wof:placetype":"venue"
},
  "geometry": {"coordinates":[-94.432289,35.361331],"type":"Point"}
}