{
  "type": "Feature",
  "properties": {
    "iso:country":"US",
    "sg:address":"3505 S Walton Blvd",
    "sg:city":"Bentonville",
    "sg:classifiers":[
        {
            "category":"Manufacturing",
            "subcategory":"Toys & Sporting Goods",
            "type":"Manufacturing & Wholesale Goods"
        },
        {
            "category":"Utilities",
            "subcategory":"Natural Gas",
            "type":"Services"
        }
    ],
    "sg:phone":"+1 479 273 7625",
    "sg:postcode":"72712",
    "sg:province":"AR",
    "sg:tags":[
        "fireworks-wholesale",
        "firework",
        "manufacturer"
    ],
    "wof:name":"Rainbow Fireworks Inc",
    "wof:placetype":"venue"
},
  "geometry": {"coordinates":[-94.210876,36.336941],"type":"Point"}
}