{
  "type": "Feature",
  "properties": {
    "addr:full":"109 N Georgia St Crossett AR 71635",
    "addr:housenumber":"109",
    "addr:postcode":"71635",
    "addr:street":"N Georgia St",
    "iso:country":"US",
    "sg:address":"109 N Georgia St",
    "sg:city":"Crossett",
    "sg:classifiers":[
        {
            "category":"Organizations",
            "subcategory":"Religious Organization",
            "type":"Services"
        }
    ],
    "sg:phone":"+1 870 364 6923",
    "sg:postcode":"71635",
    "sg:province":"AR",
    "sg:tags":[
        "testament",
        "churches-church",
        "christ-new"
    ],
    "wof:name":"Chruch Christ",
    "wof:placetype":"venue"
},
  "geometry": {"coordinates":[-91.968329,33.135137],"type":"Point"}
}