{
  "type": "Feature",
  "properties": {
    "iso:country":"US",
    "sg:address":"109 W Kentucky St",
    "sg:city":"Caraway",
    "sg:classifiers":[
        {
            "category":"Personal",
            "subcategory":"Beauty Salon",
            "type":"Services"
        }
    ],
    "sg:phone":"+1 870 482 3773",
    "sg:postcode":"72419",
    "sg:province":"AR",
    "wof:name":"Brenda's Cut'n Loose",
    "wof:placetype":"venue"
},
  "geometry": {"coordinates":[-90.323989,35.760845],"type":"Point"}
}