{
  "type": "Feature",
  "properties": {
    "iso:country":"US",
    "sg:address":"110 S Chestnut St",
    "sg:city":"Morrilton",
    "sg:classifiers":[
        {
            "category":"Education",
            "subcategory":"School",
            "type":"Public Place"
        }
    ],
    "sg:phone":"+1 501 354 8123",
    "sg:postcode":"72110",
    "sg:province":"AR",
    "sg:tags":[
        "academic",
        "special"
    ],
    "wof:name":"Conway County Literacy Council",
    "wof:placetype":"venue"
},
  "geometry": {"coordinates":[-92.742737,35.151889],"type":"Point"}
}