{
  "type": "Feature",
  "properties": {
    "iso:country":"US",
    "sg:address":"1203 W 6th St",
    "sg:city":"El Dorado",
    "sg:classifiers":[
        {
            "category":"Organizations",
            "subcategory":"Religious Organization",
            "type":"Services"
        }
    ],
    "sg:phone":"+1 870 862 3392",
    "sg:postcode":"71730",
    "sg:province":"AR",
    "sg:tags":[
        "church"
    ],
    "wof:name":"Divinefaith Fellowship Bapt",
    "wof:placetype":"venue"
},
  "geometry": {"coordinates":[-92.680746,33.223196],"type":"Point"}
}