{
  "type": "Feature",
  "properties": {
    "iso:country":"US",
    "sg:address":"3002 Pines Mall Dr",
    "sg:city":"Pine Bluff",
    "sg:classifiers":[
        {
            "category":"Restaurant",
            "type":"Food & Drink"
        }
    ],
    "sg:phone":"+1 870 535 0980",
    "sg:postcode":"71601",
    "sg:province":"AR",
    "sg:tags":[
        "fast"
    ],
    "wof:name":"Taco Bell",
    "wof:placetype":"venue"
},
  "geometry": {"coordinates":[-91.97031,34.207431],"type":"Point"}
}