{
  "type": "Feature",
  "properties": {
    "iso:country":"US",
    "sg:address":"10010 Macarthur Dr",
    "sg:city":"N Little Rock",
    "sg:classifiers":[
        {
            "category":"Home & Garden",
            "subcategory":"Garden Supply",
            "type":"Retail Goods"
        }
    ],
    "sg:phone":"+1 501 851 3675",
    "sg:postcode":"72118",
    "sg:province":"AR",
    "sg:tags":[
        "lawn",
        "mower"
    ],
    "wof:name":"Quality Small Engine Repair",
    "wof:placetype":"venue"
},
  "geometry": {"coordinates":[-92.335858,34.841014],"type":"Point"}
}