{
  "type": "Feature",
  "properties": {
    "addr:full":"1218 Stone St Jonesboro AR 72401",
    "addr:housenumber":"1218",
    "addr:postcode":"72401",
    "addr:street":"Stone St",
    "iso:country":"US",
    "sg:address":"1218 Stone St",
    "sg:city":"Jonesboro",
    "sg:classifiers":[
        {
            "category":"Insurance",
            "subcategory":"Insurance Agent",
            "type":"Services"
        }
    ],
    "sg:phone":"+1 870 972 8640",
    "sg:postcode":"72401",
    "sg:province":"AR",
    "wof:name":"Nationwide Mutual Insurance",
    "wof:placetype":"venue"
},
  "geometry": {"coordinates":[-90.675622,35.831019],"type":"Point"}
}