{
  "type": "Feature",
  "properties": {
    "iso:country":"US",
    "sg:address":"330 N Main St",
    "sg:city":"Malvern",
    "sg:classifiers":[
        {
            "category":"Banks & Credit Unions",
            "subcategory":"Bank",
            "type":"Services"
        }
    ],
    "sg:phone":"+1 501 332 8005",
    "sg:postcode":"72104",
    "sg:province":"AR",
    "wof:name":"Malvern National Bank",
    "wof:placetype":"venue"
},
  "geometry": {"coordinates":[-92.81844100000001,34.37076],"type":"Point"}
}