{
  "type": "Feature",
  "properties": {
    "iso:country":"US",
    "sg:address":"7800 Taylor Ave",
    "sg:city":"Heber Springs",
    "sg:classifiers":[
        {
            "category":"Recreation",
            "subcategory":"Marina",
            "type":"Entertainment"
        }
    ],
    "sg:phone":"+1 501 362 5571",
    "sg:postcode":"72543",
    "sg:province":"AR",
    "sg:tags":[
        "operation"
    ],
    "wof:name":"Heber Springs Dry Storage Inc",
    "wof:placetype":"venue"
},
  "geometry": {"coordinates":[-92.079513,35.493817],"type":"Point"}
}