{
  "type": "Feature",
  "properties": {
    "addr:full":"315 W Dequincy Ave De Queen AR 71832",
    "addr:housenumber":"315",
    "addr:postcode":"71832",
    "addr:street":"W Dequincy Ave De Queen",
    "iso:country":"US",
    "sg:address":"315 W Dequincy Ave",
    "sg:city":"De Queen",
    "sg:classifiers":[
        {
            "category":"Health Services",
            "subcategory":"Health Practitioner",
            "type":"Services"
        }
    ],
    "sg:phone":"+1 870 642 5035",
    "sg:postcode":"71832",
    "sg:province":"AR",
    "sg:tags":[
        "midwife"
    ],
    "wof:name":"Genesis Home Birth Service",
    "wof:placetype":"venue"
},
  "geometry": {"coordinates":[-94.34138400000001,34.041668],"type":"Point"}
}