{
  "type": "Feature",
  "properties": {
    "addr:full":"3262 Albert Pike Rd Hot Springs AR 71913",
    "addr:housenumber":"3262",
    "addr:postcode":"71913",
    "addr:street":"Albert Pike Rd",
    "iso:country":"US",
    "sg:address":"3262 Albert Pike Rd",
    "sg:city":"Hot Springs",
    "sg:classifiers":[
        {
            "category":"Building & Trades",
            "subcategory":"Landscaping Services",
            "type":"Services"
        }
    ],
    "sg:phone":"+1 501 627 4472",
    "sg:postcode":"71913",
    "sg:province":"AR",
    "sg:tags":[
        "lawn",
        "maintenance",
        "grounds"
    ],
    "wof:name":"J & C Lawn Svc",
    "wof:placetype":"venue"
},
  "geometry": {"coordinates":[-93.13042,34.506994],"type":"Point"}
}