{
  "type": "Feature",
  "properties": {
    "addr:full":"305 S 40th St Rogers AR 72758",
    "addr:housenumber":"305",
    "addr:postcode":"72758",
    "addr:street":"S 40Th St",
    "iso:country":"US",
    "sg:address":"305 S 40th St",
    "sg:city":"Rogers",
    "sg:classifiers":[
        {
            "category":"Building & Trades",
            "subcategory":"Construction",
            "type":"Services"
        }
    ],
    "sg:phone":"+1 479 903 5197",
    "sg:postcode":"72758",
    "sg:province":"AR",
    "sg:tags":[
        "carpentry",
        "contractor"
    ],
    "wof:name":"Jodys Doors Inc",
    "wof:placetype":"venue"
},
  "geometry": {"coordinates":[-94.175105,36.333759],"type":"Point"}
}