{
  "type": "Feature",
  "properties": {
    "addr:full":"201 Estes Lexa AR 72355",
    "addr:housenumber":"201",
    "addr:postcode":"72355",
    "addr:street":"Estes Lexa",
    "iso:country":"US",
    "sg:address":"201 Estes",
    "sg:city":"Lexa",
    "sg:classifiers":[
        {
            "category":"Organizations",
            "subcategory":"Religious Organization",
            "type":"Services"
        }
    ],
    "sg:phone":"+1 870 295 6530",
    "sg:postcode":"72355",
    "sg:province":"AR",
    "sg:tags":[
        "church"
    ],
    "wof:name":"Rondo Missionary Baptist Ch",
    "wof:placetype":"venue"
},
  "geometry": {"coordinates":[-90.820899,34.659338],"type":"Point"}
}