{
  "type": "Feature",
  "properties": {
    "iso:country":"US",
    "sg:address":"109 Industrial Rd",
    "sg:city":"El Dorado",
    "sg:classifiers":[
        {
            "category":"Wholesale",
            "subcategory":"Machinery & Supplies",
            "type":"Manufacturing & Wholesale Goods"
        }
    ],
    "sg:phone":"+1 870 862 3494",
    "sg:postcode":"71730",
    "sg:province":"AR",
    "sg:tags":[
        "field",
        "oil",
        "equipment"
    ],
    "wof:name":"Wilbur Davis Oil Field Equip",
    "wof:placetype":"venue"
},
  "geometry": {"coordinates":[-92.617903,33.190929],"type":"Point"}
}