{
  "type": "Feature",
  "properties": {
    "iso:country":"US",
    "sg:address":"1409 Thornhill St",
    "sg:city":"Alma",
    "sg:classifiers":[
        {
            "category":"Insurance",
            "subcategory":"Hazard Insurance",
            "type":"Services"
        }
    ],
    "sg:phone":"+1 479 965 7833",
    "sg:postcode":"72921",
    "sg:province":"AR",
    "wof:name":"Roger Dale Edwards",
    "wof:placetype":"venue"
},
  "geometry": {"coordinates":[-94.231951,35.413536],"type":"Point"}
}