{
  "type": "Feature",
  "properties": {
    "iso:country":"US",
    "sg:address":"800 S Locust St",
    "sg:city":"Ashdown",
    "sg:classifiers":[
        {
            "category":"Insurance",
            "subcategory":"Insurance Agent",
            "type":"Services"
        }
    ],
    "sg:phone":"+1 870 898 8787",
    "sg:postcode":"71822",
    "sg:province":"AR",
    "wof:name":"Apple Barrel",
    "wof:placetype":"venue"
},
  "geometry": {"coordinates":[-94.118114,33.664177],"type":"Point"}
}