{
  "type": "Feature",
  "properties": {
    "addr:full":"1240 Fox Run Ln Elkins AR 72727",
    "addr:housenumber":"1240",
    "addr:postcode":"72727",
    "addr:street":"Fox Run Ln",
    "iso:country":"US",
    "sg:address":"1240 Fox Run Ln",
    "sg:city":"Elkins",
    "sg:classifiers":[
        {
            "category":"Building & Trades",
            "subcategory":"Construction",
            "type":"Services"
        }
    ],
    "sg:phone":"+1 479 643 4098",
    "sg:postcode":"72727",
    "sg:province":"AR",
    "sg:tags":[
        "woodworker"
    ],
    "wof:name":"Whiteley's Custom Woodworking",
    "wof:placetype":"venue"
},
  "geometry": {"coordinates":[-94.030276,36.027342],"type":"Point"}
}