{
  "type": "Feature",
  "properties": {
    "iso:country":"US",
    "sg:address":"74 Stonehaven Dr",
    "sg:city":"Bella Vista",
    "sg:classifiers":[
        {
            "category":"Professional",
            "subcategory":"Management & Consulting",
            "type":"Services"
        }
    ],
    "sg:phone":"+1 479 876 6143",
    "sg:postcode":"72715",
    "sg:province":"AR",
    "wof:name":"Harold Harp & Associates",
    "wof:placetype":"venue"
},
  "geometry": {"coordinates":[-94.337158,36.460006],"type":"Point"}
}