{
  "type": "Feature",
  "properties": {
    "iso:country":"US",
    "sg:address":"1658 State Hwy 52 W",
    "sg:city":"Crossett",
    "sg:classifiers":[
        {
            "category":"Food & Beverages",
            "subcategory":"Groceries & Convenience Stores",
            "type":"Retail Goods"
        }
    ],
    "sg:phone":"+1 870 364 2709",
    "sg:postcode":"71635",
    "sg:province":"AR",
    "sg:website":"www.e-zmart.com",
    "wof:name":"E-Z Mart",
    "wof:placetype":"venue"
},
  "geometry": {"coordinates":[-91.939627,33.167956],"type":"Point"}
}