{
  "type": "Feature",
  "properties": {
    "addr:full":"800 State Hwy 160-S Portland AR 71663",
    "addr:housenumber":"800",
    "addr:postcode":"71663",
    "addr:street":"State Hwy",
    "iso:country":"US",
    "sg:address":"800 State Hwy 160-S",
    "sg:city":"Portland",
    "sg:classifiers":[
        {
            "category":"Wholesale",
            "subcategory":"Groceries",
            "type":"Manufacturing & Wholesale Goods"
        }
    ],
    "sg:phone":"+1 870 737 4383",
    "sg:postcode":"71663",
    "sg:province":"AR",
    "sg:tags":[
        "nut",
        "processing"
    ],
    "sg:website":"www.justicenut.com",
    "wof:name":"Justice Nut Co",
    "wof:placetype":"venue"
},
  "geometry": {"coordinates":[-91.475605,33.224466],"type":"Point"}
}