{
  "type": "Feature",
  "properties": {
    "iso:country":"US",
    "sg:address":"27663 Hwy 67",
    "sg:city":"Malvern",
    "sg:classifiers":[
        {
            "category":"Building & Trades",
            "subcategory":"Construction",
            "type":"Services"
        }
    ],
    "sg:phone":"+1 501 337 1408",
    "sg:postcode":"72104",
    "sg:province":"AR",
    "sg:tags":[
        "excavation",
        "contractor"
    ],
    "wof:name":"Central Excavating",
    "wof:placetype":"venue"
},
  "geometry": {"coordinates":[-92.835257,34.323173],"type":"Point"}
}