{
  "type": "Feature",
  "properties": {
    "iso:country":"US",
    "sg:address":"515 S Main St",
    "sg:city":"Jay",
    "sg:classifiers":[
        {
            "category":"Banks & Credit Unions",
            "subcategory":"Bank",
            "type":"Services"
        },
        {
            "category":"Shopping",
            "subcategory":"Used Merchandise",
            "type":"Retail Goods"
        }
    ],
    "sg:phone":"+1 918 253 4062",
    "sg:postcode":"74346",
    "sg:province":"OK",
    "sg:tags":[
        "resale",
        "shop",
        "second",
        "hand"
    ],
    "wof:name":"Hollie's Flowers And Gifts",
    "wof:placetype":"venue"
},
  "geometry": {"coordinates":[-94.797605,36.421162],"type":"Point"}
}