{
  "type": "Feature",
  "properties": {
    "iso:country":"US",
    "sg:address":"400 N Center St",
    "sg:city":"Lonoke",
    "sg:classifiers":[
        {
            "category":"Shopping",
            "subcategory":"Gifts & Souvenirs",
            "type":"Retail Goods"
        }
    ],
    "sg:phone":"+1 501 676 5332",
    "sg:postcode":"72086",
    "sg:province":"AR",
    "sg:tags":[
        "shop"
    ],
    "wof:name":"Cat's Meow Inc",
    "wof:placetype":"venue"
},
  "geometry": {"coordinates":[-91.900024,34.787684],"type":"Point"}
}