{
  "type": "Feature",
  "properties": {
    "addr:full":"103 S 3rd St Heber Springs AR 72543",
    "addr:housenumber":"103",
    "addr:postcode":"72543",
    "addr:street":"S 3Rd St",
    "iso:country":"US",
    "sg:address":"103 S 3rd St",
    "sg:city":"Heber Springs",
    "sg:classifiers":[
        {
            "category":"Education",
            "subcategory":"Dance Studio",
            "type":"Public Place"
        }
    ],
    "sg:phone":"+1 501 362 3107",
    "sg:postcode":"72543",
    "sg:province":"AR",
    "sg:tags":[
        "instruction",
        "dancing"
    ],
    "wof:name":"Judi King School Of Dance",
    "wof:placetype":"venue"
},
  "geometry": {"coordinates":[-92.031386,35.491536],"type":"Point"}
}