{
  "type": "Feature",
  "properties": {
    "iso:country":"US",
    "sg:address":"823 S West Ave",
    "sg:city":"El Dorado",
    "sg:classifiers":[
        {
            "category":"Building & Trades",
            "subcategory":"Construction",
            "type":"Services"
        }
    ],
    "sg:phone":"+1 870 864 0012",
    "sg:postcode":"71730",
    "sg:province":"AR",
    "sg:tags":[
        "contractor"
    ],
    "wof:name":"El Dorado Irrigation",
    "wof:placetype":"venue"
},
  "geometry": {"coordinates":[-92.66552299999999,33.204157],"type":"Point"}
}