{
  "type": "Feature",
  "properties": {
    "addr:full":"34 Forest Ln Eureka Springs AR 72632",
    "addr:housenumber":"34",
    "addr:postcode":"72632",
    "addr:street":"Forest Ln",
    "iso:country":"US",
    "sg:address":"34 Forest Ln",
    "sg:city":"Eureka Springs",
    "sg:classifiers":[
        {
            "category":"Manufacturing",
            "subcategory":"Building Materials",
            "type":"Manufacturing & Wholesale Goods"
        }
    ],
    "sg:phone":"+1 479 253 5645",
    "sg:postcode":"72632",
    "sg:province":"AR",
    "sg:tags":[
        "product",
        "wood",
        "mfg"
    ],
    "wof:name":"Scroll Saw Shop",
    "wof:placetype":"venue"
},
  "geometry": {"coordinates":[-93.73244099999999,36.374446],"type":"Point"}
}