{
  "type": "Feature",
  "properties": {
    "addr:full":"3889 Willowood Ave Springdale AR 72762",
    "addr:housenumber":"3889",
    "addr:postcode":"72762",
    "addr:street":"Willowood Ave",
    "iso:country":"US",
    "sg:address":"3889 Willowood Ave",
    "sg:city":"Springdale",
    "sg:classifiers":[
        {
            "category":"Education",
            "subcategory":"University",
            "type":"Public Place"
        }
    ],
    "sg:phone":"+1 479 524 3131",
    "sg:postcode":"72762",
    "sg:province":"AR",
    "sg:tags":[
        "college"
    ],
    "sg:website":"http://www.jbu.edu",
    "wof:name":"Northwest Center",
    "wof:placetype":"venue"
},
  "geometry": {"coordinates":[-94.172667,36.194419],"type":"Point"}
}