{
  "type": "Feature",
  "properties": {
    "iso:country":"US",
    "sg:address":"206 Chestnut St",
    "sg:city":"England",
    "sg:phone":"+1 501 681 3055",
    "sg:postcode":"72046",
    "sg:province":"AR",
    "sg:tags":[
        "product",
        "farm",
        "food",
        "soybean",
        "rice",
        "cotton"
    ],
    "wof:name":"Max Foster Farms",
    "wof:placetype":"venue"
},
  "geometry": {"coordinates":[-91.952979,34.547931],"type":"Point"}
}