{
  "type": "Feature",
  "properties": {
    "addr:full":"5 Cottonwood Dr Searcy AR 72143",
    "addr:housenumber":"5",
    "addr:postcode":"72143",
    "addr:street":"Cottonwood Dr",
    "iso:country":"US",
    "sg:address":"5 Cottonwood Dr",
    "sg:city":"Searcy",
    "sg:classifiers":[
        {
            "category":"Professional",
            "subcategory":"Art Services",
            "type":"Services"
        }
    ],
    "sg:phone":"+1 501 268 1128",
    "sg:postcode":"72143",
    "sg:province":"AR",
    "sg:tags":[
        "interior",
        "designer",
        "decorator"
    ],
    "wof:name":"C C Mckay And Company",
    "wof:placetype":"venue"
},
  "geometry": {"coordinates":[-91.759975,35.240709],"type":"Point"}
}