{
  "type": "Feature",
  "properties": {
    "addr:full":"16800 Teague Rd Malvern AR 72104",
    "addr:housenumber":"16800",
    "addr:postcode":"72104",
    "addr:street":"Teague Rd",
    "iso:country":"US",
    "sg:address":"16800 Teague Rd",
    "sg:city":"Malvern",
    "sg:classifiers":[
        {
            "category":"Building & Trades",
            "subcategory":"Construction",
            "type":"Services"
        }
    ],
    "sg:phone":"+1 501 939 2308",
    "sg:postcode":"72104",
    "sg:province":"AR",
    "sg:tags":[
        "concrete",
        "contractor"
    ],
    "wof:name":"Hutzels Concrete Const Co",
    "wof:placetype":"venue"
},
  "geometry": {"coordinates":[-92.77210100000001,34.521932],"type":"Point"}
}