{
  "type": "Feature",
  "properties": {
    "addr:full":"2811 Hwy 62 W Mountain Home AR 72653",
    "addr:housenumber":"2811",
    "addr:postcode":"72653",
    "addr:street":"Hwy 62 W",
    "iso:country":"US",
    "sg:address":"2811 Hwy 62 W",
    "sg:city":"Mountain Home",
    "sg:classifiers":[
        {
            "category":"Restaurant",
            "type":"Food & Drink"
        }
    ],
    "sg:phone":"+1 870 492 4407",
    "sg:postcode":"72653",
    "sg:province":"AR",
    "wof:name":"Arby's",
    "wof:placetype":"venue"
},
  "geometry": {"coordinates":[-92.407579,36.315462],"type":"Point"}
}