{
  "type": "Feature",
  "properties": {
    "iso:country":"US",
    "sg:address":"1809 Red Wings Rd",
    "sg:city":"Bismarck",
    "sg:classifiers":[
        {
            "category":"Professional",
            "type":"Services"
        }
    ],
    "sg:phone":"+1 501 865 2736",
    "sg:postcode":"71929",
    "sg:province":"AR",
    "wof:name":"Jason M Clary",
    "wof:placetype":"venue"
},
  "geometry": {"coordinates":[-93.221773,34.303164],"type":"Point"}
}