{
  "type": "Feature",
  "properties": {
    "iso:country":"US",
    "sg:address":"1521 Towson Ave",
    "sg:city":"Fort Smith",
    "sg:classifiers":[
        {
            "category":"Autos & Motor Vehicles",
            "subcategory":"Auto Supplies",
            "type":"Retail Goods"
        }
    ],
    "sg:phone":"+1 479 441 0746",
    "sg:postcode":"72901",
    "sg:province":"AR",
    "sg:tags":[
        "automobile",
        "parts"
    ],
    "wof:name":"Chloride Battery",
    "wof:placetype":"venue"
},
  "geometry": {"coordinates":[-94.421391,35.369359],"type":"Point"}
}