{
  "type": "Feature",
  "properties": {
    "addr:full":"22809 Wilson St Mabelvale AR 72103",
    "addr:housenumber":"22809",
    "addr:postcode":"72103",
    "addr:street":"Wilson St",
    "iso:country":"US",
    "sg:address":"22809 Wilson St",
    "sg:city":"Mabelvale",
    "sg:classifiers":[
        {
            "category":"Building & Trades",
            "subcategory":"Construction",
            "type":"Services"
        }
    ],
    "sg:phone":"+1 501 602 2200",
    "sg:postcode":"72103",
    "sg:province":"AR",
    "sg:tags":[
        "repairing",
        "remodeling",
        "contractor"
    ],
    "wof:name":"Charles Waltz Home Remodeling",
    "wof:placetype":"venue"
},
  "geometry": {"coordinates":[-92.396565,34.5449],"type":"Point"}
}