{
  "type": "Feature",
  "properties": {
    "addr:full":"112 Normandy Rd Little Rock AR 72207",
    "addr:housenumber":"112",
    "addr:postcode":"72207",
    "addr:street":"Normandy Rd",
    "iso:country":"US",
    "sg:address":"112 Normandy Rd",
    "sg:city":"Little Rock",
    "sg:classifiers":[
        {
            "category":"Banks & Credit Unions",
            "subcategory":"Financial Services",
            "type":"Services"
        }
    ],
    "sg:phone":"+1 501 664 2502",
    "sg:postcode":"72207",
    "sg:province":"AR",
    "sg:tags":[
        "investment",
        "closed"
    ],
    "wof:name":"JKL Investments Ltd",
    "wof:placetype":"venue"
},
  "geometry": {"coordinates":[-92.34277899999999,34.767231],"type":"Point"}
}