{
  "type": "Feature",
  "properties": {
    "iso:country":"US",
    "sg:address":"2035 Hwy 62 W",
    "sg:city":"Mountain Home",
    "sg:classifiers":[
        {
            "category":"Professional",
            "type":"Services"
        }
    ],
    "sg:phone":"+1 870 425 8912",
    "sg:postcode":"72653",
    "sg:province":"AR",
    "sg:tags":[
        "establishment"
    ],
    "wof:name":"Teletrust Inc",
    "wof:placetype":"venue"
},
  "geometry": {"coordinates":[-92.39305899999999,36.320871],"type":"Point"}
}