{
  "type": "Feature",
  "properties": {
    "iso:country":"US",
    "sg:address":"10120 US Hwy 70",
    "sg:city":"N Little Rock",
    "sg:classifiers":[
        {
            "category":"Retail",
            "subcategory":"Auto Repair",
            "type":"Services"
        }
    ],
    "sg:phone":"+1 501 945 7679",
    "sg:postcode":"72117",
    "sg:province":"AR",
    "sg:tags":[
        "trailer"
    ],
    "wof:name":"Liberty Trailer Parts & Svc",
    "wof:placetype":"venue"
},
  "geometry": {"coordinates":[-92.15334,34.773251],"type":"Point"}
}