{
  "type": "Feature",
  "properties": {
    "iso:country":"US",
    "sg:address":"711 Higdon Ferry Rd",
    "sg:city":"Hot Springs National Park",
    "sg:classifiers":[
        {
            "category":"Real Estate",
            "subcategory":"Real Estate Agent",
            "type":"Services"
        }
    ],
    "sg:phone":"+1 501 520 4800",
    "sg:postcode":"71913",
    "sg:province":"AR",
    "wof:name":"Prime Realty & Management Co",
    "wof:placetype":"venue"
},
  "geometry": {"coordinates":[-93.061871,34.477905],"type":"Point"}
}