{
  "type": "Feature",
  "properties": {
    "iso:country":"US",
    "sg:address":"1100 W Henri de Tonti Blvd",
    "sg:city":"Springdale",
    "sg:classifiers":[
        {
            "category":"Real Estate",
            "subcategory":"Real Estate Services",
            "type":"Services"
        },
        {
            "category":"Real Estate",
            "subcategory":"Real Estate Agent",
            "type":"Services"
        }
    ],
    "sg:phone":"+1 479 750 2772",
    "sg:postcode":"72762",
    "sg:province":"AR",
    "sg:tags":[
        "buyer",
        "management",
        "broker"
    ],
    "sg:website":"http://www.propertystore.com",
    "wof:name":"Real Estate Education Center",
    "wof:placetype":"venue"
},
  "geometry": {"coordinates":[-94.250567,36.176737],"type":"Point"}
}