{
  "type": "Feature",
  "properties": {
    "iso:country":"US",
    "sg:address":"1843 E Highland Dr",
    "sg:city":"Jonesboro",
    "sg:classifiers":[
        {
            "category":"Shopping",
            "subcategory":"Department Store",
            "type":"Retail Goods"
        },
        {
            "category":"Shopping",
            "subcategory":"Clothing, Apparel, & Fashions",
            "type":"Retail Goods"
        }
    ],
    "sg:phone":"+1 870 931 9643",
    "sg:postcode":"72401",
    "sg:province":"AR",
    "sg:tags":[
        "family"
    ],
    "sg:website":"www.goodysonline.com",
    "wof:name":"Goodys Family Clothing 191",
    "wof:placetype":"venue"
},
  "geometry": {"coordinates":[-90.686024,35.821151],"type":"Point"}
}