{
  "type": "Feature",
  "properties": {
    "addr:full":"425 NW 4th St Walnut Ridge AR 72476",
    "addr:housenumber":"425",
    "addr:postcode":"72476",
    "addr:street":"Nw 4Th St",
    "iso:country":"US",
    "sg:address":"425 NW 4th St",
    "sg:city":"Walnut Ridge",
    "sg:classifiers":[
        {
            "category":"Restaurant",
            "type":"Food & Drink"
        }
    ],
    "sg:menulink":"http://www.allmenus.com/ar/campbell/231375-sonic/menu/",
    "sg:phone":"+1 870 886 5558",
    "sg:postcode":"72476",
    "sg:province":"AR",
    "sg:tags":[
        "burger",
        "american"
    ],
    "wof:name":"Sonic",
    "wof:placetype":"venue"
},
  "geometry": {"coordinates":[-90.955558,36.072472],"type":"Point"}
}