{
  "type": "Feature",
  "properties": {
    "iso:country":"US",
    "sg:address":"2170 N Central Ave",
    "sg:city":"Batesville",
    "sg:classifiers":[
        {
            "category":"Restaurant",
            "type":"Food & Drink"
        }
    ],
    "sg:phone":"+1 870 698 9088",
    "sg:postcode":"72501",
    "sg:province":"AR",
    "wof:name":"E & B Bigger Burgers",
    "wof:placetype":"venue"
},
  "geometry": {"coordinates":[-91.661506,35.785089],"type":"Point"}
}