{
  "type": "Feature",
  "properties": {
    "addr:full":"196 Hawthicket Rd Mount Vernon AR 72111",
    "addr:housenumber":"196",
    "addr:postcode":"72111",
    "addr:street":"Hawthicket Rd",
    "iso:country":"US",
    "sg:address":"196 Hawthicket Rd",
    "sg:city":"Mount Vernon",
    "sg:classifiers":[
        {
            "category":"Utilities",
            "subcategory":"Refuse",
            "type":"Services"
        }
    ],
    "sg:phone":"+1 501 849 3408",
    "sg:postcode":"72111",
    "sg:province":"AR",
    "sg:tags":[
        "system"
    ],
    "wof:name":"King Trash Service",
    "wof:placetype":"venue"
},
  "geometry": {"coordinates":[-92.11639599999999,35.190673],"type":"Point"}
}