{
  "type": "Feature",
  "properties": {
    "iso:country":"US",
    "sg:address":"301 E 6th St",
    "sg:city":"Mountain Home",
    "sg:classifiers":[
        {
            "category":"Government",
            "subcategory":"Office",
            "type":"Public Place"
        }
    ],
    "sg:phone":"+1 870 425 8910",
    "sg:postcode":"72653",
    "sg:province":"AR",
    "sg:tags":[
        "village"
    ],
    "wof:name":"Baxter County Small Claims",
    "wof:placetype":"venue"
},
  "geometry": {"coordinates":[-92.38194,36.33538],"type":"Point"}
}