{
  "type": "Feature",
  "properties": {
    "iso:country":"US",
    "sg:address":"322 Caddo Trl",
    "sg:city":"Jacksonville",
    "sg:classifiers":[
        {
            "category":"Building & Trades",
            "subcategory":"Construction",
            "type":"Services"
        }
    ],
    "sg:phone":"+1 501 982 6770",
    "sg:postcode":"72076",
    "sg:province":"AR",
    "sg:tags":[
        "roofing",
        "contractor"
    ],
    "wof:name":"David Teague Roofing Inc",
    "wof:placetype":"venue"
},
  "geometry": {"coordinates":[-92.074512,34.846221],"type":"Point"}
}