{
  "type": "Feature",
  "properties": {
    "iso:country":"US",
    "sg:address":"3200 S 2nd Ave",
    "sg:city":"Paragould",
    "sg:classifiers":[
        {
            "category":"Professional",
            "type":"Services"
        }
    ],
    "sg:phone":"+1 870 335 9505",
    "sg:postcode":"72450",
    "sg:province":"AR",
    "sg:tags":[
        "establishment"
    ],
    "wof:name":"Earthgrain Co",
    "wof:placetype":"venue"
},
  "geometry": {"coordinates":[-90.486053,36.026998],"type":"Point"}
}