{
  "type": "Feature",
  "properties": {
    "iso:country":"US",
    "sg:address":"42 Stevens Rd",
    "sg:city":"Conway",
    "sg:phone":"+1 501 327 5580",
    "sg:postcode":"72032",
    "sg:province":"AR",
    "sg:tags":[
        "sorting",
        "money",
        "bill",
        "wrapping",
        "machine",
        "equipment",
        "handling",
        "coin",
        "counting"
    ],
    "wof:name":"L & L Systems Inc",
    "wof:placetype":"venue"
},
  "geometry": {"coordinates":[-92.383002,35.116884],"type":"Point"}
}