{
  "type": "Feature",
  "properties": {
    "iso:country":"US",
    "sg:address":"152 N Main St",
    "sg:city":"Dumas",
    "sg:classifiers":[
        {
            "category":"Restaurant",
            "type":"Food & Drink"
        }
    ],
    "sg:phone":"+1 870 382 4922",
    "sg:postcode":"71639",
    "sg:province":"AR",
    "sg:tags":[
        "house",
        "steak",
        "barbecue"
    ],
    "wof:name":"Hall's B B Q",
    "wof:placetype":"venue"
},
  "geometry": {"coordinates":[-91.492437,33.888952],"type":"Point"}
}