{
  "type": "Feature",
  "properties": {
    "iso:country":"US",
    "sg:address":"13 Brookway Dr",
    "sg:city":"North Little Rock",
    "sg:classifiers":[
        {
            "category":"Retail",
            "subcategory":"Portrait Studio",
            "type":"Services"
        }
    ],
    "sg:phone":"+1 501 835 4138",
    "sg:postcode":"72120",
    "sg:province":"AR",
    "sg:tags":[
        "photo"
    ],
    "wof:name":"Bakers Photography",
    "wof:placetype":"venue"
},
  "geometry": {"coordinates":[-92.238128,34.87917],"type":"Point"}
}