{
  "type": "Feature",
  "properties": {
    "iso:country":"US",
    "sg:address":"323 Robin Ln",
    "sg:city":"Walnut Ridge",
    "sg:classifiers":[
        {
            "category":"Building & Trades",
            "subcategory":"Cleaning & Sanitation",
            "type":"Services"
        }
    ],
    "sg:phone":"+1 870 886 2832",
    "sg:postcode":"72476",
    "sg:province":"AR",
    "sg:tags":[
        "maintenance"
    ],
    "wof:name":"Dewys Janitorial & Lawn Svc",
    "wof:placetype":"venue"
},
  "geometry": {"coordinates":[-90.941541,36.069727],"type":"Point"}
}