{
  "type": "Feature",
  "properties": {
    "iso:country":"US",
    "sg:address":"1101 Central Blvd",
    "sg:city":"Bull Shoals",
    "sg:classifiers":[
        {
            "category":"Restaurant",
            "type":"Food & Drink"
        }
    ],
    "sg:phone":"+1 870 445 4100",
    "sg:postcode":"72619",
    "sg:province":"AR",
    "wof:name":"Bush's Pizza & More",
    "wof:placetype":"venue"
},
  "geometry": {"coordinates":[-92.58653,36.383955],"type":"Point"}
}