{
  "type": "Feature",
  "properties": {
    "iso:country":"US",
    "sg:address":"67 Hope Dr",
    "sg:city":"Bella Vista",
    "sg:classifiers":[
        {
            "category":"Professional",
            "subcategory":"Research",
            "type":"Services"
        }
    ],
    "sg:phone":"+1 479 855 0962",
    "sg:postcode":"72715",
    "sg:province":"AR",
    "sg:tags":[
        "commercial",
        "physical"
    ],
    "wof:name":"Trager Technologies Inc",
    "wof:placetype":"venue"
},
  "geometry": {"coordinates":[-94.267761,36.4872],"type":"Point"}
}