{
  "type": "Feature",
  "properties": {
    "iso:country":"US",
    "sg:address":"6712 State Hwy 161",
    "sg:city":"North Little Rock",
    "sg:classifiers":[
        {
            "category":"Bars & Pubs",
            "type":"Food & Drink"
        }
    ],
    "sg:phone":"+1 501 833 0414",
    "sg:postcode":"72117",
    "sg:province":"AR",
    "sg:tags":[
        "drinking"
    ],
    "wof:name":"Chiefs Bar",
    "wof:placetype":"venue"
},
  "geometry": {"coordinates":[-92.17653,34.811026],"type":"Point"}
}