{
  "type": "Feature",
  "properties": {
    "iso:country":"US",
    "sg:address":"2447 N Lakeshore Dr",
    "sg:city":"Lake Village",
    "sg:classifiers":[
        {
            "category":"Professional",
            "type":"Services"
        }
    ],
    "sg:phone":"+1 870 265 2401",
    "sg:postcode":"71653",
    "sg:province":"AR",
    "wof:name":"Loretta L Williamson",
    "wof:placetype":"venue"
},
  "geometry": {"coordinates":[-91.27262399999999,33.347978],"type":"Point"}
}