{
  "type": "Feature",
  "properties": {
    "iso:country":"US",
    "sg:address":"507 Pope Dr",
    "sg:city":"Benton",
    "sg:classifiers":[
        {
            "category":"Manufacturing",
            "subcategory":"Metals",
            "type":"Manufacturing & Wholesale Goods"
        }
    ],
    "sg:phone":"+1 501 776 2779",
    "sg:postcode":"72015",
    "sg:province":"AR",
    "sg:tags":[
        "metalwork",
        "architectural",
        "mfg"
    ],
    "wof:name":"Confederate Ironworks Inc",
    "wof:placetype":"venue"
},
  "geometry": {"coordinates":[-92.547786,34.557616],"type":"Point"}
}