{
  "type": "Feature",
  "properties": {
    "addr:full":"1021 Shobe Rd Bryant AR 72022",
    "addr:housenumber":"1021",
    "addr:postcode":"72022",
    "addr:street":"Shobe Rd",
    "iso:country":"US",
    "sg:address":"1021 Shobe Rd",
    "sg:city":"Bryant",
    "sg:classifiers":[
        {
            "category":"Manufacturing",
            "subcategory":"Signs",
            "type":"Manufacturing & Wholesale Goods"
        }
    ],
    "sg:phone":"+1 501 952 4796",
    "sg:postcode":"72022",
    "sg:province":"AR",
    "sg:tags":[
        "graphic",
        "advertising",
        "designer",
        "specialty"
    ],
    "wof:name":"Jim Walters Sign & Graphics",
    "wof:placetype":"venue"
},
  "geometry": {"coordinates":[-92.482491,34.613673],"type":"Point"}
}