{
  "type": "Feature",
  "properties": {
    "addr:full":"2825 Race St Jonesboro AR 72401",
    "addr:housenumber":"2825",
    "addr:postcode":"72401",
    "addr:street":"Race St",
    "iso:country":"US",
    "sg:address":"2825 Race St",
    "sg:city":"Jonesboro",
    "sg:classifiers":[
        {
            "category":"Retail",
            "subcategory":"Auto Repair",
            "type":"Services"
        }
    ],
    "sg:phone":"+1 870 972 6440",
    "sg:postcode":"72401",
    "sg:province":"AR",
    "sg:tags":[
        "repairing",
        "automobile",
        "part",
        "supply"
    ],
    "wof:name":"Gerald's Automotive Service",
    "wof:placetype":"venue"
},
  "geometry": {"coordinates":[-90.672057,35.813958],"type":"Point"}
}