{
  "type": "Feature",
  "properties": {
    "iso:country":"US",
    "sg:address":"4205 Longview Rd",
    "sg:city":"Little Rock",
    "sg:classifiers":[
        {
            "category":"Retail",
            "subcategory":"Animal Services",
            "type":"Services"
        }
    ],
    "sg:phone":"+1 501 868 4882",
    "sg:postcode":"72212",
    "sg:province":"AR",
    "wof:name":"J & J Stables",
    "wof:placetype":"venue"
},
  "geometry": {"coordinates":[-92.428636,34.790929],"type":"Point"}
}