{
  "type": "Feature",
  "properties": {
    "iso:country":"US",
    "sg:address":"2110 W Beebe Capps Expy",
    "sg:city":"Searcy",
    "sg:classifiers":[
        {
            "category":"Personal",
            "subcategory":"Beauty Salon",
            "type":"Services"
        }
    ],
    "sg:phone":"+1 501 368 8787",
    "sg:postcode":"72143",
    "sg:province":"AR",
    "sg:tags":[
        "manicuring"
    ],
    "wof:name":"Contempo Nails",
    "wof:placetype":"venue"
},
  "geometry": {"coordinates":[-91.76907,35.247528],"type":"Point"}
}