{
  "type": "Feature",
  "properties": {
    "iso:country":"US",
    "sg:address":"161 Wilson Mill Rd",
    "sg:city":"Monticello",
    "sg:classifiers":[
        {
            "category":"Professional",
            "type":"Services"
        }
    ],
    "sg:phone":"+1 870 224 2393",
    "sg:postcode":"71655",
    "sg:province":"AR",
    "sg:tags":[
        "forestry",
        "consulting"
    ],
    "wof:name":"Meek Forestry",
    "wof:placetype":"venue"
},
  "geometry": {"coordinates":[-91.794834,33.579449],"type":"Point"}
}