{
  "type": "Feature",
  "properties": {
    "iso:country":"US",
    "sg:address":"5613 Cache Rd",
    "sg:city":"Paragould",
    "sg:classifiers":[
        {
            "category":"Personal",
            "subcategory":"Barber",
            "type":"Services"
        }
    ],
    "sg:phone":"+1 870 236 1302",
    "sg:postcode":"72450",
    "sg:province":"AR",
    "sg:tags":[
        "shop"
    ],
    "wof:name":"Bobs Barber Shop",
    "wof:placetype":"venue"
},
  "geometry": {"coordinates":[-90.55778599999999,36.06745],"type":"Point"}
}