{
  "type": "Feature",
  "properties": {
    "iso:country":"US",
    "sg:address":"196 Grant 748",
    "sg:city":"Sheridan",
    "sg:classifiers":[
        {
            "category":"Banks & Credit Unions",
            "subcategory":"Financial Services",
            "type":"Services"
        }
    ],
    "sg:phone":"+1 870 942 8344",
    "sg:postcode":"72150",
    "sg:province":"AR",
    "sg:tags":[
        "management",
        "open",
        "investment"
    ],
    "wof:name":"KASH Land Inc",
    "wof:placetype":"venue"
},
  "geometry": {"coordinates":[-92.361357,34.313894],"type":"Point"}
}