{
  "type": "Feature",
  "properties": {
    "iso:country":"US",
    "sg:address":"15717 Taylor Loop Rd",
    "sg:city":"Little Rock",
    "sg:classifiers":[
        {
            "category":"Social Services",
            "subcategory":"Child Care",
            "type":"Services"
        },
        {
            "category":"Education",
            "subcategory":"School",
            "type":"Public Place"
        }
    ],
    "sg:phone":"+1 501 868 6030",
    "sg:postcode":"72223",
    "sg:province":"AR",
    "sg:tags":[
        "day"
    ],
    "wof:name":"Chanel Valley Montessori Schl",
    "wof:placetype":"venue"
},
  "geometry": {"coordinates":[-92.446883,34.795887],"type":"Point"}
}