{
  "type": "Feature",
  "properties": {
    "addr:full":"3430 W Sunset Ave Springdale AR 72762",
    "addr:housenumber":"3430",
    "addr:postcode":"72762",
    "addr:street":"W Sunset Ave",
    "iso:country":"US",
    "sg:address":"3430 W Sunset Ave",
    "sg:city":"Springdale",
    "sg:classifiers":[
        {
            "category":"Shopping",
            "subcategory":"Discount & Variety Stores",
            "type":"Retail Goods"
        }
    ],
    "sg:phone":"+1 479 927 1212",
    "sg:postcode":"72762",
    "sg:province":"AR",
    "wof:name":"Dollar General",
    "wof:placetype":"venue"
},
  "geometry": {"coordinates":[-94.167658,36.175133],"type":"Point"}
}