{
  "type": "Feature",
  "properties": {
    "iso:country":"US",
    "sg:address":"400 W Capitol Ave",
    "sg:city":"Little Rock",
    "sg:classifiers":[
        {
            "category":"Real Estate",
            "subcategory":"Real Estate Agent",
            "type":"Services"
        }
    ],
    "sg:phone":"+1 501 372 6161",
    "sg:postcode":"72201",
    "sg:province":"AR",
    "sg:tags":[
        "management"
    ],
    "sg:website":"www.dicksonflakepartners.com",
    "wof:name":"Colliers Dickson Flake Partner",
    "wof:placetype":"venue"
},
  "geometry": {"coordinates":[-92.27587699999999,34.744814],"type":"Point"}
}