{
  "type": "Feature",
  "properties": {
    "iso:country":"US",
    "sg:address":"105 N Rodney Parham Rd",
    "sg:city":"Little Rock",
    "sg:classifiers":[
        {
            "category":"Shopping",
            "subcategory":"Used Merchandise",
            "type":"Retail Goods"
        }
    ],
    "sg:phone":"+1 501 225 0100",
    "sg:postcode":"72205",
    "sg:province":"AR",
    "sg:tags":[
        "antique"
    ],
    "wof:name":"Little Rock Antq & Flea Market",
    "wof:placetype":"venue"
},
  "geometry": {"coordinates":[-92.36762,34.753489],"type":"Point"}
}