{
  "type": "Feature",
  "properties": {
    "iso:country":"US",
    "sg:address":"1853 E Briarcliff St",
    "sg:city":"Fayetteville",
    "sg:classifiers":[
        {
            "category":"Building & Trades",
            "subcategory":"Construction",
            "type":"Services"
        }
    ],
    "sg:phone":"+1 479 582 0540",
    "sg:postcode":"72703",
    "sg:province":"AR",
    "sg:tags":[
        "electrical",
        "contractor"
    ],
    "wof:name":"American Electrical Svcs & RPS",
    "wof:placetype":"venue"
},
  "geometry": {"coordinates":[-94.13645200000001,36.108554],"type":"Point"}
}