{
  "type": "Feature",
  "properties": {
    "iso:country":"US",
    "sg:address":"19439 Lawson Rd",
    "sg:city":"Little Rock",
    "sg:classifiers":[
        {
            "category":"Organizations",
            "subcategory":"Religious Organization",
            "type":"Services"
        }
    ],
    "sg:phone":"+1 501 821 2588",
    "sg:postcode":"72210",
    "sg:province":"AR",
    "wof:name":"Southwest Church of Christ",
    "wof:placetype":"venue"
},
  "geometry": {"coordinates":[-92.513437,34.71759],"type":"Point"}
}