{
  "type": "Feature",
  "properties": {
    "addr:full":"7401 Sulphur Springs Rd Pine Bluff AR 71603",
    "addr:housenumber":"7401",
    "addr:postcode":"71603",
    "addr:street":"Sulphur Springs Rd",
    "iso:country":"US",
    "sg:address":"7401 Sulphur Springs Rd",
    "sg:city":"Pine Bluff",
    "sg:classifiers":[
        {
            "category":"Personal",
            "type":"Services"
        }
    ],
    "sg:phone":"+1 870 879 9952",
    "sg:postcode":"71603",
    "sg:province":"AR",
    "sg:tags":[
        "credit",
        "debt",
        "counseling"
    ],
    "wof:name":"Credit Doctor",
    "wof:placetype":"venue"
},
  "geometry": {"coordinates":[-92.106407,34.181121],"type":"Point"}
}