{
  "type": "Feature",
  "properties": {
    "iso:country":"US",
    "sg:address":"7420 Enmar Dr",
    "sg:city":"Little Rock",
    "sg:classifiers":[
        {
            "category":"Wholesale",
            "subcategory":"Construction Materials",
            "type":"Manufacturing & Wholesale Goods"
        }
    ],
    "sg:phone":"+1 501 562 3112",
    "sg:postcode":"72209",
    "sg:province":"AR",
    "sg:tags":[
        "metal",
        "component"
    ],
    "wof:name":"Metal Direct Inc",
    "wof:placetype":"venue"
},
  "geometry": {"coordinates":[-92.349396,34.680431],"type":"Point"}
}