{
  "type": "Feature",
  "properties": {
    "iso:country":"US",
    "sg:address":"1701 S Main St",
    "sg:city":"Hope",
    "sg:classifiers":[
        {
            "category":"Education",
            "subcategory":"School",
            "type":"Public Place"
        }
    ],
    "sg:phone":"+1 870 777 3451",
    "sg:postcode":"71801",
    "sg:province":"AR",
    "wof:name":"Hope High School",
    "wof:placetype":"venue"
},
  "geometry": {"coordinates":[-93.586998,33.652908],"type":"Point"}
}