{
  "type": "Feature",
  "properties": {
    "iso:country":"US",
    "sg:address":"1901 N Buerkle St",
    "sg:city":"Stuttgart",
    "sg:classifiers":[
        {
            "category":"Health Services",
            "subcategory":"Doctor",
            "type":"Services"
        }
    ],
    "sg:phone":"+1 870 673 7211",
    "sg:postcode":"72160",
    "sg:province":"AR",
    "sg:tags":[
        "medical"
    ],
    "wof:name":"Carl Northcutt MD",
    "wof:placetype":"venue"
},
  "geometry": {"coordinates":[-91.55745,34.52147],"type":"Point"}
}