{
  "type": "Feature",
  "properties": {
    "addr:full":"1390 E Robinson Ave Springdale AR 72764",
    "addr:housenumber":"1390",
    "addr:postcode":"72764",
    "addr:street":"E Robinson Ave",
    "iso:country":"US",
    "sg:address":"1390 E Robinson Ave",
    "sg:city":"Springdale",
    "sg:classifiers":[
        {
            "category":"Real Estate",
            "subcategory":"Real Estate Operator",
            "type":"Services"
        }
    ],
    "sg:phone":"+1 479 750 0525",
    "sg:postcode":"72764",
    "sg:province":"AR",
    "sg:tags":[
        "mall",
        "shopping",
        "center"
    ],
    "wof:name":"Grand Plaza Auto Mall",
    "wof:placetype":"venue"
},
  "geometry": {"coordinates":[-94.11757,36.166986],"type":"Point"}
}