{
  "type": "Feature",
  "properties": {
    "addr:full":"211 N 23rd St Paragould AR 72450",
    "addr:housenumber":"211",
    "addr:postcode":"72450",
    "addr:street":"N 23Rd St",
    "iso:country":"US",
    "sg:address":"211 N 23rd St",
    "sg:city":"Paragould",
    "sg:classifiers":[
        {
            "category":"Personal",
            "subcategory":"Beauty Salon",
            "type":"Services"
        }
    ],
    "sg:phone":"+1 870 236 6266",
    "sg:postcode":"72450",
    "sg:province":"AR",
    "sg:tags":[
        "shop"
    ],
    "wof:name":"First Class Cuts",
    "wof:placetype":"venue"
},
  "geometry": {"coordinates":[-90.51501399999999,36.060646],"type":"Point"}
}