{
  "type": "Feature",
  "properties": {
    "iso:country":"US",
    "sg:address":"2919 S Arkansas Ave",
    "sg:city":"Russellville",
    "sg:classifiers":[
        {
            "category":"Manufacturing",
            "subcategory":"Printing",
            "type":"Manufacturing & Wholesale Goods"
        }
    ],
    "sg:phone":"+1 479 498 2380",
    "sg:postcode":"72802",
    "sg:province":"AR",
    "sg:tags":[
        "publishing"
    ],
    "wof:name":"Circle G Express Inc",
    "wof:placetype":"venue"
},
  "geometry": {"coordinates":[-93.137212,35.249273],"type":"Point"}
}