{
  "type": "Feature",
  "properties": {
    "iso:country":"US",
    "sg:address":"711 E Main St",
    "sg:city":"Magnolia",
    "sg:classifiers":[
        {
            "category":"Shopping",
            "subcategory":"Clothing, Apparel, & Fashions",
            "type":"Retail Goods"
        }
    ],
    "sg:phone":"+1 870 234 6611",
    "sg:postcode":"71753",
    "sg:province":"AR",
    "wof:name":"J C Penney Catalog Merchant",
    "wof:placetype":"venue"
},
  "geometry": {"coordinates":[-93.231014,33.266811],"type":"Point"}
}