{
  "type": "Feature",
  "properties": {
    "addr:full":"10576 Flag Slough Ln Weiner AR 72479",
    "addr:housenumber":"10576",
    "addr:postcode":"72479",
    "addr:street":"Flag Slough Ln",
    "iso:country":"US",
    "sg:address":"10576 Flag Slough Ln",
    "sg:city":"Weiner",
    "sg:classifiers":[
        {
            "category":"Recreation",
            "type":"Entertainment"
        }
    ],
    "sg:phone":"+1 870 684 2281",
    "sg:postcode":"72479",
    "sg:province":"AR",
    "sg:tags":[
        "parks"
    ],
    "wof:name":"Bayou Deview Wma",
    "wof:placetype":"venue"
},
  "geometry": {"coordinates":[-90.965594,35.613215],"type":"Point"}
}