{
  "type": "Feature",
  "properties": {
    "addr:full":"311 Airport Rd Bentonville AR 72712",
    "addr:housenumber":"311",
    "addr:postcode":"72712",
    "addr:street":"Airport Rd",
    "iso:country":"US",
    "sg:address":"311 Airport Rd",
    "sg:city":"Bentonville",
    "sg:classifiers":[
        {
            "category":"Wholesale",
            "subcategory":"Machinery & Supplies",
            "type":"Manufacturing & Wholesale Goods"
        }
    ],
    "sg:phone":"+1 479 464 7699",
    "sg:postcode":"72712",
    "sg:province":"AR",
    "sg:tags":[
        "equipment",
        "irrigation",
        "system"
    ],
    "wof:name":"Keeling Co",
    "wof:placetype":"venue"
},
  "geometry": {"coordinates":[-94.21417099999999,36.342877],"type":"Point"}
}