{
  "type": "Feature",
  "properties": {
    "iso:country":"US",
    "sg:address":"11421 State Hwy 27",
    "sg:city":"Hector",
    "sg:classifiers":[
        {
            "category":"Organizations",
            "subcategory":"Religious Organization",
            "type":"Services"
        }
    ],
    "sg:phone":"+1 479 284 3026",
    "sg:postcode":"72843",
    "sg:province":"AR",
    "sg:tags":[
        "church"
    ],
    "wof:name":"Assembly Of God Church",
    "wof:placetype":"venue"
},
  "geometry": {"coordinates":[-92.974662,35.468129],"type":"Point"}
}