{
  "type": "Feature",
  "properties": {
    "iso:country":"US",
    "sg:address":"5411 E Nettleton Ave",
    "sg:city":"Jonesboro",
    "sg:classifiers":[
        {
            "category":"Social Services",
            "subcategory":"Child Care",
            "type":"Services"
        },
        {
            "category":"Education",
            "subcategory":"Preschool",
            "type":"Public Place"
        }
    ],
    "sg:phone":"+1 870 268 6599",
    "sg:postcode":"72401",
    "sg:province":"AR",
    "sg:tags":[
        "kindergarten",
        "nursery",
        "day"
    ],
    "wof:name":"Munchkin Land Child Care & Learning Center",
    "wof:placetype":"venue"
},
  "geometry": {"coordinates":[-90.640644,35.810736],"type":"Point"}
}