{
  "type": "Feature",
  "properties": {
    "addr:full":"1919 Albert Pike Rd Hot Springs AR 71913",
    "addr:housenumber":"1919",
    "addr:postcode":"71913",
    "addr:street":"Albert Pike Rd",
    "iso:country":"US",
    "sg:address":"1919 Albert Pike Rd",
    "sg:city":"Hot Springs",
    "sg:classifiers":[
        {
            "category":"Autos & Motor Vehicles",
            "subcategory":"Automobile Sales",
            "type":"Retail Goods"
        }
    ],
    "sg:phone":"+1 501 318 3030",
    "sg:postcode":"71913",
    "sg:province":"AR",
    "sg:tags":[
        "car",
        "dealer"
    ],
    "wof:name":"Car Depot Of Hot Springs",
    "wof:placetype":"venue"
},
  "geometry": {"coordinates":[-93.09755699999999,34.493939],"type":"Point"}
}