{
  "type": "Feature",
  "properties": {
    "iso:country":"US",
    "sg:address":"1501 S Ohio St",
    "sg:city":"Pine Bluff",
    "sg:classifiers":[
        {
            "category":"Retail",
            "subcategory":"Repair Shop",
            "type":"Services"
        }
    ],
    "sg:phone":"+1 870 535 7714",
    "sg:postcode":"71601",
    "sg:province":"AR",
    "sg:tags":[
        "upholsterer"
    ],
    "wof:name":"Nickolsons Auto Upholstery",
    "wof:placetype":"venue"
},
  "geometry": {"coordinates":[-91.989492,34.217408],"type":"Point"}
}