{
  "type": "Feature",
  "properties": {
    "addr:full":"5440 S 66th St Fort Smith AR 72903",
    "addr:housenumber":"5440",
    "addr:postcode":"72903",
    "addr:street":"S 66Th St",
    "iso:country":"US",
    "sg:address":"5440 S 66th St",
    "sg:city":"Fort Smith",
    "sg:classifiers":[
        {
            "category":"Wholesale",
            "subcategory":"Stationery",
            "type":"Manufacturing & Wholesale Goods"
        }
    ],
    "sg:phone":"+1 479 648 2900",
    "sg:postcode":"72903",
    "sg:province":"AR",
    "sg:tags":[
        "product",
        "paper"
    ],
    "wof:name":"Xpedx",
    "wof:placetype":"venue"
},
  "geometry": {"coordinates":[-94.36072799999999,35.327318],"type":"Point"}
}