{
  "type": "Feature",
  "properties": {
    "addr:full":"330 N Main St Waldron AR 72958",
    "addr:housenumber":"330",
    "addr:postcode":"72958",
    "addr:street":"N Main St",
    "iso:country":"US",
    "sg:address":"330 N Main St",
    "sg:city":"Waldron",
    "sg:classifiers":[
        {
            "category":"Shopping",
            "subcategory":"Gifts & Souvenirs",
            "type":"Retail Goods"
        },
        {
            "category":"Shopping",
            "subcategory":"Florist",
            "type":"Retail Goods"
        }
    ],
    "sg:phone":"+1 479 637 4401",
    "sg:postcode":"72958",
    "sg:province":"AR",
    "sg:tags":[
        "shop"
    ],
    "wof:name":"The Gift Box & Flowers Inc",
    "wof:placetype":"venue"
},
  "geometry": {"coordinates":[-94.091285,34.902486],"type":"Point"}
}