{
  "type": "Feature",
  "properties": {
    "addr:full":"424 Central Ave Hot Springs AR 71901",
    "addr:housenumber":"424",
    "addr:postcode":"71901",
    "addr:street":"Central Ave",
    "iso:country":"US",
    "sg:address":"424 Central Ave",
    "sg:city":"Hot Springs",
    "sg:classifiers":[
        {
            "category":"Shopping",
            "subcategory":"Gifts & Souvenirs",
            "type":"Retail Goods"
        }
    ],
    "sg:phone":"+1 501 624 8787",
    "sg:postcode":"71901",
    "sg:province":"AR",
    "sg:tags":[
        "collectible"
    ],
    "wof:name":"Candlelight Galleria",
    "wof:placetype":"venue"
},
  "geometry": {"coordinates":[-93.054002,34.513425],"type":"Point"}
}