{
  "type": "Feature",
  "properties": {
    "addr:full":"2316 Cantrell Rd Little Rock AR 72202",
    "addr:housenumber":"2316",
    "addr:postcode":"72202",
    "addr:street":"Cantrell Rd",
    "iso:country":"US",
    "sg:address":"2316 Cantrell Rd",
    "sg:city":"Little Rock",
    "sg:classifiers":[
        {
            "category":"Wholesale",
            "subcategory":"Sporting Goods",
            "type":"Manufacturing & Wholesale Goods"
        }
    ],
    "sg:phone":"+1 501 537 6255",
    "sg:postcode":"72202",
    "sg:province":"AR",
    "wof:name":"Country Sport",
    "wof:placetype":"venue"
},
  "geometry": {"coordinates":[-92.303012,34.758171],"type":"Point"}
}