{
  "type": "Feature",
  "properties": {
    "iso:country":"US",
    "sg:address":"11500 Cord Rd",
    "sg:city":"Cord",
    "sg:classifiers":[
        {
            "category":"Farming",
            "subcategory":"Farm",
            "type":"Manufacturing & Wholesale Goods"
        }
    ],
    "sg:phone":"+1 870 528 4901",
    "sg:postcode":"72524",
    "sg:province":"AR",
    "sg:tags":[
        "crop",
        "general"
    ],
    "wof:name":"Dickey Darrell L& Jo Ann",
    "wof:placetype":"venue"
},
  "geometry": {"coordinates":[-91.305666,35.883123],"type":"Point"}
}