{
  "type": "Feature",
  "properties": {
    "iso:country":"US",
    "sg:address":"5623 Kavanaugh Blvd",
    "sg:city":"Little Rock",
    "sg:classifiers":[
        {
            "category":"Personal",
            "subcategory":"Beauty Salon",
            "type":"Services"
        }
    ],
    "sg:phone":"+1 501 960 4894",
    "sg:postcode":"72207",
    "sg:province":"AR",
    "sg:tags":[
        "treatment",
        "skin"
    ],
    "wof:name":"Alchemy Shop Little Rock",
    "wof:placetype":"venue"
},
  "geometry": {"coordinates":[-92.336955,34.770146],"type":"Point"}
}