{
  "type": "Feature",
  "properties": {
    "iso:country":"US",
    "sg:address":"2808 Mockingbird Ln",
    "sg:city":"Arkadelphia",
    "sg:classifiers":[
        {
            "category":"Professional",
            "subcategory":"Computer Services",
            "type":"Services"
        }
    ],
    "sg:phone":"+1 870 403 7718",
    "sg:postcode":"71923",
    "sg:province":"AR",
    "sg:tags":[
        "website",
        "design"
    ],
    "wof:name":"Z Total",
    "wof:placetype":"venue"
},
  "geometry": {"coordinates":[-93.084915,34.119052],"type":"Point"}
}