{
  "type": "Feature",
  "properties": {
    "iso:country":"US",
    "sg:address":"1410 N Arkansas Ave",
    "sg:city":"Russellville",
    "sg:classifiers":[
        {
            "category":"Restaurant",
            "type":"Food & Drink"
        }
    ],
    "sg:phone":"+1 479 968 1410",
    "sg:postcode":"72801",
    "sg:province":"AR",
    "sg:website":"www.whataburger.com",
    "wof:name":"Whataburger",
    "wof:placetype":"venue"
},
  "geometry": {"coordinates":[-93.133259,35.292794],"type":"Point"}
}