{
  "type": "Feature",
  "properties": {
    "iso:country":"US",
    "sg:address":"2813 SW 14th St",
    "sg:city":"Bentonville",
    "sg:classifiers":[
        {
            "category":"Insurance",
            "subcategory":"Hazard Insurance",
            "type":"Services"
        }
    ],
    "sg:phone":"+1 479 271 5333",
    "sg:postcode":"72712",
    "sg:province":"AR",
    "sg:tags":[
        "bond"
    ],
    "wof:name":"First Arkansas Bail Bonds",
    "wof:placetype":"venue"
},
  "geometry": {"coordinates":[-94.242952,36.357553],"type":"Point"}
}