{
  "type": "Feature",
  "properties": {
    "addr:full":"2119 W Beebe Capps Expy Searcy AR 72143",
    "addr:housenumber":"2119",
    "addr:postcode":"72143",
    "addr:street":"W Beebe Capps Expy",
    "iso:country":"US",
    "sg:address":"2119 W Beebe Capps Expy",
    "sg:city":"Searcy",
    "sg:classifiers":[
        {
            "category":"Professional",
            "subcategory":"Employment Agencies",
            "type":"Services"
        }
    ],
    "sg:phone":"+1 501 268 4700",
    "sg:postcode":"72143",
    "sg:province":"AR",
    "sg:tags":[
        "opportunity"
    ],
    "sg:website":"www.expresspersonnel.com",
    "wof:name":"Express Personnel Svc",
    "wof:placetype":"venue"
},
  "geometry": {"coordinates":[-91.761782,35.247151],"type":"Point"}
}