{
  "type": "Feature",
  "properties": {
    "iso:country":"US",
    "sg:address":"308 W Commercial St",
    "sg:city":"Ozark",
    "sg:classifiers":[
        {
            "category":"Retail",
            "subcategory":"Portrait Studio",
            "type":"Services"
        }
    ],
    "sg:phone":"+1 479 667 5531",
    "sg:postcode":"72949",
    "sg:province":"AR",
    "sg:tags":[
        "photographer"
    ],
    "wof:name":"Hoffman Photography & Frames",
    "wof:placetype":"venue"
},
  "geometry": {"coordinates":[-93.82813400000001,35.487074],"type":"Point"}
}