{
  "type": "Feature",
  "properties": {
    "iso:country":"US",
    "sg:address":"11410 Hwy 365",
    "sg:city":"Little Rock",
    "sg:classifiers":[
        {
            "category":"Food & Beverages",
            "subcategory":"Groceries & Convenience Stores",
            "type":"Retail Goods"
        }
    ],
    "sg:phone":"+1 501 897 5126",
    "sg:postcode":"72206",
    "sg:province":"AR",
    "wof:name":"Cash & Carry Market",
    "wof:placetype":"venue"
},
  "geometry": {"coordinates":[-92.227766,34.643483],"type":"Point"}
}