{
  "type": "Feature",
  "properties": {
    "addr:full":"5605 W 32nd St Little Rock AR 72204",
    "addr:housenumber":"5605",
    "addr:postcode":"72204",
    "addr:street":"W 32Nd St",
    "iso:country":"US",
    "sg:address":"5605 W 32nd St",
    "sg:city":"Little Rock",
    "sg:classifiers":[
        {
            "category":"Organizations",
            "subcategory":"Religious Organization",
            "type":"Services"
        }
    ],
    "sg:phone":"+1 501 661 1153",
    "sg:postcode":"72204",
    "sg:province":"AR",
    "sg:tags":[
        "church"
    ],
    "sg:website":"www.ualrwf.org",
    "wof:name":"U A L R Wesley Foundation",
    "wof:placetype":"venue"
},
  "geometry": {"coordinates":[-92.337446,34.72297],"type":"Point"}
}