{
  "type": "Feature",
  "properties": {
    "iso:country":"US",
    "sg:address":"222 N Hervey St",
    "sg:city":"Hope",
    "sg:classifiers":[
        {
            "category":"Real Estate",
            "subcategory":"Real Estate Services",
            "type":"Services"
        },
        {
            "category":"Professional",
            "subcategory":"Research",
            "type":"Services"
        }
    ],
    "sg:phone":"+1 870 777 0605",
    "sg:postcode":"71801",
    "sg:province":"AR",
    "sg:tags":[
        "abstracter",
        "title"
    ],
    "wof:name":"Hope Title Company Inc",
    "wof:placetype":"venue"
},
  "geometry": {"coordinates":[-93.597425,33.669459],"type":"Point"}
}