{
  "type": "Feature",
  "properties": {
    "iso:country":"US",
    "sg:address":"9 Haddington Dr",
    "sg:city":"Bella Vista",
    "sg:classifiers":[
        {
            "category":"Home & Garden",
            "subcategory":"Carpets & Floor Coverings",
            "type":"Retail Goods"
        }
    ],
    "sg:phone":"+1 479 876 2742",
    "sg:postcode":"72715",
    "sg:province":"AR",
    "sg:tags":[
        "window"
    ],
    "wof:name":"Discount Furniture Mart",
    "wof:placetype":"venue"
},
  "geometry": {"coordinates":[-94.331683,36.494306],"type":"Point"}
}