{
  "type": "Feature",
  "properties": {
    "iso:country":"US",
    "sg:address":"901 Fair Park Blvd",
    "sg:city":"Little Rock",
    "sg:classifiers":[
        {
            "category":"Travel",
            "subcategory":"Hotels & Motels",
            "type":"Entertainment"
        }
    ],
    "sg:phone":"+1 501 664 7000",
    "sg:postcode":"72204",
    "sg:province":"AR",
    "sg:tags":[
        "operation"
    ],
    "sg:website":"www.laquinta.com",
    "wof:name":"LA Quinta Inn",
    "wof:placetype":"venue"
},
  "geometry": {"coordinates":[-92.33438,34.742993],"type":"Point"}
}