{
  "type": "Feature",
  "properties": {
    "iso:country":"US",
    "sg:address":"4608 W Walnut St",
    "sg:city":"Rogers",
    "sg:classifiers":[
        {
            "category":"Shopping",
            "subcategory":"Bicycles & Sporting Goods",
            "type":"Retail Goods"
        }
    ],
    "sg:phone":"+1 479 636 9300",
    "sg:postcode":"72756",
    "sg:province":"AR",
    "wof:name":"Golf Headquarters",
    "wof:placetype":"venue"
},
  "geometry": {"coordinates":[-94.181099,36.335098],"type":"Point"}
}