{
  "type": "Feature",
  "properties": {
    "iso:country":"US",
    "sg:address":"1605 Choctaw St",
    "sg:city":"Harrison",
    "sg:classifiers":[
        {
            "category":"Retail",
            "subcategory":"Auto Repair",
            "type":"Services"
        }
    ],
    "sg:phone":"+1 870 741 8413",
    "sg:postcode":"72601",
    "sg:province":"AR",
    "wof:name":"Front Wheel Drive",
    "wof:placetype":"venue"
},
  "geometry": {"coordinates":[-93.127892,36.236176],"type":"Point"}
}