{
  "type": "Feature",
  "properties": {
    "iso:country":"US",
    "sg:address":"7 Portea Dr",
    "sg:city":"Pine Bluff",
    "sg:classifiers":[
        {
            "category":"Building & Trades",
            "subcategory":"Cleaning & Sanitation",
            "type":"Services"
        }
    ],
    "sg:phone":"+1 870 534 4038",
    "sg:postcode":"71601",
    "sg:province":"AR",
    "sg:tags":[
        "maintenance"
    ],
    "wof:name":"ServiceMaster",
    "wof:placetype":"venue"
},
  "geometry": {"coordinates":[-91.97233,34.224014],"type":"Point"}
}