{
  "type": "Feature",
  "properties": {
    "iso:country":"US",
    "sg:address":"707 S Walnut St",
    "sg:city":"Harrison",
    "sg:classifiers":[
        {
            "category":"Manufacturing",
            "subcategory":"Tools & Machinery",
            "type":"Manufacturing & Wholesale Goods"
        }
    ],
    "sg:phone":"+1 870 743 3588",
    "sg:postcode":"72601",
    "sg:province":"AR",
    "sg:tags":[
        "mfg",
        "furniture"
    ],
    "wof:name":"Jim Mulanax Co",
    "wof:placetype":"venue"
},
  "geometry": {"coordinates":[-93.10537600000001,36.222943],"type":"Point"}
}