{
  "type": "Feature",
  "properties": {
    "iso:country":"US",
    "sg:address":"18136 I- 30",
    "sg:city":"Benton",
    "sg:classifiers":[
        {
            "category":"Manufacturing",
            "subcategory":"Motor Vehicles & Parts",
            "type":"Manufacturing & Wholesale Goods"
        }
    ],
    "sg:phone":"+1 501 315 7252",
    "sg:postcode":"72015",
    "sg:province":"AR",
    "sg:tags":[
        "mfg"
    ],
    "wof:name":"B&R Trailer Mfg Inc",
    "wof:placetype":"venue"
},
  "geometry": {"coordinates":[-92.566694,34.588173],"type":"Point"}
}