{
  "type": "Feature",
  "properties": {
    "iso:country":"US",
    "sg:address":"1800 N Missouri St",
    "sg:city":"West Memphis",
    "sg:classifiers":[
        {
            "category":"Real Estate",
            "subcategory":"Real Estate Operator",
            "type":"Services"
        }
    ],
    "sg:phone":"+1 870 735 6244",
    "sg:postcode":"72301",
    "sg:province":"AR",
    "sg:tags":[
        "mall",
        "shopping",
        "center"
    ],
    "wof:name":"Holiday Plaza Mall Shop",
    "wof:placetype":"venue"
},
  "geometry": {"coordinates":[-90.184681,35.165563],"type":"Point"}
}