{
  "type": "Feature",
  "properties": {
    "iso:country":"US",
    "sg:address":"241 Darby Ln",
    "sg:city":"Russellville",
    "sg:classifiers":[
        {
            "category":"Building & Trades",
            "subcategory":"Construction",
            "type":"Services"
        }
    ],
    "sg:phone":"+1 479 890 3647",
    "sg:postcode":"72802",
    "sg:province":"AR",
    "sg:tags":[
        "residential",
        "painting",
        "contractor"
    ],
    "wof:name":"River Valley Painting",
    "wof:placetype":"venue"
},
  "geometry": {"coordinates":[-93.13397000000001,35.316841],"type":"Point"}
}