{
  "type": "Feature",
  "properties": {
    "iso:country":"US",
    "sg:address":"3343 Springhill Rd",
    "sg:city":"North Little Rock",
    "sg:classifiers":[
        {
            "category":"Health Services",
            "subcategory":"Doctor",
            "type":"Services"
        }
    ],
    "sg:phone":"+1 501 758 5133",
    "sg:postcode":"72117",
    "sg:province":"AR",
    "sg:tags":[
        "clinic",
        "medical"
    ],
    "wof:name":"Arkansas Heart Group",
    "wof:placetype":"venue"
},
  "geometry": {"coordinates":[-92.218226,34.783267],"type":"Point"}
}