{
  "type": "Feature",
  "properties": {
    "addr:full":"1894 W 6th St Fayetteville AR 72701",
    "addr:housenumber":"1894",
    "addr:postcode":"72701",
    "addr:street":"W 6Th St",
    "iso:country":"US",
    "sg:address":"1894 W 6th St",
    "sg:city":"Fayetteville",
    "sg:classifiers":[
        {
            "category":"Building & Trades",
            "subcategory":"Construction",
            "type":"Services"
        }
    ],
    "sg:phone":"+1 479 751 0448",
    "sg:postcode":"72701",
    "sg:province":"AR",
    "sg:tags":[
        "carpenter"
    ],
    "wof:name":"Charles Carpener",
    "wof:placetype":"venue"
},
  "geometry": {"coordinates":[-94.186048,36.056587],"type":"Point"}
}