{
  "type": "Feature",
  "properties": {
    "iso:country":"US",
    "sg:address":"920 Malvern Ave",
    "sg:city":"Hot Springs",
    "sg:classifiers":[
        {
            "category":"Autos & Motor Vehicles",
            "subcategory":"Auto Supplies",
            "type":"Retail Goods"
        },
        {
            "category":"Wholesale",
            "subcategory":"Auto Parts",
            "type":"Manufacturing & Wholesale Goods"
        }
    ],
    "sg:phone":"+1 501 624 4687",
    "sg:postcode":"71901",
    "sg:province":"AR",
    "sg:tags":[
        "automobile",
        "automotive"
    ],
    "wof:name":"Rynders Auto Supply Inc",
    "wof:placetype":"venue"
},
  "geometry": {"coordinates":[-93.046574,34.502308],"type":"Point"}
}