{
  "type": "Feature",
  "properties": {
    "iso:country":"US",
    "sg:address":"9259 US Hwy 65",
    "sg:city":"Bee Branch",
    "sg:classifiers":[
        {
            "category":"Food & Beverages",
            "subcategory":"Groceries & Convenience Stores",
            "type":"Retail Goods"
        }
    ],
    "sg:phone":"+1 501 745 7701",
    "sg:postcode":"72013",
    "sg:province":"AR",
    "wof:name":"Bee Branch Mini Mart & Truck",
    "wof:placetype":"venue"
},
  "geometry": {"coordinates":[-92.41635599999999,35.47098],"type":"Point"}
}