{
  "type": "Feature",
  "properties": {
    "iso:country":"US",
    "sg:address":"237 Alpine St",
    "sg:city":"Hot Springs",
    "sg:classifiers":[
        {
            "category":"Restaurant",
            "type":"Food & Drink"
        }
    ],
    "sg:phone":"+1 501 623 8099",
    "sg:postcode":"71913",
    "sg:province":"AR",
    "sg:tags":[
        "caterer"
    ],
    "wof:name":"Green Herb",
    "wof:placetype":"venue"
},
  "geometry": {"coordinates":[-93.064463,34.482517],"type":"Point"}
}