{
  "type": "Feature",
  "properties": {
    "iso:country":"US",
    "sg:address":"1210 Shibley Rd",
    "sg:city":"Van Buren",
    "sg:classifiers":[
        {
            "category":"Professional",
            "subcategory":"Business Services",
            "type":"Services"
        }
    ],
    "sg:phone":"+1 479 471 5106",
    "sg:postcode":"72956",
    "sg:province":"AR",
    "wof:name":"Manus Enterprises LLC",
    "wof:placetype":"venue"
},
  "geometry": {"coordinates":[-94.293155,35.450466],"type":"Point"}
}