{
  "type": "Feature",
  "properties": {
    "iso:country":"US",
    "sg:address":"7300 Dollarway Rd",
    "sg:city":"White Hall",
    "sg:classifiers":[
        {
            "category":"Professional",
            "subcategory":"Business Services",
            "type":"Services"
        }
    ],
    "sg:phone":"+1 870 247 3123",
    "sg:postcode":"71602",
    "sg:province":"AR",
    "wof:name":"Kesl & Assoc Representative",
    "wof:placetype":"venue"
},
  "geometry": {"coordinates":[-92.084177,34.263662],"type":"Point"}
}