{
  "type": "Feature",
  "properties": {
    "iso:country":"US",
    "sg:address":"1400 Hathaway Dr",
    "sg:city":"Conway",
    "sg:classifiers":[
        {
            "category":"Wholesale",
            "subcategory":"Machinery & Supplies",
            "type":"Manufacturing & Wholesale Goods"
        }
    ],
    "sg:phone":"+1 501 327 3788",
    "sg:postcode":"72034",
    "sg:province":"AR",
    "sg:tags":[
        "pressure",
        "washing",
        "equipment"
    ],
    "wof:name":"Allied Services",
    "wof:placetype":"venue"
},
  "geometry": {"coordinates":[-92.452383,35.055619],"type":"Point"}
}