{
  "type": "Feature",
  "properties": {
    "addr:full":"210 Deer Acres Cabot AR 72023",
    "addr:housenumber":"210",
    "addr:postcode":"72023",
    "addr:street":"Deer Acres",
    "iso:country":"US",
    "sg:address":"210 Deer Acres",
    "sg:city":"Cabot",
    "sg:classifiers":[
        {
            "category":"Autos & Motor Vehicles",
            "subcategory":"Automobile Sales",
            "type":"Retail Goods"
        }
    ],
    "sg:phone":"+1 501 843 3476",
    "sg:postcode":"72023",
    "sg:province":"AR",
    "sg:tags":[
        "dealers-used",
        "car",
        "used",
        "cars-wholesale"
    ],
    "wof:name":"Dalton's Classic Autos",
    "wof:placetype":"venue"
},
  "geometry": {"coordinates":[-92.06328600000001,34.941074],"type":"Point"}
}