{
  "type": "Feature",
  "properties": {
    "addr:full":"11214 Hickory Ln Omaha AR 72662",
    "addr:housenumber":"11214",
    "addr:postcode":"72662",
    "addr:street":"Hickory Ln",
    "iso:country":"US",
    "sg:address":"11214 Hickory Ln",
    "sg:city":"Omaha",
    "sg:classifiers":[
        {
            "category":"Health Services",
            "subcategory":"Clinic",
            "type":"Services"
        }
    ],
    "sg:phone":"+1 870 426 1753",
    "sg:postcode":"72662",
    "sg:province":"AR",
    "sg:tags":[
        "wellness",
        "program"
    ],
    "wof:name":"Ultimate Health & Wellness",
    "wof:placetype":"venue"
},
  "geometry": {"coordinates":[-93.199234,36.455259],"type":"Point"}
}