{
  "type": "Feature",
  "properties": {
    "iso:country":"US",
    "sg:address":"800 S Main St",
    "sg:city":"Dumas",
    "sg:classifiers":[
        {
            "category":"Manufacturing",
            "subcategory":"Pet Food",
            "type":"Manufacturing & Wholesale Goods"
        },
        {
            "category":"Shopping",
            "subcategory":"Pets & Pet Supplies",
            "type":"Retail Goods"
        }
    ],
    "sg:phone":"+1 870 382 2600",
    "sg:postcode":"71639",
    "sg:province":"AR",
    "sg:tags":[
        "feed",
        "manufacturer",
        "foods-wholesale"
    ],
    "wof:name":"Arkat Animal Nutrition",
    "wof:placetype":"venue"
},
  "geometry": {"coordinates":[-91.489449,33.877361],"type":"Point"}
}