{
  "type": "Feature",
  "properties": {
    "iso:country":"US",
    "sg:address":"2790 S 2nd St Ste C",
    "sg:city":"Cabot",
    "sg:classifiers":[
        {
            "category":"Personal",
            "subcategory":"Beauty Salon",
            "type":"Services"
        }
    ],
    "sg:phone":"+1 501 843 6200",
    "sg:postcode":"72023",
    "sg:province":"AR",
    "sg:website":"http://www.asavvysalon@yahoo.com",
    "wof:name":"A Savvy You Salon",
    "wof:placetype":"venue"
},
  "geometry": {"coordinates":[-92.054159,34.951232],"type":"Point"}
}