{
  "type": "Feature",
  "properties": {
    "iso:country":"US",
    "sg:address":"207 S Main St",
    "sg:city":"England",
    "sg:classifiers":[
        {
            "category":"Home & Garden",
            "subcategory":"Hardware",
            "type":"Retail Goods"
        }
    ],
    "sg:phone":"+1 501 842 2244",
    "sg:postcode":"72046",
    "sg:province":"AR",
    "wof:name":"England Hardware",
    "wof:placetype":"venue"
},
  "geometry": {"coordinates":[-91.969058,34.544012],"type":"Point"}
}