{
  "type": "Feature",
  "properties": {
    "iso:country":"US",
    "sg:address":"181 S Front Ave",
    "sg:city":"Piggott",
    "sg:classifiers":[
        {
            "category":"Cinema",
            "subcategory":"Movie Rental",
            "type":"Entertainment"
        }
    ],
    "sg:phone":"+1 870 598 3744",
    "sg:postcode":"72454",
    "sg:province":"AR",
    "sg:tags":[
        "video",
        "tape"
    ],
    "wof:name":"The Movie House",
    "wof:placetype":"venue"
},
  "geometry": {"coordinates":[-90.19089,36.381867],"type":"Point"}
}