{
  "type": "Feature",
  "properties": {
    "iso:country":"US",
    "sg:address":"23233 I- 30",
    "sg:city":"Bryant",
    "sg:classifiers":[
        {
            "category":"Health Services",
            "subcategory":"Doctor",
            "type":"Services"
        }
    ],
    "sg:phone":"+1 501 847 4410",
    "sg:postcode":"72022",
    "sg:province":"AR",
    "sg:tags":[
        "physician",
        "surgeon"
    ],
    "wof:name":"Medical Weight Management",
    "wof:placetype":"venue"
},
  "geometry": {"coordinates":[-92.49191,34.622158],"type":"Point"}
}