{
  "type": "Feature",
  "properties": {
    "iso:country":"US",
    "sg:address":"711 SE J St",
    "sg:city":"Bentonville",
    "sg:classifiers":[
        {
            "category":"Professional",
            "subcategory":"Computer Services",
            "type":"Services"
        }
    ],
    "sg:phone":"+1 479 553 0100",
    "sg:postcode":"72712",
    "sg:province":"AR",
    "sg:tags":[
        "cd-rom"
    ],
    "wof:name":"Sinomax U S A Inc",
    "wof:placetype":"venue"
},
  "geometry": {"coordinates":[-94.196754,36.36457],"type":"Point"}
}