{
  "type": "Feature",
  "properties": {
    "iso:country":"US",
    "sg:address":"3607 Mcdaniel Rd",
    "sg:city":"Paragould",
    "sg:classifiers":[
        {
            "category":"Professional",
            "subcategory":"Detective & Security Services",
            "type":"Services"
        }
    ],
    "sg:phone":"+1 870 236 6008",
    "sg:postcode":"72450",
    "sg:province":"AR",
    "sg:tags":[
        "information",
        "bureau"
    ],
    "wof:name":"Earthling Creative Services",
    "wof:placetype":"venue"
},
  "geometry": {"coordinates":[-90.534219,36.023573],"type":"Point"}
}