{
  "type": "Feature",
  "properties": {
    "addr:full":"1601 S Grand St Stuttgart AR 72160",
    "addr:housenumber":"1601",
    "addr:postcode":"72160",
    "addr:street":"S Grand St",
    "iso:country":"US",
    "sg:address":"1601 S Grand St",
    "sg:city":"Stuttgart",
    "sg:classifiers":[
        {
            "category":"Building & Trades",
            "subcategory":"Construction",
            "type":"Services"
        }
    ],
    "sg:phone":"+1 870 672 9023",
    "sg:postcode":"72160",
    "sg:province":"AR",
    "sg:tags":[
        "contractor"
    ],
    "wof:name":"Bo Pullman Roofing",
    "wof:placetype":"venue"
},
  "geometry": {"coordinates":[-91.55042,34.48813],"type":"Point"}
}