{
  "type": "Feature",
  "properties": {
    "iso:country":"US",
    "sg:address":"20318 Sonora Acres Rd",
    "sg:city":"Springdale",
    "sg:classifiers":[
        {
            "category":"Restaurant",
            "type":"Food & Drink"
        }
    ],
    "sg:phone":"+1 479 725 2566",
    "sg:postcode":"72764",
    "sg:province":"AR",
    "wof:name":"Machu Picchu Peruvian Cuisine",
    "wof:placetype":"venue"
},
  "geometry": {"coordinates":[-94.043001,36.166552],"type":"Point"}
}