{
  "type": "Feature",
  "properties": {
    "addr:full":"3929 Mccain Blvd North Little Rock AR 72116",
    "addr:housenumber":"3929",
    "addr:postcode":"72116",
    "addr:street":"Mccain Blvd",
    "iso:country":"US",
    "sg:address":"3929 Mccain Blvd",
    "sg:city":"North Little Rock",
    "sg:classifiers":[
        {
            "category":"Restaurant",
            "type":"Food & Drink"
        }
    ],
    "sg:menulink":"http://www.allmenus.com/ar/hill/219278-lubys/menu/",
    "sg:phone":"+1 501 771 4911",
    "sg:postcode":"72116",
    "sg:province":"AR",
    "sg:tags":[
        "new",
        "american"
    ],
    "wof:name":"Luby's",
    "wof:placetype":"venue"
},
  "geometry": {"coordinates":[-92.226224,34.792589],"type":"Point"}
}