{
  "type": "Feature",
  "properties": {
    "iso:country":"US",
    "sg:address":"702 E 4th St",
    "sg:city":"Russellville",
    "sg:classifiers":[
        {
            "category":"Professional",
            "subcategory":"Business Services",
            "type":"Services"
        }
    ],
    "sg:phone":"+1 479 968 2028",
    "sg:postcode":"72801",
    "sg:province":"AR",
    "sg:tags":[
        "auctioneer"
    ],
    "sg:website":"www.spearauction.com",
    "wof:name":"Spear Auctioneers Inc",
    "wof:placetype":"venue"
},
  "geometry": {"coordinates":[-93.125733,35.274859],"type":"Point"}
}