{
  "type": "Feature",
  "properties": {
    "addr:full":"310 Hwy 62 E Mountain Home AR 72653",
    "addr:housenumber":"310",
    "addr:postcode":"72653",
    "addr:street":"Hwy 62 E",
    "iso:country":"US",
    "sg:address":"310 Hwy 62 E",
    "sg:city":"Mountain Home",
    "sg:classifiers":[
        {
            "category":"Banks & Credit Unions",
            "subcategory":"Bank",
            "type":"Services"
        }
    ],
    "sg:phone":"+1 870 425 1507",
    "sg:postcode":"72653",
    "sg:province":"AR",
    "sg:website":"www.com1nb.com",
    "wof:name":"Community First National Bank",
    "wof:placetype":"venue"
},
  "geometry": {"coordinates":[-92.38215700000001,36.342174],"type":"Point"}
}