{
  "type": "Feature",
  "properties": {
    "addr:full":"104 W Modesto Ave Russellville AR 72801",
    "addr:housenumber":"104",
    "addr:postcode":"72801",
    "addr:street":"W Modesto Ave",
    "iso:country":"US",
    "sg:address":"104 W Modesto Ave",
    "sg:city":"Russellville",
    "sg:classifiers":[
        {
            "category":"Shopping",
            "type":"Retail Goods"
        }
    ],
    "sg:phone":"+1 479 968 7701",
    "sg:postcode":"72801",
    "sg:province":"AR",
    "sg:tags":[
        "merchandise"
    ],
    "wof:name":"Dennis Dans Shop",
    "wof:placetype":"venue"
},
  "geometry": {"coordinates":[-93.166213,35.289754],"type":"Point"}
}