{
  "type": "Feature",
  "properties": {
    "addr:full":"906 W 4th St Fordyce AR 71742",
    "addr:housenumber":"906",
    "addr:postcode":"71742",
    "addr:street":"W 4Th St",
    "iso:country":"US",
    "sg:address":"906 W 4th St",
    "sg:city":"Fordyce",
    "sg:classifiers":[
        {
            "category":"Shopping",
            "subcategory":"Department Store",
            "type":"Retail Goods"
        },
        {
            "category":"Shopping",
            "subcategory":"Discount & Variety Stores",
            "type":"Retail Goods"
        },
        {
            "category":"Shopping",
            "type":"Retail Goods"
        },
        {
            "category":"Food & Beverages",
            "subcategory":"Groceries & Convenience Stores",
            "type":"Retail Goods"
        }
    ],
    "sg:phone":"+1 870 352 5515",
    "sg:postcode":"71742",
    "sg:province":"AR",
    "sg:tags":[
        "merchandise"
    ],
    "sg:website":"http://www.dollargeneral.com",
    "wof:name":"Dollar General",
    "wof:placetype":"venue"
},
  "geometry": {"coordinates":[-92.425994,33.812651],"type":"Point"}
}