{
  "type": "Feature",
  "properties": {
    "iso:country":"US",
    "sg:address":"31900 S 680 Rd",
    "sg:city":"Grove",
    "sg:classifiers":[
        {
            "category":"Building & Trades",
            "subcategory":"Electrical",
            "type":"Services"
        }
    ],
    "sg:phone":"+1 918 787 6745",
    "sg:postcode":"74344",
    "sg:province":"OK",
    "sg:tags":[
        "industrial",
        "electrician",
        "contractors-commercial",
        "electric"
    ],
    "sg:website":"http://www.epicelectricok.com",
    "wof:name":"Epic Electric",
    "wof:placetype":"venue"
},
  "geometry": {"coordinates":[-94.653065,36.612555],"type":"Point"}
}