{
  "type": "Feature",
  "properties": {
    "iso:country":"US",
    "sg:address":"4710 Stratton Ave",
    "sg:city":"Little Rock",
    "sg:classifiers":[
        {
            "category":"Professional",
            "subcategory":"Secretarial Services",
            "type":"Services"
        }
    ],
    "sg:phone":"+1 501 565 5933",
    "sg:postcode":"72209",
    "sg:province":"AR",
    "sg:tags":[
        "reporting"
    ],
    "wof:name":"Fobbs Professional Typing Svc",
    "wof:placetype":"venue"
},
  "geometry": {"coordinates":[-92.330049,34.674414],"type":"Point"}
}