{
  "type": "Feature",
  "properties": {
    "addr:full":"1137 Front St Conway AR 72032",
    "addr:housenumber":"1137",
    "addr:postcode":"72032",
    "addr:street":"Front St",
    "iso:country":"US",
    "sg:address":"1137 Front St",
    "sg:city":"Conway",
    "sg:classifiers":[
        {
            "category":"Restaurant",
            "type":"Food & Drink"
        }
    ],
    "sg:phone":"+1 501 329 8625",
    "sg:postcode":"72032",
    "sg:province":"AR",
    "wof:name":"Stoby's",
    "wof:placetype":"venue"
},
  "geometry": {"coordinates":[-92.44280000000001,35.094841],"type":"Point"}
}