{
  "type": "Feature",
  "properties": {
    "iso:country":"US",
    "sg:address":"1401 E Main St",
    "sg:city":"Magnolia",
    "sg:classifiers":[
        {
            "category":"Restaurant",
            "type":"Food & Drink"
        }
    ],
    "sg:phone":"+1 870 234 5114",
    "sg:postcode":"71753",
    "sg:province":"AR",
    "wof:name":"Kentucky Fried Chicken Of Magnolia Inc",
    "wof:placetype":"venue"
},
  "geometry": {"coordinates":[-93.222868,33.266726],"type":"Point"}
}