{
  "type": "Feature",
  "properties": {
    "addr:full":"11809 Arch St Little Rock AR 72206",
    "addr:housenumber":"11809",
    "addr:postcode":"72206",
    "addr:street":"Arch St",
    "iso:country":"US",
    "sg:address":"11809 Arch St",
    "sg:city":"Little Rock",
    "sg:classifiers":[
        {
            "category":"Autos & Motor Vehicles",
            "subcategory":"Automobile Sales",
            "type":"Retail Goods"
        }
    ],
    "sg:phone":"+1 501 261 7830",
    "sg:postcode":"72206",
    "sg:province":"AR",
    "sg:tags":[
        "car",
        "dealer"
    ],
    "wof:name":"Richardson Autoplex",
    "wof:placetype":"venue"
},
  "geometry": {"coordinates":[-92.309352,34.640395],"type":"Point"}
}