{
  "type": "Feature",
  "properties": {
    "iso:country":"US",
    "sg:address":"21238 Braswell Rd",
    "sg:city":"Springdale",
    "sg:classifiers":[
        {
            "category":"Professional",
            "subcategory":"Management & Consulting",
            "type":"Services"
        }
    ],
    "sg:phone":"+1 479 750 7188",
    "sg:postcode":"72764",
    "sg:province":"AR",
    "sg:tags":[
        "farm"
    ],
    "wof:name":"Jimmy Rogers",
    "wof:placetype":"venue"
},
  "geometry": {"coordinates":[-93.993315,36.182215],"type":"Point"}
}