{
  "type": "Feature",
  "properties": {
    "addr:full":"999 Mount Union Rd El Dorado AR 71730",
    "addr:housenumber":"999",
    "addr:postcode":"71730",
    "addr:street":"Mount Union Rd",
    "iso:country":"US",
    "sg:address":"999 Mount Union Rd",
    "sg:city":"El Dorado",
    "sg:classifiers":[
        {
            "category":"Building & Trades",
            "subcategory":"Construction",
            "type":"Services"
        }
    ],
    "sg:phone":"+1 870 862 2965",
    "sg:postcode":"71730",
    "sg:province":"AR",
    "sg:tags":[
        "residential"
    ],
    "wof:name":"Henry A Moore Jr",
    "wof:placetype":"venue"
},
  "geometry": {"coordinates":[-92.620576,33.109663],"type":"Point"}
}