{
  "type": "Feature",
  "properties": {
    "addr:full":"1287 Sunrise Ave Springdale AR 72764",
    "addr:housenumber":"1287",
    "addr:postcode":"72764",
    "addr:street":"Sunrise Ave",
    "iso:country":"US",
    "sg:address":"1287 Sunrise Ave",
    "sg:city":"Springdale",
    "sg:classifiers":[
        {
            "category":"Building & Trades",
            "subcategory":"Construction",
            "type":"Services"
        }
    ],
    "sg:phone":"+1 479 751 3944",
    "sg:postcode":"72764",
    "sg:province":"AR",
    "sg:tags":[
        "hanging",
        "contractor"
    ],
    "wof:name":"C E Jackson Painting",
    "wof:placetype":"venue"
},
  "geometry": {"coordinates":[-94.138041,36.215297],"type":"Point"}
}