{
  "type": "Feature",
  "properties": {
    "addr:full":"1733 Hwy 63 Williford AR 72482",
    "addr:housenumber":"1733",
    "addr:postcode":"72482",
    "addr:street":"Hwy 63",
    "iso:country":"US",
    "sg:address":"1733 Hwy 63",
    "sg:city":"Williford",
    "sg:classifiers":[
        {
            "category":"Retail",
            "subcategory":"Repair Shop",
            "type":"Services"
        }
    ],
    "sg:phone":"+1 870 966 4410",
    "sg:postcode":"72482",
    "sg:province":"AR",
    "sg:tags":[
        "repairing",
        "saw"
    ],
    "wof:name":"Hughes Carbide Saw & Craft",
    "wof:placetype":"venue"
},
  "geometry": {"coordinates":[-91.39112299999999,36.285734],"type":"Point"}
}