{
  "type": "Feature",
  "properties": {
    "iso:country":"US",
    "sg:address":"1606 W 24th Ave",
    "sg:city":"Pine Bluff",
    "sg:classifiers":[
        {
            "category":"Building & Trades",
            "subcategory":"Construction",
            "type":"Services"
        }
    ],
    "sg:phone":"+1 870 535 5070",
    "sg:postcode":"71603",
    "sg:province":"AR",
    "sg:tags":[
        "coping",
        "plastering",
        "tiling",
        "pool",
        "swimming"
    ],
    "wof:name":"Crystal Clear Pool Svc",
    "wof:placetype":"venue"
},
  "geometry": {"coordinates":[-92.019364,34.205331],"type":"Point"}
}