{
  "type": "Feature",
  "properties": {
    "iso:country":"US",
    "sg:address":"1315 N 10th St",
    "sg:city":"Arkadelphia",
    "sg:classifiers":[
        {
            "category":"Insurance",
            "subcategory":"Insurance Agent",
            "type":"Services"
        }
    ],
    "sg:phone":"+1 870 246 8222",
    "sg:postcode":"71923",
    "sg:province":"AR",
    "wof:name":"Garrett Insurance",
    "wof:placetype":"venue"
},
  "geometry": {"coordinates":[-93.062702,34.143583],"type":"Point"}
}