{
  "type": "Feature",
  "properties": {
    "iso:country":"US",
    "sg:address":"19723 I- 30",
    "sg:city":"Benton",
    "sg:classifiers":[
        {
            "category":"Professional",
            "subcategory":"Business Services",
            "type":"Services"
        }
    ],
    "sg:phone":"+1 501 860 7232",
    "sg:postcode":"72015",
    "sg:province":"AR",
    "sg:tags":[
        "auctioneer"
    ],
    "wof:name":"Global Online Auctions",
    "wof:placetype":"venue"
},
  "geometry": {"coordinates":[-92.534881,34.60563],"type":"Point"}
}