{
  "type": "Feature",
  "properties": {
    "addr:full":"400 W Market St Ozark AR 72949",
    "addr:housenumber":"400",
    "addr:postcode":"72949",
    "addr:street":"W Market St",
    "iso:country":"US",
    "sg:address":"400 W Market St",
    "sg:city":"Ozark",
    "sg:classifiers":[
        {
            "category":"Organizations",
            "subcategory":"Religious Organization",
            "type":"Services"
        }
    ],
    "sg:phone":"+1 479 667 3858",
    "sg:postcode":"72949",
    "sg:province":"AR",
    "sg:tags":[
        "church"
    ],
    "sg:website":"www.ozarkfbc.org",
    "wof:name":"First Baptist Church",
    "wof:placetype":"venue"
},
  "geometry": {"coordinates":[-93.82896,35.48864],"type":"Point"}
}