{
  "type": "Feature",
  "properties": {
    "iso:country":"US",
    "sg:address":"250 E Centerton Blvd",
    "sg:city":"Centerton",
    "sg:classifiers":[
        {
            "category":"Social Services",
            "type":"Services"
        }
    ],
    "sg:phone":"+1 479 795 1802",
    "sg:postcode":"72719",
    "sg:province":"AR",
    "sg:tags":[
        "youth",
        "organization",
        "center"
    ],
    "wof:name":"Youth Bridge",
    "wof:placetype":"venue"
},
  "geometry": {"coordinates":[-94.280226,36.358405],"type":"Point"}
}