{
  "type": "Feature",
  "properties": {
    "iso:country":"US",
    "sg:address":"1601 N 6th St",
    "sg:city":"Fort Smith",
    "sg:classifiers":[
        {
            "category":"Wholesale",
            "subcategory":"Machinery & Supplies",
            "type":"Manufacturing & Wholesale Goods"
        }
    ],
    "sg:phone":"+1 479 785 2554",
    "sg:postcode":"72901",
    "sg:province":"AR",
    "sg:tags":[
        "machine",
        "tool"
    ],
    "sg:website":"www.diamondjackmachinery.com",
    "wof:name":"Jack Diamond Machinery Inc",
    "wof:placetype":"venue"
},
  "geometry": {"coordinates":[-94.41346799999999,35.399446],"type":"Point"}
}