{
  "type": "Feature",
  "properties": {
    "iso:country":"US",
    "sg:address":"1145 Jims Ln",
    "sg:city":"Conway",
    "sg:classifiers":[
        {
            "category":"Retail",
            "subcategory":"Car Wash",
            "type":"Services"
        }
    ],
    "sg:phone":"+1 501 697 3996",
    "sg:postcode":"72032",
    "sg:province":"AR",
    "sg:tags":[
        "polishing",
        "washing"
    ],
    "wof:name":"Hocus Pocus Auto Salon",
    "wof:placetype":"venue"
},
  "geometry": {"coordinates":[-92.41077,35.092116],"type":"Point"}
}