{
  "type": "Feature",
  "properties": {
    "addr:full":"100 Manson Rd Sherwood AR 72120",
    "addr:housenumber":"100",
    "addr:postcode":"72120",
    "addr:street":"Manson Rd",
    "iso:country":"US",
    "sg:address":"100 Manson Rd",
    "sg:city":"Sherwood",
    "sg:classifiers":[
        {
            "category":"Real Estate",
            "subcategory":"Real Estate Services",
            "type":"Services"
        },
        {
            "category":"Real Estate",
            "subcategory":"Real Estate Operator",
            "type":"Services"
        }
    ],
    "sg:phone":"+1 501 833 8889",
    "sg:postcode":"72120",
    "sg:province":"AR",
    "sg:tags":[
        "vacancy",
        "apartment",
        "rental",
        "finder",
        "listing"
    ],
    "wof:name":"Park Crest",
    "wof:placetype":"venue"
},
  "geometry": {"coordinates":[-92.18879699999999,34.833792],"type":"Point"}
}