{
  "type": "Feature",
  "properties": {
    "iso:country":"US",
    "sg:address":"4131 McFadden Rd",
    "sg:city":"White Hall",
    "sg:classifiers":[
        {
            "category":"Health Services",
            "subcategory":"Clinic",
            "type":"Services"
        }
    ],
    "sg:phone":"+1 870 535 4669",
    "sg:postcode":"71602",
    "sg:province":"AR",
    "sg:tags":[
        "specialty",
        "outpatient"
    ],
    "wof:name":"Arkansas Rehab Delta Cadet Pro",
    "wof:placetype":"venue"
},
  "geometry": {"coordinates":[-92.04234099999999,34.29763],"type":"Point"}
}