{
  "type": "Feature",
  "properties": {
    "addr:full":"107 Garden Oaks Ctr Camden AR 71701",
    "addr:housenumber":"107",
    "addr:postcode":"71701",
    "addr:street":"Garden Oaks Ctr",
    "iso:country":"US",
    "sg:address":"107 Garden Oaks Ctr",
    "sg:city":"Camden",
    "sg:classifiers":[
        {
            "category":"Restaurant",
            "type":"Food & Drink"
        }
    ],
    "sg:menulink":"http://www.allmenus.com/ar/ecore-fabre/66003-pizza-hut/menu/",
    "sg:phone":"+1 870 836 6421",
    "sg:postcode":"71701",
    "sg:province":"AR",
    "sg:tags":[
        "american",
        "pizza"
    ],
    "wof:name":"Pizza Hut",
    "wof:placetype":"venue"
},
  "geometry": {"coordinates":[-92.84975799999999,33.584091],"type":"Point"}
}