{
  "type": "Feature",
  "properties": {
    "addr:full":"201 W Pine St Brinkley AR 72021",
    "addr:housenumber":"201",
    "addr:postcode":"72021",
    "addr:street":"W Pine St",
    "iso:country":"US",
    "sg:address":"201 W Pine St",
    "sg:city":"Brinkley",
    "sg:classifiers":[
        {
            "category":"Shopping",
            "subcategory":"Florist",
            "type":"Retail Goods"
        }
    ],
    "sg:phone":"+1 870 734 2993",
    "sg:postcode":"72021",
    "sg:province":"AR",
    "wof:name":"Flower Patch",
    "wof:placetype":"venue"
},
  "geometry": {"coordinates":[-91.196242,34.888799],"type":"Point"}
}