{
  "type": "Feature",
  "properties": {
    "addr:full":"1408 Crooked Bayou Dr Mc Gehee AR 71654",
    "addr:housenumber":"1408",
    "addr:postcode":"71654",
    "addr:street":"Crooked Bayou Dr",
    "iso:country":"US",
    "sg:address":"1408 Crooked Bayou Dr",
    "sg:city":"Mc Gehee",
    "sg:classifiers":[
        {
            "category":"Real Estate",
            "subcategory":"Developer",
            "type":"Services"
        }
    ],
    "sg:phone":"+1 870 222 3595",
    "sg:postcode":"71654",
    "sg:province":"AR",
    "sg:tags":[
        "cemetery"
    ],
    "wof:name":"McGehee Cemetery Assoc Inc",
    "wof:placetype":"venue"
},
  "geometry": {"coordinates":[-91.36129699999999,33.606972],"type":"Point"}
}