{
  "type": "Feature",
  "properties": {
    "addr:full":"284 Cornbridge Rd Mineral Springs AR 71851",
    "addr:housenumber":"284",
    "addr:postcode":"71851",
    "addr:street":"Cornbridge Rd",
    "iso:country":"US",
    "sg:address":"284 Cornbridge Rd",
    "sg:city":"Mineral Springs",
    "sg:classifiers":[
        {
            "category":"Manufacturing",
            "subcategory":"Building Materials",
            "type":"Manufacturing & Wholesale Goods"
        }
    ],
    "sg:phone":"+1 870 287 7222",
    "sg:postcode":"71851",
    "sg:province":"AR",
    "sg:tags":[
        "member",
        "mfg",
        "wood",
        "structural"
    ],
    "wof:name":"American Land Timber",
    "wof:placetype":"venue"
},
  "geometry": {"coordinates":[-94.002545,33.883511],"type":"Point"}
}