{
  "type": "Feature",
  "properties": {
    "addr:full":"5208 Primrose Ln Little Rock AR 72209",
    "addr:housenumber":"5208",
    "addr:postcode":"72209",
    "addr:street":"Primrose Ln",
    "iso:country":"US",
    "sg:address":"5208 Primrose Ln",
    "sg:city":"Little Rock",
    "sg:classifiers":[
        {
            "category":"Manufacturing",
            "subcategory":"Paper Products",
            "type":"Manufacturing & Wholesale Goods"
        }
    ],
    "sg:phone":"+1 501 348 6734",
    "sg:postcode":"72209",
    "sg:province":"AR",
    "sg:tags":[
        "die",
        "mfg"
    ],
    "wof:name":"Reasons",
    "wof:placetype":"venue"
},
  "geometry": {"coordinates":[-92.33927300000001,34.702507],"type":"Point"}
}