{
  "type": "Feature",
  "properties": {
    "iso:country":"US",
    "sg:address":"401 S Bowman Rd",
    "sg:city":"Little Rock",
    "sg:classifiers":[
        {
            "category":"Retail",
            "subcategory":"Laundry & Dry Cleaning",
            "type":"Services"
        }
    ],
    "sg:phone":"+1 501 224 4340",
    "sg:postcode":"72211",
    "sg:province":"AR",
    "sg:tags":[
        "drycleaning",
        "plant"
    ],
    "wof:name":"Chenal Laundry & Dry Cleaners",
    "wof:placetype":"venue"
},
  "geometry": {"coordinates":[-92.407113,34.749604],"type":"Point"}
}