{
  "type": "Feature",
  "properties": {
    "iso:country":"US",
    "sg:address":"3600 John F Kennedy Blvd",
    "sg:city":"N Little Rock",
    "sg:classifiers":[
        {
            "category":"Organizations",
            "subcategory":"Religious Organization",
            "type":"Services"
        }
    ],
    "sg:phone":"+1 501 771 5555",
    "sg:postcode":"72116",
    "sg:province":"AR",
    "sg:tags":[
        "church"
    ],
    "wof:name":"Destiny By Design Church",
    "wof:placetype":"venue"
},
  "geometry": {"coordinates":[-92.26032499999999,34.789125],"type":"Point"}
}