{
  "type": "Feature",
  "properties": {
    "iso:country":"US",
    "sg:address":"410 W 8th St",
    "sg:city":"El Dorado",
    "sg:classifiers":[
        {
            "category":"Personal",
            "subcategory":"Tanning Parlor",
            "type":"Services"
        }
    ],
    "sg:phone":"+1 870 863 6111",
    "sg:postcode":"71730",
    "sg:province":"AR",
    "sg:tags":[
        "salon"
    ],
    "wof:name":"Becky's Tanning Salon",
    "wof:placetype":"venue"
},
  "geometry": {"coordinates":[-92.66927800000001,33.2257],"type":"Point"}
}