{
  "type": "Feature",
  "properties": {
    "addr:full":"2707 Ridgepointe Dr Jonesboro AR 72404",
    "addr:housenumber":"2707",
    "addr:postcode":"72404",
    "addr:street":"Ridgepointe Dr",
    "iso:country":"US",
    "sg:address":"2707 Ridgepointe Dr",
    "sg:city":"Jonesboro",
    "sg:classifiers":[
        {
            "category":"Insurance",
            "subcategory":"Hazard Insurance",
            "type":"Services"
        }
    ],
    "sg:phone":"+1 870 935 7306",
    "sg:postcode":"72404",
    "sg:province":"AR",
    "wof:name":"Imrie Doug & Leanne",
    "wof:placetype":"venue"
},
  "geometry": {"coordinates":[-90.76955700000001,35.810195],"type":"Point"}
}