{
  "type": "Feature",
  "properties": {
    "iso:country":"US",
    "sg:address":"4500 Narrows Rd",
    "sg:city":"Lonsdale",
    "sg:classifiers":[
        {
            "category":"Retail",
            "subcategory":"Repair Shop",
            "type":"Services"
        }
    ],
    "sg:phone":"+1 501 794 1849",
    "sg:postcode":"72087",
    "sg:province":"AR",
    "sg:tags":[
        "armature",
        "rewinding"
    ],
    "wof:name":"Skinner Electric Works Inc",
    "wof:placetype":"venue"
},
  "geometry": {"coordinates":[-92.740174,34.59418],"type":"Point"}
}