{
  "type": "Feature",
  "properties": {
    "iso:country":"US",
    "sg:address":"2844 Morningside Pl",
    "sg:city":"Van Buren",
    "sg:classifiers":[
        {
            "category":"Professional",
            "type":"Services"
        }
    ],
    "sg:phone":"+1 479 474 1096",
    "sg:postcode":"72956",
    "sg:province":"AR",
    "wof:name":"Summerhill Loyd Co",
    "wof:placetype":"venue"
},
  "geometry": {"coordinates":[-94.376746,35.479518],"type":"Point"}
}