{
  "type": "Feature",
  "properties": {
    "iso:country":"US",
    "sg:address":"413 W 3rd St",
    "sg:city":"Hope",
    "sg:classifiers":[
        {
            "category":"Autos & Motor Vehicles",
            "subcategory":"Automobile Sales",
            "type":"Retail Goods"
        }
    ],
    "sg:phone":"+1 870 777 5203",
    "sg:postcode":"71801",
    "sg:province":"AR",
    "sg:tags":[
        "car",
        "dealer"
    ],
    "wof:name":"S & S Auto Sales Inc",
    "wof:placetype":"venue"
},
  "geometry": {"coordinates":[-93.595166,33.666075],"type":"Point"}
}