{
  "type": "Feature",
  "properties": {
    "iso:country":"US",
    "sg:address":"22020 Dorothy Dr",
    "sg:city":"Siloam Springs",
    "sg:classifiers":[
        {
            "category":"Building & Trades",
            "subcategory":"Construction",
            "type":"Services"
        }
    ],
    "sg:phone":"+1 479 524 5964",
    "sg:postcode":"72761",
    "sg:province":"OK",
    "sg:tags":[
        "excavation",
        "contractor"
    ],
    "wof:name":"Roberts Concrete and Cnstr",
    "wof:placetype":"venue"
},
  "geometry": {"coordinates":[-94.523097,36.216665],"type":"Point"}
}