{
  "type": "Feature",
  "properties": {
    "iso:country":"US",
    "sg:address":"28 Pinto Trl",
    "sg:city":"Greenbrier",
    "sg:classifiers":[
        {
            "category":"Social Services",
            "subcategory":"Child Care",
            "type":"Services"
        }
    ],
    "sg:phone":"+1 501 679 2228",
    "sg:postcode":"72058",
    "sg:province":"AR",
    "sg:tags":[
        "day"
    ],
    "wof:name":"Brownings Family Day Care",
    "wof:placetype":"venue"
},
  "geometry": {"coordinates":[-92.36308,35.239507],"type":"Point"}
}