{
  "type": "Feature",
  "properties": {
    "iso:country":"US",
    "sg:address":"1741 Heber Springs Rd N",
    "sg:city":"Tumbling Shoals",
    "sg:classifiers":[
        {
            "category":"Manufacturing",
            "subcategory":"Rubber & Plastics",
            "type":"Manufacturing & Wholesale Goods"
        }
    ],
    "sg:phone":"+1 501 250 0238",
    "sg:postcode":"72581",
    "sg:province":"AR",
    "sg:tags":[
        "product",
        "mfg"
    ],
    "wof:name":"United Plastics Technology",
    "wof:placetype":"venue"
},
  "geometry": {"coordinates":[-91.971153,35.540407],"type":"Point"}
}