{
  "type": "Feature",
  "properties": {
    "iso:country":"US",
    "sg:address":"35 Romine Ave",
    "sg:city":"Hoxie",
    "sg:classifiers":[
        {
            "category":"Utilities",
            "subcategory":"Refuse",
            "type":"Services"
        }
    ],
    "sg:phone":"+1 870 932 5155",
    "sg:postcode":"72433",
    "sg:province":"AR",
    "sg:tags":[
        "garbage",
        "collection"
    ],
    "wof:name":"Downum Waste Svc Inc",
    "wof:placetype":"venue"
},
  "geometry": {"coordinates":[-90.997903,36.059458],"type":"Point"}
}