{
  "type": "Feature",
  "properties": {
    "iso:country":"US",
    "sg:address":"1705 N College Ave",
    "sg:city":"Fayetteville",
    "sg:classifiers":[
        {
            "category":"Restaurant",
            "type":"Food & Drink"
        }
    ],
    "sg:phone":"+1 479 442 2070",
    "sg:postcode":"72703",
    "sg:province":"AR",
    "sg:tags":[
        "eating"
    ],
    "wof:name":"Long John Silvers",
    "wof:placetype":"venue"
},
  "geometry": {"coordinates":[-94.155311,36.085669],"type":"Point"}
}