{
  "type": "Feature",
  "properties": {
    "iso:country":"US",
    "sg:address":"30 Happy Valley Dr",
    "sg:city":"Conway",
    "sg:classifiers":[
        {
            "category":"Building & Trades",
            "subcategory":"Construction",
            "type":"Services"
        }
    ],
    "sg:phone":"+1 501 336 9221",
    "sg:postcode":"72034",
    "sg:province":"AR",
    "sg:tags":[
        "house"
    ],
    "wof:name":"Duvall Construction",
    "wof:placetype":"venue"
},
  "geometry": {"coordinates":[-92.426769,35.035895],"type":"Point"}
}