{
  "type": "Feature",
  "properties": {
    "addr:full":"8823 Barber St North Little Rock AR 72120",
    "addr:housenumber":"8823",
    "addr:postcode":"72120",
    "addr:street":"Barber St",
    "iso:country":"US",
    "sg:address":"8823 Barber St",
    "sg:city":"North Little Rock",
    "sg:classifiers":[
        {
            "category":"Retail",
            "subcategory":"Repair Shop",
            "type":"Services"
        }
    ],
    "sg:phone":"+1 501 834 1593",
    "sg:postcode":"72120",
    "sg:province":"AR",
    "sg:tags":[
        "welding"
    ],
    "wof:name":"T C Welding Fab",
    "wof:placetype":"venue"
},
  "geometry": {"coordinates":[-92.22470800000001,34.834558],"type":"Point"}
}