{
  "type": "Feature",
  "properties": {
    "addr:full":"1043 N Washington St Forrest City AR 72335",
    "addr:housenumber":"1043",
    "addr:postcode":"72335",
    "addr:street":"N Washington St",
    "iso:country":"US",
    "sg:address":"1043 N Washington St",
    "sg:city":"Forrest City",
    "sg:classifiers":[
        {
            "category":"Real Estate",
            "subcategory":"Real Estate Agent",
            "type":"Services"
        }
    ],
    "sg:phone":"+1 870 633 0181",
    "sg:postcode":"72335",
    "sg:province":"AR",
    "wof:name":"Ramsey Realty",
    "wof:placetype":"venue"
},
  "geometry": {"coordinates":[-90.787334,35.019638],"type":"Point"}
}