{
  "type": "Feature",
  "properties": {
    "iso:country":"US",
    "sg:address":"10624 Glendale Rd",
    "sg:city":"Pine Bluff",
    "sg:classifiers":[
        {
            "category":"Shopping",
            "subcategory":"Clothing, Apparel, & Fashions",
            "type":"Retail Goods"
        }
    ],
    "sg:phone":"+1 870 534 4855",
    "sg:postcode":"71603",
    "sg:province":"AR",
    "wof:name":"Wearable Arts",
    "wof:placetype":"venue"
},
  "geometry": {"coordinates":[-91.995389,34.086092],"type":"Point"}
}