{
  "type": "Feature",
  "properties": {
    "iso:country":"US",
    "sg:address":"401 S Main St",
    "sg:city":"Stuttgart",
    "sg:classifiers":[
        {
            "category":"Shopping",
            "subcategory":"Musical Instruments",
            "type":"Retail Goods"
        }
    ],
    "sg:phone":"+1 870 673 9318",
    "sg:postcode":"72160",
    "sg:province":"AR",
    "wof:name":"Davis Music Sups & Bb Bk Str",
    "wof:placetype":"venue"
},
  "geometry": {"coordinates":[-91.55261,34.49924],"type":"Point"}
}