{
  "type": "Feature",
  "properties": {
    "iso:country":"US",
    "sg:address":"261 S New York Ave",
    "sg:city":"Caraway",
    "sg:classifiers":[
        {
            "category":"Home & Garden",
            "subcategory":"Carpets & Floor Coverings",
            "type":"Retail Goods"
        }
    ],
    "sg:phone":"+1 870 482 1020",
    "sg:postcode":"72419",
    "sg:province":"AR",
    "sg:tags":[
        "distributor",
        "rug",
        "manufacturer"
    ],
    "wof:name":"Tri State Carpets",
    "wof:placetype":"venue"
},
  "geometry": {"coordinates":[-90.322632,35.757244],"type":"Point"}
}