{
  "type": "Feature",
  "properties": {
    "iso:country":"US",
    "sg:address":"1912 N Hills Blvd",
    "sg:city":"Van Buren",
    "sg:classifiers":[
        {
            "category":"Retail",
            "subcategory":"Repair Shop",
            "type":"Services"
        }
    ],
    "sg:phone":"+1 479 410 1133",
    "sg:postcode":"72956",
    "sg:province":"AR",
    "wof:name":"Nat Plumbing",
    "wof:placetype":"venue"
},
  "geometry": {"coordinates":[-94.36592,35.465149],"type":"Point"}
}