{
  "type": "Feature",
  "properties": {
    "addr:full":"2501 Hwy 286 W Conway AR 72034",
    "addr:housenumber":"2501",
    "addr:postcode":"72034",
    "addr:street":"Hwy 286 W",
    "iso:country":"US",
    "sg:address":"2501 Hwy 286 W",
    "sg:city":"Conway",
    "sg:classifiers":[
        {
            "category":"Shopping",
            "subcategory":"Tobacco",
            "type":"Retail Goods"
        }
    ],
    "sg:phone":"+1 501 450 7626",
    "sg:postcode":"72034",
    "sg:province":"AR",
    "sg:tags":[
        "product"
    ],
    "wof:name":"Tobacco Station USA",
    "wof:placetype":"venue"
},
  "geometry": {"coordinates":[-92.466303,35.070364],"type":"Point"}
}