{
  "type": "Feature",
  "properties": {
    "iso:country":"US",
    "sg:address":"119 Traskwood Rd",
    "sg:city":"Malvern",
    "sg:classifiers":[
        {
            "category":"Personal",
            "subcategory":"Beauty Salon",
            "type":"Services"
        }
    ],
    "sg:phone":"+1 501 332 6003",
    "sg:postcode":"72104",
    "sg:province":"AR",
    "sg:tags":[
        "shop"
    ],
    "wof:name":"Kim's Mane Attraction",
    "wof:placetype":"venue"
},
  "geometry": {"coordinates":[-92.72753299999999,34.459271],"type":"Point"}
}