{
  "type": "Feature",
  "properties": {
    "addr:full":"3699 Murrell Pl Springdale AR 72762",
    "addr:housenumber":"3699",
    "addr:postcode":"72762",
    "addr:street":"Murrell Pl",
    "iso:country":"US",
    "sg:address":"3699 Murrell Pl",
    "sg:city":"Springdale",
    "sg:classifiers":[
        {
            "category":"Building & Trades",
            "subcategory":"Construction",
            "type":"Services"
        }
    ],
    "sg:phone":"+1 479 361 2554",
    "sg:postcode":"72762",
    "sg:province":"AR",
    "sg:tags":[
        "excavating",
        "contractor"
    ],
    "wof:name":"Holtzclaw Excavating Inc",
    "wof:placetype":"venue"
},
  "geometry": {"coordinates":[-94.195395,36.153115],"type":"Point"}
}