{
  "type": "Feature",
  "properties": {
    "iso:country":"US",
    "sg:address":"19863 I- 30",
    "sg:city":"Benton",
    "sg:classifiers":[
        {
            "category":"Professional",
            "subcategory":"Advertising",
            "type":"Services"
        }
    ],
    "sg:phone":"+1 501 407 8088",
    "sg:postcode":"72015",
    "sg:province":"AR",
    "sg:tags":[
        "distribution"
    ],
    "wof:name":"Ameron Distributor",
    "wof:placetype":"venue"
},
  "geometry": {"coordinates":[-92.534354,34.605767],"type":"Point"}
}