{
  "type": "Feature",
  "properties": {
    "iso:country":"US",
    "sg:address":"945 N Plum St",
    "sg:city":"Booneville",
    "sg:classifiers":[
        {
            "category":"Education",
            "subcategory":"School",
            "type":"Public Place"
        }
    ],
    "sg:phone":"+1 479 675 3277",
    "sg:postcode":"72927",
    "sg:province":"AR",
    "wof:name":"Booneville High School",
    "wof:placetype":"venue"
},
  "geometry": {"coordinates":[-93.908339,35.145387],"type":"Point"}
}