{
  "type": "Feature",
  "properties": {
    "iso:country":"US",
    "sg:address":"3860 Eger Dr",
    "sg:city":"Harrison",
    "sg:classifiers":[
        {
            "category":"Professional",
            "subcategory":"Advertising",
            "type":"Services"
        }
    ],
    "sg:phone":"+1 870 365 3692",
    "sg:postcode":"72601",
    "sg:province":"AR",
    "sg:tags":[
        "advertising-broadcast",
        "film"
    ],
    "sg:website":"http://www.bransonworldradio.com",
    "wof:name":"Branson World Radio",
    "wof:placetype":"venue"
},
  "geometry": {"coordinates":[-93.017418,36.229909],"type":"Point"}
}