{
  "type": "Feature",
  "properties": {
    "iso:country":"US",
    "sg:address":"1925 N Green Acres Rd",
    "sg:city":"Fayetteville",
    "sg:classifiers":[
        {
            "category":"Organizations",
            "subcategory":"Religious Organization",
            "type":"Services"
        }
    ],
    "sg:phone":"+1 479 521 1295",
    "sg:postcode":"72703",
    "sg:province":"AR",
    "wof:name":"Washington Madison Baptist Association",
    "wof:placetype":"venue"
},
  "geometry": {"coordinates":[-94.155365,36.086209],"type":"Point"}
}