{
  "type": "Feature",
  "properties": {
    "addr:full":"1014 Malcolm Ave Newport AR 72112",
    "addr:housenumber":"1014",
    "addr:postcode":"72112",
    "addr:street":"Malcolm Ave",
    "iso:country":"US",
    "sg:address":"1014 Malcolm Ave",
    "sg:city":"Newport",
    "sg:classifiers":[
        {
            "category":"Shopping",
            "subcategory":"Discount & Variety Stores",
            "type":"Retail Goods"
        }
    ],
    "sg:phone":"+1 870 523 6723",
    "sg:postcode":"72112",
    "sg:province":"AR",
    "wof:name":"Family Dollar Stores",
    "wof:placetype":"venue"
},
  "geometry": {"coordinates":[-91.267658,35.606195],"type":"Point"}
}