{
  "type": "Feature",
  "properties": {
    "iso:country":"US",
    "sg:address":"301 Merganzer Dr",
    "sg:city":"Jacksonville",
    "sg:classifiers":[
        {
            "category":"Organizations",
            "subcategory":"Professional Association",
            "type":"Services"
        }
    ],
    "sg:phone":"+1 501 835 3513",
    "sg:postcode":"72076",
    "sg:province":"AR",
    "wof:name":"International Reading Asso",
    "wof:placetype":"venue"
},
  "geometry": {"coordinates":[-92.171265,34.859924],"type":"Point"}
}