{
  "type": "Feature",
  "properties": {
    "iso:country":"US",
    "sg:address":"300 N 3rd St",
    "sg:city":"Mc Gehee",
    "sg:classifiers":[
        {
            "category":"Utilities",
            "subcategory":"Telephone",
            "type":"Services"
        }
    ],
    "sg:phone":"+1 800 403 3302",
    "sg:postcode":"71654",
    "sg:province":"AR",
    "wof:name":"Southwestern Bell Telephone LP",
    "wof:placetype":"venue"
},
  "geometry": {"coordinates":[-91.39934,33.63043],"type":"Point"}
}