{
  "type": "Feature",
  "properties": {
    "iso:country":"US",
    "sg:address":"108 Main St",
    "sg:city":"Wickes",
    "sg:classifiers":[
        {
            "category":"Government",
            "subcategory":"Office",
            "type":"Public Place"
        }
    ],
    "sg:phone":"+1 870 385 2575",
    "sg:postcode":"71973",
    "sg:province":"AR",
    "sg:tags":[
        "city"
    ],
    "wof:name":"Wickes City Hall",
    "wof:placetype":"venue"
},
  "geometry": {"coordinates":[-94.336853,34.301899],"type":"Point"}
}