{
  "type": "Feature",
  "properties": {
    "iso:country":"US",
    "sg:address":"1316 Edison Ave",
    "sg:city":"Benton",
    "sg:classifiers":[
        {
            "category":"Food & Beverages",
            "subcategory":"Groceries & Convenience Stores",
            "type":"Retail Goods"
        }
    ],
    "sg:phone":"+1 501 315 7141",
    "sg:postcode":"72015",
    "sg:province":"AR",
    "sg:website":"http://www.save-a-lot.com/",
    "wof:name":"Save-A-Lot",
    "wof:placetype":"venue"
},
  "geometry": {"coordinates":[-92.57185800000001,34.557307],"type":"Point"}
}