{
  "type": "Feature",
  "properties": {
    "addr:full":"2525 W Mount Comfort Rd Fayetteville AR 72704",
    "addr:housenumber":"2525",
    "addr:postcode":"72704",
    "addr:street":"W Mount Comfort Rd",
    "iso:country":"US",
    "sg:address":"2525 W Mount Comfort Rd",
    "sg:city":"Fayetteville",
    "sg:classifiers":[
        {
            "category":"Home & Garden",
            "subcategory":"Garden Supply",
            "type":"Retail Goods"
        }
    ],
    "sg:phone":"+1 479 442 7430",
    "sg:postcode":"72704",
    "sg:province":"AR",
    "wof:name":"Epperly Investments",
    "wof:placetype":"venue"
},
  "geometry": {"coordinates":[-94.19565,36.092566],"type":"Point"}
}