{
  "type": "Feature",
  "properties": {
    "iso:country":"US",
    "sg:address":"1002 Mcclain Rd Ste 110",
    "sg:city":"Bentonville",
    "sg:classifiers":[
        {
            "category":"Manufacturing",
            "subcategory":"Petroleum Products",
            "type":"Manufacturing & Wholesale Goods"
        }
    ],
    "sg:phone":"+1 479 273 1178",
    "sg:postcode":"72712",
    "sg:province":"AR",
    "sg:tags":[
        "contract"
    ],
    "sg:website":"http://www.dss-retail.com",
    "wof:name":"Decision Support Services",
    "wof:placetype":"venue"
},
  "geometry": {"coordinates":[-94.172409,36.381802],"type":"Point"}
}