{
  "type": "Feature",
  "properties": {
    "addr:full":"309 W Cedar St Brinkley AR 72021",
    "addr:housenumber":"309",
    "addr:postcode":"72021",
    "addr:street":"W Cedar St",
    "iso:country":"US",
    "sg:address":"309 W Cedar St",
    "sg:city":"Brinkley",
    "sg:classifiers":[
        {
            "category":"Government",
            "subcategory":"Office",
            "type":"Public Place"
        }
    ],
    "sg:phone":"+1 870 734 1816",
    "sg:postcode":"72021",
    "sg:province":"AR",
    "sg:website":"http://www.aseaar.org",
    "wof:name":"Revenue Office",
    "wof:placetype":"venue"
},
  "geometry": {"coordinates":[-91.194688,34.888063],"type":"Point"}
}