{
  "type": "Feature",
  "properties": {
    "addr:full":"217 N East Ave Fayetteville AR 72701",
    "addr:housenumber":"217",
    "addr:postcode":"72701",
    "addr:street":"N East Ave",
    "iso:country":"US",
    "sg:address":"217 N East Ave",
    "sg:city":"Fayetteville",
    "sg:classifiers":[
        {
            "category":"Freight",
            "type":"Transportation"
        }
    ],
    "sg:phone":"+1 479 718 7070",
    "sg:postcode":"72701",
    "sg:province":"AR",
    "sg:tags":[
        "trucking"
    ],
    "wof:name":"Show Transport Co",
    "wof:placetype":"venue"
},
  "geometry": {"coordinates":[-94.15963499999999,36.06604],"type":"Point"}
}