{
  "type": "Feature",
  "properties": {
    "iso:country":"US",
    "sg:address":"4616 Old Warren Rd",
    "sg:city":"Pine Bluff",
    "sg:classifiers":[
        {
            "category":"Professional",
            "subcategory":"Advertising",
            "type":"Services"
        }
    ],
    "sg:phone":"+1 870 541 9099",
    "sg:postcode":"71603",
    "sg:province":"AR",
    "wof:name":"Cox Media Advertising",
    "wof:placetype":"venue"
},
  "geometry": {"coordinates":[-92.045022,34.179397],"type":"Point"}
}