{
  "type": "Feature",
  "properties": {
    "iso:country":"US",
    "sg:address":"1314 US Hwy 71 Bus",
    "sg:city":"Fort Smith",
    "sg:classifiers":[
        {
            "category":"Travel",
            "subcategory":"Hotels & Motels",
            "type":"Entertainment"
        }
    ],
    "sg:phone":"+1 479 646 1661",
    "sg:postcode":"72901",
    "sg:province":"AR",
    "sg:tags":[
        "operation"
    ],
    "wof:name":"Magnolia Inn Motel",
    "wof:placetype":"venue"
},
  "geometry": {"coordinates":[-94.421499,35.370374],"type":"Point"}
}