{
  "type": "Feature",
  "properties": {
    "addr:full":"309 American Rd El Dorado AR 71730",
    "addr:housenumber":"309",
    "addr:postcode":"71730",
    "addr:street":"American Rd",
    "iso:country":"US",
    "sg:address":"309 American Rd",
    "sg:city":"El Dorado",
    "sg:classifiers":[
        {
            "category":"Wholesale",
            "subcategory":"Chemicals & Plastics",
            "type":"Manufacturing & Wholesale Goods"
        }
    ],
    "sg:phone":"+1 870 862 9850",
    "sg:postcode":"71730",
    "sg:province":"AR",
    "wof:name":"Jayco Coating and Supply Inc",
    "wof:placetype":"venue"
},
  "geometry": {"coordinates":[-92.63087400000001,33.209084],"type":"Point"}
}