{
  "type": "Feature",
  "properties": {
    "addr:full":"4128 Misenheimer Rd Mountain View AR 72560",
    "addr:housenumber":"4128",
    "addr:postcode":"72560",
    "addr:street":"Misenheimer Rd",
    "iso:country":"US",
    "sg:address":"4128 Misenheimer Rd",
    "sg:city":"Mountain View",
    "sg:classifiers":[
        {
            "category":"Professional",
            "subcategory":"Business Services",
            "type":"Services"
        }
    ],
    "sg:phone":"+1 870 269 4503",
    "sg:postcode":"72560",
    "sg:province":"AR",
    "wof:name":"S & S Salvage",
    "wof:placetype":"venue"
},
  "geometry": {"coordinates":[-92.06362900000001,35.820016],"type":"Point"}
}