{
  "type": "Feature",
  "properties": {
    "addr:full":"1490 California Ave SW Camden AR 71701",
    "addr:housenumber":"1490",
    "addr:postcode":"71701",
    "addr:street":"California Ave Sw",
    "iso:country":"US",
    "sg:address":"1490 California Ave SW",
    "sg:city":"Camden",
    "sg:classifiers":[
        {
            "category":"Personal",
            "subcategory":"Beauty Salon",
            "type":"Services"
        }
    ],
    "sg:phone":"+1 870 836 6440",
    "sg:postcode":"71701",
    "sg:province":"AR",
    "sg:tags":[
        "shop"
    ],
    "wof:name":"Top Cut Barber & Beauty Shop",
    "wof:placetype":"venue"
},
  "geometry": {"coordinates":[-92.85478000000001,33.558489],"type":"Point"}
}