{
  "type": "Feature",
  "properties": {
    "iso:country":"US",
    "sg:address":"3813 Quail Ln",
    "sg:city":"Benton",
    "sg:classifiers":[
        {
            "category":"Real Estate",
            "subcategory":"Real Estate Agent",
            "type":"Services"
        }
    ],
    "sg:phone":"+1 501 794 1003",
    "sg:postcode":"72019",
    "sg:province":"AR",
    "wof:name":"Summit Properties",
    "wof:placetype":"venue"
},
  "geometry": {"coordinates":[-92.541409,34.61412],"type":"Point"}
}