{
  "type": "Feature",
  "properties": {
    "iso:country":"US",
    "sg:address":"2524 W Main St",
    "sg:city":"Russellville",
    "sg:classifiers":[
        {
            "category":"Building & Trades",
            "subcategory":"Equipment Rental",
            "type":"Services"
        }
    ],
    "sg:phone":"+1 479 229 3367",
    "sg:postcode":"72801",
    "sg:province":"AR",
    "sg:tags":[
        "medical",
        "merchandise"
    ],
    "wof:name":"American Homepatient",
    "wof:placetype":"venue"
},
  "geometry": {"coordinates":[-93.155147,35.284502],"type":"Point"}
}