{
  "type": "Feature",
  "properties": {
    "iso:country":"US",
    "sg:address":"1851 E Huntsville Rd",
    "sg:city":"Fayetteville",
    "sg:classifiers":[
        {
            "category":"Wholesale",
            "subcategory":"Groceries",
            "type":"Manufacturing & Wholesale Goods"
        }
    ],
    "sg:phone":"+1 479 527 0763",
    "sg:postcode":"72701",
    "sg:province":"AR",
    "wof:name":"Pepper Source Ltd",
    "wof:placetype":"venue"
},
  "geometry": {"coordinates":[-94.134787,36.053736],"type":"Point"}
}