{
  "type": "Feature",
  "properties": {
    "iso:country":"US",
    "sg:address":"320 Executive Ct",
    "sg:city":"Little Rock",
    "sg:classifiers":[
        {
            "category":"Real Estate",
            "subcategory":"Real Estate Agent",
            "type":"Services"
        }
    ],
    "sg:phone":"+1 501 223 3800",
    "sg:postcode":"72205",
    "sg:province":"AR",
    "sg:tags":[
        "manager",
        "developer"
    ],
    "sg:website":"www.terrymooreinc.com",
    "wof:name":"Terry Moore & Associates Inc",
    "wof:placetype":"venue"
},
  "geometry": {"coordinates":[-92.390412,34.753302],"type":"Point"}
}