{
  "type": "Feature",
  "properties": {
    "iso:country":"US",
    "sg:address":"1400 N Division St",
    "sg:city":"Blytheville",
    "sg:classifiers":[
        {
            "category":"Health Services",
            "subcategory":"Nursing And Care Facility",
            "type":"Services"
        }
    ],
    "sg:phone":"+1 870 763 0240",
    "sg:postcode":"72315",
    "sg:province":"AR",
    "sg:tags":[
        "skilled"
    ],
    "wof:name":"Beverly",
    "wof:placetype":"venue"
},
  "geometry": {"coordinates":[-89.918922,35.941669],"type":"Point"}
}