{
  "type": "Feature",
  "properties": {
    "iso:country":"US",
    "sg:address":"1772 E Lake Rd",
    "sg:city":"Springdale",
    "sg:classifiers":[
        {
            "category":"Communications",
            "subcategory":"Radio Station",
            "type":"Services"
        }
    ],
    "sg:phone":"+1 479 751 8800",
    "sg:postcode":"72762",
    "sg:province":"AR",
    "wof:name":"P M C Drywall Inc",
    "wof:placetype":"venue"
},
  "geometry": {"coordinates":[-94.211589,36.201463],"type":"Point"}
}