{
  "type": "Feature",
  "properties": {
    "iso:country":"US",
    "sg:address":"8 Arrow Ridge Ct",
    "sg:city":"Little Rock",
    "sg:classifiers":[
        {
            "category":"Professional",
            "subcategory":"Management & Consulting",
            "type":"Services"
        }
    ],
    "sg:phone":"+1 501 221 1976",
    "sg:postcode":"72205",
    "sg:province":"AR",
    "sg:tags":[
        "consultant",
        "training"
    ],
    "wof:name":"Polansky & Associates",
    "wof:placetype":"venue"
},
  "geometry": {"coordinates":[-92.3704,34.761048],"type":"Point"}
}