{
  "type": "Feature",
  "properties": {
    "addr:full":"2621 W Main St Russellville AR 72801",
    "addr:housenumber":"2621",
    "addr:postcode":"72801",
    "addr:street":"W Main St",
    "iso:country":"US",
    "sg:address":"2621 W Main St",
    "sg:city":"Russellville",
    "sg:classifiers":[
        {
            "category":"Autos & Motor Vehicles",
            "subcategory":"Fuel & Gas Station",
            "type":"Retail Goods"
        }
    ],
    "sg:phone":"+1 479 890 6002",
    "sg:postcode":"72801",
    "sg:province":"AR",
    "sg:tags":[
        "oil"
    ],
    "wof:name":"Exxon Mobil Corp",
    "wof:placetype":"venue"
},
  "geometry": {"coordinates":[-93.158832,35.285471],"type":"Point"}
}