{
  "type": "Feature",
  "properties": {
    "iso:country":"US",
    "sg:address":"2621 W Main St",
    "sg:city":"Russellville",
    "sg:classifiers":[
        {
            "category":"Autos & Motor Vehicles",
            "subcategory":"Fuel & Gas Station",
            "type":"Retail Goods"
        }
    ],
    "sg:phone":"+1 479 890 6002",
    "sg:postcode":"72801",
    "sg:province":"AR",
    "sg:tags":[
        "oil"
    ],
    "wof:name":"Exxon Mobil Corp",
    "wof:placetype":"venue"
},
  "geometry": {"coordinates":[-93.158832,35.285471],"type":"Point"}
}