{
  "type": "Feature",
  "properties": {
    "addr:full":"10020 Townsend Rd Benton AR 72019",
    "addr:housenumber":"10020",
    "addr:postcode":"72019",
    "addr:street":"Townsend Rd",
    "iso:country":"US",
    "sg:address":"10020 Townsend Rd",
    "sg:city":"Benton",
    "sg:classifiers":[
        {
            "category":"Wholesale",
            "subcategory":"Farm Supplies",
            "type":"Manufacturing & Wholesale Goods"
        }
    ],
    "sg:phone":"+1 501 315 6700",
    "sg:postcode":"72019",
    "sg:province":"AR",
    "sg:tags":[
        "feed"
    ],
    "wof:name":"Bar None Feed",
    "wof:placetype":"venue"
},
  "geometry": {"coordinates":[-92.696361,34.534402],"type":"Point"}
}