{
  "type": "Feature",
  "properties": {
    "addr:full":"1203 Monte NE Rd Rogers AR 72756",
    "addr:housenumber":"1203",
    "addr:postcode":"72756",
    "addr:street":"Monte Ne Rd",
    "iso:country":"US",
    "sg:address":"1203 Monte NE Rd",
    "sg:city":"Rogers",
    "sg:classifiers":[
        {
            "category":"Food & Beverages",
            "subcategory":"Supermarket",
            "type":"Retail Goods"
        },
        {
            "category":"Food & Beverages",
            "subcategory":"Groceries & Convenience Stores",
            "type":"Retail Goods"
        }
    ],
    "sg:phone":"+1 479 631 3075",
    "sg:postcode":"72756",
    "sg:province":"AR",
    "sg:tags":[
        "super"
    ],
    "sg:website":"http://www.stopandshop.com",
    "wof:name":"Stop & Shop",
    "wof:placetype":"venue"
},
  "geometry": {"coordinates":[-94.108811,36.32186],"type":"Point"}
}