{
  "type": "Feature",
  "properties": {
    "iso:country":"US",
    "sg:address":"1633 Kelly Ave",
    "sg:city":"Springdale",
    "sg:classifiers":[
        {
            "category":"Building & Trades",
            "subcategory":"Construction",
            "type":"Services"
        }
    ],
    "sg:phone":"+1 479 361 9566",
    "sg:postcode":"72762",
    "sg:province":"AR",
    "sg:tags":[
        "insulation",
        "heat",
        "contractor"
    ],
    "wof:name":"Arkansas Foam Insulation",
    "wof:placetype":"venue"
},
  "geometry": {"coordinates":[-94.26324700000001,36.155096],"type":"Point"}
}