{
  "type": "Feature",
  "properties": {
    "addr:full":"22391 Butler Ford Rd Springdale AR 72764",
    "addr:housenumber":"22391",
    "addr:postcode":"72764",
    "addr:street":"Butler Ford Rd",
    "iso:country":"US",
    "sg:address":"22391 Butler Ford Rd",
    "sg:city":"Springdale",
    "sg:classifiers":[
        {
            "category":"Building & Trades",
            "subcategory":"Landscaping Services",
            "type":"Services"
        },
        {
            "category":"Building & Trades",
            "subcategory":"Cleaning & Sanitation",
            "type":"Services"
        },
        {
            "category":"Professional",
            "subcategory":"Employment Agencies",
            "type":"Services"
        },
        {
            "category":"Building & Trades",
            "subcategory":"Construction",
            "type":"Services"
        }
    ],
    "sg:phone":"+1 479 304 6605",
    "sg:postcode":"72764",
    "sg:province":"AR",
    "sg:tags":[
        "fire",
        "remodeling",
        "handyman",
        "damage",
        "contractor",
        "water",
        "planning",
        "restoration",
        "painting",
        "landscape",
        "kitchen"
    ],
    "sg:website":"http://www.blankenshipslabor.com/",
    "wof:name":"Blankenship's Labor Services",
    "wof:placetype":"venue"
},
  "geometry": {"coordinates":[-94.01759699999999,36.211926],"type":"Point"}
}