{
  "type": "Feature",
  "properties": {
    "iso:country":"US",
    "sg:address":"3900 Dave Ward Dr",
    "sg:city":"Conway",
    "sg:classifiers":[
        {
            "category":"Personal",
            "subcategory":"Beauty Salon",
            "type":"Services"
        }
    ],
    "sg:phone":"+1 501 329 7729",
    "sg:postcode":"72034",
    "sg:province":"AR",
    "wof:name":"Smart Style Family Hair Salon",
    "wof:placetype":"venue"
},
  "geometry": {"coordinates":[-92.499757,35.071061],"type":"Point"}
}