{
  "type": "Feature",
  "properties": {
    "iso:country":"US",
    "sg:address":"405 E Michigan St",
    "sg:city":"Stuttgart",
    "sg:classifiers":[
        {
            "category":"Travel",
            "subcategory":"Hotels & Motels",
            "type":"Entertainment"
        }
    ],
    "sg:phone":"+1 870 673 2671",
    "sg:postcode":"72160",
    "sg:province":"AR",
    "sg:tags":[
        "inn",
        "motor"
    ],
    "wof:name":"Walker Motor Inn",
    "wof:placetype":"venue"
},
  "geometry": {"coordinates":[-91.547164,34.509498],"type":"Point"}
}