{
  "type": "Feature",
  "properties": {
    "iso:country":"US",
    "sg:address":"1423 E 9th St",
    "sg:city":"Mountain Home",
    "sg:classifiers":[
        {
            "category":"Autos & Motor Vehicles",
            "subcategory":"Fuel & Gas Station",
            "type":"Retail Goods"
        }
    ],
    "sg:phone":"+1 870 425 3693",
    "sg:postcode":"72653",
    "sg:province":"AR",
    "sg:tags":[
        "oil"
    ],
    "wof:name":"South Side Fina",
    "wof:placetype":"venue"
},
  "geometry": {"coordinates":[-92.36234,36.332855],"type":"Point"}
}