{
  "type": "Feature",
  "properties": {
    "iso:country":"US",
    "sg:address":"149 Park St",
    "sg:city":"Monticello",
    "sg:classifiers":[
        {
            "category":"Restaurant",
            "type":"Food & Drink"
        }
    ],
    "sg:phone":"+1 870 460 9348",
    "sg:postcode":"71655",
    "sg:province":"AR",
    "sg:tags":[
        "mexican"
    ],
    "wof:name":"Ameca Mexican Restaurant",
    "wof:placetype":"venue"
},
  "geometry": {"coordinates":[-91.797474,33.647043],"type":"Point"}
}