{
  "type": "Feature",
  "properties": {
    "iso:country":"US",
    "sg:address":"12107 Red Oak Dr",
    "sg:city":"Fayetteville",
    "sg:classifiers":[
        {
            "category":"Food & Beverages",
            "subcategory":"Candy",
            "type":"Retail Goods"
        }
    ],
    "sg:phone":"+1 479 361 9671",
    "sg:postcode":"72704",
    "sg:province":"AR",
    "wof:name":"Classic Candies",
    "wof:placetype":"venue"
},
  "geometry": {"coordinates":[-94.254532,36.128641],"type":"Point"}
}