{
  "type": "Feature",
  "properties": {
    "addr:full":"411 S 7th St Paragould AR 72450",
    "addr:housenumber":"411",
    "addr:postcode":"72450",
    "addr:street":"S 7Th St",
    "iso:country":"US",
    "sg:address":"411 S 7th St",
    "sg:city":"Paragould",
    "sg:classifiers":[
        {
            "category":"Insurance",
            "subcategory":"Life Insurance",
            "type":"Services"
        }
    ],
    "sg:phone":"+1 870 236 8714",
    "sg:postcode":"72450",
    "sg:province":"AR",
    "sg:tags":[
        "agency"
    ],
    "wof:name":"Anico",
    "wof:placetype":"venue"
},
  "geometry": {"coordinates":[-90.494473,36.052599],"type":"Point"}
}