{
  "type": "Feature",
  "properties": {
    "iso:country":"US",
    "sg:address":"5630 Park Ave",
    "sg:city":"Hot Springs National",
    "sg:classifiers":[
        {
            "category":"Building & Trades",
            "subcategory":"Construction",
            "type":"Services"
        }
    ],
    "sg:phone":"+1 501 624 7932",
    "sg:postcode":"71901",
    "sg:province":"AR",
    "sg:tags":[
        "contractor",
        "nonresidential"
    ],
    "wof:name":"Aero-Tech Siding and Windows",
    "wof:placetype":"venue"
},
  "geometry": {"coordinates":[-92.964734,34.590227],"type":"Point"}
}