{
  "type": "Feature",
  "properties": {
    "iso:country":"US",
    "sg:address":"7806 SW Blue Jay Ln Apt 14",
    "sg:city":"Bentonville",
    "sg:classifiers":[
        {
            "category":"Real Estate",
            "subcategory":"Real Estate Operator",
            "type":"Services"
        }
    ],
    "sg:phone":"+1 479 224 0277",
    "sg:postcode":"72712",
    "sg:province":"AR",
    "sg:tags":[
        "apartment"
    ],
    "wof:name":"Vaughn Apartments",
    "wof:placetype":"venue"
},
  "geometry": {"coordinates":[-94.3007,36.3134],"type":"Point"}
}