{
  "type": "Feature",
  "properties": {
    "iso:country":"US",
    "sg:address":"306 N Main St",
    "sg:city":"Fordyce",
    "sg:classifiers":[
        {
            "category":"Manufacturing",
            "subcategory":"Printing",
            "type":"Manufacturing & Wholesale Goods"
        }
    ],
    "sg:phone":"+1 870 352 3146",
    "sg:postcode":"71742",
    "sg:province":"AR",
    "sg:tags":[
        "publishing"
    ],
    "wof:name":"Office Products",
    "wof:placetype":"venue"
},
  "geometry": {"coordinates":[-92.412915,33.813707],"type":"Point"}
}