{
  "type": "Feature",
  "properties": {
    "iso:country":"US",
    "sg:address":"2716 N Church St",
    "sg:city":"Jonesboro",
    "sg:classifiers":[
        {
            "category":"Wholesale",
            "subcategory":"Farm Supplies",
            "type":"Manufacturing & Wholesale Goods"
        }
    ],
    "sg:phone":"+1 870 935 0053",
    "sg:postcode":"72401",
    "sg:province":"AR",
    "sg:tags":[
        "feed"
    ],
    "wof:name":"Gibson's Feed & Farm Supply",
    "wof:placetype":"venue"
},
  "geometry": {"coordinates":[-90.702557,35.878542],"type":"Point"}
}