{
  "type": "Feature",
  "properties": {
    "iso:country":"US",
    "sg:address":"7015 Russwood Ln E",
    "sg:city":"Mabelvale",
    "sg:classifiers":[
        {
            "category":"Building & Trades",
            "subcategory":"Cleaning & Sanitation",
            "type":"Services"
        }
    ],
    "sg:phone":"+1 501 261 7431",
    "sg:postcode":"72103",
    "sg:province":"AR",
    "sg:tags":[
        "janitor"
    ],
    "wof:name":"Top One Svc",
    "wof:placetype":"venue"
},
  "geometry": {"coordinates":[-92.363561,34.60653],"type":"Point"}
}