{
  "type": "Feature",
  "properties": {
    "iso:country":"US",
    "sg:address":"19008 Macarthur Dr",
    "sg:city":"N Little Rock",
    "sg:classifiers":[
        {
            "category":"Food & Beverages",
            "subcategory":"Liquor & Beverages",
            "type":"Retail Goods"
        }
    ],
    "sg:phone":"+1 501 851 2723",
    "sg:postcode":"72118",
    "sg:province":"AR",
    "wof:name":"Oscar's Liquor Store",
    "wof:placetype":"venue"
},
  "geometry": {"coordinates":[-92.37694500000001,34.886876],"type":"Point"}
}