{
  "type": "Feature",
  "properties": {
    "iso:country":"US",
    "sg:address":"939 E Main St",
    "sg:city":"Blytheville",
    "sg:classifiers":[
        {
            "category":"Autos & Motor Vehicles",
            "subcategory":"Auto Supplies",
            "type":"Retail Goods"
        }
    ],
    "sg:phone":"+1 870 763 1247",
    "sg:postcode":"72315",
    "sg:province":"AR",
    "sg:tags":[
        "automotive",
        "parts",
        "automobile"
    ],
    "wof:name":"Advance Auto Parts Inc",
    "wof:placetype":"venue"
},
  "geometry": {"coordinates":[-89.883866,35.927214],"type":"Point"}
}