{
  "type": "Feature",
  "properties": {
    "iso:country":"US",
    "sg:address":"38 Crestwood Dr",
    "sg:city":"Eureka Springs",
    "sg:classifiers":[
        {
            "category":"Personal",
            "type":"Services"
        }
    ],
    "sg:phone":"+1 479 253 2526",
    "sg:postcode":"72631",
    "sg:province":"AR",
    "sg:tags":[
        "wedding",
        "chapel"
    ],
    "wof:name":"All About Love",
    "wof:placetype":"venue"
},
  "geometry": {"coordinates":[-93.836178,36.382737],"type":"Point"}
}