{
  "type": "Feature",
  "properties": {
    "iso:country":"US",
    "sg:address":"8250 W McNelly Rd",
    "sg:city":"Bentonville",
    "sg:classifiers":[
        {
            "category":"Shopping",
            "type":"Retail Goods"
        }
    ],
    "sg:phone":"+1 479 464 5000",
    "sg:postcode":"72712",
    "sg:province":"AR",
    "sg:tags":[
        "plastic"
    ],
    "wof:name":"Thomson Marketing Group",
    "wof:placetype":"venue"
},
  "geometry": {"coordinates":[-94.21263999999999,36.427763],"type":"Point"}
}