{
  "type": "Feature",
  "properties": {
    "iso:country":"US",
    "sg:address":"11525 Highway 49 N",
    "sg:city":"Marmaduke",
    "sg:classifiers":[
        {
            "category":"Banks & Credit Unions",
            "subcategory":"Bank",
            "type":"Services"
        }
    ],
    "sg:phone":"+1 870 597 4300",
    "sg:postcode":"72443",
    "sg:province":"AR",
    "sg:tags":[
        "saving",
        "commercial"
    ],
    "sg:website":"http://www.bancorpsouthonline.com",
    "wof:name":"Bancorpsouth",
    "wof:placetype":"venue"
},
  "geometry": {"coordinates":[-90.32811599999999,36.231788],"type":"Point"}
}