{
  "type": "Feature",
  "properties": {
    "iso:country":"US",
    "sg:address":"2929 S Caraway Rd",
    "sg:city":"Jonesboro",
    "sg:classifiers":[
        {
            "category":"Professional",
            "subcategory":"Computer Services",
            "type":"Services"
        },
        {
            "category":"Shopping",
            "subcategory":"Computers & Home Electronics",
            "type":"Retail Goods"
        }
    ],
    "sg:phone":"+1 870 931 7655",
    "sg:postcode":"72404",
    "sg:province":"AR",
    "sg:tags":[
        "prepackaged",
        "software",
        "custom"
    ],
    "wof:name":"Diamond Software",
    "wof:placetype":"venue"
},
  "geometry": {"coordinates":[-90.67828,35.807961],"type":"Point"}
}