{
  "type": "Feature",
  "properties": {
    "iso:country":"US",
    "sg:address":"111 Ashley Road 357",
    "sg:city":"Wilmot",
    "sg:phone":"+1 870 473 2837",
    "sg:postcode":"71676",
    "sg:province":"AR",
    "sg:tags":[
        "farm",
        "cotton"
    ],
    "wof:name":"Harvey Farms",
    "wof:placetype":"venue"
},
  "geometry": {"coordinates":[-91.623644,33.071814],"type":"Point"}
}