{
  "type": "Feature",
  "properties": {
    "iso:country":"US",
    "sg:address":"1405 Ingram St",
    "sg:city":"Springdale",
    "sg:classifiers":[
        {
            "category":"Freight",
            "type":"Transportation"
        }
    ],
    "sg:phone":"+1 479 751 0484",
    "sg:postcode":"72764",
    "sg:province":"AR",
    "sg:tags":[
        "broker",
        "trucking"
    ],
    "sg:website":"http://www.delp.net",
    "wof:name":"Delp, Inc.",
    "wof:placetype":"venue"
},
  "geometry": {"coordinates":[-94.141228,36.170131],"type":"Point"}
}