{
  "type": "Feature",
  "properties": {
    "iso:country":"US",
    "sg:address":"10244 Norwich Rd",
    "sg:city":"Lincoln",
    "sg:classifiers":[
        {
            "category":"Farming",
            "subcategory":"Farm",
            "type":"Manufacturing & Wholesale Goods"
        }
    ],
    "sg:phone":"+1 479 824 3521",
    "sg:postcode":"72744",
    "sg:province":"AR",
    "sg:tags":[
        "crop",
        "general"
    ],
    "wof:name":"Whorton Farms Inc",
    "wof:placetype":"venue"
},
  "geometry": {"coordinates":[-94.467592,35.992433],"type":"Point"}
}