{
  "type": "Feature",
  "properties": {
    "iso:country":"US",
    "sg:address":"167 Polk Road 41 N",
    "sg:city":"Mena",
    "sg:classifiers":[
        {
            "category":"Shopping",
            "type":"Retail Goods"
        }
    ],
    "sg:phone":"+1 479 394 3133",
    "sg:postcode":"71953",
    "sg:province":"OK",
    "sg:tags":[
        "merchandise"
    ],
    "wof:name":"Circle M Utilities",
    "wof:placetype":"venue"
},
  "geometry": {"coordinates":[-94.301073,34.600049],"type":"Point"}
}