{
  "type": "Feature",
  "properties": {
    "iso:country":"US",
    "sg:address":"1125 Morningside Dr",
    "sg:city":"Conway",
    "sg:classifiers":[
        {
            "category":"Shopping",
            "subcategory":"Department Store",
            "type":"Retail Goods"
        }
    ],
    "sg:phone":"+1 501 327 9746",
    "sg:postcode":"72034",
    "sg:province":"AR",
    "sg:tags":[
        "shop"
    ],
    "sg:website":"www.fredsinc.com",
    "wof:name":"Fred's Store",
    "wof:placetype":"venue"
},
  "geometry": {"coordinates":[-92.46611,35.093704],"type":"Point"}
}