{
  "type": "Feature",
  "properties": {
    "addr:full":"3023 Browns Ln Jonesboro AR 72401",
    "addr:housenumber":"3023",
    "addr:postcode":"72401",
    "addr:street":"Browns Ln",
    "iso:country":"US",
    "sg:address":"3023 Browns Ln",
    "sg:city":"Jonesboro",
    "sg:classifiers":[
        {
            "category":"Home & Garden",
            "subcategory":"Building Materials",
            "type":"Retail Goods"
        }
    ],
    "sg:phone":"+1 870 932 6675",
    "sg:postcode":"72401",
    "sg:province":"AR",
    "wof:name":"Barton's Do It Ctr",
    "wof:placetype":"venue"
},
  "geometry": {"coordinates":[-90.68723300000001,35.808237],"type":"Point"}
}