{
  "type": "Feature",
  "properties": {
    "iso:country":"US",
    "sg:address":"3914 W 12th St",
    "sg:city":"Little Rock",
    "sg:classifiers":[
        {
            "category":"Social Services",
            "subcategory":"Child Care",
            "type":"Services"
        }
    ],
    "sg:phone":"+1 501 603 2233",
    "sg:postcode":"72204",
    "sg:province":"AR",
    "sg:tags":[
        "day"
    ],
    "wof:name":"Nina's Babyland",
    "wof:placetype":"venue"
},
  "geometry": {"coordinates":[-92.317757,34.740575],"type":"Point"}
}