{
  "type": "Feature",
  "properties": {
    "addr:full":"303 W 3rd St Fordyce AR 71742",
    "addr:housenumber":"303",
    "addr:postcode":"71742",
    "addr:street":"W 3Rd St",
    "iso:country":"US",
    "sg:address":"303 W 3rd St",
    "sg:city":"Fordyce",
    "sg:classifiers":[
        {
            "category":"Professional",
            "subcategory":"Lawyer & Legal Services",
            "type":"Services"
        }
    ],
    "sg:phone":"+1 870 352 8846",
    "sg:postcode":"71742",
    "sg:province":"AR",
    "wof:name":"Casa Dallas Cleveland Calhoun",
    "wof:placetype":"venue"
},
  "geometry": {"coordinates":[-92.414456,33.811742],"type":"Point"}
}