{
  "type": "Feature",
  "properties": {
    "addr:full":"620 E Wood St Ashdown AR 71822",
    "addr:housenumber":"620",
    "addr:postcode":"71822",
    "addr:street":"E Wood St",
    "iso:country":"US",
    "sg:address":"620 E Wood St",
    "sg:city":"Ashdown",
    "sg:classifiers":[
        {
            "category":"Retail",
            "subcategory":"Auto Repair",
            "type":"Services"
        }
    ],
    "sg:phone":"+1 870 898 2312",
    "sg:postcode":"71822",
    "sg:province":"AR",
    "wof:name":"Jones' Brothers Garage",
    "wof:placetype":"venue"
},
  "geometry": {"coordinates":[-94.124399,33.667317],"type":"Point"}
}