{
  "type": "Feature",
  "properties": {
    "iso:country":"US",
    "sg:address":"6912 Sheridan Rd",
    "sg:city":"White Hall",
    "sg:classifiers":[
        {
            "category":"Personal",
            "type":"Services"
        }
    ],
    "sg:phone":"+1 870 247 0928",
    "sg:postcode":"71602",
    "sg:province":"AR",
    "wof:name":"Roys Tanning Salon",
    "wof:placetype":"venue"
},
  "geometry": {"coordinates":[-92.08796,34.254585],"type":"Point"}
}