{
  "type": "Feature",
  "properties": {
    "iso:country":"US",
    "sg:address":"2200 S Waldron Rd",
    "sg:city":"Fort Smith",
    "sg:classifiers":[
        {
            "category":"Professional",
            "subcategory":"Accounting & Tax Preparation",
            "type":"Services"
        }
    ],
    "sg:phone":"+1 479 452 4747",
    "sg:postcode":"72903",
    "sg:province":"AR",
    "wof:name":"Eb Lowe Jr",
    "wof:placetype":"venue"
},
  "geometry": {"coordinates":[-94.372919,35.361126],"type":"Point"}
}