{
  "type": "Feature",
  "properties": {
    "iso:country":"US",
    "sg:address":"21 Newcastle Dr",
    "sg:city":"Cabot",
    "sg:classifiers":[
        {
            "category":"Transit Center",
            "subcategory":"Freight",
            "type":"Transportation"
        },
        {
            "category":"Freight",
            "type":"Transportation"
        }
    ],
    "sg:phone":"+1 501 454 3268",
    "sg:postcode":"72023",
    "sg:province":"AR",
    "sg:tags":[
        "local",
        "trucking-motor",
        "trucking"
    ],
    "wof:name":"Bonnie Hatcher",
    "wof:placetype":"venue"
},
  "geometry": {"coordinates":[-92.033142,34.956846],"type":"Point"}
}