{
  "type": "Feature",
  "properties": {
    "iso:country":"US",
    "sg:address":"504 S 8th St",
    "sg:city":"Des Arc",
    "sg:classifiers":[
        {
            "category":"Freight",
            "type":"Transportation"
        }
    ],
    "sg:phone":"+1 870 256 4087",
    "sg:postcode":"72040",
    "sg:province":"AR",
    "sg:tags":[
        "operator",
        "local",
        "trucking"
    ],
    "wof:name":"Felty Trucking",
    "wof:placetype":"venue"
},
  "geometry": {"coordinates":[-91.501332,34.973021],"type":"Point"}
}