{
  "type": "Feature",
  "properties": {
    "iso:country":"US",
    "sg:address":"1800 Stirman Ave",
    "sg:city":"Fayetteville",
    "sg:classifiers":[
        {
            "category":"Building & Trades",
            "subcategory":"Plumbing",
            "type":"Services"
        }
    ],
    "sg:phone":"+1 479 443 9331",
    "sg:postcode":"72701",
    "sg:province":"AR",
    "sg:tags":[
        "conditioning",
        "air",
        "system",
        "contractor"
    ],
    "wof:name":"Commercial Svc Inc",
    "wof:placetype":"venue"
},
  "geometry": {"coordinates":[-94.175006,36.045809],"type":"Point"}
}