{
  "type": "Feature",
  "properties": {
    "iso:country":"US",
    "sg:address":"131 W Industrial Park Rd",
    "sg:city":"Harrison",
    "sg:classifiers":[
        {
            "category":"Social Services",
            "type":"Services"
        }
    ],
    "sg:phone":"+1 870 741 7677",
    "sg:postcode":"72601",
    "sg:province":"AR",
    "sg:tags":[
        "consultant",
        "security",
        "representative"
    ],
    "sg:website":"https://secure.ssa.gov/apps6z/FOLO/fo001.jsp",
    "wof:name":"Social Security Administration",
    "wof:placetype":"venue"
},
  "geometry": {"coordinates":[-93.121135,36.250531],"type":"Point"}
}