{
  "type": "Feature",
  "properties": {
    "iso:country":"US",
    "sg:address":"189 Little River 11",
    "sg:city":"Ashdown",
    "sg:classifiers":[
        {
            "category":"Manufacturing",
            "subcategory":"Lumber",
            "type":"Manufacturing & Wholesale Goods"
        }
    ],
    "sg:phone":"+1 870 542 6743",
    "sg:postcode":"71822",
    "sg:province":"AR",
    "sg:tags":[
        "fire",
        "fighting"
    ],
    "wof:name":"Arden Vlntr Fire Deptartment",
    "wof:placetype":"venue"
},
  "geometry": {"coordinates":[-94.287,33.666828],"type":"Point"}
}