{
  "type": "Feature",
  "properties": {
    "iso:country":"US",
    "sg:address":"9029 W State Hwy 22",
    "sg:city":"Ratcliff",
    "sg:classifiers":[
        {
            "category":"Shopping",
            "subcategory":"Computers & Home Electronics",
            "type":"Retail Goods"
        }
    ],
    "sg:phone":"+1 479 635 2197",
    "sg:postcode":"72951",
    "sg:province":"AR",
    "sg:tags":[
        "equipment",
        "dealer"
    ],
    "wof:name":"Castle Computers",
    "wof:placetype":"venue"
},
  "geometry": {"coordinates":[-93.872294,35.302566],"type":"Point"}
}