{
  "type": "Feature",
  "properties": {
    "addr:full":"1012 E Maddox Rd Jacksonville AR 72076",
    "addr:housenumber":"1012",
    "addr:postcode":"72076",
    "addr:street":"E Maddox Rd",
    "iso:country":"US",
    "sg:address":"1012 E Maddox Rd",
    "sg:city":"Jacksonville",
    "sg:classifiers":[
        {
            "category":"Wholesale",
            "subcategory":"Farm Supplies",
            "type":"Manufacturing & Wholesale Goods"
        }
    ],
    "sg:phone":"+1 501 985 1649",
    "sg:postcode":"72076",
    "sg:province":"AR",
    "wof:name":"Tonyville Feed",
    "wof:placetype":"venue"
},
  "geometry": {"coordinates":[-92.09588100000001,34.911773],"type":"Point"}
}