{
  "type": "Feature",
  "properties": {
    "iso:country":"US",
    "sg:address":"706 S 6th St",
    "sg:city":"Rogers",
    "sg:classifiers":[
        {
            "category":"Building & Trades",
            "subcategory":"Construction",
            "type":"Services"
        }
    ],
    "sg:phone":"+1 479 631 7430",
    "sg:postcode":"72756",
    "sg:province":"AR",
    "sg:tags":[
        "hanging",
        "contractor"
    ],
    "wof:name":"Heitz Painting",
    "wof:placetype":"venue"
},
  "geometry": {"coordinates":[-94.123123,36.327126],"type":"Point"}
}