{
  "type": "Feature",
  "properties": {
    "iso:country":"US",
    "sg:address":"323 Polk St S",
    "sg:city":"Mena",
    "sg:classifiers":[
        {
            "category":"Building & Trades",
            "subcategory":"Construction",
            "type":"Services"
        }
    ],
    "sg:phone":"+1 479 394 1239",
    "sg:postcode":"71953",
    "sg:province":"AR",
    "sg:tags":[
        "heavy"
    ],
    "wof:name":"Mena Waste Water Treatment",
    "wof:placetype":"venue"
},
  "geometry": {"coordinates":[-94.251518,34.585499],"type":"Point"}
}