{
  "type": "Feature",
  "properties": {
    "iso:country":"US",
    "sg:address":"220 W 5th St",
    "sg:city":"Hope",
    "sg:classifiers":[
        {
            "category":"Manufacturing",
            "subcategory":"Chemicals & Compounds",
            "type":"Manufacturing & Wholesale Goods"
        }
    ],
    "sg:phone":"+1 870 777 3251",
    "sg:postcode":"71801",
    "sg:province":"AR",
    "sg:tags":[
        "plastic"
    ],
    "wof:name":"Tolber Corp",
    "wof:placetype":"venue"
},
  "geometry": {"coordinates":[-93.592412,33.664821],"type":"Point"}
}