{
  "type": "Feature",
  "properties": {
    "iso:country":"US",
    "sg:address":"2113 S 54th St",
    "sg:city":"Rogers",
    "sg:classifiers":[
        {
            "category":"Manufacturing",
            "subcategory":"Pet Food",
            "type":"Manufacturing & Wholesale Goods"
        }
    ],
    "sg:phone":"+1 479 271 9983",
    "sg:postcode":"72758",
    "sg:province":"AR",
    "sg:tags":[
        "mfg"
    ],
    "wof:name":"Star-Kist",
    "wof:placetype":"venue"
},
  "geometry": {"coordinates":[-94.193893,36.315466],"type":"Point"}
}