{
  "type": "Feature",
  "properties": {
    "iso:country":"US",
    "sg:address":"245 N Main St",
    "sg:city":"Waldron",
    "sg:classifiers":[
        {
            "category":"Shopping",
            "subcategory":"Florist",
            "type":"Retail Goods"
        }
    ],
    "sg:phone":"+1 479 637 4838",
    "sg:postcode":"72958",
    "sg:province":"AR",
    "wof:name":"Moss Bank",
    "wof:placetype":"venue"
},
  "geometry": {"coordinates":[-94.0912,34.902413],"type":"Point"}
}