{
  "type": "Feature",
  "properties": {
    "iso:country":"US",
    "sg:address":"2727 S Caraway Rd",
    "sg:city":"Jonesboro",
    "sg:classifiers":[
        {
            "category":"Autos & Motor Vehicles",
            "subcategory":"Auto Supplies",
            "type":"Retail Goods"
        }
    ],
    "sg:phone":"+1 870 972 1854",
    "sg:postcode":"72404",
    "sg:province":"AR",
    "sg:tags":[
        "automobile",
        "stereo",
        "radio"
    ],
    "wof:name":"Car Audio Plus",
    "wof:placetype":"venue"
},
  "geometry": {"coordinates":[-90.678144,35.811783],"type":"Point"}
}