{
  "type": "Feature",
  "properties": {
    "iso:country":"US",
    "sg:address":"10101 Mabelvale Plaza Dr",
    "sg:city":"Little Rock",
    "sg:classifiers":[
        {
            "category":"Shopping",
            "subcategory":"Shoes",
            "type":"Retail Goods"
        }
    ],
    "sg:phone":"+1 501 562 3974",
    "sg:postcode":"72209",
    "sg:province":"AR",
    "wof:name":"Payless Shoe Source",
    "wof:placetype":"venue"
},
  "geometry": {"coordinates":[-92.37846,34.677584],"type":"Point"}
}