{
  "type": "Feature",
  "properties": {
    "addr:full":"3802 Grand Ave Fort Smith AR 72904",
    "addr:housenumber":"3802",
    "addr:postcode":"72904",
    "addr:street":"Grand Ave",
    "iso:country":"US",
    "sg:address":"3802 Grand Ave",
    "sg:city":"Fort Smith",
    "sg:classifiers":[
        {
            "category":"Government",
            "subcategory":"Office",
            "type":"Public Place"
        }
    ],
    "sg:phone":"+1 479 785 4696",
    "sg:postcode":"72904",
    "sg:province":"AR",
    "sg:tags":[
        "federal",
        "security"
    ],
    "wof:name":"US Coast Guard Auxiliary",
    "wof:placetype":"venue"
},
  "geometry": {"coordinates":[-94.389377,35.385628],"type":"Point"}
}