{
  "type": "Feature",
  "properties": {
    "iso:country":"US",
    "sg:address":"121 M L King Jr Dr",
    "sg:city":"Ashdown",
    "sg:classifiers":[
        {
            "category":"Freight",
            "type":"Transportation"
        }
    ],
    "sg:phone":"+1 870 898 3901",
    "sg:postcode":"71822",
    "sg:province":"AR",
    "sg:tags":[
        "mover"
    ],
    "wof:name":"C B Moving Svc",
    "wof:placetype":"venue"
},
  "geometry": {"coordinates":[-94.131835,33.671293],"type":"Point"}
}