{
  "type": "Feature",
  "properties": {
    "iso:country":"US",
    "sg:address":"15182 Brown Rd",
    "sg:city":"Prairie Grove",
    "sg:classifiers":[
        {
            "category":"Arts & Performance",
            "subcategory":"Theater",
            "type":"Entertainment"
        }
    ],
    "sg:phone":"+1 479 521 4341",
    "sg:postcode":"72753",
    "sg:province":"AR",
    "sg:tags":[
        "group"
    ],
    "wof:name":"Sound Explosion",
    "wof:placetype":"venue"
},
  "geometry": {"coordinates":[-94.33320000000001,35.889389],"type":"Point"}
}