{
  "type": "Feature",
  "properties": {
    "iso:country":"US",
    "sg:address":"91 N Razorback Rd",
    "sg:city":"Fayetteville",
    "sg:classifiers":[
        {
            "category":"Organizations",
            "subcategory":"Non-profit Organization",
            "type":"Services"
        }
    ],
    "sg:phone":"+1 479 443 1518",
    "sg:postcode":"72701",
    "sg:province":"AR",
    "sg:tags":[
        "fund",
        "counselor",
        "raising"
    ],
    "wof:name":"Razorback Foundation",
    "wof:placetype":"venue"
},
  "geometry": {"coordinates":[-94.180277,36.064247],"type":"Point"}
}