{
  "type": "Feature",
  "properties": {
    "iso:country":"US",
    "sg:address":"165 Chambers Pt",
    "sg:city":"Hot Springs National Park",
    "sg:classifiers":[
        {
            "category":"Professional",
            "subcategory":"Management & Consulting",
            "type":"Services"
        }
    ],
    "sg:phone":"+1 501 520 5702",
    "sg:postcode":"71913",
    "sg:province":"AR",
    "sg:tags":[
        "battle",
        "system",
        "air"
    ],
    "wof:name":"Marc W Barber Consulting",
    "wof:placetype":"venue"
},
  "geometry": {"coordinates":[-93.057095,34.447054],"type":"Point"}
}