{
  "type": "Feature",
  "properties": {
    "addr:full":"105 Flint St Jonesboro AR 72401",
    "addr:housenumber":"105",
    "addr:postcode":"72401",
    "addr:street":"Flint St",
    "iso:country":"US",
    "sg:address":"105 Flint St",
    "sg:city":"Jonesboro",
    "sg:classifiers":[
        {
            "category":"Wholesale",
            "subcategory":"Scrap",
            "type":"Manufacturing & Wholesale Goods"
        }
    ],
    "sg:phone":"+1 870 932 8361",
    "sg:postcode":"72401",
    "sg:province":"AR",
    "sg:tags":[
        "metal",
        "iron"
    ],
    "sg:website":"www.him.com",
    "wof:name":"Hummelstein Iron & Metal Inc",
    "wof:placetype":"venue"
},
  "geometry": {"coordinates":[-90.71050099999999,35.842399],"type":"Point"}
}