{
  "type": "Feature",
  "properties": {
    "addr:full":"12111 W Markham St Little Rock AR 72211",
    "addr:housenumber":"12111",
    "addr:postcode":"72211",
    "addr:street":"W Markham St",
    "iso:country":"US",
    "sg:address":"12111 W Markham St",
    "sg:city":"Little Rock",
    "sg:classifiers":[
        {
            "category":"Shopping",
            "subcategory":"Computers & Home Electronics",
            "type":"Retail Goods"
        }
    ],
    "sg:phone":"+1 601 856 0008",
    "sg:postcode":"72211",
    "sg:province":"AR",
    "sg:tags":[
        "consumer"
    ],
    "wof:name":"Digital Systems Inc",
    "wof:placetype":"venue"
},
  "geometry": {"coordinates":[-92.41304599999999,34.754047],"type":"Point"}
}