{
  "type": "Feature",
  "properties": {
    "iso:country":"US",
    "sg:address":"142 3rd",
    "sg:city":"Manila",
    "sg:classifiers":[
        {
            "category":"Organizations",
            "subcategory":"Religious Organization",
            "type":"Services"
        }
    ],
    "sg:phone":"+1 870 561 3141",
    "sg:postcode":"72442",
    "sg:province":"AR",
    "sg:tags":[
        "church"
    ],
    "wof:name":"Calvary Baptist Church",
    "wof:placetype":"venue"
},
  "geometry": {"coordinates":[-90.16485,35.873725],"type":"Point"}
}