{
  "type": "Feature",
  "properties": {
    "iso:country":"US",
    "sg:address":"201 N Front St",
    "sg:city":"Donaldson",
    "sg:classifiers":[
        {
            "category":"Home & Garden",
            "subcategory":"Hardware",
            "type":"Retail Goods"
        }
    ],
    "sg:phone":"+1 501 384 2219",
    "sg:postcode":"71941",
    "sg:province":"AR",
    "wof:name":"Henry's Mercantile Co",
    "wof:placetype":"venue"
},
  "geometry": {"coordinates":[-92.92214,34.23861],"type":"Point"}
}