{
  "type": "Feature",
  "properties": {
    "addr:full":"123 Big Pine Rd Batesville AR 72501",
    "addr:housenumber":"123",
    "addr:postcode":"72501",
    "addr:street":"Big Pine Rd",
    "iso:country":"US",
    "sg:address":"123 Big Pine Rd",
    "sg:city":"Batesville",
    "sg:classifiers":[
        {
            "category":"Professional",
            "subcategory":"Accounting & Tax Preparation",
            "type":"Services"
        }
    ],
    "sg:phone":"+1 870 793 5683",
    "sg:postcode":"72501",
    "sg:province":"AR",
    "sg:tags":[
        "accountant"
    ],
    "wof:name":"Robert A Brown CPA",
    "wof:placetype":"venue"
},
  "geometry": {"coordinates":[-91.597173,35.771312],"type":"Point"}
}