{
  "type": "Feature",
  "properties": {
    "iso:country":"US",
    "sg:address":"5405 Alma Hwy",
    "sg:city":"Van Buren",
    "sg:classifiers":[
        {
            "category":"Shopping",
            "subcategory":"Florist",
            "type":"Retail Goods"
        }
    ],
    "sg:phone":"+1 479 474 0080",
    "sg:postcode":"72956",
    "sg:province":"AR",
    "wof:name":"Forget Me Not Floral",
    "wof:placetype":"venue"
},
  "geometry": {"coordinates":[-94.286405,35.459624],"type":"Point"}
}