{
  "type": "Feature",
  "properties": {
    "addr:full":"3401 Park Ave Fort Smith AR 72903",
    "addr:housenumber":"3401",
    "addr:postcode":"72903",
    "addr:street":"Park Ave",
    "iso:country":"US",
    "sg:address":"3401 Park Ave",
    "sg:city":"Fort Smith",
    "sg:classifiers":[
        {
            "category":"Real Estate",
            "subcategory":"Real Estate Operator",
            "type":"Services"
        }
    ],
    "sg:phone":"+1 479 785 2235",
    "sg:postcode":"72903",
    "sg:province":"AR",
    "sg:tags":[
        "building",
        "apartment"
    ],
    "wof:name":"Park Terrace Apartments",
    "wof:placetype":"venue"
},
  "geometry": {"coordinates":[-94.396913,35.378595],"type":"Point"}
}