{
  "type": "Feature",
  "properties": {
    "iso:country":"US",
    "sg:address":"216 E Broadway",
    "sg:city":"Glenwood",
    "sg:classifiers":[
        {
            "category":"Personal",
            "subcategory":"Barber",
            "type":"Services"
        }
    ],
    "sg:phone":"+1 870 356 3029",
    "sg:postcode":"71943",
    "sg:province":"AR",
    "wof:name":"O K Barber Shop",
    "wof:placetype":"venue"
},
  "geometry": {"coordinates":[-93.550108,34.326935],"type":"Point"}
}