{
  "type": "Feature",
  "properties": {
    "addr:full":"3017 Grand Ave Fort Smith AR 72901",
    "addr:housenumber":"3017",
    "addr:postcode":"72901",
    "addr:street":"Grand Ave",
    "iso:country":"US",
    "sg:address":"3017 Grand Ave",
    "sg:city":"Fort Smith",
    "sg:classifiers":[
        {
            "category":"Retail",
            "subcategory":"Car Wash",
            "type":"Services"
        }
    ],
    "sg:phone":"+1 479 785 1219",
    "sg:postcode":"72901",
    "sg:province":"AR",
    "sg:tags":[
        "carwash"
    ],
    "wof:name":"Enelson Castro",
    "wof:placetype":"venue"
},
  "geometry": {"coordinates":[-94.39886,35.386002],"type":"Point"}
}