{
  "type": "Feature",
  "properties": {
    "iso:country":"US",
    "sg:address":"1402 Eastline Rd",
    "sg:city":"Searcy",
    "sg:classifiers":[
        {
            "category":"Insurance",
            "subcategory":"Insurance Agent",
            "type":"Services"
        },
        {
            "category":"Insurance",
            "subcategory":"Hazard Insurance",
            "type":"Services"
        },
        {
            "category":"Insurance",
            "subcategory":"Health Insurance",
            "type":"Services"
        },
        {
            "category":"Insurance",
            "subcategory":"Life Insurance",
            "type":"Services"
        }
    ],
    "sg:phone":"+1 501 268 2800",
    "sg:postcode":"72143",
    "sg:province":"AR",
    "sg:tags":[
        "plans-information",
        "auto",
        "referral",
        "commercial",
        "business"
    ],
    "sg:website":"http://progressive.com",
    "wof:name":"Billie Ghent Insurance Agency",
    "wof:placetype":"venue"
},
  "geometry": {"coordinates":[-91.696263,35.23489],"type":"Point"}
}