{
  "type": "Feature",
  "properties": {
    "iso:country":"US",
    "sg:address":"1802 Hwy 201 N",
    "sg:city":"Mountain Home",
    "sg:classifiers":[
        {
            "category":"Building & Trades",
            "subcategory":"Plumbing",
            "type":"Services"
        }
    ],
    "sg:phone":"+1 870 425 4717",
    "sg:postcode":"72653",
    "sg:province":"AR",
    "sg:tags":[
        "conditioning",
        "air",
        "system",
        "contractor"
    ],
    "wof:name":"Central Heating & Cooling Inc",
    "wof:placetype":"venue"
},
  "geometry": {"coordinates":[-92.38600700000001,36.35955],"type":"Point"}
}