{
  "type": "Feature",
  "properties": {
    "iso:country":"US",
    "sg:address":"600 N Thompson St",
    "sg:city":"Springdale",
    "sg:classifiers":[
        {
            "category":"Autos & Motor Vehicles",
            "subcategory":"Automobile Sales",
            "type":"Retail Goods"
        }
    ],
    "sg:phone":"+1 479 756 0097",
    "sg:postcode":"72764",
    "sg:province":"AR",
    "sg:tags":[
        "car",
        "used",
        "dealer"
    ],
    "wof:name":"Jones Motors Inc",
    "wof:placetype":"venue"
},
  "geometry": {"coordinates":[-94.138352,36.189741],"type":"Point"}
}