{
  "type": "Feature",
  "properties": {
    "addr:full":"616 N 14th St Fort Smith AR 72901",
    "addr:housenumber":"616",
    "addr:postcode":"72901",
    "addr:street":"N 14Th St",
    "iso:country":"US",
    "sg:address":"616 N 14th St",
    "sg:city":"Fort Smith",
    "sg:classifiers":[
        {
            "category":"Education",
            "subcategory":"School",
            "type":"Public Place"
        }
    ],
    "sg:phone":"+1 479 783 4159",
    "sg:postcode":"72901",
    "sg:province":"AR",
    "sg:tags":[
        "high",
        "junior"
    ],
    "wof:name":"Darby Junior High School",
    "wof:placetype":"venue"
},
  "geometry": {"coordinates":[-94.412747,35.387526],"type":"Point"}
}