{
  "type": "Feature",
  "properties": {
    "iso:country":"US",
    "sg:address":"425 E Pecan St",
    "sg:city":"El Dorado",
    "sg:classifiers":[
        {
            "category":"Social Services",
            "subcategory":"Child Care",
            "type":"Services"
        }
    ],
    "sg:phone":"+1 870 863 8128",
    "sg:postcode":"71730",
    "sg:province":"AR",
    "wof:name":"Good Shepard Child Care Ctr",
    "wof:placetype":"venue"
},
  "geometry": {"coordinates":[-92.660051,33.197933],"type":"Point"}
}