{
  "type": "Feature",
  "properties": {
    "iso:country":"US",
    "sg:address":"3343 Spring St",
    "sg:city":"Hot Springs",
    "sg:classifiers":[
        {
            "category":"Building & Trades",
            "subcategory":"Plumbing",
            "type":"Services"
        }
    ],
    "sg:phone":"+1 501 262 1336",
    "sg:postcode":"71901",
    "sg:province":"AR",
    "sg:tags":[
        "heating",
        "contractor"
    ],
    "wof:name":"Danny Hamilton Heat & Air",
    "wof:placetype":"venue"
},
  "geometry": {"coordinates":[-92.965181,34.499399],"type":"Point"}
}