{
  "type": "Feature",
  "properties": {
    "iso:country":"US",
    "sg:address":"710 N Main St",
    "sg:city":"Hamburg",
    "sg:classifiers":[
        {
            "category":"Personal",
            "subcategory":"Beauty Salon",
            "type":"Services"
        },
        {
            "category":"Personal",
            "subcategory":"Tanning Parlor",
            "type":"Services"
        }
    ],
    "sg:phone":"+1 870 853 9020",
    "sg:postcode":"71646",
    "sg:province":"AR",
    "wof:name":"Main Hair & Nail Salon",
    "wof:placetype":"venue"
},
  "geometry": {"coordinates":[-91.797437,33.230633],"type":"Point"}
}