{
  "type": "Feature",
  "properties": {
    "iso:country":"US",
    "sg:address":"2210 S School Ave",
    "sg:city":"Fayetteville",
    "sg:classifiers":[
        {
            "category":"Building & Trades",
            "subcategory":"Plumbing",
            "type":"Services"
        }
    ],
    "sg:phone":"+1 479 442 0800",
    "sg:postcode":"72701",
    "sg:province":"AR",
    "sg:tags":[
        "contractor"
    ],
    "wof:name":"Arkansas Automatic Sprinklers",
    "wof:placetype":"venue"
},
  "geometry": {"coordinates":[-94.16613,36.040351],"type":"Point"}
}