{
  "type": "Feature",
  "properties": {
    "iso:country":"US",
    "sg:address":"4411 Asher Ave",
    "sg:city":"Little Rock",
    "sg:classifiers":[
        {
            "category":"Building & Trades",
            "subcategory":"Pest Control",
            "type":"Services"
        }
    ],
    "sg:phone":"+1 501 666 0392",
    "sg:postcode":"72204",
    "sg:province":"AR",
    "wof:name":"Anchor Termite & Pest Control",
    "wof:placetype":"venue"
},
  "geometry": {"coordinates":[-92.322702,34.724014],"type":"Point"}
}