{
  "type": "Feature",
  "properties": {
    "iso:country":"US",
    "sg:address":"10983 Hwy 223 S",
    "sg:city":"Bexar",
    "sg:classifiers":[
        {
            "category":"Manufacturing",
            "subcategory":"Lumber",
            "type":"Manufacturing & Wholesale Goods"
        }
    ],
    "sg:phone":"+1 870 458 2359",
    "sg:postcode":"72515",
    "sg:province":"AR",
    "sg:tags":[
        "logging"
    ],
    "wof:name":"Chris Stepp Logging",
    "wof:placetype":"venue"
},
  "geometry": {"coordinates":[-92.028966,36.27642],"type":"Point"}
}