{
  "type": "Feature",
  "properties": {
    "addr:full":"411 W Main St Russellville AR 72801",
    "addr:housenumber":"411",
    "addr:postcode":"72801",
    "addr:street":"W Main St",
    "iso:country":"US",
    "sg:address":"411 W Main St",
    "sg:city":"Russellville",
    "sg:classifiers":[
        {
            "category":"Autos & Motor Vehicles",
            "subcategory":"Auto Supplies",
            "type":"Retail Goods"
        }
    ],
    "sg:phone":"+1 479 705 0155",
    "sg:postcode":"72801",
    "sg:province":"AR",
    "sg:tags":[
        "automobile",
        "parts"
    ],
    "wof:name":"Autozone",
    "wof:placetype":"venue"
},
  "geometry": {"coordinates":[-93.13722199999999,35.278956],"type":"Point"}
}