{
  "type": "Feature",
  "properties": {
    "addr:full":"1792 E Joyce Blvd Ste 3 Fayetteville AR 72703",
    "addr:housenumber":"1792",
    "addr:postcode":"72703",
    "addr:street":"E Joyce Blvd Ste 3",
    "iso:country":"US",
    "sg:address":"1792 E Joyce Blvd Ste 3",
    "sg:city":"Fayetteville",
    "sg:classifiers":[
        {
            "category":"Health Services",
            "subcategory":"Doctor",
            "type":"Services"
        }
    ],
    "sg:phone":"+1 479 582 5905",
    "sg:postcode":"72703",
    "sg:province":"AR",
    "sg:tags":[
        "physician",
        "surgeon"
    ],
    "wof:name":"Integrated Health Associates",
    "wof:placetype":"venue"
},
  "geometry": {"coordinates":[-94.134862,36.120099],"type":"Point"}
}