{
  "type": "Feature",
  "properties": {
    "iso:country":"US",
    "sg:address":"1160 N College Ave",
    "sg:city":"Fayetteville",
    "sg:classifiers":[
        {
            "category":"Professional",
            "subcategory":"Employment Agencies",
            "type":"Services"
        }
    ],
    "sg:phone":"+1 479 973 6509",
    "sg:postcode":"72703",
    "sg:province":"AR",
    "sg:tags":[
        "opportunity"
    ],
    "sg:website":"www.rsstaffing.com",
    "wof:name":"R S Staffing Svc Inc",
    "wof:placetype":"venue"
},
  "geometry": {"coordinates":[-94.156983,36.07868],"type":"Point"}
}