{
  "type": "Feature",
  "properties": {
    "addr:full":"1330 S Donaghey Ave Conway AR 72034",
    "addr:housenumber":"1330",
    "addr:postcode":"72034",
    "addr:street":"S Donaghey Ave",
    "iso:country":"US",
    "sg:address":"1330 S Donaghey Ave",
    "sg:city":"Conway",
    "sg:classifiers":[
        {
            "category":"Education",
            "subcategory":"School",
            "type":"Public Place"
        }
    ],
    "sg:phone":"+1 501 328 0200",
    "sg:postcode":"72034",
    "sg:province":"AR",
    "wof:name":"Kid's World Multicultural Lrng",
    "wof:placetype":"venue"
},
  "geometry": {"coordinates":[-92.454791,35.062913],"type":"Point"}
}