{
  "type": "Feature",
  "properties": {
    "addr:full":"1114 W 19th Ter Russellville AR 72801",
    "addr:housenumber":"1114",
    "addr:postcode":"72801",
    "addr:street":"W 19Th Ter",
    "iso:country":"US",
    "sg:address":"1114 W 19th Ter",
    "sg:city":"Russellville",
    "sg:classifiers":[
        {
            "category":"Professional",
            "type":"Services"
        }
    ],
    "sg:phone":"+1 479 967 4213",
    "sg:postcode":"72801",
    "sg:province":"AR",
    "wof:name":"Kenneth Rogers",
    "wof:placetype":"venue"
},
  "geometry": {"coordinates":[-93.145404,35.262198],"type":"Point"}
}