{
  "type": "Feature",
  "properties": {
    "iso:country":"US",
    "sg:address":"5000 Young Rd",
    "sg:city":"Little Rock",
    "sg:classifiers":[
        {
            "category":"Organizations",
            "subcategory":"Religious Organization",
            "type":"Services"
        }
    ],
    "sg:phone":"+1 501 568 1104",
    "sg:postcode":"72209",
    "sg:province":"AR",
    "wof:name":"Graceland Kids",
    "wof:placetype":"venue"
},
  "geometry": {"coordinates":[-92.334741,34.679506],"type":"Point"}
}