{
  "type": "Feature",
  "properties": {
    "iso:country":"US",
    "sg:address":"318 W Bond Ave",
    "sg:city":"West Memphis",
    "sg:classifiers":[
        {
            "category":"Social Services",
            "type":"Services"
        }
    ],
    "sg:phone":"+1 870 735 2123",
    "sg:postcode":"72301",
    "sg:province":"AR",
    "sg:tags":[
        "organization",
        "welfare"
    ],
    "wof:name":"Justice Network",
    "wof:placetype":"venue"
},
  "geometry": {"coordinates":[-90.19120599999999,35.147914],"type":"Point"}
}