{
  "type": "Feature",
  "properties": {
    "iso:country":"US",
    "sg:address":"4804 W 31st St",
    "sg:city":"Little Rock",
    "sg:classifiers":[
        {
            "category":"Shopping",
            "subcategory":"Gifts & Souvenirs",
            "type":"Retail Goods"
        }
    ],
    "sg:phone":"+1 501 664 7239",
    "sg:postcode":"72204",
    "sg:province":"AR",
    "wof:name":"Paulas Stuff",
    "wof:placetype":"venue"
},
  "geometry": {"coordinates":[-92.329763,34.723871],"type":"Point"}
}