{
  "type": "Feature",
  "properties": {
    "iso:country":"US",
    "sg:address":"15827 Serenity Point Ln",
    "sg:city":"Rogers",
    "sg:classifiers":[
        {
            "category":"Personal",
            "type":"Services"
        },
        {
            "category":"Autos & Motor Vehicles",
            "subcategory":"Auto Supplies",
            "type":"Retail Goods"
        }
    ],
    "sg:phone":"+1 479 925 2131",
    "sg:postcode":"72756",
    "sg:province":"AR",
    "sg:tags":[
        "automobile",
        "part",
        "towing"
    ],
    "sg:website":"http://www.towmate.com",
    "wof:name":"Towmate",
    "wof:placetype":"venue"
},
  "geometry": {"coordinates":[-94.032312,36.334446],"type":"Point"}
}