{
  "type": "Feature",
  "properties": {
    "addr:full":"1708 S 8th St Rogers AR 72756",
    "addr:housenumber":"1708",
    "addr:postcode":"72756",
    "addr:street":"S 8Th St",
    "iso:country":"US",
    "sg:address":"1708 S 8th St",
    "sg:city":"Rogers",
    "sg:classifiers":[
        {
            "category":"Wholesale",
            "subcategory":"Auto Parts",
            "type":"Manufacturing & Wholesale Goods"
        }
    ],
    "sg:phone":"+1 479 631 1844",
    "sg:postcode":"72756",
    "sg:province":"AR",
    "sg:tags":[
        "body",
        "shop",
        "automobile"
    ],
    "wof:name":"Wholesale Auto Paints & Body",
    "wof:placetype":"venue"
},
  "geometry": {"coordinates":[-94.12626299999999,36.317253],"type":"Point"}
}