{
  "type": "Feature",
  "properties": {
    "addr:full":"6301 S Hazel St Pine Bluff AR 71603",
    "addr:housenumber":"6301",
    "addr:postcode":"71603",
    "addr:street":"S Hazel St",
    "iso:country":"US",
    "sg:address":"6301 S Hazel St",
    "sg:city":"Pine Bluff",
    "sg:classifiers":[
        {
            "category":"Health Services",
            "subcategory":"Nursing And Care Facility",
            "type":"Services"
        },
        {
            "category":"Social Services",
            "subcategory":"Adult Care",
            "type":"Services"
        }
    ],
    "sg:phone":"+1 870 534 8153",
    "sg:postcode":"71603",
    "sg:province":"AR",
    "sg:tags":[
        "home",
        "residential"
    ],
    "wof:name":"Arkansas Convalescent Center",
    "wof:placetype":"venue"
},
  "geometry": {"coordinates":[-92.02402499999999,34.160382],"type":"Point"}
}