{
  "type": "Feature",
  "properties": {
    "iso:country":"US",
    "sg:address":"212 N Main St",
    "sg:city":"Dell",
    "sg:classifiers":[
        {
            "category":"Government",
            "subcategory":"Post Office",
            "type":"Public Place"
        }
    ],
    "sg:phone":"+1 870 564 2502",
    "sg:postcode":"72426",
    "sg:province":"AR",
    "sg:tags":[
        "postal",
        "us"
    ],
    "wof:name":"US Post Office",
    "wof:placetype":"venue"
},
  "geometry": {"coordinates":[-90.043571,35.856798],"type":"Point"}
}