{
  "type": "Feature",
  "properties": {
    "iso:country":"US",
    "sg:address":"184 Little River 33",
    "sg:city":"Ashdown",
    "sg:classifiers":[
        {
            "category":"Organizations",
            "subcategory":"Religious Organization",
            "type":"Services"
        }
    ],
    "sg:phone":"+1 870 898 3268",
    "sg:postcode":"71822",
    "sg:province":"AR",
    "wof:name":"Hopewell Missionary Bapti",
    "wof:placetype":"venue"
},
  "geometry": {"coordinates":[-93.983668,33.664194],"type":"Point"}
}