{
  "type": "Feature",
  "properties": {
    "iso:country":"US",
    "sg:address":"810 Holiman St",
    "sg:city":"Springdale",
    "sg:classifiers":[
        {
            "category":"Freight",
            "type":"Transportation"
        }
    ],
    "sg:phone":"+1 479 756 0938",
    "sg:postcode":"72762",
    "sg:province":"AR",
    "sg:tags":[
        "special"
    ],
    "wof:name":"B & B Self Mini Storage",
    "wof:placetype":"venue"
},
  "geometry": {"coordinates":[-94.158566,36.176275],"type":"Point"}
}