{
  "type": "Feature",
  "properties": {
    "iso:country":"US",
    "sg:address":"3813 S Division St",
    "sg:city":"Blytheville",
    "sg:classifiers":[
        {
            "category":"Freight",
            "type":"Transportation"
        }
    ],
    "sg:phone":"+1 870 763 8778",
    "sg:postcode":"72315",
    "sg:province":"AR",
    "sg:tags":[
        "terminal",
        "facility",
        "truck",
        "hauling",
        "trucking"
    ],
    "wof:name":"Truckers Express Inc",
    "wof:placetype":"venue"
},
  "geometry": {"coordinates":[-89.918678,35.888276],"type":"Point"}
}