{
  "type": "Feature",
  "properties": {
    "addr:full":"3714 State Hwy 316 Lexa AR 72355",
    "addr:housenumber":"3714",
    "addr:postcode":"72355",
    "addr:street":"State Hwy 316",
    "iso:country":"US",
    "sg:address":"3714 State Hwy 316",
    "sg:city":"Lexa",
    "sg:phone":"+1 870 572 9199",
    "sg:postcode":"72355",
    "sg:province":"AR",
    "sg:tags":[
        "farm",
        "soybean"
    ],
    "wof:name":"North Creek Gin Company Inc",
    "wof:placetype":"venue"
},
  "geometry": {"coordinates":[-90.82100699999999,34.605872],"type":"Point"}
}