{
  "type": "Feature",
  "properties": {
    "iso:country":"US",
    "sg:address":"203 E 1st Ave",
    "sg:city":"Crossett",
    "sg:classifiers":[
        {
            "category":"Banks & Credit Unions",
            "subcategory":"Bank",
            "type":"Services"
        }
    ],
    "sg:phone":"+1 870 364 4477",
    "sg:postcode":"71635",
    "sg:province":"AR",
    "sg:tags":[
        "plan",
        "business",
        "institution"
    ],
    "wof:name":"Community Bank Of Crossett",
    "wof:placetype":"venue"
},
  "geometry": {"coordinates":[-91.960138,33.135332],"type":"Point"}
}