{
  "type": "Feature",
  "properties": {
    "addr:full":"7101 Archwood Dr Little Rock AR 72204",
    "addr:housenumber":"7101",
    "addr:postcode":"72204",
    "addr:street":"Archwood Dr",
    "iso:country":"US",
    "sg:address":"7101 Archwood Dr",
    "sg:city":"Little Rock",
    "sg:classifiers":[
        {
            "category":"Education",
            "subcategory":"Special Training",
            "type":"Public Place"
        }
    ],
    "sg:phone":"+1 501 565 9456",
    "sg:postcode":"72204",
    "sg:province":"AR",
    "wof:name":"Mack Davis Scholarship Trust",
    "wof:placetype":"venue"
},
  "geometry": {"coordinates":[-92.353565,34.727284],"type":"Point"}
}