{
  "type": "Feature",
  "properties": {
    "iso:country":"US",
    "sg:address":"3111 McEntire Rd",
    "sg:city":"Pine Bluff",
    "sg:classifiers":[
        {
            "category":"Professional",
            "subcategory":"Business Services",
            "type":"Services"
        }
    ],
    "sg:phone":"+1 870 535 3714",
    "sg:postcode":"71601",
    "sg:province":"AR",
    "sg:tags":[
        "printing"
    ],
    "wof:name":"R & M Printing",
    "wof:placetype":"venue"
},
  "geometry": {"coordinates":[-91.901911,34.105889],"type":"Point"}
}