{
  "type": "Feature",
  "properties": {
    "iso:country":"US",
    "sg:address":"2335 N Rondo Rd",
    "sg:city":"Texarkana",
    "sg:classifiers":[
        {
            "category":"Organizations",
            "subcategory":"Religious Organization",
            "type":"Services"
        }
    ],
    "sg:phone":"+1 870 772 7142",
    "sg:postcode":"71854",
    "sg:province":"AR",
    "sg:tags":[
        "church"
    ],
    "wof:name":"Rondo United Methodist Church",
    "wof:placetype":"venue"
},
  "geometry": {"coordinates":[-93.97765,33.443661],"type":"Point"}
}