{
  "type": "Feature",
  "properties": {
    "iso:country":"US",
    "sg:address":"1300 S Mississippi St",
    "sg:city":"Crossett",
    "sg:classifiers":[
        {
            "category":"Education",
            "subcategory":"School",
            "type":"Public Place"
        }
    ],
    "sg:phone":"+1 870 364 3182",
    "sg:postcode":"71635",
    "sg:province":"AR",
    "wof:name":"Price Elementary School",
    "wof:placetype":"venue"
},
  "geometry": {"coordinates":[-91.972412,33.120373],"type":"Point"}
}