{
  "type": "Feature",
  "properties": {
    "addr:full":"106 Lake Shore Dr Russellville AR 72802",
    "addr:housenumber":"106",
    "addr:postcode":"72802",
    "addr:street":"Lake Shore Dr",
    "iso:country":"US",
    "sg:address":"106 Lake Shore Dr",
    "sg:city":"Russellville",
    "sg:classifiers":[
        {
            "category":"Insurance",
            "subcategory":"Insurance Agent",
            "type":"Services"
        }
    ],
    "sg:phone":"+1 479 968 9595",
    "sg:postcode":"72802",
    "sg:province":"AR",
    "wof:name":"New York Life Insurance Co",
    "wof:placetype":"venue"
},
  "geometry": {"coordinates":[-93.185787,35.304367],"type":"Point"}
}