{
  "type": "Feature",
  "properties": {
    "iso:country":"US",
    "sg:address":"883 Walnut Grove Ave",
    "sg:city":"Springdale",
    "sg:classifiers":[
        {
            "category":"Retail",
            "subcategory":"Auto Repair",
            "type":"Services"
        }
    ],
    "sg:phone":"+1 479 751 7100",
    "sg:postcode":"72764",
    "sg:province":"AR",
    "sg:tags":[
        "automotive"
    ],
    "wof:name":"Discount Towing",
    "wof:placetype":"venue"
},
  "geometry": {"coordinates":[-94.124274,36.152482],"type":"Point"}
}