{
  "type": "Feature",
  "properties": {
    "iso:country":"US",
    "sg:address":"522 Military Rd",
    "sg:city":"Jacksonville",
    "sg:classifiers":[
        {
            "category":"Professional",
            "subcategory":"Business Services",
            "type":"Services"
        }
    ],
    "sg:phone":"+1 501 776 0870",
    "sg:postcode":"72076",
    "sg:province":"AR",
    "sg:tags":[
        "interior",
        "consultant",
        "design",
        "decorator"
    ],
    "wof:name":"Hearts'n Flowers Inc",
    "wof:placetype":"venue"
},
  "geometry": {"coordinates":[-92.11167399999999,34.852354],"type":"Point"}
}