{
  "type": "Feature",
  "properties": {
    "addr:full":"1501 Malcolm Ave Newport AR 72112",
    "addr:housenumber":"1501",
    "addr:postcode":"72112",
    "addr:street":"Malcolm Ave",
    "iso:country":"US",
    "sg:address":"1501 Malcolm Ave",
    "sg:city":"Newport",
    "sg:classifiers":[
        {
            "category":"Autos & Motor Vehicles",
            "subcategory":"Auto Supplies",
            "type":"Retail Goods"
        }
    ],
    "sg:phone":"+1 870 523 6735",
    "sg:postcode":"72112",
    "sg:province":"AR",
    "sg:tags":[
        "tire"
    ],
    "wof:name":"Farmers Tire Mart Inc",
    "wof:placetype":"venue"
},
  "geometry": {"coordinates":[-91.26161999999999,35.60592],"type":"Point"}
}