{
  "type": "Feature",
  "properties": {
    "iso:country":"US",
    "sg:address":"4403 Central Ave",
    "sg:city":"Hot Springs",
    "sg:classifiers":[
        {
            "category":"Banks & Credit Unions",
            "subcategory":"Bank",
            "type":"Services"
        }
    ],
    "sg:phone":"+1 501 525 4685",
    "sg:postcode":"71913",
    "sg:province":"AR",
    "sg:tags":[
        "cashing",
        "check"
    ],
    "wof:name":"First American Cash Advance",
    "wof:placetype":"venue"
},
  "geometry": {"coordinates":[-93.07570200000001,34.451789],"type":"Point"}
}