{
  "type": "Feature",
  "properties": {
    "iso:country":"US",
    "sg:address":"13510 Avilla W",
    "sg:city":"Alexander",
    "sg:classifiers":[
        {
            "category":"Professional",
            "type":"Services"
        }
    ],
    "sg:phone":"+1 501 794 1402",
    "sg:postcode":"72002",
    "sg:province":"AR",
    "sg:tags":[
        "establishment"
    ],
    "wof:name":"Lake Norrell Fire Protctn Dist",
    "wof:placetype":"venue"
},
  "geometry": {"coordinates":[-92.609579,34.683401],"type":"Point"}
}