{
  "type": "Feature",
  "properties": {
    "iso:country":"US",
    "sg:address":"801 Carlton St",
    "sg:city":"Springdale",
    "sg:classifiers":[
        {
            "category":"Health Services",
            "subcategory":"Doctor",
            "type":"Services"
        }
    ],
    "sg:phone":"+1 479 750 1151",
    "sg:postcode":"72762",
    "sg:province":"AR",
    "sg:tags":[
        "psychologist"
    ],
    "wof:name":"Savanna Mccain Cloer",
    "wof:placetype":"venue"
},
  "geometry": {"coordinates":[-94.15284,36.17569],"type":"Point"}
}