{
  "type": "Feature",
  "properties": {
    "iso:country":"US",
    "sg:address":"4938 E Nettleton Ave",
    "sg:city":"Jonesboro",
    "sg:classifiers":[
        {
            "category":"Recreation",
            "type":"Entertainment"
        }
    ],
    "sg:phone":"+1 870 933 7290",
    "sg:postcode":"72401",
    "sg:province":"AR",
    "sg:tags":[
        "center"
    ],
    "wof:name":"Richard's This & That",
    "wof:placetype":"venue"
},
  "geometry": {"coordinates":[-90.64988099999999,35.818092],"type":"Point"}
}