{
  "type": "Feature",
  "properties": {
    "addr:full":"5749 Oak Ridge Rd Ravenden Springs AR 72460",
    "addr:housenumber":"5749",
    "addr:postcode":"72460",
    "addr:street":"Oak Ridge Rd",
    "iso:country":"US",
    "sg:address":"5749 Oak Ridge Rd",
    "sg:city":"Ravenden Springs",
    "sg:classifiers":[
        {
            "category":"Education",
            "subcategory":"School",
            "type":"Public Place"
        }
    ],
    "sg:phone":"+1 870 869 2479",
    "sg:postcode":"72460",
    "sg:province":"AR",
    "sg:tags":[
        "elementary",
        "district",
        "secondary"
    ],
    "wof:name":"Randolph Co School District",
    "wof:placetype":"venue"
},
  "geometry": {"coordinates":[-91.20547999999999,36.370702],"type":"Point"}
}