{
  "type": "Feature",
  "properties": {
    "iso:country":"US",
    "sg:address":"312 Main St",
    "sg:city":"Little Rock",
    "sg:classifiers":[
        {
            "category":"Recreation",
            "type":"Entertainment"
        }
    ],
    "sg:phone":"+1 501 975 7575",
    "sg:postcode":"72201",
    "sg:province":"AR",
    "sg:tags":[
        "ticket"
    ],
    "wof:name":"Ticketmaster",
    "wof:placetype":"venue"
},
  "geometry": {"coordinates":[-92.270843,34.745781],"type":"Point"}
}