{
  "type": "Feature",
  "properties": {
    "iso:country":"US",
    "sg:address":"502 W Main St",
    "sg:city":"Cabot",
    "sg:classifiers":[
        {
            "category":"Insurance",
            "subcategory":"Insurance Agent",
            "type":"Services"
        },
        {
            "category":"Insurance",
            "subcategory":"Hazard Insurance",
            "type":"Services"
        },
        {
            "category":"Insurance",
            "subcategory":"Title Insurance",
            "type":"Services"
        },
        {
            "category":"Insurance",
            "subcategory":"Life Insurance",
            "type":"Services"
        }
    ],
    "sg:phone":"+1 501 605 1258",
    "sg:postcode":"72023",
    "sg:province":"AR",
    "sg:tags":[
        "business",
        "auto",
        "commercial",
        "homeowner",
        "motorcycle",
        "renter"
    ],
    "wof:name":"Allstate Insurance Company - Mark Goings",
    "wof:placetype":"venue"
},
  "geometry": {"coordinates":[-92.019493,34.975634],"type":"Point"}
}