{
  "type": "Feature",
  "properties": {
    "iso:country":"US",
    "sg:address":"2531 Greene Rd 932",
    "sg:city":"Paragould",
    "sg:phone":"+1 870 239 5770",
    "sg:postcode":"72450",
    "sg:province":"AR",
    "sg:tags":[
        "farm",
        "cotton"
    ],
    "wof:name":"Gary Fitzgerald",
    "wof:placetype":"venue"
},
  "geometry": {"coordinates":[-90.405333,36.013551],"type":"Point"}
}