{
  "type": "Feature",
  "properties": {
    "iso:country":"US",
    "sg:address":"353 Hwy 63",
    "sg:city":"Ravenden",
    "sg:classifiers":[
        {
            "category":"Professional",
            "subcategory":"Business Services",
            "type":"Services"
        }
    ],
    "sg:phone":"+1 870 966 3384",
    "sg:postcode":"72459",
    "sg:province":"AR",
    "wof:name":"P G Trucking Inc",
    "wof:placetype":"venue"
},
  "geometry": {"coordinates":[-91.28859,36.25998],"type":"Point"}
}