{
  "type": "Feature",
  "properties": {
    "iso:country":"US",
    "sg:address":"3882 The New Rd",
    "sg:city":"Shirley",
    "sg:classifiers":[
        {
            "category":"Farming",
            "subcategory":"Farm",
            "type":"Manufacturing & Wholesale Goods"
        }
    ],
    "sg:phone":"+1 501 745 3882",
    "sg:postcode":"72153",
    "sg:province":"AR",
    "wof:name":"Fred Herman",
    "wof:placetype":"venue"
},
  "geometry": {"coordinates":[-92.368876,35.586804],"type":"Point"}
}