{
  "type": "Feature",
  "properties": {
    "iso:country":"US",
    "sg:address":"448 S Alabama St",
    "sg:city":"Marianna",
    "sg:classifiers":[
        {
            "category":"Cinema",
            "subcategory":"Movie Rental",
            "type":"Entertainment"
        }
    ],
    "sg:phone":"+1 870 295 2325",
    "sg:postcode":"72360",
    "sg:province":"AR",
    "sg:tags":[
        "video",
        "tape"
    ],
    "wof:name":"Mr Video",
    "wof:placetype":"venue"
},
  "geometry": {"coordinates":[-90.76694999999999,34.76397],"type":"Point"}
}