{
  "type": "Feature",
  "properties": {
    "iso:country":"US",
    "sg:address":"3000 Vinson Rd",
    "sg:city":"Little Rock",
    "sg:classifiers":[
        {
            "category":"Shopping",
            "subcategory":"Bicycles & Sporting Goods",
            "type":"Retail Goods"
        }
    ],
    "sg:phone":"+1 501 888 7801",
    "sg:postcode":"72206",
    "sg:province":"AR",
    "wof:name":"Drifters Gun Shop",
    "wof:placetype":"venue"
},
  "geometry": {"coordinates":[-92.311764,34.647484],"type":"Point"}
}