{
  "type": "Feature",
  "properties": {
    "iso:country":"US",
    "sg:address":"40 Jones Ln",
    "sg:city":"Morrilton",
    "sg:classifiers":[
        {
            "category":"Government",
            "subcategory":"Fire Station",
            "type":"Public Place"
        }
    ],
    "sg:phone":"+1 501 727 5250",
    "sg:postcode":"72110",
    "sg:province":"AR",
    "sg:tags":[
        "department"
    ],
    "wof:name":"Petitjean Mt Fire Dept",
    "wof:placetype":"venue"
},
  "geometry": {"coordinates":[-92.890988,35.133851],"type":"Point"}
}