{
  "type": "Feature",
  "properties": {
    "iso:country":"US",
    "sg:address":"228 N Gray St",
    "sg:city":"Newport",
    "sg:classifiers":[
        {
            "category":"Food & Beverages",
            "subcategory":"Groceries & Convenience Stores",
            "type":"Retail Goods"
        }
    ],
    "sg:phone":"+1 870 523 6715",
    "sg:postcode":"72112",
    "sg:province":"AR",
    "wof:name":"Highway 71 Grocery",
    "wof:placetype":"venue"
},
  "geometry": {"coordinates":[-91.25879999999999,35.606739],"type":"Point"}
}