{
  "type": "Feature",
  "properties": {
    "iso:country":"US",
    "sg:address":"810 Newport Rd",
    "sg:city":"Batesville",
    "sg:classifiers":[
        {
            "category":"Transit Center",
            "subcategory":"Freight",
            "type":"Transportation"
        },
        {
            "category":"Freight",
            "type":"Transportation"
        }
    ],
    "sg:phone":"+1 870 251 2806",
    "sg:postcode":"72501",
    "sg:province":"AR",
    "sg:tags":[
        "local",
        "trucking-motor",
        "trucking"
    ],
    "sg:website":"http://www.billdavistrucking.com",
    "wof:name":"Bill Davis Trucking, Inc.",
    "wof:placetype":"venue"
},
  "geometry": {"coordinates":[-91.598681,35.694053],"type":"Point"}
}