{
  "type": "Feature",
  "properties": {
    "iso:country":"US",
    "sg:address":"2821 W Main St",
    "sg:city":"Blytheville",
    "sg:classifiers":[
        {
            "category":"Professional",
            "type":"Services"
        }
    ],
    "sg:phone":"+1 870 762 2261",
    "sg:postcode":"72315",
    "sg:province":"AR",
    "sg:tags":[
        "establishment"
    ],
    "wof:name":"Drainage District",
    "wof:placetype":"venue"
},
  "geometry": {"coordinates":[-89.938021,35.923127],"type":"Point"}
}