{
  "type": "Feature",
  "properties": {
    "addr:full":"1605 W Shady Grove Rd Springdale AR 72764",
    "addr:housenumber":"1605",
    "addr:postcode":"72764",
    "addr:street":"W Shady Grove Rd",
    "iso:country":"US",
    "sg:address":"1605 W Shady Grove Rd",
    "sg:city":"Springdale",
    "sg:classifiers":[
        {
            "category":"Food & Beverages",
            "subcategory":"Farmers Market",
            "type":"Retail Goods"
        },
        {
            "category":"Wholesale",
            "subcategory":"Fruits & Vegetables",
            "type":"Manufacturing & Wholesale Goods"
        }
    ],
    "sg:phone":"+1 479 872 0200",
    "sg:postcode":"72764",
    "sg:province":"AR",
    "sg:tags":[
        "shipper",
        "grower",
        "vegetables-wholesale"
    ],
    "wof:name":"Kimball & Thompson Produce Company",
    "wof:placetype":"venue"
},
  "geometry": {"coordinates":[-94.148869,36.14572],"type":"Point"}
}