{
  "type": "Feature",
  "properties": {
    "iso:country":"US",
    "sg:address":"18402 Gardenia Rd",
    "sg:city":"Springdale",
    "sg:classifiers":[
        {
            "category":"Professional",
            "subcategory":"Computer Services",
            "type":"Services"
        }
    ],
    "sg:phone":"+1 479 872 6081",
    "sg:postcode":"72764",
    "sg:province":"AR",
    "sg:tags":[
        "related"
    ],
    "wof:name":"Haags Comp Consultg",
    "wof:placetype":"venue"
},
  "geometry": {"coordinates":[-94.02125,36.177437],"type":"Point"}
}