{
  "type": "Feature",
  "properties": {
    "iso:country":"US",
    "sg:address":"316 W Main St",
    "sg:city":"Blytheville",
    "sg:classifiers":[
        {
            "category":"Shopping",
            "subcategory":"Books",
            "type":"Retail Goods"
        }
    ],
    "sg:phone":"+1 870 763 3333",
    "sg:postcode":"72315",
    "sg:province":"AR",
    "sg:tags":[
        "new",
        "dealer"
    ],
    "wof:name":"That Bookstore In Blytheville",
    "wof:placetype":"venue"
},
  "geometry": {"coordinates":[-89.906796,35.927395],"type":"Point"}
}