{
  "type": "Feature",
  "properties": {
    "iso:country":"US",
    "sg:address":"12111 W Markham St",
    "sg:city":"Little Rock",
    "sg:classifiers":[
        {
            "category":"Professional",
            "subcategory":"Computer Services",
            "type":"Services"
        }
    ],
    "sg:phone":"+1 501 529 2000",
    "sg:postcode":"72211",
    "sg:province":"AR",
    "sg:tags":[
        "website",
        "design"
    ],
    "sg:website":"www.giftedlizardwebdesign.com",
    "wof:name":"Unleashed Web Design",
    "wof:placetype":"venue"
},
  "geometry": {"coordinates":[-92.41304599999999,34.754047],"type":"Point"}
}