{
  "type": "Feature",
  "properties": {
    "iso:country":"US",
    "sg:address":"161 Walnut St",
    "sg:city":"Marianna",
    "sg:classifiers":[
        {
            "category":"Education",
            "subcategory":"School",
            "type":"Public Place"
        }
    ],
    "sg:phone":"+1 870 295 2511",
    "sg:postcode":"72360",
    "sg:province":"AR",
    "sg:tags":[
        "child",
        "day",
        "care"
    ],
    "wof:name":"Hippy",
    "wof:placetype":"venue"
},
  "geometry": {"coordinates":[-90.76115,34.777264],"type":"Point"}
}