{
  "type": "Feature",
  "properties": {
    "iso:country":"US",
    "sg:address":"2027 N Juneway Ter",
    "sg:city":"Fayetteville",
    "sg:classifiers":[
        {
            "category":"Professional",
            "subcategory":"Research",
            "type":"Services"
        }
    ],
    "sg:phone":"+1 479 443 4527",
    "sg:postcode":"72703",
    "sg:province":"AR",
    "sg:tags":[
        "sustainable",
        "center"
    ],
    "wof:name":"Brilliance LLC",
    "wof:placetype":"venue"
},
  "geometry": {"coordinates":[-94.14568800000001,36.087616],"type":"Point"}
}