{
  "type": "Feature",
  "properties": {
    "iso:country":"US",
    "sg:address":"208 N Hervey St",
    "sg:city":"Hope",
    "sg:classifiers":[
        {
            "category":"Utilities",
            "subcategory":"Mobile Phone",
            "type":"Services"
        }
    ],
    "sg:phone":"+1 870 777 9217",
    "sg:postcode":"71801",
    "sg:province":"AR",
    "sg:tags":[
        "telephone",
        "cellular"
    ],
    "wof:name":"Alltel",
    "wof:placetype":"venue"
},
  "geometry": {"coordinates":[-93.59773199999999,33.670104],"type":"Point"}
}