{
  "type": "Feature",
  "properties": {
    "iso:country":"US",
    "sg:address":"5417 Pinnacle Point Dr",
    "sg:city":"Rogers",
    "sg:classifiers":[
        {
            "category":"Utilities",
            "type":"Services"
        }
    ],
    "sg:phone":"+1 479 464 4665",
    "sg:postcode":"72758",
    "sg:province":"AR",
    "sg:tags":[
        "provider",
        "internet"
    ],
    "wof:name":"Telxcom",
    "wof:placetype":"venue"
},
  "geometry": {"coordinates":[-94.1866,36.311501],"type":"Point"}
}