{
  "type": "Feature",
  "properties": {
    "addr:full":"534 W Washington Ave Jonesboro AR 72401",
    "addr:housenumber":"534",
    "addr:postcode":"72401",
    "addr:street":"W Washington Ave",
    "iso:country":"US",
    "sg:address":"534 W Washington Ave",
    "sg:city":"Jonesboro",
    "sg:classifiers":[
        {
            "category":"Travel",
            "subcategory":"Hotels & Motels",
            "type":"Entertainment"
        }
    ],
    "sg:phone":"+1 870 935 9300",
    "sg:postcode":"72401",
    "sg:province":"AR",
    "sg:tags":[
        "breakfast",
        "accommodation",
        "bed"
    ],
    "wof:name":"West Washington Guest House",
    "wof:placetype":"venue"
},
  "geometry": {"coordinates":[-90.708085,35.838449],"type":"Point"}
}