{
  "type": "Feature",
  "properties": {
    "addr:full":"515 Enterprise Dr Ste 106 Lowell AR 72745",
    "addr:housenumber":"515",
    "addr:postcode":"72745",
    "addr:street":"Enterprise Dr Ste 106",
    "iso:country":"US",
    "sg:address":"515 Enterprise Dr Ste 106",
    "sg:city":"Lowell",
    "sg:classifiers":[
        {
            "category":"Communications",
            "subcategory":"Newspaper",
            "type":"Services"
        }
    ],
    "sg:phone":"+1 479 770 8400",
    "sg:postcode":"72745",
    "sg:province":"AR",
    "sg:tags":[
        "print",
        "medium"
    ],
    "sg:website":"www.arkansasonline.com",
    "wof:name":"Arkansas Democrat-Gazette",
    "wof:placetype":"venue"
},
  "geometry": {"coordinates":[-94.146372,36.250917],"type":"Point"}
}