{
  "type": "Feature",
  "properties": {
    "iso:country":"US",
    "sg:address":"249 Coyote Cir",
    "sg:city":"Story",
    "sg:classifiers":[
        {
            "category":"Farming",
            "subcategory":"Livestock Farm",
            "type":"Manufacturing & Wholesale Goods"
        }
    ],
    "sg:phone":"+1 870 867 3463",
    "sg:postcode":"71970",
    "sg:province":"AR",
    "sg:tags":[
        "hog",
        "or",
        "feedlot"
    ],
    "wof:name":"Makin Bacon Farms",
    "wof:placetype":"venue"
},
  "geometry": {"coordinates":[-93.508867,34.725711],"type":"Point"}
}