{
  "type": "Feature",
  "properties": {
    "iso:country":"US",
    "sg:address":"1623 E Oak St",
    "sg:city":"Conway",
    "sg:classifiers":[
        {
            "category":"Shopping",
            "subcategory":"Bicycles & Sporting Goods",
            "type":"Retail Goods"
        }
    ],
    "sg:phone":"+1 501 327 7001",
    "sg:postcode":"72032",
    "sg:province":"AR",
    "wof:name":"Clarks Saddle & Boot Repair",
    "wof:placetype":"venue"
},
  "geometry": {"coordinates":[-92.405337,35.091105],"type":"Point"}
}