{
  "type": "Feature",
  "properties": {
    "addr:full":"9688 Benton Ridge Cir Bentonville AR 72712",
    "addr:housenumber":"9688",
    "addr:postcode":"72712",
    "addr:street":"Benton Ridge Cir",
    "iso:country":"US",
    "sg:address":"9688 Benton Ridge Cir",
    "sg:city":"Bentonville",
    "sg:classifiers":[
        {
            "category":"Professional",
            "subcategory":"Engineering",
            "type":"Services"
        }
    ],
    "sg:phone":"+1 479 273 1563",
    "sg:postcode":"72712",
    "sg:province":"AR",
    "sg:tags":[
        "ecological",
        "engineer"
    ],
    "wof:name":"Maran Environmental Cons",
    "wof:placetype":"venue"
},
  "geometry": {"coordinates":[-94.165316,36.390475],"type":"Point"}
}