{
  "type": "Feature",
  "properties": {
    "addr:full":"21734 Christman Rd Fayetteville AR 72703",
    "addr:housenumber":"21734",
    "addr:postcode":"72703",
    "addr:street":"Christman Rd",
    "iso:country":"US",
    "sg:address":"21734 Christman Rd",
    "sg:city":"Fayetteville",
    "sg:classifiers":[
        {
            "category":"Farming",
            "subcategory":"Livestock Farm",
            "type":"Manufacturing & Wholesale Goods"
        }
    ],
    "sg:phone":"+1 479 789 5466",
    "sg:postcode":"72703",
    "sg:province":"AR",
    "sg:tags":[
        "animal",
        "general"
    ],
    "wof:name":"Healing Horse Ranch LLC",
    "wof:placetype":"venue"
},
  "geometry": {"coordinates":[-93.948964,36.123911],"type":"Point"}
}