{
  "type": "Feature",
  "properties": {
    "iso:country":"US",
    "sg:address":"412 W Holt Rd",
    "sg:city":"Lincoln",
    "sg:classifiers":[
        {
            "category":"Farming",
            "subcategory":"Poultry Farm",
            "type":"Manufacturing & Wholesale Goods"
        }
    ],
    "sg:phone":"+1 479 824 5360",
    "sg:postcode":"72744",
    "sg:province":"AR",
    "sg:tags":[
        "chicken"
    ],
    "wof:name":"Barker Verla",
    "wof:placetype":"venue"
},
  "geometry": {"coordinates":[-94.438503,35.95903],"type":"Point"}
}