{
  "type": "Feature",
  "properties": {
    "addr:full":"4800 Jerry Dr Little Rock AR 72223",
    "addr:housenumber":"4800",
    "addr:postcode":"72223",
    "addr:street":"Jerry Dr",
    "iso:country":"US",
    "sg:address":"4800 Jerry Dr",
    "sg:city":"Little Rock",
    "sg:classifiers":[
        {
            "category":"Building & Trades",
            "subcategory":"Electrical",
            "type":"Services"
        }
    ],
    "sg:phone":"+1 501 868 9500",
    "sg:postcode":"72223",
    "sg:province":"AR",
    "sg:tags":[
        "electrical",
        "contractor"
    ],
    "wof:name":"Bob Coppings Services",
    "wof:placetype":"venue"
},
  "geometry": {"coordinates":[-92.434935,34.801093],"type":"Point"}
}