{
  "type": "Feature",
  "properties": {
    "iso:country":"US",
    "sg:address":"3403 W Walnut St",
    "sg:city":"Rogers",
    "sg:classifiers":[
        {
            "category":"Professional",
            "subcategory":"Business Services",
            "type":"Services"
        }
    ],
    "sg:phone":"+1 479 986 9890",
    "sg:postcode":"72756",
    "sg:province":"AR",
    "sg:tags":[
        "appraiser"
    ],
    "wof:name":"Roger's Appraisal Svc",
    "wof:placetype":"venue"
},
  "geometry": {"coordinates":[-94.169468,36.334777],"type":"Point"}
}