{
  "type": "Feature",
  "properties": {
    "iso:country":"US",
    "sg:address":"203 W Dequeen Ave",
    "sg:city":"De Queen",
    "sg:classifiers":[
        {
            "category":"Shopping",
            "subcategory":"Catalog Store",
            "type":"Retail Goods"
        }
    ],
    "sg:phone":"+1 870 642 2833",
    "sg:postcode":"71832",
    "sg:province":"AR",
    "sg:tags":[
        "mail",
        "house"
    ],
    "wof:name":"JC Penney",
    "wof:placetype":"venue"
},
  "geometry": {"coordinates":[-94.33972199999999,34.03771],"type":"Point"}
}