{
  "type": "Feature",
  "properties": {
    "iso:country":"US",
    "sg:address":"229 N School Ave",
    "sg:city":"Fayetteville",
    "sg:classifiers":[
        {
            "category":"Arts & Performance",
            "subcategory":"Theater",
            "type":"Entertainment"
        }
    ],
    "sg:phone":"+1 479 521 4166",
    "sg:postcode":"72701",
    "sg:province":"AR",
    "sg:tags":[
        "band",
        "orchestra"
    ],
    "sg:website":"www.nasymphony.org",
    "wof:name":"North Arkansas Symphony",
    "wof:placetype":"venue"
},
  "geometry": {"coordinates":[-94.164281,36.065943],"type":"Point"}
}