{
  "type": "Feature",
  "properties": {
    "iso:country":"US",
    "sg:address":"141 Central Ave",
    "sg:city":"Jacksonville",
    "sg:classifiers":[
        {
            "category":"Social Services",
            "subcategory":"Child Care",
            "type":"Services"
        }
    ],
    "sg:phone":"+1 501 982 3202",
    "sg:postcode":"72076",
    "sg:province":"AR",
    "wof:name":"Mrs Jones Little Lambs Inc",
    "wof:placetype":"venue"
},
  "geometry": {"coordinates":[-92.102332,34.865327],"type":"Point"}
}