{
  "type": "Feature",
  "properties": {
    "iso:country":"US",
    "sg:address":"269 Fairview Rd",
    "sg:city":"Searcy",
    "sg:classifiers":[
        {
            "category":"Retail",
            "subcategory":"Repair Shop",
            "type":"Services"
        }
    ],
    "sg:phone":"+1 501 278 5626",
    "sg:postcode":"72143",
    "sg:province":"AR",
    "sg:tags":[
        "refinishing",
        "furniture"
    ],
    "wof:name":"Duncan Furniture Refinishing",
    "wof:placetype":"venue"
},
  "geometry": {"coordinates":[-91.749067,35.287327],"type":"Point"}
}