{
  "type": "Feature",
  "properties": {
    "iso:country":"US",
    "sg:address":"617 Ball Park Rd",
    "sg:city":"Russellville",
    "sg:classifiers":[
        {
            "category":"Farming",
            "subcategory":"Poultry Farm",
            "type":"Manufacturing & Wholesale Goods"
        }
    ],
    "sg:phone":"+1 479 967 5649",
    "sg:postcode":"72802",
    "sg:province":"AR",
    "sg:tags":[
        "hatchery"
    ],
    "wof:name":"Farming",
    "wof:placetype":"venue"
},
  "geometry": {"coordinates":[-93.00344800000001,35.352795],"type":"Point"}
}