{
  "type": "Feature",
  "properties": {
    "iso:country":"US",
    "sg:address":"108 W Woodrow St",
    "sg:city":"Jonesboro",
    "sg:classifiers":[
        {
            "category":"Organizations",
            "subcategory":"Religious Organization",
            "type":"Services"
        }
    ],
    "sg:phone":"+1 870 802 2653",
    "sg:postcode":"72401",
    "sg:province":"AR",
    "sg:tags":[
        "church"
    ],
    "wof:name":"Community Of Christ Kids Bible",
    "wof:placetype":"venue"
},
  "geometry": {"coordinates":[-90.706218,35.85087],"type":"Point"}
}