{
  "type": "Feature",
  "properties": {
    "iso:country":"US",
    "sg:address":"12710 Timber Bend Dr",
    "sg:city":"Little Rock",
    "sg:classifiers":[
        {
            "category":"Building & Trades",
            "subcategory":"Construction",
            "type":"Services"
        }
    ],
    "sg:phone":"+1 501 221 9684",
    "sg:postcode":"72211",
    "sg:province":"AR",
    "sg:tags":[
        "house"
    ],
    "wof:name":"Mwf Construction",
    "wof:placetype":"venue"
},
  "geometry": {"coordinates":[-92.414531,34.748347],"type":"Point"}
}