{
  "type": "Feature",
  "properties": {
    "addr:full":"1722 Duncan St Conway AR 72034",
    "addr:housenumber":"1722",
    "addr:postcode":"72034",
    "addr:street":"Duncan St",
    "iso:country":"US",
    "sg:address":"1722 Duncan St",
    "sg:city":"Conway",
    "sg:classifiers":[
        {
            "category":"Professional",
            "subcategory":"Art Services",
            "type":"Services"
        }
    ],
    "sg:phone":"+1 501 450 9614",
    "sg:postcode":"72034",
    "sg:province":"AR",
    "sg:tags":[
        "graphic",
        "designer"
    ],
    "wof:name":"Graphic Design",
    "wof:placetype":"venue"
},
  "geometry": {"coordinates":[-92.44756700000001,35.093552],"type":"Point"}
}