{
  "type": "Feature",
  "properties": {
    "iso:country":"US",
    "sg:address":"510 S Fulton St",
    "sg:city":"Hope",
    "sg:classifiers":[
        {
            "category":"Communications",
            "subcategory":"Film & Video Production",
            "type":"Services"
        }
    ],
    "sg:phone":"+1 870 722 5625",
    "sg:postcode":"71801",
    "sg:province":"AR",
    "sg:tags":[
        "motion"
    ],
    "wof:name":"Hassans Touch",
    "wof:placetype":"venue"
},
  "geometry": {"coordinates":[-93.60015199999999,33.663054],"type":"Point"}
}