{
  "type": "Feature",
  "properties": {
    "addr:full":"31395 S 618 Rd Grove OK 74344",
    "addr:housenumber":"31395",
    "addr:postcode":"74344",
    "addr:street":"S 618 Rd",
    "iso:country":"US",
    "sg:address":"31395 S 618 Rd",
    "sg:city":"Grove",
    "sg:classifiers":[
        {
            "category":"Animal Shelter",
            "type":"Public Place"
        },
        {
            "category":"Shopping",
            "subcategory":"Pets & Pet Supplies",
            "type":"Retail Goods"
        },
        {
            "category":"Retail",
            "subcategory":"Animal Services",
            "type":"Services"
        },
        {
            "category":"Retail",
            "subcategory":"Pet Boarding",
            "type":"Services"
        }
    ],
    "sg:phone":"+1 918 786 7034",
    "sg:postcode":"74344",
    "sg:province":"OK",
    "sg:tags":[
        "training",
        "dog",
        "cat",
        "furnishing",
        "grooming",
        "kennel",
        "store"
    ],
    "wof:name":"Doggie Do",
    "wof:placetype":"venue"
},
  "geometry": {"coordinates":[-94.77758799999999,36.562935],"type":"Point"}
}