{
  "type": "Feature",
  "properties": {
    "addr:full":"301 E Stadium Magnolia AR 71753",
    "addr:housenumber":"301",
    "addr:postcode":"71753",
    "addr:street":"E Stadium Magnolia",
    "iso:country":"US",
    "sg:address":"301 E Stadium",
    "sg:city":"Magnolia",
    "sg:classifiers":[
        {
            "category":"Health Services",
            "subcategory":"Doctor",
            "type":"Services"
        }
    ],
    "sg:phone":"+1 870 234 9800",
    "sg:postcode":"71753",
    "sg:province":"AR",
    "sg:tags":[
        "physician",
        "immunology",
        "allergy",
        "surgeons",
        "treatment",
        "surgeon",
        "surgery-general"
    ],
    "sg:website":"http://www.healthcareexpress.us",
    "wof:name":"Healthcare Express",
    "wof:placetype":"venue"
},
  "geometry": {"coordinates":[-93.237498,33.278935],"type":"Point"}
}