{
  "type": "Feature",
  "properties": {
    "addr:full":"112 Rainbow Dr Cabot AR 72023",
    "addr:housenumber":"112",
    "addr:postcode":"72023",
    "addr:street":"Rainbow Dr",
    "iso:country":"US",
    "sg:address":"112 Rainbow Dr",
    "sg:city":"Cabot",
    "sg:classifiers":[
        {
            "category":"Professional",
            "subcategory":"Detective & Security Services",
            "type":"Services"
        },
        {
            "category":"Manufacturing",
            "subcategory":"Electronics",
            "type":"Manufacturing & Wholesale Goods"
        },
        {
            "category":"Manufacturing",
            "subcategory":"Building Materials",
            "type":"Manufacturing & Wholesale Goods"
        }
    ],
    "sg:phone":"+1 501 605 9333",
    "sg:postcode":"72023",
    "sg:province":"AR",
    "sg:tags":[
        "control",
        "monitoring",
        "equipment-wholesale",
        "alarm",
        "system",
        "systems-wholesale",
        "fire",
        "manufacturer"
    ],
    "wof:name":"Alarm Works Of Arkansas Inc",
    "wof:placetype":"venue"
},
  "geometry": {"coordinates":[-92.06025,34.948066],"type":"Point"}
}