{
  "type": "Feature",
  "properties": {
    "iso:country":"US",
    "sg:address":"130 N Main St",
    "sg:city":"Springdale",
    "sg:classifiers":[
        {
            "category":"Organizations",
            "subcategory":"Religious Organization",
            "type":"Services"
        }
    ],
    "sg:phone":"+1 479 751 1528",
    "sg:postcode":"72764",
    "sg:province":"AR",
    "sg:tags":[
        "church"
    ],
    "wof:name":"United Methodist Dist",
    "wof:placetype":"venue"
},
  "geometry": {"coordinates":[-94.132322,36.18601],"type":"Point"}
}