{
  "type": "Feature",
  "properties": {
    "addr:full":"513 Main St Arkadelphia AR 71923",
    "addr:housenumber":"513",
    "addr:postcode":"71923",
    "addr:street":"Main St",
    "iso:country":"US",
    "sg:address":"513 Main St",
    "sg:city":"Arkadelphia",
    "sg:classifiers":[
        {
            "category":"Shopping",
            "type":"Retail Goods"
        }
    ],
    "sg:phone":"+1 870 246 5800",
    "sg:postcode":"71923",
    "sg:province":"AR",
    "sg:tags":[
        "picture",
        "frame"
    ],
    "wof:name":"J & S Framing",
    "wof:placetype":"venue"
},
  "geometry": {"coordinates":[-93.053455,34.119494],"type":"Point"}
}