{
  "type": "Feature",
  "properties": {
    "iso:country":"US",
    "sg:address":"316 W Center St",
    "sg:city":"Beebe",
    "sg:classifiers":[
        {
            "category":"Shopping Center",
            "type":"Public Place"
        }
    ],
    "sg:phone":"+1 501 882 2424",
    "sg:postcode":"72012",
    "sg:province":"AR",
    "sg:tags":[
        "flea",
        "market"
    ],
    "wof:name":"Do Drop In Flea Market",
    "wof:placetype":"venue"
},
  "geometry": {"coordinates":[-91.88413799999999,35.068262],"type":"Point"}
}