{
  "type": "Feature",
  "properties": {
    "iso:country":"US",
    "sg:address":"3623 Lacoste Dr",
    "sg:city":"Jonesboro",
    "sg:classifiers":[
        {
            "category":"Wholesale",
            "subcategory":"Construction Materials",
            "type":"Manufacturing & Wholesale Goods"
        }
    ],
    "sg:phone":"+1 870 972 6566",
    "sg:postcode":"72404",
    "sg:province":"AR",
    "wof:name":"Orr Enterprises LLC",
    "wof:placetype":"venue"
},
  "geometry": {"coordinates":[-90.76817,35.806105],"type":"Point"}
}