{
  "type": "Feature",
  "properties": {
    "addr:full":"1111 N 4th St Paris AR 72855",
    "addr:housenumber":"1111",
    "addr:postcode":"72855",
    "addr:street":"N 4Th St",
    "iso:country":"US",
    "sg:address":"1111 N 4th St",
    "sg:city":"Paris",
    "sg:classifiers":[
        {
            "category":"Banks & Credit Unions",
            "subcategory":"Financial Services",
            "type":"Services"
        }
    ],
    "sg:phone":"+1 479 963 6242",
    "sg:postcode":"72855",
    "sg:province":"AR",
    "sg:tags":[
        "investor"
    ],
    "wof:name":"Kenneth E Kiefer",
    "wof:placetype":"venue"
},
  "geometry": {"coordinates":[-93.727007,35.301739],"type":"Point"}
}