{
  "type": "Feature",
  "properties": {
    "addr:full":"14512 E Highway 12 Rogers AR 72756",
    "addr:housenumber":"14512",
    "addr:postcode":"72756",
    "addr:street":"E Highway 12",
    "iso:country":"US",
    "sg:address":"14512 E Highway 12",
    "sg:city":"Rogers",
    "sg:classifiers":[
        {
            "category":"Banks & Credit Unions",
            "subcategory":"Bank",
            "type":"Services"
        }
    ],
    "sg:phone":"+1 479 925 7077",
    "sg:postcode":"72756",
    "sg:province":"AR",
    "sg:tags":[
        "saving",
        "commercial"
    ],
    "sg:website":"http://www.fsbank.com",
    "wof:name":"First Security Bank",
    "wof:placetype":"venue"
},
  "geometry": {"coordinates":[-94.028136,36.330761],"type":"Point"}
}