{
  "type": "Feature",
  "properties": {
    "iso:country":"US",
    "sg:address":"211 SE Walton Blvd",
    "sg:city":"Bentonville",
    "sg:classifiers":[
        {
            "category":"Organizations",
            "subcategory":"Religious Organization",
            "type":"Services"
        }
    ],
    "sg:phone":"+1 479 366 3169",
    "sg:postcode":"72712",
    "sg:province":"AR",
    "sg:tags":[
        "church"
    ],
    "sg:website":"www.nwafamilychurch.com",
    "wof:name":"Northwest Arkansas Family Chr",
    "wof:placetype":"venue"
},
  "geometry": {"coordinates":[-94.20841,36.335644],"type":"Point"}
}