{
  "type": "Feature",
  "properties": {
    "iso:country":"US",
    "sg:address":"110 N 11th St",
    "sg:city":"Heber Springs",
    "sg:classifiers":[
        {
            "category":"Professional",
            "subcategory":"Engineering",
            "type":"Services"
        }
    ],
    "sg:phone":"+1 501 362 3118",
    "sg:postcode":"72543",
    "sg:province":"AR",
    "wof:name":"Mehlburger Firm",
    "wof:placetype":"venue"
},
  "geometry": {"coordinates":[-92.040981,35.495308],"type":"Point"}
}