{
  "type": "Feature",
  "properties": {
    "iso:country":"US",
    "sg:address":"162 Mosley Rd",
    "sg:city":"Arkadelphia",
    "sg:classifiers":[
        {
            "category":"Professional",
            "type":"Services"
        }
    ],
    "sg:phone":"+1 870 230 1814",
    "sg:postcode":"71923",
    "sg:province":"AR",
    "wof:name":"J Tommy Curtis",
    "wof:placetype":"venue"
},
  "geometry": {"coordinates":[-93.132036,34.173853],"type":"Point"}
}