{
  "type": "Feature",
  "properties": {
    "iso:country":"US",
    "sg:address":"11 Cardinal Valley Dr",
    "sg:city":"North Little Rock",
    "sg:classifiers":[
        {
            "category":"Farming",
            "subcategory":"Orchard",
            "type":"Manufacturing & Wholesale Goods"
        }
    ],
    "sg:phone":"+1 501 835 0182",
    "sg:postcode":"72120",
    "sg:province":"AR",
    "sg:tags":[
        "fruit",
        "tree"
    ],
    "wof:name":"Waltons Orchards",
    "wof:placetype":"venue"
},
  "geometry": {"coordinates":[-92.230792,34.887199],"type":"Point"}
}