{
  "type": "Feature",
  "properties": {
    "addr:full":"1301 Main St Des Arc AR 72040",
    "addr:housenumber":"1301",
    "addr:postcode":"72040",
    "addr:street":"Main St",
    "iso:country":"US",
    "sg:address":"1301 Main St",
    "sg:city":"Des Arc",
    "sg:classifiers":[
        {
            "category":"Restaurant",
            "type":"Food & Drink"
        }
    ],
    "sg:menulink":"http://www.allmenus.com/ar/white-river/66610-pizza-pro/menu/",
    "sg:phone":"+1 870 256 4847",
    "sg:postcode":"72040",
    "sg:province":"AR",
    "sg:tags":[
        "american",
        "pizza"
    ],
    "wof:name":"Pizza Pro",
    "wof:placetype":"venue"
},
  "geometry": {"coordinates":[-91.507158,34.977086],"type":"Point"}
}