{
  "type": "Feature",
  "properties": {
    "iso:country":"US",
    "sg:address":"1615 W Main St",
    "sg:city":"Corning",
    "sg:classifiers":[
        {
            "category":"Restaurant",
            "type":"Food & Drink"
        }
    ],
    "sg:phone":"+1 870 857 6884",
    "sg:postcode":"72422",
    "sg:province":"AR",
    "sg:tags":[
        "style",
        "family"
    ],
    "wof:name":"Parkview Restaurant",
    "wof:placetype":"venue"
},
  "geometry": {"coordinates":[-90.59214299999999,36.411323],"type":"Point"}
}