{
  "type": "Feature",
  "properties": {
    "addr:full":"596 Hwy 317 Ashdown AR 71822",
    "addr:housenumber":"596",
    "addr:postcode":"71822",
    "addr:street":"Hwy 317 Ashdown",
    "iso:country":"US",
    "sg:address":"596 Hwy 317",
    "sg:city":"Ashdown",
    "sg:classifiers":[
        {
            "category":"Professional",
            "subcategory":"Research",
            "type":"Services"
        }
    ],
    "sg:phone":"+1 870 898 5320",
    "sg:postcode":"71822",
    "sg:province":"AR",
    "sg:tags":[
        "nonphysical",
        "commercial"
    ],
    "wof:name":"Rab Marketing",
    "wof:placetype":"venue"
},
  "geometry": {"coordinates":[-94.012505,33.711538],"type":"Point"}
}