{
  "type": "Feature",
  "properties": {
    "addr:full":"450 Nomoe Rd Royal AR 71968",
    "addr:housenumber":"450",
    "addr:postcode":"71968",
    "addr:street":"Nomoe Rd",
    "iso:country":"US",
    "sg:address":"450 Nomoe Rd",
    "sg:city":"Royal",
    "sg:classifiers":[
        {
            "category":"Building & Trades",
            "subcategory":"Landscaping Services",
            "type":"Services"
        }
    ],
    "sg:phone":"+1 501 760 1810",
    "sg:postcode":"71968",
    "sg:province":"AR",
    "sg:tags":[
        "lawn"
    ],
    "wof:name":"W L Jennings Landscape",
    "wof:placetype":"venue"
},
  "geometry": {"coordinates":[-93.287628,34.49361],"type":"Point"}
}