{
  "type": "Feature",
  "properties": {
    "addr:full":"900 Chapel Hill Rd De Queen AR 71832",
    "addr:housenumber":"900",
    "addr:postcode":"71832",
    "addr:street":"Chapel Hill Rd De",
    "iso:country":"US",
    "sg:address":"900 Chapel Hill Rd",
    "sg:city":"De Queen",
    "sg:classifiers":[
        {
            "category":"Organizations",
            "subcategory":"Labor Organization",
            "type":"Services"
        }
    ],
    "sg:phone":"+1 870 642 6501",
    "sg:postcode":"71832",
    "sg:province":"AR",
    "sg:website":"www.ibew.org",
    "wof:name":"IBEW",
    "wof:placetype":"venue"
},
  "geometry": {"coordinates":[-94.41732399999999,34.020581],"type":"Point"}
}