{
  "type": "Feature",
  "properties": {
    "iso:country":"US",
    "sg:address":"6304 Crystal Hill Rd",
    "sg:city":"N Little Rock",
    "sg:classifiers":[
        {
            "category":"Organizations",
            "subcategory":"Religious Organization",
            "type":"Services"
        }
    ],
    "sg:phone":"+1 501 771 0174",
    "sg:postcode":"72118",
    "sg:province":"AR",
    "sg:tags":[
        "church"
    ],
    "wof:name":"Warren Hill Baptist Church",
    "wof:placetype":"venue"
},
  "geometry": {"coordinates":[-92.33850200000001,34.818165],"type":"Point"}
}