{
  "type": "Feature",
  "properties": {
    "addr:full":"3805 Elliott Ave Springdale AR 72762",
    "addr:housenumber":"3805",
    "addr:postcode":"72762",
    "addr:street":"Elliott Ave",
    "iso:country":"US",
    "sg:address":"3805 Elliott Ave",
    "sg:city":"Springdale",
    "sg:classifiers":[
        {
            "category":"Home & Garden",
            "subcategory":"Carpets & Floor Coverings",
            "type":"Retail Goods"
        }
    ],
    "sg:phone":"+1 479 750 4248",
    "sg:postcode":"72762",
    "sg:province":"AR",
    "sg:tags":[
        "dealer",
        "rug"
    ],
    "wof:name":"Mc Garrah Carpets",
    "wof:placetype":"venue"
},
  "geometry": {"coordinates":[-94.17456900000001,36.17659],"type":"Point"}
}