{
  "type": "Feature",
  "properties": {
    "iso:country":"US",
    "sg:address":"1423 Broadway St",
    "sg:city":"Little Rock",
    "sg:classifiers":[
        {
            "category":"Professional",
            "subcategory":"Engineering",
            "type":"Services"
        }
    ],
    "sg:phone":"+1 501 374 0038",
    "sg:postcode":"72202",
    "sg:province":"AR",
    "sg:tags":[
        "engineer"
    ],
    "wof:name":"FHA Structrual Engr LLC",
    "wof:placetype":"venue"
},
  "geometry": {"coordinates":[-92.277705,34.735234],"type":"Point"}
}