{
  "type": "Feature",
  "properties": {
    "iso:country":"US",
    "sg:address":"519 N Spring St",
    "sg:city":"Harrison",
    "sg:classifiers":[
        {
            "category":"Retail",
            "subcategory":"Funeral Services",
            "type":"Services"
        }
    ],
    "sg:phone":"+1 870 741 3113",
    "sg:postcode":"72601",
    "sg:province":"AR",
    "sg:tags":[
        "director"
    ],
    "wof:name":"Christeson Funeral Home",
    "wof:placetype":"venue"
},
  "geometry": {"coordinates":[-93.109646,36.23532],"type":"Point"}
}