{
  "type": "Feature",
  "properties": {
    "iso:country":"US",
    "sg:address":"2813 E Nettleton Ave",
    "sg:city":"Jonesboro",
    "sg:classifiers":[
        {
            "category":"Shopping",
            "subcategory":"Crafts & Fabrics",
            "type":"Retail Goods"
        }
    ],
    "sg:phone":"+1 870 932 0690",
    "sg:postcode":"72401",
    "sg:province":"AR",
    "sg:tags":[
        "store"
    ],
    "sg:website":"www.hancockfabrics.com",
    "wof:name":"Hancock Fabrics",
    "wof:placetype":"venue"
},
  "geometry": {"coordinates":[-90.67081,35.828297],"type":"Point"}
}