{
  "type": "Feature",
  "properties": {
    "iso:country":"US",
    "sg:address":"5 Portea Dr",
    "sg:city":"Pine Bluff",
    "sg:classifiers":[
        {
            "category":"Wholesale",
            "subcategory":"Machinery & Supplies",
            "type":"Manufacturing & Wholesale Goods"
        },
        {
            "category":"Building & Trades",
            "subcategory":"Construction",
            "type":"Services"
        }
    ],
    "sg:phone":"+1 870 536 9166",
    "sg:postcode":"71601",
    "sg:province":"AR",
    "sg:tags":[
        "industrial",
        "cleaning"
    ],
    "wof:name":"Hydrovac Services Inc",
    "wof:placetype":"venue"
},
  "geometry": {"coordinates":[-91.97228800000001,34.224013],"type":"Point"}
}