{
  "type": "Feature",
  "properties": {
    "addr:full":"854 Walnut St Conway AR 72032",
    "addr:housenumber":"854",
    "addr:postcode":"72032",
    "addr:street":"Walnut St",
    "iso:country":"US",
    "sg:address":"854 Walnut St",
    "sg:city":"Conway",
    "sg:classifiers":[
        {
            "category":"Retail",
            "subcategory":"Auto Repair",
            "type":"Services"
        }
    ],
    "sg:phone":"+1 501 329 8006",
    "sg:postcode":"72032",
    "sg:province":"AR",
    "sg:tags":[
        "automotive"
    ],
    "wof:name":"Auto Cleanup & Body Repair",
    "wof:placetype":"venue"
},
  "geometry": {"coordinates":[-92.436066,35.096261],"type":"Point"}
}