{
  "type": "Feature",
  "properties": {
    "iso:country":"US",
    "sg:address":"14172 Dartmoor Rd",
    "sg:city":"Bentonville",
    "sg:classifiers":[
        {
            "category":"Professional",
            "subcategory":"Engineering",
            "type":"Services"
        }
    ],
    "sg:phone":"+1 479 855 6314",
    "sg:postcode":"72712",
    "sg:province":"AR",
    "sg:tags":[
        "design",
        "system",
        "septic"
    ],
    "wof:name":"Buchanan Services",
    "wof:placetype":"venue"
},
  "geometry": {"coordinates":[-94.212292,36.440275],"type":"Point"}
}