{
  "type": "Feature",
  "properties": {
    "addr:full":"2334 State Highway 77 Marion AR 72364",
    "addr:housenumber":"2334",
    "addr:postcode":"72364",
    "addr:street":"State Highway 77",
    "iso:country":"US",
    "sg:address":"2334 State Highway 77",
    "sg:city":"Marion",
    "sg:classifiers":[
        {
            "category":"Retail",
            "subcategory":"Auto Repair",
            "type":"Services"
        }
    ],
    "sg:phone":"+1 662 655 1613",
    "sg:postcode":"72364",
    "sg:province":"AR",
    "wof:name":"Elite Tire & Automotive Inc",
    "wof:placetype":"venue"
},
  "geometry": {"coordinates":[-90.183798,35.199512],"type":"Point"}
}