{
  "type": "Feature",
  "properties": {
    "iso:country":"US",
    "sg:address":"5400 N State Line Ave",
    "sg:city":"Texarkana",
    "sg:classifiers":[
        {
            "category":"Wholesale",
            "subcategory":"Vending Machines",
            "type":"Manufacturing & Wholesale Goods"
        }
    ],
    "sg:phone":"+1 870 772 0152",
    "sg:postcode":"71854",
    "sg:province":"AR",
    "wof:name":"Yates Vending Co",
    "wof:placetype":"venue"
},
  "geometry": {"coordinates":[-94.043082,33.475402],"type":"Point"}
}