{
  "type": "Feature",
  "properties": {
    "iso:country":"US",
    "sg:address":"3837 East St",
    "sg:city":"Texarkana",
    "sg:classifiers":[
        {
            "category":"Building & Trades",
            "subcategory":"Construction",
            "type":"Services"
        }
    ],
    "sg:phone":"+1 870 773 0300",
    "sg:postcode":"71854",
    "sg:province":"AR",
    "sg:tags":[
        "excavation",
        "contractor"
    ],
    "wof:name":"Cleve Batte Construction Inc",
    "wof:placetype":"venue"
},
  "geometry": {"coordinates":[-93.99969299999999,33.386046],"type":"Point"}
}