{
  "type": "Feature",
  "properties": {
    "iso:country":"US",
    "sg:address":"6 Kings Ct",
    "sg:city":"Heber Springs",
    "sg:classifiers":[
        {
            "category":"Home & Garden",
            "subcategory":"Home Furnishings",
            "type":"Retail Goods"
        }
    ],
    "sg:phone":"+1 501 250 0517",
    "sg:postcode":"72543",
    "sg:province":"AR",
    "wof:name":"Bruce N Cotton",
    "wof:placetype":"venue"
},
  "geometry": {"coordinates":[-92.102506,35.461991],"type":"Point"}
}