{
  "type": "Feature",
  "properties": {
    "iso:country":"US",
    "sg:address":"4610 N Saint Louis St",
    "sg:city":"Batesville",
    "sg:classifiers":[
        {
            "category":"Building & Trades",
            "subcategory":"Construction",
            "type":"Services"
        }
    ],
    "sg:phone":"+1 870 793 3967",
    "sg:postcode":"72501",
    "sg:province":"AR",
    "sg:tags":[
        "home",
        "builder"
    ],
    "wof:name":"Bishop Homes Inc",
    "wof:placetype":"venue"
},
  "geometry": {"coordinates":[-91.582694,35.843678],"type":"Point"}
}