{
  "type": "Feature",
  "properties": {
    "addr:full":"1645 Hwy 412 W Siloam Springs OK 72761",
    "addr:housenumber":"1645",
    "addr:postcode":"72761",
    "addr:street":"Hwy 412 W",
    "iso:country":"US",
    "sg:address":"1645 Hwy 412 W",
    "sg:city":"Siloam Springs",
    "sg:classifiers":[
        {
            "category":"Banks & Credit Unions",
            "subcategory":"Bank",
            "type":"Services"
        }
    ],
    "sg:phone":"+1 479 524 2500",
    "sg:postcode":"72761",
    "sg:province":"OK",
    "wof:name":"First National Bank",
    "wof:placetype":"venue"
},
  "geometry": {"coordinates":[-94.556462,36.17637],"type":"Point"}
}