{
  "type": "Feature",
  "properties": {
    "iso:country":"US",
    "sg:address":"16004 Cantrell Rd",
    "sg:city":"Little Rock",
    "sg:classifiers":[
        {
            "category":"Wholesale",
            "subcategory":"Farm Supplies",
            "type":"Manufacturing & Wholesale Goods"
        }
    ],
    "sg:phone":"+1 501 868 9164",
    "sg:postcode":"72223",
    "sg:province":"AR",
    "sg:tags":[
        "feed"
    ],
    "wof:name":"Uncle Jack's Feed & Farm Inc",
    "wof:placetype":"venue"
},
  "geometry": {"coordinates":[-92.44914300000001,34.803002],"type":"Point"}
}