{
  "type": "Feature",
  "properties": {
    "addr:full":"508 Ridge Ave Mena AR 71953",
    "addr:housenumber":"508",
    "addr:postcode":"71953",
    "addr:street":"Ridge Ave",
    "iso:country":"US",
    "sg:address":"508 Ridge Ave",
    "sg:city":"Mena",
    "sg:classifiers":[
        {
            "category":"Manufacturing",
            "subcategory":"Lumber",
            "type":"Manufacturing & Wholesale Goods"
        }
    ],
    "sg:phone":"+1 479 394 2575",
    "sg:postcode":"71953",
    "sg:province":"AR",
    "sg:tags":[
        "logging"
    ],
    "wof:name":"Hughes Logging Company",
    "wof:placetype":"venue"
},
  "geometry": {"coordinates":[-94.23713100000001,34.572273],"type":"Point"}
}