{
  "type": "Feature",
  "properties": {
    "iso:country":"US",
    "sg:address":"414 Chickasawba Ave",
    "sg:city":"Blytheville",
    "sg:classifiers":[
        {
            "category":"Personal",
            "subcategory":"Beauty Salon",
            "type":"Services"
        }
    ],
    "sg:phone":"+1 870 763 3010",
    "sg:postcode":"72315",
    "sg:province":"AR",
    "sg:tags":[
        "shop"
    ],
    "wof:name":"Magic Fingers Hair Salon",
    "wof:placetype":"venue"
},
  "geometry": {"coordinates":[-89.90779000000001,35.929326],"type":"Point"}
}