{
  "type": "Feature",
  "properties": {
    "iso:country":"US",
    "sg:address":"9108 N Rodney Parham Rd",
    "sg:city":"Little Rock",
    "sg:classifiers":[
        {
            "category":"Education",
            "subcategory":"Dance Studio",
            "type":"Public Place"
        }
    ],
    "sg:phone":"+1 501 217 8777",
    "sg:postcode":"72205",
    "sg:province":"AR",
    "sg:tags":[
        "instruction",
        "dancing"
    ],
    "wof:name":"Broadway Stars",
    "wof:placetype":"venue"
},
  "geometry": {"coordinates":[-92.373779,34.757095],"type":"Point"}
}