{
  "type": "Feature",
  "properties": {
    "iso:country":"US",
    "sg:address":"1501 W Sunset Ave",
    "sg:city":"Springdale",
    "sg:classifiers":[
        {
            "category":"Home & Garden",
            "subcategory":"Building Materials",
            "type":"Retail Goods"
        }
    ],
    "sg:phone":"+1 479 927 9563",
    "sg:postcode":"72764",
    "sg:province":"AR",
    "wof:name":"Wallpaper Images & Paint",
    "wof:placetype":"venue"
},
  "geometry": {"coordinates":[-94.14772499999999,36.174695],"type":"Point"}
}