{
  "type": "Feature",
  "properties": {
    "iso:country":"US",
    "sg:address":"480 S Saint Louis St",
    "sg:city":"Batesville",
    "sg:classifiers":[
        {
            "category":"Banks & Credit Unions",
            "subcategory":"Bank",
            "type":"Services"
        }
    ],
    "sg:phone":"+1 870 698 6300",
    "sg:postcode":"72501",
    "sg:province":"AR",
    "wof:name":"Citizens Bank",
    "wof:placetype":"venue"
},
  "geometry": {"coordinates":[-91.64086,35.775077],"type":"Point"}
}