{
  "type": "Feature",
  "properties": {
    "iso:country":"US",
    "sg:address":"2009 S Oak St",
    "sg:city":"Stuttgart",
    "sg:classifiers":[
        {
            "category":"Organizations",
            "subcategory":"Religious Organization",
            "type":"Services"
        }
    ],
    "sg:phone":"+1 870 672 8521",
    "sg:postcode":"72160",
    "sg:province":"AR",
    "sg:tags":[
        "church"
    ],
    "wof:name":"Lighthouse Church",
    "wof:placetype":"venue"
},
  "geometry": {"coordinates":[-91.53804599999999,34.482003],"type":"Point"}
}