{
  "type": "Feature",
  "properties": {
    "iso:country":"US",
    "sg:address":"13830 L C Hickman Rd",
    "sg:city":"Gravette",
    "sg:classifiers":[
        {
            "category":"Retail",
            "subcategory":"Repair Shop",
            "type":"Services"
        }
    ],
    "sg:phone":"+1 479 795 4082",
    "sg:postcode":"72736",
    "sg:province":"AR",
    "sg:tags":[
        "repairing",
        "lawn",
        "mower"
    ],
    "wof:name":"All-Small Engine Repair",
    "wof:placetype":"venue"
},
  "geometry": {"coordinates":[-94.33585600000001,36.352094],"type":"Point"}
}