{
  "type": "Feature",
  "properties": {
    "iso:country":"US",
    "sg:address":"8701 Fourche Dam Pike",
    "sg:city":"Little Rock",
    "sg:classifiers":[
        {
            "category":"Food & Beverages",
            "subcategory":"Groceries & Convenience Stores",
            "type":"Retail Goods"
        }
    ],
    "sg:phone":"+1 501 490 0113",
    "sg:postcode":"72206",
    "sg:province":"AR",
    "wof:name":"Max Mart",
    "wof:placetype":"venue"
},
  "geometry": {"coordinates":[-92.189828,34.707422],"type":"Point"}
}