{
  "type": "Feature",
  "properties": {
    "iso:country":"US",
    "sg:address":"1911 N West Ave",
    "sg:city":"El Dorado",
    "sg:classifiers":[
        {
            "category":"Cinema",
            "subcategory":"Movie Rental",
            "type":"Entertainment"
        }
    ],
    "sg:phone":"+1 870 863 7828",
    "sg:postcode":"71730",
    "sg:province":"AR",
    "sg:tags":[
        "video"
    ],
    "wof:name":"Reelplay Entertainment Inc",
    "wof:placetype":"venue"
},
  "geometry": {"coordinates":[-92.665397,33.232747],"type":"Point"}
}