{
  "type": "Feature",
  "properties": {
    "addr:full":"9188 Hwy 38 E Hughes AR 72348",
    "addr:housenumber":"9188",
    "addr:postcode":"72348",
    "addr:street":"Hwy 38 E Hughes",
    "iso:country":"US",
    "sg:address":"9188 Hwy 38 E",
    "sg:city":"Hughes",
    "sg:classifiers":[
        {
            "category":"Wholesale",
            "subcategory":"Machinery & Supplies",
            "type":"Manufacturing & Wholesale Goods"
        },
        {
            "category":"Autos & Motor Vehicles",
            "subcategory":"Auto Supplies",
            "type":"Retail Goods"
        }
    ],
    "sg:phone":"+1 870 339 3585",
    "sg:postcode":"72348",
    "sg:province":"AR",
    "sg:tags":[
        "farm",
        "equipment",
        "used",
        "tire"
    ],
    "wof:name":"Longhorn Equipment Corporation",
    "wof:placetype":"venue"
},
  "geometry": {"coordinates":[-90.519908,34.94862],"type":"Point"}
}