{
  "type": "Feature",
  "properties": {
    "addr:full":"1009 N Hervey St Hope AR 71801",
    "addr:housenumber":"1009",
    "addr:postcode":"71801",
    "addr:street":"N Hervey St",
    "iso:country":"US",
    "sg:address":"1009 N Hervey St",
    "sg:city":"Hope",
    "sg:classifiers":[
        {
            "category":"Shopping",
            "subcategory":"Tobacco",
            "type":"Retail Goods"
        }
    ],
    "sg:phone":"+1 870 777 0355",
    "sg:postcode":"71801",
    "sg:province":"AR",
    "sg:tags":[
        "cigarette",
        "cigar",
        "dealer"
    ],
    "wof:name":"Puff N Stuff",
    "wof:placetype":"venue"
},
  "geometry": {"coordinates":[-93.599954,33.675791],"type":"Point"}
}