{
  "type": "Feature",
  "properties": {
    "iso:country":"US",
    "sg:address":"4616 Highway 59 N",
    "sg:city":"Grove",
    "sg:classifiers":[
        {
            "category":"Autos & Motor Vehicles",
            "subcategory":"Boat Sales",
            "type":"Retail Goods"
        }
    ],
    "sg:phone":"+1 918 786 8800",
    "sg:postcode":"74344",
    "sg:province":"OK",
    "wof:name":"Arrowhead Boat Sales",
    "wof:placetype":"venue"
},
  "geometry": {"coordinates":[-94.77773000000001,36.519055],"type":"Point"}
}