{
  "type": "Feature",
  "properties": {
    "iso:country":"US",
    "sg:address":"2500 Zero St",
    "sg:city":"Fort Smith",
    "sg:classifiers":[
        {
            "category":"Restaurant",
            "type":"Food & Drink"
        }
    ],
    "sg:menulink":"http://www.allmenus.com/ar/upper/54557-eureka-pizza/menu/",
    "sg:phone":"+1 479 648 6767",
    "sg:postcode":"72901",
    "sg:province":"AR",
    "sg:tags":[
        "american",
        "pizza"
    ],
    "wof:name":"Eureka Pizza",
    "wof:placetype":"venue"
},
  "geometry": {"coordinates":[-94.408523,35.327763],"type":"Point"}
}