{
  "type": "Feature",
  "properties": {
    "addr:full":"890 Madison 6381 Huntsville AR 72740",
    "addr:housenumber":"890;6381",
    "addr:postcode":"72740",
    "iso:country":"US",
    "sg:address":"890 Madison 6381",
    "sg:city":"Huntsville",
    "sg:classifiers":[
        {
            "category":"Freight",
            "type":"Transportation"
        }
    ],
    "sg:phone":"+1 479 559 2783",
    "sg:postcode":"72740",
    "sg:province":"AR",
    "wof:name":"Trans America Logistics",
    "wof:placetype":"venue"
},
  "geometry": {"coordinates":[-93.81103400000001,35.971298],"type":"Point"}
}