{
  "type": "Feature",
  "properties": {
    "iso:country":"US",
    "sg:address":"503 E Lafayette St",
    "sg:city":"Fayetteville",
    "sg:classifiers":[
        {
            "category":"Professional",
            "subcategory":"Business Services",
            "type":"Services"
        }
    ],
    "sg:phone":"+1 479 442 8107",
    "sg:postcode":"72701",
    "sg:province":"AR",
    "wof:name":"Ferrell Enterprises",
    "wof:placetype":"venue"
},
  "geometry": {"coordinates":[-94.150195,36.068308],"type":"Point"}
}