{
  "type": "Feature",
  "properties": {
    "iso:country":"US",
    "sg:address":"8122 Highway 107 Ste C",
    "sg:city":"Sherwood",
    "sg:classifiers":[
        {
            "category":"Shopping",
            "subcategory":"Hobbies, Toys, & Games",
            "type":"Retail Goods"
        }
    ],
    "sg:phone":"+1 501 833 3423",
    "sg:postcode":"72120",
    "sg:province":"AR",
    "sg:tags":[
        "shop",
        "hobby",
        "model"
    ],
    "sg:website":"http://www.imaginegamesonline.com",
    "wof:name":"IMAGINE! Hobbies & Games",
    "wof:placetype":"venue"
},
  "geometry": {"coordinates":[-92.231275,34.828746],"type":"Point"}
}