{
  "type": "Feature",
  "properties": {
    "iso:country":"US",
    "sg:address":"9 Venado Ln",
    "sg:city":"Hot Springs Vlg",
    "sg:classifiers":[
        {
            "category":"Professional",
            "subcategory":"Business Services",
            "type":"Services"
        }
    ],
    "sg:phone":"+1 501 922 9199",
    "sg:postcode":"71909",
    "sg:province":"AR",
    "sg:tags":[
        "notary"
    ],
    "wof:name":"Gayle Coy",
    "wof:placetype":"venue"
},
  "geometry": {"coordinates":[-92.99559600000001,34.633376],"type":"Point"}
}