{
  "type": "Feature",
  "properties": {
    "iso:country":"US",
    "sg:address":"400 Madison St",
    "sg:city":"Judsonia",
    "sg:classifiers":[
        {
            "category":"Government",
            "subcategory":"Fire Station",
            "type":"Public Place"
        },
        {
            "category":"Building & Trades",
            "subcategory":"Cleaning & Sanitation",
            "type":"Services"
        }
    ],
    "sg:phone":"+1 501 305 4777",
    "sg:postcode":"72081",
    "sg:province":"AR",
    "sg:tags":[
        "recovery",
        "damage",
        "water",
        "restoration",
        "relief",
        "disaster"
    ],
    "wof:name":"Custom Carpet Care Incorporated",
    "wof:placetype":"venue"
},
  "geometry": {"coordinates":[-91.636431,35.271815],"type":"Point"}
}