{
  "type": "Feature",
  "properties": {
    "addr:full":"6813 Old Military Rd Subiaco AR 72865",
    "addr:housenumber":"6813",
    "addr:postcode":"72865",
    "addr:street":"Old Military Rd",
    "iso:country":"US",
    "sg:address":"6813 Old Military Rd",
    "sg:city":"Subiaco",
    "sg:classifiers":[
        {
            "category":"Farming",
            "subcategory":"Livestock Farm",
            "type":"Manufacturing & Wholesale Goods"
        }
    ],
    "sg:phone":"+1 479 934 4406",
    "sg:postcode":"72865",
    "sg:province":"AR",
    "wof:name":"Strobel Farm Inc",
    "wof:placetype":"venue"
},
  "geometry": {"coordinates":[-93.61851299999999,35.305667],"type":"Point"}
}