{
  "type": "Feature",
  "properties": {
    "iso:country":"US",
    "sg:address":"4000 Old Warren Rd",
    "sg:city":"Pine Bluff",
    "sg:classifiers":[
        {
            "category":"Social Services",
            "subcategory":"Child Care",
            "type":"Services"
        }
    ],
    "sg:phone":"+1 870 541 9092",
    "sg:postcode":"71603",
    "sg:province":"AR",
    "sg:tags":[
        "day"
    ],
    "wof:name":"Kid Factory",
    "wof:placetype":"venue"
},
  "geometry": {"coordinates":[-92.039375,34.182817],"type":"Point"}
}