{
  "type": "Feature",
  "properties": {
    "iso:country":"US",
    "sg:address":"1306 Military Rd",
    "sg:city":"Benton",
    "sg:classifiers":[
        {
            "category":"Real Estate",
            "subcategory":"Real Estate Agent",
            "type":"Services"
        }
    ],
    "sg:phone":"+1 501 315 1950",
    "sg:postcode":"72015",
    "sg:province":"AR",
    "wof:name":"Chuck Warford",
    "wof:placetype":"venue"
},
  "geometry": {"coordinates":[-92.577713,34.57615],"type":"Point"}
}