{
  "type": "Feature",
  "properties": {
    "addr:full":"109 W Main St Paragould AR 72450",
    "addr:housenumber":"109",
    "addr:postcode":"72450",
    "addr:street":"W Main St",
    "iso:country":"US",
    "sg:address":"109 W Main St",
    "sg:city":"Paragould",
    "sg:classifiers":[
        {
            "category":"Building & Trades",
            "subcategory":"Construction",
            "type":"Services"
        }
    ],
    "sg:phone":"+1 870 215 0505",
    "sg:postcode":"72450",
    "sg:province":"AR",
    "sg:tags":[
        "handyman"
    ],
    "wof:name":"House Doctor's Handyman Svc",
    "wof:placetype":"venue"
},
  "geometry": {"coordinates":[-90.487343,36.054655],"type":"Point"}
}