{
  "type": "Feature",
  "properties": {
    "iso:country":"US",
    "sg:address":"2300 Preston St",
    "sg:city":"Texarkana",
    "sg:classifiers":[
        {
            "category":"Education",
            "subcategory":"Special Training",
            "type":"Public Place"
        }
    ],
    "sg:phone":"+1 870 772 7054",
    "sg:postcode":"71854",
    "sg:province":"AR",
    "sg:tags":[
        "educational"
    ],
    "wof:name":"Southwest Arkansas",
    "wof:placetype":"venue"
},
  "geometry": {"coordinates":[-94.019096,33.427132],"type":"Point"}
}