{
  "type": "Feature",
  "properties": {
    "addr:full":"2217 S Caraway Rd Jonesboro AR 72404",
    "addr:housenumber":"2217",
    "addr:postcode":"72404",
    "addr:street":"S Caraway Rd",
    "iso:country":"US",
    "sg:address":"2217 S Caraway Rd",
    "sg:city":"Jonesboro",
    "sg:classifiers":[
        {
            "category":"Shopping",
            "subcategory":"Stationery & Office Supplies",
            "type":"Retail Goods"
        }
    ],
    "sg:phone":"+1 870 972 0144",
    "sg:postcode":"72404",
    "sg:province":"AR",
    "wof:name":"Sav-On Discount Office Supply",
    "wof:placetype":"venue"
},
  "geometry": {"coordinates":[-90.677975,35.818486],"type":"Point"}
}