{
  "type": "Feature",
  "properties": {
    "addr:full":"908 Holmes Rd Searcy AR 72143",
    "addr:housenumber":"908",
    "addr:postcode":"72143",
    "addr:street":"Holmes Rd",
    "iso:country":"US",
    "sg:address":"908 Holmes Rd",
    "sg:city":"Searcy",
    "sg:classifiers":[
        {
            "category":"Professional",
            "subcategory":"Art Services",
            "type":"Services"
        },
        {
            "category":"Professional",
            "subcategory":"Advertising",
            "type":"Services"
        },
        {
            "category":"Professional",
            "subcategory":"Business Services",
            "type":"Services"
        },
        {
            "category":"Professional",
            "subcategory":"Computer Services",
            "type":"Services"
        }
    ],
    "sg:phone":"+1 501 268 1771",
    "sg:postcode":"72143",
    "sg:province":"AR",
    "sg:tags":[
        "development",
        "publisher",
        "product",
        "graphic",
        "designers-industrial",
        "marketing",
        "agency",
        "commercial",
        "specialty",
        "designer",
        "design",
        "software",
        "developer"
    ],
    "sg:website":"http://www.lassocreative.com",
    "wof:name":"Think Advertising",
    "wof:placetype":"venue"
},
  "geometry": {"coordinates":[-91.745857,35.260923],"type":"Point"}
}