{
  "type": "Feature",
  "properties": {
    "iso:country":"US",
    "sg:address":"323 Marion Anderson Rd",
    "sg:city":"Hot Springs National Park",
    "sg:classifiers":[
        {
            "category":"Building & Trades",
            "subcategory":"Construction",
            "type":"Services"
        }
    ],
    "sg:phone":"+1 501 760 7490",
    "sg:postcode":"71913",
    "sg:province":"AR",
    "sg:tags":[
        "house"
    ],
    "wof:name":"Greenwhich Village",
    "wof:placetype":"venue"
},
  "geometry": {"coordinates":[-93.139161,34.4599],"type":"Point"}
}