{
  "type": "Feature",
  "properties": {
    "addr:full":"220 W Stephenson Ave Harrison AR 72601",
    "addr:housenumber":"220",
    "addr:postcode":"72601",
    "addr:street":"W Stephenson Ave",
    "iso:country":"US",
    "sg:address":"220 W Stephenson Ave",
    "sg:city":"Harrison",
    "sg:classifiers":[
        {
            "category":"Professional",
            "type":"Services"
        }
    ],
    "sg:phone":"+1 870 743 7460",
    "sg:postcode":"72601",
    "sg:province":"AR",
    "sg:tags":[
        "establishment"
    ],
    "wof:name":"C S Fairview",
    "wof:placetype":"venue"
},
  "geometry": {"coordinates":[-93.108879,36.229686],"type":"Point"}
}