{
  "type": "Feature",
  "properties": {
    "iso:country":"US",
    "sg:address":"4216 Clubhouse Dr",
    "sg:city":"Jonesboro",
    "sg:classifiers":[
        {
            "category":"Insurance",
            "subcategory":"Hazard Insurance",
            "type":"Services"
        }
    ],
    "sg:phone":"+1 870 931 3952",
    "sg:postcode":"72401",
    "sg:province":"AR",
    "sg:tags":[
        "commercial",
        "business"
    ],
    "wof:name":"Tri-J Insurance Inc",
    "wof:placetype":"venue"
},
  "geometry": {"coordinates":[-90.639261,35.885392],"type":"Point"}
}