{
  "type": "Feature",
  "properties": {
    "addr:full":"2400 E Main St El Dorado AR 71730",
    "addr:housenumber":"2400",
    "addr:postcode":"71730",
    "addr:street":"E Main St",
    "iso:country":"US",
    "sg:address":"2400 E Main St",
    "sg:city":"El Dorado",
    "sg:classifiers":[
        {
            "category":"Autos & Motor Vehicles",
            "subcategory":"Fuel & Gas Station",
            "type":"Retail Goods"
        }
    ],
    "sg:phone":"+1 870 863 5891",
    "sg:postcode":"71730",
    "sg:province":"AR",
    "sg:tags":[
        "grocery",
        "station",
        "gasoline"
    ],
    "wof:name":"BP",
    "wof:placetype":"venue"
},
  "geometry": {"coordinates":[-92.63676100000001,33.213543],"type":"Point"}
}