{
  "type": "Feature",
  "properties": {
    "addr:full":"3318 S 79th St Fort Smith AR 72903",
    "addr:housenumber":"3318",
    "addr:postcode":"72903",
    "addr:street":"S 79Th St",
    "iso:country":"US",
    "sg:address":"3318 S 79th St",
    "sg:city":"Fort Smith",
    "sg:classifiers":[
        {
            "category":"Organizations",
            "subcategory":"Religious Organization",
            "type":"Services"
        }
    ],
    "sg:phone":"+1 479 484 7854",
    "sg:postcode":"72903",
    "sg:province":"AR",
    "sg:tags":[
        "church"
    ],
    "wof:name":"God's House Of Prayer",
    "wof:placetype":"venue"
},
  "geometry": {"coordinates":[-94.345133,35.348265],"type":"Point"}
}