{
  "type": "Feature",
  "properties": {
    "iso:country":"US",
    "sg:address":"120 Rising Fast Rd",
    "sg:city":"Batesville",
    "sg:classifiers":[
        {
            "category":"Freight",
            "type":"Transportation"
        }
    ],
    "sg:phone":"+1 870 251 3003",
    "sg:postcode":"72501",
    "sg:province":"AR",
    "sg:tags":[
        "operator",
        "local",
        "trucking"
    ],
    "wof:name":"Truck Transport Inc",
    "wof:placetype":"venue"
},
  "geometry": {"coordinates":[-91.63711499999999,35.731277],"type":"Point"}
}