{
  "type": "Feature",
  "properties": {
    "iso:country":"US",
    "sg:address":"2980 Franklin Cir",
    "sg:city":"Conway",
    "sg:classifiers":[
        {
            "category":"Professional",
            "type":"Services"
        }
    ],
    "sg:phone":"+1 501 327 3824",
    "sg:postcode":"72034",
    "sg:province":"AR",
    "wof:name":"Shadowstorm Inc",
    "wof:placetype":"venue"
},
  "geometry": {"coordinates":[-92.474692,35.105334],"type":"Point"}
}