{
  "type": "Feature",
  "properties": {
    "iso:country":"US",
    "sg:address":"11436 Highway 49 N",
    "sg:city":"Marmaduke",
    "sg:classifiers":[
        {
            "category":"Professional",
            "subcategory":"Business Services",
            "type":"Services"
        },
        {
            "category":"Government",
            "subcategory":"Post Office",
            "type":"Public Place"
        }
    ],
    "sg:phone":"+1 800 275 8777",
    "sg:postcode":"72443",
    "sg:province":"AR",
    "sg:tags":[
        "mail",
        "shipping"
    ],
    "sg:website":"http://www.usps.com",
    "wof:name":"USPS - United States Post Office - Marmaduke Main Office",
    "wof:placetype":"venue"
},
  "geometry": {"coordinates":[-90.330907,36.229439],"type":"Point"}
}