{
  "type": "Feature",
  "properties": {
    "addr:full":"501 S Jackson Ave El Dorado AR 71730",
    "addr:housenumber":"501",
    "addr:postcode":"71730",
    "addr:street":"S Jackson Ave",
    "iso:country":"US",
    "sg:address":"501 S Jackson Ave",
    "sg:city":"El Dorado",
    "sg:classifiers":[
        {
            "category":"Manufacturing",
            "subcategory":"Tools & Machinery",
            "type":"Manufacturing & Wholesale Goods"
        }
    ],
    "sg:phone":"+1 870 862 4288",
    "sg:postcode":"71730",
    "sg:province":"AR",
    "sg:tags":[
        "machine",
        "shop"
    ],
    "wof:name":"Spencer Iron Works Inc",
    "wof:placetype":"venue"
},
  "geometry": {"coordinates":[-92.661165,33.207371],"type":"Point"}
}