{
  "type": "Feature",
  "properties": {
    "addr:full":"104 S Thompson St Springdale AR 72764",
    "addr:housenumber":"104",
    "addr:postcode":"72764",
    "addr:street":"S Thompson St",
    "iso:country":"US",
    "sg:address":"104 S Thompson St",
    "sg:city":"Springdale",
    "sg:classifiers":[
        {
            "category":"Home & Garden",
            "subcategory":"Building Materials",
            "type":"Retail Goods"
        }
    ],
    "sg:phone":"+1 479 750 0711",
    "sg:postcode":"72764",
    "sg:province":"AR",
    "sg:tags":[
        "plumbing",
        "fixture",
        "supply"
    ],
    "wof:name":"Locke Supply Co",
    "wof:placetype":"venue"
},
  "geometry": {"coordinates":[-94.138621,36.184394],"type":"Point"}
}