{
  "type": "Feature",
  "properties": {
    "iso:country":"US",
    "sg:address":"715 N Beech St",
    "sg:city":"N Little Rock",
    "sg:classifiers":[
        {
            "category":"Personal",
            "subcategory":"Barber",
            "type":"Services"
        }
    ],
    "sg:phone":"+1 501 372 9638",
    "sg:postcode":"72114",
    "sg:province":"AR",
    "sg:tags":[
        "shop"
    ],
    "wof:name":"Garden Towers Barber Shop",
    "wof:placetype":"venue"
},
  "geometry": {"coordinates":[-92.253157,34.760499],"type":"Point"}
}