{
  "type": "Feature",
  "properties": {
    "iso:country":"US",
    "sg:address":"2454 Highway 79 W",
    "sg:city":"Marianna",
    "sg:classifiers":[
        {
            "category":"Farming",
            "subcategory":"Farm",
            "type":"Manufacturing & Wholesale Goods"
        }
    ],
    "sg:phone":"+1 870 295 6945",
    "sg:postcode":"72360",
    "sg:province":"AR",
    "wof:name":"Russell Farms",
    "wof:placetype":"venue"
},
  "geometry": {"coordinates":[-90.82821199999999,34.77466],"type":"Point"}
}