{
  "type": "Feature",
  "properties": {
    "iso:country":"US",
    "sg:address":"105 E Crandall Ave",
    "sg:city":"Harrison",
    "sg:classifiers":[
        {
            "category":"Organizations",
            "subcategory":"Non-profit Organization",
            "type":"Services"
        }
    ],
    "sg:phone":"+1 870 741 9406",
    "sg:postcode":"72601",
    "sg:province":"AR",
    "wof:name":"Ozark Opportunities Inc",
    "wof:placetype":"venue"
},
  "geometry": {"coordinates":[-93.107036,36.238286],"type":"Point"}
}