{
  "type": "Feature",
  "properties": {
    "iso:country":"US",
    "sg:address":"5819 Rogers Ave",
    "sg:city":"Fort Smith",
    "sg:classifiers":[
        {
            "category":"Shopping",
            "subcategory":"Computers & Home Electronics",
            "type":"Retail Goods"
        }
    ],
    "sg:phone":"+1 479 452 9988",
    "sg:postcode":"72903",
    "sg:province":"AR",
    "sg:tags":[
        "equipment",
        "dealer"
    ],
    "wof:name":"JPC Computer Ctr",
    "wof:placetype":"venue"
},
  "geometry": {"coordinates":[-94.36667,35.360391],"type":"Point"}
}