{
  "type": "Feature",
  "properties": {
    "addr:full":"2701 Crestwood Rd N Little Rock AR 72116",
    "addr:housenumber":"2701",
    "addr:postcode":"72116",
    "addr:street":"Crestwood Rd N",
    "iso:country":"US",
    "sg:address":"2701 Crestwood Rd",
    "sg:city":"N Little Rock",
    "sg:classifiers":[
        {
            "category":"Real Estate",
            "subcategory":"Real Estate Agent",
            "type":"Services"
        }
    ],
    "sg:phone":"+1 501 753 0774",
    "sg:postcode":"72116",
    "sg:province":"AR",
    "wof:name":"Lakewood Property Owners Assn",
    "wof:placetype":"venue"
},
  "geometry": {"coordinates":[-92.236504,34.79981],"type":"Point"}
}