{
  "type": "Feature",
  "properties": {
    "iso:country":"US",
    "sg:address":"8695 Old Military Rd",
    "sg:city":"Subiaco",
    "sg:classifiers":[
        {
            "category":"Retail",
            "subcategory":"Repair Shop",
            "type":"Services"
        }
    ],
    "sg:phone":"+1 479 934 4465",
    "sg:postcode":"72865",
    "sg:province":"AR",
    "wof:name":"B F Radio Sales",
    "wof:placetype":"venue"
},
  "geometry": {"coordinates":[-93.585186,35.304744],"type":"Point"}
}