{
  "type": "Feature",
  "properties": {
    "addr:full":"303 W 8th Ave Crossett AR 71635",
    "addr:housenumber":"303",
    "addr:postcode":"71635",
    "addr:street":"W 8Th Ave",
    "iso:country":"US",
    "sg:address":"303 W 8th Ave",
    "sg:city":"Crossett",
    "sg:classifiers":[
        {
            "category":"Social Services",
            "subcategory":"Child Care",
            "type":"Services"
        }
    ],
    "sg:phone":"+1 870 304 3178",
    "sg:postcode":"71635",
    "sg:province":"AR",
    "sg:tags":[
        "day"
    ],
    "wof:name":"Brite Beginning",
    "wof:placetype":"venue"
},
  "geometry": {"coordinates":[-91.964088,33.125369],"type":"Point"}
}