{
  "type": "Feature",
  "properties": {
    "addr:full":"180 Wakefield Rd Nashville AR 71852",
    "addr:housenumber":"180",
    "addr:postcode":"71852",
    "addr:street":"Wakefield Rd",
    "iso:country":"US",
    "sg:address":"180 Wakefield Rd",
    "sg:city":"Nashville",
    "sg:classifiers":[
        {
            "category":"Retail",
            "subcategory":"Auto Repair",
            "type":"Services"
        }
    ],
    "sg:phone":"+1 870 845 5251",
    "sg:postcode":"71852",
    "sg:province":"AR",
    "sg:tags":[
        "muffler",
        "exhaust",
        "system"
    ],
    "wof:name":"Larry's United Muffler Shop",
    "wof:placetype":"venue"
},
  "geometry": {"coordinates":[-93.906796,33.949502],"type":"Point"}
}