{
  "type": "Feature",
  "properties": {
    "iso:country":"US",
    "sg:address":"827 Atalanta Dr",
    "sg:city":"Rogers",
    "sg:classifiers":[
        {
            "category":"Banks & Credit Unions",
            "subcategory":"Investment Brokerage",
            "type":"Services"
        }
    ],
    "sg:phone":"+1 479 636 5034",
    "sg:postcode":"72756",
    "sg:province":"AR",
    "sg:tags":[
        "trust"
    ],
    "wof:name":"Bradford Family Trust",
    "wof:placetype":"venue"
},
  "geometry": {"coordinates":[-94.10167800000001,36.33934],"type":"Point"}
}