{
  "type": "Feature",
  "properties": {
    "iso:country":"US",
    "sg:address":"111 N Freeman St",
    "sg:city":"Dermott",
    "sg:classifiers":[
        {
            "category":"Government",
            "subcategory":"Office",
            "type":"Public Place"
        }
    ],
    "sg:phone":"+1 870 538 3253",
    "sg:postcode":"71638",
    "sg:province":"AR",
    "wof:name":"Hot Check Office",
    "wof:placetype":"venue"
},
  "geometry": {"coordinates":[-91.434634,33.52721],"type":"Point"}
}