{
  "type": "Feature",
  "properties": {
    "addr:full":"1537 Co Rd 210 Eureka Springs AR 72632",
    "addr:housenumber":"1537;210",
    "addr:postcode":"72632",
    "addr:street":"Co Rd",
    "iso:country":"US",
    "sg:address":"1537 Co Rd 210",
    "sg:city":"Eureka Springs",
    "sg:classifiers":[
        {
            "category":"Professional",
            "type":"Services"
        }
    ],
    "sg:phone":"+1 479 253 2362",
    "sg:postcode":"72632",
    "sg:province":"AR",
    "sg:tags":[
        "establishment"
    ],
    "wof:name":"Preferred Systems Support",
    "wof:placetype":"venue"
},
  "geometry": {"coordinates":[-93.80176,36.448551],"type":"Point"}
}