{
  "type": "Feature",
  "properties": {
    "iso:country":"US",
    "sg:address":"15 Butterfield Ln",
    "sg:city":"Little Rock",
    "sg:classifiers":[
        {
            "category":"Professional",
            "subcategory":"Art Services",
            "type":"Services"
        }
    ],
    "sg:phone":"+1 501 224 0692",
    "sg:postcode":"72223",
    "sg:province":"AR",
    "sg:tags":[
        "photography",
        "commercial"
    ],
    "wof:name":"Matt Bradley Photography",
    "wof:placetype":"venue"
},
  "geometry": {"coordinates":[-92.412028,34.791562],"type":"Point"}
}