{
  "type": "Feature",
  "properties": {
    "iso:country":"US",
    "sg:address":"1 Allied Dr",
    "sg:city":"Little Rock",
    "sg:classifiers":[
        {
            "category":"Utilities",
            "subcategory":"Telephone",
            "type":"Services"
        }
    ],
    "sg:phone":"+1 501 905 5247",
    "sg:postcode":"72202",
    "sg:province":"AR",
    "sg:tags":[
        "communications"
    ],
    "wof:name":"Roaming",
    "wof:placetype":"venue"
},
  "geometry": {"coordinates":[-92.30386799999999,34.762385],"type":"Point"}
}