{
  "type": "Feature",
  "properties": {
    "addr:full":"1087 State Hwy 276 Stuttgart AR 72160",
    "addr:housenumber":"1087",
    "addr:postcode":"72160",
    "addr:street":"State Hwy 276",
    "iso:country":"US",
    "sg:address":"1087 State Hwy 276",
    "sg:city":"Stuttgart",
    "sg:classifiers":[
        {
            "category":"Restaurant",
            "type":"Food & Drink"
        }
    ],
    "sg:phone":"+1 870 946 1299",
    "sg:postcode":"72160",
    "sg:province":"AR",
    "sg:tags":[
        "eating"
    ],
    "wof:name":"Virginia's Cafe",
    "wof:placetype":"venue"
},
  "geometry": {"coordinates":[-91.512348,34.222684],"type":"Point"}
}