{
  "type": "Feature",
  "properties": {
    "addr:full":"1011 Burke Ave Jonesboro AR 72401",
    "addr:housenumber":"1011",
    "addr:postcode":"72401",
    "addr:street":"Burke Ave",
    "iso:country":"US",
    "sg:address":"1011 Burke Ave",
    "sg:city":"Jonesboro",
    "sg:classifiers":[
        {
            "category":"Building & Trades",
            "subcategory":"Pest Control",
            "type":"Services"
        }
    ],
    "sg:phone":"+1 870 932 1361",
    "sg:postcode":"72401",
    "sg:province":"AR",
    "wof:name":"Jonesboro Termite Co",
    "wof:placetype":"venue"
},
  "geometry": {"coordinates":[-90.717235,35.841746],"type":"Point"}
}