{
  "type": "Feature",
  "properties": {
    "addr:full":"326 Dillard Ave Forrest City AR 72335",
    "addr:housenumber":"326",
    "addr:postcode":"72335",
    "addr:street":"Dillard Ave",
    "iso:country":"US",
    "sg:address":"326 Dillard Ave",
    "sg:city":"Forrest City",
    "sg:classifiers":[
        {
            "category":"Professional",
            "subcategory":"Lawyer & Legal Services",
            "type":"Services"
        }
    ],
    "sg:phone":"+1 870 633 6850",
    "sg:postcode":"72335",
    "sg:province":"AR",
    "sg:tags":[
        "attorney"
    ],
    "wof:name":"Ann B Hudson Pa Attorney",
    "wof:placetype":"venue"
},
  "geometry": {"coordinates":[-90.78713,35.011567],"type":"Point"}
}