{
  "type": "Feature",
  "properties": {
    "addr:full":"5214 Village Pkwy Rogers AR 72758",
    "addr:housenumber":"5214",
    "addr:postcode":"72758",
    "addr:street":"Village Pkwy",
    "iso:country":"US",
    "sg:address":"5214 Village Pkwy",
    "sg:city":"Rogers",
    "sg:classifiers":[
        {
            "category":"Personal",
            "type":"Services"
        }
    ],
    "sg:phone":"+1 479 254 0755",
    "sg:postcode":"72758",
    "sg:province":"AR",
    "wof:name":"Healthy Insprtions Weight Loss",
    "wof:placetype":"venue"
},
  "geometry": {"coordinates":[-94.187029,36.317483],"type":"Point"}
}