{
  "type": "Feature",
  "properties": {
    "iso:country":"US",
    "sg:address":"1901 Wheeler Ave",
    "sg:city":"Fort Smith",
    "sg:classifiers":[
        {
            "category":"Manufacturing",
            "subcategory":"Furniture",
            "type":"Manufacturing & Wholesale Goods"
        }
    ],
    "sg:phone":"+1 479 785 2351",
    "sg:postcode":"72901",
    "sg:province":"AR",
    "sg:tags":[
        "metal"
    ],
    "sg:website":"www.lloydflanders.com",
    "wof:name":"Flanders Industries Inc",
    "wof:placetype":"venue"
},
  "geometry": {"coordinates":[-94.426016,35.366586],"type":"Point"}
}