{
  "type": "Feature",
  "properties": {
    "iso:country":"US",
    "sg:address":"1811 Alonzo St",
    "sg:city":"Jonesboro",
    "sg:classifiers":[
        {
            "category":"Retail",
            "subcategory":"Funeral Services",
            "type":"Services"
        }
    ],
    "sg:phone":"+1 870 935 8320",
    "sg:postcode":"72401",
    "sg:province":"AR",
    "sg:tags":[
        "director"
    ],
    "wof:name":"Baker Stevens & Wright",
    "wof:placetype":"venue"
},
  "geometry": {"coordinates":[-90.715923,35.824163],"type":"Point"}
}