{
  "type": "Feature",
  "properties": {
    "iso:country":"US",
    "sg:address":"1401 W 6th St",
    "sg:city":"Little Rock",
    "sg:classifiers":[
        {
            "category":"Professional",
            "type":"Services"
        }
    ],
    "sg:phone":"+1 501 374 9256",
    "sg:postcode":"72201",
    "sg:province":"AR",
    "sg:tags":[
        "establishment"
    ],
    "wof:name":"Accutype",
    "wof:placetype":"venue"
},
  "geometry": {"coordinates":[-92.287351,34.745334],"type":"Point"}
}