{
  "type": "Feature",
  "properties": {
    "iso:country":"US",
    "sg:address":"60 Arias Way",
    "sg:city":"Hot Springs National",
    "sg:classifiers":[
        {
            "category":"Real Estate",
            "subcategory":"Real Estate Agent",
            "type":"Services"
        }
    ],
    "sg:phone":"+1 501 922 0229",
    "sg:postcode":"71909",
    "sg:province":"AR",
    "wof:name":"Shirley Koonce Co",
    "wof:placetype":"venue"
},
  "geometry": {"coordinates":[-92.991989,34.676152],"type":"Point"}
}