{
  "type": "Feature",
  "properties": {
    "iso:country":"US",
    "sg:address":"11048 Orpha Rd",
    "sg:city":"Farmington",
    "sg:classifiers":[
        {
            "category":"Shopping",
            "subcategory":"Computers & Home Electronics",
            "type":"Retail Goods"
        }
    ],
    "sg:phone":"+1 479 236 1007",
    "sg:postcode":"72730",
    "sg:province":"AR",
    "wof:name":"Cherokee Entertainment",
    "wof:placetype":"venue"
},
  "geometry": {"coordinates":[-94.282445,36.005264],"type":"Point"}
}