{
  "type": "Feature",
  "properties": {
    "addr:full":"244 Sfc 704 Forrest City AR 72335",
    "addr:housenumber":"244;704",
    "addr:postcode":"72335",
    "addr:street":"Sfc",
    "iso:country":"US",
    "sg:address":"244 Sfc 704",
    "sg:city":"Forrest City",
    "sg:classifiers":[
        {
            "category":"Building & Trades",
            "subcategory":"Electrical",
            "type":"Services"
        }
    ],
    "sg:phone":"+1 870 633 4501",
    "sg:postcode":"72335",
    "sg:province":"AR",
    "sg:tags":[
        "electrical",
        "contractor"
    ],
    "wof:name":"Cook S Electric",
    "wof:placetype":"venue"
},
  "geometry": {"coordinates":[-90.757158,34.991087],"type":"Point"}
}