{
  "type": "Feature",
  "properties": {
    "iso:country":"US",
    "sg:address":"3970 Park Ave",
    "sg:city":"Hot Springs",
    "sg:classifiers":[
        {
            "category":"Shopping",
            "type":"Retail Goods"
        }
    ],
    "sg:phone":"+1 501 318 1393",
    "sg:postcode":"71901",
    "sg:province":"AR",
    "sg:tags":[
        "coin",
        "dealer",
        "supply"
    ],
    "wof:name":"Anthony's Coins & Cutlery",
    "wof:placetype":"venue"
},
  "geometry": {"coordinates":[-92.995371,34.562912],"type":"Point"}
}