{
  "type": "Feature",
  "properties": {
    "iso:country":"US",
    "sg:address":"2475 Hwy 62 W",
    "sg:city":"Pocahontas",
    "sg:classifiers":[
        {
            "category":"Autos & Motor Vehicles",
            "subcategory":"Auto Supplies",
            "type":"Retail Goods"
        }
    ],
    "sg:phone":"+1 870 892 4646",
    "sg:postcode":"72455",
    "sg:province":"AR",
    "wof:name":"Baltz Auto Supply",
    "wof:placetype":"venue"
},
  "geometry": {"coordinates":[-90.992005,36.257631],"type":"Point"}
}