{
  "type": "Feature",
  "properties": {
    "iso:country":"US",
    "sg:address":"3832 Central Ave",
    "sg:city":"Hot Springs",
    "sg:classifiers":[
        {
            "category":"Banks & Credit Unions",
            "subcategory":"Bank",
            "type":"Services"
        }
    ],
    "sg:phone":"+1 501 525 1114",
    "sg:postcode":"71913",
    "sg:province":"AR",
    "wof:name":"Elk Horn Bank",
    "wof:placetype":"venue"
},
  "geometry": {"coordinates":[-93.061759,34.462112],"type":"Point"}
}