{
  "type": "Feature",
  "properties": {
    "iso:country":"US",
    "sg:address":"308 SE 18th St",
    "sg:city":"Bentonville",
    "sg:classifiers":[
        {
            "category":"Food & Beverages",
            "subcategory":"Groceries & Convenience Stores",
            "type":"Retail Goods"
        }
    ],
    "sg:phone":"+1 479 254 3863",
    "sg:postcode":"72712",
    "sg:province":"AR",
    "sg:tags":[
        "product"
    ],
    "wof:name":"Ruiz Food Products Inc",
    "wof:placetype":"venue"
},
  "geometry": {"coordinates":[-94.205806,36.351695],"type":"Point"}
}