{
  "type": "Feature",
  "properties": {
    "addr:full":"19492 US Hwy 62 W Holiday Island AR 72631",
    "addr:postcode":"19492;72631",
    "addr:street":"Us Hwy 62 W",
    "iso:country":"US",
    "sg:address":"19492 US Hwy 62 W",
    "sg:city":"Holiday Island",
    "sg:classifiers":[
        {
            "category":"Home & Garden",
            "subcategory":"Building Materials",
            "type":"Retail Goods"
        }
    ],
    "sg:phone":"+1 479 253 7397",
    "sg:postcode":"72631",
    "sg:province":"AR",
    "sg:tags":[
        "glass",
        "window",
        "plate"
    ],
    "wof:name":"Holiday Island Glass",
    "wof:placetype":"venue"
},
  "geometry": {"coordinates":[-93.830827,36.464223],"type":"Point"}
}