{
  "type": "Feature",
  "properties": {
    "addr:full":"3406 Willow Rd Jonesboro AR 72404",
    "addr:housenumber":"3406",
    "addr:postcode":"72404",
    "addr:street":"Willow Rd",
    "iso:country":"US",
    "sg:address":"3406 Willow Rd",
    "sg:city":"Jonesboro",
    "sg:classifiers":[
        {
            "category":"Wholesale",
            "subcategory":"Construction Materials",
            "type":"Manufacturing & Wholesale Goods"
        }
    ],
    "sg:phone":"+1 870 972 5420",
    "sg:postcode":"72404",
    "sg:province":"AR",
    "sg:tags":[
        "siding"
    ],
    "wof:name":"Norandex Inc",
    "wof:placetype":"venue"
},
  "geometry": {"coordinates":[-90.651354,35.801366],"type":"Point"}
}