{
  "type": "Feature",
  "properties": {
    "iso:country":"US",
    "sg:address":"663 Oakland Ave Ste A",
    "sg:city":"Helena",
    "sg:classifiers":[
        {
            "category":"Health Services",
            "subcategory":"Dentist",
            "type":"Services"
        }
    ],
    "sg:phone":"+1 870 572 6575",
    "sg:postcode":"72342",
    "sg:province":"AR",
    "wof:name":"Twin Cities Dental Clinic",
    "wof:placetype":"venue"
},
  "geometry": {"coordinates":[-90.626959,34.541279],"type":"Point"}
}