{
  "type": "Feature",
  "properties": {
    "iso:country":"US",
    "sg:address":"1819 S 8th St",
    "sg:city":"Rogers",
    "sg:classifiers":[
        {
            "category":"Autos & Motor Vehicles",
            "subcategory":"Fuel & Gas Station",
            "type":"Retail Goods"
        }
    ],
    "sg:phone":"+1 479 631 1474",
    "sg:postcode":"72756",
    "sg:province":"AR",
    "sg:tags":[
        "oil"
    ],
    "wof:name":"Murphy Oil USA Inc",
    "wof:placetype":"venue"
},
  "geometry": {"coordinates":[-94.12632600000001,36.311666],"type":"Point"}
}