{
  "type": "Feature",
  "properties": {
    "addr:full":"8105 Zeuber Rd Little Rock AR 72206",
    "addr:housenumber":"8105",
    "addr:postcode":"72206",
    "addr:street":"Zeuber Rd",
    "iso:country":"US",
    "sg:address":"8105 Zeuber Rd",
    "sg:city":"Little Rock",
    "sg:classifiers":[
        {
            "category":"Freight",
            "type":"Transportation"
        }
    ],
    "sg:phone":"+1 501 490 2091",
    "sg:postcode":"72206",
    "sg:province":"AR",
    "sg:tags":[
        "operator",
        "trucking"
    ],
    "sg:website":"www.centralfreight.com",
    "wof:name":"Central Freight Lines Inc",
    "wof:placetype":"venue"
},
  "geometry": {"coordinates":[-92.19332199999999,34.697695],"type":"Point"}
}