{
  "type": "Feature",
  "properties": {
    "iso:country":"US",
    "sg:address":"207 SW A St",
    "sg:city":"Bentonville",
    "sg:classifiers":[
        {
            "category":"Professional",
            "type":"Services"
        }
    ],
    "sg:phone":"+1 479 464 4939",
    "sg:postcode":"72712",
    "sg:province":"AR",
    "sg:tags":[
        "establishment"
    ],
    "wof:name":"Clinicare",
    "wof:placetype":"venue"
},
  "geometry": {"coordinates":[-94.210214,36.369684],"type":"Point"}
}