{
  "type": "Feature",
  "properties": {
    "addr:full":"2800 S Reynolds Rd Bryant AR 72022",
    "addr:housenumber":"2800",
    "addr:postcode":"72022",
    "addr:street":"S Reynolds Rd",
    "iso:country":"US",
    "sg:address":"2800 S Reynolds Rd",
    "sg:city":"Bryant",
    "sg:classifiers":[
        {
            "category":"Professional",
            "subcategory":"Business Services",
            "type":"Services"
        }
    ],
    "sg:phone":"+1 501 557 5667",
    "sg:postcode":"72022",
    "sg:province":"AR",
    "sg:tags":[
        "labeling"
    ],
    "sg:website":"www.arkansaslabeling.com",
    "wof:name":"Arkansas Labeling Inc",
    "wof:placetype":"venue"
},
  "geometry": {"coordinates":[-92.495653,34.568965],"type":"Point"}
}