{
  "type": "Feature",
  "properties": {
    "iso:country":"US",
    "sg:address":"902 S Walton Blvd",
    "sg:city":"Bentonville",
    "sg:classifiers":[
        {
            "category":"Professional",
            "type":"Services"
        }
    ],
    "sg:phone":"+1 479 273 5444",
    "sg:postcode":"72712",
    "sg:province":"AR",
    "sg:tags":[
        "establishment"
    ],
    "wof:name":"Lifetime Hoan Corp",
    "wof:placetype":"venue"
},
  "geometry": {"coordinates":[-94.217332,36.361762],"type":"Point"}
}