{
  "type": "Feature",
  "properties": {
    "iso:country":"US",
    "sg:address":"805 W Semmes Ave",
    "sg:city":"Osceola",
    "sg:classifiers":[
        {
            "category":"Education",
            "subcategory":"Special Training",
            "type":"Public Place"
        }
    ],
    "sg:phone":"+1 870 563 6845",
    "sg:postcode":"72370",
    "sg:province":"AR",
    "sg:tags":[
        "publishing"
    ],
    "wof:name":"Larry Wamble",
    "wof:placetype":"venue"
},
  "geometry": {"coordinates":[-89.978762,35.704898],"type":"Point"}
}