{
  "type": "Feature",
  "properties": {
    "iso:country":"US",
    "sg:address":"108 N Washington Ave",
    "sg:city":"El Dorado",
    "sg:classifiers":[
        {
            "category":"Shopping",
            "subcategory":"Used Merchandise",
            "type":"Retail Goods"
        }
    ],
    "sg:phone":"+1 870 862 4743",
    "sg:postcode":"71730",
    "sg:province":"AR",
    "sg:tags":[
        "shop",
        "consignment"
    ],
    "wof:name":"Upscale Resale",
    "wof:placetype":"venue"
},
  "geometry": {"coordinates":[-92.66381699999999,33.212517],"type":"Point"}
}