{
  "type": "Feature",
  "properties": {
    "addr:full":"10608 Dundee Ct Fort Smith AR 72908",
    "addr:housenumber":"10608",
    "addr:postcode":"72908",
    "addr:street":"Dundee Ct",
    "iso:country":"US",
    "sg:address":"10608 Dundee Ct",
    "sg:city":"Fort Smith",
    "sg:classifiers":[
        {
            "category":"Communications",
            "type":"Services"
        }
    ],
    "sg:phone":"+1 479 648 1612",
    "sg:postcode":"72908",
    "sg:province":"AR",
    "sg:tags":[
        "communication"
    ],
    "wof:name":"B&S Communicatons LLC",
    "wof:placetype":"venue"
},
  "geometry": {"coordinates":[-94.410488,35.284274],"type":"Point"}
}