{
  "type": "Feature",
  "properties": {
    "addr:full":"803 Malcolm Ave Newport AR 72112",
    "addr:housenumber":"803",
    "addr:postcode":"72112",
    "addr:street":"Malcolm Ave",
    "iso:country":"US",
    "sg:address":"803 Malcolm Ave",
    "sg:city":"Newport",
    "sg:classifiers":[
        {
            "category":"Professional",
            "subcategory":"Employment Agencies",
            "type":"Services"
        }
    ],
    "sg:phone":"+1 870 523 2464",
    "sg:postcode":"72112",
    "sg:province":"AR",
    "sg:tags":[
        "help",
        "supply"
    ],
    "wof:name":"Schwegman Office Supply",
    "wof:placetype":"venue"
},
  "geometry": {"coordinates":[-91.270128,35.606424],"type":"Point"}
}