{
  "type": "Feature",
  "properties": {
    "iso:country":"US",
    "sg:address":"125 Sears Ln",
    "sg:city":"Helena",
    "sg:classifiers":[
        {
            "category":"Autos & Motor Vehicles",
            "subcategory":"Auto Supplies",
            "type":"Retail Goods"
        },
        {
            "category":"Manufacturing",
            "subcategory":"Motor Vehicles & Parts",
            "type":"Manufacturing & Wholesale Goods"
        },
        {
            "category":"Building & Trades",
            "subcategory":"Electrical",
            "type":"Services"
        }
    ],
    "sg:phone":"+1 870 338 3364",
    "sg:postcode":"72342",
    "sg:province":"AR",
    "sg:tags":[
        "electrician",
        "electric",
        "motors-used"
    ],
    "wof:name":"M & W Electric",
    "wof:placetype":"venue"
},
  "geometry": {"coordinates":[-90.615693,34.500655],"type":"Point"}
}