{
  "type": "Feature",
  "properties": {
    "iso:country":"US",
    "sg:address":"14982 Highway 396",
    "sg:city":"Omaha",
    "sg:classifiers":[
        {
            "category":"Farming",
            "subcategory":"Farm",
            "type":"Manufacturing & Wholesale Goods"
        }
    ],
    "sg:phone":"+1 870 426 3414",
    "sg:postcode":"72662",
    "sg:province":"AR",
    "wof:name":"Johnny & Mindy Arnold",
    "wof:placetype":"venue"
},
  "geometry": {"coordinates":[-93.278226,36.405553],"type":"Point"}
}