{
  "type": "Feature",
  "properties": {
    "addr:full":"218 Leach St Hot Springs National Park AR 71913",
    "addr:housenumber":"218",
    "addr:postcode":"71913",
    "addr:street":"Leach St;Park",
    "iso:country":"US",
    "sg:address":"218 Leach St",
    "sg:city":"Hot Springs National Park",
    "sg:classifiers":[
        {
            "category":"Building & Trades",
            "subcategory":"Construction",
            "type":"Services"
        }
    ],
    "sg:phone":"+1 501 624 4674",
    "sg:postcode":"71913",
    "sg:province":"AR",
    "sg:tags":[
        "hanging",
        "contractor"
    ],
    "wof:name":"Vicki Spivey Wallpaperhanging",
    "wof:placetype":"venue"
},
  "geometry": {"coordinates":[-93.06115800000001,34.489407],"type":"Point"}
}