{
  "type": "Feature",
  "properties": {
    "iso:country":"US",
    "sg:address":"1124 Leawood St",
    "sg:city":"Blytheville",
    "sg:classifiers":[
        {
            "category":"Professional",
            "subcategory":"Lawyer & Legal Services",
            "type":"Services"
        }
    ],
    "sg:phone":"+1 870 763 1043",
    "sg:postcode":"72315",
    "sg:province":"AR",
    "sg:tags":[
        "attorney"
    ],
    "wof:name":"Sanders, Kevin B",
    "wof:placetype":"venue"
},
  "geometry": {"coordinates":[-89.889099,35.937399],"type":"Point"}
}