{
  "type": "Feature",
  "properties": {
    "iso:country":"US",
    "sg:address":"1665 N College Ave",
    "sg:city":"Fayetteville",
    "sg:classifiers":[
        {
            "category":"Sports & Exercise",
            "subcategory":"Gym",
            "type":"Entertainment"
        }
    ],
    "sg:phone":"+1 479 582 0306",
    "sg:postcode":"72703",
    "sg:province":"AR",
    "sg:tags":[
        "fitness",
        "physical",
        "facility"
    ],
    "wof:name":"N W A Fitness & Barbell Club",
    "wof:placetype":"venue"
},
  "geometry": {"coordinates":[-94.156572,36.081601],"type":"Point"}
}