{
  "type": "Feature",
  "properties": {
    "addr:full":"1101 Oak St Conway AR 72032",
    "addr:housenumber":"1101",
    "addr:postcode":"72032",
    "addr:street":"Oak St",
    "iso:country":"US",
    "sg:address":"1101 Oak St",
    "sg:city":"Conway",
    "sg:classifiers":[
        {
            "category":"Shopping",
            "subcategory":"Clothing, Apparel, & Fashions",
            "type":"Retail Goods"
        }
    ],
    "sg:phone":"+1 501 764 4700",
    "sg:postcode":"72032",
    "sg:province":"AR",
    "wof:name":"Trinkets",
    "wof:placetype":"venue"
},
  "geometry": {"coordinates":[-92.43972599999999,35.090997],"type":"Point"}
}