{
  "type": "Feature",
  "properties": {
    "iso:country":"US",
    "sg:address":"175 Ash St",
    "sg:city":"Knobel",
    "sg:classifiers":[
        {
            "category":"Retail",
            "subcategory":"Auto Repair",
            "type":"Services"
        }
    ],
    "sg:phone":"+1 870 259 3528",
    "sg:postcode":"72435",
    "sg:province":"AR",
    "wof:name":"Bill Forbes",
    "wof:placetype":"venue"
},
  "geometry": {"coordinates":[-90.604398,36.315386],"type":"Point"}
}