{
  "type": "Feature",
  "properties": {
    "addr:full":"204 Whispering Hill Hot Springs AR 71901",
    "addr:housenumber":"204",
    "addr:postcode":"71901",
    "addr:street":"Whispering Hill",
    "iso:country":"US",
    "sg:address":"204 Whispering Hill",
    "sg:city":"Hot Springs",
    "sg:classifiers":[
        {
            "category":"Professional",
            "subcategory":"Management & Consulting",
            "type":"Services"
        }
    ],
    "sg:phone":"+1 501 318 1465",
    "sg:postcode":"71901",
    "sg:province":"AR",
    "sg:tags":[
        "aviation",
        "consultant"
    ],
    "wof:name":"LJH Aviation Assest Mgmt",
    "wof:placetype":"venue"
},
  "geometry": {"coordinates":[-93.01022500000001,34.487927],"type":"Point"}
}