{
  "type": "Feature",
  "properties": {
    "iso:country":"US",
    "sg:address":"1510 State Hwy 25 B N",
    "sg:city":"Heber Springs",
    "sg:classifiers":[
        {
            "category":"Food & Beverages",
            "subcategory":"Groceries & Convenience Stores",
            "type":"Retail Goods"
        }
    ],
    "sg:phone":"+1 501 362 1958",
    "sg:postcode":"72543",
    "sg:province":"AR",
    "wof:name":"Flash Market 17",
    "wof:placetype":"venue"
},
  "geometry": {"coordinates":[-92.02944599999999,35.505085],"type":"Point"}
}