{
  "type": "Feature",
  "properties": {
    "iso:country":"US",
    "sg:address":"14021 Arch St",
    "sg:city":"Little Rock",
    "sg:classifiers":[
        {
            "category":"Building & Trades",
            "subcategory":"Landscaping Services",
            "type":"Services"
        }
    ],
    "sg:phone":"+1 501 888 3400",
    "sg:postcode":"72206",
    "sg:province":"AR",
    "sg:tags":[
        "landscape",
        "contractor"
    ],
    "wof:name":"Residential French Drains",
    "wof:placetype":"venue"
},
  "geometry": {"coordinates":[-92.313852,34.621316],"type":"Point"}
}