{
  "type": "Feature",
  "properties": {
    "iso:country":"US",
    "sg:address":"1122 E Calhoun St",
    "sg:city":"Luxora",
    "sg:classifiers":[
        {
            "category":"Education",
            "subcategory":"School",
            "type":"Public Place"
        }
    ],
    "sg:phone":"+1 870 658 2412",
    "sg:postcode":"72358",
    "sg:province":"AR",
    "sg:tags":[
        "k-",
        "private"
    ],
    "wof:name":"Luxora Elem. School",
    "wof:placetype":"venue"
},
  "geometry": {"coordinates":[-89.936602,35.756031],"type":"Point"}
}