{
  "type": "Feature",
  "properties": {
    "addr:full":"900 Atlanta St Fort Smith AR 72901",
    "addr:housenumber":"900",
    "addr:postcode":"72901",
    "addr:street":"Atlanta St",
    "iso:country":"US",
    "sg:address":"900 Atlanta St",
    "sg:city":"Fort Smith",
    "sg:classifiers":[
        {
            "category":"Manufacturing",
            "subcategory":"Building Materials",
            "type":"Manufacturing & Wholesale Goods"
        }
    ],
    "sg:phone":"+1 479 783 8666",
    "sg:postcode":"72901",
    "sg:province":"AR",
    "sg:tags":[
        "manufacture",
        "wooden",
        "truss",
        "wall"
    ],
    "sg:website":"www.capstructures.com",
    "wof:name":"Capital Structures",
    "wof:placetype":"venue"
},
  "geometry": {"coordinates":[-94.42349299999999,35.356506],"type":"Point"}
}