{
  "type": "Feature",
  "properties": {
    "addr:full":"349 Madison 8969 Huntsville AR 72740",
    "addr:housenumber":"349",
    "addr:postcode":"8969;72740",
    "iso:country":"US",
    "sg:address":"349 Madison 8969",
    "sg:city":"Huntsville",
    "sg:classifiers":[
        {
            "category":"Wholesale",
            "subcategory":"Farm Supplies",
            "type":"Manufacturing & Wholesale Goods"
        }
    ],
    "sg:phone":"+1 479 559 2762",
    "sg:postcode":"72740",
    "sg:province":"AR",
    "sg:tags":[
        "equipment"
    ],
    "wof:name":"Miller Farm",
    "wof:placetype":"venue"
},
  "geometry": {"coordinates":[-93.719742,36.184818],"type":"Point"}
}