{
  "type": "Feature",
  "properties": {
    "addr:full":"310 Towson Ave Fort Smith AR 72901",
    "addr:housenumber":"310",
    "addr:postcode":"72901",
    "addr:street":"Towson Ave",
    "iso:country":"US",
    "sg:address":"310 Towson Ave",
    "sg:city":"Fort Smith",
    "sg:classifiers":[
        {
            "category":"Professional",
            "subcategory":"Detective & Security Services",
            "type":"Services"
        }
    ],
    "sg:phone":"+1 479 709 9436",
    "sg:postcode":"72901",
    "sg:province":"AR",
    "sg:tags":[
        "system"
    ],
    "wof:name":"Titan Security & Sound",
    "wof:placetype":"venue"
},
  "geometry": {"coordinates":[-94.421194,35.380364],"type":"Point"}
}