{
  "type": "Feature",
  "properties": {
    "iso:country":"US",
    "sg:address":"1423 E 6th St",
    "sg:city":"Little Rock",
    "sg:classifiers":[
        {
            "category":"Manufacturing",
            "subcategory":"Metals",
            "type":"Manufacturing & Wholesale Goods"
        }
    ],
    "sg:phone":"+1 501 340 6200",
    "sg:postcode":"72202",
    "sg:province":"AR",
    "sg:tags":[
        "steel"
    ],
    "sg:website":"www.afcosteel.com",
    "wof:name":"Afco Steel Inc",
    "wof:placetype":"venue"
},
  "geometry": {"coordinates":[-92.254968,34.741818],"type":"Point"}
}