{
  "type": "Feature",
  "properties": {
    "iso:country":"US",
    "sg:address":"4600 Foster St",
    "sg:city":"Little Rock",
    "sg:classifiers":[
        {
            "category":"Wholesale",
            "subcategory":"Machinery & Supplies",
            "type":"Manufacturing & Wholesale Goods"
        }
    ],
    "sg:phone":"+1 501 565 1717",
    "sg:postcode":"72204",
    "sg:province":"AR",
    "sg:tags":[
        "compressor",
        "gas"
    ],
    "wof:name":"Williams Air Compressor",
    "wof:placetype":"venue"
},
  "geometry": {"coordinates":[-92.379926,34.71138],"type":"Point"}
}