{
  "type": "Feature",
  "properties": {
    "iso:country":"US",
    "sg:address":"632 Mulligan Ln",
    "sg:city":"Malvern",
    "sg:classifiers":[
        {
            "category":"Retail",
            "subcategory":"Veterinary Services",
            "type":"Services"
        }
    ],
    "sg:phone":"+1 501 337 9380",
    "sg:postcode":"72104",
    "sg:province":"AR",
    "sg:tags":[
        "specialty"
    ],
    "wof:name":"Second Chance Animal Rescue",
    "wof:placetype":"venue"
},
  "geometry": {"coordinates":[-92.739354,34.278159],"type":"Point"}
}