{
  "type": "Feature",
  "properties": {
    "iso:country":"US",
    "sg:address":"2355 Sequoyah Dr",
    "sg:city":"Rogers",
    "sg:classifiers":[
        {
            "category":"Professional",
            "subcategory":"Computer Services",
            "type":"Services"
        }
    ],
    "sg:phone":"+1 479 872 9085",
    "sg:postcode":"72758",
    "sg:province":"AR",
    "sg:tags":[
        "technical",
        "assistance",
        "support"
    ],
    "wof:name":"Nwa Networks",
    "wof:placetype":"venue"
},
  "geometry": {"coordinates":[-94.085578,36.303859],"type":"Point"}
}