{
  "type": "Feature",
  "properties": {
    "addr:full":"118 W Thompson St Amity AR 71921",
    "addr:housenumber":"118",
    "addr:postcode":"71921",
    "addr:street":"W Thompson St",
    "iso:country":"US",
    "sg:address":"118 W Thompson St",
    "sg:city":"Amity",
    "sg:classifiers":[
        {
            "category":"Autos & Motor Vehicles",
            "subcategory":"Fuel & Gas Station",
            "type":"Retail Goods"
        }
    ],
    "sg:phone":"+1 870 342 9423",
    "sg:postcode":"71921",
    "sg:province":"AR",
    "wof:name":"Cowboy Corner",
    "wof:placetype":"venue"
},
  "geometry": {"coordinates":[-93.46130700000001,34.264799],"type":"Point"}
}