{
  "type": "Feature",
  "properties": {
    "iso:country":"US",
    "sg:address":"7603 Rogers Ave",
    "sg:city":"Fort Smith",
    "sg:classifiers":[
        {
            "category":"Shopping",
            "subcategory":"Discount & Variety Stores",
            "type":"Retail Goods"
        }
    ],
    "sg:phone":"+1 479 452 2740",
    "sg:postcode":"72903",
    "sg:province":"AR",
    "wof:name":"Dollar Tree",
    "wof:placetype":"venue"
},
  "geometry": {"coordinates":[-94.34607699999999,35.350816],"type":"Point"}
}