{
  "type": "Feature",
  "properties": {
    "addr:full":"431 Highway 71 N Alma AR 72921",
    "addr:housenumber":"431",
    "addr:postcode":"72921",
    "addr:street":"Highway 71 N",
    "iso:country":"US",
    "sg:address":"431 Highway 71 N",
    "sg:city":"Alma",
    "sg:classifiers":[
        {
            "category":"Bars & Pubs",
            "type":"Food & Drink"
        },
        {
            "category":"Restaurant",
            "type":"Food & Drink"
        }
    ],
    "sg:menulink":"http://www.allmenus.com/ar/alma/33821-cracker-barrel-old-country-store/menu/",
    "sg:phone":"+1 479 632 0767",
    "sg:postcode":"72921",
    "sg:province":"AR",
    "sg:tags":[
        "american",
        "southern"
    ],
    "wof:name":"Cracker Barrel Old Country Store",
    "wof:placetype":"venue"
},
  "geometry": {"coordinates":[-94.22621599999999,35.490278],"type":"Point"}
}