{
  "type": "Feature",
  "properties": {
    "addr:full":"2205 Douglas St Bentonville AR 72712",
    "addr:housenumber":"2205",
    "addr:postcode":"72712",
    "addr:street":"Douglas St",
    "iso:country":"US",
    "sg:address":"2205 Douglas St",
    "sg:city":"Bentonville",
    "sg:classifiers":[
        {
            "category":"Shopping",
            "subcategory":"Used Merchandise",
            "type":"Retail Goods"
        }
    ],
    "sg:phone":"+1 479 271 0401",
    "sg:postcode":"72712",
    "sg:province":"AR",
    "sg:tags":[
        "flea",
        "market"
    ],
    "wof:name":"Spinnin Wheel Resale & More",
    "wof:placetype":"venue"
},
  "geometry": {"coordinates":[-94.186637,36.360607],"type":"Point"}
}