{
  "type": "Feature",
  "properties": {
    "iso:country":"US",
    "sg:address":"18 Beaverfork Pl",
    "sg:city":"Conway",
    "sg:classifiers":[
        {
            "category":"Professional",
            "subcategory":"Engineering",
            "type":"Services"
        }
    ],
    "sg:phone":"+1 501 504 2000",
    "sg:postcode":"72032",
    "sg:province":"AR",
    "sg:tags":[
        "engineer"
    ],
    "wof:name":"Buie Engineering",
    "wof:placetype":"venue"
},
  "geometry": {"coordinates":[-92.435624,35.140475],"type":"Point"}
}