{
  "type": "Feature",
  "properties": {
    "iso:country":"US",
    "sg:address":"707 Dewey Ave",
    "sg:city":"Mena",
    "sg:classifiers":[
        {
            "category":"Freight",
            "type":"Transportation"
        }
    ],
    "sg:phone":"+1 479 394 5942",
    "sg:postcode":"71953",
    "sg:province":"OK",
    "sg:tags":[
        "operator",
        "local",
        "trucking"
    ],
    "wof:name":"D&D Timber & Trucking",
    "wof:placetype":"venue"
},
  "geometry": {"coordinates":[-94.243206,34.588964],"type":"Point"}
}