{
  "type": "Feature",
  "properties": {
    "iso:country":"US",
    "sg:address":"4701 E Broadway St",
    "sg:city":"North Little Rock",
    "sg:classifiers":[
        {
            "category":"Retail",
            "subcategory":"Auto Repair",
            "type":"Services"
        }
    ],
    "sg:phone":"+1 501 945 5979",
    "sg:postcode":"72117",
    "sg:province":"AR",
    "sg:tags":[
        "general"
    ],
    "wof:name":"Rose City Auto Sales",
    "wof:placetype":"venue"
},
  "geometry": {"coordinates":[-92.21128,34.760777],"type":"Point"}
}