{
  "type": "Feature",
  "properties": {
    "addr:full":"1735 E Broadway Ave Forrest City AR 72335",
    "addr:housenumber":"1735",
    "addr:postcode":"72335",
    "addr:street":"E Broadway Ave",
    "iso:country":"US",
    "sg:address":"1735 E Broadway Ave",
    "sg:city":"Forrest City",
    "sg:classifiers":[
        {
            "category":"Wholesale",
            "subcategory":"Electrical",
            "type":"Manufacturing & Wholesale Goods"
        }
    ],
    "sg:phone":"+1 870 633 4997",
    "sg:postcode":"72335",
    "sg:province":"AR",
    "sg:tags":[
        "equipment",
        "electric",
        "supply"
    ],
    "sg:website":"www.a-e-o.com",
    "wof:name":"Arkansas Electrical Outlet",
    "wof:placetype":"venue"
},
  "geometry": {"coordinates":[-90.77158799999999,35.012234],"type":"Point"}
}