{
  "type": "Feature",
  "properties": {
    "addr:full":"203 Harry Dr Bono AR 72416",
    "addr:housenumber":"203",
    "addr:postcode":"72416",
    "addr:street":"Harry Dr",
    "iso:country":"US",
    "sg:address":"203 Harry Dr",
    "sg:city":"Bono",
    "sg:classifiers":[
        {
            "category":"Wholesale",
            "subcategory":"Motor Vehicles",
            "type":"Manufacturing & Wholesale Goods"
        },
        {
            "category":"Travel",
            "subcategory":"Travel Agent",
            "type":"Entertainment"
        },
        {
            "category":"Retail",
            "subcategory":"Auto Repair",
            "type":"Services"
        }
    ],
    "sg:phone":"+1 870 932 7597",
    "sg:postcode":"72416",
    "sg:province":"AR",
    "sg:tags":[
        "recreational",
        "campers-wholesale",
        "truck",
        "trailer",
        "manufacturer"
    ],
    "wof:name":"Diesel & Trailer Inc., Jonesboro",
    "wof:placetype":"venue"
},
  "geometry": {"coordinates":[-90.764095,35.847345],"type":"Point"}
}