{
  "type": "Feature",
  "properties": {
    "iso:country":"US",
    "sg:address":"420 E New Hope Rd",
    "sg:city":"Rogers",
    "sg:classifiers":[
        {
            "category":"Freight",
            "type":"Transportation"
        },
        {
            "category":"Building & Trades",
            "subcategory":"Construction",
            "type":"Services"
        }
    ],
    "sg:phone":"+1 479 636 7385",
    "sg:postcode":"72758",
    "sg:province":"AR",
    "sg:tags":[
        "commercial",
        "storage",
        "special",
        "home"
    ],
    "wof:name":"Russell Storage",
    "wof:placetype":"venue"
},
  "geometry": {"coordinates":[-94.111999,36.311387],"type":"Point"}
}