{
  "type": "Feature",
  "properties": {
    "addr:full":"700 Baltimore Ave Manila AR 72442",
    "addr:housenumber":"700",
    "addr:postcode":"72442",
    "addr:street":"Baltimore Ave",
    "iso:country":"US",
    "sg:address":"700 Baltimore Ave",
    "sg:city":"Manila",
    "sg:classifiers":[
        {
            "category":"Autos & Motor Vehicles",
            "subcategory":"Automobile Sales",
            "type":"Retail Goods"
        }
    ],
    "sg:phone":"+1 870 561 3488",
    "sg:postcode":"72442",
    "sg:province":"AR",
    "sg:tags":[
        "car",
        "dealer"
    ],
    "wof:name":"Hamilton Auto Sales",
    "wof:placetype":"venue"
},
  "geometry": {"coordinates":[-90.166203,35.884889],"type":"Point"}
}