{
  "type": "Feature",
  "properties": {
    "iso:country":"US",
    "sg:address":"910 Professional Acres Dr",
    "sg:city":"Jonesboro",
    "sg:classifiers":[
        {
            "category":"Health Services",
            "subcategory":"Doctor",
            "type":"Services"
        }
    ],
    "sg:phone":"+1 870 932 2881",
    "sg:postcode":"72401",
    "sg:province":"AR",
    "sg:tags":[
        "dentist"
    ],
    "wof:name":"Samuel L Watts DDS",
    "wof:placetype":"venue"
},
  "geometry": {"coordinates":[-90.692573,35.83462],"type":"Point"}
}