{
  "type": "Feature",
  "properties": {
    "iso:country":"US",
    "sg:address":"14420 Frontier Dr",
    "sg:city":"N Little Rock",
    "sg:classifiers":[
        {
            "category":"Home & Garden",
            "subcategory":"Building Materials",
            "type":"Retail Goods"
        }
    ],
    "sg:phone":"+1 501 803 3722",
    "sg:postcode":"72113",
    "sg:province":"AR",
    "sg:tags":[
        "shutter"
    ],
    "wof:name":"Accent Shutters Inc",
    "wof:placetype":"venue"
},
  "geometry": {"coordinates":[-92.382976,34.886489],"type":"Point"}
}