{
  "type": "Feature",
  "properties": {
    "iso:country":"US",
    "sg:address":"1236 S Diamond Blvd",
    "sg:city":"Diamond City",
    "sg:classifiers":[
        {
            "category":"Retail",
            "subcategory":"Auto Repair",
            "type":"Services"
        }
    ],
    "sg:phone":"+1 870 422 1371",
    "sg:postcode":"72630",
    "sg:province":"AR",
    "sg:tags":[
        "repairing",
        "automobile"
    ],
    "wof:name":"Ozark Marine Auto & Truck",
    "wof:placetype":"venue"
},
  "geometry": {"coordinates":[-92.913296,36.447902],"type":"Point"}
}