{
  "type": "Feature",
  "properties": {
    "iso:country":"US",
    "sg:address":"1214 E 3rd St",
    "sg:city":"Hope",
    "sg:classifiers":[
        {
            "category":"Retail",
            "subcategory":"Repair Shop",
            "type":"Services"
        }
    ],
    "sg:phone":"+1 870 777 8889",
    "sg:postcode":"71801",
    "sg:province":"AR",
    "sg:tags":[
        "plumbing",
        "drain",
        "cleaning",
        "sewer"
    ],
    "wof:name":"Alberson Plumbing Co",
    "wof:placetype":"venue"
},
  "geometry": {"coordinates":[-93.577589,33.668293],"type":"Point"}
}