{
  "type": "Feature",
  "properties": {
    "iso:country":"US",
    "sg:address":"1107 E Main St",
    "sg:city":"Clarksville",
    "sg:classifiers":[
        {
            "category":"Retail",
            "subcategory":"Repair Shop",
            "type":"Services"
        }
    ],
    "sg:phone":"+1 479 754 2628",
    "sg:postcode":"72830",
    "sg:province":"AR",
    "sg:tags":[
        "lock",
        "locksmith"
    ],
    "wof:name":"Tri County Locksmith",
    "wof:placetype":"venue"
},
  "geometry": {"coordinates":[-93.440965,35.470599],"type":"Point"}
}