{
  "type": "Feature",
  "properties": {
    "iso:country":"US",
    "sg:address":"19630 Arch Street Pike",
    "sg:city":"Little Rock",
    "sg:classifiers":[
        {
            "category":"Social Services",
            "subcategory":"Child Care",
            "type":"Services"
        }
    ],
    "sg:phone":"+1 501 888 5058",
    "sg:postcode":"72206",
    "sg:province":"AR",
    "sg:tags":[
        "day"
    ],
    "wof:name":"Amys Kountry Kids",
    "wof:placetype":"venue"
},
  "geometry": {"coordinates":[-92.328436,34.576284],"type":"Point"}
}