{
  "type": "Feature",
  "properties": {
    "iso:country":"US",
    "sg:address":"3094 US Hwy 71",
    "sg:city":"Mena",
    "sg:classifiers":[
        {
            "category":"Retail",
            "subcategory":"Repair Shop",
            "type":"Services"
        }
    ],
    "sg:phone":"+1 479 394 2535",
    "sg:postcode":"71953",
    "sg:province":"AR",
    "wof:name":"Daves Cycle Center",
    "wof:placetype":"venue"
},
  "geometry": {"coordinates":[-94.26689,34.563754],"type":"Point"}
}