{
  "type": "Feature",
  "properties": {
    "addr:full":"409 W Main St Clarksville AR 72830",
    "addr:housenumber":"409",
    "addr:postcode":"72830",
    "addr:street":"W Main St",
    "iso:country":"US",
    "sg:address":"409 W Main St",
    "sg:city":"Clarksville",
    "sg:classifiers":[
        {
            "category":"Shopping",
            "subcategory":"Department Store",
            "type":"Retail Goods"
        },
        {
            "category":"Shopping",
            "subcategory":"Discount & Variety Stores",
            "type":"Retail Goods"
        }
    ],
    "sg:phone":"+1 479 705 0021",
    "sg:postcode":"72830",
    "sg:province":"AR",
    "sg:website":"http://www.fredsdiscount.com",
    "wof:name":"Fred's",
    "wof:placetype":"venue"
},
  "geometry": {"coordinates":[-93.466424,35.471218],"type":"Point"}
}