{
  "type": "Feature",
  "properties": {
    "addr:full":"128 Anselmi Rd Bald Knob AR 72010",
    "addr:housenumber":"128",
    "addr:postcode":"72010",
    "addr:street":"Anselmi Rd",
    "iso:country":"US",
    "sg:address":"128 Anselmi Rd",
    "sg:city":"Bald Knob",
    "sg:classifiers":[
        {
            "category":"Building & Trades",
            "subcategory":"Landscaping Services",
            "type":"Services"
        }
    ],
    "sg:phone":"+1 501 724 6508",
    "sg:postcode":"72010",
    "sg:province":"AR",
    "wof:name":"D & G Contract Mowers",
    "wof:placetype":"venue"
},
  "geometry": {"coordinates":[-91.57888699999999,35.339901],"type":"Point"}
}