{
  "type": "Feature",
  "properties": {
    "iso:country":"US",
    "sg:address":"711 SE J St",
    "sg:city":"Bentonville",
    "sg:classifiers":[
        {
            "category":"Shopping",
            "subcategory":"Optical Goods",
            "type":"Retail Goods"
        }
    ],
    "sg:phone":"+1 479 271 8506",
    "sg:postcode":"72712",
    "sg:province":"AR",
    "wof:name":"Nouveau Eyewear",
    "wof:placetype":"venue"
},
  "geometry": {"coordinates":[-94.196669,36.365068],"type":"Point"}
}