{
  "type": "Feature",
  "properties": {
    "iso:country":"US",
    "sg:address":"4555 Central Ave",
    "sg:city":"Hot Springs",
    "sg:classifiers":[
        {
            "category":"Autos & Motor Vehicles",
            "subcategory":"Automobile Sales",
            "type":"Retail Goods"
        }
    ],
    "sg:phone":"+1 501 375 1036",
    "sg:postcode":"71913",
    "sg:province":"AR",
    "sg:tags":[
        "car",
        "dealer"
    ],
    "sg:website":"www.orrtoyota.com",
    "wof:name":"Orr Pontiac Cadillac Toyota",
    "wof:placetype":"venue"
},
  "geometry": {"coordinates":[-93.082295,34.44929],"type":"Point"}
}