{
  "type": "Feature",
  "properties": {
    "addr:full":"561 Dumas City Rd El Dorado AR 71730",
    "addr:housenumber":"561",
    "addr:postcode":"71730",
    "addr:street":"Dumas City Rd",
    "iso:country":"US",
    "sg:address":"561 Dumas City Rd",
    "sg:city":"El Dorado",
    "sg:classifiers":[
        {
            "category":"Building & Trades",
            "subcategory":"Electrical",
            "type":"Services"
        }
    ],
    "sg:phone":"+1 870 862 2789",
    "sg:postcode":"71730",
    "sg:province":"AR",
    "sg:tags":[
        "installs",
        "television",
        "system",
        "cable",
        "operates"
    ],
    "wof:name":"Foster Rentals",
    "wof:placetype":"venue"
},
  "geometry": {"coordinates":[-92.756165,33.265495],"type":"Point"}
}