{
  "type": "Feature",
  "properties": {
    "iso:country":"US",
    "sg:address":"1591 US Hwy 64",
    "sg:city":"Wynne",
    "sg:classifiers":[
        {
            "category":"Manufacturing",
            "subcategory":"Tools & Machinery",
            "type":"Manufacturing & Wholesale Goods"
        }
    ],
    "sg:phone":"+1 870 238 5322",
    "sg:postcode":"72396",
    "sg:province":"AR",
    "sg:tags":[
        "farm",
        "equipment",
        "mfg"
    ],
    "wof:name":"H & H Manufacturing & Repairs",
    "wof:placetype":"venue"
},
  "geometry": {"coordinates":[-90.90053899999999,35.251609],"type":"Point"}
}