{
  "type": "Feature",
  "properties": {
    "iso:country":"US",
    "sg:address":"204 Rosewood Dr",
    "sg:city":"Paragould",
    "sg:classifiers":[
        {
            "category":"Building & Trades",
            "subcategory":"Construction",
            "type":"Services"
        }
    ],
    "sg:phone":"+1 870 236 7097",
    "sg:postcode":"72450",
    "sg:province":"AR",
    "sg:tags":[
        "nonresidential"
    ],
    "wof:name":"Carlile Inc",
    "wof:placetype":"venue"
},
  "geometry": {"coordinates":[-90.533628,36.057395],"type":"Point"}
}