{
  "type": "Feature",
  "properties": {
    "iso:country":"US",
    "sg:address":"213 Chinquepin Dr",
    "sg:city":"Magnolia",
    "sg:classifiers":[
        {
            "category":"Professional",
            "type":"Services"
        }
    ],
    "sg:phone":"+1 870 234 5739",
    "sg:postcode":"71753",
    "sg:province":"AR",
    "wof:name":"Curtis J Elliott",
    "wof:placetype":"venue"
},
  "geometry": {"coordinates":[-93.192523,33.285467],"type":"Point"}
}