{
  "type": "Feature",
  "properties": {
    "addr:full":"902 SE 13th Ct Bentonville AR 72712",
    "addr:housenumber":"902",
    "addr:postcode":"72712",
    "addr:street":"Se 13Th Ct",
    "iso:country":"US",
    "sg:address":"902 SE 13th Ct",
    "sg:city":"Bentonville",
    "sg:classifiers":[
        {
            "category":"Health Services",
            "subcategory":"Doctor",
            "type":"Services"
        }
    ],
    "sg:phone":"+1 479 273 9056",
    "sg:postcode":"72712",
    "sg:province":"AR",
    "sg:tags":[
        "physician",
        "surgeon"
    ],
    "wof:name":"Bentonville Medical Assoc",
    "wof:placetype":"venue"
},
  "geometry": {"coordinates":[-94.19811199999999,36.357998],"type":"Point"}
}