{
  "type": "Feature",
  "properties": {
    "iso:country":"US",
    "sg:address":"201 Bush St",
    "sg:city":"Hughes",
    "sg:classifiers":[
        {
            "category":"Bars & Pubs",
            "type":"Food & Drink"
        }
    ],
    "sg:phone":"+1 870 339 2130",
    "sg:postcode":"72348",
    "sg:province":"AR",
    "sg:tags":[
        "lounge",
        "cocktail"
    ],
    "wof:name":"Blue Lounge",
    "wof:placetype":"venue"
},
  "geometry": {"coordinates":[-90.470389,34.947931],"type":"Point"}
}