{
  "type": "Feature",
  "properties": {
    "iso:country":"US",
    "sg:address":"21 Venable Ln",
    "sg:city":"Scott",
    "sg:classifiers":[
        {
            "category":"Real Estate",
            "subcategory":"Real Estate Operator",
            "type":"Services"
        }
    ],
    "sg:phone":"+1 501 961 2106",
    "sg:postcode":"72142",
    "sg:province":"AR",
    "sg:tags":[
        "property",
        "lessor"
    ],
    "wof:name":"Webb Farms",
    "wof:placetype":"venue"
},
  "geometry": {"coordinates":[-92.10198,34.653862],"type":"Point"}
}