{
  "type": "Feature",
  "properties": {
    "addr:full":"150 S Walker St Ashdown AR 71822",
    "addr:housenumber":"150",
    "addr:postcode":"71822",
    "addr:street":"S Walker St",
    "iso:country":"US",
    "sg:address":"150 S Walker St",
    "sg:city":"Ashdown",
    "sg:classifiers":[
        {
            "category":"Organizations",
            "subcategory":"Religious Organization",
            "type":"Services"
        }
    ],
    "sg:phone":"+1 870 898 3237",
    "sg:postcode":"71822",
    "sg:province":"AR",
    "sg:tags":[
        "church"
    ],
    "sg:website":"www.firstagchurch.com",
    "wof:name":"First Assembly Of God Church",
    "wof:placetype":"venue"
},
  "geometry": {"coordinates":[-94.124347,33.670689],"type":"Point"}
}