{
  "type": "Feature",
  "properties": {
    "addr:full":"2851 Salmon Ln Harrison AR 72601",
    "addr:housenumber":"2851",
    "addr:postcode":"72601",
    "addr:street":"Salmon Ln",
    "iso:country":"US",
    "sg:address":"2851 Salmon Ln",
    "sg:city":"Harrison",
    "sg:classifiers":[
        {
            "category":"Personal",
            "subcategory":"Beauty Salon",
            "type":"Services"
        }
    ],
    "sg:phone":"+1 870 741 0129",
    "sg:postcode":"72601",
    "sg:province":"AR",
    "sg:tags":[
        "shop"
    ],
    "wof:name":"Hair Corral",
    "wof:placetype":"venue"
},
  "geometry": {"coordinates":[-93.078326,36.200638],"type":"Point"}
}