{
  "type": "Feature",
  "properties": {
    "iso:country":"US",
    "sg:address":"215 Lower Danville Rd",
    "sg:city":"Dardanelle",
    "sg:classifiers":[
        {
            "category":"Professional",
            "subcategory":"Accounting & Tax Preparation",
            "type":"Services"
        }
    ],
    "sg:phone":"+1 479 229 2295",
    "sg:postcode":"72834",
    "sg:province":"AR",
    "wof:name":"Terry Dortch",
    "wof:placetype":"venue"
},
  "geometry": {"coordinates":[-93.152438,35.210804],"type":"Point"}
}