{
  "type": "Feature",
  "properties": {
    "iso:country":"US",
    "sg:address":"1350 S Gutensohn Rd",
    "sg:city":"Springdale",
    "sg:classifiers":[
        {
            "category":"Shopping",
            "subcategory":"Hobbies, Toys, & Games",
            "type":"Retail Goods"
        },
        {
            "category":"Manufacturing",
            "subcategory":"Jewelry",
            "type":"Manufacturing & Wholesale Goods"
        }
    ],
    "sg:phone":"+1 479 751 7800",
    "sg:postcode":"72762",
    "sg:province":"AR",
    "sg:tags":[
        "platinum",
        "gold",
        "supply",
        "buyer",
        "coin",
        "silver"
    ],
    "wof:name":"Nwa Gold & Silver",
    "wof:placetype":"venue"
},
  "geometry": {"coordinates":[-94.161372,36.175182],"type":"Point"}
}