{
  "type": "Feature",
  "properties": {
    "iso:country":"US",
    "sg:address":"8 Glendale Ct",
    "sg:city":"Arkadelphia",
    "sg:classifiers":[
        {
            "category":"Building & Trades",
            "subcategory":"Plumbing",
            "type":"Services"
        }
    ],
    "sg:phone":"+1 870 246 8248",
    "sg:postcode":"71923",
    "sg:province":"AR",
    "sg:tags":[
        "conditioning",
        "contractor",
        "system",
        "air"
    ],
    "wof:name":"Tolson Heating & Air Cond Inc",
    "wof:placetype":"venue"
},
  "geometry": {"coordinates":[-93.082836,34.13021],"type":"Point"}
}