{
  "type": "Feature",
  "properties": {
    "iso:country":"US",
    "sg:address":"215 SE 8th St",
    "sg:city":"Bentonville",
    "sg:classifiers":[
        {
            "category":"Government",
            "subcategory":"Fire Station",
            "type":"Public Place"
        }
    ],
    "sg:phone":"+1 479 271 3152",
    "sg:postcode":"72712",
    "sg:province":"AR",
    "sg:tags":[
        "protection"
    ],
    "wof:name":"Bentonville Fire Dept Pma",
    "wof:placetype":"venue"
},
  "geometry": {"coordinates":[-94.206642,36.364252],"type":"Point"}
}