{
  "type": "Feature",
  "properties": {
    "iso:country":"US",
    "sg:address":"6065 Long Creek Rd",
    "sg:city":"Alpena",
    "sg:classifiers":[
        {
            "category":"Farming",
            "subcategory":"Dairy Farm",
            "type":"Manufacturing & Wholesale Goods"
        }
    ],
    "sg:phone":"+1 870 437 5301",
    "sg:postcode":"72611",
    "sg:province":"AR",
    "wof:name":"Jessica's Mountain",
    "wof:placetype":"venue"
},
  "geometry": {"coordinates":[-93.274603,36.338717],"type":"Point"}
}