{
  "type": "Feature",
  "properties": {
    "iso:country":"US",
    "sg:address":"1404 NE McClain Rd",
    "sg:city":"Bentonville",
    "sg:classifiers":[
        {
            "category":"Organizations",
            "subcategory":"Professional Association",
            "type":"Services"
        }
    ],
    "sg:phone":"+1 914 631 8000",
    "sg:postcode":"72712",
    "sg:province":"AR",
    "sg:tags":[
        "business"
    ],
    "wof:name":"Bayer Healthcare LLC",
    "wof:placetype":"venue"
},
  "geometry": {"coordinates":[-94.171621,36.38686],"type":"Point"}
}