{
  "type": "Feature",
  "properties": {
    "addr:full":"206 SE 1st St Atkins AR 72823",
    "addr:housenumber":"206",
    "addr:postcode":"72823",
    "addr:street":"Se 1St St",
    "iso:country":"US",
    "sg:address":"206 SE 1st St",
    "sg:city":"Atkins",
    "sg:classifiers":[
        {
            "category":"Building & Trades",
            "subcategory":"Plumbing",
            "type":"Services"
        }
    ],
    "sg:phone":"+1 479 641 2317",
    "sg:postcode":"72823",
    "sg:province":"AR",
    "sg:tags":[
        "boiler",
        "cleaning"
    ],
    "wof:name":"H & W Boiler Svc",
    "wof:placetype":"venue"
},
  "geometry": {"coordinates":[-92.93623100000001,35.24138],"type":"Point"}
}