{
  "type": "Feature",
  "properties": {
    "addr:full":"309 Oak Wood Dr Dover AR 72837",
    "addr:housenumber":"309",
    "addr:postcode":"72837",
    "addr:street":"Oak Wood Dr",
    "iso:country":"US",
    "sg:address":"309 Oak Wood Dr",
    "sg:city":"Dover",
    "sg:classifiers":[
        {
            "category":"Arts & Performance",
            "subcategory":"Theater",
            "type":"Entertainment"
        }
    ],
    "sg:phone":"+1 479 331 2112",
    "sg:postcode":"72837",
    "sg:province":"AR",
    "sg:tags":[
        "live",
        "music"
    ],
    "wof:name":"Party Time Entertainment",
    "wof:placetype":"venue"
},
  "geometry": {"coordinates":[-93.08471,35.378295],"type":"Point"}
}