{
  "type": "Feature",
  "properties": {
    "addr:full":"16145 Hwy 9 Mountain View AR 72560",
    "addr:housenumber":"16145",
    "addr:postcode":"72560",
    "addr:street":"Hwy 9 Mountain View",
    "iso:country":"US",
    "sg:address":"16145 Hwy 9",
    "sg:city":"Mountain View",
    "sg:classifiers":[
        {
            "category":"Government",
            "subcategory":"Fire Station",
            "type":"Public Place"
        }
    ],
    "sg:phone":"+1 870 269 4556",
    "sg:postcode":"72560",
    "sg:province":"AR",
    "sg:tags":[
        "department"
    ],
    "wof:name":"Dodd Mountain Fire Dept",
    "wof:placetype":"venue"
},
  "geometry": {"coordinates":[-92.145438,35.833756],"type":"Point"}
}