{
  "type": "Feature",
  "properties": {
    "addr:full":"1320 Foster Dr Ashdown AR 71822",
    "addr:housenumber":"1320",
    "addr:postcode":"71822",
    "addr:street":"Foster Dr",
    "iso:country":"US",
    "sg:address":"1320 Foster Dr",
    "sg:city":"Ashdown",
    "sg:classifiers":[
        {
            "category":"Social Services",
            "subcategory":"Child Care",
            "type":"Services"
        }
    ],
    "sg:phone":"+1 870 898 5452",
    "sg:postcode":"71822",
    "sg:province":"AR",
    "sg:tags":[
        "nursery",
        "day"
    ],
    "sg:website":"http://eclkc.ohs.acf.hhs.gov/hslc/",
    "wof:name":"Ashdown Head Start Center",
    "wof:placetype":"venue"
},
  "geometry": {"coordinates":[-94.145399,33.671717],"type":"Point"}
}