{
  "type": "Feature",
  "properties": {
    "iso:country":"US",
    "sg:address":"4436 Roundhill Rd",
    "sg:city":"Malvern",
    "sg:classifiers":[
        {
            "category":"Professional",
            "type":"Services"
        }
    ],
    "sg:phone":"+1 501 337 7925",
    "sg:postcode":"72104",
    "sg:province":"AR",
    "wof:name":"William J Earls",
    "wof:placetype":"venue"
},
  "geometry": {"coordinates":[-92.78089,34.18712],"type":"Point"}
}