{
  "type": "Feature",
  "properties": {
    "addr:full":"803 Henryetta St Springdale AR 72762",
    "addr:housenumber":"803",
    "addr:postcode":"72762",
    "addr:street":"Henryetta St",
    "iso:country":"US",
    "sg:address":"803 Henryetta St",
    "sg:city":"Springdale",
    "sg:classifiers":[
        {
            "category":"Retail",
            "subcategory":"Auto Repair",
            "type":"Services"
        }
    ],
    "sg:phone":"+1 479 790 2844",
    "sg:postcode":"72762",
    "sg:province":"AR",
    "sg:tags":[
        "repairing",
        "automobile"
    ],
    "wof:name":"Image Auto",
    "wof:placetype":"venue"
},
  "geometry": {"coordinates":[-94.153871,36.174847],"type":"Point"}
}