{
  "type": "Feature",
  "properties": {
    "iso:country":"US",
    "sg:address":"1111 W 22nd St",
    "sg:city":"Stuttgart",
    "sg:classifiers":[
        {
            "category":"Social Services",
            "subcategory":"Child Care",
            "type":"Services"
        }
    ],
    "sg:phone":"+1 870 673 4516",
    "sg:postcode":"72160",
    "sg:province":"AR",
    "wof:name":"Growing Tree Child Dev Ctr",
    "wof:placetype":"venue"
},
  "geometry": {"coordinates":[-91.565309,34.479515],"type":"Point"}
}