{
  "type": "Feature",
  "properties": {
    "iso:country":"US",
    "sg:address":"150 Legion Rd",
    "sg:city":"West Memphis",
    "sg:classifiers":[
        {
            "category":"Professional",
            "subcategory":"Business Services",
            "type":"Services"
        }
    ],
    "sg:phone":"+1 870 266 3616",
    "sg:postcode":"72301",
    "sg:province":"AR",
    "sg:tags":[
        "hanger",
        "sign"
    ],
    "wof:name":"Sanders Fabrication & Erection",
    "wof:placetype":"venue"
},
  "geometry": {"coordinates":[-90.133955,35.142468],"type":"Point"}
}