{
  "type": "Feature",
  "properties": {
    "addr:full":"104 S Rosetta St Little Rock AR 72205",
    "addr:housenumber":"104",
    "addr:postcode":"72205",
    "addr:street":"S Rosetta St",
    "iso:country":"US",
    "sg:address":"104 S Rosetta St",
    "sg:city":"Little Rock",
    "sg:classifiers":[
        {
            "category":"Government",
            "subcategory":"Office",
            "type":"Public Place"
        }
    ],
    "sg:phone":"+1 501 663 7590",
    "sg:postcode":"72205",
    "sg:province":"AR",
    "sg:tags":[
        "management"
    ],
    "wof:name":"Berg Cih Inc",
    "wof:placetype":"venue"
},
  "geometry": {"coordinates":[-92.308808,34.7492],"type":"Point"}
}