{
  "type": "Feature",
  "properties": {
    "iso:country":"US",
    "sg:address":"4220 N Rodney Parham Rd",
    "sg:city":"Little Rock",
    "sg:classifiers":[
        {
            "category":"Banks & Credit Unions",
            "subcategory":"Bank",
            "type":"Services"
        }
    ],
    "sg:phone":"+1 501 978 4500",
    "sg:postcode":"72212",
    "sg:province":"AR",
    "wof:name":"Metropolitan National Bank",
    "wof:placetype":"venue"
},
  "geometry": {"coordinates":[-92.397401,34.790661],"type":"Point"}
}