{
  "type": "Feature",
  "properties": {
    "iso:country":"US",
    "sg:address":"605 Eureka Ave",
    "sg:city":"Berryville",
    "sg:classifiers":[
        {
            "category":"Real Estate",
            "subcategory":"Real Estate Agent",
            "type":"Services"
        }
    ],
    "sg:phone":"+1 870 423 2950",
    "sg:postcode":"72616",
    "sg:province":"AR",
    "sg:website":"www.lmontgomery.com",
    "wof:name":"Larry Montgomery Real Estate",
    "wof:placetype":"venue"
},
  "geometry": {"coordinates":[-93.575326,36.367036],"type":"Point"}
}