{
  "type": "Feature",
  "properties": {
    "addr:full":"804 Virginia Ave Bauxite AR 72011",
    "addr:housenumber":"804",
    "addr:postcode":"72011",
    "addr:street":"Virginia Ave",
    "iso:country":"US",
    "sg:address":"804 Virginia Ave",
    "sg:city":"Bauxite",
    "sg:classifiers":[
        {
            "category":"Building & Trades",
            "subcategory":"Construction",
            "type":"Services"
        }
    ],
    "sg:phone":"+1 501 602 5056",
    "sg:postcode":"72011",
    "sg:province":"AR",
    "sg:tags":[
        "excavation",
        "contractor"
    ],
    "wof:name":"J & R Construction & Excavation, Inc",
    "wof:placetype":"venue"
},
  "geometry": {"coordinates":[-92.520478,34.559663],"type":"Point"}
}