{
  "type": "Feature",
  "properties": {
    "iso:country":"US",
    "sg:address":"23601 Barry Ln",
    "sg:city":"Little Rock",
    "sg:classifiers":[
        {
            "category":"Utilities",
            "subcategory":"Refuse",
            "type":"Services"
        }
    ],
    "sg:phone":"+1 501 821 3944",
    "sg:postcode":"72210",
    "sg:province":"AR",
    "sg:tags":[
        "garbage",
        "collection"
    ],
    "wof:name":"Cherry's Trash Svc",
    "wof:placetype":"venue"
},
  "geometry": {"coordinates":[-92.537121,34.730349],"type":"Point"}
}