{
  "type": "Feature",
  "properties": {
    "iso:country":"US",
    "sg:address":"2355 E Grand Ave",
    "sg:city":"Hot Springs National",
    "sg:classifiers":[
        {
            "category":"Food & Beverages",
            "subcategory":"Groceries & Convenience Stores",
            "type":"Retail Goods"
        }
    ],
    "sg:phone":"+1 501 321 2028",
    "sg:postcode":"71901",
    "sg:province":"AR",
    "wof:name":"Star Stop",
    "wof:placetype":"venue"
},
  "geometry": {"coordinates":[-93.000123,34.505089],"type":"Point"}
}