{
  "type": "Feature",
  "properties": {
    "addr:full":"103 W Shepherd St Nashville AR 71852",
    "addr:housenumber":"103",
    "addr:postcode":"71852",
    "addr:street":"W Shepherd St",
    "iso:country":"US",
    "sg:address":"103 W Shepherd St",
    "sg:city":"Nashville",
    "sg:classifiers":[
        {
            "category":"Building & Trades",
            "subcategory":"Equipment Rental",
            "type":"Services"
        }
    ],
    "sg:phone":"+1 870 845 4308",
    "sg:postcode":"71852",
    "sg:province":"AR",
    "sg:tags":[
        "player",
        "recorder",
        "video"
    ],
    "wof:name":"Video World",
    "wof:placetype":"venue"
},
  "geometry": {"coordinates":[-93.848316,33.945455],"type":"Point"}
}