{
  "type": "Feature",
  "properties": {
    "iso:country":"US",
    "sg:address":"3205 Chrysler Cove",
    "sg:city":"Conway",
    "sg:classifiers":[
        {
            "category":"Professional",
            "subcategory":"Business Services",
            "type":"Services"
        }
    ],
    "sg:phone":"+1 501 327 3212",
    "sg:postcode":"72034",
    "sg:province":"AR",
    "wof:name":"Tim Rose Enterprises Inc",
    "wof:placetype":"venue"
},
  "geometry": {"coordinates":[-92.479907,35.102233],"type":"Point"}
}