{
  "type": "Feature",
  "properties": {
    "iso:country":"US",
    "sg:address":"16556 E Hewitt Springs Rd",
    "sg:city":"Springdale",
    "sg:classifiers":[
        {
            "category":"Building & Trades",
            "subcategory":"Construction",
            "type":"Services"
        }
    ],
    "sg:phone":"+1 479 750 4476",
    "sg:postcode":"72764",
    "sg:province":"AR",
    "sg:tags":[
        "general",
        "contractor"
    ],
    "wof:name":"Heritage Builders NWA Inc",
    "wof:placetype":"venue"
},
  "geometry": {"coordinates":[-94.063192,36.172169],"type":"Point"}
}