{
  "type": "Feature",
  "properties": {
    "iso:country":"US",
    "sg:address":"4255 US Hwy 71 Bus",
    "sg:city":"Springdale",
    "sg:classifiers":[
        {
            "category":"Building & Trades",
            "subcategory":"Landscaping Services",
            "type":"Services"
        }
    ],
    "sg:phone":"+1 479 636 1717",
    "sg:postcode":"72764",
    "sg:province":"AR",
    "sg:tags":[
        "landscape",
        "contractor"
    ],
    "wof:name":"Blue Ribbon Lawns",
    "wof:placetype":"venue"
},
  "geometry": {"coordinates":[-94.143937,36.147939],"type":"Point"}
}