{
  "type": "Feature",
  "properties": {
    "addr:full":"940 W Maple St Fayetteville AR 72701",
    "addr:housenumber":"940",
    "addr:postcode":"72701",
    "addr:street":"W Maple St",
    "iso:country":"US",
    "sg:address":"940 W Maple St",
    "sg:city":"Fayetteville",
    "sg:classifiers":[
        {
            "category":"Education",
            "subcategory":"College",
            "type":"Public Place"
        }
    ],
    "sg:phone":"+1 479 521 5613",
    "sg:postcode":"72701",
    "sg:province":"AR",
    "sg:tags":[
        "housing",
        "student"
    ],
    "wof:name":"CHI Omega Sorority",
    "wof:placetype":"venue"
},
  "geometry": {"coordinates":[-94.173286,36.070278],"type":"Point"}
}