{
  "type": "Feature",
  "properties": {
    "iso:country":"US",
    "sg:address":"256 Hope Cir",
    "sg:city":"Malvern",
    "sg:classifiers":[
        {
            "category":"Manufacturing",
            "subcategory":"Buildings",
            "type":"Manufacturing & Wholesale Goods"
        },
        {
            "category":"Building & Trades",
            "subcategory":"Construction",
            "type":"Services"
        }
    ],
    "sg:phone":"+1 501 229 2047",
    "sg:postcode":"72104",
    "sg:province":"AR",
    "sg:tags":[
        "home",
        "builder",
        "contractor"
    ],
    "wof:name":"Stone Brothers Construction",
    "wof:placetype":"venue"
},
  "geometry": {"coordinates":[-92.842145,34.442914],"type":"Point"}
}