{
  "type": "Feature",
  "properties": {
    "iso:country":"US",
    "sg:address":"20354 Nicodemus Church Rd",
    "sg:city":"Siloam Springs",
    "sg:classifiers":[
        {
            "category":"Retail",
            "subcategory":"Portrait Studio",
            "type":"Services"
        }
    ],
    "sg:phone":"+1 479 549 4039",
    "sg:postcode":"72761",
    "sg:province":"OK",
    "sg:tags":[
        "photographer",
        "photo"
    ],
    "wof:name":"Bergland Photography",
    "wof:placetype":"venue"
},
  "geometry": {"coordinates":[-94.48763,36.122831],"type":"Point"}
}