{
  "type": "Feature",
  "properties": {
    "iso:country":"US",
    "sg:address":"122 Huntcliff Dr",
    "sg:city":"Jonesboro",
    "sg:classifiers":[
        {
            "category":"Professional",
            "subcategory":"Management & Consulting",
            "type":"Services"
        }
    ],
    "sg:phone":"+1 870 935 7748",
    "sg:postcode":"72404",
    "sg:province":"AR",
    "sg:tags":[
        "business"
    ],
    "wof:name":"Griffin AG-Consultg",
    "wof:placetype":"venue"
},
  "geometry": {"coordinates":[-90.709243,35.79195],"type":"Point"}
}