{
  "type": "Feature",
  "properties": {
    "iso:country":"US",
    "sg:address":"2100 W 38th St",
    "sg:city":"N Little Rock",
    "sg:classifiers":[
        {
            "category":"Retail",
            "subcategory":"Auto Repair",
            "type":"Services"
        }
    ],
    "sg:phone":"+1 501 753 0997",
    "sg:postcode":"72118",
    "sg:province":"AR",
    "sg:tags":[
        "body",
        "automobile",
        "painting"
    ],
    "wof:name":"Custom 1 Paint & Body Shop",
    "wof:placetype":"venue"
},
  "geometry": {"coordinates":[-92.288945,34.790678],"type":"Point"}
}