{
  "type": "Feature",
  "properties": {
    "iso:country":"US",
    "sg:address":"231 Persimmon Pond Rd",
    "sg:city":"Pocahontas",
    "sg:classifiers":[
        {
            "category":"Professional",
            "type":"Services"
        }
    ],
    "sg:phone":"+1 870 892 8059",
    "sg:postcode":"72455",
    "sg:province":"AR",
    "wof:name":"Larry Poe",
    "wof:placetype":"venue"
},
  "geometry": {"coordinates":[-91.054062,36.348597],"type":"Point"}
}