{
  "type": "Feature",
  "properties": {
    "iso:country":"US",
    "sg:address":"2212 W Beebe Capps Expy",
    "sg:city":"Searcy",
    "sg:classifiers":[
        {
            "category":"Shopping",
            "subcategory":"Bicycles & Sporting Goods",
            "type":"Retail Goods"
        }
    ],
    "sg:phone":"+1 501 278 5515",
    "sg:postcode":"72143",
    "sg:province":"AR",
    "wof:name":"Bike City",
    "wof:placetype":"venue"
},
  "geometry": {"coordinates":[-91.763949,35.247361],"type":"Point"}
}