{
  "type": "Feature",
  "properties": {
    "iso:country":"US",
    "sg:address":"422 S 21st St",
    "sg:city":"Blytheville",
    "sg:classifiers":[
        {
            "category":"Food & Beverages",
            "subcategory":"Meat & Fish",
            "type":"Retail Goods"
        }
    ],
    "sg:phone":"+1 870 763 3474",
    "sg:postcode":"72315",
    "sg:province":"AR",
    "sg:tags":[
        "seafood"
    ],
    "wof:name":"City Fish Market",
    "wof:placetype":"venue"
},
  "geometry": {"coordinates":[-89.927695,35.924317],"type":"Point"}
}