{
  "type": "Feature",
  "properties": {
    "iso:country":"US",
    "sg:address":"2750 Pine St",
    "sg:city":"Arkadelphia",
    "sg:classifiers":[
        {
            "category":"Shopping",
            "subcategory":"Pharmacy",
            "type":"Retail Goods"
        }
    ],
    "sg:phone":"+1 870 246 6751",
    "sg:postcode":"71923",
    "sg:province":"AR",
    "wof:name":"Freds Discount Pharmacy",
    "wof:placetype":"venue"
},
  "geometry": {"coordinates":[-93.08171900000001,34.122779],"type":"Point"}
}