{
  "type": "Feature",
  "properties": {
    "iso:country":"US",
    "sg:address":"5515 Towson Ave",
    "sg:city":"Fort Smith",
    "sg:classifiers":[
        {
            "category":"Insurance",
            "subcategory":"Insurance Agent",
            "type":"Services"
        }
    ],
    "sg:phone":"+1 479 648 0575",
    "sg:postcode":"72901",
    "sg:province":"AR",
    "wof:name":"Best One-Stop Insurance",
    "wof:placetype":"venue"
},
  "geometry": {"coordinates":[-94.422846,35.331741],"type":"Point"}
}