{
  "type": "Feature",
  "properties": {
    "iso:country":"US",
    "sg:address":"2017 Military Rd",
    "sg:city":"Benton",
    "sg:classifiers":[
        {
            "category":"Place Of Worship",
            "subcategory":"Church",
            "type":"Public Place"
        },
        {
            "category":"Place Of Worship",
            "type":"Public Place"
        }
    ],
    "sg:phone":"+1 501 778 8025",
    "sg:postcode":"72015",
    "sg:province":"AR",
    "sg:tags":[
        "churches-interdenominational",
        "churches-various",
        "denomination"
    ],
    "wof:name":"Great Commission Ministry",
    "wof:placetype":"venue"
},
  "geometry": {"coordinates":[-92.570947,34.582615],"type":"Point"}
}