{
  "type": "Feature",
  "properties": {
    "addr:full":"896 Co Rd 2030 Altus AR 72821",
    "addr:housenumber":"896",
    "addr:postcode":"2030;72821",
    "addr:street":"Co Rd",
    "iso:country":"US",
    "sg:address":"896 Co Rd 2030",
    "sg:city":"Altus",
    "sg:classifiers":[
        {
            "category":"Farming",
            "subcategory":"Farm",
            "type":"Manufacturing & Wholesale Goods"
        }
    ],
    "sg:phone":"+1 479 497 2026",
    "sg:postcode":"72821",
    "sg:province":"AR",
    "sg:tags":[
        "agricultural",
        "production",
        "crop"
    ],
    "wof:name":"Lewis Freeman Farms",
    "wof:placetype":"venue"
},
  "geometry": {"coordinates":[-93.682846,35.418093],"type":"Point"}
}