{
  "type": "Feature",
  "properties": {
    "iso:country":"US",
    "sg:address":"600 N Main St",
    "sg:city":"Hamburg",
    "sg:classifiers":[
        {
            "category":"Autos & Motor Vehicles",
            "subcategory":"Fuel & Gas Station",
            "type":"Retail Goods"
        }
    ],
    "sg:phone":"+1 870 853 8939",
    "sg:postcode":"71646",
    "sg:province":"AR",
    "sg:tags":[
        "convenience",
        "gasoline",
        "store"
    ],
    "wof:name":"Exxon Family Mart",
    "wof:placetype":"venue"
},
  "geometry": {"coordinates":[-91.79744700000001,33.229649],"type":"Point"}
}