{
  "type": "Feature",
  "properties": {
    "addr:full":"1601 Cavanaugh Rd Fort Smith AR 72908",
    "addr:housenumber":"1601",
    "addr:postcode":"72908",
    "addr:street":"Cavanaugh Rd",
    "iso:country":"US",
    "sg:address":"1601 Cavanaugh Rd",
    "sg:city":"Fort Smith",
    "sg:classifiers":[
        {
            "category":"Professional",
            "subcategory":"Management & Consulting",
            "type":"Services"
        }
    ],
    "sg:phone":"+1 479 646 6426",
    "sg:postcode":"72908",
    "sg:province":"AR",
    "sg:tags":[
        "retail",
        "direct",
        "sales"
    ],
    "wof:name":"Southern Spring Water",
    "wof:placetype":"venue"
},
  "geometry": {"coordinates":[-94.419983,35.312175],"type":"Point"}
}