{
  "type": "Feature",
  "properties": {
    "addr:full":"111 Saint Clare Ct Sherwood AR 72120",
    "addr:housenumber":"111",
    "addr:postcode":"72120",
    "addr:street":"Saint Clare Ct",
    "iso:country":"US",
    "sg:address":"111 Saint Clare Ct",
    "sg:city":"Sherwood",
    "sg:classifiers":[
        {
            "category":"Autos & Motor Vehicles",
            "subcategory":"Automobile Sales",
            "type":"Retail Goods"
        }
    ],
    "sg:phone":"+1 501 833 3778",
    "sg:postcode":"72120",
    "sg:province":"AR",
    "sg:tags":[
        "new",
        "used",
        "car"
    ],
    "wof:name":"Flyin' High Motor Sales",
    "wof:placetype":"venue"
},
  "geometry": {"coordinates":[-92.229479,34.805825],"type":"Point"}
}