{
  "type": "Feature",
  "properties": {
    "addr:full":"9709 Warden Rd Sherwood AR 72120",
    "addr:housenumber":"9709",
    "addr:postcode":"72120",
    "addr:street":"Warden Rd",
    "iso:country":"US",
    "sg:address":"9709 Warden Rd",
    "sg:city":"Sherwood",
    "sg:classifiers":[
        {
            "category":"Shopping",
            "subcategory":"Florist",
            "type":"Retail Goods"
        }
    ],
    "sg:phone":"+1 501 833 2633",
    "sg:postcode":"72120",
    "sg:province":"AR",
    "wof:name":"Burnett's Nursery & Landscape",
    "wof:placetype":"venue"
},
  "geometry": {"coordinates":[-92.18608399999999,34.828857],"type":"Point"}
}