{
  "type": "Feature",
  "properties": {
    "iso:country":"US",
    "sg:address":"2938 State Hwy 288",
    "sg:city":"Ratcliff",
    "sg:classifiers":[
        {
            "category":"Organizations",
            "subcategory":"Religious Organization",
            "type":"Services"
        }
    ],
    "sg:phone":"+1 479 635 2555",
    "sg:postcode":"72951",
    "sg:province":"AR",
    "sg:tags":[
        "church"
    ],
    "wof:name":"Mt Hope Missionary Baptist Ch",
    "wof:placetype":"venue"
},
  "geometry": {"coordinates":[-93.879668,35.363675],"type":"Point"}
}