{
  "type": "Feature",
  "properties": {
    "addr:full":"9200 Springhill Rd Alexander AR 72002",
    "addr:housenumber":"9200",
    "addr:postcode":"72002",
    "addr:street":"Springhill Rd",
    "iso:country":"US",
    "sg:address":"9200 Springhill Rd",
    "sg:city":"Alexander",
    "sg:classifiers":[
        {
            "category":"Building & Trades",
            "subcategory":"Construction",
            "type":"Services"
        }
    ],
    "sg:phone":"+1 501 316 2546",
    "sg:postcode":"72002",
    "sg:province":"AR",
    "sg:tags":[
        "equipment",
        "supply",
        "drywall",
        "contractor"
    ],
    "wof:name":"Glen Ward Drywall",
    "wof:placetype":"venue"
},
  "geometry": {"coordinates":[-92.52476900000001,34.674207],"type":"Point"}
}