{
  "type": "Feature",
  "properties": {
    "addr:full":"1412 Franklin St Jonesboro AR 72401",
    "addr:housenumber":"1412",
    "addr:postcode":"72401",
    "addr:street":"Franklin St",
    "iso:country":"US",
    "sg:address":"1412 Franklin St",
    "sg:city":"Jonesboro",
    "sg:classifiers":[
        {
            "category":"Health Services",
            "subcategory":"Medical Lab",
            "type":"Services"
        }
    ],
    "sg:phone":"+1 870 972 8422",
    "sg:postcode":"72401",
    "sg:province":"AR",
    "sg:tags":[
        "laboratory",
        "dental"
    ],
    "wof:name":"Fivecoat Dental Lab Inc",
    "wof:placetype":"venue"
},
  "geometry": {"coordinates":[-90.683623,35.8283],"type":"Point"}
}