{
  "type": "Feature",
  "properties": {
    "iso:country":"US",
    "sg:address":"58 Maryton Park Cove",
    "sg:city":"Little Rock",
    "sg:classifiers":[
        {
            "category":"Real Estate",
            "subcategory":"Real Estate Agent",
            "type":"Services"
        }
    ],
    "sg:phone":"+1 501 565 8648",
    "sg:postcode":"72204",
    "sg:province":"AR",
    "wof:name":"Washington Enterprises LLC",
    "wof:placetype":"venue"
},
  "geometry": {"coordinates":[-92.351859,34.728285],"type":"Point"}
}