{
  "type": "Feature",
  "properties": {
    "iso:country":"US",
    "sg:address":"13555 Wilhelm Dr",
    "sg:city":"Alexander",
    "sg:classifiers":[
        {
            "category":"Manufacturing",
            "subcategory":"Apparel",
            "type":"Manufacturing & Wholesale Goods"
        }
    ],
    "sg:phone":"+1 501 316 2295",
    "sg:postcode":"72002",
    "sg:province":"AR",
    "wof:name":"Linda Gerrald",
    "wof:placetype":"venue"
},
  "geometry": {"coordinates":[-92.571634,34.690091],"type":"Point"}
}