{
  "type": "Feature",
  "properties": {
    "iso:country":"US",
    "sg:address":"405 E Railroad Ave",
    "sg:city":"Morrilton",
    "sg:classifiers":[
        {
            "category":"Wholesale",
            "subcategory":"Farm Supplies",
            "type":"Manufacturing & Wholesale Goods"
        }
    ],
    "sg:phone":"+1 501 354 4738",
    "sg:postcode":"72110",
    "sg:province":"AR",
    "sg:tags":[
        "feed",
        "concentrate",
        "supplement"
    ],
    "wof:name":"Mon-Ark Feed & Supply",
    "wof:placetype":"venue"
},
  "geometry": {"coordinates":[-92.740534,35.151644],"type":"Point"}
}