{
  "type": "Feature",
  "properties": {
    "addr:full":"400 Main St Crossett AR 71635",
    "addr:housenumber":"400",
    "addr:postcode":"71635",
    "addr:street":"Main St",
    "iso:country":"US",
    "sg:address":"400 Main St",
    "sg:city":"Crossett",
    "sg:classifiers":[
        {
            "category":"Health Services",
            "subcategory":"Nursing And Care Facility",
            "type":"Services"
        }
    ],
    "sg:phone":"+1 870 364 6401",
    "sg:postcode":"71635",
    "sg:province":"AR",
    "sg:tags":[
        "home",
        "retirement",
        "community"
    ],
    "wof:name":"F L & B Inc",
    "wof:placetype":"venue"
},
  "geometry": {"coordinates":[-91.96145300000001,33.131091],"type":"Point"}
}