{
  "type": "Feature",
  "properties": {
    "addr:full":"1006 Greene Rd 606 Paragould AR 72450",
    "addr:housenumber":"1006",
    "addr:postcode":"72450",
    "addr:street":"Greene Rd 606 Paragould",
    "iso:country":"US",
    "sg:address":"1006 Greene Rd 606",
    "sg:city":"Paragould",
    "sg:classifiers":[
        {
            "category":"Farming",
            "subcategory":"Farm",
            "type":"Manufacturing & Wholesale Goods"
        }
    ],
    "sg:phone":"+1 870 215 0739",
    "sg:postcode":"72450",
    "sg:province":"AR",
    "sg:tags":[
        "crop",
        "general"
    ],
    "wof:name":"Rld Farms LLC",
    "wof:placetype":"venue"
},
  "geometry": {"coordinates":[-90.62839099999999,36.08835],"type":"Point"}
}