{
  "type": "Feature",
  "properties": {
    "iso:country":"US",
    "sg:address":"406 W Oak St",
    "sg:city":"Mc Gehee",
    "sg:classifiers":[
        {
            "category":"Government",
            "subcategory":"Court House",
            "type":"Public Place"
        }
    ],
    "sg:phone":"+1 870 222 6885",
    "sg:postcode":"71654",
    "sg:province":"AR",
    "sg:tags":[
        "county"
    ],
    "wof:name":"Desha County Circuit Judge",
    "wof:placetype":"venue"
},
  "geometry": {"coordinates":[-91.399197,33.627862],"type":"Point"}
}