{
  "type": "Feature",
  "properties": {
    "iso:country":"US",
    "sg:address":"1500 W Shady Grove Rd",
    "sg:city":"Springdale",
    "sg:classifiers":[
        {
            "category":"Shopping",
            "subcategory":"Stationery & Office Supplies",
            "type":"Retail Goods"
        },
        {
            "category":"Wholesale",
            "subcategory":"Office Equipment",
            "type":"Manufacturing & Wholesale Goods"
        }
    ],
    "sg:phone":"+1 479 750 1777",
    "sg:postcode":"72764",
    "sg:province":"AR",
    "sg:tags":[
        "register",
        "autographic",
        "furniture"
    ],
    "wof:name":"Office Saver",
    "wof:placetype":"venue"
},
  "geometry": {"coordinates":[-94.148332,36.145706],"type":"Point"}
}