{
  "type": "Feature",
  "properties": {
    "iso:country":"US",
    "sg:address":"503 Walnut St",
    "sg:city":"Crossett",
    "sg:classifiers":[
        {
            "category":"Social Services",
            "type":"Services"
        },
        {
            "category":"Organizations",
            "subcategory":"Community Association",
            "type":"Services"
        }
    ],
    "sg:phone":"+1 870 364 3266",
    "sg:postcode":"71635",
    "sg:province":"AR",
    "wof:name":"Crossett Eagle Boosters",
    "wof:placetype":"venue"
},
  "geometry": {"coordinates":[-91.950668,33.129424],"type":"Point"}
}