{
  "type": "Feature",
  "properties": {
    "iso:country":"US",
    "sg:address":"5920 Highway 5 N",
    "sg:city":"Bryant",
    "sg:classifiers":[
        {
            "category":"Restaurant",
            "type":"Food & Drink"
        }
    ],
    "sg:phone":"+1 501 847 7771",
    "sg:postcode":"72022",
    "sg:province":"AR",
    "wof:name":"Super Suppers",
    "wof:placetype":"venue"
},
  "geometry": {"coordinates":[-92.499448,34.624675],"type":"Point"}
}