{
  "type": "Feature",
  "properties": {
    "addr:full":"210 Owl St Mc Gehee AR 71654",
    "addr:housenumber":"210",
    "addr:postcode":"71654",
    "addr:street":"Owl St;Gehee",
    "iso:country":"US",
    "sg:address":"210 Owl St",
    "sg:city":"Mc Gehee",
    "sg:classifiers":[
        {
            "category":"Autos & Motor Vehicles",
            "subcategory":"Automobile Sales",
            "type":"Retail Goods"
        }
    ],
    "sg:phone":"+1 870 222 5813",
    "sg:postcode":"71654",
    "sg:province":"AR",
    "sg:tags":[
        "car",
        "dealer"
    ],
    "wof:name":"King's Used Cars",
    "wof:placetype":"venue"
},
  "geometry": {"coordinates":[-91.382828,33.607424],"type":"Point"}
}