{
  "type": "Feature",
  "properties": {
    "iso:country":"US",
    "sg:address":"96 S Main St",
    "sg:city":"Strawberry",
    "sg:classifiers":[
        {
            "category":"Food & Beverages",
            "subcategory":"Groceries & Convenience Stores",
            "type":"Retail Goods"
        }
    ],
    "sg:phone":"+1 870 528 4311",
    "sg:postcode":"72469",
    "sg:province":"AR",
    "wof:name":"Strawberry Grocery",
    "wof:placetype":"venue"
},
  "geometry": {"coordinates":[-91.321341,35.965929],"type":"Point"}
}