{
  "type": "Feature",
  "properties": {
    "iso:country":"US",
    "sg:address":"220 E Main St",
    "sg:city":"Green Forest",
    "sg:classifiers":[
        {
            "category":"Professional",
            "subcategory":"Business Services",
            "type":"Services"
        }
    ],
    "sg:phone":"+1 870 438 5695",
    "sg:postcode":"72638",
    "sg:province":"AR",
    "wof:name":"Old Town Flea Market",
    "wof:placetype":"venue"
},
  "geometry": {"coordinates":[-93.434308,36.335431],"type":"Point"}
}