{
  "type": "Feature",
  "properties": {
    "iso:country":"US",
    "sg:address":"10853 State Hwy 336",
    "sg:city":"Clinton",
    "sg:classifiers":[
        {
            "category":"Freight",
            "type":"Transportation"
        }
    ],
    "sg:phone":"+1 501 277 9066",
    "sg:postcode":"72031",
    "sg:province":"AR",
    "sg:tags":[
        "local",
        "trucking"
    ],
    "wof:name":"Higher Authority Trucking",
    "wof:placetype":"venue"
},
  "geometry": {"coordinates":[-92.51546999999999,35.466992],"type":"Point"}
}