{
  "type": "Feature",
  "properties": {
    "iso:country":"US",
    "sg:address":"1004 Ash St",
    "sg:city":"Texarkana",
    "sg:classifiers":[
        {
            "category":"Organizations",
            "subcategory":"Religious Organization",
            "type":"Services"
        }
    ],
    "sg:phone":"+1 870 772 8802",
    "sg:postcode":"71854",
    "sg:province":"TX",
    "sg:tags":[
        "church"
    ],
    "wof:name":"Miles Chapel Church Parsonage",
    "wof:placetype":"venue"
},
  "geometry": {"coordinates":[-94.040879,33.433744],"type":"Point"}
}