{
  "type": "Feature",
  "properties": {
    "iso:country":"US",
    "sg:address":"207 Olive St",
    "sg:city":"Hot Springs",
    "sg:classifiers":[
        {
            "category":"Personal",
            "subcategory":"Tanning Parlor",
            "type":"Services"
        },
        {
            "category":"Arts & Performance",
            "subcategory":"Theater",
            "type":"Entertainment"
        }
    ],
    "sg:phone":"+1 501 609 0656",
    "sg:postcode":"71901",
    "sg:province":"AR",
    "sg:tags":[
        "salon",
        "group"
    ],
    "wof:name":"Johnson Tanning",
    "wof:placetype":"venue"
},
  "geometry": {"coordinates":[-93.054768,34.506662],"type":"Point"}
}