{
  "type": "Feature",
  "properties": {
    "iso:country":"US",
    "sg:address":"870 Mockingbird Cir",
    "sg:city":"Marmaduke",
    "sg:classifiers":[
        {
            "category":"Building & Trades",
            "subcategory":"Electrical",
            "type":"Services"
        }
    ],
    "sg:phone":"+1 870 586 9477",
    "sg:postcode":"72443",
    "sg:province":"AR",
    "sg:tags":[
        "electrical",
        "contractor"
    ],
    "wof:name":"Erosion Svc",
    "wof:placetype":"venue"
},
  "geometry": {"coordinates":[-90.50058300000001,36.216663],"type":"Point"}
}