{
  "type": "Feature",
  "properties": {
    "iso:country":"US",
    "sg:address":"1402 US Hwy 71",
    "sg:city":"Mena",
    "sg:classifiers":[
        {
            "category":"Health Services",
            "subcategory":"Doctor",
            "type":"Services"
        }
    ],
    "sg:phone":"+1 479 394 3540",
    "sg:postcode":"71953",
    "sg:province":"OK",
    "sg:tags":[
        "clinic"
    ],
    "wof:name":"Simpson Chiropractic Clinic",
    "wof:placetype":"venue"
},
  "geometry": {"coordinates":[-94.216292,34.586485],"type":"Point"}
}