{
  "type": "Feature",
  "properties": {
    "addr:full":"707 US Hwy 278 Monticello AR 71655",
    "addr:housenumber":"707",
    "addr:postcode":"71655",
    "addr:street":"Us Hwy 278",
    "iso:country":"US",
    "sg:address":"707 US Hwy 278",
    "sg:city":"Monticello",
    "sg:classifiers":[
        {
            "category":"Insurance",
            "subcategory":"Insurance Agent",
            "type":"Services"
        }
    ],
    "sg:phone":"+1 870 367 7000",
    "sg:postcode":"71655",
    "sg:province":"AR",
    "wof:name":"David Funderburg Insurance Inc",
    "wof:placetype":"venue"
},
  "geometry": {"coordinates":[-91.779865,33.628959],"type":"Point"}
}