{
  "type": "Feature",
  "properties": {
    "iso:country":"US",
    "sg:address":"6004 US Hwy 271",
    "sg:city":"Fort Smith",
    "sg:classifiers":[
        {
            "category":"Retail",
            "subcategory":"Auto Repair",
            "type":"Services"
        }
    ],
    "sg:phone":"+1 479 646 8361",
    "sg:postcode":"72908",
    "sg:province":"AR",
    "sg:tags":[
        "automotive",
        "wrecker"
    ],
    "wof:name":"Murphrees Towing and Recovery",
    "wof:placetype":"venue"
},
  "geometry": {"coordinates":[-94.422255,35.3247],"type":"Point"}
}