{
  "type": "Feature",
  "properties": {
    "addr:full":"821 Hogan Ln Conway AR 72034",
    "addr:housenumber":"821",
    "addr:postcode":"72034",
    "addr:street":"Hogan Ln",
    "iso:country":"US",
    "sg:address":"821 Hogan Ln",
    "sg:city":"Conway",
    "sg:classifiers":[
        {
            "category":"Personal",
            "subcategory":"Beauty Salon",
            "type":"Services"
        }
    ],
    "sg:phone":"+1 501 327 6245",
    "sg:postcode":"72034",
    "sg:province":"AR",
    "sg:tags":[
        "manicuring"
    ],
    "wof:name":"Paradise Nail Salon",
    "wof:placetype":"venue"
},
  "geometry": {"coordinates":[-92.49797599999999,35.091597],"type":"Point"}
}