{
  "type": "Feature",
  "properties": {
    "iso:country":"US",
    "sg:address":"4601 Fairway Ave",
    "sg:city":"North Little Rock",
    "sg:classifiers":[
        {
            "category":"Health Services",
            "subcategory":"Doctor",
            "type":"Services"
        }
    ],
    "sg:phone":"+1 501 758 7462",
    "sg:postcode":"72116",
    "sg:province":"AR",
    "wof:name":"Brad W Jolly",
    "wof:placetype":"venue"
},
  "geometry": {"coordinates":[-92.234897,34.796796],"type":"Point"}
}