{
  "type": "Feature",
  "properties": {
    "addr:full":"2832 Bella Vista Way Bella Vista AR 72714",
    "addr:housenumber":"2832",
    "addr:postcode":"72714",
    "addr:street":"Bella Vista Way",
    "iso:country":"US",
    "sg:address":"2832 Bella Vista Way",
    "sg:city":"Bella Vista",
    "sg:classifiers":[
        {
            "category":"Health Services",
            "subcategory":"Doctor",
            "type":"Services"
        }
    ],
    "sg:phone":"+1 479 855 6049",
    "sg:postcode":"72714",
    "sg:province":"AR",
    "sg:tags":[
        "medical"
    ],
    "wof:name":"State Farm Insurance",
    "wof:placetype":"venue"
},
  "geometry": {"coordinates":[-94.23629200000001,36.437403],"type":"Point"}
}