{
  "type": "Feature",
  "properties": {
    "addr:full":"2910 Pines Mall Dr Pine Bluff AR 71601",
    "addr:housenumber":"2910",
    "addr:postcode":"71601",
    "addr:street":"Pines Mall Dr",
    "iso:country":"US",
    "sg:address":"2910 Pines Mall Dr",
    "sg:city":"Pine Bluff",
    "sg:classifiers":[
        {
            "category":"Restaurant",
            "type":"Food & Drink"
        }
    ],
    "sg:menulink":"http://www.allmenus.com/ar/vaugine/173992-wendys/menu/",
    "sg:phone":"+1 870 536 3576",
    "sg:postcode":"71601",
    "sg:province":"AR",
    "sg:tags":[
        "burger",
        "american",
        "soup"
    ],
    "wof:name":"Wendy's",
    "wof:placetype":"venue"
},
  "geometry": {"coordinates":[-91.96704699999999,34.21156],"type":"Point"}
}