{
  "type": "Feature",
  "properties": {
    "addr:full":"2322 Cantrell Rd Little Rock AR 72202",
    "addr:housenumber":"2322",
    "addr:postcode":"72202",
    "addr:street":"Cantrell Rd",
    "iso:country":"US",
    "sg:address":"2322 Cantrell Rd",
    "sg:city":"Little Rock",
    "sg:classifiers":[
        {
            "category":"Shopping",
            "subcategory":"Used Merchandise",
            "type":"Retail Goods"
        }
    ],
    "sg:phone":"+1 501 375 4242",
    "sg:postcode":"72202",
    "sg:province":"AR",
    "sg:tags":[
        "furniture"
    ],
    "wof:name":"Office Furniture Liquidator",
    "wof:placetype":"venue"
},
  "geometry": {"coordinates":[-92.30290599999999,34.758144],"type":"Point"}
}