{
  "type": "Feature",
  "properties": {
    "iso:country":"US",
    "sg:address":"1008 Quapaw Dr",
    "sg:city":"Redfield",
    "sg:classifiers":[
        {
            "category":"Building & Trades",
            "subcategory":"Construction",
            "type":"Services"
        }
    ],
    "sg:phone":"+1 501 397 5077",
    "sg:postcode":"72132",
    "sg:province":"AR",
    "sg:tags":[
        "general"
    ],
    "wof:name":"JRC Construction Inc",
    "wof:placetype":"venue"
},
  "geometry": {"coordinates":[-92.189413,34.429697],"type":"Point"}
}