{
  "type": "Feature",
  "properties": {
    "iso:country":"US",
    "sg:address":"3100 S Reynolds Rd",
    "sg:city":"Bauxite",
    "sg:classifiers":[
        {
            "category":"Manufacturing",
            "subcategory":"Paper Products",
            "type":"Manufacturing & Wholesale Goods"
        }
    ],
    "sg:phone":"+1 501 557 5595",
    "sg:postcode":"72011",
    "sg:province":"AR",
    "sg:tags":[
        "converted",
        "business",
        "mfg"
    ],
    "wof:name":"L E G S",
    "wof:placetype":"venue"
},
  "geometry": {"coordinates":[-92.495842,34.565213],"type":"Point"}
}