{
  "type": "Feature",
  "properties": {
    "iso:country":"US",
    "sg:address":"3101 SE 14th St",
    "sg:city":"Bentonville",
    "sg:classifiers":[
        {
            "category":"Health Services",
            "subcategory":"Doctor",
            "type":"Services"
        }
    ],
    "sg:phone":"+1 479 986 6155",
    "sg:postcode":"72712",
    "sg:province":"AR",
    "sg:tags":[
        "physician",
        "family",
        "practice",
        "surgeons",
        "medicine",
        "surgeon"
    ],
    "sg:website":"http://www.mercy4u.com/",
    "wof:name":"Mercy Health Center: Garrett David MD",
    "wof:placetype":"venue"
},
  "geometry": {"coordinates":[-94.176147,36.356319],"type":"Point"}
}