{
  "type": "Feature",
  "properties": {
    "iso:country":"US",
    "sg:address":"1421 Falls Blvd S",
    "sg:city":"Wynne",
    "sg:classifiers":[
        {
            "category":"Community Center",
            "subcategory":"Senior",
            "type":"Public Place"
        },
        {
            "category":"Health Services",
            "subcategory":"Nursing And Care Facility",
            "type":"Services"
        },
        {
            "category":"Health Services",
            "subcategory":"Health Practitioner",
            "type":"Services"
        },
        {
            "category":"Social Services",
            "subcategory":"Adult Care",
            "type":"Services"
        }
    ],
    "sg:phone":"+1 870 238 3816",
    "sg:postcode":"72396",
    "sg:province":"AR",
    "sg:tags":[
        "home",
        "counseling",
        "eldercare-home",
        "citizen"
    ],
    "sg:website":"http://www.e4aonline.com",
    "wof:name":"East Arkansas Area Agency On Aging",
    "wof:placetype":"venue"
},
  "geometry": {"coordinates":[-90.78913,35.212306],"type":"Point"}
}