{
  "type": "Feature",
  "properties": {
    "addr:full":"1002 S Wood St Stuttgart AR 72160",
    "addr:housenumber":"1002",
    "addr:postcode":"72160",
    "addr:street":"S Wood St",
    "iso:country":"US",
    "sg:address":"1002 S Wood St",
    "sg:city":"Stuttgart",
    "sg:classifiers":[
        {
            "category":"Personal",
            "subcategory":"Beauty Salon",
            "type":"Services"
        }
    ],
    "sg:phone":"+1 870 747 3445",
    "sg:postcode":"72160",
    "sg:province":"AR",
    "sg:tags":[
        "shop"
    ],
    "wof:name":"Ohimis Beauty Shop",
    "wof:placetype":"venue"
},
  "geometry": {"coordinates":[-91.545506,34.493772],"type":"Point"}
}