{
  "type": "Feature",
  "properties": {
    "iso:country":"US",
    "sg:address":"11050 State Hwy 59",
    "sg:city":"Gravette",
    "sg:classifiers":[
        {
            "category":"Building & Trades",
            "subcategory":"Construction",
            "type":"Services"
        }
    ],
    "sg:phone":"+1 479 787 5459",
    "sg:postcode":"72736",
    "sg:province":"AR",
    "sg:tags":[
        "contractor"
    ],
    "wof:name":"Garrett Workshop",
    "wof:placetype":"venue"
},
  "geometry": {"coordinates":[-94.44163399999999,36.389507],"type":"Point"}
}