{
  "type": "Feature",
  "properties": {
    "addr:full":"101 Schuman St Foreman AR 71836",
    "addr:housenumber":"101",
    "addr:postcode":"71836",
    "addr:street":"Schuman St",
    "iso:country":"US",
    "sg:address":"101 Schuman St",
    "sg:city":"Foreman",
    "sg:classifiers":[
        {
            "category":"Personal",
            "subcategory":"Beauty Salon",
            "type":"Services"
        }
    ],
    "sg:phone":"+1 870 542 6115",
    "sg:postcode":"71836",
    "sg:province":"AR",
    "wof:name":"Debbies Family Hair Care",
    "wof:placetype":"venue"
},
  "geometry": {"coordinates":[-94.39707900000001,33.720604],"type":"Point"}
}