{
  "type": "Feature",
  "properties": {
    "iso:country":"US",
    "sg:address":"1054 Race Rd",
    "sg:city":"Pottsville",
    "sg:classifiers":[
        {
            "category":"Wholesale",
            "subcategory":"Poultry",
            "type":"Manufacturing & Wholesale Goods"
        }
    ],
    "sg:phone":"+1 479 968 3215",
    "sg:postcode":"72858",
    "sg:province":"AR",
    "sg:tags":[
        "farm"
    ],
    "wof:name":"Danny E Davis Poultry Far",
    "wof:placetype":"venue"
},
  "geometry": {"coordinates":[-93.059601,35.194823],"type":"Point"}
}