{
  "type": "Feature",
  "properties": {
    "iso:country":"US",
    "sg:address":"308 W Main St",
    "sg:city":"Cabot",
    "sg:classifiers":[
        {
            "category":"Insurance",
            "subcategory":"Insurance Agent",
            "type":"Services"
        }
    ],
    "sg:phone":"+1 501 941 2886",
    "sg:postcode":"72023",
    "sg:province":"AR",
    "wof:name":"Doug Wilson Insurance Agency",
    "wof:placetype":"venue"
},
  "geometry": {"coordinates":[-92.018879,34.975374],"type":"Point"}
}