{
  "type": "Feature",
  "properties": {
    "iso:country":"US",
    "sg:address":"1016 E Main St",
    "sg:city":"Magnolia",
    "sg:classifiers":[
        {
            "category":"Food & Beverages",
            "subcategory":"Groceries & Convenience Stores",
            "type":"Retail Goods"
        }
    ],
    "sg:phone":"+1 870 234 7704",
    "sg:postcode":"71753",
    "sg:province":"AR",
    "sg:tags":[
        "station"
    ],
    "wof:name":"Fire Ball Express",
    "wof:placetype":"venue"
},
  "geometry": {"coordinates":[-93.22759600000001,33.266898],"type":"Point"}
}