{
  "type": "Feature",
  "properties": {
    "addr:full":"9 Westwood Ct Pine Bluff AR 71601",
    "addr:housenumber":"9",
    "addr:postcode":"71601",
    "addr:street":"Westwood Ct",
    "iso:country":"US",
    "sg:address":"9 Westwood Ct",
    "sg:city":"Pine Bluff",
    "sg:classifiers":[
        {
            "category":"Professional",
            "subcategory":"Management & Consulting",
            "type":"Services"
        }
    ],
    "sg:phone":"+1 870 536 2031",
    "sg:postcode":"71601",
    "sg:province":"AR",
    "sg:tags":[
        "retail",
        "direct",
        "sales"
    ],
    "wof:name":"Gardenias",
    "wof:placetype":"venue"
},
  "geometry": {"coordinates":[-92.02038,34.250873],"type":"Point"}
}