{
  "type": "Feature",
  "properties": {
    "addr:full":"101 Polk St N Mena OK 71953",
    "addr:housenumber":"101",
    "addr:postcode":"71953",
    "addr:street":"Polk St N",
    "iso:country":"US",
    "sg:address":"101 Polk St N",
    "sg:city":"Mena",
    "sg:classifiers":[
        {
            "category":"Home & Garden",
            "subcategory":"Furniture",
            "type":"Retail Goods"
        }
    ],
    "sg:phone":"+1 479 243 3119",
    "sg:postcode":"71953",
    "sg:province":"OK",
    "wof:name":"Martin's Furniture",
    "wof:placetype":"venue"
},
  "geometry": {"coordinates":[-94.25136500000001,34.589925],"type":"Point"}
}