{
  "type": "Feature",
  "properties": {
    "iso:country":"US",
    "sg:address":"3001 Peach Tree Dr",
    "sg:city":"Little Rock",
    "sg:classifiers":[
        {
            "category":"Building & Trades",
            "subcategory":"Construction",
            "type":"Services"
        }
    ],
    "sg:phone":"+1 501 224 2316",
    "sg:postcode":"72211",
    "sg:province":"AR",
    "sg:tags":[
        "house"
    ],
    "wof:name":"Sweetland Construction",
    "wof:placetype":"venue"
},
  "geometry": {"coordinates":[-92.401768,34.729341],"type":"Point"}
}