{
  "type": "Feature",
  "properties": {
    "iso:country":"US",
    "sg:address":"9016 Highway 90",
    "sg:city":"Rector",
    "sg:classifiers":[
        {
            "category":"Building & Trades",
            "subcategory":"Equipment Rental",
            "type":"Services"
        }
    ],
    "sg:phone":"+1 870 566 2446",
    "sg:postcode":"72461",
    "sg:province":"AR",
    "sg:tags":[
        "yard",
        "leasing",
        "store"
    ],
    "wof:name":"Dbkr Rentals",
    "wof:placetype":"venue"
},
  "geometry": {"coordinates":[-90.294954,36.312126],"type":"Point"}
}