{
  "type": "Feature",
  "properties": {
    "iso:country":"US",
    "sg:address":"227 Co Rd 457",
    "sg:city":"Jonesboro",
    "sg:classifiers":[
        {
            "category":"Building & Trades",
            "subcategory":"Construction",
            "type":"Services"
        }
    ],
    "sg:phone":"+1 870 972 0835",
    "sg:postcode":"72404",
    "sg:province":"AR",
    "sg:tags":[
        "house"
    ],
    "wof:name":"J&D Builders Inc",
    "wof:placetype":"venue"
},
  "geometry": {"coordinates":[-90.667317,35.716839],"type":"Point"}
}