{
  "type": "Feature",
  "properties": {
    "addr:full":"2633 Laurel Cir Rogers AR 72758",
    "addr:housenumber":"2633",
    "addr:postcode":"72758",
    "addr:street":"Laurel Cir",
    "iso:country":"US",
    "sg:address":"2633 Laurel Cir",
    "sg:city":"Rogers",
    "sg:classifiers":[
        {
            "category":"Food & Beverages",
            "subcategory":"Liquor & Beverages",
            "type":"Retail Goods"
        }
    ],
    "sg:phone":"+1 479 636 3397",
    "sg:postcode":"72758",
    "sg:province":"AR",
    "sg:tags":[
        "dry",
        "ice"
    ],
    "wof:name":"Naco 2",
    "wof:placetype":"venue"
},
  "geometry": {"coordinates":[-94.12532,36.290846],"type":"Point"}
}