{
  "type": "Feature",
  "properties": {
    "iso:country":"US",
    "sg:address":"416 S 8th St",
    "sg:city":"Rogers",
    "sg:classifiers":[
        {
            "category":"Restaurant",
            "type":"Food & Drink"
        }
    ],
    "sg:phone":"+1 479 636 1120",
    "sg:postcode":"72756",
    "sg:province":"AR",
    "wof:name":"Kelly's Cafe",
    "wof:placetype":"venue"
},
  "geometry": {"coordinates":[-94.125744,36.330033],"type":"Point"}
}