{
  "type": "Feature",
  "properties": {
    "addr:full":"800 E Harding St Morrilton AR 72110",
    "addr:housenumber":"800",
    "addr:postcode":"72110",
    "addr:street":"E Harding St",
    "iso:country":"US",
    "sg:address":"800 E Harding St",
    "sg:city":"Morrilton",
    "sg:classifiers":[
        {
            "category":"Autos & Motor Vehicles",
            "subcategory":"Auto Supplies",
            "type":"Retail Goods"
        }
    ],
    "sg:phone":"+1 501 354 8005",
    "sg:postcode":"72110",
    "sg:province":"AR",
    "sg:tags":[
        "automobile",
        "parts"
    ],
    "wof:name":"O'REILLY Auto Parts",
    "wof:placetype":"venue"
},
  "geometry": {"coordinates":[-92.733609,35.163008],"type":"Point"}
}