{
  "type": "Feature",
  "properties": {
    "addr:full":"9700 N Rodney Parham Rd Little Rock AR 72227",
    "addr:housenumber":"9700",
    "addr:postcode":"72227",
    "addr:street":"N;Parham Rd",
    "iso:country":"US",
    "sg:address":"9700 N Rodney Parham Rd",
    "sg:city":"Little Rock",
    "sg:classifiers":[
        {
            "category":"Restaurant",
            "type":"Food & Drink"
        }
    ],
    "sg:phone":"+1 501 537 2357",
    "sg:postcode":"72227",
    "sg:province":"AR",
    "sg:tags":[
        "eating"
    ],
    "wof:name":"Legends",
    "wof:placetype":"venue"
},
  "geometry": {"coordinates":[-92.383381,34.762565],"type":"Point"}
}