{
  "type": "Feature",
  "properties": {
    "addr:full":"1802 E Broadway St N Little Rock AR 72114",
    "addr:housenumber":"1802",
    "addr:postcode":"72114",
    "addr:street":"E Broadway St N",
    "iso:country":"US",
    "sg:address":"1802 E Broadway St",
    "sg:city":"N Little Rock",
    "sg:classifiers":[
        {
            "category":"Autos & Motor Vehicles",
            "subcategory":"Automobile Sales",
            "type":"Retail Goods"
        }
    ],
    "sg:phone":"+1 501 378 7704",
    "sg:postcode":"72114",
    "sg:province":"AR",
    "sg:tags":[
        "car",
        "dealer"
    ],
    "wof:name":"Car-Mart",
    "wof:placetype":"venue"
},
  "geometry": {"coordinates":[-92.246262,34.75548],"type":"Point"}
}