{
  "type": "Feature",
  "properties": {
    "addr:full":"7712 Wooded Hills Rd Harrison AR 72601",
    "addr:housenumber":"7712",
    "addr:postcode":"72601",
    "addr:street":"Wooded Hills Rd",
    "iso:country":"US",
    "sg:address":"7712 Wooded Hills Rd",
    "sg:city":"Harrison",
    "sg:classifiers":[
        {
            "category":"Building & Trades",
            "subcategory":"Landscaping Services",
            "type":"Services"
        }
    ],
    "sg:phone":"+1 870 741 7100",
    "sg:postcode":"72601",
    "sg:province":"AR",
    "wof:name":"Yard Doctor",
    "wof:placetype":"venue"
},
  "geometry": {"coordinates":[-93.070528,36.313416],"type":"Point"}
}