{
  "type": "Feature",
  "properties": {
    "addr:full":"8931 Fresno Ct Fort Smith AR 72903",
    "addr:housenumber":"8931",
    "addr:postcode":"72903",
    "addr:street":"Fresno Ct",
    "iso:country":"US",
    "sg:address":"8931 Fresno Ct",
    "sg:city":"Fort Smith",
    "sg:classifiers":[
        {
            "category":"Building & Trades",
            "subcategory":"Construction",
            "type":"Services"
        }
    ],
    "sg:phone":"+1 479 478 8753",
    "sg:postcode":"72903",
    "sg:province":"AR",
    "sg:tags":[
        "contractor"
    ],
    "wof:name":"Cowboy Contracting",
    "wof:placetype":"venue"
},
  "geometry": {"coordinates":[-94.33291,35.349261],"type":"Point"}
}