{
  "type": "Feature",
  "properties": {
    "iso:country":"US",
    "sg:address":"18319 S Alexander Rd",
    "sg:city":"Alexander",
    "sg:classifiers":[
        {
            "category":"Retail",
            "subcategory":"Car Wash",
            "type":"Services"
        }
    ],
    "sg:phone":"+1 501 305 9528",
    "sg:postcode":"72002",
    "sg:province":"AR",
    "wof:name":"Sunshine Detailing",
    "wof:placetype":"venue"
},
  "geometry": {"coordinates":[-92.442928,34.580244],"type":"Point"}
}