{
  "type": "Feature",
  "properties": {
    "addr:full":"1206 N 8th St Rogers AR 72756",
    "addr:housenumber":"1206",
    "addr:postcode":"72756",
    "addr:street":"N 8Th St",
    "iso:country":"US",
    "sg:address":"1206 N 8th St",
    "sg:city":"Rogers",
    "sg:classifiers":[
        {
            "category":"Shopping",
            "type":"Retail Goods"
        }
    ],
    "sg:phone":"+1 479 986 0900",
    "sg:postcode":"72756",
    "sg:province":"AR",
    "sg:tags":[
        "wedding",
        "supply"
    ],
    "wof:name":"Chateau De L'Amour",
    "wof:placetype":"venue"
},
  "geometry": {"coordinates":[-94.125523,36.347624],"type":"Point"}
}