{
  "type": "Feature",
  "properties": {
    "addr:full":"615 E 2nd St S Prescott AR 71857",
    "addr:housenumber":"615",
    "addr:postcode":"71857",
    "addr:street":"E 2Nd St S",
    "iso:country":"US",
    "sg:address":"615 E 2nd St S",
    "sg:city":"Prescott",
    "sg:classifiers":[
        {
            "category":"Organizations",
            "subcategory":"Religious Organization",
            "type":"Services"
        }
    ],
    "sg:phone":"+1 870 887 5031",
    "sg:postcode":"71857",
    "sg:province":"AR",
    "wof:name":"Central Baptist Church",
    "wof:placetype":"venue"
},
  "geometry": {"coordinates":[-93.38413799999999,33.79775],"type":"Point"}
}