{
  "type": "Feature",
  "properties": {
    "addr:full":"15410 Quail Rd Fayetteville AR 72704",
    "addr:housenumber":"15410",
    "addr:postcode":"72704",
    "addr:street":"Quail Rd",
    "iso:country":"US",
    "sg:address":"15410 Quail Rd",
    "sg:city":"Fayetteville",
    "sg:classifiers":[
        {
            "category":"Real Estate",
            "subcategory":"Real Estate Agent",
            "type":"Services"
        }
    ],
    "sg:phone":"+1 479 957 3056",
    "sg:postcode":"72704",
    "sg:province":"AR",
    "sg:tags":[
        "inspection"
    ],
    "wof:name":"Covenant Property Evaluations",
    "wof:placetype":"venue"
},
  "geometry": {"coordinates":[-94.299077,36.083514],"type":"Point"}
}