{
  "type": "Feature",
  "properties": {
    "addr:full":"350 Hubbard Rd Conway AR 72034",
    "addr:housenumber":"350",
    "addr:postcode":"72034",
    "addr:street":"Hubbard Rd",
    "iso:country":"US",
    "sg:address":"350 Hubbard Rd",
    "sg:city":"Conway",
    "sg:classifiers":[
        {
            "category":"Organizations",
            "subcategory":"Non-profit Organization",
            "type":"Services"
        },
        {
            "category":"Health Services",
            "subcategory":"Nursing And Care Facility",
            "type":"Services"
        }
    ],
    "sg:phone":"+1 501 329 1703",
    "sg:postcode":"72034",
    "sg:province":"AR",
    "sg:tags":[
        "intermediate"
    ],
    "wof:name":"Creative Leaving",
    "wof:placetype":"venue"
},
  "geometry": {"coordinates":[-92.467208,35.083291],"type":"Point"}
}