{
  "type": "Feature",
  "properties": {
    "iso:country":"US",
    "sg:address":"200 W 1st St",
    "sg:city":"Fordyce",
    "sg:classifiers":[
        {
            "category":"Personal",
            "subcategory":"Barber",
            "type":"Services"
        }
    ],
    "sg:phone":"+1 870 352 5523",
    "sg:postcode":"71742",
    "sg:province":"AR",
    "sg:tags":[
        "shop"
    ],
    "wof:name":"Crains Barber Shop",
    "wof:placetype":"venue"
},
  "geometry": {"coordinates":[-92.41249999999999,33.81099],"type":"Point"}
}