{
  "type": "Feature",
  "properties": {
    "iso:country":"US",
    "sg:address":"3013 Lewis St",
    "sg:city":"Little Rock",
    "sg:classifiers":[
        {
            "category":"Recreation",
            "type":"Entertainment"
        }
    ],
    "sg:phone":"+1 501 664 4595",
    "sg:postcode":"72204",
    "sg:province":"AR",
    "sg:tags":[
        "martial",
        "arts",
        "instruction"
    ],
    "wof:name":"Albert De Mers",
    "wof:placetype":"venue"
},
  "geometry": {"coordinates":[-92.32077200000001,34.723949],"type":"Point"}
}