{
  "type": "Feature",
  "properties": {
    "iso:country":"US",
    "sg:address":"1820 Zero St",
    "sg:city":"Fort Smith",
    "sg:classifiers":[
        {
            "category":"Restaurant",
            "type":"Food & Drink"
        }
    ],
    "sg:phone":"+1 479 785 4998",
    "sg:postcode":"72908",
    "sg:province":"AR",
    "sg:tags":[
        "eating"
    ],
    "wof:name":"KFC",
    "wof:placetype":"venue"
},
  "geometry": {"coordinates":[-94.413545,35.327834],"type":"Point"}
}