{
  "type": "Feature",
  "properties": {
    "iso:country":"US",
    "sg:address":"804 Edgewood Dr",
    "sg:city":"Bryant",
    "sg:classifiers":[
        {
            "category":"Professional",
            "subcategory":"Computer Services",
            "type":"Services"
        }
    ],
    "sg:phone":"+1 501 734 0017",
    "sg:postcode":"72022",
    "sg:province":"AR",
    "sg:tags":[
        "internet"
    ],
    "wof:name":"Soft WYRE",
    "wof:placetype":"venue"
},
  "geometry": {"coordinates":[-92.50241800000001,34.613568],"type":"Point"}
}