{
  "type": "Feature",
  "properties": {
    "iso:country":"US",
    "sg:address":"7000 Asher Ave",
    "sg:city":"Little Rock",
    "sg:classifiers":[
        {
            "category":"Restaurant",
            "type":"Food & Drink"
        }
    ],
    "sg:phone":"+1 501 562 8212",
    "sg:postcode":"72204",
    "sg:province":"AR",
    "wof:name":"LA-Guadalubana",
    "wof:placetype":"venue"
},
  "geometry": {"coordinates":[-92.352883,34.717962],"type":"Point"}
}