{
  "type": "Feature",
  "properties": {
    "iso:country":"US",
    "sg:address":"504 Walker Rd",
    "sg:city":"Lavaca",
    "sg:classifiers":[
        {
            "category":"Farming",
            "subcategory":"Livestock Farm",
            "type":"Manufacturing & Wholesale Goods"
        }
    ],
    "sg:phone":"+1 479 674 5528",
    "sg:postcode":"72941",
    "sg:province":"AR",
    "sg:tags":[
        "beef",
        "feedlot",
        "cattle"
    ],
    "wof:name":"Lloyd W Walker",
    "wof:placetype":"venue"
},
  "geometry": {"coordinates":[-94.172283,35.315791],"type":"Point"}
}