{
  "type": "Feature",
  "properties": {
    "iso:country":"US",
    "sg:address":"2333 N College Ave",
    "sg:city":"Fayetteville",
    "sg:classifiers":[
        {
            "category":"Shopping",
            "type":"Retail Goods"
        }
    ],
    "sg:phone":"+1 479 443 7262",
    "sg:postcode":"72703",
    "sg:province":"AR",
    "sg:tags":[
        "art",
        "gallery",
        "dealer"
    ],
    "wof:name":"Duck Club Gallery",
    "wof:placetype":"venue"
},
  "geometry": {"coordinates":[-94.152916,36.09448],"type":"Point"}
}