{
  "type": "Feature",
  "properties": {
    "iso:country":"US",
    "sg:address":"1406 SE 5th St",
    "sg:city":"Bentonville",
    "sg:classifiers":[
        {
            "category":"Manufacturing",
            "subcategory":"Glass & Minerals",
            "type":"Manufacturing & Wholesale Goods"
        }
    ],
    "sg:phone":"+1 479 273 9545",
    "sg:postcode":"72712",
    "sg:province":"AR",
    "sg:tags":[
        "ready"
    ],
    "wof:name":"Mid-Continent Concrete Co",
    "wof:placetype":"venue"
},
  "geometry": {"coordinates":[-94.188002,36.367425],"type":"Point"}
}