{
  "type": "Feature",
  "properties": {
    "iso:country":"US",
    "sg:address":"412 Sturgis Rd",
    "sg:city":"Conway",
    "sg:classifiers":[
        {
            "category":"Building & Trades",
            "subcategory":"Construction",
            "type":"Services"
        }
    ],
    "sg:phone":"+1 501 470 0850",
    "sg:postcode":"72034",
    "sg:province":"AR",
    "sg:tags":[
        "concrete",
        "contractor"
    ],
    "wof:name":"Laskers Inc",
    "wof:placetype":"venue"
},
  "geometry": {"coordinates":[-92.418194,34.997597],"type":"Point"}
}