{
  "type": "Feature",
  "properties": {
    "iso:country":"US",
    "sg:address":"721 Skyview Dr",
    "sg:city":"Greenwood",
    "sg:classifiers":[
        {
            "category":"Ice Cream",
            "type":"Food & Drink"
        }
    ],
    "sg:phone":"+1 479 650 3427",
    "sg:postcode":"72936",
    "sg:province":"AR",
    "wof:name":"The Dog Pound Ice Cream Parlor",
    "wof:placetype":"venue"
},
  "geometry": {"coordinates":[-94.21691,35.201463],"type":"Point"}
}