{
  "type": "Feature",
  "properties": {
    "iso:country":"US",
    "sg:address":"919 W 4th St",
    "sg:city":"Rector",
    "sg:classifiers":[
        {
            "category":"Building & Trades",
            "subcategory":"Plumbing",
            "type":"Services"
        }
    ],
    "sg:phone":"+1 870 595 3373",
    "sg:postcode":"72461",
    "sg:province":"AR",
    "sg:tags":[
        "septic"
    ],
    "wof:name":"Watson Septic Svc",
    "wof:placetype":"venue"
},
  "geometry": {"coordinates":[-90.30274199999999,36.263618],"type":"Point"}
}