{
  "type": "Feature",
  "properties": {
    "iso:country":"US",
    "sg:address":"425 Helen St",
    "sg:city":"West Helena",
    "sg:classifiers":[
        {
            "category":"Banks & Credit Unions",
            "subcategory":"Bank",
            "type":"Services"
        }
    ],
    "sg:phone":"+1 870 572 3481",
    "sg:postcode":"72390",
    "sg:province":"AR",
    "wof:name":"First National Bank - Phillips",
    "wof:placetype":"venue"
},
  "geometry": {"coordinates":[-90.645247,34.551348],"type":"Point"}
}