{
  "type": "Feature",
  "properties": {
    "iso:country":"US",
    "sg:address":"21228 Dawn Hill Rd E",
    "sg:city":"Siloam Springs",
    "sg:classifiers":[
        {
            "category":"Shopping",
            "subcategory":"Crafts & Fabrics",
            "type":"Retail Goods"
        }
    ],
    "sg:phone":"+1 479 736 2802",
    "sg:postcode":"72761",
    "sg:province":"OK",
    "sg:tags":[
        "sewing"
    ],
    "wof:name":"Sew Fine Custom Sewing",
    "wof:placetype":"venue"
},
  "geometry": {"coordinates":[-94.50512,36.235532],"type":"Point"}
}