{
  "type": "Feature",
  "properties": {
    "addr:full":"230 Newman Dr N Little Rock AR 72117",
    "addr:housenumber":"230",
    "addr:postcode":"72117",
    "addr:street":"Newman Dr N",
    "iso:country":"US",
    "sg:address":"230 Newman Dr",
    "sg:city":"N Little Rock",
    "sg:classifiers":[
        {
            "category":"Manufacturing",
            "subcategory":"Printing",
            "type":"Manufacturing & Wholesale Goods"
        }
    ],
    "sg:phone":"+1 501 945 7477",
    "sg:postcode":"72117",
    "sg:province":"AR",
    "sg:tags":[
        "printer"
    ],
    "wof:name":"PIP Printing",
    "wof:placetype":"venue"
},
  "geometry": {"coordinates":[-92.206723,34.804433],"type":"Point"}
}