{
  "type": "Feature",
  "properties": {
    "addr:full":"342 Meyers Creek Rd Royal AR 71968",
    "addr:housenumber":"342",
    "addr:postcode":"71968",
    "addr:street":"Meyers Creek Rd",
    "iso:country":"US",
    "sg:address":"342 Meyers Creek Rd",
    "sg:city":"Royal",
    "sg:classifiers":[
        {
            "category":"Shopping",
            "type":"Retail Goods"
        }
    ],
    "sg:phone":"+1 501 991 3739",
    "sg:postcode":"71968",
    "sg:province":"AR",
    "sg:tags":[
        "ice"
    ],
    "wof:name":"Crystal Springs Ice Company",
    "wof:placetype":"venue"
},
  "geometry": {"coordinates":[-93.358574,34.464648],"type":"Point"}
}