{
  "type": "Feature",
  "properties": {
    "addr:full":"2001 Midyett St Beebe AR 72012",
    "addr:housenumber":"2001",
    "addr:postcode":"72012",
    "addr:street":"Midyett St",
    "iso:country":"US",
    "sg:address":"2001 Midyett St",
    "sg:city":"Beebe",
    "sg:classifiers":[
        {
            "category":"Retail",
            "subcategory":"Auto Repair",
            "type":"Services"
        }
    ],
    "sg:phone":"+1 501 882 1065",
    "sg:postcode":"72012",
    "sg:province":"AR",
    "sg:tags":[
        "repairing",
        "automobile"
    ],
    "wof:name":"J & S Auto Sales",
    "wof:placetype":"venue"
},
  "geometry": {"coordinates":[-91.908787,35.070493],"type":"Point"}
}