{
  "type": "Feature",
  "properties": {
    "iso:country":"US",
    "sg:address":"524 Sherwood Ave",
    "sg:city":"Mena",
    "sg:classifiers":[
        {
            "category":"Travel",
            "subcategory":"Travel Agent",
            "type":"Entertainment"
        }
    ],
    "sg:phone":"+1 479 394 1334",
    "sg:postcode":"71953",
    "sg:province":"AR",
    "sg:tags":[
        "agency",
        "bureau"
    ],
    "wof:name":"Fare Finders Travel Inc",
    "wof:placetype":"venue"
},
  "geometry": {"coordinates":[-94.235811,34.583253],"type":"Point"}
}