{
  "type": "Feature",
  "properties": {
    "addr:full":"216 E Emma Ave Springdale AR 72764",
    "addr:housenumber":"216",
    "addr:postcode":"72764",
    "addr:street":"E Emma Ave",
    "iso:country":"US",
    "sg:address":"216 E Emma Ave",
    "sg:city":"Springdale",
    "sg:classifiers":[
        {
            "category":"Banks & Credit Unions",
            "subcategory":"Atm",
            "type":"Services"
        }
    ],
    "sg:phone":"+1 479 927 9062",
    "sg:postcode":"72764",
    "sg:province":"AR",
    "sg:tags":[
        "bankruptcy"
    ],
    "wof:name":"Adams & Brady",
    "wof:placetype":"venue"
},
  "geometry": {"coordinates":[-94.12930299999999,36.184799],"type":"Point"}
}