{
  "type": "Feature",
  "properties": {
    "iso:country":"US",
    "sg:address":"12099 Landers Rd",
    "sg:city":"Rogers",
    "sg:classifiers":[
        {
            "category":"Retail",
            "subcategory":"Laundry & Dry Cleaning",
            "type":"Services"
        }
    ],
    "sg:phone":"+1 479 936 8636",
    "sg:postcode":"72756",
    "sg:province":"AR",
    "sg:tags":[
        "cleaners",
        "rug",
        "carpet"
    ],
    "wof:name":"Blue Ribbon Svc",
    "wof:placetype":"venue"
},
  "geometry": {"coordinates":[-94.097305,36.400267],"type":"Point"}
}