{
  "type": "Feature",
  "properties": {
    "addr:full":"300 S 8th St Rogers AR 72756",
    "addr:housenumber":"300",
    "addr:postcode":"72756",
    "addr:street":"S 8Th St",
    "iso:country":"US",
    "sg:address":"300 S 8th St",
    "sg:city":"Rogers",
    "sg:classifiers":[
        {
            "category":"Autos & Motor Vehicles",
            "subcategory":"Automobile Sales",
            "type":"Retail Goods"
        }
    ],
    "sg:phone":"+1 479 636 0998",
    "sg:postcode":"72756",
    "sg:province":"AR",
    "sg:tags":[
        "dealers-used",
        "car",
        "used",
        "cars-wholesale"
    ],
    "wof:name":"Supermercado La Villita",
    "wof:placetype":"venue"
},
  "geometry": {"coordinates":[-94.125671,36.33152],"type":"Point"}
}