{
  "type": "Feature",
  "properties": {
    "addr:full":"4907 E Broad St Texarkana AR 71854",
    "addr:housenumber":"4907",
    "addr:postcode":"71854",
    "addr:street":"E Broad St",
    "iso:country":"US",
    "sg:address":"4907 E Broad St",
    "sg:city":"Texarkana",
    "sg:classifiers":[
        {
            "category":"Retail",
            "subcategory":"Auto Repair",
            "type":"Services"
        }
    ],
    "sg:phone":"+1 870 772 5573",
    "sg:postcode":"71854",
    "sg:province":"AR",
    "sg:tags":[
        "trailer"
    ],
    "wof:name":"P E Truck & Trailer Repair Inc",
    "wof:placetype":"venue"
},
  "geometry": {"coordinates":[-93.983583,33.472092],"type":"Point"}
}