{
  "type": "Feature",
  "properties": {
    "iso:country":"US",
    "sg:address":"312 Jacuzzi Ln",
    "sg:city":"Lonoke",
    "sg:classifiers":[
        {
            "category":"Shopping",
            "subcategory":"Used Merchandise",
            "type":"Retail Goods"
        },
        {
            "category":"Professional",
            "subcategory":"Business Services",
            "type":"Services"
        }
    ],
    "sg:phone":"+1 501 676 0064",
    "sg:postcode":"72086",
    "sg:province":"AR",
    "sg:tags":[
        "flea",
        "market"
    ],
    "wof:name":"June's Trinkets & Treasures",
    "wof:placetype":"venue"
},
  "geometry": {"coordinates":[-91.892596,34.786401],"type":"Point"}
}