{
  "type": "Feature",
  "properties": {
    "iso:country":"US",
    "sg:address":"8338 Mopac Rd",
    "sg:city":"Brinkley",
    "sg:classifiers":[
        {
            "category":"Manufacturing",
            "subcategory":"Food",
            "type":"Manufacturing & Wholesale Goods"
        }
    ],
    "sg:phone":"+1 870 734 1762",
    "sg:postcode":"72021",
    "sg:province":"AR",
    "sg:tags":[
        "product"
    ],
    "wof:name":"Dale Oltmann",
    "wof:placetype":"venue"
},
  "geometry": {"coordinates":[-91.180833,34.858874],"type":"Point"}
}