{
  "type": "Feature",
  "properties": {
    "iso:country":"US",
    "sg:address":"60 E Township St",
    "sg:city":"Fayetteville",
    "sg:classifiers":[
        {
            "category":"Manufacturing",
            "subcategory":"Tools & Machinery",
            "type":"Manufacturing & Wholesale Goods"
        }
    ],
    "sg:phone":"+1 479 442 0374",
    "sg:postcode":"72703",
    "sg:province":"AR",
    "sg:tags":[
        "goods-wholesale",
        "optical",
        "manufacturer"
    ],
    "wof:name":"Chitwood Optical",
    "wof:placetype":"venue"
},
  "geometry": {"coordinates":[-94.15646599999999,36.09524],"type":"Point"}
}