{
  "type": "Feature",
  "properties": {
    "iso:country":"US",
    "sg:address":"2460 Grant 73",
    "sg:city":"Sheridan",
    "sg:classifiers":[
        {
            "category":"Professional",
            "type":"Services"
        }
    ],
    "sg:phone":"+1 870 942 3380",
    "sg:postcode":"72150",
    "sg:province":"AR",
    "wof:name":"Sandra J Shearer",
    "wof:placetype":"venue"
},
  "geometry": {"coordinates":[-92.306356,34.322017],"type":"Point"}
}