{
  "type": "Feature",
  "properties": {
    "addr:full":"3408 Ridge Pass Ct Little Rock AR 72227",
    "addr:housenumber":"3408",
    "addr:postcode":"72227",
    "addr:street":"Ridge Pass Ct",
    "iso:country":"US",
    "sg:address":"3408 Ridge Pass Ct",
    "sg:city":"Little Rock",
    "sg:classifiers":[
        {
            "category":"Home & Garden",
            "subcategory":"Building Materials",
            "type":"Retail Goods"
        }
    ],
    "sg:phone":"+1 501 223 9444",
    "sg:postcode":"72227",
    "sg:province":"AR",
    "sg:tags":[
        "kitchen",
        "cabinet"
    ],
    "wof:name":"R E Garrison Design",
    "wof:placetype":"venue"
},
  "geometry": {"coordinates":[-92.38278800000001,34.783804],"type":"Point"}
}