{
  "type": "Feature",
  "properties": {
    "addr:full":"630 Cash Rd SW Camden AR 71701",
    "addr:housenumber":"630",
    "addr:postcode":"71701",
    "addr:street":"Cash Rd Sw",
    "iso:country":"US",
    "sg:address":"630 Cash Rd SW",
    "sg:city":"Camden",
    "sg:classifiers":[
        {
            "category":"Banks & Credit Unions",
            "subcategory":"Investment Brokerage",
            "type":"Services"
        }
    ],
    "sg:phone":"+1 870 836 4004",
    "sg:postcode":"71701",
    "sg:province":"AR",
    "sg:tags":[
        "security"
    ],
    "wof:name":"Edward Jones 07153",
    "wof:placetype":"venue"
},
  "geometry": {"coordinates":[-92.85146400000001,33.576082],"type":"Point"}
}