{
  "type": "Feature",
  "properties": {
    "addr:full":"6909 W 34th St Little Rock AR 72204",
    "addr:housenumber":"6909",
    "addr:postcode":"72204",
    "addr:street":"W 34Th St",
    "iso:country":"US",
    "sg:address":"6909 W 34th St",
    "sg:city":"Little Rock",
    "sg:classifiers":[
        {
            "category":"Restaurant",
            "type":"Food & Drink"
        }
    ],
    "sg:phone":"+1 501 687 0834",
    "sg:postcode":"72204",
    "sg:province":"AR",
    "sg:tags":[
        "eating"
    ],
    "wof:name":"Seb Web Cafe",
    "wof:placetype":"venue"
},
  "geometry": {"coordinates":[-92.351997,34.721789],"type":"Point"}
}