{
  "type": "Feature",
  "properties": {
    "addr:full":"2917 Swiss Family Dr Altus AR 72821",
    "addr:housenumber":"2917",
    "addr:postcode":"72821",
    "addr:street":"Family Dr",
    "iso:country":"US",
    "sg:address":"2917 Swiss Family Dr",
    "sg:city":"Altus",
    "sg:classifiers":[
        {
            "category":"Farming",
            "subcategory":"Nursery",
            "type":"Manufacturing & Wholesale Goods"
        }
    ],
    "sg:phone":"+1 479 468 9463",
    "sg:postcode":"72821",
    "sg:province":"AR",
    "sg:tags":[
        "grower",
        "nursery-wholesale"
    ],
    "wof:name":"Alpine Nursery",
    "wof:placetype":"venue"
},
  "geometry": {"coordinates":[-93.753728,35.461773],"type":"Point"}
}