{
  "type": "Feature",
  "properties": {
    "iso:country":"US",
    "sg:address":"1120 Holly St",
    "sg:city":"Helena",
    "sg:classifiers":[
        {
            "category":"Social Services",
            "subcategory":"Child Care",
            "type":"Services"
        }
    ],
    "sg:phone":"+1 870 338 7802",
    "sg:postcode":"72342",
    "sg:province":"AR",
    "sg:tags":[
        "day"
    ],
    "wof:name":"Mid-Delta Head Start",
    "wof:placetype":"venue"
},
  "geometry": {"coordinates":[-90.589319,34.535577],"type":"Point"}
}