{
  "type": "Feature",
  "properties": {
    "iso:country":"US",
    "sg:address":"214 Gillham Rd",
    "sg:city":"Beebe",
    "sg:classifiers":[
        {
            "category":"Freight",
            "type":"Transportation"
        }
    ],
    "sg:phone":"+1 501 882 9782",
    "sg:postcode":"72012",
    "sg:province":"AR",
    "sg:tags":[
        "local",
        "trucking"
    ],
    "wof:name":"Frisbee Trucking",
    "wof:placetype":"venue"
},
  "geometry": {"coordinates":[-91.989006,35.085879],"type":"Point"}
}