{
  "type": "Feature",
  "properties": {
    "iso:country":"US",
    "sg:address":"1215 Whitney Ln",
    "sg:city":"Kensett",
    "sg:classifiers":[
        {
            "category":"Organizations",
            "subcategory":"Religious Organization",
            "type":"Services"
        }
    ],
    "sg:phone":"+1 501 742 3413",
    "sg:postcode":"72082",
    "sg:province":"AR",
    "wof:name":"Assembly Of God Church",
    "wof:placetype":"venue"
},
  "geometry": {"coordinates":[-91.678084,35.245665],"type":"Point"}
}