{
  "type": "Feature",
  "properties": {
    "iso:country":"US",
    "sg:address":"1 Tyler St",
    "sg:city":"Greenbrier",
    "sg:classifiers":[
        {
            "category":"Professional",
            "subcategory":"Advertising",
            "type":"Services"
        }
    ],
    "sg:phone":"+1 501 679 4900",
    "sg:postcode":"72058",
    "sg:province":"AR",
    "sg:tags":[
        "distribution"
    ],
    "wof:name":"Nu-Way Distributors",
    "wof:placetype":"venue"
},
  "geometry": {"coordinates":[-92.388446,35.211667],"type":"Point"}
}