{
  "type": "Feature",
  "properties": {
    "iso:country":"US",
    "sg:address":"328 Linwood St",
    "sg:city":"Osceola",
    "sg:classifiers":[
        {
            "category":"Building & Trades",
            "subcategory":"Construction",
            "type":"Services"
        }
    ],
    "sg:phone":"+1 870 563 6474",
    "sg:postcode":"72370",
    "sg:province":"AR",
    "sg:tags":[
        "contractor"
    ],
    "wof:name":"Booker Construction Co",
    "wof:placetype":"venue"
},
  "geometry": {"coordinates":[-89.977422,35.706748],"type":"Point"}
}