{
  "type": "Feature",
  "properties": {
    "iso:country":"US",
    "sg:address":"7 Barra Ln",
    "sg:city":"Bella Vista",
    "sg:classifiers":[
        {
            "category":"Education",
            "subcategory":"Special Training",
            "type":"Public Place"
        }
    ],
    "sg:phone":"+1 479 876 1647",
    "sg:postcode":"72715",
    "sg:province":"AR",
    "sg:tags":[
        "educational"
    ],
    "wof:name":"Care Quest University",
    "wof:placetype":"venue"
},
  "geometry": {"coordinates":[-94.32011,36.474351],"type":"Point"}
}