{
  "type": "Feature",
  "properties": {
    "addr:full":"1804 N Taylor St Little Rock AR 72207",
    "addr:housenumber":"1804",
    "addr:postcode":"72207",
    "addr:street":"N Taylor St",
    "iso:country":"US",
    "sg:address":"1804 N Taylor St",
    "sg:city":"Little Rock",
    "sg:classifiers":[
        {
            "category":"Restaurant",
            "type":"Food & Drink"
        }
    ],
    "sg:phone":"+1 501 666 2475",
    "sg:postcode":"72207",
    "sg:province":"AR",
    "sg:tags":[
        "eating"
    ],
    "wof:name":"Nan King",
    "wof:placetype":"venue"
},
  "geometry": {"coordinates":[-92.33596900000001,34.769169],"type":"Point"}
}