{
  "type": "Feature",
  "properties": {
    "addr:full":"3062 N Co Rd 69 Manila AR 72442",
    "addr:housenumber":"3062;69",
    "addr:postcode":"72442",
    "addr:street":"N Co Rd",
    "iso:country":"US",
    "sg:address":"3062 N Co Rd 69",
    "sg:city":"Manila",
    "sg:classifiers":[
        {
            "category":"Farming",
            "subcategory":"Farm",
            "type":"Manufacturing & Wholesale Goods"
        }
    ],
    "sg:phone":"+1 870 561 3500",
    "sg:postcode":"72442",
    "sg:province":"AR",
    "sg:tags":[
        "rice",
        "wheat",
        "soybean",
        "cotton"
    ],
    "wof:name":"Wildy Farms",
    "wof:placetype":"venue"
},
  "geometry": {"coordinates":[-90.248414,35.859184],"type":"Point"}
}