{
  "type": "Feature",
  "properties": {
    "iso:country":"US",
    "sg:address":"538 Lost Rd",
    "sg:city":"Malvern",
    "sg:classifiers":[
        {
            "category":"Freight",
            "type":"Transportation"
        }
    ],
    "sg:phone":"+1 501 384 5266",
    "sg:postcode":"72104",
    "sg:province":"AR",
    "sg:tags":[
        "operator",
        "mill",
        "local",
        "trucking"
    ],
    "wof:name":"Nix Logging Inc",
    "wof:placetype":"venue"
},
  "geometry": {"coordinates":[-92.852589,34.17564],"type":"Point"}
}