{
  "type": "Feature",
  "properties": {
    "iso:country":"US",
    "sg:address":"527 Spring St",
    "sg:city":"Hot Springs",
    "sg:classifiers":[
        {
            "category":"Recreation",
            "type":"Entertainment"
        }
    ],
    "sg:phone":"+1 501 624 3124",
    "sg:postcode":"71901",
    "sg:province":"AR",
    "sg:tags":[
        "parks"
    ],
    "sg:website":"www.nps.gov",
    "wof:name":"US National Park Svc",
    "wof:placetype":"venue"
},
  "geometry": {"coordinates":[-93.048631,34.512234],"type":"Point"}
}