{
  "type": "Feature",
  "properties": {
    "iso:country":"US",
    "sg:address":"2200 N Rodney Parham Rd",
    "sg:city":"Little Rock",
    "sg:classifiers":[
        {
            "category":"Professional",
            "subcategory":"Engineering",
            "type":"Services"
        },
        {
            "category":"Building & Trades",
            "subcategory":"Landscaping Services",
            "type":"Services"
        }
    ],
    "sg:phone":"+1 479 444 7880",
    "sg:postcode":"72212",
    "sg:province":"AR",
    "sg:tags":[
        "surveyor",
        "consulting",
        "architect",
        "landscape",
        "engineer"
    ],
    "wof:name":"Development Consultants Inc",
    "wof:placetype":"venue"
},
  "geometry": {"coordinates":[-92.402529,34.773787],"type":"Point"}
}