{
  "type": "Feature",
  "properties": {
    "addr:full":"1894 W Sunset Ave Springdale AR 72762",
    "addr:housenumber":"1894",
    "addr:postcode":"72762",
    "addr:street":"W Sunset Ave",
    "iso:country":"US",
    "sg:address":"1894 W Sunset Ave",
    "sg:city":"Springdale",
    "sg:classifiers":[
        {
            "category":"Banks & Credit Unions",
            "subcategory":"Investment Brokerage",
            "type":"Services"
        },
        {
            "category":"Banks & Credit Unions",
            "subcategory":"Financial Services",
            "type":"Services"
        }
    ],
    "sg:phone":"+1 479 872 0000",
    "sg:postcode":"72762",
    "sg:province":"AR",
    "sg:tags":[
        "management"
    ],
    "wof:name":"Blue Ribbon Auto",
    "wof:placetype":"venue"
},
  "geometry": {"coordinates":[-94.151687,36.174782],"type":"Point"}
}