{
  "type": "Feature",
  "properties": {
    "iso:country":"US",
    "sg:address":"256 Hwy 71 N",
    "sg:city":"Ashdown",
    "sg:classifiers":[
        {
            "category":"Government",
            "subcategory":"Office",
            "type":"Public Place"
        }
    ],
    "sg:phone":"+1 870 898 3249",
    "sg:postcode":"71822",
    "sg:province":"AR",
    "sg:tags":[
        "city",
        "program"
    ],
    "wof:name":"City Of Ashdown Sanitation",
    "wof:placetype":"venue"
},
  "geometry": {"coordinates":[-94.146917,33.711397],"type":"Point"}
}