{
  "type": "Feature",
  "properties": {
    "iso:country":"US",
    "sg:address":"1507 E Race Ave",
    "sg:city":"Searcy",
    "sg:classifiers":[
        {
            "category":"Banks & Credit Unions",
            "subcategory":"Bank",
            "type":"Services"
        }
    ],
    "sg:phone":"+1 501 368 0400",
    "sg:postcode":"72143",
    "sg:province":"AR",
    "sg:tags":[
        "loan",
        "real estate"
    ],
    "wof:name":"Regions Mortgage Inc",
    "wof:placetype":"venue"
},
  "geometry": {"coordinates":[-91.720081,35.250605],"type":"Point"}
}