{
  "type": "Feature",
  "properties": {
    "iso:country":"US",
    "sg:address":"3501 E Roosevelt Rd",
    "sg:city":"Little Rock",
    "sg:classifiers":[
        {
            "category":"Retail",
            "subcategory":"Auto Rental",
            "type":"Services"
        }
    ],
    "sg:phone":"+1 501 376 7221",
    "sg:postcode":"72206",
    "sg:province":"AR",
    "sg:tags":[
        "passenger",
        "car"
    ],
    "wof:name":"National Car Rental",
    "wof:placetype":"venue"
},
  "geometry": {"coordinates":[-92.237882,34.719727],"type":"Point"}
}