{
  "type": "Feature",
  "properties": {
    "addr:full":"3317 SE L St Bentonville AR 72712",
    "addr:housenumber":"3317",
    "addr:postcode":"72712",
    "addr:street":"Se L St",
    "iso:country":"US",
    "sg:address":"3317 SE L St",
    "sg:city":"Bentonville",
    "sg:classifiers":[
        {
            "category":"Health Services",
            "subcategory":"Nursing And Care Facility",
            "type":"Services"
        },
        {
            "category":"Social Services",
            "subcategory":"Adult Care",
            "type":"Services"
        }
    ],
    "sg:phone":"+1 479 254 8759",
    "sg:postcode":"72712",
    "sg:province":"AR",
    "sg:tags":[
        "home",
        "intermediate",
        "residential"
    ],
    "wof:name":"Gardens At Osage Terrace",
    "wof:placetype":"venue"
},
  "geometry": {"coordinates":[-94.194203,36.337302],"type":"Point"}
}