{
  "type": "Feature",
  "properties": {
    "iso:country":"US",
    "sg:address":"5610 Dollarway Rd",
    "sg:city":"White Hall",
    "sg:classifiers":[
        {
            "category":"Manufacturing",
            "subcategory":"Motor Vehicles & Parts",
            "type":"Manufacturing & Wholesale Goods"
        }
    ],
    "sg:phone":"+1 870 267 1875",
    "sg:postcode":"71602",
    "sg:province":"AR",
    "sg:tags":[
        "body",
        "mfg"
    ],
    "wof:name":"Soark Bus Sales Inc",
    "wof:placetype":"venue"
},
  "geometry": {"coordinates":[-92.060782,34.244108],"type":"Point"}
}