{
  "type": "Feature",
  "properties": {
    "iso:country":"US",
    "sg:address":"359 Co Rd 757",
    "sg:city":"Jonesboro",
    "sg:classifiers":[
        {
            "category":"Building & Trades",
            "subcategory":"Construction",
            "type":"Services"
        }
    ],
    "sg:phone":"+1 870 932 2220",
    "sg:postcode":"72401",
    "sg:province":"AR",
    "sg:tags":[
        "house"
    ],
    "wof:name":"Kline Construction",
    "wof:placetype":"venue"
},
  "geometry": {"coordinates":[-90.688936,35.915115],"type":"Point"}
}