{
  "type": "Feature",
  "properties": {
    "iso:country":"US",
    "sg:address":"920 Harrison St",
    "sg:city":"Batesville",
    "sg:classifiers":[
        {
            "category":"Communications",
            "subcategory":"Radio Station",
            "type":"Services"
        }
    ],
    "sg:phone":"+1 870 793 9393",
    "sg:postcode":"72501",
    "sg:province":"AR",
    "sg:tags":[
        "broadcast"
    ],
    "wof:name":"Max 93 One Request Line",
    "wof:placetype":"venue"
},
  "geometry": {"coordinates":[-91.641542,35.769695],"type":"Point"}
}