{
  "type": "Feature",
  "properties": {
    "addr:full":"110 N Main St Dermott AR 71638",
    "addr:housenumber":"110",
    "addr:postcode":"71638",
    "addr:street":"N Main St",
    "iso:country":"US",
    "sg:address":"110 N Main St",
    "sg:city":"Dermott",
    "sg:classifiers":[
        {
            "category":"Local Transit",
            "type":"Transportation"
        }
    ],
    "sg:phone":"+1 870 000 1111",
    "sg:postcode":"71638",
    "sg:province":"AR",
    "sg:tags":[
        "ambulance"
    ],
    "wof:name":"Pafford Ambulance Svc",
    "wof:placetype":"venue"
},
  "geometry": {"coordinates":[-91.43597699999999,33.527013],"type":"Point"}
}