{
  "type": "Feature",
  "properties": {
    "addr:full":"1111 S Walton Blvd Bentonville AR 72712",
    "addr:housenumber":"1111",
    "addr:postcode":"72712",
    "addr:street":"S Walton Blvd",
    "iso:country":"US",
    "sg:address":"1111 S Walton Blvd",
    "sg:city":"Bentonville",
    "sg:classifiers":[
        {
            "category":"Building & Trades",
            "subcategory":"Plumbing",
            "type":"Services"
        }
    ],
    "sg:phone":"+1 479 464 8556",
    "sg:postcode":"72712",
    "sg:province":"AR",
    "sg:tags":[
        "home",
        "plumber",
        "improvement",
        "contractor"
    ],
    "wof:name":"Bentonville Plumbing",
    "wof:placetype":"venue"
},
  "geometry": {"coordinates":[-94.215745,36.359771],"type":"Point"}
}