{
  "type": "Feature",
  "properties": {
    "iso:country":"US",
    "sg:address":"213 Glenview Ln",
    "sg:city":"N Little Rock",
    "sg:classifiers":[
        {
            "category":"Organizations",
            "subcategory":"Religious Organization",
            "type":"Services"
        }
    ],
    "sg:phone":"+1 501 955 2304",
    "sg:postcode":"72117",
    "sg:province":"AR",
    "sg:tags":[
        "church"
    ],
    "wof:name":"Rivewrview AME Church",
    "wof:placetype":"venue"
},
  "geometry": {"coordinates":[-92.210737,34.764034],"type":"Point"}
}