{
  "type": "Feature",
  "properties": {
    "iso:country":"US",
    "sg:address":"106 Lee Dr",
    "sg:city":"Corning",
    "sg:classifiers":[
        {
            "category":"Retail",
            "subcategory":"Auto Rental",
            "type":"Services"
        }
    ],
    "sg:phone":"+1 870 857 6177",
    "sg:postcode":"72422",
    "sg:province":"AR",
    "sg:tags":[
        "truck",
        "leasing"
    ],
    "wof:name":"Penske Truck Leasing Co LP",
    "wof:placetype":"venue"
},
  "geometry": {"coordinates":[-90.57376,36.421119],"type":"Point"}
}