{
  "type": "Feature",
  "properties": {
    "iso:country":"US",
    "sg:address":"427 E 4th St",
    "sg:city":"Russellville",
    "sg:classifiers":[
        {
            "category":"Food & Beverages",
            "subcategory":"Bakery",
            "type":"Retail Goods"
        }
    ],
    "sg:phone":"+1 479 968 4091",
    "sg:postcode":"72801",
    "sg:province":"AR",
    "wof:name":"Sugar Shack",
    "wof:placetype":"venue"
},
  "geometry": {"coordinates":[-93.129244,35.275075],"type":"Point"}
}