{
  "type": "Feature",
  "properties": {
    "iso:country":"US",
    "sg:address":"120 Avalon Pl",
    "sg:city":"Helena",
    "sg:classifiers":[
        {
            "category":"Insurance",
            "subcategory":"Insurance Agent",
            "type":"Services"
        }
    ],
    "sg:phone":"+1 870 338 8908",
    "sg:postcode":"72342",
    "sg:province":"AR",
    "wof:name":"First Delta Insurance Inc",
    "wof:placetype":"venue"
},
  "geometry": {"coordinates":[-90.605858,34.538799],"type":"Point"}
}