{
  "type": "Feature",
  "properties": {
    "iso:country":"US",
    "sg:address":"21176 I- 30",
    "sg:city":"Bryant",
    "sg:classifiers":[
        {
            "category":"Home & Garden",
            "subcategory":"Building Materials",
            "type":"Retail Goods"
        }
    ],
    "sg:phone":"+1 501 794 0514",
    "sg:postcode":"72022",
    "sg:province":"AR",
    "sg:tags":[
        "lumber"
    ],
    "wof:name":"Ridout Lumber Co",
    "wof:placetype":"venue"
},
  "geometry": {"coordinates":[-92.52600700000001,34.608459],"type":"Point"}
}