{
  "type": "Feature",
  "properties": {
    "iso:country":"US",
    "sg:address":"1923 County Ave",
    "sg:city":"Texarkana",
    "sg:classifiers":[
        {
            "category":"Banks & Credit Unions",
            "subcategory":"Investment Brokerage",
            "type":"Services"
        }
    ],
    "sg:phone":"+1 870 773 8043",
    "sg:postcode":"71854",
    "sg:province":"AR",
    "sg:tags":[
        "security",
        "commodity",
        "contract"
    ],
    "wof:name":"Futures Trading Co",
    "wof:placetype":"venue"
},
  "geometry": {"coordinates":[-94.038345,33.441762],"type":"Point"}
}