{
  "type": "Feature",
  "properties": {
    "iso:country":"US",
    "sg:address":"233 E Main St",
    "sg:city":"Piggott",
    "sg:classifiers":[
        {
            "category":"Professional",
            "subcategory":"Business Services",
            "type":"Services"
        }
    ],
    "sg:phone":"+1 870 598 2336",
    "sg:postcode":"72454",
    "sg:province":"AR",
    "sg:tags":[
        "real estate"
    ],
    "wof:name":"Magee Auction & Realty",
    "wof:placetype":"venue"
},
  "geometry": {"coordinates":[-90.188318,36.382033],"type":"Point"}
}