{
  "type": "Feature",
  "properties": {
    "iso:country":"US",
    "sg:address":"2730 N West Ave",
    "sg:city":"El Dorado",
    "sg:classifiers":[
        {
            "category":"Utilities",
            "subcategory":"Telephone",
            "type":"Services"
        }
    ],
    "sg:phone":"+1 870 875 1810",
    "sg:postcode":"71730",
    "sg:province":"AR",
    "sg:tags":[
        "communications",
        "merchandise"
    ],
    "wof:name":"CenturyTel",
    "wof:placetype":"venue"
},
  "geometry": {"coordinates":[-92.665711,33.239415],"type":"Point"}
}