{
  "type": "Feature",
  "properties": {
    "addr:full":"128 Westwood Loop Bismarck AR 71929",
    "addr:housenumber":"128",
    "addr:postcode":"71929",
    "addr:street":"Westwood Loop",
    "iso:country":"US",
    "sg:address":"128 Westwood Loop",
    "sg:city":"Bismarck",
    "sg:classifiers":[
        {
            "category":"Building & Trades",
            "subcategory":"Construction",
            "type":"Services"
        }
    ],
    "sg:phone":"+1 501 865 2368",
    "sg:postcode":"71929",
    "sg:province":"AR",
    "sg:tags":[
        "contractor"
    ],
    "wof:name":"Cherokee Siding Co",
    "wof:placetype":"venue"
},
  "geometry": {"coordinates":[-93.177897,34.279435],"type":"Point"}
}