{
  "type": "Feature",
  "properties": {
    "iso:country":"US",
    "sg:address":"4701 W Commercial Dr",
    "sg:city":"Sherwood",
    "sg:classifiers":[
        {
            "category":"Organizations",
            "subcategory":"Community Association",
            "type":"Services"
        }
    ],
    "sg:phone":"+1 501 758 1137",
    "sg:postcode":"72116",
    "sg:province":"AR",
    "sg:tags":[
        "fraternal"
    ],
    "wof:name":"Crescent Lodge",
    "wof:placetype":"venue"
},
  "geometry": {"coordinates":[-92.22183099999999,34.797668],"type":"Point"}
}