{
  "type": "Feature",
  "properties": {
    "iso:country":"US",
    "sg:address":"918 N 24th St",
    "sg:city":"Rogers",
    "sg:classifiers":[
        {
            "category":"Home & Garden",
            "subcategory":"Carpets & Floor Coverings",
            "type":"Retail Goods"
        }
    ],
    "sg:phone":"+1 479 631 0311",
    "sg:postcode":"72756",
    "sg:province":"AR",
    "wof:name":"Walkers Carpet Service",
    "wof:placetype":"venue"
},
  "geometry": {"coordinates":[-94.15235,36.344449],"type":"Point"}
}