{
  "type": "Feature",
  "properties": {
    "iso:country":"US",
    "sg:address":"709 Maul Rd",
    "sg:city":"Camden",
    "sg:classifiers":[
        {
            "category":"Real Estate",
            "subcategory":"Developer",
            "type":"Services"
        }
    ],
    "sg:phone":"+1 870 836 8252",
    "sg:postcode":"71701",
    "sg:province":"AR",
    "wof:name":"Brh Development Corp",
    "wof:placetype":"venue"
},
  "geometry": {"coordinates":[-92.841131,33.59662],"type":"Point"}
}