{
  "type": "Feature",
  "properties": {
    "addr:full":"809 W Barton Ave West Memphis AR 72301",
    "addr:housenumber":"809",
    "addr:postcode":"72301",
    "addr:street":"W Barton Ave",
    "iso:country":"US",
    "sg:address":"809 W Barton Ave",
    "sg:city":"West Memphis",
    "sg:classifiers":[
        {
            "category":"Restaurant",
            "type":"Food & Drink"
        }
    ],
    "sg:phone":"+1 870 400 2202",
    "sg:postcode":"72301",
    "sg:province":"AR",
    "sg:tags":[
        "eating"
    ],
    "wof:name":"Tamales & Things",
    "wof:placetype":"venue"
},
  "geometry": {"coordinates":[-90.20419200000001,35.153556],"type":"Point"}
}