{
  "type": "Feature",
  "properties": {
    "iso:country":"US",
    "sg:address":"3403 Highway 367 S",
    "sg:city":"Cabot",
    "sg:classifiers":[
        {
            "category":"Retail",
            "subcategory":"Veterinary Services",
            "type":"Services"
        }
    ],
    "sg:phone":"+1 501 941 7387",
    "sg:postcode":"72023",
    "sg:province":"AR",
    "sg:tags":[
        "veterinarian"
    ],
    "wof:name":"All For Pets Veterinary Clinic",
    "wof:placetype":"venue"
},
  "geometry": {"coordinates":[-92.05938999999999,34.948425],"type":"Point"}
}