{
  "type": "Feature",
  "properties": {
    "iso:country":"US",
    "sg:address":"3718 Plantation Cir",
    "sg:city":"Jonesboro",
    "sg:classifiers":[
        {
            "category":"Building & Trades",
            "subcategory":"Construction",
            "type":"Services"
        }
    ],
    "sg:phone":"+1 870 931 0259",
    "sg:postcode":"72404",
    "sg:province":"AR",
    "sg:tags":[
        "altering",
        "house",
        "remodeling",
        "contractor"
    ],
    "wof:name":"Kenneth Wayne Mcdaniel",
    "wof:placetype":"venue"
},
  "geometry": {"coordinates":[-90.71581999999999,35.794887],"type":"Point"}
}