{
  "type": "Feature",
  "properties": {
    "iso:country":"US",
    "sg:address":"408 N 8th St",
    "sg:city":"Rogers",
    "sg:classifiers":[
        {
            "category":"Health Services",
            "subcategory":"Optometrist",
            "type":"Services"
        }
    ],
    "sg:phone":"+1 479 636 1960",
    "sg:postcode":"72756",
    "sg:province":"AR",
    "wof:name":"Parenti-Morris Eyecare",
    "wof:placetype":"venue"
},
  "geometry": {"coordinates":[-94.12584,36.336249],"type":"Point"}
}