{
  "type": "Feature",
  "properties": {
    "iso:country":"US",
    "sg:address":"719 W Walnut St",
    "sg:city":"Walnut Ridge",
    "sg:classifiers":[
        {
            "category":"Autos & Motor Vehicles",
            "subcategory":"Automobile Sales",
            "type":"Retail Goods"
        }
    ],
    "sg:phone":"+1 870 886 1835",
    "sg:postcode":"72476",
    "sg:province":"AR",
    "sg:tags":[
        "car",
        "dealer"
    ],
    "wof:name":"Moore Brothers Used Cars",
    "wof:placetype":"venue"
},
  "geometry": {"coordinates":[-90.960356,36.073361],"type":"Point"}
}