{
  "type": "Feature",
  "properties": {
    "iso:country":"US",
    "sg:address":"15 W South St",
    "sg:city":"Fayetteville",
    "sg:classifiers":[
        {
            "category":"Utilities",
            "subcategory":"Sewage",
            "type":"Services"
        },
        {
            "category":"Sports & Exercise",
            "subcategory":"Race Track",
            "type":"Entertainment"
        }
    ],
    "sg:phone":"+1 479 442 4412",
    "sg:postcode":"72701",
    "sg:province":"AR",
    "sg:tags":[
        "equipment-wholesale",
        "equipment",
        "treatment"
    ],
    "sg:website":"http://www.cuzn.com",
    "wof:name":"Filter Foam Technology Inc",
    "wof:placetype":"venue"
},
  "geometry": {"coordinates":[-94.159911,36.059153],"type":"Point"}
}