{
  "type": "Feature",
  "properties": {
    "iso:country":"US",
    "sg:address":"428 Dodd Ln",
    "sg:city":"Fox",
    "sg:classifiers":[
        {
            "category":"Insurance",
            "subcategory":"Hazard Insurance",
            "type":"Services"
        }
    ],
    "sg:phone":"+1 870 746 4477",
    "sg:postcode":"72051",
    "sg:province":"AR",
    "wof:name":"Don A Dodd",
    "wof:placetype":"venue"
},
  "geometry": {"coordinates":[-92.322131,35.83487],"type":"Point"}
}