{
  "type": "Feature",
  "properties": {
    "iso:country":"US",
    "sg:address":"100 Ponderosa Way",
    "sg:city":"Hot Springs Vlg",
    "sg:classifiers":[
        {
            "category":"Organizations",
            "subcategory":"Religious Organization",
            "type":"Services"
        }
    ],
    "sg:phone":"+1 501 922 0404",
    "sg:postcode":"71909",
    "sg:province":"AR",
    "sg:tags":[
        "church"
    ],
    "sg:website":"www.villagebiblechurchhsv.org",
    "wof:name":"Village Bible Church",
    "wof:placetype":"venue"
},
  "geometry": {"coordinates":[-92.98268899999999,34.65106],"type":"Point"}
}