{
  "type": "Feature",
  "properties": {
    "addr:full":"506 E Ave H Hope AR 71801",
    "addr:housenumber":"506",
    "addr:postcode":"71801",
    "addr:street":"E Ave H",
    "iso:country":"US",
    "sg:address":"506 E Ave H",
    "sg:city":"Hope",
    "sg:classifiers":[
        {
            "category":"Personal",
            "subcategory":"Beauty Salon",
            "type":"Services"
        }
    ],
    "sg:phone":"+1 870 777 5156",
    "sg:postcode":"71801",
    "sg:province":"AR",
    "sg:tags":[
        "shop"
    ],
    "wof:name":"J Renee's Styles Unlimited",
    "wof:placetype":"venue"
},
  "geometry": {"coordinates":[-93.58876100000001,33.675758],"type":"Point"}
}