{
  "type": "Feature",
  "properties": {
    "iso:country":"US",
    "sg:address":"341 Hwy 425 S",
    "sg:city":"Monticello",
    "sg:classifiers":[
        {
            "category":"Cinema",
            "subcategory":"Movie Rental",
            "type":"Entertainment"
        }
    ],
    "sg:phone":"+1 870 367 7510",
    "sg:postcode":"71655",
    "sg:province":"AR",
    "sg:tags":[
        "leasing",
        "video",
        "disc",
        "tape"
    ],
    "sg:website":"www.moviegallery.com",
    "wof:name":"Movie Gallery",
    "wof:placetype":"venue"
},
  "geometry": {"coordinates":[-91.802671,33.624388],"type":"Point"}
}