{
  "type": "Feature",
  "properties": {
    "iso:country":"US",
    "sg:address":"22292 Hwy 51",
    "sg:city":"Malvern",
    "sg:classifiers":[
        {
            "category":"Organizations",
            "subcategory":"Religious Organization",
            "type":"Services"
        }
    ],
    "sg:phone":"+1 501 467 3003",
    "sg:postcode":"72104",
    "sg:province":"AR",
    "sg:tags":[
        "church"
    ],
    "wof:name":"Magnet Cove United Mthdst Chr",
    "wof:placetype":"venue"
},
  "geometry": {"coordinates":[-92.835182,34.449114],"type":"Point"}
}