{
  "type": "Feature",
  "properties": {
    "iso:country":"US",
    "sg:address":"801 N 10th St",
    "sg:city":"Fort Smith",
    "sg:classifiers":[
        {
            "category":"Autos & Motor Vehicles",
            "subcategory":"Automobile Sales",
            "type":"Retail Goods"
        }
    ],
    "sg:phone":"+1 479 785 4557",
    "sg:postcode":"72901",
    "sg:province":"AR",
    "sg:tags":[
        "used"
    ],
    "wof:name":"Bargain Corner Auto Sales",
    "wof:placetype":"venue"
},
  "geometry": {"coordinates":[-94.414874,35.391614],"type":"Point"}
}