{
  "type": "Feature",
  "properties": {
    "iso:country":"US",
    "sg:address":"104 SE 6th St",
    "sg:city":"Bentonville",
    "sg:classifiers":[
        {
            "category":"Education",
            "subcategory":"Dance Studio",
            "type":"Public Place"
        }
    ],
    "sg:phone":"+1 479 273 7576",
    "sg:postcode":"72712",
    "sg:province":"AR",
    "sg:tags":[
        "instruction",
        "dancing"
    ],
    "wof:name":"Gina's Dance Co",
    "wof:placetype":"venue"
},
  "geometry": {"coordinates":[-94.20777200000001,36.3661],"type":"Point"}
}