{
  "type": "Feature",
  "properties": {
    "iso:country":"US",
    "sg:address":"506 Oak St",
    "sg:city":"Conway",
    "sg:classifiers":[
        {
            "category":"Shopping",
            "subcategory":"Musical Instruments",
            "type":"Retail Goods"
        }
    ],
    "sg:phone":"+1 501 327 8129",
    "sg:postcode":"72032",
    "sg:province":"AR",
    "wof:name":"Jack's Music",
    "wof:placetype":"venue"
},
  "geometry": {"coordinates":[-92.43325900000001,35.091814],"type":"Point"}
}