{
  "type": "Feature",
  "properties": {
    "iso:country":"US",
    "sg:address":"132 Hyde Pkwy",
    "sg:city":"Shirley",
    "sg:classifiers":[
        {
            "category":"Professional",
            "type":"Services"
        }
    ],
    "sg:phone":"+1 501 884 4288",
    "sg:postcode":"72153",
    "sg:province":"AR",
    "wof:name":"Life In Ozarks",
    "wof:placetype":"venue"
},
  "geometry": {"coordinates":[-92.273183,35.602675],"type":"Point"}
}