{
  "type": "Feature",
  "properties": {
    "addr:full":"1001 US Hwy 71 Mena OK 71953",
    "addr:housenumber":"1001",
    "addr:postcode":"71953",
    "addr:street":"Us Hwy 71",
    "iso:country":"US",
    "sg:address":"1001 US Hwy 71",
    "sg:city":"Mena",
    "sg:classifiers":[
        {
            "category":"Building & Trades",
            "subcategory":"Plumbing",
            "type":"Services"
        }
    ],
    "sg:phone":"+1 479 437 3577",
    "sg:postcode":"71953",
    "sg:province":"OK",
    "sg:tags":[
        "plumbing",
        "contractor"
    ],
    "wof:name":"Fagan Plumbing Inc",
    "wof:placetype":"venue"
},
  "geometry": {"coordinates":[-94.239272,34.579206],"type":"Point"}
}