{
  "type": "Feature",
  "properties": {
    "iso:country":"US",
    "sg:address":"302 Charmont Dr",
    "sg:city":"Charleston",
    "sg:classifiers":[
        {
            "category":"Farming",
            "subcategory":"Farm",
            "type":"Manufacturing & Wholesale Goods"
        }
    ],
    "sg:phone":"+1 479 965 7504",
    "sg:postcode":"72933",
    "sg:province":"AR",
    "sg:tags":[
        "crop",
        "general"
    ],
    "wof:name":"Mh Farms",
    "wof:placetype":"venue"
},
  "geometry": {"coordinates":[-94.05571999999999,35.299113],"type":"Point"}
}