{
  "type": "Feature",
  "properties": {
    "iso:country":"US",
    "sg:address":"153 E Monte Painter Dr",
    "sg:city":"Fayetteville",
    "sg:classifiers":[
        {
            "category":"Health Services",
            "subcategory":"Doctor",
            "type":"Services"
        }
    ],
    "sg:phone":"+1 479 444 2223",
    "sg:postcode":"72703",
    "sg:province":"AR",
    "sg:tags":[
        "physician",
        "surgeon"
    ],
    "wof:name":"Center For Pain Management",
    "wof:placetype":"venue"
},
  "geometry": {"coordinates":[-94.156446,36.109884],"type":"Point"}
}