{
  "type": "Feature",
  "properties": {
    "addr:full":"9 Saye St Vilonia AR 72173",
    "addr:housenumber":"9",
    "addr:postcode":"72173",
    "addr:street":"Saye St",
    "iso:country":"US",
    "sg:address":"9 Saye St",
    "sg:city":"Vilonia",
    "sg:classifiers":[
        {
            "category":"Farming",
            "subcategory":"Farm",
            "type":"Manufacturing & Wholesale Goods"
        }
    ],
    "sg:phone":"+1 501 796 3363",
    "sg:postcode":"72173",
    "sg:province":"AR",
    "wof:name":"Porter Vaughan Farm",
    "wof:placetype":"venue"
},
  "geometry": {"coordinates":[-92.22941400000001,35.089351],"type":"Point"}
}