{
  "type": "Feature",
  "properties": {
    "iso:country":"US",
    "sg:address":"320 Long Island Dr",
    "sg:city":"Hot Springs",
    "sg:classifiers":[
        {
            "category":"Travel",
            "subcategory":"Hotels & Motels",
            "type":"Entertainment"
        }
    ],
    "sg:phone":"+1 501 525 3600",
    "sg:postcode":"71913",
    "sg:province":"AR",
    "sg:website":"www.longislandlakeresort.com",
    "wof:name":"Long Island Lake Resort",
    "wof:placetype":"venue"
},
  "geometry": {"coordinates":[-93.078537,34.432524],"type":"Point"}
}