{
  "type": "Feature",
  "properties": {
    "addr:full":"11586 State Hwy 359 London AR 72847",
    "addr:housenumber":"11586",
    "addr:postcode":"72847",
    "addr:street":"State Hwy 359",
    "iso:country":"US",
    "sg:address":"11586 State Hwy 359",
    "sg:city":"London",
    "sg:classifiers":[
        {
            "category":"Government",
            "subcategory":"Fire Station",
            "type":"Public Place"
        }
    ],
    "sg:phone":"+1 479 885 6167",
    "sg:postcode":"72847",
    "sg:province":"AR",
    "sg:tags":[
        "department"
    ],
    "wof:name":"Flatrock Rfd 5",
    "wof:placetype":"venue"
},
  "geometry": {"coordinates":[-93.316095,35.357574],"type":"Point"}
}