{
  "type": "Feature",
  "properties": {
    "addr:full":"17 Wagon Wheel Ct Little Rock AR 72211",
    "addr:housenumber":"17",
    "addr:postcode":"72211",
    "addr:street":"Wagon Wheel Ct",
    "iso:country":"US",
    "sg:address":"17 Wagon Wheel Ct",
    "sg:city":"Little Rock",
    "sg:classifiers":[
        {
            "category":"Health Services",
            "subcategory":"Health Practitioner",
            "type":"Services"
        }
    ],
    "sg:phone":"+1 501 223 8211",
    "sg:postcode":"72211",
    "sg:province":"AR",
    "sg:tags":[
        "pathologist",
        "speech"
    ],
    "wof:name":"ABC Therapy Inc",
    "wof:placetype":"venue"
},
  "geometry": {"coordinates":[-92.415683,34.742655],"type":"Point"}
}