{
  "type": "Feature",
  "properties": {
    "iso:country":"US",
    "sg:address":"1100 N University Ave",
    "sg:city":"Little Rock",
    "sg:classifiers":[
        {
            "category":"Wholesale",
            "subcategory":"Drugs",
            "type":"Manufacturing & Wholesale Goods"
        }
    ],
    "sg:phone":"+1 501 664 6674",
    "sg:postcode":"72207",
    "sg:province":"AR",
    "sg:tags":[
        "perfume"
    ],
    "wof:name":"111 Eterprises",
    "wof:placetype":"venue"
},
  "geometry": {"coordinates":[-92.341031,34.760365],"type":"Point"}
}