{
  "type": "Feature",
  "properties": {
    "iso:country":"US",
    "sg:address":"8201 Cantrell Rd",
    "sg:city":"Little Rock",
    "sg:classifiers":[
        {
            "category":"Banks & Credit Unions",
            "subcategory":"Financial Services",
            "type":"Services"
        }
    ],
    "sg:phone":"+1 501 748 4800",
    "sg:postcode":"72227",
    "sg:province":"AR",
    "sg:tags":[
        "company",
        "holding"
    ],
    "sg:website":"www.centennialbank.net",
    "wof:name":"Centennial Bancshares Inc",
    "wof:placetype":"venue"
},
  "geometry": {"coordinates":[-92.368217,34.777138],"type":"Point"}
}