{
  "type": "Feature",
  "properties": {
    "iso:country":"US",
    "sg:address":"7900 US Hwy 71",
    "sg:city":"Fort Smith",
    "sg:classifiers":[
        {
            "category":"Bars & Pubs",
            "type":"Food & Drink"
        }
    ],
    "sg:phone":"+1 479 649 6555",
    "sg:postcode":"72908",
    "sg:province":"AR",
    "sg:tags":[
        "club",
        "night"
    ],
    "wof:name":"Regina's House Of Dolls II",
    "wof:placetype":"venue"
},
  "geometry": {"coordinates":[-94.397004,35.309475],"type":"Point"}
}