{
  "type": "Feature",
  "properties": {
    "iso:country":"US",
    "sg:address":"130 W Emma Ave",
    "sg:city":"Springdale",
    "sg:classifiers":[
        {
            "category":"Bars & Pubs",
            "type":"Food & Drink"
        }
    ],
    "sg:phone":"+1 479 751 7599",
    "sg:postcode":"72764",
    "sg:province":"AR",
    "sg:tags":[
        "drinking"
    ],
    "wof:name":"Sunset Saloon LLC",
    "wof:placetype":"venue"
},
  "geometry": {"coordinates":[-94.13113,36.185155],"type":"Point"}
}