{
  "type": "Feature",
  "properties": {
    "iso:country":"US",
    "sg:address":"2704 Gray Fox Ln",
    "sg:city":"Jacksonville",
    "sg:classifiers":[
        {
            "category":"Professional",
            "subcategory":"Detective & Security Services",
            "type":"Services"
        }
    ],
    "sg:phone":"+1 501 766 0938",
    "sg:postcode":"72076",
    "sg:province":"AR",
    "sg:tags":[
        "information",
        "bureau"
    ],
    "wof:name":"Mattison Enterprises",
    "wof:placetype":"venue"
},
  "geometry": {"coordinates":[-92.091164,34.88956],"type":"Point"}
}