{
  "type": "Feature",
  "properties": {
    "addr:full":"623 W 34th St Little Rock AR 72206",
    "addr:housenumber":"623",
    "addr:postcode":"72206",
    "addr:street":"W 34Th St",
    "iso:country":"US",
    "sg:address":"623 W 34th St",
    "sg:city":"Little Rock",
    "sg:classifiers":[
        {
            "category":"Freight",
            "type":"Transportation"
        }
    ],
    "sg:phone":"+1 501 374 8472",
    "sg:postcode":"72206",
    "sg:province":"AR",
    "sg:tags":[
        "operator",
        "local",
        "trucking"
    ],
    "wof:name":"Lafferty Hauling Service",
    "wof:placetype":"venue"
},
  "geometry": {"coordinates":[-92.281569,34.715251],"type":"Point"}
}