{
  "type": "Feature",
  "properties": {
    "iso:country":"US",
    "sg:address":"411 S Walnut St",
    "sg:city":"Osceola",
    "sg:classifiers":[
        {
            "category":"Restaurant",
            "type":"Food & Drink"
        }
    ],
    "sg:phone":"+1 870 563 4575",
    "sg:postcode":"72370",
    "sg:province":"AR",
    "wof:name":"Joe's Place",
    "wof:placetype":"venue"
},
  "geometry": {"coordinates":[-89.969992,35.700818],"type":"Point"}
}