{
  "type": "Feature",
  "properties": {
    "iso:country":"US",
    "sg:address":"709 W Emma Ave",
    "sg:city":"Springdale",
    "sg:classifiers":[
        {
            "category":"Food & Beverages",
            "subcategory":"Groceries & Convenience Stores",
            "type":"Retail Goods"
        }
    ],
    "sg:phone":"+1 479 756 4033",
    "sg:postcode":"72764",
    "sg:province":"AR",
    "wof:name":"Uncle Junes",
    "wof:placetype":"venue"
},
  "geometry": {"coordinates":[-94.136261,36.185032],"type":"Point"}
}