{
  "type": "Feature",
  "properties": {
    "addr:full":"705 N Church St Atkins AR 72823",
    "addr:housenumber":"705",
    "addr:postcode":"72823",
    "addr:street":"N Church St",
    "iso:country":"US",
    "sg:address":"705 N Church St",
    "sg:city":"Atkins",
    "sg:classifiers":[
        {
            "category":"Government",
            "subcategory":"Post Office",
            "type":"Public Place"
        }
    ],
    "sg:phone":"+1 479 641 7210",
    "sg:postcode":"72823",
    "sg:province":"AR",
    "sg:tags":[
        "postal",
        "us"
    ],
    "sg:website":"www.usps.com",
    "wof:name":"US Post Office",
    "wof:placetype":"venue"
},
  "geometry": {"coordinates":[-92.937577,35.249138],"type":"Point"}
}