{
  "type": "Feature",
  "properties": {
    "addr:full":"248 Greenwood Ave Lepanto AR 72354",
    "addr:housenumber":"248",
    "addr:postcode":"72354",
    "addr:street":"Greenwood Ave Lepanto",
    "iso:country":"US",
    "sg:address":"248 Greenwood Ave",
    "sg:city":"Lepanto",
    "sg:classifiers":[
        {
            "category":"Insurance",
            "subcategory":"Insurance Agent",
            "type":"Services"
        }
    ],
    "sg:phone":"+1 870 475 2222",
    "sg:postcode":"72354",
    "sg:province":"AR",
    "wof:name":"Tyler Insurance",
    "wof:placetype":"venue"
},
  "geometry": {"coordinates":[-90.33058699999999,35.611887],"type":"Point"}
}