{
  "type": "Feature",
  "properties": {
    "iso:country":"US",
    "sg:address":"222 Industrial Blvd",
    "sg:city":"Conway",
    "sg:classifiers":[
        {
            "category":"Real Estate",
            "subcategory":"Real Estate Agent",
            "type":"Services"
        }
    ],
    "sg:phone":"+1 501 329 5555",
    "sg:postcode":"72032",
    "sg:province":"AR",
    "sg:website":"www.homesilove.com",
    "wof:name":"Coldwell Banker",
    "wof:placetype":"venue"
},
  "geometry": {"coordinates":[-92.427339,35.066691],"type":"Point"}
}