{
  "type": "Feature",
  "properties": {
    "addr:full":"812 N Hwy 62 65 Harrison AR 72601",
    "addr:housenumber":"812;65",
    "addr:postcode":"72601",
    "addr:street":"N Hwy 62;Harrison",
    "iso:country":"US",
    "sg:address":"812 N Hwy 62 65",
    "sg:city":"Harrison",
    "sg:classifiers":[
        {
            "category":"Home & Garden",
            "subcategory":"Building Materials",
            "type":"Retail Goods"
        }
    ],
    "sg:phone":"+1 870 741 5456",
    "sg:postcode":"72601",
    "sg:province":"AR",
    "sg:tags":[
        "paint"
    ],
    "wof:name":"Sherwin-Williams Paints",
    "wof:placetype":"venue"
},
  "geometry": {"coordinates":[-93.12031899999999,36.252382],"type":"Point"}
}