{
  "type": "Feature",
  "properties": {
    "addr:full":"62 E Main St Booneville AR 72927",
    "addr:housenumber":"62",
    "addr:postcode":"72927",
    "addr:street":"E Main St",
    "iso:country":"US",
    "sg:address":"62 E Main St",
    "sg:city":"Booneville",
    "sg:classifiers":[
        {
            "category":"Shopping",
            "subcategory":"Gifts & Souvenirs",
            "type":"Retail Goods"
        }
    ],
    "sg:phone":"+1 479 675 3322",
    "sg:postcode":"72927",
    "sg:province":"AR",
    "sg:tags":[
        "shop"
    ],
    "wof:name":"Camelot Finer Things Gifts",
    "wof:placetype":"venue"
},
  "geometry": {"coordinates":[-93.921182,35.14013],"type":"Point"}
}