{
  "type": "Feature",
  "properties": {
    "iso:country":"US",
    "sg:address":"133 N Main St",
    "sg:city":"Beebe",
    "sg:classifiers":[
        {
            "category":"Professional",
            "type":"Services"
        }
    ],
    "sg:phone":"+1 501 882 3852",
    "sg:postcode":"72012",
    "sg:province":"AR",
    "sg:tags":[
        "establishment"
    ],
    "wof:name":"Wilbur D Mills Early Childhood",
    "wof:placetype":"venue"
},
  "geometry": {"coordinates":[-91.880471,35.070902],"type":"Point"}
}