{
  "type": "Feature",
  "properties": {
    "iso:country":"US",
    "sg:address":"6104 Sandy Parker Ct",
    "sg:city":"Fort Smith",
    "sg:classifiers":[
        {
            "category":"Health Services",
            "subcategory":"Medical Lab",
            "type":"Services"
        }
    ],
    "sg:phone":"+1 479 649 7270",
    "sg:postcode":"72916",
    "sg:province":"AR",
    "sg:tags":[
        "laboratory"
    ],
    "wof:name":"Presley Speech Pathology Inc",
    "wof:placetype":"venue"
},
  "geometry": {"coordinates":[-94.373362,35.323435],"type":"Point"}
}