{
  "type": "Feature",
  "properties": {
    "iso:country":"US",
    "sg:address":"705 W Faulkner St",
    "sg:city":"El Dorado",
    "sg:classifiers":[
        {
            "category":"Health Services",
            "subcategory":"Doctor",
            "type":"Services"
        }
    ],
    "sg:phone":"+1 870 862 8850",
    "sg:postcode":"71730",
    "sg:province":"AR",
    "sg:tags":[
        "dentist"
    ],
    "wof:name":"Stephen A Scott DDS",
    "wof:placetype":"venue"
},
  "geometry": {"coordinates":[-92.672619,33.214663],"type":"Point"}
}