{
  "type": "Feature",
  "properties": {
    "addr:full":"3503 Jasmine Ln Harrison AR 72601",
    "addr:housenumber":"3503",
    "addr:postcode":"72601",
    "addr:street":"Jasmine Ln",
    "iso:country":"US",
    "sg:address":"3503 Jasmine Ln",
    "sg:city":"Harrison",
    "sg:classifiers":[
        {
            "category":"Freight",
            "type":"Transportation"
        }
    ],
    "sg:phone":"+1 870 741 5549",
    "sg:postcode":"72601",
    "sg:province":"AR",
    "sg:tags":[
        "delivery",
        "operator",
        "local",
        "trucking"
    ],
    "wof:name":"Greg Wienert Inc",
    "wof:placetype":"venue"
},
  "geometry": {"coordinates":[-93.067708,36.16744],"type":"Point"}
}