{
  "type": "Feature",
  "properties": {
    "iso:country":"US",
    "sg:address":"371 N Moore Ave",
    "sg:city":"Piggott",
    "sg:classifiers":[
        {
            "category":"Social Services",
            "type":"Services"
        }
    ],
    "sg:phone":"+1 870 598 1029",
    "sg:postcode":"72454",
    "sg:province":"AR",
    "sg:tags":[
        "child",
        "referral",
        "care"
    ],
    "wof:name":"Curtain Climbers Learn & Play",
    "wof:placetype":"venue"
},
  "geometry": {"coordinates":[-90.18254,36.384287],"type":"Point"}
}