{
  "type": "Feature",
  "properties": {
    "iso:country":"US",
    "sg:address":"315 W Bond Ave",
    "sg:city":"West Memphis",
    "sg:classifiers":[
        {
            "category":"Home & Garden",
            "subcategory":"Garden Supply",
            "type":"Retail Goods"
        }
    ],
    "sg:phone":"+1 870 732 2266",
    "sg:postcode":"72301",
    "sg:province":"AR",
    "sg:tags":[
        "nurseryman"
    ],
    "wof:name":"Southern Shade Nursery",
    "wof:placetype":"venue"
},
  "geometry": {"coordinates":[-90.191114,35.148065],"type":"Point"}
}