{
  "type": "Feature",
  "properties": {
    "addr:full":"217 W Park St Carlisle AR 72024",
    "addr:housenumber":"217",
    "addr:postcode":"72024",
    "addr:street":"W Park St",
    "iso:country":"US",
    "sg:address":"217 W Park St",
    "sg:city":"Carlisle",
    "sg:classifiers":[
        {
            "category":"Wholesale",
            "subcategory":"Durable Goods & Equipment",
            "type":"Manufacturing & Wholesale Goods"
        }
    ],
    "sg:phone":"+1 870 552 7681",
    "sg:postcode":"72024",
    "sg:province":"AR",
    "sg:tags":[
        "laser"
    ],
    "wof:name":"Laserplane/Spectra Precision",
    "wof:placetype":"venue"
},
  "geometry": {"coordinates":[-91.74894399999999,34.780341],"type":"Point"}
}