{
  "type": "Feature",
  "properties": {
    "addr:full":"38 Amanda Dr Batesville AR 72501",
    "addr:housenumber":"38",
    "addr:postcode":"72501",
    "addr:street":"Amanda Dr",
    "iso:country":"US",
    "sg:address":"38 Amanda Dr",
    "sg:city":"Batesville",
    "sg:classifiers":[
        {
            "category":"Personal",
            "type":"Services"
        }
    ],
    "sg:phone":"+1 870 698 9815",
    "sg:postcode":"72501",
    "sg:province":"AR",
    "wof:name":"Best Rates Storage",
    "wof:placetype":"venue"
},
  "geometry": {"coordinates":[-91.65735599999999,35.7374],"type":"Point"}
}