{
  "type": "Feature",
  "properties": {
    "addr:full":"506 E Broadway St Morrilton AR 72110",
    "addr:housenumber":"506",
    "addr:postcode":"72110",
    "addr:street":"E Broadway St",
    "iso:country":"US",
    "sg:address":"506 E Broadway St",
    "sg:city":"Morrilton",
    "sg:classifiers":[
        {
            "category":"Organizations",
            "subcategory":"Religious Organization",
            "type":"Services"
        }
    ],
    "sg:phone":"+1 501 354 4181",
    "sg:postcode":"72110",
    "sg:province":"AR",
    "wof:name":"Sacred Heart Church",
    "wof:placetype":"venue"
},
  "geometry": {"coordinates":[-92.740134,35.152038],"type":"Point"}
}