{
  "type": "Feature",
  "properties": {
    "addr:full":"515 W Narroway St Benton AR 72015",
    "addr:housenumber":"515",
    "addr:postcode":"72015",
    "addr:street":"W Narroway St",
    "iso:country":"US",
    "sg:address":"515 W Narroway St",
    "sg:city":"Benton",
    "sg:classifiers":[
        {
            "category":"Wholesale",
            "subcategory":"Machinery & Supplies",
            "type":"Manufacturing & Wholesale Goods"
        }
    ],
    "sg:phone":"+1 501 778 5304",
    "sg:postcode":"72015",
    "sg:province":"AR",
    "sg:tags":[
        "manufacturer"
    ],
    "wof:name":"Kordsmeier Sales Inc",
    "wof:placetype":"venue"
},
  "geometry": {"coordinates":[-92.5926,34.568903],"type":"Point"}
}