{
  "type": "Feature",
  "properties": {
    "addr:full":"320 Whittington Ave Hot Springs National AR 71901",
    "addr:housenumber":"320",
    "addr:postcode":"71901",
    "addr:street":"Whittington Ave",
    "iso:country":"US",
    "sg:address":"320 Whittington Ave",
    "sg:city":"Hot Springs National",
    "sg:classifiers":[
        {
            "category":"Health Services",
            "subcategory":"Nursing And Care Facility",
            "type":"Services"
        }
    ],
    "sg:phone":"+1 501 623 5260",
    "sg:postcode":"71901",
    "sg:province":"AR",
    "wof:name":"Whittington Manor",
    "wof:placetype":"venue"
},
  "geometry": {"coordinates":[-93.06124,34.516357],"type":"Point"}
}