{
  "type": "Feature",
  "properties": {
    "iso:country":"US",
    "sg:address":"6718 Shadow Valley Rd",
    "sg:city":"Rogers",
    "sg:classifiers":[
        {
            "category":"Professional",
            "subcategory":"Management & Consulting",
            "type":"Services"
        }
    ],
    "sg:phone":"+1 479 203 1100",
    "sg:postcode":"72758",
    "sg:province":"AR",
    "sg:tags":[
        "consultant"
    ],
    "wof:name":"Lawrence Fennell & Assoc",
    "wof:placetype":"venue"
},
  "geometry": {"coordinates":[-94.209985,36.28982],"type":"Point"}
}