{
  "type": "Feature",
  "properties": {
    "addr:full":"1502 Sunshine Rd Royal AR 71968",
    "addr:housenumber":"1502",
    "addr:postcode":"71968",
    "addr:street":"Sunshine Rd",
    "iso:country":"US",
    "sg:address":"1502 Sunshine Rd",
    "sg:city":"Royal",
    "sg:classifiers":[
        {
            "category":"Place Of Worship",
            "subcategory":"Church",
            "type":"Public Place"
        },
        {
            "category":"Place Of Worship",
            "type":"Public Place"
        },
        {
            "category":"Organizations",
            "subcategory":"Religious Organization",
            "type":"Services"
        }
    ],
    "sg:phone":"+1 501 767 3806",
    "sg:postcode":"71968",
    "sg:province":"AR",
    "sg:tags":[
        "god",
        "churches-church",
        "churches-pentecostal"
    ],
    "wof:name":"Church Of God Forrest Hill",
    "wof:placetype":"venue"
},
  "geometry": {"coordinates":[-93.27336699999999,34.486893],"type":"Point"}
}