{
  "type": "Feature",
  "properties": {
    "iso:country":"US",
    "sg:address":"3688 Mountain Pine Rd",
    "sg:city":"Mountain Pine",
    "sg:classifiers":[
        {
            "category":"Retail",
            "subcategory":"Auto Repair",
            "type":"Services"
        }
    ],
    "sg:phone":"+1 501 767 5697",
    "sg:postcode":"71956",
    "sg:province":"AR",
    "sg:tags":[
        "body",
        "automobile",
        "painting"
    ],
    "wof:name":"Buttrums' Body Repair & Pntng",
    "wof:placetype":"venue"
},
  "geometry": {"coordinates":[-93.145473,34.588003],"type":"Point"}
}