{
  "type": "Feature",
  "properties": {
    "addr:full":"19010 Mahar Rd Roland AR 72135",
    "addr:postcode":"19010;72135",
    "addr:street":"Mahar Rd Roland",
    "iso:country":"US",
    "sg:address":"19010 Mahar Rd",
    "sg:city":"Roland",
    "sg:classifiers":[
        {
            "category":"Freight",
            "type":"Transportation"
        }
    ],
    "sg:phone":"+1 501 868 9549",
    "sg:postcode":"72135",
    "sg:province":"AR",
    "sg:tags":[
        "operator",
        "local",
        "trucking"
    ],
    "wof:name":"Chuck Elam Hauling",
    "wof:placetype":"venue"
},
  "geometry": {"coordinates":[-92.479079,34.869196],"type":"Point"}
}