{
  "type": "Feature",
  "properties": {
    "iso:country":"US",
    "sg:address":"2407 Massard Rd",
    "sg:city":"Fort Smith",
    "sg:classifiers":[
        {
            "category":"Social Services",
            "subcategory":"Child Care",
            "type":"Services"
        },
        {
            "category":"Education",
            "subcategory":"School",
            "type":"Public Place"
        }
    ],
    "sg:phone":"+1 479 452 5330",
    "sg:postcode":"72903",
    "sg:province":"AR",
    "sg:website":"www.1stlutheran.com",
    "wof:name":"First Lutheran Preschool",
    "wof:placetype":"venue"
},
  "geometry": {"coordinates":[-94.34033,35.358515],"type":"Point"}
}