{
  "type": "Feature",
  "properties": {
    "iso:country":"US",
    "sg:address":"6001 Southwind Dr",
    "sg:city":"North Little Rock",
    "sg:classifiers":[
        {
            "category":"Professional",
            "type":"Services"
        }
    ],
    "sg:phone":"+1 501 753 9522",
    "sg:postcode":"72118",
    "sg:province":"AR",
    "wof:name":"John V Simons",
    "wof:placetype":"venue"
},
  "geometry": {"coordinates":[-92.332444,34.810566],"type":"Point"}
}