{
  "type": "Feature",
  "properties": {
    "addr:full":"220 White Dr Batesville AR 72501",
    "addr:housenumber":"220",
    "addr:postcode":"72501",
    "addr:street":"White Dr",
    "iso:country":"US",
    "sg:address":"220 White Dr",
    "sg:city":"Batesville",
    "sg:classifiers":[
        {
            "category":"Retail",
            "subcategory":"Laundry & Dry Cleaning",
            "type":"Services"
        }
    ],
    "sg:phone":"+1 870 793 5665",
    "sg:postcode":"72501",
    "sg:province":"AR",
    "wof:name":"Nu-Way Linen Supply",
    "wof:placetype":"venue"
},
  "geometry": {"coordinates":[-91.657635,35.788525],"type":"Point"}
}