{
  "type": "Feature",
  "properties": {
    "addr:full":"356 N Grant Ave Booneville AR 72927",
    "addr:housenumber":"356",
    "addr:postcode":"72927",
    "addr:street":"N Grant Ave",
    "iso:country":"US",
    "sg:address":"356 N Grant Ave",
    "sg:city":"Booneville",
    "sg:classifiers":[
        {
            "category":"Professional",
            "subcategory":"Lawyer & Legal Services",
            "type":"Services"
        }
    ],
    "sg:phone":"+1 479 675 2100",
    "sg:postcode":"72927",
    "sg:province":"AR",
    "sg:tags":[
        "plan"
    ],
    "wof:name":"Williams, John R Law Office",
    "wof:placetype":"venue"
},
  "geometry": {"coordinates":[-93.92049299999999,35.140686],"type":"Point"}
}