{
  "type": "Feature",
  "properties": {
    "iso:country":"US",
    "sg:address":"1605 Harkrider St",
    "sg:city":"Conway",
    "sg:classifiers":[
        {
            "category":"Manufacturing",
            "subcategory":"Buildings",
            "type":"Manufacturing & Wholesale Goods"
        },
        {
            "category":"Building & Trades",
            "subcategory":"Construction",
            "type":"Services"
        }
    ],
    "sg:phone":"+1 501 327 2120",
    "sg:postcode":"72032",
    "sg:province":"AR",
    "sg:tags":[
        "industrial",
        "waterproofing",
        "builder",
        "specialty",
        "system",
        "heating",
        "contractor",
        "contractors-commercial",
        "home",
        "air conditioning"
    ],
    "wof:name":"Sherman Waterproofing Incorporated",
    "wof:placetype":"venue"
},
  "geometry": {"coordinates":[-92.440394,35.102304],"type":"Point"}
}