{
  "type": "Feature",
  "properties": {
    "addr:full":"1311 Rebsamen Park Rd Little Rock AR 72202",
    "addr:housenumber":"1311",
    "addr:postcode":"72202",
    "addr:street":"Rebsamen Park Rd",
    "iso:country":"US",
    "sg:address":"1311 Rebsamen Park Rd",
    "sg:city":"Little Rock",
    "sg:classifiers":[
        {
            "category":"Wholesale",
            "subcategory":"Apparel",
            "type":"Manufacturing & Wholesale Goods"
        },
        {
            "category":"Wholesale",
            "subcategory":"Home Furnishings",
            "type":"Manufacturing & Wholesale Goods"
        }
    ],
    "sg:phone":"+1 501 663 0674",
    "sg:postcode":"72202",
    "sg:province":"AR",
    "sg:tags":[
        "upholstery",
        "curtain",
        "material",
        "fabric",
        "drapery"
    ],
    "wof:name":"Larry's Inc",
    "wof:placetype":"venue"
},
  "geometry": {"coordinates":[-92.310023,34.762553],"type":"Point"}
}