{
  "type": "Feature",
  "properties": {
    "iso:country":"US",
    "sg:address":"474 California Ave SW",
    "sg:city":"Camden",
    "sg:classifiers":[
        {
            "category":"Professional",
            "subcategory":"Employment Agencies",
            "type":"Services"
        }
    ],
    "sg:phone":"+1 870 574 1521",
    "sg:postcode":"71701",
    "sg:province":"AR",
    "sg:tags":[
        "help",
        "supply"
    ],
    "wof:name":"Southwest Arkansas Planning &",
    "wof:placetype":"venue"
},
  "geometry": {"coordinates":[-92.833915,33.579463],"type":"Point"}
}