{
  "type": "Feature",
  "properties": {
    "iso:country":"US",
    "sg:address":"205 Treasure Isle Rd",
    "sg:city":"Hot Springs",
    "sg:classifiers":[
        {
            "category":"Shopping",
            "subcategory":"Used Merchandise",
            "type":"Retail Goods"
        }
    ],
    "sg:phone":"+1 501 767 0719",
    "sg:postcode":"71913",
    "sg:province":"AR",
    "sg:tags":[
        "pawnbroker"
    ],
    "wof:name":"Vulistis Gun & Pawn",
    "wof:placetype":"venue"
},
  "geometry": {"coordinates":[-93.176061,34.50939],"type":"Point"}
}