{
  "type": "Feature",
  "properties": {
    "addr:full":"2707 Mount Holly Rd Camden AR 71701",
    "addr:housenumber":"2707",
    "addr:postcode":"71701",
    "addr:street":"Mount Holly Rd",
    "iso:country":"US",
    "sg:address":"2707 Mount Holly Rd",
    "sg:city":"Camden",
    "sg:classifiers":[
        {
            "category":"Place Of Worship",
            "subcategory":"Church",
            "type":"Public Place"
        },
        {
            "category":"Place Of Worship",
            "type":"Public Place"
        }
    ],
    "sg:phone":"+1 870 231 5228",
    "sg:postcode":"71701",
    "sg:province":"AR",
    "sg:tags":[
        "testament",
        "christ-new",
        "churches-church",
        "christ"
    ],
    "sg:website":"http://www.cullendalecoc.com",
    "wof:name":"Church of Christ Cullendale",
    "wof:placetype":"venue"
},
  "geometry": {"coordinates":[-92.85072700000001,33.518824],"type":"Point"}
}