{
  "type": "Feature",
  "properties": {
    "iso:country":"US",
    "sg:address":"2568 Hwy 62 E",
    "sg:city":"Mountain Home",
    "sg:classifiers":[
        {
            "category":"Banks & Credit Unions",
            "subcategory":"Bank",
            "type":"Services"
        }
    ],
    "sg:phone":"+1 870 492 5010",
    "sg:postcode":"72653",
    "sg:province":"AR",
    "sg:tags":[
        "cashing",
        "check"
    ],
    "wof:name":"Cash Advance Of Mountain Home",
    "wof:placetype":"venue"
},
  "geometry": {"coordinates":[-92.33404899999999,36.361509],"type":"Point"}
}