{
  "type": "Feature",
  "properties": {
    "addr:full":"6037 Central Ave Hot Springs AR 71913",
    "addr:housenumber":"6037",
    "addr:postcode":"71913",
    "addr:street":"Central Ave",
    "iso:country":"US",
    "sg:address":"6037 Central Ave",
    "sg:city":"Hot Springs",
    "sg:classifiers":[
        {
            "category":"Mining & Drilling",
            "type":"Manufacturing & Wholesale Goods"
        }
    ],
    "sg:phone":"+1 501 525 0135",
    "sg:postcode":"71913",
    "sg:province":"AR",
    "sg:tags":[
        "stone"
    ],
    "wof:name":"Arkansas Stoneworks",
    "wof:placetype":"venue"
},
  "geometry": {"coordinates":[-93.094061,34.411757],"type":"Point"}
}