{
  "type": "Feature",
  "properties": {
    "addr:full":"204 S Grand St Grove OK 74344",
    "addr:housenumber":"204",
    "addr:postcode":"74344",
    "addr:street":"S Grand St Grove",
    "iso:country":"US",
    "sg:address":"204 S Grand St",
    "sg:city":"Grove",
    "sg:classifiers":[
        {
            "category":"Fast Food",
            "type":"Food & Drink"
        },
        {
            "category":"Restaurant",
            "type":"Food & Drink"
        }
    ],
    "sg:phone":"+1 918 786 2291",
    "sg:postcode":"74344",
    "sg:province":"OK",
    "sg:tags":[
        "style",
        "hamburger",
        "family",
        "dog",
        "lunch",
        "hot",
        "take",
        "american",
        "brunch",
        "breakfast"
    ],
    "wof:name":"McDonald's Office",
    "wof:placetype":"venue"
},
  "geometry": {"coordinates":[-94.770636,36.594447],"type":"Point"}
}