{
  "type": "Feature",
  "properties": {
    "iso:country":"US",
    "sg:address":"1710 W Sycamore St",
    "sg:city":"Rogers",
    "sg:classifiers":[
        {
            "category":"Social Services",
            "subcategory":"Child Care",
            "type":"Services"
        }
    ],
    "sg:phone":"+1 479 636 4797",
    "sg:postcode":"72758",
    "sg:province":"AR",
    "sg:tags":[
        "day"
    ],
    "wof:name":"Alpha Child Day Care Center",
    "wof:placetype":"venue"
},
  "geometry": {"coordinates":[-94.141267,36.327459],"type":"Point"}
}