{
  "type": "Feature",
  "properties": {
    "iso:country":"US",
    "sg:address":"205 2nd St",
    "sg:city":"Green Forest",
    "sg:classifiers":[
        {
            "category":"Insurance",
            "subcategory":"Insurance Agent",
            "type":"Services"
        }
    ],
    "sg:phone":"+1 870 438 6115",
    "sg:postcode":"72638",
    "sg:province":"AR",
    "wof:name":"Shibley Insurance Inc",
    "wof:placetype":"venue"
},
  "geometry": {"coordinates":[-93.433857,36.334675],"type":"Point"}
}