{
  "type": "Feature",
  "properties": {
    "addr:full":"7 Lazo Pl Hot Springs Vlg AR 71909",
    "addr:housenumber":"7",
    "addr:postcode":"71909",
    "addr:street":"Lazo Pl",
    "iso:country":"US",
    "sg:address":"7 Lazo Pl",
    "sg:city":"Hot Springs Vlg",
    "sg:classifiers":[
        {
            "category":"Manufacturing",
            "subcategory":"Printing",
            "type":"Manufacturing & Wholesale Goods"
        }
    ],
    "sg:phone":"+1 501 922 1831",
    "sg:postcode":"71909",
    "sg:province":"AR",
    "sg:tags":[
        "publisher"
    ],
    "wof:name":"Hilt Publishing Inc",
    "wof:placetype":"venue"
},
  "geometry": {"coordinates":[-92.975314,34.655134],"type":"Point"}
}