{
  "type": "Feature",
  "properties": {
    "iso:country":"US",
    "sg:address":"2901 Commerce Dr",
    "sg:city":"Jonesboro",
    "sg:classifiers":[
        {
            "category":"Freight",
            "type":"Transportation"
        }
    ],
    "sg:phone":"+1 870 932 5713",
    "sg:postcode":"72401",
    "sg:province":"AR",
    "sg:tags":[
        "operator",
        "local",
        "trucking"
    ],
    "wof:name":"J & W Cartage Inc",
    "wof:placetype":"venue"
},
  "geometry": {"coordinates":[-90.624607,35.807786],"type":"Point"}
}