{
  "type": "Feature",
  "properties": {
    "addr:full":"14521 State Hwy 107 Jacksonville AR 72076",
    "addr:housenumber":"14521",
    "addr:postcode":"72076",
    "addr:street":"State Hwy 107",
    "iso:country":"US",
    "sg:address":"14521 State Hwy 107",
    "sg:city":"Jacksonville",
    "sg:classifiers":[
        {
            "category":"Retail",
            "subcategory":"Veterinary Services",
            "type":"Services"
        }
    ],
    "sg:phone":"+1 501 835 7115",
    "sg:postcode":"72076",
    "sg:province":"AR",
    "wof:name":"Pet Care",
    "wof:placetype":"venue"
},
  "geometry": {"coordinates":[-92.18527899999999,34.880302],"type":"Point"}
}