{
  "type": "Feature",
  "properties": {
    "iso:country":"US",
    "sg:address":"2395 N College Ave",
    "sg:city":"Fayetteville",
    "sg:classifiers":[
        {
            "category":"Autos & Motor Vehicles",
            "subcategory":"Automobile Sales",
            "type":"Retail Goods"
        }
    ],
    "sg:phone":"+1 479 442 5321",
    "sg:postcode":"72703",
    "sg:province":"AR",
    "sg:tags":[
        "car",
        "dealer"
    ],
    "sg:website":"www.timhurdlincolnmercury.com",
    "wof:name":"Tim Hurd Lincoln Mercury",
    "wof:placetype":"venue"
},
  "geometry": {"coordinates":[-94.153103,36.093633],"type":"Point"}
}