{
  "type": "Feature",
  "properties": {
    "iso:country":"US",
    "sg:address":"821 N Main St",
    "sg:city":"Harrison",
    "sg:classifiers":[
        {
            "category":"Professional",
            "subcategory":"Accounting & Tax Preparation",
            "type":"Services"
        }
    ],
    "sg:phone":"+1 870 741 1040",
    "sg:postcode":"72601",
    "sg:province":"AR",
    "wof:name":"Mr Movie of Mountain Home",
    "wof:placetype":"venue"
},
  "geometry": {"coordinates":[-93.106967,36.239384],"type":"Point"}
}