{
  "type": "Feature",
  "properties": {
    "iso:country":"US",
    "sg:address":"15 Timberwood Dr",
    "sg:city":"Cabot",
    "sg:classifiers":[
        {
            "category":"Professional",
            "subcategory":"Management & Consulting",
            "type":"Services"
        }
    ],
    "sg:phone":"+1 501 941 9584",
    "sg:postcode":"72023",
    "sg:province":"AR",
    "sg:tags":[
        "retail",
        "direct",
        "sales"
    ],
    "wof:name":"Frill & Frippery",
    "wof:placetype":"venue"
},
  "geometry": {"coordinates":[-92.006051,34.986633],"type":"Point"}
}