{
  "type": "Feature",
  "properties": {
    "addr:full":"1601 Louisiana St Little Rock AR 72206",
    "addr:housenumber":"1601",
    "addr:postcode":"72206",
    "addr:street":"Louisiana St",
    "iso:country":"US",
    "sg:address":"1601 Louisiana St",
    "sg:city":"Little Rock",
    "sg:classifiers":[
        {
            "category":"Organizations",
            "subcategory":"Religious Organization",
            "type":"Services"
        }
    ],
    "sg:phone":"+1 501 375 1600",
    "sg:postcode":"72206",
    "sg:province":"AR",
    "sg:tags":[
        "church"
    ],
    "sg:website":"www.qqumc.org",
    "wof:name":"Quapaw Quarter Untd Mthdst Chr",
    "wof:placetype":"venue"
},
  "geometry": {"coordinates":[-92.27461599999999,34.732572],"type":"Point"}
}