{
  "type": "Feature",
  "properties": {
    "iso:country":"US",
    "sg:address":"702 Laughrun Dr",
    "sg:city":"Forrest City",
    "sg:classifiers":[
        {
            "category":"Restaurant",
            "type":"Food & Drink"
        }
    ],
    "sg:phone":"+1 870 633 3101",
    "sg:postcode":"72335",
    "sg:province":"AR",
    "sg:tags":[
        "eating"
    ],
    "wof:name":"Wings In Flight Inc",
    "wof:placetype":"venue"
},
  "geometry": {"coordinates":[-90.798062,35.024568],"type":"Point"}
}