{
  "type": "Feature",
  "properties": {
    "iso:country":"US",
    "sg:address":"1218 Military Rd",
    "sg:city":"Benton",
    "sg:classifiers":[
        {
            "category":"Coffee & Tea",
            "type":"Food & Drink"
        },
        {
            "category":"Bakery",
            "type":"Food & Drink"
        },
        {
            "category":"Donuts",
            "type":"Food & Drink"
        }
    ],
    "sg:menulink":"http://www.allmenus.com/ar/bauxite/230932-daylight-donuts/menu/",
    "sg:phone":"+1 501 778 1147",
    "sg:postcode":"72015",
    "sg:province":"AR",
    "sg:tags":[
        "american",
        "pastry"
    ],
    "wof:name":"Daylight Donuts",
    "wof:placetype":"venue"
},
  "geometry": {"coordinates":[-92.579199,34.574775],"type":"Point"}
}