{
  "type": "Feature",
  "properties": {
    "iso:country":"US",
    "sg:address":"2215 Smackover Hwy",
    "sg:city":"El Dorado",
    "sg:classifiers":[
        {
            "category":"Mining & Drilling",
            "type":"Manufacturing & Wholesale Goods"
        }
    ],
    "sg:phone":"+1 870 546 3395",
    "sg:postcode":"71730",
    "sg:province":"AR",
    "sg:tags":[
        "field"
    ],
    "wof:name":"Oil Operators",
    "wof:placetype":"venue"
},
  "geometry": {"coordinates":[-92.686767,33.308979],"type":"Point"}
}