{
  "type": "Feature",
  "properties": {
    "iso:country":"US",
    "sg:address":"5024 US Hwy 64 E",
    "sg:city":"Pottsville",
    "sg:classifiers":[
        {
            "category":"Wholesale",
            "subcategory":"Groceries",
            "type":"Manufacturing & Wholesale Goods"
        }
    ],
    "sg:phone":"+1 479 890 6636",
    "sg:postcode":"72858",
    "sg:province":"AR",
    "sg:tags":[
        "food",
        "product"
    ],
    "wof:name":"Tyson Feed Mill",
    "wof:placetype":"venue"
},
  "geometry": {"coordinates":[-93.069811,35.266954],"type":"Point"}
}