{
  "type": "Feature",
  "properties": {
    "addr:full":"24928 Cherokee Rd Gentry AR 72734",
    "addr:housenumber":"24928",
    "addr:postcode":"72734",
    "addr:street":"Cherokee Rd",
    "iso:country":"US",
    "sg:address":"24928 Cherokee Rd",
    "sg:city":"Gentry",
    "sg:classifiers":[
        {
            "category":"Farming",
            "subcategory":"Dairy Farm",
            "type":"Manufacturing & Wholesale Goods"
        }
    ],
    "sg:phone":"+1 479 736 8535",
    "sg:postcode":"72734",
    "sg:province":"AR",
    "sg:tags":[
        "beef",
        "cattle"
    ],
    "wof:name":"Donald L Amos",
    "wof:placetype":"venue"
},
  "geometry": {"coordinates":[-94.582807,36.298401],"type":"Point"}
}