{
  "type": "Feature",
  "properties": {
    "iso:country":"US",
    "sg:address":"303 E Calhoun St",
    "sg:city":"Magnolia",
    "sg:classifiers":[
        {
            "category":"Professional",
            "subcategory":"Accounting & Tax Preparation",
            "type":"Services"
        }
    ],
    "sg:phone":"+1 870 234 1500",
    "sg:postcode":"71753",
    "sg:province":"AR",
    "sg:tags":[
        "accountant"
    ],
    "wof:name":"Steve Kincaid CPA",
    "wof:placetype":"venue"
},
  "geometry": {"coordinates":[-93.23828399999999,33.265724],"type":"Point"}
}