{
  "type": "Feature",
  "properties": {
    "addr:full":"2219 N 55th Ln Fort Smith AR 72904",
    "addr:housenumber":"2219",
    "addr:postcode":"72904",
    "addr:street":"N 55Th Ln",
    "iso:country":"US",
    "sg:address":"2219 N 55th Ln",
    "sg:city":"Fort Smith",
    "sg:classifiers":[
        {
            "category":"Freight",
            "type":"Transportation"
        }
    ],
    "sg:phone":"+1 479 452 5359",
    "sg:postcode":"72904",
    "sg:province":"AR",
    "sg:tags":[
        "trucking"
    ],
    "wof:name":"Pressley Trucking Inc",
    "wof:placetype":"venue"
},
  "geometry": {"coordinates":[-94.369772,35.399528],"type":"Point"}
}