{
  "type": "Feature",
  "properties": {
    "iso:country":"US",
    "sg:address":"607 N Storer Ave",
    "sg:city":"Fayetteville",
    "sg:classifiers":[
        {
            "category":"Organizations",
            "subcategory":"Religious Organization",
            "type":"Services"
        }
    ],
    "sg:phone":"+1 479 973 2702",
    "sg:postcode":"72701",
    "sg:province":"AR",
    "sg:tags":[
        "church"
    ],
    "wof:name":"Temple Shalom of NW Arkansas",
    "wof:placetype":"venue"
},
  "geometry": {"coordinates":[-94.172245,36.072787],"type":"Point"}
}