{
  "type": "Feature",
  "properties": {
    "addr:full":"108 Main St NE Gravette AR 72736",
    "addr:housenumber":"108",
    "addr:postcode":"72736",
    "addr:street":"Main St Ne",
    "iso:country":"US",
    "sg:address":"108 Main St NE",
    "sg:city":"Gravette",
    "sg:classifiers":[
        {
            "category":"Utilities",
            "subcategory":"Electric",
            "type":"Services"
        }
    ],
    "sg:phone":"+1 479 787 5241",
    "sg:postcode":"72736",
    "sg:province":"AR",
    "wof:name":"Empire District Electric Co",
    "wof:placetype":"venue"
},
  "geometry": {"coordinates":[-94.45316699999999,36.422373],"type":"Point"}
}