{
  "type": "Feature",
  "properties": {
    "iso:country":"US",
    "sg:address":"300 E Rush Ave",
    "sg:city":"Harrison",
    "sg:classifiers":[
        {
            "category":"Professional",
            "subcategory":"Research",
            "type":"Services"
        },
        {
            "category":"Professional",
            "subcategory":"Management & Consulting",
            "type":"Services"
        }
    ],
    "sg:phone":"+1 870 365 0789",
    "sg:postcode":"72601",
    "sg:province":"AR",
    "sg:tags":[
        "environmental",
        "ecological",
        "business"
    ],
    "wof:name":"Environmental Global & Contain",
    "wof:placetype":"venue"
},
  "geometry": {"coordinates":[-93.104801,36.230826],"type":"Point"}
}