{
  "type": "Feature",
  "properties": {
    "addr:full":"509 E 4th St Russellville AR 72801",
    "addr:housenumber":"509",
    "addr:postcode":"72801",
    "addr:street":"E 4Th St",
    "iso:country":"US",
    "sg:address":"509 E 4th St",
    "sg:city":"Russellville",
    "sg:classifiers":[
        {
            "category":"Shopping",
            "subcategory":"Shoes",
            "type":"Retail Goods"
        }
    ],
    "sg:phone":"+1 479 968 8980",
    "sg:postcode":"72801",
    "sg:province":"AR",
    "sg:tags":[
        "leather",
        "boot"
    ],
    "wof:name":"Woody's Boot & Shoe Shop",
    "wof:placetype":"venue"
},
  "geometry": {"coordinates":[-93.128213,35.275065],"type":"Point"}
}