{
  "type": "Feature",
  "properties": {
    "addr:full":"2004 Portland Rd Portland AR 71663",
    "addr:housenumber":"2004",
    "addr:postcode":"71663",
    "addr:street":"Portland Rd",
    "iso:country":"US",
    "sg:address":"2004 Portland Rd",
    "sg:city":"Portland",
    "sg:classifiers":[
        {
            "category":"Manufacturing",
            "subcategory":"Lumber",
            "type":"Manufacturing & Wholesale Goods"
        }
    ],
    "sg:phone":"+1 870 737 2158",
    "sg:postcode":"71663",
    "sg:province":"AR",
    "sg:tags":[
        "logging"
    ],
    "wof:name":"Thomas E Moyers",
    "wof:placetype":"venue"
},
  "geometry": {"coordinates":[-91.432372,33.212978],"type":"Point"}
}