{
  "type": "Feature",
  "properties": {
    "iso:country":"US",
    "sg:address":"118 Virginia St",
    "sg:city":"Springdale",
    "sg:classifiers":[
        {
            "category":"Retail",
            "subcategory":"Auto Repair",
            "type":"Services"
        }
    ],
    "sg:phone":"+1 479 756 0808",
    "sg:postcode":"72764",
    "sg:province":"AR",
    "sg:tags":[
        "body"
    ],
    "wof:name":"Countryside Autobody",
    "wof:placetype":"venue"
},
  "geometry": {"coordinates":[-94.13969299999999,36.187169],"type":"Point"}
}