{
  "type": "Feature",
  "properties": {
    "iso:country":"US",
    "sg:address":"1015 Lincoln St",
    "sg:city":"Conway",
    "sg:classifiers":[
        {
            "category":"Wholesale",
            "subcategory":"Electrical",
            "type":"Manufacturing & Wholesale Goods"
        }
    ],
    "sg:phone":"+1 501 730 0500",
    "sg:postcode":"72032",
    "sg:province":"AR",
    "sg:tags":[
        "equipment"
    ],
    "wof:name":"Graybar Electric Company Inc",
    "wof:placetype":"venue"
},
  "geometry": {"coordinates":[-92.433365,35.093431],"type":"Point"}
}