{
  "type": "Feature",
  "properties": {
    "iso:country":"US",
    "sg:address":"6170 Getty Dr",
    "sg:city":"North Little Rock",
    "sg:classifiers":[
        {
            "category":"Manufacturing",
            "subcategory":"Glass & Minerals",
            "type":"Manufacturing & Wholesale Goods"
        }
    ],
    "sg:phone":"+1 501 835 7992",
    "sg:postcode":"72117",
    "sg:province":"AR",
    "sg:tags":[
        "mfg",
        "cut",
        "contractor",
        "trade"
    ],
    "wof:name":"Sherwood Marble Co Inc",
    "wof:placetype":"venue"
},
  "geometry": {"coordinates":[-92.190628,34.8228],"type":"Point"}
}