{
  "type": "Feature",
  "properties": {
    "iso:country":"US",
    "sg:address":"1317 N 10th St",
    "sg:city":"Arkadelphia",
    "sg:classifiers":[
        {
            "category":"Autos & Motor Vehicles",
            "subcategory":"Automobile Sales",
            "type":"Retail Goods"
        }
    ],
    "sg:phone":"+1 870 230 8099",
    "sg:postcode":"71923",
    "sg:province":"AR",
    "sg:tags":[
        "used"
    ],
    "wof:name":"Davis Auto Sales",
    "wof:placetype":"venue"
},
  "geometry": {"coordinates":[-93.062511,34.143555],"type":"Point"}
}