{
  "type": "Feature",
  "properties": {
    "iso:country":"US",
    "sg:address":"8631 Harvard Dr",
    "sg:city":"Fort Smith",
    "sg:classifiers":[
        {
            "category":"Wholesale",
            "subcategory":"Stationery",
            "type":"Manufacturing & Wholesale Goods"
        }
    ],
    "sg:phone":"+1 479 646 5955",
    "sg:postcode":"72908",
    "sg:province":"AR",
    "sg:tags":[
        "supply"
    ],
    "wof:name":"FSA Forms",
    "wof:placetype":"venue"
},
  "geometry": {"coordinates":[-94.415018,35.30294],"type":"Point"}
}