{
  "type": "Feature",
  "properties": {
    "addr:full":"124 S Main St Brinkley AR 72021",
    "addr:housenumber":"124",
    "addr:postcode":"72021",
    "addr:street":"S Main St",
    "iso:country":"US",
    "sg:address":"124 S Main St",
    "sg:city":"Brinkley",
    "sg:classifiers":[
        {
            "category":"Shopping",
            "subcategory":"Computers & Home Electronics",
            "type":"Retail Goods"
        }
    ],
    "sg:phone":"+1 870 734 3443",
    "sg:postcode":"72021",
    "sg:province":"AR",
    "sg:tags":[
        "equipment",
        "electronic",
        "supply"
    ],
    "wof:name":"Radio Shack",
    "wof:placetype":"venue"
},
  "geometry": {"coordinates":[-91.19464000000001,34.886348],"type":"Point"}
}