{
  "type": "Feature",
  "properties": {
    "iso:country":"US",
    "sg:address":"3 Hickory Ln",
    "sg:city":"Maumelle",
    "sg:classifiers":[
        {
            "category":"Professional",
            "subcategory":"Business Services",
            "type":"Services"
        }
    ],
    "sg:phone":"+1 501 851 1090",
    "sg:postcode":"72113",
    "sg:province":"AR",
    "sg:tags":[
        "inspection"
    ],
    "wof:name":"Homecoming Inspections",
    "wof:placetype":"venue"
},
  "geometry": {"coordinates":[-92.400841,34.868698],"type":"Point"}
}