{
  "type": "Feature",
  "properties": {
    "addr:full":"4719 Dollarway Rd White Hall AR 71602",
    "addr:housenumber":"4719",
    "addr:postcode":"71602",
    "addr:street":"Dollarway Rd",
    "iso:country":"US",
    "sg:address":"4719 Dollarway Rd",
    "sg:city":"White Hall",
    "sg:classifiers":[
        {
            "category":"Autos & Motor Vehicles",
            "subcategory":"Automobile Sales",
            "type":"Retail Goods"
        }
    ],
    "sg:phone":"+1 870 541 0508",
    "sg:postcode":"71602",
    "sg:province":"AR",
    "sg:tags":[
        "car",
        "used",
        "dealer"
    ],
    "wof:name":"Raineys' Auto Mart",
    "wof:placetype":"venue"
},
  "geometry": {"coordinates":[-92.051062,34.240037],"type":"Point"}
}