{
  "type": "Feature",
  "properties": {
    "addr:full":"5601 State Hwy 15 Sherrill AR 72152",
    "addr:housenumber":"5601",
    "addr:postcode":"72152",
    "addr:street":"State Hwy 15 Sherrill",
    "iso:country":"US",
    "sg:address":"5601 State Hwy 15",
    "sg:city":"Sherrill",
    "sg:classifiers":[
        {
            "category":"Organizations",
            "subcategory":"Religious Organization",
            "type":"Services"
        }
    ],
    "sg:phone":"+1 870 766 4060",
    "sg:postcode":"72152",
    "sg:province":"AR",
    "sg:tags":[
        "church"
    ],
    "wof:name":"Corinth Baptist Church",
    "wof:placetype":"venue"
},
  "geometry": {"coordinates":[-91.938664,34.374284],"type":"Point"}
}