{
  "type": "Feature",
  "properties": {
    "iso:country":"US",
    "sg:address":"508 Ragweed Valley Rd",
    "sg:city":"Royal",
    "sg:classifiers":[
        {
            "category":"Professional",
            "subcategory":"Detective & Security Services",
            "type":"Services"
        }
    ],
    "sg:phone":"+1 501 991 3637",
    "sg:postcode":"71968",
    "sg:province":"AR",
    "sg:tags":[
        "car"
    ],
    "wof:name":"Mike Roberson",
    "wof:placetype":"venue"
},
  "geometry": {"coordinates":[-93.294369,34.508787],"type":"Point"}
}