{
  "type": "Feature",
  "properties": {
    "addr:full":"34 Marshall Rd Vilonia AR 72173",
    "addr:housenumber":"34",
    "addr:postcode":"72173",
    "addr:street":"Marshall Rd",
    "iso:country":"US",
    "sg:address":"34 Marshall Rd",
    "sg:city":"Vilonia",
    "sg:classifiers":[
        {
            "category":"Retail",
            "subcategory":"Repair Shop",
            "type":"Services"
        }
    ],
    "sg:phone":"+1 501 796 8277",
    "sg:postcode":"72173",
    "sg:province":"AR",
    "sg:tags":[
        "welding"
    ],
    "wof:name":"Rose Welding Service",
    "wof:placetype":"venue"
},
  "geometry": {"coordinates":[-92.22520799999999,35.083768],"type":"Point"}
}