{
  "type": "Feature",
  "properties": {
    "addr:full":"1912 Green Mountain Dr Little Rock AR 72212",
    "addr:housenumber":"1912",
    "addr:postcode":"72212",
    "addr:street":"Green Mountain Dr",
    "iso:country":"US",
    "sg:address":"1912 Green Mountain Dr",
    "sg:city":"Little Rock",
    "sg:classifiers":[
        {
            "category":"Real Estate",
            "subcategory":"Real Estate Operator",
            "type":"Services"
        }
    ],
    "sg:phone":"+1 501 227 0154",
    "sg:postcode":"72212",
    "sg:province":"AR",
    "sg:tags":[
        "building",
        "apartment"
    ],
    "wof:name":"Fox Run Apartments",
    "wof:placetype":"venue"
},
  "geometry": {"coordinates":[-92.403733,34.770275],"type":"Point"}
}