{
  "type": "Feature",
  "properties": {
    "addr:full":"2114 W Beebe Capps Expy Searcy AR 72143",
    "addr:housenumber":"2114",
    "addr:postcode":"72143",
    "addr:street":"W Beebe Capps Expy",
    "iso:country":"US",
    "sg:address":"2114 W Beebe Capps Expy",
    "sg:city":"Searcy",
    "sg:classifiers":[
        {
            "category":"Fast Food",
            "type":"Food & Drink"
        },
        {
            "category":"Restaurant",
            "type":"Food & Drink"
        },
        {
            "category":"Food & Beverages",
            "subcategory":"Groceries & Convenience Stores",
            "type":"Retail Goods"
        }
    ],
    "sg:phone":"+1 501 279 7775",
    "sg:postcode":"72143",
    "sg:province":"AR",
    "sg:tags":[
        "shop",
        "american",
        "sandwich",
        "take"
    ],
    "sg:website":"http://www.subway.com",
    "wof:name":"SUBWAY",
    "wof:placetype":"venue"
},
  "geometry": {"coordinates":[-91.708257,35.239234],"type":"Point"}
}