{
  "type": "Feature",
  "properties": {
    "iso:country":"US",
    "sg:address":"501 Malvern Ave",
    "sg:city":"Hot Springs",
    "sg:classifiers":[
        {
            "category":"Building & Trades",
            "subcategory":"Construction",
            "type":"Services"
        }
    ],
    "sg:phone":"+1 501 318 1200",
    "sg:postcode":"71901",
    "sg:province":"AR",
    "sg:tags":[
        "contractor"
    ],
    "wof:name":"Woodman Building Senior Living",
    "wof:placetype":"venue"
},
  "geometry": {"coordinates":[-93.049966,34.506989],"type":"Point"}
}