{
  "type": "Feature",
  "properties": {
    "addr:full":"9313 Keeton Ln Harrison AR 72601",
    "addr:housenumber":"9313",
    "addr:postcode":"72601",
    "addr:street":"Keeton Ln",
    "iso:country":"US",
    "sg:address":"9313 Keeton Ln",
    "sg:city":"Harrison",
    "sg:classifiers":[
        {
            "category":"Manufacturing",
            "subcategory":"Lumber",
            "type":"Manufacturing & Wholesale Goods"
        }
    ],
    "sg:phone":"+1 870 437 2428",
    "sg:postcode":"72601",
    "sg:province":"AR",
    "sg:tags":[
        "mfg",
        "shaving"
    ],
    "wof:name":"B & K Farms",
    "wof:placetype":"venue"
},
  "geometry": {"coordinates":[-93.24881000000001,36.266861],"type":"Point"}
}