{
  "type": "Feature",
  "properties": {
    "iso:country":"US",
    "sg:address":"802 W Main St",
    "sg:city":"Cabot",
    "sg:classifiers":[
        {
            "category":"Shopping",
            "subcategory":"Bicycles & Sporting Goods",
            "type":"Retail Goods"
        }
    ],
    "sg:phone":"+1 501 605 1618",
    "sg:postcode":"72023",
    "sg:province":"AR",
    "wof:name":"Rayburn's Sporting Goods",
    "wof:placetype":"venue"
},
  "geometry": {"coordinates":[-92.029936,34.978757],"type":"Point"}
}