{
  "type": "Feature",
  "properties": {
    "iso:country":"US",
    "sg:address":"637 Hwy 365",
    "sg:city":"Mayflower",
    "sg:classifiers":[
        {
            "category":"Real Estate",
            "subcategory":"Real Estate Agent",
            "type":"Services"
        }
    ],
    "sg:phone":"+1 501 470 3100",
    "sg:postcode":"72106",
    "sg:province":"AR",
    "sg:website":"www.realestateone.com",
    "wof:name":"Real Estate One",
    "wof:placetype":"venue"
},
  "geometry": {"coordinates":[-92.427357,34.940917],"type":"Point"}
}