{
  "type": "Feature",
  "properties": {
    "iso:country":"US",
    "sg:address":"800 Professional Acres Dr",
    "sg:city":"Jonesboro",
    "sg:classifiers":[
        {
            "category":"Health Services",
            "subcategory":"Doctor",
            "type":"Services"
        }
    ],
    "sg:phone":"+1 870 932 0930",
    "sg:postcode":"72401",
    "sg:province":"AR",
    "sg:tags":[
        "medical"
    ],
    "wof:name":"J T Young",
    "wof:placetype":"venue"
},
  "geometry": {"coordinates":[-90.692687,35.833244],"type":"Point"}
}