{
  "type": "Feature",
  "properties": {
    "addr:full":"139 Shuttle St Hot Springs AR 71913",
    "addr:housenumber":"139",
    "addr:postcode":"71913",
    "addr:street":"Shuttle St",
    "iso:country":"US",
    "sg:address":"139 Shuttle St",
    "sg:city":"Hot Springs",
    "sg:classifiers":[
        {
            "category":"Building & Trades",
            "subcategory":"Construction",
            "type":"Services"
        }
    ],
    "sg:phone":"+1 501 767 1329",
    "sg:postcode":"71913",
    "sg:province":"AR",
    "sg:tags":[
        "roofing",
        "contractor"
    ],
    "wof:name":"TCB Construction",
    "wof:placetype":"venue"
},
  "geometry": {"coordinates":[-93.132554,34.503801],"type":"Point"}
}