{
  "type": "Feature",
  "properties": {
    "addr:full":"10402 Stagecoach Rd Little Rock AR 72210",
    "addr:housenumber":"10402",
    "addr:postcode":"72210",
    "addr:street":"Stagecoach Rd",
    "iso:country":"US",
    "sg:address":"10402 Stagecoach Rd",
    "sg:city":"Little Rock",
    "sg:classifiers":[
        {
            "category":"Restaurant",
            "type":"Food & Drink"
        }
    ],
    "sg:phone":"+1 501 455 8500",
    "sg:postcode":"72210",
    "sg:province":"AR",
    "sg:tags":[
        "eating"
    ],
    "wof:name":"Las Palmas III",
    "wof:placetype":"venue"
},
  "geometry": {"coordinates":[-92.426361,34.6569],"type":"Point"}
}