{
  "type": "Feature",
  "properties": {
    "addr:full":"221 W 2nd Ave Pine Bluff AR 71601",
    "addr:housenumber":"221",
    "addr:postcode":"71601",
    "addr:street":"W 2Nd Ave",
    "iso:country":"US",
    "sg:address":"221 W 2nd Ave",
    "sg:city":"Pine Bluff",
    "sg:classifiers":[
        {
            "category":"Wholesale",
            "subcategory":"Machinery & Supplies",
            "type":"Manufacturing & Wholesale Goods"
        }
    ],
    "sg:phone":"+1 870 536 1089",
    "sg:postcode":"71601",
    "sg:province":"AR",
    "sg:tags":[
        "janitor"
    ],
    "wof:name":"Pine Bluff Janitor Supply Co",
    "wof:placetype":"venue"
},
  "geometry": {"coordinates":[-92.005224,34.228445],"type":"Point"}
}