{
  "type": "Feature",
  "properties": {
    "iso:country":"US",
    "sg:address":"255 Brantley Rd",
    "sg:city":"Searcy",
    "sg:classifiers":[
        {
            "category":"Freight",
            "type":"Transportation"
        }
    ],
    "sg:phone":"+1 501 268 7909",
    "sg:postcode":"72143",
    "sg:province":"AR",
    "sg:tags":[
        "trucking"
    ],
    "wof:name":"Diamond A Enterprises",
    "wof:placetype":"venue"
},
  "geometry": {"coordinates":[-91.74324,35.195251],"type":"Point"}
}