{
  "type": "Feature",
  "properties": {
    "iso:country":"US",
    "sg:address":"228 Oliver St",
    "sg:city":"Conway",
    "sg:classifiers":[
        {
            "category":"Professional",
            "type":"Services"
        }
    ],
    "sg:phone":"+1 501 327 2511",
    "sg:postcode":"72034",
    "sg:province":"AR",
    "wof:name":"Jeffery Hill",
    "wof:placetype":"venue"
},
  "geometry": {"coordinates":[-92.441819,35.080362],"type":"Point"}
}