{
  "type": "Feature",
  "properties": {
    "iso:country":"US",
    "sg:address":"2 Bentley Dr",
    "sg:city":"Conway",
    "sg:classifiers":[
        {
            "category":"Professional",
            "type":"Services"
        }
    ],
    "sg:phone":"+1 501 450 7743",
    "sg:postcode":"72034",
    "sg:province":"AR",
    "sg:tags":[
        "writer",
        "merchandise"
    ],
    "wof:name":"Continuing Education Services Inc",
    "wof:placetype":"venue"
},
  "geometry": {"coordinates":[-92.44064299999999,35.033298],"type":"Point"}
}