{
  "type": "Feature",
  "properties": {
    "addr:full":"15013 State Hwy 107 Jacksonville AR 72076",
    "addr:housenumber":"15013",
    "addr:postcode":"72076",
    "addr:street":"State Hwy 107",
    "iso:country":"US",
    "sg:address":"15013 State Hwy 107",
    "sg:city":"Jacksonville",
    "sg:classifiers":[
        {
            "category":"Building & Trades",
            "subcategory":"Electrical",
            "type":"Services"
        }
    ],
    "sg:phone":"+1 501 835 5452",
    "sg:postcode":"72076",
    "sg:province":"AR",
    "sg:tags":[
        "electric",
        "contractor"
    ],
    "sg:website":"www.johnsonelectricincusa.com",
    "wof:name":"Johnson Electric",
    "wof:placetype":"venue"
},
  "geometry": {"coordinates":[-92.177533,34.882236],"type":"Point"}
}