{
  "type": "Feature",
  "properties": {
    "iso:country":"US",
    "sg:address":"4321 Pine Cone Dr",
    "sg:city":"Little Rock",
    "sg:classifiers":[
        {
            "category":"Communications",
            "subcategory":"Film & Video Production",
            "type":"Services"
        }
    ],
    "sg:phone":"+1 501 952 3163",
    "sg:postcode":"72209",
    "sg:province":"AR",
    "sg:tags":[
        "taping"
    ],
    "wof:name":"D Visions",
    "wof:placetype":"venue"
},
  "geometry": {"coordinates":[-92.325941,34.662788],"type":"Point"}
}