{
  "type": "Feature",
  "properties": {
    "iso:country":"US",
    "sg:address":"2915 E Broadway St",
    "sg:city":"N Little Rock",
    "sg:classifiers":[
        {
            "category":"Autos & Motor Vehicles",
            "subcategory":"Automobile Sales",
            "type":"Retail Goods"
        }
    ],
    "sg:phone":"+1 501 945 2389",
    "sg:postcode":"72114",
    "sg:province":"AR",
    "sg:tags":[
        "car",
        "dealer"
    ],
    "wof:name":"B & B Auto Sales",
    "wof:placetype":"venue"
},
  "geometry": {"coordinates":[-92.234088,34.755328],"type":"Point"}
}