{
  "type": "Feature",
  "properties": {
    "iso:country":"US",
    "sg:address":"502 Binghamwood Rd",
    "sg:city":"Little Rock",
    "sg:classifiers":[
        {
            "category":"Wholesale",
            "subcategory":"Vending Machines",
            "type":"Manufacturing & Wholesale Goods"
        }
    ],
    "sg:phone":"+1 501 261 7942",
    "sg:postcode":"72206",
    "sg:province":"AR",
    "wof:name":"Dwight & Angela Vending",
    "wof:placetype":"venue"
},
  "geometry": {"coordinates":[-92.280475,34.59611],"type":"Point"}
}