{
  "type": "Feature",
  "properties": {
    "iso:country":"US",
    "sg:address":"719 State Hwy 21",
    "sg:city":"Clarksville",
    "sg:classifiers":[
        {
            "category":"Retail",
            "subcategory":"Portrait Studio",
            "type":"Services"
        }
    ],
    "sg:phone":"+1 479 754 7700",
    "sg:postcode":"72830",
    "sg:province":"AR",
    "sg:tags":[
        "photographer",
        "photo"
    ],
    "wof:name":"Davie Clair Photography",
    "wof:placetype":"venue"
},
  "geometry": {"coordinates":[-93.435776,35.478438],"type":"Point"}
}