{
  "type": "Feature",
  "properties": {
    "iso:country":"US",
    "sg:address":"4511 Asher Ave",
    "sg:city":"Little Rock",
    "sg:classifiers":[
        {
            "category":"Retail",
            "subcategory":"Auto Repair",
            "type":"Services"
        }
    ],
    "sg:phone":"+1 501 666 4900",
    "sg:postcode":"72204",
    "sg:province":"AR",
    "sg:tags":[
        "body",
        "paint",
        "shop"
    ],
    "wof:name":"Econo Auto Painting",
    "wof:placetype":"venue"
},
  "geometry": {"coordinates":[-92.323844,34.723574],"type":"Point"}
}