{
  "type": "Feature",
  "properties": {
    "addr:full":"3918 Pecan Grove Rd Rudy AR 72952",
    "addr:housenumber":"3918",
    "addr:postcode":"72952",
    "addr:street":"Pecan Grove Rd",
    "iso:country":"US",
    "sg:address":"3918 Pecan Grove Rd",
    "sg:city":"Rudy",
    "sg:classifiers":[
        {
            "category":"Social Services",
            "subcategory":"Job Training",
            "type":"Services"
        }
    ],
    "sg:phone":"+1 479 632 6337",
    "sg:postcode":"72952",
    "sg:province":"AR",
    "sg:tags":[
        "rehabilitation"
    ],
    "wof:name":"Center For Pediatric Therapy",
    "wof:placetype":"venue"
},
  "geometry": {"coordinates":[-94.25115099999999,35.532505],"type":"Point"}
}