{
  "type": "Feature",
  "properties": {
    "iso:country":"US",
    "sg:address":"1405 N Missouri St",
    "sg:city":"West Memphis",
    "sg:classifiers":[
        {
            "category":"Banks & Credit Unions",
            "subcategory":"Bank",
            "type":"Services"
        }
    ],
    "sg:phone":"+1 870 735 9501",
    "sg:postcode":"72301",
    "sg:province":"AR",
    "sg:tags":[
        "loan",
        "real estate"
    ],
    "wof:name":"First Tennessee Home Loans",
    "wof:placetype":"venue"
},
  "geometry": {"coordinates":[-90.184636,35.161591],"type":"Point"}
}