{
  "type": "Feature",
  "properties": {
    "iso:country":"US",
    "sg:address":"600 N Pierce St",
    "sg:city":"Little Rock",
    "sg:classifiers":[
        {
            "category":"Utilities",
            "subcategory":"Telephone",
            "type":"Services"
        }
    ],
    "sg:phone":"+1 501 247 6395",
    "sg:postcode":"72205",
    "sg:province":"AR",
    "sg:tags":[
        "communications"
    ],
    "wof:name":"C Jay Communications",
    "wof:placetype":"venue"
},
  "geometry": {"coordinates":[-92.33805,34.757483],"type":"Point"}
}