{
  "type": "Feature",
  "properties": {
    "iso:country":"US",
    "sg:address":"701 S Arkansas St",
    "sg:city":"Rogers",
    "sg:classifiers":[
        {
            "category":"Autos & Motor Vehicles",
            "subcategory":"Fuel & Gas Station",
            "type":"Retail Goods"
        }
    ],
    "sg:phone":"+1 479 631 6108",
    "sg:postcode":"72756",
    "sg:province":"AR",
    "sg:tags":[
        "station",
        "gasoline"
    ],
    "wof:name":"Bobs Automotive & Rogers Wrckr",
    "wof:placetype":"venue"
},
  "geometry": {"coordinates":[-94.115819,36.325548],"type":"Point"}
}