{
  "type": "Feature",
  "properties": {
    "addr:full":"14650 Hwy 141 N Paragould AR 72450",
    "addr:housenumber":"14650",
    "addr:postcode":"72450",
    "addr:street":"Hwy 141 N",
    "iso:country":"US",
    "sg:address":"14650 Hwy 141 N",
    "sg:city":"Paragould",
    "sg:classifiers":[
        {
            "category":"Farming",
            "subcategory":"Farm",
            "type":"Manufacturing & Wholesale Goods"
        }
    ],
    "sg:phone":"+1 870 586 0825",
    "sg:postcode":"72450",
    "sg:province":"AR",
    "sg:tags":[
        "crop",
        "general"
    ],
    "wof:name":"Scott Dowler",
    "wof:placetype":"venue"
},
  "geometry": {"coordinates":[-90.54864600000001,36.221573],"type":"Point"}
}