{
  "type": "Feature",
  "properties": {
    "addr:full":"321 Honey Hill Rd Searcy AR 72143",
    "addr:housenumber":"321",
    "addr:postcode":"72143",
    "addr:street":"Honey Hill Rd",
    "iso:country":"US",
    "sg:address":"321 Honey Hill Rd",
    "sg:city":"Searcy",
    "sg:classifiers":[
        {
            "category":"Building & Trades",
            "subcategory":"Construction",
            "type":"Services"
        }
    ],
    "sg:phone":"+1 501 268 3219",
    "sg:postcode":"72143",
    "sg:province":"AR",
    "sg:tags":[
        "road",
        "contractor"
    ],
    "wof:name":"Hoss Construction Co, Inc",
    "wof:placetype":"venue"
},
  "geometry": {"coordinates":[-91.793739,35.227051],"type":"Point"}
}