{
  "type": "Feature",
  "properties": {
    "addr:full":"511 Old Wire Rd Springdale AR 72764",
    "addr:housenumber":"511",
    "addr:postcode":"72764",
    "addr:street":"Old Wire Rd",
    "iso:country":"US",
    "sg:address":"511 Old Wire Rd",
    "sg:city":"Springdale",
    "sg:classifiers":[
        {
            "category":"Shopping",
            "subcategory":"Bicycles & Sporting Goods",
            "type":"Retail Goods"
        }
    ],
    "sg:phone":"+1 479 927 2244",
    "sg:postcode":"72764",
    "sg:province":"AR",
    "sg:tags":[
        "gun",
        "gunsmith"
    ],
    "wof:name":"Sturm's Indoor Gun Range",
    "wof:placetype":"venue"
},
  "geometry": {"coordinates":[-94.12702899999999,36.197367],"type":"Point"}
}