{
  "type": "Feature",
  "properties": {
    "addr:full":"8521 Geyer Springs Rd Little Rock AR 72209",
    "addr:housenumber":"8521",
    "addr:postcode":"72209",
    "addr:street":"Geyer Springs Rd",
    "iso:country":"US",
    "sg:address":"8521 Geyer Springs Rd",
    "sg:city":"Little Rock",
    "sg:classifiers":[
        {
            "category":"Shopping",
            "subcategory":"Beauty & Cosmetics",
            "type":"Retail Goods"
        }
    ],
    "sg:phone":"+1 501 568 7931",
    "sg:postcode":"72209",
    "sg:province":"AR",
    "sg:tags":[
        "merchandise"
    ],
    "wof:name":"Hair Plus Beauty Supply Inc",
    "wof:placetype":"venue"
},
  "geometry": {"coordinates":[-92.344154,34.671343],"type":"Point"}
}