{
  "type": "Feature",
  "properties": {
    "addr:full":"161 Hempstead 278 Hope AR 71801",
    "addr:housenumber":"161;278",
    "addr:postcode":"71801",
    "addr:street":"Hempstead",
    "iso:country":"US",
    "sg:address":"161 Hempstead 278",
    "sg:city":"Hope",
    "sg:classifiers":[
        {
            "category":"Sports & Exercise",
            "subcategory":"Playing Field",
            "type":"Entertainment"
        }
    ],
    "sg:phone":"+1 870 777 2912",
    "sg:postcode":"71801",
    "sg:province":"AR",
    "sg:tags":[
        "farm",
        "game"
    ],
    "wof:name":"Tyson",
    "wof:placetype":"venue"
},
  "geometry": {"coordinates":[-93.61778099999999,33.736491],"type":"Point"}
}