{
  "type": "Feature",
  "properties": {
    "iso:country":"US",
    "sg:address":"161 Hempstead 278",
    "sg:city":"Hope",
    "sg:classifiers":[
        {
            "category":"Sports & Exercise",
            "subcategory":"Playing Field",
            "type":"Entertainment"
        }
    ],
    "sg:phone":"+1 870 777 2912",
    "sg:postcode":"71801",
    "sg:province":"AR",
    "sg:tags":[
        "farm",
        "game"
    ],
    "wof:name":"Tyson",
    "wof:placetype":"venue"
},
  "geometry": {"coordinates":[-93.617781,33.736491],"type":"Point"}
}