{
  "type": "Feature",
  "properties": {
    "addr:full":"100 Jo St Osceola AR 72370",
    "addr:housenumber":"100",
    "addr:postcode":"72370",
    "addr:street":"Jo St",
    "iso:country":"US",
    "sg:address":"100 Jo St",
    "sg:city":"Osceola",
    "sg:classifiers":[
        {
            "category":"Organizations",
            "subcategory":"Religious Organization",
            "type":"Services"
        }
    ],
    "sg:phone":"+1 870 563 3443",
    "sg:postcode":"72370",
    "sg:province":"AR",
    "sg:tags":[
        "church"
    ],
    "wof:name":"Osceola Church Of God",
    "wof:placetype":"venue"
},
  "geometry": {"coordinates":[-89.998932,35.696194],"type":"Point"}
}