{
  "type": "Feature",
  "properties": {
    "iso:country":"US",
    "sg:address":"113 Windamere Ter",
    "sg:city":"Hot Springs",
    "sg:classifiers":[
        {
            "category":"Building & Trades",
            "subcategory":"Construction",
            "type":"Services"
        }
    ],
    "sg:phone":"+1 501 767 8600",
    "sg:postcode":"71913",
    "sg:province":"AR",
    "sg:tags":[
        "contractor"
    ],
    "wof:name":"Bob J's Construction",
    "wof:placetype":"venue"
},
  "geometry": {"coordinates":[-93.148357,34.476306],"type":"Point"}
}