{
  "type": "Feature",
  "properties": {
    "addr:full":"121 Ouachita Road 85 Bearden AR 71720",
    "addr:housenumber":"121",
    "addr:postcode":"71720",
    "addr:street":"Ouachita Road 85",
    "iso:country":"US",
    "sg:address":"121 Ouachita Road 85",
    "sg:city":"Bearden",
    "sg:classifiers":[
        {
            "category":"Organizations",
            "subcategory":"Religious Organization",
            "type":"Services"
        }
    ],
    "sg:phone":"+1 870 687 2101",
    "sg:postcode":"71720",
    "sg:province":"AR",
    "sg:tags":[
        "church"
    ],
    "wof:name":"New Macedonia AME Church",
    "wof:placetype":"venue"
},
  "geometry": {"coordinates":[-92.602773,33.731423],"type":"Point"}
}