{
  "type": "Feature",
  "properties": {
    "addr:full":"369 Central Ave Hot Springs AR 71901",
    "addr:housenumber":"369",
    "addr:postcode":"71901",
    "addr:street":"Central Ave",
    "iso:country":"US",
    "sg:address":"369 Central Ave",
    "sg:city":"Hot Springs",
    "sg:classifiers":[
        {
            "category":"Recreation",
            "type":"Entertainment"
        }
    ],
    "sg:phone":"+1 501 624 2701",
    "sg:postcode":"71901",
    "sg:province":"AR",
    "sg:tags":[
        "parks"
    ],
    "wof:name":"Hot Springs National Park",
    "wof:placetype":"venue"
},
  "geometry": {"coordinates":[-93.05368300000001,34.514419],"type":"Point"}
}