{
  "type": "Feature",
  "properties": {
    "iso:country":"US",
    "sg:address":"1800 N Reynolds Rd",
    "sg:city":"Bryant",
    "sg:classifiers":[
        {
            "category":"Shopping",
            "subcategory":"Tobacco",
            "type":"Retail Goods"
        }
    ],
    "sg:phone":"+1 501 847 6656",
    "sg:postcode":"72022",
    "sg:province":"AR",
    "sg:tags":[
        "cigarette",
        "product",
        "cigar",
        "dealer"
    ],
    "wof:name":"Tobacco Shack",
    "wof:placetype":"venue"
},
  "geometry": {"coordinates":[-92.495651,34.611592],"type":"Point"}
}