{
  "type": "Feature",
  "properties": {
    "iso:country":"US",
    "sg:address":"39 S Elizabeth St",
    "sg:city":"Dover",
    "sg:classifiers":[
        {
            "category":"Personal",
            "subcategory":"Barber",
            "type":"Services"
        }
    ],
    "sg:phone":"+1 479 331 3310",
    "sg:postcode":"72837",
    "sg:province":"AR",
    "wof:name":"Daryl Pritchard Barber Shop",
    "wof:placetype":"venue"
},
  "geometry": {"coordinates":[-93.115545,35.401541],"type":"Point"}
}