{
  "type": "Feature",
  "properties": {
    "iso:country":"US",
    "sg:address":"1643 Amy Dr",
    "sg:city":"Fordyce",
    "sg:classifiers":[
        {
            "category":"Transit Center",
            "subcategory":"Freight",
            "type":"Transportation"
        },
        {
            "category":"Freight",
            "type":"Transportation"
        }
    ],
    "sg:phone":"+1 870 352 7278",
    "sg:postcode":"71742",
    "sg:province":"AR",
    "sg:tags":[
        "local",
        "trucking-motor",
        "trucking"
    ],
    "wof:name":"Wa Raney Trucking Inc",
    "wof:placetype":"venue"
},
  "geometry": {"coordinates":[-92.43128,33.804305],"type":"Point"}
}