{
  "type": "Feature",
  "properties": {
    "iso:country":"US",
    "sg:address":"4500 Towson Ave",
    "sg:city":"Fort Smith",
    "sg:classifiers":[
        {
            "category":"Shopping",
            "type":"Retail Goods"
        }
    ],
    "sg:phone":"+1 479 709 7000",
    "sg:postcode":"72901",
    "sg:province":"AR",
    "sg:tags":[
        "limb",
        "artificial"
    ],
    "sg:website":"www.rvortho.com",
    "wof:name":"River Valley Prostetics",
    "wof:placetype":"venue"
},
  "geometry": {"coordinates":[-94.422726,35.339299],"type":"Point"}
}