{
  "type": "Feature",
  "properties": {
    "iso:country":"US",
    "sg:address":"102 E Central Ave",
    "sg:city":"Bentonville",
    "sg:classifiers":[
        {
            "category":"Professional",
            "type":"Services"
        }
    ],
    "sg:phone":"+1 479 254 8775",
    "sg:postcode":"72712",
    "sg:province":"AR",
    "sg:tags":[
        "establishment"
    ],
    "wof:name":"Dymo Corp",
    "wof:placetype":"venue"
},
  "geometry": {"coordinates":[-94.208104,36.372227],"type":"Point"}
}