{
  "type": "Feature",
  "properties": {
    "addr:full":"1702 Swift Dr Jacksonville AR 72076",
    "addr:housenumber":"1702",
    "addr:postcode":"72076",
    "addr:street":"Swift Dr",
    "iso:country":"US",
    "sg:address":"1702 Swift Dr",
    "sg:city":"Jacksonville",
    "sg:classifiers":[
        {
            "category":"Wholesale",
            "subcategory":"Hardware",
            "type":"Manufacturing & Wholesale Goods"
        }
    ],
    "sg:phone":"+1 501 982 3008",
    "sg:postcode":"72076",
    "sg:province":"AR",
    "sg:tags":[
        "used",
        "boiler"
    ],
    "wof:name":"Lamatt Sales & Marketing",
    "wof:placetype":"venue"
},
  "geometry": {"coordinates":[-92.127865,34.884003],"type":"Point"}
}