{
  "type": "Feature",
  "properties": {
    "iso:country":"US",
    "sg:address":"108 E Church St",
    "sg:city":"Warren",
    "sg:classifiers":[
        {
            "category":"Travel",
            "subcategory":"Hotels & Motels",
            "type":"Entertainment"
        }
    ],
    "sg:phone":"+1 870 226 5881",
    "sg:postcode":"71671",
    "sg:province":"AR",
    "sg:tags":[
        "operation"
    ],
    "wof:name":"Economy Inn",
    "wof:placetype":"venue"
},
  "geometry": {"coordinates":[-92.064195,33.612476],"type":"Point"}
}