{
  "type": "Feature",
  "properties": {
    "iso:country":"US",
    "sg:address":"8594 Oakland Rd",
    "sg:city":"Oakland",
    "sg:classifiers":[
        {
            "category":"Travel",
            "subcategory":"Resort",
            "type":"Entertainment"
        },
        {
            "category":"Recreation",
            "type":"Entertainment"
        }
    ],
    "sg:phone":"+1 870 431 8877",
    "sg:postcode":"72661",
    "sg:province":"AR",
    "sg:tags":[
        "camps-recreational"
    ],
    "sg:website":"http://www.persimmonpoint.com",
    "wof:name":"Persimmon Point Inc",
    "wof:placetype":"venue"
},
  "geometry": {"coordinates":[-92.609451,36.441978],"type":"Point"}
}