{
  "type": "Feature",
  "properties": {
    "addr:full":"1 Iron Horse Rd Little Rock AR 72223",
    "addr:housenumber":"1",
    "addr:postcode":"72223",
    "addr:street":"Iron Horse Rd",
    "iso:country":"US",
    "sg:address":"1 Iron Horse Rd",
    "sg:city":"Little Rock",
    "sg:classifiers":[
        {
            "category":"Building & Trades",
            "subcategory":"Construction",
            "type":"Services"
        }
    ],
    "sg:phone":"+1 501 821 5680",
    "sg:postcode":"72223",
    "sg:province":"AR",
    "sg:tags":[
        "contractor"
    ],
    "wof:name":"Ark La Tex Drywall and Sup Co",
    "wof:placetype":"venue"
},
  "geometry": {"coordinates":[-92.47662099999999,34.7542],"type":"Point"}
}