{
  "type": "Feature",
  "properties": {
    "addr:full":"2054 S 54th St Rogers AR 72758",
    "addr:housenumber":"2054",
    "addr:postcode":"72758",
    "addr:street":"S 54Th St",
    "iso:country":"US",
    "sg:address":"2054 S 54th St",
    "sg:city":"Rogers",
    "sg:classifiers":[
        {
            "category":"Health Services",
            "subcategory":"Doctor",
            "type":"Services"
        }
    ],
    "sg:phone":"+1 479 464 4334",
    "sg:postcode":"72758",
    "sg:province":"AR",
    "sg:tags":[
        "medical"
    ],
    "wof:name":"Kenneth Ubben",
    "wof:placetype":"venue"
},
  "geometry": {"coordinates":[-94.193963,36.314872],"type":"Point"}
}