{
  "type": "Feature",
  "properties": {
    "addr:full":"371 Hwy 82 E Magnolia AR 71753",
    "addr:housenumber":"371",
    "addr:postcode":"71753",
    "addr:street":"Hwy 82 E Magnolia",
    "iso:country":"US",
    "sg:address":"371 Hwy 82 E",
    "sg:city":"Magnolia",
    "sg:classifiers":[
        {
            "category":"Building & Trades",
            "subcategory":"Construction",
            "type":"Services"
        }
    ],
    "sg:phone":"+1 870 234 6020",
    "sg:postcode":"71753",
    "sg:province":"AR",
    "sg:tags":[
        "general",
        "contractor"
    ],
    "wof:name":"Perritt & Vickers Inc",
    "wof:placetype":"venue"
},
  "geometry": {"coordinates":[-93.204109,33.260287],"type":"Point"}
}