{
  "type": "Feature",
  "properties": {
    "addr:full":"3401 Atwood Rd Little Rock AR 72206",
    "addr:housenumber":"3401",
    "addr:postcode":"72206",
    "addr:street":"Atwood Rd",
    "iso:country":"US",
    "sg:address":"3401 Atwood Rd",
    "sg:city":"Little Rock",
    "sg:classifiers":[
        {
            "category":"Professional",
            "subcategory":"Accounting & Tax Preparation",
            "type":"Services"
        }
    ],
    "sg:phone":"+1 501 888 4829",
    "sg:postcode":"72206",
    "sg:province":"AR",
    "sg:tags":[
        "bookkeeping",
        "general"
    ],
    "wof:name":"Excel Bookkeeping Systems",
    "wof:placetype":"venue"
},
  "geometry": {"coordinates":[-92.32276,34.611165],"type":"Point"}
}