{
  "type": "Feature",
  "properties": {
    "iso:country":"US",
    "sg:address":"620 W Lancashire Blvd",
    "sg:city":"Bella Vista",
    "sg:classifiers":[
        {
            "category":"Health Services",
            "subcategory":"Health Practitioner",
            "type":"Services"
        }
    ],
    "sg:phone":"+1 479 876 6686",
    "sg:postcode":"72715",
    "sg:province":"AR",
    "sg:tags":[
        "therapist",
        "physical"
    ],
    "wof:name":"Rehabfirst",
    "wof:placetype":"venue"
},
  "geometry": {"coordinates":[-94.287781,36.456261],"type":"Point"}
}