{
  "type": "Feature",
  "properties": {
    "addr:full":"704 N Missouri St West Memphis AR 72301",
    "addr:housenumber":"704",
    "addr:postcode":"72301",
    "addr:street":"N Missouri St",
    "iso:country":"US",
    "sg:address":"704 N Missouri St",
    "sg:city":"West Memphis",
    "sg:classifiers":[
        {
            "category":"Real Estate",
            "subcategory":"Real Estate Agent",
            "type":"Services"
        }
    ],
    "sg:phone":"+1 870 732 4655",
    "sg:postcode":"72301",
    "sg:province":"AR",
    "sg:tags":[
        "house",
        "construct"
    ],
    "sg:website":"www.coldwellbanker.com",
    "wof:name":"Coldwell Banker",
    "wof:placetype":"venue"
},
  "geometry": {"coordinates":[-90.184836,35.153834],"type":"Point"}
}