{
  "type": "Feature",
  "properties": {
    "addr:full":"117 E Main St El Dorado AR 71730",
    "addr:housenumber":"117",
    "addr:postcode":"71730",
    "addr:street":"E Main St",
    "iso:country":"US",
    "sg:address":"117 E Main St",
    "sg:city":"El Dorado",
    "sg:classifiers":[
        {
            "category":"Restaurant",
            "type":"Food & Drink"
        }
    ],
    "sg:phone":"+1 870 863 6611",
    "sg:postcode":"71730",
    "sg:province":"AR",
    "wof:name":"Corner Cafe",
    "wof:placetype":"venue"
},
  "geometry": {"coordinates":[-92.663623,33.211794],"type":"Point"}
}