{
  "type": "Feature",
  "properties": {
    "addr:full":"24701 S 655 Rd Grove OK 74344",
    "addr:housenumber":"24701",
    "addr:postcode":"74344",
    "addr:street":"S 655 Rd",
    "iso:country":"US",
    "sg:address":"24701 S 655 Rd",
    "sg:city":"Grove",
    "sg:classifiers":[
        {
            "category":"Recreation",
            "subcategory":"Amusement Park",
            "type":"Entertainment"
        }
    ],
    "sg:phone":"+1 918 786 8528",
    "sg:postcode":"74344",
    "sg:province":"OK",
    "wof:name":"Seneca-Cayuga Tribal Bingo",
    "wof:placetype":"venue"
},
  "geometry": {"coordinates":[-94.706776,36.657752],"type":"Point"}
}