{
  "type": "Feature",
  "properties": {
    "iso:country":"US",
    "sg:address":"503 Kirschwood Dr",
    "sg:city":"Hot Springs National Park",
    "sg:classifiers":[
        {
            "category":"Building & Trades",
            "subcategory":"Construction",
            "type":"Services"
        }
    ],
    "sg:phone":"+1 501 767 6967",
    "sg:postcode":"71913",
    "sg:province":"AR",
    "sg:tags":[
        "house"
    ],
    "wof:name":"Cash Construction",
    "wof:placetype":"venue"
},
  "geometry": {"coordinates":[-93.17863,34.49799],"type":"Point"}
}