{
  "type": "Feature",
  "properties": {
    "iso:country":"US",
    "sg:address":"510 River Rd",
    "sg:city":"Lakeview",
    "sg:classifiers":[
        {
            "category":"Wholesale",
            "subcategory":"Toys & Hobbies",
            "type":"Manufacturing & Wholesale Goods"
        },
        {
            "category":"Manufacturing",
            "subcategory":"Printing",
            "type":"Manufacturing & Wholesale Goods"
        }
    ],
    "sg:phone":"+1 870 431 5808",
    "sg:postcode":"72642",
    "sg:province":"AR",
    "sg:tags":[
        "wholesaler",
        "book"
    ],
    "sg:website":"www.whimseyunlimited.com",
    "wof:name":"Whimsem Unlimited",
    "wof:placetype":"venue"
},
  "geometry": {"coordinates":[-92.58572599999999,36.348361],"type":"Point"}
}