{
  "type": "Feature",
  "properties": {
    "iso:country":"US",
    "sg:address":"300 Rawls Rd Rison",
    "sg:city":"Rison",
    "sg:classifiers":[
        {
            "category":"Structure",
            "subcategory":"Building",
            "type":"Public Place"
        },
        {
            "category":"Building & Trades",
            "subcategory":"Plumbing",
            "type":"Services"
        }
    ],
    "sg:phone":"+1 800 824 4066",
    "sg:postcode":"71665",
    "sg:province":"AR",
    "sg:tags":[
        "shelter",
        "storm",
        "tank",
        "system",
        "septic"
    ],
    "sg:website":"http://www.rawlsconcrete.com",
    "wof:name":"Rawls Concrete Products Inc",
    "wof:placetype":"venue"
},
  "geometry": {"coordinates":[-92.102739,33.930715],"type":"Point"}
}