{
  "type": "Feature",
  "properties": {
    "addr:full":"6420 H St Little Rock AR 72205",
    "addr:housenumber":"6420",
    "addr:postcode":"72205",
    "addr:street":"H St",
    "iso:country":"US",
    "sg:address":"6420 H St",
    "sg:city":"Little Rock",
    "sg:classifiers":[
        {
            "category":"Home & Garden",
            "subcategory":"Furniture",
            "type":"Retail Goods"
        },
        {
            "category":"Wholesale",
            "subcategory":"Durable Goods & Equipment",
            "type":"Manufacturing & Wholesale Goods"
        }
    ],
    "sg:phone":"+1 501 666 2371",
    "sg:postcode":"72205",
    "sg:province":"AR",
    "sg:tags":[
        "representative",
        "manufacturer"
    ],
    "wof:name":"Speck C Q Raw Materials Co",
    "wof:placetype":"venue"
},
  "geometry": {"coordinates":[-92.345282,34.759718],"type":"Point"}
}