{
  "type": "Feature",
  "properties": {
    "iso:country":"US",
    "sg:address":"315 W Broadway",
    "sg:city":"West Memphis",
    "sg:classifiers":[
        {
            "category":"Building & Trades",
            "subcategory":"Construction",
            "type":"Services"
        }
    ],
    "sg:phone":"+1 870 733 0743",
    "sg:postcode":"72301",
    "sg:province":"AR",
    "sg:tags":[
        "resurfacing",
        "laying",
        "refinishing",
        "floor"
    ],
    "wof:name":"Quality Flooring",
    "wof:placetype":"venue"
},
  "geometry": {"coordinates":[-90.191123,35.146581],"type":"Point"}
}