{
  "type": "Feature",
  "properties": {
    "iso:country":"US",
    "sg:address":"5923 Dollarway Rd",
    "sg:city":"White Hall",
    "sg:classifiers":[
        {
            "category":"Retail",
            "subcategory":"Auto Repair",
            "type":"Services"
        }
    ],
    "sg:phone":"+1 870 247 0468",
    "sg:postcode":"71602",
    "sg:province":"AR",
    "sg:tags":[
        "body"
    ],
    "wof:name":"California Jacks Auto Body",
    "wof:placetype":"venue"
},
  "geometry": {"coordinates":[-92.06331900000001,34.245428],"type":"Point"}
}