{
  "type": "Feature",
  "properties": {
    "iso:country":"US",
    "sg:address":"3271 N Wimberly Dr",
    "sg:city":"Fayetteville",
    "sg:classifiers":[
        {
            "category":"Shopping",
            "subcategory":"Gifts & Souvenirs",
            "type":"Retail Goods"
        }
    ],
    "sg:phone":"+1 479 713 6100",
    "sg:postcode":"72703",
    "sg:province":"AR",
    "sg:tags":[
        "shop"
    ],
    "wof:name":"Recovery Road Gift Shop",
    "wof:placetype":"venue"
},
  "geometry": {"coordinates":[-94.154241,36.111119],"type":"Point"}
}