{
  "type": "Feature",
  "properties": {
    "iso:country":"US",
    "sg:address":"378 Williamson Rd",
    "sg:city":"Royal",
    "sg:classifiers":[
        {
            "category":"Building & Trades",
            "subcategory":"Construction",
            "type":"Services"
        }
    ],
    "sg:phone":"+1 501 767 8128",
    "sg:postcode":"71968",
    "sg:province":"AR",
    "sg:tags":[
        "house"
    ],
    "wof:name":"Pounders Construction Inc",
    "wof:placetype":"venue"
},
  "geometry": {"coordinates":[-93.25979100000001,34.498935],"type":"Point"}
}