{
  "type": "Feature",
  "properties": {
    "addr:full":"3203 Eva Dr White Hall AR 71602",
    "addr:housenumber":"3203",
    "addr:postcode":"71602",
    "addr:street":"Eva Dr",
    "iso:country":"US",
    "sg:address":"3203 Eva Dr",
    "sg:city":"White Hall",
    "sg:classifiers":[
        {
            "category":"Building & Trades",
            "subcategory":"Construction",
            "type":"Services"
        }
    ],
    "sg:phone":"+1 870 247 2117",
    "sg:postcode":"71602",
    "sg:province":"AR",
    "sg:tags":[
        "downspouts",
        "house",
        "gutter"
    ],
    "wof:name":"Fletcher's Construction",
    "wof:placetype":"venue"
},
  "geometry": {"coordinates":[-92.14845,34.303684],"type":"Point"}
}