{
  "type": "Feature",
  "properties": {
    "iso:country":"US",
    "sg:address":"1802 Airport Rd",
    "sg:city":"Hot Springs",
    "sg:classifiers":[
        {
            "category":"Building & Trades",
            "subcategory":"Construction",
            "type":"Services"
        }
    ],
    "sg:phone":"+1 501 767 5066",
    "sg:postcode":"71913",
    "sg:province":"AR",
    "sg:tags":[
        "roofing",
        "contractor"
    ],
    "wof:name":"Dollar Sheet Metal",
    "wof:placetype":"venue"
},
  "geometry": {"coordinates":[-93.148672,34.460473],"type":"Point"}
}