{
  "type": "Feature",
  "properties": {
    "iso:country":"US",
    "sg:address":"106 W 14th St",
    "sg:city":"Yellville",
    "sg:classifiers":[
        {
            "category":"Retail",
            "subcategory":"Animal Services",
            "type":"Services"
        }
    ],
    "sg:phone":"+1 870 449 6932",
    "sg:postcode":"72687",
    "sg:province":"AR",
    "wof:name":"Shear Pleasure Pet Grooming",
    "wof:placetype":"venue"
},
  "geometry": {"coordinates":[-92.685682,36.242341],"type":"Point"}
}