{
  "type": "Feature",
  "properties": {
    "addr:full":"121 Financial Dr Cabot AR 72023",
    "addr:housenumber":"121",
    "addr:postcode":"72023",
    "addr:street":"Financial Dr",
    "iso:country":"US",
    "sg:address":"121 Financial Dr",
    "sg:city":"Cabot",
    "sg:classifiers":[
        {
            "category":"Banks & Credit Unions",
            "subcategory":"Financial Services",
            "type":"Services"
        },
        {
            "category":"Real Estate",
            "subcategory":"Real Estate Services",
            "type":"Services"
        },
        {
            "category":"Real Estate",
            "subcategory":"Developer",
            "type":"Services"
        },
        {
            "category":"Real Estate",
            "subcategory":"Real Estate Agent",
            "type":"Services"
        }
    ],
    "sg:phone":"+1 501 843 1164",
    "sg:postcode":"72023",
    "sg:province":"AR",
    "sg:tags":[
        "buyer",
        "consultant",
        "loan",
        "commercial",
        "broker"
    ],
    "sg:website":"http://www.coldwellbanker.com",
    "wof:name":"Coldwell Banker",
    "wof:placetype":"venue"
},
  "geometry": {"coordinates":[-92.05869300000001,34.946433],"type":"Point"}
}