{
  "type": "Feature",
  "properties": {
    "addr:full":"677 Pittman Rd Hot Springs AR 71913",
    "addr:housenumber":"677",
    "addr:postcode":"71913",
    "addr:street":"Pittman Rd",
    "iso:country":"US",
    "sg:address":"677 Pittman Rd",
    "sg:city":"Hot Springs",
    "sg:classifiers":[
        {
            "category":"Building & Trades",
            "subcategory":"Construction",
            "type":"Services"
        }
    ],
    "sg:phone":"+1 501 767 3992",
    "sg:postcode":"71913",
    "sg:province":"AR",
    "sg:tags":[
        "general",
        "contractor"
    ],
    "wof:name":"Dixon Construction Inc",
    "wof:placetype":"venue"
},
  "geometry": {"coordinates":[-93.166719,34.43644],"type":"Point"}
}