{
  "type": "Feature",
  "properties": {
    "iso:country":"US",
    "sg:address":"606 1st Ave SE",
    "sg:city":"Gravette",
    "sg:classifiers":[
        {
            "category":"Place Of Worship",
            "subcategory":"Church",
            "type":"Public Place"
        },
        {
            "category":"Place Of Worship",
            "type":"Public Place"
        }
    ],
    "sg:phone":"+1 479 787 9601",
    "sg:postcode":"72736",
    "sg:province":"AR",
    "sg:tags":[
        "churches-interdenominational",
        "churches-various",
        "denomination"
    ],
    "wof:name":"Jabez Ministries",
    "wof:placetype":"venue"
},
  "geometry": {"coordinates":[-94.453141,36.416242],"type":"Point"}
}