{
  "type": "Feature",
  "properties": {
    "iso:country":"US",
    "sg:address":"311 W Dickson St",
    "sg:city":"Fayetteville",
    "sg:classifiers":[
        {
            "category":"Professional",
            "subcategory":"Art Services",
            "type":"Services"
        },
        {
            "category":"Professional",
            "subcategory":"Advertising",
            "type":"Services"
        }
    ],
    "sg:phone":"+1 479 582 2695",
    "sg:postcode":"72701",
    "sg:province":"AR",
    "sg:tags":[
        "graphic",
        "counselor",
        "design"
    ],
    "wof:name":"Doxa Total Design Strategy",
    "wof:placetype":"venue"
},
  "geometry": {"coordinates":[-94.164138,36.066342],"type":"Point"}
}