{
  "type": "Feature",
  "properties": {
    "iso:country":"US",
    "sg:address":"2187 State Hwy 349",
    "sg:city":"Jonesboro",
    "sg:classifiers":[
        {
            "category":"Organizations",
            "subcategory":"Religious Organization",
            "type":"Services"
        }
    ],
    "sg:phone":"+1 870 935 9877",
    "sg:postcode":"72404",
    "sg:province":"AR",
    "sg:tags":[
        "church"
    ],
    "wof:name":"Oak Grove Baptist Church",
    "wof:placetype":"venue"
},
  "geometry": {"coordinates":[-90.802855,35.821369],"type":"Point"}
}