{
  "type": "Feature",
  "properties": {
    "iso:country":"US",
    "sg:address":"204 N Front St",
    "sg:city":"Dardanelle",
    "sg:classifiers":[
        {
            "category":"Professional",
            "subcategory":"Business Services",
            "type":"Services"
        }
    ],
    "sg:phone":"+1 479 229 3543",
    "sg:postcode":"72834",
    "sg:province":"AR",
    "sg:tags":[
        "appraiser"
    ],
    "wof:name":"Tri-County Appraisals",
    "wof:placetype":"venue"
},
  "geometry": {"coordinates":[-93.154196,35.22212],"type":"Point"}
}