{
  "type": "Feature",
  "properties": {
    "iso:country":"US",
    "sg:address":"1002 S Pine St",
    "sg:city":"Cabot",
    "sg:classifiers":[
        {
            "category":"Food & Beverages",
            "subcategory":"Groceries & Convenience Stores",
            "type":"Retail Goods"
        }
    ],
    "sg:phone":"+1 501 605 0286",
    "sg:postcode":"72023",
    "sg:province":"AR",
    "wof:name":"Mayn-Mart",
    "wof:placetype":"venue"
},
  "geometry": {"coordinates":[-92.008532,34.956277],"type":"Point"}
}