{
  "type": "Feature",
  "properties": {
    "iso:country":"US",
    "sg:address":"1115 Windover Rd",
    "sg:city":"Jonesboro",
    "sg:classifiers":[
        {
            "category":"Health Services",
            "subcategory":"Doctor",
            "type":"Services"
        }
    ],
    "sg:phone":"+1 870 932 2300",
    "sg:postcode":"72401",
    "sg:province":"AR",
    "sg:tags":[
        "dentist"
    ],
    "wof:name":"Wright Damon C",
    "wof:placetype":"venue"
},
  "geometry": {"coordinates":[-90.690568,35.813616],"type":"Point"}
}