{
  "type": "Feature",
  "properties": {
    "iso:country":"US",
    "sg:address":"305 E Maple St",
    "sg:city":"Pocahontas",
    "sg:classifiers":[
        {
            "category":"Manufacturing",
            "subcategory":"Apparel",
            "type":"Manufacturing & Wholesale Goods"
        }
    ],
    "sg:phone":"+1 870 892 0715",
    "sg:postcode":"72455",
    "sg:province":"AR",
    "sg:tags":[
        "embroidery",
        "mfg"
    ],
    "wof:name":"Thread Bear Designs",
    "wof:placetype":"venue"
},
  "geometry": {"coordinates":[-90.960318,36.272718],"type":"Point"}
}