{
  "type": "Feature",
  "properties": {
    "iso:country":"US",
    "sg:address":"103 N College Ave",
    "sg:city":"Fayetteville",
    "sg:classifiers":[
        {
            "category":"Professional",
            "subcategory":"Business Services",
            "type":"Services"
        }
    ],
    "sg:phone":"+1 479 251 7176",
    "sg:postcode":"72701",
    "sg:province":"AR",
    "wof:name":"Continental Card Transactions",
    "wof:placetype":"venue"
},
  "geometry": {"coordinates":[-94.15795300000001,36.064607],"type":"Point"}
}