{
  "type": "Feature",
  "properties": {
    "iso:country":"US",
    "sg:address":"718 S Main St",
    "sg:city":"Mountain Home",
    "sg:classifiers":[
        {
            "category":"Autos & Motor Vehicles",
            "subcategory":"Auto Supplies",
            "type":"Retail Goods"
        }
    ],
    "sg:phone":"+1 870 424 3767",
    "sg:postcode":"72653",
    "sg:province":"AR",
    "wof:name":"Auto Trim Design",
    "wof:placetype":"venue"
},
  "geometry": {"coordinates":[-92.3854,36.334568],"type":"Point"}
}