{
  "type": "Feature",
  "properties": {
    "iso:country":"US",
    "sg:address":"4498 Lee Road 116",
    "sg:city":"Moro",
    "sg:classifiers":[
        {
            "category":"Manufacturing",
            "subcategory":"Food",
            "type":"Manufacturing & Wholesale Goods"
        }
    ],
    "sg:phone":"+1 870 768 4624",
    "sg:postcode":"72368",
    "sg:province":"AR",
    "sg:tags":[
        "product"
    ],
    "wof:name":"Broadway Farms",
    "wof:placetype":"venue"
},
  "geometry": {"coordinates":[-90.97175300000001,34.746605],"type":"Point"}
}