{
  "type": "Feature",
  "properties": {
    "iso:country":"US",
    "sg:address":"2210 Sybel Cove",
    "sg:city":"Jonesboro",
    "sg:classifiers":[
        {
            "category":"Real Estate",
            "subcategory":"Real Estate Operator",
            "type":"Services"
        }
    ],
    "sg:phone":"+1 870 931 1520",
    "sg:postcode":"72401",
    "sg:province":"AR",
    "sg:tags":[
        "apartment"
    ],
    "wof:name":"West Minister Apartments",
    "wof:placetype":"venue"
},
  "geometry": {"coordinates":[-90.67997,35.848503],"type":"Point"}
}