{
  "type": "Feature",
  "properties": {
    "iso:country":"US",
    "sg:address":"19763 Hwy 70 E",
    "sg:city":"Heth",
    "sg:classifiers":[
        {
            "category":"Government",
            "subcategory":"Post Office",
            "type":"Public Place"
        }
    ],
    "sg:phone":"+1 870 657 2408",
    "sg:postcode":"72346",
    "sg:province":"AR",
    "wof:name":"US Post Office",
    "wof:placetype":"venue"
},
  "geometry": {"coordinates":[-90.490255,35.129361],"type":"Point"}
}