{
  "type": "Feature",
  "properties": {
    "iso:country":"US",
    "sg:address":"723 E Longview St",
    "sg:city":"Fayetteville",
    "sg:classifiers":[
        {
            "category":"Building & Trades",
            "subcategory":"Construction",
            "type":"Services"
        }
    ],
    "sg:phone":"+1 479 841 3891",
    "sg:postcode":"72703",
    "sg:province":"AR",
    "sg:tags":[
        "remodeling",
        "general"
    ],
    "wof:name":"Meek Bros",
    "wof:placetype":"venue"
},
  "geometry": {"coordinates":[-94.14622,36.11126],"type":"Point"}
}