{
  "type": "Feature",
  "properties": {
    "iso:country":"US",
    "sg:address":"313 S Garfield St",
    "sg:city":"Weiner",
    "sg:classifiers":[
        {
            "category":"Education",
            "subcategory":"School",
            "type":"Public Place"
        }
    ],
    "sg:phone":"+1 870 684 2252",
    "sg:postcode":"72479",
    "sg:province":"AR",
    "wof:name":"Weiner Elementary School",
    "wof:placetype":"venue"
},
  "geometry": {"coordinates":[-90.905616,35.616692],"type":"Point"}
}