{
  "type": "Feature",
  "properties": {
    "iso:country":"US",
    "sg:address":"253 Hwy 70",
    "sg:city":"Glenwood",
    "sg:classifiers":[
        {
            "category":"Personal",
            "subcategory":"Beauty Salon",
            "type":"Services"
        }
    ],
    "sg:phone":"+1 870 356 6287",
    "sg:postcode":"71943",
    "sg:province":"AR",
    "sg:tags":[
        "shop"
    ],
    "wof:name":"Nat & Company",
    "wof:placetype":"venue"
},
  "geometry": {"coordinates":[-93.406387,34.372824],"type":"Point"}
}