{
  "type": "Feature",
  "properties": {
    "addr:full":"904 State Hwy 12 Bentonville AR 72712",
    "addr:housenumber":"904",
    "addr:postcode":"72712",
    "addr:street":"State Hwy 12",
    "iso:country":"US",
    "sg:address":"904 State Hwy 12",
    "sg:city":"Bentonville",
    "sg:classifiers":[
        {
            "category":"Organizations",
            "subcategory":"Religious Organization",
            "type":"Services"
        }
    ],
    "sg:phone":"+1 479 464 5050",
    "sg:postcode":"72712",
    "sg:province":"AR",
    "sg:tags":[
        "church"
    ],
    "wof:name":"Cornerstone Baptist Church",
    "wof:placetype":"venue"
},
  "geometry": {"coordinates":[-94.20065700000001,36.335363],"type":"Point"}
}