{
  "type": "Feature",
  "properties": {
    "iso:country":"US",
    "sg:address":"239 Mount Pisgah Rd",
    "sg:city":"Searcy",
    "sg:classifiers":[
        {
            "category":"Farming",
            "subcategory":"Livestock Farm",
            "type":"Manufacturing & Wholesale Goods"
        }
    ],
    "sg:phone":"+1 501 268 1569",
    "sg:postcode":"72143",
    "sg:province":"AR",
    "sg:tags":[
        "beef",
        "feedlot",
        "cattle"
    ],
    "wof:name":"George Brown Farms",
    "wof:placetype":"venue"
},
  "geometry": {"coordinates":[-91.835559,35.297073],"type":"Point"}
}