{
  "type": "Feature",
  "properties": {
    "iso:country":"US",
    "sg:address":"2920 Mcclellan Dr",
    "sg:city":"Jonesboro",
    "sg:classifiers":[
        {
            "category":"Professional",
            "subcategory":"Detective & Security Services",
            "type":"Services"
        }
    ],
    "sg:phone":"+1 870 910 8129",
    "sg:postcode":"72401",
    "sg:province":"AR",
    "sg:tags":[
        "information",
        "bureau"
    ],
    "wof:name":"Arkansas Rehabilitation Services",
    "wof:placetype":"venue"
},
  "geometry": {"coordinates":[-90.686242,35.808153],"type":"Point"}
}