{
  "type": "Feature",
  "properties": {
    "iso:country":"US",
    "sg:address":"776 Highway 70 E",
    "sg:city":"Glenwood",
    "sg:classifiers":[
        {
            "category":"Organizations",
            "subcategory":"Religious Organization",
            "type":"Services"
        }
    ],
    "sg:phone":"+1 870 356 5465",
    "sg:postcode":"71943",
    "sg:province":"AR",
    "wof:name":"Porter Christian Dev Center",
    "wof:placetype":"venue"
},
  "geometry": {"coordinates":[-93.538753,34.326081],"type":"Point"}
}