{
  "type": "Feature",
  "properties": {
    "iso:country":"US",
    "sg:address":"2108 W Dewitt Henry Dr",
    "sg:city":"Beebe",
    "sg:classifiers":[
        {
            "category":"Retail",
            "subcategory":"Laundry & Dry Cleaning",
            "type":"Services"
        }
    ],
    "sg:phone":"+1 501 882 9777",
    "sg:postcode":"72012",
    "sg:province":"AR",
    "sg:tags":[
        "cleaners"
    ],
    "wof:name":"Regency Cleaners",
    "wof:placetype":"venue"
},
  "geometry": {"coordinates":[-91.90552700000001,35.071248],"type":"Point"}
}