{
  "type": "Feature",
  "properties": {
    "iso:country":"US",
    "sg:address":"807 Brownlee Ave",
    "sg:city":"N Little Rock",
    "sg:classifiers":[
        {
            "category":"Organizations",
            "subcategory":"Religious Organization",
            "type":"Services"
        }
    ],
    "sg:phone":"+1 501 945 5767",
    "sg:postcode":"72117",
    "sg:province":"AR",
    "sg:tags":[
        "church"
    ],
    "wof:name":"St Joe Baptist Church",
    "wof:placetype":"venue"
},
  "geometry": {"coordinates":[-92.197658,34.797795],"type":"Point"}
}