{
  "type": "Feature",
  "properties": {
    "iso:country":"US",
    "sg:address":"551 Whisker Rd",
    "sg:city":"Ward",
    "sg:classifiers":[
        {
            "category":"Building & Trades",
            "subcategory":"Construction",
            "type":"Services"
        }
    ],
    "sg:phone":"+1 501 605 0141",
    "sg:postcode":"72176",
    "sg:province":"AR",
    "sg:tags":[
        "house"
    ],
    "wof:name":"B & L Home Improvement",
    "wof:placetype":"venue"
},
  "geometry": {"coordinates":[-91.819076,34.994431],"type":"Point"}
}