{
  "type": "Feature",
  "properties": {
    "iso:country":"US",
    "sg:address":"2301 S 56th St",
    "sg:city":"Fort Smith",
    "sg:classifiers":[
        {
            "category":"Real Estate",
            "subcategory":"Real Estate Agent",
            "type":"Services"
        }
    ],
    "sg:phone":"+1 479 452 6565",
    "sg:postcode":"72903",
    "sg:province":"AR",
    "wof:name":"Yarbrough & Yarbrough Realtors",
    "wof:placetype":"venue"
},
  "geometry": {"coordinates":[-94.370814,35.360581],"type":"Point"}
}