{
  "type": "Feature",
  "properties": {
    "addr:full":"402 E Harding St Morrilton AR 72110",
    "addr:housenumber":"402",
    "addr:postcode":"72110",
    "addr:street":"E Harding St",
    "iso:country":"US",
    "sg:address":"402 E Harding St",
    "sg:city":"Morrilton",
    "sg:classifiers":[
        {
            "category":"Autos & Motor Vehicles",
            "subcategory":"Fuel & Gas Station",
            "type":"Retail Goods"
        }
    ],
    "sg:phone":"+1 501 354 1630",
    "sg:postcode":"72110",
    "sg:province":"AR",
    "sg:tags":[
        "station",
        "gasoline"
    ],
    "wof:name":"Texaco",
    "wof:placetype":"venue"
},
  "geometry": {"coordinates":[-92.738117,35.162999],"type":"Point"}
}