{
  "type": "Feature",
  "properties": {
    "iso:country":"US",
    "sg:address":"1410 Zero St",
    "sg:city":"Fort Smith",
    "sg:classifiers":[
        {
            "category":"Retail",
            "subcategory":"Auto Repair",
            "type":"Services"
        }
    ],
    "sg:phone":"+1 479 648 3030",
    "sg:postcode":"72908",
    "sg:province":"AR",
    "sg:tags":[
        "repairing",
        "automobile"
    ],
    "wof:name":"Precision Tune Auto Care",
    "wof:placetype":"venue"
},
  "geometry": {"coordinates":[-94.41905300000001,35.327995],"type":"Point"}
}