{
  "type": "Feature",
  "properties": {
    "iso:country":"US",
    "sg:address":"2202 S Walton Blvd",
    "sg:city":"Bentonville",
    "sg:classifiers":[
        {
            "category":"Organizations",
            "subcategory":"Religious Organization",
            "type":"Services"
        }
    ],
    "sg:phone":"+1 479 273 5683",
    "sg:postcode":"72712",
    "sg:province":"AR",
    "wof:name":"Devotional Line",
    "wof:placetype":"venue"
},
  "geometry": {"coordinates":[-94.210634,36.348018],"type":"Point"}
}