{
  "type": "Feature",
  "properties": {
    "addr:full":"1355 E Henri de Tonti Blvd Springdale AR 72762",
    "addr:housenumber":"1355",
    "addr:postcode":"72762",
    "addr:street":"E Henri De Tonti Blvd",
    "iso:country":"US",
    "sg:address":"1355 E Henri de Tonti Blvd",
    "sg:city":"Springdale",
    "sg:classifiers":[
        {
            "category":"Shopping",
            "type":"Retail Goods"
        }
    ],
    "sg:phone":"+1 479 366 7212",
    "sg:postcode":"72762",
    "sg:province":"AR",
    "sg:tags":[
        "merchandise"
    ],
    "wof:name":"Quantitative Insights Phoenix Stores",
    "wof:placetype":"venue"
},
  "geometry": {"coordinates":[-94.213855,36.175882],"type":"Point"}
}