{
  "type": "Feature",
  "properties": {
    "iso:country":"US",
    "sg:address":"1284 W Henri de Tonti Blvd",
    "sg:city":"Springdale",
    "sg:classifiers":[
        {
            "category":"Travel",
            "subcategory":"Travel Agent",
            "type":"Entertainment"
        },
        {
            "category":"Autos & Motor Vehicles",
            "subcategory":"Auto Supplies",
            "type":"Retail Goods"
        },
        {
            "category":"Military Area",
            "subcategory":"Naval Base",
            "type":"Public Place"
        },
        {
            "category":"Retail",
            "subcategory":"Auto Repair",
            "type":"Services"
        },
        {
            "category":"Autos & Motor Vehicles",
            "subcategory":"Recreational Vehicle Sales",
            "type":"Retail Goods"
        }
    ],
    "sg:phone":"+1 479 306 5555",
    "sg:postcode":"72762",
    "sg:province":"AR",
    "sg:tags":[
        "utility",
        "campers-repair",
        "camper",
        "hitch",
        "equipment",
        "part",
        "home",
        "lease",
        "trailer",
        "campers-rent"
    ],
    "sg:website":"http://www.wheelsrv.net",
    "wof:name":"Wheels RV Too",
    "wof:placetype":"venue"
},
  "geometry": {"coordinates":[-94.255461,36.176855],"type":"Point"}
}