{
  "type": "Feature",
  "properties": {
    "addr:full":"3811 S Indiana St Pine Bluff AR 71601",
    "addr:housenumber":"3811",
    "addr:postcode":"71601",
    "addr:street":"S Indiana St",
    "iso:country":"US",
    "sg:address":"3811 S Indiana St",
    "sg:city":"Pine Bluff",
    "sg:classifiers":[
        {
            "category":"Organizations",
            "subcategory":"Religious Organization",
            "type":"Services"
        }
    ],
    "sg:phone":"+1 870 536 3646",
    "sg:postcode":"71601",
    "sg:province":"AR",
    "sg:tags":[
        "church"
    ],
    "wof:name":"Greater United Missionary Bapt",
    "wof:placetype":"venue"
},
  "geometry": {"coordinates":[-91.993578,34.188815],"type":"Point"}
}