{
  "type": "Feature",
  "properties": {
    "iso:country":"US",
    "sg:address":"725 Almoo St",
    "sg:city":"Lowell",
    "sg:classifiers":[
        {
            "category":"Professional",
            "subcategory":"Business Services",
            "type":"Services"
        }
    ],
    "sg:phone":"+1 479 381 1881",
    "sg:postcode":"72745",
    "sg:province":"AR",
    "wof:name":"Pennys Enterprises of NW Ark",
    "wof:placetype":"venue"
},
  "geometry": {"coordinates":[-94.129493,36.264699],"type":"Point"}
}