{
  "type": "Feature",
  "properties": {
    "iso:country":"US",
    "sg:address":"14961 Readings Rd",
    "sg:city":"Siloam Springs",
    "sg:classifiers":[
        {
            "category":"Manufacturing",
            "subcategory":"Food",
            "type":"Manufacturing & Wholesale Goods"
        }
    ],
    "sg:phone":"+1 479 524 6421",
    "sg:postcode":"72761",
    "sg:province":"OK",
    "sg:tags":[
        "canning"
    ],
    "wof:name":"Allen Canning Co",
    "wof:placetype":"venue"
},
  "geometry": {"coordinates":[-94.42641399999999,36.205403],"type":"Point"}
}