{
  "type": "Feature",
  "properties": {
    "iso:country":"US",
    "sg:address":"519 E Capitol Ave",
    "sg:city":"Little Rock",
    "sg:classifiers":[
        {
            "category":"Organizations",
            "subcategory":"Political Organization",
            "type":"Services"
        }
    ],
    "sg:phone":"+1 501 374 2932",
    "sg:postcode":"72202",
    "sg:province":"AR",
    "wof:name":"Marvins Parks For Congress",
    "wof:placetype":"venue"
},
  "geometry": {"coordinates":[-92.26531199999999,34.743303],"type":"Point"}
}