{
  "type": "Feature",
  "properties": {
    "addr:full":"1109 N Phoenix Ave Russellville AR 72801",
    "addr:housenumber":"1109",
    "addr:postcode":"72801",
    "addr:street":"N Phoenix Ave",
    "iso:country":"US",
    "sg:address":"1109 N Phoenix Ave",
    "sg:city":"Russellville",
    "sg:classifiers":[
        {
            "category":"Building & Trades",
            "subcategory":"Landscaping Services",
            "type":"Services"
        }
    ],
    "sg:phone":"+1 479 967 1137",
    "sg:postcode":"72801",
    "sg:province":"AR",
    "sg:tags":[
        "landscape"
    ],
    "wof:name":"Holloway Landscaping",
    "wof:placetype":"venue"
},
  "geometry": {"coordinates":[-93.146935,35.288704],"type":"Point"}
}