{
  "type": "Feature",
  "properties": {
    "iso:country":"US",
    "sg:address":"419 Phillip St",
    "sg:city":"Imboden",
    "sg:classifiers":[
        {
            "category":"Manufacturing",
            "subcategory":"Lumber",
            "type":"Manufacturing & Wholesale Goods"
        }
    ],
    "sg:phone":"+1 870 869 0086",
    "sg:postcode":"72434",
    "sg:province":"AR",
    "sg:tags":[
        "logging"
    ],
    "wof:name":"Bucks Logging Co Inc",
    "wof:placetype":"venue"
},
  "geometry": {"coordinates":[-91.197615,36.202957],"type":"Point"}
}