{
  "type": "Feature",
  "properties": {
    "addr:full":"110 School St Elm Springs AR 72728",
    "addr:housenumber":"110",
    "addr:postcode":"72728",
    "addr:street":"School St",
    "iso:country":"US",
    "sg:address":"110 School St",
    "sg:city":"Elm Springs",
    "sg:classifiers":[
        {
            "category":"Organizations",
            "subcategory":"Religious Organization",
            "type":"Services"
        }
    ],
    "sg:phone":"+1 479 248 1290",
    "sg:postcode":"72728",
    "sg:province":"AR",
    "sg:website":"www.umc.org",
    "wof:name":"Elm Springs United Methodist Church",
    "wof:placetype":"venue"
},
  "geometry": {"coordinates":[-94.234802,36.2062],"type":"Point"}
}