{
  "type": "Feature",
  "properties": {
    "addr:full":"1301 N 13th St Fort Smith AR 72901",
    "addr:housenumber":"1301",
    "addr:postcode":"72901",
    "addr:street":"N 13Th St",
    "iso:country":"US",
    "sg:address":"1301 N 13th St",
    "sg:city":"Fort Smith",
    "sg:classifiers":[
        {
            "category":"Organizations",
            "subcategory":"Religious Organization",
            "type":"Services"
        }
    ],
    "sg:phone":"+1 479 782 6568",
    "sg:postcode":"72901",
    "sg:province":"AR",
    "sg:tags":[
        "church"
    ],
    "wof:name":"Unity Missionary Baptst Church",
    "wof:placetype":"venue"
},
  "geometry": {"coordinates":[-94.40845899999999,35.393508],"type":"Point"}
}