{
  "type": "Feature",
  "properties": {
    "iso:country":"US",
    "sg:address":"1301 N 13th St",
    "sg:city":"Fort Smith",
    "sg:classifiers":[
        {
            "category":"Organizations",
            "subcategory":"Religious Organization",
            "type":"Services"
        }
    ],
    "sg:phone":"+1 479 782 6568",
    "sg:postcode":"72901",
    "sg:province":"AR",
    "sg:tags":[
        "church"
    ],
    "wof:name":"Unity Missionary Baptst Church",
    "wof:placetype":"venue"
},
  "geometry": {"coordinates":[-94.408459,35.393508],"type":"Point"}
}