{
  "type": "Feature",
  "properties": {
    "iso:country":"US",
    "sg:address":"9214 N Rodney Parham Rd",
    "sg:city":"Little Rock",
    "sg:classifiers":[
        {
            "category":"Retail",
            "subcategory":"Auto Repair",
            "type":"Services"
        }
    ],
    "sg:phone":"+1 501 224 6108",
    "sg:postcode":"72227",
    "sg:province":"AR",
    "sg:tags":[
        "exhaust"
    ],
    "wof:name":"Midas Muffler",
    "wof:placetype":"venue"
},
  "geometry": {"coordinates":[-92.37666400000001,34.757792],"type":"Point"}
}