{
  "type": "Feature",
  "properties": {
    "iso:country":"US",
    "sg:address":"1817 S Woodrow St",
    "sg:city":"Little Rock",
    "sg:classifiers":[
        {
            "category":"Restaurant",
            "type":"Food & Drink"
        }
    ],
    "sg:phone":"+1 501 296 9070",
    "sg:postcode":"72204",
    "sg:province":"AR",
    "wof:name":"Woodrow Super Store",
    "wof:placetype":"venue"
},
  "geometry": {"coordinates":[-92.30592799999999,34.734166],"type":"Point"}
}