{
  "type": "Feature",
  "properties": {
    "iso:country":"US",
    "sg:address":"208 Suttle Dr",
    "sg:city":"Springdale",
    "sg:classifiers":[
        {
            "category":"Manufacturing",
            "subcategory":"Furniture",
            "type":"Manufacturing & Wholesale Goods"
        }
    ],
    "sg:phone":"+1 479 756 6688",
    "sg:postcode":"72764",
    "sg:province":"AR",
    "sg:tags":[
        "drapery",
        "mfg"
    ],
    "wof:name":"Clarks Upholstery & Drapery",
    "wof:placetype":"venue"
},
  "geometry": {"coordinates":[-94.144505,36.137764],"type":"Point"}
}