{
  "type": "Feature",
  "properties": {
    "iso:country":"US",
    "sg:address":"120 Leander St",
    "sg:city":"Benton",
    "sg:classifiers":[
        {
            "category":"Retail",
            "subcategory":"Car Wash",
            "type":"Services"
        }
    ],
    "sg:phone":"+1 501 776 0840",
    "sg:postcode":"72015",
    "sg:province":"AR",
    "sg:tags":[
        "polishing",
        "washing"
    ],
    "wof:name":"Old School Car Wash",
    "wof:placetype":"venue"
},
  "geometry": {"coordinates":[-92.60189800000001,34.564956],"type":"Point"}
}