{
  "type": "Feature",
  "properties": {
    "addr:full":"3685 Noblett Dr Conway AR 72034",
    "addr:housenumber":"3685",
    "addr:postcode":"72034",
    "addr:street":"Noblett Dr",
    "iso:country":"US",
    "sg:address":"3685 Noblett Dr",
    "sg:city":"Conway",
    "sg:classifiers":[
        {
            "category":"Professional",
            "subcategory":"Management & Consulting",
            "type":"Services"
        }
    ],
    "sg:phone":"+1 501 329 8902",
    "sg:postcode":"72034",
    "sg:province":"AR",
    "wof:name":"Johnson Management Systems",
    "wof:placetype":"venue"
},
  "geometry": {"coordinates":[-92.491975,35.0786],"type":"Point"}
}