{
  "type": "Feature",
  "properties": {
    "iso:country":"US",
    "sg:address":"209 N Main St",
    "sg:city":"Searcy",
    "sg:classifiers":[
        {
            "category":"Food & Beverages",
            "subcategory":"Groceries & Convenience Stores",
            "type":"Retail Goods"
        }
    ],
    "sg:phone":"+1 501 742 3781",
    "sg:postcode":"72143",
    "sg:province":"AR",
    "wof:name":"Georgetown One Stop",
    "wof:placetype":"venue"
},
  "geometry": {"coordinates":[-91.736396,35.250055],"type":"Point"}
}