{
  "type": "Feature",
  "properties": {
    "iso:country":"US",
    "sg:address":"405 S Main St",
    "sg:city":"Grove",
    "sg:classifiers":[
        {
            "category":"Building & Trades",
            "subcategory":"Pest Control",
            "type":"Services"
        }
    ],
    "sg:phone":"+1 918 787 2234",
    "sg:postcode":"74344",
    "sg:province":"OK",
    "sg:tags":[
        "spraying"
    ],
    "wof:name":"State Pest Control",
    "wof:placetype":"venue"
},
  "geometry": {"coordinates":[-94.769205,36.59238],"type":"Point"}
}