{
  "type": "Feature",
  "properties": {
    "addr:full":"6403 Fourche Dam Pike Little Rock AR 72206",
    "addr:postcode":"6403;72206",
    "addr:street":"Fourche Dam Pike",
    "iso:country":"US",
    "sg:address":"6403 Fourche Dam Pike",
    "sg:city":"Little Rock",
    "sg:classifiers":[
        {
            "category":"Retail",
            "subcategory":"Auto Repair",
            "type":"Services"
        }
    ],
    "sg:phone":"+1 501 490 1360",
    "sg:postcode":"72206",
    "sg:province":"AR",
    "sg:tags":[
        "automotive",
        "general"
    ],
    "wof:name":"Routh Wrecker Service",
    "wof:placetype":"venue"
},
  "geometry": {"coordinates":[-92.1983,34.721648],"type":"Point"}
}