{
  "type": "Feature",
  "properties": {
    "iso:country":"US",
    "sg:address":"305 Mulberry Hwy 64 E",
    "sg:city":"Mulberry",
    "sg:classifiers":[
        {
            "category":"Freight",
            "type":"Transportation"
        }
    ],
    "sg:phone":"+1 479 997 1080",
    "sg:postcode":"72947",
    "sg:province":"AR",
    "sg:tags":[
        "trucking"
    ],
    "wof:name":"Sharkey Transportation",
    "wof:placetype":"venue"
},
  "geometry": {"coordinates":[-94.048439,35.502408],"type":"Point"}
}