{
  "type": "Feature",
  "properties": {
    "iso:country":"US",
    "sg:address":"924 Highway 318 S",
    "sg:city":"Marvell",
    "sg:classifiers":[
        {
            "category":"Manufacturing",
            "subcategory":"Textiles",
            "type":"Manufacturing & Wholesale Goods"
        }
    ],
    "sg:phone":"+1 870 829 2948",
    "sg:postcode":"72366",
    "sg:province":"AR",
    "sg:tags":[
        "broker",
        "cotton"
    ],
    "wof:name":"Allen Culp",
    "wof:placetype":"venue"
},
  "geometry": {"coordinates":[-90.948219,34.451691],"type":"Point"}
}