{
  "type": "Feature",
  "properties": {
    "iso:country":"US",
    "sg:address":"201 Skyline Dr Ste. 30",
    "sg:city":"Conway",
    "sg:classifiers":[
        {
            "category":"Health Services",
            "subcategory":"Dentist",
            "type":"Services"
        }
    ],
    "sg:phone":"+1 501 329 3598",
    "sg:postcode":"72032",
    "sg:province":"AR",
    "sg:tags":[
        "dental",
        "clinic"
    ],
    "sg:website":"http://www.conwaydentistry.com",
    "wof:name":"Turney Ellen Family Dentistry",
    "wof:placetype":"venue"
},
  "geometry": {"coordinates":[-92.429733,35.112488],"type":"Point"}
}