{
  "type": "Feature",
  "properties": {
    "addr:full":"503 Trenton St Huntsville AR 72740",
    "addr:housenumber":"503",
    "addr:postcode":"72740",
    "addr:street":"Trenton St",
    "iso:country":"US",
    "sg:address":"503 Trenton St",
    "sg:city":"Huntsville",
    "sg:classifiers":[
        {
            "category":"Government",
            "subcategory":"Office",
            "type":"Public Place"
        }
    ],
    "sg:phone":"+1 479 738 6537",
    "sg:postcode":"72740",
    "sg:province":"AR",
    "wof:name":"Madison County Veterans Svc",
    "wof:placetype":"venue"
},
  "geometry": {"coordinates":[-93.72928899999999,36.087301],"type":"Point"}
}