{
  "type": "Feature",
  "properties": {
    "iso:country":"US",
    "sg:address":"12211 State Hwy 300",
    "sg:city":"Roland",
    "sg:classifiers":[
        {
            "category":"Organizations",
            "subcategory":"Religious Organization",
            "type":"Services"
        }
    ],
    "sg:phone":"+1 501 868 1804",
    "sg:postcode":"72135",
    "sg:province":"AR",
    "sg:tags":[
        "church"
    ],
    "wof:name":"First Baptist Chr-Natural Stps",
    "wof:placetype":"venue"
},
  "geometry": {"coordinates":[-92.474228,34.865055],"type":"Point"}
}