{
  "type": "Feature",
  "properties": {
    "iso:country":"US",
    "sg:address":"4000 N Rodney Parham Rd",
    "sg:city":"Little Rock",
    "sg:classifiers":[
        {
            "category":"Organizations",
            "subcategory":"Religious Organization",
            "type":"Services"
        }
    ],
    "sg:phone":"+1 501 225 6774",
    "sg:postcode":"72212",
    "sg:province":"AR",
    "wof:name":"Christ King Catholic Church",
    "wof:placetype":"venue"
},
  "geometry": {"coordinates":[-92.39835600000001,34.789738],"type":"Point"}
}