{
  "type": "Feature",
  "properties": {
    "iso:country":"US",
    "sg:address":"2408 W New Hope Rd",
    "sg:city":"Rogers",
    "sg:classifiers":[
        {
            "category":"Insurance",
            "subcategory":"Hazard Insurance",
            "type":"Services"
        },
        {
            "category":"Insurance",
            "subcategory":"Health Insurance",
            "type":"Services"
        }
    ],
    "sg:phone":"+1 479 631 7242",
    "sg:postcode":"72758",
    "sg:province":"AR",
    "sg:tags":[
        "dental",
        "commercial",
        "business"
    ],
    "wof:name":"Williamson Insurance Agency",
    "wof:placetype":"venue"
},
  "geometry": {"coordinates":[-94.153267,36.312404],"type":"Point"}
}