{
  "type": "Feature",
  "properties": {
    "iso:country":"US",
    "sg:address":"3012 W 12th St",
    "sg:city":"Little Rock",
    "sg:classifiers":[
        {
            "category":"Organizations",
            "subcategory":"Non-profit Organization",
            "type":"Services"
        }
    ],
    "sg:phone":"+1 501 663 2281",
    "sg:postcode":"72204",
    "sg:province":"AR",
    "sg:tags":[
        "development",
        "community"
    ],
    "wof:name":"Save Our Children Cmnty Prj",
    "wof:placetype":"venue"
},
  "geometry": {"coordinates":[-92.307959,34.740078],"type":"Point"}
}