{
  "type": "Feature",
  "properties": {
    "iso:country":"US",
    "sg:address":"701 Park Ave",
    "sg:city":"Hot Springs",
    "sg:classifiers":[
        {
            "category":"Autos & Motor Vehicles",
            "subcategory":"Fuel & Gas Station",
            "type":"Retail Goods"
        }
    ],
    "sg:phone":"+1 501 623 4042",
    "sg:postcode":"71901",
    "sg:province":"AR",
    "sg:tags":[
        "oil"
    ],
    "wof:name":"Park Avenue Exxon",
    "wof:placetype":"venue"
},
  "geometry": {"coordinates":[-93.05238199999999,34.526375],"type":"Point"}
}