{
  "type": "Feature",
  "properties": {
    "addr:full":"10424 Hwy 319 W Austin AR 72007",
    "addr:housenumber":"10424",
    "addr:postcode":"72007",
    "addr:street":"Hwy 319 W",
    "iso:country":"US",
    "sg:address":"10424 Hwy 319 W",
    "sg:city":"Austin",
    "sg:classifiers":[
        {
            "category":"Building & Trades",
            "subcategory":"Construction",
            "type":"Services"
        }
    ],
    "sg:phone":"+1 501 681 3657",
    "sg:postcode":"72007",
    "sg:province":"AR",
    "sg:tags":[
        "house"
    ],
    "wof:name":"James D Bellar Constr",
    "wof:placetype":"venue"
},
  "geometry": {"coordinates":[-92.1113,35.056209],"type":"Point"}
}