{
  "type": "Feature",
  "properties": {
    "iso:country":"US",
    "sg:address":"117 Brandiles Ln",
    "sg:city":"Hot Springs National Park",
    "sg:classifiers":[
        {
            "category":"Arts & Performance",
            "subcategory":"Theater",
            "type":"Entertainment"
        }
    ],
    "sg:phone":"+1 501 525 8000",
    "sg:postcode":"71913",
    "sg:province":"AR",
    "sg:tags":[
        "group"
    ],
    "wof:name":"Solutions Home Entrmt LLC",
    "wof:placetype":"venue"
},
  "geometry": {"coordinates":[-93.122884,34.508075],"type":"Point"}
}