{
  "type": "Feature",
  "properties": {
    "addr:full":"6420 Asher Ave Little Rock AR 72204",
    "addr:housenumber":"6420",
    "addr:postcode":"72204",
    "addr:street":"Asher Ave",
    "iso:country":"US",
    "sg:address":"6420 Asher Ave",
    "sg:city":"Little Rock",
    "sg:classifiers":[
        {
            "category":"Shopping",
            "subcategory":"Department Store",
            "type":"Retail Goods"
        }
    ],
    "sg:phone":"+1 501 568 2980",
    "sg:postcode":"72204",
    "sg:province":"AR",
    "wof:name":"Wal-Mart",
    "wof:placetype":"venue"
},
  "geometry": {"coordinates":[-92.348862,34.718023],"type":"Point"}
}