{
  "type": "Feature",
  "properties": {
    "addr:full":"40 Mill Run Trl Batesville AR 72501",
    "addr:housenumber":"40",
    "addr:postcode":"72501",
    "addr:street":"Mill Run Trl",
    "iso:country":"US",
    "sg:address":"40 Mill Run Trl",
    "sg:city":"Batesville",
    "sg:classifiers":[
        {
            "category":"Banks & Credit Unions",
            "subcategory":"Financial Services",
            "type":"Services"
        }
    ],
    "sg:phone":"+1 870 793 7978",
    "sg:postcode":"72501",
    "sg:province":"AR",
    "sg:tags":[
        "investor"
    ],
    "wof:name":"Smart Investments",
    "wof:placetype":"venue"
},
  "geometry": {"coordinates":[-91.60885500000001,35.773066],"type":"Point"}
}