{
  "type": "Feature",
  "properties": {
    "addr:full":"116 Mulberry St Marianna AR 72360",
    "addr:housenumber":"116",
    "addr:postcode":"72360",
    "addr:street":"Mulberry St",
    "iso:country":"US",
    "sg:address":"116 Mulberry St",
    "sg:city":"Marianna",
    "sg:classifiers":[
        {
            "category":"Social Services",
            "subcategory":"Job Training",
            "type":"Services"
        },
        {
            "category":"Social Services",
            "subcategory":"Adult Care",
            "type":"Services"
        },
        {
            "category":"Social Services",
            "subcategory":"Retirement Home",
            "type":"Services"
        }
    ],
    "sg:phone":"+1 870 295 4550",
    "sg:postcode":"72360",
    "sg:province":"AR",
    "sg:tags":[
        "nurses-home",
        "convalescent",
        "nursing",
        "homes-skilled",
        "facility"
    ],
    "wof:name":"Delta Transitional Home",
    "wof:placetype":"venue"
},
  "geometry": {"coordinates":[-90.758809,34.777531],"type":"Point"}
}