{
  "type": "Feature",
  "properties": {
    "iso:country":"US",
    "sg:address":"1198 Greene Road 601",
    "sg:city":"Paragould",
    "sg:classifiers":[
        {
            "category":"Manufacturing",
            "subcategory":"Buildings",
            "type":"Manufacturing & Wholesale Goods"
        },
        {
            "category":"Building & Trades",
            "subcategory":"Construction",
            "type":"Services"
        }
    ],
    "sg:phone":"+1 870 573 6575",
    "sg:postcode":"72450",
    "sg:province":"AR",
    "sg:tags":[
        "home",
        "builder",
        "contractor"
    ],
    "wof:name":"Edrington Properties",
    "wof:placetype":"venue"
},
  "geometry": {"coordinates":[-90.648231,36.083977],"type":"Point"}
}