{
  "type": "Feature",
  "properties": {
    "iso:country":"US",
    "sg:address":"1656 Dilar Dr",
    "sg:city":"Grove",
    "sg:classifiers":[
        {
            "category":"Professional",
            "subcategory":"Business Services",
            "type":"Services"
        }
    ],
    "sg:phone":"+1 918 787 6484",
    "sg:postcode":"74344",
    "sg:province":"OK",
    "wof:name":"Enterprises In RB Fidler",
    "wof:placetype":"venue"
},
  "geometry": {"coordinates":[-94.791921,36.561431],"type":"Point"}
}