{
  "type": "Feature",
  "properties": {
    "addr:full":"3703 W Roosevelt Rd Little Rock AR 72204",
    "addr:housenumber":"3703",
    "addr:postcode":"72204",
    "addr:street":"W Roosevelt Rd",
    "iso:country":"US",
    "sg:address":"3703 W Roosevelt Rd",
    "sg:city":"Little Rock",
    "sg:classifiers":[
        {
            "category":"Government",
            "subcategory":"Police Station",
            "type":"Public Place"
        }
    ],
    "sg:phone":"+1 501 324 9209",
    "sg:postcode":"72204",
    "sg:province":"AR",
    "sg:tags":[
        "commission",
        "training",
        "law",
        "enforcement",
        "standard"
    ],
    "wof:name":"Commission of Law Enforcement",
    "wof:placetype":"venue"
},
  "geometry": {"coordinates":[-92.31632399999999,34.725812],"type":"Point"}
}