{
  "type": "Feature",
  "properties": {
    "iso:country":"US",
    "sg:address":"7610 Main St E",
    "sg:city":"Lead Hill",
    "sg:classifiers":[
        {
            "category":"Shopping",
            "subcategory":"Bicycles & Sporting Goods",
            "type":"Retail Goods"
        }
    ],
    "sg:phone":"+1 870 436 3202",
    "sg:postcode":"72644",
    "sg:province":"AR",
    "wof:name":"Roadside Bait & Tackle",
    "wof:placetype":"venue"
},
  "geometry": {"coordinates":[-92.91036699999999,36.394718],"type":"Point"}
}