{
  "type": "Feature",
  "properties": {
    "addr:full":"2621 Kellogg Acres Rd North Little Rock AR 72120",
    "addr:housenumber":"2621",
    "addr:postcode":"72120",
    "addr:street":"Kellogg Acres Rd",
    "iso:country":"US",
    "sg:address":"2621 Kellogg Acres Rd",
    "sg:city":"North Little Rock",
    "sg:classifiers":[
        {
            "category":"Real Estate",
            "subcategory":"Real Estate Agent",
            "type":"Services"
        }
    ],
    "sg:phone":"+1 501 835 8333",
    "sg:postcode":"72120",
    "sg:province":"AR",
    "wof:name":"Centaur Service Co",
    "wof:placetype":"venue"
},
  "geometry": {"coordinates":[-92.234212,34.873119],"type":"Point"}
}