{
  "type": "Feature",
  "properties": {
    "iso:country":"US",
    "sg:address":"101 N 3rd",
    "sg:city":"West Helena",
    "sg:classifiers":[
        {
            "category":"Personal",
            "subcategory":"Beauty Salon",
            "type":"Services"
        }
    ],
    "sg:phone":"+1 870 572 6243",
    "sg:postcode":"72390",
    "sg:province":"AR",
    "sg:tags":[
        "shop"
    ],
    "wof:name":"Keyya's Hair Gallery",
    "wof:placetype":"venue"
},
  "geometry": {"coordinates":[-90.64254699999999,34.546088],"type":"Point"}
}