{
  "type": "Feature",
  "properties": {
    "iso:country":"US",
    "sg:address":"1348 Central Ave",
    "sg:city":"Hot Springs National",
    "sg:classifiers":[
        {
            "category":"Health Services",
            "subcategory":"Doctor",
            "type":"Services"
        }
    ],
    "sg:phone":"+1 501 321 1239",
    "sg:postcode":"71901",
    "sg:province":"AR",
    "wof:name":"Earl McWherter DDS PA",
    "wof:placetype":"venue"
},
  "geometry": {"coordinates":[-93.056338,34.500151],"type":"Point"}
}