{
  "type": "Feature",
  "properties": {
    "addr:full":"312 SE 1st St Corning AR 72422",
    "addr:housenumber":"312",
    "addr:postcode":"72422",
    "addr:street":"Se 1St St",
    "iso:country":"US",
    "sg:address":"312 SE 1st St",
    "sg:city":"Corning",
    "sg:classifiers":[
        {
            "category":"Personal",
            "subcategory":"Beauty Salon",
            "type":"Services"
        }
    ],
    "sg:phone":"+1 870 857 5306",
    "sg:postcode":"72422",
    "sg:province":"AR",
    "sg:tags":[
        "shop"
    ],
    "wof:name":"Roberts",
    "wof:placetype":"venue"
},
  "geometry": {"coordinates":[-90.579322,36.407808],"type":"Point"}
}