{
  "type": "Feature",
  "properties": {
    "iso:country":"US",
    "sg:address":"7421 Palm Beach Ave",
    "sg:city":"Benton",
    "sg:classifiers":[
        {
            "category":"Structure",
            "subcategory":"Office Building",
            "type":"Public Place"
        }
    ],
    "sg:phone":"+1 501 680 5180",
    "sg:postcode":"72019",
    "sg:province":"AR",
    "sg:tags":[
        "park"
    ],
    "wof:name":"Wss Properties",
    "wof:placetype":"venue"
},
  "geometry": {"coordinates":[-92.522807,34.631666],"type":"Point"}
}