{
  "type": "Feature",
  "properties": {
    "addr:full":"3810 N Front St Fayetteville AR 72703",
    "addr:housenumber":"3810",
    "addr:postcode":"72703",
    "addr:street":"N Front St",
    "iso:country":"US",
    "sg:address":"3810 N Front St",
    "sg:city":"Fayetteville",
    "sg:classifiers":[
        {
            "category":"Professional",
            "subcategory":"Lawyer & Legal Services",
            "type":"Services"
        }
    ],
    "sg:phone":"+1 479 582 4800",
    "sg:postcode":"72703",
    "sg:province":"AR",
    "sg:tags":[
        "attorney",
        "accident",
        "personal",
        "automobile",
        "disability",
        "damage",
        "property",
        "social",
        "security",
        "injury",
        "law"
    ],
    "sg:website":"http://www.sterlinglawfirm.com",
    "wof:name":"Sterling Law Firm PA",
    "wof:placetype":"venue"
},
  "geometry": {"coordinates":[-94.144233,36.119015],"type":"Point"}
}