{
  "type": "Feature",
  "properties": {
    "iso:country":"US",
    "sg:address":"2500 S Arkansas Ave",
    "sg:city":"Russellville",
    "sg:classifiers":[
        {
            "category":"Shopping",
            "subcategory":"Computers & Home Electronics",
            "type":"Retail Goods"
        },
        {
            "category":"Home & Garden",
            "subcategory":"Household Appliances",
            "type":"Retail Goods"
        },
        {
            "category":"Home & Garden",
            "subcategory":"Hardware",
            "type":"Retail Goods"
        },
        {
            "category":"Manufacturing",
            "subcategory":"Tools & Machinery",
            "type":"Manufacturing & Wholesale Goods"
        },
        {
            "category":"Manufacturing",
            "subcategory":"Electronics",
            "type":"Manufacturing & Wholesale Goods"
        },
        {
            "category":"Wholesale",
            "subcategory":"Electrical",
            "type":"Manufacturing & Wholesale Goods"
        }
    ],
    "sg:phone":"+1 479 968 1296",
    "sg:postcode":"72802",
    "sg:province":"AR",
    "sg:tags":[
        "major",
        "electric",
        "supply",
        "supplies-wholesale",
        "equipment-testing",
        "equipment",
        "appliances-small",
        "consumer",
        "store",
        "manufacturer"
    ],
    "wof:name":"Vinson Electric Supply, Inc.",
    "wof:placetype":"venue"
},
  "geometry": {"coordinates":[-93.133785,35.255002],"type":"Point"}
}