{
  "type": "Feature",
  "properties": {
    "iso:country":"US",
    "sg:address":"521 N Lakeshore Dr",
    "sg:city":"Lake Village",
    "sg:classifiers":[
        {
            "category":"Organizations",
            "subcategory":"Religious Organization",
            "type":"Services"
        }
    ],
    "sg:phone":"+1 870 265 2230",
    "sg:postcode":"71653",
    "sg:province":"AR",
    "wof:name":"Episcopal Church Study",
    "wof:placetype":"venue"
},
  "geometry": {"coordinates":[-91.280208,33.335663],"type":"Point"}
}