{
  "type": "Feature",
  "properties": {
    "addr:full":"309 Ware Rd Greenwood AR 72936",
    "addr:housenumber":"309",
    "addr:postcode":"72936",
    "addr:street":"Ware Rd",
    "iso:country":"US",
    "sg:address":"309 Ware Rd",
    "sg:city":"Greenwood",
    "sg:classifiers":[
        {
            "category":"Shopping",
            "subcategory":"Florist",
            "type":"Retail Goods"
        }
    ],
    "sg:phone":"+1 479 996 7527",
    "sg:postcode":"72936",
    "sg:province":"AR",
    "wof:name":"Wedding Flowers & Dreams",
    "wof:placetype":"venue"
},
  "geometry": {"coordinates":[-94.22619899999999,35.207908],"type":"Point"}
}