{
  "type": "Feature",
  "properties": {
    "iso:country":"US",
    "sg:address":"309 Ware Rd",
    "sg:city":"Greenwood",
    "sg:classifiers":[
        {
            "category":"Shopping",
            "subcategory":"Florist",
            "type":"Retail Goods"
        }
    ],
    "sg:phone":"+1 479 996 7527",
    "sg:postcode":"72936",
    "sg:province":"AR",
    "wof:name":"Wedding Flowers & Dreams",
    "wof:placetype":"venue"
},
  "geometry": {"coordinates":[-94.226199,35.207908],"type":"Point"}
}