{
  "type": "Feature",
  "properties": {
    "iso:country":"US",
    "sg:address":"112 W Tulsa St",
    "sg:city":"Siloam Springs",
    "sg:classifiers":[
        {
            "category":"Real Estate",
            "subcategory":"Real Estate Agent",
            "type":"Services"
        }
    ],
    "sg:phone":"+1 479 524 3123",
    "sg:postcode":"72761",
    "sg:province":"OK",
    "sg:website":"www.wardjonesrealty.com",
    "wof:name":"Ward Jones Realtors",
    "wof:placetype":"venue"
},
  "geometry": {"coordinates":[-94.54239,36.177956],"type":"Point"}
}