{
  "type": "Feature",
  "properties": {
    "addr:full":"360 Madison 2729 Kingston AR 72742",
    "addr:housenumber":"360;2729",
    "addr:postcode":"72742",
    "iso:country":"US",
    "sg:address":"360 Madison 2729",
    "sg:city":"Kingston",
    "sg:classifiers":[
        {
            "category":"Travel",
            "subcategory":"Hotels & Motels",
            "type":"Entertainment"
        }
    ],
    "sg:phone":"+1 479 665 2986",
    "sg:postcode":"72742",
    "sg:province":"AR",
    "sg:tags":[
        "breakfast",
        "accommodation",
        "bed"
    ],
    "wof:name":"Fools Cove Ranch B & B",
    "wof:placetype":"venue"
},
  "geometry": {"coordinates":[-93.471788,36.0595],"type":"Point"}
}