{
  "type": "Feature",
  "properties": {
    "iso:country":"US",
    "sg:address":"700 W Kingshighway",
    "sg:city":"Paragould",
    "sg:classifiers":[
        {
            "category":"Health Services",
            "subcategory":"Doctor",
            "type":"Services"
        },
        {
            "category":"Health Services",
            "subcategory":"Podiatrist",
            "type":"Services"
        }
    ],
    "sg:phone":"+1 870 239 6004",
    "sg:postcode":"72450",
    "sg:province":"AR",
    "sg:tags":[
        "physician",
        "surgeon",
        "surgeons"
    ],
    "wof:name":"Bryan Glenn",
    "wof:placetype":"venue"
},
  "geometry": {"coordinates":[-90.49411000000001,36.052457],"type":"Point"}
}