{
  "type": "Feature",
  "properties": {
    "iso:country":"US",
    "sg:address":"2610 S Caraway Rd",
    "sg:city":"Jonesboro",
    "sg:classifiers":[
        {
            "category":"Building & Trades",
            "subcategory":"Construction",
            "type":"Services"
        }
    ],
    "sg:phone":"+1 870 972 1316",
    "sg:postcode":"72401",
    "sg:province":"AR",
    "sg:tags":[
        "builder",
        "operative"
    ],
    "sg:website":"www.ubh.com",
    "wof:name":"United-Bilt Homes Inc",
    "wof:placetype":"venue"
},
  "geometry": {"coordinates":[-90.677936,35.813839],"type":"Point"}
}