{
  "type": "Feature",
  "properties": {
    "addr:full":"1823 W Broadway Ave Forrest City AR 72335",
    "addr:housenumber":"1823",
    "addr:postcode":"72335",
    "addr:street":"W Broadway Ave",
    "iso:country":"US",
    "sg:address":"1823 W Broadway Ave",
    "sg:city":"Forrest City",
    "sg:classifiers":[
        {
            "category":"Home & Garden",
            "subcategory":"Building Materials",
            "type":"Retail Goods"
        }
    ],
    "sg:phone":"+1 870 633 9457",
    "sg:postcode":"72335",
    "sg:province":"AR",
    "sg:tags":[
        "lumber"
    ],
    "wof:name":"Ridout Lumber Co",
    "wof:placetype":"venue"
},
  "geometry": {"coordinates":[-90.800854,34.999954],"type":"Point"}
}