{
  "type": "Feature",
  "properties": {
    "iso:country":"US",
    "sg:address":"1214 Albert Pike Rd",
    "sg:city":"Hot Springs National Park",
    "sg:classifiers":[
        {
            "category":"Restaurant",
            "type":"Food & Drink"
        }
    ],
    "sg:phone":"+1 501 321 9663",
    "sg:postcode":"71913",
    "sg:province":"AR",
    "sg:tags":[
        "eating"
    ],
    "wof:name":"McDonalds",
    "wof:placetype":"venue"
},
  "geometry": {"coordinates":[-93.081568,34.493438],"type":"Point"}
}