{
  "type": "Feature",
  "properties": {
    "iso:country":"US",
    "sg:address":"8155 Edgemont Rd",
    "sg:city":"Greers Ferry",
    "sg:classifiers":[
        {
            "category":"Shopping",
            "subcategory":"Tobacco",
            "type":"Retail Goods"
        }
    ],
    "sg:phone":"+1 501 825 8256",
    "sg:postcode":"72067",
    "sg:province":"AR",
    "sg:tags":[
        "cigarette",
        "product",
        "cigar",
        "dealer"
    ],
    "wof:name":"Discount Tobacco of Arkansas",
    "wof:placetype":"venue"
},
  "geometry": {"coordinates":[-92.177222,35.572033],"type":"Point"}
}