{
  "type": "Feature",
  "properties": {
    "addr:full":"805 E 3rd St Hope AR 71801",
    "addr:housenumber":"805",
    "addr:postcode":"71801",
    "addr:street":"E 3Rd St",
    "iso:country":"US",
    "sg:address":"805 E 3rd St",
    "sg:city":"Hope",
    "sg:classifiers":[
        {
            "category":"Insurance",
            "subcategory":"Hazard Insurance",
            "type":"Services"
        }
    ],
    "sg:phone":"+1 870 703 5898",
    "sg:postcode":"71801",
    "sg:province":"AR",
    "wof:name":"Aflac",
    "wof:placetype":"venue"
},
  "geometry": {"coordinates":[-93.582443,33.668299],"type":"Point"}
}