{
  "type": "Feature",
  "properties": {
    "iso:country":"US",
    "sg:address":"504 E Jim Ford Rd",
    "sg:city":"Sherrill",
    "sg:classifiers":[
        {
            "category":"Manufacturing",
            "subcategory":"Food",
            "type":"Manufacturing & Wholesale Goods"
        }
    ],
    "sg:phone":"+1 870 766 8945",
    "sg:postcode":"72152",
    "sg:province":"AR",
    "sg:tags":[
        "product"
    ],
    "wof:name":"T J Bolin Farms",
    "wof:placetype":"venue"
},
  "geometry": {"coordinates":[-91.964923,34.379369],"type":"Point"}
}