{
  "type": "Feature",
  "properties": {
    "iso:country":"US",
    "sg:address":"147 Neely Ave",
    "sg:city":"Marion",
    "sg:classifiers":[
        {
            "category":"Professional",
            "subcategory":"Management & Consulting",
            "type":"Services"
        }
    ],
    "sg:phone":"+1 870 739 2220",
    "sg:postcode":"72364",
    "sg:province":"AR",
    "sg:tags":[
        "personnel",
        "consultant"
    ],
    "wof:name":"LSIA Total Staffing Co",
    "wof:placetype":"venue"
},
  "geometry": {"coordinates":[-90.200455,35.21455],"type":"Point"}
}