{
  "type": "Feature",
  "properties": {
    "addr:full":"86 Woodberry Ln Salem AR 72576",
    "addr:housenumber":"86",
    "addr:postcode":"72576",
    "addr:street":"Woodberry Ln",
    "iso:country":"US",
    "sg:address":"86 Woodberry Ln",
    "sg:city":"Salem",
    "sg:classifiers":[
        {
            "category":"Autos & Motor Vehicles",
            "subcategory":"Automobile Sales",
            "type":"Retail Goods"
        }
    ],
    "sg:phone":"+1 870 895 2102",
    "sg:postcode":"72576",
    "sg:province":"AR",
    "sg:tags":[
        "used"
    ],
    "wof:name":"Salem Car Store",
    "wof:placetype":"venue"
},
  "geometry": {"coordinates":[-91.77839,36.337811],"type":"Point"}
}