{
  "type": "Feature",
  "properties": {
    "iso:country":"US",
    "sg:address":"914 W B St",
    "sg:city":"Russellville",
    "sg:classifiers":[
        {
            "category":"Education",
            "subcategory":"Special Training",
            "type":"Public Place"
        }
    ],
    "sg:phone":"+1 479 967 9191",
    "sg:postcode":"72801",
    "sg:province":"AR",
    "sg:tags":[
        "instruction",
        "driving"
    ],
    "wof:name":"River Valley Driver Education",
    "wof:placetype":"venue"
},
  "geometry": {"coordinates":[-93.141554,35.281362],"type":"Point"}
}