{
  "type": "Feature",
  "properties": {
    "addr:full":"1509 S Arkansas Ave Russellville AR 72801",
    "addr:housenumber":"1509",
    "addr:postcode":"72801",
    "addr:street":"S Arkansas Ave",
    "iso:country":"US",
    "sg:address":"1509 S Arkansas Ave",
    "sg:city":"Russellville",
    "sg:classifiers":[
        {
            "category":"Autos & Motor Vehicles",
            "subcategory":"Automobile Sales",
            "type":"Retail Goods"
        }
    ],
    "sg:phone":"+1 479 890 8596",
    "sg:postcode":"72801",
    "sg:province":"AR",
    "sg:tags":[
        "car",
        "dealer"
    ],
    "wof:name":"B & G's Auto Sales",
    "wof:placetype":"venue"
},
  "geometry": {"coordinates":[-93.134186,35.264892],"type":"Point"}
}