{
  "type": "Feature",
  "properties": {
    "iso:country":"US",
    "sg:address":"700 W Capitol Ave",
    "sg:city":"Little Rock",
    "sg:classifiers":[
        {
            "category":"Government",
            "subcategory":"Office",
            "type":"Public Place"
        }
    ],
    "sg:phone":"+1 501 324 5246",
    "sg:postcode":"72201",
    "sg:province":"AR",
    "sg:tags":[
        "counsel",
        "general"
    ],
    "wof:name":"Office of General Counsel",
    "wof:placetype":"venue"
},
  "geometry": {"coordinates":[-92.279463,34.745284],"type":"Point"}
}