{
  "type": "Feature",
  "properties": {
    "iso:country":"US",
    "sg:address":"9811 Maumelle Blvd",
    "sg:city":"Maumelle",
    "sg:classifiers":[
        {
            "category":"Restaurant",
            "type":"Food & Drink"
        }
    ],
    "sg:menulink":"http://www.allmenus.com/ar/hill/61145-pasta-jacks/menu/",
    "sg:phone":"+1 501 753 6860",
    "sg:postcode":"72113",
    "sg:province":"AR",
    "sg:tags":[
        "italian"
    ],
    "wof:name":"Pasta Jack's",
    "wof:placetype":"venue"
},
  "geometry": {"coordinates":[-92.37063000000001,34.822334],"type":"Point"}
}