{
  "type": "Feature",
  "properties": {
    "addr:full":"2301 S Main St Hope AR 71801",
    "addr:housenumber":"2301",
    "addr:postcode":"71801",
    "addr:street":"S Main St",
    "iso:country":"US",
    "sg:address":"2301 S Main St",
    "sg:city":"Hope",
    "sg:classifiers":[
        {
            "category":"Shopping",
            "subcategory":"Bicycles & Sporting Goods",
            "type":"Retail Goods"
        }
    ],
    "sg:phone":"+1 870 777 3330",
    "sg:postcode":"71801",
    "sg:province":"AR",
    "wof:name":"Townsend Outdoors Inc",
    "wof:placetype":"venue"
},
  "geometry": {"coordinates":[-93.59171000000001,33.646076],"type":"Point"}
}