{
  "type": "Feature",
  "properties": {
    "iso:country":"US",
    "sg:address":"1101 Main St",
    "sg:city":"Crossett",
    "sg:classifiers":[
        {
            "category":"Banks & Credit Unions",
            "subcategory":"Bank",
            "type":"Services"
        }
    ],
    "sg:phone":"+1 870 304 3218",
    "sg:postcode":"71635",
    "sg:province":"AR",
    "sg:website":"www.cpmefcu.org",
    "wof:name":"CPMEFCU",
    "wof:placetype":"venue"
},
  "geometry": {"coordinates":[-91.961053,33.12131],"type":"Point"}
}