{
  "type": "Feature",
  "properties": {
    "iso:country":"US",
    "sg:address":"1911 W Parker Rd",
    "sg:city":"Jonesboro",
    "sg:classifiers":[
        {
            "category":"Health Services",
            "subcategory":"Optometrist",
            "type":"Services"
        },
        {
            "category":"Shopping",
            "subcategory":"Optical Goods",
            "type":"Retail Goods"
        }
    ],
    "sg:phone":"+1 870 910 5493",
    "sg:postcode":"72404",
    "sg:province":"AR",
    "sg:tags":[
        "lens",
        "contact"
    ],
    "wof:name":"Vision Care Consultants",
    "wof:placetype":"venue"
},
  "geometry": {"coordinates":[-90.739118,35.821925],"type":"Point"}
}