{
  "type": "Feature",
  "properties": {
    "iso:country":"US",
    "sg:address":"6679 Heber Springs Rd N",
    "sg:city":"Drasco",
    "sg:classifiers":[
        {
            "category":"Government",
            "subcategory":"Post Office",
            "type":"Public Place"
        }
    ],
    "sg:phone":"+1 870 668 3985",
    "sg:postcode":"72530",
    "sg:province":"AR",
    "wof:name":"US Post Office",
    "wof:placetype":"venue"
},
  "geometry": {"coordinates":[-91.947301,35.626104],"type":"Point"}
}