{
  "type": "Feature",
  "properties": {
    "addr:full":"10230 Sugar Creek Rd Bentonville AR 72712",
    "addr:housenumber":"10230",
    "addr:postcode":"72712",
    "addr:street":"Sugar Creek Rd",
    "iso:country":"US",
    "sg:address":"10230 Sugar Creek Rd",
    "sg:city":"Bentonville",
    "sg:classifiers":[
        {
            "category":"Building & Trades",
            "subcategory":"Construction",
            "type":"Services"
        }
    ],
    "sg:phone":"+1 479 254 1088",
    "sg:postcode":"72712",
    "sg:province":"AR",
    "sg:tags":[
        "roofing",
        "contractor"
    ],
    "wof:name":"J & M Roofing",
    "wof:placetype":"venue"
},
  "geometry": {"coordinates":[-94.141526,36.410259],"type":"Point"}
}