{
  "type": "Feature",
  "properties": {
    "iso:country":"US",
    "sg:address":"1673 US Hwy 371",
    "sg:city":"Prescott",
    "sg:classifiers":[
        {
            "category":"Autos & Motor Vehicles",
            "subcategory":"Fuel & Gas Station",
            "type":"Retail Goods"
        }
    ],
    "sg:phone":"+1 870 887 5811",
    "sg:postcode":"71857",
    "sg:province":"AR",
    "sg:tags":[
        "plaza",
        "truck",
        "stops"
    ],
    "wof:name":"Exit 44 Auto Truck Stop",
    "wof:placetype":"venue"
},
  "geometry": {"coordinates":[-93.425732,33.81057],"type":"Point"}
}