{
  "type": "Feature",
  "properties": {
    "addr:full":"9825 Crossroads Benton AR 72019",
    "addr:housenumber":"9825",
    "addr:postcode":"72019",
    "addr:street":"Crossroads",
    "iso:country":"US",
    "sg:address":"9825 Crossroads",
    "sg:city":"Benton",
    "sg:classifiers":[
        {
            "category":"Manufacturing",
            "subcategory":"Metals",
            "type":"Manufacturing & Wholesale Goods"
        }
    ],
    "sg:phone":"+1 501 776 2031",
    "sg:postcode":"72019",
    "sg:province":"AR",
    "sg:tags":[
        "tower"
    ],
    "wof:name":"SBA Towers",
    "wof:placetype":"venue"
},
  "geometry": {"coordinates":[-92.688661,34.536916],"type":"Point"}
}