{
  "type": "Feature",
  "properties": {
    "iso:country":"US",
    "sg:address":"4761 Malvern Rd",
    "sg:city":"Hot Springs",
    "sg:classifiers":[
        {
            "category":"Food & Beverages",
            "subcategory":"Liquor & Beverages",
            "type":"Retail Goods"
        }
    ],
    "sg:phone":"+1 501 262 3752",
    "sg:postcode":"71901",
    "sg:province":"AR",
    "wof:name":"Bud's Liquor Store",
    "wof:placetype":"venue"
},
  "geometry": {"coordinates":[-92.92587399999999,34.46545],"type":"Point"}
}