{
  "type": "Feature",
  "properties": {
    "iso:country":"US",
    "sg:address":"600 N Grant St",
    "sg:city":"Cabot",
    "sg:classifiers":[
        {
            "category":"Social Services",
            "type":"Services"
        }
    ],
    "sg:phone":"+1 501 843 2196",
    "sg:postcode":"72023",
    "sg:province":"AR",
    "sg:tags":[
        "senior",
        "citizen"
    ],
    "wof:name":"Cabot Senior Citizens Ctr",
    "wof:placetype":"venue"
},
  "geometry": {"coordinates":[-92.010575,34.977071],"type":"Point"}
}