{
  "type": "Feature",
  "properties": {
    "addr:full":"510 California Ave SW Camden AR 71701",
    "addr:housenumber":"510",
    "addr:postcode":"71701",
    "addr:street":"California Ave Sw",
    "iso:country":"US",
    "sg:address":"510 California Ave SW",
    "sg:city":"Camden",
    "sg:classifiers":[
        {
            "category":"Retail",
            "subcategory":"Self-service Laundry",
            "type":"Services"
        }
    ],
    "sg:phone":"+1 870 836 0527",
    "sg:postcode":"71701",
    "sg:province":"AR",
    "wof:name":"Camden Laundermatic",
    "wof:placetype":"venue"
},
  "geometry": {"coordinates":[-92.83393700000001,33.578906],"type":"Point"}
}