{
  "type": "Feature",
  "properties": {
    "iso:country":"US",
    "sg:address":"4241 Gabel Dr",
    "sg:city":"Fayetteville",
    "sg:classifiers":[
        {
            "category":"Organizations",
            "subcategory":"Religious Organization",
            "type":"Services"
        }
    ],
    "sg:phone":"+1 479 575 9025",
    "sg:postcode":"72703",
    "sg:province":"AR",
    "sg:tags":[
        "church"
    ],
    "wof:name":"Church Of Jesus Christ Of Lds",
    "wof:placetype":"venue"
},
  "geometry": {"coordinates":[-94.14189399999999,36.128764],"type":"Point"}
}