{
  "type": "Feature",
  "properties": {
    "iso:country":"US",
    "sg:address":"957 Highway 425 N",
    "sg:city":"Monticello",
    "sg:classifiers":[
        {
            "category":"Home & Garden",
            "subcategory":"Garden Supply",
            "type":"Retail Goods"
        },
        {
            "category":"Shopping",
            "subcategory":"Gifts & Souvenirs",
            "type":"Retail Goods"
        },
        {
            "category":"Shopping",
            "subcategory":"Crafts & Fabrics",
            "type":"Retail Goods"
        },
        {
            "category":"Shopping",
            "subcategory":"Florist",
            "type":"Retail Goods"
        }
    ],
    "sg:phone":"+1 870 367 6241",
    "sg:postcode":"71655",
    "sg:province":"AR",
    "sg:tags":[
        "plant",
        "etc-retail",
        "dried",
        "basket",
        "trees-silk",
        "flowers"
    ],
    "sg:website":"http://www.townandcountryfloristar.com",
    "wof:name":"Town & Country Florist",
    "wof:placetype":"venue"
},
  "geometry": {"coordinates":[-91.802702,33.655626],"type":"Point"}
}