{
  "type": "Feature",
  "properties": {
    "iso:country":"US",
    "sg:address":"404 S Pleasant St",
    "sg:city":"Springdale",
    "sg:classifiers":[
        {
            "category":"Real Estate",
            "subcategory":"Real Estate Operator",
            "type":"Services"
        }
    ],
    "sg:phone":"+1 479 751 0153",
    "sg:postcode":"72764",
    "sg:province":"AR",
    "sg:tags":[
        "building",
        "nonresidential"
    ],
    "wof:name":"Beth Properties LLC",
    "wof:placetype":"venue"
},
  "geometry": {"coordinates":[-94.143063,36.181521],"type":"Point"}
}