{
  "type": "Feature",
  "properties": {
    "iso:country":"US",
    "sg:address":"1411 Larkwood Dr",
    "sg:city":"Jonesboro",
    "sg:classifiers":[
        {
            "category":"Education",
            "subcategory":"Special Training",
            "type":"Public Place"
        }
    ],
    "sg:phone":"+1 870 931 6570",
    "sg:postcode":"72401",
    "sg:province":"AR",
    "sg:tags":[
        "instruction",
        "music"
    ],
    "sg:website":"www.kindermusikofjonesboro.com",
    "wof:name":"Kindermusik Of Jonesboro",
    "wof:placetype":"venue"
},
  "geometry": {"coordinates":[-90.67104,35.827205],"type":"Point"}
}