{
  "type": "Feature",
  "properties": {
    "addr:full":"2101 Carleton Pl Fort Smith AR 72908",
    "addr:housenumber":"2101",
    "addr:postcode":"72908",
    "addr:street":"Carleton Pl",
    "iso:country":"US",
    "sg:address":"2101 Carleton Pl",
    "sg:city":"Fort Smith",
    "sg:classifiers":[
        {
            "category":"Professional",
            "type":"Services"
        }
    ],
    "sg:phone":"+1 479 646 6281",
    "sg:postcode":"72908",
    "sg:province":"AR",
    "wof:name":"Gha Inc",
    "wof:placetype":"venue"
},
  "geometry": {"coordinates":[-94.413275,35.280873],"type":"Point"}
}