{
  "type": "Feature",
  "properties": {
    "iso:country":"US",
    "sg:address":"304 W Bond Ave",
    "sg:city":"West Memphis",
    "sg:classifiers":[
        {
            "category":"Banks & Credit Unions",
            "subcategory":"Investment Brokerage",
            "type":"Services"
        }
    ],
    "sg:phone":"+1 870 733 9980",
    "sg:postcode":"72301",
    "sg:province":"AR",
    "sg:tags":[
        "commodity",
        "contract"
    ],
    "wof:name":"Capstone Capital Management",
    "wof:placetype":"venue"
},
  "geometry": {"coordinates":[-90.190877,35.147919],"type":"Point"}
}