{
  "type": "Feature",
  "properties": {
    "addr:full":"1009 NW J St Bentonville AR 72712",
    "addr:housenumber":"1009",
    "addr:postcode":"72712",
    "addr:street":"Nw J St",
    "iso:country":"US",
    "sg:address":"1009 NW J St",
    "sg:city":"Bentonville",
    "sg:classifiers":[
        {
            "category":"Personal",
            "subcategory":"Beauty Salon",
            "type":"Services"
        }
    ],
    "sg:phone":"+1 479 464 4247",
    "sg:postcode":"72712",
    "sg:province":"AR",
    "wof:name":"Sarah's Styles",
    "wof:placetype":"venue"
},
  "geometry": {"coordinates":[-94.223039,36.384622],"type":"Point"}
}