{
  "type": "Feature",
  "properties": {
    "addr:full":"435 N Garland Ave Fayetteville AR 72701",
    "addr:housenumber":"435",
    "addr:postcode":"72701",
    "addr:street":"N Garland Ave",
    "iso:country":"US",
    "sg:address":"435 N Garland Ave",
    "sg:city":"Fayetteville",
    "sg:classifiers":[
        {
            "category":"Travel",
            "subcategory":"Travel Agent",
            "type":"Entertainment"
        }
    ],
    "sg:phone":"+1 479 575 9494",
    "sg:postcode":"72701",
    "sg:province":"AR",
    "sg:tags":[
        "agency",
        "bureau"
    ],
    "wof:name":"Travel Depot Inc",
    "wof:placetype":"venue"
},
  "geometry": {"coordinates":[-94.175742,36.068405],"type":"Point"}
}