{
  "type": "Feature",
  "properties": {
    "iso:country":"US",
    "sg:address":"1033 Ems Dr",
    "sg:city":"Batesville",
    "sg:classifiers":[
        {
            "category":"Health Services",
            "subcategory":"Hospital",
            "type":"Services"
        }
    ],
    "sg:phone":"+1 870 793 5708",
    "sg:postcode":"72501",
    "sg:province":"AR",
    "sg:tags":[
        "ambulance"
    ],
    "wof:name":"Link Vital",
    "wof:placetype":"venue"
},
  "geometry": {"coordinates":[-91.63838199999999,35.764561],"type":"Point"}
}