{
  "type": "Feature",
  "properties": {
    "iso:country":"US",
    "sg:address":"2615 N Prickett Rd",
    "sg:city":"Bryant",
    "sg:classifiers":[
        {
            "category":"Professional",
            "subcategory":"Lawyer & Legal Services",
            "type":"Services"
        }
    ],
    "sg:phone":"+1 501 847 5297",
    "sg:postcode":"72022",
    "sg:province":"AR",
    "sg:tags":[
        "attorney",
        "practice"
    ],
    "wof:name":"Levisee Lora",
    "wof:placetype":"venue"
},
  "geometry": {"coordinates":[-92.507003,34.617734],"type":"Point"}
}