{
  "type": "Feature",
  "properties": {
    "addr:full":"503 W Monroe Ave Lowell AR 72745",
    "addr:housenumber":"503",
    "addr:postcode":"72745",
    "addr:street":"W Monroe Ave",
    "iso:country":"US",
    "sg:address":"503 W Monroe Ave",
    "sg:city":"Lowell",
    "sg:classifiers":[
        {
            "category":"Restaurant",
            "type":"Food & Drink"
        }
    ],
    "sg:menulink":"http://www.allmenus.com/ar/cave-springs/190405-mcdonalds/menu/",
    "sg:postcode":"72745",
    "sg:province":"AR",
    "sg:tags":[
        "burger",
        "american"
    ],
    "wof:name":"McDonald's",
    "wof:placetype":"venue"
},
  "geometry": {"coordinates":[-94.145749,36.254319],"type":"Point"}
}