{
  "type": "Feature",
  "properties": {
    "addr:full":"1730 N West Ave El Dorado AR 71730",
    "addr:housenumber":"1730",
    "addr:postcode":"71730",
    "addr:street":"N West Ave",
    "iso:country":"US",
    "sg:address":"1730 N West Ave",
    "sg:city":"El Dorado",
    "sg:classifiers":[
        {
            "category":"Restaurant",
            "type":"Food & Drink"
        }
    ],
    "sg:menulink":"http://www.allmenus.com/ar/el-dorado/190352-mcdonalds/menu/",
    "sg:postcode":"71730",
    "sg:province":"AR",
    "sg:tags":[
        "burger",
        "american"
    ],
    "wof:name":"McDonald's",
    "wof:placetype":"venue"
},
  "geometry": {"coordinates":[-92.66544,33.234747],"type":"Point"}
}