{
  "type": "Feature",
  "properties": {
    "iso:country":"US",
    "sg:address":"414 W Laurel Ave",
    "sg:city":"Lowell",
    "sg:classifiers":[
        {
            "category":"Professional",
            "subcategory":"Management & Consulting",
            "type":"Services"
        }
    ],
    "sg:phone":"+1 479 636 2769",
    "sg:postcode":"72758",
    "sg:province":"AR",
    "sg:tags":[
        "business"
    ],
    "wof:name":"Speer Consulting Inc",
    "wof:placetype":"venue"
},
  "geometry": {"coordinates":[-94.140341,36.290231],"type":"Point"}
}