{
  "type": "Feature",
  "properties": {
    "iso:country":"US",
    "sg:address":"811 Hamilton Dairy Rd",
    "sg:city":"Hot Springs National",
    "sg:classifiers":[
        {
            "category":"Professional",
            "type":"Services"
        }
    ],
    "sg:phone":"+1 501 625 3794",
    "sg:postcode":"71909",
    "sg:province":"AR",
    "wof:name":"James Gage",
    "wof:placetype":"venue"
},
  "geometry": {"coordinates":[-92.980413,34.593233],"type":"Point"}
}