{
  "type": "Feature",
  "properties": {
    "addr:full":"1227 Military Rd Benton AR 72015",
    "addr:housenumber":"1227",
    "addr:postcode":"72015",
    "addr:street":"Military Rd",
    "iso:country":"US",
    "sg:address":"1227 Military Rd",
    "sg:city":"Benton",
    "sg:classifiers":[
        {
            "category":"Insurance",
            "subcategory":"Insurance Agent",
            "type":"Services"
        }
    ],
    "sg:phone":"+1 501 776 2560",
    "sg:postcode":"72015",
    "sg:province":"AR",
    "wof:name":"Allstate Insurance Co",
    "wof:placetype":"venue"
},
  "geometry": {"coordinates":[-92.57670400000001,34.57699],"type":"Point"}
}