{
  "type": "Feature",
  "properties": {
    "iso:country":"US",
    "sg:address":"310 S Main St",
    "sg:city":"Berryville",
    "sg:classifiers":[
        {
            "category":"Health Services",
            "subcategory":"Health Practitioner",
            "type":"Services"
        }
    ],
    "sg:phone":"+1 870 423 6801",
    "sg:postcode":"72616",
    "sg:province":"AR",
    "sg:tags":[
        "therapist",
        "physical"
    ],
    "wof:name":"HPT Inc",
    "wof:placetype":"venue"
},
  "geometry": {"coordinates":[-93.566175,36.362385],"type":"Point"}
}