{
  "type": "Feature",
  "properties": {
    "addr:full":"2916 Parkwood Dr Rogers AR 72756",
    "addr:housenumber":"2916",
    "addr:postcode":"72756",
    "addr:street":"Parkwood Dr",
    "iso:country":"US",
    "sg:address":"2916 Parkwood Dr",
    "sg:city":"Rogers",
    "sg:classifiers":[
        {
            "category":"Home & Garden",
            "subcategory":"Building Materials",
            "type":"Retail Goods"
        }
    ],
    "sg:phone":"+1 479 640 0214",
    "sg:postcode":"72756",
    "sg:province":"AR",
    "sg:tags":[
        "stone"
    ],
    "wof:name":"Diamond Stone Inc",
    "wof:placetype":"venue"
},
  "geometry": {"coordinates":[-94.15807,36.33802],"type":"Point"}
}