{
  "type": "Feature",
  "properties": {
    "iso:country":"US",
    "sg:address":"801 N Mississippi St",
    "sg:city":"Little Rock",
    "sg:classifiers":[
        {
            "category":"Communications",
            "subcategory":"Film & Video Production",
            "type":"Services"
        }
    ],
    "sg:phone":"+1 501 666 3778",
    "sg:postcode":"72205",
    "sg:province":"AR",
    "sg:tags":[
        "motion"
    ],
    "wof:name":"Corporate Care",
    "wof:placetype":"venue"
},
  "geometry": {"coordinates":[-92.358559,34.760073],"type":"Point"}
}