{
  "type": "Feature",
  "properties": {
    "iso:country":"US",
    "sg:address":"3801 John F Kennedy Blvd",
    "sg:city":"Sherwood",
    "sg:classifiers":[
        {
            "category":"Education",
            "subcategory":"School",
            "type":"Public Place"
        }
    ],
    "sg:phone":"+1 501 771 8175",
    "sg:postcode":"72116",
    "sg:province":"AR",
    "wof:name":"Park Hill Elementary School",
    "wof:placetype":"venue"
},
  "geometry": {"coordinates":[-92.25979100000001,34.791891],"type":"Point"}
}