{
  "type": "Feature",
  "properties": {
    "iso:country":"US",
    "sg:address":"2737 N College Ave",
    "sg:city":"Fayetteville",
    "sg:classifiers":[
        {
            "category":"Home & Garden",
            "subcategory":"Building Materials",
            "type":"Retail Goods"
        }
    ],
    "sg:phone":"+1 479 575 0011",
    "sg:postcode":"72703",
    "sg:province":"AR",
    "sg:tags":[
        "paint",
        "industrial",
        "equipment"
    ],
    "wof:name":"Sterling Paint Ctr",
    "wof:placetype":"venue"
},
  "geometry": {"coordinates":[-94.149689,36.100771],"type":"Point"}
}