{
  "type": "Feature",
  "properties": {
    "addr:full":"600 Pepperbox Rd Mountain View AR 72560",
    "addr:housenumber":"600",
    "addr:postcode":"72560",
    "addr:street":"Pepperbox Rd",
    "iso:country":"US",
    "sg:address":"600 Pepperbox Rd",
    "sg:city":"Mountain View",
    "sg:classifiers":[
        {
            "category":"Professional",
            "type":"Services"
        }
    ],
    "sg:phone":"+1 870 269 7500",
    "sg:postcode":"72560",
    "sg:province":"AR",
    "sg:tags":[
        "establishment"
    ],
    "wof:name":"Magic Network",
    "wof:placetype":"venue"
},
  "geometry": {"coordinates":[-92.04177799999999,35.739937],"type":"Point"}
}