{
  "type": "Feature",
  "properties": {
    "iso:country":"US",
    "sg:address":"708 S Thompson St",
    "sg:city":"Springdale",
    "sg:classifiers":[
        {
            "category":"Food & Beverages",
            "subcategory":"Bakery",
            "type":"Retail Goods"
        }
    ],
    "sg:phone":"+1 479 872 1003",
    "sg:postcode":"72764",
    "sg:province":"AR",
    "wof:name":"El Progresso Bakery",
    "wof:placetype":"venue"
},
  "geometry": {"coordinates":[-94.13884400000001,36.178792],"type":"Point"}
}