{
  "type": "Feature",
  "properties": {
    "iso:country":"US",
    "sg:address":"4915 S Thompson St",
    "sg:city":"Springdale",
    "sg:classifiers":[
        {
            "category":"Shopping",
            "subcategory":"Bicycles & Sporting Goods",
            "type":"Retail Goods"
        },
        {
            "category":"Shopping",
            "subcategory":"Clothing, Apparel, & Fashions",
            "type":"Retail Goods"
        }
    ],
    "sg:phone":"+1 479 756 1344",
    "sg:postcode":"72764",
    "sg:province":"AR",
    "sg:tags":[
        "equipment",
        "camping"
    ],
    "wof:name":"Lewis & Clark Outfitters",
    "wof:placetype":"venue"
},
  "geometry": {"coordinates":[-94.144119,36.142382],"type":"Point"}
}