{
  "type": "Feature",
  "properties": {
    "iso:country":"US",
    "sg:address":"304 S Gee St",
    "sg:city":"Jonesboro",
    "sg:classifiers":[
        {
            "category":"Shopping",
            "subcategory":"Used Merchandise",
            "type":"Retail Goods"
        },
        {
            "category":"Shopping",
            "subcategory":"Hobbies, Toys, & Games",
            "type":"Retail Goods"
        }
    ],
    "sg:phone":"+1 870 972 0644",
    "sg:postcode":"72401",
    "sg:province":"AR",
    "sg:tags":[
        "flea",
        "business",
        "market"
    ],
    "wof:name":"Gee Street Craft & Antiq Mall",
    "wof:placetype":"venue"
},
  "geometry": {"coordinates":[-90.725596,35.840365],"type":"Point"}
}