{
  "type": "Feature",
  "properties": {
    "iso:country":"US",
    "sg:address":"802 E Faulkner St",
    "sg:city":"El Dorado",
    "sg:classifiers":[
        {
            "category":"Personal",
            "subcategory":"Beauty Salon",
            "type":"Services"
        }
    ],
    "sg:phone":"+1 870 881 0110",
    "sg:postcode":"71730",
    "sg:province":"AR",
    "sg:tags":[
        "shop"
    ],
    "wof:name":"Flawless Images Beauty & Barbe",
    "wof:placetype":"venue"
},
  "geometry": {"coordinates":[-92.656047,33.214593],"type":"Point"}
}