{
  "type": "Feature",
  "properties": {
    "addr:full":"8603 Hercules Dr Jacksonville AR 72076",
    "addr:housenumber":"8603",
    "addr:postcode":"72076",
    "addr:street":"Hercules Dr",
    "iso:country":"US",
    "sg:address":"8603 Hercules Dr",
    "sg:city":"Jacksonville",
    "sg:classifiers":[
        {
            "category":"Building & Trades",
            "subcategory":"Electrical",
            "type":"Services"
        }
    ],
    "sg:phone":"+1 501 988 5173",
    "sg:postcode":"72076",
    "sg:province":"AR",
    "sg:tags":[
        "electrical",
        "contractor"
    ],
    "wof:name":"Clements Electric",
    "wof:placetype":"venue"
},
  "geometry": {"coordinates":[-92.130286,34.944433],"type":"Point"}
}