{
  "type": "Feature",
  "properties": {
    "addr:full":"646 S Harkrider St Conway AR 72032",
    "addr:housenumber":"646",
    "addr:postcode":"72032",
    "addr:street":"S Harkrider St",
    "iso:country":"US",
    "sg:address":"646 S Harkrider St",
    "sg:city":"Conway",
    "sg:classifiers":[
        {
            "category":"Restaurant",
            "type":"Food & Drink"
        }
    ],
    "sg:menulink":"http://www.allmenus.com/ar/cadron/111584-subway/menu/",
    "sg:phone":"+1 501 327 4949",
    "sg:postcode":"72032",
    "sg:province":"AR",
    "sg:tags":[
        "american",
        "sandwich"
    ],
    "wof:name":"Subway",
    "wof:placetype":"venue"
},
  "geometry": {"coordinates":[-92.430995,35.069509],"type":"Point"}
}