{
  "type": "Feature",
  "properties": {
    "iso:country":"US",
    "sg:address":"12310 Arch St",
    "sg:city":"Little Rock",
    "sg:classifiers":[
        {
            "category":"Autos & Motor Vehicles",
            "subcategory":"Automobile Sales",
            "type":"Retail Goods"
        }
    ],
    "sg:phone":"+1 501 888 1237",
    "sg:postcode":"72206",
    "sg:province":"AR",
    "sg:tags":[
        "car",
        "dealer"
    ],
    "wof:name":"J Y Auto Sales",
    "wof:placetype":"venue"
},
  "geometry": {"coordinates":[-92.31074700000001,34.637826],"type":"Point"}
}