{
  "type": "Feature",
  "properties": {
    "addr:full":"1916 Race St Jonesboro AR 72401",
    "addr:housenumber":"1916",
    "addr:postcode":"72401",
    "addr:street":"Race St",
    "iso:country":"US",
    "sg:address":"1916 Race St",
    "sg:city":"Jonesboro",
    "sg:classifiers":[
        {
            "category":"Arena",
            "subcategory":"Sports Club",
            "type":"Entertainment"
        }
    ],
    "sg:phone":"+1 870 932 0140",
    "sg:postcode":"72401",
    "sg:province":"AR",
    "sg:tags":[
        "health"
    ],
    "sg:website":"http://www.thetrimgym.com",
    "wof:name":"Trim Gym Health & Fitness Club",
    "wof:placetype":"venue"
},
  "geometry": {"coordinates":[-90.68208300000001,35.814004],"type":"Point"}
}