{
  "type": "Feature",
  "properties": {
    "addr:full":"306 N Missouri St West Memphis AR 72301",
    "addr:housenumber":"306",
    "addr:postcode":"72301",
    "addr:street":"N Missouri St",
    "iso:country":"US",
    "sg:address":"306 N Missouri St",
    "sg:city":"West Memphis",
    "sg:classifiers":[
        {
            "category":"Wholesale",
            "subcategory":"Electrical",
            "type":"Manufacturing & Wholesale Goods"
        }
    ],
    "sg:phone":"+1 870 735 4123",
    "sg:postcode":"72301",
    "sg:province":"AR",
    "sg:tags":[
        "communication",
        "facsimile",
        "equipment"
    ],
    "wof:name":"Douglas Business Machines",
    "wof:placetype":"venue"
},
  "geometry": {"coordinates":[-90.18485699999999,35.149325],"type":"Point"}
}