{
  "type": "Feature",
  "properties": {
    "iso:country":"US",
    "sg:address":"389 High Point Rd",
    "sg:city":"Hattieville",
    "sg:classifiers":[
        {
            "category":"Farming",
            "subcategory":"Farm & Veterinary Services",
            "type":"Manufacturing & Wholesale Goods"
        }
    ],
    "sg:phone":"+1 501 354 4010",
    "sg:postcode":"72063",
    "sg:province":"AR",
    "sg:tags":[
        "livestock"
    ],
    "wof:name":"James Sponer Poultry Farm",
    "wof:placetype":"venue"
},
  "geometry": {"coordinates":[-92.740936,35.315956],"type":"Point"}
}