{
  "type": "Feature",
  "properties": {
    "iso:country":"US",
    "sg:address":"110 Main St",
    "sg:city":"Crossett",
    "sg:classifiers":[
        {
            "category":"Shopping",
            "subcategory":"Pharmacy",
            "type":"Retail Goods"
        }
    ],
    "sg:phone":"+1 870 364 4141",
    "sg:postcode":"71635",
    "sg:province":"AR",
    "wof:name":"Spikes Drug Store",
    "wof:placetype":"venue"
},
  "geometry": {"coordinates":[-91.961508,33.135172],"type":"Point"}
}