{
  "type": "Feature",
  "properties": {
    "addr:full":"110 Main St Crossett AR 71635",
    "addr:housenumber":"110",
    "addr:postcode":"71635",
    "addr:street":"Main St",
    "iso:country":"US",
    "sg:address":"110 Main St",
    "sg:city":"Crossett",
    "sg:classifiers":[
        {
            "category":"Shopping",
            "subcategory":"Pharmacy",
            "type":"Retail Goods"
        }
    ],
    "sg:phone":"+1 870 364 4141",
    "sg:postcode":"71635",
    "sg:province":"AR",
    "wof:name":"Spikes Drug Store",
    "wof:placetype":"venue"
},
  "geometry": {"coordinates":[-91.96150799999999,33.135172],"type":"Point"}
}