{
  "type": "Feature",
  "properties": {
    "addr:full":"2818 W Lawson Rd Alexander AR 72002",
    "addr:housenumber":"2818",
    "addr:postcode":"72002",
    "addr:street":"W Lawson Rd",
    "iso:country":"US",
    "sg:address":"2818 W Lawson Rd",
    "sg:city":"Alexander",
    "sg:classifiers":[
        {
            "category":"Professional",
            "type":"Services"
        }
    ],
    "sg:phone":"+1 501 316 1155",
    "sg:postcode":"72002",
    "sg:province":"AR",
    "wof:name":"Conrad Trach Service",
    "wof:placetype":"venue"
},
  "geometry": {"coordinates":[-92.590952,34.708494],"type":"Point"}
}