{
  "type": "Feature",
  "properties": {
    "addr:full":"307 S Thompson St Ste C Springdale AR 72764",
    "addr:housenumber":"307",
    "addr:postcode":"72764",
    "addr:street":"S Thompson St Ste C",
    "iso:country":"US",
    "sg:address":"307 S Thompson St Ste C",
    "sg:city":"Springdale",
    "sg:classifiers":[
        {
            "category":"Health Services",
            "subcategory":"Doctor",
            "type":"Services"
        }
    ],
    "sg:phone":"+1 479 751 6004",
    "sg:postcode":"72764",
    "sg:province":"AR",
    "sg:tags":[
        "physician",
        "kidneys",
        "surgeons",
        "nephrology"
    ],
    "sg:website":"www.arkansaskidneyconsultants.com",
    "wof:name":"Arkansas Kidney Consultants",
    "wof:placetype":"venue"
},
  "geometry": {"coordinates":[-94.138424,36.183405],"type":"Point"}
}