{
  "type": "Feature",
  "properties": {
    "iso:country":"US",
    "sg:address":"8889 Kennedy Rd",
    "sg:city":"Rogers",
    "sg:classifiers":[
        {
            "category":"Building & Trades",
            "subcategory":"Construction",
            "type":"Services"
        },
        {
            "category":"Building & Trades",
            "subcategory":"Plumbing",
            "type":"Services"
        }
    ],
    "sg:phone":"+1 479 925 7071",
    "sg:postcode":"72758",
    "sg:province":"AR",
    "sg:tags":[
        "mechanical",
        "nonresidential",
        "contractor"
    ],
    "wof:name":"Lakeview Plumbing Inc",
    "wof:placetype":"venue"
},
  "geometry": {"coordinates":[-94.070525,36.308346],"type":"Point"}
}