{
  "type": "Feature",
  "properties": {
    "addr:full":"544 W Hillsboro St El Dorado AR 71730",
    "addr:housenumber":"544",
    "addr:postcode":"71730",
    "addr:street":"W Hillsboro St",
    "iso:country":"US",
    "sg:address":"544 W Hillsboro St",
    "sg:city":"El Dorado",
    "sg:classifiers":[
        {
            "category":"Shopping",
            "subcategory":"Jewelry",
            "type":"Retail Goods"
        }
    ],
    "sg:phone":"+1 870 862 0271",
    "sg:postcode":"71730",
    "sg:province":"AR",
    "sg:tags":[
        "jeweler"
    ],
    "wof:name":"Cole's Jewelers & Mfg",
    "wof:placetype":"venue"
},
  "geometry": {"coordinates":[-92.66965500000001,33.207488],"type":"Point"}
}