{
  "type": "Feature",
  "properties": {
    "iso:country":"US",
    "sg:address":"14503 Single Pine Dr",
    "sg:city":"Mabelvale",
    "sg:classifiers":[
        {
            "category":"Social Services",
            "subcategory":"Child Care",
            "type":"Services"
        }
    ],
    "sg:phone":"+1 501 455 2818",
    "sg:postcode":"72103",
    "sg:province":"AR",
    "sg:tags":[
        "nursery",
        "day"
    ],
    "wof:name":"Medical Learning",
    "wof:placetype":"venue"
},
  "geometry": {"coordinates":[-92.397676,34.619304],"type":"Point"}
}