{
  "type": "Feature",
  "properties": {
    "addr:full":"1001 Shaver St Springdale AR 72762",
    "addr:housenumber":"1001",
    "addr:postcode":"72762",
    "addr:street":"Shaver St",
    "iso:country":"US",
    "sg:address":"1001 Shaver St",
    "sg:city":"Springdale",
    "sg:classifiers":[
        {
            "category":"Manufacturing",
            "subcategory":"Metals",
            "type":"Manufacturing & Wholesale Goods"
        },
        {
            "category":"Manufacturing",
            "subcategory":"Tools & Machinery",
            "type":"Manufacturing & Wholesale Goods"
        }
    ],
    "sg:phone":"+1 479 751 2727",
    "sg:postcode":"72762",
    "sg:province":"AR",
    "sg:tags":[
        "poultry",
        "equipment",
        "structural",
        "fabrication",
        "supply"
    ],
    "wof:name":"American Pellet Mill Services",
    "wof:placetype":"venue"
},
  "geometry": {"coordinates":[-94.17042600000001,36.177692],"type":"Point"}
}