{
  "type": "Feature",
  "properties": {
    "iso:country":"US",
    "sg:address":"600 W Broadway",
    "sg:city":"Spiro",
    "sg:classifiers":[
        {
            "category":"Education",
            "subcategory":"School",
            "type":"Public Place"
        }
    ],
    "sg:phone":"+1 918 962 2463",
    "sg:postcode":"74959",
    "sg:province":"OK",
    "wof:name":"Spiro Public School Office",
    "wof:placetype":"venue"
},
  "geometry": {"coordinates":[-94.626232,35.241002],"type":"Point"}
}