{
  "type": "Feature",
  "properties": {
    "iso:country":"US",
    "sg:address":"618 S Main St",
    "sg:city":"Pine Bluff",
    "sg:classifiers":[
        {
            "category":"Professional",
            "subcategory":"Accounting & Tax Preparation",
            "type":"Services"
        }
    ],
    "sg:phone":"+1 870 535 8476",
    "sg:postcode":"71601",
    "sg:province":"AR",
    "sg:tags":[
        "accountant"
    ],
    "wof:name":"Lee & Co Pa",
    "wof:placetype":"venue"
},
  "geometry": {"coordinates":[-92.003493,34.2219],"type":"Point"}
}