{
  "type": "Feature",
  "properties": {
    "addr:full":"3511 E Race Ave Searcy AR 72143",
    "addr:housenumber":"3511",
    "addr:postcode":"72143",
    "addr:street":"E Race Ave",
    "iso:country":"US",
    "sg:address":"3511 E Race Ave",
    "sg:city":"Searcy",
    "sg:classifiers":[
        {
            "category":"Shopping",
            "subcategory":"Shoes",
            "type":"Retail Goods"
        }
    ],
    "sg:phone":"+1 501 268 5057",
    "sg:postcode":"72143",
    "sg:province":"AR",
    "wof:name":"Shoe Department",
    "wof:placetype":"venue"
},
  "geometry": {"coordinates":[-91.69422900000001,35.250431],"type":"Point"}
}