{
  "type": "Feature",
  "properties": {
    "iso:country":"US",
    "sg:address":"1401 Snow Ln",
    "sg:city":"Alexander",
    "sg:classifiers":[
        {
            "category":"Retail",
            "subcategory":"Repair Shop",
            "type":"Services"
        }
    ],
    "sg:phone":"+1 501 316 1946",
    "sg:postcode":"72002",
    "sg:province":"AR",
    "sg:tags":[
        "welding"
    ],
    "wof:name":"Naylors Welding & Fabrication",
    "wof:placetype":"venue"
},
  "geometry": {"coordinates":[-92.565826,34.665454],"type":"Point"}
}