{
  "type": "Feature",
  "properties": {
    "iso:country":"US",
    "sg:address":"601 Howard St",
    "sg:city":"Pocola",
    "sg:classifiers":[
        {
            "category":"Building & Trades",
            "subcategory":"Construction",
            "type":"Services"
        }
    ],
    "sg:phone":"+1 918 436 2882",
    "sg:postcode":"74902",
    "sg:province":"OK",
    "sg:tags":[
        "carpentry",
        "contractor"
    ],
    "wof:name":"M & D Cabinet Works",
    "wof:placetype":"venue"
},
  "geometry": {"coordinates":[-94.481245,35.274356],"type":"Point"}
}