{
  "type": "Feature",
  "properties": {
    "iso:country":"US",
    "sg:address":"315 Jackman St",
    "sg:city":"Benton",
    "sg:classifiers":[
        {
            "category":"Personal",
            "subcategory":"Beauty Salon",
            "type":"Services"
        }
    ],
    "sg:phone":"+1 501 778 8979",
    "sg:postcode":"72015",
    "sg:province":"AR",
    "sg:tags":[
        "shop"
    ],
    "wof:name":"Bowers Beauty Shop",
    "wof:placetype":"venue"
},
  "geometry": {"coordinates":[-92.59172599999999,34.557938],"type":"Point"}
}