{
  "type": "Feature",
  "properties": {
    "iso:country":"US",
    "sg:address":"16 Tortoise Park Cove",
    "sg:city":"Little Rock",
    "sg:classifiers":[
        {
            "category":"Social Services",
            "type":"Services"
        }
    ],
    "sg:phone":"+1 501 223 8727",
    "sg:postcode":"72211",
    "sg:province":"AR",
    "sg:tags":[
        "counselor",
        "marriage",
        "family"
    ],
    "wof:name":"Counseling Centers",
    "wof:placetype":"venue"
},
  "geometry": {"coordinates":[-92.407664,34.763337],"type":"Point"}
}