{
  "type": "Feature",
  "properties": {
    "iso:country":"US",
    "sg:address":"415 Francis Ln",
    "sg:city":"Charleston",
    "sg:classifiers":[
        {
            "category":"Professional",
            "subcategory":"Art Services",
            "type":"Services"
        }
    ],
    "sg:phone":"+1 479 965 0253",
    "sg:postcode":"72933",
    "sg:province":"AR",
    "sg:tags":[
        "taxidermist"
    ],
    "wof:name":"Taxidermy Unlimited",
    "wof:placetype":"venue"
},
  "geometry": {"coordinates":[-94.049122,35.294061],"type":"Point"}
}