{
  "type": "Feature",
  "properties": {
    "iso:country":"US",
    "sg:address":"5317 W 65th St",
    "sg:city":"Little Rock",
    "sg:classifiers":[
        {
            "category":"Wholesale",
            "subcategory":"Groceries",
            "type":"Manufacturing & Wholesale Goods"
        }
    ],
    "sg:phone":"+1 501 565 3395",
    "sg:postcode":"72209",
    "sg:province":"AR",
    "sg:tags":[
        "tortilla"
    ],
    "wof:name":"Tortilla Brenda",
    "wof:placetype":"venue"
},
  "geometry": {"coordinates":[-92.3383,34.690424],"type":"Point"}
}