{
  "type": "Feature",
  "properties": {
    "iso:country":"US",
    "sg:address":"142 Randall Dr",
    "sg:city":"Jacksonville",
    "sg:classifiers":[
        {
            "category":"Shopping",
            "subcategory":"Clothing, Apparel, & Fashions",
            "type":"Retail Goods"
        }
    ],
    "sg:phone":"+1 501 960 1784",
    "sg:postcode":"72076",
    "sg:province":"AR",
    "wof:name":"Fancy Fines LLC",
    "wof:placetype":"venue"
},
  "geometry": {"coordinates":[-92.183425,34.874967],"type":"Point"}
}