{
  "type": "Feature",
  "properties": {
    "addr:full":"310 W Union Ave Wynne AR 72396",
    "addr:housenumber":"310",
    "addr:postcode":"72396",
    "addr:street":"W Union Ave",
    "iso:country":"US",
    "sg:address":"310 W Union Ave",
    "sg:city":"Wynne",
    "sg:classifiers":[
        {
            "category":"Autos & Motor Vehicles",
            "subcategory":"Automobile Sales",
            "type":"Retail Goods"
        }
    ],
    "sg:phone":"+1 870 208 8528",
    "sg:postcode":"72396",
    "sg:province":"AR",
    "sg:tags":[
        "used"
    ],
    "wof:name":"Smith Owens Auto Sales",
    "wof:placetype":"venue"
},
  "geometry": {"coordinates":[-90.794038,35.223637],"type":"Point"}
}