{
  "type": "Feature",
  "properties": {
    "addr:full":"5653 Highway 165 S Gillett AR 72055",
    "addr:housenumber":"5653",
    "addr:postcode":"72055",
    "addr:street":"Highway 165 S Gillett",
    "iso:country":"US",
    "sg:address":"5653 Highway 165 S",
    "sg:city":"Gillett",
    "sg:classifiers":[
        {
            "category":"Autos & Motor Vehicles",
            "subcategory":"Automobile Sales",
            "type":"Retail Goods"
        }
    ],
    "sg:phone":"+1 870 548 2441",
    "sg:postcode":"72055",
    "sg:province":"AR",
    "sg:tags":[
        "dealers-used",
        "car",
        "used",
        "cars-wholesale",
        "new"
    ],
    "wof:name":"King's Auto Sales",
    "wof:placetype":"venue"
},
  "geometry": {"coordinates":[-91.384567,33.983744],"type":"Point"}
}