{
  "type": "Feature",
  "properties": {
    "addr:full":"1620 Middle Rd Conway AR 72032",
    "addr:housenumber":"1620",
    "addr:postcode":"72032",
    "addr:street":"Middle Rd",
    "iso:country":"US",
    "sg:address":"1620 Middle Rd",
    "sg:city":"Conway",
    "sg:classifiers":[
        {
            "category":"Professional",
            "type":"Services"
        },
        {
            "category":"Real Estate",
            "subcategory":"Real Estate Operator",
            "type":"Services"
        }
    ],
    "sg:phone":"+1 501 548 6268",
    "sg:postcode":"72032",
    "sg:province":"AR",
    "sg:tags":[
        "apartment"
    ],
    "wof:name":"Oak Grove Commons",
    "wof:placetype":"venue"
},
  "geometry": {"coordinates":[-92.40452500000001,35.076655],"type":"Point"}
}