{
  "type": "Feature",
  "properties": {
    "iso:country":"US",
    "sg:address":"901 E Broadway St",
    "sg:city":"Morrilton",
    "sg:classifiers":[
        {
            "category":"Government",
            "subcategory":"Fire Station",
            "type":"Public Place"
        }
    ],
    "sg:phone":"+1 501 354 3113",
    "sg:postcode":"72110",
    "sg:province":"AR",
    "sg:tags":[
        "protection"
    ],
    "wof:name":"Plumerville-City of",
    "wof:placetype":"venue"
},
  "geometry": {"coordinates":[-92.734972,35.1519],"type":"Point"}
}