{
  "type": "Feature",
  "properties": {
    "iso:country":"US",
    "sg:address":"2010 Ridgway Rd",
    "sg:city":"Pine Bluff",
    "sg:classifiers":[
        {
            "category":"Food & Beverages",
            "subcategory":"Groceries & Convenience Stores",
            "type":"Retail Goods"
        }
    ],
    "sg:phone":"+1 870 536 3003",
    "sg:postcode":"71603",
    "sg:province":"AR",
    "wof:name":"Cornerstop",
    "wof:placetype":"venue"
},
  "geometry": {"coordinates":[-92.030928,34.165319],"type":"Point"}
}