{
  "type": "Feature",
  "properties": {
    "iso:country":"US",
    "sg:address":"1210 Hot Springs Hwy",
    "sg:city":"Benton",
    "sg:classifiers":[
        {
            "category":"Government",
            "subcategory":"Office",
            "type":"Public Place"
        }
    ],
    "sg:phone":"+1 501 778 3671",
    "sg:postcode":"72019",
    "sg:province":"AR",
    "sg:tags":[
        "federal"
    ],
    "wof:name":"Natural Resources Conservation",
    "wof:placetype":"venue"
},
  "geometry": {"coordinates":[-92.590388,34.573538],"type":"Point"}
}