{
  "type": "Feature",
  "properties": {
    "iso:country":"US",
    "sg:address":"275 W Kiehl Ave",
    "sg:city":"Sherwood",
    "sg:classifiers":[
        {
            "category":"Insurance",
            "subcategory":"Insurance Agent",
            "type":"Services"
        }
    ],
    "sg:phone":"+1 501 834 4001",
    "sg:postcode":"72120",
    "sg:province":"AR",
    "wof:name":"James Greene & Assoc",
    "wof:placetype":"venue"
},
  "geometry": {"coordinates":[-92.23443899999999,34.833293],"type":"Point"}
}