{
  "type": "Feature",
  "properties": {
    "iso:country":"US",
    "sg:address":"65 State Hwy 1",
    "sg:city":"Colt",
    "sg:classifiers":[
        {
            "category":"Building & Trades",
            "subcategory":"Equipment Rental",
            "type":"Services"
        }
    ],
    "sg:phone":"+1 870 238 7062",
    "sg:postcode":"72326",
    "sg:province":"AR",
    "wof:name":"AAA Rent All & Sales Inc",
    "wof:placetype":"venue"
},
  "geometry": {"coordinates":[-90.80237,35.151749],"type":"Point"}
}