{
  "type": "Feature",
  "properties": {
    "addr:full":"1155 W 6th St Fayetteville AR 72701",
    "addr:housenumber":"1155",
    "addr:postcode":"72701",
    "addr:street":"W 6Th St",
    "iso:country":"US",
    "sg:address":"1155 W 6th St",
    "sg:city":"Fayetteville",
    "sg:classifiers":[
        {
            "category":"Professional",
            "subcategory":"Lawyer & Legal Services",
            "type":"Services"
        }
    ],
    "sg:phone":"+1 479 443 7660",
    "sg:postcode":"72701",
    "sg:province":"AR",
    "wof:name":"Rita G Hempen Attorney",
    "wof:placetype":"venue"
},
  "geometry": {"coordinates":[-94.17671300000001,36.056738],"type":"Point"}
}