{
  "type": "Feature",
  "properties": {
    "iso:country":"US",
    "sg:address":"2126 N 1st St",
    "sg:city":"Jacksonville",
    "sg:classifiers":[
        {
            "category":"Shopping",
            "subcategory":"Shoes",
            "type":"Retail Goods"
        }
    ],
    "sg:phone":"+1 501 982 7300",
    "sg:postcode":"72076",
    "sg:province":"AR",
    "wof:name":"Wings N Things/Jacksonville AR",
    "wof:placetype":"venue"
},
  "geometry": {"coordinates":[-92.109476,34.881163],"type":"Point"}
}