{
  "type": "Feature",
  "properties": {
    "iso:country":"US",
    "sg:address":"11 Lancaster Ln",
    "sg:city":"Conway",
    "sg:classifiers":[
        {
            "category":"Recreation",
            "subcategory":"Sailing Club",
            "type":"Entertainment"
        }
    ],
    "sg:phone":"+1 501 450 6424",
    "sg:postcode":"72032",
    "sg:province":"AR",
    "sg:tags":[
        "caster",
        "glide"
    ],
    "wof:name":"E-Z Roll Inc",
    "wof:placetype":"venue"
},
  "geometry": {"coordinates":[-92.40634,35.120776],"type":"Point"}
}