{
  "type": "Feature",
  "properties": {
    "addr:full":"703 Broadway St Smackover AR 71762",
    "addr:housenumber":"703",
    "addr:postcode":"71762",
    "addr:street":"Broadway St",
    "iso:country":"US",
    "sg:address":"703 Broadway St",
    "sg:city":"Smackover",
    "sg:classifiers":[
        {
            "category":"Manufacturing",
            "subcategory":"Printing",
            "type":"Manufacturing & Wholesale Goods"
        }
    ],
    "sg:phone":"+1 870 725 2311",
    "sg:postcode":"71762",
    "sg:province":"AR",
    "sg:tags":[
        "lithographic",
        "commercial"
    ],
    "wof:name":"Broadway Printing",
    "wof:placetype":"venue"
},
  "geometry": {"coordinates":[-92.72278,33.370261],"type":"Point"}
}