{
  "type": "Feature",
  "properties": {
    "addr:full":"820 Evans Mountain Rd Atkins AR 72823",
    "addr:housenumber":"820",
    "addr:postcode":"72823",
    "addr:street":"Evans Mountain Rd",
    "iso:country":"US",
    "sg:address":"820 Evans Mountain Rd",
    "sg:city":"Atkins",
    "sg:classifiers":[
        {
            "category":"Organizations",
            "subcategory":"Religious Organization",
            "type":"Services"
        }
    ],
    "sg:phone":"+1 479 284 2005",
    "sg:postcode":"72823",
    "sg:province":"AR",
    "sg:tags":[
        "church"
    ],
    "wof:name":"Evans Mt Full Gospel Church",
    "wof:placetype":"venue"
},
  "geometry": {"coordinates":[-92.872705,35.439959],"type":"Point"}
}