{
  "type": "Feature",
  "properties": {
    "addr:full":"13821 Chambers Rd Bauxite AR 72011",
    "addr:housenumber":"13821",
    "addr:postcode":"72011",
    "addr:street":"Chambers Rd",
    "iso:country":"US",
    "sg:address":"13821 Chambers Rd",
    "sg:city":"Bauxite",
    "sg:classifiers":[
        {
            "category":"Real Estate",
            "subcategory":"Real Estate Services",
            "type":"Services"
        }
    ],
    "sg:phone":"+1 501 557 2037",
    "sg:postcode":"72011",
    "sg:province":"AR",
    "sg:tags":[
        "building",
        "maintenance"
    ],
    "wof:name":"C & S Building Services",
    "wof:placetype":"venue"
},
  "geometry": {"coordinates":[-92.445604,34.518453],"type":"Point"}
}