{
  "type": "Feature",
  "properties": {
    "iso:country":"US",
    "sg:address":"8635 Edgemont Rd",
    "sg:city":"Greers Ferry",
    "sg:classifiers":[
        {
            "category":"Banks & Credit Unions",
            "subcategory":"Bank",
            "type":"Services"
        }
    ],
    "sg:phone":"+1 501 825 6217",
    "sg:postcode":"72067",
    "sg:province":"AR",
    "wof:name":"US Bank",
    "wof:placetype":"venue"
},
  "geometry": {"coordinates":[-92.17653799999999,35.582709],"type":"Point"}
}