{
  "type": "Feature",
  "properties": {
    "iso:country":"US",
    "sg:address":"191 Burkett Flat Rd",
    "sg:city":"Greenbrier",
    "sg:classifiers":[
        {
            "category":"Insurance",
            "subcategory":"Insurance Agent",
            "type":"Services"
        }
    ],
    "sg:phone":"+1 501 679 6961",
    "sg:postcode":"72058",
    "sg:province":"AR",
    "wof:name":"Nationwide Insurance",
    "wof:placetype":"venue"
},
  "geometry": {"coordinates":[-92.45164200000001,35.254199],"type":"Point"}
}