{
  "type": "Feature",
  "properties": {
    "addr:full":"1020 W Holly St Rogers AR 72756",
    "addr:housenumber":"1020",
    "addr:postcode":"72756",
    "addr:street":"W Holly St",
    "iso:country":"US",
    "sg:address":"1020 W Holly St",
    "sg:city":"Rogers",
    "sg:classifiers":[
        {
            "category":"Shopping",
            "subcategory":"Computers & Home Electronics",
            "type":"Retail Goods"
        }
    ],
    "sg:phone":"+1 479 936 8600",
    "sg:postcode":"72756",
    "sg:province":"AR",
    "wof:name":"P C Turnkey",
    "wof:placetype":"venue"
},
  "geometry": {"coordinates":[-94.130207,36.323085],"type":"Point"}
}