{
  "type": "Feature",
  "properties": {
    "iso:country":"US",
    "sg:address":"1003 Oakwood Dr",
    "sg:city":"Wynne",
    "sg:classifiers":[
        {
            "category":"Professional",
            "type":"Services"
        }
    ],
    "sg:phone":"+1 870 238 9651",
    "sg:postcode":"72396",
    "sg:province":"AR",
    "wof:name":"Bethell LLC",
    "wof:placetype":"venue"
},
  "geometry": {"coordinates":[-90.763609,35.234265],"type":"Point"}
}