{
  "type": "Feature",
  "properties": {
    "addr:full":"2100 Harrison St Batesville AR 72501",
    "addr:housenumber":"2100",
    "addr:postcode":"72501",
    "addr:street":"Harrison St",
    "iso:country":"US",
    "sg:address":"2100 Harrison St",
    "sg:city":"Batesville",
    "sg:classifiers":[
        {
            "category":"Retail",
            "subcategory":"Auto Rental",
            "type":"Services"
        }
    ],
    "sg:phone":"+1 870 793 8211",
    "sg:postcode":"72501",
    "sg:province":"AR",
    "sg:tags":[
        "renting",
        "truck",
        "leasing"
    ],
    "wof:name":"U-Haul Co",
    "wof:placetype":"venue"
},
  "geometry": {"coordinates":[-91.63009,35.769521],"type":"Point"}
}