{
  "type": "Feature",
  "properties": {
    "iso:country":"US",
    "sg:address":"16135 US Hwy 71",
    "sg:city":"Greenwood",
    "sg:classifiers":[
        {
            "category":"Banks & Credit Unions",
            "subcategory":"Investment Brokerage",
            "type":"Services"
        }
    ],
    "sg:phone":"+1 479 996 3451",
    "sg:postcode":"72936",
    "sg:province":"AR",
    "sg:tags":[
        "advisory",
        "financial"
    ],
    "wof:name":"Allied Home Mortgage Capital",
    "wof:placetype":"venue"
},
  "geometry": {"coordinates":[-94.318664,35.232307],"type":"Point"}
}