{
  "type": "Feature",
  "properties": {
    "iso:country":"US",
    "sg:address":"313 Roosevelt Ave",
    "sg:city":"West Memphis",
    "sg:classifiers":[
        {
            "category":"Professional",
            "type":"Services"
        }
    ],
    "sg:phone":"+1 870 735 3329",
    "sg:postcode":"72301",
    "sg:province":"AR",
    "wof:name":"Diane Morley",
    "wof:placetype":"venue"
},
  "geometry": {"coordinates":[-90.191047,35.152734],"type":"Point"}
}