{
  "type": "Feature",
  "properties": {
    "addr:full":"3214 Happy Valley Dr Little Rock AR 72212",
    "addr:housenumber":"3214",
    "addr:postcode":"72212",
    "addr:street":"Happy Valley Dr",
    "iso:country":"US",
    "sg:address":"3214 Happy Valley Dr",
    "sg:city":"Little Rock",
    "sg:classifiers":[
        {
            "category":"Professional",
            "type":"Services"
        }
    ],
    "sg:phone":"+1 501 225 3623",
    "sg:postcode":"72212",
    "sg:province":"AR",
    "wof:name":"Rilley Scott Keeling",
    "wof:placetype":"venue"
},
  "geometry": {"coordinates":[-92.40075299999999,34.782217],"type":"Point"}
}