{
  "type": "Feature",
  "properties": {
    "addr:full":"1615 S 22nd St Fort Smith AR 72901",
    "addr:housenumber":"1615",
    "addr:postcode":"72901",
    "addr:street":"S 22Nd St",
    "iso:country":"US",
    "sg:address":"1615 S 22nd St",
    "sg:city":"Fort Smith",
    "sg:classifiers":[
        {
            "category":"Real Estate",
            "subcategory":"Real Estate Operator",
            "type":"Services"
        }
    ],
    "sg:phone":"+1 479 782 1560",
    "sg:postcode":"72901",
    "sg:province":"AR",
    "sg:tags":[
        "apartment"
    ],
    "wof:name":"Tara Garden Apartments",
    "wof:placetype":"venue"
},
  "geometry": {"coordinates":[-94.409789,35.367784],"type":"Point"}
}