{
  "type": "Feature",
  "properties": {
    "iso:country":"US",
    "sg:address":"254 Buttrum Rd",
    "sg:city":"Royal",
    "sg:classifiers":[
        {
            "category":"Transit Center",
            "subcategory":"Freight",
            "type":"Transportation"
        },
        {
            "category":"Freight",
            "type":"Transportation"
        }
    ],
    "sg:phone":"+1 501 767 9789",
    "sg:postcode":"71968",
    "sg:province":"AR",
    "sg:tags":[
        "trucking-motor",
        "trucking"
    ],
    "wof:name":"Bats Transport Services Inc",
    "wof:placetype":"venue"
},
  "geometry": {"coordinates":[-93.28372,34.505053],"type":"Point"}
}