{
  "type": "Feature",
  "properties": {
    "iso:country":"US",
    "sg:address":"133 Park St",
    "sg:city":"Monticello",
    "sg:classifiers":[
        {
            "category":"Health Services",
            "subcategory":"Doctor",
            "type":"Services"
        }
    ],
    "sg:phone":"+1 870 367 7500",
    "sg:postcode":"71655",
    "sg:province":"AR",
    "wof:name":"Eubanks Terri Dr DDS PA",
    "wof:placetype":"venue"
},
  "geometry": {"coordinates":[-91.797482,33.647274],"type":"Point"}
}