{
  "type": "Feature",
  "properties": {
    "iso:country":"US",
    "sg:address":"215 Cherokee Cir",
    "sg:city":"Little Rock",
    "sg:classifiers":[
        {
            "category":"Travel",
            "subcategory":"Campground",
            "type":"Entertainment"
        }
    ],
    "sg:phone":"+1 501 225 3188",
    "sg:postcode":"72205",
    "sg:province":"AR",
    "sg:tags":[
        "camp"
    ],
    "wof:name":"J T Patton",
    "wof:placetype":"venue"
},
  "geometry": {"coordinates":[-92.36215300000001,34.750016],"type":"Point"}
}