{
  "type": "Feature",
  "properties": {
    "addr:full":"104 N 37th St Rogers AR 72756",
    "addr:housenumber":"104",
    "addr:postcode":"72756",
    "addr:street":"N 37Th St",
    "iso:country":"US",
    "sg:address":"104 N 37th St",
    "sg:city":"Rogers",
    "sg:classifiers":[
        {
            "category":"Health Services",
            "subcategory":"Clinic",
            "type":"Services"
        }
    ],
    "sg:phone":"+1 479 636 7700",
    "sg:postcode":"72756",
    "sg:province":"AR",
    "sg:tags":[
        "home",
        "agency",
        "employment"
    ],
    "sg:website":"www.superiorcare.com",
    "wof:name":"Superior Senior Care",
    "wof:placetype":"venue"
},
  "geometry": {"coordinates":[-94.170197,36.334599],"type":"Point"}
}