{
  "type": "Feature",
  "properties": {
    "addr:full":"104 E 2nd Ave Crossett AR 71635",
    "addr:housenumber":"104",
    "addr:postcode":"71635",
    "addr:street":"E 2Nd Ave",
    "iso:country":"US",
    "sg:address":"104 E 2nd Ave",
    "sg:city":"Crossett",
    "sg:classifiers":[
        {
            "category":"Shopping",
            "subcategory":"Department Store",
            "type":"Retail Goods"
        }
    ],
    "sg:phone":"+1 870 364 3344",
    "sg:postcode":"71635",
    "sg:province":"AR",
    "sg:website":"www.sharpeclothing.com",
    "wof:name":"Sharpe's Department Store",
    "wof:placetype":"venue"
},
  "geometry": {"coordinates":[-91.961461,33.133864],"type":"Point"}
}