{
  "type": "Feature",
  "properties": {
    "addr:full":"2504 S Lincoln St Siloam Springs OK 72761",
    "addr:housenumber":"2504",
    "addr:postcode":"72761",
    "addr:street":"S Lincoln St",
    "iso:country":"US",
    "sg:address":"2504 S Lincoln St",
    "sg:city":"Siloam Springs",
    "sg:classifiers":[
        {
            "category":"Building & Trades",
            "subcategory":"Construction",
            "type":"Services"
        }
    ],
    "sg:phone":"+1 479 524 4515",
    "sg:postcode":"72761",
    "sg:province":"OK",
    "sg:tags":[
        "residential"
    ],
    "wof:name":"Cochran Freeman Cnstr LLC",
    "wof:placetype":"venue"
},
  "geometry": {"coordinates":[-94.528364,36.164336],"type":"Point"}
}