{
  "type": "Feature",
  "properties": {
    "iso:country":"US",
    "sg:address":"576 Co Rd 125",
    "sg:city":"Corning",
    "sg:classifiers":[
        {
            "category":"Professional",
            "type":"Services"
        }
    ],
    "sg:phone":"+1 870 276 5653",
    "sg:postcode":"72422",
    "sg:province":"AR",
    "wof:name":"Chris D Mathis",
    "wof:placetype":"venue"
},
  "geometry": {"coordinates":[-90.67723100000001,36.371481],"type":"Point"}
}