{
  "type": "Feature",
  "properties": {
    "iso:country":"US",
    "sg:address":"399 E Robinson Ave",
    "sg:city":"Springdale",
    "sg:classifiers":[
        {
            "category":"Building & Trades",
            "subcategory":"Construction",
            "type":"Services"
        }
    ],
    "sg:phone":"+1 479 751 8701",
    "sg:postcode":"72764",
    "sg:province":"AR",
    "sg:tags":[
        "painting",
        "contractor"
    ],
    "wof:name":"Burnett, Norman Painting Co",
    "wof:placetype":"venue"
},
  "geometry": {"coordinates":[-94.127614,36.167122],"type":"Point"}
}