{
  "type": "Feature",
  "properties": {
    "iso:country":"US",
    "sg:address":"3995 White Dr",
    "sg:city":"Batesville",
    "sg:classifiers":[
        {
            "category":"Building & Trades",
            "subcategory":"Cleaning & Sanitation",
            "type":"Services"
        }
    ],
    "sg:phone":"+1 870 793 4281",
    "sg:postcode":"72501",
    "sg:province":"AR",
    "sg:tags":[
        "maintenance"
    ],
    "wof:name":"Qualls Cleaning Inc",
    "wof:placetype":"venue"
},
  "geometry": {"coordinates":[-91.56023,35.797168],"type":"Point"}
}