{
  "type": "Feature",
  "properties": {
    "iso:country":"US",
    "sg:address":"6 Miranda Ln",
    "sg:city":"Magnolia",
    "sg:classifiers":[
        {
            "category":"Communications",
            "subcategory":"Radio Station",
            "type":"Services"
        }
    ],
    "sg:phone":"+1 870 234 6229",
    "sg:postcode":"71753",
    "sg:province":"AR",
    "sg:tags":[
        "broadcast"
    ],
    "wof:name":"FM Development",
    "wof:placetype":"venue"
},
  "geometry": {"coordinates":[-93.195641,33.264006],"type":"Point"}
}