{
  "type": "Feature",
  "properties": {
    "iso:country":"US",
    "sg:address":"16026 N Mount Olive Rd",
    "sg:city":"Gravette",
    "sg:classifiers":[
        {
            "category":"Social Services",
            "subcategory":"Child Care",
            "type":"Services"
        }
    ],
    "sg:phone":"+1 479 787 9803",
    "sg:postcode":"72736",
    "sg:province":"AR",
    "sg:tags":[
        "day"
    ],
    "wof:name":"My Little School",
    "wof:placetype":"venue"
},
  "geometry": {"coordinates":[-94.38858399999999,36.378027],"type":"Point"}
}