{
  "type": "Feature",
  "properties": {
    "addr:full":"1512 S River Rd Lavaca AR 72941",
    "addr:housenumber":"1512",
    "addr:postcode":"72941",
    "addr:street":"S River Rd",
    "iso:country":"US",
    "sg:address":"1512 S River Rd",
    "sg:city":"Lavaca",
    "sg:classifiers":[
        {
            "category":"Professional",
            "subcategory":"Art Services",
            "type":"Services"
        }
    ],
    "sg:phone":"+1 479 674 2113",
    "sg:postcode":"72941",
    "sg:province":"AR",
    "sg:tags":[
        "commercial",
        "design"
    ],
    "wof:name":"Hunter Graphics",
    "wof:placetype":"venue"
},
  "geometry": {"coordinates":[-94.195699,35.325765],"type":"Point"}
}