{
  "type": "Feature",
  "properties": {
    "iso:country":"US",
    "sg:address":"210 Rowe Ave",
    "sg:city":"Pocola",
    "sg:classifiers":[
        {
            "category":"Personal",
            "type":"Services"
        }
    ],
    "sg:phone":"+1 918 436 7930",
    "sg:postcode":"74902",
    "sg:province":"OK",
    "wof:name":"Exotic Tans & Video Rentals",
    "wof:placetype":"venue"
},
  "geometry": {"coordinates":[-94.44461800000001,35.271972],"type":"Point"}
}