{
  "type": "Feature",
  "properties": {
    "iso:country":"US",
    "sg:address":"15 Glenwood Dr",
    "sg:city":"Cabot",
    "sg:classifiers":[
        {
            "category":"Education",
            "subcategory":"Dance Studio",
            "type":"Public Place"
        }
    ],
    "sg:phone":"+1 501 843 9805",
    "sg:postcode":"72023",
    "sg:province":"AR",
    "sg:tags":[
        "instruction",
        "dancing"
    ],
    "wof:name":"River City Gymnastics Dance",
    "wof:placetype":"venue"
},
  "geometry": {"coordinates":[-92.004908,34.947949],"type":"Point"}
}