{
  "type": "Feature",
  "properties": {
    "iso:country":"US",
    "sg:address":"1350 California Ave SW",
    "sg:city":"Camden",
    "sg:classifiers":[
        {
            "category":"Manufacturing",
            "subcategory":"Tools & Machinery",
            "type":"Manufacturing & Wholesale Goods"
        }
    ],
    "sg:phone":"+1 870 837 1701",
    "sg:postcode":"71701",
    "sg:province":"AR",
    "sg:tags":[
        "shop",
        "repair",
        "industrial",
        "mfg",
        "automobile",
        "machine",
        "automotive"
    ],
    "wof:name":"Beavers Automotive Machine",
    "wof:placetype":"venue"
},
  "geometry": {"coordinates":[-92.851573,33.560663],"type":"Point"}
}