{
  "type": "Feature",
  "properties": {
    "iso:country":"US",
    "sg:address":"19 Scott Ln",
    "sg:city":"Conway",
    "sg:classifiers":[
        {
            "category":"Wholesale",
            "subcategory":"Painting Supplies",
            "type":"Manufacturing & Wholesale Goods"
        }
    ],
    "sg:phone":"+1 501 764 1767",
    "sg:postcode":"72032",
    "sg:province":"AR",
    "sg:tags":[
        "paint-wholesale",
        "manufacturer"
    ],
    "wof:name":"Billy L Stain",
    "wof:placetype":"venue"
},
  "geometry": {"coordinates":[-92.333468,35.090312],"type":"Point"}
}