{
  "type": "Feature",
  "properties": {
    "iso:country":"US",
    "sg:address":"3001 W Markham St",
    "sg:city":"Little Rock",
    "sg:classifiers":[
        {
            "category":"Government",
            "subcategory":"Office",
            "type":"Public Place"
        }
    ],
    "sg:phone":"+1 501 663 9451",
    "sg:postcode":"72205",
    "sg:province":"AR",
    "sg:tags":[
        "village"
    ],
    "wof:name":"Little Rock Neighborhood Alert",
    "wof:placetype":"venue"
},
  "geometry": {"coordinates":[-92.307587,34.750935],"type":"Point"}
}