{
  "type": "Feature",
  "properties": {
    "iso:country":"US",
    "sg:address":"315 Morgan Rd",
    "sg:city":"Batesville",
    "sg:classifiers":[
        {
            "category":"Professional",
            "subcategory":"Secretarial Services",
            "type":"Services"
        }
    ],
    "sg:phone":"+1 870 793 6465",
    "sg:postcode":"72501",
    "sg:province":"AR",
    "sg:tags":[
        "assistant",
        "administrative"
    ],
    "wof:name":"Martha Smith",
    "wof:placetype":"venue"
},
  "geometry": {"coordinates":[-91.560245,35.76027],"type":"Point"}
}