{
  "type": "Feature",
  "properties": {
    "addr:full":"100 SW 14th St Bentonville AR 72712",
    "addr:housenumber":"100",
    "addr:postcode":"72712",
    "addr:street":"Sw 14Th St",
    "iso:country":"US",
    "sg:address":"100 SW 14th St",
    "sg:city":"Bentonville",
    "sg:classifiers":[
        {
            "category":"Insurance",
            "subcategory":"Insurance Agent",
            "type":"Services"
        }
    ],
    "sg:phone":"+1 479 271 0649",
    "sg:postcode":"72712",
    "sg:province":"AR",
    "wof:name":"Allstate Insurance Co",
    "wof:placetype":"venue"
},
  "geometry": {"coordinates":[-94.210533,36.356989],"type":"Point"}
}