{
  "type": "Feature",
  "properties": {
    "iso:country":"US",
    "sg:address":"126 Valley Acres Cir",
    "sg:city":"Hot Springs",
    "sg:classifiers":[
        {
            "category":"Retail",
            "subcategory":"Auto Repair",
            "type":"Services"
        }
    ],
    "sg:phone":"+1 501 623 4861",
    "sg:postcode":"71913",
    "sg:province":"AR",
    "sg:tags":[
        "recreational",
        "general",
        "vehicle"
    ],
    "wof:name":"Tom's Rv & Mobile Home Repair",
    "wof:placetype":"venue"
},
  "geometry": {"coordinates":[-93.098753,34.544166],"type":"Point"}
}