{
  "type": "Feature",
  "properties": {
    "addr:full":"775 W Trout Dr Fayetteville AR 72703",
    "addr:housenumber":"775",
    "addr:postcode":"72703",
    "addr:street":"W Trout Dr",
    "iso:country":"US",
    "sg:address":"775 W Trout Dr",
    "sg:city":"Fayetteville",
    "sg:classifiers":[
        {
            "category":"Real Estate",
            "subcategory":"Real Estate Operator",
            "type":"Services"
        }
    ],
    "sg:phone":"+1 479 442 4594",
    "sg:postcode":"72703",
    "sg:province":"AR",
    "sg:tags":[
        "apartment"
    ],
    "wof:name":"Leverett Townshouses",
    "wof:placetype":"venue"
},
  "geometry": {"coordinates":[-94.16978,36.079173],"type":"Point"}
}