{
  "type": "Feature",
  "properties": {
    "iso:country":"US",
    "sg:address":"129 Geneva Dr",
    "sg:city":"Hot Springs",
    "sg:classifiers":[
        {
            "category":"Building & Trades",
            "subcategory":"Construction",
            "type":"Services"
        }
    ],
    "sg:phone":"+1 501 337 7414",
    "sg:postcode":"71913",
    "sg:province":"AR",
    "sg:tags":[
        "roofing",
        "contractor"
    ],
    "wof:name":"Arkansas Straightline Roofing",
    "wof:placetype":"venue"
},
  "geometry": {"coordinates":[-93.163788,34.511424],"type":"Point"}
}