{
  "type": "Feature",
  "properties": {
    "addr:full":"25 N Wedgewood Dr Blytheville AR 72315",
    "addr:housenumber":"25",
    "addr:postcode":"72315",
    "addr:street":"N Wedgewood Dr Blytheville",
    "iso:country":"US",
    "sg:address":"25 N Wedgewood Dr",
    "sg:city":"Blytheville",
    "sg:classifiers":[
        {
            "category":"Real Estate",
            "subcategory":"Real Estate Operator",
            "type":"Services"
        }
    ],
    "sg:phone":"+1 870 762 2404",
    "sg:postcode":"72315",
    "sg:province":"AR",
    "sg:tags":[
        "mobile",
        "home",
        "site"
    ],
    "wof:name":"Holstead",
    "wof:placetype":"venue"
},
  "geometry": {"coordinates":[-89.907023,35.946516],"type":"Point"}
}