{
  "type": "Feature",
  "properties": {
    "iso:country":"US",
    "sg:address":"15594 Linville Rd",
    "sg:city":"Rogers",
    "sg:classifiers":[
        {
            "category":"Professional",
            "type":"Services"
        }
    ],
    "sg:phone":"+1 479 925 3929",
    "sg:postcode":"72756",
    "sg:province":"AR",
    "wof:name":"Foodpro LLC",
    "wof:placetype":"venue"
},
  "geometry": {"coordinates":[-94.035346,36.330329],"type":"Point"}
}