{
  "type": "Feature",
  "properties": {
    "addr:full":"2028 Dodson Ave Fort Smith AR 72901",
    "addr:housenumber":"2028",
    "addr:postcode":"72901",
    "addr:street":"Dodson Ave",
    "iso:country":"US",
    "sg:address":"2028 Dodson Ave",
    "sg:city":"Fort Smith",
    "sg:classifiers":[
        {
            "category":"Banks & Credit Unions",
            "subcategory":"Bank",
            "type":"Services"
        }
    ],
    "sg:phone":"+1 479 484 5300",
    "sg:postcode":"72901",
    "sg:province":"AR",
    "sg:tags":[
        "loan",
        "real estate"
    ],
    "wof:name":"Amstar Mortgage",
    "wof:placetype":"venue"
},
  "geometry": {"coordinates":[-94.410915,35.372227],"type":"Point"}
}