{
  "type": "Feature",
  "properties": {
    "iso:country":"US",
    "sg:address":"1369 Madison 3120",
    "sg:city":"Huntsville",
    "sg:classifiers":[
        {
            "category":"Manufacturing",
            "subcategory":"Buildings",
            "type":"Manufacturing & Wholesale Goods"
        },
        {
            "category":"Building & Trades",
            "subcategory":"Construction",
            "type":"Services"
        }
    ],
    "sg:phone":"+1 479 232 5922",
    "sg:postcode":"72740",
    "sg:province":"AR",
    "sg:tags":[
        "home",
        "builder",
        "contractor"
    ],
    "wof:name":"Hepler Construction",
    "wof:placetype":"venue"
},
  "geometry": {"coordinates":[-93.683661,36.004861],"type":"Point"}
}