{
  "type": "Feature",
  "properties": {
    "iso:country":"US",
    "sg:address":"1039 US Hwy 278",
    "sg:city":"Monticello",
    "sg:classifiers":[
        {
            "category":"Restaurant",
            "type":"Food & Drink"
        }
    ],
    "sg:phone":"+1 870 460 0106",
    "sg:postcode":"71655",
    "sg:province":"AR",
    "sg:tags":[
        "eating"
    ],
    "wof:name":"Cowboy's Restaurant",
    "wof:placetype":"venue"
},
  "geometry": {"coordinates":[-91.771263,33.628399],"type":"Point"}
}