{
  "type": "Feature",
  "properties": {
    "iso:country":"US",
    "sg:address":"608 Nan Cir",
    "sg:city":"Little Rock",
    "sg:classifiers":[
        {
            "category":"Banks & Credit Unions",
            "subcategory":"Financial Services",
            "type":"Services"
        }
    ],
    "sg:phone":"+1 501 221 2598",
    "sg:postcode":"72211",
    "sg:province":"AR",
    "sg:tags":[
        "trust",
        "investment",
        "real estate"
    ],
    "wof:name":"M E Seckt Ltd",
    "wof:placetype":"venue"
},
  "geometry": {"coordinates":[-92.399003,34.758355],"type":"Point"}
}