{
  "type": "Feature",
  "properties": {
    "iso:country":"US",
    "sg:address":"327 Midland St",
    "sg:city":"Little Rock",
    "sg:classifiers":[
        {
            "category":"Wholesale",
            "subcategory":"Stationery",
            "type":"Manufacturing & Wholesale Goods"
        }
    ],
    "sg:phone":"+1 501 975 9160",
    "sg:postcode":"72205",
    "sg:province":"AR",
    "sg:tags":[
        "paper"
    ],
    "wof:name":"Omni Packaging Co",
    "wof:placetype":"venue"
},
  "geometry": {"coordinates":[-92.308265,34.751526],"type":"Point"}
}