{
  "type": "Feature",
  "properties": {
    "iso:country":"US",
    "sg:address":"100 Girard St",
    "sg:city":"Flippin",
    "sg:classifiers":[
        {
            "category":"Social Services",
            "subcategory":"Child Care",
            "type":"Services"
        }
    ],
    "sg:phone":"+1 870 453 5090",
    "sg:postcode":"72634",
    "sg:province":"AR",
    "wof:name":"Precious Ones Daycare",
    "wof:placetype":"venue"
},
  "geometry": {"coordinates":[-92.600826,36.278784],"type":"Point"}
}