{
  "type": "Feature",
  "properties": {
    "iso:country":"US",
    "sg:address":"16418 Minton Rd",
    "sg:city":"Little Rock",
    "sg:classifiers":[
        {
            "category":"Building & Trades",
            "subcategory":"Construction",
            "type":"Services"
        }
    ],
    "sg:phone":"+1 501 821 3600",
    "sg:postcode":"72210",
    "sg:province":"AR",
    "sg:tags":[
        "house",
        "nonresidential"
    ],
    "wof:name":"Melvin Garrett Construction",
    "wof:placetype":"venue"
},
  "geometry": {"coordinates":[-92.46885,34.705457],"type":"Point"}
}