{
  "type": "Feature",
  "properties": {
    "addr:full":"5 Killdeer Rd Rogers AR 72756",
    "addr:housenumber":"5",
    "addr:postcode":"72756",
    "addr:street":"Killdeer Rd",
    "iso:country":"US",
    "sg:address":"5 Killdeer Rd",
    "sg:city":"Rogers",
    "sg:classifiers":[
        {
            "category":"Building & Trades",
            "subcategory":"Construction",
            "type":"Services"
        }
    ],
    "sg:phone":"+1 479 636 0881",
    "sg:postcode":"72756",
    "sg:province":"AR",
    "sg:tags":[
        "general",
        "contractor"
    ],
    "wof:name":"Welsh Construction",
    "wof:placetype":"venue"
},
  "geometry": {"coordinates":[-94.110263,36.402408],"type":"Point"}
}