{
  "type": "Feature",
  "properties": {
    "addr:full":"12000 Ironton Rd Little Rock AR 72206",
    "addr:postcode":"12000;72206",
    "addr:street":"Ironton Rd",
    "iso:country":"US",
    "sg:address":"12000 Ironton Rd",
    "sg:city":"Little Rock",
    "sg:classifiers":[
        {
            "category":"Shopping",
            "subcategory":"Computers & Home Electronics",
            "type":"Retail Goods"
        }
    ],
    "sg:phone":"+1 501 888 6033",
    "sg:postcode":"72206",
    "sg:province":"AR",
    "wof:name":"Cutting Edge Technologies",
    "wof:placetype":"venue"
},
  "geometry": {"coordinates":[-92.268173,34.644725],"type":"Point"}
}