{
  "type": "Feature",
  "properties": {
    "iso:country":"US",
    "sg:address":"6614 Old Harrison Ln",
    "sg:city":"Fort Smith",
    "sg:classifiers":[
        {
            "category":"Freight",
            "type":"Transportation"
        }
    ],
    "sg:phone":"+1 479 646 6683",
    "sg:postcode":"72916",
    "sg:province":"AR",
    "sg:tags":[
        "operator",
        "storage",
        "special",
        "trucking"
    ],
    "wof:name":"United Van Lines",
    "wof:placetype":"venue"
},
  "geometry": {"coordinates":[-94.36562499999999,35.266416],"type":"Point"}
}