{
  "type": "Feature",
  "properties": {
    "iso:country":"US",
    "sg:address":"124 Harrison Rd",
    "sg:city":"El Dorado",
    "sg:classifiers":[
        {
            "category":"Freight",
            "type":"Transportation"
        }
    ],
    "sg:phone":"+1 870 863 4930",
    "sg:postcode":"71730",
    "sg:province":"AR",
    "sg:tags":[
        "operator",
        "local",
        "trucking"
    ],
    "wof:name":"H & B Trucking LLC",
    "wof:placetype":"venue"
},
  "geometry": {"coordinates":[-92.755489,33.162304],"type":"Point"}
}