{
  "type": "Feature",
  "properties": {
    "iso:country":"US",
    "sg:address":"1202 N Holly St",
    "sg:city":"Beebe",
    "sg:classifiers":[
        {
            "category":"Professional",
            "type":"Services"
        }
    ],
    "sg:phone":"+1 501 882 7601",
    "sg:postcode":"72012",
    "sg:province":"AR",
    "wof:name":"Carl & Cindy Bayne",
    "wof:placetype":"venue"
},
  "geometry": {"coordinates":[-91.887968,35.077244],"type":"Point"}
}