{
  "type": "Feature",
  "properties": {
    "iso:country":"US",
    "sg:address":"72 Sfc 840",
    "sg:city":"Palestine",
    "sg:classifiers":[
        {
            "category":"Personal",
            "subcategory":"Beauty Salon",
            "type":"Services"
        }
    ],
    "sg:phone":"+1 870 581 2947",
    "sg:postcode":"72372",
    "sg:province":"AR",
    "wof:name":"Darlene's Beauty Salon",
    "wof:placetype":"venue"
},
  "geometry": {"coordinates":[-90.904392,34.942905],"type":"Point"}
}