{
  "type": "Feature",
  "properties": {
    "iso:country":"US",
    "sg:address":"1215 S Thompson St",
    "sg:city":"Springdale",
    "sg:classifiers":[
        {
            "category":"Health Services",
            "subcategory":"Nursing And Care Facility",
            "type":"Services"
        }
    ],
    "sg:phone":"+1 479 756 9172",
    "sg:postcode":"72764",
    "sg:province":"AR",
    "sg:tags":[
        "hospice"
    ],
    "wof:name":"Center For Comfort & Plltv Cr",
    "wof:placetype":"venue"
},
  "geometry": {"coordinates":[-94.138957,36.174393],"type":"Point"}
}