{
  "type": "Feature",
  "properties": {
    "iso:country":"US",
    "sg:address":"780 Heber Springs Rd",
    "sg:city":"Batesville",
    "sg:classifiers":[
        {
            "category":"Retail",
            "subcategory":"Auto Repair",
            "type":"Services"
        }
    ],
    "sg:phone":"+1 870 251 4116",
    "sg:postcode":"72501",
    "sg:province":"AR",
    "sg:tags":[
        "body",
        "automobile",
        "painting"
    ],
    "wof:name":"J & L Body Shop",
    "wof:placetype":"venue"
},
  "geometry": {"coordinates":[-91.658708,35.732187],"type":"Point"}
}