{
  "type": "Feature",
  "properties": {
    "addr:full":"2382 W Clark Rd Clarksville AR 72830",
    "addr:housenumber":"2382",
    "addr:postcode":"72830",
    "addr:street":"W Clark Rd",
    "iso:country":"US",
    "sg:address":"2382 W Clark Rd",
    "sg:city":"Clarksville",
    "sg:classifiers":[
        {
            "category":"Shopping",
            "type":"Retail Goods"
        }
    ],
    "sg:phone":"+1 479 754 4022",
    "sg:postcode":"72830",
    "sg:province":"AR",
    "sg:tags":[
        "cosmetic",
        "perfume"
    ],
    "sg:website":"www.merlenorman.com",
    "wof:name":"Merle Norman Cosmetics",
    "wof:placetype":"venue"
},
  "geometry": {"coordinates":[-93.50591300000001,35.462151],"type":"Point"}
}