{
  "type": "Feature",
  "properties": {
    "iso:country":"US",
    "sg:address":"3401 SE L St",
    "sg:city":"Bentonville",
    "sg:classifiers":[
        {
            "category":"Real Estate",
            "subcategory":"Real Estate Operator",
            "type":"Services"
        }
    ],
    "sg:phone":"+1 479 464 4080",
    "sg:postcode":"72712",
    "sg:province":"AR",
    "sg:tags":[
        "apartment"
    ],
    "wof:name":"Osage Terrace",
    "wof:placetype":"venue"
},
  "geometry": {"coordinates":[-94.194236,36.336452],"type":"Point"}
}