{
  "type": "Feature",
  "properties": {
    "iso:country":"US",
    "sg:address":"10415 Stuckey Ln",
    "sg:city":"Trumann",
    "sg:classifiers":[
        {
            "category":"Wholesale",
            "subcategory":"Farm Supplies",
            "type":"Manufacturing & Wholesale Goods"
        }
    ],
    "sg:phone":"+1 870 483 7625",
    "sg:postcode":"72472",
    "sg:province":"AR",
    "sg:tags":[
        "bulk",
        "fertilizer",
        "blend"
    ],
    "wof:name":"Poinsett Fertilizer Inc",
    "wof:placetype":"venue"
},
  "geometry": {"coordinates":[-90.581739,35.604583],"type":"Point"}
}