{
  "type": "Feature",
  "properties": {
    "iso:country":"US",
    "sg:address":"9373 State Hwy 7",
    "sg:city":"Harrison",
    "sg:classifiers":[
        {
            "category":"Food & Beverages",
            "subcategory":"Meat & Fish",
            "type":"Retail Goods"
        },
        {
            "category":"Wholesale",
            "subcategory":"Meat",
            "type":"Manufacturing & Wholesale Goods"
        }
    ],
    "sg:phone":"+1 870 743 1638",
    "sg:postcode":"72601",
    "sg:province":"AR",
    "sg:tags":[
        "mfg",
        "eating",
        "prepared"
    ],
    "wof:name":"Country Smoked Meats",
    "wof:placetype":"venue"
},
  "geometry": {"coordinates":[-93.11788199999999,36.128247],"type":"Point"}
}