{
  "type": "Feature",
  "properties": {
    "iso:country":"US",
    "sg:address":"5300 Strong Hwy",
    "sg:city":"El Dorado",
    "sg:classifiers":[
        {
            "category":"Home & Garden",
            "subcategory":"Home Furnishings",
            "type":"Retail Goods"
        }
    ],
    "sg:phone":"+1 870 862 2625",
    "sg:postcode":"71730",
    "sg:province":"AR",
    "sg:tags":[
        "curtain",
        "made",
        "drapery"
    ],
    "wof:name":"Debbie Ward Custom Drapes",
    "wof:placetype":"venue"
},
  "geometry": {"coordinates":[-92.490831,33.135014],"type":"Point"}
}