{
  "type": "Feature",
  "properties": {
    "iso:country":"US",
    "sg:address":"421 N Main St",
    "sg:city":"Harrison",
    "sg:classifiers":[
        {
            "category":"Building & Trades",
            "subcategory":"Construction",
            "type":"Services"
        }
    ],
    "sg:phone":"+1 870 741 5879",
    "sg:postcode":"72601",
    "sg:province":"AR",
    "sg:tags":[
        "fabricator",
        "metal"
    ],
    "wof:name":"Best Stainless & Alloys",
    "wof:placetype":"venue"
},
  "geometry": {"coordinates":[-93.107139,36.234111],"type":"Point"}
}