{
  "type": "Feature",
  "properties": {
    "iso:country":"US",
    "sg:address":"511 W Tulsa St",
    "sg:city":"Siloam Springs",
    "sg:classifiers":[
        {
            "category":"Real Estate",
            "subcategory":"Real Estate Agent",
            "type":"Services"
        }
    ],
    "sg:phone":"+1 479 524 0774",
    "sg:postcode":"72761",
    "sg:province":"OK",
    "wof:name":"Kelley's Master Key Rlty Inc",
    "wof:placetype":"venue"
},
  "geometry": {"coordinates":[-94.545828,36.178123],"type":"Point"}
}