{
  "type": "Feature",
  "properties": {
    "iso:country":"US",
    "sg:address":"215 E Kingshighway",
    "sg:city":"Paragould",
    "sg:classifiers":[
        {
            "category":"Shopping",
            "subcategory":"Antiques",
            "type":"Retail Goods"
        }
    ],
    "sg:phone":"+1 870 236 8222",
    "sg:postcode":"72450",
    "sg:province":"AR",
    "wof:name":"Amazing Things Antique Mall",
    "wof:placetype":"venue"
},
  "geometry": {"coordinates":[-90.48459,36.052591],"type":"Point"}
}