{
  "type": "Feature",
  "properties": {
    "iso:country":"US",
    "sg:address":"126 E Washington St",
    "sg:city":"Camden",
    "sg:classifiers":[
        {
            "category":"Professional",
            "subcategory":"Business Services",
            "type":"Services"
        }
    ],
    "sg:phone":"+1 870 837 2465",
    "sg:postcode":"71701",
    "sg:province":"AR",
    "sg:tags":[
        "testing"
    ],
    "wof:name":"Nts",
    "wof:placetype":"venue"
},
  "geometry": {"coordinates":[-92.829465,33.586148],"type":"Point"}
}