{
  "type": "Feature",
  "properties": {
    "addr:full":"104 Beaty Ave Pocola OK 74902",
    "addr:housenumber":"104",
    "addr:postcode":"74902",
    "addr:street":"Beaty Ave",
    "iso:country":"US",
    "sg:address":"104 Beaty Ave",
    "sg:city":"Pocola",
    "sg:classifiers":[
        {
            "category":"Shopping",
            "subcategory":"Bicycles & Sporting Goods",
            "type":"Retail Goods"
        }
    ],
    "sg:phone":"+1 918 626 3903",
    "sg:postcode":"74902",
    "sg:province":"OK",
    "sg:tags":[
        "tackle",
        "fishing"
    ],
    "wof:name":"Performance Marine & Tackle",
    "wof:placetype":"venue"
},
  "geometry": {"coordinates":[-94.441704,35.303448],"type":"Point"}
}