{
  "type": "Feature",
  "properties": {
    "iso:country":"US",
    "sg:address":"3800 John F Kennedy Blvd",
    "sg:city":"N Little Rock",
    "sg:classifiers":[
        {
            "category":"Shopping",
            "subcategory":"Clothing, Apparel, & Fashions",
            "type":"Retail Goods"
        }
    ],
    "sg:phone":"+1 501 753 4403",
    "sg:postcode":"72116",
    "sg:province":"AR",
    "sg:tags":[
        "alteration"
    ],
    "wof:name":"Custom Design Sewing & Altrtns",
    "wof:placetype":"venue"
},
  "geometry": {"coordinates":[-92.25979100000001,34.791891],"type":"Point"}
}