{
  "type": "Feature",
  "properties": {
    "addr:full":"3100 Fox Rd Jonesboro AR 72404",
    "addr:housenumber":"3100",
    "addr:postcode":"72404",
    "addr:street":"Fox Rd",
    "iso:country":"US",
    "sg:address":"3100 Fox Rd",
    "sg:city":"Jonesboro",
    "sg:classifiers":[
        {
            "category":"Freight",
            "type":"Transportation"
        }
    ],
    "sg:phone":"+1 870 933 6236",
    "sg:postcode":"72404",
    "sg:province":"AR",
    "sg:tags":[
        "trucking"
    ],
    "wof:name":"Timmons Transit",
    "wof:placetype":"venue"
},
  "geometry": {"coordinates":[-90.667101,35.798809],"type":"Point"}
}