{
  "type": "Feature",
  "properties": {
    "iso:country":"US",
    "sg:address":"415 N College Ave",
    "sg:city":"Fayetteville",
    "sg:classifiers":[
        {
            "category":"Shopping",
            "subcategory":"Used Merchandise",
            "type":"Retail Goods"
        }
    ],
    "sg:phone":"+1 479 521 3760",
    "sg:postcode":"72701",
    "sg:province":"AR",
    "wof:name":"Ms Bettys Antiques and Junk",
    "wof:placetype":"venue"
},
  "geometry": {"coordinates":[-94.157771,36.069749],"type":"Point"}
}