{
  "type": "Feature",
  "properties": {
    "iso:country":"US",
    "sg:address":"415 E Lincoln Ave",
    "sg:city":"Searcy",
    "sg:classifiers":[
        {
            "category":"Building & Trades",
            "subcategory":"Electrical",
            "type":"Services"
        }
    ],
    "sg:phone":"+1 501 268 5744",
    "sg:postcode":"72143",
    "sg:province":"AR",
    "sg:tags":[
        "electric",
        "contractor"
    ],
    "wof:name":"Weir Electric Inc",
    "wof:placetype":"venue"
},
  "geometry": {"coordinates":[-91.734009,35.239883],"type":"Point"}
}