{
  "type": "Feature",
  "properties": {
    "iso:country":"US",
    "sg:address":"1909 State Hwy 161",
    "sg:city":"N Little Rock",
    "sg:classifiers":[
        {
            "category":"Real Estate",
            "subcategory":"Real Estate Agent",
            "type":"Services"
        }
    ],
    "sg:phone":"+1 501 945 9439",
    "sg:postcode":"72117",
    "sg:province":"AR",
    "sg:tags":[
        "finding",
        "apartment",
        "rental"
    ],
    "wof:name":"Protho Manor Apartments",
    "wof:placetype":"venue"
},
  "geometry": {"coordinates":[-92.199423,34.770556],"type":"Point"}
}