{
  "type": "Feature",
  "properties": {
    "addr:full":"1070 Beechwood Ave Fayetteville AR 72701",
    "addr:housenumber":"1070",
    "addr:postcode":"72701",
    "addr:street":"Beechwood Ave",
    "iso:country":"US",
    "sg:address":"1070 Beechwood Ave",
    "sg:city":"Fayetteville",
    "sg:classifiers":[
        {
            "category":"Manufacturing",
            "subcategory":"Glass & Minerals",
            "type":"Manufacturing & Wholesale Goods"
        }
    ],
    "sg:phone":"+1 479 521 2350",
    "sg:postcode":"72701",
    "sg:province":"AR",
    "sg:tags":[
        "cut",
        "mfg"
    ],
    "wof:name":"Fannings Cultured Marble",
    "wof:placetype":"venue"
},
  "geometry": {"coordinates":[-94.184962,36.052189],"type":"Point"}
}