{
  "type": "Feature",
  "properties": {
    "addr:full":"5701 Sullivan Rd Little Rock AR 72210",
    "addr:housenumber":"5701",
    "addr:postcode":"72210",
    "addr:street":"Sullivan Rd",
    "iso:country":"US",
    "sg:address":"5701 Sullivan Rd",
    "sg:city":"Little Rock",
    "sg:classifiers":[
        {
            "category":"Organizations",
            "subcategory":"Religious Organization",
            "type":"Services"
        }
    ],
    "sg:phone":"+1 501 455 0230",
    "sg:postcode":"72210",
    "sg:province":"AR",
    "wof:name":"Faith In Action Fellowship Inc",
    "wof:placetype":"venue"
},
  "geometry": {"coordinates":[-92.465349,34.703676],"type":"Point"}
}