{
  "type": "Feature",
  "properties": {
    "iso:country":"US",
    "sg:address":"100 N Main St",
    "sg:city":"Bald Knob",
    "sg:classifiers":[
        {
            "category":"Government",
            "subcategory":"Post Office",
            "type":"Public Place"
        }
    ],
    "sg:phone":"+1 501 000 1111",
    "sg:postcode":"72010",
    "sg:province":"AR",
    "wof:name":"US Post Office",
    "wof:placetype":"venue"
},
  "geometry": {"coordinates":[-91.56749600000001,35.312977],"type":"Point"}
}