{
  "type": "Feature",
  "properties": {
    "iso:country":"US",
    "sg:address":"109 E Markham St",
    "sg:city":"Little Rock",
    "sg:classifiers":[
        {
            "category":"Shopping",
            "subcategory":"Clothing, Apparel, & Fashions",
            "type":"Retail Goods"
        }
    ],
    "sg:phone":"+1 501 374 5606",
    "sg:postcode":"72201",
    "sg:province":"AR",
    "wof:name":"Global Apparel Sales LLC",
    "wof:placetype":"venue"
},
  "geometry": {"coordinates":[-92.269768,34.747944],"type":"Point"}
}