{
  "type": "Feature",
  "properties": {
    "iso:country":"US",
    "sg:address":"5325 W Bethany Rd",
    "sg:city":"N Little Rock",
    "sg:classifiers":[
        {
            "category":"Wholesale",
            "subcategory":"Auto Parts",
            "type":"Manufacturing & Wholesale Goods"
        }
    ],
    "sg:phone":"+1 501 945 2601",
    "sg:postcode":"72117",
    "sg:province":"AR",
    "sg:tags":[
        "equipment",
        "truck"
    ],
    "wof:name":"Central Truck Parts",
    "wof:placetype":"venue"
},
  "geometry": {"coordinates":[-92.211821,34.774451],"type":"Point"}
}