{
  "type": "Feature",
  "properties": {
    "iso:country":"US",
    "sg:address":"7801 Ball Rd",
    "sg:city":"Fort Smith",
    "sg:classifiers":[
        {
            "category":"Autos & Motor Vehicles",
            "subcategory":"Auto Supplies",
            "type":"Retail Goods"
        }
    ],
    "sg:phone":"+1 479 963 2105",
    "sg:postcode":"72908",
    "sg:province":"AR",
    "sg:tags":[
        "home"
    ],
    "wof:name":"Cloyes O E",
    "wof:placetype":"venue"
},
  "geometry": {"coordinates":[-94.39036900000001,35.311389],"type":"Point"}
}