{
  "type": "Feature",
  "properties": {
    "iso:country":"US",
    "sg:address":"391 Kevin Ln",
    "sg:city":"Springdale",
    "sg:classifiers":[
        {
            "category":"Retail",
            "subcategory":"Laundry & Dry Cleaning",
            "type":"Services"
        }
    ],
    "sg:phone":"+1 479 361 4611",
    "sg:postcode":"72762",
    "sg:province":"AR",
    "sg:tags":[
        "building",
        "maintenance"
    ],
    "wof:name":"Steamatic",
    "wof:placetype":"venue"
},
  "geometry": {"coordinates":[-94.217234,36.175977],"type":"Point"}
}