{
  "type": "Feature",
  "properties": {
    "iso:country":"US",
    "sg:address":"1201 N 8th St",
    "sg:city":"Nashville",
    "sg:classifiers":[
        {
            "category":"Education",
            "subcategory":"School",
            "type":"Public Place"
        }
    ],
    "sg:phone":"+1 870 845 3510",
    "sg:postcode":"71852",
    "sg:province":"AR",
    "sg:tags":[
        "elementary"
    ],
    "wof:name":"Nashville Primary School",
    "wof:placetype":"venue"
},
  "geometry": {"coordinates":[-93.85513,33.956997],"type":"Point"}
}