{
  "type": "Feature",
  "properties": {
    "addr:full":"137 Gandy Ln Mena OK 71953",
    "addr:housenumber":"137",
    "addr:postcode":"71953",
    "addr:street":"Gandy Ln",
    "iso:country":"US",
    "sg:address":"137 Gandy Ln",
    "sg:city":"Mena",
    "sg:classifiers":[
        {
            "category":"Professional",
            "subcategory":"Business Services",
            "type":"Services"
        }
    ],
    "sg:phone":"+1 479 394 3328",
    "sg:postcode":"71953",
    "sg:province":"OK",
    "sg:tags":[
        "embroidery"
    ],
    "wof:name":"Mel's Thread Designs",
    "wof:placetype":"venue"
},
  "geometry": {"coordinates":[-94.17433200000001,34.596343],"type":"Point"}
}