{
  "type": "Feature",
  "properties": {
    "iso:country":"US",
    "sg:address":"2400 Tulsa St",
    "sg:city":"Fort Smith",
    "sg:classifiers":[
        {
            "category":"Restaurant",
            "type":"Food & Drink"
        }
    ],
    "sg:phone":"+1 479 646 5312",
    "sg:postcode":"72901",
    "sg:province":"AR",
    "wof:name":"Reed's Drive-In",
    "wof:placetype":"venue"
},
  "geometry": {"coordinates":[-94.408791,35.335152],"type":"Point"}
}