{
  "type": "Feature",
  "properties": {
    "addr:full":"239 Elmbrook Ter Pearcy AR 71964",
    "addr:housenumber":"239",
    "addr:postcode":"71964",
    "addr:street":"Elmbrook Ter Pearcy",
    "iso:country":"US",
    "sg:address":"239 Elmbrook Ter",
    "sg:city":"Pearcy",
    "sg:classifiers":[
        {
            "category":"Banks & Credit Unions",
            "subcategory":"Bank",
            "type":"Services"
        }
    ],
    "sg:phone":"+1 501 767 9800",
    "sg:postcode":"71964",
    "sg:province":"AR",
    "sg:tags":[
        "loan",
        "real estate"
    ],
    "wof:name":"Able Mortgage & Funding",
    "wof:placetype":"venue"
},
  "geometry": {"coordinates":[-93.22137600000001,34.438419],"type":"Point"}
}