{
  "type": "Feature",
  "properties": {
    "iso:country":"US",
    "sg:address":"19 Willowood Rd",
    "sg:city":"N Little Rock",
    "sg:classifiers":[
        {
            "category":"Organizations",
            "subcategory":"Religious Organization",
            "type":"Services"
        }
    ],
    "sg:phone":"+1 501 955 2170",
    "sg:postcode":"72117",
    "sg:province":"AR",
    "wof:name":"Champions For Christ Mnstrs",
    "wof:placetype":"venue"
},
  "geometry": {"coordinates":[-92.167236,34.748399],"type":"Point"}
}