{
  "type": "Feature",
  "properties": {
    "iso:country":"US",
    "sg:address":"11053 Ervin McGarrah Rd",
    "sg:city":"Lowell",
    "sg:classifiers":[
        {
            "category":"Building & Trades",
            "subcategory":"Construction",
            "type":"Services"
        }
    ],
    "sg:phone":"+1 479 631 8067",
    "sg:postcode":"72745",
    "sg:province":"AR",
    "sg:tags":[
        "contractor"
    ],
    "wof:name":"McKay Roofing",
    "wof:placetype":"venue"
},
  "geometry": {"coordinates":[-94.077018,36.269966],"type":"Point"}
}