{
  "type": "Feature",
  "properties": {
    "iso:country":"US",
    "sg:address":"200 Carmona Rd",
    "sg:city":"Hot Springs National",
    "sg:classifiers":[
        {
            "category":"Organizations",
            "subcategory":"Religious Organization",
            "type":"Services"
        }
    ],
    "sg:phone":"+1 501 922 1030",
    "sg:postcode":"71909",
    "sg:province":"AR",
    "wof:name":"Village United Methdst Church",
    "wof:placetype":"venue"
},
  "geometry": {"coordinates":[-92.997563,34.676764],"type":"Point"}
}