{
  "type": "Feature",
  "properties": {
    "addr:full":"349 Middlebrook Rd Maynard AR 72444",
    "addr:housenumber":"349",
    "addr:postcode":"72444",
    "addr:street":"Middlebrook Rd",
    "iso:country":"US",
    "sg:address":"349 Middlebrook Rd",
    "sg:city":"Maynard",
    "sg:classifiers":[
        {
            "category":"Shopping",
            "subcategory":"Clothing, Apparel, & Fashions",
            "type":"Retail Goods"
        }
    ],
    "sg:phone":"+1 870 647 3136",
    "sg:postcode":"72444",
    "sg:province":"AR",
    "sg:tags":[
        "shirts-custom",
        "made",
        "alterations-clothing"
    ],
    "wof:name":"Cedarbrook Ranch",
    "wof:placetype":"venue"
},
  "geometry": {"coordinates":[-90.92250799999999,36.458691],"type":"Point"}
}