{
  "type": "Feature",
  "properties": {
    "iso:country":"US",
    "sg:address":"402 Fleetwood Dr",
    "sg:city":"Hot Springs National Park",
    "sg:classifiers":[
        {
            "category":"Insurance",
            "subcategory":"Insurance Agent",
            "type":"Services"
        }
    ],
    "sg:phone":"+1 501 760 1010",
    "sg:postcode":"71913",
    "sg:province":"AR",
    "wof:name":"Diamond Lakes Insurance LLC",
    "wof:placetype":"venue"
},
  "geometry": {"coordinates":[-93.150459,34.497466],"type":"Point"}
}