{
  "type": "Feature",
  "properties": {
    "iso:country":"US",
    "sg:address":"707 W 20th St",
    "sg:city":"Stuttgart",
    "sg:classifiers":[
        {
            "category":"Social Services",
            "subcategory":"Job Training",
            "type":"Services"
        },
        {
            "category":"Social Services",
            "subcategory":"Adult Care",
            "type":"Services"
        }
    ],
    "sg:phone":"+1 870 673 1657",
    "sg:postcode":"72160",
    "sg:province":"AR",
    "sg:tags":[
        "nurses-home",
        "nursing",
        "homes-skilled",
        "facility"
    ],
    "wof:name":"Crestpark Retirement Inns",
    "wof:placetype":"venue"
},
  "geometry": {"coordinates":[-91.559955,34.483157],"type":"Point"}
}