{
  "type": "Feature",
  "properties": {
    "iso:country":"US",
    "sg:address":"210 N 8th St",
    "sg:city":"Flippin",
    "sg:classifiers":[
        {
            "category":"Professional",
            "subcategory":"Business Services",
            "type":"Services"
        },
        {
            "category":"Government",
            "subcategory":"Post Office",
            "type":"Public Place"
        }
    ],
    "sg:phone":"+1 800 275 8777",
    "sg:postcode":"72634",
    "sg:province":"AR",
    "sg:tags":[
        "mail",
        "shipping"
    ],
    "sg:website":"http://www.usps.com",
    "wof:name":"USPS - United States Post Office - Flippin Main Office",
    "wof:placetype":"venue"
},
  "geometry": {"coordinates":[-92.58747700000001,36.278562],"type":"Point"}
}