{
  "type": "Feature",
  "properties": {
    "iso:country":"US",
    "sg:address":"4726 Thibault Rd",
    "sg:city":"Little Rock",
    "sg:classifiers":[
        {
            "category":"Retail",
            "subcategory":"Auto Repair",
            "type":"Services"
        }
    ],
    "sg:phone":"+1 501 490 0683",
    "sg:postcode":"72206",
    "sg:province":"AR",
    "sg:tags":[
        "truck",
        "trailer"
    ],
    "wof:name":"Quality Truck & Trailer Repair",
    "wof:placetype":"venue"
},
  "geometry": {"coordinates":[-92.183216,34.685167],"type":"Point"}
}