{
  "type": "Feature",
  "properties": {
    "iso:country":"US",
    "sg:address":"221 Monroe Ave",
    "sg:city":"Camden",
    "sg:classifiers":[
        {
            "category":"Organizations",
            "subcategory":"Religious Organization",
            "type":"Services"
        }
    ],
    "sg:phone":"+1 870 836 5150",
    "sg:postcode":"71701",
    "sg:province":"AR",
    "sg:tags":[
        "church"
    ],
    "wof:name":"Zion Hill Family Life Ctr",
    "wof:placetype":"venue"
},
  "geometry": {"coordinates":[-92.828427,33.589807],"type":"Point"}
}