{
  "type": "Feature",
  "properties": {
    "iso:country":"US",
    "sg:address":"44 Mound City Rd",
    "sg:city":"Marion",
    "sg:classifiers":[
        {
            "category":"Wholesale",
            "subcategory":"Groceries",
            "type":"Manufacturing & Wholesale Goods"
        }
    ],
    "sg:phone":"+1 870 739 2050",
    "sg:postcode":"72364",
    "sg:province":"AR",
    "sg:tags":[
        "grocers-wholesale"
    ],
    "wof:name":"Farmers Marketing Group",
    "wof:placetype":"venue"
},
  "geometry": {"coordinates":[-90.195999,35.214448],"type":"Point"}
}