{
  "type": "Feature",
  "properties": {
    "iso:country":"US",
    "sg:address":"1101 N West Ave",
    "sg:city":"El Dorado",
    "sg:classifiers":[
        {
            "category":"Professional",
            "type":"Services"
        }
    ],
    "sg:phone":"+1 870 863 3712",
    "sg:postcode":"71730",
    "sg:province":"AR",
    "sg:tags":[
        "establishment"
    ],
    "wof:name":"Community Living Arrangements",
    "wof:placetype":"venue"
},
  "geometry": {"coordinates":[-92.665549,33.222023],"type":"Point"}
}