{
  "type": "Feature",
  "properties": {
    "iso:country":"US",
    "sg:address":"455 Gap Rd",
    "sg:city":"Batesville",
    "sg:classifiers":[
        {
            "category":"Recreation",
            "type":"Entertainment"
        }
    ],
    "sg:phone":"+1 870 793 4084",
    "sg:postcode":"72501",
    "sg:province":"AR",
    "sg:tags":[
        "course",
        "golf"
    ],
    "wof:name":"Putt-N-Putt",
    "wof:placetype":"venue"
},
  "geometry": {"coordinates":[-91.59582,35.755785],"type":"Point"}
}