{
  "type": "Feature",
  "properties": {
    "addr:full":"1907 S Buerkle St Stuttgart AR 72160",
    "addr:housenumber":"1907",
    "addr:postcode":"72160",
    "addr:street":"S Buerkle St",
    "iso:country":"US",
    "sg:address":"1907 S Buerkle St",
    "sg:city":"Stuttgart",
    "sg:classifiers":[
        {
            "category":"Real Estate",
            "subcategory":"Real Estate Operator",
            "type":"Services"
        }
    ],
    "sg:phone":"+1 870 673 4013",
    "sg:postcode":"72160",
    "sg:province":"AR",
    "sg:tags":[
        "property",
        "lessor"
    ],
    "wof:name":"Shodan LLC",
    "wof:placetype":"venue"
},
  "geometry": {"coordinates":[-91.55820900000001,34.4848],"type":"Point"}
}