{
  "type": "Feature",
  "properties": {
    "iso:country":"US",
    "sg:address":"2403 County Ave",
    "sg:city":"Texarkana",
    "sg:classifiers":[
        {
            "category":"Arts & Performance",
            "subcategory":"Theater",
            "type":"Entertainment"
        }
    ],
    "sg:phone":"+1 870 779 1122",
    "sg:postcode":"71854",
    "sg:province":"AR",
    "wof:name":"A and JS",
    "wof:placetype":"venue"
},
  "geometry": {"coordinates":[-94.03824400000001,33.446405],"type":"Point"}
}