{
  "type": "Feature",
  "properties": {
    "iso:country":"US",
    "sg:address":"265 W Armstrong St",
    "sg:city":"Eudora",
    "sg:classifiers":[
        {
            "category":"Organizations",
            "subcategory":"Religious Organization",
            "type":"Services"
        }
    ],
    "sg:phone":"+1 870 355 0090",
    "sg:postcode":"71640",
    "sg:province":"AR",
    "sg:tags":[
        "church"
    ],
    "wof:name":"Journey Of My Life Outreach",
    "wof:placetype":"venue"
},
  "geometry": {"coordinates":[-91.26379799999999,33.110078],"type":"Point"}
}