{
  "type": "Feature",
  "properties": {
    "iso:country":"US",
    "sg:address":"21913 I- 30",
    "sg:city":"Bryant",
    "sg:classifiers":[
        {
            "category":"Autos & Motor Vehicles",
            "subcategory":"Motorcycle Sales",
            "type":"Retail Goods"
        }
    ],
    "sg:phone":"+1 501 653 9900",
    "sg:postcode":"72022",
    "sg:province":"AR",
    "sg:tags":[
        "all",
        "terrain"
    ],
    "wof:name":"Little Rock Polaris",
    "wof:placetype":"venue"
},
  "geometry": {"coordinates":[-92.510549,34.613217],"type":"Point"}
}