{
  "type": "Feature",
  "properties": {
    "addr:full":"109 Deposito Paseo Hot Springs Vlg AR 71909",
    "addr:housenumber":"109",
    "addr:postcode":"71909",
    "addr:street":"Paseo Hot",
    "iso:country":"US",
    "sg:address":"109 Deposito Paseo",
    "sg:city":"Hot Springs Vlg",
    "sg:classifiers":[
        {
            "category":"Freight",
            "type":"Transportation"
        }
    ],
    "sg:phone":"+1 501 922 3900",
    "sg:postcode":"71909",
    "sg:province":"AR",
    "sg:tags":[
        "commercial",
        "storage",
        "special"
    ],
    "wof:name":"Village Self Storage",
    "wof:placetype":"venue"
},
  "geometry": {"coordinates":[-92.911777,34.664425],"type":"Point"}
}