{
  "type": "Feature",
  "properties": {
    "addr:full":"3223 Greene Rd 101 Peach Orchard AR 72453",
    "addr:housenumber":"3223;101",
    "addr:postcode":"72453",
    "addr:street":"Greene Rd",
    "iso:country":"US",
    "sg:address":"3223 Greene Rd 101",
    "sg:city":"Peach Orchard",
    "sg:phone":"+1 870 249 3414",
    "sg:postcode":"72453",
    "sg:province":"AR",
    "sg:tags":[
        "farm",
        "rice",
        "soybean"
    ],
    "wof:name":"Lewis Rice",
    "wof:placetype":"venue"
},
  "geometry": {"coordinates":[-90.76586,36.252624],"type":"Point"}
}