{
  "type": "Feature",
  "properties": {
    "iso:country":"US",
    "sg:address":"31 Crestview Dr",
    "sg:city":"Jacksonville",
    "sg:classifiers":[
        {
            "category":"Banks & Credit Unions",
            "subcategory":"Investment Brokerage",
            "type":"Services"
        }
    ],
    "sg:phone":"+1 501 985 2535",
    "sg:postcode":"72076",
    "sg:province":"AR",
    "sg:tags":[
        "stock",
        "bond"
    ],
    "wof:name":"Edward Jones Co",
    "wof:placetype":"venue"
},
  "geometry": {"coordinates":[-92.123059,34.867287],"type":"Point"}
}