{
  "type": "Feature",
  "properties": {
    "iso:country":"US",
    "sg:address":"11200 Arch Street Pike",
    "sg:city":"Little Rock",
    "sg:classifiers":[
        {
            "category":"Shopping",
            "subcategory":"Pharmacy",
            "type":"Retail Goods"
        }
    ],
    "sg:phone":"+1 501 261 7181",
    "sg:postcode":"72206",
    "sg:province":"AR",
    "sg:tags":[
        "drug",
        "store"
    ],
    "wof:name":"Arch Street Pharmacy Inc",
    "wof:placetype":"venue"
},
  "geometry": {"coordinates":[-92.306831,34.645591],"type":"Point"}
}