{
  "type": "Feature",
  "properties": {
    "iso:country":"US",
    "sg:address":"201 N Van Buren St",
    "sg:city":"Little Rock",
    "sg:classifiers":[
        {
            "category":"Personal",
            "subcategory":"Beauty Salon",
            "type":"Services"
        }
    ],
    "sg:phone":"+1 501 666 5970",
    "sg:postcode":"72205",
    "sg:province":"AR",
    "wof:name":"BJH Beauty Salon",
    "wof:placetype":"venue"
},
  "geometry": {"coordinates":[-92.330339,34.753315],"type":"Point"}
}