{
  "type": "Feature",
  "properties": {
    "iso:country":"US",
    "sg:address":"23604 Highway 20",
    "sg:city":"Elaine",
    "sg:classifiers":[
        {
            "category":"Autos & Motor Vehicles",
            "subcategory":"Auto Supplies",
            "type":"Retail Goods"
        },
        {
            "category":"Retail",
            "subcategory":"Auto Repair",
            "type":"Services"
        }
    ],
    "sg:phone":"+1 870 827 3526",
    "sg:postcode":"72333",
    "sg:province":"AR",
    "sg:tags":[
        "tire"
    ],
    "wof:name":"Jimmy's Service Station",
    "wof:placetype":"venue"
},
  "geometry": {"coordinates":[-90.86441,34.314798],"type":"Point"}
}