{
  "type": "Feature",
  "properties": {
    "addr:full":"115 Tabor Ave Camden AR 71701",
    "addr:housenumber":"115",
    "addr:postcode":"71701",
    "addr:street":"Tabor Ave",
    "iso:country":"US",
    "sg:address":"115 Tabor Ave",
    "sg:city":"Camden",
    "sg:classifiers":[
        {
            "category":"Retail",
            "subcategory":"Repair Shop",
            "type":"Services"
        }
    ],
    "sg:phone":"+1 870 837 2774",
    "sg:postcode":"71701",
    "sg:province":"AR",
    "wof:name":"Power Cycle & Atv",
    "wof:placetype":"venue"
},
  "geometry": {"coordinates":[-92.740279,33.608266],"type":"Point"}
}