{
  "type": "Feature",
  "properties": {
    "iso:country":"US",
    "sg:address":"4925 Velvet Ridge",
    "sg:city":"N Little Rock",
    "sg:classifiers":[
        {
            "category":"Professional",
            "type":"Services"
        }
    ],
    "sg:phone":"+1 501 812 5060",
    "sg:postcode":"72116",
    "sg:province":"AR",
    "sg:tags":[
        "establishment"
    ],
    "wof:name":"Best Kept Secrets",
    "wof:placetype":"venue"
},
  "geometry": {"coordinates":[-92.262885,34.801231],"type":"Point"}
}