{
  "type": "Feature",
  "properties": {
    "addr:full":"202 Mimosa Dr El Dorado AR 71730",
    "addr:housenumber":"202",
    "addr:postcode":"71730",
    "addr:street":"Mimosa Dr",
    "iso:country":"US",
    "sg:address":"202 Mimosa Dr",
    "sg:city":"El Dorado",
    "sg:classifiers":[
        {
            "category":"Building & Trades",
            "subcategory":"Landscaping Services",
            "type":"Services"
        }
    ],
    "sg:phone":"+1 870 862 7366",
    "sg:postcode":"71730",
    "sg:province":"AR",
    "wof:name":"Mark Bates",
    "wof:placetype":"venue"
},
  "geometry": {"coordinates":[-92.671582,33.239248],"type":"Point"}
}