{
  "type": "Feature",
  "properties": {
    "iso:country":"US",
    "sg:address":"1301 E Martin Pl",
    "sg:city":"Pine Bluff",
    "sg:classifiers":[
        {
            "category":"Wholesale",
            "subcategory":"Electrical",
            "type":"Manufacturing & Wholesale Goods"
        }
    ],
    "sg:phone":"+1 870 535 3894",
    "sg:postcode":"71601",
    "sg:province":"AR",
    "sg:tags":[
        "communication",
        "radio",
        "system"
    ],
    "wof:name":"Douthit's Radio Svc Inc",
    "wof:placetype":"venue"
},
  "geometry": {"coordinates":[-91.989583,34.218368],"type":"Point"}
}