{
  "type": "Feature",
  "properties": {
    "addr:full":"2100 Stadium Blvd Jonesboro AR 72401",
    "addr:housenumber":"2100",
    "addr:postcode":"72401",
    "addr:street":"Stadium Blvd",
    "iso:country":"US",
    "sg:address":"2100 Stadium Blvd",
    "sg:city":"Jonesboro",
    "sg:classifiers":[
        {
            "category":"Organizations",
            "subcategory":"Religious Organization",
            "type":"Services"
        }
    ],
    "sg:phone":"+1 870 935 5134",
    "sg:postcode":"72401",
    "sg:province":"AR",
    "sg:tags":[
        "church"
    ],
    "wof:name":"Mt Zion Baptist Assn",
    "wof:placetype":"venue"
},
  "geometry": {"coordinates":[-90.66892199999999,35.819213],"type":"Point"}
}