{
  "type": "Feature",
  "properties": {
    "addr:full":"817 E Broadway Glenwood AR 71943",
    "addr:housenumber":"817",
    "addr:postcode":"71943",
    "addr:street":"E Broadway",
    "iso:country":"US",
    "sg:address":"817 E Broadway",
    "sg:city":"Glenwood",
    "sg:classifiers":[
        {
            "category":"Autos & Motor Vehicles",
            "subcategory":"Automobile Sales",
            "type":"Retail Goods"
        }
    ],
    "sg:phone":"+1 870 356 2911",
    "sg:postcode":"71943",
    "sg:province":"AR",
    "sg:tags":[
        "new",
        "car"
    ],
    "wof:name":"Kelley's Cars",
    "wof:placetype":"venue"
},
  "geometry": {"coordinates":[-93.540711,34.327419],"type":"Point"}
}