{
  "type": "Feature",
  "properties": {
    "iso:country":"US",
    "sg:address":"2905 S Walton Blvd",
    "sg:city":"Bentonville",
    "sg:classifiers":[
        {
            "category":"Banks & Credit Unions",
            "subcategory":"Bank",
            "type":"Services"
        }
    ],
    "sg:phone":"+1 479 936 8616",
    "sg:postcode":"72712",
    "sg:province":"AR",
    "sg:tags":[
        "loan",
        "real estate"
    ],
    "sg:website":"www.bankofengland-ar.com",
    "wof:name":"England Lending Inc",
    "wof:placetype":"venue"
},
  "geometry": {"coordinates":[-94.21075999999999,36.342157],"type":"Point"}
}