{
  "type": "Feature",
  "properties": {
    "iso:country":"US",
    "sg:address":"24 Arrowhead Ln",
    "sg:city":"Clarksville",
    "sg:classifiers":[
        {
            "category":"Restaurant",
            "type":"Food & Drink"
        }
    ],
    "sg:phone":"+1 479 754 3028",
    "sg:postcode":"72830",
    "sg:province":"AR",
    "sg:tags":[
        "eating"
    ],
    "wof:name":"Subway",
    "wof:placetype":"venue"
},
  "geometry": {"coordinates":[-93.498462,35.475193],"type":"Point"}
}