{
  "type": "Feature",
  "properties": {
    "iso:country":"US",
    "sg:address":"3 Roberts Pl",
    "sg:city":"Bentonville",
    "sg:classifiers":[
        {
            "category":"Building & Trades",
            "subcategory":"Construction",
            "type":"Services"
        }
    ],
    "sg:phone":"+1 479 595 3040",
    "sg:postcode":"72712",
    "sg:province":"AR",
    "sg:tags":[
        "roofing",
        "industrial",
        "altering",
        "contractor",
        "contractors-commercial",
        "remodeling"
    ],
    "wof:name":"Paragon Remodeling",
    "wof:placetype":"venue"
},
  "geometry": {"coordinates":[-94.18401799999999,36.379541],"type":"Point"}
}