{
  "type": "Feature",
  "properties": {
    "addr:full":"2008 Vaugine St Pine Bluff AR 71601",
    "addr:housenumber":"2008",
    "addr:postcode":"71601",
    "addr:street":"Vaugine St Pine Bluff",
    "iso:country":"US",
    "sg:address":"2008 Vaugine St",
    "sg:city":"Pine Bluff",
    "sg:classifiers":[
        {
            "category":"Organizations",
            "subcategory":"Religious Organization",
            "type":"Services"
        }
    ],
    "sg:phone":"+1 870 534 2227",
    "sg:postcode":"71601",
    "sg:province":"AR",
    "wof:name":"Shiloh Mssionary Baptst Church",
    "wof:placetype":"venue"
},
  "geometry": {"coordinates":[-92.02334999999999,34.232813],"type":"Point"}
}