{
  "type": "Feature",
  "properties": {
    "iso:country":"US",
    "sg:address":"1400 Pershing Hwy",
    "sg:city":"Smackover",
    "sg:classifiers":[
        {
            "category":"Health Services",
            "subcategory":"Doctor",
            "type":"Services"
        }
    ],
    "sg:phone":"+1 870 725 3471",
    "sg:postcode":"71762",
    "sg:province":"AR",
    "sg:tags":[
        "physician",
        "surgeon"
    ],
    "wof:name":"Smackover Family Practice Clnc",
    "wof:placetype":"venue"
},
  "geometry": {"coordinates":[-92.717349,33.353735],"type":"Point"}
}