{
  "type": "Feature",
  "properties": {
    "addr:full":"990 Hwy 62 E Mountain Home AR 72653",
    "addr:housenumber":"990",
    "addr:postcode":"72653",
    "addr:street":"Hwy 62 E",
    "iso:country":"US",
    "sg:address":"990 Hwy 62 E",
    "sg:city":"Mountain Home",
    "sg:classifiers":[
        {
            "category":"Restaurant",
            "type":"Food & Drink"
        }
    ],
    "sg:phone":"+1 870 425 5300",
    "sg:postcode":"72653",
    "sg:province":"AR",
    "sg:tags":[
        "eating"
    ],
    "wof:name":"Home Pride Cafe",
    "wof:placetype":"venue"
},
  "geometry": {"coordinates":[-92.37520000000001,36.347323],"type":"Point"}
}