{
  "type": "Feature",
  "properties": {
    "iso:country":"US",
    "sg:address":"309 S Highway 71",
    "sg:city":"Winslow",
    "sg:classifiers":[
        {
            "category":"Manufacturing",
            "subcategory":"Rubber & Plastics",
            "type":"Manufacturing & Wholesale Goods"
        },
        {
            "category":"Autos & Motor Vehicles",
            "subcategory":"Auto Supplies",
            "type":"Retail Goods"
        },
        {
            "category":"Retail",
            "subcategory":"Auto Repair",
            "type":"Services"
        }
    ],
    "sg:phone":"+1 479 634 2836",
    "sg:postcode":"72959",
    "sg:province":"AR",
    "sg:tags":[
        "recap",
        "retread",
        "tires-wholesale",
        "tire",
        "manufacturer"
    ],
    "sg:website":"http://www.coopertire.com/html/",
    "wof:name":"D & S Body Shop & Towing",
    "wof:placetype":"venue"
},
  "geometry": {"coordinates":[-94.12871,35.799953],"type":"Point"}
}