{
  "type": "Feature",
  "properties": {
    "addr:full":"213 Mountain Pine Rd Hot Springs AR 71913",
    "addr:housenumber":"213",
    "addr:postcode":"71913",
    "addr:street":"Mountain Pine Rd",
    "iso:country":"US",
    "sg:address":"213 Mountain Pine Rd",
    "sg:city":"Hot Springs",
    "sg:classifiers":[
        {
            "category":"Personal",
            "subcategory":"Beauty Salon",
            "type":"Services"
        }
    ],
    "sg:phone":"+1 501 767 1702",
    "sg:postcode":"71913",
    "sg:province":"AR",
    "wof:name":"Sandra's Beauty Shop",
    "wof:placetype":"venue"
},
  "geometry": {"coordinates":[-93.12661900000001,34.506849],"type":"Point"}
}