{
  "type": "Feature",
  "properties": {
    "iso:country":"US",
    "sg:address":"414 E 3rd St",
    "sg:city":"Grove",
    "sg:classifiers":[
        {
            "category":"Restaurant",
            "type":"Food & Drink"
        }
    ],
    "sg:phone":"+1 918 791 9292",
    "sg:postcode":"74344",
    "sg:province":"OK",
    "sg:website":"http://www.raggedys.com",
    "wof:name":"Dollies",
    "wof:placetype":"venue"
},
  "geometry": {"coordinates":[-94.764321,36.597953],"type":"Point"}
}