{
  "type": "Feature",
  "properties": {
    "iso:country":"US",
    "sg:address":"1201 Garland Ave",
    "sg:city":"North Little Rock",
    "sg:classifiers":[
        {
            "category":"Professional",
            "subcategory":"Lawyer & Legal Services",
            "type":"Services"
        }
    ],
    "sg:phone":"+1 501 804 0776",
    "sg:postcode":"72116",
    "sg:province":"AR",
    "wof:name":"Pinson Process Service",
    "wof:placetype":"venue"
},
  "geometry": {"coordinates":[-92.2537,34.786853],"type":"Point"}
}