{
  "type": "Feature",
  "properties": {
    "iso:country":"US",
    "sg:address":"1507 State Hwy 17",
    "sg:city":"Brinkley",
    "sg:classifiers":[
        {
            "category":"Travel",
            "subcategory":"Hotels & Motels",
            "type":"Entertainment"
        }
    ],
    "sg:phone":"+1 870 734 2121",
    "sg:postcode":"72021",
    "sg:province":"AR",
    "wof:name":"Heritage Inn",
    "wof:placetype":"venue"
},
  "geometry": {"coordinates":[-91.196896,34.908681],"type":"Point"}
}