{
  "type": "Feature",
  "properties": {
    "iso:country":"US",
    "sg:address":"605 Baxter Ave",
    "sg:city":"Mountain Home",
    "sg:classifiers":[
        {
            "category":"Restaurant",
            "type":"Food & Drink"
        }
    ],
    "sg:phone":"+1 870 425 2505",
    "sg:postcode":"72653",
    "sg:province":"AR",
    "wof:name":"Country Kettle",
    "wof:placetype":"venue"
},
  "geometry": {"coordinates":[-92.39292399999999,36.357064],"type":"Point"}
}