{
  "type": "Feature",
  "properties": {
    "iso:country":"US",
    "sg:address":"513 Columbia St",
    "sg:city":"Helena",
    "sg:classifiers":[
        {
            "category":"Wholesale",
            "subcategory":"Auto Parts",
            "type":"Manufacturing & Wholesale Goods"
        }
    ],
    "sg:phone":"+1 870 338 6039",
    "sg:postcode":"72342",
    "sg:province":"AR",
    "sg:tags":[
        "station",
        "gasoline"
    ],
    "wof:name":"Texaco",
    "wof:placetype":"venue"
},
  "geometry": {"coordinates":[-90.591303,34.52796],"type":"Point"}
}