{
  "type": "Feature",
  "properties": {
    "addr:full":"903 NW K St Bentonville AR 72712",
    "addr:housenumber":"903",
    "addr:postcode":"72712",
    "addr:street":"Nw K St",
    "iso:country":"US",
    "sg:address":"903 NW K St",
    "sg:city":"Bentonville",
    "sg:classifiers":[
        {
            "category":"Shopping",
            "subcategory":"Gifts & Souvenirs",
            "type":"Retail Goods"
        }
    ],
    "sg:phone":"+1 479 273 7127",
    "sg:postcode":"72712",
    "sg:province":"AR",
    "wof:name":"Party Plus Shoppe",
    "wof:placetype":"venue"
},
  "geometry": {"coordinates":[-94.2251,36.382149],"type":"Point"}
}