{
  "type": "Feature",
  "properties": {
    "iso:country":"US",
    "sg:address":"160 Polk Road 100",
    "sg:city":"Mena",
    "sg:classifiers":[
        {
            "category":"Manufacturing",
            "subcategory":"Buildings",
            "type":"Manufacturing & Wholesale Goods"
        },
        {
            "category":"Building & Trades",
            "subcategory":"Construction",
            "type":"Services"
        }
    ],
    "sg:phone":"+1 479 437 3108",
    "sg:postcode":"71953",
    "sg:province":"AR",
    "sg:tags":[
        "home",
        "builder",
        "contractor"
    ],
    "wof:name":"Mountain Fork Construction",
    "wof:placetype":"venue"
},
  "geometry": {"coordinates":[-94.45032500000001,34.689094],"type":"Point"}
}