{
  "type": "Feature",
  "properties": {
    "iso:country":"US",
    "sg:address":"804 Main St",
    "sg:city":"Melbourne",
    "sg:classifiers":[
        {
            "category":"Shopping",
            "subcategory":"Used Merchandise",
            "type":"Retail Goods"
        }
    ],
    "sg:phone":"+1 870 368 2231",
    "sg:postcode":"72556",
    "sg:province":"AR",
    "wof:name":"W & D Pawn",
    "wof:placetype":"venue"
},
  "geometry": {"coordinates":[-91.896778,36.058552],"type":"Point"}
}