{
  "type": "Feature",
  "properties": {
    "addr:full":"109 N May Dr Dumas AR 71639",
    "addr:housenumber":"109",
    "addr:postcode":"71639",
    "addr:street":"N May Dr Dumas",
    "iso:country":"US",
    "sg:address":"109 N May Dr",
    "sg:city":"Dumas",
    "sg:classifiers":[
        {
            "category":"Organizations",
            "subcategory":"Religious Organization",
            "type":"Services"
        }
    ],
    "sg:phone":"+1 870 382 1481",
    "sg:postcode":"71639",
    "sg:province":"AR",
    "sg:tags":[
        "clergy"
    ],
    "wof:name":"Robert Bass",
    "wof:placetype":"venue"
},
  "geometry": {"coordinates":[-91.480439,33.890184],"type":"Point"}
}