{
  "type": "Feature",
  "properties": {
    "iso:country":"US",
    "sg:address":"100 SW 14th St",
    "sg:city":"Bentonville",
    "sg:classifiers":[
        {
            "category":"Personal",
            "subcategory":"Nail Salon",
            "type":"Services"
        }
    ],
    "sg:phone":"+1 479 268 6500",
    "sg:postcode":"72712",
    "sg:province":"AR",
    "wof:name":"Ocean Nails & Spa",
    "wof:placetype":"venue"
},
  "geometry": {"coordinates":[-94.210517,36.356959],"type":"Point"}
}