{
  "type": "Feature",
  "properties": {
    "iso:country":"US",
    "sg:address":"619 N 9th St",
    "sg:city":"Augusta",
    "sg:classifiers":[
        {
            "category":"Health Services",
            "subcategory":"Health Practitioner",
            "type":"Services"
        }
    ],
    "sg:phone":"+1 870 347 5450",
    "sg:postcode":"72006",
    "sg:province":"AR",
    "sg:tags":[
        "nurse",
        "registry"
    ],
    "wof:name":"IHS Home Care",
    "wof:placetype":"venue"
},
  "geometry": {"coordinates":[-91.35788,35.287738],"type":"Point"}
}