{
  "type": "Feature",
  "properties": {
    "iso:country":"US",
    "sg:address":"551 White Rd",
    "sg:city":"Springdale",
    "sg:classifiers":[
        {
            "category":"Building & Trades",
            "subcategory":"Construction",
            "type":"Services"
        }
    ],
    "sg:phone":"+1 479 751 3884",
    "sg:postcode":"72762",
    "sg:province":"AR",
    "wof:name":"All City Block Inc",
    "wof:placetype":"venue"
},
  "geometry": {"coordinates":[-94.165196,36.19056],"type":"Point"}
}