{
  "type": "Feature",
  "properties": {
    "addr:full":"3418 US Hwy 65 Bus Pine Bluff AR 71601",
    "addr:housenumber":"3418",
    "addr:postcode":"71601",
    "addr:street":"Us Hwy 65 Bus",
    "iso:country":"US",
    "sg:address":"3418 US Hwy 65 Bus",
    "sg:city":"Pine Bluff",
    "sg:classifiers":[
        {
            "category":"Home & Garden",
            "subcategory":"Mobile Homes",
            "type":"Retail Goods"
        }
    ],
    "sg:phone":"+1 870 535 1524",
    "sg:postcode":"71601",
    "sg:province":"AR",
    "wof:name":"J & M Homes",
    "wof:placetype":"venue"
},
  "geometry": {"coordinates":[-92.038698,34.223697],"type":"Point"}
}