{
  "type": "Feature",
  "properties": {
    "addr:full":"22136 I- 30 Bryant AR 72022",
    "addr:housenumber":"22136;30",
    "addr:postcode":"72022",
    "addr:street":"I",
    "iso:country":"US",
    "sg:address":"22136 I- 30",
    "sg:city":"Bryant",
    "sg:classifiers":[
        {
            "category":"Autos & Motor Vehicles",
            "subcategory":"Automobile Sales",
            "type":"Retail Goods"
        }
    ],
    "sg:phone":"+1 501 847 7006",
    "sg:postcode":"72022",
    "sg:province":"AR",
    "sg:tags":[
        "car",
        "dealer"
    ],
    "wof:name":"Cash Auto Sales",
    "wof:placetype":"venue"
},
  "geometry": {"coordinates":[-92.50774699999999,34.614411],"type":"Point"}
}