{
  "type": "Feature",
  "properties": {
    "addr:full":"113 Farr Forrest City AR 72335",
    "addr:housenumber":"113",
    "addr:postcode":"72335",
    "addr:street":"Farr Forrest",
    "iso:country":"US",
    "sg:address":"113 Farr",
    "sg:city":"Forrest City",
    "sg:classifiers":[
        {
            "category":"Organizations",
            "subcategory":"Religious Organization",
            "type":"Services"
        }
    ],
    "sg:phone":"+1 870 630 1688",
    "sg:postcode":"72335",
    "sg:province":"AR",
    "sg:tags":[
        "church"
    ],
    "wof:name":"Taylors Chapel CME Church",
    "wof:placetype":"venue"
},
  "geometry": {"coordinates":[-90.80900699999999,34.998829],"type":"Point"}
}