{
  "type": "Feature",
  "properties": {
    "addr:full":"14309 Cantrell Rd Little Rock AR 72223",
    "addr:housenumber":"14309",
    "addr:postcode":"72223",
    "addr:street":"Cantrell Rd",
    "iso:country":"US",
    "sg:address":"14309 Cantrell Rd",
    "sg:city":"Little Rock",
    "sg:classifiers":[
        {
            "category":"Insurance",
            "subcategory":"Insurance Agent",
            "type":"Services"
        }
    ],
    "sg:phone":"+1 501 221 2128",
    "sg:postcode":"72223",
    "sg:province":"AR",
    "wof:name":"Bill Hinson Insurance",
    "wof:placetype":"venue"
},
  "geometry": {"coordinates":[-92.42995500000001,34.80248],"type":"Point"}
}