{
  "type": "Feature",
  "properties": {
    "iso:country":"US",
    "sg:address":"5519 Sulphur Springs Rd",
    "sg:city":"Pine Bluff",
    "sg:classifiers":[
        {
            "category":"Shopping",
            "type":"Retail Goods"
        }
    ],
    "sg:phone":"+1 870 879 0101",
    "sg:postcode":"71603",
    "sg:province":"AR",
    "sg:tags":[
        "monument"
    ],
    "wof:name":"Arkansas Monument Co",
    "wof:placetype":"venue"
},
  "geometry": {"coordinates":[-92.066667,34.190588],"type":"Point"}
}