{
  "type": "Feature",
  "properties": {
    "iso:country":"US",
    "sg:address":"2306 Pattywood Dr",
    "sg:city":"Bryant",
    "sg:classifiers":[
        {
            "category":"Professional",
            "subcategory":"Engineering",
            "type":"Services"
        }
    ],
    "sg:phone":"+1 501 847 1081",
    "sg:postcode":"72022",
    "sg:province":"AR",
    "wof:name":"IL Service 5842",
    "wof:placetype":"venue"
},
  "geometry": {"coordinates":[-92.48766999999999,34.616645],"type":"Point"}
}