{
  "type": "Feature",
  "properties": {
    "addr:full":"1516 Pratt Rd Little Rock AR 72206",
    "addr:housenumber":"1516",
    "addr:postcode":"72206",
    "addr:street":"Pratt Rd",
    "iso:country":"US",
    "sg:address":"1516 Pratt Rd",
    "sg:city":"Little Rock",
    "sg:classifiers":[
        {
            "category":"Building & Trades",
            "subcategory":"Construction",
            "type":"Services"
        }
    ],
    "sg:phone":"+1 501 888 8943",
    "sg:postcode":"72206",
    "sg:province":"AR",
    "sg:tags":[
        "masonry",
        "contractor"
    ],
    "wof:name":"Dowdy-Norwood Construction",
    "wof:placetype":"venue"
},
  "geometry": {"coordinates":[-92.293373,34.618221],"type":"Point"}
}