{
  "type": "Feature",
  "properties": {
    "addr:full":"800 S Thompson St Springdale AR 72764",
    "addr:housenumber":"800",
    "addr:postcode":"72764",
    "addr:street":"S Thompson St",
    "iso:country":"US",
    "sg:address":"800 S Thompson St",
    "sg:city":"Springdale",
    "sg:classifiers":[
        {
            "category":"Retail",
            "subcategory":"Repair Shop",
            "type":"Services"
        }
    ],
    "sg:phone":"+1 479 927 1988",
    "sg:postcode":"72764",
    "sg:province":"AR",
    "sg:tags":[
        "jewelry"
    ],
    "wof:name":"Wholesale Jewelry Watch",
    "wof:placetype":"venue"
},
  "geometry": {"coordinates":[-94.139002,36.177419],"type":"Point"}
}