{
  "type": "Feature",
  "properties": {
    "iso:country":"US",
    "sg:address":"1203 Nettleton Cir",
    "sg:city":"Jonesboro",
    "sg:classifiers":[
        {
            "category":"Shopping",
            "subcategory":"Computers & Home Electronics",
            "type":"Retail Goods"
        }
    ],
    "sg:phone":"+1 501 562 3554",
    "sg:postcode":"72401",
    "sg:province":"AR",
    "wof:name":"Datafix Inc",
    "wof:placetype":"venue"
},
  "geometry": {"coordinates":[-90.72163999999999,35.831681],"type":"Point"}
}