{
  "type": "Feature",
  "properties": {
    "iso:country":"US",
    "sg:address":"509 Maple St",
    "sg:city":"Crossett",
    "sg:classifiers":[
        {
            "category":"Professional",
            "subcategory":"Lawyer & Legal Services",
            "type":"Services"
        }
    ],
    "sg:phone":"+1 870 364 2047",
    "sg:postcode":"71635",
    "sg:province":"AR",
    "sg:tags":[
        "attorney"
    ],
    "wof:name":"Martin Jeremy",
    "wof:placetype":"venue"
},
  "geometry": {"coordinates":[-91.95183400000001,33.130275],"type":"Point"}
}