{
  "type": "Feature",
  "properties": {
    "iso:country":"US",
    "sg:address":"111 E Walnut St",
    "sg:city":"Paris",
    "sg:classifiers":[
        {
            "category":"Professional",
            "subcategory":"Lawyer & Legal Services",
            "type":"Services"
        }
    ],
    "sg:phone":"+1 479 963 3996",
    "sg:postcode":"72855",
    "sg:province":"AR",
    "wof:name":"Barham Law Offices",
    "wof:placetype":"venue"
},
  "geometry": {"coordinates":[-93.728965,35.292174],"type":"Point"}
}