{
  "type": "Feature",
  "properties": {
    "addr:full":"8211 Bronco Ln Sherwood AR 72120",
    "addr:housenumber":"8211",
    "addr:postcode":"72120",
    "addr:street":"Bronco Ln",
    "iso:country":"US",
    "sg:address":"8211 Bronco Ln",
    "sg:city":"Sherwood",
    "sg:classifiers":[
        {
            "category":"Retail",
            "subcategory":"Laundry & Dry Cleaning",
            "type":"Services"
        }
    ],
    "sg:phone":"+1 501 834 4346",
    "sg:postcode":"72120",
    "sg:province":"AR",
    "sg:tags":[
        "cleaners",
        "rug",
        "carpet"
    ],
    "wof:name":"Chem Dry By Wisdom Inc",
    "wof:placetype":"venue"
},
  "geometry": {"coordinates":[-92.21143600000001,34.830879],"type":"Point"}
}