{
  "type": "Feature",
  "properties": {
    "iso:country":"US",
    "sg:address":"1736 Bailey Pl",
    "sg:city":"Malvern",
    "sg:classifiers":[
        {
            "category":"Professional",
            "type":"Services"
        }
    ],
    "sg:phone":"+1 501 337 8348",
    "sg:postcode":"72104",
    "sg:province":"AR",
    "wof:name":"Bailey Queen",
    "wof:placetype":"venue"
},
  "geometry": {"coordinates":[-92.79258,34.355445],"type":"Point"}
}