{
  "type": "Feature",
  "properties": {
    "iso:country":"US",
    "sg:address":"7771 White Dr",
    "sg:city":"Cord",
    "sg:classifiers":[
        {
            "category":"Manufacturing",
            "subcategory":"Metals",
            "type":"Manufacturing & Wholesale Goods"
        }
    ],
    "sg:phone":"+1 870 799 3905",
    "sg:postcode":"72524",
    "sg:province":"AR",
    "sg:tags":[
        "steel",
        "distributor",
        "metal-wholesale",
        "warehouse",
        "fabricator",
        "mill",
        "manufacturer"
    ],
    "wof:name":"Csi Steel Fabrication & Erection",
    "wof:placetype":"venue"
},
  "geometry": {"coordinates":[-91.410816,35.83215],"type":"Point"}
}