{
  "type": "Feature",
  "properties": {
    "iso:country":"US",
    "sg:address":"1905 Kizer Dr",
    "sg:city":"Pocahontas",
    "sg:classifiers":[
        {
            "category":"Wholesale",
            "subcategory":"Hardware",
            "type":"Manufacturing & Wholesale Goods"
        }
    ],
    "sg:phone":"+1 870 892 9868",
    "sg:postcode":"72455",
    "sg:province":"AR",
    "wof:name":"Asa Enterprises",
    "wof:placetype":"venue"
},
  "geometry": {"coordinates":[-90.985714,36.250849],"type":"Point"}
}