{
  "type": "Feature",
  "properties": {
    "iso:country":"US",
    "sg:address":"4524 Jack Creek Rd",
    "sg:city":"Booneville",
    "sg:classifiers":[
        {
            "category":"Government",
            "subcategory":"Fire Station",
            "type":"Public Place"
        }
    ],
    "sg:phone":"+1 479 675 2585",
    "sg:postcode":"72927",
    "sg:province":"AR",
    "sg:tags":[
        "protection"
    ],
    "wof:name":"Grayson Fire Assoc",
    "wof:placetype":"venue"
},
  "geometry": {"coordinates":[-93.872622,35.059748],"type":"Point"}
}