{
  "type": "Feature",
  "properties": {
    "iso:country":"US",
    "sg:address":"300 Sycamore St",
    "sg:city":"Augusta",
    "sg:classifiers":[
        {
            "category":"Government",
            "subcategory":"Office",
            "type":"Public Place"
        }
    ],
    "sg:phone":"+1 870 347 2362",
    "sg:postcode":"72006",
    "sg:province":"AR",
    "sg:tags":[
        "federal"
    ],
    "wof:name":"Natural Resources Conservation",
    "wof:placetype":"venue"
},
  "geometry": {"coordinates":[-91.365685,35.279976],"type":"Point"}
}