{
  "type": "Feature",
  "properties": {
    "addr:full":"1385 California Ave SW Camden AR 71701",
    "addr:housenumber":"1385",
    "addr:postcode":"71701",
    "addr:street":"California Ave Sw",
    "iso:country":"US",
    "sg:address":"1385 California Ave SW",
    "sg:city":"Camden",
    "sg:classifiers":[
        {
            "category":"Restaurant",
            "type":"Food & Drink"
        }
    ],
    "sg:phone":"+1 870 837 1707",
    "sg:postcode":"71701",
    "sg:province":"AR",
    "wof:name":"T J's Place",
    "wof:placetype":"venue"
},
  "geometry": {"coordinates":[-92.85451399999999,33.558636],"type":"Point"}
}