{
  "type": "Feature",
  "properties": {
    "iso:country":"US",
    "sg:address":"1385 California Ave SW",
    "sg:city":"Camden",
    "sg:classifiers":[
        {
            "category":"Restaurant",
            "type":"Food & Drink"
        }
    ],
    "sg:phone":"+1 870 837 1707",
    "sg:postcode":"71701",
    "sg:province":"AR",
    "wof:name":"T J's Place",
    "wof:placetype":"venue"
},
  "geometry": {"coordinates":[-92.854514,33.558636],"type":"Point"}
}