{
  "type": "Feature",
  "properties": {
    "addr:full":"408 W 2nd Ave Pine Bluff AR 71601",
    "addr:housenumber":"408",
    "addr:postcode":"71601",
    "addr:street":"W 2Nd Ave",
    "iso:country":"US",
    "sg:address":"408 W 2nd Ave",
    "sg:city":"Pine Bluff",
    "sg:classifiers":[
        {
            "category":"Wholesale",
            "subcategory":"Machinery & Supplies",
            "type":"Manufacturing & Wholesale Goods"
        }
    ],
    "sg:phone":"+1 870 535 1871",
    "sg:postcode":"71601",
    "sg:province":"AR",
    "sg:tags":[
        "janitor"
    ],
    "wof:name":"T W Pelton & Co",
    "wof:placetype":"venue"
},
  "geometry": {"coordinates":[-92.00748,34.228298],"type":"Point"}
}