{
  "type": "Feature",
  "properties": {
    "addr:full":"504 Cedar St Crossett AR 71635",
    "addr:housenumber":"504",
    "addr:postcode":"71635",
    "addr:street":"Cedar St",
    "iso:country":"US",
    "sg:address":"504 Cedar St",
    "sg:city":"Crossett",
    "sg:classifiers":[
        {
            "category":"Social Services",
            "subcategory":"Child Care",
            "type":"Services"
        }
    ],
    "sg:phone":"+1 870 364 7645",
    "sg:postcode":"71635",
    "sg:province":"AR",
    "sg:tags":[
        "kindergarten",
        "academic",
        "school",
        "day"
    ],
    "wof:name":"Lil Scholar Pre School",
    "wof:placetype":"venue"
},
  "geometry": {"coordinates":[-91.954739,33.129823],"type":"Point"}
}