{
  "type": "Feature",
  "properties": {
    "iso:country":"US",
    "sg:address":"107 Hague Ave",
    "sg:city":"Berryville",
    "sg:classifiers":[
        {
            "category":"Retail",
            "subcategory":"Auto Repair",
            "type":"Services"
        }
    ],
    "sg:phone":"+1 870 423 7203",
    "sg:postcode":"72616",
    "sg:province":"AR",
    "sg:tags":[
        "repairing",
        "automobile"
    ],
    "wof:name":"L & J Automotive",
    "wof:placetype":"venue"
},
  "geometry": {"coordinates":[-93.567287,36.367227],"type":"Point"}
}