{
  "type": "Feature",
  "properties": {
    "addr:full":"2 Leprechaun Ln Alexander AR 72002",
    "addr:housenumber":"2",
    "addr:postcode":"72002",
    "addr:street":"Leprechaun Ln",
    "iso:country":"US",
    "sg:address":"2 Leprechaun Ln",
    "sg:city":"Alexander",
    "sg:classifiers":[
        {
            "category":"Building & Trades",
            "subcategory":"Landscaping Services",
            "type":"Services"
        }
    ],
    "sg:phone":"+1 501 920 2075",
    "sg:postcode":"72002",
    "sg:province":"AR",
    "sg:tags":[
        "landscape",
        "contractor"
    ],
    "wof:name":"Longinotti's Lawncare",
    "wof:placetype":"venue"
},
  "geometry": {"coordinates":[-92.413236,34.626514],"type":"Point"}
}