{
  "type": "Feature",
  "properties": {
    "iso:country":"US",
    "sg:address":"111 Kelly Ann St",
    "sg:city":"Bald Knob",
    "sg:classifiers":[
        {
            "category":"Retail",
            "subcategory":"Repair Shop",
            "type":"Services"
        }
    ],
    "sg:phone":"+1 501 724 8886",
    "sg:postcode":"72010",
    "sg:province":"AR",
    "wof:name":"Sumler Lock & Key Service",
    "wof:placetype":"venue"
},
  "geometry": {"coordinates":[-91.577092,35.327348],"type":"Point"}
}