{
  "type": "Feature",
  "properties": {
    "iso:country":"US",
    "sg:address":"1300 N Charley's Loop Rd",
    "sg:city":"Camden",
    "sg:classifiers":[
        {
            "category":"Building & Trades",
            "subcategory":"Construction",
            "type":"Services"
        }
    ],
    "sg:phone":"+1 870 231 5711",
    "sg:postcode":"71701",
    "sg:province":"AR",
    "sg:tags":[
        "general",
        "contractor"
    ],
    "wof:name":"William Braswell Construction",
    "wof:placetype":"venue"
},
  "geometry": {"coordinates":[-92.854581,33.518607],"type":"Point"}
}