{
  "type": "Feature",
  "properties": {
    "iso:country":"US",
    "sg:address":"1820 W 13th St",
    "sg:city":"Little Rock",
    "sg:classifiers":[
        {
            "category":"Personal",
            "subcategory":"Beauty Salon",
            "type":"Services"
        }
    ],
    "sg:phone":"+1 501 376 9489",
    "sg:postcode":"72202",
    "sg:province":"AR",
    "sg:tags":[
        "shop"
    ],
    "wof:name":"Star Performance",
    "wof:placetype":"venue"
},
  "geometry": {"coordinates":[-92.29329199999999,34.738687],"type":"Point"}
}