{
  "type": "Feature",
  "properties": {
    "addr:full":"432 Ouachita Ave Hot Springs National AR 71901",
    "addr:housenumber":"432",
    "addr:postcode":"71901",
    "addr:street":"Ouachita Ave",
    "iso:country":"US",
    "sg:address":"432 Ouachita Ave",
    "sg:city":"Hot Springs National",
    "sg:classifiers":[
        {
            "category":"Professional",
            "subcategory":"Business Services",
            "type":"Services"
        }
    ],
    "sg:phone":"+1 501 623 2030",
    "sg:postcode":"71901",
    "sg:province":"AR",
    "wof:name":"Arkansas Cama Technology",
    "wof:placetype":"venue"
},
  "geometry": {"coordinates":[-93.057951,34.505963],"type":"Point"}
}