{
  "type": "Feature",
  "properties": {
    "iso:country":"US",
    "sg:address":"5 Churchwell Ct",
    "sg:city":"Bentonville",
    "sg:classifiers":[
        {
            "category":"Building & Trades",
            "subcategory":"Construction",
            "type":"Services"
        }
    ],
    "sg:phone":"+1 479 273 5401",
    "sg:postcode":"72712",
    "sg:province":"AR",
    "sg:tags":[
        "general",
        "contractor"
    ],
    "wof:name":"Patriot Builders Inc",
    "wof:placetype":"venue"
},
  "geometry": {"coordinates":[-94.169573,36.378392],"type":"Point"}
}