{
  "type": "Feature",
  "properties": {
    "addr:full":"747 Georgia Ridge Rd Searcy AR 72143",
    "addr:housenumber":"747",
    "addr:postcode":"72143",
    "addr:street":"Georgia Ridge Rd",
    "iso:country":"US",
    "sg:address":"747 Georgia Ridge Rd",
    "sg:city":"Searcy",
    "sg:classifiers":[
        {
            "category":"Recreation",
            "type":"Entertainment"
        }
    ],
    "sg:phone":"+1 501 556 5917",
    "sg:postcode":"72143",
    "sg:province":"AR",
    "wof:name":"English Arena",
    "wof:placetype":"venue"
},
  "geometry": {"coordinates":[-91.91359799999999,35.310475],"type":"Point"}
}