{
  "type": "Feature",
  "properties": {
    "iso:country":"US",
    "sg:address":"747 Georgia Ridge Rd",
    "sg:city":"Searcy",
    "sg:classifiers":[
        {
            "category":"Recreation",
            "type":"Entertainment"
        }
    ],
    "sg:phone":"+1 501 556 5917",
    "sg:postcode":"72143",
    "sg:province":"AR",
    "wof:name":"English Arena",
    "wof:placetype":"venue"
},
  "geometry": {"coordinates":[-91.913598,35.310475],"type":"Point"}
}