{
  "type": "Feature",
  "properties": {
    "iso:country":"US",
    "sg:address":"201 E Broadway",
    "sg:city":"Glenwood",
    "sg:classifiers":[
        {
            "category":"Organizations",
            "subcategory":"Religious Organization",
            "type":"Services"
        }
    ],
    "sg:phone":"+1 870 356 4960",
    "sg:postcode":"71943",
    "sg:province":"AR",
    "wof:name":"Glenwood Spanish Sda Church",
    "wof:placetype":"venue"
},
  "geometry": {"coordinates":[-93.550926,34.32631],"type":"Point"}
}