{
  "type": "Feature",
  "properties": {
    "iso:country":"US",
    "sg:address":"2201 Pine St",
    "sg:city":"Arkadelphia",
    "sg:classifiers":[
        {
            "category":"Retail",
            "subcategory":"Auto Rental",
            "type":"Services"
        }
    ],
    "sg:phone":"+1 870 246 5991",
    "sg:postcode":"71923",
    "sg:province":"AR",
    "sg:tags":[
        "renting",
        "automobile"
    ],
    "wof:name":"Rent & Go Auto Rental Inc",
    "wof:placetype":"venue"
},
  "geometry": {"coordinates":[-93.076143,34.123122],"type":"Point"}
}