{
  "type": "Feature",
  "properties": {
    "iso:country":"US",
    "sg:address":"603 Agnes Rd",
    "sg:city":"El Dorado",
    "sg:classifiers":[
        {
            "category":"Building & Trades",
            "subcategory":"Construction",
            "type":"Services"
        }
    ],
    "sg:phone":"+1 870 862 6810",
    "sg:postcode":"71730",
    "sg:province":"AR",
    "sg:tags":[
        "television",
        "contractor",
        "company",
        "cable",
        "telephone"
    ],
    "wof:name":"Wonder Construction",
    "wof:placetype":"venue"
},
  "geometry": {"coordinates":[-92.70001,33.244471],"type":"Point"}
}