{
  "type": "Feature",
  "properties": {
    "iso:country":"US",
    "sg:address":"1030 Spatz Cir",
    "sg:city":"Conway",
    "sg:classifiers":[
        {
            "category":"Professional",
            "subcategory":"Computer Services",
            "type":"Services"
        }
    ],
    "sg:phone":"+1 501 450 9945",
    "sg:postcode":"72034",
    "sg:province":"AR",
    "sg:tags":[
        "datum"
    ],
    "wof:name":"Zany Creations",
    "wof:placetype":"venue"
},
  "geometry": {"coordinates":[-92.460713,35.065135],"type":"Point"}
}