{
  "type": "Feature",
  "properties": {
    "iso:country":"US",
    "sg:address":"13637 Degraff Rd",
    "sg:city":"Rogers",
    "sg:classifiers":[
        {
            "category":"Shopping",
            "subcategory":"Computers & Home Electronics",
            "type":"Retail Goods"
        }
    ],
    "sg:phone":"+1 479 451 9038",
    "sg:postcode":"72756",
    "sg:province":"AR",
    "sg:tags":[
        "equipment",
        "dealer",
        "software"
    ],
    "wof:name":"Moore's Computer World",
    "wof:placetype":"venue"
},
  "geometry": {"coordinates":[-94.060732,36.427165],"type":"Point"}
}