{
  "type": "Feature",
  "properties": {
    "addr:full":"4890 Grant County 14 Grapevine AR 72057",
    "addr:housenumber":"4890;14",
    "addr:postcode":"72057",
    "addr:street":"Grant",
    "iso:country":"US",
    "sg:address":"4890 Grant County 14",
    "sg:city":"Grapevine",
    "sg:classifiers":[
        {
            "category":"Place Of Worship",
            "subcategory":"Church",
            "type":"Public Place"
        },
        {
            "category":"Place Of Worship",
            "type":"Public Place"
        }
    ],
    "sg:phone":"+1 870 942 1827",
    "sg:postcode":"72057",
    "sg:province":"AR",
    "sg:tags":[
        "churches-presbyterian-arp",
        "churches-presbyterian"
    ],
    "wof:name":"Pine Ridge Cumberland Presbytr",
    "wof:placetype":"venue"
},
  "geometry": {"coordinates":[-92.318786,34.176624],"type":"Point"}
}