{
  "type": "Feature",
  "properties": {
    "iso:country":"US",
    "sg:address":"7 Gerald Rd",
    "sg:city":"Conway",
    "sg:classifiers":[
        {
            "category":"Wholesale",
            "subcategory":"Farm Supplies",
            "type":"Manufacturing & Wholesale Goods"
        }
    ],
    "sg:phone":"+1 501 327 7776",
    "sg:postcode":"72032",
    "sg:province":"AR",
    "sg:tags":[
        "raw",
        "product",
        "material"
    ],
    "wof:name":"Chies Whitehorse Riding Stable",
    "wof:placetype":"venue"
},
  "geometry": {"coordinates":[-92.37046,35.083975],"type":"Point"}
}