{
  "type": "Feature",
  "properties": {
    "iso:country":"US",
    "sg:address":"1101 Cavanaugh Rd",
    "sg:city":"Fort Smith",
    "sg:classifiers":[
        {
            "category":"Organizations",
            "subcategory":"Religious Organization",
            "type":"Services"
        }
    ],
    "sg:phone":"+1 479 646 1591",
    "sg:postcode":"72908",
    "sg:province":"AR",
    "wof:name":"Cavanaugh Baptist Church",
    "wof:placetype":"venue"
},
  "geometry": {"coordinates":[-94.42499599999999,35.312286],"type":"Point"}
}