{
  "type": "Feature",
  "properties": {
    "iso:country":"US",
    "sg:address":"2802 W Kingshighway",
    "sg:city":"Paragould",
    "sg:classifiers":[
        {
            "category":"Shopping",
            "subcategory":"Department Store",
            "type":"Retail Goods"
        },
        {
            "category":"Shopping",
            "subcategory":"Discount & Variety Stores",
            "type":"Retail Goods"
        },
        {
            "category":"Home & Garden",
            "subcategory":"Furniture",
            "type":"Retail Goods"
        },
        {
            "category":"Retail",
            "subcategory":"Photofinishing",
            "type":"Services"
        },
        {
            "category":"Autos & Motor Vehicles",
            "subcategory":"Auto Supplies",
            "type":"Retail Goods"
        },
        {
            "category":"Shopping",
            "subcategory":"Pharmacy",
            "type":"Retail Goods"
        }
    ],
    "sg:phone":"+1 870 236 9707",
    "sg:postcode":"72450",
    "sg:province":"AR",
    "sg:tags":[
        "photo",
        "finishing",
        "tire"
    ],
    "sg:website":"http://www.walmart.com",
    "wof:name":"Walmart Supercenter",
    "wof:placetype":"venue"
},
  "geometry": {"coordinates":[-90.52351899999999,36.059944],"type":"Point"}
}