{
  "type": "Feature",
  "properties": {
    "addr:full":"955 N Curtis Ave Pea Ridge AR 72751",
    "addr:housenumber":"955",
    "addr:postcode":"72751",
    "addr:street":"N Curtis Ave",
    "iso:country":"US",
    "sg:address":"955 N Curtis Ave",
    "sg:city":"Pea Ridge",
    "sg:classifiers":[
        {
            "category":"Real Estate",
            "subcategory":"Real Estate Agent",
            "type":"Services"
        }
    ],
    "sg:phone":"+1 479 451 1470",
    "sg:postcode":"72751",
    "sg:province":"AR",
    "wof:name":"Good Faith Realty",
    "wof:placetype":"venue"
},
  "geometry": {"coordinates":[-94.115234,36.450848],"type":"Point"}
}