{
  "type": "Feature",
  "properties": {
    "iso:country":"US",
    "sg:address":"100 Greenbrier Cir",
    "sg:city":"Crossett",
    "sg:classifiers":[
        {
            "category":"Professional",
            "subcategory":"Accounting & Tax Preparation",
            "type":"Services"
        }
    ],
    "sg:phone":"+1 870 304 3450",
    "sg:postcode":"71635",
    "sg:province":"AR",
    "sg:tags":[
        "return",
        "filing"
    ],
    "wof:name":"Junior's Tax Svc",
    "wof:placetype":"venue"
},
  "geometry": {"coordinates":[-91.966658,33.114539],"type":"Point"}
}