{
  "type": "Feature",
  "properties": {
    "iso:country":"US",
    "sg:address":"105 Park St",
    "sg:city":"Monticello",
    "sg:classifiers":[
        {
            "category":"Shopping",
            "subcategory":"Clothing, Apparel, & Fashions",
            "type":"Retail Goods"
        }
    ],
    "sg:phone":"+1 870 367 3961",
    "sg:postcode":"71655",
    "sg:province":"AR",
    "sg:website":"www.catofashions.com",
    "wof:name":"Cato",
    "wof:placetype":"venue"
},
  "geometry": {"coordinates":[-91.797493,33.64768],"type":"Point"}
}