{
  "type": "Feature",
  "properties": {
    "addr:full":"139 Ridge Rd Pocahontas AR 72455",
    "addr:housenumber":"139",
    "addr:postcode":"72455",
    "addr:street":"Ridge Rd",
    "iso:country":"US",
    "sg:address":"139 Ridge Rd",
    "sg:city":"Pocahontas",
    "sg:classifiers":[
        {
            "category":"Farming",
            "subcategory":"Livestock Farm",
            "type":"Manufacturing & Wholesale Goods"
        }
    ],
    "sg:phone":"+1 870 892 5778",
    "sg:postcode":"72455",
    "sg:province":"AR",
    "sg:tags":[
        "beef",
        "feedlot",
        "cattle"
    ],
    "wof:name":"Bill G Fort",
    "wof:placetype":"venue"
},
  "geometry": {"coordinates":[-90.965498,36.27644],"type":"Point"}
}