{
  "type": "Feature",
  "properties": {
    "iso:country":"US",
    "sg:address":"441 S Main St",
    "sg:city":"Waldron",
    "sg:classifiers":[
        {
            "category":"Food & Beverages",
            "subcategory":"Groceries & Convenience Stores",
            "type":"Retail Goods"
        }
    ],
    "sg:phone":"+1 479 637 4565",
    "sg:postcode":"72958",
    "sg:province":"AR",
    "wof:name":"Corner Mart",
    "wof:placetype":"venue"
},
  "geometry": {"coordinates":[-94.091112,34.8983],"type":"Point"}
}