{
  "type": "Feature",
  "properties": {
    "iso:country":"US",
    "sg:address":"201 Sharp Dr",
    "sg:city":"Jacksonville",
    "sg:classifiers":[
        {
            "category":"Education",
            "subcategory":"School",
            "type":"Public Place"
        }
    ],
    "sg:phone":"+1 501 241 2107",
    "sg:postcode":"72076",
    "sg:province":"AR",
    "sg:tags":[
        "middle"
    ],
    "wof:name":"Jacksonville Middle School",
    "wof:placetype":"venue"
},
  "geometry": {"coordinates":[-92.125122,34.866718],"type":"Point"}
}