{
  "type": "Feature",
  "properties": {
    "iso:country":"US",
    "sg:address":"220 W 5th St",
    "sg:city":"Hope",
    "sg:classifiers":[
        {
            "category":"Manufacturing",
            "subcategory":"Rubber & Plastics",
            "type":"Manufacturing & Wholesale Goods"
        }
    ],
    "sg:phone":"+1 870 777 5759",
    "sg:postcode":"71801",
    "sg:province":"AR",
    "sg:tags":[
        "pressure",
        "plastics-vacuum",
        "forming-manufacturers"
    ],
    "sg:website":"http://www.tolber.com",
    "wof:name":"Pyramid Plastics Inc",
    "wof:placetype":"venue"
},
  "geometry": {"coordinates":[-93.59232799999999,33.664766],"type":"Point"}
}