{
  "type": "Feature",
  "properties": {
    "iso:country":"US",
    "sg:address":"1509 Oakwood Cir",
    "sg:city":"White Hall",
    "sg:classifiers":[
        {
            "category":"Shopping",
            "subcategory":"Gifts & Souvenirs",
            "type":"Retail Goods"
        }
    ],
    "sg:phone":"+1 870 247 4713",
    "sg:postcode":"71602",
    "sg:province":"AR",
    "sg:tags":[
        "collectible"
    ],
    "wof:name":"Victorian Accents",
    "wof:placetype":"venue"
},
  "geometry": {"coordinates":[-92.117035,34.294541],"type":"Point"}
}