{
  "type": "Feature",
  "properties": {
    "iso:country":"US",
    "sg:address":"1595 County Line Rd",
    "sg:city":"Springdale",
    "sg:classifiers":[
        {
            "category":"Farming",
            "subcategory":"Farm",
            "type":"Manufacturing & Wholesale Goods"
        }
    ],
    "sg:phone":"+1 479 248 7508",
    "sg:postcode":"72762",
    "sg:province":"AR",
    "wof:name":"Danelle Carpenter Farms",
    "wof:placetype":"venue"
},
  "geometry": {"coordinates":[-94.20568400000001,36.212121],"type":"Point"}
}