{
  "type": "Feature",
  "properties": {
    "addr:full":"18115 Fawn Tree Dr Little Rock AR 72210",
    "addr:housenumber":"18115",
    "addr:postcode":"72210",
    "addr:street":"Fawn Tree Dr",
    "iso:country":"US",
    "sg:address":"18115 Fawn Tree Dr",
    "sg:city":"Little Rock",
    "sg:classifiers":[
        {
            "category":"Building & Trades",
            "subcategory":"Construction",
            "type":"Services"
        }
    ],
    "sg:phone":"+1 501 455 6378",
    "sg:postcode":"72210",
    "sg:province":"AR",
    "sg:tags":[
        "house"
    ],
    "wof:name":"Del Rio Construction Stev",
    "wof:placetype":"venue"
},
  "geometry": {"coordinates":[-92.437978,34.662114],"type":"Point"}
}