{
  "type": "Feature",
  "properties": {
    "iso:country":"US",
    "sg:address":"77 Kaney Ridge Rd",
    "sg:city":"Greenbrier",
    "sg:classifiers":[
        {
            "category":"Building & Trades",
            "subcategory":"Construction",
            "type":"Services"
        }
    ],
    "sg:phone":"+1 501 679 3934",
    "sg:postcode":"72058",
    "sg:province":"AR",
    "sg:tags":[
        "nonresidential"
    ],
    "wof:name":"J&B Developers Inc",
    "wof:placetype":"venue"
},
  "geometry": {"coordinates":[-92.410699,35.172787],"type":"Point"}
}