{
  "type": "Feature",
  "properties": {
    "addr:full":"2191 US Hwy 425 S Hamburg AR 71646",
    "addr:housenumber":"2191",
    "addr:postcode":"71646",
    "addr:street":"Us Hwy 425 S",
    "iso:country":"US",
    "sg:address":"2191 US Hwy 425 S",
    "sg:city":"Hamburg",
    "sg:classifiers":[
        {
            "category":"Personal",
            "subcategory":"Beauty Salon",
            "type":"Services"
        }
    ],
    "sg:phone":"+1 870 853 8426",
    "sg:postcode":"71646",
    "sg:province":"AR",
    "sg:tags":[
        "shop"
    ],
    "wof:name":"Dennas Hair Cuttin Corral",
    "wof:placetype":"venue"
},
  "geometry": {"coordinates":[-91.815895,33.143724],"type":"Point"}
}