{
  "type": "Feature",
  "properties": {
    "iso:country":"US",
    "sg:address":"11401 N Rodney Parham Rd",
    "sg:city":"Little Rock",
    "sg:classifiers":[
        {
            "category":"Insurance",
            "subcategory":"Insurance Agent",
            "type":"Services"
        }
    ],
    "sg:phone":"+1 501 223 9923",
    "sg:postcode":"72212",
    "sg:province":"AR",
    "wof:name":"Stewart Agency Incorporated",
    "wof:placetype":"venue"
},
  "geometry": {"coordinates":[-92.401099,34.772339],"type":"Point"}
}