{
  "type": "Feature",
  "properties": {
    "iso:country":"US",
    "sg:address":"105 Rosedale Rd",
    "sg:city":"Searcy",
    "sg:classifiers":[
        {
            "category":"Professional",
            "type":"Services"
        }
    ],
    "sg:phone":"+1 501 230 0293",
    "sg:postcode":"72143",
    "sg:province":"AR",
    "wof:name":"Dent Specialist",
    "wof:placetype":"venue"
},
  "geometry": {"coordinates":[-91.790253,35.243143],"type":"Point"}
}