{
  "type": "Feature",
  "properties": {
    "iso:country":"US",
    "sg:address":"824 Pryor Dr",
    "sg:city":"West Memphis",
    "sg:classifiers":[
        {
            "category":"Organizations",
            "subcategory":"Religious Organization",
            "type":"Services"
        }
    ],
    "sg:phone":"+1 870 735 4009",
    "sg:postcode":"72301",
    "sg:province":"AR",
    "sg:tags":[
        "church"
    ],
    "wof:name":"Rosewood United Methodist Chr",
    "wof:placetype":"venue"
},
  "geometry": {"coordinates":[-90.204009,35.156264],"type":"Point"}
}