{
  "type": "Feature",
  "properties": {
    "addr:full":"902 SE 5th St Bentonville AR 72712",
    "addr:housenumber":"902",
    "addr:postcode":"72712",
    "addr:street":"Se 5Th St",
    "iso:country":"US",
    "sg:address":"902 SE 5th St",
    "sg:city":"Bentonville",
    "sg:classifiers":[
        {
            "category":"Professional",
            "type":"Services"
        }
    ],
    "sg:phone":"+1 479 464 4111",
    "sg:postcode":"72712",
    "sg:province":"AR",
    "sg:tags":[
        "establishment"
    ],
    "wof:name":"5GLLC",
    "wof:placetype":"venue"
},
  "geometry": {"coordinates":[-94.197748,36.367497],"type":"Point"}
}