{
  "type": "Feature",
  "properties": {
    "iso:country":"US",
    "sg:address":"10101 Mabelvale Plaza Dr",
    "sg:city":"Little Rock",
    "sg:classifiers":[
        {
            "category":"Professional",
            "subcategory":"Accounting & Tax Preparation",
            "type":"Services"
        }
    ],
    "sg:phone":"+1 501 565 3434",
    "sg:postcode":"72209",
    "sg:province":"AR",
    "sg:tags":[
        "return",
        "filing"
    ],
    "wof:name":"Jackson Hewitt Tax Svc",
    "wof:placetype":"venue"
},
  "geometry": {"coordinates":[-92.37846,34.677584],"type":"Point"}
}