{
  "type": "Feature",
  "properties": {
    "iso:country":"US",
    "sg:address":"523 N 6th St",
    "sg:city":"Blytheville",
    "sg:classifiers":[
        {
            "category":"Shopping",
            "subcategory":"Pharmacy",
            "type":"Retail Goods"
        }
    ],
    "sg:phone":"+1 870 762 2024",
    "sg:postcode":"72315",
    "sg:province":"AR",
    "sg:tags":[
        "drug",
        "store"
    ],
    "wof:name":"Owen Drugs",
    "wof:placetype":"venue"
},
  "geometry": {"coordinates":[-89.910085,35.932251],"type":"Point"}
}