{
  "type": "Feature",
  "properties": {
    "iso:country":"US",
    "sg:address":"424 Church St",
    "sg:city":"Charleston",
    "sg:classifiers":[
        {
            "category":"Personal",
            "subcategory":"Beauty Salon",
            "type":"Services"
        }
    ],
    "sg:phone":"+1 479 965 7711",
    "sg:postcode":"72933",
    "sg:province":"AR",
    "wof:name":"Marsha's Beauty Express",
    "wof:placetype":"venue"
},
  "geometry": {"coordinates":[-94.04120899999999,35.300998],"type":"Point"}
}