{
  "type": "Feature",
  "properties": {
    "iso:country":"US",
    "sg:address":"8005 Camp Robinson Rd",
    "sg:city":"N Little Rock",
    "sg:classifiers":[
        {
            "category":"Government",
            "subcategory":"Office",
            "type":"Public Place"
        }
    ],
    "sg:phone":"+1 501 771 2579",
    "sg:postcode":"72118",
    "sg:province":"AR",
    "sg:tags":[
        "federal",
        "security"
    ],
    "wof:name":"US Naval Reserve",
    "wof:placetype":"venue"
},
  "geometry": {"coordinates":[-92.276847,34.819659],"type":"Point"}
}