{
  "type": "Feature",
  "properties": {
    "iso:country":"US",
    "sg:address":"176 Mullins St Apt 5",
    "sg:city":"Tyronza",
    "sg:classifiers":[
        {
            "category":"Real Estate",
            "subcategory":"Real Estate Operator",
            "type":"Services"
        }
    ],
    "sg:phone":"+1 870 487 2555",
    "sg:postcode":"72386",
    "sg:province":"AR",
    "sg:tags":[
        "apartment"
    ],
    "wof:name":"Tyronza Housing Authority",
    "wof:placetype":"venue"
},
  "geometry": {"coordinates":[-90.354794,35.489234],"type":"Point"}
}