{
  "type": "Feature",
  "properties": {
    "iso:country":"US",
    "sg:address":"3220 N State Line Ave",
    "sg:city":"Texarkana",
    "sg:classifiers":[
        {
            "category":"Retail",
            "subcategory":"Repair Shop",
            "type":"Services"
        }
    ],
    "sg:phone":"+1 870 774 1445",
    "sg:postcode":"71854",
    "sg:province":"TX",
    "sg:tags":[
        "upholsterer"
    ],
    "wof:name":"Bruces Classic Upholstery",
    "wof:placetype":"venue"
},
  "geometry": {"coordinates":[-94.043037,33.454093],"type":"Point"}
}