{
  "type": "Feature",
  "properties": {
    "iso:country":"US",
    "sg:address":"423 Williams St",
    "sg:city":"Branch",
    "sg:classifiers":[
        {
            "category":"Restaurant",
            "type":"Food & Drink"
        }
    ],
    "sg:phone":"+1 479 965 2254",
    "sg:postcode":"72928",
    "sg:province":"AR",
    "sg:tags":[
        "eating"
    ],
    "wof:name":"Dairy Diner",
    "wof:placetype":"venue"
},
  "geometry": {"coordinates":[-93.95318399999999,35.310047],"type":"Point"}
}