{
  "type": "Feature",
  "properties": {
    "iso:country":"US",
    "sg:address":"12641 Hwy 298",
    "sg:city":"Benton",
    "sg:classifiers":[
        {
            "category":"Organizations",
            "subcategory":"Religious Organization",
            "type":"Services"
        }
    ],
    "sg:phone":"+1 501 794 2215",
    "sg:postcode":"72019",
    "sg:province":"AR",
    "wof:name":"Old Union Baptist Church",
    "wof:placetype":"venue"
},
  "geometry": {"coordinates":[-92.691314,34.690171],"type":"Point"}
}