{
  "type": "Feature",
  "properties": {
    "iso:country":"US",
    "sg:address":"1 N Bass St",
    "sg:city":"Greenwood",
    "sg:classifiers":[
        {
            "category":"Health Services",
            "subcategory":"Clinic",
            "type":"Services"
        }
    ],
    "sg:phone":"+1 479 782 0527",
    "sg:postcode":"72936",
    "sg:province":"AR",
    "sg:tags":[
        "specialty",
        "outpatient"
    ],
    "wof:name":"Transcreen",
    "wof:placetype":"venue"
},
  "geometry": {"coordinates":[-94.257981,35.213474],"type":"Point"}
}