{
  "type": "Feature",
  "properties": {
    "iso:country":"US",
    "sg:address":"110 E 5th St",
    "sg:city":"El Dorado",
    "sg:classifiers":[
        {
            "category":"Arts & Performance",
            "subcategory":"Theater",
            "type":"Entertainment"
        },
        {
            "category":"Museum",
            "type":"Entertainment"
        }
    ],
    "sg:phone":"+1 870 862 5474",
    "sg:postcode":"71730",
    "sg:province":"AR",
    "sg:tags":[
        "theatrical",
        "art",
        "producer",
        "information",
        "organization",
        "gallery"
    ],
    "wof:name":"South Arkansas Arts Center",
    "wof:placetype":"venue"
},
  "geometry": {"coordinates":[-92.663381,33.221921],"type":"Point"}
}