{
  "type": "Feature",
  "properties": {
    "iso:country":"US",
    "sg:address":"711 Towne Oaks Dr",
    "sg:city":"Little Rock",
    "sg:classifiers":[
        {
            "category":"Insurance",
            "subcategory":"Insurance Agent",
            "type":"Services"
        }
    ],
    "sg:phone":"+1 501 225 8528",
    "sg:postcode":"72227",
    "sg:province":"AR",
    "wof:name":"M & R Insurance Co",
    "wof:placetype":"venue"
},
  "geometry": {"coordinates":[-92.377833,34.760998],"type":"Point"}
}