{
  "type": "Feature",
  "properties": {
    "addr:full":"6929 John F Kennedy Blvd North Little Rock AR 72116",
    "addr:housenumber":"6929",
    "addr:postcode":"72116",
    "addr:street":"John F Kennedy Blvd",
    "iso:country":"US",
    "sg:address":"6929 John F Kennedy Blvd",
    "sg:city":"North Little Rock",
    "sg:classifiers":[
        {
            "category":"Restaurant",
            "type":"Food & Drink"
        }
    ],
    "sg:menulink":"http://www.allmenus.com/ar/hill/80306-dominos-pizza/menu/",
    "sg:phone":"+1 501 834 2600",
    "sg:postcode":"72116",
    "sg:province":"AR",
    "sg:tags":[
        "american",
        "wing",
        "pizza"
    ],
    "wof:name":"Domino's Pizza",
    "wof:placetype":"venue"
},
  "geometry": {"coordinates":[-92.23907199999999,34.819081],"type":"Point"}
}