{
  "type": "Feature",
  "properties": {
    "iso:country":"US",
    "sg:address":"4063 Hwy 62 E",
    "sg:city":"Mountain Home",
    "sg:classifiers":[
        {
            "category":"Organizations",
            "subcategory":"Community Association",
            "type":"Services"
        }
    ],
    "sg:phone":"+1 870 492 5600",
    "sg:postcode":"72653",
    "sg:province":"AR",
    "sg:tags":[
        "club"
    ],
    "wof:name":"Royal 66 Theater & Subs",
    "wof:placetype":"venue"
},
  "geometry": {"coordinates":[-92.321158,36.370974],"type":"Point"}
}