{
  "type": "Feature",
  "properties": {
    "iso:country":"US",
    "sg:address":"112 W 3rd St",
    "sg:city":"Little Rock",
    "sg:classifiers":[
        {
            "category":"Restaurant",
            "type":"Food & Drink"
        }
    ],
    "sg:phone":"+1 501 324 4076",
    "sg:postcode":"72201",
    "sg:province":"AR",
    "wof:name":"Gourmet Brew & Bagels",
    "wof:placetype":"venue"
},
  "geometry": {"coordinates":[-92.271171,34.746273],"type":"Point"}
}