{
  "type": "Feature",
  "properties": {
    "iso:country":"US",
    "sg:address":"2503 S Dallas St",
    "sg:city":"Fort Smith",
    "sg:classifiers":[
        {
            "category":"Professional",
            "type":"Services"
        }
    ],
    "sg:phone":"+1 479 782 2428",
    "sg:postcode":"72901",
    "sg:province":"AR",
    "wof:name":"Jame Huynh",
    "wof:placetype":"venue"
},
  "geometry": {"coordinates":[-94.41069,35.353466],"type":"Point"}
}