{
  "type": "Feature",
  "properties": {
    "iso:country":"US",
    "sg:address":"1626 Shipps Ferry Rd",
    "sg:city":"Mountain Home",
    "sg:classifiers":[
        {
            "category":"Building & Trades",
            "subcategory":"Construction",
            "type":"Services"
        }
    ],
    "sg:phone":"+1 870 424 3339",
    "sg:postcode":"72653",
    "sg:province":"AR",
    "sg:tags":[
        "contractor"
    ],
    "wof:name":"Lake Country Homes",
    "wof:placetype":"venue"
},
  "geometry": {"coordinates":[-92.378291,36.240245],"type":"Point"}
}