{
  "type": "Feature",
  "properties": {
    "iso:country":"US",
    "sg:address":"509 N College Ave",
    "sg:city":"Fayetteville",
    "sg:classifiers":[
        {
            "category":"Professional",
            "subcategory":"Lawyer & Legal Services",
            "type":"Services"
        },
        {
            "category":"Banks & Credit Unions",
            "subcategory":"Financial Services",
            "type":"Services"
        }
    ],
    "sg:phone":"+1 479 521 7727",
    "sg:postcode":"72701",
    "sg:province":"AR",
    "sg:tags":[
        "attorney",
        "law",
        "family",
        "personal",
        "injury",
        "bankruptcy"
    ],
    "wof:name":"Ken Osborne",
    "wof:placetype":"venue"
},
  "geometry": {"coordinates":[-94.157696,36.070032],"type":"Point"}
}