{
  "type": "Feature",
  "properties": {
    "iso:country":"US",
    "sg:address":"9300 Treasure Hill Rd",
    "sg:city":"Little Rock",
    "sg:classifiers":[
        {
            "category":"Professional",
            "subcategory":"Management & Consulting",
            "type":"Services"
        }
    ],
    "sg:phone":"+1 501 227 7705",
    "sg:postcode":"72227",
    "sg:province":"AR",
    "sg:tags":[
        "business"
    ],
    "wof:name":"Another Level Consulting Group",
    "wof:placetype":"venue"
},
  "geometry": {"coordinates":[-92.37752399999999,34.761075],"type":"Point"}
}