{
  "type": "Feature",
  "properties": {
    "iso:country":"US",
    "sg:address":"415 S Rose St",
    "sg:city":"Sheridan",
    "sg:classifiers":[
        {
            "category":"Real Estate",
            "subcategory":"Real Estate Operator",
            "type":"Services"
        }
    ],
    "sg:phone":"+1 870 942 4814",
    "sg:postcode":"72150",
    "sg:province":"AR",
    "sg:tags":[
        "apartment"
    ],
    "wof:name":"Heritage Manor Of Sheridan",
    "wof:placetype":"venue"
},
  "geometry": {"coordinates":[-92.403086,34.30369],"type":"Point"}
}