{
  "type": "Feature",
  "properties": {
    "iso:country":"US",
    "sg:address":"710 E Main St",
    "sg:city":"Clarksville",
    "sg:classifiers":[
        {
            "category":"Government",
            "subcategory":"Office",
            "type":"Public Place"
        }
    ],
    "sg:phone":"+1 479 754 6488",
    "sg:postcode":"72830",
    "sg:province":"AR",
    "sg:tags":[
        "village"
    ],
    "wof:name":"Clarksville City Inspector",
    "wof:placetype":"venue"
},
  "geometry": {"coordinates":[-93.45037499999999,35.470967],"type":"Point"}
}