{
  "type": "Feature",
  "properties": {
    "iso:country":"US",
    "sg:address":"440 N Duff Ave",
    "sg:city":"Sulphur Springs",
    "sg:classifiers":[
        {
            "category":"Shopping",
            "subcategory":"Used Merchandise",
            "type":"Retail Goods"
        }
    ],
    "sg:phone":"+1 479 298 3844",
    "sg:postcode":"72768",
    "sg:province":"AR",
    "sg:tags":[
        "flea",
        "market"
    ],
    "wof:name":"Hearts Desire",
    "wof:placetype":"venue"
},
  "geometry": {"coordinates":[-94.462017,36.486696],"type":"Point"}
}