{
  "type": "Feature",
  "properties": {
    "iso:country":"US",
    "sg:address":"12019 Fortson Rd",
    "sg:city":"Jacksonville",
    "sg:classifiers":[
        {
            "category":"Freight",
            "type":"Transportation"
        }
    ],
    "sg:phone":"+1 501 988 9924",
    "sg:postcode":"72076",
    "sg:province":"AR",
    "sg:tags":[
        "operator",
        "local",
        "trucking"
    ],
    "wof:name":"Johnson Trucking",
    "wof:placetype":"venue"
},
  "geometry": {"coordinates":[-92.211288,34.982625],"type":"Point"}
}