{
  "type": "Feature",
  "properties": {
    "iso:country":"US",
    "sg:address":"411 N Main St",
    "sg:city":"North Little Rock",
    "sg:classifiers":[
        {
            "category":"Home & Garden",
            "subcategory":"Furniture",
            "type":"Retail Goods"
        }
    ],
    "sg:phone":"+1 501 372 2984",
    "sg:postcode":"72114",
    "sg:province":"AR",
    "sg:tags":[
        "household",
        "appliance"
    ],
    "wof:name":"Twin City Furniture and Appl",
    "wof:placetype":"venue"
},
  "geometry": {"coordinates":[-92.267749,34.757958],"type":"Point"}
}