{
  "type": "Feature",
  "properties": {
    "iso:country":"US",
    "sg:address":"801 W Locust St",
    "sg:city":"Cabot",
    "sg:classifiers":[
        {
            "category":"Real Estate",
            "subcategory":"Real Estate Agent",
            "type":"Services"
        }
    ],
    "sg:phone":"+1 501 843 4473",
    "sg:postcode":"72023",
    "sg:province":"AR",
    "wof:name":"Century 21",
    "wof:placetype":"venue"
},
  "geometry": {"coordinates":[-92.022941,34.979747],"type":"Point"}
}