{
  "type": "Feature",
  "properties": {
    "addr:full":"685 E Main St Piggott AR 72454",
    "addr:housenumber":"685",
    "addr:postcode":"72454",
    "addr:street":"E Main St",
    "iso:country":"US",
    "sg:address":"685 E Main St",
    "sg:city":"Piggott",
    "sg:classifiers":[
        {
            "category":"Wholesale",
            "subcategory":"Tobacco Products",
            "type":"Manufacturing & Wholesale Goods"
        },
        {
            "category":"Shopping",
            "subcategory":"Tobacco",
            "type":"Retail Goods"
        }
    ],
    "sg:phone":"+1 870 598 5783",
    "sg:postcode":"72454",
    "sg:province":"AR",
    "sg:tags":[
        "cigarette",
        "cigar",
        "dealer"
    ],
    "wof:name":"Tobacco Superstore 34",
    "wof:placetype":"venue"
},
  "geometry": {"coordinates":[-90.182903,36.381743],"type":"Point"}
}