{
  "type": "Feature",
  "properties": {
    "iso:country":"US",
    "sg:address":"3155 S Reynolds Rd",
    "sg:city":"Bauxite",
    "sg:classifiers":[
        {
            "category":"Building & Trades",
            "subcategory":"Construction",
            "type":"Services"
        }
    ],
    "sg:phone":"+1 501 602 5556",
    "sg:postcode":"72011",
    "sg:province":"AR",
    "sg:tags":[
        "road",
        "contractor"
    ],
    "wof:name":"Cranford Construction Co",
    "wof:placetype":"venue"
},
  "geometry": {"coordinates":[-92.495609,34.564556],"type":"Point"}
}