{
  "type": "Feature",
  "properties": {
    "iso:country":"US",
    "sg:address":"3521 E Nettleton Ave",
    "sg:city":"Jonesboro",
    "sg:classifiers":[
        {
            "category":"Professional",
            "subcategory":"Computer Services",
            "type":"Services"
        }
    ],
    "sg:phone":"+1 870 933 2664",
    "sg:postcode":"72401",
    "sg:province":"AR",
    "sg:tags":[
        "internet"
    ],
    "sg:website":"www.moneyinaflash.net",
    "wof:name":"MONEYINAFLASH.NET",
    "wof:placetype":"venue"
},
  "geometry": {"coordinates":[-90.66249,35.82827],"type":"Point"}
}