{
  "type": "Feature",
  "properties": {
    "iso:country":"US",
    "sg:address":"2129 S 56th St",
    "sg:city":"Fort Smith",
    "sg:classifiers":[
        {
            "category":"Shopping",
            "subcategory":"Computers & Home Electronics",
            "type":"Retail Goods"
        }
    ],
    "sg:phone":"+1 479 478 8844",
    "sg:postcode":"72903",
    "sg:province":"AR",
    "wof:name":"Computer Pros",
    "wof:placetype":"venue"
},
  "geometry": {"coordinates":[-94.370852,35.35932],"type":"Point"}
}