{
  "type": "Feature",
  "properties": {
    "iso:country":"US",
    "sg:address":"1510 Mill St",
    "sg:city":"Conway",
    "sg:classifiers":[
        {
            "category":"Professional",
            "subcategory":"Lawyer & Legal Services",
            "type":"Services"
        }
    ],
    "sg:phone":"+1 501 329 8730",
    "sg:postcode":"72034",
    "sg:province":"AR",
    "sg:tags":[
        "attorney",
        "practice"
    ],
    "wof:name":"Vaden, Marcus",
    "wof:placetype":"venue"
},
  "geometry": {"coordinates":[-92.443947,35.095363],"type":"Point"}
}