{
  "type": "Feature",
  "properties": {
    "iso:country":"US",
    "sg:address":"1400 W Markham St",
    "sg:city":"Little Rock",
    "sg:classifiers":[
        {
            "category":"Professional",
            "subcategory":"Advertising",
            "type":"Services"
        }
    ],
    "sg:phone":"+1 501 666 8926",
    "sg:postcode":"72201",
    "sg:province":"AR",
    "sg:tags":[
        "counselor",
        "management",
        "agency",
        "relations",
        "public"
    ],
    "sg:website":"www.sellsclark.com",
    "wof:name":"Sells Clark",
    "wof:placetype":"venue"
},
  "geometry": {"coordinates":[-92.286882,34.75006],"type":"Point"}
}