{
  "type": "Feature",
  "properties": {
    "iso:country":"US",
    "sg:address":"1885 E Harold St",
    "sg:city":"Fayetteville",
    "sg:classifiers":[
        {
            "category":"Professional",
            "subcategory":"Business Services",
            "type":"Services"
        }
    ],
    "sg:phone":"+1 479 582 4702",
    "sg:postcode":"72703",
    "sg:province":"AR",
    "wof:name":"Lanier Assoc Co",
    "wof:placetype":"venue"
},
  "geometry": {"coordinates":[-94.13425,36.109458],"type":"Point"}
}