{
  "type": "Feature",
  "properties": {
    "iso:country":"US",
    "sg:address":"1520 E Main St",
    "sg:city":"Siloam Springs",
    "sg:classifiers":[
        {
            "category":"Retail",
            "subcategory":"Auto Repair",
            "type":"Services"
        }
    ],
    "sg:phone":"+1 479 524 5711",
    "sg:postcode":"72761",
    "sg:province":"OK",
    "sg:tags":[
        "body",
        "automobile",
        "painting"
    ],
    "wof:name":"Finn's Body Shop & Towing",
    "wof:placetype":"venue"
},
  "geometry": {"coordinates":[-94.52673,36.181312],"type":"Point"}
}