{
  "type": "Feature",
  "properties": {
    "iso:country":"US",
    "sg:address":"2710 Rife Medical Ln",
    "sg:city":"Rogers",
    "sg:classifiers":[
        {
            "category":"Health Services",
            "subcategory":"Doctor",
            "type":"Services"
        },
        {
            "category":"Health Services",
            "subcategory":"Hospital",
            "type":"Services"
        }
    ],
    "sg:phone":"+1 479 338 0200",
    "sg:postcode":"72758",
    "sg:province":"AR",
    "sg:website":"www.mercy4u.com",
    "wof:name":"Mercy Medical Center",
    "wof:placetype":"venue"
},
  "geometry": {"coordinates":[-94.182189,36.304842],"type":"Point"}
}