{
  "type": "Feature",
  "properties": {
    "iso:country":"US",
    "sg:address":"637 Scales Ave SE",
    "sg:city":"Camden",
    "sg:classifiers":[
        {
            "category":"Retail",
            "subcategory":"Auto Repair",
            "type":"Services"
        }
    ],
    "sg:phone":"+1 870 836 5900",
    "sg:postcode":"71701",
    "sg:province":"AR",
    "sg:tags":[
        "repairing",
        "automobile"
    ],
    "wof:name":"S & S Automotive",
    "wof:placetype":"venue"
},
  "geometry": {"coordinates":[-92.819706,33.576075],"type":"Point"}
}