{
  "type": "Feature",
  "properties": {
    "addr:full":"701 Hwy 289 Horseshoe Bend AR 72512",
    "addr:housenumber":"701",
    "addr:postcode":"72512",
    "addr:street":"Hwy 289;Bend",
    "iso:country":"US",
    "sg:address":"701 Hwy 289",
    "sg:city":"Horseshoe Bend",
    "sg:classifiers":[
        {
            "category":"Shopping",
            "subcategory":"Gifts & Souvenirs",
            "type":"Retail Goods"
        }
    ],
    "sg:phone":"+1 870 670 5279",
    "sg:postcode":"72512",
    "sg:province":"AR",
    "sg:tags":[
        "shop"
    ],
    "wof:name":"Cottage Square",
    "wof:placetype":"venue"
},
  "geometry": {"coordinates":[-91.767257,36.240043],"type":"Point"}
}