{
  "type": "Feature",
  "properties": {
    "addr:full":"250 Hempstead 322 Rd Nashville AR 71852",
    "addr:housenumber":"250;322",
    "addr:postcode":"71852",
    "addr:street":"Hempstead;Rd",
    "iso:country":"US",
    "sg:address":"250 Hempstead 322 Rd",
    "sg:city":"Nashville",
    "sg:classifiers":[
        {
            "category":"Farming",
            "subcategory":"Farm",
            "type":"Manufacturing & Wholesale Goods"
        }
    ],
    "sg:phone":"+1 870 845 1850",
    "sg:postcode":"71852",
    "sg:province":"AR",
    "wof:name":"Double T Farms",
    "wof:placetype":"venue"
},
  "geometry": {"coordinates":[-93.812584,33.880953],"type":"Point"}
}