{
  "type": "Feature",
  "properties": {
    "addr:full":"1932 Hwy 62 E Mountain Home AR 72653",
    "addr:housenumber":"1932",
    "addr:postcode":"72653",
    "addr:street":"Hwy 62 E",
    "iso:country":"US",
    "sg:address":"1932 Hwy 62 E",
    "sg:city":"Mountain Home",
    "sg:classifiers":[
        {
            "category":"Retail",
            "subcategory":"Auto Repair",
            "type":"Services"
        }
    ],
    "sg:phone":"+1 870 425 2231",
    "sg:postcode":"72653",
    "sg:province":"AR",
    "sg:tags":[
        "wrecker"
    ],
    "wof:name":"Donnie's Wrecker Svc",
    "wof:placetype":"venue"
},
  "geometry": {"coordinates":[-92.34988,36.35594],"type":"Point"}
}