{
  "type": "Feature",
  "properties": {
    "iso:country":"US",
    "sg:address":"801 Central Ave",
    "sg:city":"Hot Springs National",
    "sg:classifiers":[
        {
            "category":"Professional",
            "type":"Services"
        }
    ],
    "sg:phone":"+1 501 321 1972",
    "sg:postcode":"71901",
    "sg:province":"AR",
    "wof:name":"H & Creative Concepts Inc",
    "wof:placetype":"venue"
},
  "geometry": {"coordinates":[-93.054062,34.509432],"type":"Point"}
}