{
  "type": "Feature",
  "properties": {
    "iso:country":"US",
    "sg:address":"502 Oak St",
    "sg:city":"Conway",
    "sg:classifiers":[
        {
            "category":"Professional",
            "type":"Services"
        }
    ],
    "sg:phone":"+1 501 327 3222",
    "sg:postcode":"72032",
    "sg:province":"AR",
    "sg:tags":[
        "establishment"
    ],
    "wof:name":"Hoppin Johns",
    "wof:placetype":"venue"
},
  "geometry": {"coordinates":[-92.433298,35.091815],"type":"Point"}
}