{
  "type": "Feature",
  "properties": {
    "addr:full":"2130 Landover Trl Conway AR 72032",
    "addr:housenumber":"2130",
    "addr:postcode":"72032",
    "addr:street":"Landover Trl",
    "iso:country":"US",
    "sg:address":"2130 Landover Trl",
    "sg:city":"Conway",
    "sg:classifiers":[
        {
            "category":"Professional",
            "subcategory":"Management & Consulting",
            "type":"Services"
        },
        {
            "category":"Education",
            "subcategory":"Special Training",
            "type":"Public Place"
        }
    ],
    "sg:phone":"+1 501 269 3111",
    "sg:postcode":"72032",
    "sg:province":"AR",
    "sg:tags":[
        "consultant",
        "educational"
    ],
    "wof:name":"Triad Educational Services",
    "wof:placetype":"venue"
},
  "geometry": {"coordinates":[-92.45408999999999,35.106129],"type":"Point"}
}