{
  "type": "Feature",
  "properties": {
    "addr:full":"21797 Ridgeview Ln Rogers AR 72756",
    "addr:housenumber":"21797",
    "addr:postcode":"72756",
    "addr:street":"Ridgeview Ln",
    "iso:country":"US",
    "sg:address":"21797 Ridgeview Ln",
    "sg:city":"Rogers",
    "sg:classifiers":[
        {
            "category":"Building & Trades",
            "subcategory":"Construction",
            "type":"Services"
        }
    ],
    "sg:phone":"+1 479 789 2510",
    "sg:postcode":"72756",
    "sg:province":"AR",
    "sg:tags":[
        "house"
    ],
    "wof:name":"TKB Construction Inc",
    "wof:placetype":"venue"
},
  "geometry": {"coordinates":[-93.901546,36.303001],"type":"Point"}
}