{
  "type": "Feature",
  "properties": {
    "addr:full":"84 Court St Marion AR 72364",
    "addr:housenumber":"84",
    "addr:postcode":"72364",
    "addr:street":"Court St",
    "iso:country":"US",
    "sg:address":"84 Court St",
    "sg:city":"Marion",
    "sg:classifiers":[
        {
            "category":"Professional",
            "subcategory":"Lawyer & Legal Services",
            "type":"Services"
        }
    ],
    "sg:phone":"+1 870 739 2588",
    "sg:postcode":"72364",
    "sg:province":"AR",
    "sg:tags":[
        "attorney"
    ],
    "wof:name":"Donaldson & Donaldson",
    "wof:placetype":"venue"
},
  "geometry": {"coordinates":[-90.196668,35.214506],"type":"Point"}
}