{
  "type": "Feature",
  "properties": {
    "addr:full":"857 State Hwy 52 Eudora AR 71640",
    "addr:housenumber":"857",
    "addr:postcode":"71640",
    "addr:street":"State Hwy 52",
    "iso:country":"US",
    "sg:address":"857 State Hwy 52",
    "sg:city":"Eudora",
    "sg:phone":"+1 870 355 2269",
    "sg:postcode":"71640",
    "sg:province":"AR",
    "sg:tags":[
        "wheat",
        "farm",
        "cash",
        "grain",
        "soybean",
        "rice"
    ],
    "wof:name":"Johnny Reginelli",
    "wof:placetype":"venue"
},
  "geometry": {"coordinates":[-91.34364100000001,33.051265],"type":"Point"}
}