{
  "type": "Feature",
  "properties": {
    "iso:country":"US",
    "sg:address":"432 Country Club Rd",
    "sg:city":"Pocahontas",
    "sg:classifiers":[
        {
            "category":"Shopping",
            "subcategory":"Luggage & Leather Goods",
            "type":"Retail Goods"
        }
    ],
    "sg:phone":"+1 870 892 5200",
    "sg:postcode":"72455",
    "sg:province":"AR",
    "sg:tags":[
        "case"
    ],
    "sg:website":"www.weickcustomcases.com",
    "wof:name":"Weick Custom Cases Inc",
    "wof:placetype":"venue"
},
  "geometry": {"coordinates":[-90.996515,36.291848],"type":"Point"}
}