{
  "type": "Feature",
  "properties": {
    "addr:full":"10708 Sycamore Rd Lowell AR 72745",
    "addr:housenumber":"10708",
    "addr:postcode":"72745",
    "addr:street":"Sycamore Rd",
    "iso:country":"US",
    "sg:address":"10708 Sycamore Rd",
    "sg:city":"Lowell",
    "sg:classifiers":[
        {
            "category":"Building & Trades",
            "subcategory":"Construction",
            "type":"Services"
        }
    ],
    "sg:phone":"+1 479 636 9519",
    "sg:postcode":"72745",
    "sg:province":"AR",
    "sg:tags":[
        "residential"
    ],
    "wof:name":"McKenna Construction",
    "wof:placetype":"venue"
},
  "geometry": {"coordinates":[-94.05295599999999,36.275068],"type":"Point"}
}