{
  "type": "Feature",
  "properties": {
    "iso:country":"US",
    "sg:address":"408 Fire Tower Rd",
    "sg:city":"Bald Knob",
    "sg:classifiers":[
        {
            "category":"Organizations",
            "subcategory":"Religious Organization",
            "type":"Services"
        }
    ],
    "sg:phone":"+1 501 724 2507",
    "sg:postcode":"72010",
    "sg:province":"AR",
    "wof:name":"Centennial Baptist Church",
    "wof:placetype":"venue"
},
  "geometry": {"coordinates":[-91.54122099999999,35.405014],"type":"Point"}
}