{
  "type": "Feature",
  "properties": {
    "addr:full":"608 S Jefferson St De Witt AR 72042",
    "addr:housenumber":"608",
    "addr:postcode":"72042",
    "addr:street":"S Jefferson St",
    "iso:country":"US",
    "sg:address":"608 S Jefferson St",
    "sg:city":"De Witt",
    "sg:classifiers":[
        {
            "category":"Retail",
            "subcategory":"Auto Repair",
            "type":"Services"
        }
    ],
    "sg:phone":"+1 870 946 0334",
    "sg:postcode":"72042",
    "sg:province":"AR",
    "sg:tags":[
        "wrecker"
    ],
    "wof:name":"Theis Enterprise",
    "wof:placetype":"venue"
},
  "geometry": {"coordinates":[-91.33771400000001,34.290007],"type":"Point"}
}