{
  "type": "Feature",
  "properties": {
    "iso:country":"US",
    "sg:address":"1300 N Thompson St Ste M",
    "sg:city":"Springdale",
    "sg:classifiers":[
        {
            "category":"Professional",
            "subcategory":"Employment Agencies",
            "type":"Services"
        }
    ],
    "sg:phone":"+1 479 750 3212",
    "sg:postcode":"72764",
    "sg:province":"AR",
    "sg:website":"www.laborready.com",
    "wof:name":"Labor Ready",
    "wof:placetype":"venue"
},
  "geometry": {"coordinates":[-94.13809999999999,36.195999],"type":"Point"}
}