{
  "type": "Feature",
  "properties": {
    "iso:country":"US",
    "sg:address":"1 Shady Lane Dr",
    "sg:city":"Conway",
    "sg:classifiers":[
        {
            "category":"Real Estate",
            "subcategory":"Real Estate Services",
            "type":"Services"
        },
        {
            "category":"Real Estate",
            "subcategory":"Surveying",
            "type":"Services"
        },
        {
            "category":"Professional",
            "subcategory":"Business Services",
            "type":"Services"
        }
    ],
    "sg:phone":"+1 501 336 8778",
    "sg:postcode":"72034",
    "sg:province":"AR",
    "sg:tags":[
        "commercial",
        "appraisers-business",
        "industrial",
        "appraisers-commercial",
        "appraiser"
    ],
    "wof:name":"Mid-Ark. Appraisals",
    "wof:placetype":"venue"
},
  "geometry": {"coordinates":[-92.473328,35.094208],"type":"Point"}
}