{
  "type": "Feature",
  "properties": {
    "addr:full":"258 Alta Vista Dr Harrison AR 72601",
    "addr:housenumber":"258",
    "addr:postcode":"72601",
    "addr:street":"Alta Vista Dr",
    "iso:country":"US",
    "sg:address":"258 Alta Vista Dr",
    "sg:city":"Harrison",
    "sg:classifiers":[
        {
            "category":"Manufacturing",
            "subcategory":"Food",
            "type":"Manufacturing & Wholesale Goods"
        }
    ],
    "sg:phone":"+1 870 743 3556",
    "sg:postcode":"72601",
    "sg:province":"AR",
    "sg:tags":[
        "specialty",
        "mfg",
        "frozen",
        "direct",
        "sales",
        "retail"
    ],
    "wof:name":"Schwans Home Service Inc",
    "wof:placetype":"venue"
},
  "geometry": {"coordinates":[-93.02353100000001,36.185574],"type":"Point"}
}