{
  "type": "Feature",
  "properties": {
    "iso:country":"US",
    "sg:address":"226 W Mountain St",
    "sg:city":"Fayetteville",
    "sg:classifiers":[
        {
            "category":"Professional",
            "subcategory":"Business Services",
            "type":"Services"
        }
    ],
    "sg:phone":"+1 479 582 5554",
    "sg:postcode":"72701",
    "sg:province":"AR",
    "sg:tags":[
        "merchandise"
    ],
    "wof:name":"Artful Spaces",
    "wof:placetype":"venue"
},
  "geometry": {"coordinates":[-94.162846,36.062031],"type":"Point"}
}