{
  "type": "Feature",
  "properties": {
    "iso:country":"US",
    "sg:address":"314 E 6th St",
    "sg:city":"Little Rock",
    "sg:classifiers":[
        {
            "category":"Shopping",
            "subcategory":"Gifts & Souvenirs",
            "type":"Retail Goods"
        }
    ],
    "sg:phone":"+1 501 244 2253",
    "sg:postcode":"72202",
    "sg:province":"AR",
    "wof:name":"Arkansas Souvenir Superstore D",
    "wof:placetype":"venue"
},
  "geometry": {"coordinates":[-92.268421,34.742852],"type":"Point"}
}