{
  "type": "Feature",
  "properties": {
    "iso:country":"US",
    "sg:address":"417 N Rosser St",
    "sg:city":"Forrest City",
    "sg:classifiers":[
        {
            "category":"Insurance",
            "subcategory":"Insurance Agent",
            "type":"Services"
        }
    ],
    "sg:phone":"+1 870 633 4119",
    "sg:postcode":"72335",
    "sg:province":"AR",
    "wof:name":"St Francis County Farm Bureau",
    "wof:placetype":"venue"
},
  "geometry": {"coordinates":[-90.787864,35.012282],"type":"Point"}
}