{
  "type": "Feature",
  "properties": {
    "addr:full":"1408 E Church St Warren AR 71671",
    "addr:housenumber":"1408",
    "addr:postcode":"71671",
    "addr:street":"E Church St",
    "iso:country":"US",
    "sg:address":"1408 E Church St",
    "sg:city":"Warren",
    "sg:classifiers":[
        {
            "category":"Travel",
            "subcategory":"Hotels & Motels",
            "type":"Entertainment"
        }
    ],
    "sg:phone":"+1 870 226 9888",
    "sg:postcode":"71671",
    "sg:province":"AR",
    "wof:name":"Super 8 Warren",
    "wof:placetype":"venue"
},
  "geometry": {"coordinates":[-92.04777900000001,33.60973],"type":"Point"}
}