{
  "type": "Feature",
  "properties": {
    "iso:country":"US",
    "sg:address":"401 W Waterman St",
    "sg:city":"Dumas",
    "sg:classifiers":[
        {
            "category":"Food & Beverages",
            "subcategory":"Groceries & Convenience Stores",
            "type":"Retail Goods"
        }
    ],
    "sg:phone":"+1 870 382 3322",
    "sg:postcode":"71639",
    "sg:province":"AR",
    "wof:name":"Corner Stop",
    "wof:placetype":"venue"
},
  "geometry": {"coordinates":[-91.49749,33.886829],"type":"Point"}
}