{
  "type": "Feature",
  "properties": {
    "addr:full":"2102 S 1st St Rogers AR 72758",
    "addr:housenumber":"2102",
    "addr:postcode":"72758",
    "addr:street":"S 1St St",
    "iso:country":"US",
    "sg:address":"2102 S 1st St",
    "sg:city":"Rogers",
    "sg:classifiers":[
        {
            "category":"Wholesale",
            "subcategory":"Groceries",
            "type":"Manufacturing & Wholesale Goods"
        }
    ],
    "sg:phone":"+1 479 271 8200",
    "sg:postcode":"72758",
    "sg:province":"AR",
    "sg:tags":[
        "eating",
        "general"
    ],
    "wof:name":"Food Talk Inc",
    "wof:placetype":"venue"
},
  "geometry": {"coordinates":[-94.11751099999999,36.309932],"type":"Point"}
}