{
  "type": "Feature",
  "properties": {
    "iso:country":"US",
    "sg:address":"4232 E 43rd St",
    "sg:city":"N Little Rock",
    "sg:classifiers":[
        {
            "category":"Building & Trades",
            "subcategory":"Electrical",
            "type":"Services"
        }
    ],
    "sg:phone":"+1 501 945 9305",
    "sg:postcode":"72117",
    "sg:province":"AR",
    "sg:tags":[
        "electrical",
        "electric",
        "contractor"
    ],
    "wof:name":"Horton's Electric Inc",
    "wof:placetype":"venue"
},
  "geometry": {"coordinates":[-92.217542,34.793715],"type":"Point"}
}