{
  "type": "Feature",
  "properties": {
    "iso:country":"US",
    "sg:address":"1306 Stuckey St",
    "sg:city":"Bauxite",
    "sg:classifiers":[
        {
            "category":"Building & Trades",
            "subcategory":"Construction",
            "type":"Services"
        }
    ],
    "sg:phone":"+1 501 557 5082",
    "sg:postcode":"72011",
    "sg:province":"AR",
    "sg:tags":[
        "house"
    ],
    "wof:name":"L Robin Babbitt",
    "wof:placetype":"venue"
},
  "geometry": {"coordinates":[-92.516397,34.555905],"type":"Point"}
}