{
  "type": "Feature",
  "properties": {
    "iso:country":"US",
    "sg:address":"1561 NW 110th St",
    "sg:city":"Grove",
    "sg:classifiers":[
        {
            "category":"Restaurant",
            "type":"Food & Drink"
        }
    ],
    "sg:phone":"+1 918 786 2865",
    "sg:postcode":"74344",
    "sg:province":"OK",
    "sg:tags":[
        "eating"
    ],
    "wof:name":"Armandas Restaurant",
    "wof:placetype":"venue"
},
  "geometry": {"coordinates":[-94.812003,36.631774],"type":"Point"}
}