{
  "type": "Feature",
  "properties": {
    "iso:country":"US",
    "sg:address":"2621 NE Hudson Rd",
    "sg:city":"Rogers",
    "sg:classifiers":[
        {
            "category":"Wholesale",
            "subcategory":"Electrical",
            "type":"Manufacturing & Wholesale Goods"
        }
    ],
    "sg:phone":"+1 479 756 8055",
    "sg:postcode":"72756",
    "sg:province":"AR",
    "sg:tags":[
        "plumbing",
        "equipment"
    ],
    "wof:name":"Marks Plumbing and Elc Sup",
    "wof:placetype":"venue"
},
  "geometry": {"coordinates":[-94.114355,36.35618],"type":"Point"}
}