{
  "type": "Feature",
  "properties": {
    "iso:country":"US",
    "sg:address":"2087 S Barrington Rd",
    "sg:city":"Springdale",
    "sg:classifiers":[
        {
            "category":"Shopping",
            "subcategory":"Jewelry",
            "type":"Retail Goods"
        },
        {
            "category":"Manufacturing",
            "subcategory":"Jewelry",
            "type":"Manufacturing & Wholesale Goods"
        }
    ],
    "sg:phone":"+1 479 361 9033",
    "sg:postcode":"72762",
    "sg:province":"AR",
    "sg:tags":[
        "designer",
        "jeweler"
    ],
    "wof:name":"Mick Wagner",
    "wof:placetype":"venue"
},
  "geometry": {"coordinates":[-94.241593,36.156275],"type":"Point"}
}