{
  "type": "Feature",
  "properties": {
    "addr:full":"3807 McCain Park Dr N Little Rock AR 72116",
    "addr:housenumber":"3807",
    "addr:postcode":"72116",
    "addr:street":"Mccain Park Dr N",
    "iso:country":"US",
    "sg:address":"3807 McCain Park Dr",
    "sg:city":"N Little Rock",
    "sg:classifiers":[
        {
            "category":"Banks & Credit Unions",
            "subcategory":"Bank",
            "type":"Services"
        }
    ],
    "sg:phone":"+1 501 758 1931",
    "sg:postcode":"72116",
    "sg:province":"AR",
    "sg:tags":[
        "loan",
        "real estate"
    ],
    "wof:name":"Allied Home Mortgage Capital",
    "wof:placetype":"venue"
},
  "geometry": {"coordinates":[-92.222874,34.796213],"type":"Point"}
}