{
  "type": "Feature",
  "properties": {
    "iso:country":"US",
    "sg:address":"1882 US Hwy 70 Bus",
    "sg:city":"De Queen",
    "sg:classifiers":[
        {
            "category":"Airport",
            "type":"Transportation"
        }
    ],
    "sg:phone":"+1 870 642 5861",
    "sg:postcode":"71832",
    "sg:province":"AR",
    "wof:name":"Sevier County Airport",
    "wof:placetype":"venue"
},
  "geometry": {"coordinates":[-94.368698,34.038281],"type":"Point"}
}