{
  "type": "Feature",
  "properties": {
    "iso:country":"US",
    "sg:address":"5317 John F Kennedy Blvd",
    "sg:city":"N Little Rock",
    "sg:classifiers":[
        {
            "category":"Real Estate",
            "subcategory":"Real Estate Services",
            "type":"Services"
        }
    ],
    "sg:phone":"+1 501 372 5116",
    "sg:postcode":"72116",
    "sg:province":"AR",
    "sg:tags":[
        "company",
        "title"
    ],
    "wof:name":"Stewart Title Co",
    "wof:placetype":"venue"
},
  "geometry": {"coordinates":[-92.253552,34.80399],"type":"Point"}
}