{
  "type": "Feature",
  "properties": {
    "addr:full":"2408 N College Ave Fayetteville AR 72703",
    "addr:housenumber":"2408",
    "addr:postcode":"72703",
    "addr:street":"N College Ave",
    "iso:country":"US",
    "sg:address":"2408 N College Ave",
    "sg:city":"Fayetteville",
    "sg:classifiers":[
        {
            "category":"Retail",
            "subcategory":"Auto Rental",
            "type":"Services"
        }
    ],
    "sg:phone":"+1 479 443 2965",
    "sg:postcode":"72703",
    "sg:province":"AR",
    "sg:tags":[
        "truck",
        "trailer",
        "utility"
    ],
    "wof:name":"U-Haul",
    "wof:placetype":"venue"
},
  "geometry": {"coordinates":[-94.152393,36.095833],"type":"Point"}
}