{
  "type": "Feature",
  "properties": {
    "addr:full":"5301 Wheeler Ave Fort Smith AR 72901",
    "addr:housenumber":"5301",
    "addr:postcode":"72901",
    "addr:street":"Wheeler Ave",
    "iso:country":"US",
    "sg:address":"5301 Wheeler Ave",
    "sg:city":"Fort Smith",
    "sg:classifiers":[
        {
            "category":"Health Services",
            "subcategory":"Nursing And Care Facility",
            "type":"Services"
        }
    ],
    "sg:phone":"+1 479 646 3454",
    "sg:postcode":"72901",
    "sg:province":"AR",
    "sg:tags":[
        "home",
        "skilled",
        "convalescent"
    ],
    "wof:name":"Rose Care Center of Fort Smith",
    "wof:placetype":"venue"
},
  "geometry": {"coordinates":[-94.427145,35.336452],"type":"Point"}
}