{
  "type": "Feature",
  "properties": {
    "iso:country":"US",
    "sg:address":"1100 W 16th Ave",
    "sg:city":"Pine Bluff",
    "sg:classifiers":[
        {
            "category":"Food & Beverages",
            "subcategory":"Groceries & Convenience Stores",
            "type":"Retail Goods"
        }
    ],
    "sg:phone":"+1 870 534 1715",
    "sg:postcode":"71603",
    "sg:province":"AR",
    "wof:name":"Stop N Shop",
    "wof:placetype":"venue"
},
  "geometry": {"coordinates":[-92.014479,34.213175],"type":"Point"}
}