{
  "type": "Feature",
  "properties": {
    "iso:country":"US",
    "sg:address":"13 Tanglewood Dr",
    "sg:city":"Batesville",
    "sg:classifiers":[
        {
            "category":"Building & Trades",
            "subcategory":"Landscaping Services",
            "type":"Services"
        }
    ],
    "sg:phone":"+1 870 793 4220",
    "sg:postcode":"72501",
    "sg:province":"AR",
    "wof:name":"Wolfs Landscaping",
    "wof:placetype":"venue"
},
  "geometry": {"coordinates":[-91.62166999999999,35.770496],"type":"Point"}
}