{
  "type": "Feature",
  "properties": {
    "iso:country":"US",
    "sg:address":"817 Saint Marys St",
    "sg:city":"Lake Village",
    "sg:classifiers":[
        {
            "category":"Food & Beverages",
            "subcategory":"Liquor & Beverages",
            "type":"Retail Goods"
        }
    ],
    "sg:phone":"+1 870 265 3151",
    "sg:postcode":"71653",
    "sg:province":"AR",
    "wof:name":"817 Liquor",
    "wof:placetype":"venue"
},
  "geometry": {"coordinates":[-91.290566,33.330002],"type":"Point"}
}