{
  "type": "Feature",
  "properties": {
    "addr:full":"17 E 1st St Mountain Home AR 72653",
    "addr:housenumber":"17",
    "addr:postcode":"72653",
    "addr:street":"E 1St St",
    "iso:country":"US",
    "sg:address":"17 E 1st St",
    "sg:city":"Mountain Home",
    "sg:classifiers":[
        {
            "category":"Retail",
            "subcategory":"Repair Shop",
            "type":"Services"
        }
    ],
    "sg:phone":"+1 870 425 0727",
    "sg:postcode":"72653",
    "sg:province":"AR",
    "sg:tags":[
        "gallery"
    ],
    "wof:name":"1st Street Frmng & Art Gallery",
    "wof:placetype":"venue"
},
  "geometry": {"coordinates":[-92.383893,36.340243],"type":"Point"}
}