{
  "type": "Feature",
  "properties": {
    "addr:full":"103 E 21st St Little Rock AR 72206",
    "addr:housenumber":"103",
    "addr:postcode":"72206",
    "addr:street":"E 21St St",
    "iso:country":"US",
    "sg:address":"103 E 21st St",
    "sg:city":"Little Rock",
    "sg:classifiers":[
        {
            "category":"Organizations",
            "subcategory":"Community Association",
            "type":"Services"
        }
    ],
    "sg:phone":"+1 501 374 5585",
    "sg:postcode":"72206",
    "sg:province":"AR",
    "wof:name":"Project Vote",
    "wof:placetype":"venue"
},
  "geometry": {"coordinates":[-92.27251800000001,34.72859],"type":"Point"}
}