{
  "type": "Feature",
  "properties": {
    "addr:full":"817 E Johnson Ave Jonesboro AR 72401",
    "addr:housenumber":"817",
    "addr:postcode":"72401",
    "addr:street":"E Johnson Ave",
    "iso:country":"US",
    "sg:address":"817 E Johnson Ave",
    "sg:city":"Jonesboro",
    "sg:classifiers":[
        {
            "category":"Wholesale",
            "subcategory":"Electrical",
            "type":"Manufacturing & Wholesale Goods"
        },
        {
            "category":"Wholesale",
            "subcategory":"Construction Materials",
            "type":"Manufacturing & Wholesale Goods"
        },
        {
            "category":"Home & Garden",
            "subcategory":"Building Materials",
            "type":"Retail Goods"
        },
        {
            "category":"Professional",
            "subcategory":"Engineering",
            "type":"Services"
        }
    ],
    "sg:phone":"+1 870 932 3495",
    "sg:postcode":"72401",
    "sg:province":"AR",
    "sg:tags":[
        "system",
        "systems-wholesale",
        "equipment",
        "heating",
        "air conditioning",
        "manufacturer"
    ],
    "wof:name":"Wss- Dayton",
    "wof:placetype":"venue"
},
  "geometry": {"coordinates":[-90.696956,35.845259],"type":"Point"}
}