{
  "type": "Feature",
  "properties": {
    "iso:country":"US",
    "sg:address":"591 N Rockcliff Rd",
    "sg:city":"Fayetteville",
    "sg:classifiers":[
        {
            "category":"Health Services",
            "subcategory":"Doctor",
            "type":"Services"
        }
    ],
    "sg:phone":"+1 479 442 3713",
    "sg:postcode":"72701",
    "sg:province":"AR",
    "sg:tags":[
        "medical"
    ],
    "wof:name":"Frederic K Spies MD PA",
    "wof:placetype":"venue"
},
  "geometry": {"coordinates":[-94.124866,36.073027],"type":"Point"}
}