{
  "type": "Feature",
  "properties": {
    "iso:country":"US",
    "sg:address":"507 Mountain View Rd",
    "sg:city":"Glenwood",
    "sg:classifiers":[
        {
            "category":"Personal",
            "type":"Services"
        }
    ],
    "sg:phone":"+1 870 356 4426",
    "sg:postcode":"71943",
    "sg:province":"AR",
    "sg:tags":[
        "assistant"
    ],
    "wof:name":"Oakpark Village",
    "wof:placetype":"venue"
},
  "geometry": {"coordinates":[-93.54068,34.331234],"type":"Point"}
}