{
  "type": "Feature",
  "properties": {
    "iso:country":"US",
    "sg:address":"103 SE 22nd St",
    "sg:city":"Bentonville",
    "sg:classifiers":[
        {
            "category":"Professional",
            "subcategory":"Advertising",
            "type":"Services"
        }
    ],
    "sg:phone":"+1 479 271 8201",
    "sg:postcode":"72712",
    "sg:province":"AR",
    "sg:tags":[
        "agency"
    ],
    "wof:name":"Retailtainment Inc",
    "wof:placetype":"venue"
},
  "geometry": {"coordinates":[-94.209696,36.347896],"type":"Point"}
}