{
  "type": "Feature",
  "properties": {
    "iso:country":"US",
    "sg:address":"769 Surrey Dr",
    "sg:city":"Lakeview",
    "sg:classifiers":[
        {
            "category":"Restaurant",
            "type":"Food & Drink"
        },
        {
            "category":"Food & Beverages",
            "subcategory":"Groceries & Convenience Stores",
            "type":"Retail Goods"
        }
    ],
    "sg:phone":"+1 870 431 4073",
    "sg:postcode":"72642",
    "sg:province":"AR",
    "sg:tags":[
        "shop",
        "sandwich",
        "pizza"
    ],
    "wof:name":"Airport Pizza & Subs",
    "wof:placetype":"venue"
},
  "geometry": {"coordinates":[-92.5448,36.366433],"type":"Point"}
}