{
  "type": "Feature",
  "properties": {
    "addr:full":"805 E Parkway Dr Russellville AR 72801",
    "addr:housenumber":"805",
    "addr:postcode":"72801",
    "addr:street":"E Parkway Dr",
    "iso:country":"US",
    "sg:address":"805 E Parkway Dr",
    "sg:city":"Russellville",
    "sg:classifiers":[
        {
            "category":"Shopping",
            "subcategory":"Jewelry",
            "type":"Retail Goods"
        }
    ],
    "sg:phone":"+1 479 967 7833",
    "sg:postcode":"72801",
    "sg:province":"AR",
    "sg:tags":[
        "repair",
        "fine"
    ],
    "wof:name":"Lee Anns Fine Jewelry Inc",
    "wof:placetype":"venue"
},
  "geometry": {"coordinates":[-93.12425399999999,35.281149],"type":"Point"}
}