{
  "type": "Feature",
  "properties": {
    "addr:full":"1140 W Walnut St Rogers AR 72756",
    "addr:housenumber":"1140",
    "addr:postcode":"72756",
    "addr:street":"W Walnut St",
    "iso:country":"US",
    "sg:address":"1140 W Walnut St",
    "sg:city":"Rogers",
    "sg:classifiers":[
        {
            "category":"Health Services",
            "subcategory":"Doctor",
            "type":"Services"
        }
    ],
    "sg:phone":"+1 479 636 2711",
    "sg:postcode":"72756",
    "sg:province":"AR",
    "sg:tags":[
        "practice",
        "obstetrician",
        "family",
        "gynecologist"
    ],
    "wof:name":"Wilson Cynthia MD",
    "wof:placetype":"venue"
},
  "geometry": {"coordinates":[-94.131699,36.333801],"type":"Point"}
}