{
  "type": "Feature",
  "properties": {
    "iso:country":"US",
    "sg:address":"308 E Union Ave",
    "sg:city":"Monticello",
    "sg:classifiers":[
        {
            "category":"Organizations",
            "subcategory":"Community Association",
            "type":"Services"
        }
    ],
    "sg:phone":"+1 870 460 0360",
    "sg:postcode":"71655",
    "sg:province":"AR",
    "wof:name":"Legion 2 American Joe",
    "wof:placetype":"venue"
},
  "geometry": {"coordinates":[-91.788967,33.630782],"type":"Point"}
}