{
  "type": "Feature",
  "properties": {
    "iso:country":"US",
    "sg:address":"1817 Executive Sq",
    "sg:city":"Jonesboro",
    "sg:classifiers":[
        {
            "category":"Health Services",
            "subcategory":"Doctor",
            "type":"Services"
        }
    ],
    "sg:phone":"+1 870 972 8190",
    "sg:postcode":"72401",
    "sg:province":"AR",
    "sg:tags":[
        "dentist"
    ],
    "wof:name":"Woodruff & Woodruff",
    "wof:placetype":"venue"
},
  "geometry": {"coordinates":[-90.68819000000001,35.809872],"type":"Point"}
}