{
  "type": "Feature",
  "properties": {
    "iso:country":"US",
    "sg:address":"401 S Jefferson St",
    "sg:city":"Magnolia",
    "sg:classifiers":[
        {
            "category":"Wholesale",
            "subcategory":"Hardware",
            "type":"Manufacturing & Wholesale Goods"
        }
    ],
    "sg:phone":"+1 870 234 1940",
    "sg:postcode":"71753",
    "sg:province":"AR",
    "sg:tags":[
        "plumbing",
        "air",
        "heating",
        "conditioning",
        "welding"
    ],
    "wof:name":"Law Supply Inc",
    "wof:placetype":"venue"
},
  "geometry": {"coordinates":[-93.241359,33.26445],"type":"Point"}
}