{
  "type": "Feature",
  "properties": {
    "addr:full":"420 E Main St El Dorado AR 71730",
    "addr:housenumber":"420",
    "addr:postcode":"71730",
    "addr:street":"E Main St",
    "iso:country":"US",
    "sg:address":"420 E Main St",
    "sg:city":"El Dorado",
    "sg:classifiers":[
        {
            "category":"Shopping",
            "type":"Retail Goods"
        }
    ],
    "sg:phone":"+1 870 862 3067",
    "sg:postcode":"71730",
    "sg:province":"AR",
    "sg:tags":[
        "merchandise",
        "business",
        "mfg"
    ],
    "wof:name":"R-J Trophies",
    "wof:placetype":"venue"
},
  "geometry": {"coordinates":[-92.661022,33.211922],"type":"Point"}
}