{
  "type": "Feature",
  "properties": {
    "addr:full":"3320 N Arkansas Ave Russellville AR 72802",
    "addr:housenumber":"3320",
    "addr:postcode":"72802",
    "addr:street":"N Arkansas Ave",
    "iso:country":"US",
    "sg:address":"3320 N Arkansas Ave",
    "sg:city":"Russellville",
    "sg:classifiers":[
        {
            "category":"Travel",
            "subcategory":"Hotels & Motels",
            "type":"Entertainment"
        }
    ],
    "sg:phone":"+1 479 968 2187",
    "sg:postcode":"72802",
    "sg:province":"AR",
    "sg:tags":[
        "operation"
    ],
    "wof:name":"Lakeside Resort Motel & Rv PK",
    "wof:placetype":"venue"
},
  "geometry": {"coordinates":[-93.137378,35.312909],"type":"Point"}
}