{
  "type": "Feature",
  "properties": {
    "iso:country":"US",
    "sg:address":"105 S Main St",
    "sg:city":"England",
    "sg:classifiers":[
        {
            "category":"Shopping",
            "subcategory":"Used Merchandise",
            "type":"Retail Goods"
        }
    ],
    "sg:phone":"+1 501 842 1521",
    "sg:postcode":"72046",
    "sg:province":"AR",
    "sg:tags":[
        "second",
        "store",
        "hand"
    ],
    "wof:name":"Home Again",
    "wof:placetype":"venue"
},
  "geometry": {"coordinates":[-91.969542,34.54492],"type":"Point"}
}