{
  "type": "Feature",
  "properties": {
    "iso:country":"US",
    "sg:address":"23 Shackleford Dr",
    "sg:city":"Little Rock",
    "sg:classifiers":[
        {
            "category":"Manufacturing",
            "subcategory":"Tools & Machinery",
            "type":"Manufacturing & Wholesale Goods"
        }
    ],
    "sg:phone":"+1 501 224 0953",
    "sg:postcode":"72211",
    "sg:province":"AR",
    "sg:tags":[
        "optical"
    ],
    "wof:name":"Metro Optics Inc",
    "wof:placetype":"venue"
},
  "geometry": {"coordinates":[-92.397814,34.754791],"type":"Point"}
}