{
  "type": "Feature",
  "properties": {
    "iso:country":"US",
    "sg:address":"306 Eureka Ave",
    "sg:city":"Berryville",
    "sg:classifiers":[
        {
            "category":"Professional",
            "subcategory":"Computer Services",
            "type":"Services"
        }
    ],
    "sg:phone":"+1 870 423 6223",
    "sg:postcode":"72616",
    "sg:province":"AR",
    "sg:tags":[
        "internet"
    ],
    "sg:website":"www.hbeark.com",
    "wof:name":"HBE Internet",
    "wof:placetype":"venue"
},
  "geometry": {"coordinates":[-93.57238599999999,36.367137],"type":"Point"}
}