{
  "type": "Feature",
  "properties": {
    "iso:country":"US",
    "sg:address":"2500 S Knoxville Ave",
    "sg:city":"Russellville",
    "sg:classifiers":[
        {
            "category":"Real Estate",
            "subcategory":"Developer",
            "type":"Services"
        }
    ],
    "sg:phone":"+1 479 968 4909",
    "sg:postcode":"72802",
    "sg:province":"AR",
    "sg:tags":[
        "cemetery"
    ],
    "wof:name":"Rest Haven Memorial Park",
    "wof:placetype":"venue"
},
  "geometry": {"coordinates":[-93.121148,35.256244],"type":"Point"}
}