{
  "type": "Feature",
  "properties": {
    "iso:country":"US",
    "sg:address":"1100 N University Ave",
    "sg:city":"Little Rock",
    "sg:classifiers":[
        {
            "category":"Health Services",
            "subcategory":"Doctor",
            "type":"Services"
        }
    ],
    "sg:phone":"+1 501 664 3018",
    "sg:postcode":"72207",
    "sg:province":"AR",
    "sg:tags":[
        "medical"
    ],
    "wof:name":"Edx Medicine Center Inc",
    "wof:placetype":"venue"
},
  "geometry": {"coordinates":[-92.341031,34.760365],"type":"Point"}
}