{
  "type": "Feature",
  "properties": {
    "iso:country":"US",
    "sg:address":"5420 Kavanaugh Blvd",
    "sg:city":"Little Rock",
    "sg:classifiers":[
        {
            "category":"Government",
            "subcategory":"Post Office",
            "type":"Public Place"
        }
    ],
    "sg:phone":"+1 501 666 5126",
    "sg:postcode":"72207",
    "sg:province":"AR",
    "wof:name":"US Post Office",
    "wof:placetype":"venue"
},
  "geometry": {"coordinates":[-92.333877,34.770196],"type":"Point"}
}