{
  "type": "Feature",
  "properties": {
    "iso:country":"US",
    "sg:address":"441 W Cedar St",
    "sg:city":"El Dorado",
    "sg:classifiers":[
        {
            "category":"Food & Beverages",
            "subcategory":"Specialty",
            "type":"Retail Goods"
        }
    ],
    "sg:phone":"+1 870 862 1244",
    "sg:postcode":"71730",
    "sg:province":"AR",
    "sg:tags":[
        "water",
        "bulk",
        "company"
    ],
    "wof:name":"Union Co Water Conservation",
    "wof:placetype":"venue"
},
  "geometry": {"coordinates":[-92.671223,33.211099],"type":"Point"}
}