{
  "type": "Feature",
  "properties": {
    "addr:full":"2800 O St S Fort Smith AR 72901",
    "addr:housenumber":"2800",
    "addr:postcode":"72901",
    "addr:street":"O St S",
    "iso:country":"US",
    "sg:address":"2800 O St S",
    "sg:city":"Fort Smith",
    "sg:classifiers":[
        {
            "category":"Manufacturing",
            "subcategory":"Building Materials",
            "type":"Manufacturing & Wholesale Goods"
        }
    ],
    "sg:phone":"+1 479 782 5896",
    "sg:postcode":"72901",
    "sg:province":"AR",
    "sg:tags":[
        "mfg",
        "wood",
        "kitchen",
        "cabinet"
    ],
    "wof:name":"Beckman Cabinets",
    "wof:placetype":"venue"
},
  "geometry": {"coordinates":[-94.401065,35.367747],"type":"Point"}
}