{
  "type": "Feature",
  "properties": {
    "iso:country":"US",
    "sg:address":"1840 Amelia Dr",
    "sg:city":"Conway",
    "sg:classifiers":[
        {
            "category":"Professional",
            "subcategory":"Management & Consulting",
            "type":"Services"
        }
    ],
    "sg:phone":"+1 501 327 8381",
    "sg:postcode":"72034",
    "sg:province":"AR",
    "sg:tags":[
        "business"
    ],
    "wof:name":"Utility Recovery Services Inc",
    "wof:placetype":"venue"
},
  "geometry": {"coordinates":[-92.489166,35.104594],"type":"Point"}
}