{
  "type": "Feature",
  "properties": {
    "iso:country":"US",
    "sg:address":"107 US Hwy 71",
    "sg:city":"Fouke",
    "sg:classifiers":[
        {
            "category":"Food & Beverages",
            "subcategory":"Groceries & Convenience Stores",
            "type":"Retail Goods"
        }
    ],
    "sg:phone":"+1 870 653 4621",
    "sg:postcode":"71837",
    "sg:province":"AR",
    "sg:tags":[
        "station",
        "gasoline"
    ],
    "wof:name":"Fouke Food Center",
    "wof:placetype":"venue"
},
  "geometry": {"coordinates":[-93.885595,33.260851],"type":"Point"}
}