{
  "type": "Feature",
  "properties": {
    "iso:country":"US",
    "sg:address":"3907 Massard Rd",
    "sg:city":"Fort Smith",
    "sg:classifiers":[
        {
            "category":"Railroad",
            "type":"Transportation"
        }
    ],
    "sg:phone":"+1 479 452 7398",
    "sg:postcode":"72903",
    "sg:province":"AR",
    "sg:tags":[
        "operator",
        "line"
    ],
    "wof:name":"R & R Resources Inc",
    "wof:placetype":"venue"
},
  "geometry": {"coordinates":[-94.340677,35.344378],"type":"Point"}
}