{
  "type": "Feature",
  "properties": {
    "addr:full":"130 E Page Ave Malvern AR 72104",
    "addr:housenumber":"130",
    "addr:postcode":"72104",
    "addr:street":"E Page Ave",
    "iso:country":"US",
    "sg:address":"130 E Page Ave",
    "sg:city":"Malvern",
    "sg:classifiers":[
        {
            "category":"Retail",
            "subcategory":"Car Wash",
            "type":"Services"
        },
        {
            "category":"Retail",
            "subcategory":"Auto Repair",
            "type":"Services"
        }
    ],
    "sg:phone":"+1 501 815 2102",
    "sg:postcode":"72104",
    "sg:province":"AR",
    "sg:tags":[
        "automotive",
        "detail",
        "clean",
        "automobile"
    ],
    "wof:name":"Karen's Kar Kare",
    "wof:placetype":"venue"
},
  "geometry": {"coordinates":[-92.811695,34.36288],"type":"Point"}
}