{
  "type": "Feature",
  "properties": {
    "iso:country":"US",
    "sg:address":"6367 US Hwy 61",
    "sg:city":"Blytheville",
    "sg:classifiers":[
        {
            "category":"Wholesale",
            "subcategory":"Non-durable Goods",
            "type":"Manufacturing & Wholesale Goods"
        }
    ],
    "sg:phone":"+1 870 762 0586",
    "sg:postcode":"72315",
    "sg:province":"AR",
    "wof:name":"Trade Distributions Inc",
    "wof:placetype":"venue"
},
  "geometry": {"coordinates":[-89.901149,35.997425],"type":"Point"}
}