{
  "type": "Feature",
  "properties": {
    "iso:country":"US",
    "sg:address":"1810 L E Gilliland Dr",
    "sg:city":"Texarkana",
    "sg:classifiers":[
        {
            "category":"Manufacturing",
            "subcategory":"Printing",
            "type":"Manufacturing & Wholesale Goods"
        }
    ],
    "sg:phone":"+1 870 772 7931",
    "sg:postcode":"71854",
    "sg:province":"AR",
    "sg:tags":[
        "printer"
    ],
    "sg:website":"www.firsttapeandlabel.com",
    "wof:name":"First Tape & Label",
    "wof:placetype":"venue"
},
  "geometry": {"coordinates":[-94.005387,33.431058],"type":"Point"}
}