{
  "type": "Feature",
  "properties": {
    "iso:country":"US",
    "sg:address":"611 N Main St",
    "sg:city":"North Little Rock",
    "sg:classifiers":[
        {
            "category":"Professional",
            "subcategory":"Accounting & Tax Preparation",
            "type":"Services"
        }
    ],
    "sg:phone":"+1 501 374 2910",
    "sg:postcode":"72114",
    "sg:province":"AR",
    "wof:name":"Amy Hall",
    "wof:placetype":"venue"
},
  "geometry": {"coordinates":[-92.267661,34.759931],"type":"Point"}
}