{
  "type": "Feature",
  "properties": {
    "iso:country":"US",
    "sg:address":"207 W Lafayette St",
    "sg:city":"Fayetteville",
    "sg:classifiers":[
        {
            "category":"Insurance",
            "subcategory":"Insurance Agent",
            "type":"Services"
        }
    ],
    "sg:phone":"+1 479 444 3399",
    "sg:postcode":"72701",
    "sg:province":"AR",
    "sg:tags":[
        "consultant"
    ],
    "wof:name":"Corporate Benefit Planners",
    "wof:placetype":"venue"
},
  "geometry": {"coordinates":[-94.16293899999999,36.068591],"type":"Point"}
}