{
  "type": "Feature",
  "properties": {
    "addr:full":"2114 S Main St Grove OK 74344",
    "addr:housenumber":"2114",
    "addr:postcode":"74344",
    "addr:street":"S Main St Grove",
    "iso:country":"US",
    "sg:address":"2114 S Main St",
    "sg:city":"Grove",
    "sg:classifiers":[
        {
            "category":"Banks & Credit Unions",
            "subcategory":"Bank",
            "type":"Services"
        }
    ],
    "sg:phone":"+1 918 787 6028",
    "sg:postcode":"74344",
    "sg:province":"OK",
    "sg:tags":[
        "loan",
        "real estate"
    ],
    "wof:name":"Wells Fargo Home Mortgage Inc",
    "wof:placetype":"venue"
},
  "geometry": {"coordinates":[-94.769156,36.579043],"type":"Point"}
}