{
  "type": "Feature",
  "properties": {
    "iso:country":"US",
    "sg:address":"2990 E Moore Ave",
    "sg:city":"Searcy",
    "sg:classifiers":[
        {
            "category":"Insurance",
            "subcategory":"Hazard Insurance",
            "type":"Services"
        }
    ],
    "sg:phone":"+1 501 268 1608",
    "sg:postcode":"72143",
    "sg:province":"AR",
    "sg:website":"http://statefarm.mqgroup.com/url.asp?usr=041375",
    "wof:name":"State Farm Insurance Agent-Mickey Holt",
    "wof:placetype":"venue"
},
  "geometry": {"coordinates":[-91.701338,35.253762],"type":"Point"}
}