{
  "type": "Feature",
  "properties": {
    "iso:country":"US",
    "sg:address":"103 N Poplar St",
    "sg:city":"Searcy",
    "sg:classifiers":[
        {
            "category":"Shopping",
            "subcategory":"Discount & Variety Stores",
            "type":"Retail Goods"
        }
    ],
    "sg:phone":"+1 501 368 0712",
    "sg:postcode":"72143",
    "sg:province":"AR",
    "sg:website":"www.biglots.com",
    "wof:name":"Big Lots",
    "wof:placetype":"venue"
},
  "geometry": {"coordinates":[-91.69176400000001,35.252549],"type":"Point"}
}