{
  "type": "Feature",
  "properties": {
    "iso:country":"US",
    "sg:address":"2911 W Commercial St",
    "sg:city":"Ozark",
    "sg:classifiers":[
        {
            "category":"Insurance",
            "subcategory":"Hazard Insurance",
            "type":"Services"
        }
    ],
    "sg:phone":"+1 479 667 1260",
    "sg:postcode":"72949",
    "sg:province":"AR",
    "sg:tags":[
        "commercial",
        "business"
    ],
    "wof:name":"First Western Insurance",
    "wof:placetype":"venue"
},
  "geometry": {"coordinates":[-93.857321,35.49014],"type":"Point"}
}