{
  "type": "Feature",
  "properties": {
    "addr:full":"7609 Dan Thomas Rd Little Rock AR 72206",
    "addr:housenumber":"7609",
    "addr:postcode":"72206",
    "addr:street":"Dan Thomas Rd",
    "iso:country":"US",
    "sg:address":"7609 Dan Thomas Rd",
    "sg:city":"Little Rock",
    "sg:classifiers":[
        {
            "category":"Building & Trades",
            "subcategory":"Construction",
            "type":"Services"
        }
    ],
    "sg:phone":"+1 501 490 0676",
    "sg:postcode":"72206",
    "sg:province":"AR",
    "sg:tags":[
        "general",
        "contractor"
    ],
    "wof:name":"Pettit Contracting",
    "wof:placetype":"venue"
},
  "geometry": {"coordinates":[-92.242986,34.678039],"type":"Point"}
}