{
  "type": "Feature",
  "properties": {
    "iso:country":"US",
    "sg:address":"805 S Division St",
    "sg:city":"Blytheville",
    "sg:classifiers":[
        {
            "category":"Retail",
            "subcategory":"Veterinary Services",
            "type":"Services"
        }
    ],
    "sg:phone":"+1 870 763 3101",
    "sg:postcode":"72315",
    "sg:province":"AR",
    "sg:tags":[
        "clinic",
        "veterinarian",
        "hospital"
    ],
    "wof:name":"Blytheville Animal Hospital",
    "wof:placetype":"venue"
},
  "geometry": {"coordinates":[-89.918769,35.919616],"type":"Point"}
}