{
  "type": "Feature",
  "properties": {
    "iso:country":"US",
    "sg:address":"617 Tracy Lawrence Ave",
    "sg:city":"Foreman",
    "sg:classifiers":[
        {
            "category":"Building & Trades",
            "subcategory":"Construction",
            "type":"Services"
        },
        {
            "category":"Manufacturing",
            "subcategory":"Building Materials",
            "type":"Manufacturing & Wholesale Goods"
        }
    ],
    "sg:phone":"+1 870 542 7901",
    "sg:postcode":"71836",
    "sg:province":"AR",
    "sg:tags":[
        "roofing",
        "industrial",
        "sheet",
        "work",
        "metal",
        "contractor",
        "contractors-commercial"
    ],
    "wof:name":"Tanner Sheet Metal And Roofing",
    "wof:placetype":"venue"
},
  "geometry": {"coordinates":[-94.395413,33.721737],"type":"Point"}
}