{
  "type": "Feature",
  "properties": {
    "iso:country":"US",
    "sg:address":"2900 Richardson Dr",
    "sg:city":"Jonesboro",
    "sg:classifiers":[
        {
            "category":"Freight",
            "type":"Transportation"
        }
    ],
    "sg:phone":"+1 870 974 9500",
    "sg:postcode":"72401",
    "sg:province":"AR",
    "sg:tags":[
        "commercial",
        "storage"
    ],
    "wof:name":"United Self Storage",
    "wof:placetype":"venue"
},
  "geometry": {"coordinates":[-90.6602,35.808616],"type":"Point"}
}