{
  "type": "Feature",
  "properties": {
    "iso:country":"US",
    "sg:address":"225 E Markham St",
    "sg:city":"Little Rock",
    "sg:classifiers":[
        {
            "category":"Bars & Pubs",
            "type":"Food & Drink"
        }
    ],
    "sg:phone":"+1 501 378 7500",
    "sg:postcode":"72201",
    "sg:province":"AR",
    "sg:tags":[
        "drinking"
    ],
    "sg:website":"www.nucuisine-lounge.com",
    "wof:name":"Nu Cuisine Lounge",
    "wof:placetype":"venue"
},
  "geometry": {"coordinates":[-92.268662,34.747799],"type":"Point"}
}