{
  "type": "Feature",
  "properties": {
    "iso:country":"US",
    "sg:address":"2039 E Main St",
    "sg:city":"Cabot",
    "sg:classifiers":[
        {
            "category":"Health Services",
            "subcategory":"Health Practitioner",
            "type":"Services"
        }
    ],
    "sg:phone":"+1 501 605 8980",
    "sg:postcode":"72023",
    "sg:province":"AR",
    "sg:tags":[
        "therapist",
        "physical"
    ],
    "wof:name":"Cabot Physical Rehabilitation",
    "wof:placetype":"venue"
},
  "geometry": {"coordinates":[-91.996042,34.967267],"type":"Point"}
}