{
  "type": "Feature",
  "properties": {
    "iso:country":"US",
    "sg:address":"736 Cuffman Mill Rd",
    "sg:city":"Rockport",
    "sg:classifiers":[
        {
            "category":"Place Of Worship",
            "type":"Public Place"
        },
        {
            "category":"Place Of Worship",
            "subcategory":"Temple",
            "type":"Public Place"
        }
    ],
    "sg:phone":"+1 501 467 3200",
    "sg:postcode":"72104",
    "sg:province":"AR",
    "sg:tags":[
        "church"
    ],
    "wof:name":"Temple Industries",
    "wof:placetype":"venue"
},
  "geometry": {"coordinates":[-92.81704,34.390975],"type":"Point"}
}