{
  "type": "Feature",
  "properties": {
    "iso:country":"US",
    "sg:address":"32 Plainview Dr",
    "sg:city":"Mc Gehee",
    "sg:classifiers":[
        {
            "category":"Professional",
            "type":"Services"
        }
    ],
    "sg:phone":"+1 870 222 5818",
    "sg:postcode":"71654",
    "sg:province":"AR",
    "wof:name":"D&D Services Inc",
    "wof:placetype":"venue"
},
  "geometry": {"coordinates":[-91.41248,33.63416],"type":"Point"}
}