{
  "type": "Feature",
  "properties": {
    "iso:country":"US",
    "sg:address":"2619 Kavanaugh Blvd",
    "sg:city":"Little Rock",
    "sg:classifiers":[
        {
            "category":"Professional",
            "type":"Services"
        },
        {
            "category":"Retail",
            "subcategory":"Animal Services",
            "type":"Services"
        }
    ],
    "sg:phone":"+1 501 296 9800",
    "sg:postcode":"72205",
    "sg:province":"AR",
    "sg:tags":[
        "pet",
        "grooming",
        "washing"
    ],
    "sg:website":"www.doghousespa.com",
    "wof:name":"Dog House Bath & Grooming Salo",
    "wof:placetype":"venue"
},
  "geometry": {"coordinates":[-92.322202,34.757228],"type":"Point"}
}