{
  "type": "Feature",
  "properties": {
    "iso:country":"US",
    "sg:address":"17022 Arch St",
    "sg:city":"Little Rock",
    "sg:classifiers":[
        {
            "category":"Manufacturing",
            "subcategory":"Building Materials",
            "type":"Manufacturing & Wholesale Goods"
        }
    ],
    "sg:phone":"+1 501 888 3218",
    "sg:postcode":"72206",
    "sg:province":"AR",
    "wof:name":"Sunset Premium Hardwoods",
    "wof:placetype":"venue"
},
  "geometry": {"coordinates":[-92.320699,34.606158],"type":"Point"}
}