{
  "type": "Feature",
  "properties": {
    "iso:country":"US",
    "sg:address":"5101 S 44th St",
    "sg:city":"Rogers",
    "sg:classifiers":[
        {
            "category":"Building & Trades",
            "subcategory":"Construction",
            "type":"Services"
        }
    ],
    "sg:phone":"+1 479 636 8255",
    "sg:postcode":"72758",
    "sg:province":"AR",
    "sg:tags":[
        "home",
        "builder"
    ],
    "sg:website":"www.vmphomes.com",
    "wof:name":"Vance M Puttkammer Homes Inc",
    "wof:placetype":"venue"
},
  "geometry": {"coordinates":[-94.176935,36.289992],"type":"Point"}
}