{
  "type": "Feature",
  "properties": {
    "addr:full":"701 Butterfield Coach Rd Springdale AR 72764",
    "addr:housenumber":"701",
    "addr:postcode":"72764",
    "addr:street":"Butterfield Coach Rd",
    "iso:country":"US",
    "sg:address":"701 Butterfield Coach Rd",
    "sg:city":"Springdale",
    "sg:classifiers":[
        {
            "category":"Utilities",
            "subcategory":"Refuse",
            "type":"Services"
        },
        {
            "category":"Wholesale",
            "subcategory":"Drugs",
            "type":"Manufacturing & Wholesale Goods"
        }
    ],
    "sg:phone":"+1 479 751 7320",
    "sg:postcode":"72764",
    "sg:province":"AR",
    "sg:tags":[
        "disposal",
        "industrial",
        "commercial",
        "garbage",
        "equipment"
    ],
    "wof:name":"J V Manufacturing",
    "wof:placetype":"venue"
},
  "geometry": {"coordinates":[-94.095749,36.181271],"type":"Point"}
}