{
  "type": "Feature",
  "properties": {
    "addr:full":"4101 E Grand Ave Hot Springs AR 71901",
    "addr:housenumber":"4101",
    "addr:postcode":"71901",
    "addr:street":"E Grand Ave",
    "iso:country":"US",
    "sg:address":"4101 E Grand Ave",
    "sg:city":"Hot Springs",
    "sg:classifiers":[
        {
            "category":"Manufacturing",
            "subcategory":"Metals",
            "type":"Manufacturing & Wholesale Goods"
        }
    ],
    "sg:phone":"+1 501 262 5108",
    "sg:postcode":"71901",
    "sg:province":"AR",
    "sg:tags":[
        "tower"
    ],
    "wof:name":"SBA Tower",
    "wof:placetype":"venue"
},
  "geometry": {"coordinates":[-92.931039,34.513992],"type":"Point"}
}