{
  "type": "Feature",
  "properties": {
    "iso:country":"US",
    "sg:address":"220 Grice Ln",
    "sg:city":"Kingsland",
    "sg:classifiers":[
        {
            "category":"Manufacturing",
            "subcategory":"Lumber",
            "type":"Manufacturing & Wholesale Goods"
        }
    ],
    "sg:phone":"+1 870 348 5552",
    "sg:postcode":"71652",
    "sg:province":"AR",
    "sg:tags":[
        "logging"
    ],
    "wof:name":"Grice Timber Services",
    "wof:placetype":"venue"
},
  "geometry": {"coordinates":[-92.28514800000001,33.85095],"type":"Point"}
}