{
  "type": "Feature",
  "properties": {
    "iso:country":"US",
    "sg:address":"20868 Highway 74",
    "sg:city":"Huntsville",
    "sg:classifiers":[
        {
            "category":"Building & Trades",
            "subcategory":"Electrical",
            "type":"Services"
        }
    ],
    "sg:phone":"+1 479 232 5370",
    "sg:postcode":"72740",
    "sg:province":"AR",
    "sg:tags":[
        "industrial",
        "electrician",
        "contractors-commercial",
        "electric"
    ],
    "wof:name":"Smith Electric",
    "wof:placetype":"venue"
},
  "geometry": {"coordinates":[-93.675219,36.033793],"type":"Point"}
}