{
  "type": "Feature",
  "properties": {
    "iso:country":"US",
    "sg:address":"631 Big Creek Rd",
    "sg:city":"Malvern",
    "sg:classifiers":[
        {
            "category":"Place Of Worship",
            "subcategory":"Church",
            "type":"Public Place"
        },
        {
            "category":"Place Of Worship",
            "type":"Public Place"
        }
    ],
    "sg:phone":"+1 501 332 3471",
    "sg:postcode":"72104",
    "sg:province":"AR",
    "sg:tags":[
        "churches-baptist-general",
        "churches-baptist"
    ],
    "wof:name":"Big Creek Mssnry. Baptist Ch.",
    "wof:placetype":"venue"
},
  "geometry": {"coordinates":[-92.706169,34.322063],"type":"Point"}
}