{
  "type": "Feature",
  "properties": {
    "iso:country":"US",
    "sg:address":"969 Main St",
    "sg:city":"Vilonia",
    "sg:classifiers":[
        {
            "category":"Home & Garden",
            "subcategory":"Hardware",
            "type":"Retail Goods"
        }
    ],
    "sg:phone":"+1 501 796 4555",
    "sg:postcode":"72173",
    "sg:province":"AR",
    "wof:name":"Vilonia Hardware",
    "wof:placetype":"venue"
},
  "geometry": {"coordinates":[-92.230521,35.082043],"type":"Point"}
}