{
  "type": "Feature",
  "properties": {
    "addr:full":"4400 Rixie Rd North Little Rock AR 72117",
    "addr:housenumber":"4400",
    "addr:postcode":"72117",
    "addr:street":"Rixie Rd",
    "iso:country":"US",
    "sg:address":"4400 Rixie Rd",
    "sg:city":"North Little Rock",
    "sg:classifiers":[
        {
            "category":"Building & Trades",
            "subcategory":"Construction",
            "type":"Services"
        }
    ],
    "sg:phone":"+1 501 833 9700",
    "sg:postcode":"72117",
    "sg:province":"AR",
    "sg:tags":[
        "fire",
        "restoration",
        "damage",
        "contractor"
    ],
    "wof:name":"First Choice Restoration Inc",
    "wof:placetype":"venue"
},
  "geometry": {"coordinates":[-92.182236,34.828158],"type":"Point"}
}