{
  "type": "Feature",
  "properties": {
    "iso:country":"US",
    "sg:address":"14011 Wilkerson Rd",
    "sg:city":"Little Rock",
    "sg:classifiers":[
        {
            "category":"Freight",
            "type":"Transportation"
        }
    ],
    "sg:phone":"+1 501 888 1230",
    "sg:postcode":"72206",
    "sg:province":"AR",
    "sg:tags":[
        "operator",
        "local",
        "trucking"
    ],
    "wof:name":"Rolling Thunder Trucking Inc",
    "wof:placetype":"venue"
},
  "geometry": {"coordinates":[-92.32134000000001,34.621774],"type":"Point"}
}