{
  "type": "Feature",
  "properties": {
    "addr:full":"200 N West Ave El Dorado AR 71730",
    "addr:housenumber":"200",
    "addr:postcode":"71730",
    "addr:street":"N West Ave",
    "iso:country":"US",
    "sg:address":"200 N West Ave",
    "sg:city":"El Dorado",
    "sg:classifiers":[
        {
            "category":"Banks & Credit Unions",
            "subcategory":"Bank",
            "type":"Services"
        }
    ],
    "sg:phone":"+1 870 881 5124",
    "sg:postcode":"71730",
    "sg:province":"AR",
    "sg:tags":[
        "national"
    ],
    "wof:name":"Simmons First Bank El Dorado",
    "wof:placetype":"venue"
},
  "geometry": {"coordinates":[-92.665497,33.213304],"type":"Point"}
}