{
  "type": "Feature",
  "properties": {
    "iso:country":"US",
    "sg:address":"601 Grand Point Dr",
    "sg:city":"Hot Springs National",
    "sg:classifiers":[
        {
            "category":"Professional",
            "type":"Services"
        }
    ],
    "sg:phone":"+1 501 262 4860",
    "sg:postcode":"71901",
    "sg:province":"AR",
    "wof:name":"Paul E Botteron",
    "wof:placetype":"venue"
},
  "geometry": {"coordinates":[-93.041055,34.457101],"type":"Point"}
}