{
  "type": "Feature",
  "properties": {
    "addr:full":"801 S Rodney Parham Rd Little Rock AR 72205",
    "addr:housenumber":"801",
    "addr:postcode":"72205",
    "addr:street":"S Rodney Parham Rd",
    "iso:country":"US",
    "sg:address":"801 S Rodney Parham Rd",
    "sg:city":"Little Rock",
    "sg:classifiers":[
        {
            "category":"Restaurant",
            "type":"Food & Drink"
        }
    ],
    "sg:phone":"+1 501 227 6123",
    "sg:postcode":"72205",
    "sg:province":"AR",
    "sg:tags":[
        "personal",
        "eating"
    ],
    "wof:name":"Fabulous Foods & Events",
    "wof:placetype":"venue"
},
  "geometry": {"coordinates":[-92.358913,34.74502],"type":"Point"}
}