{
  "type": "Feature",
  "properties": {
    "iso:country":"US",
    "sg:address":"511 N Dixieland Rd",
    "sg:city":"Rogers",
    "sg:classifiers":[
        {
            "category":"Education",
            "subcategory":"School",
            "type":"Public Place"
        }
    ],
    "sg:phone":"+1 479 631 3615",
    "sg:postcode":"72756",
    "sg:province":"AR",
    "sg:website":"www.rogers.k12.ar.us",
    "wof:name":"Oakdale Junior High School",
    "wof:placetype":"venue"
},
  "geometry": {"coordinates":[-94.143478,36.334656],"type":"Point"}
}