{
  "type": "Feature",
  "properties": {
    "iso:country":"US",
    "sg:address":"5000 LUVENE AVE",
    "sg:city":"SPRINGDALE",
    "sg:classifiers":[
        {
            "category":"Travel",
            "subcategory":"Hotels & Motels",
            "type":"Entertainment"
        }
    ],
    "sg:phone":"+1 479 872 1490",
    "sg:postcode":"72762",
    "sg:province":"AR",
    "sg:tags":[
        "corporate",
        "lodging"
    ],
    "sg:website":"http://redirect.searchignite.com/si/cm/tracking/DGTrackingRedirect.aspx?siclientid=2918&siredirect=http%3A%2F%2Fwww%2Eextendedstayamerica%2Ecom%2FFSD&sisearchengine=155&siproduct=ESA+Fayetteville+%2D+Springdale&clearppc=1",
    "wof:name":"Extended Stay America Fayetteville - Springdale",
    "wof:placetype":"venue"
},
  "geometry": {"coordinates":[-94.185982,36.168164],"type":"Point"}
}