{
  "type": "Feature",
  "properties": {
    "addr:full":"914 Columbia Ave Benton AR 72015",
    "addr:housenumber":"914",
    "addr:postcode":"72015",
    "addr:street":"Columbia Ave",
    "iso:country":"US",
    "sg:address":"914 Columbia Ave",
    "sg:city":"Benton",
    "sg:classifiers":[
        {
            "category":"Social Services",
            "subcategory":"Child Care",
            "type":"Services"
        }
    ],
    "sg:phone":"+1 501 776 4070",
    "sg:postcode":"72015",
    "sg:province":"AR",
    "wof:name":"Sharon's Day Care",
    "wof:placetype":"venue"
},
  "geometry": {"coordinates":[-92.577012,34.558528],"type":"Point"}
}