{
  "type": "Feature",
  "properties": {
    "iso:country":"US",
    "sg:address":"2506 E State Hwy 312",
    "sg:city":"Blytheville",
    "sg:phone":"+1 870 763 4747",
    "sg:postcode":"72315",
    "sg:province":"AR",
    "sg:tags":[
        "milo",
        "farming",
        "wheat",
        "soybean",
        "cotton"
    ],
    "wof:name":"Dixon Farms Inc",
    "wof:placetype":"venue"
},
  "geometry": {"coordinates":[-89.927027,35.871402],"type":"Point"}
}