{
  "type": "Feature",
  "properties": {
    "iso:country":"US",
    "sg:address":"5612 Patterson Rd",
    "sg:city":"Little Rock",
    "sg:classifiers":[
        {
            "category":"Building & Trades",
            "subcategory":"Construction",
            "type":"Services"
        }
    ],
    "sg:phone":"+1 501 568 5101",
    "sg:postcode":"72209",
    "sg:province":"AR",
    "sg:tags":[
        "contractor"
    ],
    "wof:name":"Gutter Helmet of Louisville",
    "wof:placetype":"venue"
},
  "geometry": {"coordinates":[-92.325347,34.697371],"type":"Point"}
}