{
  "type": "Feature",
  "properties": {
    "addr:full":"5911 R St Little Rock AR 72207",
    "addr:housenumber":"5911",
    "addr:postcode":"72207",
    "addr:street":"R St",
    "iso:country":"US",
    "sg:address":"5911 R St",
    "sg:city":"Little Rock",
    "sg:classifiers":[
        {
            "category":"Restaurant",
            "type":"Food & Drink"
        }
    ],
    "sg:menulink":"http://www.allmenus.com/ar/little-rock/81531-papa-johns-pizza/menu/",
    "sg:phone":"+1 501 664 5777",
    "sg:postcode":"72207",
    "sg:province":"AR",
    "sg:tags":[
        "american",
        "pizza"
    ],
    "wof:name":"Papa John's Pizza",
    "wof:placetype":"venue"
},
  "geometry": {"coordinates":[-92.339996,34.76933],"type":"Point"}
}