{
  "type": "Feature",
  "properties": {
    "addr:full":"2801 Spring St Hot Springs National AR 71901",
    "addr:housenumber":"2801",
    "addr:postcode":"71901",
    "addr:street":"Spring St",
    "iso:country":"US",
    "sg:address":"2801 Spring St",
    "sg:city":"Hot Springs National",
    "sg:classifiers":[
        {
            "category":"Education",
            "subcategory":"School",
            "type":"Public Place"
        }
    ],
    "sg:phone":"+1 501 262 1220",
    "sg:postcode":"71901",
    "sg:province":"AR",
    "wof:name":"Cutter-Morning Star High Schl",
    "wof:placetype":"venue"
},
  "geometry": {"coordinates":[-92.99165600000001,34.502853],"type":"Point"}
}