{
  "type": "Feature",
  "properties": {
    "iso:country":"US",
    "sg:address":"137 County Road 602",
    "sg:city":"Berryville",
    "sg:classifiers":[
        {
            "category":"Shopping",
            "subcategory":"Hobbies, Toys, & Games",
            "type":"Retail Goods"
        },
        {
            "category":"Recreation",
            "subcategory":"Gun Range",
            "type":"Entertainment"
        }
    ],
    "sg:phone":"+1 870 423 2294",
    "sg:postcode":"72616",
    "sg:province":"AR",
    "sg:tags":[
        "safety",
        "instruction",
        "marksmanship",
        "gunsmith"
    ],
    "wof:name":"Gunman Of Arkansas Inc",
    "wof:placetype":"venue"
},
  "geometry": {"coordinates":[-93.519514,36.398584],"type":"Point"}
}