{
  "type": "Feature",
  "properties": {
    "iso:country":"US",
    "sg:address":"201 S Hill Ave",
    "sg:city":"El Dorado",
    "sg:classifiers":[
        {
            "category":"Social Services",
            "subcategory":"Child Care",
            "type":"Services"
        }
    ],
    "sg:phone":"+1 870 862 2570",
    "sg:postcode":"71730",
    "sg:province":"AR",
    "sg:tags":[
        "kindergarten",
        "academic",
        "school"
    ],
    "wof:name":"First United Methodist Kndgrtn",
    "wof:placetype":"venue"
},
  "geometry": {"coordinates":[-92.662026,33.211129],"type":"Point"}
}