{
  "type": "Feature",
  "properties": {
    "iso:country":"US",
    "sg:address":"2809 W 12th St",
    "sg:city":"Little Rock",
    "sg:classifiers":[
        {
            "category":"Restaurant",
            "type":"Food & Drink"
        }
    ],
    "sg:phone":"+1 501 296 9900",
    "sg:postcode":"72204",
    "sg:province":"AR",
    "wof:name":"Sports & Beyond",
    "wof:placetype":"venue"
},
  "geometry": {"coordinates":[-92.305071,34.739799],"type":"Point"}
}