{
  "type": "Feature",
  "properties": {
    "iso:country":"US",
    "sg:address":"420 W Huron St",
    "sg:city":"Stuttgart",
    "sg:classifiers":[
        {
            "category":"Social Services",
            "subcategory":"Adult Care",
            "type":"Services"
        }
    ],
    "sg:phone":"+1 870 673 4383",
    "sg:postcode":"72160",
    "sg:province":"AR",
    "sg:tags":[
        "nursing",
        "facility",
        "residential",
        "skilled",
        "homes-institutional",
        "aged"
    ],
    "wof:name":"Forrest Manor",
    "wof:placetype":"venue"
},
  "geometry": {"coordinates":[-91.555728,34.511494],"type":"Point"}
}