{
  "type": "Feature",
  "properties": {
    "iso:country":"US",
    "sg:address":"6 Fiegel Loop",
    "sg:city":"Conway",
    "sg:classifiers":[
        {
            "category":"Retail",
            "subcategory":"Repair Shop",
            "type":"Services"
        }
    ],
    "sg:phone":"+1 501 450 7373",
    "sg:postcode":"72032",
    "sg:province":"AR",
    "sg:tags":[
        "welding"
    ],
    "wof:name":"Bufford Welding & Fabrication",
    "wof:placetype":"venue"
},
  "geometry": {"coordinates":[-92.33545100000001,35.092961],"type":"Point"}
}