{
  "type": "Feature",
  "properties": {
    "iso:country":"US",
    "sg:address":"131 W Main St",
    "sg:city":"Clarksville",
    "sg:classifiers":[
        {
            "category":"Professional",
            "subcategory":"Engineering",
            "type":"Services"
        }
    ],
    "sg:phone":"+1 479 754 8446",
    "sg:postcode":"72830",
    "sg:province":"AR",
    "sg:tags":[
        "engineer"
    ],
    "wof:name":"Brooks Consulting Svc",
    "wof:placetype":"venue"
},
  "geometry": {"coordinates":[-93.462749,35.471105],"type":"Point"}
}