{
  "type": "Feature",
  "properties": {
    "iso:country":"US",
    "sg:address":"203 S Bell St",
    "sg:city":"Foreman",
    "sg:classifiers":[
        {
            "category":"Freight",
            "type":"Transportation"
        }
    ],
    "sg:phone":"+1 870 542 6296",
    "sg:postcode":"71836",
    "sg:province":"AR",
    "sg:tags":[
        "grain",
        "elevator"
    ],
    "wof:name":"Mason Grain Elevator",
    "wof:placetype":"venue"
},
  "geometry": {"coordinates":[-94.39593499999999,33.719658],"type":"Point"}
}