{
  "type": "Feature",
  "properties": {
    "iso:country":"US",
    "sg:address":"105 W 2nd Ave",
    "sg:city":"Crossett",
    "sg:classifiers":[
        {
            "category":"Train Station",
            "subcategory":"Rail",
            "type":"Transportation"
        }
    ],
    "sg:phone":"+1 870 364 9000",
    "sg:postcode":"71635",
    "sg:province":"AR",
    "sg:tags":[
        "railroad"
    ],
    "wof:name":"Fordyce And Princeton R. R. Co.",
    "wof:placetype":"venue"
},
  "geometry": {"coordinates":[-91.961578,33.13386],"type":"Point"}
}