{
  "type": "Feature",
  "properties": {
    "iso:country":"US",
    "sg:address":"474 Trout Springs Rd",
    "sg:city":"Harrison",
    "sg:classifiers":[
        {
            "category":"Food & Beverages",
            "subcategory":"Groceries & Convenience Stores",
            "type":"Retail Goods"
        }
    ],
    "sg:phone":"+1 870 391 3658",
    "sg:postcode":"72601",
    "sg:province":"AR",
    "wof:name":"Vendor Grocery",
    "wof:placetype":"venue"
},
  "geometry": {"coordinates":[-93.181031,36.30253],"type":"Point"}
}