{
  "type": "Feature",
  "properties": {
    "iso:country":"US",
    "sg:address":"11766 Valley View Ln",
    "sg:city":"Bentonville",
    "sg:classifiers":[
        {
            "category":"Professional",
            "type":"Services"
        }
    ],
    "sg:phone":"+1 479 271 7674",
    "sg:postcode":"72712",
    "sg:province":"AR",
    "wof:name":"Baker Geren D D",
    "wof:placetype":"venue"
},
  "geometry": {"coordinates":[-94.24704,36.396992],"type":"Point"}
}