{
  "type": "Feature",
  "properties": {
    "iso:country":"US",
    "sg:address":"5531 US Hwy 82 W",
    "sg:city":"Crossett",
    "sg:classifiers":[
        {
            "category":"Government",
            "subcategory":"Office",
            "type":"Public Place"
        }
    ],
    "sg:phone":"+1 870 364 3168",
    "sg:postcode":"71635",
    "sg:province":"AR",
    "sg:tags":[
        "federal"
    ],
    "sg:website":"www.fws.gov",
    "wof:name":"US Fish & Wildlife Dept Svc",
    "wof:placetype":"venue"
},
  "geometry": {"coordinates":[-92.089267,33.151653],"type":"Point"}
}