{
  "type": "Feature",
  "properties": {
    "iso:country":"US",
    "sg:address":"2680 Shasten St",
    "sg:city":"Grove",
    "sg:classifiers":[
        {
            "category":"Banks & Credit Unions",
            "subcategory":"Bank",
            "type":"Services"
        },
        {
            "category":"Shopping",
            "subcategory":"Used Merchandise",
            "type":"Retail Goods"
        }
    ],
    "sg:phone":"+1 918 786 7513",
    "sg:postcode":"74344",
    "sg:province":"OK",
    "sg:tags":[
        "resale",
        "shop",
        "second",
        "hand"
    ],
    "wof:name":"3 Dumb Blondes",
    "wof:placetype":"venue"
},
  "geometry": {"coordinates":[-94.80320500000001,36.576335],"type":"Point"}
}