{
  "type": "Feature",
  "properties": {
    "iso:country":"US",
    "sg:address":"1083 Main St",
    "sg:city":"Vilonia",
    "sg:classifiers":[
        {
            "category":"Insurance",
            "subcategory":"Insurance Agent",
            "type":"Services"
        }
    ],
    "sg:phone":"+1 501 796 8233",
    "sg:postcode":"72173",
    "sg:province":"AR",
    "wof:name":"Sue Gordon Shock Insurance",
    "wof:placetype":"venue"
},
  "geometry": {"coordinates":[-92.21170499999999,35.083441],"type":"Point"}
}