{
  "type": "Feature",
  "properties": {
    "iso:country":"US",
    "sg:address":"3371 Central Ave",
    "sg:city":"Hot Springs National Park",
    "sg:classifiers":[
        {
            "category":"Restaurant",
            "type":"Food & Drink"
        }
    ],
    "sg:phone":"+1 501 625 5610",
    "sg:postcode":"71913",
    "sg:province":"AR",
    "sg:tags":[
        "fast"
    ],
    "wof:name":"Taco Bell",
    "wof:placetype":"venue"
},
  "geometry": {"coordinates":[-93.05978,34.473937],"type":"Point"}
}