{
  "type": "Feature",
  "properties": {
    "addr:full":"901 E Main St Siloam Springs OK 72761",
    "addr:housenumber":"901",
    "addr:postcode":"72761",
    "addr:street":"E Main St",
    "iso:country":"US",
    "sg:address":"901 E Main St",
    "sg:city":"Siloam Springs",
    "sg:classifiers":[
        {
            "category":"Autos & Motor Vehicles",
            "subcategory":"Auto Supplies",
            "type":"Retail Goods"
        }
    ],
    "sg:phone":"+1 479 549 3566",
    "sg:postcode":"72761",
    "sg:province":"OK",
    "sg:tags":[
        "tire"
    ],
    "wof:name":"Latino Tires",
    "wof:placetype":"venue"
},
  "geometry": {"coordinates":[-94.53345400000001,36.184091],"type":"Point"}
}