{
  "type": "Feature",
  "properties": {
    "iso:country":"US",
    "sg:address":"315 Phillips Rd",
    "sg:city":"N Little Rock",
    "sg:classifiers":[
        {
            "category":"Manufacturing",
            "subcategory":"Glass & Minerals",
            "type":"Manufacturing & Wholesale Goods"
        }
    ],
    "sg:phone":"+1 501 945 2336",
    "sg:postcode":"72117",
    "sg:province":"AR",
    "sg:tags":[
        "cement"
    ],
    "wof:name":"Precision Packaging Inc",
    "wof:placetype":"venue"
},
  "geometry": {"coordinates":[-92.221946,34.756757],"type":"Point"}
}