{
  "type": "Feature",
  "properties": {
    "iso:country":"US",
    "sg:address":"814 W C St",
    "sg:city":"Russellville",
    "sg:classifiers":[
        {
            "category":"Social Services",
            "subcategory":"Child Care",
            "type":"Services"
        }
    ],
    "sg:phone":"+1 479 967 0865",
    "sg:postcode":"72801",
    "sg:province":"AR",
    "wof:name":"Arkansas Valley Karate Academy",
    "wof:placetype":"venue"
},
  "geometry": {"coordinates":[-93.140266,35.281859],"type":"Point"}
}