{
  "type": "Feature",
  "properties": {
    "addr:full":"402 Kennedy Blvd Monticello AR 71655",
    "addr:housenumber":"402",
    "addr:postcode":"71655",
    "addr:street":"Kennedy Blvd",
    "iso:country":"US",
    "sg:address":"402 Kennedy Blvd",
    "sg:city":"Monticello",
    "sg:classifiers":[
        {
            "category":"Shopping",
            "type":"Retail Goods"
        }
    ],
    "sg:phone":"+1 870 367 3037",
    "sg:postcode":"71655",
    "sg:province":"AR",
    "sg:tags":[
        "pet",
        "shop"
    ],
    "wof:name":"F & J Home Improvement",
    "wof:placetype":"venue"
},
  "geometry": {"coordinates":[-91.77681800000001,33.639026],"type":"Point"}
}