{
  "type": "Feature",
  "properties": {
    "addr:full":"3359 W Old Farmington Rd Fayetteville AR 72704",
    "addr:housenumber":"3359",
    "addr:postcode":"72704",
    "addr:street":"W Old Farmington Rd",
    "iso:country":"US",
    "sg:address":"3359 W Old Farmington Rd",
    "sg:city":"Fayetteville",
    "sg:classifiers":[
        {
            "category":"Social Services",
            "subcategory":"Child Care",
            "type":"Services"
        }
    ],
    "sg:phone":"+1 479 466 6047",
    "sg:postcode":"72704",
    "sg:province":"AR",
    "wof:name":"A Child's Place Daycare",
    "wof:placetype":"venue"
},
  "geometry": {"coordinates":[-94.208327,36.051762],"type":"Point"}
}