{
  "type": "Feature",
  "properties": {
    "addr:full":"432 Court Sq De Witt AR 72042",
    "addr:housenumber":"432",
    "addr:postcode":"72042",
    "addr:street":"Court Sq De Witt",
    "iso:country":"US",
    "sg:address":"432 Court Sq",
    "sg:city":"De Witt",
    "sg:classifiers":[
        {
            "category":"Home & Garden",
            "subcategory":"Hardware",
            "type":"Retail Goods"
        }
    ],
    "sg:phone":"+1 870 946 1621",
    "sg:postcode":"72042",
    "sg:province":"AR",
    "sg:tags":[
        "store"
    ],
    "wof:name":"Gary W McGahhey Hardware Co",
    "wof:placetype":"venue"
},
  "geometry": {"coordinates":[-91.335365,34.295831],"type":"Point"}
}