{
  "type": "Feature",
  "properties": {
    "addr:full":"7000 Yarberry Ln Little Rock AR 72209",
    "addr:housenumber":"7000",
    "addr:postcode":"72209",
    "addr:street":"Yarberry Ln",
    "iso:country":"US",
    "sg:address":"7000 Yarberry Ln",
    "sg:city":"Little Rock",
    "sg:classifiers":[
        {
            "category":"Building & Trades",
            "subcategory":"Plumbing",
            "type":"Services"
        }
    ],
    "sg:phone":"+1 501 247 6380",
    "sg:postcode":"72209",
    "sg:province":"AR",
    "sg:tags":[
        "conditioning",
        "air",
        "system",
        "contractor"
    ],
    "wof:name":"Mc Ghee's Maintenance Heating",
    "wof:placetype":"venue"
},
  "geometry": {"coordinates":[-92.357934,34.644094],"type":"Point"}
}