{
  "type": "Feature",
  "properties": {
    "iso:country":"US",
    "sg:address":"14198 Monica Dr",
    "sg:city":"Gravette",
    "sg:classifiers":[
        {
            "category":"Building & Trades",
            "subcategory":"Construction",
            "type":"Services"
        }
    ],
    "sg:phone":"+1 479 795 2133",
    "sg:postcode":"72736",
    "sg:province":"AR",
    "sg:tags":[
        "concrete",
        "contractor"
    ],
    "wof:name":"BTC Concrete Inc",
    "wof:placetype":"venue"
},
  "geometry": {"coordinates":[-94.343696,36.373955],"type":"Point"}
}