{
  "type": "Feature",
  "properties": {
    "iso:country":"US",
    "sg:address":"11451 Hwy 37 N",
    "sg:city":"Tuckerman",
    "sg:phone":"+1 870 252 3345",
    "sg:postcode":"72473",
    "sg:province":"AR",
    "sg:tags":[
        "farm",
        "rice",
        "soybean"
    ],
    "wof:name":"Riley Alvis",
    "wof:placetype":"venue"
},
  "geometry": {"coordinates":[-91.07291600000001,35.716343],"type":"Point"}
}