{
  "type": "Feature",
  "properties": {
    "iso:country":"US",
    "sg:address":"4472 Cloud Mountain Rd",
    "sg:city":"Hector",
    "sg:classifiers":[
        {
            "category":"Building & Trades",
            "subcategory":"Construction",
            "type":"Services"
        }
    ],
    "sg:phone":"+1 479 284 2911",
    "sg:postcode":"72843",
    "sg:province":"AR",
    "sg:tags":[
        "house"
    ],
    "wof:name":"Lusk Robert Bulldozer Service",
    "wof:placetype":"venue"
},
  "geometry": {"coordinates":[-93.016619,35.426075],"type":"Point"}
}