{
  "type": "Feature",
  "properties": {
    "addr:full":"801 S Main St Mountain Home AR 72653",
    "addr:housenumber":"801",
    "addr:postcode":"72653",
    "addr:street":"S Main St",
    "iso:country":"US",
    "sg:address":"801 S Main St",
    "sg:city":"Mountain Home",
    "sg:classifiers":[
        {
            "category":"Shopping",
            "subcategory":"Florist",
            "type":"Retail Goods"
        }
    ],
    "sg:phone":"+1 870 425 8900",
    "sg:postcode":"72653",
    "sg:province":"AR",
    "wof:name":"Bloomers Florist",
    "wof:placetype":"venue"
},
  "geometry": {"coordinates":[-92.38523000000001,36.33389],"type":"Point"}
}