{
  "type": "Feature",
  "properties": {
    "iso:country":"US",
    "sg:address":"158 Co Rd 396",
    "sg:city":"Jonesboro",
    "sg:classifiers":[
        {
            "category":"Shopping",
            "subcategory":"Stationery & Office Supplies",
            "type":"Retail Goods"
        }
    ],
    "sg:phone":"+1 870 802 0349",
    "sg:postcode":"72401",
    "sg:province":"AR",
    "wof:name":"Holden Graphics Services",
    "wof:placetype":"venue"
},
  "geometry": {"coordinates":[-90.736311,35.888631],"type":"Point"}
}