{
  "type": "Feature",
  "properties": {
    "addr:full":"5482 Main St Crawfordsville AR 72327",
    "addr:housenumber":"5482",
    "addr:postcode":"72327",
    "addr:street":"Main St",
    "iso:country":"US",
    "sg:address":"5482 Main St",
    "sg:city":"Crawfordsville",
    "sg:classifiers":[
        {
            "category":"Utilities",
            "subcategory":"Telephone",
            "type":"Services"
        }
    ],
    "sg:phone":"+1 800 403 3302",
    "sg:postcode":"72327",
    "sg:province":"AR",
    "wof:name":"Southwestern Bell Telephone LP",
    "wof:placetype":"venue"
},
  "geometry": {"coordinates":[-90.326686,35.220328],"type":"Point"}
}