{
  "type": "Feature",
  "properties": {
    "iso:country":"US",
    "sg:address":"8501 Geyer Springs Rd",
    "sg:city":"Little Rock",
    "sg:classifiers":[
        {
            "category":"Insurance",
            "subcategory":"Insurance Agent",
            "type":"Services"
        }
    ],
    "sg:phone":"+1 501 568 5516",
    "sg:postcode":"72209",
    "sg:province":"AR",
    "wof:name":"R A Green Insurance",
    "wof:placetype":"venue"
},
  "geometry": {"coordinates":[-92.34424199999999,34.671107],"type":"Point"}
}