{
  "type": "Feature",
  "properties": {
    "iso:country":"US",
    "sg:address":"833 Airport Rd",
    "sg:city":"Hot Springs",
    "sg:classifiers":[
        {
            "category":"Shopping",
            "subcategory":"Used Merchandise",
            "type":"Retail Goods"
        }
    ],
    "sg:phone":"+1 501 767 3800",
    "sg:postcode":"71913",
    "sg:province":"AR",
    "sg:tags":[
        "antique"
    ],
    "wof:name":"Bob Goodman Auction Co",
    "wof:placetype":"venue"
},
  "geometry": {"coordinates":[-93.102862,34.480671],"type":"Point"}
}