{
  "type": "Feature",
  "properties": {
    "iso:country":"US",
    "sg:address":"2215 Wildwood Ave",
    "sg:city":"Sherwood",
    "sg:classifiers":[
        {
            "category":"Health Services",
            "subcategory":"Clinic",
            "type":"Services"
        }
    ],
    "sg:phone":"+1 501 552 7570",
    "sg:postcode":"72120",
    "sg:province":"AR",
    "wof:name":"Shah, Bushra",
    "wof:placetype":"venue"
},
  "geometry": {"coordinates":[-92.206705,34.814381],"type":"Point"}
}