{
  "type": "Feature",
  "properties": {
    "iso:country":"US",
    "sg:address":"3894 US Hwy 67 N",
    "sg:city":"Walnut Ridge",
    "sg:classifiers":[
        {
            "category":"Autos & Motor Vehicles",
            "subcategory":"Automobile Sales",
            "type":"Retail Goods"
        }
    ],
    "sg:phone":"+1 870 886 7159",
    "sg:postcode":"72476",
    "sg:province":"AR",
    "sg:tags":[
        "car",
        "dealer"
    ],
    "wof:name":"Mathews Auto Sales",
    "wof:placetype":"venue"
},
  "geometry": {"coordinates":[-90.95661699999999,36.133061],"type":"Point"}
}