{
  "type": "Feature",
  "properties": {
    "iso:country":"US",
    "sg:address":"5015 Georgia Ridge Est",
    "sg:city":"Alma",
    "sg:classifiers":[
        {
            "category":"Professional",
            "subcategory":"Engineering",
            "type":"Services"
        }
    ],
    "sg:phone":"+1 479 997 8897",
    "sg:postcode":"72921",
    "sg:province":"AR",
    "sg:tags":[
        "consulting",
        "engineer"
    ],
    "wof:name":"Kline Engineering Pa",
    "wof:placetype":"venue"
},
  "geometry": {"coordinates":[-94.148497,35.532115],"type":"Point"}
}