{
  "type": "Feature",
  "properties": {
    "iso:country":"US",
    "sg:address":"902 S Grand St",
    "sg:city":"Stuttgart",
    "sg:classifiers":[
        {
            "category":"Professional",
            "type":"Services"
        }
    ],
    "sg:phone":"+1 870 673 1413",
    "sg:postcode":"72160",
    "sg:province":"AR",
    "wof:name":"Roland Curtis Inc",
    "wof:placetype":"venue"
},
  "geometry": {"coordinates":[-91.550305,34.494821],"type":"Point"}
}