{
  "type": "Feature",
  "properties": {
    "iso:country":"US",
    "sg:address":"2770 Hwy 32 W",
    "sg:city":"Foreman",
    "sg:classifiers":[
        {
            "category":"Professional",
            "type":"Services"
        }
    ],
    "sg:phone":"+1 870 542 7378",
    "sg:postcode":"71836",
    "sg:province":"AR",
    "wof:name":"Randall Carrell",
    "wof:placetype":"venue"
},
  "geometry": {"coordinates":[-94.359191,33.682237],"type":"Point"}
}