{
  "type": "Feature",
  "properties": {
    "addr:full":"18149 State Hwy 18 Lake City AR 72447",
    "addr:housenumber":"18149",
    "addr:postcode":"72447",
    "addr:street":"State Hwy 18",
    "iso:country":"US",
    "sg:address":"18149 State Hwy 18",
    "sg:city":"Lake City",
    "sg:phone":"+1 870 486 2438",
    "sg:postcode":"72447",
    "sg:province":"AR",
    "sg:tags":[
        "farm",
        "cotton"
    ],
    "wof:name":"Roger Steele",
    "wof:placetype":"venue"
},
  "geometry": {"coordinates":[-90.368156,35.876553],"type":"Point"}
}