{
  "type": "Feature",
  "properties": {
    "iso:country":"US",
    "sg:address":"1001 W Walnut St",
    "sg:city":"Rogers",
    "sg:classifiers":[
        {
            "category":"Health Services",
            "subcategory":"Doctor",
            "type":"Services"
        }
    ],
    "sg:phone":"+1 479 636 7848",
    "sg:postcode":"72756",
    "sg:province":"AR",
    "sg:tags":[
        "clinic"
    ],
    "wof:name":"EZ To Quit Smoking Clinic",
    "wof:placetype":"venue"
},
  "geometry": {"coordinates":[-94.129644,36.333628],"type":"Point"}
}