{
  "type": "Feature",
  "properties": {
    "iso:country":"US",
    "sg:address":"411 S Victory St",
    "sg:city":"Little Rock",
    "sg:classifiers":[
        {
            "category":"Professional",
            "subcategory":"Advertising",
            "type":"Services"
        }
    ],
    "sg:phone":"+1 501 374 1500",
    "sg:postcode":"72201",
    "sg:province":"AR",
    "sg:tags":[
        "counselor"
    ],
    "sg:website":"www.arkansaspress.org",
    "wof:name":"Arkansas Press Svc",
    "wof:placetype":"venue"
},
  "geometry": {"coordinates":[-92.286464,34.746346],"type":"Point"}
}