{
  "type": "Feature",
  "properties": {
    "addr:full":"1133 State Hwy 163 Wynne AR 72396",
    "addr:housenumber":"1133",
    "addr:postcode":"72396",
    "addr:street":"State Hwy 163",
    "iso:country":"US",
    "sg:address":"1133 State Hwy 163",
    "sg:city":"Wynne",
    "sg:phone":"+1 870 238 3177",
    "sg:postcode":"72396",
    "sg:province":"AR",
    "sg:tags":[
        "farm",
        "rice",
        "soybean"
    ],
    "wof:name":"Larry Young",
    "wof:placetype":"venue"
},
  "geometry": {"coordinates":[-90.70372399999999,35.223625],"type":"Point"}
}