{
  "type": "Feature",
  "properties": {
    "addr:full":"503 Thomas Blvd Springdale AR 72762",
    "addr:housenumber":"503",
    "addr:postcode":"72762",
    "addr:street":"Thomas Blvd",
    "iso:country":"US",
    "sg:address":"503 Thomas Blvd",
    "sg:city":"Springdale",
    "sg:classifiers":[
        {
            "category":"Retail",
            "subcategory":"Laundry & Dry Cleaning",
            "type":"Services"
        }
    ],
    "sg:phone":"+1 479 750 0694",
    "sg:postcode":"72762",
    "sg:province":"AR",
    "sg:tags":[
        "laundries-self"
    ],
    "wof:name":"Neighborhood Coin Laundry",
    "wof:placetype":"venue"
},
  "geometry": {"coordinates":[-94.156913,36.189205],"type":"Point"}
}