{
  "type": "Feature",
  "properties": {
    "addr:full":"5600 Kavanaugh Blvd Little Rock AR 72207",
    "addr:postcode":"5600;72207",
    "addr:street":"Kavanaugh Blvd",
    "iso:country":"US",
    "sg:address":"5600 Kavanaugh Blvd",
    "sg:city":"Little Rock",
    "sg:classifiers":[
        {
            "category":"Shopping",
            "subcategory":"Clothing, Apparel, & Fashions",
            "type":"Retail Goods"
        }
    ],
    "sg:phone":"+1 501 664 7330",
    "sg:postcode":"72207",
    "sg:province":"AR",
    "sg:tags":[
        "wear"
    ],
    "wof:name":"Feinstein's",
    "wof:placetype":"venue"
},
  "geometry": {"coordinates":[-92.337035,34.770225],"type":"Point"}
}