{
  "type": "Feature",
  "properties": {
    "addr:full":"3 Newbridge Ct Little Rock AR 72227",
    "addr:housenumber":"3",
    "addr:postcode":"72227",
    "addr:street":"Newbridge Ct",
    "iso:country":"US",
    "sg:address":"3 Newbridge Ct",
    "sg:city":"Little Rock",
    "sg:classifiers":[
        {
            "category":"Health Services",
            "subcategory":"Health Practitioner",
            "type":"Services"
        }
    ],
    "sg:phone":"+1 501 223 8698",
    "sg:postcode":"72227",
    "sg:province":"AR",
    "wof:name":"A Step Ahead Theorpy For Kids",
    "wof:placetype":"venue"
},
  "geometry": {"coordinates":[-92.378483,34.776853],"type":"Point"}
}