{
  "type": "Feature",
  "properties": {
    "iso:country":"US",
    "sg:address":"1504 S Leslie St",
    "sg:city":"Stuttgart",
    "sg:classifiers":[
        {
            "category":"Professional",
            "subcategory":"Business Services",
            "type":"Services"
        }
    ],
    "sg:phone":"+1 870 673 6551",
    "sg:postcode":"72160",
    "sg:province":"AR",
    "sg:tags":[
        "auctioneer"
    ],
    "sg:website":"www.pondersauction.com",
    "wof:name":"Ponder's Auctions",
    "wof:placetype":"venue"
},
  "geometry": {"coordinates":[-91.54915699999999,34.488991],"type":"Point"}
}