{
  "type": "Feature",
  "properties": {
    "iso:country":"US",
    "sg:address":"1710 Harrison St",
    "sg:city":"Batesville",
    "sg:classifiers":[
        {
            "category":"Professional",
            "subcategory":"Business Services",
            "type":"Services"
        }
    ],
    "sg:phone":"+1 870 262 1200",
    "sg:postcode":"72501",
    "sg:province":"AR",
    "sg:tags":[
        "information",
        "referral"
    ],
    "wof:name":"Physicians Information Svc",
    "wof:placetype":"venue"
},
  "geometry": {"coordinates":[-91.634776,35.769498],"type":"Point"}
}