{
  "type": "Feature",
  "properties": {
    "addr:full":"5321 W 65th St Little Rock AR 72209",
    "addr:housenumber":"5321",
    "addr:postcode":"72209",
    "addr:street":"W 65Th St",
    "iso:country":"US",
    "sg:address":"5321 W 65th St",
    "sg:city":"Little Rock",
    "sg:classifiers":[
        {
            "category":"Food & Beverages",
            "subcategory":"Liquor & Beverages",
            "type":"Retail Goods"
        }
    ],
    "sg:phone":"+1 501 562 6150",
    "sg:postcode":"72209",
    "sg:province":"AR",
    "sg:tags":[
        "alcoholic"
    ],
    "wof:name":"905 Liquor Inc",
    "wof:placetype":"venue"
},
  "geometry": {"coordinates":[-92.338263,34.690423],"type":"Point"}
}