{
  "type": "Feature",
  "properties": {
    "addr:full":"1721 N Main St N Little Rock AR 72114",
    "addr:housenumber":"1721",
    "addr:postcode":"72114",
    "addr:street":"N Main St N",
    "iso:country":"US",
    "sg:address":"1721 N Main St",
    "sg:city":"N Little Rock",
    "sg:classifiers":[
        {
            "category":"Shopping",
            "subcategory":"Tobacco",
            "type":"Retail Goods"
        }
    ],
    "sg:phone":"+1 501 771 9675",
    "sg:postcode":"72114",
    "sg:province":"AR",
    "sg:tags":[
        "cigarette",
        "cigar",
        "dealer"
    ],
    "wof:name":"Hogs Smoke Shop Et Cetra",
    "wof:placetype":"venue"
},
  "geometry": {"coordinates":[-92.267168,34.771096],"type":"Point"}
}