{
  "type": "Feature",
  "properties": {
    "iso:country":"US",
    "sg:address":"104 Best Industrial Dr",
    "sg:city":"Jonesboro",
    "sg:classifiers":[
        {
            "category":"Wholesale",
            "subcategory":"Painting Supplies",
            "type":"Manufacturing & Wholesale Goods"
        }
    ],
    "sg:phone":"+1 870 935 9977",
    "sg:postcode":"72401",
    "sg:province":"AR",
    "sg:tags":[
        "paint"
    ],
    "wof:name":"Ingels Inc",
    "wof:placetype":"venue"
},
  "geometry": {"coordinates":[-90.739988,35.847255],"type":"Point"}
}