{
  "type": "Feature",
  "properties": {
    "iso:country":"US",
    "sg:address":"15 N Locust Ave",
    "sg:city":"Fayetteville",
    "sg:classifiers":[
        {
            "category":"Restaurant",
            "type":"Food & Drink"
        }
    ],
    "sg:phone":"+1 479 442 4896",
    "sg:postcode":"72701",
    "sg:province":"AR",
    "wof:name":"Humble Onion Grill",
    "wof:placetype":"venue"
},
  "geometry": {"coordinates":[-94.16313599999999,36.063576],"type":"Point"}
}