{
  "type": "Feature",
  "properties": {
    "iso:country":"US",
    "sg:address":"1016 Golf Course Dr",
    "sg:city":"Searcy",
    "sg:classifiers":[
        {
            "category":"Manufacturing",
            "subcategory":"Food",
            "type":"Manufacturing & Wholesale Goods"
        }
    ],
    "sg:phone":"+1 501 368 0089",
    "sg:postcode":"72143",
    "sg:province":"AR",
    "sg:tags":[
        "product"
    ],
    "wof:name":"Kenneth Canfield",
    "wof:placetype":"venue"
},
  "geometry": {"coordinates":[-91.698854,35.257574],"type":"Point"}
}