{
  "type": "Feature",
  "properties": {
    "addr:full":"4 Kirkoswald Cir Bella Vista AR 72715",
    "addr:housenumber":"4",
    "addr:postcode":"72715",
    "addr:street":"Kirkoswald Cir",
    "iso:country":"US",
    "sg:address":"4 Kirkoswald Cir",
    "sg:city":"Bella Vista",
    "sg:classifiers":[
        {
            "category":"Building & Trades",
            "subcategory":"Cleaning & Sanitation",
            "type":"Services"
        }
    ],
    "sg:phone":"+1 479 855 4882",
    "sg:postcode":"72715",
    "sg:province":"AR",
    "sg:tags":[
        "maintenance"
    ],
    "wof:name":"Spit & Shine Cleaning Contract",
    "wof:placetype":"venue"
},
  "geometry": {"coordinates":[-94.34776599999999,36.493704],"type":"Point"}
}