{
  "type": "Feature",
  "properties": {
    "iso:country":"US",
    "sg:address":"610 SE E St",
    "sg:city":"Bentonville",
    "sg:classifiers":[
        {
            "category":"Building & Trades",
            "subcategory":"Landscaping Services",
            "type":"Services"
        }
    ],
    "sg:phone":"+1 479 273 9639",
    "sg:postcode":"72712",
    "sg:province":"AR",
    "wof:name":"Arkansas Landscape Mgt Co",
    "wof:placetype":"venue"
},
  "geometry": {"coordinates":[-94.203226,36.365159],"type":"Point"}
}