{
  "type": "Feature",
  "properties": {
    "addr:full":"2805 W Pullen St Pine Bluff AR 71601",
    "addr:housenumber":"2805",
    "addr:postcode":"71601",
    "addr:street":"W Pullen St",
    "iso:country":"US",
    "sg:address":"2805 W Pullen St",
    "sg:city":"Pine Bluff",
    "sg:classifiers":[
        {
            "category":"Personal",
            "subcategory":"Barber",
            "type":"Services"
        }
    ],
    "sg:phone":"+1 870 535 8220",
    "sg:postcode":"71601",
    "sg:province":"AR",
    "wof:name":"Magnificent Brothers Barbering",
    "wof:placetype":"venue"
},
  "geometry": {"coordinates":[-92.03162500000001,34.230938],"type":"Point"}
}