{
  "type": "Feature",
  "properties": {
    "iso:country":"US",
    "sg:address":"21167 Black Oak Dr",
    "sg:city":"Garfield",
    "sg:classifiers":[
        {
            "category":"Wholesale",
            "subcategory":"Hardware",
            "type":"Manufacturing & Wholesale Goods"
        }
    ],
    "sg:phone":"+1 479 359 3871",
    "sg:postcode":"72732",
    "sg:province":"AR",
    "sg:tags":[
        "saw"
    ],
    "wof:name":"Costum Woodworks",
    "wof:placetype":"venue"
},
  "geometry": {"coordinates":[-93.9114,36.381329],"type":"Point"}
}