{
  "type": "Feature",
  "properties": {
    "iso:country":"US",
    "sg:address":"16424 Lawson Rd",
    "sg:city":"Little Rock",
    "sg:classifiers":[
        {
            "category":"Building & Trades",
            "subcategory":"Construction",
            "type":"Services"
        }
    ],
    "sg:phone":"+1 501 455 1044",
    "sg:postcode":"72210",
    "sg:province":"AR",
    "sg:tags":[
        "excavating",
        "contractor"
    ],
    "wof:name":"Glover & Carpenter Cnstr Co",
    "wof:placetype":"venue"
},
  "geometry": {"coordinates":[-92.459855,34.70507],"type":"Point"}
}