{
  "type": "Feature",
  "properties": {
    "iso:country":"US",
    "sg:address":"2118 Parnell Dr",
    "sg:city":"Fayetteville",
    "sg:classifiers":[
        {
            "category":"Retail",
            "subcategory":"Auto Repair",
            "type":"Services"
        }
    ],
    "sg:phone":"+1 479 443 6569",
    "sg:postcode":"72701",
    "sg:province":"AR",
    "sg:tags":[
        "automotive"
    ],
    "wof:name":"Budget Towing and Recovery",
    "wof:placetype":"venue"
},
  "geometry": {"coordinates":[-94.189361,36.053553],"type":"Point"}
}