{
  "type": "Feature",
  "properties": {
    "iso:country":"US",
    "sg:address":"1106 Backus Ave",
    "sg:city":"Springdale",
    "sg:classifiers":[
        {
            "category":"Autos & Motor Vehicles",
            "subcategory":"Auto Supplies",
            "type":"Retail Goods"
        }
    ],
    "sg:phone":"+1 479 750 1140",
    "sg:postcode":"72764",
    "sg:province":"AR",
    "sg:tags":[
        "regulation",
        "commercial",
        "tire"
    ],
    "wof:name":"Latino Tires",
    "wof:placetype":"venue"
},
  "geometry": {"coordinates":[-94.142674,36.196048],"type":"Point"}
}