{
  "type": "Feature",
  "properties": {
    "iso:country":"US",
    "sg:address":"8216 Arch St",
    "sg:city":"Little Rock",
    "sg:classifiers":[
        {
            "category":"Manufacturing",
            "subcategory":"Tools & Machinery",
            "type":"Manufacturing & Wholesale Goods"
        }
    ],
    "sg:phone":"+1 501 570 0700",
    "sg:postcode":"72206",
    "sg:province":"AR",
    "sg:tags":[
        "crane"
    ],
    "sg:website":"www.barnhartcrane.com",
    "wof:name":"Barnhart Crane & Rigging Co",
    "wof:placetype":"venue"
},
  "geometry": {"coordinates":[-92.303549,34.673943],"type":"Point"}
}