{
  "type": "Feature",
  "properties": {
    "iso:country":"US",
    "sg:address":"41 Dendron St",
    "sg:city":"Conway",
    "sg:classifiers":[
        {
            "category":"Professional",
            "subcategory":"Employment Agencies",
            "type":"Services"
        }
    ],
    "sg:phone":"+1 501 513 9194",
    "sg:postcode":"72032",
    "sg:province":"AR",
    "wof:name":"S Nelson",
    "wof:placetype":"venue"
},
  "geometry": {"coordinates":[-92.408806,35.088138],"type":"Point"}
}