{
  "type": "Feature",
  "properties": {
    "iso:country":"US",
    "sg:address":"40 Market Plz",
    "sg:city":"N Little Rock",
    "sg:classifiers":[
        {
            "category":"Home & Garden",
            "subcategory":"Carpets & Floor Coverings",
            "type":"Retail Goods"
        }
    ],
    "sg:phone":"+1 501 955 5501",
    "sg:postcode":"72117",
    "sg:province":"AR",
    "sg:tags":[
        "dealer",
        "rug"
    ],
    "wof:name":"Crazy Dave's Carpets",
    "wof:placetype":"venue"
},
  "geometry": {"coordinates":[-92.202961,34.786179],"type":"Point"}
}