{
  "type": "Feature",
  "properties": {
    "iso:country":"US",
    "sg:address":"4 Medical Ln",
    "sg:city":"Conway",
    "sg:classifiers":[
        {
            "category":"Health Services",
            "subcategory":"Doctor",
            "type":"Services"
        }
    ],
    "sg:phone":"+1 501 329 5205",
    "sg:postcode":"72034",
    "sg:province":"AR",
    "sg:tags":[
        "dentist"
    ],
    "wof:name":"Banister Family Dental",
    "wof:placetype":"venue"
},
  "geometry": {"coordinates":[-92.46008500000001,35.090176],"type":"Point"}
}