{
  "type": "Feature",
  "properties": {
    "addr:full":"2904 W Kings Hwy Paragould AR 72450",
    "addr:housenumber":"2904",
    "addr:postcode":"72450",
    "addr:street":"W Kings Hwy",
    "iso:country":"US",
    "sg:address":"2904 W Kings Hwy",
    "sg:city":"Paragould",
    "sg:classifiers":[
        {
            "category":"Cafe",
            "type":"Food & Drink"
        }
    ],
    "sg:menulink":"http://www.allmenus.com/ar/spring-grove/12805-the-dixie-cafe/menu/",
    "sg:phone":"+1 870 239 2000",
    "sg:postcode":"72450",
    "sg:province":"AR",
    "sg:tags":[
        "american"
    ],
    "wof:name":"The Dixie Cafe",
    "wof:placetype":"venue"
},
  "geometry": {"coordinates":[-90.525575,36.059891],"type":"Point"}
}