{
  "type": "Feature",
  "properties": {
    "iso:country":"US",
    "sg:address":"303 W Trimble Ave",
    "sg:city":"Berryville",
    "sg:classifiers":[
        {
            "category":"Shopping",
            "type":"Retail Goods"
        }
    ],
    "sg:phone":"+1 870 423 4141",
    "sg:postcode":"72616",
    "sg:province":"AR",
    "sg:tags":[
        "telephone",
        "cellular"
    ],
    "wof:name":"Russell Cellular",
    "wof:placetype":"venue"
},
  "geometry": {"coordinates":[-93.57853299999999,36.368337],"type":"Point"}
}