{
  "type": "Feature",
  "properties": {
    "iso:country":"US",
    "sg:address":"905 N Main St",
    "sg:city":"Bentonville",
    "sg:classifiers":[
        {
            "category":"Retail",
            "subcategory":"Portrait Studio",
            "type":"Services"
        }
    ],
    "sg:phone":"+1 479 855 4534",
    "sg:postcode":"72712",
    "sg:province":"AR",
    "sg:tags":[
        "photo"
    ],
    "wof:name":"Amy Hoff Photography",
    "wof:placetype":"venue"
},
  "geometry": {"coordinates":[-94.208759,36.380388],"type":"Point"}
}