{
  "type": "Feature",
  "properties": {
    "addr:full":"1010 Dortch Loop North Little Rock AR 72117",
    "addr:housenumber":"1010",
    "addr:postcode":"72117",
    "addr:street":"Dortch Loop",
    "iso:country":"US",
    "sg:address":"1010 Dortch Loop",
    "sg:city":"North Little Rock",
    "sg:classifiers":[
        {
            "category":"Professional",
            "subcategory":"Accounting & Tax Preparation",
            "type":"Services"
        }
    ],
    "sg:phone":"+1 501 961 1214",
    "sg:postcode":"72117",
    "sg:province":"AR",
    "wof:name":"Smith Rachel CPA PA",
    "wof:placetype":"venue"
},
  "geometry": {"coordinates":[-92.10795299999999,34.738327],"type":"Point"}
}