{
  "type": "Feature",
  "properties": {
    "iso:country":"US",
    "sg:address":"2911 Alpe Rd",
    "sg:city":"Crawfordsville",
    "sg:classifiers":[
        {
            "category":"Place Of Worship",
            "type":"Public Place"
        },
        {
            "category":"Place Of Worship",
            "subcategory":"Temple",
            "type":"Public Place"
        }
    ],
    "sg:phone":"+1 870 823 5230",
    "sg:postcode":"72327",
    "sg:province":"AR",
    "sg:tags":[
        "church"
    ],
    "wof:name":"Temple Eastex Inc",
    "wof:placetype":"venue"
},
  "geometry": {"coordinates":[-90.343773,35.241545],"type":"Point"}
}