{
  "type": "Feature",
  "properties": {
    "iso:country":"US",
    "sg:address":"1003 Anderson St",
    "sg:city":"West Helena",
    "sg:classifiers":[
        {
            "category":"Professional",
            "type":"Services"
        }
    ],
    "sg:phone":"+1 870 572 5016",
    "sg:postcode":"72390",
    "sg:province":"AR",
    "wof:name":"D & L Anderson Interprises",
    "wof:placetype":"venue"
},
  "geometry": {"coordinates":[-90.645172,34.550156],"type":"Point"}
}