{
  "type": "Feature",
  "properties": {
    "iso:country":"US",
    "sg:address":"101 Zachary Ln",
    "sg:city":"Lonoke",
    "sg:classifiers":[
        {
            "category":"Shopping",
            "type":"Retail Goods"
        }
    ],
    "sg:phone":"+1 501 940 3255",
    "sg:postcode":"72086",
    "sg:province":"AR",
    "sg:tags":[
        "merchandise"
    ],
    "wof:name":"Zack Eaves Custom Shop",
    "wof:placetype":"venue"
},
  "geometry": {"coordinates":[-91.994294,34.808296],"type":"Point"}
}