{
  "type": "Feature",
  "properties": {
    "iso:country":"US",
    "sg:address":"6000 W Markham St",
    "sg:city":"Little Rock",
    "sg:classifiers":[
        {
            "category":"Restaurant",
            "type":"Food & Drink"
        }
    ],
    "sg:phone":"+1 501 558 3477",
    "sg:postcode":"72205",
    "sg:province":"AR",
    "sg:tags":[
        "parlor",
        "ice",
        "cream"
    ],
    "sg:website":"www.dippindots.com",
    "wof:name":"Dippin' Dots",
    "wof:placetype":"venue"
},
  "geometry": {"coordinates":[-92.34233999999999,34.752313],"type":"Point"}
}