{
  "type": "Feature",
  "properties": {
    "iso:country":"US",
    "sg:address":"2017 E Race Ave",
    "sg:city":"Searcy",
    "sg:classifiers":[
        {
            "category":"Utilities",
            "subcategory":"Mobile Phone",
            "type":"Services"
        }
    ],
    "sg:phone":"+1 501 279 0011",
    "sg:postcode":"72143",
    "sg:province":"AR",
    "sg:tags":[
        "telephone",
        "cellular"
    ],
    "wof:name":"Cingular Wireless",
    "wof:placetype":"venue"
},
  "geometry": {"coordinates":[-91.713846,35.25053],"type":"Point"}
}