{
  "type": "Feature",
  "properties": {
    "iso:country":"US",
    "sg:address":"58 Chenal Cir",
    "sg:city":"Little Rock",
    "sg:classifiers":[
        {
            "category":"Shopping",
            "subcategory":"Gifts & Souvenirs",
            "type":"Retail Goods"
        }
    ],
    "sg:phone":"+1 501 821 1122",
    "sg:postcode":"72223",
    "sg:province":"AR",
    "wof:name":"Hair First Glass Gifts",
    "wof:placetype":"venue"
},
  "geometry": {"coordinates":[-92.47459600000001,34.776535],"type":"Point"}
}