{
  "type": "Feature",
  "properties": {
    "addr:full":"501 Airport Rd Bentonville AR 72712",
    "addr:housenumber":"501",
    "addr:postcode":"72712",
    "addr:street":"Airport Rd",
    "iso:country":"US",
    "sg:address":"501 Airport Rd",
    "sg:city":"Bentonville",
    "sg:classifiers":[
        {
            "category":"Sports & Exercise",
            "subcategory":"Golf",
            "type":"Entertainment"
        }
    ],
    "sg:phone":"+1 479 273 1316",
    "sg:postcode":"72712",
    "sg:province":"AR",
    "wof:name":"On Target Golf Center",
    "wof:placetype":"venue"
},
  "geometry": {"coordinates":[-94.216499,36.342899],"type":"Point"}
}