{
  "type": "Feature",
  "properties": {
    "iso:country":"US",
    "sg:address":"320 Sycamore St",
    "sg:city":"Augusta",
    "sg:classifiers":[
        {
            "category":"Social Services",
            "subcategory":"Child Care",
            "type":"Services"
        }
    ],
    "sg:phone":"+1 870 347 5596",
    "sg:postcode":"72006",
    "sg:province":"AR",
    "sg:tags":[
        "kindergarten",
        "academic",
        "school"
    ],
    "wof:name":"Crowley's Ridge Development",
    "wof:placetype":"venue"
},
  "geometry": {"coordinates":[-91.365428,35.27987],"type":"Point"}
}