{
  "type": "Feature",
  "properties": {
    "iso:country":"US",
    "sg:address":"64 River Ridge Rd",
    "sg:city":"Little Rock",
    "sg:classifiers":[
        {
            "category":"Professional",
            "type":"Services"
        }
    ],
    "sg:phone":"+1 501 225 7002",
    "sg:postcode":"72227",
    "sg:province":"AR",
    "wof:name":"Eiseman Foundation",
    "wof:placetype":"venue"
},
  "geometry": {"coordinates":[-92.378516,34.792416],"type":"Point"}
}