{
  "type": "Feature",
  "properties": {
    "addr:full":"142 Campground Ln Beebe AR 72012",
    "addr:housenumber":"142",
    "addr:postcode":"72012",
    "addr:street":"Campground Ln",
    "iso:country":"US",
    "sg:address":"142 Campground Ln",
    "sg:city":"Beebe",
    "sg:classifiers":[
        {
            "category":"Building & Trades",
            "subcategory":"Construction",
            "type":"Services"
        }
    ],
    "sg:phone":"+1 501 882 3880",
    "sg:postcode":"72012",
    "sg:province":"AR",
    "sg:tags":[
        "concrete",
        "contractor"
    ],
    "wof:name":"Cut Rite Inc",
    "wof:placetype":"venue"
},
  "geometry": {"coordinates":[-91.843402,35.061452],"type":"Point"}
}