{
  "type": "Feature",
  "properties": {
    "iso:country":"US",
    "sg:address":"4064 Bellefonte Rd",
    "sg:city":"Harrison",
    "sg:classifiers":[
        {
            "category":"Organizations",
            "subcategory":"Religious Organization",
            "type":"Services"
        }
    ],
    "sg:phone":"+1 870 429 5728",
    "sg:postcode":"72601",
    "sg:province":"AR",
    "wof:name":"Capps Full Gospel Church",
    "wof:placetype":"venue"
},
  "geometry": {"coordinates":[-93.019561,36.156168],"type":"Point"}
}