{
  "type": "Feature",
  "properties": {
    "iso:country":"US",
    "sg:address":"9601 Lile Dr",
    "sg:city":"Little Rock",
    "sg:classifiers":[
        {
            "category":"Health Services",
            "subcategory":"Doctor",
            "type":"Services"
        }
    ],
    "sg:phone":"+1 501 219 9198",
    "sg:postcode":"72205",
    "sg:province":"AR",
    "sg:tags":[
        "medical"
    ],
    "wof:name":"Graham Physcl Mdcine Rehab Svc",
    "wof:placetype":"venue"
},
  "geometry": {"coordinates":[-92.37944,34.74543],"type":"Point"}
}