{
  "type": "Feature",
  "properties": {
    "iso:country":"US",
    "sg:address":"320 Luzerne St",
    "sg:city":"Mount Ida",
    "sg:classifiers":[
        {
            "category":"Health Services",
            "subcategory":"Medical Lab",
            "type":"Services"
        }
    ],
    "sg:phone":"+1 870 867 2175",
    "sg:postcode":"71957",
    "sg:province":"AR",
    "sg:tags":[
        "laboratory"
    ],
    "wof:name":"Bearden Jeffrey MD",
    "wof:placetype":"venue"
},
  "geometry": {"coordinates":[-93.639268,34.552583],"type":"Point"}
}