{
  "type": "Feature",
  "properties": {
    "iso:country":"US",
    "sg:address":"25914 State Hwy 10",
    "sg:city":"Roland",
    "sg:classifiers":[
        {
            "category":"Building & Trades",
            "subcategory":"Construction",
            "type":"Services"
        }
    ],
    "sg:phone":"+1 501 868 5784",
    "sg:postcode":"72135",
    "sg:province":"AR",
    "sg:tags":[
        "contractor"
    ],
    "wof:name":"Innovtive Bldrs of Little Rock",
    "wof:placetype":"venue"
},
  "geometry": {"coordinates":[-92.54906099999999,34.836312],"type":"Point"}
}