{
  "type": "Feature",
  "properties": {
    "iso:country":"US",
    "sg:address":"1007 N Buerkle St",
    "sg:city":"Stuttgart",
    "sg:classifiers":[
        {
            "category":"Shopping",
            "subcategory":"Bicycles & Sporting Goods",
            "type":"Retail Goods"
        }
    ],
    "sg:phone":"+1 870 673 3926",
    "sg:postcode":"72160",
    "sg:province":"AR",
    "sg:tags":[
        "shop",
        "pawn"
    ],
    "wof:name":"Grand Prairie Trading & Loan",
    "wof:placetype":"venue"
},
  "geometry": {"coordinates":[-91.557748,34.510801],"type":"Point"}
}