{
  "type": "Feature",
  "properties": {
    "iso:country":"US",
    "sg:address":"3 Club Rd",
    "sg:city":"Horseshoe Bend",
    "sg:classifiers":[
        {
            "category":"Wholesale",
            "subcategory":"Motor Vehicles",
            "type":"Manufacturing & Wholesale Goods"
        }
    ],
    "sg:phone":"+1 870 670 4900",
    "sg:postcode":"72512",
    "sg:province":"AR",
    "wof:name":"Bilbo Transports",
    "wof:placetype":"venue"
},
  "geometry": {"coordinates":[-91.76401300000001,36.229143],"type":"Point"}
}