{
  "type": "Feature",
  "properties": {
    "iso:country":"US",
    "sg:address":"217 S 21st Ter",
    "sg:city":"Fort Smith",
    "sg:classifiers":[
        {
            "category":"Building & Trades",
            "subcategory":"Construction",
            "type":"Services"
        }
    ],
    "sg:phone":"+1 479 629 6561",
    "sg:postcode":"72908",
    "sg:province":"AR",
    "sg:tags":[
        "designer",
        "dealer",
        "pool",
        "swimming"
    ],
    "wof:name":"Southern Pools",
    "wof:placetype":"venue"
},
  "geometry": {"coordinates":[-94.410951,35.30789],"type":"Point"}
}