{
  "type": "Feature",
  "properties": {
    "iso:country":"US",
    "sg:address":"1 August Ln",
    "sg:city":"Bella Vista",
    "sg:classifiers":[
        {
            "category":"Professional",
            "subcategory":"Business Services",
            "type":"Services"
        }
    ],
    "sg:phone":"+1 479 855 2922",
    "sg:postcode":"72714",
    "sg:province":"AR",
    "wof:name":"At Ease Designs",
    "wof:placetype":"venue"
},
  "geometry": {"coordinates":[-94.2522,36.453368],"type":"Point"}
}