{
  "type": "Feature",
  "properties": {
    "iso:country":"US",
    "sg:address":"20603 Arch Street Pike",
    "sg:city":"Little Rock",
    "sg:classifiers":[
        {
            "category":"Shopping",
            "subcategory":"Florist",
            "type":"Retail Goods"
        }
    ],
    "sg:phone":"+1 501 888 3377",
    "sg:postcode":"72206",
    "sg:province":"AR",
    "wof:name":"Floral Express",
    "wof:placetype":"venue"
},
  "geometry": {"coordinates":[-92.335561,34.568579],"type":"Point"}
}