{
  "type": "Feature",
  "properties": {
    "iso:country":"US",
    "sg:address":"110 E Elm St",
    "sg:city":"El Dorado",
    "sg:classifiers":[
        {
            "category":"Restaurant",
            "type":"Food & Drink"
        }
    ],
    "sg:phone":"+1 870 863 4000",
    "sg:postcode":"71730",
    "sg:province":"AR",
    "wof:name":"Fayrays",
    "wof:placetype":"venue"
},
  "geometry": {"coordinates":[-92.663672,33.212499],"type":"Point"}
}