{
  "type": "Feature",
  "properties": {
    "addr:full":"218 S Maple St Little Rock AR 72205",
    "addr:housenumber":"218",
    "addr:postcode":"72205",
    "addr:street":"S Maple St",
    "iso:country":"US",
    "sg:address":"218 S Maple St",
    "sg:city":"Little Rock",
    "sg:classifiers":[
        {
            "category":"Retail",
            "subcategory":"Portrait Studio",
            "type":"Services"
        }
    ],
    "sg:phone":"+1 501 952 9422",
    "sg:postcode":"72205",
    "sg:province":"AR",
    "sg:tags":[
        "photo"
    ],
    "wof:name":"Shawn Miller Photography",
    "wof:placetype":"venue"
},
  "geometry": {"coordinates":[-92.31431499999999,34.74987],"type":"Point"}
}