{
  "type": "Feature",
  "properties": {
    "iso:country":"US",
    "sg:address":"5300 Rogers Ave",
    "sg:city":"Fort Smith",
    "sg:classifiers":[
        {
            "category":"Personal",
            "type":"Services"
        },
        {
            "category":"Shopping",
            "subcategory":"Clothing, Apparel, & Fashions",
            "type":"Retail Goods"
        }
    ],
    "sg:phone":"+1 479 452 1177",
    "sg:postcode":"72903",
    "sg:province":"AR",
    "sg:tags":[
        "shop",
        "tuxedo",
        "bridal",
        "rental"
    ],
    "wof:name":"Beau's Tuxedos",
    "wof:placetype":"venue"
},
  "geometry": {"coordinates":[-94.37383199999999,35.363275],"type":"Point"}
}