{
  "type": "Feature",
  "properties": {
    "iso:country":"US",
    "sg:address":"1203 N Maple St",
    "sg:city":"Searcy",
    "sg:classifiers":[
        {
            "category":"Autos & Motor Vehicles",
            "subcategory":"Boat Sales",
            "type":"Retail Goods"
        }
    ],
    "sg:phone":"+1 501 268 7985",
    "sg:postcode":"72143",
    "sg:province":"AR",
    "sg:tags":[
        "dealer",
        "sales"
    ],
    "wof:name":"Discount Marine",
    "wof:placetype":"venue"
},
  "geometry": {"coordinates":[-91.744759,35.262496],"type":"Point"}
}