{
  "type": "Feature",
  "properties": {
    "addr:full":"2827 E Millennium Pl Fayetteville AR 72703",
    "addr:housenumber":"2827",
    "addr:postcode":"72703",
    "addr:street":"E Millennium Pl",
    "iso:country":"US",
    "sg:address":"2827 E Millennium Pl",
    "sg:city":"Fayetteville",
    "sg:classifiers":[
        {
            "category":"Health Services",
            "subcategory":"Doctor",
            "type":"Services"
        }
    ],
    "sg:phone":"+1 479 521 4447",
    "sg:postcode":"72703",
    "sg:province":"AR",
    "wof:name":"Charles Chad Johnson",
    "wof:placetype":"venue"
},
  "geometry": {"coordinates":[-94.121667,36.12091],"type":"Point"}
}