{
  "type": "Feature",
  "properties": {
    "iso:country":"US",
    "sg:address":"1404 W Pershing Blvd",
    "sg:city":"N Little Rock",
    "sg:classifiers":[
        {
            "category":"Wholesale",
            "subcategory":"Farm Supplies",
            "type":"Manufacturing & Wholesale Goods"
        }
    ],
    "sg:phone":"+1 501 753 2727",
    "sg:postcode":"72114",
    "sg:province":"AR",
    "sg:tags":[
        "control",
        "equipment",
        "pest"
    ],
    "wof:name":"Arkansas Pest Control Supplies",
    "wof:placetype":"venue"
},
  "geometry": {"coordinates":[-92.28216399999999,34.78141],"type":"Point"}
}