{
  "type": "Feature",
  "properties": {
    "iso:country":"US",
    "sg:address":"4600 Towson Ave",
    "sg:city":"Fort Smith",
    "sg:classifiers":[
        {
            "category":"Health Services",
            "subcategory":"Health Practitioner",
            "type":"Services"
        }
    ],
    "sg:phone":"+1 479 709 7150",
    "sg:postcode":"72901",
    "sg:province":"AR",
    "sg:tags":[
        "therapist",
        "physical"
    ],
    "wof:name":"River Valley Rehab Ctr",
    "wof:placetype":"venue"
},
  "geometry": {"coordinates":[-94.422691,35.340461],"type":"Point"}
}