{
  "type": "Feature",
  "properties": {
    "iso:country":"US",
    "sg:address":"16 Regency Dr",
    "sg:city":"Texarkana",
    "sg:classifiers":[
        {
            "category":"Building & Trades",
            "subcategory":"Construction",
            "type":"Services"
        }
    ],
    "sg:phone":"+1 870 774 6234",
    "sg:postcode":"71854",
    "sg:province":"AR",
    "sg:tags":[
        "house"
    ],
    "wof:name":"Betty Cox Design Consultant",
    "wof:placetype":"venue"
},
  "geometry": {"coordinates":[-94.016465,33.450358],"type":"Point"}
}