{
  "type": "Feature",
  "properties": {
    "iso:country":"US",
    "sg:address":"777 Lawrence St",
    "sg:city":"Batesville",
    "sg:classifiers":[
        {
            "category":"Retail",
            "subcategory":"Auto Repair",
            "type":"Services"
        }
    ],
    "sg:phone":"+1 870 698 1593",
    "sg:postcode":"72501",
    "sg:province":"AR",
    "sg:tags":[
        "repairing",
        "automobile"
    ],
    "wof:name":"Lenney's Automotive Repair Service",
    "wof:placetype":"venue"
},
  "geometry": {"coordinates":[-91.645251,35.766694],"type":"Point"}
}