{
  "type": "Feature",
  "properties": {
    "addr:full":"1406 US Hwy 49 N Paragould AR 72450",
    "addr:housenumber":"1406",
    "addr:postcode":"72450",
    "addr:street":"Us Hwy 49 N",
    "iso:country":"US",
    "sg:address":"1406 US Hwy 49 N",
    "sg:city":"Paragould",
    "sg:classifiers":[
        {
            "category":"Organizations",
            "subcategory":"Religious Organization",
            "type":"Services"
        }
    ],
    "sg:phone":"+1 870 236 3238",
    "sg:postcode":"72450",
    "sg:province":"AR",
    "sg:tags":[
        "church"
    ],
    "wof:name":"Church Of God",
    "wof:placetype":"venue"
},
  "geometry": {"coordinates":[-90.49807300000001,36.072619],"type":"Point"}
}