{
  "type": "Feature",
  "properties": {
    "iso:country":"US",
    "sg:address":"216 Nisbett St",
    "sg:city":"Jonesboro",
    "sg:classifiers":[
        {
            "category":"Manufacturing",
            "subcategory":"Metals",
            "type":"Manufacturing & Wholesale Goods"
        }
    ],
    "sg:phone":"+1 870 933 7309",
    "sg:postcode":"72401",
    "sg:province":"AR",
    "sg:tags":[
        "fab",
        "steel",
        "mfg"
    ],
    "wof:name":"Double Safe Doors",
    "wof:placetype":"venue"
},
  "geometry": {"coordinates":[-90.718557,35.841372],"type":"Point"}
}