{
  "type": "Feature",
  "properties": {
    "iso:country":"US",
    "sg:address":"2500 Hwy 67 S",
    "sg:city":"Newport",
    "sg:classifiers":[
        {
            "category":"Shopping",
            "subcategory":"Department Store",
            "type":"Retail Goods"
        }
    ],
    "sg:phone":"+1 870 523 2500",
    "sg:postcode":"72473",
    "sg:province":"AR",
    "wof:name":"Wal-Mart",
    "wof:placetype":"venue"
},
  "geometry": {"coordinates":[-91.211268,35.711636],"type":"Point"}
}