{
  "type": "Feature",
  "properties": {
    "iso:country":"US",
    "sg:address":"4600 S University Ave",
    "sg:city":"Little Rock",
    "sg:classifiers":[
        {
            "category":"Autos & Motor Vehicles",
            "subcategory":"Automobile Sales",
            "type":"Retail Goods"
        }
    ],
    "sg:phone":"+1 501 562 3673",
    "sg:postcode":"72204",
    "sg:province":"AR",
    "sg:tags":[
        "car",
        "dealer"
    ],
    "sg:website":"www.landersfordsales.com",
    "wof:name":"Landers Ford",
    "wof:placetype":"venue"
},
  "geometry": {"coordinates":[-92.344074,34.707896],"type":"Point"}
}