{
  "type": "Feature",
  "properties": {
    "iso:country":"US",
    "sg:address":"1000 S Division St",
    "sg:city":"Lavaca",
    "sg:classifiers":[
        {
            "category":"Education",
            "subcategory":"School",
            "type":"Public Place"
        }
    ],
    "sg:phone":"+1 479 674 5618",
    "sg:postcode":"72941",
    "sg:province":"AR",
    "wof:name":"Lavaca Middle School",
    "wof:placetype":"venue"
},
  "geometry": {"coordinates":[-94.17332,35.328817],"type":"Point"}
}