{
  "type": "Feature",
  "properties": {
    "iso:country":"US",
    "sg:address":"6717 Garrison Rd",
    "sg:city":"Little Rock",
    "sg:classifiers":[
        {
            "category":"Retail",
            "subcategory":"Car Wash",
            "type":"Services"
        }
    ],
    "sg:phone":"+1 501 225 4442",
    "sg:postcode":"72223",
    "sg:province":"AR",
    "sg:tags":[
        "automobile",
        "detail",
        "clean"
    ],
    "wof:name":"Superior Detail & Auto Sales",
    "wof:placetype":"venue"
},
  "geometry": {"coordinates":[-92.573624,34.803156],"type":"Point"}
}