{
  "type": "Feature",
  "properties": {
    "iso:country":"US",
    "sg:address":"105 Cox",
    "sg:city":"Benton",
    "sg:classifiers":[
        {
            "category":"Social Services",
            "type":"Services"
        }
    ],
    "sg:phone":"+1 501 315 8100",
    "sg:postcode":"72015",
    "sg:province":"AR",
    "sg:tags":[
        "youth",
        "organization",
        "center"
    ],
    "wof:name":"Boys & Girls Club",
    "wof:placetype":"venue"
},
  "geometry": {"coordinates":[-92.571922,34.562899],"type":"Point"}
}