{
  "type": "Feature",
  "properties": {
    "iso:country":"US",
    "sg:address":"701 Lisa Ln W",
    "sg:city":"Van Buren",
    "sg:classifiers":[
        {
            "category":"Building & Trades",
            "subcategory":"Cleaning & Sanitation",
            "type":"Services"
        }
    ],
    "sg:phone":"+1 479 471 1334",
    "sg:postcode":"72956",
    "sg:province":"AR",
    "sg:tags":[
        "ventilating",
        "system"
    ],
    "wof:name":"Keen Services",
    "wof:placetype":"venue"
},
  "geometry": {"coordinates":[-94.370886,35.452548],"type":"Point"}
}