{
  "type": "Feature",
  "properties": {
    "addr:full":"2707 Carma St Benton AR 72015",
    "addr:housenumber":"2707",
    "addr:postcode":"72015",
    "addr:street":"Carma St",
    "iso:country":"US",
    "sg:address":"2707 Carma St",
    "sg:city":"Benton",
    "sg:classifiers":[
        {
            "category":"Recreation",
            "type":"Entertainment"
        }
    ],
    "sg:phone":"+1 501 315 1250",
    "sg:postcode":"72015",
    "sg:province":"AR",
    "sg:tags":[
        "farm",
        "equine"
    ],
    "wof:name":"Carma Farm",
    "wof:placetype":"venue"
},
  "geometry": {"coordinates":[-92.559383,34.533998],"type":"Point"}
}