{
  "type": "Feature",
  "properties": {
    "iso:country":"US",
    "sg:address":"2720 Woods Ln",
    "sg:city":"Rogers",
    "sg:classifiers":[
        {
            "category":"Shopping",
            "subcategory":"Books",
            "type":"Retail Goods"
        }
    ],
    "sg:phone":"+1 479 636 2222",
    "sg:postcode":"72756",
    "sg:province":"AR",
    "sg:tags":[
        "dealer"
    ],
    "sg:website":"www.nwacc.edu",
    "wof:name":"N W Ark Comm Coil Bookstore",
    "wof:placetype":"venue"
},
  "geometry": {"coordinates":[-94.155548,36.35616],"type":"Point"}
}