{
  "type": "Feature",
  "properties": {
    "iso:country":"US",
    "sg:address":"3327 O St N",
    "sg:city":"Fort Smith",
    "sg:classifiers":[
        {
            "category":"Home & Garden",
            "subcategory":"Garden Supply",
            "type":"Retail Goods"
        }
    ],
    "sg:phone":"+1 479 782 9987",
    "sg:postcode":"72904",
    "sg:province":"AR",
    "sg:tags":[
        "plant",
        "flower",
        "nurseryman"
    ],
    "wof:name":"Neumeiers Nursery & Florist",
    "wof:placetype":"venue"
},
  "geometry": {"coordinates":[-94.396047,35.393242],"type":"Point"}
}