{
  "type": "Feature",
  "properties": {
    "iso:country":"US",
    "sg:address":"2 Colonial Dr",
    "sg:city":"Texarkana",
    "sg:classifiers":[
        {
            "category":"Airline",
            "type":"Transportation"
        }
    ],
    "sg:phone":"+1 870 774 2474",
    "sg:postcode":"71854",
    "sg:province":"AR",
    "sg:tags":[
        "equipment",
        "nonscheduled",
        "air"
    ],
    "wof:name":"Helicopters Southwest",
    "wof:placetype":"venue"
},
  "geometry": {"coordinates":[-94.018701,33.451713],"type":"Point"}
}