{
  "type": "Feature",
  "properties": {
    "iso:country":"US",
    "sg:address":"810 State Hwy 10",
    "sg:city":"Perryville",
    "sg:classifiers":[
        {
            "category":"Food & Beverages",
            "subcategory":"Groceries & Convenience Stores",
            "type":"Retail Goods"
        }
    ],
    "sg:phone":"+1 501 889 2261",
    "sg:postcode":"72126",
    "sg:province":"AR",
    "wof:name":"Friendly Food Market",
    "wof:placetype":"venue"
},
  "geometry": {"coordinates":[-92.79449,35.041128],"type":"Point"}
}