{
  "type": "Feature",
  "properties": {
    "addr:full":"4522 Lynch Dr North Little Rock AR 72117",
    "addr:housenumber":"4522",
    "addr:postcode":"72117",
    "addr:street":"Lynch Dr",
    "iso:country":"US",
    "sg:address":"4522 Lynch Dr",
    "sg:city":"North Little Rock",
    "sg:classifiers":[
        {
            "category":"Insurance",
            "subcategory":"Insurance Agent",
            "type":"Services"
        }
    ],
    "sg:phone":"+1 501 945 5511",
    "sg:postcode":"72117",
    "sg:province":"AR",
    "wof:name":"Webb & Associates Inc",
    "wof:placetype":"venue"
},
  "geometry": {"coordinates":[-92.212112,34.758497],"type":"Point"}
}