{
  "type": "Feature",
  "properties": {
    "iso:country":"US",
    "sg:address":"1370 Front St",
    "sg:city":"Eudora",
    "sg:classifiers":[
        {
            "category":"Bars & Pubs",
            "type":"Food & Drink"
        }
    ],
    "sg:phone":"+1 870 355 8581",
    "sg:postcode":"71640",
    "sg:province":"AR",
    "wof:name":"Blue Front Tavern",
    "wof:placetype":"venue"
},
  "geometry": {"coordinates":[-91.25966200000001,33.124144],"type":"Point"}
}