{
  "type": "Feature",
  "properties": {
    "addr:full":"400 Maul Rd Camden AR 71701",
    "addr:housenumber":"400",
    "addr:postcode":"71701",
    "addr:street":"Maul Rd",
    "iso:country":"US",
    "sg:address":"400 Maul Rd",
    "sg:city":"Camden",
    "sg:classifiers":[
        {
            "category":"Professional",
            "subcategory":"Management & Consulting",
            "type":"Services"
        },
        {
            "category":"Education",
            "subcategory":"Special Training",
            "type":"Public Place"
        }
    ],
    "sg:phone":"+1 870 836 2213",
    "sg:postcode":"71701",
    "sg:province":"AR",
    "sg:tags":[
        "consultant",
        "educational",
        "c",
        "business"
    ],
    "sg:website":"www.scsc.k12.ar.us",
    "wof:name":"South Central Service Co-Op",
    "wof:placetype":"venue"
},
  "geometry": {"coordinates":[-92.83625000000001,33.5944],"type":"Point"}
}