{
  "type": "Feature",
  "properties": {
    "addr:full":"439 N Main St Nashville AR 71852",
    "addr:housenumber":"439",
    "addr:postcode":"71852",
    "addr:street":"N Main St",
    "iso:country":"US",
    "sg:address":"439 N Main St",
    "sg:city":"Nashville",
    "sg:classifiers":[
        {
            "category":"Professional",
            "subcategory":"Lawyer & Legal Services",
            "type":"Services"
        }
    ],
    "sg:phone":"+1 870 845 1550",
    "sg:postcode":"71852",
    "sg:province":"AR",
    "sg:tags":[
        "attorney"
    ],
    "wof:name":"Leann Daniel",
    "wof:placetype":"venue"
},
  "geometry": {"coordinates":[-93.847115,33.947147],"type":"Point"}
}