{
  "type": "Feature",
  "properties": {
    "iso:country":"US",
    "sg:address":"2700 Bryan Rd",
    "sg:city":"Van Buren",
    "sg:classifiers":[
        {
            "category":"Professional",
            "subcategory":"Employment Agencies",
            "type":"Services"
        }
    ],
    "sg:phone":"+1 479 471 0400",
    "sg:postcode":"72956",
    "sg:province":"AR",
    "wof:name":"TEC Employment Company",
    "wof:placetype":"venue"
},
  "geometry": {"coordinates":[-94.330757,35.439966],"type":"Point"}
}