{
  "type": "Feature",
  "properties": {
    "iso:country":"US",
    "sg:address":"8914 Southshore Dr",
    "sg:city":"Hackett",
    "sg:classifiers":[
        {
            "category":"Professional",
            "type":"Services"
        }
    ],
    "sg:phone":"+1 479 639 1228",
    "sg:postcode":"72937",
    "sg:province":"AR",
    "sg:tags":[
        "establishment"
    ],
    "wof:name":"Frye H B+jr",
    "wof:placetype":"venue"
},
  "geometry": {"coordinates":[-94.41597,35.08953],"type":"Point"}
}