{
  "type": "Feature",
  "properties": {
    "iso:country":"US",
    "sg:address":"5117 Hwy 141 S",
    "sg:city":"Paragould",
    "sg:classifiers":[
        {
            "category":"Building & Trades",
            "subcategory":"Construction",
            "type":"Services"
        }
    ],
    "sg:phone":"+1 870 476 3195",
    "sg:postcode":"72450",
    "sg:province":"AR",
    "sg:tags":[
        "contractor"
    ],
    "wof:name":"Michael Vowell",
    "wof:placetype":"venue"
},
  "geometry": {"coordinates":[-90.705221,36.007556],"type":"Point"}
}