{
  "type": "Feature",
  "properties": {
    "addr:full":"210 N 4th St Mc Gehee AR 71654",
    "addr:housenumber":"210",
    "addr:postcode":"71654",
    "addr:street":"N 4Th St;Gehee",
    "iso:country":"US",
    "sg:address":"210 N 4th St",
    "sg:city":"Mc Gehee",
    "sg:classifiers":[
        {
            "category":"Organizations",
            "subcategory":"Religious Organization",
            "type":"Services"
        }
    ],
    "sg:phone":"+1 870 222 4399",
    "sg:postcode":"71654",
    "sg:province":"AR",
    "wof:name":"Meir Chayim Temple",
    "wof:placetype":"venue"
},
  "geometry": {"coordinates":[-91.399725,33.628982],"type":"Point"}
}