{
  "type": "Feature",
  "properties": {
    "addr:full":"19 Baker Rd Glenwood AR 71943",
    "addr:housenumber":"19",
    "addr:postcode":"71943",
    "addr:street":"Baker Rd",
    "iso:country":"US",
    "sg:address":"19 Baker Rd",
    "sg:city":"Glenwood",
    "sg:classifiers":[
        {
            "category":"Professional",
            "subcategory":"Business Services",
            "type":"Services"
        }
    ],
    "sg:phone":"+1 870 356 4848",
    "sg:postcode":"71943",
    "sg:province":"AR",
    "sg:tags":[
        "auctioneer"
    ],
    "sg:website":"http://www.fowlerauctioneers.com",
    "wof:name":"Fowler Auctioneers, Inc.",
    "wof:placetype":"venue"
},
  "geometry": {"coordinates":[-93.535359,34.327252],"type":"Point"}
}