{
  "type": "Feature",
  "properties": {
    "iso:country":"US",
    "sg:address":"911 S 28th St",
    "sg:city":"Rogers",
    "sg:classifiers":[
        {
            "category":"Food & Beverages",
            "subcategory":"Specialty",
            "type":"Retail Goods"
        }
    ],
    "sg:phone":"+1 479 636 7622",
    "sg:postcode":"72758",
    "sg:province":"AR",
    "sg:tags":[
        "tea",
        "coffee"
    ],
    "wof:name":"Executive Coffee Svc",
    "wof:placetype":"venue"
},
  "geometry": {"coordinates":[-94.16175,36.327037],"type":"Point"}
}