{
  "type": "Feature",
  "properties": {
    "iso:country":"US",
    "sg:address":"158 E Sycamore St",
    "sg:city":"Fayetteville",
    "sg:classifiers":[
        {
            "category":"Professional",
            "subcategory":"Accounting & Tax Preparation",
            "type":"Services"
        }
    ],
    "sg:phone":"+1 479 582 1700",
    "sg:postcode":"72703",
    "sg:province":"AR",
    "sg:tags":[
        "accountant"
    ],
    "wof:name":"Terry L Drake CPA",
    "wof:placetype":"venue"
},
  "geometry": {"coordinates":[-94.157691,36.084535],"type":"Point"}
}