{
  "type": "Feature",
  "properties": {
    "addr:full":"181 E Oak St Conway AR 72032",
    "addr:housenumber":"181",
    "addr:postcode":"72032",
    "addr:street":"E Oak St",
    "iso:country":"US",
    "sg:address":"181 E Oak St",
    "sg:city":"Conway",
    "sg:classifiers":[
        {
            "category":"Wholesale",
            "subcategory":"Medical Equipment & Supplies",
            "type":"Manufacturing & Wholesale Goods"
        }
    ],
    "sg:phone":"+1 501 328 0202",
    "sg:postcode":"72032",
    "sg:province":"AR",
    "wof:name":"Bird Bear Medical Inc",
    "wof:placetype":"venue"
},
  "geometry": {"coordinates":[-92.427218,35.091554],"type":"Point"}
}