{
  "type": "Feature",
  "properties": {
    "iso:country":"US",
    "sg:address":"2602 E Central Ave",
    "sg:city":"Bentonville",
    "sg:classifiers":[
        {
            "category":"Building & Trades",
            "subcategory":"Plumbing",
            "type":"Services"
        },
        {
            "category":"Building & Trades",
            "subcategory":"Cleaning & Sanitation",
            "type":"Services"
        }
    ],
    "sg:phone":"+1 479 271 5377",
    "sg:postcode":"72712",
    "sg:province":"AR",
    "sg:tags":[
        "cleaner",
        "repairer",
        "sewer",
        "plumbing-drain"
    ],
    "wof:name":"Steves Plumbing Sewer Service",
    "wof:placetype":"venue"
},
  "geometry": {"coordinates":[-94.180722,36.370891],"type":"Point"}
}