{
  "type": "Feature",
  "properties": {
    "addr:full":"32770 State Hwy 23 Huntsville AR 72740",
    "addr:housenumber":"32770",
    "addr:postcode":"72740",
    "addr:street":"State Hwy 23",
    "iso:country":"US",
    "sg:address":"32770 State Hwy 23",
    "sg:city":"Huntsville",
    "sg:classifiers":[
        {
            "category":"Freight",
            "type":"Transportation"
        }
    ],
    "sg:phone":"+1 479 559 2817",
    "sg:postcode":"72740",
    "sg:province":"AR",
    "sg:tags":[
        "special"
    ],
    "wof:name":"Secure Storage",
    "wof:placetype":"venue"
},
  "geometry": {"coordinates":[-93.73751,36.146837],"type":"Point"}
}