{
  "type": "Feature",
  "properties": {
    "addr:full":"2910 Midland Blvd Fort Smith AR 72904",
    "addr:housenumber":"2910",
    "addr:postcode":"72904",
    "addr:street":"Midland Blvd",
    "iso:country":"US",
    "sg:address":"2910 Midland Blvd",
    "sg:city":"Fort Smith",
    "sg:classifiers":[
        {
            "category":"Shopping",
            "subcategory":"Tobacco",
            "type":"Retail Goods"
        }
    ],
    "sg:phone":"+1 479 783 2696",
    "sg:postcode":"72904",
    "sg:province":"AR",
    "sg:tags":[
        "cigarette",
        "product",
        "cigar",
        "dealer"
    ],
    "wof:name":"Discount Tobacco",
    "wof:placetype":"venue"
},
  "geometry": {"coordinates":[-94.39367300000001,35.409455],"type":"Point"}
}