{
  "type": "Feature",
  "properties": {
    "iso:country":"US",
    "sg:address":"346 Industrial Rd",
    "sg:city":"El Dorado",
    "sg:classifiers":[
        {
            "category":"Building & Trades",
            "subcategory":"Landscaping Services",
            "type":"Services"
        }
    ],
    "sg:phone":"+1 870 862 7662",
    "sg:postcode":"71730",
    "sg:province":"AR",
    "sg:tags":[
        "lawn",
        "maintenance",
        "grounds"
    ],
    "wof:name":"Parker Lawn Care Inc",
    "wof:placetype":"venue"
},
  "geometry": {"coordinates":[-92.616661,33.196385],"type":"Point"}
}