{
  "type": "Feature",
  "properties": {
    "addr:full":"4900 Central Ave Hot Springs AR 71913",
    "addr:housenumber":"4900",
    "addr:postcode":"71913",
    "addr:street":"Central Ave",
    "iso:country":"US",
    "sg:address":"4900 Central Ave",
    "sg:city":"Hot Springs",
    "sg:classifiers":[
        {
            "category":"Education",
            "subcategory":"Vocational School",
            "type":"Public Place"
        }
    ],
    "sg:phone":"+1 501 760 6889",
    "sg:postcode":"71913",
    "sg:province":"AR",
    "sg:tags":[
        "real estate"
    ],
    "wof:name":"National Real Est Invstmnt Inc",
    "wof:placetype":"venue"
},
  "geometry": {"coordinates":[-93.08842799999999,34.439423],"type":"Point"}
}