{
  "type": "Feature",
  "properties": {
    "iso:country":"US",
    "sg:address":"41 W Main St",
    "sg:city":"Farmington",
    "sg:classifiers":[
        {
            "category":"Organizations",
            "subcategory":"Religious Organization",
            "type":"Services"
        }
    ],
    "sg:phone":"+1 479 267 3182",
    "sg:postcode":"72730",
    "sg:province":"AR",
    "sg:tags":[
        "church"
    ],
    "wof:name":"Church Of Christ",
    "wof:placetype":"venue"
},
  "geometry": {"coordinates":[-94.242218,36.04179],"type":"Point"}
}