{
  "type": "Feature",
  "properties": {
    "addr:full":"6809 Hwy 89 S Cabot AR 72023",
    "addr:housenumber":"6809",
    "addr:postcode":"72023",
    "addr:street":"Hwy 89 S",
    "iso:country":"US",
    "sg:address":"6809 Hwy 89 S",
    "sg:city":"Cabot",
    "sg:classifiers":[
        {
            "category":"Manufacturing",
            "subcategory":"Building Materials",
            "type":"Manufacturing & Wholesale Goods"
        }
    ],
    "sg:phone":"+1 501 676 5444",
    "sg:postcode":"72023",
    "sg:province":"AR",
    "wof:name":"Fleming Millwork Inc",
    "wof:placetype":"venue"
},
  "geometry": {"coordinates":[-91.993776,34.882137],"type":"Point"}
}