{
  "type": "Feature",
  "properties": {
    "addr:full":"234 Provo Rd Lockesburg AR 71846",
    "addr:housenumber":"234",
    "addr:postcode":"71846",
    "addr:street":"Provo Rd",
    "iso:country":"US",
    "sg:address":"234 Provo Rd",
    "sg:city":"Lockesburg",
    "sg:classifiers":[
        {
            "category":"Professional",
            "type":"Services"
        }
    ],
    "sg:phone":"+1 870 289 6289",
    "sg:postcode":"71846",
    "sg:province":"AR",
    "wof:name":"Freddy Marshall",
    "wof:placetype":"venue"
},
  "geometry": {"coordinates":[-94.164902,33.975401],"type":"Point"}
}