{
  "type": "Feature",
  "properties": {
    "iso:country":"US",
    "sg:address":"503 Walnut St",
    "sg:city":"Texarkana",
    "sg:classifiers":[
        {
            "category":"Health Services",
            "subcategory":"Doctor",
            "type":"Services"
        }
    ],
    "sg:phone":"+1 870 774 1632",
    "sg:postcode":"71854",
    "sg:province":"AR",
    "sg:tags":[
        "clinic"
    ],
    "wof:name":"Miller County Health Clinic",
    "wof:placetype":"venue"
},
  "geometry": {"coordinates":[-94.042147,33.426456],"type":"Point"}
}