{
  "type": "Feature",
  "properties": {
    "iso:country":"US",
    "sg:address":"610 N College St",
    "sg:city":"Mountain Home",
    "sg:classifiers":[
        {
            "category":"Education",
            "subcategory":"School",
            "type":"Public Place"
        }
    ],
    "sg:phone":"+1 870 425 1251",
    "sg:postcode":"72653",
    "sg:province":"AR",
    "wof:name":"Nelson-Wilks-Herron Elementary",
    "wof:placetype":"venue"
},
  "geometry": {"coordinates":[-92.380967,36.347256],"type":"Point"}
}