{
  "type": "Feature",
  "properties": {
    "iso:country":"US",
    "sg:address":"326 Co Rd 361",
    "sg:city":"Bono",
    "sg:classifiers":[
        {
            "category":"Wholesale",
            "subcategory":"Sporting Goods",
            "type":"Manufacturing & Wholesale Goods"
        }
    ],
    "sg:phone":"+1 870 932 9394",
    "sg:postcode":"72416",
    "sg:province":"AR",
    "sg:tags":[
        "real estate"
    ],
    "wof:name":"Quackertime Outfitters Inc",
    "wof:placetype":"venue"
},
  "geometry": {"coordinates":[-90.767245,35.926231],"type":"Point"}
}