{
  "type": "Feature",
  "properties": {
    "addr:full":"4038 Remington Dr Fayetteville AR 72703",
    "addr:housenumber":"4038",
    "addr:postcode":"72703",
    "addr:street":"Remington Dr",
    "iso:country":"US",
    "sg:address":"4038 Remington Dr",
    "sg:city":"Fayetteville",
    "sg:classifiers":[
        {
            "category":"Health Services",
            "subcategory":"Doctor",
            "type":"Services"
        }
    ],
    "sg:phone":"+1 479 444 6691",
    "sg:postcode":"72703",
    "sg:province":"AR",
    "sg:tags":[
        "clinic"
    ],
    "wof:name":"Infectious Disease Specialists",
    "wof:placetype":"venue"
},
  "geometry": {"coordinates":[-94.141169,36.123822],"type":"Point"}
}