{
  "type": "Feature",
  "properties": {
    "iso:country":"US",
    "sg:address":"344 Acklin Gap Rd",
    "sg:city":"Conway",
    "sg:classifiers":[
        {
            "category":"Professional",
            "subcategory":"Management & Consulting",
            "type":"Services"
        }
    ],
    "sg:phone":"+1 501 329 9386",
    "sg:postcode":"72032",
    "sg:province":"AR",
    "sg:tags":[
        "business"
    ],
    "wof:name":"CFS Consulting & Financial",
    "wof:placetype":"venue"
},
  "geometry": {"coordinates":[-92.361489,35.133451],"type":"Point"}
}