{
  "type": "Feature",
  "properties": {
    "addr:full":"4042 Mount Tabor Rd Lonoke AR 72086",
    "addr:housenumber":"4042",
    "addr:postcode":"72086",
    "addr:street":"Mount Tabor Rd",
    "iso:country":"US",
    "sg:address":"4042 Mount Tabor Rd",
    "sg:city":"Lonoke",
    "sg:classifiers":[
        {
            "category":"Manufacturing",
            "subcategory":"Wood Products",
            "type":"Manufacturing & Wholesale Goods"
        }
    ],
    "sg:phone":"+1 501 843 1072",
    "sg:postcode":"72086",
    "sg:province":"AR",
    "sg:tags":[
        "mfg"
    ],
    "wof:name":"Country Wood-N Stuff",
    "wof:placetype":"venue"
},
  "geometry": {"coordinates":[-91.94898000000001,34.908683],"type":"Point"}
}