{
  "type": "Feature",
  "properties": {
    "iso:country":"US",
    "sg:address":"605 Old Post Rd",
    "sg:city":"Russellville",
    "sg:classifiers":[
        {
            "category":"Professional",
            "subcategory":"Advertising",
            "type":"Services"
        }
    ],
    "sg:phone":"+1 479 967 3595",
    "sg:postcode":"72802",
    "sg:province":"AR",
    "sg:tags":[
        "mail"
    ],
    "wof:name":"Tim Robertson & Assoc",
    "wof:placetype":"venue"
},
  "geometry": {"coordinates":[-93.16963,35.266779],"type":"Point"}
}