{
  "type": "Feature",
  "properties": {
    "iso:country":"US",
    "sg:address":"11 Briarwood Cir",
    "sg:city":"Dumas",
    "sg:classifiers":[
        {
            "category":"Retail",
            "subcategory":"Repair Shop",
            "type":"Services"
        }
    ],
    "sg:phone":"+1 870 382 4070",
    "sg:postcode":"71639",
    "sg:province":"AR",
    "wof:name":"Kens Locksmithing Service",
    "wof:placetype":"venue"
},
  "geometry": {"coordinates":[-91.47049,33.881696],"type":"Point"}
}