{
  "type": "Feature",
  "properties": {
    "addr:full":"3815 Macarthur Dr N Little Rock AR 72118",
    "addr:housenumber":"3815",
    "addr:postcode":"72118",
    "addr:street":"Macarthur Dr N",
    "iso:country":"US",
    "sg:address":"3815 Macarthur Dr",
    "sg:city":"N Little Rock",
    "sg:classifiers":[
        {
            "category":"Restaurant",
            "type":"Food & Drink"
        }
    ],
    "sg:phone":"+1 501 753 1012",
    "sg:postcode":"72118",
    "sg:province":"AR",
    "sg:tags":[
        "eating"
    ],
    "wof:name":"Bellwood Diner",
    "wof:placetype":"venue"
},
  "geometry": {"coordinates":[-92.284088,34.790188],"type":"Point"}
}