{
  "type": "Feature",
  "properties": {
    "addr:full":"651 Peyton St Ward AR 72176",
    "addr:housenumber":"651",
    "addr:postcode":"72176",
    "addr:street":"Peyton St",
    "iso:country":"US",
    "sg:address":"651 Peyton St",
    "sg:city":"Ward",
    "sg:classifiers":[
        {
            "category":"Government",
            "subcategory":"Office",
            "type":"Public Place"
        }
    ],
    "sg:phone":"+1 501 605 1921",
    "sg:postcode":"72176",
    "sg:province":"AR",
    "sg:tags":[
        "village"
    ],
    "wof:name":"Ward City Office",
    "wof:placetype":"venue"
},
  "geometry": {"coordinates":[-91.960922,35.01224],"type":"Point"}
}