{
  "type": "Feature",
  "properties": {
    "iso:country":"US",
    "sg:address":"2015 S Washington",
    "sg:city":"Magnolia",
    "sg:classifiers":[
        {
            "category":"Place Of Worship",
            "subcategory":"Church",
            "type":"Public Place"
        },
        {
            "category":"Place Of Worship",
            "type":"Public Place"
        }
    ],
    "sg:phone":"+1 870 234 1601",
    "sg:postcode":"71753",
    "sg:province":"AR",
    "sg:tags":[
        "churches-baptist-general",
        "churches-baptist"
    ],
    "wof:name":"Free Union Missionary Baptist Church",
    "wof:placetype":"venue"
},
  "geometry": {"coordinates":[-93.237538,33.288587],"type":"Point"}
}