{
  "type": "Feature",
  "properties": {
    "addr:full":"313 Hancock Rd Crossett AR 71635",
    "addr:housenumber":"313",
    "addr:postcode":"71635",
    "addr:street":"Hancock Rd",
    "iso:country":"US",
    "sg:address":"313 Hancock Rd",
    "sg:city":"Crossett",
    "sg:classifiers":[
        {
            "category":"Manufacturing",
            "subcategory":"Glass & Minerals",
            "type":"Manufacturing & Wholesale Goods"
        }
    ],
    "sg:phone":"+1 870 364 8280",
    "sg:postcode":"71635",
    "sg:province":"AR",
    "sg:tags":[
        "ready",
        "concrete",
        "mfg"
    ],
    "wof:name":"Texas Industries Inc",
    "wof:placetype":"venue"
},
  "geometry": {"coordinates":[-91.981528,33.137386],"type":"Point"}
}