{
  "type": "Feature",
  "properties": {
    "addr:full":"113 N Mount Olive St Siloam Springs OK 72761",
    "addr:housenumber":"113",
    "addr:postcode":"72761",
    "addr:street":"N Mount Olive St",
    "iso:country":"US",
    "sg:address":"113 N Mount Olive St",
    "sg:city":"Siloam Springs",
    "sg:classifiers":[
        {
            "category":"Home & Garden",
            "subcategory":"Furniture",
            "type":"Retail Goods"
        }
    ],
    "sg:phone":"+1 479 524 5689",
    "sg:postcode":"72761",
    "sg:province":"OK",
    "wof:name":"Hank's Fine Furniture",
    "wof:placetype":"venue"
},
  "geometry": {"coordinates":[-94.541426,36.185908],"type":"Point"}
}