{
  "type": "Feature",
  "properties": {
    "iso:country":"US",
    "sg:address":"3114 Hwy 31",
    "sg:city":"Beebe",
    "sg:classifiers":[
        {
            "category":"Real Estate",
            "subcategory":"Real Estate Agent",
            "type":"Services"
        }
    ],
    "sg:phone":"+1 501 882 0900",
    "sg:postcode":"72012",
    "sg:province":"AR",
    "sg:tags":[
        "agency",
        "rental"
    ],
    "wof:name":"P & R Rentals LLC",
    "wof:placetype":"venue"
},
  "geometry": {"coordinates":[-91.872939,35.061558],"type":"Point"}
}