{
  "type": "Feature",
  "properties": {
    "addr:full":"716 S 7th St Heber Springs AR 72543",
    "addr:housenumber":"716",
    "addr:postcode":"72543",
    "addr:street":"S 7Th St",
    "iso:country":"US",
    "sg:address":"716 S 7th St",
    "sg:city":"Heber Springs",
    "sg:classifiers":[
        {
            "category":"Food & Beverages",
            "subcategory":"Groceries & Convenience Stores",
            "type":"Retail Goods"
        }
    ],
    "sg:phone":"+1 501 362 2854",
    "sg:postcode":"72543",
    "sg:province":"AR",
    "wof:name":"E Z Mart Stores",
    "wof:placetype":"venue"
},
  "geometry": {"coordinates":[-92.036871,35.48573],"type":"Point"}
}