{
  "type": "Feature",
  "properties": {
    "iso:country":"US",
    "sg:address":"687 N Parrott Dr",
    "sg:city":"Huntsville",
    "sg:classifiers":[
        {
            "category":"Shopping",
            "subcategory":"Florist",
            "type":"Retail Goods"
        }
    ],
    "sg:phone":"+1 479 738 1717",
    "sg:postcode":"72740",
    "sg:province":"AR",
    "wof:name":"Huntsville Floral & Gifts",
    "wof:placetype":"venue"
},
  "geometry": {"coordinates":[-93.729884,36.09294],"type":"Point"}
}