{
  "type": "Feature",
  "properties": {
    "addr:full":"900 E Collin Raye Dr De Queen AR 71832",
    "addr:housenumber":"900",
    "addr:postcode":"71832",
    "addr:street":"E Collin Raye Dr De Queen",
    "iso:country":"US",
    "sg:address":"900 E Collin Raye Dr",
    "sg:city":"De Queen",
    "sg:classifiers":[
        {
            "category":"Food & Beverages",
            "subcategory":"Groceries & Convenience Stores",
            "type":"Retail Goods"
        }
    ],
    "sg:phone":"+1 870 642 3224",
    "sg:postcode":"71832",
    "sg:province":"AR",
    "wof:name":"E Z Mart Stores",
    "wof:placetype":"venue"
},
  "geometry": {"coordinates":[-94.325738,34.045539],"type":"Point"}
}