{
  "type": "Feature",
  "properties": {
    "iso:country":"US",
    "sg:address":"806 E Booth Rd",
    "sg:city":"Searcy",
    "sg:classifiers":[
        {
            "category":"Recreation",
            "type":"Entertainment"
        }
    ],
    "sg:phone":"+1 501 268 9226",
    "sg:postcode":"72143",
    "sg:province":"AR",
    "wof:name":"Batter Up Batting Cages",
    "wof:placetype":"venue"
},
  "geometry": {"coordinates":[-91.72869799999999,35.224153],"type":"Point"}
}