{
  "type": "Feature",
  "properties": {
    "iso:country":"US",
    "sg:address":"1224 N Main St",
    "sg:city":"Harrison",
    "sg:classifiers":[
        {
            "category":"Real Estate",
            "subcategory":"Real Estate Services",
            "type":"Services"
        },
        {
            "category":"Real Estate",
            "subcategory":"Real Estate Agent",
            "type":"Services"
        }
    ],
    "sg:phone":"+1 870 741 6188",
    "sg:postcode":"72601",
    "sg:province":"AR",
    "sg:tags":[
        "buyer",
        "broker"
    ],
    "wof:name":"Freida Mae Hudson Revocable Trust",
    "wof:placetype":"venue"
},
  "geometry": {"coordinates":[-93.115143,36.24445],"type":"Point"}
}