{
  "type": "Feature",
  "properties": {
    "addr:full":"6416 Asher Ave Little Rock AR 72204",
    "addr:housenumber":"6416",
    "addr:postcode":"72204",
    "addr:street":"Asher Ave",
    "iso:country":"US",
    "sg:address":"6416 Asher Ave",
    "sg:city":"Little Rock",
    "sg:classifiers":[
        {
            "category":"Retail",
            "subcategory":"Laundry & Dry Cleaning",
            "type":"Services"
        }
    ],
    "sg:phone":"+1 501 568 7777",
    "sg:postcode":"72204",
    "sg:province":"AR",
    "sg:tags":[
        "shoe",
        "power"
    ],
    "wof:name":"Elite Laundry and Cleaners",
    "wof:placetype":"venue"
},
  "geometry": {"coordinates":[-92.34891,34.718025],"type":"Point"}
}