{
  "type": "Feature",
  "properties": {
    "iso:country":"US",
    "sg:address":"1323 N Main St",
    "sg:city":"Harrison",
    "sg:classifiers":[
        {
            "category":"Shopping",
            "subcategory":"Clothing, Apparel, & Fashions",
            "type":"Retail Goods"
        }
    ],
    "sg:phone":"+1 870 741 0024",
    "sg:postcode":"72601",
    "sg:province":"AR",
    "wof:name":"Tiny Tots Shoppe",
    "wof:placetype":"venue"
},
  "geometry": {"coordinates":[-93.113868,36.243339],"type":"Point"}
}