{
  "type": "Feature",
  "properties": {
    "iso:country":"US",
    "sg:address":"209 N Main St",
    "sg:city":"Benton",
    "sg:classifiers":[
        {
            "category":"Real Estate",
            "subcategory":"Real Estate Agent",
            "type":"Services"
        }
    ],
    "sg:phone":"+1 501 315 7228",
    "sg:postcode":"72015",
    "sg:province":"AR",
    "wof:name":"Centrion LLC",
    "wof:placetype":"venue"
},
  "geometry": {"coordinates":[-92.586863,34.565461],"type":"Point"}
}