{
  "type": "Feature",
  "properties": {
    "iso:country":"US",
    "sg:address":"1900 W Main St",
    "sg:city":"Russellville",
    "sg:classifiers":[
        {
            "category":"Organizations",
            "subcategory":"Religious Organization",
            "type":"Services"
        }
    ],
    "sg:phone":"+1 479 967 3699",
    "sg:postcode":"72801",
    "sg:province":"AR",
    "sg:tags":[
        "church"
    ],
    "wof:name":"St John's Catholic Church",
    "wof:placetype":"venue"
},
  "geometry": {"coordinates":[-93.151898,35.283463],"type":"Point"}
}