{
  "type": "Feature",
  "properties": {
    "iso:country":"US",
    "sg:address":"2110 O St S",
    "sg:city":"Fort Smith",
    "sg:classifiers":[
        {
            "category":"Retail",
            "subcategory":"Auto Repair",
            "type":"Services"
        }
    ],
    "sg:phone":"+1 479 782 9195",
    "sg:postcode":"72901",
    "sg:province":"AR",
    "sg:tags":[
        "automobile",
        "customizing"
    ],
    "wof:name":"Inline Motor Sports",
    "wof:placetype":"venue"
},
  "geometry": {"coordinates":[-94.40951,35.368349],"type":"Point"}
}