{
  "type": "Feature",
  "properties": {
    "iso:country":"US",
    "sg:address":"2100 Main St",
    "sg:city":"Mammoth Spring",
    "sg:classifiers":[
        {
            "category":"Professional",
            "type":"Services"
        }
    ],
    "sg:phone":"+1 870 856 2450",
    "sg:postcode":"72554",
    "sg:province":"AR",
    "sg:tags":[
        "establishment"
    ],
    "wof:name":"Jessie James Studio",
    "wof:placetype":"venue"
},
  "geometry": {"coordinates":[-91.561015,36.493563],"type":"Point"}
}