{
  "type": "Feature",
  "properties": {
    "iso:country":"US",
    "sg:address":"119 Gene Bell Cove",
    "sg:city":"Hot Springs",
    "sg:classifiers":[
        {
            "category":"Professional",
            "subcategory":"Advertising",
            "type":"Services"
        }
    ],
    "sg:phone":"+1 501 622 7315",
    "sg:postcode":"71913",
    "sg:province":"AR",
    "sg:tags":[
        "counselor"
    ],
    "wof:name":"Don Cassil Advertising",
    "wof:placetype":"venue"
},
  "geometry": {"coordinates":[-93.125756,34.438786],"type":"Point"}
}