{
  "type": "Feature",
  "properties": {
    "iso:country":"US",
    "sg:address":"915 W Main St",
    "sg:city":"Russellville",
    "sg:classifiers":[
        {
            "category":"Professional",
            "subcategory":"Accounting & Tax Preparation",
            "type":"Services"
        }
    ],
    "sg:phone":"+1 479 967 3600",
    "sg:postcode":"72801",
    "sg:province":"AR",
    "sg:tags":[
        "accountant"
    ],
    "sg:website":"www.shoptaw-labahn.com",
    "wof:name":"Shoptaw Labahn & Co",
    "wof:placetype":"venue"
},
  "geometry": {"coordinates":[-93.14197299999999,35.280386],"type":"Point"}
}