{
  "type": "Feature",
  "properties": {
    "iso:country":"US",
    "sg:address":"900 Albert Pike Rd",
    "sg:city":"Hot Springs",
    "sg:classifiers":[
        {
            "category":"Banks & Credit Unions",
            "subcategory":"Bank",
            "type":"Services"
        }
    ],
    "sg:phone":"+1 501 624 8807",
    "sg:postcode":"71913",
    "sg:province":"AR",
    "wof:name":"Regions",
    "wof:placetype":"venue"
},
  "geometry": {"coordinates":[-93.07962000000001,34.493926],"type":"Point"}
}