{
  "type": "Feature",
  "properties": {
    "iso:country":"US",
    "sg:address":"111 N Main St",
    "sg:city":"Cave City",
    "sg:classifiers":[
        {
            "category":"Food & Beverages",
            "subcategory":"Groceries & Convenience Stores",
            "type":"Retail Goods"
        }
    ],
    "sg:phone":"+1 870 283 5187",
    "sg:postcode":"72521",
    "sg:province":"AR",
    "sg:tags":[
        "grocer"
    ],
    "wof:name":"Hometown Market",
    "wof:placetype":"venue"
},
  "geometry": {"coordinates":[-91.548444,35.941602],"type":"Point"}
}