{
  "type": "Feature",
  "properties": {
    "iso:country":"US",
    "sg:address":"301 E Main St",
    "sg:city":"Batesville",
    "sg:classifiers":[
        {
            "category":"Shopping",
            "subcategory":"Computers & Home Electronics",
            "type":"Retail Goods"
        }
    ],
    "sg:phone":"+1 870 793 2555",
    "sg:postcode":"72501",
    "sg:province":"AR",
    "sg:tags":[
        "instrument",
        "musical"
    ],
    "wof:name":"Platter Inn Music Store",
    "wof:placetype":"venue"
},
  "geometry": {"coordinates":[-91.651219,35.771741],"type":"Point"}
}