{
  "type": "Feature",
  "properties": {
    "iso:country":"US",
    "sg:address":"1014 S 6th St",
    "sg:city":"Augusta",
    "sg:classifiers":[
        {
            "category":"Retail",
            "subcategory":"Auto Repair",
            "type":"Services"
        }
    ],
    "sg:phone":"+1 870 347 5561",
    "sg:postcode":"72006",
    "sg:province":"AR",
    "sg:tags":[
        "body"
    ],
    "wof:name":"Augusta Jims Body Shop",
    "wof:placetype":"venue"
},
  "geometry": {"coordinates":[-91.362512,35.272952],"type":"Point"}
}