{
  "type": "Feature",
  "properties": {
    "iso:country":"US",
    "sg:address":"3031 Short Mountain Rd",
    "sg:city":"Paris",
    "sg:classifiers":[
        {
            "category":"Farming",
            "subcategory":"Livestock Farm",
            "type":"Manufacturing & Wholesale Goods"
        }
    ],
    "sg:phone":"+1 479 963 6441",
    "sg:postcode":"72855",
    "sg:province":"AR",
    "sg:tags":[
        "animal",
        "general"
    ],
    "wof:name":"Steven W Titsworth",
    "wof:placetype":"venue"
},
  "geometry": {"coordinates":[-93.790802,35.31232],"type":"Point"}
}