{
  "type": "Feature",
  "properties": {
    "iso:country":"US",
    "sg:address":"2511 Margaret Cir",
    "sg:city":"Conway",
    "sg:classifiers":[
        {
            "category":"Cinema",
            "subcategory":"Movie Rental",
            "type":"Entertainment"
        }
    ],
    "sg:phone":"+1 501 450 7714",
    "sg:postcode":"72034",
    "sg:province":"AR",
    "sg:tags":[
        "video",
        "tape"
    ],
    "wof:name":"Home Video",
    "wof:placetype":"venue"
},
  "geometry": {"coordinates":[-92.465774,35.06669],"type":"Point"}
}