{
  "type": "Feature",
  "properties": {
    "iso:country":"US",
    "sg:address":"5121 Warden Rd",
    "sg:city":"North Little Rock",
    "sg:classifiers":[
        {
            "category":"Shopping",
            "subcategory":"Gifts & Souvenirs",
            "type":"Retail Goods"
        }
    ],
    "sg:phone":"+1 501 961 1218",
    "sg:postcode":"72116",
    "sg:province":"AR",
    "wof:name":"Tussie Mussie",
    "wof:placetype":"venue"
},
  "geometry": {"coordinates":[-92.215816,34.800402],"type":"Point"}
}