{
  "type": "Feature",
  "properties": {
    "addr:full":"1410 E Center St Beebe AR 72012",
    "addr:housenumber":"1410",
    "addr:postcode":"72012",
    "addr:street":"E Center St",
    "iso:country":"US",
    "sg:address":"1410 E Center St",
    "sg:city":"Beebe",
    "sg:classifiers":[
        {
            "category":"Retail",
            "subcategory":"Auto Repair",
            "type":"Services"
        }
    ],
    "sg:phone":"+1 501 882 6262",
    "sg:postcode":"72012",
    "sg:province":"AR",
    "sg:tags":[
        "repairing",
        "automobile"
    ],
    "wof:name":"American Auto & Tire Repair",
    "wof:placetype":"venue"
},
  "geometry": {"coordinates":[-91.86530999999999,35.084061],"type":"Point"}
}