{
  "type": "Feature",
  "properties": {
    "addr:full":"210 Locust St Malvern AR 72104",
    "addr:housenumber":"210",
    "addr:postcode":"72104",
    "addr:street":"Locust St",
    "iso:country":"US",
    "sg:address":"210 Locust St",
    "sg:city":"Malvern",
    "sg:classifiers":[
        {
            "category":"Government",
            "subcategory":"Court House",
            "type":"Public Place"
        }
    ],
    "sg:phone":"+1 501 337 4328",
    "sg:postcode":"72104",
    "sg:province":"AR",
    "sg:tags":[
        "county"
    ],
    "wof:name":"Hot Spring Juvenile Court",
    "wof:placetype":"venue"
},
  "geometry": {"coordinates":[-92.81478,34.363282],"type":"Point"}
}