{
  "type": "Feature",
  "properties": {
    "iso:country":"US",
    "sg:address":"2238 Tall Timber Rd",
    "sg:city":"Hardy",
    "sg:classifiers":[
        {
            "category":"Farming",
            "subcategory":"Farm",
            "type":"Manufacturing & Wholesale Goods"
        }
    ],
    "sg:phone":"+1 870 856 3674",
    "sg:postcode":"72542",
    "sg:province":"AR",
    "wof:name":"Davis Farm",
    "wof:placetype":"venue"
},
  "geometry": {"coordinates":[-91.495358,36.345694],"type":"Point"}
}