{
  "type": "Feature",
  "properties": {
    "addr:full":"306 Mountain Home Rd Paragould AR 72450",
    "addr:housenumber":"306",
    "addr:postcode":"72450",
    "addr:street":"Mountain Home Rd",
    "iso:country":"US",
    "sg:address":"306 Mountain Home Rd",
    "sg:city":"Paragould",
    "sg:classifiers":[
        {
            "category":"Autos & Motor Vehicles",
            "subcategory":"Auto Supplies",
            "type":"Retail Goods"
        },
        {
            "category":"Manufacturing",
            "subcategory":"Glass & Minerals",
            "type":"Manufacturing & Wholesale Goods"
        },
        {
            "category":"Retail",
            "subcategory":"Auto Repair",
            "type":"Services"
        }
    ],
    "sg:phone":"+1 870 240 3158",
    "sg:postcode":"72450",
    "sg:province":"AR",
    "sg:tags":[
        "plate",
        "automobile",
        "glass-auto",
        "accessory",
        "window",
        "part",
        "windshield"
    ],
    "wof:name":"Bishop's Mobile Glass",
    "wof:placetype":"venue"
},
  "geometry": {"coordinates":[-90.573133,36.069757],"type":"Point"}
}