{
  "type": "Feature",
  "properties": {
    "addr:full":"703 Lewis Lee Rd Delight AR 71940",
    "addr:housenumber":"703",
    "addr:postcode":"71940",
    "addr:street":"Lewis Lee Rd",
    "iso:country":"US",
    "sg:address":"703 Lewis Lee Rd",
    "sg:city":"Delight",
    "sg:classifiers":[
        {
            "category":"Professional",
            "subcategory":"Credit Reporting & Collection",
            "type":"Services"
        }
    ],
    "sg:phone":"+1 870 379 2008",
    "sg:postcode":"71940",
    "sg:province":"AR",
    "sg:tags":[
        "fee"
    ],
    "wof:name":"Elizabeth ONeal",
    "wof:placetype":"venue"
},
  "geometry": {"coordinates":[-93.499886,33.983191],"type":"Point"}
}