{
  "type": "Feature",
  "properties": {
    "iso:country":"US",
    "sg:address":"1500 S Ansley St",
    "sg:city":"Nashville",
    "sg:classifiers":[
        {
            "category":"Organizations",
            "subcategory":"Religious Organization",
            "type":"Services"
        }
    ],
    "sg:phone":"+1 870 845 0151",
    "sg:postcode":"71852",
    "sg:province":"AR",
    "sg:tags":[
        "church"
    ],
    "wof:name":"Mt Zion Baptist Church",
    "wof:placetype":"venue"
},
  "geometry": {"coordinates":[-93.84505,33.929863],"type":"Point"}
}