{
  "type": "Feature",
  "properties": {
    "iso:country":"US",
    "sg:address":"4360 State Hwy 77",
    "sg:city":"Marion",
    "sg:classifiers":[
        {
            "category":"Autos & Motor Vehicles",
            "subcategory":"Automobile Sales",
            "type":"Retail Goods"
        },
        {
            "category":"Wholesale",
            "subcategory":"Motor Vehicles",
            "type":"Manufacturing & Wholesale Goods"
        }
    ],
    "sg:phone":"+1 870 739 8600",
    "sg:postcode":"72364",
    "sg:province":"AR",
    "sg:tags":[
        "new",
        "used",
        "trailer",
        "semi"
    ],
    "wof:name":"Truck Trailers & Equipment Inc",
    "wof:placetype":"venue"
},
  "geometry": {"coordinates":[-90.2086,35.237398],"type":"Point"}
}