{
  "type": "Feature",
  "properties": {
    "addr:full":"225 S Church St Jonesboro AR 72401",
    "addr:housenumber":"225",
    "addr:postcode":"72401",
    "addr:street":"S Church St",
    "iso:country":"US",
    "sg:address":"225 S Church St",
    "sg:city":"Jonesboro",
    "sg:classifiers":[
        {
            "category":"Real Estate",
            "subcategory":"Real Estate Operator",
            "type":"Services"
        }
    ],
    "sg:phone":"+1 870 530 2020",
    "sg:postcode":"72401",
    "sg:province":"AR",
    "sg:tags":[
        "building",
        "nonresidential"
    ],
    "wof:name":"Jet Properties LLC",
    "wof:placetype":"venue"
},
  "geometry": {"coordinates":[-90.70405599999999,35.841712],"type":"Point"}
}