{
  "type": "Feature",
  "properties": {
    "iso:country":"US",
    "sg:address":"46 Beloit Dr",
    "sg:city":"Heber Springs",
    "sg:classifiers":[
        {
            "category":"Real Estate",
            "subcategory":"Real Estate Operator",
            "type":"Services"
        }
    ],
    "sg:phone":"+1 501 362 7568",
    "sg:postcode":"72543",
    "sg:province":"AR",
    "sg:tags":[
        "building",
        "nonresidential"
    ],
    "wof:name":"Ragsdell Properties LLC",
    "wof:placetype":"venue"
},
  "geometry": {"coordinates":[-92.084855,35.497764],"type":"Point"}
}