{
  "type": "Feature",
  "properties": {
    "iso:country":"US",
    "sg:address":"224 S 8th St",
    "sg:city":"Rogers",
    "sg:classifiers":[
        {
            "category":"Shopping",
            "type":"Retail Goods"
        }
    ],
    "sg:phone":"+1 479 631 0000",
    "sg:postcode":"72756",
    "sg:province":"AR",
    "sg:tags":[
        "telephone",
        "cellular"
    ],
    "wof:name":"Wireless One-Stop",
    "wof:placetype":"venue"
},
  "geometry": {"coordinates":[-94.125739,36.332732],"type":"Point"}
}