{
  "type": "Feature",
  "properties": {
    "iso:country":"US",
    "sg:address":"2011 Weidner St",
    "sg:city":"Stuttgart",
    "sg:classifiers":[
        {
            "category":"Farming",
            "subcategory":"Farm",
            "type":"Manufacturing & Wholesale Goods"
        }
    ],
    "sg:phone":"+1 870 673 4228",
    "sg:postcode":"72160",
    "sg:province":"AR",
    "sg:tags":[
        "crop",
        "general"
    ],
    "wof:name":"Dwight Carter Farms",
    "wof:placetype":"venue"
},
  "geometry": {"coordinates":[-91.566035,34.483745],"type":"Point"}
}