{
  "type": "Feature",
  "properties": {
    "iso:country":"US",
    "sg:address":"51 Meadowbrook Dr",
    "sg:city":"Little Rock",
    "sg:classifiers":[
        {
            "category":"Shopping",
            "subcategory":"Computers & Home Electronics",
            "type":"Retail Goods"
        }
    ],
    "sg:phone":"+1 501 224 9377",
    "sg:postcode":"72205",
    "sg:province":"AR",
    "sg:tags":[
        "parts",
        "supply"
    ],
    "wof:name":"State Business Supply",
    "wof:placetype":"venue"
},
  "geometry": {"coordinates":[-92.383663,34.752069],"type":"Point"}
}