{
  "type": "Feature",
  "properties": {
    "addr:full":"1520 E Main St Russellville AR 72801",
    "addr:housenumber":"1520",
    "addr:postcode":"72801",
    "addr:street":"E Main St",
    "iso:country":"US",
    "sg:address":"1520 E Main St",
    "sg:city":"Russellville",
    "sg:classifiers":[
        {
            "category":"Personal",
            "subcategory":"Beauty Salon",
            "type":"Services"
        }
    ],
    "sg:phone":"+1 479 880 1221",
    "sg:postcode":"72801",
    "sg:province":"AR",
    "wof:name":"Got Hair Got Nails Got Style",
    "wof:placetype":"venue"
},
  "geometry": {"coordinates":[-93.115093,35.278285],"type":"Point"}
}