{
  "type": "Feature",
  "properties": {
    "iso:country":"US",
    "sg:address":"240 Morrow Church Rd",
    "sg:city":"Searcy",
    "sg:classifiers":[
        {
            "category":"Professional",
            "subcategory":"Engineering",
            "type":"Services"
        }
    ],
    "sg:phone":"+1 501 742 1427",
    "sg:postcode":"72143",
    "sg:province":"AR",
    "wof:name":"Flood Plain Services",
    "wof:placetype":"venue"
},
  "geometry": {"coordinates":[-91.68952,35.194578],"type":"Point"}
}