{
  "type": "Feature",
  "properties": {
    "iso:country":"US",
    "sg:address":"9034 Hwy 141 N",
    "sg:city":"Beech Grove",
    "sg:classifiers":[
        {
            "category":"Government",
            "subcategory":"Post Office",
            "type":"Public Place"
        }
    ],
    "sg:phone":"+1 870 586 0653",
    "sg:postcode":"72412",
    "sg:province":"AR",
    "wof:name":"US Post Office",
    "wof:placetype":"venue"
},
  "geometry": {"coordinates":[-90.618337,36.183946],"type":"Point"}
}