{
  "type": "Feature",
  "properties": {
    "iso:country":"US",
    "sg:address":"1305 W 43rd Ave",
    "sg:city":"Pine Bluff",
    "sg:classifiers":[
        {
            "category":"Health Services",
            "subcategory":"Doctor",
            "type":"Services"
        }
    ],
    "sg:phone":"+1 870 534 8515",
    "sg:postcode":"71603",
    "sg:province":"AR",
    "sg:tags":[
        "physician",
        "surgeon"
    ],
    "wof:name":"Walker Health Care For Women",
    "wof:placetype":"venue"
},
  "geometry": {"coordinates":[-92.017409,34.186059],"type":"Point"}
}