{
  "type": "Feature",
  "properties": {
    "iso:country":"US",
    "sg:address":"705 E 16th St",
    "sg:city":"N Little Rock",
    "sg:classifiers":[
        {
            "category":"Social Services",
            "subcategory":"Child Care",
            "type":"Services"
        }
    ],
    "sg:phone":"+1 501 376 0077",
    "sg:postcode":"72114",
    "sg:province":"AR",
    "wof:name":"Bright Beginnings Christian",
    "wof:placetype":"venue"
},
  "geometry": {"coordinates":[-92.25891900000001,34.769233],"type":"Point"}
}