{
  "type": "Feature",
  "properties": {
    "iso:country":"US",
    "sg:address":"720 S 3rd St",
    "sg:city":"Rogers",
    "sg:classifiers":[
        {
            "category":"Organizations",
            "subcategory":"Religious Organization",
            "type":"Services"
        }
    ],
    "sg:phone":"+1 479 631 9966",
    "sg:postcode":"72756",
    "sg:province":"AR",
    "wof:name":"Vineyard Chrstn Flwshp N W Ark",
    "wof:placetype":"venue"
},
  "geometry": {"coordinates":[-94.119406,36.327008],"type":"Point"}
}