{
  "type": "Feature",
  "properties": {
    "iso:country":"US",
    "sg:address":"2320 Remington Rd",
    "sg:city":"Conway",
    "sg:classifiers":[
        {
            "category":"Building & Trades",
            "subcategory":"Equipment Rental",
            "type":"Services"
        }
    ],
    "sg:phone":"+1 501 329 8574",
    "sg:postcode":"72032",
    "sg:province":"AR",
    "sg:tags":[
        "camping"
    ],
    "wof:name":"Phil's Tent Rental & Setup",
    "wof:placetype":"venue"
},
  "geometry": {"coordinates":[-92.46301699999999,35.109575],"type":"Point"}
}