{
  "type": "Feature",
  "properties": {
    "iso:country":"US",
    "sg:address":"2511 Hwy 63",
    "sg:city":"Hardy",
    "sg:classifiers":[
        {
            "category":"Local Transit",
            "type":"Transportation"
        }
    ],
    "sg:phone":"+1 870 856 2253",
    "sg:postcode":"72542",
    "sg:province":"AR",
    "sg:tags":[
        "bus",
        "line"
    ],
    "wof:name":"Greyhound Bus Lines",
    "wof:placetype":"venue"
},
  "geometry": {"coordinates":[-91.44118400000001,36.300148],"type":"Point"}
}