{
  "type": "Feature",
  "properties": {
    "iso:country":"US",
    "sg:address":"130 W Center St",
    "sg:city":"Beebe",
    "sg:classifiers":[
        {
            "category":"Manufacturing",
            "subcategory":"Retail Goods",
            "type":"Manufacturing & Wholesale Goods"
        }
    ],
    "sg:phone":"+1 501 882 1048",
    "sg:postcode":"72012",
    "sg:province":"AR",
    "sg:tags":[
        "manufacturer"
    ],
    "wof:name":"Legacy Collection",
    "wof:placetype":"venue"
},
  "geometry": {"coordinates":[-91.880437,35.069995],"type":"Point"}
}