{
  "type": "Feature",
  "properties": {
    "addr:full":"1674 Maul Rd Camden AR 71701",
    "addr:housenumber":"1674",
    "addr:postcode":"71701",
    "addr:street":"Maul Rd",
    "iso:country":"US",
    "sg:address":"1674 Maul Rd",
    "sg:city":"Camden",
    "sg:classifiers":[
        {
            "category":"Organizations",
            "subcategory":"Religious Organization",
            "type":"Services"
        }
    ],
    "sg:phone":"+1 870 836 6954",
    "sg:postcode":"71701",
    "sg:province":"AR",
    "sg:tags":[
        "church"
    ],
    "wof:name":"First Landmark Baptist Church",
    "wof:placetype":"venue"
},
  "geometry": {"coordinates":[-92.862481,33.598354],"type":"Point"}
}