{
  "type": "Feature",
  "properties": {
    "addr:full":"21 W Martin Ln Greenbrier AR 72058",
    "addr:housenumber":"21",
    "addr:postcode":"72058",
    "addr:street":"W Martin Ln",
    "iso:country":"US",
    "sg:address":"21 W Martin Ln",
    "sg:city":"Greenbrier",
    "sg:classifiers":[
        {
            "category":"Professional",
            "type":"Services"
        }
    ],
    "sg:phone":"+1 501 679 5265",
    "sg:postcode":"72058",
    "sg:province":"AR",
    "wof:name":"Donald Burnside",
    "wof:placetype":"venue"
},
  "geometry": {"coordinates":[-92.428996,35.198703],"type":"Point"}
}