{
  "type": "Feature",
  "properties": {
    "iso:country":"US",
    "sg:address":"909 Ouachita Road 17",
    "sg:city":"Chidester",
    "sg:classifiers":[
        {
            "category":"Organizations",
            "subcategory":"Religious Organization",
            "type":"Services"
        }
    ],
    "sg:phone":"+1 870 685 2035",
    "sg:postcode":"71726",
    "sg:province":"AR",
    "sg:tags":[
        "church"
    ],
    "wof:name":"Adams Chapel Missionary Baptst",
    "wof:placetype":"venue"
},
  "geometry": {"coordinates":[-93.0368,33.606639],"type":"Point"}
}