{
  "type": "Feature",
  "properties": {
    "iso:country":"US",
    "sg:address":"1340 Hogan Roberts Loop",
    "sg:city":"Atkins",
    "sg:classifiers":[
        {
            "category":"Freight",
            "type":"Transportation"
        }
    ],
    "sg:phone":"+1 479 641 1357",
    "sg:postcode":"72823",
    "sg:province":"AR",
    "sg:tags":[
        "operator",
        "local",
        "trucking"
    ],
    "wof:name":"Jl Trucking",
    "wof:placetype":"venue"
},
  "geometry": {"coordinates":[-92.956402,35.313569],"type":"Point"}
}