{
  "type": "Feature",
  "properties": {
    "addr:full":"4522 S 16th St Fort Smith AR 72901",
    "addr:housenumber":"4522",
    "addr:postcode":"72901",
    "addr:street":"S 16Th St",
    "iso:country":"US",
    "sg:address":"4522 S 16th St",
    "sg:city":"Fort Smith",
    "sg:classifiers":[
        {
            "category":"Manufacturing",
            "subcategory":"Tools & Machinery",
            "type":"Manufacturing & Wholesale Goods"
        }
    ],
    "sg:phone":"+1 479 646 3091",
    "sg:postcode":"72901",
    "sg:province":"AR",
    "sg:tags":[
        "die"
    ],
    "wof:name":"Anco Tool & Die Inc",
    "wof:placetype":"venue"
},
  "geometry": {"coordinates":[-94.41777399999999,35.344125],"type":"Point"}
}