{
  "type": "Feature",
  "properties": {
    "addr:full":"111 S 2nd St Rogers AR 72756",
    "addr:housenumber":"111",
    "addr:postcode":"72756",
    "addr:street":"S 2Nd St",
    "iso:country":"US",
    "sg:address":"111 S 2nd St",
    "sg:city":"Rogers",
    "sg:classifiers":[
        {
            "category":"Wholesale",
            "subcategory":"Construction Materials",
            "type":"Manufacturing & Wholesale Goods"
        }
    ],
    "sg:phone":"+1 479 636 7473",
    "sg:postcode":"72756",
    "sg:province":"AR",
    "sg:tags":[
        "pipe",
        "article",
        "smoker"
    ],
    "wof:name":"Romeo's Downtown Pipe & Tobacco Co",
    "wof:placetype":"venue"
},
  "geometry": {"coordinates":[-94.117408,36.333024],"type":"Point"}
}