{
  "type": "Feature",
  "properties": {
    "iso:country":"US",
    "sg:address":"5512 Oakridge Dr",
    "sg:city":"Pine Bluff",
    "sg:classifiers":[
        {
            "category":"Building & Trades",
            "subcategory":"Construction",
            "type":"Services"
        }
    ],
    "sg:phone":"+1 870 879 3116",
    "sg:postcode":"71603",
    "sg:province":"AR",
    "sg:tags":[
        "house",
        "insurance"
    ],
    "wof:name":"Mitchell & Associates Inc",
    "wof:placetype":"venue"
},
  "geometry": {"coordinates":[-92.064962,34.186463],"type":"Point"}
}