{
  "type": "Feature",
  "properties": {
    "iso:country":"US",
    "sg:address":"124 N Jackson St",
    "sg:city":"Magnolia",
    "sg:classifiers":[
        {
            "category":"Professional",
            "subcategory":"Lawyer & Legal Services",
            "type":"Services"
        }
    ],
    "sg:phone":"+1 870 234 9200",
    "sg:postcode":"71753",
    "sg:province":"AR",
    "wof:name":"Rebecca A Jones",
    "wof:placetype":"venue"
},
  "geometry": {"coordinates":[-93.23919,33.267996],"type":"Point"}
}