{
  "type": "Feature",
  "properties": {
    "iso:country":"US",
    "sg:address":"25 Watson Fisher Rd",
    "sg:city":"De Witt",
    "sg:classifiers":[
        {
            "category":"Professional",
            "type":"Services"
        }
    ],
    "sg:phone":"+1 870 946 0393",
    "sg:postcode":"72042",
    "sg:province":"AR",
    "wof:name":"Stanley D Fox",
    "wof:placetype":"venue"
},
  "geometry": {"coordinates":[-91.297358,34.327254],"type":"Point"}
}