{
  "type": "Feature",
  "properties": {
    "addr:full":"912 W 4TH ST FORDYCE AR 71742",
    "addr:housenumber":"912",
    "addr:postcode":"71742",
    "addr:street":"W 4Th St",
    "iso:country":"US",
    "sg:address":"912 W 4TH ST",
    "sg:city":"FORDYCE",
    "sg:classifiers":[
        {
            "category":"Home & Garden",
            "subcategory":"Household Appliances",
            "type":"Retail Goods"
        },
        {
            "category":"Communications",
            "subcategory":"Radio Station",
            "type":"Services"
        },
        {
            "category":"Shopping",
            "subcategory":"Computers & Home Electronics",
            "type":"Retail Goods"
        },
        {
            "category":"Home & Garden",
            "subcategory":"Furniture",
            "type":"Retail Goods"
        }
    ],
    "sg:phone":"+1 870 352 2665",
    "sg:postcode":"71742",
    "sg:province":"AR",
    "sg:tags":[
        "renting",
        "television",
        "leasing",
        "radio-renting",
        "equipment",
        "rental"
    ],
    "sg:website":"http://www.rentacenter.com/",
    "wof:name":"Rent-A-Center",
    "wof:placetype":"venue"
},
  "geometry": {"coordinates":[-92.426039,33.812654],"type":"Point"}
}