{
  "type": "Feature",
  "properties": {
    "iso:country":"US",
    "sg:address":"924 Hwy 62 E",
    "sg:city":"Mountain Home",
    "sg:classifiers":[
        {
            "category":"Shopping",
            "subcategory":"Gifts & Souvenirs",
            "type":"Retail Goods"
        }
    ],
    "sg:phone":"+1 870 424 3003",
    "sg:postcode":"72653",
    "sg:province":"AR",
    "wof:name":"Floral Department",
    "wof:placetype":"venue"
},
  "geometry": {"coordinates":[-92.375112,36.347414],"type":"Point"}
}