{
  "type": "Feature",
  "properties": {
    "iso:country":"US",
    "sg:address":"200 Stacy Springs Rd",
    "sg:city":"Heber Springs",
    "sg:classifiers":[
        {
            "category":"Retail",
            "subcategory":"Auto Repair",
            "type":"Services"
        }
    ],
    "sg:phone":"+1 501 362 0116",
    "sg:postcode":"72543",
    "sg:province":"AR",
    "sg:tags":[
        "shop",
        "automobile",
        "machine",
        "general"
    ],
    "wof:name":"Easons Automotive Machine Shop",
    "wof:placetype":"venue"
},
  "geometry": {"coordinates":[-92.072362,35.463376],"type":"Point"}
}