{
  "type": "Feature",
  "properties": {
    "addr:full":"6800 Dallas St Fort Smith AR 72903",
    "addr:housenumber":"6800",
    "addr:postcode":"72903",
    "addr:street":"Dallas St",
    "iso:country":"US",
    "sg:address":"6800 Dallas St",
    "sg:city":"Fort Smith",
    "sg:classifiers":[
        {
            "category":"Health Services",
            "subcategory":"Doctor",
            "type":"Services"
        }
    ],
    "sg:phone":"+1 479 478 8900",
    "sg:postcode":"72903",
    "sg:province":"AR",
    "sg:tags":[
        "clinic"
    ],
    "wof:name":"Airecore Medical Svc",
    "wof:placetype":"venue"
},
  "geometry": {"coordinates":[-94.357747,35.351577],"type":"Point"}
}