{
  "type": "Feature",
  "properties": {
    "addr:full":"270 Windwood Dr Cabot AR 72023",
    "addr:housenumber":"270",
    "addr:postcode":"72023",
    "addr:street":"Windwood Dr",
    "iso:country":"US",
    "sg:address":"270 Windwood Dr",
    "sg:city":"Cabot",
    "sg:classifiers":[
        {
            "category":"Professional",
            "subcategory":"Accounting & Tax Preparation",
            "type":"Services"
        }
    ],
    "sg:phone":"+1 501 843 3896",
    "sg:postcode":"72023",
    "sg:province":"AR",
    "wof:name":"BNC Medical Services Inc",
    "wof:placetype":"venue"
},
  "geometry": {"coordinates":[-91.988985,34.930259],"type":"Point"}
}