{
  "type": "Feature",
  "properties": {
    "iso:country":"US",
    "sg:address":"717 E 8th St",
    "sg:city":"El Dorado",
    "sg:classifiers":[
        {
            "category":"Building & Trades",
            "subcategory":"Equipment Rental",
            "type":"Services"
        }
    ],
    "sg:phone":"+1 870 918 8088",
    "sg:postcode":"71730",
    "sg:province":"AR",
    "wof:name":"Lucas Rentals LLC",
    "wof:placetype":"venue"
},
  "geometry": {"coordinates":[-92.656778,33.224865],"type":"Point"}
}