{
  "type": "Feature",
  "properties": {
    "iso:country":"US",
    "sg:address":"5611 State Hwy 261",
    "sg:city":"Marianna",
    "sg:classifiers":[
        {
            "category":"Organizations",
            "subcategory":"Religious Organization",
            "type":"Services"
        }
    ],
    "sg:phone":"+1 870 295 5157",
    "sg:postcode":"72368",
    "sg:province":"AR",
    "sg:tags":[
        "church"
    ],
    "wof:name":"Mt Gillian Baptist Church",
    "wof:placetype":"venue"
},
  "geometry": {"coordinates":[-90.90799,34.85516],"type":"Point"}
}