{
  "type": "Feature",
  "properties": {
    "addr:full":"6 Catalina Ct Little Rock AR 72211",
    "addr:housenumber":"6",
    "addr:postcode":"72211",
    "addr:street":"Catalina Ct",
    "iso:country":"US",
    "sg:address":"6 Catalina Ct",
    "sg:city":"Little Rock",
    "sg:classifiers":[
        {
            "category":"Building & Trades",
            "subcategory":"Electrical",
            "type":"Services"
        }
    ],
    "sg:phone":"+1 501 224 3765",
    "sg:postcode":"72211",
    "sg:province":"AR",
    "sg:tags":[
        "electrical",
        "contractor"
    ],
    "wof:name":"L & R Services",
    "wof:placetype":"venue"
},
  "geometry": {"coordinates":[-92.396846,34.756297],"type":"Point"}
}