{
  "type": "Feature",
  "properties": {
    "addr:full":"1017 Malcolm Ave Newport AR 72112",
    "addr:housenumber":"1017",
    "addr:postcode":"72112",
    "addr:street":"Malcolm Ave",
    "iso:country":"US",
    "sg:address":"1017 Malcolm Ave",
    "sg:city":"Newport",
    "sg:classifiers":[
        {
            "category":"Recreation",
            "type":"Entertainment"
        }
    ],
    "sg:phone":"+1 870 512 5425",
    "sg:postcode":"72112",
    "sg:province":"AR",
    "sg:tags":[
        "martial",
        "arts",
        "instruction"
    ],
    "wof:name":"Joey Perry's Martial Arts Acad",
    "wof:placetype":"venue"
},
  "geometry": {"coordinates":[-91.267627,35.606343],"type":"Point"}
}