{
  "type": "Feature",
  "properties": {
    "iso:country":"US",
    "sg:address":"2501 W Dewitt Henry Dr",
    "sg:city":"Beebe",
    "sg:classifiers":[
        {
            "category":"Retail",
            "subcategory":"Veterinary Services",
            "type":"Services"
        }
    ],
    "sg:phone":"+1 501 882 5350",
    "sg:postcode":"72012",
    "sg:province":"AR",
    "sg:tags":[
        "clinic",
        "hospital",
        "veterinarian",
        "specialty"
    ],
    "wof:name":"Apple Farm Veterinary Hospital",
    "wof:placetype":"venue"
},
  "geometry": {"coordinates":[-91.912688,35.066668],"type":"Point"}
}