{
  "type": "Feature",
  "properties": {
    "iso:country":"US",
    "sg:address":"6412 Jacksonville Cutoff Rd",
    "sg:city":"Jacksonville",
    "sg:classifiers":[
        {
            "category":"Building & Trades",
            "subcategory":"Construction",
            "type":"Services"
        }
    ],
    "sg:phone":"+1 501 835 7947",
    "sg:postcode":"72076",
    "sg:province":"AR",
    "sg:tags":[
        "siding",
        "contractor"
    ],
    "wof:name":"Tracy Dobbins",
    "wof:placetype":"venue"
},
  "geometry": {"coordinates":[-92.18087,34.868092],"type":"Point"}
}