{
  "type": "Feature",
  "properties": {
    "addr:full":"325 S 6th Pl Lowell AR 72745",
    "addr:housenumber":"325",
    "addr:postcode":"72745",
    "addr:street":"S 6Th Pl",
    "iso:country":"US",
    "sg:address":"325 S 6th Pl",
    "sg:city":"Lowell",
    "sg:classifiers":[
        {
            "category":"Health Services",
            "subcategory":"Doctor",
            "type":"Services"
        },
        {
            "category":"Health Services",
            "subcategory":"Clinic",
            "type":"Services"
        }
    ],
    "sg:phone":"+1 479 770 0700",
    "sg:postcode":"72745",
    "sg:province":"AR",
    "sg:tags":[
        "physician",
        "pediatrics",
        "family",
        "endocrinology",
        "medical",
        "practice",
        "surgeons",
        "manipulative",
        "osteopathic",
        "treatment",
        "medicine",
        "metabolism",
        "diabetes"
    ],
    "wof:name":"Lowell Medical Center",
    "wof:placetype":"venue"
},
  "geometry": {"coordinates":[-94.14998300000001,36.24987],"type":"Point"}
}