{
  "type": "Feature",
  "properties": {
    "iso:country":"US",
    "sg:address":"122 E Rush Ave",
    "sg:city":"Harrison",
    "sg:classifiers":[
        {
            "category":"Government",
            "subcategory":"Office",
            "type":"Public Place"
        }
    ],
    "sg:phone":"+1 870 741 1789",
    "sg:postcode":"72601",
    "sg:province":"AR",
    "sg:tags":[
        "village"
    ],
    "wof:name":"Convention & Visitor's Bureau",
    "wof:placetype":"venue"
},
  "geometry": {"coordinates":[-93.107126,36.230804],"type":"Point"}
}