{
  "type": "Feature",
  "properties": {
    "iso:country":"US",
    "sg:address":"1555 E Oak St",
    "sg:city":"Conway",
    "sg:classifiers":[
        {
            "category":"Autos & Motor Vehicles",
            "subcategory":"Automobile Sales",
            "type":"Retail Goods"
        }
    ],
    "sg:phone":"+1 501 329 3970",
    "sg:postcode":"72032",
    "sg:province":"AR",
    "sg:tags":[
        "car",
        "dealer"
    ],
    "wof:name":"Larry's Auto Sales",
    "wof:placetype":"venue"
},
  "geometry": {"coordinates":[-92.406464,35.091125],"type":"Point"}
}