{
  "type": "Feature",
  "properties": {
    "addr:full":"1137 W Washington St Camden AR 71701",
    "addr:housenumber":"1137",
    "addr:postcode":"71701",
    "addr:street":"W Washington St",
    "iso:country":"US",
    "sg:address":"1137 W Washington St",
    "sg:city":"Camden",
    "sg:classifiers":[
        {
            "category":"Restaurant",
            "type":"Food & Drink"
        }
    ],
    "sg:phone":"+1 870 836 0474",
    "sg:postcode":"71701",
    "sg:province":"AR",
    "wof:name":"Woods Place",
    "wof:placetype":"venue"
},
  "geometry": {"coordinates":[-92.851406,33.584946],"type":"Point"}
}