{
  "type": "Feature",
  "properties": {
    "addr:full":"8100 T P White Dr Cabot AR 72023",
    "addr:housenumber":"8100",
    "addr:postcode":"72023",
    "addr:street":"T P White Dr",
    "iso:country":"US",
    "sg:address":"8100 T P White Dr",
    "sg:city":"Cabot",
    "sg:classifiers":[
        {
            "category":"Shopping",
            "subcategory":"Clothing, Apparel, & Fashions",
            "type":"Retail Goods"
        }
    ],
    "sg:phone":"+1 501 982 0904",
    "sg:postcode":"72023",
    "sg:province":"AR",
    "sg:tags":[
        "western"
    ],
    "wof:name":"Cowboy Way Western Store",
    "wof:placetype":"venue"
},
  "geometry": {"coordinates":[-92.075125,34.939658],"type":"Point"}
}