{
  "type": "Feature",
  "properties": {
    "addr:full":"5515 State Hwy 8 Mena AR 71953",
    "addr:housenumber":"5515",
    "addr:postcode":"71953",
    "addr:street":"State Hwy 8",
    "iso:country":"US",
    "sg:address":"5515 State Hwy 8",
    "sg:city":"Mena",
    "sg:classifiers":[
        {
            "category":"Freight",
            "type":"Transportation"
        }
    ],
    "sg:phone":"+1 479 394 5817",
    "sg:postcode":"71953",
    "sg:province":"AR",
    "sg:tags":[
        "operator",
        "local",
        "trucking"
    ],
    "wof:name":"Rosenboom Trucking Inc",
    "wof:placetype":"venue"
},
  "geometry": {"coordinates":[-94.41334500000001,34.639296],"type":"Point"}
}