{
  "type": "Feature",
  "properties": {
    "addr:full":"309 N Chestnut St Harrison AR 72601",
    "addr:housenumber":"309",
    "addr:postcode":"72601",
    "addr:street":"N Chestnut St",
    "iso:country":"US",
    "sg:address":"309 N Chestnut St",
    "sg:city":"Harrison",
    "sg:classifiers":[
        {
            "category":"Shopping",
            "subcategory":"Jewelry",
            "type":"Retail Goods"
        }
    ],
    "sg:phone":"+1 870 365 3079",
    "sg:postcode":"72601",
    "sg:province":"AR",
    "wof:name":"Selections By Victoria",
    "wof:placetype":"venue"
},
  "geometry": {"coordinates":[-93.10195899999999,36.232911],"type":"Point"}
}