{
  "type": "Feature",
  "properties": {
    "iso:country":"US",
    "sg:address":"12100 US Hwy 270",
    "sg:city":"White Hall",
    "sg:classifiers":[
        {
            "category":"Social Services",
            "subcategory":"Child Care",
            "type":"Services"
        }
    ],
    "sg:phone":"+1 870 247 5350",
    "sg:postcode":"71602",
    "sg:province":"AR",
    "sg:tags":[
        "day"
    ],
    "wof:name":"L & R Day Care",
    "wof:placetype":"venue"
},
  "geometry": {"coordinates":[-92.172186,34.29119],"type":"Point"}
}