{
  "type": "Feature",
  "properties": {
    "iso:country":"US",
    "sg:address":"326 Tanglewood Dr",
    "sg:city":"Monticello",
    "sg:classifiers":[
        {
            "category":"Retail",
            "subcategory":"Repair Shop",
            "type":"Services"
        }
    ],
    "sg:phone":"+1 870 367 9451",
    "sg:postcode":"71655",
    "sg:province":"AR",
    "sg:tags":[
        "locksmith"
    ],
    "wof:name":"Locks & Keys",
    "wof:placetype":"venue"
},
  "geometry": {"coordinates":[-91.817858,33.639481],"type":"Point"}
}