{
  "type": "Feature",
  "properties": {
    "addr:full":"1809 S Pierce St Little Rock AR 72204",
    "addr:housenumber":"1809",
    "addr:postcode":"72204",
    "addr:street":"S Pierce St",
    "iso:country":"US",
    "sg:address":"1809 S Pierce St",
    "sg:city":"Little Rock",
    "sg:classifiers":[
        {
            "category":"Professional",
            "subcategory":"Management & Consulting",
            "type":"Services"
        }
    ],
    "sg:phone":"+1 501 663 0294",
    "sg:postcode":"72204",
    "sg:province":"AR",
    "sg:tags":[
        "business"
    ],
    "wof:name":"Cathys Development Consultant",
    "wof:placetype":"venue"
},
  "geometry": {"coordinates":[-92.338075,34.734933],"type":"Point"}
}