{
  "type": "Feature",
  "properties": {
    "addr:full":"12 Wilson Farm Rd Greenbrier AR 72058",
    "addr:housenumber":"12",
    "addr:postcode":"72058",
    "addr:street":"Wilson Farm Rd",
    "iso:country":"US",
    "sg:address":"12 Wilson Farm Rd",
    "sg:city":"Greenbrier",
    "sg:classifiers":[
        {
            "category":"Organizations",
            "subcategory":"Religious Organization",
            "type":"Services"
        }
    ],
    "sg:phone":"+1 501 679 3647",
    "sg:postcode":"72058",
    "sg:province":"AR",
    "sg:website":"www.gb-church-of-christ.org",
    "wof:name":"Church Of Christ",
    "wof:placetype":"venue"
},
  "geometry": {"coordinates":[-92.387857,35.22251],"type":"Point"}
}