{
  "type": "Feature",
  "properties": {
    "addr:full":"980 Neely Loop Rison AR 71665",
    "addr:housenumber":"980",
    "addr:postcode":"71665",
    "addr:street":"Neely Loop",
    "iso:country":"US",
    "sg:address":"980 Neely Loop",
    "sg:city":"Rison",
    "sg:classifiers":[
        {
            "category":"Retail",
            "subcategory":"Animal Services",
            "type":"Services"
        }
    ],
    "sg:phone":"+1 870 357 8158",
    "sg:postcode":"71665",
    "sg:province":"AR",
    "wof:name":"Paul Beard Cutting Horses",
    "wof:placetype":"venue"
},
  "geometry": {"coordinates":[-91.99830900000001,33.7954],"type":"Point"}
}