{
  "type": "Feature",
  "properties": {
    "addr:full":"525 Cedar Creek Rd Hot Springs National AR 71901",
    "addr:housenumber":"525",
    "addr:postcode":"71901",
    "addr:street":"Cedar Creek Rd;National",
    "iso:country":"US",
    "sg:address":"525 Cedar Creek Rd",
    "sg:city":"Hot Springs National",
    "sg:classifiers":[
        {
            "category":"Shopping",
            "subcategory":"Jewelry",
            "type":"Retail Goods"
        }
    ],
    "sg:phone":"+1 501 262 2245",
    "sg:postcode":"71901",
    "sg:province":"AR",
    "wof:name":"Family Jewelry",
    "wof:placetype":"venue"
},
  "geometry": {"coordinates":[-92.962913,34.517763],"type":"Point"}
}