{
  "type": "Feature",
  "properties": {
    "addr:full":"105 US Hwy 70 Hazen AR 72064",
    "addr:housenumber":"105",
    "addr:postcode":"72064",
    "addr:street":"Us Hwy 70",
    "iso:country":"US",
    "sg:address":"105 US Hwy 70",
    "sg:city":"Hazen",
    "sg:classifiers":[
        {
            "category":"Retail",
            "subcategory":"Auto Repair",
            "type":"Services"
        }
    ],
    "sg:phone":"+1 870 255 3309",
    "sg:postcode":"72064",
    "sg:province":"AR",
    "sg:tags":[
        "repairing",
        "automobile"
    ],
    "wof:name":"Rick's Automotive",
    "wof:placetype":"venue"
},
  "geometry": {"coordinates":[-91.58357599999999,34.780485],"type":"Point"}
}