{
  "type": "Feature",
  "properties": {
    "iso:country":"US",
    "sg:address":"2105 Griderfield-Ladd Rd",
    "sg:city":"Pine Bluff",
    "sg:phone":"+1 870 536 4777",
    "sg:postcode":"71601",
    "sg:province":"AR",
    "sg:tags":[
        "farm",
        "soybean"
    ],
    "wof:name":"Marty Shell",
    "wof:placetype":"venue"
},
  "geometry": {"coordinates":[-91.944564,34.171293],"type":"Point"}
}