{
  "type": "Feature",
  "properties": {
    "iso:country":"US",
    "sg:address":"388 Pine Ridge Rd",
    "sg:city":"Pottsville",
    "sg:classifiers":[
        {
            "category":"Wholesale",
            "subcategory":"Durable Goods & Equipment",
            "type":"Manufacturing & Wholesale Goods"
        }
    ],
    "sg:phone":"+1 479 968 4504",
    "sg:postcode":"72858",
    "sg:province":"AR",
    "wof:name":"Howerton Log Industries",
    "wof:placetype":"venue"
},
  "geometry": {"coordinates":[-93.035948,35.242852],"type":"Point"}
}