{
  "type": "Feature",
  "properties": {
    "addr:full":"401 Oaklawn Cir Little Rock AR 72206",
    "addr:housenumber":"401",
    "addr:postcode":"72206",
    "addr:street":"Oaklawn Cir",
    "iso:country":"US",
    "sg:address":"401 Oaklawn Cir",
    "sg:city":"Little Rock",
    "sg:classifiers":[
        {
            "category":"Shopping",
            "subcategory":"Clothing, Apparel, & Fashions",
            "type":"Retail Goods"
        }
    ],
    "sg:phone":"+1 501 888 6867",
    "sg:postcode":"72206",
    "sg:province":"AR",
    "wof:name":"Spellbound LLC",
    "wof:placetype":"venue"
},
  "geometry": {"coordinates":[-92.300185,34.57279],"type":"Point"}
}