{
  "type": "Feature",
  "properties": {
    "iso:country":"US",
    "sg:address":"2910 E Broadway St",
    "sg:city":"N Little Rock",
    "sg:classifiers":[
        {
            "category":"Food & Beverages",
            "subcategory":"Groceries & Convenience Stores",
            "type":"Retail Goods"
        }
    ],
    "sg:phone":"+1 501 945 6927",
    "sg:postcode":"72114",
    "sg:province":"AR",
    "wof:name":"Dodges Chicken Store",
    "wof:placetype":"venue"
},
  "geometry": {"coordinates":[-92.234047,34.755176],"type":"Point"}
}