{
  "type": "Feature",
  "properties": {
    "addr:full":"3251 E Idlewood Way Fayetteville AR 72703",
    "addr:housenumber":"3251",
    "addr:postcode":"72703",
    "addr:street":"E Idlewood Way",
    "iso:country":"US",
    "sg:address":"3251 E Idlewood Way",
    "sg:city":"Fayetteville",
    "sg:classifiers":[
        {
            "category":"Restaurant",
            "type":"Food & Drink"
        }
    ],
    "sg:phone":"+1 479 443 2523",
    "sg:postcode":"72703",
    "sg:province":"AR",
    "wof:name":"Acropolis Restaurant",
    "wof:placetype":"venue"
},
  "geometry": {"coordinates":[-94.11480400000001,36.10122],"type":"Point"}
}