{
  "type": "Feature",
  "properties": {
    "iso:country":"US",
    "sg:address":"3251 E Idlewood Way",
    "sg:city":"Fayetteville",
    "sg:classifiers":[
        {
            "category":"Restaurant",
            "type":"Food & Drink"
        }
    ],
    "sg:phone":"+1 479 443 2523",
    "sg:postcode":"72703",
    "sg:province":"AR",
    "wof:name":"Acropolis Restaurant",
    "wof:placetype":"venue"
},
  "geometry": {"coordinates":[-94.114804,36.10122],"type":"Point"}
}