{
  "type": "Feature",
  "properties": {
    "iso:country":"US",
    "sg:address":"10149 Cord Rd",
    "sg:city":"Cord",
    "sg:phone":"+1 870 799 8142",
    "sg:postcode":"72524",
    "sg:province":"AR",
    "sg:tags":[
        "beef",
        "farm",
        "corn",
        "soybean",
        "cattle",
        "rice",
        "feedlot"
    ],
    "wof:name":"Gene Lucy",
    "wof:placetype":"venue"
},
  "geometry": {"coordinates":[-91.302941,35.861443],"type":"Point"}
}