{
  "type": "Feature",
  "properties": {
    "addr:full":"2218 Selma St Texarkana AR 71854",
    "addr:housenumber":"2218",
    "addr:postcode":"71854",
    "addr:street":"Selma St",
    "iso:country":"US",
    "sg:address":"2218 Selma St",
    "sg:city":"Texarkana",
    "sg:classifiers":[
        {
            "category":"Professional",
            "subcategory":"Business Services",
            "type":"Services"
        }
    ],
    "sg:phone":"+1 870 772 6993",
    "sg:postcode":"71854",
    "sg:province":"AR",
    "sg:tags":[
        "auction"
    ],
    "wof:name":"Mcadams Auctions",
    "wof:placetype":"venue"
},
  "geometry": {"coordinates":[-94.029489,33.400308],"type":"Point"}
}