{
  "type": "Feature",
  "properties": {
    "iso:country":"US",
    "sg:address":"3201 State Hwy 161",
    "sg:city":"N Little Rock",
    "sg:classifiers":[
        {
            "category":"Freight",
            "type":"Transportation"
        }
    ],
    "sg:phone":"+1 501 604 3700",
    "sg:postcode":"72117",
    "sg:province":"AR",
    "sg:tags":[
        "operator",
        "trucking"
    ],
    "wof:name":"Southern Trucking Corp",
    "wof:placetype":"venue"
},
  "geometry": {"coordinates":[-92.204045,34.779153],"type":"Point"}
}