{
  "type": "Feature",
  "properties": {
    "iso:country":"US",
    "sg:address":"412 S Hwy 65 82",
    "sg:city":"Lake Village",
    "sg:classifiers":[
        {
            "category":"Travel",
            "subcategory":"Hotels & Motels",
            "type":"Entertainment"
        }
    ],
    "sg:phone":"+1 870 265 5341",
    "sg:postcode":"71653",
    "sg:province":"AR",
    "wof:name":"Lake Plaza Inn",
    "wof:placetype":"venue"
},
  "geometry": {"coordinates":[-91.29201,33.329285],"type":"Point"}
}