{
  "type": "Feature",
  "properties": {
    "iso:country":"US",
    "sg:address":"2474 E Joyce Blvd Ste 2",
    "sg:city":"Fayetteville",
    "sg:classifiers":[
        {
            "category":"Education",
            "subcategory":"School",
            "type":"Public Place"
        }
    ],
    "sg:phone":"+1 479 521 8326",
    "sg:postcode":"72703",
    "sg:province":"AR",
    "sg:tags":[
        "k-",
        "private"
    ],
    "wof:name":"On Your Mark Academy",
    "wof:placetype":"venue"
},
  "geometry": {"coordinates":[-94.125826,36.119953],"type":"Point"}
}