{
  "type": "Feature",
  "properties": {
    "iso:country":"US",
    "sg:address":"2013 Green Acres",
    "sg:city":"Fayetteville",
    "sg:classifiers":[
        {
            "category":"Freight",
            "type":"Transportation"
        }
    ],
    "sg:phone":"+1 479 251 7925",
    "sg:postcode":"72703",
    "sg:province":"AR",
    "sg:tags":[
        "operator",
        "trucking"
    ],
    "wof:name":"Quality Trucking",
    "wof:placetype":"venue"
},
  "geometry": {"coordinates":[-94.155615,36.090149],"type":"Point"}
}