{
  "type": "Feature",
  "properties": {
    "addr:full":"2 Cabot Cove Cabot AR 72023",
    "addr:housenumber":"2",
    "addr:postcode":"72023",
    "addr:street":"Cabot Cove",
    "iso:country":"US",
    "sg:address":"2 Cabot Cove",
    "sg:city":"Cabot",
    "sg:classifiers":[
        {
            "category":"Personal",
            "subcategory":"Barber",
            "type":"Services"
        }
    ],
    "sg:phone":"+1 501 843 6326",
    "sg:postcode":"72023",
    "sg:province":"AR",
    "wof:name":"Randy's Styling Salon",
    "wof:placetype":"venue"
},
  "geometry": {"coordinates":[-92.01830200000001,34.996483],"type":"Point"}
}