{
  "type": "Feature",
  "properties": {
    "iso:country":"US",
    "sg:address":"2200 Malcolm Ave",
    "sg:city":"Newport",
    "sg:classifiers":[
        {
            "category":"Restaurant",
            "type":"Food & Drink"
        }
    ],
    "sg:menulink":"http://www.allmenus.com/ar/union/198700-kfc---kentucky-fried-chicken/menu/",
    "sg:phone":"+1 870 523 6323",
    "sg:postcode":"72112",
    "sg:province":"AR",
    "sg:tags":[
        "american",
        "chicken"
    ],
    "wof:name":"KFC - Kentucky Fried Chicken",
    "wof:placetype":"venue"
},
  "geometry": {"coordinates":[-91.25481499999999,35.605551],"type":"Point"}
}