{
  "type": "Feature",
  "properties": {
    "iso:country":"US",
    "sg:address":"7221 State Hwy 98",
    "sg:city":"Magnolia",
    "sg:classifiers":[
        {
            "category":"Organizations",
            "subcategory":"Religious Organization",
            "type":"Services"
        }
    ],
    "sg:phone":"+1 870 695 3112",
    "sg:postcode":"71753",
    "sg:province":"AR",
    "sg:tags":[
        "church"
    ],
    "wof:name":"Macedonia Baptist Church Study",
    "wof:placetype":"venue"
},
  "geometry": {"coordinates":[-93.132978,33.352849],"type":"Point"}
}