{
  "type": "Feature",
  "properties": {
    "iso:country":"US",
    "sg:address":"140 W Main St",
    "sg:city":"Gentry",
    "sg:classifiers":[
        {
            "category":"Restaurant",
            "type":"Food & Drink"
        }
    ],
    "sg:phone":"+1 479 736 5554",
    "sg:postcode":"72734",
    "sg:province":"AR",
    "wof:name":"Tillys Across The Border",
    "wof:placetype":"venue"
},
  "geometry": {"coordinates":[-94.486975,36.267647],"type":"Point"}
}