{
  "type": "Feature",
  "properties": {
    "iso:country":"US",
    "sg:address":"34510 W Hundley Rd",
    "sg:city":"Bigelow",
    "sg:classifiers":[
        {
            "category":"Real Estate",
            "subcategory":"Real Estate Operator",
            "type":"Services"
        }
    ],
    "sg:phone":"+1 501 330 2816",
    "sg:postcode":"72016",
    "sg:province":"AR",
    "sg:tags":[
        "railroad",
        "property",
        "lessor"
    ],
    "wof:name":"Khc Family Properties Inc",
    "wof:placetype":"venue"
},
  "geometry": {"coordinates":[-92.644361,34.924108],"type":"Point"}
}