{
  "type": "Feature",
  "properties": {
    "iso:country":"US",
    "sg:address":"112 S Fulton St",
    "sg:city":"Clarksville",
    "sg:classifiers":[
        {
            "category":"Professional",
            "type":"Services"
        },
        {
            "category":"Organizations",
            "subcategory":"Political Organization",
            "type":"Services"
        }
    ],
    "sg:phone":"+1 479 705 9200",
    "sg:postcode":"72830",
    "sg:province":"AR",
    "wof:name":"Mc Cain Campaign",
    "wof:placetype":"venue"
},
  "geometry": {"coordinates":[-93.465725,35.470975],"type":"Point"}
}