{
  "type": "Feature",
  "properties": {
    "addr:full":"4262 W Mount Comfort Rd Fayetteville AR 72704",
    "addr:housenumber":"4262",
    "addr:postcode":"72704",
    "addr:street":"W Mount Comfort Rd",
    "iso:country":"US",
    "sg:address":"4262 W Mount Comfort Rd",
    "sg:city":"Fayetteville",
    "sg:classifiers":[
        {
            "category":"Organizations",
            "subcategory":"Religious Organization",
            "type":"Services"
        }
    ],
    "sg:phone":"+1 479 442 6009",
    "sg:postcode":"72704",
    "sg:province":"AR",
    "sg:tags":[
        "church"
    ],
    "wof:name":"Shiloh Community Church",
    "wof:placetype":"venue"
},
  "geometry": {"coordinates":[-94.218924,36.093347],"type":"Point"}
}