{
  "type": "Feature",
  "properties": {
    "iso:country":"US",
    "sg:address":"202 Girard St",
    "sg:city":"Flippin",
    "sg:classifiers":[
        {
            "category":"Retail",
            "subcategory":"Repair Shop",
            "type":"Services"
        }
    ],
    "sg:phone":"+1 870 453 7124",
    "sg:postcode":"72634",
    "sg:province":"AR",
    "sg:tags":[
        "blacksmith"
    ],
    "wof:name":"Can Do Auto & Blacksmith",
    "wof:placetype":"venue"
},
  "geometry": {"coordinates":[-92.597179,36.279005],"type":"Point"}
}