{
  "type": "Feature",
  "properties": {
    "iso:country":"US",
    "sg:address":"400 W Oak St",
    "sg:city":"El Dorado",
    "sg:classifiers":[
        {
            "category":"Real Estate",
            "subcategory":"Real Estate Agent",
            "type":"Services"
        }
    ],
    "sg:phone":"+1 870 875 1188",
    "sg:postcode":"71730",
    "sg:province":"AR",
    "wof:name":"McGee Apraisal",
    "wof:placetype":"venue"
},
  "geometry": {"coordinates":[-92.667466,33.213587],"type":"Point"}
}