{
  "type": "Feature",
  "properties": {
    "iso:country":"US",
    "sg:address":"403 W Church St",
    "sg:city":"Horseshoe Bend",
    "sg:classifiers":[
        {
            "category":"Retail",
            "subcategory":"Repair Shop",
            "type":"Services"
        }
    ],
    "sg:phone":"+1 870 670 5545",
    "sg:postcode":"72512",
    "sg:province":"AR",
    "sg:tags":[
        "repairing",
        "lawn",
        "mower"
    ],
    "wof:name":"Horseshoe Bend Sales & Svc",
    "wof:placetype":"venue"
},
  "geometry": {"coordinates":[-91.756022,36.216767],"type":"Point"}
}