{
  "type": "Feature",
  "properties": {
    "addr:full":"1543 Ford Ave Springdale AR 72764",
    "addr:housenumber":"1543",
    "addr:postcode":"72764",
    "addr:street":"Ford Ave",
    "iso:country":"US",
    "sg:address":"1543 Ford Ave",
    "sg:city":"Springdale",
    "sg:classifiers":[
        {
            "category":"Freight",
            "type":"Transportation"
        }
    ],
    "sg:phone":"+1 479 751 7192",
    "sg:postcode":"72764",
    "sg:province":"AR",
    "sg:tags":[
        "terminal",
        "motor"
    ],
    "sg:website":"www.myyellow.com",
    "wof:name":"Yellow Transportation Inc",
    "wof:placetype":"venue"
},
  "geometry": {"coordinates":[-94.113131,36.177023],"type":"Point"}
}