{
  "type": "Feature",
  "properties": {
    "iso:country":"US",
    "sg:address":"806 W 22nd St",
    "sg:city":"Stuttgart",
    "sg:classifiers":[
        {
            "category":"Professional",
            "type":"Services"
        }
    ],
    "sg:phone":"+1 870 673 8730",
    "sg:postcode":"72160",
    "sg:province":"AR",
    "wof:name":"Home Plus",
    "wof:placetype":"venue"
},
  "geometry": {"coordinates":[-91.562279,34.479594],"type":"Point"}
}