{
  "type": "Feature",
  "properties": {
    "iso:country":"US",
    "sg:address":"10125 Beaver Ln",
    "sg:city":"Rogers",
    "sg:classifiers":[
        {
            "category":"Retail",
            "subcategory":"Repair Shop",
            "type":"Services"
        }
    ],
    "sg:phone":"+1 479 925 1556",
    "sg:postcode":"72758",
    "sg:province":"AR",
    "sg:tags":[
        "body",
        "auto",
        "upholsterer"
    ],
    "wof:name":"Brown's Custom Trim Shop",
    "wof:placetype":"venue"
},
  "geometry": {"coordinates":[-94.025515,36.284988],"type":"Point"}
}