{
  "type": "Feature",
  "properties": {
    "iso:country":"US",
    "sg:address":"600 Hospital Dr",
    "sg:city":"Mountain Home",
    "sg:classifiers":[
        {
            "category":"Retail",
            "subcategory":"Funeral Services",
            "type":"Services"
        }
    ],
    "sg:phone":"+1 870 425 6978",
    "sg:postcode":"72653",
    "sg:province":"AR",
    "sg:tags":[
        "director"
    ],
    "sg:website":"www.kirbyboaz.com",
    "wof:name":"Kirby Boaz Funeral Home",
    "wof:placetype":"venue"
},
  "geometry": {"coordinates":[-92.39441,36.34298],"type":"Point"}
}