{
  "type": "Feature",
  "properties": {
    "addr:full":"121 S Laurel St Hope AR 71801",
    "addr:housenumber":"121",
    "addr:postcode":"71801",
    "addr:street":"S Laurel St",
    "iso:country":"US",
    "sg:address":"121 S Laurel St",
    "sg:city":"Hope",
    "sg:classifiers":[
        {
            "category":"Government",
            "subcategory":"Post Office",
            "type":"Public Place"
        }
    ],
    "sg:phone":"+1 870 777 3580",
    "sg:postcode":"71801",
    "sg:province":"AR",
    "wof:name":"US Post Office",
    "wof:placetype":"venue"
},
  "geometry": {"coordinates":[-93.588655,33.669544],"type":"Point"}
}