{
  "type": "Feature",
  "properties": {
    "addr:full":"421 E Cypress St Brinkley AR 72021",
    "addr:housenumber":"421",
    "addr:postcode":"72021",
    "addr:street":"E Cypress St",
    "iso:country":"US",
    "sg:address":"421 E Cypress St",
    "sg:city":"Brinkley",
    "sg:classifiers":[
        {
            "category":"Retail",
            "subcategory":"Auto Repair",
            "type":"Services"
        }
    ],
    "sg:phone":"+1 870 734 1414",
    "sg:postcode":"72021",
    "sg:province":"AR",
    "sg:tags":[
        "repairing",
        "automobile"
    ],
    "wof:name":"Jeff's Repair",
    "wof:placetype":"venue"
},
  "geometry": {"coordinates":[-91.181417,34.887189],"type":"Point"}
}