{
  "type": "Feature",
  "properties": {
    "iso:country":"US",
    "sg:address":"1700 Island Harbor Marina Rd",
    "sg:city":"White Hall",
    "sg:classifiers":[
        {
            "category":"Recreation",
            "subcategory":"Marina",
            "type":"Entertainment"
        }
    ],
    "sg:phone":"+1 870 536 3288",
    "sg:postcode":"71602",
    "sg:province":"AR",
    "sg:tags":[
        "rental",
        "boat",
        "operates"
    ],
    "wof:name":"Island Harbor Marina",
    "wof:placetype":"venue"
},
  "geometry": {"coordinates":[-91.95302599999999,34.27776],"type":"Point"}
}