{
  "type": "Feature",
  "properties": {
    "addr:full":"111 S Pruett St Paragould AR 72450",
    "addr:housenumber":"111",
    "addr:postcode":"72450",
    "addr:street":"S Pruett St",
    "iso:country":"US",
    "sg:address":"111 S Pruett St",
    "sg:city":"Paragould",
    "sg:classifiers":[
        {
            "category":"Personal",
            "subcategory":"Beauty Salon",
            "type":"Services"
        }
    ],
    "sg:phone":"+1 870 215 0105",
    "sg:postcode":"72450",
    "sg:province":"AR",
    "sg:tags":[
        "shop"
    ],
    "wof:name":"Joetta's Uptown Beauty Salon",
    "wof:placetype":"venue"
},
  "geometry": {"coordinates":[-90.48612900000001,36.05565],"type":"Point"}
}