{
  "type": "Feature",
  "properties": {
    "iso:country":"US",
    "sg:address":"111 S Pruett St",
    "sg:city":"Paragould",
    "sg:classifiers":[
        {
            "category":"Personal",
            "subcategory":"Beauty Salon",
            "type":"Services"
        }
    ],
    "sg:phone":"+1 870 215 0105",
    "sg:postcode":"72450",
    "sg:province":"AR",
    "sg:tags":[
        "shop"
    ],
    "wof:name":"Joetta's Uptown Beauty Salon",
    "wof:placetype":"venue"
},
  "geometry": {"coordinates":[-90.486129,36.05565],"type":"Point"}
}