{
  "type": "Feature",
  "properties": {
    "addr:full":"3601 W Roosevelt Rd Little Rock AR 72204",
    "addr:housenumber":"3601",
    "addr:postcode":"72204",
    "addr:street":"W Roosevelt Rd",
    "iso:country":"US",
    "sg:address":"3601 W Roosevelt Rd",
    "sg:city":"Little Rock",
    "sg:classifiers":[
        {
            "category":"Professional",
            "subcategory":"Management & Consulting",
            "type":"Services"
        }
    ],
    "sg:phone":"+1 501 663 4416",
    "sg:postcode":"72204",
    "sg:province":"AR",
    "sg:tags":[
        "business"
    ],
    "wof:name":"McGinnis Business Svcs Corp",
    "wof:placetype":"venue"
},
  "geometry": {"coordinates":[-92.312836,34.725647],"type":"Point"}
}