{
  "type": "Feature",
  "properties": {
    "iso:country":"US",
    "sg:address":"250 Central Ave",
    "sg:city":"Hot Springs",
    "sg:classifiers":[
        {
            "category":"Museum",
            "type":"Entertainment"
        }
    ],
    "sg:phone":"+1 501 623 5836",
    "sg:postcode":"71901",
    "sg:province":"AR",
    "sg:tags":[
        "shop",
        "gift",
        "ice",
        "stand",
        "wax",
        "cream"
    ],
    "wof:name":"Tussaud Josephine Wax Museum",
    "wof:placetype":"venue"
},
  "geometry": {"coordinates":[-93.05398599999999,34.516987],"type":"Point"}
}