{
  "type": "Feature",
  "properties": {
    "addr:city":"Hot Springs",
    "addr:full":"250 Central Ave Hot Springs, Ar 71901",
    "addr:house_number":"250",
    "addr:housenumber":"250",
    "addr:phone":"+1 501-623-5836",
    "addr:postcode":"71901",
    "addr:road":"Central Ave",
    "addr:state":"AR",
    "addr:street":"Central Ave",
    "iso:country":"US",
    "sg:address":"250 Central Ave",
    "sg:city":"Hot Springs",
    "sg:classifiers":[
        {
            "category":"Museum",
            "type":"Entertainment"
        }
    ],
    "sg:phone":"+1 501 623 5836",
    "sg:postcode":"71901",
    "sg:province":"AR",
    "sg:tags":[
        "shop",
        "gift",
        "ice",
        "stand",
        "wax",
        "cream"
    ],
    "wof:name":"Josephine Tussaud Wax Museum",
    "wof:placetype":"venue"
},
  "geometry": {"coordinates":[-93.05410000000001,34.51711],"type":"Point"}
}