{
  "type": "Feature",
  "properties": {
    "addr:full":"969 Main St Vilonia AR 72173",
    "addr:housenumber":"969",
    "addr:postcode":"72173",
    "addr:street":"Main St",
    "iso:country":"US",
    "sg:address":"969 Main St",
    "sg:city":"Vilonia",
    "sg:classifiers":[
        {
            "category":"Building & Trades",
            "subcategory":"Equipment Rental",
            "type":"Services"
        }
    ],
    "sg:phone":"+1 501 796 3292",
    "sg:postcode":"72173",
    "sg:province":"AR",
    "sg:tags":[
        "moving",
        "supply"
    ],
    "wof:name":"U-Haul Co",
    "wof:placetype":"venue"
},
  "geometry": {"coordinates":[-92.230521,35.082043],"type":"Point"}
}