{
  "type": "Feature",
  "properties": {
    "iso:country":"US",
    "sg:address":"300 S Main St",
    "sg:city":"Rector",
    "sg:classifiers":[
        {
            "category":"Shopping",
            "subcategory":"Florist",
            "type":"Retail Goods"
        }
    ],
    "sg:phone":"+1 870 595 2135",
    "sg:postcode":"72461",
    "sg:province":"AR",
    "wof:name":"Rector Flowers And Gifts",
    "wof:placetype":"venue"
},
  "geometry": {"coordinates":[-90.292764,36.258796],"type":"Point"}
}