{
  "type": "Feature",
  "properties": {
    "iso:country":"US",
    "sg:address":"7215 Gable Dr",
    "sg:city":"Little Rock",
    "sg:classifiers":[
        {
            "category":"Professional",
            "type":"Services"
        }
    ],
    "sg:phone":"+1 501 664 5262",
    "sg:postcode":"72205",
    "sg:province":"AR",
    "wof:name":"Biodiscovery LLC",
    "wof:placetype":"venue"
},
  "geometry": {"coordinates":[-92.356245,34.758987],"type":"Point"}
}