{
  "type": "Feature",
  "properties": {
    "addr:full":"124 N Jackson St Magnolia AR 71753",
    "addr:housenumber":"124",
    "addr:postcode":"71753",
    "addr:street":"N Jackson St",
    "iso:country":"US",
    "sg:address":"124 N Jackson St",
    "sg:city":"Magnolia",
    "sg:classifiers":[
        {
            "category":"Wholesale",
            "subcategory":"Construction Materials",
            "type":"Manufacturing & Wholesale Goods"
        }
    ],
    "sg:phone":"+1 870 234 4800",
    "sg:postcode":"71753",
    "sg:province":"AR",
    "sg:tags":[
        "timberland",
        "company",
        "timber"
    ],
    "wof:name":"Alliance Timber Inc",
    "wof:placetype":"venue"
},
  "geometry": {"coordinates":[-93.23918999999999,33.267996],"type":"Point"}
}