{
  "type": "Feature",
  "properties": {
    "addr:full":"14198 Highway 5 S Norfork AR 72658",
    "addr:housenumber":"14198",
    "addr:postcode":"72658",
    "addr:street":"Highway 5 S",
    "iso:country":"US",
    "sg:address":"14198 Highway 5 S",
    "sg:city":"Norfork",
    "sg:classifiers":[
        {
            "category":"Coffee & Tea",
            "type":"Food & Drink"
        },
        {
            "category":"Restaurant",
            "type":"Food & Drink"
        }
    ],
    "sg:phone":"+1 870 499 7400",
    "sg:postcode":"72658",
    "sg:province":"AR",
    "sg:tags":[
        "espresso"
    ],
    "wof:name":"Norfork Cafe",
    "wof:placetype":"venue"
},
  "geometry": {"coordinates":[-92.261881,36.19826],"type":"Point"}
}