{
  "type": "Feature",
  "properties": {
    "addr:full":"402 Main St Lake Village AR 71653",
    "addr:housenumber":"402",
    "addr:postcode":"71653",
    "addr:street":"Main St",
    "iso:country":"US",
    "sg:address":"402 Main St",
    "sg:city":"Lake Village",
    "sg:classifiers":[
        {
            "category":"Shopping",
            "subcategory":"Jewelry",
            "type":"Retail Goods"
        }
    ],
    "sg:phone":"+1 870 265 3656",
    "sg:postcode":"71653",
    "sg:province":"AR",
    "sg:tags":[
        "jeweler"
    ],
    "wof:name":"Sunriver Corp",
    "wof:placetype":"venue"
},
  "geometry": {"coordinates":[-91.285009,33.33164],"type":"Point"}
}