{
  "type": "Feature",
  "properties": {
    "addr:full":"301 S Pocola Blvd Pocola OK 74902",
    "addr:housenumber":"301",
    "addr:postcode":"74902",
    "addr:street":"S Pocola Blvd",
    "iso:country":"US",
    "sg:address":"301 S Pocola Blvd",
    "sg:city":"Pocola",
    "sg:classifiers":[
        {
            "category":"Retail",
            "subcategory":"Funeral Services",
            "type":"Services"
        }
    ],
    "sg:phone":"+1 918 436 2415",
    "sg:postcode":"74902",
    "sg:province":"OK",
    "sg:tags":[
        "director"
    ],
    "wof:name":"Evans & Miller Funeral Home",
    "wof:placetype":"venue"
},
  "geometry": {"coordinates":[-94.47810200000001,35.259599],"type":"Point"}
}