{
  "type": "Feature",
  "properties": {
    "iso:country":"US",
    "sg:address":"2605 Highway 135 N",
    "sg:city":"Paragould",
    "sg:classifiers":[
        {
            "category":"Manufacturing",
            "subcategory":"Buildings",
            "type":"Manufacturing & Wholesale Goods"
        },
        {
            "category":"Building & Trades",
            "subcategory":"Construction",
            "type":"Services"
        }
    ],
    "sg:phone":"+1 870 236 7159",
    "sg:postcode":"72450",
    "sg:province":"AR",
    "sg:tags":[
        "home",
        "builder",
        "contractor"
    ],
    "wof:name":"George Spence Const",
    "wof:placetype":"venue"
},
  "geometry": {"coordinates":[-90.502505,36.091794],"type":"Point"}
}