{
  "type": "Feature",
  "properties": {
    "addr:full":"114 Hwy 286 E Conway AR 72032",
    "addr:housenumber":"114",
    "addr:postcode":"72032",
    "addr:street":"Hwy 286 E",
    "iso:country":"US",
    "sg:address":"114 Hwy 286 E",
    "sg:city":"Conway",
    "sg:classifiers":[
        {
            "category":"Organizations",
            "subcategory":"Labor Organization",
            "type":"Services"
        }
    ],
    "sg:phone":"+1 501 327 2510",
    "sg:postcode":"72032",
    "sg:province":"AR",
    "wof:name":"UAW Local 1762",
    "wof:placetype":"venue"
},
  "geometry": {"coordinates":[-92.396029,35.066067],"type":"Point"}
}