{
  "type": "Feature",
  "properties": {
    "iso:country":"US",
    "sg:address":"616 Euclid St",
    "sg:city":"Texarkana",
    "sg:classifiers":[
        {
            "category":"Recreation",
            "type":"Entertainment"
        }
    ],
    "sg:phone":"+1 870 772 8856",
    "sg:postcode":"71854",
    "sg:province":"TX",
    "sg:tags":[
        "center"
    ],
    "wof:name":"Vera Bradfield Ctr",
    "wof:placetype":"venue"
},
  "geometry": {"coordinates":[-94.037003,33.405591],"type":"Point"}
}