{
  "type": "Feature",
  "properties": {
    "iso:country":"US",
    "sg:address":"12287 N Old Cincinnati Rd",
    "sg:city":"Summers",
    "sg:classifiers":[
        {
            "category":"Farming",
            "subcategory":"Dairy Farm",
            "type":"Manufacturing & Wholesale Goods"
        }
    ],
    "sg:phone":"+1 479 824 4087",
    "sg:postcode":"72769",
    "sg:province":"AR",
    "wof:name":"Jackson Dairy",
    "wof:placetype":"venue"
},
  "geometry": {"coordinates":[-94.50513599999999,36.029225],"type":"Point"}
}