{
  "type": "Feature",
  "properties": {
    "iso:country":"US",
    "sg:address":"450 Hopper Ridge Rd",
    "sg:city":"Redfield",
    "sg:classifiers":[
        {
            "category":"Building & Trades",
            "subcategory":"Construction",
            "type":"Services"
        }
    ],
    "sg:phone":"+1 501 397 5077",
    "sg:postcode":"72132",
    "sg:province":"AR",
    "sg:tags":[
        "general",
        "contractor"
    ],
    "wof:name":"SCA Bass Construction Inc",
    "wof:placetype":"venue"
},
  "geometry": {"coordinates":[-92.23435600000001,34.464631],"type":"Point"}
}