{
  "type": "Feature",
  "properties": {
    "iso:country":"US",
    "sg:address":"1302 Stratford Dr",
    "sg:city":"West Memphis",
    "sg:classifiers":[
        {
            "category":"Insurance",
            "subcategory":"Hazard Insurance",
            "type":"Services"
        }
    ],
    "sg:phone":"+1 870 732 8727",
    "sg:postcode":"72301",
    "sg:province":"AR",
    "sg:tags":[
        "bond"
    ],
    "wof:name":"A 1 Bail Bond Co",
    "wof:placetype":"venue"
},
  "geometry": {"coordinates":[-90.211868,35.156675],"type":"Point"}
}