{
  "type": "Feature",
  "properties": {
    "iso:country":"US",
    "sg:address":"118 E Church Ave",
    "sg:city":"Berryville",
    "sg:classifiers":[
        {
            "category":"Education",
            "subcategory":"Special Training",
            "type":"Public Place"
        }
    ],
    "sg:phone":"+1 870 423 4500",
    "sg:postcode":"72616",
    "sg:province":"AR",
    "sg:tags":[
        "reading",
        "instruction",
        "improvement"
    ],
    "wof:name":"Carroll County Literacy Cncl",
    "wof:placetype":"venue"
},
  "geometry": {"coordinates":[-93.56625699999999,36.365454],"type":"Point"}
}