{
  "type": "Feature",
  "properties": {
    "addr:full":"611 Dream Valley Rd Rogers AR 72756",
    "addr:housenumber":"611",
    "addr:postcode":"72756",
    "addr:street":"Dream Valley Rd",
    "iso:country":"US",
    "sg:address":"611 Dream Valley Rd",
    "sg:city":"Rogers",
    "sg:classifiers":[
        {
            "category":"Professional",
            "subcategory":"Testing Lab",
            "type":"Services"
        }
    ],
    "sg:phone":"+1 479 636 8782",
    "sg:postcode":"72756",
    "sg:province":"AR",
    "sg:tags":[
        "laboratory",
        "product",
        "consumer"
    ],
    "wof:name":"Consumer Testing Laboratories",
    "wof:placetype":"venue"
},
  "geometry": {"coordinates":[-94.085877,36.342304],"type":"Point"}
}