{
  "type": "Feature",
  "properties": {
    "addr:full":"301 W 16th St Hope AR 71801",
    "addr:housenumber":"301",
    "addr:postcode":"71801",
    "addr:street":"W 16Th St",
    "iso:country":"US",
    "sg:address":"301 W 16th St",
    "sg:city":"Hope",
    "sg:classifiers":[
        {
            "category":"Professional",
            "subcategory":"Lawyer & Legal Services",
            "type":"Services"
        }
    ],
    "sg:phone":"+1 870 777 0900",
    "sg:postcode":"71801",
    "sg:province":"AR",
    "sg:tags":[
        "governmental",
        "law",
        "administrative",
        "attorney"
    ],
    "wof:name":"8th North Judicial District",
    "wof:placetype":"venue"
},
  "geometry": {"coordinates":[-93.58953099999999,33.653839],"type":"Point"}
}