{
  "type": "Feature",
  "properties": {
    "addr:full":"308 W Broadway West Memphis AR 72301",
    "addr:housenumber":"308",
    "addr:postcode":"72301",
    "addr:street":"W Broadway",
    "iso:country":"US",
    "sg:address":"308 W Broadway",
    "sg:city":"West Memphis",
    "sg:classifiers":[
        {
            "category":"Personal",
            "type":"Services"
        }
    ],
    "sg:phone":"+1 870 732 8871",
    "sg:postcode":"72301",
    "sg:province":"AR",
    "sg:tags":[
        "credit",
        "debt",
        "counseling"
    ],
    "wof:name":"Credit Doctor",
    "wof:placetype":"venue"
},
  "geometry": {"coordinates":[-90.19097499999999,35.146439],"type":"Point"}
}