{
  "type": "Feature",
  "properties": {
    "iso:country":"US",
    "sg:address":"23 S Poplar St",
    "sg:city":"Marianna",
    "sg:classifiers":[
        {
            "category":"Personal",
            "subcategory":"Shoe Repair & Shine",
            "type":"Services"
        },
        {
            "category":"Home & Garden",
            "subcategory":"Furniture",
            "type":"Retail Goods"
        }
    ],
    "sg:phone":"+1 870 295 4600",
    "sg:postcode":"72360",
    "sg:province":"AR",
    "sg:tags":[
        "repairing",
        "television",
        "boot",
        "appliance",
        "stereo",
        "sh"
    ],
    "wof:name":"Smith's Shoe Store & Repair",
    "wof:placetype":"venue"
},
  "geometry": {"coordinates":[-90.75746,34.773115],"type":"Point"}
}