{
  "type": "Feature",
  "properties": {
    "addr:full":"875 S Dogwood St Siloam Springs OK 72761",
    "addr:housenumber":"875",
    "addr:postcode":"72761",
    "addr:street":"S Dogwood St",
    "iso:country":"US",
    "sg:address":"875 S Dogwood St",
    "sg:city":"Siloam Springs",
    "sg:classifiers":[
        {
            "category":"Retail",
            "subcategory":"Auto Repair",
            "type":"Services"
        }
    ],
    "sg:phone":"+1 479 524 8774",
    "sg:postcode":"72761",
    "sg:province":"OK",
    "sg:tags":[
        "automobile",
        "lubrication"
    ],
    "wof:name":"Speed Lube",
    "wof:placetype":"venue"
},
  "geometry": {"coordinates":[-94.555082,36.176549],"type":"Point"}
}