{
  "type": "Feature",
  "properties": {
    "iso:country":"US",
    "sg:address":"5800 Baucum Pike",
    "sg:city":"N Little Rock",
    "sg:classifiers":[
        {
            "category":"Professional",
            "subcategory":"Business Services",
            "type":"Services"
        }
    ],
    "sg:phone":"+1 501 945 7874",
    "sg:postcode":"72117",
    "sg:province":"AR",
    "sg:tags":[
        "auctioneer"
    ],
    "wof:name":"Wayne M Ball Auction & Realty",
    "wof:placetype":"venue"
},
  "geometry": {"coordinates":[-92.198534,34.746064],"type":"Point"}
}