{
  "type": "Feature",
  "properties": {
    "iso:country":"US",
    "sg:address":"1820 Matt Ln",
    "sg:city":"Hensley",
    "sg:classifiers":[
        {
            "category":"Retail",
            "subcategory":"Repair Shop",
            "type":"Services"
        }
    ],
    "sg:phone":"+1 501 888 6339",
    "sg:postcode":"72065",
    "sg:province":"AR",
    "sg:tags":[
        "equipment",
        "telephone",
        "system"
    ],
    "wof:name":"B & D Communications",
    "wof:placetype":"venue"
},
  "geometry": {"coordinates":[-92.26440599999999,34.555624],"type":"Point"}
}