{
  "type": "Feature",
  "properties": {
    "iso:country":"US",
    "sg:address":"229 W 18th St",
    "sg:city":"Smackover",
    "sg:classifiers":[
        {
            "category":"Organizations",
            "subcategory":"Religious Organization",
            "type":"Services"
        }
    ],
    "sg:phone":"+1 870 725 3800",
    "sg:postcode":"71762",
    "sg:province":"AR",
    "wof:name":"Abundant Life Ministries",
    "wof:placetype":"venue"
},
  "geometry": {"coordinates":[-92.733682,33.349177],"type":"Point"}
}