{
  "type": "Feature",
  "properties": {
    "iso:country":"US",
    "sg:address":"149 Springhill Trl",
    "sg:city":"Hot Springs Vlg",
    "sg:classifiers":[
        {
            "category":"Personal",
            "subcategory":"Beauty Salon",
            "type":"Services"
        }
    ],
    "sg:phone":"+1 501 624 0072",
    "sg:postcode":"71909",
    "sg:province":"AR",
    "wof:name":"New Life Hair Styling",
    "wof:placetype":"venue"
},
  "geometry": {"coordinates":[-93.024351,34.616661],"type":"Point"}
}