{
  "type": "Feature",
  "properties": {
    "addr:full":"603 W Church Ave Berryville AR 72616",
    "addr:housenumber":"603",
    "addr:postcode":"72616",
    "addr:street":"W Church Ave",
    "iso:country":"US",
    "sg:address":"603 W Church Ave",
    "sg:city":"Berryville",
    "sg:classifiers":[
        {
            "category":"Manufacturing",
            "subcategory":"Signs",
            "type":"Manufacturing & Wholesale Goods"
        }
    ],
    "sg:phone":"+1 870 423 6423",
    "sg:postcode":"72616",
    "sg:province":"AR",
    "sg:tags":[
        "specialty",
        "mfg"
    ],
    "wof:name":"Kennett Signs",
    "wof:placetype":"venue"
},
  "geometry": {"coordinates":[-93.572603,36.364256],"type":"Point"}
}