{
  "type": "Feature",
  "properties": {
    "iso:country":"US",
    "sg:address":"18 Cyrus Rex Rd",
    "sg:city":"Rogers",
    "sg:classifiers":[
        {
            "category":"Building & Trades",
            "subcategory":"Cleaning & Sanitation",
            "type":"Services"
        },
        {
            "category":"Shopping",
            "subcategory":"Crafts & Fabrics",
            "type":"Retail Goods"
        },
        {
            "category":"Military Area",
            "subcategory":"Armory",
            "type":"Public Place"
        },
        {
            "category":"Building & Trades",
            "subcategory":"Construction",
            "type":"Services"
        }
    ],
    "sg:phone":"+1 479 925 2222",
    "sg:postcode":"72756",
    "sg:province":"AR",
    "sg:tags":[
        "repair",
        "industrial",
        "fence",
        "deck",
        "builder",
        "contractor",
        "treatment",
        "cleaning-commercial",
        "fence-sales"
    ],
    "sg:website":"http://www.deckworksnaw.com",
    "wof:name":"Deck Works",
    "wof:placetype":"venue"
},
  "geometry": {"coordinates":[-93.99702600000001,36.346223],"type":"Point"}
}