{
  "type": "Feature",
  "properties": {
    "iso:country":"US",
    "sg:address":"4701 Memorial Dr",
    "sg:city":"Blytheville",
    "sg:classifiers":[
        {
            "category":"Social Services",
            "type":"Services"
        },
        {
            "category":"Place Of Worship",
            "subcategory":"Church",
            "type":"Public Place"
        },
        {
            "category":"Place Of Worship",
            "type":"Public Place"
        }
    ],
    "sg:phone":"+1 870 532 6788",
    "sg:postcode":"72315",
    "sg:province":"AR",
    "sg:tags":[
        "churches-interdenominational",
        "churches-various",
        "denomination"
    ],
    "wof:name":"South Mississippi County United Way Inc",
    "wof:placetype":"venue"
},
  "geometry": {"coordinates":[-89.963882,35.959209],"type":"Point"}
}