{
  "type": "Feature",
  "properties": {
    "iso:country":"US",
    "sg:address":"1600 W Kingshighway",
    "sg:city":"Paragould",
    "sg:classifiers":[
        {
            "category":"Fast Food",
            "type":"Food & Drink"
        },
        {
            "category":"Restaurant",
            "type":"Food & Drink"
        }
    ],
    "sg:phone":"+1 870 239 3772",
    "sg:postcode":"72450",
    "sg:province":"AR",
    "sg:tags":[
        "asian",
        "chinese",
        "pan"
    ],
    "wof:name":"Hunan Chinese Restaurant",
    "wof:placetype":"venue"
},
  "geometry": {"coordinates":[-90.505998,36.052771],"type":"Point"}
}