{
  "type": "Feature",
  "properties": {
    "iso:country":"US",
    "sg:address":"615 E Washington Ave",
    "sg:city":"Jonesboro",
    "sg:classifiers":[
        {
            "category":"Social Services",
            "subcategory":"Child Care",
            "type":"Services"
        }
    ],
    "sg:phone":"+1 870 935 3917",
    "sg:postcode":"72401",
    "sg:province":"AR",
    "wof:name":"CRDC Head Start Child Devmnt",
    "wof:placetype":"venue"
},
  "geometry": {"coordinates":[-90.698378,35.83827],"type":"Point"}
}