{
  "type": "Feature",
  "properties": {
    "iso:country":"US",
    "sg:address":"800 S Main St",
    "sg:city":"Brinkley",
    "sg:classifiers":[
        {
            "category":"Education",
            "subcategory":"School",
            "type":"Public Place"
        }
    ],
    "sg:phone":"+1 870 734 5000",
    "sg:postcode":"72021",
    "sg:province":"AR",
    "wof:name":"Brinkley Public Schools Supt",
    "wof:placetype":"venue"
},
  "geometry": {"coordinates":[-91.194665,34.877808],"type":"Point"}
}