{
  "type": "Feature",
  "properties": {
    "iso:country":"US",
    "sg:address":"3413 Hwy 270 W",
    "sg:city":"Sheridan",
    "sg:classifiers":[
        {
            "category":"Personal",
            "subcategory":"Beauty Salon",
            "type":"Services"
        }
    ],
    "sg:phone":"+1 870 942 2511",
    "sg:postcode":"72150",
    "sg:province":"AR",
    "wof:name":"Gennies Family Hair Care",
    "wof:placetype":"venue"
},
  "geometry": {"coordinates":[-92.451842,34.311396],"type":"Point"}
}