{
  "type": "Feature",
  "properties": {
    "iso:country":"US",
    "sg:address":"148 W Main St",
    "sg:city":"Batesville",
    "sg:classifiers":[
        {
            "category":"Shopping",
            "subcategory":"Discount & Variety Stores",
            "type":"Retail Goods"
        }
    ],
    "sg:phone":"+1 870 793 2130",
    "sg:postcode":"72501",
    "sg:province":"AR",
    "sg:tags":[
        "merchandise",
        "general"
    ],
    "wof:name":"Tienda LA Illusion",
    "wof:placetype":"venue"
},
  "geometry": {"coordinates":[-91.654669,35.769607],"type":"Point"}
}