{
  "type": "Feature",
  "properties": {
    "iso:country":"US",
    "sg:address":"427 W Tanner Dr",
    "sg:city":"Fayetteville",
    "sg:classifiers":[
        {
            "category":"Professional",
            "subcategory":"Art Services",
            "type":"Services"
        }
    ],
    "sg:phone":"+1 479 521 3224",
    "sg:postcode":"72701",
    "sg:province":"AR",
    "sg:tags":[
        "photography",
        "commercial"
    ],
    "wof:name":"Photos By Tish",
    "wof:placetype":"venue"
},
  "geometry": {"coordinates":[-94.180539,35.995215],"type":"Point"}
}