{
  "type": "Feature",
  "properties": {
    "iso:country":"US",
    "sg:address":"26 Looper Rd",
    "sg:city":"North Little Rock",
    "sg:classifiers":[
        {
            "category":"Shopping",
            "subcategory":"Computers & Home Electronics",
            "type":"Retail Goods"
        }
    ],
    "sg:phone":"+1 501 376 7104",
    "sg:postcode":"72120",
    "sg:province":"AR",
    "wof:name":"APS Wireless",
    "wof:placetype":"venue"
},
  "geometry": {"coordinates":[-92.234195,34.836635],"type":"Point"}
}