{
  "type": "Feature",
  "properties": {
    "iso:country":"US",
    "sg:address":"8711 Pinnacle Valley Rd",
    "sg:city":"Little Rock",
    "sg:classifiers":[
        {
            "category":"Freight",
            "type":"Transportation"
        }
    ],
    "sg:phone":"+1 501 868 5987",
    "sg:postcode":"72223",
    "sg:province":"AR",
    "sg:tags":[
        "operator",
        "local",
        "trucking"
    ],
    "wof:name":"Ready Hauling Inc",
    "wof:placetype":"venue"
},
  "geometry": {"coordinates":[-92.435794,34.827297],"type":"Point"}
}