{
  "type": "Feature",
  "properties": {
    "iso:country":"US",
    "sg:address":"104 N Starr Ave",
    "sg:city":"Lincoln",
    "sg:classifiers":[
        {
            "category":"Retail",
            "subcategory":"Auto Repair",
            "type":"Services"
        }
    ],
    "sg:phone":"+1 479 824 3671",
    "sg:postcode":"72744",
    "sg:province":"AR",
    "sg:tags":[
        "body",
        "automobile",
        "top",
        "upholstery"
    ],
    "wof:name":"Wright's Auto Upholstery",
    "wof:placetype":"venue"
},
  "geometry": {"coordinates":[-94.424426,35.951593],"type":"Point"}
}