{
  "type": "Feature",
  "properties": {
    "addr:full":"1087 Halleck Ln Pea Ridge AR 72751",
    "addr:housenumber":"1087",
    "addr:postcode":"72751",
    "addr:street":"Halleck Ln",
    "iso:country":"US",
    "sg:address":"1087 Halleck Ln",
    "sg:city":"Pea Ridge",
    "sg:classifiers":[
        {
            "category":"Home & Garden",
            "subcategory":"Building Materials",
            "type":"Retail Goods"
        }
    ],
    "sg:phone":"+1 479 451 1905",
    "sg:postcode":"72751",
    "sg:province":"AR",
    "sg:tags":[
        "glass",
        "leaded"
    ],
    "wof:name":"Zadock's Stained Glass",
    "wof:placetype":"venue"
},
  "geometry": {"coordinates":[-94.12464,36.432362],"type":"Point"}
}