{
  "type": "Feature",
  "properties": {
    "iso:country":"US",
    "sg:address":"704 E Church St",
    "sg:city":"Morrilton",
    "sg:classifiers":[
        {
            "category":"Education",
            "subcategory":"School",
            "type":"Public Place"
        }
    ],
    "sg:phone":"+1 501 354 9400",
    "sg:postcode":"72110",
    "sg:province":"AR",
    "wof:name":"South Conway County Supt",
    "wof:placetype":"venue"
},
  "geometry": {"coordinates":[-92.736334,35.149643],"type":"Point"}
}