{
  "type": "Feature",
  "properties": {
    "iso:country":"US",
    "sg:address":"8411 Ferndale Cut Off Rd",
    "sg:city":"Little Rock",
    "sg:classifiers":[
        {
            "category":"Building & Trades",
            "subcategory":"Landscaping Services",
            "type":"Services"
        }
    ],
    "sg:phone":"+1 501 868 9070",
    "sg:postcode":"72223",
    "sg:province":"AR",
    "wof:name":"Morris David Landscaping",
    "wof:placetype":"venue"
},
  "geometry": {"coordinates":[-92.524056,34.816411],"type":"Point"}
}