{
  "type": "Feature",
  "properties": {
    "iso:country":"US",
    "sg:address":"2221 Westover Dr",
    "sg:city":"Little Rock",
    "sg:classifiers":[
        {
            "category":"Professional",
            "subcategory":"Lawyer & Legal Services",
            "type":"Services"
        }
    ],
    "sg:phone":"+1 501 280 9104",
    "sg:postcode":"72207",
    "sg:province":"AR",
    "sg:tags":[
        "attorney"
    ],
    "wof:name":"David A Orsini",
    "wof:placetype":"venue"
},
  "geometry": {"coordinates":[-92.34876199999999,34.773395],"type":"Point"}
}