{
  "type": "Feature",
  "properties": {
    "iso:country":"US",
    "sg:address":"3100 N Albert Pike Ave",
    "sg:city":"Fort Smith",
    "sg:classifiers":[
        {
            "category":"Shopping",
            "subcategory":"Florist",
            "type":"Retail Goods"
        }
    ],
    "sg:phone":"+1 479 783 5880",
    "sg:postcode":"72904",
    "sg:province":"AR",
    "wof:name":"Trishas Florals Creation",
    "wof:placetype":"venue"
},
  "geometry": {"coordinates":[-94.38472,35.410207],"type":"Point"}
}