{
  "type": "Feature",
  "properties": {
    "addr:full":"18516 Winn Creek Rd Winslow AR 72959",
    "addr:housenumber":"18516",
    "addr:postcode":"72959",
    "addr:street":"Winn Creek Rd",
    "iso:country":"US",
    "sg:address":"18516 Winn Creek Rd",
    "sg:city":"Winslow",
    "sg:classifiers":[
        {
            "category":"Building & Trades",
            "subcategory":"Construction",
            "type":"Services"
        }
    ],
    "sg:phone":"+1 479 839 3591",
    "sg:postcode":"72959",
    "sg:province":"AR",
    "sg:tags":[
        "house",
        "contractor"
    ],
    "wof:name":"Rennie Construction",
    "wof:placetype":"venue"
},
  "geometry": {"coordinates":[-94.19226500000001,35.82485],"type":"Point"}
}