{
  "type": "Feature",
  "properties": {
    "addr:full":"1391 State Hwy 136 Osceola AR 72370",
    "addr:housenumber":"1391",
    "addr:postcode":"72370",
    "addr:street":"State Hwy 136",
    "iso:country":"US",
    "sg:address":"1391 State Hwy 136",
    "sg:city":"Osceola",
    "sg:classifiers":[
        {
            "category":"Shopping",
            "subcategory":"Used Merchandise",
            "type":"Retail Goods"
        }
    ],
    "sg:phone":"+1 870 531 2110",
    "sg:postcode":"72370",
    "sg:province":"AR",
    "sg:tags":[
        "antique"
    ],
    "wof:name":"Wildwood Antiques Inc",
    "wof:placetype":"venue"
},
  "geometry": {"coordinates":[-90.24103599999999,35.710231],"type":"Point"}
}