{
  "type": "Feature",
  "properties": {
    "iso:country":"US",
    "sg:address":"556 Robin Hood Ct",
    "sg:city":"Springdale",
    "sg:classifiers":[
        {
            "category":"Place Of Worship",
            "type":"Public Place"
        }
    ],
    "sg:phone":"+1 479 872 2338",
    "sg:postcode":"72764",
    "sg:province":"AR",
    "sg:tags":[
        "church"
    ],
    "wof:name":"Trinity Temple A G Church",
    "wof:placetype":"venue"
},
  "geometry": {"coordinates":[-94.138881,36.156877],"type":"Point"}
}