{
  "type": "Feature",
  "properties": {
    "iso:country":"US",
    "sg:address":"3190 E Van Buren",
    "sg:city":"Eureka Springs",
    "sg:classifiers":[
        {
            "category":"Utilities",
            "subcategory":"Refuse",
            "type":"Services"
        }
    ],
    "sg:phone":"+1 479 253 7773",
    "sg:postcode":"72616",
    "sg:province":"AR",
    "sg:tags":[
        "system"
    ],
    "wof:name":"Eureka Springs Recycling Dept",
    "wof:placetype":"venue"
},
  "geometry": {"coordinates":[-93.65049,36.397936],"type":"Point"}
}