{
  "type": "Feature",
  "properties": {
    "addr:full":"137 Malvern Rd Arkadelphia AR 71923",
    "addr:housenumber":"137",
    "addr:postcode":"71923",
    "addr:street":"Malvern Rd",
    "iso:country":"US",
    "sg:address":"137 Malvern Rd",
    "sg:city":"Arkadelphia",
    "sg:classifiers":[
        {
            "category":"Government",
            "subcategory":"Fire Station",
            "type":"Public Place"
        }
    ],
    "sg:phone":"+1 870 246 3216",
    "sg:postcode":"71923",
    "sg:province":"AR",
    "sg:tags":[
        "company",
        "volunteer"
    ],
    "wof:name":"Fire Department",
    "wof:placetype":"venue"
},
  "geometry": {"coordinates":[-93.064183,34.185368],"type":"Point"}
}