{
  "type": "Feature",
  "properties": {
    "iso:country":"US",
    "sg:address":"14623 Cedar Heights Rd",
    "sg:city":"N Little Rock",
    "sg:classifiers":[
        {
            "category":"Building & Trades",
            "subcategory":"Construction",
            "type":"Services"
        }
    ],
    "sg:phone":"+1 501 851 8580",
    "sg:postcode":"72118",
    "sg:province":"AR",
    "sg:tags":[
        "excavation",
        "excavating",
        "contractor"
    ],
    "wof:name":"Dirt Works of Arkansas",
    "wof:placetype":"venue"
},
  "geometry": {"coordinates":[-92.359319,34.887668],"type":"Point"}
}