{
  "type": "Feature",
  "properties": {
    "addr:full":"1507 W Center St Bald Knob AR 72010",
    "addr:housenumber":"1507",
    "addr:postcode":"72010",
    "addr:street":"W Center St",
    "iso:country":"US",
    "sg:address":"1507 W Center St",
    "sg:city":"Bald Knob",
    "sg:classifiers":[
        {
            "category":"Organizations",
            "subcategory":"Religious Organization",
            "type":"Services"
        }
    ],
    "sg:phone":"+1 501 724 5316",
    "sg:postcode":"72010",
    "sg:province":"AR",
    "sg:tags":[
        "church"
    ],
    "wof:name":"Central Baptist Church",
    "wof:placetype":"venue"
},
  "geometry": {"coordinates":[-91.58481399999999,35.311277],"type":"Point"}
}