{
  "type": "Feature",
  "properties": {
    "iso:country":"US",
    "sg:address":"1308 Zero St",
    "sg:city":"Fort Smith",
    "sg:classifiers":[
        {
            "category":"Building & Trades",
            "subcategory":"Landscaping Services",
            "type":"Services"
        }
    ],
    "sg:phone":"+1 479 442 0007",
    "sg:postcode":"72908",
    "sg:province":"AR",
    "sg:tags":[
        "spraying"
    ],
    "wof:name":"Tri-Hill Turf Care",
    "wof:placetype":"venue"
},
  "geometry": {"coordinates":[-94.418212,35.327971],"type":"Point"}
}