{
  "type": "Feature",
  "properties": {
    "iso:country":"US",
    "sg:address":"1497 US Hwy 49",
    "sg:city":"Rector",
    "sg:classifiers":[
        {
            "category":"Retail",
            "subcategory":"Auto Repair",
            "type":"Services"
        }
    ],
    "sg:phone":"+1 870 595 3388",
    "sg:postcode":"72461",
    "sg:province":"AR",
    "sg:tags":[
        "glass",
        "replacement",
        "contractor"
    ],
    "wof:name":"Clay County Glass Co",
    "wof:placetype":"venue"
},
  "geometry": {"coordinates":[-90.261586,36.259214],"type":"Point"}
}