{
  "type": "Feature",
  "properties": {
    "addr:full":"443 State Rte 247 Russellville AR 72802",
    "addr:housenumber":"443",
    "addr:postcode":"72802",
    "addr:street":"State Rte 247",
    "iso:country":"US",
    "sg:address":"443 State Rte 247",
    "sg:city":"Russellville",
    "sg:classifiers":[
        {
            "category":"Freight",
            "type":"Transportation"
        }
    ],
    "sg:phone":"+1 479 890 5007",
    "sg:postcode":"72802",
    "sg:province":"AR",
    "sg:tags":[
        "special"
    ],
    "wof:name":"Truck-R-Parts",
    "wof:placetype":"venue"
},
  "geometry": {"coordinates":[-93.13728500000001,35.227852],"type":"Point"}
}