{
  "type": "Feature",
  "properties": {
    "iso:country":"US",
    "sg:address":"2300 E Harding Ave",
    "sg:city":"Pine Bluff",
    "sg:classifiers":[
        {
            "category":"Local Transit",
            "type":"Transportation"
        }
    ],
    "sg:phone":"+1 870 543 5130",
    "sg:postcode":"71601",
    "sg:province":"AR",
    "sg:tags":[
        "bus",
        "line"
    ],
    "wof:name":"Pine Bluff Transit",
    "wof:placetype":"venue"
},
  "geometry": {"coordinates":[-91.978905,34.213047],"type":"Point"}
}