{
  "type": "Feature",
  "properties": {
    "addr:full":"9438 Hwy 62 W Imboden AR 72434",
    "addr:housenumber":"9438",
    "addr:postcode":"72434",
    "addr:street":"Hwy 62 W",
    "iso:country":"US",
    "sg:address":"9438 Hwy 62 W",
    "sg:city":"Imboden",
    "sg:classifiers":[
        {
            "category":"Building & Trades",
            "subcategory":"Construction",
            "type":"Services"
        }
    ],
    "sg:phone":"+1 870 869 1055",
    "sg:postcode":"72434",
    "sg:province":"AR",
    "sg:tags":[
        "masonry",
        "contractor"
    ],
    "wof:name":"Two Rivers Stone",
    "wof:placetype":"venue"
},
  "geometry": {"coordinates":[-91.117204,36.23619],"type":"Point"}
}