{
  "type": "Feature",
  "properties": {
    "iso:country":"US",
    "sg:address":"10715 US Hwy 64 W",
    "sg:city":"London",
    "sg:classifiers":[
        {
            "category":"Shopping",
            "type":"Retail Goods"
        }
    ],
    "sg:phone":"+1 479 293 4405",
    "sg:postcode":"72847",
    "sg:province":"AR",
    "sg:tags":[
        "merchandise"
    ],
    "wof:name":"London Auction Barn",
    "wof:placetype":"venue"
},
  "geometry": {"coordinates":[-93.26032600000001,35.331382],"type":"Point"}
}