{
  "type": "Feature",
  "properties": {
    "addr:full":"105 W B St Russellville AR 72801",
    "addr:housenumber":"105",
    "addr:postcode":"72801",
    "addr:street":"W B St",
    "iso:country":"US",
    "sg:address":"105 W B St",
    "sg:city":"Russellville",
    "sg:classifiers":[
        {
            "category":"Government",
            "subcategory":"Office",
            "type":"Public Place"
        }
    ],
    "sg:phone":"+1 479 968 7098",
    "sg:postcode":"72801",
    "sg:province":"AR",
    "wof:name":"Pope Cooperative Extension Svc",
    "wof:placetype":"venue"
},
  "geometry": {"coordinates":[-93.134969,35.279231],"type":"Point"}
}