{
  "type": "Feature",
  "properties": {
    "iso:country":"US",
    "sg:address":"920 Highway 62 Spur",
    "sg:city":"Berryville",
    "sg:classifiers":[
        {
            "category":"Utilities",
            "subcategory":"Electric",
            "type":"Services"
        },
        {
            "category":"Manufacturing",
            "subcategory":"Electronics",
            "type":"Manufacturing & Wholesale Goods"
        }
    ],
    "sg:phone":"+1 479 738 2217",
    "sg:postcode":"72616",
    "sg:province":"AR",
    "sg:tags":[
        "equipment-testing"
    ],
    "sg:website":"http://www.carrollecc.com",
    "wof:name":"Carroll Electric Cooperative Corporation",
    "wof:placetype":"venue"
},
  "geometry": {"coordinates":[-93.595843,36.382063],"type":"Point"}
}