{
  "type": "Feature",
  "properties": {
    "iso:country":"US",
    "sg:address":"1214 US Hwy 49",
    "sg:city":"Brinkley",
    "sg:classifiers":[
        {
            "category":"Health Services",
            "subcategory":"Nursing And Care Facility",
            "type":"Services"
        }
    ],
    "sg:phone":"+1 870 734 3636",
    "sg:postcode":"72021",
    "sg:province":"AR",
    "sg:tags":[
        "home",
        "convalescent"
    ],
    "wof:name":"Cla-Cliff Nursing & Rehab",
    "wof:placetype":"venue"
},
  "geometry": {"coordinates":[-91.198116,34.904824],"type":"Point"}
}