{
  "type": "Feature",
  "properties": {
    "addr:full":"550 S Main St Bald Knob AR 72010",
    "addr:housenumber":"550",
    "addr:postcode":"72010",
    "addr:street":"S Main St",
    "iso:country":"US",
    "sg:address":"550 S Main St",
    "sg:city":"Bald Knob",
    "sg:classifiers":[
        {
            "category":"Government",
            "subcategory":"Office",
            "type":"Public Place"
        }
    ],
    "sg:phone":"+1 501 724 6442",
    "sg:postcode":"72010",
    "sg:province":"AR",
    "sg:tags":[
        "village"
    ],
    "wof:name":"Bald Knob Water Filter Plant",
    "wof:placetype":"venue"
},
  "geometry": {"coordinates":[-91.56575100000001,35.308843],"type":"Point"}
}