{
  "type": "Feature",
  "properties": {
    "iso:country":"US",
    "sg:address":"3916 Robinwood Cir",
    "sg:city":"Bryant",
    "sg:classifiers":[
        {
            "category":"Banks & Credit Unions",
            "subcategory":"Investment Brokerage",
            "type":"Services"
        }
    ],
    "sg:phone":"+1 501 804 2404",
    "sg:postcode":"72022",
    "sg:province":"AR",
    "sg:tags":[
        "advisory"
    ],
    "wof:name":"Front Porch Investments",
    "wof:placetype":"venue"
},
  "geometry": {"coordinates":[-92.498397,34.630365],"type":"Point"}
}