{
  "type": "Feature",
  "properties": {
    "addr:full":"811 Hobson Ave Hot Springs AR 71913",
    "addr:housenumber":"811",
    "addr:postcode":"71913",
    "addr:street":"Hobson Ave",
    "iso:country":"US",
    "sg:address":"811 Hobson Ave",
    "sg:city":"Hot Springs",
    "sg:classifiers":[
        {
            "category":"Home & Garden",
            "subcategory":"Household Appliances",
            "type":"Retail Goods"
        }
    ],
    "sg:phone":"+1 501 321 4908",
    "sg:postcode":"71913",
    "sg:province":"AR",
    "sg:tags":[
        "cleaners",
        "vacuum"
    ],
    "wof:name":"Electrolux",
    "wof:placetype":"venue"
},
  "geometry": {"coordinates":[-93.06864,34.497978],"type":"Point"}
}