{
  "type": "Feature",
  "properties": {
    "iso:country":"US",
    "sg:address":"1202 Trimble Ave",
    "sg:city":"Berryville",
    "sg:classifiers":[
        {
            "category":"Autos & Motor Vehicles",
            "subcategory":"Automobile Sales",
            "type":"Retail Goods"
        }
    ],
    "sg:phone":"+1 870 423 2280",
    "sg:postcode":"72616",
    "sg:province":"AR",
    "sg:tags":[
        "dealers-used",
        "used",
        "cars-wholesale",
        "car"
    ],
    "sg:website":"http://www.car-mart.com",
    "wof:name":"Car-Mart",
    "wof:placetype":"venue"
},
  "geometry": {"coordinates":[-93.583012,36.376344],"type":"Point"}
}