{
  "type": "Feature",
  "properties": {
    "iso:country":"US",
    "sg:address":"908 S Walton Blvd",
    "sg:city":"Bentonville",
    "sg:classifiers":[
        {
            "category":"Shopping",
            "subcategory":"Clothing, Apparel, & Fashions",
            "type":"Retail Goods"
        }
    ],
    "sg:phone":"+1 479 464 0474",
    "sg:postcode":"72712",
    "sg:province":"AR",
    "wof:name":"Popsicle Playwear LTD",
    "wof:placetype":"venue"
},
  "geometry": {"coordinates":[-94.21739,36.361841],"type":"Point"}
}