{
  "type": "Feature",
  "properties": {
    "iso:country":"US",
    "sg:address":"108 Celeste Dr",
    "sg:city":"Pearcy",
    "sg:classifiers":[
        {
            "category":"Professional",
            "type":"Services"
        }
    ],
    "sg:phone":"+1 501 767 1132",
    "sg:postcode":"71964",
    "sg:province":"AR",
    "wof:name":"Danny Vaughn",
    "wof:placetype":"venue"
},
  "geometry": {"coordinates":[-93.195666,34.438656],"type":"Point"}
}