{
  "type": "Feature",
  "properties": {
    "iso:country":"US",
    "sg:address":"7724 Landers Rd",
    "sg:city":"North Little Rock",
    "sg:classifiers":[
        {
            "category":"Real Estate",
            "subcategory":"Developer",
            "type":"Services"
        }
    ],
    "sg:phone":"+1 501 835 3515",
    "sg:postcode":"72117",
    "sg:province":"AR",
    "sg:tags":[
        "funeral",
        "cemetery"
    ],
    "wof:name":"Rest Hills Funeral HM & Mem Pk",
    "wof:placetype":"venue"
},
  "geometry": {"coordinates":[-92.19213,34.825138],"type":"Point"}
}