{
  "type": "Feature",
  "properties": {
    "iso:country":"US",
    "sg:address":"623 W Stillwell Ave",
    "sg:city":"De Queen",
    "sg:classifiers":[
        {
            "category":"Organizations",
            "subcategory":"Religious Organization",
            "type":"Services"
        }
    ],
    "sg:phone":"+1 870 642 8487",
    "sg:postcode":"71832",
    "sg:province":"AR",
    "sg:tags":[
        "monastery",
        "convent"
    ],
    "wof:name":"St Barbara's Convent",
    "wof:placetype":"venue"
},
  "geometry": {"coordinates":[-94.344819,34.036646],"type":"Point"}
}