{
  "type": "Feature",
  "properties": {
    "iso:country":"US",
    "sg:address":"7619 John Harden Dr",
    "sg:city":"Jacksonville",
    "sg:classifiers":[
        {
            "category":"Organizations",
            "subcategory":"Community Association",
            "type":"Services"
        }
    ],
    "sg:phone":"+1 501 982 0091",
    "sg:postcode":"72023",
    "sg:province":"AR",
    "sg:tags":[
        "club"
    ],
    "wof:name":"Hollywood Country Club",
    "wof:placetype":"venue"
},
  "geometry": {"coordinates":[-92.080118,34.93317],"type":"Point"}
}