{
  "type": "Feature",
  "properties": {
    "addr:full":"102 N Main St England AR 72046",
    "addr:housenumber":"102",
    "addr:postcode":"72046",
    "addr:street":"N Main St",
    "iso:country":"US",
    "sg:address":"102 N Main St",
    "sg:city":"England",
    "sg:classifiers":[
        {
            "category":"Autos & Motor Vehicles",
            "subcategory":"Automobile Sales",
            "type":"Retail Goods"
        }
    ],
    "sg:phone":"+1 501 842 1136",
    "sg:postcode":"72046",
    "sg:province":"AR",
    "sg:tags":[
        "car",
        "dealer"
    ],
    "wof:name":"England Motors",
    "wof:placetype":"venue"
},
  "geometry": {"coordinates":[-91.970015,34.545869],"type":"Point"}
}