{
  "type": "Feature",
  "properties": {
    "iso:country":"US",
    "sg:address":"2035 Pleasant Valley Rd",
    "sg:city":"Van Buren",
    "sg:classifiers":[
        {
            "category":"Building & Trades",
            "subcategory":"Construction",
            "type":"Services"
        }
    ],
    "sg:phone":"+1 479 474 7995",
    "sg:postcode":"72956",
    "sg:province":"AR",
    "sg:tags":[
        "boring",
        "work",
        "tunneling",
        "contractor"
    ],
    "wof:name":"Main Construction Co",
    "wof:placetype":"venue"
},
  "geometry": {"coordinates":[-94.275249,35.465111],"type":"Point"}
}