{
  "type": "Feature",
  "properties": {
    "iso:country":"US",
    "sg:address":"3100 SE 14th St",
    "sg:city":"Bentonville",
    "sg:classifiers":[
        {
            "category":"Travel",
            "subcategory":"Hotels & Motels",
            "type":"Entertainment"
        }
    ],
    "sg:phone":"+1 479 621 0202",
    "sg:postcode":"72712",
    "sg:province":"AR",
    "sg:tags":[
        "hotels-apartment",
        "corporate",
        "lodging"
    ],
    "sg:website":"http://marriott.com/ROGTS",
    "wof:name":"TownePlace Suites by Marriott Bentonville Rogers",
    "wof:placetype":"venue"
},
  "geometry": {"coordinates":[-94.176147,36.356319],"type":"Point"}
}