{
  "type": "Feature",
  "properties": {
    "iso:country":"US",
    "sg:address":"8598 Junction City Hwy",
    "sg:city":"El Dorado",
    "sg:classifiers":[
        {
            "category":"Restaurant",
            "type":"Food & Drink"
        }
    ],
    "sg:phone":"+1 870 924 5107",
    "sg:postcode":"71730",
    "sg:province":"AR",
    "wof:name":"Ricthie's Family Dining",
    "wof:placetype":"venue"
},
  "geometry": {"coordinates":[-92.694835,33.061397],"type":"Point"}
}