{
  "type": "Feature",
  "properties": {
    "addr:full":"200 Kentucky St Caraway AR 72419",
    "addr:housenumber":"200",
    "addr:postcode":"72419",
    "addr:street":"Kentucky St",
    "iso:country":"US",
    "sg:address":"200 Kentucky St",
    "sg:city":"Caraway",
    "sg:classifiers":[
        {
            "category":"Retail",
            "subcategory":"Auto Repair",
            "type":"Services"
        }
    ],
    "sg:phone":"+1 870 482 3769",
    "sg:postcode":"72419",
    "sg:province":"AR",
    "sg:tags":[
        "body",
        "automobile",
        "painting",
        "repairing"
    ],
    "wof:name":"City Body Shop",
    "wof:placetype":"venue"
},
  "geometry": {"coordinates":[-90.32260100000001,35.760731],"type":"Point"}
}