{
  "type": "Feature",
  "properties": {
    "addr:full":"PO Box 278 Springdale AR 72765",
    "addr:housenumber":"po",
    "addr:postcode":"72765",
    "addr:street":"Box 278",
    "iso:country":"US",
    "sg:address":"PO Box 278",
    "sg:city":"Springdale",
    "sg:classifiers":[
        {
            "category":"Autos & Motor Vehicles",
            "subcategory":"Auto Supplies",
            "type":"Retail Goods"
        },
        {
            "category":"Retail",
            "subcategory":"Auto Repair",
            "type":"Services"
        }
    ],
    "sg:phone":"+1 479 361 2120",
    "sg:postcode":"72765",
    "sg:province":"AR",
    "sg:tags":[
        "tire"
    ],
    "wof:name":"Straightline Automotive Inc",
    "wof:placetype":"venue"
},
  "geometry": {"coordinates":[-94.131401,36.181702],"type":"Point"}
}