{
  "type": "Feature",
  "properties": {
    "iso:country":"US",
    "sg:address":"107 Elysian Hills Dr",
    "sg:city":"Hot Springs National Park",
    "sg:classifiers":[
        {
            "category":"Professional",
            "type":"Services"
        }
    ],
    "sg:phone":"+1 501 767 6323",
    "sg:postcode":"71913",
    "sg:province":"AR",
    "wof:name":"Sinclair Carlton",
    "wof:placetype":"venue"
},
  "geometry": {"coordinates":[-93.145872,34.436642],"type":"Point"}
}