{
  "type": "Feature",
  "properties": {
    "iso:country":"US",
    "sg:address":"327 Regal Oaks Cir",
    "sg:city":"White Hall",
    "sg:classifiers":[
        {
            "category":"Wholesale",
            "subcategory":"Vending Machines",
            "type":"Manufacturing & Wholesale Goods"
        }
    ],
    "sg:phone":"+1 870 247 0037",
    "sg:postcode":"71602",
    "sg:province":"AR",
    "sg:tags":[
        "operator"
    ],
    "wof:name":"Jacks Vending Service",
    "wof:placetype":"venue"
},
  "geometry": {"coordinates":[-92.08333,34.270624],"type":"Point"}
}