{
  "type": "Feature",
  "properties": {
    "iso:country":"US",
    "sg:address":"603 N Main St",
    "sg:city":"Nashville",
    "sg:classifiers":[
        {
            "category":"Organizations",
            "subcategory":"Community Association",
            "type":"Services"
        }
    ],
    "sg:phone":"+1 870 845 1914",
    "sg:postcode":"71852",
    "sg:province":"AR",
    "sg:tags":[
        "fraternal"
    ],
    "wof:name":"Pleasant Valley Lodge",
    "wof:placetype":"venue"
},
  "geometry": {"coordinates":[-93.846997,33.949588],"type":"Point"}
}