{
  "type": "Feature",
  "properties": {
    "iso:country":"US",
    "sg:address":"902 N Center St",
    "sg:city":"Lonoke",
    "sg:classifiers":[
        {
            "category":"Industrial Area",
            "type":"Public Place"
        }
    ],
    "sg:phone":"+1 501 676 2721",
    "sg:postcode":"72086",
    "sg:province":"AR",
    "sg:tags":[
        "development"
    ],
    "sg:website":"http://www.capdd.org",
    "wof:name":"Central Arkansas Planning And Development District, Inc.",
    "wof:placetype":"venue"
},
  "geometry": {"coordinates":[-91.899979,34.791017],"type":"Point"}
}