{
  "type": "Feature",
  "properties": {
    "addr:full":"300 Dallas Ave Mena AR 71953",
    "addr:housenumber":"300",
    "addr:postcode":"71953",
    "addr:street":"Dallas Ave",
    "iso:country":"US",
    "sg:address":"300 Dallas Ave",
    "sg:city":"Mena",
    "sg:classifiers":[
        {
            "category":"Organizations",
            "subcategory":"Religious Organization",
            "type":"Services"
        }
    ],
    "sg:phone":"+1 479 394 2697",
    "sg:postcode":"71953",
    "sg:province":"AR",
    "sg:tags":[
        "church"
    ],
    "wof:name":"Dallas Avenue Baptist Church",
    "wof:placetype":"venue"
},
  "geometry": {"coordinates":[-94.229372,34.57956],"type":"Point"}
}