{
  "type": "Feature",
  "properties": {
    "iso:country":"US",
    "sg:address":"13221 Pleasant Forest Dr",
    "sg:city":"Little Rock",
    "sg:classifiers":[
        {
            "category":"Professional",
            "subcategory":"Management & Consulting",
            "type":"Services"
        }
    ],
    "sg:phone":"+1 501 223 8427",
    "sg:postcode":"72212",
    "sg:province":"AR",
    "sg:tags":[
        "consultant",
        "business"
    ],
    "wof:name":"Synergy Consulting LLC",
    "wof:placetype":"venue"
},
  "geometry": {"coordinates":[-92.420031,34.790053],"type":"Point"}
}