{
  "type": "Feature",
  "properties": {
    "iso:country":"US",
    "sg:address":"6575 Sumter Dr",
    "sg:city":"Fayetteville",
    "sg:classifiers":[
        {
            "category":"Building & Trades",
            "subcategory":"Construction",
            "type":"Services"
        }
    ],
    "sg:phone":"+1 479 957 3467",
    "sg:postcode":"72704",
    "sg:province":"AR",
    "sg:tags":[
        "masonry",
        "contractor"
    ],
    "wof:name":"Phillips Masonry",
    "wof:placetype":"venue"
},
  "geometry": {"coordinates":[-94.253658,36.076641],"type":"Point"}
}