{
  "type": "Feature",
  "properties": {
    "iso:country":"US",
    "sg:address":"48 Adams St",
    "sg:city":"Wilson",
    "sg:classifiers":[
        {
            "category":"Manufacturing",
            "subcategory":"Buildings",
            "type":"Manufacturing & Wholesale Goods"
        },
        {
            "category":"Building & Trades",
            "subcategory":"Construction",
            "type":"Services"
        }
    ],
    "sg:phone":"+1 870 655 8757",
    "sg:postcode":"72395",
    "sg:province":"AR",
    "sg:tags":[
        "home",
        "builder",
        "contractor"
    ],
    "wof:name":"Jim Walker",
    "wof:placetype":"venue"
},
  "geometry": {"coordinates":[-90.04763,35.56691],"type":"Point"}
}