{
  "type": "Feature",
  "properties": {
    "iso:country":"US",
    "sg:address":"2418 S Kerr Rd",
    "sg:city":"Lonoke",
    "sg:classifiers":[
        {
            "category":"Freight",
            "type":"Transportation"
        }
    ],
    "sg:phone":"+1 501 982 3997",
    "sg:postcode":"72086",
    "sg:province":"AR",
    "sg:tags":[
        "operator",
        "local",
        "trucking"
    ],
    "wof:name":"MRM Trucking Inc",
    "wof:placetype":"venue"
},
  "geometry": {"coordinates":[-92.032907,34.808297],"type":"Point"}
}