{
  "type": "Feature",
  "properties": {
    "addr:full":"2056 State Hwy 69 Paragould AR 72450",
    "addr:housenumber":"2056",
    "addr:postcode":"72450",
    "addr:street":"State Hwy 69",
    "iso:country":"US",
    "sg:address":"2056 State Hwy 69",
    "sg:city":"Paragould",
    "sg:classifiers":[
        {
            "category":"Freight",
            "type":"Transportation"
        }
    ],
    "sg:phone":"+1 870 236 2460",
    "sg:postcode":"72450",
    "sg:province":"AR",
    "sg:tags":[
        "commercial",
        "storage"
    ],
    "wof:name":"Laubach Warehouse & Storage",
    "wof:placetype":"venue"
},
  "geometry": {"coordinates":[-90.486497,36.01012],"type":"Point"}
}