{
  "type": "Feature",
  "properties": {
    "iso:country":"US",
    "sg:address":"150 Gates Ln",
    "sg:city":"Batesville",
    "sg:classifiers":[
        {
            "category":"Professional",
            "type":"Services"
        }
    ],
    "sg:phone":"+1 870 793 6781",
    "sg:postcode":"72501",
    "sg:province":"AR",
    "wof:name":"Deloris Boyett",
    "wof:placetype":"venue"
},
  "geometry": {"coordinates":[-91.53314,35.74484],"type":"Point"}
}