{
  "type": "Feature",
  "properties": {
    "addr:full":"301 N Shackleford Rd Little Rock AR 72211",
    "addr:housenumber":"301",
    "addr:postcode":"72211",
    "addr:street":"N Shackleford Rd",
    "iso:country":"US",
    "sg:address":"301 N Shackleford Rd",
    "sg:city":"Little Rock",
    "sg:classifiers":[
        {
            "category":"Professional",
            "subcategory":"Business Services",
            "type":"Services"
        }
    ],
    "sg:phone":"+1 501 716 9112",
    "sg:postcode":"72211",
    "sg:province":"AR",
    "sg:tags":[
        "embroidery"
    ],
    "wof:name":"Embroidme",
    "wof:placetype":"venue"
},
  "geometry": {"coordinates":[-92.39388099999999,34.756116],"type":"Point"}
}