{
  "type": "Feature",
  "properties": {
    "iso:country":"US",
    "sg:address":"611 S Madison St",
    "sg:city":"Magnolia",
    "sg:classifiers":[
        {
            "category":"Organizations",
            "subcategory":"Community Association",
            "type":"Services"
        }
    ],
    "sg:phone":"+1 870 234 3700",
    "sg:postcode":"71753",
    "sg:province":"AR",
    "wof:name":"Southwest Ark Comm Dev Ctr",
    "wof:placetype":"venue"
},
  "geometry": {"coordinates":[-93.242867,33.262375],"type":"Point"}
}