{
  "type": "Feature",
  "properties": {
    "addr:full":"812 SW Raintree Ln Bentonville AR 72712",
    "addr:housenumber":"812",
    "addr:postcode":"72712",
    "addr:street":"Sw Raintree Ln",
    "iso:country":"US",
    "sg:address":"812 SW Raintree Ln",
    "sg:city":"Bentonville",
    "sg:classifiers":[
        {
            "category":"Professional",
            "subcategory":"Advertising",
            "type":"Services"
        }
    ],
    "sg:phone":"+1 479 254 0949",
    "sg:postcode":"72712",
    "sg:province":"AR",
    "sg:tags":[
        "distribution"
    ],
    "wof:name":"Pacesetter Imports",
    "wof:placetype":"venue"
},
  "geometry": {"coordinates":[-94.220715,36.360732],"type":"Point"}
}