{
  "type": "Feature",
  "properties": {
    "addr:full":"4221 Oakhill Ln Jonesboro AR 72401",
    "addr:housenumber":"4221",
    "addr:postcode":"72401",
    "addr:street":"Oakhill Ln",
    "iso:country":"US",
    "sg:address":"4221 Oakhill Ln",
    "sg:city":"Jonesboro",
    "sg:classifiers":[
        {
            "category":"Personal",
            "subcategory":"Beauty Salon",
            "type":"Services"
        }
    ],
    "sg:phone":"+1 870 972 0068",
    "sg:postcode":"72401",
    "sg:province":"AR",
    "sg:tags":[
        "shop"
    ],
    "wof:name":"Hair Clinic",
    "wof:placetype":"venue"
},
  "geometry": {"coordinates":[-90.643333,35.858243],"type":"Point"}
}