{
  "type": "Feature",
  "properties": {
    "addr:full":"4040 Highway 20 Helena AR 72342",
    "addr:housenumber":"4040",
    "addr:postcode":"72342",
    "addr:street":"Highway 20",
    "iso:country":"US",
    "sg:address":"4040 Highway 20",
    "sg:city":"Helena",
    "sg:classifiers":[
        {
            "category":"Manufacturing",
            "subcategory":"Food",
            "type":"Manufacturing & Wholesale Goods"
        }
    ],
    "sg:phone":"+1 870 338 8043",
    "sg:postcode":"72342",
    "sg:province":"AR",
    "sg:tags":[
        "product"
    ],
    "wof:name":"Napoleon Medley",
    "wof:placetype":"venue"
},
  "geometry": {"coordinates":[-90.619457,34.449014],"type":"Point"}
}