{
  "type": "Feature",
  "properties": {
    "addr:full":"115 Belle Ave Alma AR 72921",
    "addr:housenumber":"115",
    "addr:postcode":"72921",
    "addr:street":"Belle Ave",
    "iso:country":"US",
    "sg:address":"115 Belle Ave",
    "sg:city":"Alma",
    "sg:classifiers":[
        {
            "category":"Building & Trades",
            "subcategory":"Cleaning & Sanitation",
            "type":"Services"
        }
    ],
    "sg:phone":"+1 479 632 9717",
    "sg:postcode":"72921",
    "sg:province":"AR",
    "sg:tags":[
        "maintenance"
    ],
    "wof:name":"Ozarks Janitorial Co",
    "wof:placetype":"venue"
},
  "geometry": {"coordinates":[-94.20607099999999,35.490216],"type":"Point"}
}