{
  "type": "Feature",
  "properties": {
    "iso:country":"US",
    "sg:address":"316 Church St",
    "sg:city":"Lake Village",
    "sg:classifiers":[
        {
            "category":"Building & Trades",
            "subcategory":"Plumbing",
            "type":"Services"
        }
    ],
    "sg:phone":"+1 870 265 4363",
    "sg:postcode":"71653",
    "sg:province":"AR",
    "sg:tags":[
        "contractor"
    ],
    "wof:name":"Jerry Heating and Air",
    "wof:placetype":"venue"
},
  "geometry": {"coordinates":[-91.284068,33.330833],"type":"Point"}
}