{
  "type": "Feature",
  "properties": {
    "iso:country":"US",
    "sg:address":"1103 S 7th St",
    "sg:city":"Heber Springs",
    "sg:classifiers":[
        {
            "category":"Shopping",
            "subcategory":"Gifts & Souvenirs",
            "type":"Retail Goods"
        }
    ],
    "sg:phone":"+1 501 362 5560",
    "sg:postcode":"72543",
    "sg:province":"AR",
    "sg:tags":[
        "shop"
    ],
    "wof:name":"Browsing Post",
    "wof:placetype":"venue"
},
  "geometry": {"coordinates":[-92.037036,35.481552],"type":"Point"}
}