{
  "type": "Feature",
  "properties": {
    "iso:country":"US",
    "sg:address":"5825 Heber Springs Rd W",
    "sg:city":"Quitman",
    "sg:classifiers":[
        {
            "category":"Banks & Credit Unions",
            "subcategory":"Bank",
            "type":"Services"
        }
    ],
    "sg:phone":"+1 501 589 2200",
    "sg:postcode":"72131",
    "sg:province":"AR",
    "sg:tags":[
        "institution",
        "business"
    ],
    "wof:name":"Cleburne Cnty Bank-Quitman BR",
    "wof:placetype":"venue"
},
  "geometry": {"coordinates":[-92.198778,35.390856],"type":"Point"}
}