{
  "type": "Feature",
  "properties": {
    "iso:country":"US",
    "sg:address":"58 Heatherbrae Cir",
    "sg:city":"Little Rock",
    "sg:classifiers":[
        {
            "category":"Building & Trades",
            "subcategory":"Construction",
            "type":"Services"
        }
    ],
    "sg:phone":"+1 501 868 8460",
    "sg:postcode":"72223",
    "sg:province":"AR",
    "sg:tags":[
        "house",
        "general",
        "contractor"
    ],
    "wof:name":"T-1 Construction Inc",
    "wof:placetype":"venue"
},
  "geometry": {"coordinates":[-92.442832,34.796612],"type":"Point"}
}