{
  "type": "Feature",
  "properties": {
    "iso:country":"US",
    "sg:address":"13 Military Rd",
    "sg:city":"Marion",
    "sg:classifiers":[
        {
            "category":"Government",
            "subcategory":"Office",
            "type":"Public Place"
        }
    ],
    "sg:phone":"+1 870 739 5414",
    "sg:postcode":"72364",
    "sg:province":"AR",
    "sg:tags":[
        "township",
        "government-city",
        "village"
    ],
    "sg:website":"http://www.marionarkansas.org",
    "wof:name":"City Of Marion",
    "wof:placetype":"venue"
},
  "geometry": {"coordinates":[-90.197632,35.214434],"type":"Point"}
}