{
  "type": "Feature",
  "properties": {
    "addr:full":"12453 State Hwy 214 Harrisburg AR 72432",
    "addr:housenumber":"12453",
    "addr:postcode":"72432",
    "addr:street":"State Hwy 214",
    "iso:country":"US",
    "sg:address":"12453 State Hwy 214",
    "sg:city":"Harrisburg",
    "sg:classifiers":[
        {
            "category":"Farming",
            "subcategory":"Farm",
            "type":"Manufacturing & Wholesale Goods"
        }
    ],
    "sg:phone":"+1 870 578 2961",
    "sg:postcode":"72432",
    "sg:province":"AR",
    "sg:tags":[
        "general"
    ],
    "wof:name":"Triple W Farms",
    "wof:placetype":"venue"
},
  "geometry": {"coordinates":[-90.814796,35.474757],"type":"Point"}
}