{
  "type": "Feature",
  "properties": {
    "addr:full":"503 E 7th St Little Rock AR 72202",
    "addr:housenumber":"503",
    "addr:postcode":"72202",
    "addr:street":"E 7Th St",
    "iso:country":"US",
    "sg:address":"503 E 7th St",
    "sg:city":"Little Rock",
    "sg:classifiers":[
        {
            "category":"Professional",
            "subcategory":"Art Services",
            "type":"Services"
        }
    ],
    "sg:phone":"+1 501 851 4274",
    "sg:postcode":"72202",
    "sg:province":"AR",
    "sg:tags":[
        "graphic",
        "design",
        "artist"
    ],
    "wof:name":"Design Studio",
    "wof:placetype":"venue"
},
  "geometry": {"coordinates":[-92.265946,34.741352],"type":"Point"}
}