{
  "type": "Feature",
  "properties": {
    "iso:country":"US",
    "sg:address":"3930 McCain Blvd",
    "sg:city":"North Little Rock",
    "sg:classifiers":[
        {
            "category":"Shopping",
            "subcategory":"Department Store",
            "type":"Retail Goods"
        }
    ],
    "sg:phone":"+1 501 771 7200",
    "sg:postcode":"72116",
    "sg:province":"AR",
    "wof:name":"Sears",
    "wof:placetype":"venue"
},
  "geometry": {"coordinates":[-92.22919899999999,34.791358],"type":"Point"}
}