{
  "type": "Feature",
  "properties": {
    "iso:country":"US",
    "sg:address":"608 E Main St",
    "sg:city":"Magnolia",
    "sg:classifiers":[
        {
            "category":"Retail",
            "subcategory":"Repair Shop",
            "type":"Services"
        }
    ],
    "sg:phone":"+1 870 234 3326",
    "sg:postcode":"71753",
    "sg:province":"AR",
    "sg:tags":[
        "jewelry"
    ],
    "wof:name":"Haynes Jewelry Repair Shop",
    "wof:placetype":"venue"
},
  "geometry": {"coordinates":[-93.232714,33.26702],"type":"Point"}
}