{
  "type": "Feature",
  "properties": {
    "iso:country":"US",
    "sg:address":"6056 State Hwy 36 W",
    "sg:city":"Rose Bud",
    "sg:classifiers":[
        {
            "category":"Shopping",
            "subcategory":"Gifts & Souvenirs",
            "type":"Retail Goods"
        },
        {
            "category":"Cinema",
            "subcategory":"Movie Rental",
            "type":"Entertainment"
        }
    ],
    "sg:phone":"+1 501 556 0820",
    "sg:postcode":"72137",
    "sg:province":"AR",
    "sg:tags":[
        "leasing",
        "video",
        "disc",
        "tape"
    ],
    "wof:name":"Inspirations",
    "wof:placetype":"venue"
},
  "geometry": {"coordinates":[-92.08863,35.332499],"type":"Point"}
}