{
  "type": "Feature",
  "properties": {
    "addr:full":"56351 E 307 Rd Afton OK 74331",
    "addr:housenumber":"56351",
    "addr:postcode":"74331",
    "addr:street":"E 307 Rd",
    "iso:country":"US",
    "sg:address":"56351 E 307 Rd",
    "sg:city":"Afton",
    "sg:classifiers":[
        {
            "category":"Mining & Drilling",
            "type":"Manufacturing & Wholesale Goods"
        }
    ],
    "sg:phone":"+1 918 257 5050",
    "sg:postcode":"74331",
    "sg:province":"OK",
    "sg:tags":[
        "oil",
        "gas",
        "producer"
    ],
    "wof:name":"Trees Oil Co",
    "wof:placetype":"venue"
},
  "geometry": {"coordinates":[-94.856337,36.570434],"type":"Point"}
}