{
  "type": "Feature",
  "properties": {
    "addr:full":"18 Cumberland Dr Cabot AR 72023",
    "addr:housenumber":"18",
    "addr:postcode":"72023",
    "addr:street":"Cumberland Dr",
    "iso:country":"US",
    "sg:address":"18 Cumberland Dr",
    "sg:city":"Cabot",
    "sg:classifiers":[
        {
            "category":"Sports & Exercise",
            "subcategory":"Golf",
            "type":"Entertainment"
        }
    ],
    "sg:phone":"+1 501 605 1232",
    "sg:postcode":"72023",
    "sg:province":"AR",
    "sg:tags":[
        "course"
    ],
    "wof:name":"460 Golf",
    "wof:placetype":"venue"
},
  "geometry": {"coordinates":[-91.995733,34.976875],"type":"Point"}
}