{
  "type": "Feature",
  "properties": {
    "iso:country":"US",
    "sg:address":"2382 Red Wings Rd",
    "sg:city":"Bismarck",
    "sg:classifiers":[
        {
            "category":"Organizations",
            "subcategory":"Religious Organization",
            "type":"Services"
        }
    ],
    "sg:phone":"+1 501 865 1333",
    "sg:postcode":"71929",
    "sg:province":"AR",
    "wof:name":"Oneness Pentecostal Church",
    "wof:placetype":"venue"
},
  "geometry": {"coordinates":[-93.208611,34.30717],"type":"Point"}
}