{
  "type": "Feature",
  "properties": {
    "iso:country":"US",
    "sg:address":"9020 Chicot Rd",
    "sg:city":"Little Rock",
    "sg:classifiers":[
        {
            "category":"Real Estate",
            "subcategory":"Real Estate Agent",
            "type":"Services"
        }
    ],
    "sg:phone":"+1 501 562 7878",
    "sg:postcode":"72209",
    "sg:province":"AR",
    "wof:name":"Dyers Real Estate",
    "wof:placetype":"venue"
},
  "geometry": {"coordinates":[-92.362121,34.66931],"type":"Point"}
}