{
  "type": "Feature",
  "properties": {
    "addr:full":"16066 Spring Club Dr Hensley AR 72065",
    "addr:housenumber":"16066",
    "addr:postcode":"72065",
    "addr:street":"Spring Club Dr",
    "iso:country":"US",
    "sg:address":"16066 Spring Club Dr",
    "sg:city":"Hensley",
    "sg:classifiers":[
        {
            "category":"Airport",
            "type":"Transportation"
        }
    ],
    "sg:phone":"+1 501 778 4359",
    "sg:postcode":"72065",
    "sg:province":"AR",
    "sg:tags":[
        "aircraft",
        "maintenance"
    ],
    "wof:name":"Looker Aviation",
    "wof:placetype":"venue"
},
  "geometry": {"coordinates":[-92.320187,34.539922],"type":"Point"}
}