{
  "type": "Feature",
  "properties": {
    "iso:country":"US",
    "sg:address":"2900 Old Greenwood Rd",
    "sg:city":"Fort Smith",
    "sg:classifiers":[
        {
            "category":"Personal",
            "subcategory":"Beauty Salon",
            "type":"Services"
        }
    ],
    "sg:phone":"+1 479 648 1505",
    "sg:postcode":"72903",
    "sg:province":"AR",
    "sg:tags":[
        "shop"
    ],
    "wof:name":"Nails By Cyndie",
    "wof:placetype":"venue"
},
  "geometry": {"coordinates":[-94.394839,35.355497],"type":"Point"}
}