{
  "type": "Feature",
  "properties": {
    "addr:full":"416 E Main St Gassville AR 72635",
    "addr:housenumber":"416",
    "addr:postcode":"72635",
    "addr:street":"E Main St",
    "iso:country":"US",
    "sg:address":"416 E Main St",
    "sg:city":"Gassville",
    "sg:classifiers":[
        {
            "category":"Health Services",
            "subcategory":"Clinic",
            "type":"Services"
        }
    ],
    "sg:phone":"+1 870 435 6300",
    "sg:postcode":"72635",
    "sg:province":"AR",
    "sg:tags":[
        "specialty",
        "outpatient"
    ],
    "wof:name":"O M A R T",
    "wof:placetype":"venue"
},
  "geometry": {"coordinates":[-92.489431,36.284445],"type":"Point"}
}