{
  "type": "Feature",
  "properties": {
    "addr:full":"3305 Archie Watkins Rd Farmington AR 72730",
    "addr:housenumber":"3305",
    "addr:postcode":"72730",
    "addr:street":"Archie Watkins Rd",
    "iso:country":"US",
    "sg:address":"3305 Archie Watkins Rd",
    "sg:city":"Farmington",
    "sg:classifiers":[
        {
            "category":"Wholesale",
            "subcategory":"Stationery",
            "type":"Manufacturing & Wholesale Goods"
        },
        {
            "category":"Manufacturing",
            "subcategory":"Printing",
            "type":"Manufacturing & Wholesale Goods"
        }
    ],
    "sg:phone":"+1 479 267 4444",
    "sg:postcode":"72730",
    "sg:province":"AR",
    "sg:tags":[
        "cards",
        "post",
        "commercial"
    ],
    "wof:name":"Down River Cards",
    "wof:placetype":"venue"
},
  "geometry": {"coordinates":[-94.224851,36.024976],"type":"Point"}
}