{
  "type": "Feature",
  "properties": {
    "iso:country":"US",
    "sg:address":"1624 State Hwy 9",
    "sg:city":"Morrilton",
    "sg:classifiers":[
        {
            "category":"Banks & Credit Unions",
            "subcategory":"Bank",
            "type":"Services"
        }
    ],
    "sg:phone":"+1 501 354 2500",
    "sg:postcode":"72110",
    "sg:province":"AR",
    "sg:tags":[
        "state",
        "commercial"
    ],
    "wof:name":"First Arkansas Valley Bank",
    "wof:placetype":"venue"
},
  "geometry": {"coordinates":[-92.717586,35.179864],"type":"Point"}
}