{
  "type": "Feature",
  "properties": {
    "addr:full":"1900 Midland Blvd Fort Smith AR 72904",
    "addr:housenumber":"1900",
    "addr:postcode":"72904",
    "addr:street":"Midland Blvd",
    "iso:country":"US",
    "sg:address":"1900 Midland Blvd",
    "sg:city":"Fort Smith",
    "sg:classifiers":[
        {
            "category":"Restaurant",
            "type":"Food & Drink"
        }
    ],
    "sg:phone":"+1 479 782 7509",
    "sg:postcode":"72904",
    "sg:province":"AR",
    "sg:tags":[
        "eating"
    ],
    "wof:name":"Thai Food",
    "wof:placetype":"venue"
},
  "geometry": {"coordinates":[-94.40539,35.399704],"type":"Point"}
}