{
  "type": "Feature",
  "properties": {
    "iso:country":"US",
    "sg:address":"209 N College St",
    "sg:city":"Mountain Home",
    "sg:classifiers":[
        {
            "category":"Real Estate",
            "subcategory":"Real Estate Agent",
            "type":"Services"
        }
    ],
    "sg:phone":"+1 870 425 2840",
    "sg:postcode":"72653",
    "sg:province":"AR",
    "sg:tags":[
        "management"
    ],
    "wof:name":"Full Circle Properties",
    "wof:placetype":"venue"
},
  "geometry": {"coordinates":[-92.38077800000001,36.341963],"type":"Point"}
}