{
  "type": "Feature",
  "properties": {
    "iso:country":"US",
    "sg:address":"1911 W Parker Rd",
    "sg:city":"Jonesboro",
    "sg:classifiers":[
        {
            "category":"Shopping",
            "subcategory":"Optical Goods",
            "type":"Retail Goods"
        }
    ],
    "sg:phone":"+1 870 910 5493",
    "sg:postcode":"72404",
    "sg:province":"AR",
    "wof:name":"Ross Eye Care",
    "wof:placetype":"venue"
},
  "geometry": {"coordinates":[-90.672989,35.806732],"type":"Point"}
}