{
  "type": "Feature",
  "properties": {
    "iso:country":"US",
    "sg:address":"356 Harkrider St",
    "sg:city":"Conway",
    "sg:classifiers":[
        {
            "category":"Professional",
            "type":"Services"
        }
    ],
    "sg:phone":"+1 501 450 7022",
    "sg:postcode":"72032",
    "sg:province":"AR",
    "wof:name":"LA Princesa Plaza",
    "wof:placetype":"venue"
},
  "geometry": {"coordinates":[-92.436616,35.081193],"type":"Point"}
}