{
  "type": "Feature",
  "properties": {
    "iso:country":"US",
    "sg:address":"4416 W 26th St",
    "sg:city":"Little Rock",
    "sg:classifiers":[
        {
            "category":"Communications",
            "subcategory":"Film & Video Production",
            "type":"Services"
        }
    ],
    "sg:phone":"+1 501 661 0433",
    "sg:postcode":"72204",
    "sg:province":"AR",
    "sg:tags":[
        "motion"
    ],
    "wof:name":"J ROC Steady Productions LLC",
    "wof:placetype":"venue"
},
  "geometry": {"coordinates":[-92.323824,34.728051],"type":"Point"}
}