{
  "type": "Feature",
  "properties": {
    "iso:country":"US",
    "sg:address":"206 W Dodson St",
    "sg:city":"Nashville",
    "sg:classifiers":[
        {
            "category":"Organizations",
            "subcategory":"Religious Organization",
            "type":"Services"
        }
    ],
    "sg:phone":"+1 870 845 1318",
    "sg:postcode":"71852",
    "sg:province":"AR",
    "sg:tags":[
        "church"
    ],
    "wof:name":"Dodson Street Church Of Christ",
    "wof:placetype":"venue"
},
  "geometry": {"coordinates":[-93.848525,33.934052],"type":"Point"}
}