{
  "type": "Feature",
  "properties": {
    "iso:country":"US",
    "sg:address":"1945 S West Ave",
    "sg:city":"El Dorado",
    "sg:classifiers":[
        {
            "category":"Wholesale",
            "subcategory":"Machinery & Supplies",
            "type":"Manufacturing & Wholesale Goods"
        }
    ],
    "sg:phone":"+1 870 863 8018",
    "sg:postcode":"71730",
    "sg:province":"AR",
    "sg:tags":[
        "pressure",
        "washing",
        "equipment"
    ],
    "wof:name":"Hoss Power Distributors",
    "wof:placetype":"venue"
},
  "geometry": {"coordinates":[-92.665748,33.194646],"type":"Point"}
}