{
  "type": "Feature",
  "properties": {
    "iso:country":"US",
    "sg:address":"115 Audubon Dr Ste 15",
    "sg:city":"Maumelle",
    "sg:classifiers":[
        {
            "category":"Insurance",
            "subcategory":"Hazard Insurance",
            "type":"Services"
        }
    ],
    "sg:phone":"+1 501 851 7370",
    "sg:postcode":"72113",
    "sg:province":"AR",
    "sg:website":"http://statefarm.mqgroup.com/url.asp?usr=041596",
    "wof:name":"State Farm Insurance Agent-Anthony Otwell",
    "wof:placetype":"venue"
},
  "geometry": {"coordinates":[-92.40463800000001,34.850672],"type":"Point"}
}