{
  "type": "Feature",
  "properties": {
    "iso:country":"US",
    "sg:address":"105 N Pocola Blvd",
    "sg:city":"Pocola",
    "sg:classifiers":[
        {
            "category":"Banks & Credit Unions",
            "subcategory":"Bank",
            "type":"Services"
        }
    ],
    "sg:phone":"+1 918 436 2105",
    "sg:postcode":"74902",
    "sg:province":"OK",
    "sg:tags":[
        "institution",
        "business"
    ],
    "wof:name":"Anchor Financial Services Inc",
    "wof:placetype":"venue"
},
  "geometry": {"coordinates":[-94.47803,35.267203],"type":"Point"}
}