{
  "type": "Feature",
  "properties": {
    "addr:full":"100 Dixon St Melbourne AR 72556",
    "addr:housenumber":"100",
    "addr:postcode":"72556",
    "addr:street":"Dixon St",
    "iso:country":"US",
    "sg:address":"100 Dixon St",
    "sg:city":"Melbourne",
    "sg:classifiers":[
        {
            "category":"Real Estate",
            "subcategory":"Real Estate Agent",
            "type":"Services"
        }
    ],
    "sg:phone":"+1 870 368 4429",
    "sg:postcode":"72556",
    "sg:province":"AR",
    "sg:website":"http://www.cooper-realty.net",
    "wof:name":"Cooper Realty",
    "wof:placetype":"venue"
},
  "geometry": {"coordinates":[-91.910076,36.07324],"type":"Point"}
}