{
  "type": "Feature",
  "properties": {
    "addr:full":"4012 Jackson Road 5 Bradford AR 72020",
    "addr:housenumber":"4012",
    "addr:postcode":"72020",
    "addr:street":"Jackson Road 5",
    "iso:country":"US",
    "sg:address":"4012 Jackson Road 5",
    "sg:city":"Bradford",
    "sg:classifiers":[
        {
            "category":"Autos & Motor Vehicles",
            "subcategory":"Automobile Sales",
            "type":"Retail Goods"
        }
    ],
    "sg:phone":"+1 501 344 8653",
    "sg:postcode":"72020",
    "sg:province":"AR",
    "sg:tags":[
        "dealers-used",
        "car",
        "used",
        "cars-wholesale"
    ],
    "wof:name":"C & C Auto Sales",
    "wof:placetype":"venue"
},
  "geometry": {"coordinates":[-91.497089,35.448917],"type":"Point"}
}