{
  "type": "Feature",
  "properties": {
    "iso:country":"US",
    "sg:address":"37 Leisurewood Ln",
    "sg:city":"Maumelle",
    "sg:classifiers":[
        {
            "category":"Building & Trades",
            "subcategory":"Construction",
            "type":"Services"
        }
    ],
    "sg:phone":"+1 501 851 2834",
    "sg:postcode":"72113",
    "sg:province":"AR",
    "sg:tags":[
        "speculative",
        "builder",
        "custom"
    ],
    "wof:name":"Odom Gayle Builder",
    "wof:placetype":"venue"
},
  "geometry": {"coordinates":[-92.409032,34.864861],"type":"Point"}
}