{
  "type": "Feature",
  "properties": {
    "iso:country":"US",
    "sg:address":"600 W Markham St",
    "sg:city":"Little Rock",
    "sg:classifiers":[
        {
            "category":"Social Services",
            "type":"Services"
        }
    ],
    "sg:phone":"+1 501 371 4613",
    "sg:postcode":"72201",
    "sg:province":"AR",
    "sg:tags":[
        "probation"
    ],
    "wof:name":"Little Rock Traffic Probation",
    "wof:placetype":"venue"
},
  "geometry": {"coordinates":[-92.27691299999999,34.748985],"type":"Point"}
}