{
  "type": "Feature",
  "properties": {
    "addr:full":"3202 NE Red Hawk Dr Bentonville AR 72712",
    "addr:housenumber":"3202",
    "addr:postcode":"72712",
    "addr:street":"Ne Red Hawk Dr",
    "iso:country":"US",
    "sg:address":"3202 NE Red Hawk Dr",
    "sg:city":"Bentonville",
    "sg:classifiers":[
        {
            "category":"Manufacturing",
            "subcategory":"Chemicals & Compounds",
            "type":"Manufacturing & Wholesale Goods"
        }
    ],
    "sg:phone":"+1 479 464 7434",
    "sg:postcode":"72712",
    "sg:province":"AR",
    "sg:tags":[
        "preparation",
        "art",
        "artist",
        "fine",
        "mfg"
    ],
    "sg:website":"http://www.scottscompany.com",
    "wof:name":"The Scotts Company",
    "wof:placetype":"venue"
},
  "geometry": {"coordinates":[-94.174471,36.384474],"type":"Point"}
}