{
  "type": "Feature",
  "properties": {
    "iso:country":"US",
    "sg:address":"18 County Road 377",
    "sg:city":"Wynne",
    "sg:classifiers":[
        {
            "category":"Manufacturing",
            "subcategory":"Food",
            "type":"Manufacturing & Wholesale Goods"
        },
        {
            "category":"Farming",
            "subcategory":"Farm",
            "type":"Manufacturing & Wholesale Goods"
        }
    ],
    "sg:phone":"+1 870 238 0244",
    "sg:postcode":"72396",
    "sg:province":"AR",
    "sg:tags":[
        "product"
    ],
    "wof:name":"Matthews Sweet Potato Farm",
    "wof:placetype":"venue"
},
  "geometry": {"coordinates":[-90.729015,35.299679],"type":"Point"}
}