{
  "type": "Feature",
  "properties": {
    "iso:country":"US",
    "sg:address":"304 E Central St",
    "sg:city":"Siloam Springs",
    "sg:classifiers":[
        {
            "category":"Shopping",
            "subcategory":"Crafts & Fabrics",
            "type":"Retail Goods"
        }
    ],
    "sg:phone":"+1 479 524 5244",
    "sg:postcode":"72761",
    "sg:province":"OK",
    "sg:tags":[
        "sewing"
    ],
    "wof:name":"Sager Creek Quilts & Tea Room",
    "wof:placetype":"venue"
},
  "geometry": {"coordinates":[-94.538979,36.185046],"type":"Point"}
}