{
  "type": "Feature",
  "properties": {
    "iso:country":"US",
    "sg:address":"1241 Batesville Blvd",
    "sg:city":"Batesville",
    "sg:classifiers":[
        {
            "category":"Professional",
            "subcategory":"Accounting & Tax Preparation",
            "type":"Services"
        }
    ],
    "sg:phone":"+1 870 251 1256",
    "sg:postcode":"72501",
    "sg:province":"AR",
    "sg:tags":[
        "accountant"
    ],
    "wof:name":"Mc Doniel & Cantrell Cpa's LLP",
    "wof:placetype":"venue"
},
  "geometry": {"coordinates":[-91.636997,35.723773],"type":"Point"}
}