{
  "type": "Feature",
  "properties": {
    "addr:full":"2202 US Hwy 71 Mena OK 71953",
    "addr:housenumber":"2202",
    "addr:postcode":"71953",
    "addr:street":"Us Hwy 71",
    "iso:country":"US",
    "sg:address":"2202 US Hwy 71",
    "sg:city":"Mena",
    "sg:classifiers":[
        {
            "category":"Autos & Motor Vehicles",
            "subcategory":"Automobile Sales",
            "type":"Retail Goods"
        }
    ],
    "sg:phone":"+1 479 394 6601",
    "sg:postcode":"71953",
    "sg:province":"OK",
    "sg:tags":[
        "car",
        "dealer"
    ],
    "wof:name":"Woody's Preowned Cars & Svc",
    "wof:placetype":"venue"
},
  "geometry": {"coordinates":[-94.25665100000001,34.567349],"type":"Point"}
}