{
  "type": "Feature",
  "properties": {
    "addr:full":"110 Rolling Oaks Dr N Little Rock AR 72113",
    "addr:housenumber":"110",
    "addr:postcode":"72113",
    "addr:street":"Rolling Oaks Dr N",
    "iso:country":"US",
    "sg:address":"110 Rolling Oaks Dr",
    "sg:city":"N Little Rock",
    "sg:classifiers":[
        {
            "category":"Manufacturing",
            "subcategory":"Printing",
            "type":"Manufacturing & Wholesale Goods"
        }
    ],
    "sg:phone":"+1 501 851 0001",
    "sg:postcode":"72113",
    "sg:province":"AR",
    "sg:tags":[
        "publisher"
    ],
    "wof:name":"Maumelle Living Inc",
    "wof:placetype":"venue"
},
  "geometry": {"coordinates":[-92.402446,34.87828],"type":"Point"}
}