{
  "type": "Feature",
  "properties": {
    "addr:full":"1001 W 7th St Little Rock AR 72201",
    "addr:housenumber":"1001",
    "addr:postcode":"72201",
    "addr:street":"W 7Th St",
    "iso:country":"US",
    "sg:address":"1001 W 7th St",
    "sg:city":"Little Rock",
    "sg:classifiers":[
        {
            "category":"Arts & Performance",
            "subcategory":"Theater",
            "type":"Entertainment"
        }
    ],
    "sg:phone":"+1 501 374 3761",
    "sg:postcode":"72201",
    "sg:province":"AR",
    "sg:tags":[
        "theatrical"
    ],
    "wof:name":"Weekend Theatre",
    "wof:placetype":"venue"
},
  "geometry": {"coordinates":[-92.283407,34.743794],"type":"Point"}
}