{
  "type": "Feature",
  "properties": {
    "addr:full":"11925 State Hwy 123 Lamar AR 72846",
    "addr:housenumber":"11925",
    "addr:postcode":"72846",
    "addr:street":"State Hwy 123 Lamar",
    "iso:country":"US",
    "sg:address":"11925 State Hwy 123",
    "sg:city":"Lamar",
    "sg:classifiers":[
        {
            "category":"Food & Beverages",
            "subcategory":"Groceries & Convenience Stores",
            "type":"Retail Goods"
        }
    ],
    "sg:phone":"+1 479 885 6330",
    "sg:postcode":"72846",
    "sg:province":"AR",
    "sg:tags":[
        "grocer"
    ],
    "wof:name":"Hagarville Grocery & Station",
    "wof:placetype":"venue"
},
  "geometry": {"coordinates":[-93.33360399999999,35.515192],"type":"Point"}
}