{
  "type": "Feature",
  "properties": {
    "iso:country":"US",
    "sg:address":"205 E Johnson Ave",
    "sg:city":"Springdale",
    "sg:classifiers":[
        {
            "category":"Shopping",
            "subcategory":"Party Supplies",
            "type":"Retail Goods"
        }
    ],
    "sg:phone":"+1 479 750 3438",
    "sg:postcode":"72764",
    "sg:province":"AR",
    "sg:tags":[
        "decoration",
        "rental",
        "tents-rental"
    ],
    "wof:name":"Intents Inc",
    "wof:placetype":"venue"
},
  "geometry": {"coordinates":[-94.12989,36.18639],"type":"Point"}
}