{
  "type": "Feature",
  "properties": {
    "iso:country":"US",
    "sg:address":"1708 S 8th St",
    "sg:city":"Rogers",
    "sg:classifiers":[
        {
            "category":"Insurance",
            "subcategory":"Insurance Agent",
            "type":"Services"
        }
    ],
    "sg:phone":"+1 479 631 6444",
    "sg:postcode":"72756",
    "sg:province":"AR",
    "wof:name":"Woodman of World Lf Insur Soc",
    "wof:placetype":"venue"
},
  "geometry": {"coordinates":[-94.12626299999999,36.317253],"type":"Point"}
}