{
  "type": "Feature",
  "properties": {
    "addr:full":"1000 Fairview Rd SW Camden AR 71701",
    "addr:housenumber":"1000",
    "addr:postcode":"71701",
    "addr:street":"Fairview Rd Sw",
    "iso:country":"US",
    "sg:address":"1000 Fairview Rd SW",
    "sg:city":"Camden",
    "sg:classifiers":[
        {
            "category":"Shopping",
            "subcategory":"Discount & Variety Stores",
            "type":"Retail Goods"
        }
    ],
    "sg:phone":"+1 870 231 4504",
    "sg:postcode":"71701",
    "sg:province":"AR",
    "wof:name":"Dollar General",
    "wof:placetype":"venue"
},
  "geometry": {"coordinates":[-92.84922899999999,33.536449],"type":"Point"}
}