{
  "type": "Feature",
  "properties": {
    "addr:full":"310 W State Highway 18 Manila AR 72442",
    "addr:housenumber":"310",
    "addr:postcode":"72442",
    "addr:street":"W State Highway 18",
    "iso:country":"US",
    "sg:address":"310 W State Highway 18",
    "sg:city":"Manila",
    "sg:classifiers":[
        {
            "category":"Autos & Motor Vehicles",
            "subcategory":"Automobile Sales",
            "type":"Retail Goods"
        },
        {
            "category":"Retail",
            "subcategory":"Auto Repair",
            "type":"Services"
        }
    ],
    "sg:phone":"+1 870 561 4333",
    "sg:postcode":"72442",
    "sg:province":"AR",
    "sg:tags":[
        "dealers-used",
        "car",
        "used",
        "cars-wholesale"
    ],
    "wof:name":"City Auto",
    "wof:placetype":"venue"
},
  "geometry": {"coordinates":[-90.17782,35.88333],"type":"Point"}
}