{
  "type": "Feature",
  "properties": {
    "iso:country":"US",
    "sg:address":"112 W Center St",
    "sg:city":"Fayetteville",
    "sg:classifiers":[
        {
            "category":"Professional",
            "subcategory":"Accounting & Tax Preparation",
            "type":"Services"
        }
    ],
    "sg:phone":"+1 479 443 7878",
    "sg:postcode":"72701",
    "sg:province":"AR",
    "sg:tags":[
        "bookkeeping"
    ],
    "wof:name":"John S Latour CPA",
    "wof:placetype":"venue"
},
  "geometry": {"coordinates":[-94.161732,36.062751],"type":"Point"}
}