{
  "type": "Feature",
  "properties": {
    "addr:full":"321 Olive St Hot Springs AR 71901",
    "addr:housenumber":"321",
    "addr:postcode":"71901",
    "addr:street":"Olive St",
    "iso:country":"US",
    "sg:address":"321 Olive St",
    "sg:city":"Hot Springs",
    "sg:classifiers":[
        {
            "category":"Home & Garden",
            "subcategory":"Furniture",
            "type":"Retail Goods"
        },
        {
            "category":"Real Estate",
            "subcategory":"Real Estate Operator",
            "type":"Services"
        }
    ],
    "sg:phone":"+1 501 624 6554",
    "sg:postcode":"71901",
    "sg:province":"AR",
    "sg:tags":[
        "building",
        "apartment",
        "furnishing"
    ],
    "wof:name":"Boardwalk Apartments",
    "wof:placetype":"venue"
},
  "geometry": {"coordinates":[-93.05613099999999,34.507173],"type":"Point"}
}