{
  "type": "Feature",
  "properties": {
    "iso:country":"US",
    "sg:address":"2825 Highway 35 N",
    "sg:city":"Sheridan",
    "sg:classifiers":[
        {
            "category":"Professional",
            "subcategory":"Lawyer & Legal Services",
            "type":"Services"
        }
    ],
    "sg:phone":"+1 870 942 7523",
    "sg:postcode":"72150",
    "sg:province":"AR",
    "sg:tags":[
        "attorney",
        "law",
        "malpractice"
    ],
    "wof:name":"James Mason Rea",
    "wof:placetype":"venue"
},
  "geometry": {"coordinates":[-92.418842,34.328277],"type":"Point"}
}