{
  "type": "Feature",
  "properties": {
    "iso:country":"US",
    "sg:address":"7111 Russwood Ln E",
    "sg:city":"Mabelvale",
    "sg:classifiers":[
        {
            "category":"Professional",
            "subcategory":"Engineering",
            "type":"Services"
        }
    ],
    "sg:phone":"+1 501 888 1459",
    "sg:postcode":"72103",
    "sg:province":"AR",
    "wof:name":"Burnside Tool Design Inc",
    "wof:placetype":"venue"
},
  "geometry": {"coordinates":[-92.362752,34.606512],"type":"Point"}
}