{
  "type": "Feature",
  "properties": {
    "addr:full":"989 Industrial Park Rd Heber Springs AR 72543",
    "addr:housenumber":"989",
    "addr:postcode":"72543",
    "addr:street":"Industrial Park Rd",
    "iso:country":"US",
    "sg:address":"989 Industrial Park Rd",
    "sg:city":"Heber Springs",
    "sg:classifiers":[
        {
            "category":"Health Services",
            "subcategory":"Health Practitioner",
            "type":"Services"
        }
    ],
    "sg:phone":"+1 501 362 7025",
    "sg:postcode":"72543",
    "sg:province":"AR",
    "wof:name":"Matthews Physical Therphy Inc",
    "wof:placetype":"venue"
},
  "geometry": {"coordinates":[-91.948716,35.51275],"type":"Point"}
}