{
  "type": "Feature",
  "properties": {
    "iso:country":"US",
    "sg:address":"3114 Trinity Blvd",
    "sg:city":"Texarkana",
    "sg:classifiers":[
        {
            "category":"Freight",
            "type":"Transportation"
        }
    ],
    "sg:phone":"+1 870 772 4314",
    "sg:postcode":"71854",
    "sg:province":"TX",
    "sg:tags":[
        "commercial",
        "storage"
    ],
    "wof:name":"Payless Storage Inc",
    "wof:placetype":"venue"
},
  "geometry": {"coordinates":[-94.009663,33.477844],"type":"Point"}
}