{
  "type": "Feature",
  "properties": {
    "addr:full":"501 Harrod Rd White Hall AR 71602",
    "addr:housenumber":"501",
    "addr:postcode":"71602",
    "addr:street":"Harrod Rd",
    "iso:country":"US",
    "sg:address":"501 Harrod Rd",
    "sg:city":"White Hall",
    "sg:classifiers":[
        {
            "category":"Professional",
            "subcategory":"Business Services",
            "type":"Services"
        }
    ],
    "sg:phone":"+1 870 247 9466",
    "sg:postcode":"71602",
    "sg:province":"AR",
    "wof:name":"Studdard Enterprises Inc",
    "wof:placetype":"venue"
},
  "geometry": {"coordinates":[-92.076634,34.268061],"type":"Point"}
}