{
  "type": "Feature",
  "properties": {
    "addr:full":"500 S Whitehead Dr De Witt AR 72042",
    "addr:housenumber":"500",
    "addr:postcode":"72042",
    "addr:street":"S Whitehead Dr De Witt",
    "iso:country":"US",
    "sg:address":"500 S Whitehead Dr",
    "sg:city":"De Witt",
    "sg:classifiers":[
        {
            "category":"Autos & Motor Vehicles",
            "subcategory":"Automobile Sales",
            "type":"Retail Goods"
        }
    ],
    "sg:phone":"+1 870 946 2594",
    "sg:postcode":"72042",
    "sg:province":"AR",
    "sg:tags":[
        "car",
        "dealer"
    ],
    "wof:name":"Horton Motors",
    "wof:placetype":"venue"
},
  "geometry": {"coordinates":[-91.324482,34.290272],"type":"Point"}
}