{
  "type": "Feature",
  "properties": {
    "iso:country":"US",
    "sg:address":"415 Golf Links Rd",
    "sg:city":"Hot Springs",
    "sg:classifiers":[
        {
            "category":"Freight",
            "type":"Transportation"
        },
        {
            "category":"Recreation",
            "subcategory":"Marina",
            "type":"Entertainment"
        }
    ],
    "sg:phone":"+1 501 609 0002",
    "sg:postcode":"71901",
    "sg:province":"AR",
    "sg:tags":[
        "commercial",
        "operation",
        "storage"
    ],
    "wof:name":"A A A Storage World",
    "wof:placetype":"venue"
},
  "geometry": {"coordinates":[-93.04826,34.475562],"type":"Point"}
}