{
  "type": "Feature",
  "properties": {
    "addr:full":"187 S Broadview St Greenbrier AR 72058",
    "addr:housenumber":"187",
    "addr:postcode":"72058",
    "addr:street":"S Broadview St",
    "iso:country":"US",
    "sg:address":"187 S Broadview St",
    "sg:city":"Greenbrier",
    "sg:classifiers":[
        {
            "category":"Home & Garden",
            "subcategory":"Building Materials",
            "type":"Retail Goods"
        }
    ],
    "sg:phone":"+1 501 679 4985",
    "sg:postcode":"72058",
    "sg:province":"AR",
    "sg:tags":[
        "mixed",
        "concrete"
    ],
    "wof:name":"Computa-Mix Inc",
    "wof:placetype":"venue"
},
  "geometry": {"coordinates":[-92.388464,35.211003],"type":"Point"}
}