{
  "type": "Feature",
  "properties": {
    "iso:country":"US",
    "sg:address":"105 S Montgomery St",
    "sg:city":"Clarksville",
    "sg:classifiers":[
        {
            "category":"Personal",
            "subcategory":"Beauty Salon",
            "type":"Services"
        }
    ],
    "sg:phone":"+1 479 705 1190",
    "sg:postcode":"72830",
    "sg:province":"AR",
    "wof:name":"Hair Cottage",
    "wof:placetype":"venue"
},
  "geometry": {"coordinates":[-93.47393599999999,35.471104],"type":"Point"}
}