{
  "type": "Feature",
  "properties": {
    "addr:full":"42 W Ash St Brinkley AR 72021",
    "addr:housenumber":"42",
    "addr:postcode":"72021",
    "addr:street":"W Ash St",
    "iso:country":"US",
    "sg:address":"42 W Ash St",
    "sg:city":"Brinkley",
    "sg:classifiers":[
        {
            "category":"Organizations",
            "subcategory":"Religious Organization",
            "type":"Services"
        }
    ],
    "sg:phone":"+1 870 734 1899",
    "sg:postcode":"72021",
    "sg:province":"AR",
    "sg:tags":[
        "church"
    ],
    "wof:name":"Brown Chapel",
    "wof:placetype":"venue"
},
  "geometry": {"coordinates":[-91.189527,34.885846],"type":"Point"}
}