{
  "type": "Feature",
  "properties": {
    "iso:country":"US",
    "sg:address":"222 Melrose Cir",
    "sg:city":"North Little Rock",
    "sg:classifiers":[
        {
            "category":"Retail",
            "subcategory":"Repair Shop",
            "type":"Services"
        }
    ],
    "sg:phone":"+1 501 682 1544",
    "sg:postcode":"72114",
    "sg:province":"AR",
    "wof:name":"Shortcut Upholstery",
    "wof:placetype":"venue"
},
  "geometry": {"coordinates":[-92.273073,34.761916],"type":"Point"}
}