{
  "type": "Feature",
  "properties": {
    "iso:country":"US",
    "sg:address":"351 S 5th St",
    "sg:city":"Ashdown",
    "sg:classifiers":[
        {
            "category":"Food & Beverages",
            "subcategory":"Groceries & Convenience Stores",
            "type":"Retail Goods"
        }
    ],
    "sg:phone":"+1 870 898 2199",
    "sg:postcode":"71822",
    "sg:province":"AR",
    "wof:name":"Stop Quick Two",
    "wof:placetype":"venue"
},
  "geometry": {"coordinates":[-94.135554,33.669092],"type":"Point"}
}