{
  "type": "Feature",
  "properties": {
    "iso:country":"US",
    "sg:address":"384 N Main Ave",
    "sg:city":"Fayetteville",
    "sg:classifiers":[
        {
            "category":"Retail",
            "subcategory":"Auto Repair",
            "type":"Services"
        }
    ],
    "sg:phone":"+1 479 527 6599",
    "sg:postcode":"72701",
    "sg:province":"AR",
    "wof:name":"Joe's Auto Repair",
    "wof:placetype":"venue"
},
  "geometry": {"coordinates":[-94.173852,35.99865],"type":"Point"}
}