{
  "type": "Feature",
  "properties": {
    "iso:country":"US",
    "sg:address":"1000 S Futrall Dr",
    "sg:city":"Fayetteville",
    "sg:classifiers":[
        {
            "category":"Travel",
            "subcategory":"Hotels & Motels",
            "type":"Entertainment"
        }
    ],
    "sg:phone":"+1 479 442 3041",
    "sg:postcode":"72701",
    "sg:province":"AR",
    "wof:name":"Red Roof Inn-Fayetteville",
    "wof:placetype":"venue"
},
  "geometry": {"coordinates":[-94.193411,36.054181],"type":"Point"}
}