{
  "type": "Feature",
  "properties": {
    "iso:country":"US",
    "sg:address":"2001 Main St",
    "sg:city":"Van Buren",
    "sg:classifiers":[
        {
            "category":"Shopping",
            "subcategory":"Used Merchandise",
            "type":"Retail Goods"
        }
    ],
    "sg:phone":"+1 479 410 3060",
    "sg:postcode":"72956",
    "sg:province":"AR",
    "sg:tags":[
        "clothing"
    ],
    "wof:name":"Nancy's",
    "wof:placetype":"venue"
},
  "geometry": {"coordinates":[-94.337231,35.436568],"type":"Point"}
}