{
  "type": "Feature",
  "properties": {
    "iso:country":"US",
    "sg:address":"1902 Pin Oak Dr",
    "sg:city":"Springdale",
    "sg:classifiers":[
        {
            "category":"Recreation",
            "type":"Entertainment"
        }
    ],
    "sg:phone":"+1 479 872 8287",
    "sg:postcode":"72762",
    "sg:province":"AR",
    "sg:tags":[
        "instruction",
        "gymnastic"
    ],
    "wof:name":"Tumblebus",
    "wof:placetype":"venue"
},
  "geometry": {"coordinates":[-94.15603,36.178088],"type":"Point"}
}