{
  "type": "Feature",
  "properties": {
    "iso:country":"US",
    "sg:address":"561 Columbia Rd 61",
    "sg:city":"Magnolia",
    "sg:classifiers":[
        {
            "category":"Building & Trades",
            "subcategory":"Construction",
            "type":"Services"
        }
    ],
    "sg:phone":"+1 870 234 7653",
    "sg:postcode":"71753",
    "sg:province":"AR",
    "sg:tags":[
        "roofing",
        "contractor"
    ],
    "wof:name":"Arma",
    "wof:placetype":"venue"
},
  "geometry": {"coordinates":[-93.192378,33.283322],"type":"Point"}
}