{
  "type": "Feature",
  "properties": {
    "addr:full":"561 Columbia Rd 61 Magnolia AR 71753",
    "addr:housenumber":"561;61",
    "addr:postcode":"71753",
    "addr:street":"Columbia Rd;Magnolia",
    "iso:country":"US",
    "sg:address":"561 Columbia Rd 61",
    "sg:city":"Magnolia",
    "sg:classifiers":[
        {
            "category":"Building & Trades",
            "subcategory":"Construction",
            "type":"Services"
        }
    ],
    "sg:phone":"+1 870 234 7653",
    "sg:postcode":"71753",
    "sg:province":"AR",
    "sg:tags":[
        "roofing",
        "contractor"
    ],
    "wof:name":"Arma",
    "wof:placetype":"venue"
},
  "geometry": {"coordinates":[-93.19237800000001,33.283322],"type":"Point"}
}