{
  "type": "Feature",
  "properties": {
    "iso:country":"US",
    "sg:address":"718 Harris Rd",
    "sg:city":"Jacksonville",
    "sg:classifiers":[
        {
            "category":"Education",
            "subcategory":"School",
            "type":"Public Place"
        }
    ],
    "sg:phone":"+1 501 982 9436",
    "sg:postcode":"72076",
    "sg:province":"AR",
    "wof:name":"North Pulaski High School",
    "wof:placetype":"venue"
},
  "geometry": {"coordinates":[-92.159585,34.883435],"type":"Point"}
}