{
  "type": "Feature",
  "properties": {
    "iso:country":"US",
    "sg:address":"100 Bringler Dr",
    "sg:city":"Maumelle",
    "sg:classifiers":[
        {
            "category":"Social Services",
            "subcategory":"Retirement Home",
            "type":"Services"
        }
    ],
    "sg:phone":"+1 501 803 0756",
    "sg:postcode":"72113",
    "sg:province":"AR",
    "sg:tags":[
        "community"
    ],
    "wof:name":"Senior Care of Maumelle",
    "wof:placetype":"venue"
},
  "geometry": {"coordinates":[-92.395526,34.869167],"type":"Point"}
}