{
  "type": "Feature",
  "properties": {
    "iso:country":"US",
    "sg:address":"103 W Washington St",
    "sg:city":"Camden",
    "sg:classifiers":[
        {
            "category":"Shopping",
            "subcategory":"Books",
            "type":"Retail Goods"
        }
    ],
    "sg:phone":"+1 870 837 1111",
    "sg:postcode":"71701",
    "sg:province":"AR",
    "wof:name":"Corner Post Discount Books",
    "wof:placetype":"venue"
},
  "geometry": {"coordinates":[-92.829708,33.585989],"type":"Point"}
}