{
  "type": "Feature",
  "properties": {
    "iso:country":"US",
    "sg:address":"15072 Crawford Pt",
    "sg:city":"Rogers",
    "sg:classifiers":[
        {
            "category":"Sports & Exercise",
            "subcategory":"Sports Center",
            "type":"Entertainment"
        }
    ],
    "sg:phone":"+1 479 685 1308",
    "sg:postcode":"72756",
    "sg:province":"AR",
    "wof:name":"Arkansas War Cats Football Club, Inc.",
    "wof:placetype":"venue"
},
  "geometry": {"coordinates":[-94.048316,36.315023],"type":"Point"}
}