{
  "type": "Feature",
  "properties": {
    "iso:country":"US",
    "sg:address":"14965 Country Pl",
    "sg:city":"Alexander",
    "sg:classifiers":[
        {
            "category":"Building & Trades",
            "subcategory":"Construction",
            "type":"Services"
        }
    ],
    "sg:phone":"+1 501 847 1172",
    "sg:postcode":"72002",
    "sg:province":"AR",
    "sg:tags":[
        "nonresidential"
    ],
    "wof:name":"Arkansas Barn Sales Inc",
    "wof:placetype":"venue"
},
  "geometry": {"coordinates":[-92.584513,34.701512],"type":"Point"}
}