{
  "type": "Feature",
  "properties": {
    "addr:full":"143 Cofer Rd Searcy AR 72143",
    "addr:housenumber":"143",
    "addr:postcode":"72143",
    "addr:street":"Cofer Rd",
    "iso:country":"US",
    "sg:address":"143 Cofer Rd",
    "sg:city":"Searcy",
    "sg:classifiers":[
        {
            "category":"Farming",
            "subcategory":"Farm",
            "type":"Manufacturing & Wholesale Goods"
        }
    ],
    "sg:phone":"+1 501 268 5971",
    "sg:postcode":"72143",
    "sg:province":"AR",
    "sg:tags":[
        "crop",
        "general"
    ],
    "wof:name":"Cofer Brothers Farms",
    "wof:placetype":"venue"
},
  "geometry": {"coordinates":[-91.82285,35.247299],"type":"Point"}
}