{
  "type": "Feature",
  "properties": {
    "iso:country":"US",
    "sg:address":"724 2nd St",
    "sg:city":"Conway",
    "sg:classifiers":[
        {
            "category":"Home & Garden",
            "subcategory":"Home Furnishings",
            "type":"Retail Goods"
        },
        {
            "category":"Building & Trades",
            "subcategory":"Electrical",
            "type":"Services"
        },
        {
            "category":"Utilities",
            "subcategory":"Cable",
            "type":"Services"
        }
    ],
    "sg:phone":"+1 501 329 3861",
    "sg:postcode":"72032",
    "sg:province":"AR",
    "sg:tags":[
        "industrial",
        "electrician",
        "electric",
        "light",
        "tube",
        "fixture",
        "lighting",
        "contractors-commercial",
        "bulb"
    ],
    "wof:name":"Hambuchen Lighting",
    "wof:placetype":"venue"
},
  "geometry": {"coordinates":[-92.426685,35.089345],"type":"Point"}
}