{
  "type": "Feature",
  "properties": {
    "iso:country":"US",
    "sg:address":"321 W Bradley",
    "sg:city":"Chidester",
    "sg:classifiers":[
        {
            "category":"Organizations",
            "subcategory":"Religious Organization",
            "type":"Services"
        }
    ],
    "sg:phone":"+1 870 685 2471",
    "sg:postcode":"71726",
    "sg:province":"AR",
    "sg:tags":[
        "church"
    ],
    "wof:name":"Bethel AME Church",
    "wof:placetype":"venue"
},
  "geometry": {"coordinates":[-93.02244899999999,33.699165],"type":"Point"}
}