{
  "type": "Feature",
  "properties": {
    "iso:country":"US",
    "sg:address":"520 State Hwy 19",
    "sg:city":"Prescott",
    "sg:classifiers":[
        {
            "category":"Autos & Motor Vehicles",
            "subcategory":"Fuel & Gas Station",
            "type":"Retail Goods"
        }
    ],
    "sg:phone":"+1 870 887 3890",
    "sg:postcode":"71857",
    "sg:province":"AR",
    "sg:tags":[
        "station",
        "gasoline"
    ],
    "wof:name":"Fuel Express Inc",
    "wof:placetype":"venue"
},
  "geometry": {"coordinates":[-93.385282,33.791186],"type":"Point"}
}