{
  "type": "Feature",
  "properties": {
    "addr:full":"1130 Chestnut St Magnolia AR 71753",
    "addr:housenumber":"1130",
    "addr:postcode":"71753",
    "addr:street":"Chestnut St",
    "iso:country":"US",
    "sg:address":"1130 Chestnut St",
    "sg:city":"Magnolia",
    "sg:classifiers":[
        {
            "category":"Retail",
            "subcategory":"Repair Shop",
            "type":"Services"
        }
    ],
    "sg:phone":"+1 870 234 3675",
    "sg:postcode":"71753",
    "sg:province":"AR",
    "wof:name":"Timberland Marine",
    "wof:placetype":"venue"
},
  "geometry": {"coordinates":[-93.224526,33.27573],"type":"Point"}
}