{
  "type": "Feature",
  "properties": {
    "iso:country":"US",
    "sg:address":"10504 Maumelle Blvd",
    "sg:city":"N Little Rock",
    "sg:classifiers":[
        {
            "category":"Wholesale",
            "subcategory":"Machinery & Supplies",
            "type":"Manufacturing & Wholesale Goods"
        }
    ],
    "sg:phone":"+1 501 753 4100",
    "sg:postcode":"72113",
    "sg:province":"AR",
    "sg:tags":[
        "contractor"
    ],
    "sg:website":"www.agprocompanies.com",
    "wof:name":"A G Pro Central Ar",
    "wof:placetype":"venue"
},
  "geometry": {"coordinates":[-92.377275,34.824935],"type":"Point"}
}