{
  "type": "Feature",
  "properties": {
    "iso:country":"US",
    "sg:address":"1493 Forest Hills Blvd",
    "sg:city":"Bella Vista",
    "sg:classifiers":[
        {
            "category":"Real Estate",
            "subcategory":"Surveying",
            "type":"Services"
        }
    ],
    "sg:phone":"+1 479 925 1733",
    "sg:postcode":"72715",
    "sg:province":"AR",
    "wof:name":"Cochrans Surveying",
    "wof:placetype":"venue"
},
  "geometry": {"coordinates":[-94.296553,36.468225],"type":"Point"}
}