{
  "type": "Feature",
  "properties": {
    "iso:country":"US",
    "sg:address":"154 Ashley Rd 467",
    "sg:city":"Hamburg",
    "sg:classifiers":[
        {
            "category":"Professional",
            "type":"Services"
        }
    ],
    "sg:phone":"+1 870 853 9380",
    "sg:postcode":"71646",
    "sg:province":"AR",
    "wof:name":"Standridge Flying Service",
    "wof:placetype":"venue"
},
  "geometry": {"coordinates":[-91.907463,33.262071],"type":"Point"}
}