{
  "type": "Feature",
  "properties": {
    "iso:country":"US",
    "sg:address":"1726 Acorn Dr",
    "sg:city":"Rogers",
    "sg:classifiers":[
        {
            "category":"Home & Garden",
            "subcategory":"Carpets & Floor Coverings",
            "type":"Retail Goods"
        }
    ],
    "sg:phone":"+1 479 621 0077",
    "sg:postcode":"72756",
    "sg:province":"AR",
    "sg:tags":[
        "retailer",
        "rug",
        "dealer"
    ],
    "wof:name":"ABC Decorating Specialties Inc",
    "wof:placetype":"venue"
},
  "geometry": {"coordinates":[-94.141198,36.357245],"type":"Point"}
}