{
  "type": "Feature",
  "properties": {
    "iso:country":"US",
    "sg:address":"3203 NE Red Hawk Dr",
    "sg:city":"Bentonville",
    "sg:classifiers":[
        {
            "category":"Professional",
            "subcategory":"Management & Consulting",
            "type":"Services"
        }
    ],
    "sg:phone":"+1 479 271 6608",
    "sg:postcode":"72712",
    "sg:province":"AR",
    "sg:tags":[
        "retail",
        "direct",
        "sales"
    ],
    "wof:name":"Springs Industries Inc",
    "wof:placetype":"venue"
},
  "geometry": {"coordinates":[-94.174284,36.384738],"type":"Point"}
}