{
  "type": "Feature",
  "properties": {
    "addr:full":"518 S Thompson St Springdale AR 72764",
    "addr:housenumber":"518",
    "addr:postcode":"72764",
    "addr:street":"S Thompson St",
    "iso:country":"US",
    "sg:address":"518 S Thompson St",
    "sg:city":"Springdale",
    "sg:classifiers":[
        {
            "category":"Shopping",
            "subcategory":"Clothing, Apparel, & Fashions",
            "type":"Retail Goods"
        }
    ],
    "sg:phone":"+1 479 751 1290",
    "sg:postcode":"72764",
    "sg:province":"AR",
    "sg:tags":[
        "wig",
        "hair",
        "hairpiece",
        "toupee",
        "piece"
    ],
    "wof:name":"Wig Villa",
    "wof:placetype":"venue"
},
  "geometry": {"coordinates":[-94.138741,36.180729],"type":"Point"}
}