{
  "type": "Feature",
  "properties": {
    "iso:country":"US",
    "sg:address":"9695 Highway 115",
    "sg:city":"Pocahontas",
    "sg:classifiers":[
        {
            "category":"Building & Trades",
            "subcategory":"Construction",
            "type":"Services"
        }
    ],
    "sg:phone":"+1 870 647 2959",
    "sg:postcode":"72455",
    "sg:province":"AR",
    "sg:tags":[
        "roofing",
        "industrial",
        "contractors-commercial",
        "contractor"
    ],
    "wof:name":"Barr's Bill Roofing",
    "wof:placetype":"venue"
},
  "geometry": {"coordinates":[-90.929704,36.362527],"type":"Point"}
}