{
  "type": "Feature",
  "properties": {
    "iso:country":"US",
    "sg:address":"1805 W Beebe Capps Expy",
    "sg:city":"Searcy",
    "sg:classifiers":[
        {
            "category":"Restaurant",
            "type":"Food & Drink"
        }
    ],
    "sg:phone":"+1 501 368 8773",
    "sg:postcode":"72143",
    "sg:province":"AR",
    "wof:name":"Popeye's Chicken & Biscuits",
    "wof:placetype":"venue"
},
  "geometry": {"coordinates":[-91.756333,35.247346],"type":"Point"}
}