{
  "type": "Feature",
  "properties": {
    "iso:country":"US",
    "sg:address":"219 W Main St",
    "sg:city":"Farmington",
    "sg:classifiers":[
        {
            "category":"Shopping",
            "subcategory":"Discount & Variety Stores",
            "type":"Retail Goods"
        }
    ],
    "sg:phone":"+1 479 267 4488",
    "sg:postcode":"72730",
    "sg:province":"AR",
    "wof:name":"Dollar General",
    "wof:placetype":"venue"
},
  "geometry": {"coordinates":[-94.250855,36.040677],"type":"Point"}
}