{
  "type": "Feature",
  "properties": {
    "iso:country":"US",
    "sg:address":"7786 Old Payneway Ln",
    "sg:city":"Trumann",
    "sg:classifiers":[
        {
            "category":"Professional",
            "subcategory":"Business Services",
            "type":"Services"
        }
    ],
    "sg:phone":"+1 870 593 2080",
    "sg:postcode":"72472",
    "sg:province":"AR",
    "wof:name":"Partnership Bay Village Farms",
    "wof:placetype":"venue"
},
  "geometry": {"coordinates":[-90.483541,35.562796],"type":"Point"}
}