{
  "type": "Feature",
  "properties": {
    "addr:full":"111 N Main St Cave City AR 72521",
    "addr:housenumber":"111",
    "addr:postcode":"72521",
    "addr:street":"N Main St",
    "iso:country":"US",
    "sg:address":"111 N Main St",
    "sg:city":"Cave City",
    "sg:classifiers":[
        {
            "category":"Banks & Credit Unions",
            "subcategory":"Bank",
            "type":"Services"
        }
    ],
    "sg:phone":"+1 870 283 6931",
    "sg:postcode":"72521",
    "sg:province":"AR",
    "sg:tags":[
        "money",
        "transfer"
    ],
    "wof:name":"Western Union Town & Country",
    "wof:placetype":"venue"
},
  "geometry": {"coordinates":[-91.548444,35.941602],"type":"Point"}
}