{
  "type": "Feature",
  "properties": {
    "iso:country":"US",
    "sg:address":"1723 Main St",
    "sg:city":"Van Buren",
    "sg:classifiers":[
        {
            "category":"Shopping",
            "subcategory":"Computers & Home Electronics",
            "type":"Retail Goods"
        }
    ],
    "sg:phone":"+1 479 474 3700",
    "sg:postcode":"72956",
    "sg:province":"AR",
    "wof:name":"Sound World",
    "wof:placetype":"venue"
},
  "geometry": {"coordinates":[-94.34069,35.436672],"type":"Point"}
}