{
  "type": "Feature",
  "properties": {
    "addr:full":"409 E 4th St Russellville AR 72801",
    "addr:housenumber":"409",
    "addr:postcode":"72801",
    "addr:street":"E 4Th St",
    "iso:country":"US",
    "sg:address":"409 E 4th St",
    "sg:city":"Russellville",
    "sg:classifiers":[
        {
            "category":"Professional",
            "subcategory":"Accounting & Tax Preparation",
            "type":"Services"
        }
    ],
    "sg:phone":"+1 479 967 4439",
    "sg:postcode":"72801",
    "sg:province":"AR",
    "sg:tags":[
        "accountant"
    ],
    "wof:name":"Ricky Taylor CPA",
    "wof:placetype":"venue"
},
  "geometry": {"coordinates":[-93.12948,35.275076],"type":"Point"}
}