{
  "type": "Feature",
  "properties": {
    "iso:country":"US",
    "sg:address":"2473 N Fennchurch Way",
    "sg:city":"Fayetteville",
    "sg:classifiers":[
        {
            "category":"Professional",
            "subcategory":"Research",
            "type":"Services"
        }
    ],
    "sg:phone":"+1 479 443 4772",
    "sg:postcode":"72703",
    "sg:province":"AR",
    "wof:name":"Shields Research & Consulting",
    "wof:placetype":"venue"
},
  "geometry": {"coordinates":[-94.11133599999999,36.09649],"type":"Point"}
}