{
  "type": "Feature",
  "properties": {
    "addr:full":"601 Albert Pike Rd Hot Springs AR 71913",
    "addr:housenumber":"601",
    "addr:postcode":"71913",
    "addr:street":"Albert Pike Rd",
    "iso:country":"US",
    "sg:address":"601 Albert Pike Rd",
    "sg:city":"Hot Springs",
    "sg:classifiers":[
        {
            "category":"Wholesale",
            "subcategory":"Machinery & Supplies",
            "type":"Manufacturing & Wholesale Goods"
        }
    ],
    "sg:phone":"+1 501 623 7795",
    "sg:postcode":"71913",
    "sg:province":"AR",
    "sg:tags":[
        "equipment",
        "welding"
    ],
    "wof:name":"Stevens Inc Engine & Welding",
    "wof:placetype":"venue"
},
  "geometry": {"coordinates":[-93.075605,34.496204],"type":"Point"}
}