{
  "type": "Feature",
  "properties": {
    "addr:full":"3339 Central Ave Hot Springs AR 71913",
    "addr:housenumber":"3339",
    "addr:postcode":"71913",
    "addr:street":"Central Ave",
    "iso:country":"US",
    "sg:address":"3339 Central Ave",
    "sg:city":"Hot Springs",
    "sg:classifiers":[
        {
            "category":"Shopping",
            "subcategory":"Computers & Home Electronics",
            "type":"Retail Goods"
        }
    ],
    "sg:phone":"+1 501 767 5152",
    "sg:postcode":"71913",
    "sg:province":"AR",
    "sg:tags":[
        "equipment",
        "satellite",
        "system"
    ],
    "sg:website":"www.dishcash.com",
    "wof:name":"DISHCASH.COM",
    "wof:placetype":"venue"
},
  "geometry": {"coordinates":[-93.059769,34.475209],"type":"Point"}
}