{
  "type": "Feature",
  "properties": {
    "addr:full":"2209 E Highland Dr Jonesboro AR 72401",
    "addr:housenumber":"2209",
    "addr:postcode":"72401",
    "addr:street":"E Highland Dr",
    "iso:country":"US",
    "sg:address":"2209 E Highland Dr",
    "sg:city":"Jonesboro",
    "sg:classifiers":[
        {
            "category":"Shopping",
            "subcategory":"Gifts & Souvenirs",
            "type":"Retail Goods"
        }
    ],
    "sg:phone":"+1 870 268 0016",
    "sg:postcode":"72401",
    "sg:province":"AR",
    "sg:tags":[
        "shop"
    ],
    "wof:name":"Tuesday Morning",
    "wof:placetype":"venue"
},
  "geometry": {"coordinates":[-90.679284,35.821148],"type":"Point"}
}