{
  "type": "Feature",
  "properties": {
    "addr:full":"1985 Allen Chapel Rd Batesville AR 72501",
    "addr:housenumber":"1985",
    "addr:postcode":"72501",
    "addr:street":"Allen Chapel Rd",
    "iso:country":"US",
    "sg:address":"1985 Allen Chapel Rd",
    "sg:city":"Batesville",
    "sg:classifiers":[
        {
            "category":"Shopping",
            "subcategory":"Gifts & Souvenirs",
            "type":"Retail Goods"
        }
    ],
    "sg:phone":"+1 870 251 2233",
    "sg:postcode":"72501",
    "sg:province":"AR",
    "wof:name":"Pac Rats",
    "wof:placetype":"venue"
},
  "geometry": {"coordinates":[-91.59978599999999,35.695961],"type":"Point"}
}