{
  "type": "Feature",
  "properties": {
    "iso:country":"US",
    "sg:address":"3061 N Market Ave",
    "sg:city":"Fayetteville",
    "sg:classifiers":[
        {
            "category":"Building & Trades",
            "subcategory":"Construction",
            "type":"Services"
        }
    ],
    "sg:phone":"+1 479 444 6214",
    "sg:postcode":"72703",
    "sg:province":"AR",
    "sg:tags":[
        "contractor"
    ],
    "wof:name":"Environmental Protection Asso",
    "wof:placetype":"venue"
},
  "geometry": {"coordinates":[-94.143952,36.106949],"type":"Point"}
}