{
  "type": "Feature",
  "properties": {
    "addr:full":"300 Jackson Hts West Memphis AR 72301",
    "addr:housenumber":"300",
    "addr:postcode":"72301",
    "addr:street":"Jackson Hts",
    "iso:country":"US",
    "sg:address":"300 Jackson Hts",
    "sg:city":"West Memphis",
    "sg:classifiers":[
        {
            "category":"Health Services",
            "subcategory":"Nursing And Care Facility",
            "type":"Services"
        },
        {
            "category":"Real Estate",
            "subcategory":"Real Estate Agent",
            "type":"Services"
        }
    ],
    "sg:phone":"+1 870 702 6574",
    "sg:postcode":"72301",
    "sg:province":"AR",
    "sg:tags":[
        "home",
        "property",
        "management",
        "community",
        "retirement"
    ],
    "wof:name":"Senior Residences West Memphis",
    "wof:placetype":"venue"
},
  "geometry": {"coordinates":[-90.157746,35.141347],"type":"Point"}
}