{
  "type": "Feature",
  "properties": {
    "iso:country":"US",
    "sg:address":"23 Joe Hogan Ln",
    "sg:city":"Lonoke",
    "sg:classifiers":[
        {
            "category":"Government",
            "subcategory":"Office",
            "type":"Public Place"
        }
    ],
    "sg:phone":"+1 501 676 6963",
    "sg:postcode":"72086",
    "sg:province":"AR",
    "sg:tags":[
        "state"
    ],
    "sg:website":"www.agfc.com",
    "wof:name":"Joe Hogan Fish Hatchery",
    "wof:placetype":"venue"
},
  "geometry": {"coordinates":[-91.90951200000001,34.768679],"type":"Point"}
}