{
  "type": "Feature",
  "properties": {
    "addr:full":"3807 Malvern Rd Hot Springs AR 71901",
    "addr:housenumber":"3807",
    "addr:postcode":"71901",
    "addr:street":"Malvern Rd",
    "iso:country":"US",
    "sg:address":"3807 Malvern Rd",
    "sg:city":"Hot Springs",
    "sg:classifiers":[
        {
            "category":"Building & Trades",
            "subcategory":"Construction",
            "type":"Services"
        }
    ],
    "sg:phone":"+1 501 620 4960",
    "sg:postcode":"71901",
    "sg:province":"AR",
    "sg:tags":[
        "steel",
        "erectors"
    ],
    "wof:name":"Steel & Erection Svc Corp",
    "wof:placetype":"venue"
},
  "geometry": {"coordinates":[-92.966464,34.464132],"type":"Point"}
}