{
  "type": "Feature",
  "properties": {
    "addr:full":"13670 State Hwy 59 Gentry AR 72734",
    "addr:housenumber":"13670",
    "addr:postcode":"72734",
    "addr:street":"State Hwy 59",
    "iso:country":"US",
    "sg:address":"13670 State Hwy 59",
    "sg:city":"Gentry",
    "sg:classifiers":[
        {
            "category":"Retail",
            "subcategory":"Auto Repair",
            "type":"Services"
        }
    ],
    "sg:phone":"+1 479 736 2247",
    "sg:postcode":"72734",
    "sg:province":"AR",
    "sg:tags":[
        "general"
    ],
    "wof:name":"Express Fleet Maintenance",
    "wof:placetype":"venue"
},
  "geometry": {"coordinates":[-94.48612799999999,36.232176],"type":"Point"}
}