{
  "type": "Feature",
  "properties": {
    "iso:country":"US",
    "sg:address":"11586 Cedar Dr",
    "sg:city":"Garfield",
    "sg:classifiers":[
        {
            "category":"Shopping",
            "type":"Retail Goods"
        }
    ],
    "sg:phone":"+1 479 359 0050",
    "sg:postcode":"72732",
    "sg:province":"AR",
    "sg:tags":[
        "merchandise"
    ],
    "wof:name":"Turner S Country Store",
    "wof:placetype":"venue"
},
  "geometry": {"coordinates":[-93.905552,36.385456],"type":"Point"}
}