{
  "type": "Feature",
  "properties": {
    "iso:country":"US",
    "sg:address":"1436 Cooper Rd",
    "sg:city":"Malvern",
    "sg:classifiers":[
        {
            "category":"Place Of Worship",
            "subcategory":"Church",
            "type":"Public Place"
        },
        {
            "category":"Place Of Worship",
            "type":"Public Place"
        },
        {
            "category":"Organizations",
            "subcategory":"Religious Organization",
            "type":"Services"
        }
    ],
    "sg:phone":"+1 501 337 7626",
    "sg:postcode":"72104",
    "sg:province":"AR",
    "sg:tags":[
        "god",
        "god-independent",
        "churches-assemblies",
        "denomination",
        "churches-interdenominational",
        "churches-various"
    ],
    "wof:name":"Cooper Assembly of God Church",
    "wof:placetype":"venue"
},
  "geometry": {"coordinates":[-92.777327,34.426557],"type":"Point"}
}