{
  "type": "Feature",
  "properties": {
    "addr:full":"520 Little River 13 Foreman AR 71836",
    "addr:housenumber":"520;13",
    "addr:postcode":"71836",
    "addr:street":"Little River",
    "iso:country":"US",
    "sg:address":"520 Little River 13",
    "sg:city":"Foreman",
    "sg:classifiers":[
        {
            "category":"Retail",
            "subcategory":"Repair Shop",
            "type":"Services"
        }
    ],
    "sg:phone":"+1 870 542 6462",
    "sg:postcode":"71836",
    "sg:province":"AR",
    "sg:tags":[
        "freezers-repair",
        "refrigerator"
    ],
    "wof:name":"Gene S Refrigeration Serv",
    "wof:placetype":"venue"
},
  "geometry": {"coordinates":[-94.383335,33.726371],"type":"Point"}
}