{
  "type": "Feature",
  "properties": {
    "iso:country":"US",
    "sg:address":"402 S Reynolds Rd",
    "sg:city":"Bryant",
    "sg:classifiers":[
        {
            "category":"Shopping",
            "subcategory":"Used Merchandise",
            "type":"Retail Goods"
        }
    ],
    "sg:phone":"+1 501 847 5197",
    "sg:postcode":"72022",
    "sg:province":"AR",
    "wof:name":"Elite Repeat For Kids",
    "wof:placetype":"venue"
},
  "geometry": {"coordinates":[-92.48982700000001,34.591662],"type":"Point"}
}