{
  "type": "Feature",
  "properties": {
    "iso:country":"US",
    "sg:address":"879 Eden Cir",
    "sg:city":"Fayetteville",
    "sg:classifiers":[
        {
            "category":"Building & Trades",
            "subcategory":"Landscaping Services",
            "type":"Services"
        }
    ],
    "sg:phone":"+1 479 251 7636",
    "sg:postcode":"72701",
    "sg:province":"AR",
    "sg:tags":[
        "landscape",
        "contractor"
    ],
    "wof:name":"Delray's Lawn & Landscape Svc",
    "wof:placetype":"venue"
},
  "geometry": {"coordinates":[-94.174329,36.03977],"type":"Point"}
}