{
  "type": "Feature",
  "properties": {
    "iso:country":"US",
    "sg:address":"1034 Village Dr",
    "sg:city":"Arkadelphia",
    "sg:classifiers":[
        {
            "category":"Building & Trades",
            "subcategory":"Construction",
            "type":"Services"
        }
    ],
    "sg:phone":"+1 870 246 2377",
    "sg:postcode":"71923",
    "sg:province":"AR",
    "sg:tags":[
        "general",
        "contractor"
    ],
    "wof:name":"Harrington Construction Co",
    "wof:placetype":"venue"
},
  "geometry": {"coordinates":[-93.077027,34.139921],"type":"Point"}
}