{
  "type": "Feature",
  "properties": {
    "iso:country":"US",
    "sg:address":"6709 Lantana Rd",
    "sg:city":"Little Rock",
    "sg:classifiers":[
        {
            "category":"Social Services",
            "subcategory":"Child Care",
            "type":"Services"
        }
    ],
    "sg:phone":"+1 501 568 1342",
    "sg:postcode":"72209",
    "sg:province":"AR",
    "sg:tags":[
        "day"
    ],
    "wof:name":"Eloise Goss Dcfh",
    "wof:placetype":"venue"
},
  "geometry": {"coordinates":[-92.352262,34.674446],"type":"Point"}
}