{
  "type": "Feature",
  "properties": {
    "iso:country":"US",
    "sg:address":"814 Main St",
    "sg:city":"Arkadelphia",
    "sg:classifiers":[
        {
            "category":"Autos & Motor Vehicles",
            "subcategory":"Auto Supplies",
            "type":"Retail Goods"
        }
    ],
    "sg:phone":"+1 501 605 0606",
    "sg:postcode":"71923",
    "sg:province":"AR",
    "sg:tags":[
        "automobile",
        "parts"
    ],
    "wof:name":"O'REILLY Auto Parts",
    "wof:placetype":"venue"
},
  "geometry": {"coordinates":[-93.05629500000001,34.119687],"type":"Point"}
}