{
  "type": "Feature",
  "properties": {
    "iso:country":"US",
    "sg:address":"531 Hwy 64 E",
    "sg:city":"Conway",
    "sg:classifiers":[
        {
            "category":"Autos & Motor Vehicles",
            "subcategory":"Automobile Sales",
            "type":"Retail Goods"
        }
    ],
    "sg:phone":"+1 501 505 8834",
    "sg:postcode":"72032",
    "sg:province":"AR",
    "sg:tags":[
        "car",
        "dealer"
    ],
    "wof:name":"Buy Rite Auto Sales",
    "wof:placetype":"venue"
},
  "geometry": {"coordinates":[-92.301025,35.078101],"type":"Point"}
}