{
  "type": "Feature",
  "properties": {
    "addr:full":"2700 W Main St Clarksville AR 72830",
    "addr:housenumber":"2700",
    "addr:postcode":"72830",
    "addr:street":"W Main St",
    "iso:country":"US",
    "sg:address":"2700 W Main St",
    "sg:city":"Clarksville",
    "sg:classifiers":[
        {
            "category":"Government",
            "subcategory":"Police Station",
            "type":"Public Place"
        }
    ],
    "sg:phone":"+1 479 754 3096",
    "sg:postcode":"72830",
    "sg:province":"AR",
    "sg:tags":[
        "department"
    ],
    "wof:name":"Hwy Patrol Field Offc-Troop J",
    "wof:placetype":"venue"
},
  "geometry": {"coordinates":[-93.423979,35.464734],"type":"Point"}
}