{
  "type": "Feature",
  "properties": {
    "iso:country":"US",
    "sg:address":"305 Eureka Ave",
    "sg:city":"Berryville",
    "sg:classifiers":[
        {
            "category":"Professional",
            "subcategory":"Business Services",
            "type":"Services"
        }
    ],
    "sg:phone":"+1 870 423 2997",
    "sg:postcode":"72616",
    "sg:province":"AR",
    "sg:tags":[
        "real estate"
    ],
    "wof:name":"Montgomery Larry RE & Auctnr",
    "wof:placetype":"venue"
},
  "geometry": {"coordinates":[-93.572413,36.366987],"type":"Point"}
}