{
  "type": "Feature",
  "properties": {
    "iso:country":"US",
    "sg:address":"901 Parker St",
    "sg:city":"N Little Rock",
    "sg:classifiers":[
        {
            "category":"Social Services",
            "type":"Services"
        }
    ],
    "sg:phone":"+1 501 374 3686",
    "sg:postcode":"72114",
    "sg:province":"AR",
    "sg:tags":[
        "organization",
        "welfare"
    ],
    "sg:website":"www.youthandfamilies.org",
    "wof:name":"Centers For Youth & Families",
    "wof:placetype":"venue"
},
  "geometry": {"coordinates":[-92.280791,34.763639],"type":"Point"}
}