{
  "type": "Feature",
  "properties": {
    "addr:full":"456 Lake Hamilton Dr Hot Springs AR 71913",
    "addr:housenumber":"456",
    "addr:postcode":"71913",
    "addr:street":"Lake Hamilton Dr",
    "iso:country":"US",
    "sg:address":"456 Lake Hamilton Dr",
    "sg:city":"Hot Springs",
    "sg:classifiers":[
        {
            "category":"Building & Trades",
            "subcategory":"Construction",
            "type":"Services"
        }
    ],
    "sg:phone":"+1 501 525 2226",
    "sg:postcode":"71913",
    "sg:province":"AR",
    "sg:tags":[
        "product",
        "asphalt"
    ],
    "wof:name":"Alternative Pavement Solutions",
    "wof:placetype":"venue"
},
  "geometry": {"coordinates":[-93.074015,34.446606],"type":"Point"}
}