{
  "type": "Feature",
  "properties": {
    "iso:country":"US",
    "sg:address":"239 Central Rd",
    "sg:city":"Arkadelphia",
    "sg:classifiers":[
        {
            "category":"Wholesale",
            "subcategory":"Machinery & Supplies",
            "type":"Manufacturing & Wholesale Goods"
        },
        {
            "category":"Recreation",
            "subcategory":"Arcade",
            "type":"Entertainment"
        }
    ],
    "sg:phone":"+1 870 246 3104",
    "sg:postcode":"71923",
    "sg:province":"AR",
    "sg:tags":[
        "ride",
        "park",
        "equipment",
        "device",
        "operator",
        "establishment",
        "amusement"
    ],
    "wof:name":"Brewer Electronic & Amusements",
    "wof:placetype":"venue"
},
  "geometry": {"coordinates":[-93.11856899999999,34.100923],"type":"Point"}
}