{
  "type": "Feature",
  "properties": {
    "addr:full":"1005 E 10th St Smackover AR 71762",
    "addr:housenumber":"1005",
    "addr:postcode":"71762",
    "addr:street":"E 10Th St",
    "iso:country":"US",
    "sg:address":"1005 E 10th St",
    "sg:city":"Smackover",
    "sg:classifiers":[
        {
            "category":"Shopping",
            "subcategory":"Clothing, Apparel, & Fashions",
            "type":"Retail Goods"
        }
    ],
    "sg:phone":"+1 870 725 2564",
    "sg:postcode":"71762",
    "sg:province":"AR",
    "sg:tags":[
        "shirts-custom",
        "made",
        "alterations-clothing"
    ],
    "wof:name":"Fashions By Jessie",
    "wof:placetype":"venue"
},
  "geometry": {"coordinates":[-92.714173,33.36031],"type":"Point"}
}