{
  "type": "Feature",
  "properties": {
    "addr:full":"19133 Engineer Rd Springdale AR 72764",
    "addr:housenumber":"19133",
    "addr:postcode":"72764",
    "addr:street":"Engineer Rd",
    "iso:country":"US",
    "sg:address":"19133 Engineer Rd",
    "sg:city":"Springdale",
    "sg:classifiers":[
        {
            "category":"Retail",
            "subcategory":"Auto Repair",
            "type":"Services"
        }
    ],
    "sg:phone":"+1 479 751 4502",
    "sg:postcode":"72764",
    "sg:province":"AR",
    "sg:tags":[
        "wrecker"
    ],
    "wof:name":"D & D Wrecker & Auto",
    "wof:placetype":"venue"
},
  "geometry": {"coordinates":[-94.049713,36.144708],"type":"Point"}
}