{
  "type": "Feature",
  "properties": {
    "addr:full":"706 Sue St Magnolia AR 71753",
    "addr:housenumber":"706",
    "addr:postcode":"71753",
    "addr:street":"Sue St",
    "iso:country":"US",
    "sg:address":"706 Sue St",
    "sg:city":"Magnolia",
    "sg:classifiers":[
        {
            "category":"Professional",
            "subcategory":"Management & Consulting",
            "type":"Services"
        }
    ],
    "sg:phone":"+1 870 234 8883",
    "sg:postcode":"71753",
    "sg:province":"AR",
    "wof:name":"Port City Marketing",
    "wof:placetype":"venue"
},
  "geometry": {"coordinates":[-93.230752,33.285399],"type":"Point"}
}