{
  "type": "Feature",
  "properties": {
    "iso:country":"US",
    "sg:address":"1610 S Falls Blvd",
    "sg:city":"Wynne",
    "sg:classifiers":[
        {
            "category":"Autos & Motor Vehicles",
            "subcategory":"Auto Supplies",
            "type":"Retail Goods"
        }
    ],
    "sg:phone":"+1 870 238 5911",
    "sg:postcode":"72396",
    "sg:province":"AR",
    "sg:tags":[
        "automobile",
        "parts"
    ],
    "wof:name":"Advance Auto Parts Inc",
    "wof:placetype":"venue"
},
  "geometry": {"coordinates":[-90.79225,35.204124],"type":"Point"}
}