{
  "type": "Feature",
  "properties": {
    "iso:country":"US",
    "sg:address":"711 Towne Oaks Dr",
    "sg:city":"Little Rock",
    "sg:classifiers":[
        {
            "category":"Professional",
            "subcategory":"Computer Services",
            "type":"Services"
        }
    ],
    "sg:phone":"+1 501 223 2492",
    "sg:postcode":"72227",
    "sg:province":"AR",
    "sg:tags":[
        "repair"
    ],
    "wof:name":"LKT Svc",
    "wof:placetype":"venue"
},
  "geometry": {"coordinates":[-92.377833,34.760998],"type":"Point"}
}