{
  "type": "Feature",
  "properties": {
    "iso:country":"US",
    "sg:address":"7624 Cantrell Rd",
    "sg:city":"Little Rock",
    "sg:classifiers":[
        {
            "category":"Professional",
            "subcategory":"Accounting & Tax Preparation",
            "type":"Services"
        }
    ],
    "sg:phone":"+1 501 227 6664",
    "sg:postcode":"72227",
    "sg:province":"AR",
    "sg:tags":[
        "return",
        "filing"
    ],
    "wof:name":"Tax Ax Inc",
    "wof:placetype":"venue"
},
  "geometry": {"coordinates":[-92.359506,34.772877],"type":"Point"}
}