{
  "type": "Feature",
  "properties": {
    "iso:country":"US",
    "sg:address":"1148 E Stearns St",
    "sg:city":"Fayetteville",
    "sg:classifiers":[
        {
            "category":"Health Services",
            "subcategory":"Chiropractor",
            "type":"Services"
        }
    ],
    "sg:phone":"+1 479 443 3211",
    "sg:postcode":"72703",
    "sg:province":"AR",
    "wof:name":"Reddell Clinic of Chiropractic",
    "wof:placetype":"venue"
},
  "geometry": {"coordinates":[-94.142253,36.123517],"type":"Point"}
}