{
  "type": "Feature",
  "properties": {
    "addr:full":"217 W College Fordyce AR 71742",
    "addr:housenumber":"217",
    "addr:postcode":"71742",
    "addr:street":"W College Fordyce",
    "iso:country":"US",
    "sg:address":"217 W College",
    "sg:city":"Fordyce",
    "sg:classifiers":[
        {
            "category":"Personal",
            "subcategory":"Beauty Salon",
            "type":"Services"
        }
    ],
    "sg:phone":"+1 870 352 5945",
    "sg:postcode":"71742",
    "sg:province":"AR",
    "wof:name":"Sherrys Beauty Shop",
    "wof:placetype":"venue"
},
  "geometry": {"coordinates":[-92.416675,33.815991],"type":"Point"}
}