{
  "type": "Feature",
  "properties": {
    "iso:country":"US",
    "sg:address":"5105 Mc Clanahan Dr",
    "sg:city":"N Little Rock",
    "sg:classifiers":[
        {
            "category":"Professional",
            "subcategory":"Advertising",
            "type":"Services"
        }
    ],
    "sg:phone":"+1 501 821 2000",
    "sg:postcode":"72116",
    "sg:province":"AR",
    "sg:tags":[
        "mail"
    ],
    "wof:name":"Sun Media Systems",
    "wof:placetype":"venue"
},
  "geometry": {"coordinates":[-92.21780699999999,34.80111],"type":"Point"}
}