{
  "type": "Feature",
  "properties": {
    "addr:full":"1720 Tudor Loop Benton AR 72019",
    "addr:housenumber":"1720",
    "addr:postcode":"72019",
    "addr:street":"Tudor Loop",
    "iso:country":"US",
    "sg:address":"1720 Tudor Loop",
    "sg:city":"Benton",
    "sg:classifiers":[
        {
            "category":"Wholesale",
            "subcategory":"Metals & Minerals",
            "type":"Manufacturing & Wholesale Goods"
        }
    ],
    "sg:phone":"+1 501 315 4441",
    "sg:postcode":"72019",
    "sg:province":"AR",
    "sg:tags":[
        "manufacturer"
    ],
    "wof:name":"High Tech Fabrication",
    "wof:placetype":"venue"
},
  "geometry": {"coordinates":[-92.676225,34.561161],"type":"Point"}
}