{
  "type": "Feature",
  "properties": {
    "addr:full":"4203 Baseline Rd Little Rock AR 72209",
    "addr:housenumber":"4203",
    "addr:postcode":"72209",
    "addr:street":"Baseline Rd",
    "iso:country":"US",
    "sg:address":"4203 Baseline Rd",
    "sg:city":"Little Rock",
    "sg:classifiers":[
        {
            "category":"Freight",
            "type":"Transportation"
        }
    ],
    "sg:phone":"+1 501 570 7611",
    "sg:postcode":"72209",
    "sg:province":"AR",
    "sg:tags":[
        "trucking"
    ],
    "wof:name":"R & T Trucking",
    "wof:placetype":"venue"
},
  "geometry": {"coordinates":[-92.32225800000001,34.668045],"type":"Point"}
}