{
  "type": "Feature",
  "properties": {
    "addr:full":"2902 Bella Vista Way Bella Vista AR 72714",
    "addr:housenumber":"2902",
    "addr:postcode":"72714",
    "addr:street":"Bella Vista Way",
    "iso:country":"US",
    "sg:address":"2902 Bella Vista Way",
    "sg:city":"Bella Vista",
    "sg:classifiers":[
        {
            "category":"Shopping",
            "subcategory":"Clothing, Apparel, & Fashions",
            "type":"Retail Goods"
        }
    ],
    "sg:phone":"+1 479 855 1698",
    "sg:postcode":"72714",
    "sg:province":"AR",
    "wof:name":"Sweet's Fashions",
    "wof:placetype":"venue"
},
  "geometry": {"coordinates":[-94.235153,36.435959],"type":"Point"}
}