{
  "type": "Feature",
  "properties": {
    "iso:country":"US",
    "sg:address":"6423 Stagecoach Rd",
    "sg:city":"Little Rock",
    "sg:classifiers":[
        {
            "category":"Education",
            "subcategory":"School",
            "type":"Public Place"
        }
    ],
    "sg:phone":"+1 501 447 4300",
    "sg:postcode":"72204",
    "sg:province":"AR",
    "sg:website":"www.lrsd.org",
    "wof:name":"Dodd Elementary School",
    "wof:placetype":"venue"
},
  "geometry": {"coordinates":[-92.39586799999999,34.688119],"type":"Point"}
}