{
  "type": "Feature",
  "properties": {
    "iso:country":"US",
    "sg:address":"27359 Hwy 67",
    "sg:city":"Malvern",
    "sg:classifiers":[
        {
            "category":"Retail",
            "subcategory":"Auto Repair",
            "type":"Services"
        }
    ],
    "sg:phone":"+1 501 337 1627",
    "sg:postcode":"72104",
    "sg:province":"AR",
    "sg:tags":[
        "automotive",
        "general"
    ],
    "wof:name":"Elrods Garage",
    "wof:placetype":"venue"
},
  "geometry": {"coordinates":[-92.834767,34.327253],"type":"Point"}
}