{
  "type": "Feature",
  "properties": {
    "iso:country":"US",
    "sg:address":"701 Main St",
    "sg:city":"Melbourne",
    "sg:classifiers":[
        {
            "category":"Shopping",
            "subcategory":"Florist",
            "type":"Retail Goods"
        }
    ],
    "sg:phone":"+1 870 368 4144",
    "sg:postcode":"72556",
    "sg:province":"AR",
    "wof:name":"Melbourne Florists & Hm Decor",
    "wof:placetype":"venue"
},
  "geometry": {"coordinates":[-91.89786100000001,36.058546],"type":"Point"}
}