{
  "type": "Feature",
  "properties": {
    "addr:full":"17 Cortez Kennedy Ave Wilson AR 72395",
    "addr:housenumber":"17",
    "addr:postcode":"72395",
    "addr:street":"Cortez Kennedy Ave",
    "iso:country":"US",
    "sg:address":"17 Cortez Kennedy Ave",
    "sg:city":"Wilson",
    "sg:classifiers":[
        {
            "category":"Wholesale",
            "subcategory":"Chemicals & Plastics",
            "type":"Manufacturing & Wholesale Goods"
        }
    ],
    "sg:phone":"+1 870 655 8787",
    "sg:postcode":"72395",
    "sg:province":"AR",
    "wof:name":"Home Oil Co",
    "wof:placetype":"venue"
},
  "geometry": {"coordinates":[-90.041663,35.568509],"type":"Point"}
}