{
  "type": "Feature",
  "properties": {
    "iso:country":"US",
    "sg:address":"600 Hardin Rd",
    "sg:city":"Little Rock",
    "sg:classifiers":[
        {
            "category":"Travel",
            "subcategory":"Hotels & Motels",
            "type":"Entertainment"
        }
    ],
    "sg:phone":"+1 501 954 9199",
    "sg:postcode":"72211",
    "sg:province":"AR",
    "sg:tags":[
        "operation"
    ],
    "sg:website":"www.extendedstayhotels.com",
    "wof:name":"Extended Stay America Inc",
    "wof:placetype":"venue"
},
  "geometry": {"coordinates":[-92.398513,34.747802],"type":"Point"}
}