{
  "type": "Feature",
  "properties": {
    "addr:full":"6805 W 12th St Little Rock AR 72204",
    "addr:housenumber":"6805",
    "addr:postcode":"72204",
    "addr:street":"W 12Th St",
    "iso:country":"US",
    "sg:address":"6805 W 12th St",
    "sg:city":"Little Rock",
    "sg:classifiers":[
        {
            "category":"Shopping",
            "subcategory":"Bicycles & Sporting Goods",
            "type":"Retail Goods"
        }
    ],
    "sg:phone":"+1 501 663 2245",
    "sg:postcode":"72204",
    "sg:province":"AR",
    "sg:tags":[
        "equipment",
        "archery",
        "supply"
    ],
    "wof:name":"Archer's Advantage Inc",
    "wof:placetype":"venue"
},
  "geometry": {"coordinates":[-92.351479,34.741659],"type":"Point"}
}