{
  "type": "Feature",
  "properties": {
    "iso:country":"US",
    "sg:address":"1040 S Redmond Rd",
    "sg:city":"Jacksonville",
    "sg:classifiers":[
        {
            "category":"Wholesale",
            "subcategory":"Durable Goods & Equipment",
            "type":"Manufacturing & Wholesale Goods"
        }
    ],
    "sg:phone":"+1 501 982 4571",
    "sg:postcode":"72076",
    "sg:province":"AR",
    "sg:tags":[
        "laser"
    ],
    "sg:website":"www.improvedconstructionmethods.com",
    "wof:name":"ICM Arkansas Sales",
    "wof:placetype":"venue"
},
  "geometry": {"coordinates":[-92.121882,34.856451],"type":"Point"}
}