{
  "type": "Feature",
  "properties": {
    "iso:country":"US",
    "sg:address":"6111 W 83rd St",
    "sg:city":"Little Rock",
    "sg:classifiers":[
        {
            "category":"Education",
            "subcategory":"School",
            "type":"Public Place"
        }
    ],
    "sg:phone":"+1 501 568 3247",
    "sg:postcode":"72209",
    "sg:province":"AR",
    "sg:website":"www.fcslr.com",
    "wof:name":"Second Baptist Christian Acad",
    "wof:placetype":"venue"
},
  "geometry": {"coordinates":[-92.346099,34.674565],"type":"Point"}
}