{
  "type": "Feature",
  "properties": {
    "iso:country":"US",
    "sg:address":"4013 W Walnut St",
    "sg:city":"Rogers",
    "sg:classifiers":[
        {
            "category":"Shopping",
            "type":"Retail Goods"
        }
    ],
    "sg:phone":"+1 479 636 4214",
    "sg:postcode":"72756",
    "sg:province":"AR",
    "sg:tags":[
        "pet",
        "food",
        "supply"
    ],
    "wof:name":"PETCO",
    "wof:placetype":"venue"
},
  "geometry": {"coordinates":[-94.175127,36.334915],"type":"Point"}
}