{
  "type": "Feature",
  "properties": {
    "addr:full":"11311 S Highway 96 Greenwood AR 72936",
    "addr:housenumber":"11311",
    "addr:postcode":"72936",
    "addr:street":"S Highway 96",
    "iso:country":"US",
    "sg:address":"11311 S Highway 96",
    "sg:city":"Greenwood",
    "sg:classifiers":[
        {
            "category":"Wholesale",
            "subcategory":"Machinery & Supplies",
            "type":"Manufacturing & Wholesale Goods"
        }
    ],
    "sg:phone":"+1 479 996 5612",
    "sg:postcode":"72936",
    "sg:province":"AR",
    "sg:tags":[
        "equipment",
        "industrial"
    ],
    "wof:name":"Diamond C Land Cattle Equip",
    "wof:placetype":"venue"
},
  "geometry": {"coordinates":[-94.222098,35.220071],"type":"Point"}
}