{
  "type": "Feature",
  "properties": {
    "iso:country":"US",
    "sg:address":"1725 Junction City Rd",
    "sg:city":"El Dorado",
    "sg:classifiers":[
        {
            "category":"Wholesale",
            "subcategory":"Construction Materials",
            "type":"Manufacturing & Wholesale Goods"
        },
        {
            "category":"Manufacturing",
            "subcategory":"Wood Products",
            "type":"Manufacturing & Wholesale Goods"
        }
    ],
    "sg:phone":"+1 870 864 8980",
    "sg:postcode":"71730",
    "sg:province":"AR",
    "sg:tags":[
        "timberland",
        "company",
        "preserving",
        "timber"
    ],
    "sg:website":"www.plumcreek.com",
    "wof:name":"Plum Creek Timber Company Inc",
    "wof:placetype":"venue"
},
  "geometry": {"coordinates":[-92.64545699999999,33.203106],"type":"Point"}
}