{
  "type": "Feature",
  "properties": {
    "iso:country":"US",
    "sg:address":"114 Buckthorn Ln",
    "sg:city":"Mountain Pine",
    "sg:classifiers":[
        {
            "category":"Professional",
            "subcategory":"Art Services",
            "type":"Services"
        }
    ],
    "sg:phone":"+1 501 767 1731",
    "sg:postcode":"71956",
    "sg:province":"AR",
    "sg:tags":[
        "artist"
    ],
    "wof:name":"Portrait Painter",
    "wof:placetype":"venue"
},
  "geometry": {"coordinates":[-93.151025,34.602458],"type":"Point"}
}