{
  "type": "Feature",
  "properties": {
    "iso:country":"US",
    "sg:address":"1815 Towson Ave",
    "sg:city":"Fort Smith",
    "sg:classifiers":[
        {
            "category":"Retail",
            "subcategory":"Repair Shop",
            "type":"Services"
        }
    ],
    "sg:phone":"+1 479 782 1953",
    "sg:postcode":"72901",
    "sg:province":"AR",
    "wof:name":"A-1 Lock Key & Gun",
    "wof:placetype":"venue"
},
  "geometry": {"coordinates":[-94.42145600000001,35.367752],"type":"Point"}
}