{
  "type": "Feature",
  "properties": {
    "iso:country":"US",
    "sg:address":"1100 N Arkansas Ave",
    "sg:city":"Russellville",
    "sg:classifiers":[
        {
            "category":"Autos & Motor Vehicles",
            "subcategory":"Fuel & Gas Station",
            "type":"Retail Goods"
        }
    ],
    "sg:phone":"+1 479 967 0380",
    "sg:postcode":"72801",
    "sg:province":"AR",
    "wof:name":"Coulson Oil Inc",
    "wof:placetype":"venue"
},
  "geometry": {"coordinates":[-93.133392,35.28841],"type":"Point"}
}