{
  "type": "Feature",
  "properties": {
    "addr:full":"4911 Kavanaugh Blvd Little Rock AR 72207",
    "addr:housenumber":"4911",
    "addr:postcode":"72207",
    "addr:street":"Kavanaugh Blvd",
    "iso:country":"US",
    "sg:address":"4911 Kavanaugh Blvd",
    "sg:city":"Little Rock",
    "sg:classifiers":[
        {
            "category":"Communications",
            "type":"Services"
        }
    ],
    "sg:phone":"+1 501 663 1454",
    "sg:postcode":"72207",
    "sg:province":"AR",
    "sg:tags":[
        "communication"
    ],
    "wof:name":"Vital Communications",
    "wof:placetype":"venue"
},
  "geometry": {"coordinates":[-92.329793,34.768908],"type":"Point"}
}