{
  "type": "Feature",
  "properties": {
    "iso:country":"US",
    "sg:address":"271 State Hwy 212",
    "sg:city":"Dumas",
    "sg:classifiers":[
        {
            "category":"Food & Beverages",
            "subcategory":"Groceries & Convenience Stores",
            "type":"Retail Goods"
        }
    ],
    "sg:phone":"+1 870 382 2198",
    "sg:postcode":"71639",
    "sg:province":"AR",
    "sg:tags":[
        "product"
    ],
    "wof:name":"Riceland Foods Inc Pendleton",
    "wof:placetype":"venue"
},
  "geometry": {"coordinates":[-91.36999900000001,33.981886],"type":"Point"}
}