{
  "type": "Feature",
  "properties": {
    "addr:full":"15 Cortez Kennedy Ave Wilson AR 72395",
    "addr:housenumber":"15",
    "addr:postcode":"72395",
    "addr:street":"Cortez Kennedy Ave",
    "iso:country":"US",
    "sg:address":"15 Cortez Kennedy Ave",
    "sg:city":"Wilson",
    "sg:classifiers":[
        {
            "category":"Personal",
            "subcategory":"Beauty Salon",
            "type":"Services"
        }
    ],
    "sg:phone":"+1 870 655 8338",
    "sg:postcode":"72395",
    "sg:province":"AR",
    "sg:tags":[
        "shop"
    ],
    "wof:name":"Shear Beauty",
    "wof:placetype":"venue"
},
  "geometry": {"coordinates":[-90.04139600000001,35.568626],"type":"Point"}
}