{
  "type": "Feature",
  "properties": {
    "iso:country":"US",
    "sg:address":"111 W Shepherd St",
    "sg:city":"Nashville",
    "sg:classifiers":[
        {
            "category":"Building & Trades",
            "subcategory":"Pest Control",
            "type":"Services"
        }
    ],
    "sg:phone":"+1 870 845 4320",
    "sg:postcode":"71852",
    "sg:province":"AR",
    "wof:name":"Lawrence Termite & Pest Cntrl",
    "wof:placetype":"venue"
},
  "geometry": {"coordinates":[-93.84823,33.945454],"type":"Point"}
}