{
  "type": "Feature",
  "properties": {
    "addr:full":"4248 Lawson Rd El Dorado AR 71730",
    "addr:housenumber":"4248",
    "addr:postcode":"71730",
    "addr:street":"Lawson Rd",
    "iso:country":"US",
    "sg:address":"4248 Lawson Rd",
    "sg:city":"El Dorado",
    "sg:classifiers":[
        {
            "category":"Government",
            "subcategory":"Post Office",
            "type":"Public Place"
        }
    ],
    "sg:phone":"+1 870 962 3641",
    "sg:postcode":"71730",
    "sg:province":"AR",
    "wof:name":"US Post Office",
    "wof:placetype":"venue"
},
  "geometry": {"coordinates":[-92.44313699999999,33.158212],"type":"Point"}
}