{
  "type": "Feature",
  "properties": {
    "addr:full":"2424 E Grand Ave Hot Springs National AR 71901",
    "addr:housenumber":"2424",
    "addr:postcode":"71901",
    "addr:street":"E Grand Ave",
    "iso:country":"US",
    "sg:address":"2424 E Grand Ave",
    "sg:city":"Hot Springs National",
    "sg:classifiers":[
        {
            "category":"Wholesale",
            "subcategory":"Construction Materials",
            "type":"Manufacturing & Wholesale Goods"
        }
    ],
    "sg:phone":"+1 501 262 4121",
    "sg:postcode":"71901",
    "sg:province":"AR",
    "sg:tags":[
        "siding"
    ],
    "wof:name":"Forest Siding Supply Inc (ar)",
    "wof:placetype":"venue"
},
  "geometry": {"coordinates":[-92.994704,34.504483],"type":"Point"}
}