{
  "type": "Feature",
  "properties": {
    "addr:full":"532 W 1st St S Prescott AR 71857",
    "addr:housenumber":"532",
    "addr:postcode":"71857",
    "addr:street":"W 1St St S",
    "iso:country":"US",
    "sg:address":"532 W 1st St S",
    "sg:city":"Prescott",
    "sg:classifiers":[
        {
            "category":"Government",
            "subcategory":"Office",
            "type":"Public Place"
        }
    ],
    "sg:phone":"+1 870 887 2818",
    "sg:postcode":"71857",
    "sg:province":"AR",
    "wof:name":"Nevada County Extension Office",
    "wof:placetype":"venue"
},
  "geometry": {"coordinates":[-93.38463299999999,33.799549],"type":"Point"}
}