{
  "type": "Feature",
  "properties": {
    "addr:full":"250 N 2nd St Ashdown AR 71822",
    "addr:housenumber":"250",
    "addr:postcode":"71822",
    "addr:street":"N 2Nd St",
    "iso:country":"US",
    "sg:address":"250 N 2nd St",
    "sg:city":"Ashdown",
    "sg:classifiers":[
        {
            "category":"Government",
            "subcategory":"Office",
            "type":"Public Place"
        }
    ],
    "sg:phone":"+1 870 898 2622",
    "sg:postcode":"71822",
    "sg:province":"AR",
    "sg:tags":[
        "village"
    ],
    "wof:name":"Ashdown City Administrator",
    "wof:placetype":"venue"
},
  "geometry": {"coordinates":[-94.131668,33.671871],"type":"Point"}
}