{
  "type": "Feature",
  "properties": {
    "iso:country":"US",
    "sg:address":"1301 Texas St",
    "sg:city":"Mena",
    "sg:classifiers":[
        {
            "category":"Farming",
            "subcategory":"Farm",
            "type":"Manufacturing & Wholesale Goods"
        }
    ],
    "sg:phone":"+1 479 394 4921",
    "sg:postcode":"71953",
    "sg:province":"AR",
    "wof:name":"Stevenson Tree Farms",
    "wof:placetype":"venue"
},
  "geometry": {"coordinates":[-94.250621,34.5767],"type":"Point"}
}