{
  "type": "Feature",
  "properties": {
    "addr:full":"113 W Walnut St Rogers AR 72756",
    "addr:housenumber":"113",
    "addr:postcode":"72756",
    "addr:street":"W Walnut St",
    "iso:country":"US",
    "sg:address":"113 W Walnut St",
    "sg:city":"Rogers",
    "sg:classifiers":[
        {
            "category":"Food & Beverages",
            "subcategory":"Bakery",
            "type":"Retail Goods"
        }
    ],
    "sg:phone":"+1 479 246 9000",
    "sg:postcode":"72756",
    "sg:province":"AR",
    "wof:name":"Sweet Dreams Bakery",
    "wof:placetype":"venue"
},
  "geometry": {"coordinates":[-94.117254,36.333165],"type":"Point"}
}