{
  "type": "Feature",
  "properties": {
    "addr:full":"1001 W Walnut St Rogers AR 72756",
    "addr:housenumber":"1001",
    "addr:postcode":"72756",
    "addr:street":"W Walnut St",
    "iso:country":"US",
    "sg:address":"1001 W Walnut St",
    "sg:city":"Rogers",
    "sg:classifiers":[
        {
            "category":"Building & Trades",
            "subcategory":"Construction",
            "type":"Services"
        }
    ],
    "sg:phone":"+1 479 636 3708",
    "sg:postcode":"72756",
    "sg:province":"AR",
    "sg:tags":[
        "contractor"
    ],
    "wof:name":"Don Myers & Assoc",
    "wof:placetype":"venue"
},
  "geometry": {"coordinates":[-94.129644,36.333628],"type":"Point"}
}