{
  "type": "Feature",
  "properties": {
    "iso:country":"US",
    "sg:address":"5581 Bob Mills Rd",
    "sg:city":"Springdale",
    "sg:classifiers":[
        {
            "category":"Utilities",
            "subcategory":"Fuel Oil & Lpg",
            "type":"Services"
        }
    ],
    "sg:phone":"+1 479 756 5927",
    "sg:postcode":"72762",
    "sg:province":"AR",
    "sg:tags":[
        "oils-fuel"
    ],
    "wof:name":"Loren R Bailey Fuel Manag",
    "wof:placetype":"venue"
},
  "geometry": {"coordinates":[-94.191867,36.199066],"type":"Point"}
}