{
  "type": "Feature",
  "properties": {
    "iso:country":"US",
    "sg:address":"8218 Cantrell Rd",
    "sg:city":"Little Rock",
    "sg:classifiers":[
        {
            "category":"Shopping",
            "subcategory":"Bicycles & Sporting Goods",
            "type":"Retail Goods"
        },
        {
            "category":"Shopping",
            "subcategory":"Clothing, Apparel, & Fashions",
            "type":"Retail Goods"
        }
    ],
    "sg:phone":"+1 501 227 6345",
    "sg:postcode":"72227",
    "sg:province":"AR",
    "sg:tags":[
        "equipment",
        "tennis",
        "sport",
        "supply"
    ],
    "wof:name":"Tennis Shoppe Inc",
    "wof:placetype":"venue"
},
  "geometry": {"coordinates":[-92.367879,34.777167],"type":"Point"}
}