{
  "type": "Feature",
  "properties": {
    "iso:country":"US",
    "sg:address":"2124 Military Rd",
    "sg:city":"Benton",
    "sg:classifiers":[
        {
            "category":"Retail",
            "subcategory":"Repair Shop",
            "type":"Services"
        },
        {
            "category":"Professional",
            "subcategory":"Computer Services",
            "type":"Services"
        },
        {
            "category":"Shopping",
            "subcategory":"Computers & Home Electronics",
            "type":"Retail Goods"
        },
        {
            "category":"Wholesale",
            "subcategory":"Computers",
            "type":"Manufacturing & Wholesale Goods"
        }
    ],
    "sg:phone":"+1 501 778 8811",
    "sg:postcode":"72015",
    "sg:province":"AR",
    "sg:tags":[
        "designer",
        "supply",
        "technical",
        "repair-business",
        "assistance",
        "system",
        "hardware",
        "equipment",
        "consultant",
        "support"
    ],
    "sg:website":"http://www.arscomputing.com",
    "wof:name":"ARS Computing",
    "wof:placetype":"venue"
},
  "geometry": {"coordinates":[-92.56912199999999,34.58355],"type":"Point"}
}