{
  "type": "Feature",
  "properties": {
    "iso:country":"US",
    "sg:address":"404 Wallace Rd",
    "sg:city":"N Little Rock",
    "sg:classifiers":[
        {
            "category":"Organizations",
            "subcategory":"Religious Organization",
            "type":"Services"
        }
    ],
    "sg:phone":"+1 501 945 1123",
    "sg:postcode":"72117",
    "sg:province":"AR",
    "sg:tags":[
        "church"
    ],
    "wof:name":"New Zion Grove Baptist Church",
    "wof:placetype":"venue"
},
  "geometry": {"coordinates":[-92.19303,34.794772],"type":"Point"}
}