{
  "type": "Feature",
  "properties": {
    "addr:full":"1000 N University Ave Little Rock AR 72207",
    "addr:housenumber":"1000",
    "addr:postcode":"72207",
    "addr:street":"N University Ave",
    "iso:country":"US",
    "sg:address":"1000 N University Ave",
    "sg:city":"Little Rock",
    "sg:classifiers":[
        {
            "category":"Health Services",
            "subcategory":"Doctor",
            "type":"Services"
        }
    ],
    "sg:phone":"+1 501 223 8003",
    "sg:postcode":"72207",
    "sg:province":"AR",
    "sg:tags":[
        "physician",
        "clinic",
        "surgeon"
    ],
    "wof:name":"Arkansas Oncology Assoc PA",
    "wof:placetype":"venue"
},
  "geometry": {"coordinates":[-92.340987,34.761273],"type":"Point"}
}