{
  "type": "Feature",
  "properties": {
    "iso:country":"US",
    "sg:address":"145 S Kaylee Dr",
    "sg:city":"Ashdown",
    "sg:classifiers":[
        {
            "category":"Organizations",
            "subcategory":"Religious Organization",
            "type":"Services"
        }
    ],
    "sg:phone":"+1 870 898 5845",
    "sg:postcode":"71822",
    "sg:province":"AR",
    "sg:tags":[
        "church"
    ],
    "wof:name":"Church Of Nazerine Parsonage",
    "wof:placetype":"venue"
},
  "geometry": {"coordinates":[-94.138511,33.692485],"type":"Point"}
}