{
  "type": "Feature",
  "properties": {
    "iso:country":"US",
    "sg:address":"2119 Wolfe St",
    "sg:city":"Little Rock",
    "sg:classifiers":[
        {
            "category":"Organizations",
            "subcategory":"Religious Organization",
            "type":"Services"
        }
    ],
    "sg:phone":"+1 501 372 4137",
    "sg:postcode":"72202",
    "sg:province":"AR",
    "sg:tags":[
        "church"
    ],
    "wof:name":"Jehovah's Witnesses",
    "wof:placetype":"venue"
},
  "geometry": {"coordinates":[-92.29300000000001,34.728918],"type":"Point"}
}