{
  "type": "Feature",
  "properties": {
    "iso:country":"US",
    "sg:address":"1617 W Main St",
    "sg:city":"Corning",
    "sg:classifiers":[
        {
            "category":"Travel",
            "subcategory":"Hotels & Motels",
            "type":"Entertainment"
        }
    ],
    "sg:phone":"+1 870 857 3513",
    "sg:postcode":"72422",
    "sg:province":"AR",
    "sg:tags":[
        "lodging"
    ],
    "wof:name":"Parkview Motel",
    "wof:placetype":"venue"
},
  "geometry": {"coordinates":[-90.592196,36.411324],"type":"Point"}
}