{
  "type": "Feature",
  "properties": {
    "iso:country":"US",
    "sg:address":"333 E Market Ave",
    "sg:city":"Searcy",
    "sg:classifiers":[
        {
            "category":"Farming",
            "subcategory":"Poultry Farm",
            "type":"Manufacturing & Wholesale Goods"
        }
    ],
    "sg:phone":"+1 501 268 6581",
    "sg:postcode":"72143",
    "sg:province":"AR",
    "sg:tags":[
        "turkey"
    ],
    "wof:name":"Southwest 40 Farm",
    "wof:placetype":"venue"
},
  "geometry": {"coordinates":[-91.734367,35.249552],"type":"Point"}
}