{
  "type": "Feature",
  "properties": {
    "addr:full":"333 E Market Ave Searcy AR 72143",
    "addr:housenumber":"333",
    "addr:postcode":"72143",
    "addr:street":"E Market Ave",
    "iso:country":"US",
    "sg:address":"333 E Market Ave",
    "sg:city":"Searcy",
    "sg:classifiers":[
        {
            "category":"Farming",
            "subcategory":"Poultry Farm",
            "type":"Manufacturing & Wholesale Goods"
        }
    ],
    "sg:phone":"+1 501 268 6581",
    "sg:postcode":"72143",
    "sg:province":"AR",
    "sg:tags":[
        "turkey"
    ],
    "wof:name":"Southwest 40 Farm",
    "wof:placetype":"venue"
},
  "geometry": {"coordinates":[-91.73436700000001,35.249552],"type":"Point"}
}