{
  "type": "Feature",
  "properties": {
    "iso:country":"US",
    "sg:address":"9724 Jenny Lind Rd",
    "sg:city":"Fort Smith",
    "sg:classifiers":[
        {
            "category":"Retail",
            "subcategory":"Laundry & Dry Cleaning",
            "type":"Services"
        }
    ],
    "sg:phone":"+1 479 646 3713",
    "sg:postcode":"72908",
    "sg:province":"AR",
    "sg:tags":[
        "drycleaning",
        "plant"
    ],
    "wof:name":"Industrial Glove Cleaners",
    "wof:placetype":"venue"
},
  "geometry": {"coordinates":[-94.40685499999999,35.291912],"type":"Point"}
}