{
  "type": "Feature",
  "properties": {
    "iso:country":"US",
    "sg:address":"1977 Tucker Mountain Rd",
    "sg:city":"Dover",
    "sg:classifiers":[
        {
            "category":"Structure",
            "subcategory":"Warehouse",
            "type":"Public Place"
        }
    ],
    "sg:phone":"+1 479 968 3637",
    "sg:postcode":"72837",
    "sg:province":"AR",
    "sg:tags":[
        "warehouses-merchandise",
        "warehouses-public-commercial"
    ],
    "wof:name":"Van Horn Family Partnership",
    "wof:placetype":"venue"
},
  "geometry": {"coordinates":[-93.181895,35.36467],"type":"Point"}
}