{
  "type": "Feature",
  "properties": {
    "iso:country":"US",
    "sg:address":"2561 State Hwy 287",
    "sg:city":"Solgohachia",
    "sg:classifiers":[
        {
            "category":"Home & Garden",
            "subcategory":"Building Materials",
            "type":"Retail Goods"
        }
    ],
    "sg:phone":"+1 501 208 9901",
    "sg:postcode":"72156",
    "sg:province":"AR",
    "sg:tags":[
        "type",
        "door"
    ],
    "wof:name":"J J Overhead Door",
    "wof:placetype":"venue"
},
  "geometry": {"coordinates":[-92.678991,35.289184],"type":"Point"}
}