{
  "type": "Feature",
  "properties": {
    "iso:country":"US",
    "sg:address":"1320 Highway 62 65 N",
    "sg:city":"Harrison",
    "sg:classifiers":[
        {
            "category":"Restaurant",
            "type":"Food & Drink"
        }
    ],
    "sg:menulink":"http://www.allmenus.com/ar/north-harrison/110750-quiznos-sub/menu/",
    "sg:phone":"+1 870 741 3737",
    "sg:postcode":"72601",
    "sg:province":"AR",
    "sg:tags":[
        "wrap",
        "american",
        "sandwich"
    ],
    "wof:name":"Quiznos Sub",
    "wof:placetype":"venue"
},
  "geometry": {"coordinates":[-93.112229,36.245704],"type":"Point"}
}