{
  "type": "Feature",
  "properties": {
    "addr:full":"1301 N Main Ct Beebe AR 72012",
    "addr:housenumber":"1301",
    "addr:postcode":"72012",
    "addr:street":"N Main Ct",
    "iso:country":"US",
    "sg:address":"1301 N Main Ct",
    "sg:city":"Beebe",
    "sg:classifiers":[
        {
            "category":"Shopping",
            "subcategory":"Computers & Home Electronics",
            "type":"Retail Goods"
        }
    ],
    "sg:phone":"+1 501 247 5450",
    "sg:postcode":"72012",
    "sg:province":"AR",
    "wof:name":"Computeristics",
    "wof:placetype":"venue"
},
  "geometry": {"coordinates":[-91.88005699999999,35.082783],"type":"Point"}
}