{
  "type": "Feature",
  "properties": {
    "iso:country":"US",
    "sg:address":"494 S Broad St",
    "sg:city":"Batesville",
    "sg:classifiers":[
        {
            "category":"Personal",
            "subcategory":"Beauty Salon",
            "type":"Services"
        }
    ],
    "sg:phone":"+1 870 698 1183",
    "sg:postcode":"72501",
    "sg:province":"AR",
    "wof:name":"Salon Lafemme",
    "wof:placetype":"venue"
},
  "geometry": {"coordinates":[-91.651717,35.768989],"type":"Point"}
}