{
  "type": "Feature",
  "properties": {
    "addr:full":"2207 Oak Creek Rd West Memphis AR 72301",
    "addr:housenumber":"2207",
    "addr:postcode":"72301",
    "addr:street":"Oak Creek Rd",
    "iso:country":"US",
    "sg:address":"2207 Oak Creek Rd",
    "sg:city":"West Memphis",
    "sg:classifiers":[
        {
            "category":"Building & Trades",
            "subcategory":"Construction",
            "type":"Services"
        }
    ],
    "sg:phone":"+1 870 735 5614",
    "sg:postcode":"72301",
    "sg:province":"AR",
    "sg:tags":[
        "concrete",
        "contractor"
    ],
    "wof:name":"Budget Construction Co",
    "wof:placetype":"venue"
},
  "geometry": {"coordinates":[-90.225661,35.142886],"type":"Point"}
}