{
  "type": "Feature",
  "properties": {
    "iso:country":"US",
    "sg:address":"14790 Fathom Rd",
    "sg:city":"Fayetteville",
    "sg:classifiers":[
        {
            "category":"Farming",
            "subcategory":"Farm",
            "type":"Manufacturing & Wholesale Goods"
        }
    ],
    "sg:phone":"+1 479 643 2355",
    "sg:postcode":"72701",
    "sg:province":"AR",
    "wof:name":"Arnett Hog Farm",
    "wof:placetype":"venue"
},
  "geometry": {"coordinates":[-94.035769,35.893209],"type":"Point"}
}