{
  "type": "Feature",
  "properties": {
    "addr:full":"7423 US Hwy 271 Fort Smith AR 72908",
    "addr:housenumber":"7423",
    "addr:postcode":"72908",
    "addr:street":"Us Hwy 271",
    "iso:country":"US",
    "sg:address":"7423 US Hwy 271",
    "sg:city":"Fort Smith",
    "sg:classifiers":[
        {
            "category":"Autos & Motor Vehicles",
            "subcategory":"Auto Supplies",
            "type":"Retail Goods"
        }
    ],
    "sg:phone":"+1 479 646 6988",
    "sg:postcode":"72908",
    "sg:province":"AR",
    "sg:tags":[
        "equipment",
        "racing",
        "car",
        "automobile"
    ],
    "sg:website":"www.southwestspeed.com",
    "wof:name":"Southwest Speed Auto Racing",
    "wof:placetype":"venue"
},
  "geometry": {"coordinates":[-94.422883,35.314749],"type":"Point"}
}