{
  "type": "Feature",
  "properties": {
    "iso:country":"US",
    "sg:address":"80 Hill St",
    "sg:city":"Marianna",
    "sg:classifiers":[
        {
            "category":"Organizations",
            "subcategory":"Religious Organization",
            "type":"Services"
        }
    ],
    "sg:phone":"+1 870 295 4503",
    "sg:postcode":"72360",
    "sg:province":"AR",
    "sg:tags":[
        "church"
    ],
    "wof:name":"Kingdom Hall Of Jehovah's",
    "wof:placetype":"venue"
},
  "geometry": {"coordinates":[-90.754924,34.769858],"type":"Point"}
}