{
  "type": "Feature",
  "properties": {
    "addr:full":"103 Bransford Rd Lonoke AR 72086",
    "addr:housenumber":"103",
    "addr:postcode":"72086",
    "addr:street":"Bransford Rd",
    "iso:country":"US",
    "sg:address":"103 Bransford Rd",
    "sg:city":"Lonoke",
    "sg:classifiers":[
        {
            "category":"Farming",
            "subcategory":"Farm & Veterinary Services",
            "type":"Manufacturing & Wholesale Goods"
        }
    ],
    "sg:phone":"+1 501 676 2464",
    "sg:postcode":"72086",
    "sg:province":"AR",
    "sg:tags":[
        "cotton",
        "ginning"
    ],
    "wof:name":"Pettus Gin Company",
    "wof:placetype":"venue"
},
  "geometry": {"coordinates":[-91.91753199999999,34.67501],"type":"Point"}
}