{
  "type": "Feature",
  "properties": {
    "addr:full":"926 State Hwy 73 Washington AR 71862",
    "addr:housenumber":"926",
    "addr:postcode":"71862",
    "addr:street":"State Hwy 73",
    "iso:country":"US",
    "sg:address":"926 State Hwy 73",
    "sg:city":"Washington",
    "sg:classifiers":[
        {
            "category":"Food & Beverages",
            "subcategory":"Groceries & Convenience Stores",
            "type":"Retail Goods"
        }
    ],
    "sg:phone":"+1 870 983 2250",
    "sg:postcode":"71862",
    "sg:province":"AR",
    "wof:name":"Davis Grocery Store",
    "wof:placetype":"venue"
},
  "geometry": {"coordinates":[-93.696896,33.704224],"type":"Point"}
}