{
  "type": "Feature",
  "properties": {
    "iso:country":"US",
    "sg:address":"400 W Main St",
    "sg:city":"Blytheville",
    "sg:classifiers":[
        {
            "category":"Banks & Credit Unions",
            "subcategory":"Bank",
            "type":"Services"
        }
    ],
    "sg:phone":"+1 870 763 8101",
    "sg:postcode":"72315",
    "sg:province":"AR",
    "sg:website":"www.farmersbankbly.com",
    "wof:name":"Farmers Bank & Trust Co",
    "wof:placetype":"venue"
},
  "geometry": {"coordinates":[-89.908058,35.927495],"type":"Point"}
}