{
  "type": "Feature",
  "properties": {
    "addr:full":"107 S Madden St Foreman AR 71836",
    "addr:housenumber":"107",
    "addr:postcode":"71836",
    "addr:street":"S Madden St",
    "iso:country":"US",
    "sg:address":"107 S Madden St",
    "sg:city":"Foreman",
    "sg:classifiers":[
        {
            "category":"Utilities",
            "subcategory":"Water",
            "type":"Services"
        }
    ],
    "sg:phone":"+1 870 542 7701",
    "sg:postcode":"71836",
    "sg:province":"AR",
    "sg:tags":[
        "company",
        "sewage"
    ],
    "wof:name":"Little River RDA Water",
    "wof:placetype":"venue"
},
  "geometry": {"coordinates":[-94.392034,33.720256],"type":"Point"}
}