{
  "type": "Feature",
  "properties": {
    "iso:country":"US",
    "sg:address":"603 S Division St",
    "sg:city":"Lavaca",
    "sg:classifiers":[
        {
            "category":"Education",
            "subcategory":"Special Training",
            "type":"Public Place"
        }
    ],
    "sg:phone":"+1 479 674 7004",
    "sg:postcode":"72941",
    "sg:province":"AR",
    "wof:name":"South Seb Co Special Ed Co Op",
    "wof:placetype":"venue"
},
  "geometry": {"coordinates":[-94.173072,35.337494],"type":"Point"}
}