{
  "type": "Feature",
  "properties": {
    "addr:full":"5213 Rogers Ave Fort Smith AR 72903",
    "addr:housenumber":"5213",
    "addr:postcode":"72903",
    "addr:street":"Rogers Ave",
    "iso:country":"US",
    "sg:address":"5213 Rogers Ave",
    "sg:city":"Fort Smith",
    "sg:classifiers":[
        {
            "category":"Real Estate",
            "subcategory":"Real Estate Agent",
            "type":"Services"
        }
    ],
    "sg:phone":"+1 479 452 5597",
    "sg:postcode":"72903",
    "sg:province":"AR",
    "sg:website":"www.unitedcountry.com",
    "wof:name":"United Country Real Estate",
    "wof:placetype":"venue"
},
  "geometry": {"coordinates":[-94.37792399999999,35.36664],"type":"Point"}
}