{
  "type": "Feature",
  "properties": {
    "addr:full":"1141 E Main St Batesville AR 72501",
    "addr:housenumber":"1141",
    "addr:postcode":"72501",
    "addr:street":"E Main St",
    "iso:country":"US",
    "sg:address":"1141 E Main St",
    "sg:city":"Batesville",
    "sg:classifiers":[
        {
            "category":"Banks & Credit Unions",
            "subcategory":"Bank",
            "type":"Services"
        }
    ],
    "sg:phone":"+1 870 698 2237",
    "sg:postcode":"72501",
    "sg:province":"AR",
    "sg:tags":[
        "national",
        "commercial"
    ],
    "wof:name":"Regions Bank",
    "wof:placetype":"venue"
},
  "geometry": {"coordinates":[-91.643181,35.776374],"type":"Point"}
}