{
  "type": "Feature",
  "properties": {
    "iso:country":"US",
    "sg:address":"2412 E 6th Ave",
    "sg:city":"Pine Bluff",
    "sg:classifiers":[
        {
            "category":"Retail",
            "subcategory":"Auto Repair",
            "type":"Services"
        }
    ],
    "sg:phone":"+1 870 534 4241",
    "sg:postcode":"71601",
    "sg:province":"AR",
    "sg:tags":[
        "repairing",
        "automobile",
        "automotive"
    ],
    "wof:name":"Euorpean Motors",
    "wof:placetype":"venue"
},
  "geometry": {"coordinates":[-91.978,34.224425],"type":"Point"}
}