{
  "type": "Feature",
  "properties": {
    "iso:country":"US",
    "sg:address":"1920 Dallas St",
    "sg:city":"Fort Smith",
    "sg:classifiers":[
        {
            "category":"Professional",
            "subcategory":"Accounting & Tax Preparation",
            "type":"Services"
        }
    ],
    "sg:phone":"+1 479 784 9669",
    "sg:postcode":"72901",
    "sg:province":"AR",
    "sg:tags":[
        "return",
        "filing"
    ],
    "wof:name":"Taxmart",
    "wof:placetype":"venue"
},
  "geometry": {"coordinates":[-94.413342,35.353373],"type":"Point"}
}