{
  "type": "Feature",
  "properties": {
    "addr:full":"1716 Highway 1 N Lexa AR 72355",
    "addr:housenumber":"1716",
    "addr:postcode":"72355",
    "addr:street":"Highway 1 N",
    "iso:country":"US",
    "sg:address":"1716 Highway 1 N",
    "sg:city":"Lexa",
    "sg:classifiers":[
        {
            "category":"Farming",
            "subcategory":"Farm",
            "type":"Manufacturing & Wholesale Goods"
        }
    ],
    "sg:phone":"+1 870 572 5822",
    "sg:postcode":"72355",
    "sg:province":"AR",
    "wof:name":"Ronald Turner",
    "wof:placetype":"venue"
},
  "geometry": {"coordinates":[-90.76808200000001,34.584682],"type":"Point"}
}