{
  "type": "Feature",
  "properties": {
    "iso:country":"US",
    "sg:address":"1406 US Hwy 371",
    "sg:city":"Prescott",
    "sg:classifiers":[
        {
            "category":"Home & Garden",
            "subcategory":"Building Materials",
            "type":"Retail Goods"
        }
    ],
    "sg:phone":"+1 870 887 2673",
    "sg:postcode":"71857",
    "sg:province":"AR",
    "wof:name":"Firestone Building Products Co",
    "wof:placetype":"venue"
},
  "geometry": {"coordinates":[-93.407084,33.81033],"type":"Point"}
}