{
  "type": "Feature",
  "properties": {
    "iso:country":"US",
    "sg:address":"5011 Hawthorne Rd",
    "sg:city":"Little Rock",
    "sg:classifiers":[
        {
            "category":"Banks & Credit Unions",
            "subcategory":"Financial Services",
            "type":"Services"
        }
    ],
    "sg:phone":"+1 501 661 1188",
    "sg:postcode":"72207",
    "sg:province":"AR",
    "sg:tags":[
        "investor"
    ],
    "wof:name":"Burlingame Investments Lt",
    "wof:placetype":"venue"
},
  "geometry": {"coordinates":[-92.329476,34.772855],"type":"Point"}
}