{
  "type": "Feature",
  "properties": {
    "addr:full":"11500 Arbor Acres Rd Springdale AR 72762",
    "addr:housenumber":"11500",
    "addr:postcode":"72762",
    "addr:street":"Arbor Acres Rd",
    "iso:country":"US",
    "sg:address":"11500 Arbor Acres Rd",
    "sg:city":"Springdale",
    "sg:classifiers":[
        {
            "category":"Retail",
            "subcategory":"Repair Shop",
            "type":"Services"
        }
    ],
    "sg:phone":"+1 479 361 5774",
    "sg:postcode":"72762",
    "sg:province":"AR",
    "sg:tags":[
        "tool",
        "grinding"
    ],
    "wof:name":"Tool Grinding Specialists Inc",
    "wof:placetype":"venue"
},
  "geometry": {"coordinates":[-94.244468,36.144009],"type":"Point"}
}