{
  "type": "Feature",
  "properties": {
    "addr:full":"710 Marcella Ave Lake Village AR 71653",
    "addr:housenumber":"710",
    "addr:postcode":"71653",
    "addr:street":"Marcella Ave Lake Village",
    "iso:country":"US",
    "sg:address":"710 Marcella Ave",
    "sg:city":"Lake Village",
    "sg:classifiers":[
        {
            "category":"Wholesale",
            "subcategory":"Construction Materials",
            "type":"Manufacturing & Wholesale Goods"
        },
        {
            "category":"Manufacturing",
            "subcategory":"Metals",
            "type":"Manufacturing & Wholesale Goods"
        }
    ],
    "sg:phone":"+1 870 265 5504",
    "sg:postcode":"71653",
    "sg:province":"AR",
    "sg:tags":[
        "fencing",
        "link",
        "chain",
        "fence"
    ],
    "wof:name":"Phillips Fence Company Inc",
    "wof:placetype":"venue"
},
  "geometry": {"coordinates":[-91.288776,33.318522],"type":"Point"}
}