{
  "type": "Feature",
  "properties": {
    "iso:country":"US",
    "sg:address":"102 N Alabama St",
    "sg:city":"Crossett",
    "sg:classifiers":[
        {
            "category":"Building & Trades",
            "subcategory":"Equipment Rental",
            "type":"Services"
        }
    ],
    "sg:phone":"+1 870 364 5244",
    "sg:postcode":"71635",
    "sg:province":"AR",
    "wof:name":"Best Value Rental Inc",
    "wof:placetype":"venue"
},
  "geometry": {"coordinates":[-91.963026,33.135276],"type":"Point"}
}