{
  "type": "Feature",
  "properties": {
    "iso:country":"US",
    "sg:address":"1030 Grant 73",
    "sg:city":"Sheridan",
    "sg:classifiers":[
        {
            "category":"Restaurant",
            "type":"Food & Drink"
        }
    ],
    "sg:phone":"+1 870 942 5251",
    "sg:postcode":"72150",
    "sg:province":"AR",
    "wof:name":"D Harlon Henry",
    "wof:placetype":"venue"
},
  "geometry": {"coordinates":[-92.317436,34.333874],"type":"Point"}
}