{
  "type": "Feature",
  "properties": {
    "iso:country":"US",
    "sg:address":"424 S 14th St",
    "sg:city":"West Memphis",
    "sg:classifiers":[
        {
            "category":"Social Services",
            "type":"Services"
        }
    ],
    "sg:phone":"+1 870 732 4397",
    "sg:postcode":"72301",
    "sg:province":"AR",
    "sg:tags":[
        "organization",
        "welfare"
    ],
    "wof:name":"All Our Children",
    "wof:placetype":"venue"
},
  "geometry": {"coordinates":[-90.167714,35.141579],"type":"Point"}
}