{
  "type": "Feature",
  "properties": {
    "addr:full":"109 Creekwood Dr Searcy AR 72143",
    "addr:housenumber":"109",
    "addr:postcode":"72143",
    "addr:street":"Creekwood Dr",
    "iso:country":"US",
    "sg:address":"109 Creekwood Dr",
    "sg:city":"Searcy",
    "sg:classifiers":[
        {
            "category":"Food & Beverages",
            "subcategory":"Groceries & Convenience Stores",
            "type":"Retail Goods"
        }
    ],
    "sg:phone":"+1 501 278 5593",
    "sg:postcode":"72143",
    "sg:province":"AR",
    "wof:name":"Town & Country",
    "wof:placetype":"venue"
},
  "geometry": {"coordinates":[-91.765984,35.215991],"type":"Point"}
}