{
  "type": "Feature",
  "properties": {
    "iso:country":"US",
    "sg:address":"304 Frisco St",
    "sg:city":"Marked Tree",
    "sg:classifiers":[
        {
            "category":"Organizations",
            "subcategory":"Religious Organization",
            "type":"Services"
        }
    ],
    "sg:phone":"+1 870 358 2991",
    "sg:postcode":"72365",
    "sg:province":"AR",
    "sg:tags":[
        "church"
    ],
    "wof:name":"First United Methodist Church",
    "wof:placetype":"venue"
},
  "geometry": {"coordinates":[-90.41936200000001,35.530895],"type":"Point"}
}