{
  "type": "Feature",
  "properties": {
    "iso:country":"US",
    "sg:address":"7200 Mabievale Pike",
    "sg:city":"Little Rock",
    "sg:classifiers":[
        {
            "category":"Social Services",
            "subcategory":"Child Care",
            "type":"Services"
        }
    ],
    "sg:phone":"+1 501 570 0754",
    "sg:postcode":"72209",
    "sg:province":"AR",
    "sg:tags":[
        "day"
    ],
    "wof:name":"Perfecting New Life Learning C",
    "wof:placetype":"venue"
},
  "geometry": {"coordinates":[-92.355206,34.684022],"type":"Point"}
}