{
  "type": "Feature",
  "properties": {
    "addr:full":"124 S Market St Benton AR 72015",
    "addr:housenumber":"124",
    "addr:postcode":"72015",
    "addr:street":"S Market St",
    "iso:country":"US",
    "sg:address":"124 S Market St",
    "sg:city":"Benton",
    "sg:classifiers":[
        {
            "category":"Shopping",
            "subcategory":"Gifts & Souvenirs",
            "type":"Retail Goods"
        }
    ],
    "sg:phone":"+1 501 315 9141",
    "sg:postcode":"72015",
    "sg:province":"AR",
    "sg:tags":[
        "shop"
    ],
    "wof:name":"Angies Bridal & Gifts",
    "wof:placetype":"venue"
},
  "geometry": {"coordinates":[-92.588161,34.563206],"type":"Point"}
}