{
  "type": "Feature",
  "properties": {
    "addr:full":"6014 Southwest Dr Jonesboro AR 72404",
    "addr:housenumber":"6014",
    "addr:postcode":"72404",
    "addr:street":"Southwest Dr",
    "iso:country":"US",
    "sg:address":"6014 Southwest Dr",
    "sg:city":"Jonesboro",
    "sg:classifiers":[
        {
            "category":"Building & Trades",
            "subcategory":"Construction",
            "type":"Services"
        }
    ],
    "sg:phone":"+1 870 802 4888",
    "sg:postcode":"72404",
    "sg:province":"AR",
    "sg:tags":[
        "water",
        "well",
        "drilling"
    ],
    "wof:name":"Gipson Well Of Jonesboro",
    "wof:placetype":"venue"
},
  "geometry": {"coordinates":[-90.755725,35.777831],"type":"Point"}
}