{
  "type": "Feature",
  "properties": {
    "iso:country":"US",
    "sg:address":"601 N 1st St",
    "sg:city":"Jacksonville",
    "sg:classifiers":[
        {
            "category":"Home & Garden",
            "subcategory":"Building Materials",
            "type":"Retail Goods"
        }
    ],
    "sg:phone":"+1 501 985 8600",
    "sg:postcode":"72076",
    "sg:province":"AR",
    "sg:tags":[
        "center"
    ],
    "wof:name":"Lowe's",
    "wof:placetype":"venue"
},
  "geometry": {"coordinates":[-92.109549,34.8708],"type":"Point"}
}