{
  "type": "Feature",
  "properties": {
    "iso:country":"US",
    "sg:address":"215 Riverbend Ln",
    "sg:city":"Clinton",
    "sg:classifiers":[
        {
            "category":"Freight",
            "type":"Transportation"
        }
    ],
    "sg:phone":"+1 501 745 6277",
    "sg:postcode":"72031",
    "sg:province":"AR",
    "sg:tags":[
        "operator",
        "trucking"
    ],
    "wof:name":"Stylin & Profilin",
    "wof:placetype":"venue"
},
  "geometry": {"coordinates":[-92.403628,35.575161],"type":"Point"}
}