{
  "type": "Feature",
  "properties": {
    "iso:country":"US",
    "sg:address":"383 Greene Rd 845",
    "sg:city":"Paragould",
    "sg:classifiers":[
        {
            "category":"Organizations",
            "subcategory":"Religious Organization",
            "type":"Services"
        }
    ],
    "sg:phone":"+1 870 335 9537",
    "sg:postcode":"72450",
    "sg:province":"AR",
    "sg:tags":[
        "church"
    ],
    "wof:name":"Churchvines Chapel Baptist",
    "wof:placetype":"venue"
},
  "geometry": {"coordinates":[-90.46505500000001,36.092915],"type":"Point"}
}