{
  "type": "Feature",
  "properties": {
    "addr:full":"209 W Easy St Rogers AR 72756",
    "addr:housenumber":"209",
    "addr:postcode":"72756",
    "addr:street":"W Easy St",
    "iso:country":"US",
    "sg:address":"209 W Easy St",
    "sg:city":"Rogers",
    "sg:classifiers":[
        {
            "category":"Home & Garden",
            "subcategory":"Mobile Homes",
            "type":"Retail Goods"
        }
    ],
    "sg:phone":"+1 479 936 8620",
    "sg:postcode":"72756",
    "sg:province":"AR",
    "sg:tags":[
        "commercial",
        "unit"
    ],
    "wof:name":"Jotto Desk",
    "wof:placetype":"venue"
},
  "geometry": {"coordinates":[-94.121441,36.348033],"type":"Point"}
}