{
  "type": "Feature",
  "properties": {
    "iso:country":"US",
    "sg:address":"4903 Kelly Rd",
    "sg:city":"N Little Rock",
    "sg:classifiers":[
        {
            "category":"Building & Trades",
            "subcategory":"Construction",
            "type":"Services"
        }
    ],
    "sg:phone":"+1 501 771 2902",
    "sg:postcode":"72118",
    "sg:province":"AR",
    "sg:tags":[
        "pipe",
        "line",
        "contractor"
    ],
    "wof:name":"CPCS Inc",
    "wof:placetype":"venue"
},
  "geometry": {"coordinates":[-92.32413,34.822576],"type":"Point"}
}