{
  "type": "Feature",
  "properties": {
    "addr:full":"1102 S Pine St Cabot AR 72023",
    "addr:housenumber":"1102",
    "addr:postcode":"72023",
    "addr:street":"S Pine St",
    "iso:country":"US",
    "sg:address":"1102 S Pine St",
    "sg:city":"Cabot",
    "sg:classifiers":[
        {
            "category":"Personal",
            "subcategory":"Beauty Salon",
            "type":"Services"
        }
    ],
    "sg:phone":"+1 501 843 4332",
    "sg:postcode":"72023",
    "sg:province":"AR",
    "sg:tags":[
        "shop"
    ],
    "wof:name":"Hair Cuts & More",
    "wof:placetype":"venue"
},
  "geometry": {"coordinates":[-92.00855799999999,34.955076],"type":"Point"}
}