{
  "type": "Feature",
  "properties": {
    "iso:country":"US",
    "sg:address":"317 S Shackleford Rd",
    "sg:city":"Little Rock",
    "sg:classifiers":[
        {
            "category":"Building & Trades",
            "subcategory":"Construction",
            "type":"Services"
        }
    ],
    "sg:phone":"+1 501 954 9856",
    "sg:postcode":"72211",
    "sg:province":"AR",
    "sg:tags":[
        "general",
        "contractor"
    ],
    "wof:name":"C J Torre Construction",
    "wof:placetype":"venue"
},
  "geometry": {"coordinates":[-92.393809,34.753023],"type":"Point"}
}