{
  "type": "Feature",
  "properties": {
    "addr:full":"5912 R St Little Rock AR 72207",
    "addr:housenumber":"5912",
    "addr:postcode":"72207",
    "addr:street":"R St",
    "iso:country":"US",
    "sg:address":"5912 R St",
    "sg:city":"Little Rock",
    "sg:classifiers":[
        {
            "category":"Personal",
            "subcategory":"Shoe Repair & Shine",
            "type":"Services"
        }
    ],
    "sg:phone":"+1 501 664 2717",
    "sg:postcode":"72207",
    "sg:province":"AR",
    "sg:tags":[
        "parlor",
        "shoes"
    ],
    "wof:name":"Shoe Master",
    "wof:placetype":"venue"
},
  "geometry": {"coordinates":[-92.339904,34.769413],"type":"Point"}
}