{
  "type": "Feature",
  "properties": {
    "addr:full":"2000 Columbia Road 11 E Magnolia AR 71753",
    "addr:housenumber":"2000",
    "addr:postcode":"71753",
    "addr:street":"Columbia Road 11 E Magnolia",
    "iso:country":"US",
    "sg:address":"2000 Columbia Road 11 E",
    "sg:city":"Magnolia",
    "sg:classifiers":[
        {
            "category":"Manufacturing",
            "subcategory":"Buildings",
            "type":"Manufacturing & Wholesale Goods"
        },
        {
            "category":"Building & Trades",
            "subcategory":"Construction",
            "type":"Services"
        }
    ],
    "sg:phone":"+1 870 234 2716",
    "sg:postcode":"71753",
    "sg:province":"AR",
    "sg:tags":[
        "home",
        "builder",
        "contractor"
    ],
    "wof:name":"Morgan Builders",
    "wof:placetype":"venue"
},
  "geometry": {"coordinates":[-93.168379,33.222328],"type":"Point"}
}