{
  "type": "Feature",
  "properties": {
    "iso:country":"US",
    "sg:address":"5119 Vaughn Rd",
    "sg:city":"North Little Rock",
    "sg:classifiers":[
        {
            "category":"Freight",
            "type":"Transportation"
        }
    ],
    "sg:phone":"+1 501 753 2150",
    "sg:postcode":"72118",
    "sg:province":"AR",
    "sg:tags":[
        "operator",
        "local",
        "trucking"
    ],
    "wof:name":"P&J Trucking Inc",
    "wof:placetype":"venue"
},
  "geometry": {"coordinates":[-92.324098,34.820229],"type":"Point"}
}