{
  "type": "Feature",
  "properties": {
    "addr:full":"2520 Riverfront Dr Little Rock AR 72202",
    "addr:housenumber":"2520",
    "addr:postcode":"72202",
    "addr:street":"Riverfront Dr",
    "iso:country":"US",
    "sg:address":"2520 Riverfront Dr",
    "sg:city":"Little Rock",
    "sg:classifiers":[
        {
            "category":"Professional",
            "subcategory":"Art Services",
            "type":"Services"
        }
    ],
    "sg:phone":"+1 501 661 4650",
    "sg:postcode":"72202",
    "sg:province":"AR",
    "sg:tags":[
        "commercial",
        "design"
    ],
    "wof:name":"Birddog Creative",
    "wof:placetype":"venue"
},
  "geometry": {"coordinates":[-92.31153,34.774921],"type":"Point"}
}