{
  "type": "Feature",
  "properties": {
    "addr:full":"222 State Hwy 7 Jasper AR 72641",
    "addr:housenumber":"222",
    "addr:postcode":"72641",
    "addr:street":"State Hwy 7",
    "iso:country":"US",
    "sg:address":"222 State Hwy 7",
    "sg:city":"Jasper",
    "sg:classifiers":[
        {
            "category":"Insurance",
            "subcategory":"Insurance Agent",
            "type":"Services"
        }
    ],
    "sg:phone":"+1 870 446 5590",
    "sg:postcode":"72641",
    "sg:province":"AR",
    "wof:name":"Newton County Farm Bureau",
    "wof:placetype":"venue"
},
  "geometry": {"coordinates":[-93.18705,36.003721],"type":"Point"}
}