{
  "type": "Feature",
  "properties": {
    "iso:country":"US",
    "sg:address":"809 N Hervey St",
    "sg:city":"Hope",
    "sg:classifiers":[
        {
            "category":"Personal",
            "subcategory":"Beauty Salon",
            "type":"Services"
        }
    ],
    "sg:phone":"+1 870 722 6137",
    "sg:postcode":"71801",
    "sg:province":"AR",
    "sg:tags":[
        "manicuring"
    ],
    "wof:name":"Lovely Nails",
    "wof:placetype":"venue"
},
  "geometry": {"coordinates":[-93.59938099999999,33.675092],"type":"Point"}
}