{
  "type": "Feature",
  "properties": {
    "addr:full":"1214 W School St Ozark AR 72949",
    "addr:housenumber":"1214",
    "addr:postcode":"72949",
    "addr:street":"W School St",
    "iso:country":"US",
    "sg:address":"1214 W School St",
    "sg:city":"Ozark",
    "sg:classifiers":[
        {
            "category":"Social Services",
            "subcategory":"Job Training",
            "type":"Services"
        }
    ],
    "sg:phone":"+1 479 667 4477",
    "sg:postcode":"72949",
    "sg:province":"AR",
    "sg:tags":[
        "rehabilitation"
    ],
    "wof:name":"Enterpriser",
    "wof:placetype":"venue"
},
  "geometry": {"coordinates":[-93.837884,35.489783],"type":"Point"}
}