{
  "type": "Feature",
  "properties": {
    "iso:country":"US",
    "sg:address":"720 N Gaskill St",
    "sg:city":"Huntsville",
    "sg:classifiers":[
        {
            "category":"Health Services",
            "subcategory":"Health Practitioner",
            "type":"Services"
        }
    ],
    "sg:phone":"+1 479 738 5415",
    "sg:postcode":"72740",
    "sg:province":"AR",
    "sg:tags":[
        "therapist",
        "physical"
    ],
    "wof:name":"EHS Huntsville Physcl Thrpy",
    "wof:placetype":"venue"
},
  "geometry": {"coordinates":[-93.74243,36.090766],"type":"Point"}
}