{
  "type": "Feature",
  "properties": {
    "iso:country":"US",
    "sg:address":"109 Bear Tooth Pass",
    "sg:city":"Monticello",
    "sg:classifiers":[
        {
            "category":"Travel",
            "subcategory":"Travel Agent",
            "type":"Entertainment"
        }
    ],
    "sg:phone":"+1 870 367 3427",
    "sg:postcode":"71655",
    "sg:province":"AR",
    "sg:tags":[
        "agency",
        "bureau"
    ],
    "wof:name":"Great Escapes",
    "wof:placetype":"venue"
},
  "geometry": {"coordinates":[-91.755733,33.728885],"type":"Point"}
}