{
  "type": "Feature",
  "properties": {
    "addr:full":"412 E Harding Ave Pine Bluff AR 71601",
    "addr:housenumber":"412",
    "addr:postcode":"71601",
    "addr:street":"E Harding Ave",
    "iso:country":"US",
    "sg:address":"412 E Harding Ave",
    "sg:city":"Pine Bluff",
    "sg:classifiers":[
        {
            "category":"Restaurant",
            "type":"Food & Drink"
        }
    ],
    "sg:phone":"+1 870 536 4681",
    "sg:postcode":"71601",
    "sg:province":"AR",
    "sg:tags":[
        "eating"
    ],
    "wof:name":"Rib Shack Restaurant",
    "wof:placetype":"venue"
},
  "geometry": {"coordinates":[-91.99930500000001,34.212704],"type":"Point"}
}