{
  "type": "Feature",
  "properties": {
    "iso:country":"US",
    "sg:address":"103 S Carter Ave",
    "sg:city":"Lincoln",
    "sg:classifiers":[
        {
            "category":"Building & Trades",
            "subcategory":"Construction",
            "type":"Services"
        }
    ],
    "sg:phone":"+1 479 824 3636",
    "sg:postcode":"72744",
    "sg:province":"AR",
    "sg:tags":[
        "marking",
        "maintenance",
        "parking"
    ],
    "wof:name":"Lincoln Street Dept",
    "wof:placetype":"venue"
},
  "geometry": {"coordinates":[-94.422284,35.949806],"type":"Point"}
}