{
  "type": "Feature",
  "properties": {
    "addr:full":"9601 Lile Dr Little Rock AR 72205",
    "addr:housenumber":"9601",
    "addr:postcode":"72205",
    "addr:street":"Lile Dr",
    "iso:country":"US",
    "sg:address":"9601 Lile Dr",
    "sg:city":"Little Rock",
    "sg:classifiers":[
        {
            "category":"Health Services",
            "subcategory":"Doctor",
            "type":"Services"
        }
    ],
    "sg:phone":"+1 501 227 9434",
    "sg:postcode":"72205",
    "sg:province":"AR",
    "sg:tags":[
        "medical"
    ],
    "wof:name":"Crow R Lewis MD PA",
    "wof:placetype":"venue"
},
  "geometry": {"coordinates":[-92.37944,34.74543],"type":"Point"}
}