{
  "type": "Feature",
  "properties": {
    "iso:country":"US",
    "sg:address":"100 Whitetail Ln",
    "sg:city":"Stuttgart",
    "sg:phone":"+1 870 673 7730",
    "sg:postcode":"72160",
    "sg:province":"AR",
    "sg:tags":[
        "farm",
        "wheat",
        "soybean"
    ],
    "wof:name":"Johnny Simpson",
    "wof:placetype":"venue"
},
  "geometry": {"coordinates":[-91.603357,34.436254],"type":"Point"}
}