{
  "type": "Feature",
  "properties": {
    "iso:country":"US",
    "sg:address":"212 Natural Resource Dr",
    "sg:city":"Little Rock",
    "sg:classifiers":[
        {
            "category":"Health Services",
            "subcategory":"Health Practitioner",
            "type":"Services"
        }
    ],
    "sg:phone":"+1 501 847 7251",
    "sg:postcode":"72205",
    "sg:province":"AR",
    "sg:tags":[
        "therapist",
        "physical"
    ],
    "wof:name":"Arkansas Institute Of Rehab",
    "wof:placetype":"venue"
},
  "geometry": {"coordinates":[-92.386101,34.759133],"type":"Point"}
}