{
  "type": "Feature",
  "properties": {
    "addr:full":"7705 Southridge Dr Fort Smith AR 72908",
    "addr:housenumber":"7705",
    "addr:postcode":"72908",
    "addr:street":"Southridge Dr",
    "iso:country":"US",
    "sg:address":"7705 Southridge Dr",
    "sg:city":"Fort Smith",
    "sg:classifiers":[
        {
            "category":"Professional",
            "subcategory":"Computer Services",
            "type":"Services"
        }
    ],
    "sg:phone":"+1 479 782 0005",
    "sg:postcode":"72908",
    "sg:province":"AR",
    "sg:tags":[
        "internet"
    ],
    "sg:website":"www.cyberspyderwebservices.com",
    "wof:name":"Cyberspyder",
    "wof:placetype":"venue"
},
  "geometry": {"coordinates":[-94.420974,35.311253],"type":"Point"}
}