{
  "type": "Feature",
  "properties": {
    "iso:country":"US",
    "sg:address":"498 Kirby Rd",
    "sg:city":"Umpire",
    "sg:classifiers":[
        {
            "category":"Shopping",
            "subcategory":"Florist",
            "type":"Retail Goods"
        }
    ],
    "sg:phone":"+1 870 583 2831",
    "sg:postcode":"71971",
    "sg:province":"AR",
    "wof:name":"Kountry Kitchen & Krafts",
    "wof:placetype":"venue"
},
  "geometry": {"coordinates":[-94.061199,34.267708],"type":"Point"}
}