{
  "type": "Feature",
  "properties": {
    "iso:country":"US",
    "sg:address":"15113 Kent Dr",
    "sg:city":"Alexander",
    "sg:classifiers":[
        {
            "category":"Freight",
            "type":"Transportation"
        }
    ],
    "sg:phone":"+1 501 847 6135",
    "sg:postcode":"72002",
    "sg:province":"AR",
    "sg:tags":[
        "haul",
        "long",
        "trucking"
    ],
    "wof:name":"Td Transport Inc",
    "wof:placetype":"venue"
},
  "geometry": {"coordinates":[-92.444628,34.61417],"type":"Point"}
}