{
  "type": "Feature",
  "properties": {
    "iso:country":"US",
    "sg:address":"89 E Main St",
    "sg:city":"Lamar",
    "sg:classifiers":[
        {
            "category":"Organizations",
            "subcategory":"Professional Association",
            "type":"Services"
        }
    ],
    "sg:phone":"+1 479 885 2607",
    "sg:postcode":"72846",
    "sg:province":"AR",
    "wof:name":"East Johnson County Water Assn",
    "wof:placetype":"venue"
},
  "geometry": {"coordinates":[-93.386766,35.440294],"type":"Point"}
}