{
  "type": "Feature",
  "properties": {
    "iso:country":"US",
    "sg:address":"628 Hwy 412 W",
    "sg:city":"Fayetteville",
    "sg:classifiers":[
        {
            "category":"Professional",
            "subcategory":"Lawyer & Legal Services",
            "type":"Services"
        }
    ],
    "sg:phone":"+1 479 521 5656",
    "sg:postcode":"72761",
    "sg:province":"OK",
    "sg:tags":[
        "attorney"
    ],
    "wof:name":"Norwood & Norwood",
    "wof:placetype":"venue"
},
  "geometry": {"coordinates":[-94.547237,36.173671],"type":"Point"}
}