{
  "type": "Feature",
  "properties": {
    "iso:country":"US",
    "sg:address":"8900 Maumelle Blvd",
    "sg:city":"N Little Rock",
    "sg:phone":"+1 501 812 5030",
    "sg:postcode":"72113",
    "sg:province":"AR",
    "sg:tags":[
        "equipment",
        "supply"
    ],
    "sg:website":"www.pioneerdc.com",
    "wof:name":"Pioneer Distributing Co",
    "wof:placetype":"venue"
},
  "geometry": {"coordinates":[-92.362396,34.81382],"type":"Point"}
}