{
  "type": "Feature",
  "properties": {
    "addr:full":"2814 John Harden Dr Jacksonville AR 72076",
    "addr:housenumber":"2814",
    "addr:postcode":"72076",
    "addr:street":"John Harden Dr",
    "iso:country":"US",
    "sg:address":"2814 John Harden Dr",
    "sg:city":"Jacksonville",
    "sg:classifiers":[
        {
            "category":"Manufacturing",
            "subcategory":"Food",
            "type":"Manufacturing & Wholesale Goods"
        },
        {
            "category":"Wholesale",
            "subcategory":"Groceries",
            "type":"Manufacturing & Wholesale Goods"
        },
        {
            "category":"Ice Cream",
            "type":"Food & Drink"
        }
    ],
    "sg:phone":"+1 501 982 6550",
    "sg:postcode":"72076",
    "sg:province":"AR",
    "sg:tags":[
        "frozen",
        "dessert",
        "products-wholesale"
    ],
    "sg:website":"http://www.schwans.com",
    "wof:name":"Schwan's",
    "wof:placetype":"venue"
},
  "geometry": {"coordinates":[-92.103139,34.890951],"type":"Point"}
}