{
  "type": "Feature",
  "properties": {
    "iso:country":"US",
    "sg:address":"620 N Main St",
    "sg:city":"Harrison",
    "sg:classifiers":[
        {
            "category":"Health Services",
            "subcategory":"Hospital",
            "type":"Services"
        },
        {
            "category":"Community Center",
            "type":"Public Place"
        },
        {
            "category":"Health Services",
            "subcategory":"Clinic",
            "type":"Services"
        }
    ],
    "sg:phone":"+1 870 414 4000",
    "sg:postcode":"72601",
    "sg:province":"AR",
    "sg:tags":[
        "medical",
        "surgery"
    ],
    "sg:website":"http://www.narmc.com",
    "wof:name":"North Arkansas Regional Medical Center",
    "wof:placetype":"venue"
},
  "geometry": {"coordinates":[-93.107158,36.235765],"type":"Point"}
}