{
  "type": "Feature",
  "properties": {
    "iso:country":"US",
    "sg:address":"1003 W Main St",
    "sg:city":"Clarksville",
    "sg:classifiers":[
        {
            "category":"Retail",
            "subcategory":"Laundry & Dry Cleaning",
            "type":"Services"
        }
    ],
    "sg:phone":"+1 479 754 4855",
    "sg:postcode":"72830",
    "sg:province":"AR",
    "wof:name":"Collins Laundry",
    "wof:placetype":"venue"
},
  "geometry": {"coordinates":[-93.470961,35.470853],"type":"Point"}
}