{
  "type": "Feature",
  "properties": {
    "iso:country":"US",
    "sg:address":"5704 McClure Rd",
    "sg:city":"Van Buren",
    "sg:classifiers":[
        {
            "category":"Professional",
            "subcategory":"Secretarial Services",
            "type":"Services"
        }
    ],
    "sg:phone":"+1 479 410 3101",
    "sg:postcode":"72956",
    "sg:province":"AR",
    "sg:tags":[
        "resume"
    ],
    "sg:website":"www.1executiveresume.com",
    "wof:name":"A Great Resume Svc",
    "wof:placetype":"venue"
},
  "geometry": {"coordinates":[-94.286406,35.391777],"type":"Point"}
}