{
  "type": "Feature",
  "properties": {
    "iso:country":"US",
    "sg:address":"258 Highway 332 E",
    "sg:city":"Hope",
    "sg:classifiers":[
        {
            "category":"Farming",
            "subcategory":"Farm",
            "type":"Manufacturing & Wholesale Goods"
        }
    ],
    "sg:phone":"+1 870 777 6956",
    "sg:postcode":"71801",
    "sg:province":"AR",
    "wof:name":"Ronnie Burke",
    "wof:placetype":"venue"
},
  "geometry": {"coordinates":[-93.56650500000001,33.776157],"type":"Point"}
}