{
  "type": "Feature",
  "properties": {
    "addr:full":"1901 W Pullen St Pine Bluff AR 71601",
    "addr:housenumber":"1901",
    "addr:postcode":"71601",
    "addr:street":"W Pullen St",
    "iso:country":"US",
    "sg:address":"1901 W Pullen St",
    "sg:city":"Pine Bluff",
    "sg:classifiers":[
        {
            "category":"Retail",
            "subcategory":"Repair Shop",
            "type":"Services"
        }
    ],
    "sg:phone":"+1 870 535 8173",
    "sg:postcode":"71601",
    "sg:province":"AR",
    "sg:tags":[
        "repairing",
        "piano",
        "refinishing"
    ],
    "wof:name":"Martin Piano Co & Furn Movers",
    "wof:placetype":"venue"
},
  "geometry": {"coordinates":[-92.022471,34.230744],"type":"Point"}
}