{
  "type": "Feature",
  "properties": {
    "iso:country":"US",
    "sg:address":"233 Garden Oaks Dr SW",
    "sg:city":"Camden",
    "sg:classifiers":[
        {
            "category":"Shopping",
            "subcategory":"Musical Instruments",
            "type":"Retail Goods"
        },
        {
            "category":"Arts & Performance",
            "subcategory":"Music",
            "type":"Entertainment"
        }
    ],
    "sg:phone":"+1 870 836 6844",
    "sg:postcode":"71701",
    "sg:province":"AR",
    "sg:tags":[
        "guitar",
        "amplifier",
        "sheet"
    ],
    "wof:name":"Bensberg Music Store",
    "wof:placetype":"venue"
},
  "geometry": {"coordinates":[-92.849698,33.584077],"type":"Point"}
}