{
  "type": "Feature",
  "properties": {
    "iso:country":"US",
    "sg:address":"127 Honson Dr",
    "sg:city":"Monticello",
    "sg:classifiers":[
        {
            "category":"Freight",
            "type":"Transportation"
        }
    ],
    "sg:phone":"+1 870 367 2754",
    "sg:postcode":"71655",
    "sg:province":"AR",
    "sg:tags":[
        "trucking"
    ],
    "wof:name":"Jam Trucking Inc",
    "wof:placetype":"venue"
},
  "geometry": {"coordinates":[-91.827061,33.648217],"type":"Point"}
}