{
  "type": "Feature",
  "properties": {
    "iso:country":"US",
    "sg:address":"2501 N State Line Ave",
    "sg:city":"Texarkana",
    "sg:classifiers":[
        {
            "category":"Shopping",
            "subcategory":"Clothing, Apparel, & Fashions",
            "type":"Retail Goods"
        }
    ],
    "sg:phone":"+1 903 793 7333",
    "sg:postcode":"75503",
    "sg:province":"TX",
    "sg:tags":[
        "shop",
        "bridal"
    ],
    "wof:name":"Reed's Bridal",
    "wof:placetype":"venue"
},
  "geometry": {"coordinates":[-94.04310599999999,33.441117],"type":"Point"}
}