{
  "type": "Feature",
  "properties": {
    "addr:full":"129 Co Rd 741 Wynne AR 72396",
    "addr:housenumber":"129;741",
    "addr:postcode":"72396",
    "addr:street":"Co Rd",
    "iso:country":"US",
    "sg:address":"129 Co Rd 741",
    "sg:city":"Wynne",
    "sg:classifiers":[
        {
            "category":"Organizations",
            "subcategory":"Religious Organization",
            "type":"Services"
        }
    ],
    "sg:phone":"+1 870 238 9719",
    "sg:postcode":"72396",
    "sg:province":"AR",
    "sg:tags":[
        "church"
    ],
    "wof:name":"St James Missionary Baptist",
    "wof:placetype":"venue"
},
  "geometry": {"coordinates":[-90.79633,35.18609],"type":"Point"}
}