{
  "type": "Feature",
  "properties": {
    "iso:country":"US",
    "sg:address":"222 E Semmes Ave",
    "sg:city":"Osceola",
    "sg:classifiers":[
        {
            "category":"Organizations",
            "subcategory":"Religious Organization",
            "type":"Services"
        }
    ],
    "sg:phone":"+1 870 563 5731",
    "sg:postcode":"72370",
    "sg:province":"AR",
    "wof:name":"Pleasant Grove Baptist Chur Ch",
    "wof:placetype":"venue"
},
  "geometry": {"coordinates":[-89.966467,35.70482],"type":"Point"}
}