{
  "type": "Feature",
  "properties": {
    "addr:full":"23808 State Hwy 300 Roland AR 72135",
    "addr:housenumber":"23808",
    "addr:postcode":"72135",
    "addr:street":"State Hwy 300 Roland",
    "iso:country":"US",
    "sg:address":"23808 State Hwy 300",
    "sg:city":"Roland",
    "sg:classifiers":[
        {
            "category":"Organizations",
            "subcategory":"Religious Organization",
            "type":"Services"
        }
    ],
    "sg:phone":"+1 501 868 8419",
    "sg:postcode":"72135",
    "sg:province":"AR",
    "sg:tags":[
        "church"
    ],
    "wof:name":"Mt Moriah United Pent Church",
    "wof:placetype":"venue"
},
  "geometry": {"coordinates":[-92.521036,34.916134],"type":"Point"}
}