{
  "type": "Feature",
  "properties": {
    "iso:country":"US",
    "sg:address":"404 S Main St",
    "sg:city":"Jonesboro",
    "sg:classifiers":[
        {
            "category":"Professional",
            "subcategory":"Lawyer & Legal Services",
            "type":"Services"
        }
    ],
    "sg:phone":"+1 870 935 5400",
    "sg:postcode":"72401",
    "sg:province":"AR",
    "sg:tags":[
        "attorney"
    ],
    "wof:name":"Paul N Ford",
    "wof:placetype":"venue"
},
  "geometry": {"coordinates":[-90.704874,35.839081],"type":"Point"}
}