{
  "type": "Feature",
  "properties": {
    "iso:country":"US",
    "sg:address":"2915 S Hazel St",
    "sg:city":"Pine Bluff",
    "sg:classifiers":[
        {
            "category":"Health Services",
            "subcategory":"Clinic",
            "type":"Services"
        }
    ],
    "sg:phone":"+1 870 535 0010",
    "sg:postcode":"71603",
    "sg:province":"AR",
    "sg:tags":[
        "specialty",
        "outpatient"
    ],
    "wof:name":"Boaz Carter and Associates",
    "wof:placetype":"venue"
},
  "geometry": {"coordinates":[-92.024561,34.199174],"type":"Point"}
}