{
  "type": "Feature",
  "properties": {
    "addr:full":"3105 S Main St Searcy AR 72143",
    "addr:housenumber":"3105",
    "addr:postcode":"72143",
    "addr:street":"S Main St",
    "iso:country":"US",
    "sg:address":"3105 S Main St",
    "sg:city":"Searcy",
    "sg:classifiers":[
        {
            "category":"Professional",
            "subcategory":"Employment Agencies",
            "type":"Services"
        }
    ],
    "sg:phone":"+1 501 268 8162",
    "sg:postcode":"72143",
    "sg:province":"AR",
    "sg:tags":[
        "consultant",
        "search",
        "executive"
    ],
    "wof:name":"Arkansas State Recruiting",
    "wof:placetype":"venue"
},
  "geometry": {"coordinates":[-91.732587,35.210293],"type":"Point"}
}