{
  "type": "Feature",
  "properties": {
    "iso:country":"US",
    "sg:address":"4909 Dollarway Rd",
    "sg:city":"White Hall",
    "sg:classifiers":[
        {
            "category":"Autos & Motor Vehicles",
            "subcategory":"Automobile Sales",
            "type":"Retail Goods"
        }
    ],
    "sg:phone":"+1 870 535 3263",
    "sg:postcode":"71602",
    "sg:province":"AR",
    "sg:tags":[
        "car",
        "used",
        "dealer"
    ],
    "wof:name":"Dane's Auto Sales",
    "wof:placetype":"venue"
},
  "geometry": {"coordinates":[-92.05413,34.2414],"type":"Point"}
}