{
  "type": "Feature",
  "properties": {
    "iso:country":"US",
    "sg:address":"510 E Huntsville Rd",
    "sg:city":"Fayetteville",
    "sg:classifiers":[
        {
            "category":"Professional",
            "subcategory":"Accounting & Tax Preparation",
            "type":"Services"
        }
    ],
    "sg:phone":"+1 479 527 9301",
    "sg:postcode":"72701",
    "sg:province":"AR",
    "sg:tags":[
        "return"
    ],
    "wof:name":"Fayetteville Bookkeeping & Tax",
    "wof:placetype":"venue"
},
  "geometry": {"coordinates":[-94.15173,36.056643],"type":"Point"}
}