{
  "type": "Feature",
  "properties": {
    "iso:country":"US",
    "sg:address":"11800 Sweetwater Run",
    "sg:city":"N Little Rock",
    "sg:classifiers":[
        {
            "category":"Restaurant",
            "type":"Food & Drink"
        }
    ],
    "sg:phone":"+1 501 945 7533",
    "sg:postcode":"72117",
    "sg:province":"AR",
    "sg:tags":[
        "personal",
        "eating",
        "caterer"
    ],
    "wof:name":"Mom's Catering",
    "wof:placetype":"venue"
},
  "geometry": {"coordinates":[-92.13455,34.775753],"type":"Point"}
}