{
  "type": "Feature",
  "properties": {
    "iso:country":"US",
    "sg:address":"33 Shannon Dr",
    "sg:city":"Little Rock",
    "sg:classifiers":[
        {
            "category":"Real Estate",
            "subcategory":"Real Estate Operator",
            "type":"Services"
        }
    ],
    "sg:phone":"+1 501 666 2140",
    "sg:postcode":"72207",
    "sg:province":"AR",
    "sg:tags":[
        "building",
        "nonresidential"
    ],
    "wof:name":"C&P Properties LLC",
    "wof:placetype":"venue"
},
  "geometry": {"coordinates":[-92.34770899999999,34.767421],"type":"Point"}
}