{
  "type": "Feature",
  "properties": {
    "iso:country":"US",
    "sg:address":"723 Broadway St",
    "sg:city":"Smackover",
    "sg:classifiers":[
        {
            "category":"Shopping",
            "subcategory":"Clothing, Apparel, & Fashions",
            "type":"Retail Goods"
        }
    ],
    "sg:phone":"+1 870 725 3541",
    "sg:postcode":"71762",
    "sg:province":"AR",
    "wof:name":"Classic Dress Shop The",
    "wof:placetype":"venue"
},
  "geometry": {"coordinates":[-92.722783,33.370253],"type":"Point"}
}