{
  "type": "Feature",
  "properties": {
    "iso:country":"US",
    "sg:address":"820 Gravel Pit Rd",
    "sg:city":"Camden",
    "sg:classifiers":[
        {
            "category":"Organizations",
            "subcategory":"Religious Organization",
            "type":"Services"
        }
    ],
    "sg:phone":"+1 870 836 3744",
    "sg:postcode":"71701",
    "sg:province":"AR",
    "sg:tags":[
        "church"
    ],
    "wof:name":"Zion Hill Baptist Church",
    "wof:placetype":"venue"
},
  "geometry": {"coordinates":[-92.83769,33.59915],"type":"Point"}
}