{
  "type": "Feature",
  "properties": {
    "iso:country":"US",
    "sg:address":"405 W Pridemore Dr",
    "sg:city":"Lincoln",
    "sg:classifiers":[
        {
            "category":"Shopping",
            "subcategory":"Used Merchandise",
            "type":"Retail Goods"
        }
    ],
    "sg:phone":"+1 479 824 3227",
    "sg:postcode":"72744",
    "sg:province":"AR",
    "sg:tags":[
        "flea",
        "market"
    ],
    "wof:name":"Treasure Chest Flea Market",
    "wof:placetype":"venue"
},
  "geometry": {"coordinates":[-94.42997,35.949867],"type":"Point"}
}