{
  "type": "Feature",
  "properties": {
    "addr:full":"101 Hwy 412 E Siloam Springs OK 72761",
    "addr:housenumber":"101",
    "addr:postcode":"72761",
    "addr:street":"Hwy 412 E",
    "iso:country":"US",
    "sg:address":"101 Hwy 412 E",
    "sg:city":"Siloam Springs",
    "sg:classifiers":[
        {
            "category":"Banks & Credit Unions",
            "subcategory":"Bank",
            "type":"Services"
        }
    ],
    "sg:phone":"+1 479 238 8140",
    "sg:postcode":"72761",
    "sg:province":"OK",
    "wof:name":"Liberty Bank",
    "wof:placetype":"venue"
},
  "geometry": {"coordinates":[-94.541506,36.172457],"type":"Point"}
}