{
  "type": "Feature",
  "properties": {
    "addr:full":"1821 N Garland Ave Fayetteville AR 72703",
    "addr:housenumber":"1821",
    "addr:postcode":"72703",
    "addr:street":"N Garland Ave",
    "iso:country":"US",
    "sg:address":"1821 N Garland Ave",
    "sg:city":"Fayetteville",
    "sg:classifiers":[
        {
            "category":"Professional",
            "subcategory":"Detective & Security Services",
            "type":"Services"
        }
    ],
    "sg:phone":"+1 479 650 2927",
    "sg:postcode":"72703",
    "sg:province":"AR",
    "sg:tags":[
        "information",
        "bureau"
    ],
    "wof:name":"Alan Edmondson",
    "wof:placetype":"venue"
},
  "geometry": {"coordinates":[-94.175017,36.087189],"type":"Point"}
}