{
  "type": "Feature",
  "properties": {
    "iso:country":"US",
    "sg:address":"1807 Linda Ln",
    "sg:city":"Jacksonville",
    "sg:classifiers":[
        {
            "category":"Building & Trades",
            "subcategory":"Plumbing",
            "type":"Services"
        }
    ],
    "sg:phone":"+1 501 985 3999",
    "sg:postcode":"72076",
    "sg:province":"AR",
    "sg:tags":[
        "conditioning",
        "air",
        "system",
        "contractor"
    ],
    "wof:name":"Meade's Heating & Air Cond",
    "wof:placetype":"venue"
},
  "geometry": {"coordinates":[-92.101133,34.882139],"type":"Point"}
}