{
  "type": "Feature",
  "properties": {
    "addr:full":"4609 Camp Robinson Rd N Little Rock AR 72118",
    "addr:housenumber":"4609",
    "addr:postcode":"72118",
    "addr:street":"Camp Robinson Rd N",
    "iso:country":"US",
    "sg:address":"4609 Camp Robinson Rd",
    "sg:city":"N Little Rock",
    "sg:classifiers":[
        {
            "category":"Social Services",
            "subcategory":"Child Care",
            "type":"Services"
        }
    ],
    "sg:phone":"+1 501 753 7390",
    "sg:postcode":"72118",
    "sg:province":"AR",
    "wof:name":"Bambino's Childcare & Learning",
    "wof:placetype":"venue"
},
  "geometry": {"coordinates":[-92.27103700000001,34.795568],"type":"Point"}
}