{
  "type": "Feature",
  "properties": {
    "addr:full":"305 N C St Rogers AR 72756",
    "addr:housenumber":"305",
    "addr:postcode":"72756",
    "addr:street":"N C St",
    "iso:country":"US",
    "sg:address":"305 N C St",
    "sg:city":"Rogers",
    "sg:classifiers":[
        {
            "category":"Real Estate",
            "subcategory":"Real Estate Agent",
            "type":"Services"
        }
    ],
    "sg:phone":"+1 479 636 5629",
    "sg:postcode":"72756",
    "sg:province":"AR",
    "wof:name":"Schade Enterprises",
    "wof:placetype":"venue"
},
  "geometry": {"coordinates":[-94.11287299999999,36.3347],"type":"Point"}
}