{
  "type": "Feature",
  "properties": {
    "addr:full":"2305 Covington Dr North Little Rock AR 72116",
    "addr:housenumber":"2305",
    "addr:postcode":"72116",
    "addr:street":"Covington Dr",
    "iso:country":"US",
    "sg:address":"2305 Covington Dr",
    "sg:city":"North Little Rock",
    "sg:classifiers":[
        {
            "category":"Professional",
            "subcategory":"Business Services",
            "type":"Services"
        }
    ],
    "sg:phone":"+1 501 834 3344",
    "sg:postcode":"72116",
    "sg:province":"AR",
    "wof:name":"Van Patten & Co LLC",
    "wof:placetype":"venue"
},
  "geometry": {"coordinates":[-92.238708,34.82666],"type":"Point"}
}