{
  "type": "Feature",
  "properties": {
    "iso:country":"US",
    "sg:address":"121 E Main St",
    "sg:city":"Heber Springs",
    "sg:classifiers":[
        {
            "category":"Freight",
            "type":"Transportation"
        }
    ],
    "sg:phone":"+1 501 362 8764",
    "sg:postcode":"72543",
    "sg:province":"AR",
    "sg:tags":[
        "commercial",
        "storage"
    ],
    "wof:name":"Spengler's TLC Moving Co",
    "wof:placetype":"venue"
},
  "geometry": {"coordinates":[-92.028824,35.491331],"type":"Point"}
}