{
  "type": "Feature",
  "properties": {
    "addr:full":"2223 Main St Little Rock AR 72206",
    "addr:housenumber":"2223",
    "addr:postcode":"72206",
    "addr:street":"Main St",
    "iso:country":"US",
    "sg:address":"2223 Main St",
    "sg:city":"Little Rock",
    "sg:classifiers":[
        {
            "category":"Social Services",
            "subcategory":"Job Training",
            "type":"Services"
        },
        {
            "category":"Social Services",
            "type":"Services"
        }
    ],
    "sg:phone":"+1 501 374 2870",
    "sg:postcode":"72206",
    "sg:province":"AR",
    "sg:tags":[
        "rehabilitation"
    ],
    "wof:name":"Richard Allen Living Center Fo",
    "wof:placetype":"venue"
},
  "geometry": {"coordinates":[-92.27377199999999,34.726763],"type":"Point"}
}