{
  "type": "Feature",
  "properties": {
    "iso:country":"US",
    "sg:address":"4505 W 12th St",
    "sg:city":"Little Rock",
    "sg:classifiers":[
        {
            "category":"Food & Beverages",
            "subcategory":"Meat & Fish",
            "type":"Retail Goods"
        }
    ],
    "sg:phone":"+1 501 666 3456",
    "sg:postcode":"72204",
    "sg:province":"AR",
    "sg:tags":[
        "seafood"
    ],
    "wof:name":"Peter's Fish Market",
    "wof:placetype":"venue"
},
  "geometry": {"coordinates":[-92.324883,34.740735],"type":"Point"}
}