{
  "type": "Feature",
  "properties": {
    "addr:full":"4201 N Shiloh Dr Fayetteville AR 72703",
    "addr:housenumber":"4201",
    "addr:postcode":"72703",
    "addr:street":"N Shiloh Dr",
    "iso:country":"US",
    "sg:address":"4201 N Shiloh Dr",
    "sg:city":"Fayetteville",
    "sg:classifiers":[
        {
            "category":"Health Services",
            "subcategory":"Optometrist",
            "type":"Services"
        }
    ],
    "sg:phone":"+1 479 444 8705",
    "sg:postcode":"72703",
    "sg:province":"AR",
    "wof:name":"Daniels, Lance",
    "wof:placetype":"venue"
},
  "geometry": {"coordinates":[-94.14527099999999,36.124828],"type":"Point"}
}