{
  "type": "Feature",
  "properties": {
    "iso:country":"US",
    "sg:address":"31 US Hwy 70",
    "sg:city":"De Valls Bluff",
    "sg:classifiers":[
        {
            "category":"Autos & Motor Vehicles",
            "subcategory":"Auto Supplies",
            "type":"Retail Goods"
        }
    ],
    "sg:phone":"+1 870 998 7021",
    "sg:postcode":"72041",
    "sg:province":"AR",
    "sg:tags":[
        "automobile",
        "parts"
    ],
    "wof:name":"D & T Auto Parts",
    "wof:placetype":"venue"
},
  "geometry": {"coordinates":[-91.458655,34.781532],"type":"Point"}
}