{
  "type": "Feature",
  "properties": {
    "addr:full":"309 N 6th St West Memphis AR 72301",
    "addr:housenumber":"309",
    "addr:postcode":"72301",
    "addr:street":"N 6Th St",
    "iso:country":"US",
    "sg:address":"309 N 6th St",
    "sg:city":"West Memphis",
    "sg:classifiers":[
        {
            "category":"Professional",
            "subcategory":"Accounting & Tax Preparation",
            "type":"Services"
        }
    ],
    "sg:phone":"+1 870 735 3683",
    "sg:postcode":"72301",
    "sg:province":"AR",
    "sg:tags":[
        "return",
        "filing"
    ],
    "wof:name":"Jeter Tax Svc",
    "wof:placetype":"venue"
},
  "geometry": {"coordinates":[-90.176958,35.150184],"type":"Point"}
}