{
  "type": "Feature",
  "properties": {
    "iso:country":"US",
    "sg:address":"950 Hogan Ln Ste 4",
    "sg:city":"Conway",
    "sg:classifiers":[
        {
            "category":"Insurance",
            "subcategory":"Insurance Agent",
            "type":"Services"
        },
        {
            "category":"Insurance",
            "subcategory":"Hazard Insurance",
            "type":"Services"
        }
    ],
    "sg:phone":"+1 501 505 8485",
    "sg:postcode":"72034",
    "sg:province":"AR",
    "sg:tags":[
        "adjuster"
    ],
    "wof:name":"Rickman's Claim Service",
    "wof:placetype":"venue"
},
  "geometry": {"coordinates":[-92.497833,35.092972],"type":"Point"}
}