{
  "type": "Feature",
  "properties": {
    "addr:full":"201 Twilight Ave White Hall AR 71602",
    "addr:housenumber":"201",
    "addr:postcode":"71602",
    "addr:street":"Twilight Ave",
    "iso:country":"US",
    "sg:address":"201 Twilight Ave",
    "sg:city":"White Hall",
    "sg:classifiers":[
        {
            "category":"Real Estate",
            "subcategory":"Real Estate Operator",
            "type":"Services"
        }
    ],
    "sg:phone":"+1 870 247 5252",
    "sg:postcode":"71602",
    "sg:province":"AR",
    "sg:tags":[
        "property",
        "lessor"
    ],
    "wof:name":"Tknmd Ltd Co",
    "wof:placetype":"venue"
},
  "geometry": {"coordinates":[-92.091127,34.278459],"type":"Point"}
}