{
  "type": "Feature",
  "properties": {
    "addr:full":"904 Bryan Ave Corning AR 72422",
    "addr:housenumber":"904",
    "addr:postcode":"72422",
    "addr:street":"Bryan Ave",
    "iso:country":"US",
    "sg:address":"904 Bryan Ave",
    "sg:city":"Corning",
    "sg:classifiers":[
        {
            "category":"Farming",
            "subcategory":"Farm",
            "type":"Manufacturing & Wholesale Goods"
        }
    ],
    "sg:phone":"+1 870 857 9612",
    "sg:postcode":"72422",
    "sg:province":"AR",
    "sg:tags":[
        "crop",
        "general"
    ],
    "wof:name":"Sarah Leonard LLC",
    "wof:placetype":"venue"
},
  "geometry": {"coordinates":[-90.590377,36.401758],"type":"Point"}
}