{
  "type": "Feature",
  "properties": {
    "addr:full":"1009 N Main St Harrison AR 72601",
    "addr:housenumber":"1009",
    "addr:postcode":"72601",
    "addr:street":"N Main St",
    "iso:country":"US",
    "sg:address":"1009 N Main St",
    "sg:city":"Harrison",
    "sg:classifiers":[
        {
            "category":"Manufacturing",
            "subcategory":"Rubber & Plastics",
            "type":"Manufacturing & Wholesale Goods"
        },
        {
            "category":"Autos & Motor Vehicles",
            "subcategory":"Auto Supplies",
            "type":"Retail Goods"
        },
        {
            "category":"Retail",
            "subcategory":"Auto Repair",
            "type":"Services"
        }
    ],
    "sg:phone":"+1 870 741 2740",
    "sg:postcode":"72601",
    "sg:province":"AR",
    "sg:tags":[
        "recap",
        "retread",
        "tires-wholesale",
        "tire",
        "manufacturer"
    ],
    "sg:website":"http://www.coopertire.com/html/",
    "wof:name":"Hudson Tire & Battery Inc",
    "wof:placetype":"venue"
},
  "geometry": {"coordinates":[-93.108231,36.241119],"type":"Point"}
}