{
  "type": "Feature",
  "properties": {
    "iso:country":"US",
    "sg:address":"2487 Finch Rd",
    "sg:city":"Bismarck",
    "sg:classifiers":[
        {
            "category":"Building & Trades",
            "subcategory":"Landscaping Services",
            "type":"Services"
        }
    ],
    "sg:phone":"+1 501 520 8587",
    "sg:postcode":"71929",
    "sg:province":"AR",
    "sg:tags":[
        "tree"
    ],
    "wof:name":"Lambert's Bucket Truck & Tree",
    "wof:placetype":"venue"
},
  "geometry": {"coordinates":[-93.18714,34.317901],"type":"Point"}
}