{
  "type": "Feature",
  "properties": {
    "addr:full":"4489 Harrison St Batesville AR 72501",
    "addr:housenumber":"4489",
    "addr:postcode":"72501",
    "addr:street":"Harrison St",
    "iso:country":"US",
    "sg:address":"4489 Harrison St",
    "sg:city":"Batesville",
    "sg:classifiers":[
        {
            "category":"Home & Garden",
            "subcategory":"Building Materials",
            "type":"Retail Goods"
        }
    ],
    "sg:phone":"+1 870 793 6612",
    "sg:postcode":"72501",
    "sg:province":"AR",
    "sg:tags":[
        "lumber"
    ],
    "wof:name":"Ridout Home Center",
    "wof:placetype":"venue"
},
  "geometry": {"coordinates":[-91.577623,35.76894],"type":"Point"}
}