{
  "type": "Feature",
  "properties": {
    "addr:full":"4033 E Broadway St N Little Rock AR 72114",
    "addr:housenumber":"4033",
    "addr:postcode":"72114",
    "addr:street":"E Broadway St N",
    "iso:country":"US",
    "sg:address":"4033 E Broadway St",
    "sg:city":"N Little Rock",
    "sg:phone":"+1 501 945 4555",
    "sg:postcode":"72114",
    "sg:province":"AR",
    "sg:tags":[
        "distributor",
        "oil",
        "marketer"
    ],
    "wof:name":"Green & Chapman Inc",
    "wof:placetype":"venue"
},
  "geometry": {"coordinates":[-92.220529,34.754457],"type":"Point"}
}