{
  "type": "Feature",
  "properties": {
    "iso:country":"US",
    "sg:address":"620 President Clinton Ave",
    "sg:city":"Little Rock",
    "sg:classifiers":[
        {
            "category":"Freight",
            "type":"Transportation"
        },
        {
            "category":"Professional",
            "subcategory":"Business Services",
            "type":"Services"
        }
    ],
    "sg:phone":"+1 501 374 3282",
    "sg:postcode":"72201",
    "sg:province":"AR",
    "sg:tags":[
        "record",
        "special",
        "general"
    ],
    "wof:name":"Data File Storage",
    "wof:placetype":"venue"
},
  "geometry": {"coordinates":[-92.262921,34.74709],"type":"Point"}
}