{
  "type": "Feature",
  "properties": {
    "iso:country":"US",
    "sg:address":"119 Oak St",
    "sg:city":"Hot Springs National",
    "sg:classifiers":[
        {
            "category":"Real Estate",
            "subcategory":"Real Estate Operator",
            "type":"Services"
        }
    ],
    "sg:phone":"+1 501 623 3404",
    "sg:postcode":"71901",
    "sg:province":"AR",
    "sg:tags":[
        "building",
        "apartment"
    ],
    "wof:name":"William Jefferson Clinton Cult",
    "wof:placetype":"venue"
},
  "geometry": {"coordinates":[-93.053755,34.50633],"type":"Point"}
}