{
  "type": "Feature",
  "properties": {
    "iso:country":"US",
    "sg:address":"3624 Garland Ave",
    "sg:city":"Texarkana",
    "sg:classifiers":[
        {
            "category":"Education",
            "subcategory":"School",
            "type":"Public Place"
        }
    ],
    "sg:phone":"+1 870 772 7853",
    "sg:postcode":"71854",
    "sg:province":"AR",
    "wof:name":"Arkansas Sc Texarkana",
    "wof:placetype":"venue"
},
  "geometry": {"coordinates":[-94.033541,33.457666],"type":"Point"}
}