{
  "type": "Feature",
  "properties": {
    "addr:full":"6204 Magnolia Hwy El Dorado AR 71730",
    "addr:housenumber":"6204",
    "addr:postcode":"71730",
    "addr:street":"Magnolia Hwy",
    "iso:country":"US",
    "sg:address":"6204 Magnolia Hwy",
    "sg:city":"El Dorado",
    "sg:classifiers":[
        {
            "category":"Home & Garden",
            "subcategory":"Building Materials",
            "type":"Retail Goods"
        },
        {
            "category":"Building & Trades",
            "subcategory":"Construction",
            "type":"Services"
        }
    ],
    "sg:phone":"+1 870 863 9382",
    "sg:postcode":"71730",
    "sg:province":"AR",
    "sg:tags":[
        "glass",
        "contractor",
        "door",
        "type"
    ],
    "wof:name":"Union Mirror & Glass Co",
    "wof:placetype":"venue"
},
  "geometry": {"coordinates":[-92.78904799999999,33.208714],"type":"Point"}
}