{
  "type": "Feature",
  "properties": {
    "iso:country":"US",
    "sg:address":"415 N College Ave",
    "sg:city":"Fayetteville",
    "sg:classifiers":[
        {
            "category":"Personal",
            "subcategory":"Beauty Salon",
            "type":"Services"
        }
    ],
    "sg:phone":"+1 479 443 2725",
    "sg:postcode":"72701",
    "sg:province":"AR",
    "sg:tags":[
        "hair",
        "stylist"
    ],
    "wof:name":"Karma Hair Studio",
    "wof:placetype":"venue"
},
  "geometry": {"coordinates":[-94.157754,36.068708],"type":"Point"}
}