{
  "type": "Feature",
  "properties": {
    "iso:country":"US",
    "sg:address":"2324 E Matthews Ave",
    "sg:city":"Jonesboro",
    "sg:classifiers":[
        {
            "category":"Restaurant",
            "type":"Food & Drink"
        }
    ],
    "sg:phone":"+1 870 931 0109",
    "sg:postcode":"72401",
    "sg:province":"AR",
    "sg:tags":[
        "pizza"
    ],
    "wof:name":"Pizza Chef Gourmet Pizza",
    "wof:placetype":"venue"
},
  "geometry": {"coordinates":[-90.673575,35.834441],"type":"Point"}
}