{
  "type": "Feature",
  "properties": {
    "iso:country":"US",
    "sg:address":"223 Civic St",
    "sg:city":"Hot Springs",
    "sg:classifiers":[
        {
            "category":"Organizations",
            "subcategory":"Community Association",
            "type":"Services"
        }
    ],
    "sg:phone":"+1 501 624 9111",
    "sg:postcode":"71901",
    "sg:province":"AR",
    "sg:tags":[
        "club"
    ],
    "wof:name":"Hard Times Bar",
    "wof:placetype":"venue"
},
  "geometry": {"coordinates":[-93.050624,34.510948],"type":"Point"}
}