{
  "type": "Feature",
  "properties": {
    "iso:country":"US",
    "sg:address":"1300 W 18th St",
    "sg:city":"N Little Rock",
    "sg:classifiers":[
        {
            "category":"Organizations",
            "subcategory":"Non-profit Organization",
            "type":"Services"
        }
    ],
    "sg:phone":"+1 501 666 0246",
    "sg:postcode":"72114",
    "sg:province":"AR",
    "wof:name":"Arkansas Enterprises-Disabled",
    "wof:placetype":"venue"
},
  "geometry": {"coordinates":[-92.281314,34.772366],"type":"Point"}
}