{
  "type": "Feature",
  "properties": {
    "iso:country":"US",
    "sg:address":"4221 E Johnson Ave",
    "sg:city":"Jonesboro",
    "sg:classifiers":[
        {
            "category":"Autos & Motor Vehicles",
            "subcategory":"Automobile Sales",
            "type":"Retail Goods"
        }
    ],
    "sg:phone":"+1 870 972 0885",
    "sg:postcode":"72401",
    "sg:province":"AR",
    "sg:tags":[
        "dealers-used",
        "car",
        "used",
        "cars-wholesale"
    ],
    "wof:name":"Rgb Auto Sales",
    "wof:placetype":"venue"
},
  "geometry": {"coordinates":[-90.639071,35.864204],"type":"Point"}
}