{
  "type": "Feature",
  "properties": {
    "iso:country":"US",
    "sg:address":"6910 Alcoa Rd",
    "sg:city":"Benton",
    "sg:classifiers":[
        {
            "category":"Freight",
            "type":"Transportation"
        }
    ],
    "sg:phone":"+1 501 315 1082",
    "sg:postcode":"72015",
    "sg:province":"AR",
    "sg:tags":[
        "commercial",
        "storage",
        "special"
    ],
    "wof:name":"Benton Storage Center",
    "wof:placetype":"venue"
},
  "geometry": {"coordinates":[-92.534449,34.599802],"type":"Point"}
}