{
  "type": "Feature",
  "properties": {
    "iso:country":"US",
    "sg:address":"5217 Darr Hill Rd",
    "sg:city":"Jonesboro",
    "sg:phone":"+1 870 935 3324",
    "sg:postcode":"72404",
    "sg:province":"AR",
    "sg:tags":[
        "farm",
        "rice",
        "soybean"
    ],
    "wof:name":"Gary Renck",
    "wof:placetype":"venue"
},
  "geometry": {"coordinates":[-90.745757,35.781097],"type":"Point"}
}