{
  "type": "Feature",
  "properties": {
    "iso:country":"US",
    "sg:address":"101 N Locust St",
    "sg:city":"Lead Hill",
    "sg:classifiers":[
        {
            "category":"Building & Trades",
            "subcategory":"Plumbing",
            "type":"Services"
        }
    ],
    "sg:phone":"+1 870 436 5242",
    "sg:postcode":"72644",
    "sg:province":"AR",
    "sg:tags":[
        "heating",
        "contractor"
    ],
    "wof:name":"O'Neal's Electric & Heating",
    "wof:placetype":"venue"
},
  "geometry": {"coordinates":[-92.909937,36.4219],"type":"Point"}
}