{
  "type": "Feature",
  "properties": {
    "iso:country":"US",
    "sg:address":"2619 Pecan Grove Rd",
    "sg:city":"Alma",
    "sg:classifiers":[
        {
            "category":"Personal",
            "subcategory":"Beauty Salon",
            "type":"Services"
        }
    ],
    "sg:phone":"+1 479 632 2756",
    "sg:postcode":"72921",
    "sg:province":"AR",
    "sg:tags":[
        "shop"
    ],
    "wof:name":"Ninas Beauty Shop",
    "wof:placetype":"venue"
},
  "geometry": {"coordinates":[-94.255424,35.514108],"type":"Point"}
}