{
  "type": "Feature",
  "properties": {
    "iso:country":"US",
    "sg:address":"2500 S 25th Cir",
    "sg:city":"Van Buren",
    "sg:classifiers":[
        {
            "category":"Freight",
            "type":"Transportation"
        }
    ],
    "sg:phone":"+1 479 410 2361",
    "sg:postcode":"72956",
    "sg:province":"AR",
    "sg:tags":[
        "operator",
        "trucking"
    ],
    "wof:name":"Dan Vic Distributions",
    "wof:placetype":"venue"
},
  "geometry": {"coordinates":[-94.33241099999999,35.420331],"type":"Point"}
}