{
  "type": "Feature",
  "properties": {
    "iso:country":"US",
    "sg:address":"3606 E 35th St",
    "sg:city":"Little Rock",
    "sg:classifiers":[
        {
            "category":"Autos & Motor Vehicles",
            "subcategory":"Automobile Sales",
            "type":"Retail Goods"
        }
    ],
    "sg:phone":"+1 501 490 4004",
    "sg:postcode":"72206",
    "sg:province":"AR",
    "sg:tags":[
        "used"
    ],
    "wof:name":"George Dobbing Used Cars",
    "wof:placetype":"venue"
},
  "geometry": {"coordinates":[-92.23024,34.71281],"type":"Point"}
}