{
  "type": "Feature",
  "properties": {
    "iso:country":"US",
    "sg:address":"10151 N Whitehouse Rd",
    "sg:city":"Fayetteville",
    "sg:classifiers":[
        {
            "category":"Professional",
            "subcategory":"Detective & Security Services",
            "type":"Services"
        }
    ],
    "sg:phone":"+1 479 643 3391",
    "sg:postcode":"72701",
    "sg:province":"AR",
    "sg:tags":[
        "information",
        "bureau"
    ],
    "wof:name":"H And H Electric Service",
    "wof:placetype":"venue"
},
  "geometry": {"coordinates":[-94.040176,35.982461],"type":"Point"}
}