{
  "type": "Feature",
  "properties": {
    "iso:country":"US",
    "sg:address":"2015 N Main St",
    "sg:city":"N Little Rock",
    "sg:classifiers":[
        {
            "category":"Health Services",
            "subcategory":"Clinic",
            "type":"Services"
        }
    ],
    "sg:phone":"+1 501 758 5156",
    "sg:postcode":"72114",
    "sg:province":"AR",
    "sg:tags":[
        "home"
    ],
    "wof:name":"Not Home Alone Aftercare",
    "wof:placetype":"venue"
},
  "geometry": {"coordinates":[-92.267029,34.774119],"type":"Point"}
}