{
  "type": "Feature",
  "properties": {
    "addr:full":"1722 N Starr Dr Fayetteville AR 72701",
    "addr:housenumber":"1722",
    "addr:postcode":"72701",
    "addr:street":"N Starr Dr",
    "iso:country":"US",
    "sg:address":"1722 N Starr Dr",
    "sg:city":"Fayetteville",
    "sg:classifiers":[
        {
            "category":"Education",
            "subcategory":"School",
            "type":"Public Place"
        }
    ],
    "sg:phone":"+1 479 442 0890",
    "sg:postcode":"72701",
    "sg:province":"AR",
    "wof:name":"Saint Joseph Catholic School",
    "wof:placetype":"venue"
},
  "geometry": {"coordinates":[-94.11246199999999,36.082063],"type":"Point"}
}