{
  "type": "Feature",
  "properties": {
    "iso:country":"US",
    "sg:address":"214 Hester Parker Dr",
    "sg:city":"Marked Tree",
    "sg:classifiers":[
        {
            "category":"Banks & Credit Unions",
            "subcategory":"Financial Services",
            "type":"Services"
        }
    ],
    "sg:phone":"+1 870 358 6000",
    "sg:postcode":"72365",
    "sg:province":"AR",
    "sg:tags":[
        "company",
        "holding"
    ],
    "wof:name":"Tyronza Bancshares",
    "wof:placetype":"venue"
},
  "geometry": {"coordinates":[-90.43274,35.528001],"type":"Point"}
}