{
  "type": "Feature",
  "properties": {
    "iso:country":"US",
    "sg:address":"2400 Albert Pike Rd",
    "sg:city":"Hot Springs National Park",
    "sg:classifiers":[
        {
            "category":"Home & Garden",
            "subcategory":"Hardware",
            "type":"Retail Goods"
        }
    ],
    "sg:phone":"+1 501 767 0002",
    "sg:postcode":"71913",
    "sg:province":"AR",
    "wof:name":"Riser Value Center",
    "wof:placetype":"venue"
},
  "geometry": {"coordinates":[-93.108992,34.492222],"type":"Point"}
}