{
  "type": "Feature",
  "properties": {
    "iso:country":"US",
    "sg:address":"203 NW Texas St",
    "sg:city":"Hoxie",
    "sg:classifiers":[
        {
            "category":"Autos & Motor Vehicles",
            "subcategory":"Fuel & Gas Station",
            "type":"Retail Goods"
        }
    ],
    "sg:phone":"+1 870 886 9932",
    "sg:postcode":"72433",
    "sg:province":"AR",
    "sg:tags":[
        "tackle",
        "gasoline",
        "oil",
        "bait"
    ],
    "wof:name":"Little's Service Station",
    "wof:placetype":"venue"
},
  "geometry": {"coordinates":[-90.973007,36.053353],"type":"Point"}
}