{
  "type": "Feature",
  "properties": {
    "iso:country":"US",
    "sg:address":"2220 Duracrete",
    "sg:city":"Magnolia",
    "sg:classifiers":[
        {
            "category":"Wholesale",
            "subcategory":"Metals & Minerals",
            "type":"Manufacturing & Wholesale Goods"
        }
    ],
    "sg:phone":"+1 870 234 3111",
    "sg:postcode":"71753",
    "sg:province":"AR",
    "sg:tags":[
        "pipe"
    ],
    "wof:name":"J-M Manufacturing",
    "wof:placetype":"venue"
},
  "geometry": {"coordinates":[-93.244836,33.245993],"type":"Point"}
}