{
  "type": "Feature",
  "properties": {
    "iso:country":"US",
    "sg:address":"13652 N Wedington Blacktop Rd",
    "sg:city":"Lincoln",
    "sg:classifiers":[
        {
            "category":"Farming",
            "subcategory":"Dairy Farm",
            "type":"Manufacturing & Wholesale Goods"
        }
    ],
    "sg:phone":"+1 479 846 2914",
    "sg:postcode":"72744",
    "sg:province":"AR",
    "wof:name":"Jack Hulet",
    "wof:placetype":"venue"
},
  "geometry": {"coordinates":[-94.391746,36.06069],"type":"Point"}
}