{
  "type": "Feature",
  "properties": {
    "iso:country":"US",
    "sg:address":"381 Rock Creek Rd",
    "sg:city":"Glenwood",
    "sg:classifiers":[
        {
            "category":"Manufacturing",
            "subcategory":"Tools & Machinery",
            "type":"Manufacturing & Wholesale Goods"
        },
        {
            "category":"Retail",
            "subcategory":"Repair Shop",
            "type":"Services"
        }
    ],
    "sg:phone":"+1 870 356 3523",
    "sg:postcode":"71943",
    "sg:province":"AR",
    "sg:tags":[
        "machine",
        "die",
        "maker",
        "machinery-rebuild"
    ],
    "wof:name":"Bopp Gordon Mold & Machine Company Inc",
    "wof:placetype":"venue"
},
  "geometry": {"coordinates":[-93.571184,34.309821],"type":"Point"}
}