{
  "type": "Feature",
  "properties": {
    "iso:country":"US",
    "sg:address":"4412 Macarthur Dr",
    "sg:city":"N Little Rock",
    "sg:classifiers":[
        {
            "category":"Shopping",
            "subcategory":"Stationery & Office Supplies",
            "type":"Retail Goods"
        }
    ],
    "sg:phone":"+1 501 758 1050",
    "sg:postcode":"72118",
    "sg:province":"AR",
    "wof:name":"Settle Office Products",
    "wof:placetype":"venue"
},
  "geometry": {"coordinates":[-92.289078,34.795009],"type":"Point"}
}