{
  "type": "Feature",
  "properties": {
    "iso:country":"US",
    "sg:address":"200 W Price Ave",
    "sg:city":"Springdale",
    "sg:classifiers":[
        {
            "category":"Government",
            "subcategory":"Office",
            "type":"Public Place"
        }
    ],
    "sg:phone":"+1 479 756 2037",
    "sg:postcode":"72764",
    "sg:province":"AR",
    "wof:name":"Northwest Arkansas Work Releas",
    "wof:placetype":"venue"
},
  "geometry": {"coordinates":[-94.13313,36.18778],"type":"Point"}
}