{
  "type": "Feature",
  "properties": {
    "iso:country":"US",
    "sg:address":"5111 Rogers Ave",
    "sg:city":"Fort Smith",
    "sg:classifiers":[
        {
            "category":"Professional",
            "type":"Services"
        }
    ],
    "sg:phone":"+1 479 452 1000",
    "sg:postcode":"72903",
    "sg:province":"AR",
    "sg:tags":[
        "establishment"
    ],
    "wof:name":"Warmack & Co",
    "wof:placetype":"venue"
},
  "geometry": {"coordinates":[-94.376942,35.365752],"type":"Point"}
}