{
  "type": "Feature",
  "properties": {
    "iso:country":"US",
    "sg:address":"221 Smith St",
    "sg:city":"Magnolia",
    "sg:classifiers":[
        {
            "category":"Organizations",
            "subcategory":"Religious Organization",
            "type":"Services"
        }
    ],
    "sg:phone":"+1 870 901 6653",
    "sg:postcode":"71753",
    "sg:province":"AR",
    "wof:name":"Magnolia Seventh Day Adventist",
    "wof:placetype":"venue"
},
  "geometry": {"coordinates":[-93.23877400000001,33.272172],"type":"Point"}
}