{
  "type": "Feature",
  "properties": {
    "iso:country":"US",
    "sg:address":"217 McMahan St",
    "sg:city":"Hot Springs",
    "sg:classifiers":[
        {
            "category":"Restaurant",
            "type":"Food & Drink"
        }
    ],
    "sg:phone":"+1 501 623 6467",
    "sg:postcode":"71913",
    "sg:province":"AR",
    "wof:name":"Burger King",
    "wof:placetype":"venue"
},
  "geometry": {"coordinates":[-93.058111,34.473123],"type":"Point"}
}