{
  "type": "Feature",
  "properties": {
    "iso:country":"US",
    "sg:address":"900 N Airport Rd",
    "sg:city":"Marion",
    "sg:classifiers":[
        {
            "category":"Restaurant",
            "type":"Food & Drink"
        }
    ],
    "sg:phone":"+1 870 559 2458",
    "sg:postcode":"72364",
    "sg:province":"AR",
    "wof:name":"Horizon Center Plaza",
    "wof:placetype":"venue"
},
  "geometry": {"coordinates":[-90.22295099999999,35.188736],"type":"Point"}
}