{
  "type": "Feature",
  "properties": {
    "iso:country":"US",
    "sg:address":"44 King St",
    "sg:city":"Eureka Springs",
    "sg:classifiers":[
        {
            "category":"Education",
            "subcategory":"School",
            "type":"Public Place"
        }
    ],
    "sg:phone":"+1 479 253 8651",
    "sg:postcode":"72632",
    "sg:province":"AR",
    "wof:name":"Eureka Springs Public Schools",
    "wof:placetype":"venue"
},
  "geometry": {"coordinates":[-93.735464,36.408378],"type":"Point"}
}