{
  "type": "Feature",
  "properties": {
    "iso:country":"US",
    "sg:address":"4803 Highway 67 N",
    "sg:city":"Newport",
    "sg:classifiers":[
        {
            "category":"Wholesale",
            "subcategory":"Farm Supplies",
            "type":"Manufacturing & Wholesale Goods"
        },
        {
            "category":"Wholesale",
            "subcategory":"Machinery & Supplies",
            "type":"Manufacturing & Wholesale Goods"
        },
        {
            "category":"Recreation",
            "subcategory":"Picnic Area",
            "type":"Entertainment"
        }
    ],
    "sg:phone":"+1 870 523 5504",
    "sg:postcode":"72112",
    "sg:province":"AR",
    "sg:tags":[
        "baling",
        "repair",
        "equipment-parts",
        "equipment"
    ],
    "sg:website":"http://www.allenmfgco.com",
    "wof:name":"Allen Manufacturing Co Inc",
    "wof:placetype":"venue"
},
  "geometry": {"coordinates":[-91.216744,35.703528],"type":"Point"}
}