{
  "type": "Feature",
  "properties": {
    "iso:country":"US",
    "sg:address":"734 E Lakeside Dr",
    "sg:city":"Fayetteville",
    "sg:classifiers":[
        {
            "category":"Banks & Credit Unions",
            "subcategory":"Investment Brokerage",
            "type":"Services"
        }
    ],
    "sg:phone":"+1 479 442 2414",
    "sg:postcode":"72701",
    "sg:province":"AR",
    "sg:tags":[
        "advisory"
    ],
    "wof:name":"Edb Investments",
    "wof:placetype":"venue"
},
  "geometry": {"coordinates":[-94.148205,36.076504],"type":"Point"}
}