{
  "type": "Feature",
  "properties": {
    "iso:country":"US",
    "sg:address":"1127 Glenwood Dr",
    "sg:city":"El Dorado",
    "sg:classifiers":[
        {
            "category":"Recreation",
            "type":"Entertainment"
        }
    ],
    "sg:phone":"+1 870 862 1171",
    "sg:postcode":"71730",
    "sg:province":"AR",
    "sg:tags":[
        "club",
        "tennis",
        "court",
        "swimming"
    ],
    "wof:name":"El Dorado Racquet Club Inc",
    "wof:placetype":"venue"
},
  "geometry": {"coordinates":[-92.679966,33.231748],"type":"Point"}
}