{
  "type": "Feature",
  "properties": {
    "addr:full":"2 Clement Dr Little Rock AR 72209",
    "addr:housenumber":"2",
    "addr:postcode":"72209",
    "addr:street":"Clement Dr",
    "iso:country":"US",
    "sg:address":"2 Clement Dr",
    "sg:city":"Little Rock",
    "sg:classifiers":[
        {
            "category":"Food & Beverages",
            "subcategory":"Specialty",
            "type":"Retail Goods"
        }
    ],
    "sg:phone":"+1 501 562 5955",
    "sg:postcode":"72209",
    "sg:province":"AR",
    "wof:name":"Herbalife Distributor",
    "wof:placetype":"venue"
},
  "geometry": {"coordinates":[-92.328006,34.681602],"type":"Point"}
}