{
  "type": "Feature",
  "properties": {
    "iso:country":"US",
    "sg:address":"7092 State Hwy 5",
    "sg:city":"Midway",
    "sg:classifiers":[
        {
            "category":"Real Estate",
            "subcategory":"Real Estate Operator",
            "type":"Services"
        }
    ],
    "sg:phone":"+1 870 481 5543",
    "sg:postcode":"72651",
    "sg:province":"AR",
    "sg:tags":[
        "mobile",
        "home",
        "community"
    ],
    "wof:name":"Country Life Mobile Home Park",
    "wof:placetype":"venue"
},
  "geometry": {"coordinates":[-92.469926,36.46193],"type":"Point"}
}