{
  "type": "Feature",
  "properties": {
    "iso:country":"US",
    "sg:address":"1635 Rainbow Rd",
    "sg:city":"Rogers",
    "sg:classifiers":[
        {
            "category":"Building & Trades",
            "subcategory":"Construction",
            "type":"Services"
        }
    ],
    "sg:phone":"+1 479 271 7563",
    "sg:postcode":"72758",
    "sg:province":"AR",
    "sg:tags":[
        "hanging",
        "co",
        "contractor"
    ],
    "wof:name":"Laxen Painting",
    "wof:placetype":"venue"
},
  "geometry": {"coordinates":[-94.206828,36.322835],"type":"Point"}
}