{
  "type": "Feature",
  "properties": {
    "iso:country":"US",
    "sg:address":"203 S Clifton St",
    "sg:city":"Fordyce",
    "sg:classifiers":[
        {
            "category":"Health Services",
            "subcategory":"Nursing And Care Facility",
            "type":"Services"
        }
    ],
    "sg:phone":"+1 870 352 3625",
    "sg:postcode":"71742",
    "sg:province":"AR",
    "wof:name":"Dallas County Nursing Home",
    "wof:placetype":"venue"
},
  "geometry": {"coordinates":[-92.425541,33.808509],"type":"Point"}
}