{
  "type": "Feature",
  "properties": {
    "iso:country":"US",
    "sg:address":"3000 E Highland Dr",
    "sg:city":"Jonesboro",
    "sg:classifiers":[
        {
            "category":"Real Estate",
            "subcategory":"Real Estate Operator",
            "type":"Services"
        }
    ],
    "sg:phone":"+1 870 336 2500",
    "sg:postcode":"72401",
    "sg:province":"AR",
    "sg:tags":[
        "shopping",
        "center",
        "mall",
        "department",
        "clothing",
        "store"
    ],
    "wof:name":"Mall At Turtle Creek",
    "wof:placetype":"venue"
},
  "geometry": {"coordinates":[-90.66927699999999,35.821146],"type":"Point"}
}