{
  "type": "Feature",
  "properties": {
    "iso:country":"US",
    "sg:address":"1270 Hwy 412 W",
    "sg:city":"Siloam Springs",
    "sg:classifiers":[
        {
            "category":"Building & Trades",
            "subcategory":"Construction",
            "type":"Services"
        }
    ],
    "sg:phone":"+1 479 524 4550",
    "sg:postcode":"72761",
    "sg:province":"OK",
    "sg:tags":[
        "company"
    ],
    "wof:name":"Leon Davis Construction",
    "wof:placetype":"venue"
},
  "geometry": {"coordinates":[-94.55345699999999,36.175457],"type":"Point"}
}