{
  "type": "Feature",
  "properties": {
    "iso:country":"US",
    "sg:address":"150 N School",
    "sg:city":"Bearden",
    "sg:classifiers":[
        {
            "category":"Health Services",
            "subcategory":"Doctor",
            "type":"Services"
        }
    ],
    "sg:phone":"+1 870 687 3637",
    "sg:postcode":"71720",
    "sg:province":"AR",
    "sg:tags":[
        "clinic"
    ],
    "wof:name":"Bearden Health Ctr",
    "wof:placetype":"venue"
},
  "geometry": {"coordinates":[-92.619053,33.723483],"type":"Point"}
}