{
  "type": "Feature",
  "properties": {
    "iso:country":"US",
    "sg:address":"704 E Rock St",
    "sg:city":"Morrilton",
    "sg:classifiers":[
        {
            "category":"Professional",
            "subcategory":"Detective & Security Services",
            "type":"Services"
        }
    ],
    "sg:phone":"+1 501 477 5021",
    "sg:postcode":"72110",
    "sg:province":"AR",
    "sg:tags":[
        "information",
        "bureau"
    ],
    "wof:name":"All Services",
    "wof:placetype":"venue"
},
  "geometry": {"coordinates":[-92.737427,35.158746],"type":"Point"}
}