{
  "type": "Feature",
  "properties": {
    "iso:country":"US",
    "sg:address":"223 N 1st St",
    "sg:city":"Blytheville",
    "sg:classifiers":[
        {
            "category":"Home & Garden",
            "subcategory":"Home Furnishings",
            "type":"Retail Goods"
        },
        {
            "category":"Home & Garden",
            "subcategory":"Carpets & Floor Coverings",
            "type":"Retail Goods"
        },
        {
            "category":"Home & Garden",
            "subcategory":"Furniture",
            "type":"Retail Goods"
        }
    ],
    "sg:phone":"+1 870 763 4577",
    "sg:postcode":"72315",
    "sg:province":"AR",
    "sg:tags":[
        "set",
        "rug",
        "bed",
        "mattress",
        "furniture-children's",
        "bedroom",
        "store"
    ],
    "wof:name":"First Street Furniture",
    "wof:placetype":"venue"
},
  "geometry": {"coordinates":[-89.902596,35.928629],"type":"Point"}
}