{
  "type": "Feature",
  "properties": {
    "addr:full":"560 Heritage Rd Rison AR 71665",
    "addr:housenumber":"560",
    "addr:postcode":"71665",
    "addr:street":"Heritage Rd",
    "iso:country":"US",
    "sg:address":"560 Heritage Rd",
    "sg:city":"Rison",
    "sg:classifiers":[
        {
            "category":"Real Estate",
            "subcategory":"Developer",
            "type":"Services"
        }
    ],
    "sg:phone":"+1 870 357 2839",
    "sg:postcode":"71665",
    "sg:province":"AR",
    "sg:tags":[
        "cemetery"
    ],
    "wof:name":"D & R Developments Inc",
    "wof:placetype":"venue"
},
  "geometry": {"coordinates":[-92.04228500000001,34.016717],"type":"Point"}
}