{
  "type": "Feature",
  "properties": {
    "iso:country":"US",
    "sg:address":"124 Bald Knob Rd",
    "sg:city":"Plumerville",
    "sg:classifiers":[
        {
            "category":"Home & Garden",
            "subcategory":"Building Materials",
            "type":"Retail Goods"
        }
    ],
    "sg:phone":"+1 501 354 2758",
    "sg:postcode":"72127",
    "sg:province":"AR",
    "wof:name":"L & M Metal Buildings LLC",
    "wof:placetype":"venue"
},
  "geometry": {"coordinates":[-92.646227,35.19024],"type":"Point"}
}