{
  "type": "Feature",
  "properties": {
    "iso:country":"US",
    "sg:address":"1011 Latigo Trl",
    "sg:city":"Jacksonville",
    "sg:classifiers":[
        {
            "category":"Social Services",
            "subcategory":"Child Care",
            "type":"Services"
        }
    ],
    "sg:phone":"+1 501 982 8343",
    "sg:postcode":"72076",
    "sg:province":"AR",
    "sg:tags":[
        "day"
    ],
    "wof:name":"Bobbie Shaver Day Care",
    "wof:placetype":"venue"
},
  "geometry": {"coordinates":[-92.096726,34.902722],"type":"Point"}
}