{
  "type": "Feature",
  "properties": {
    "iso:country":"US",
    "sg:address":"823 Martin Luther King Blvd",
    "sg:city":"Malvern",
    "sg:classifiers":[
        {
            "category":"Restaurant",
            "type":"Food & Drink"
        }
    ],
    "sg:phone":"+1 501 332 3848",
    "sg:postcode":"72104",
    "sg:province":"AR",
    "wof:name":"China Wok Buffet",
    "wof:placetype":"venue"
},
  "geometry": {"coordinates":[-92.823787,34.372682],"type":"Point"}
}