{
  "type": "Feature",
  "properties": {
    "iso:country":"US",
    "sg:address":"9 Cloverdale Dr",
    "sg:city":"Warren",
    "sg:classifiers":[
        {
            "category":"Manufacturing",
            "subcategory":"Lumber",
            "type":"Manufacturing & Wholesale Goods"
        }
    ],
    "sg:phone":"+1 870 226 9867",
    "sg:postcode":"71671",
    "sg:province":"AR",
    "sg:tags":[
        "forestry"
    ],
    "wof:name":"Cedar Creek Forestry",
    "wof:placetype":"venue"
},
  "geometry": {"coordinates":[-92.036677,33.605578],"type":"Point"}
}