{
  "type": "Feature",
  "properties": {
    "iso:country":"US",
    "sg:address":"4485 Cherrywood Ave",
    "sg:city":"Springdale",
    "sg:classifiers":[
        {
            "category":"Transit Center",
            "subcategory":"Freight",
            "type":"Transportation"
        },
        {
            "category":"Freight",
            "type":"Transportation"
        }
    ],
    "sg:phone":"+1 479 927 3014",
    "sg:postcode":"72762",
    "sg:province":"AR",
    "sg:tags":[
        "local",
        "trucking-motor",
        "trucking"
    ],
    "wof:name":"H J Trucking",
    "wof:placetype":"venue"
},
  "geometry": {"coordinates":[-94.179135,36.207324],"type":"Point"}
}