{
  "type": "Feature",
  "properties": {
    "addr:full":"1550 N Constitution Ave Ashdown AR 71822",
    "addr:housenumber":"1550",
    "addr:postcode":"71822",
    "addr:street":"N Constitution Ave",
    "iso:country":"US",
    "sg:address":"1550 N Constitution Ave",
    "sg:city":"Ashdown",
    "sg:classifiers":[
        {
            "category":"Retail",
            "subcategory":"Repair Shop",
            "type":"Services"
        }
    ],
    "sg:phone":"+1 870 898 5674",
    "sg:postcode":"71822",
    "sg:province":"AR",
    "sg:tags":[
        "machine",
        "washing"
    ],
    "wof:name":"Polly's Washer Repair",
    "wof:placetype":"venue"
},
  "geometry": {"coordinates":[-94.13695300000001,33.686879],"type":"Point"}
}