{
  "type": "Feature",
  "properties": {
    "iso:country":"US",
    "sg:address":"9 Mere Ln",
    "sg:city":"Bella Vista",
    "sg:classifiers":[
        {
            "category":"Retail",
            "subcategory":"Portrait Studio",
            "type":"Services"
        }
    ],
    "sg:phone":"+1 479 855 4660",
    "sg:postcode":"72714",
    "sg:province":"AR",
    "sg:tags":[
        "photo"
    ],
    "wof:name":"Johnson Photography",
    "wof:placetype":"venue"
},
  "geometry": {"coordinates":[-94.246094,36.483337],"type":"Point"}
}