{
  "type": "Feature",
  "properties": {
    "iso:country":"US",
    "sg:address":"211 N Walton Blvd",
    "sg:city":"Bentonville",
    "sg:classifiers":[
        {
            "category":"Insurance",
            "subcategory":"Insurance Agent",
            "type":"Services"
        }
    ],
    "sg:phone":"+1 479 464 4146",
    "sg:postcode":"72712",
    "sg:province":"AR",
    "wof:name":"Bill Fulkerson Insurance",
    "wof:placetype":"venue"
},
  "geometry": {"coordinates":[-94.221392,36.375151],"type":"Point"}
}