{
  "type": "Feature",
  "properties": {
    "iso:country":"US",
    "sg:address":"10 Market Plz",
    "sg:city":"N Little Rock",
    "sg:classifiers":[
        {
            "category":"Wholesale",
            "subcategory":"Fruits & Vegetables",
            "type":"Manufacturing & Wholesale Goods"
        }
    ],
    "sg:phone":"+1 501 945 4561",
    "sg:postcode":"72117",
    "sg:province":"AR",
    "wof:name":"Kyzer Plants & Produce Inc",
    "wof:placetype":"venue"
},
  "geometry": {"coordinates":[-92.20273,34.785986],"type":"Point"}
}