{
  "type": "Feature",
  "properties": {
    "addr:full":"4172 E McCain Blvd N Little Rock AR 72117",
    "addr:housenumber":"4172",
    "addr:postcode":"72117",
    "addr:street":"E Mccain Blvd N",
    "iso:country":"US",
    "sg:address":"4172 E McCain Blvd",
    "sg:city":"N Little Rock",
    "sg:classifiers":[
        {
            "category":"Shopping",
            "subcategory":"Clothing, Apparel, & Fashions",
            "type":"Retail Goods"
        }
    ],
    "sg:phone":"+1 501 945 4338",
    "sg:postcode":"72117",
    "sg:province":"AR",
    "wof:name":"It's Fashion",
    "wof:placetype":"venue"
},
  "geometry": {"coordinates":[-92.223111,34.789387],"type":"Point"}
}