{
  "type": "Feature",
  "properties": {
    "addr:full":"1320 N 10th St Arkadelphia AR 71923",
    "addr:housenumber":"1320",
    "addr:postcode":"71923",
    "addr:street":"N 10Th St",
    "iso:country":"US",
    "sg:address":"1320 N 10th St",
    "sg:city":"Arkadelphia",
    "sg:classifiers":[
        {
            "category":"Retail",
            "subcategory":"Repair Shop",
            "type":"Services"
        }
    ],
    "sg:phone":"+1 870 403 0554",
    "sg:postcode":"71923",
    "sg:province":"AR",
    "sg:tags":[
        "sharpening"
    ],
    "wof:name":"Pro Sharp",
    "wof:placetype":"venue"
},
  "geometry": {"coordinates":[-93.064679,34.147701],"type":"Point"}
}