{
  "type": "Feature",
  "properties": {
    "iso:country":"US",
    "sg:address":"250 S Constitution Ave",
    "sg:city":"Ashdown",
    "sg:classifiers":[
        {
            "category":"Travel",
            "subcategory":"Hotels & Motels",
            "type":"Entertainment"
        }
    ],
    "sg:phone":"+1 870 898 3357",
    "sg:postcode":"71822",
    "sg:province":"AR",
    "wof:name":"Budget Inn",
    "wof:placetype":"venue"
},
  "geometry": {"coordinates":[-94.12729,33.669978],"type":"Point"}
}