{
  "type": "Feature",
  "properties": {
    "addr:full":"2295 E Broadway Ave Forrest City AR 72335",
    "addr:housenumber":"2295",
    "addr:postcode":"72335",
    "addr:street":"E Broadway Ave",
    "iso:country":"US",
    "sg:address":"2295 E Broadway Ave",
    "sg:city":"Forrest City",
    "sg:classifiers":[
        {
            "category":"Building & Trades",
            "subcategory":"Construction",
            "type":"Services"
        }
    ],
    "sg:phone":"+1 870 633 2706",
    "sg:postcode":"72335",
    "sg:province":"AR",
    "sg:tags":[
        "general",
        "contractor"
    ],
    "wof:name":"CCR Inc",
    "wof:placetype":"venue"
},
  "geometry": {"coordinates":[-90.768461,35.012683],"type":"Point"}
}