{
  "type": "Feature",
  "properties": {
    "addr:full":"5723 Zero St Fort Smith AR 72903",
    "addr:postcode":"5723;72903",
    "addr:street":"Zero St",
    "iso:country":"US",
    "sg:address":"5723 Zero St",
    "sg:city":"Fort Smith",
    "sg:classifiers":[
        {
            "category":"Manufacturing",
            "subcategory":"Retail Goods",
            "type":"Manufacturing & Wholesale Goods"
        }
    ],
    "sg:phone":"+1 479 649 8818",
    "sg:postcode":"72903",
    "sg:province":"AR",
    "sg:tags":[
        "assembly",
        "fabricating"
    ],
    "wof:name":"Westark Diversified Enterprise",
    "wof:placetype":"venue"
},
  "geometry": {"coordinates":[-94.36492200000001,35.326817],"type":"Point"}
}