{
  "type": "Feature",
  "properties": {
    "iso:country":"US",
    "sg:address":"507 Pecan St",
    "sg:city":"Crossett",
    "sg:classifiers":[
        {
            "category":"Wholesale",
            "subcategory":"Non-durable Goods",
            "type":"Manufacturing & Wholesale Goods"
        }
    ],
    "sg:phone":"+1 870 364 6021",
    "sg:postcode":"71635",
    "sg:province":"AR",
    "sg:tags":[
        "craft",
        "supply"
    ],
    "wof:name":"Classic Touches",
    "wof:placetype":"venue"
},
  "geometry": {"coordinates":[-91.949433,33.130212],"type":"Point"}
}