{
  "type": "Feature",
  "properties": {
    "iso:country":"US",
    "sg:address":"1420 Mclain St Suite B",
    "sg:city":"Newport",
    "sg:classifiers":[
        {
            "category":"Banks & Credit Unions",
            "subcategory":"Investment Brokerage",
            "type":"Services"
        },
        {
            "category":"Banks & Credit Unions",
            "subcategory":"Bank",
            "type":"Services"
        },
        {
            "category":"Banks & Credit Unions",
            "subcategory":"Financial Services",
            "type":"Services"
        }
    ],
    "sg:phone":"+1 870 523 8780",
    "sg:postcode":"72112",
    "sg:province":"AR",
    "sg:tags":[
        "mutual",
        "retirement",
        "broker",
        "fund",
        "planning",
        "security",
        "bond",
        "stock"
    ],
    "sg:website":"http://www.edwardjones.com/en_US/fa/index.html&CIRN=407138",
    "wof:name":"Edward Jones - Financial Advisor: KEVIN BROWN",
    "wof:placetype":"venue"
},
  "geometry": {"coordinates":[-91.262621,35.607959],"type":"Point"}
}