{
  "type": "Feature",
  "properties": {
    "iso:country":"US",
    "sg:address":"125 S Spring St",
    "sg:city":"Searcy",
    "sg:classifiers":[
        {
            "category":"Professional",
            "type":"Services"
        }
    ],
    "sg:phone":"+1 501 268 0386",
    "sg:postcode":"72143",
    "sg:province":"AR",
    "sg:tags":[
        "establishment"
    ],
    "wof:name":"Ridout General Office",
    "wof:placetype":"venue"
},
  "geometry": {"coordinates":[-91.73763099999999,35.248472],"type":"Point"}
}