{
  "type": "Feature",
  "properties": {
    "iso:country":"US",
    "sg:address":"508 US Hwy 71",
    "sg:city":"De Queen",
    "sg:classifiers":[
        {
            "category":"Personal",
            "subcategory":"Beauty Salon",
            "type":"Services"
        }
    ],
    "sg:phone":"+1 870 584 3067",
    "sg:postcode":"71832",
    "sg:province":"AR",
    "wof:name":"Hill's For Beauty",
    "wof:placetype":"venue"
},
  "geometry": {"coordinates":[-94.322841,34.068008],"type":"Point"}
}