{
  "type": "Feature",
  "properties": {
    "addr:full":"3597 Junction City Hwy El Dorado AR 71730",
    "addr:housenumber":"3597",
    "addr:postcode":"71730",
    "addr:street":"Junction;Hwy",
    "iso:country":"US",
    "sg:address":"3597 Junction City Hwy",
    "sg:city":"El Dorado",
    "sg:classifiers":[
        {
            "category":"Autos & Motor Vehicles",
            "subcategory":"Motorcycle Sales",
            "type":"Retail Goods"
        }
    ],
    "sg:phone":"+1 870 864 0293",
    "sg:postcode":"71730",
    "sg:province":"AR",
    "sg:tags":[
        "scooter"
    ],
    "wof:name":"Gene's Moto Guzzi",
    "wof:placetype":"venue"
},
  "geometry": {"coordinates":[-92.63513500000001,33.181204],"type":"Point"}
}