{
  "type": "Feature",
  "properties": {
    "iso:country":"US",
    "sg:address":"431 McCain Blvd",
    "sg:city":"N Little Rock",
    "sg:classifiers":[
        {
            "category":"Real Estate",
            "subcategory":"Real Estate Operator",
            "type":"Services"
        }
    ],
    "sg:phone":"+1 501 791 0800",
    "sg:postcode":"72116",
    "sg:province":"AR",
    "sg:tags":[
        "apartment"
    ],
    "wof:name":"Ridgecrest-North Park",
    "wof:placetype":"venue"
},
  "geometry": {"coordinates":[-92.262686,34.798248],"type":"Point"}
}