{
  "type": "Feature",
  "properties": {
    "iso:country":"US",
    "sg:address":"2308 E Matthews Ave",
    "sg:city":"Jonesboro",
    "sg:classifiers":[
        {
            "category":"Building & Trades",
            "subcategory":"Equipment Rental",
            "type":"Services"
        }
    ],
    "sg:phone":"+1 870 932 4916",
    "sg:postcode":"72401",
    "sg:province":"AR",
    "wof:name":"E-Z Pay Rent To Own",
    "wof:placetype":"venue"
},
  "geometry": {"coordinates":[-90.673693,35.834444],"type":"Point"}
}