{
  "type": "Feature",
  "properties": {
    "iso:country":"US",
    "sg:address":"103 N Springfield St",
    "sg:city":"Berryville",
    "sg:classifiers":[
        {
            "category":"Retail",
            "subcategory":"Auto Repair",
            "type":"Services"
        }
    ],
    "sg:phone":"+1 870 423 6104",
    "sg:postcode":"72616",
    "sg:province":"AR",
    "sg:tags":[
        "wrecker"
    ],
    "wof:name":"G & I Towing",
    "wof:placetype":"venue"
},
  "geometry": {"coordinates":[-93.566317,36.366385],"type":"Point"}
}