{
  "type": "Feature",
  "properties": {
    "addr:full":"2010 Pike Ave North Little Rock AR 72114",
    "addr:housenumber":"2010",
    "addr:postcode":"72114",
    "addr:street":"Pike Ave",
    "iso:country":"US",
    "sg:address":"2010 Pike Ave",
    "sg:city":"North Little Rock",
    "sg:classifiers":[
        {
            "category":"Personal",
            "subcategory":"Beauty Salon",
            "type":"Services"
        }
    ],
    "sg:phone":"+1 501 753 0144",
    "sg:postcode":"72114",
    "sg:province":"AR",
    "sg:tags":[
        "shop"
    ],
    "wof:name":"Faith Buty & Barbr Hair Design",
    "wof:placetype":"venue"
},
  "geometry": {"coordinates":[-92.278434,34.774935],"type":"Point"}
}