{
  "type": "Feature",
  "properties": {
    "addr:full":"4500 Grand Ave Fort Smith AR 72904",
    "addr:housenumber":"4500",
    "addr:postcode":"72904",
    "addr:street":"Grand Ave",
    "iso:country":"US",
    "sg:address":"4500 Grand Ave",
    "sg:city":"Fort Smith",
    "sg:classifiers":[
        {
            "category":"Personal",
            "subcategory":"Beauty Salon",
            "type":"Services"
        }
    ],
    "sg:phone":"+1 479 782 4544",
    "sg:postcode":"72904",
    "sg:province":"AR",
    "sg:tags":[
        "shop"
    ],
    "wof:name":"Stacey's Place",
    "wof:placetype":"venue"
},
  "geometry": {"coordinates":[-94.38113,35.385512],"type":"Point"}
}