{
  "type": "Feature",
  "properties": {
    "iso:country":"US",
    "sg:address":"512 W Commercial St",
    "sg:city":"Ozark",
    "sg:classifiers":[
        {
            "category":"Insurance",
            "subcategory":"Insurance Agent",
            "type":"Services"
        },
        {
            "category":"Insurance",
            "subcategory":"Hazard Insurance",
            "type":"Services"
        },
        {
            "category":"Banks & Credit Unions",
            "subcategory":"Financial Services",
            "type":"Services"
        }
    ],
    "sg:phone":"+1 877 669 6877",
    "sg:postcode":"72949",
    "sg:province":"AR",
    "sg:tags":[
        "sharing",
        "business",
        "profit",
        "auto",
        "commercial",
        "pension",
        "property",
        "casualty",
        "plan"
    ],
    "sg:website":"http://www.nationwide.com",
    "wof:name":"Nationwide Insurance",
    "wof:placetype":"venue"
},
  "geometry": {"coordinates":[-93.829386,35.487151],"type":"Point"}
}