{
  "type": "Feature",
  "properties": {
    "iso:country":"US",
    "sg:address":"212 Arkansas Ave",
    "sg:city":"Forrest City",
    "sg:classifiers":[
        {
            "category":"Social Services",
            "subcategory":"Child Care",
            "type":"Services"
        }
    ],
    "sg:phone":"+1 870 494 4943",
    "sg:postcode":"72335",
    "sg:province":"AR",
    "wof:name":"Rainbow World Child Care",
    "wof:placetype":"venue"
},
  "geometry": {"coordinates":[-90.78836099999999,35.020069],"type":"Point"}
}