{
  "type": "Feature",
  "properties": {
    "iso:country":"US",
    "sg:address":"129 Hershell Rd",
    "sg:city":"Hot Springs",
    "sg:classifiers":[
        {
            "category":"Real Estate",
            "subcategory":"Real Estate Operator",
            "type":"Services"
        }
    ],
    "sg:phone":"+1 501 760 5143",
    "sg:postcode":"71913",
    "sg:province":"AR",
    "sg:tags":[
        "mobile",
        "home",
        "community"
    ],
    "wof:name":"Pine Mobile Home Park",
    "wof:placetype":"venue"
},
  "geometry": {"coordinates":[-93.16639499999999,34.455748],"type":"Point"}
}