{
  "type": "Feature",
  "properties": {
    "iso:country":"US",
    "sg:address":"312 W 18th St",
    "sg:city":"N Little Rock",
    "sg:classifiers":[
        {
            "category":"Retail",
            "subcategory":"Portrait Studio",
            "type":"Services"
        }
    ],
    "sg:phone":"+1 501 758 4223",
    "sg:postcode":"72114",
    "sg:province":"AR",
    "sg:tags":[
        "photographer",
        "photo"
    ],
    "wof:name":"Danny Youngblood Photography",
    "wof:placetype":"venue"
},
  "geometry": {"coordinates":[-92.271148,34.771342],"type":"Point"}
}