{
  "type": "Feature",
  "properties": {
    "iso:country":"US",
    "sg:address":"1400 Watson Ave",
    "sg:city":"Springdale",
    "sg:classifiers":[
        {
            "category":"Shopping",
            "type":"Retail Goods"
        }
    ],
    "sg:phone":"+1 479 273 1666",
    "sg:postcode":"72764",
    "sg:province":"AR",
    "sg:tags":[
        "telephone",
        "cellular"
    ],
    "wof:name":"A T & T Wireless Store",
    "wof:placetype":"venue"
},
  "geometry": {"coordinates":[-94.144803,36.178146],"type":"Point"}
}