{
  "type": "Feature",
  "properties": {
    "iso:country":"US",
    "sg:address":"7620 Rogers Ave",
    "sg:city":"Fort Smith",
    "sg:classifiers":[
        {
            "category":"Restaurant",
            "type":"Food & Drink"
        }
    ],
    "sg:menulink":"http://www.allmenus.com/ar/upper/109180-village-inn/menu/",
    "sg:phone":"+1 479 452 7007",
    "sg:postcode":"72903",
    "sg:province":"AR",
    "sg:tags":[
        "new",
        "american"
    ],
    "wof:name":"Village Inn",
    "wof:placetype":"venue"
},
  "geometry": {"coordinates":[-94.34840199999999,35.351646],"type":"Point"}
}