{
  "type": "Feature",
  "properties": {
    "iso:country":"US",
    "sg:address":"117 E Center St",
    "sg:city":"Beebe",
    "sg:classifiers":[
        {
            "category":"Restaurant",
            "type":"Food & Drink"
        }
    ],
    "sg:phone":"+1 501 882 2302",
    "sg:postcode":"72012",
    "sg:province":"AR",
    "sg:tags":[
        "eating"
    ],
    "wof:name":"Boxcar Cafe",
    "wof:placetype":"venue"
},
  "geometry": {"coordinates":[-91.87965699999999,35.070526],"type":"Point"}
}