{
  "type": "Feature",
  "properties": {
    "iso:country":"US",
    "sg:address":"420 W Jefferson Ave",
    "sg:city":"Jonesboro",
    "sg:classifiers":[
        {
            "category":"Social Services",
            "type":"Services"
        }
    ],
    "sg:phone":"+1 870 268 9300",
    "sg:postcode":"72401",
    "sg:province":"AR",
    "sg:tags":[
        "counseling"
    ],
    "wof:name":"Sandra Taylor Lcsw",
    "wof:placetype":"venue"
},
  "geometry": {"coordinates":[-90.709222,35.837099],"type":"Point"}
}