{
  "type": "Feature",
  "properties": {
    "addr:full":"351 Happy Trl Austin AR 72007",
    "addr:housenumber":"351",
    "addr:postcode":"72007",
    "addr:street":"Happy Trl",
    "iso:country":"US",
    "sg:address":"351 Happy Trl",
    "sg:city":"Austin",
    "sg:classifiers":[
        {
            "category":"Professional",
            "type":"Services"
        }
    ],
    "sg:phone":"+1 501 843 7216",
    "sg:postcode":"72007",
    "sg:province":"AR",
    "wof:name":"Dirk J Barriere",
    "wof:placetype":"venue"
},
  "geometry": {"coordinates":[-92.031527,35.063948],"type":"Point"}
}