{
  "type": "Feature",
  "properties": {
    "addr:full":"100 Terry Ln El Dorado AR 71730",
    "addr:housenumber":"100",
    "addr:postcode":"71730",
    "addr:street":"Terry Ln",
    "iso:country":"US",
    "sg:address":"100 Terry Ln",
    "sg:city":"El Dorado",
    "sg:classifiers":[
        {
            "category":"Real Estate",
            "subcategory":"Real Estate Operator",
            "type":"Services"
        }
    ],
    "sg:phone":"+1 870 862 1591",
    "sg:postcode":"71730",
    "sg:province":"AR",
    "sg:tags":[
        "mobile",
        "home",
        "community"
    ],
    "wof:name":"Cedar Park",
    "wof:placetype":"venue"
},
  "geometry": {"coordinates":[-92.55467,33.327765],"type":"Point"}
}