{
  "type": "Feature",
  "properties": {
    "iso:country":"US",
    "sg:address":"10215 Mabelvale Plaza Dr",
    "sg:city":"Little Rock",
    "sg:classifiers":[
        {
            "category":"Wholesale",
            "subcategory":"Machinery & Supplies",
            "type":"Manufacturing & Wholesale Goods"
        }
    ],
    "sg:phone":"+1 501 562 5974",
    "sg:postcode":"72209",
    "sg:province":"AR",
    "sg:tags":[
        "salon",
        "beauty"
    ],
    "wof:name":"Sally Beauty Supply",
    "wof:placetype":"venue"
},
  "geometry": {"coordinates":[-92.377959,34.677612],"type":"Point"}
}