{
  "type": "Feature",
  "properties": {
    "addr:full":"1997 S Brooklyn Rd Ratcliff AR 72951",
    "addr:housenumber":"1997",
    "addr:postcode":"72951",
    "addr:street":"S Brooklyn Rd",
    "iso:country":"US",
    "sg:address":"1997 S Brooklyn Rd",
    "sg:city":"Ratcliff",
    "sg:classifiers":[
        {
            "category":"Farming",
            "subcategory":"Dairy Farm",
            "type":"Manufacturing & Wholesale Goods"
        }
    ],
    "sg:phone":"+1 479 635 8131",
    "sg:postcode":"72951",
    "sg:province":"AR",
    "wof:name":"Hawkins Dairy",
    "wof:placetype":"venue"
},
  "geometry": {"coordinates":[-93.905874,35.287102],"type":"Point"}
}