{
  "type": "Feature",
  "properties": {
    "iso:country":"US",
    "sg:address":"502 S College Ave",
    "sg:city":"Fayetteville",
    "sg:classifiers":[
        {
            "category":"Organizations",
            "subcategory":"Membership Organization",
            "type":"Services"
        }
    ],
    "sg:phone":"+1 479 521 0809",
    "sg:postcode":"72701",
    "sg:province":"AR",
    "wof:name":"Ozark Poets Writers Collective",
    "wof:placetype":"venue"
},
  "geometry": {"coordinates":[-94.158051,36.05631],"type":"Point"}
}