{
  "type": "Feature",
  "properties": {
    "iso:country":"US",
    "sg:address":"2218 Lacari",
    "sg:city":"Magnolia",
    "sg:classifiers":[
        {
            "category":"Organizations",
            "subcategory":"Religious Organization",
            "type":"Services"
        }
    ],
    "sg:phone":"+1 870 234 3052",
    "sg:postcode":"71753",
    "sg:province":"AR",
    "sg:tags":[
        "place",
        "worship",
        "church"
    ],
    "wof:name":"Church of Christ Student Center",
    "wof:placetype":"venue"
},
  "geometry": {"coordinates":[-93.233639,33.288444],"type":"Point"}
}