{
  "type": "Feature",
  "properties": {
    "iso:country":"US",
    "sg:address":"26382 Hwy 67",
    "sg:city":"Malvern",
    "sg:classifiers":[
        {
            "category":"Wholesale",
            "subcategory":"Construction Materials",
            "type":"Manufacturing & Wholesale Goods"
        }
    ],
    "sg:phone":"+1 501 337 7172",
    "sg:postcode":"72104",
    "sg:province":"AR",
    "sg:tags":[
        "timberland",
        "company",
        "timber"
    ],
    "wof:name":"Auld Timber Inc",
    "wof:placetype":"venue"
},
  "geometry": {"coordinates":[-92.83100399999999,34.343809],"type":"Point"}
}