{
  "type": "Feature",
  "properties": {
    "iso:country":"US",
    "sg:address":"100 State Hwy 77",
    "sg:city":"Marion",
    "sg:classifiers":[
        {
            "category":"Autos & Motor Vehicles",
            "subcategory":"Automobile Sales",
            "type":"Retail Goods"
        }
    ],
    "sg:phone":"+1 870 739 4955",
    "sg:postcode":"72364",
    "sg:province":"AR",
    "sg:tags":[
        "used"
    ],
    "wof:name":"American Wholesale",
    "wof:placetype":"venue"
},
  "geometry": {"coordinates":[-90.18472800000001,35.169388],"type":"Point"}
}