{
  "type": "Feature",
  "properties": {
    "iso:country":"US",
    "sg:address":"7942 Calion Hwy",
    "sg:city":"El Dorado",
    "sg:classifiers":[
        {
            "category":"Professional",
            "subcategory":"Accounting & Tax Preparation",
            "type":"Services"
        }
    ],
    "sg:phone":"+1 870 748 2690",
    "sg:postcode":"71730",
    "sg:province":"AR",
    "sg:tags":[
        "return"
    ],
    "wof:name":"Rose Kennels",
    "wof:placetype":"venue"
},
  "geometry": {"coordinates":[-92.539719,33.337096],"type":"Point"}
}