{
  "type": "Feature",
  "properties": {
    "iso:country":"US",
    "sg:address":"720 E Wood St",
    "sg:city":"Ashdown",
    "sg:classifiers":[
        {
            "category":"Personal",
            "subcategory":"Beauty Salon",
            "type":"Services"
        }
    ],
    "sg:phone":"+1 870 898 3767",
    "sg:postcode":"71822",
    "sg:province":"AR",
    "wof:name":"Tangles Too Salon",
    "wof:placetype":"venue"
},
  "geometry": {"coordinates":[-94.121711,33.667318],"type":"Point"}
}