{
  "type": "Feature",
  "properties": {
    "iso:country":"US",
    "sg:address":"614 Broadway St",
    "sg:city":"Smackover",
    "sg:classifiers":[
        {
            "category":"Personal",
            "subcategory":"Beauty Salon",
            "type":"Services"
        }
    ],
    "sg:phone":"+1 870 725 2181",
    "sg:postcode":"71762",
    "sg:province":"AR",
    "wof:name":"Deborah's Mirror Image",
    "wof:placetype":"venue"
},
  "geometry": {"coordinates":[-92.722764,33.370298],"type":"Point"}
}