{
  "type": "Feature",
  "properties": {
    "iso:country":"US",
    "sg:address":"606 W Main St",
    "sg:city":"Cabot",
    "sg:classifiers":[
        {
            "category":"Banks & Credit Unions",
            "subcategory":"Bank",
            "type":"Services"
        }
    ],
    "sg:phone":"+1 501 743 3730",
    "sg:postcode":"72023",
    "sg:province":"AR",
    "wof:name":"Arvest Bank",
    "wof:placetype":"venue"
},
  "geometry": {"coordinates":[-92.025114,34.976133],"type":"Point"}
}