{
  "type": "Feature",
  "properties": {
    "addr:full":"320 S 12th St Paragould AR 72450",
    "addr:housenumber":"320",
    "addr:postcode":"72450",
    "addr:street":"S 12Th St",
    "iso:country":"US",
    "sg:address":"320 S 12th St",
    "sg:city":"Paragould",
    "sg:classifiers":[
        {
            "category":"Shopping",
            "subcategory":"Pharmacy",
            "type":"Retail Goods"
        }
    ],
    "sg:phone":"+1 870 236 8706",
    "sg:postcode":"72450",
    "sg:province":"AR",
    "wof:name":"Gibson Pharmacy",
    "wof:placetype":"venue"
},
  "geometry": {"coordinates":[-90.500873,36.053968],"type":"Point"}
}