{
  "type": "Feature",
  "properties": {
    "iso:country":"US",
    "sg:address":"104 E 3rd St",
    "sg:city":"Dierks",
    "sg:classifiers":[
        {
            "category":"Insurance",
            "subcategory":"Insurance Agent",
            "type":"Services"
        }
    ],
    "sg:phone":"+1 870 286 2777",
    "sg:postcode":"71833",
    "sg:province":"AR",
    "wof:name":"Archie Cothren Insurance",
    "wof:placetype":"venue"
},
  "geometry": {"coordinates":[-94.016882,34.119188],"type":"Point"}
}