{
  "type": "Feature",
  "properties": {
    "iso:country":"US",
    "sg:address":"1101 Blue Acres St",
    "sg:city":"White Hall",
    "sg:classifiers":[
        {
            "category":"Professional",
            "subcategory":"Detective & Security Services",
            "type":"Services"
        }
    ],
    "sg:phone":"+1 870 247 3833",
    "sg:postcode":"71602",
    "sg:province":"AR",
    "sg:tags":[
        "guard"
    ],
    "wof:name":"Brian R Hornsby",
    "wof:placetype":"venue"
},
  "geometry": {"coordinates":[-92.09445,34.290988],"type":"Point"}
}