{
  "type": "Feature",
  "properties": {
    "iso:country":"US",
    "sg:address":"3405 N 2nd St",
    "sg:city":"Rogers",
    "sg:classifiers":[
        {
            "category":"Building & Trades",
            "subcategory":"Plumbing",
            "type":"Services"
        }
    ],
    "sg:phone":"+1 479 246 0886",
    "sg:postcode":"72756",
    "sg:province":"AR",
    "sg:tags":[
        "heat",
        "air"
    ],
    "wof:name":"Moranco Renovations",
    "wof:placetype":"venue"
},
  "geometry": {"coordinates":[-94.115788,36.367624],"type":"Point"}
}