{
  "type": "Feature",
  "properties": {
    "addr:full":"147 Co Rd 207 Eureka Springs AR 72632",
    "addr:housenumber":"147",
    "addr:postcode":"72632",
    "addr:street":"Co Rd 207",
    "iso:country":"US",
    "sg:address":"147 Co Rd 207",
    "sg:city":"Eureka Springs",
    "sg:classifiers":[
        {
            "category":"Freight",
            "type":"Transportation"
        }
    ],
    "sg:phone":"+1 479 253 5159",
    "sg:postcode":"72632",
    "sg:province":"AR",
    "sg:tags":[
        "mover"
    ],
    "wof:name":"Roadrunner Moving",
    "wof:placetype":"venue"
},
  "geometry": {"coordinates":[-93.701126,36.416423],"type":"Point"}
}