{
  "type": "Feature",
  "properties": {
    "iso:country":"US",
    "sg:address":"1512 Schaal Rd",
    "sg:city":"Mineral Springs",
    "sg:classifiers":[
        {
            "category":"Home & Garden",
            "subcategory":"Garden Supply",
            "type":"Retail Goods"
        }
    ],
    "sg:phone":"+1 870 287 4434",
    "sg:postcode":"71851",
    "sg:province":"AR",
    "sg:tags":[
        "lawn",
        "mower"
    ],
    "wof:name":"J & L Lawn Mower Repair",
    "wof:placetype":"venue"
},
  "geometry": {"coordinates":[-93.953802,33.827831],"type":"Point"}
}