{
  "type": "Feature",
  "properties": {
    "iso:country":"US",
    "sg:address":"1714 SW Commerce Dr",
    "sg:city":"Bentonville",
    "sg:classifiers":[
        {
            "category":"Professional",
            "subcategory":"Management & Consulting",
            "type":"Services"
        }
    ],
    "sg:phone":"+1 479 271 7000",
    "sg:postcode":"72712",
    "sg:province":"AR",
    "sg:tags":[
        "marketing",
        "program"
    ],
    "wof:name":"One Source Industries LLC",
    "wof:placetype":"venue"
},
  "geometry": {"coordinates":[-94.213458,36.354405],"type":"Point"}
}