{
  "type": "Feature",
  "properties": {
    "addr:full":"2123 Labette Manor Dr Little Rock AR 72205",
    "addr:housenumber":"2123",
    "addr:postcode":"72205",
    "addr:street":"Labette Manor Dr",
    "iso:country":"US",
    "sg:address":"2123 Labette Manor Dr",
    "sg:city":"Little Rock",
    "sg:classifiers":[
        {
            "category":"Real Estate",
            "subcategory":"Real Estate Operator",
            "type":"Services"
        }
    ],
    "sg:phone":"+1 501 224 3122",
    "sg:postcode":"72205",
    "sg:province":"AR",
    "sg:tags":[
        "apartment"
    ],
    "wof:name":"Westbridge Apartments",
    "wof:placetype":"venue"
},
  "geometry": {"coordinates":[-92.376411,34.735893],"type":"Point"}
}