{
  "type": "Feature",
  "properties": {
    "iso:country":"US",
    "sg:address":"53 Judge Smith Dr",
    "sg:city":"Marion",
    "sg:classifiers":[
        {
            "category":"Retail",
            "subcategory":"Animal Services",
            "type":"Services"
        }
    ],
    "sg:phone":"+1 870 739 0733",
    "sg:postcode":"72364",
    "sg:province":"AR",
    "wof:name":"Darren Henry Kennels",
    "wof:placetype":"venue"
},
  "geometry": {"coordinates":[-90.193339,35.204961],"type":"Point"}
}