{
  "type": "Feature",
  "properties": {
    "iso:country":"US",
    "sg:address":"3206 S Thompson St",
    "sg:city":"Springdale",
    "sg:classifiers":[
        {
            "category":"Retail",
            "subcategory":"Repair Shop",
            "type":"Services"
        }
    ],
    "sg:phone":"+1 479 271 8107",
    "sg:postcode":"72764",
    "sg:province":"AR",
    "sg:tags":[
        "appliance"
    ],
    "wof:name":"Absolute Appliance Svc",
    "wof:placetype":"venue"
},
  "geometry": {"coordinates":[-94.143891,36.154835],"type":"Point"}
}