{
  "type": "Feature",
  "properties": {
    "iso:country":"US",
    "sg:address":"4000 Petro Rd",
    "sg:city":"West Memphis",
    "sg:classifiers":[
        {
            "category":"Freight",
            "type":"Transportation"
        }
    ],
    "sg:phone":"+1 870 732 2011",
    "sg:postcode":"72301",
    "sg:province":"AR",
    "sg:tags":[
        "operator",
        "broker",
        "trucking"
    ],
    "wof:name":"Tango Transport Inc",
    "wof:placetype":"venue"
},
  "geometry": {"coordinates":[-90.132416,35.153565],"type":"Point"}
}