{
  "type": "Feature",
  "properties": {
    "addr:full":"22771 Dam Site Rd Garfield AR 72732",
    "addr:housenumber":"22771",
    "addr:postcode":"72732",
    "addr:street":"Dam Site Rd",
    "iso:country":"US",
    "sg:address":"22771 Dam Site Rd",
    "sg:city":"Garfield",
    "sg:classifiers":[
        {
            "category":"Autos & Motor Vehicles",
            "subcategory":"Automobile Sales",
            "type":"Retail Goods"
        }
    ],
    "sg:phone":"+1 479 656 9666",
    "sg:postcode":"72732",
    "sg:province":"AR",
    "sg:tags":[
        "car",
        "dealer"
    ],
    "wof:name":"Auto Concepts Inc",
    "wof:placetype":"venue"
},
  "geometry": {"coordinates":[-93.87524999999999,36.437666],"type":"Point"}
}