{
  "type": "Feature",
  "properties": {
    "addr:full":"10 Town Sq Greenwood AR 72936",
    "addr:housenumber":"10",
    "addr:postcode":"72936",
    "addr:street":"Town Sq",
    "iso:country":"US",
    "sg:address":"10 Town Sq",
    "sg:city":"Greenwood",
    "sg:classifiers":[
        {
            "category":"Insurance",
            "subcategory":"Hazard Insurance",
            "type":"Services"
        }
    ],
    "sg:phone":"+1 479 996 4949",
    "sg:postcode":"72936",
    "sg:province":"AR",
    "sg:tags":[
        "commercial",
        "business"
    ],
    "wof:name":"Scatco",
    "wof:placetype":"venue"
},
  "geometry": {"coordinates":[-94.255734,35.212887],"type":"Point"}
}