{
  "type": "Feature",
  "properties": {
    "addr:full":"723 Quartz Dr Benton AR 72019",
    "addr:housenumber":"723",
    "addr:postcode":"72019",
    "addr:street":"Quartz Dr",
    "iso:country":"US",
    "sg:address":"723 Quartz Dr",
    "sg:city":"Benton",
    "sg:classifiers":[
        {
            "category":"Banks & Credit Unions",
            "subcategory":"Investment Brokerage",
            "type":"Services"
        },
        {
            "category":"Insurance",
            "subcategory":"Hazard Insurance",
            "type":"Services"
        }
    ],
    "sg:phone":"+1 501 316 1461",
    "sg:postcode":"72019",
    "sg:province":"AR",
    "sg:tags":[
        "agent",
        "resume"
    ],
    "wof:name":"Snider Agency The",
    "wof:placetype":"venue"
},
  "geometry": {"coordinates":[-92.57690100000001,34.640913],"type":"Point"}
}