{
  "type": "Feature",
  "properties": {
    "addr:full":"5 County Complex Cir Russellville AR 72802",
    "addr:housenumber":"5",
    "addr:postcode":"72802",
    "addr:street":"County Complex Cir",
    "iso:country":"US",
    "sg:address":"5 County Complex Cir",
    "sg:city":"Russellville",
    "sg:classifiers":[
        {
            "category":"Building & Trades",
            "subcategory":"Construction",
            "type":"Services"
        }
    ],
    "sg:phone":"+1 479 968 6400",
    "sg:postcode":"72802",
    "sg:province":"AR",
    "sg:tags":[
        "cont",
        "hanging"
    ],
    "wof:name":"Pope County Road Dept",
    "wof:placetype":"venue"
},
  "geometry": {"coordinates":[-93.10966999999999,35.280628],"type":"Point"}
}