{
  "type": "Feature",
  "properties": {
    "addr:full":"310 N Missouri Ave Corning AR 72422",
    "addr:housenumber":"310",
    "addr:postcode":"72422",
    "addr:street":"N Missouri Ave",
    "iso:country":"US",
    "sg:address":"310 N Missouri Ave",
    "sg:city":"Corning",
    "sg:classifiers":[
        {
            "category":"Home & Garden",
            "subcategory":"Building Materials",
            "type":"Retail Goods"
        },
        {
            "category":"Building & Trades",
            "subcategory":"Construction",
            "type":"Services"
        }
    ],
    "sg:phone":"+1 870 857 3841",
    "sg:postcode":"72422",
    "sg:province":"AR",
    "sg:tags":[
        "metal",
        "contractor"
    ],
    "wof:name":"Universal Builders Inc",
    "wof:placetype":"venue"
},
  "geometry": {"coordinates":[-90.586279,36.413531],"type":"Point"}
}