{
  "type": "Feature",
  "properties": {
    "iso:country":"US",
    "sg:address":"10301 Mayo Dr",
    "sg:city":"Barling",
    "sg:classifiers":[
        {
            "category":"Health Services",
            "subcategory":"Hospital",
            "type":"Services"
        },
        {
            "category":"Health Services",
            "subcategory":"Medical Lab",
            "type":"Services"
        }
    ],
    "sg:phone":"+1 479 494 5700",
    "sg:postcode":"72923",
    "sg:province":"AR",
    "wof:name":"Vista Health",
    "wof:placetype":"venue"
},
  "geometry": {"coordinates":[-94.318939,35.3409],"type":"Point"}
}