{
  "type": "Feature",
  "properties": {
    "addr:full":"4107 Baseline Rd Little Rock AR 72209",
    "addr:housenumber":"4107",
    "addr:postcode":"72209",
    "addr:street":"Baseline Rd",
    "iso:country":"US",
    "sg:address":"4107 Baseline Rd",
    "sg:city":"Little Rock",
    "sg:classifiers":[
        {
            "category":"Home & Garden",
            "subcategory":"Carpets & Floor Coverings",
            "type":"Retail Goods"
        }
    ],
    "sg:phone":"+1 501 562 6425",
    "sg:postcode":"72209",
    "sg:province":"AR",
    "wof:name":"Thomas Smith Floor Cover",
    "wof:placetype":"venue"
},
  "geometry": {"coordinates":[-92.32402,34.668109],"type":"Point"}
}