{
  "type": "Feature",
  "properties": {
    "addr:full":"201 Hwy 371 N Magnolia AR 71753",
    "addr:housenumber":"201",
    "addr:postcode":"71753",
    "addr:street":"Hwy 371 N Magnolia",
    "iso:country":"US",
    "sg:address":"201 Hwy 371 N",
    "sg:city":"Magnolia",
    "sg:classifiers":[
        {
            "category":"Health Services",
            "subcategory":"Hospital",
            "type":"Services"
        }
    ],
    "sg:phone":"+1 870 234 1597",
    "sg:postcode":"71753",
    "sg:province":"AR",
    "sg:tags":[
        "child",
        "specialty",
        "day",
        "care"
    ],
    "wof:name":"Kids First Magnolia",
    "wof:placetype":"venue"
},
  "geometry": {"coordinates":[-93.25346999999999,33.304099],"type":"Point"}
}