{
  "type": "Feature",
  "properties": {
    "iso:country":"US",
    "sg:address":"2420 Beauchamp Rd",
    "sg:city":"Little Rock",
    "sg:classifiers":[
        {
            "category":"Building & Trades",
            "subcategory":"Construction",
            "type":"Services"
        }
    ],
    "sg:phone":"+1 501 821 3090",
    "sg:postcode":"72210",
    "sg:province":"AR",
    "sg:tags":[
        "hanging",
        "contractor"
    ],
    "wof:name":"Perfect Match Painting Inc",
    "wof:placetype":"venue"
},
  "geometry": {"coordinates":[-92.50844499999999,34.735219],"type":"Point"}
}