{
  "type": "Feature",
  "properties": {
    "addr:full":"209 Golf Links Rd Hot Springs AR 71901",
    "addr:housenumber":"209",
    "addr:postcode":"71901",
    "addr:street":"Golf Links Rd",
    "iso:country":"US",
    "sg:address":"209 Golf Links Rd",
    "sg:city":"Hot Springs",
    "sg:classifiers":[
        {
            "category":"Home & Garden",
            "subcategory":"Carpets & Floor Coverings",
            "type":"Retail Goods"
        }
    ],
    "sg:phone":"+1 501 623 1535",
    "sg:postcode":"71901",
    "sg:province":"AR",
    "sg:tags":[
        "material"
    ],
    "wof:name":"Morrison Floor Covering",
    "wof:placetype":"venue"
},
  "geometry": {"coordinates":[-93.05504000000001,34.477805],"type":"Point"}
}