{
  "type": "Feature",
  "properties": {
    "iso:country":"US",
    "sg:address":"1029 Hwy 201 N",
    "sg:city":"Mountain Home",
    "sg:classifiers":[
        {
            "category":"Shopping",
            "type":"Retail Goods"
        }
    ],
    "sg:phone":"+1 870 424 3133",
    "sg:postcode":"72653",
    "sg:province":"AR",
    "sg:tags":[
        "awning",
        "canopy"
    ],
    "wof:name":"Advance Builders Of Mtn Home",
    "wof:placetype":"venue"
},
  "geometry": {"coordinates":[-92.38601800000001,36.352929],"type":"Point"}
}