{
  "type": "Feature",
  "properties": {
    "iso:country":"US",
    "sg:address":"924 Front St",
    "sg:city":"Conway",
    "sg:classifiers":[
        {
            "category":"Wholesale",
            "subcategory":"Medical Equipment & Supplies",
            "type":"Manufacturing & Wholesale Goods"
        },
        {
            "category":"Building & Trades",
            "subcategory":"Equipment Rental",
            "type":"Services"
        }
    ],
    "sg:phone":"+1 501 327 6476",
    "sg:postcode":"72032",
    "sg:province":"AR",
    "sg:tags":[
        "physician",
        "wheelchair",
        "ostomy",
        "surgeon",
        "retail",
        "hospital"
    ],
    "sg:website":"http://www.apexmedicalrentals.com",
    "wof:name":"Apex Medical Rental Inc.",
    "wof:placetype":"venue"
},
  "geometry": {"coordinates":[-92.440916,35.090875],"type":"Point"}
}