{
  "type": "Feature",
  "properties": {
    "iso:country":"US",
    "sg:address":"213 N Rosser St",
    "sg:city":"Forrest City",
    "sg:classifiers":[
        {
            "category":"Personal",
            "subcategory":"Beauty Salon",
            "type":"Services"
        }
    ],
    "sg:phone":"+1 870 494 3411",
    "sg:postcode":"72335",
    "sg:province":"AR",
    "sg:tags":[
        "shop"
    ],
    "wof:name":"Nicole Jones-Hutchieson",
    "wof:placetype":"venue"
},
  "geometry": {"coordinates":[-90.78711199999999,35.010545],"type":"Point"}
}