{
  "type": "Feature",
  "properties": {
    "iso:country":"US",
    "sg:address":"11678 W State Hwy 22",
    "sg:city":"Ratcliff",
    "sg:classifiers":[
        {
            "category":"Building & Trades",
            "subcategory":"Construction",
            "type":"Services"
        }
    ],
    "sg:phone":"+1 479 635 4891",
    "sg:postcode":"72951",
    "sg:province":"AR",
    "sg:tags":[
        "house"
    ],
    "wof:name":"Pendleton Construction Inc",
    "wof:placetype":"venue"
},
  "geometry": {"coordinates":[-93.915806,35.307188],"type":"Point"}
}