{
  "type": "Feature",
  "properties": {
    "addr:full":"2220 N Highway 229 Benton AR 72015",
    "addr:housenumber":"2220",
    "addr:postcode":"72015",
    "addr:street":"N Highway 229",
    "iso:country":"US",
    "sg:address":"2220 N Highway 229",
    "sg:city":"Benton",
    "sg:classifiers":[
        {
            "category":"Social Services",
            "subcategory":"Child Care",
            "type":"Services"
        },
        {
            "category":"Education",
            "subcategory":"Preschool",
            "type":"Public Place"
        }
    ],
    "sg:phone":"+1 501 776 3312",
    "sg:postcode":"72015",
    "sg:province":"AR",
    "sg:tags":[
        "kindergarten"
    ],
    "wof:name":"Rug Rats Preschool",
    "wof:placetype":"venue"
},
  "geometry": {"coordinates":[-92.644283,34.501369],"type":"Point"}
}