{
  "type": "Feature",
  "properties": {
    "addr:full":"1487 Forest Hills Blvd Bella Vista AR 72715",
    "addr:housenumber":"1487",
    "addr:postcode":"72715",
    "addr:street":"Forest Hills Blvd",
    "iso:country":"US",
    "sg:address":"1487 Forest Hills Blvd",
    "sg:city":"Bella Vista",
    "sg:classifiers":[
        {
            "category":"Professional",
            "subcategory":"Accounting & Tax Preparation",
            "type":"Services"
        }
    ],
    "sg:phone":"+1 479 855 6500",
    "sg:postcode":"72715",
    "sg:province":"AR",
    "wof:name":"Foster LLC PA",
    "wof:placetype":"venue"
},
  "geometry": {"coordinates":[-94.296505,36.468524],"type":"Point"}
}