{
  "type": "Feature",
  "properties": {
    "iso:country":"US",
    "sg:address":"530 Cash Rd NW",
    "sg:city":"Camden",
    "sg:classifiers":[
        {
            "category":"Organizations",
            "subcategory":"Religious Organization",
            "type":"Services"
        }
    ],
    "sg:phone":"+1 870 836 6275",
    "sg:postcode":"71701",
    "sg:province":"AR",
    "sg:tags":[
        "church"
    ],
    "wof:name":"Camden Second Baptist Church",
    "wof:placetype":"venue"
},
  "geometry": {"coordinates":[-92.851223,33.590401],"type":"Point"}
}