{
  "type": "Feature",
  "properties": {
    "iso:country":"US",
    "sg:address":"69 Old Highway 70 Loop",
    "sg:city":"Glenwood",
    "sg:classifiers":[
        {
            "category":"Manufacturing",
            "subcategory":"Buildings",
            "type":"Manufacturing & Wholesale Goods"
        },
        {
            "category":"Building & Trades",
            "subcategory":"Construction",
            "type":"Services"
        }
    ],
    "sg:phone":"+1 870 356 4547",
    "sg:postcode":"71943",
    "sg:province":"AR",
    "sg:tags":[
        "home",
        "builder",
        "contractor"
    ],
    "wof:name":"Ghg Construction Co Inc",
    "wof:placetype":"venue"
},
  "geometry": {"coordinates":[-93.499252,34.337551],"type":"Point"}
}