{
  "type": "Feature",
  "properties": {
    "addr:full":"7720 N Saint Louis St Cave City AR 72521",
    "addr:housenumber":"7720",
    "addr:postcode":"72521",
    "addr:street":"N Saint Louis St",
    "iso:country":"US",
    "sg:address":"7720 N Saint Louis St",
    "sg:city":"Cave City",
    "sg:classifiers":[
        {
            "category":"Food & Beverages",
            "subcategory":"Groceries & Convenience Stores",
            "type":"Retail Goods"
        }
    ],
    "sg:phone":"+1 870 283 6559",
    "sg:postcode":"72521",
    "sg:province":"AR",
    "wof:name":"Express Mart",
    "wof:placetype":"venue"
},
  "geometry": {"coordinates":[-91.54929799999999,35.931991],"type":"Point"}
}