{
  "type": "Feature",
  "properties": {
    "iso:country":"US",
    "sg:address":"208 W Emerson St",
    "sg:city":"Paragould",
    "sg:classifiers":[
        {
            "category":"Real Estate",
            "subcategory":"Real Estate Services",
            "type":"Services"
        },
        {
            "category":"Professional",
            "subcategory":"Research",
            "type":"Services"
        }
    ],
    "sg:phone":"+1 870 215 4017",
    "sg:postcode":"72450",
    "sg:province":"AR",
    "sg:tags":[
        "abstracter",
        "title"
    ],
    "wof:name":"Northeast Title Services, Inc.",
    "wof:placetype":"venue"
},
  "geometry": {"coordinates":[-90.487482,36.055569],"type":"Point"}
}