{
  "type": "Feature",
  "properties": {
    "addr:full":"3453 W State Hwy 18 Manila AR 72442",
    "addr:housenumber":"3453",
    "addr:postcode":"72442",
    "addr:street":"W State Hwy 18",
    "iso:country":"US",
    "sg:address":"3453 W State Hwy 18",
    "sg:city":"Manila",
    "sg:classifiers":[
        {
            "category":"Freight",
            "type":"Transportation"
        }
    ],
    "sg:phone":"+1 870 561 4577",
    "sg:postcode":"72442",
    "sg:province":"AR",
    "sg:tags":[
        "commercial",
        "storage"
    ],
    "wof:name":"Towell & Sons Mini Storage",
    "wof:placetype":"venue"
},
  "geometry": {"coordinates":[-90.183694,35.887219],"type":"Point"}
}