{
  "type": "Feature",
  "properties": {
    "iso:country":"US",
    "sg:address":"2581 State Hwy 185",
    "sg:city":"Marianna",
    "sg:classifiers":[
        {
            "category":"Restaurant",
            "type":"Food & Drink"
        }
    ],
    "sg:phone":"+1 870 295 4009",
    "sg:postcode":"72360",
    "sg:province":"AR",
    "sg:tags":[
        "eating"
    ],
    "wof:name":"Helena Fish Market",
    "wof:placetype":"venue"
},
  "geometry": {"coordinates":[-90.730622,34.73542],"type":"Point"}
}