{
  "type": "Feature",
  "properties": {
    "iso:country":"US",
    "sg:address":"5204 S Thompson St",
    "sg:city":"Springdale",
    "sg:classifiers":[
        {
            "category":"Personal",
            "type":"Services"
        },
        {
            "category":"Social Services",
            "type":"Services"
        }
    ],
    "sg:phone":"+1 479 751 4575",
    "sg:postcode":"72764",
    "sg:province":"AR",
    "sg:tags":[
        "credit",
        "consulting",
        "management",
        "debt",
        "counseling"
    ],
    "wof:name":"Consumer Credit Counseling Svc",
    "wof:placetype":"venue"
},
  "geometry": {"coordinates":[-94.14456199999999,36.137847],"type":"Point"}
}