{
  "type": "Feature",
  "properties": {
    "iso:country":"US",
    "sg:address":"276 Linden St",
    "sg:city":"Hot Springs",
    "sg:classifiers":[
        {
            "category":"Organizations",
            "subcategory":"Non-profit Organization",
            "type":"Services"
        }
    ],
    "sg:phone":"+1 501 624 6185",
    "sg:postcode":"71901",
    "sg:province":"AR",
    "sg:tags":[
        "information",
        "alcoholism",
        "treatment"
    ],
    "wof:name":"Quapaw House Inc",
    "wof:placetype":"venue"
},
  "geometry": {"coordinates":[-93.066222,34.51935],"type":"Point"}
}