{
  "type": "Feature",
  "properties": {
    "addr:full":"1757 Fairview Rd Searcy AR 72143",
    "addr:housenumber":"1757",
    "addr:postcode":"72143",
    "addr:street":"Fairview Rd",
    "iso:country":"US",
    "sg:address":"1757 Fairview Rd",
    "sg:city":"Searcy",
    "sg:classifiers":[
        {
            "category":"Retail",
            "subcategory":"Laundry & Dry Cleaning",
            "type":"Services"
        },
        {
            "category":"Building & Trades",
            "subcategory":"Cleaning & Sanitation",
            "type":"Services"
        }
    ],
    "sg:phone":"+1 501 728 4401",
    "sg:postcode":"72143",
    "sg:province":"AR",
    "sg:tags":[
        "cleaner",
        "tanks-treatment",
        "septic",
        "supply"
    ],
    "wof:name":"Rigsby Septic Tank Cleaning Service",
    "wof:placetype":"venue"
},
  "geometry": {"coordinates":[-91.736125,35.400064],"type":"Point"}
}