{
  "type": "Feature",
  "properties": {
    "iso:country":"US",
    "sg:address":"7628 Hardin Dr",
    "sg:city":"North Little Rock",
    "sg:classifiers":[
        {
            "category":"Wholesale",
            "subcategory":"Electrical",
            "type":"Manufacturing & Wholesale Goods"
        }
    ],
    "sg:phone":"+1 501 835 8070",
    "sg:postcode":"72117",
    "sg:province":"AR",
    "sg:tags":[
        "equipment"
    ],
    "wof:name":"Tri-Star Industrial Eqp Co",
    "wof:placetype":"venue"
},
  "geometry": {"coordinates":[-92.192294,34.823805],"type":"Point"}
}