{
  "type": "Feature",
  "properties": {
    "iso:country":"US",
    "sg:address":"13203 Macarthur Dr",
    "sg:city":"North Little Rock",
    "sg:classifiers":[
        {
            "category":"Autos & Motor Vehicles",
            "subcategory":"Automobile Sales",
            "type":"Retail Goods"
        }
    ],
    "sg:phone":"+1 501 851 7917",
    "sg:postcode":"72118",
    "sg:province":"AR",
    "sg:tags":[
        "body",
        "use",
        "used"
    ],
    "wof:name":"T S E Products Inc",
    "wof:placetype":"venue"
},
  "geometry": {"coordinates":[-92.344109,34.855972],"type":"Point"}
}