{
  "type": "Feature",
  "properties": {
    "iso:country":"US",
    "sg:address":"4040 N Frontage Rd",
    "sg:city":"Fayetteville",
    "sg:classifiers":[
        {
            "category":"Insurance",
            "subcategory":"Hazard Insurance",
            "type":"Services"
        },
        {
            "category":"Insurance",
            "subcategory":"Insurance Agent",
            "type":"Services"
        },
        {
            "category":"Insurance",
            "subcategory":"Life Insurance",
            "type":"Services"
        },
        {
            "category":"Insurance",
            "subcategory":"Title Insurance",
            "type":"Services"
        }
    ],
    "sg:phone":"+1 479 571 0911",
    "sg:postcode":"72703",
    "sg:province":"AR",
    "sg:tags":[
        "auto",
        "homeowner"
    ],
    "sg:website":"http://www.nationwide.com/agent/Fayetteville-ARKANSAS-insurance-agent/cherylgorton-long/office.html",
    "wof:name":"Cheryl Long Ins Inc - Nationwide Insurance",
    "wof:placetype":"venue"
},
  "geometry": {"coordinates":[-94.142766,36.125488],"type":"Point"}
}