{
  "type": "Feature",
  "properties": {
    "iso:country":"US",
    "sg:address":"210 W Main St",
    "sg:city":"Mountain View",
    "sg:classifiers":[
        {
            "category":"Organizations",
            "subcategory":"Membership Organization",
            "type":"Services"
        }
    ],
    "sg:phone":"+1 870 269 5200",
    "sg:postcode":"72560",
    "sg:province":"AR",
    "wof:name":"Humane Society Resale Shop",
    "wof:placetype":"venue"
},
  "geometry": {"coordinates":[-92.121281,35.868258],"type":"Point"}
}