{
  "type": "Feature",
  "properties": {
    "iso:country":"US",
    "sg:address":"210 Katye Ln",
    "sg:city":"Sherwood",
    "sg:classifiers":[
        {
            "category":"Structure",
            "subcategory":"Office Building",
            "type":"Public Place"
        }
    ],
    "sg:phone":"+1 501 833 3378",
    "sg:postcode":"72120",
    "sg:province":"AR",
    "sg:tags":[
        "park"
    ],
    "wof:name":"Moreno Properties",
    "wof:placetype":"venue"
},
  "geometry": {"coordinates":[-92.236691,34.836039],"type":"Point"}
}