{
  "type": "Feature",
  "properties": {
    "addr:full":"4301 W Markham St Little Rock AR 72205",
    "addr:housenumber":"4301",
    "addr:postcode":"72205",
    "addr:street":"W Markham St",
    "iso:country":"US",
    "sg:address":"4301 W Markham St",
    "sg:city":"Little Rock",
    "sg:classifiers":[
        {
            "category":"Health Services",
            "subcategory":"Doctor",
            "type":"Services"
        }
    ],
    "sg:phone":"+1 501 257 6064",
    "sg:postcode":"72205",
    "sg:province":"AR",
    "sg:tags":[
        "physician",
        "surgeon"
    ],
    "wof:name":"UAMS-Sleep Disorders Ctr",
    "wof:placetype":"venue"
},
  "geometry": {"coordinates":[-92.31868799999999,34.751395],"type":"Point"}
}