{
  "type": "Feature",
  "properties": {
    "iso:country":"US",
    "sg:address":"302 Davis Dr",
    "sg:city":"Hot Springs",
    "sg:classifiers":[
        {
            "category":"Building & Trades",
            "subcategory":"Construction",
            "type":"Services"
        }
    ],
    "sg:phone":"+1 501 624 1513",
    "sg:postcode":"71901",
    "sg:province":"AR",
    "sg:tags":[
        "resurfacing",
        "laying",
        "refinishing",
        "floor"
    ],
    "wof:name":"Robinson & Assoc Inc",
    "wof:placetype":"venue"
},
  "geometry": {"coordinates":[-93.008597,34.51409],"type":"Point"}
}