{
  "type": "Feature",
  "properties": {
    "iso:country":"US",
    "sg:address":"107 N Peabody Ave",
    "sg:city":"Mountain View",
    "sg:classifiers":[
        {
            "category":"Organizations",
            "subcategory":"Professional Association",
            "type":"Services"
        }
    ],
    "sg:phone":"+1 870 269 8098",
    "sg:postcode":"72560",
    "sg:province":"AR",
    "sg:tags":[
        "chambers",
        "commerce"
    ],
    "sg:website":"www.mountainviewcc.org",
    "wof:name":"Tourist Information Ctr",
    "wof:placetype":"venue"
},
  "geometry": {"coordinates":[-92.117684,35.869392],"type":"Point"}
}