{
  "type": "Feature",
  "properties": {
    "iso:country":"US",
    "sg:address":"400 W Washington St",
    "sg:city":"Hamburg",
    "sg:classifiers":[
        {
            "category":"Organizations",
            "subcategory":"Religious Organization",
            "type":"Services"
        }
    ],
    "sg:phone":"+1 870 853 2225",
    "sg:postcode":"71646",
    "sg:province":"AR",
    "sg:tags":[
        "church"
    ],
    "wof:name":"Calvary Baptist Church",
    "wof:placetype":"venue"
},
  "geometry": {"coordinates":[-91.80371100000001,33.228042],"type":"Point"}
}