{
  "type": "Feature",
  "properties": {
    "iso:country":"US",
    "sg:address":"107 Mills Park Rd",
    "sg:city":"Bryant",
    "sg:classifiers":[
        {
            "category":"Education",
            "subcategory":"Library",
            "type":"Public Place"
        }
    ],
    "sg:phone":"+1 501 847 2166",
    "sg:postcode":"72022",
    "sg:province":"AR",
    "sg:tags":[
        "executive"
    ],
    "wof:name":"Bryant Branch Library",
    "wof:placetype":"venue"
},
  "geometry": {"coordinates":[-92.489023,34.597952],"type":"Point"}
}