{
  "type": "Feature",
  "properties": {
    "addr:full":"2001 Steeple Chase Dr Jacksonville AR 72076",
    "addr:housenumber":"2001",
    "addr:postcode":"72076",
    "addr:street":"Steeple Chase Dr",
    "iso:country":"US",
    "sg:address":"2001 Steeple Chase Dr",
    "sg:city":"Jacksonville",
    "sg:classifiers":[
        {
            "category":"Farming",
            "subcategory":"Farm",
            "type":"Manufacturing & Wholesale Goods"
        }
    ],
    "sg:phone":"+1 501 843 8153",
    "sg:postcode":"72076",
    "sg:province":"AR",
    "wof:name":"Bob Stender State Farm",
    "wof:placetype":"venue"
},
  "geometry": {"coordinates":[-92.088814,34.885891],"type":"Point"}
}