{
  "type": "Feature",
  "properties": {
    "addr:full":"3442 Airport Rd Pearcy AR 71964",
    "addr:housenumber":"3442",
    "addr:postcode":"71964",
    "addr:street":"Airport Rd",
    "iso:country":"US",
    "sg:address":"3442 Airport Rd",
    "sg:city":"Pearcy",
    "sg:classifiers":[
        {
            "category":"Professional",
            "subcategory":"Business Services",
            "type":"Services"
        }
    ],
    "sg:phone":"+1 501 760 5555",
    "sg:postcode":"71964",
    "sg:province":"AR",
    "wof:name":"Design Drama",
    "wof:placetype":"venue"
},
  "geometry": {"coordinates":[-93.20931400000001,34.443449],"type":"Point"}
}