{
  "type": "Feature",
  "properties": {
    "iso:country":"US",
    "sg:address":"499 US Hwy 59",
    "sg:city":"Kansas",
    "sg:classifiers":[
        {
            "category":"Autos & Motor Vehicles",
            "subcategory":"Auto Supplies",
            "type":"Retail Goods"
        }
    ],
    "sg:phone":"+1 918 868 2871",
    "sg:postcode":"74344",
    "sg:province":"OK",
    "sg:tags":[
        "automobile",
        "parts"
    ],
    "wof:name":"Kansas Auto Parts",
    "wof:placetype":"venue"
},
  "geometry": {"coordinates":[-94.769275,36.591381],"type":"Point"}
}