{
  "type": "Feature",
  "properties": {
    "addr:full":"208 Vine St Van Buren AR 72956",
    "addr:housenumber":"208",
    "addr:postcode":"72956",
    "addr:street":"Vine St",
    "iso:country":"US",
    "sg:address":"208 Vine St",
    "sg:city":"Van Buren",
    "sg:classifiers":[
        {
            "category":"Building & Trades",
            "subcategory":"Construction",
            "type":"Services"
        }
    ],
    "sg:phone":"+1 479 471 0619",
    "sg:postcode":"72956",
    "sg:province":"AR",
    "sg:tags":[
        "general",
        "contractor"
    ],
    "wof:name":"Butch Basham Construction",
    "wof:placetype":"venue"
},
  "geometry": {"coordinates":[-94.35229099999999,35.430651],"type":"Point"}
}