{
  "type": "Feature",
  "properties": {
    "iso:country":"US",
    "sg:address":"666 E Orr St",
    "sg:city":"Piggott",
    "sg:classifiers":[
        {
            "category":"Real Estate",
            "subcategory":"Real Estate Operator",
            "type":"Services"
        }
    ],
    "sg:phone":"+1 870 598 5524",
    "sg:postcode":"72454",
    "sg:province":"AR",
    "sg:tags":[
        "apartment"
    ],
    "wof:name":"Ouggitt Family Apt",
    "wof:placetype":"venue"
},
  "geometry": {"coordinates":[-90.18309,36.384557],"type":"Point"}
}