{
  "type": "Feature",
  "properties": {
    "addr:full":"3407 E Broad St Texarkana AR 71854",
    "addr:housenumber":"3407",
    "addr:postcode":"71854",
    "addr:street":"E Broad St",
    "iso:country":"US",
    "sg:address":"3407 E Broad St",
    "sg:city":"Texarkana",
    "sg:classifiers":[
        {
            "category":"Organizations",
            "subcategory":"Community Association",
            "type":"Services"
        }
    ],
    "sg:phone":"+1 870 774 9991",
    "sg:postcode":"71854",
    "sg:province":"AR",
    "sg:tags":[
        "fraternal"
    ],
    "sg:website":"www.foe.com",
    "wof:name":"Fraternal Order Of Eagles",
    "wof:placetype":"venue"
},
  "geometry": {"coordinates":[-94.006503,33.450801],"type":"Point"}
}