{
  "type": "Feature",
  "properties": {
    "iso:country":"US",
    "sg:address":"1328 US Hwy 65",
    "sg:city":"Eudora",
    "sg:classifiers":[
        {
            "category":"Farming",
            "subcategory":"Aquatic Farm",
            "type":"Manufacturing & Wholesale Goods"
        }
    ],
    "sg:phone":"+1 870 355 4802",
    "sg:postcode":"71640",
    "sg:province":"AR",
    "sg:tags":[
        "gasoline",
        "station",
        "eating"
    ],
    "wof:name":"Holly Ridge Western Store",
    "wof:placetype":"venue"
},
  "geometry": {"coordinates":[-91.260365,33.19565],"type":"Point"}
}