{
  "type": "Feature",
  "properties": {
    "iso:country":"US",
    "sg:address":"232 N Whitehead Dr",
    "sg:city":"De Witt",
    "sg:classifiers":[
        {
            "category":"Retail",
            "subcategory":"Auto Repair",
            "type":"Services"
        }
    ],
    "sg:phone":"+1 870 946 4663",
    "sg:postcode":"72042",
    "sg:province":"AR",
    "sg:tags":[
        "truck"
    ],
    "wof:name":"D & J Transmission & Rear End",
    "wof:placetype":"venue"
},
  "geometry": {"coordinates":[-91.32405900000001,34.295625],"type":"Point"}
}