{
  "type": "Feature",
  "properties": {
    "iso:country":"US",
    "sg:address":"2300 Rusher Ln",
    "sg:city":"Jonesboro",
    "sg:classifiers":[
        {
            "category":"Shopping",
            "subcategory":"Clothing, Apparel, & Fashions",
            "type":"Retail Goods"
        }
    ],
    "sg:phone":"+1 870 931 3609",
    "sg:postcode":"72404",
    "sg:province":"AR",
    "wof:name":"Raingames USA LLC",
    "wof:placetype":"venue"
},
  "geometry": {"coordinates":[-90.74086,35.813519],"type":"Point"}
}