{
  "type": "Feature",
  "properties": {
    "addr:full":"1116 Jameson St Benton AR 72015",
    "addr:housenumber":"1116",
    "addr:postcode":"72015",
    "addr:street":"Jameson St",
    "iso:country":"US",
    "sg:address":"1116 Jameson St",
    "sg:city":"Benton",
    "sg:classifiers":[
        {
            "category":"Freight",
            "type":"Transportation"
        }
    ],
    "sg:phone":"+1 501 315 4184",
    "sg:postcode":"72015",
    "sg:province":"AR",
    "sg:tags":[
        "leasing",
        "truck",
        "hauling",
        "local"
    ],
    "wof:name":"Nutt Trucking Co Inc",
    "wof:placetype":"venue"
},
  "geometry": {"coordinates":[-92.575532,34.576206],"type":"Point"}
}