{
  "type": "Feature",
  "properties": {
    "iso:country":"US",
    "sg:address":"149 Crestview Rd",
    "sg:city":"Conway",
    "sg:classifiers":[
        {
            "category":"Organizations",
            "subcategory":"Community Association",
            "type":"Services"
        }
    ],
    "sg:phone":"+1 501 470 9394",
    "sg:postcode":"72034",
    "sg:province":"AR",
    "sg:tags":[
        "club"
    ],
    "wof:name":"Crestview Country Club",
    "wof:placetype":"venue"
},
  "geometry": {"coordinates":[-92.435812,35.005828],"type":"Point"}
}