{
  "type": "Feature",
  "properties": {
    "addr:full":"825 N Hwy 62 65 Harrison AR 72601",
    "addr:housenumber":"825;65",
    "addr:postcode":"72601",
    "addr:street":"N Hwy 62;Harrison",
    "iso:country":"US",
    "sg:address":"825 N Hwy 62 65",
    "sg:city":"Harrison",
    "sg:classifiers":[
        {
            "category":"Food & Beverages",
            "subcategory":"Groceries & Convenience Stores",
            "type":"Retail Goods"
        }
    ],
    "sg:phone":"+1 870 741 6611",
    "sg:postcode":"72601",
    "sg:province":"AR",
    "wof:name":"Short Stop",
    "wof:placetype":"venue"
},
  "geometry": {"coordinates":[-93.120036,36.252264],"type":"Point"}
}