{
  "type": "Feature",
  "properties": {
    "addr:full":"23 Lefever Ln Little Rock AR 72227",
    "addr:housenumber":"23",
    "addr:postcode":"72227",
    "addr:street":"Lefever Ln",
    "iso:country":"US",
    "sg:address":"23 Lefever Ln",
    "sg:city":"Little Rock",
    "sg:classifiers":[
        {
            "category":"Recreation",
            "type":"Entertainment"
        }
    ],
    "sg:phone":"+1 501 219 7179",
    "sg:postcode":"72227",
    "sg:province":"AR",
    "sg:tags":[
        "instruction",
        "swimming"
    ],
    "wof:name":"Arkansas Dolphins Swim Team",
    "wof:placetype":"venue"
},
  "geometry": {"coordinates":[-92.35920299999999,34.77619],"type":"Point"}
}