{
  "type": "Feature",
  "properties": {
    "iso:country":"US",
    "sg:address":"1108 N Harrel St",
    "sg:city":"Wynne",
    "sg:classifiers":[
        {
            "category":"Professional",
            "subcategory":"Lawyer & Legal Services",
            "type":"Services"
        }
    ],
    "sg:phone":"+1 870 208 8480",
    "sg:postcode":"72396",
    "sg:province":"AR",
    "sg:tags":[
        "attorney"
    ],
    "wof:name":"John N Killough",
    "wof:placetype":"venue"
},
  "geometry": {"coordinates":[-90.786733,35.23215],"type":"Point"}
}