{
  "type": "Feature",
  "properties": {
    "iso:country":"US",
    "sg:address":"4305 State Hwy 163",
    "sg:city":"Jonesboro",
    "sg:classifiers":[
        {
            "category":"Retail",
            "subcategory":"Auto Repair",
            "type":"Services"
        }
    ],
    "sg:phone":"+1 870 972 1754",
    "sg:postcode":"72404",
    "sg:province":"AR",
    "sg:tags":[
        "automotive",
        "used",
        "automobile"
    ],
    "wof:name":"Southside Auto Sales",
    "wof:placetype":"venue"
},
  "geometry": {"coordinates":[-90.661445,35.719348],"type":"Point"}
}