{
  "type": "Feature",
  "properties": {
    "iso:country":"US",
    "sg:address":"85 Batesville Blvd",
    "sg:city":"Batesville",
    "sg:classifiers":[
        {
            "category":"Insurance",
            "subcategory":"Hazard Insurance",
            "type":"Services"
        }
    ],
    "sg:phone":"+1 870 793 5485",
    "sg:postcode":"72501",
    "sg:province":"AR",
    "sg:tags":[
        "commercial",
        "business"
    ],
    "wof:name":"Vurl Shreve Insurance",
    "wof:placetype":"venue"
},
  "geometry": {"coordinates":[-91.64126899999999,35.757979],"type":"Point"}
}