{
  "type": "Feature",
  "properties": {
    "iso:country":"US",
    "sg:address":"1088 Raney Rd",
    "sg:city":"Benton",
    "sg:classifiers":[
        {
            "category":"Building & Trades",
            "subcategory":"Plumbing",
            "type":"Services"
        }
    ],
    "sg:phone":"+1 501 316 6466",
    "sg:postcode":"72019",
    "sg:province":"AR",
    "sg:tags":[
        "septic"
    ],
    "wof:name":"A C Hanes Sanitary Svc",
    "wof:placetype":"venue"
},
  "geometry": {"coordinates":[-92.580288,34.644203],"type":"Point"}
}