{
  "type": "Feature",
  "properties": {
    "iso:country":"US",
    "sg:address":"173 Marion Anderson Rd",
    "sg:city":"Hot Springs",
    "sg:classifiers":[
        {
            "category":"Insurance",
            "subcategory":"Insurance Agent",
            "type":"Services"
        }
    ],
    "sg:phone":"+1 501 760 2595",
    "sg:postcode":"71913",
    "sg:province":"AR",
    "sg:website":"www.affordablehealthcaresolutions.us",
    "wof:name":"Financial Security Corp",
    "wof:placetype":"venue"
},
  "geometry": {"coordinates":[-93.143511,34.462378],"type":"Point"}
}