{
  "type": "Feature",
  "properties": {
    "iso:country":"US",
    "sg:address":"15701 State Hwy 107",
    "sg:city":"Jacksonville",
    "sg:classifiers":[
        {
            "category":"Wholesale",
            "subcategory":"Construction Materials",
            "type":"Manufacturing & Wholesale Goods"
        }
    ],
    "sg:phone":"+1 501 835 7992",
    "sg:postcode":"72076",
    "sg:province":"AR",
    "sg:tags":[
        "marble"
    ],
    "wof:name":"Sherwood Marble Co",
    "wof:placetype":"venue"
},
  "geometry": {"coordinates":[-92.192915,34.879186],"type":"Point"}
}