{
  "type": "Feature",
  "properties": {
    "iso:country":"US",
    "sg:address":"207 N Frederick St",
    "sg:city":"Magnolia",
    "sg:classifiers":[
        {
            "category":"Banks & Credit Unions",
            "subcategory":"Bank",
            "type":"Services"
        }
    ],
    "sg:phone":"+1 870 901 6335",
    "sg:postcode":"71753",
    "sg:province":"AR",
    "sg:tags":[
        "depository",
        "banking"
    ],
    "wof:name":"First American Cash Advance",
    "wof:placetype":"venue"
},
  "geometry": {"coordinates":[-93.224413,33.268523],"type":"Point"}
}