{
  "type": "Feature",
  "properties": {
    "addr:full":"1410 Prince St Conway AR 72034",
    "addr:housenumber":"1410",
    "addr:postcode":"72034",
    "addr:street":"Prince St",
    "iso:country":"US",
    "sg:address":"1410 Prince St",
    "sg:city":"Conway",
    "sg:classifiers":[
        {
            "category":"Health Services",
            "subcategory":"Doctor",
            "type":"Services"
        }
    ],
    "sg:phone":"+1 501 327 0243",
    "sg:postcode":"72034",
    "sg:province":"AR",
    "sg:tags":[
        "dentist"
    ],
    "wof:name":"Robert J Parker DDS",
    "wof:placetype":"venue"
},
  "geometry": {"coordinates":[-92.443522,35.091852],"type":"Point"}
}