{
  "type": "Feature",
  "properties": {
    "iso:country":"US",
    "sg:address":"1001 Rushing Cir",
    "sg:city":"Little Rock",
    "sg:classifiers":[
        {
            "category":"Wholesale",
            "subcategory":"Durable Goods & Equipment",
            "type":"Manufacturing & Wholesale Goods"
        }
    ],
    "sg:phone":"+1 501 661 1943",
    "sg:postcode":"72204",
    "sg:province":"AR",
    "sg:tags":[
        "representative",
        "manufacturer"
    ],
    "wof:name":"Johnston Sales Co",
    "wof:placetype":"venue"
},
  "geometry": {"coordinates":[-92.357139,34.742817],"type":"Point"}
}