{
  "type": "Feature",
  "properties": {
    "iso:country":"US",
    "sg:address":"3610 Woodsprings Rd",
    "sg:city":"Jonesboro",
    "sg:classifiers":[
        {
            "category":"Manufacturing",
            "subcategory":"Textiles",
            "type":"Manufacturing & Wholesale Goods"
        }
    ],
    "sg:phone":"+1 870 593 2266",
    "sg:postcode":"72404",
    "sg:province":"AR",
    "sg:tags":[
        "broker",
        "cotton"
    ],
    "wof:name":"Marty White",
    "wof:placetype":"venue"
},
  "geometry": {"coordinates":[-90.763605,35.803692],"type":"Point"}
}