{
  "type": "Feature",
  "properties": {
    "iso:country":"US",
    "sg:address":"3705 Wheeler Ave",
    "sg:city":"Fort Smith",
    "sg:classifiers":[
        {
            "category":"Manufacturing",
            "subcategory":"Metals",
            "type":"Manufacturing & Wholesale Goods"
        },
        {
            "category":"Wholesale",
            "subcategory":"Metals & Minerals",
            "type":"Manufacturing & Wholesale Goods"
        }
    ],
    "sg:phone":"+1 479 649 8388",
    "sg:postcode":"72901",
    "sg:province":"AR",
    "sg:tags":[
        "center",
        "sling"
    ],
    "wof:name":"Industrial Splicing & Sling",
    "wof:placetype":"venue"
},
  "geometry": {"coordinates":[-94.426854,35.34714],"type":"Point"}
}