{
  "type": "Feature",
  "properties": {
    "iso:country":"US",
    "sg:address":"1312 E Main St",
    "sg:city":"Magnolia",
    "sg:classifiers":[
        {
            "category":"Real Estate",
            "subcategory":"Real Estate Agent",
            "type":"Services"
        }
    ],
    "sg:phone":"+1 870 234 7722",
    "sg:postcode":"71753",
    "sg:province":"AR",
    "sg:website":"www.carringtonrealty.com",
    "wof:name":"Carrington Realty",
    "wof:placetype":"venue"
},
  "geometry": {"coordinates":[-93.224236,33.266831],"type":"Point"}
}