{
  "type": "Feature",
  "properties": {
    "iso:country":"US",
    "sg:address":"7504 Dayton Rd",
    "sg:city":"Mansfield",
    "sg:classifiers":[
        {
            "category":"Professional",
            "subcategory":"Accounting & Tax Preparation",
            "type":"Services"
        }
    ],
    "sg:phone":"+1 479 928 7062",
    "sg:postcode":"72944",
    "sg:province":"AR",
    "wof:name":"Ken Boyd CPA",
    "wof:placetype":"venue"
},
  "geometry": {"coordinates":[-94.219383,35.107251],"type":"Point"}
}