{
  "type": "Feature",
  "properties": {
    "iso:country":"US",
    "sg:address":"411 Church St",
    "sg:city":"Hardy",
    "sg:classifiers":[
        {
            "category":"Organizations",
            "subcategory":"Religious Organization",
            "type":"Services"
        }
    ],
    "sg:phone":"+1 870 856 3767",
    "sg:postcode":"72542",
    "sg:province":"AR",
    "sg:tags":[
        "church"
    ],
    "wof:name":"First Baptist Church",
    "wof:placetype":"venue"
},
  "geometry": {"coordinates":[-91.486296,36.318681],"type":"Point"}
}