{
  "type": "Feature",
  "properties": {
    "iso:country":"US",
    "sg:address":"1400 Main St",
    "sg:city":"Little Rock",
    "sg:classifiers":[
        {
            "category":"Home & Garden",
            "subcategory":"Hardware",
            "type":"Retail Goods"
        }
    ],
    "sg:phone":"+1 501 374 1911",
    "sg:postcode":"72202",
    "sg:province":"AR",
    "sg:tags":[
        "tool",
        "used"
    ],
    "wof:name":"C & W Tool Repair",
    "wof:placetype":"venue"
},
  "geometry": {"coordinates":[-92.27301799999999,34.73437],"type":"Point"}
}