{
  "type": "Feature",
  "properties": {
    "addr:full":"7723 Asher Ave Little Rock AR 72204",
    "addr:housenumber":"7723",
    "addr:postcode":"72204",
    "addr:street":"Asher Ave",
    "iso:country":"US",
    "sg:address":"7723 Asher Ave",
    "sg:city":"Little Rock",
    "sg:classifiers":[
        {
            "category":"Government",
            "subcategory":"Police Station",
            "type":"Public Place"
        }
    ],
    "sg:phone":"+1 501 570 8000",
    "sg:postcode":"72204",
    "sg:province":"AR",
    "sg:tags":[
        "state"
    ],
    "sg:website":"www.cji.edu",
    "wof:name":"Criminal Justice Institute",
    "wof:placetype":"venue"
},
  "geometry": {"coordinates":[-92.36027900000001,34.714554],"type":"Point"}
}