{
  "type": "Feature",
  "properties": {
    "iso:country":"US",
    "sg:address":"17784 Marshall St",
    "sg:city":"Garfield",
    "sg:classifiers":[
        {
            "category":"Place Of Worship",
            "subcategory":"Church",
            "type":"Public Place"
        },
        {
            "category":"Place Of Worship",
            "type":"Public Place"
        },
        {
            "category":"Organizations",
            "subcategory":"Religious Organization",
            "type":"Services"
        }
    ],
    "sg:phone":"+1 479 359 3496",
    "sg:postcode":"72732",
    "sg:province":"AR",
    "sg:tags":[
        "churches-baptist-general",
        "churches-baptist"
    ],
    "sg:website":"http://www.abc-usa.org",
    "wof:name":"First Baptist Church",
    "wof:placetype":"venue"
},
  "geometry": {"coordinates":[-93.98661199999999,36.443939],"type":"Point"}
}