{
  "type": "Feature",
  "properties": {
    "iso:country":"US",
    "sg:address":"516 S Woods St",
    "sg:city":"West Memphis",
    "sg:classifiers":[
        {
            "category":"Building & Trades",
            "subcategory":"Construction",
            "type":"Services"
        }
    ],
    "sg:phone":"+1 870 735 6800",
    "sg:postcode":"72301",
    "sg:province":"AR",
    "sg:tags":[
        "concrete",
        "contractor"
    ],
    "wof:name":"Razorback Construction",
    "wof:placetype":"venue"
},
  "geometry": {"coordinates":[-90.18493700000001,35.139475],"type":"Point"}
}