{
  "type": "Feature",
  "properties": {
    "iso:country":"US",
    "sg:address":"204 E South St",
    "sg:city":"Harrisburg",
    "sg:classifiers":[
        {
            "category":"Freight",
            "type":"Transportation"
        }
    ],
    "sg:phone":"+1 870 578 9634",
    "sg:postcode":"72432",
    "sg:province":"AR",
    "sg:tags":[
        "operator",
        "local",
        "trucking"
    ],
    "wof:name":"Alan D Eberhard",
    "wof:placetype":"venue"
},
  "geometry": {"coordinates":[-90.720422,35.563267],"type":"Point"}
}