{
  "type": "Feature",
  "properties": {
    "addr:full":"404 W 1st St S Prescott AR 71835",
    "addr:housenumber":"404",
    "addr:postcode":"71835",
    "addr:street":"W 1St St S",
    "iso:country":"US",
    "sg:address":"404 W 1st St S",
    "sg:city":"Prescott",
    "sg:classifiers":[
        {
            "category":"Retail",
            "subcategory":"Repair Shop",
            "type":"Services"
        }
    ],
    "sg:phone":"+1 870 703 7761",
    "sg:postcode":"71835",
    "sg:province":"AR",
    "sg:tags":[
        "water",
        "pressure",
        "cleaning"
    ],
    "wof:name":"Kay & Kay",
    "wof:placetype":"venue"
},
  "geometry": {"coordinates":[-93.383622,33.800434],"type":"Point"}
}