{
  "type": "Feature",
  "properties": {
    "iso:country":"US",
    "sg:address":"110 Hwy 71 S",
    "sg:city":"Ashdown",
    "sg:classifiers":[
        {
            "category":"Retail",
            "subcategory":"Repair Shop",
            "type":"Services"
        }
    ],
    "sg:phone":"+1 870 898 9120",
    "sg:postcode":"71822",
    "sg:province":"AR",
    "sg:tags":[
        "welding"
    ],
    "wof:name":"OMS Shop",
    "wof:placetype":"venue"
},
  "geometry": {"coordinates":[-94.110387,33.652746],"type":"Point"}
}