{
  "type": "Feature",
  "properties": {
    "iso:country":"US",
    "sg:address":"5104 N State Line Ave",
    "sg:city":"Texarkana",
    "sg:classifiers":[
        {
            "category":"Restaurant",
            "type":"Food & Drink"
        }
    ],
    "sg:menulink":"http://www.allmenus.com/ar/garland/11664-dennys/menu/",
    "sg:phone":"+1 870 774 5438",
    "sg:postcode":"71854",
    "sg:province":"AR",
    "sg:tags":[
        "american",
        "diner"
    ],
    "wof:name":"Denny's",
    "wof:placetype":"venue"
},
  "geometry": {"coordinates":[-94.043075,33.472806],"type":"Point"}
}