{
  "type": "Feature",
  "properties": {
    "iso:country":"US",
    "sg:address":"201 S Main St",
    "sg:city":"Hope",
    "sg:classifiers":[
        {
            "category":"Shopping",
            "subcategory":"Used Merchandise",
            "type":"Retail Goods"
        }
    ],
    "sg:phone":"+1 870 777 2999",
    "sg:postcode":"71801",
    "sg:province":"AR",
    "sg:tags":[
        "antique"
    ],
    "wof:name":"Antique Corner Etc",
    "wof:placetype":"venue"
},
  "geometry": {"coordinates":[-93.591882,33.667922],"type":"Point"}
}