{
  "type": "Feature",
  "properties": {
    "iso:country":"US",
    "sg:address":"2031 Hwy 62-412",
    "sg:city":"Highland",
    "sg:classifiers":[
        {
            "category":"Autos & Motor Vehicles",
            "subcategory":"Automobile Sales",
            "type":"Retail Goods"
        }
    ],
    "sg:phone":"+1 870 856 2105",
    "sg:postcode":"72542",
    "sg:province":"AR",
    "sg:tags":[
        "car",
        "dealer"
    ],
    "wof:name":"Pap Beardsley Chevrolet Buick",
    "wof:placetype":"venue"
},
  "geometry": {"coordinates":[-91.525578,36.262215],"type":"Point"}
}