{
  "type": "Feature",
  "properties": {
    "addr:full":"334 E Gaines Ave Monticello AR 71655",
    "addr:housenumber":"334",
    "addr:postcode":"71655",
    "addr:street":"E Gaines Ave",
    "iso:country":"US",
    "sg:address":"334 E Gaines Ave",
    "sg:city":"Monticello",
    "sg:classifiers":[
        {
            "category":"Shopping",
            "subcategory":"Used Merchandise",
            "type":"Retail Goods"
        }
    ],
    "sg:phone":"+1 870 460 0370",
    "sg:postcode":"71655",
    "sg:province":"AR",
    "sg:tags":[
        "flea",
        "market"
    ],
    "wof:name":"Corner Flea Market",
    "wof:placetype":"venue"
},
  "geometry": {"coordinates":[-91.78841,33.628748],"type":"Point"}
}