{
  "type": "Feature",
  "properties": {
    "addr:full":"2020 State Hwy 229 Benton AR 72015",
    "addr:housenumber":"2020",
    "addr:postcode":"72015",
    "addr:street":"State Hwy 229",
    "iso:country":"US",
    "sg:address":"2020 State Hwy 229",
    "sg:city":"Benton",
    "sg:classifiers":[
        {
            "category":"Shopping",
            "subcategory":"Discount & Variety Stores",
            "type":"Retail Goods"
        },
        {
            "category":"Restaurant",
            "type":"Food & Drink"
        }
    ],
    "sg:phone":"+1 501 778 6388",
    "sg:postcode":"72015",
    "sg:province":"AR",
    "sg:tags":[
        "country",
        "general",
        "pizza"
    ],
    "wof:name":"Arey's General Store",
    "wof:placetype":"venue"
},
  "geometry": {"coordinates":[-92.64339,34.51413],"type":"Point"}
}