{
  "type": "Feature",
  "properties": {
    "iso:country":"US",
    "sg:address":"104 Main St",
    "sg:city":"Wickes",
    "sg:classifiers":[
        {
            "category":"Shopping",
            "subcategory":"Hobbies, Toys, & Games",
            "type":"Retail Goods"
        }
    ],
    "sg:phone":"+1 870 385 7333",
    "sg:postcode":"71973",
    "sg:province":"AR",
    "sg:tags":[
        "equipment",
        "ceramic",
        "supply"
    ],
    "wof:name":"Wilcher's Ceramics",
    "wof:placetype":"venue"
},
  "geometry": {"coordinates":[-94.33693,34.301898],"type":"Point"}
}