{
  "type": "Feature",
  "properties": {
    "iso:country":"US",
    "sg:address":"306 Main",
    "sg:city":"Hampton",
    "sg:classifiers":[
        {
            "category":"Insurance",
            "subcategory":"Insurance Agent",
            "type":"Services"
        }
    ],
    "sg:phone":"+1 870 798 4209",
    "sg:postcode":"71744",
    "sg:province":"AR",
    "wof:name":"Campbell & Co",
    "wof:placetype":"venue"
},
  "geometry": {"coordinates":[-92.466142,33.537622],"type":"Point"}
}