{
  "type": "Feature",
  "properties": {
    "iso:country":"US",
    "sg:address":"120 S Main St",
    "sg:city":"Leachville",
    "sg:classifiers":[
        {
            "category":"Professional",
            "subcategory":"Accounting & Tax Preparation",
            "type":"Services"
        }
    ],
    "sg:phone":"+1 870 539 2640",
    "sg:postcode":"72438",
    "sg:province":"AR",
    "sg:tags":[
        "accountant"
    ],
    "wof:name":"Stan Whitlow CPA",
    "wof:placetype":"venue"
},
  "geometry": {"coordinates":[-90.257964,35.937765],"type":"Point"}
}