{
  "type": "Feature",
  "properties": {
    "addr:full":"103 W Front St Lonoke AR 72086",
    "addr:housenumber":"103",
    "addr:postcode":"72086",
    "addr:street":"W Front St",
    "iso:country":"US",
    "sg:address":"103 W Front St",
    "sg:city":"Lonoke",
    "sg:classifiers":[
        {
            "category":"Insurance",
            "subcategory":"Insurance Agent",
            "type":"Services"
        }
    ],
    "sg:phone":"+1 501 676 2082",
    "sg:postcode":"72086",
    "sg:province":"AR",
    "wof:name":"Allstate Insurance Co",
    "wof:placetype":"venue"
},
  "geometry": {"coordinates":[-91.90124299999999,34.78384],"type":"Point"}
}