{
  "type": "Feature",
  "properties": {
    "iso:country":"US",
    "sg:address":"114 E Antioch St",
    "sg:city":"Delight",
    "sg:classifiers":[
        {
            "category":"Food & Beverages",
            "subcategory":"Groceries & Convenience Stores",
            "type":"Retail Goods"
        }
    ],
    "sg:phone":"+1 870 379 2415",
    "sg:postcode":"71940",
    "sg:province":"AR",
    "sg:website":"http://www.ezmart.com",
    "wof:name":"E-Z Mart",
    "wof:placetype":"venue"
},
  "geometry": {"coordinates":[-93.50629600000001,34.031602],"type":"Point"}
}