{
  "type": "Feature",
  "properties": {
    "addr:full":"115 N Dixieland Rd Rogers AR 72756",
    "addr:housenumber":"115",
    "addr:postcode":"72756",
    "addr:street":"N Dixieland Rd",
    "iso:country":"US",
    "sg:address":"115 N Dixieland Rd",
    "sg:city":"Rogers",
    "sg:classifiers":[
        {
            "category":"Organizations",
            "subcategory":"Religious Organization",
            "type":"Services"
        }
    ],
    "sg:phone":"+1 479 636 4681",
    "sg:postcode":"72756",
    "sg:province":"AR",
    "wof:name":"First Church Christ Scientist",
    "wof:placetype":"venue"
},
  "geometry": {"coordinates":[-94.143401,36.337504],"type":"Point"}
}