{
  "type": "Feature",
  "properties": {
    "addr:full":"14806 Colonel Glenn Rd Little Rock AR 72210",
    "addr:housenumber":"14806",
    "addr:postcode":"72210",
    "addr:street":"Colonel Glenn Rd",
    "iso:country":"US",
    "sg:address":"14806 Colonel Glenn Rd",
    "sg:city":"Little Rock",
    "sg:classifiers":[
        {
            "category":"Shopping",
            "subcategory":"Crafts & Fabrics",
            "type":"Retail Goods"
        },
        {
            "category":"Shopping",
            "subcategory":"Clothing, Apparel, & Fashions",
            "type":"Retail Goods"
        }
    ],
    "sg:phone":"+1 501 221 2024",
    "sg:postcode":"72210",
    "sg:province":"AR",
    "sg:tags":[
        "re",
        "sewing",
        "alteration"
    ],
    "wof:name":"Pro Stitchery Inc",
    "wof:placetype":"venue"
},
  "geometry": {"coordinates":[-92.451943,34.720405],"type":"Point"}
}