{
  "type": "Feature",
  "properties": {
    "iso:country":"US",
    "sg:address":"2824 John Barrow Rd",
    "sg:city":"Little Rock",
    "sg:classifiers":[
        {
            "category":"Building & Trades",
            "subcategory":"Construction",
            "type":"Services"
        }
    ],
    "sg:phone":"+1 501 312 8282",
    "sg:postcode":"72204",
    "sg:province":"AR",
    "sg:tags":[
        "fire",
        "restoration",
        "damage"
    ],
    "wof:name":"River City Contracting Inc",
    "wof:placetype":"venue"
},
  "geometry": {"coordinates":[-92.372841,34.727828],"type":"Point"}
}