{
  "type": "Feature",
  "properties": {
    "iso:country":"US",
    "sg:address":"430 Columbia Rd",
    "sg:city":"Magnolia",
    "sg:classifiers":[
        {
            "category":"Organizations",
            "subcategory":"Religious Organization",
            "type":"Services"
        }
    ],
    "sg:phone":"+1 870 696 3795",
    "sg:postcode":"71753",
    "sg:province":"AR",
    "sg:tags":[
        "church"
    ],
    "wof:name":"Unity United Methodist Church",
    "wof:placetype":"venue"
},
  "geometry": {"coordinates":[-93.141165,33.267404],"type":"Point"}
}