{
  "type": "Feature",
  "properties": {
    "addr:full":"6302 Hillside Ln Harrison AR 72601",
    "addr:housenumber":"6302",
    "addr:postcode":"72601",
    "addr:street":"Hillside Ln",
    "iso:country":"US",
    "sg:address":"6302 Hillside Ln",
    "sg:city":"Harrison",
    "sg:classifiers":[
        {
            "category":"Food & Beverages",
            "subcategory":"Specialty",
            "type":"Retail Goods"
        }
    ],
    "sg:phone":"+1 870 741 9596",
    "sg:postcode":"72601",
    "sg:province":"AR",
    "sg:tags":[
        "health",
        "diet"
    ],
    "wof:name":"Harrison Optimal Health Inc",
    "wof:placetype":"venue"
},
  "geometry": {"coordinates":[-93.19488699999999,36.192315],"type":"Point"}
}