{
  "type": "Feature",
  "properties": {
    "addr:full":"1801 Cavanaugh Rd Fort Smith AR 72908",
    "addr:housenumber":"1801",
    "addr:postcode":"72908",
    "addr:street":"Cavanaugh Rd",
    "iso:country":"US",
    "sg:address":"1801 Cavanaugh Rd",
    "sg:city":"Fort Smith",
    "sg:classifiers":[
        {
            "category":"Professional",
            "subcategory":"Employment Agencies",
            "type":"Services"
        }
    ],
    "sg:phone":"+1 479 646 7241",
    "sg:postcode":"72908",
    "sg:province":"AR",
    "sg:tags":[
        "opportunity"
    ],
    "wof:name":"National Transit Staffing",
    "wof:placetype":"venue"
},
  "geometry": {"coordinates":[-94.416562,35.312],"type":"Point"}
}