{
  "type": "Feature",
  "properties": {
    "iso:country":"US",
    "sg:address":"285 Hwy 71 S",
    "sg:city":"Ashdown",
    "sg:classifiers":[
        {
            "category":"Professional",
            "type":"Services"
        }
    ],
    "sg:phone":"+1 870 898 9124",
    "sg:postcode":"71853",
    "sg:province":"AR",
    "sg:tags":[
        "establishment"
    ],
    "wof:name":"ABB Combustion",
    "wof:placetype":"venue"
},
  "geometry": {"coordinates":[-94.103889,33.645952],"type":"Point"}
}