{
  "type": "Feature",
  "properties": {
    "iso:country":"US",
    "sg:address":"409 Co Rd 916",
    "sg:city":"Mountain Home",
    "sg:classifiers":[
        {
            "category":"Real Estate",
            "subcategory":"Real Estate Agent",
            "type":"Services"
        }
    ],
    "sg:phone":"+1 870 425 4700",
    "sg:postcode":"72653",
    "sg:province":"AR",
    "wof:name":"Dent's Property Management",
    "wof:placetype":"venue"
},
  "geometry": {"coordinates":[-92.435778,36.357648],"type":"Point"}
}