{
  "type": "Feature",
  "properties": {
    "addr:full":"816 1st Ave Conway AR 72032",
    "addr:housenumber":"816",
    "addr:postcode":"72032",
    "addr:street":"1St Ave",
    "iso:country":"US",
    "sg:address":"816 1st Ave",
    "sg:city":"Conway",
    "sg:classifiers":[
        {
            "category":"Restaurant",
            "type":"Food & Drink"
        }
    ],
    "sg:phone":"+1 501 327 2753",
    "sg:postcode":"72032",
    "sg:province":"AR",
    "sg:website":"www.westernsizzlin.com",
    "wof:name":"Western Sizzlin Wood Grill",
    "wof:placetype":"venue"
},
  "geometry": {"coordinates":[-92.42775899999999,35.090057],"type":"Point"}
}