{
  "type": "Feature",
  "properties": {
    "iso:country":"US",
    "sg:address":"1314 E Short Hillsboro St",
    "sg:city":"El Dorado",
    "sg:classifiers":[
        {
            "category":"Personal",
            "subcategory":"Beauty Salon",
            "type":"Services"
        }
    ],
    "sg:phone":"+1 870 862 9618",
    "sg:postcode":"71730",
    "sg:province":"AR",
    "sg:tags":[
        "shop"
    ],
    "wof:name":"Jean's Beauty Parlor",
    "wof:placetype":"venue"
},
  "geometry": {"coordinates":[-92.649331,33.207163],"type":"Point"}
}