{
  "type": "Feature",
  "properties": {
    "iso:country":"US",
    "sg:address":"324 E Ralston St",
    "sg:city":"Farmington",
    "sg:classifiers":[
        {
            "category":"Insurance",
            "subcategory":"Insurance Agent",
            "type":"Services"
        }
    ],
    "sg:phone":"+1 479 267 3843",
    "sg:postcode":"72730",
    "sg:province":"AR",
    "wof:name":"Lutheran Brotherhood Insurance",
    "wof:placetype":"venue"
},
  "geometry": {"coordinates":[-94.225107,36.04255],"type":"Point"}
}