{
  "type": "Feature",
  "properties": {
    "iso:country":"US",
    "sg:address":"210 S Moose St",
    "sg:city":"Morrilton",
    "sg:classifiers":[
        {
            "category":"Wholesale",
            "subcategory":"Toys & Hobbies",
            "type":"Manufacturing & Wholesale Goods"
        }
    ],
    "sg:phone":"+1 501 354 3428",
    "sg:postcode":"72110",
    "sg:province":"AR",
    "sg:tags":[
        "florist"
    ],
    "wof:name":"Expressions",
    "wof:placetype":"venue"
},
  "geometry": {"coordinates":[-92.744141,35.150964],"type":"Point"}
}