{
  "type": "Feature",
  "properties": {
    "iso:country":"US",
    "sg:address":"444 Atkins Blvd",
    "sg:city":"Marianna",
    "sg:classifiers":[
        {
            "category":"Health Services",
            "subcategory":"Hospital",
            "type":"Services"
        }
    ],
    "sg:phone":"+1 870 295 4050",
    "sg:postcode":"72360",
    "sg:province":"AR",
    "sg:tags":[
        "mental"
    ],
    "sg:website":"www.csoea.org",
    "wof:name":"Counseling Services Of E Ar",
    "wof:placetype":"venue"
},
  "geometry": {"coordinates":[-90.772532,34.770865],"type":"Point"}
}