{
  "type": "Feature",
  "properties": {
    "iso:country":"US",
    "sg:address":"69 E Main St",
    "sg:city":"Ashdown",
    "sg:classifiers":[
        {
            "category":"Shopping",
            "subcategory":"Used Merchandise",
            "type":"Retail Goods"
        }
    ],
    "sg:phone":"+1 870 898 8112",
    "sg:postcode":"71822",
    "sg:province":"AR",
    "wof:name":"Memories On Main",
    "wof:placetype":"venue"
},
  "geometry": {"coordinates":[-94.13119399999999,33.674398],"type":"Point"}
}