{
  "type": "Feature",
  "properties": {
    "addr:full":"963 Hwy 62 E Mountain Home AR 72653",
    "addr:housenumber":"963",
    "addr:postcode":"72653",
    "addr:street":"Hwy 62 E",
    "iso:country":"US",
    "sg:address":"963 Hwy 62 E",
    "sg:city":"Mountain Home",
    "sg:classifiers":[
        {
            "category":"Travel",
            "subcategory":"Hotels & Motels",
            "type":"Entertainment"
        }
    ],
    "sg:phone":"+1 870 425 6001",
    "sg:postcode":"72653",
    "sg:province":"AR",
    "sg:tags":[
        "operation"
    ],
    "wof:name":"Carriage Inn Motel Best Wstn",
    "wof:placetype":"venue"
},
  "geometry": {"coordinates":[-92.37527799999999,36.347359],"type":"Point"}
}