{
  "type": "Feature",
  "properties": {
    "iso:country":"US",
    "sg:address":"1322 W Hillsboro St",
    "sg:city":"El Dorado",
    "sg:classifiers":[
        {
            "category":"Organizations",
            "subcategory":"Religious Organization",
            "type":"Services"
        }
    ],
    "sg:phone":"+1 870 863 4714",
    "sg:postcode":"71730",
    "sg:province":"AR",
    "sg:tags":[
        "church"
    ],
    "wof:name":"Hillsboro Street Church Christ",
    "wof:placetype":"venue"
},
  "geometry": {"coordinates":[-92.678705,33.207568],"type":"Point"}
}