{
  "type": "Feature",
  "properties": {
    "iso:country":"US",
    "sg:address":"100 E Cassady St",
    "sg:city":"Nashville",
    "sg:classifiers":[
        {
            "category":"Food & Beverages",
            "subcategory":"Meat & Fish",
            "type":"Retail Goods"
        }
    ],
    "sg:phone":"+1 870 845 1455",
    "sg:postcode":"71852",
    "sg:province":"AR",
    "sg:tags":[
        "processing"
    ],
    "sg:website":"http://www.tyson.com",
    "wof:name":"Tyson Nashville Cafeteria",
    "wof:placetype":"venue"
},
  "geometry": {"coordinates":[-93.847221,33.928219],"type":"Point"}
}