{
  "type": "Feature",
  "properties": {
    "iso:country":"US",
    "sg:address":"132 Hwy 89 N",
    "sg:city":"Mayflower",
    "sg:classifiers":[
        {
            "category":"Organizations",
            "subcategory":"Religious Organization",
            "type":"Services"
        }
    ],
    "sg:phone":"+1 501 470 3286",
    "sg:postcode":"72106",
    "sg:province":"AR",
    "sg:tags":[
        "church"
    ],
    "wof:name":"Northside Pentecostal Church",
    "wof:placetype":"venue"
},
  "geometry": {"coordinates":[-92.44432399999999,34.961245],"type":"Point"}
}