{
  "type": "Feature",
  "properties": {
    "iso:country":"US",
    "sg:address":"96 Raven Ln",
    "sg:city":"Batesville",
    "sg:classifiers":[
        {
            "category":"Building & Trades",
            "subcategory":"Construction",
            "type":"Services"
        }
    ],
    "sg:phone":"+1 870 569 4482",
    "sg:postcode":"72501",
    "sg:province":"AR",
    "sg:tags":[
        "contractor"
    ],
    "wof:name":"Hammerhead Contracting & Development",
    "wof:placetype":"venue"
},
  "geometry": {"coordinates":[-91.526338,35.763723],"type":"Point"}
}