{
  "type": "Feature",
  "properties": {
    "iso:country":"US",
    "sg:address":"204 S Gum St",
    "sg:city":"Searcy",
    "sg:classifiers":[
        {
            "category":"Retail",
            "subcategory":"Auto Repair",
            "type":"Services"
        }
    ],
    "sg:phone":"+1 501 268 4381",
    "sg:postcode":"72143",
    "sg:province":"AR",
    "sg:tags":[
        "truck"
    ],
    "sg:website":"www.yarnells.com",
    "wof:name":"P M Svc",
    "wof:placetype":"venue"
},
  "geometry": {"coordinates":[-91.739642,35.247709],"type":"Point"}
}