{
  "type": "Feature",
  "properties": {
    "addr:full":"2120 Riverfront Dr Little Rock AR 72202",
    "addr:housenumber":"2120",
    "addr:postcode":"72202",
    "addr:street":"Riverfront Dr",
    "iso:country":"US",
    "sg:address":"2120 Riverfront Dr",
    "sg:city":"Little Rock",
    "sg:classifiers":[
        {
            "category":"Insurance",
            "subcategory":"Insurance Agent",
            "type":"Services"
        }
    ],
    "sg:phone":"+1 501 664 0204",
    "sg:postcode":"72202",
    "sg:province":"AR",
    "wof:name":"Brown & Brown",
    "wof:placetype":"venue"
},
  "geometry": {"coordinates":[-92.30677900000001,34.768975],"type":"Point"}
}