{
  "type": "Feature",
  "properties": {
    "iso:country":"US",
    "sg:address":"3638 N Front St",
    "sg:city":"Fayetteville",
    "sg:classifiers":[
        {
            "category":"Food & Beverages",
            "subcategory":"Bakery",
            "type":"Retail Goods"
        },
        {
            "category":"Bakery",
            "type":"Food & Drink"
        }
    ],
    "sg:menulink":"http://www.allmenus.com/ar/fayetteville/54588-panera-bread/menu/",
    "sg:phone":"+1 479 587 1188",
    "sg:postcode":"72703",
    "sg:province":"AR",
    "sg:tags":[
        "american",
        "sandwich",
        "bakery",
        "pastry"
    ],
    "wof:name":"Panera Bread",
    "wof:placetype":"venue"
},
  "geometry": {"coordinates":[-94.144476,36.116287],"type":"Point"}
}