{
  "type": "Feature",
  "properties": {
    "iso:country":"US",
    "sg:address":"645 Valley View Dr",
    "sg:city":"Eureka Springs",
    "sg:classifiers":[
        {
            "category":"Personal",
            "type":"Services"
        }
    ],
    "sg:phone":"+1 479 253 5814",
    "sg:postcode":"72631",
    "sg:province":"AR",
    "wof:name":"Newcomb Services",
    "wof:placetype":"venue"
},
  "geometry": {"coordinates":[-93.825946,36.39361],"type":"Point"}
}