{
  "type": "Feature",
  "properties": {
    "iso:country":"US",
    "sg:address":"128 Hwy 62 W",
    "sg:city":"Salem",
    "sg:classifiers":[
        {
            "category":"Autos & Motor Vehicles",
            "subcategory":"Fuel & Gas Station",
            "type":"Retail Goods"
        }
    ],
    "sg:phone":"+1 870 895 3646",
    "sg:postcode":"72576",
    "sg:province":"AR",
    "sg:tags":[
        "oil"
    ],
    "wof:name":"William's Station & Garage",
    "wof:placetype":"venue"
},
  "geometry": {"coordinates":[-91.823973,36.367835],"type":"Point"}
}