{
  "type": "Feature",
  "properties": {
    "iso:country":"US",
    "sg:address":"2325 Brookfield Dr",
    "sg:city":"Conway",
    "sg:classifiers":[
        {
            "category":"Professional",
            "subcategory":"Management & Consulting",
            "type":"Services"
        }
    ],
    "sg:phone":"+1 501 329 8192",
    "sg:postcode":"72032",
    "sg:province":"AR",
    "sg:tags":[
        "organizing",
        "business",
        "services-household"
    ],
    "wof:name":"Hambuchen Management Co",
    "wof:placetype":"venue"
},
  "geometry": {"coordinates":[-92.39240100000001,35.097932],"type":"Point"}
}