{
  "type": "Feature",
  "properties": {
    "iso:country":"US",
    "sg:address":"278 W Main St",
    "sg:city":"Farmington",
    "sg:classifiers":[
        {
            "category":"Education",
            "subcategory":"School",
            "type":"Public Place"
        }
    ],
    "sg:phone":"+1 479 266 1860",
    "sg:postcode":"72730",
    "sg:province":"AR",
    "wof:name":"Farmington High School",
    "wof:placetype":"venue"
},
  "geometry": {"coordinates":[-94.253484,36.039405],"type":"Point"}
}