{
  "type": "Feature",
  "properties": {
    "addr:full":"203 Apollo St Malvern AR 72104",
    "addr:housenumber":"203",
    "addr:postcode":"72104",
    "addr:street":"Apollo St",
    "iso:country":"US",
    "sg:address":"203 Apollo St",
    "sg:city":"Malvern",
    "sg:classifiers":[
        {
            "category":"Building & Trades",
            "subcategory":"Plumbing",
            "type":"Services"
        }
    ],
    "sg:phone":"+1 501 332 2153",
    "sg:postcode":"72104",
    "sg:province":"AR",
    "sg:tags":[
        "conditioning",
        "air",
        "system",
        "contractor"
    ],
    "wof:name":"Central Heat and Air",
    "wof:placetype":"venue"
},
  "geometry": {"coordinates":[-92.81306499999999,34.339926],"type":"Point"}
}