{
  "type": "Feature",
  "properties": {
    "iso:country":"US",
    "sg:address":"1004 S Main St",
    "sg:city":"Berryville",
    "sg:classifiers":[
        {
            "category":"Autos & Motor Vehicles",
            "subcategory":"Automobile Sales",
            "type":"Retail Goods"
        }
    ],
    "sg:phone":"+1 870 423 2100",
    "sg:postcode":"72616",
    "sg:province":"AR",
    "sg:tags":[
        "car",
        "dealer"
    ],
    "sg:website":"www.carrollcountychrysler.com",
    "wof:name":"Carroll County Chrysler",
    "wof:placetype":"venue"
},
  "geometry": {"coordinates":[-93.55380100000001,36.355564],"type":"Point"}
}