{
  "type": "Feature",
  "properties": {
    "iso:country":"US",
    "sg:address":"7212 Geyer Springs Rd",
    "sg:city":"Little Rock",
    "sg:classifiers":[
        {
            "category":"Restaurant",
            "type":"Food & Drink"
        }
    ],
    "sg:menulink":"http://www.allmenus.com/ar/little-rock/111630-subway/menu/",
    "sg:phone":"+1 501 562 1064",
    "sg:postcode":"72209",
    "sg:province":"AR",
    "sg:tags":[
        "american",
        "sandwich"
    ],
    "wof:name":"Subway",
    "wof:placetype":"venue"
},
  "geometry": {"coordinates":[-92.34357,34.684398],"type":"Point"}
}