{
  "type": "Feature",
  "properties": {
    "iso:country":"US",
    "sg:address":"966 McCoy Ln",
    "sg:city":"Scott",
    "sg:classifiers":[
        {
            "category":"Farming",
            "subcategory":"Livestock Farm",
            "type":"Manufacturing & Wholesale Goods"
        }
    ],
    "sg:phone":"+1 501 753 1006",
    "sg:postcode":"72142",
    "sg:province":"AR",
    "sg:tags":[
        "animal",
        "general"
    ],
    "wof:name":"J & P Ranch Inc",
    "wof:placetype":"venue"
},
  "geometry": {"coordinates":[-92.08354799999999,34.78744],"type":"Point"}
}