{
  "type": "Feature",
  "properties": {
    "iso:country":"US",
    "sg:address":"4800 Krueger Dr",
    "sg:city":"Jonesboro",
    "sg:classifiers":[
        {
            "category":"Manufacturing",
            "subcategory":"Metals",
            "type":"Manufacturing & Wholesale Goods"
        }
    ],
    "sg:phone":"+1 870 935 3711",
    "sg:postcode":"72401",
    "sg:province":"AR",
    "sg:tags":[
        "stamping"
    ],
    "sg:website":"www.deltastorage.com",
    "wof:name":"Delta Consolidated Industries",
    "wof:placetype":"venue"
},
  "geometry": {"coordinates":[-90.640223,35.81363],"type":"Point"}
}