{
  "type": "Feature",
  "properties": {
    "iso:country":"US",
    "sg:address":"812 Wendland Rd",
    "sg:city":"Helena",
    "sg:classifiers":[
        {
            "category":"Organizations",
            "subcategory":"Religious Organization",
            "type":"Services"
        }
    ],
    "sg:phone":"+1 870 572 6305",
    "sg:postcode":"72342",
    "sg:province":"AR",
    "wof:name":"Church of Living God",
    "wof:placetype":"venue"
},
  "geometry": {"coordinates":[-90.605831,34.531806],"type":"Point"}
}