{
  "type": "Feature",
  "properties": {
    "iso:country":"US",
    "sg:address":"308 Lee St",
    "sg:city":"Lake Village",
    "sg:classifiers":[
        {
            "category":"Organizations",
            "subcategory":"Religious Organization",
            "type":"Services"
        }
    ],
    "sg:phone":"+1 870 265 3580",
    "sg:postcode":"71653",
    "sg:province":"AR",
    "sg:tags":[
        "church"
    ],
    "wof:name":"Woodson Temple Church Study",
    "wof:placetype":"venue"
},
  "geometry": {"coordinates":[-91.28343700000001,33.333559],"type":"Point"}
}