{
  "type": "Feature",
  "properties": {
    "iso:country":"US",
    "sg:address":"3734 Anice Rd",
    "sg:city":"Charleston",
    "sg:classifiers":[
        {
            "category":"Farming",
            "subcategory":"Farm",
            "type":"Manufacturing & Wholesale Goods"
        }
    ],
    "sg:phone":"+1 479 965 7185",
    "sg:postcode":"72933",
    "sg:province":"AR",
    "wof:name":"James Tedder Farm",
    "wof:placetype":"venue"
},
  "geometry": {"coordinates":[-93.995954,35.418566],"type":"Point"}
}