{
  "type": "Feature",
  "properties": {
    "iso:country":"US",
    "sg:address":"100 Discovery Bay Ln",
    "sg:city":"Hot Springs",
    "sg:classifiers":[
        {
            "category":"Building & Trades",
            "subcategory":"Landscaping Services",
            "type":"Services"
        }
    ],
    "sg:phone":"+1 501 525 4586",
    "sg:postcode":"71913",
    "sg:province":"AR",
    "sg:tags":[
        "landscape",
        "contractor"
    ],
    "wof:name":"Mc Kissick Landscaping & Dsgn",
    "wof:placetype":"venue"
},
  "geometry": {"coordinates":[-93.10172,34.458064],"type":"Point"}
}