{
  "type": "Feature",
  "properties": {
    "iso:country":"US",
    "sg:address":"7206 US Hwy 64 W",
    "sg:city":"Russellville",
    "sg:classifiers":[
        {
            "category":"Food & Beverages",
            "subcategory":"Groceries & Convenience Stores",
            "type":"Retail Goods"
        }
    ],
    "sg:phone":"+1 479 498 2073",
    "sg:postcode":"72802",
    "sg:province":"AR",
    "wof:name":"Darrell's Hillside",
    "wof:placetype":"venue"
},
  "geometry": {"coordinates":[-93.197502,35.321301],"type":"Point"}
}