{
  "type": "Feature",
  "properties": {
    "iso:country":"US",
    "sg:address":"5900 Baseline Rd",
    "sg:city":"Little Rock",
    "sg:classifiers":[
        {
            "category":"Retail",
            "subcategory":"Auto Repair",
            "type":"Services"
        }
    ],
    "sg:phone":"+1 501 568 1944",
    "sg:postcode":"72209",
    "sg:province":"AR",
    "sg:tags":[
        "repairing",
        "automobile"
    ],
    "wof:name":"Quality Oil Change",
    "wof:placetype":"venue"
},
  "geometry": {"coordinates":[-92.344041,34.669219],"type":"Point"}
}