{
  "type": "Feature",
  "properties": {
    "addr:full":"304 W Nesbitt Ave Plumerville AR 72127",
    "addr:housenumber":"304",
    "addr:postcode":"72127",
    "addr:street":"W Nesbitt Ave",
    "iso:country":"US",
    "sg:address":"304 W Nesbitt Ave",
    "sg:city":"Plumerville",
    "sg:classifiers":[
        {
            "category":"Organizations",
            "subcategory":"Religious Organization",
            "type":"Services"
        }
    ],
    "sg:phone":"+1 501 354 1859",
    "sg:postcode":"72127",
    "sg:province":"AR",
    "sg:tags":[
        "church"
    ],
    "wof:name":"Portland Baptist Church",
    "wof:placetype":"venue"
},
  "geometry": {"coordinates":[-92.647795,35.161574],"type":"Point"}
}