{
  "type": "Feature",
  "properties": {
    "addr:full":"16944 Homestead Rd Harrisburg AR 72432",
    "addr:housenumber":"16944",
    "addr:postcode":"72432",
    "addr:street":"Homestead Rd",
    "iso:country":"US",
    "sg:address":"16944 Homestead Rd",
    "sg:city":"Harrisburg",
    "sg:classifiers":[
        {
            "category":"Professional",
            "type":"Services"
        }
    ],
    "sg:phone":"+1 870 578 2699",
    "sg:postcode":"72432",
    "sg:province":"AR",
    "sg:tags":[
        "establishment"
    ],
    "wof:name":"Parker Pioneer Homestead",
    "wof:placetype":"venue"
},
  "geometry": {"coordinates":[-90.73304400000001,35.483126],"type":"Point"}
}