{
  "type": "Feature",
  "properties": {
    "iso:country":"US",
    "sg:address":"2700 W Walnut St Ste A",
    "sg:city":"Rogers",
    "sg:classifiers":[
        {
            "category":"Shopping",
            "subcategory":"Clothing, Apparel, & Fashions",
            "type":"Retail Goods"
        }
    ],
    "sg:phone":"+1 479 621 0409",
    "sg:postcode":"72756",
    "sg:province":"AR",
    "sg:tags":[
        "maternity",
        "clothes"
    ],
    "wof:name":"Divine 9",
    "wof:placetype":"venue"
},
  "geometry": {"coordinates":[-94.154668,36.334268],"type":"Point"}
}