{
  "type": "Feature",
  "properties": {
    "iso:country":"US",
    "sg:address":"985 Carson Cv",
    "sg:city":"Conway",
    "sg:classifiers":[
        {
            "category":"Food & Beverages",
            "subcategory":"Specialty",
            "type":"Retail Goods"
        },
        {
            "category":"Restaurant",
            "type":"Food & Drink"
        }
    ],
    "sg:menulink":"http://www.allmenus.com/ar/cadron/136530-smoothie-king/menu/",
    "sg:phone":"+1 501 336 9555",
    "sg:postcode":"72034",
    "sg:province":"AR",
    "sg:tags":[
        "smoothy",
        "juice",
        "american"
    ],
    "wof:name":"Smoothie King",
    "wof:placetype":"venue"
},
  "geometry": {"coordinates":[-92.468064,35.092042],"type":"Point"}
}