{
  "type": "Feature",
  "properties": {
    "iso:country":"US",
    "sg:address":"33 Hope Dr",
    "sg:city":"Bella Vista",
    "sg:classifiers":[
        {
            "category":"Building & Trades",
            "subcategory":"Construction",
            "type":"Services"
        }
    ],
    "sg:phone":"+1 479 855 2762",
    "sg:postcode":"72715",
    "sg:province":"AR",
    "sg:tags":[
        "house"
    ],
    "wof:name":"Rite Home Inspections LLC",
    "wof:placetype":"venue"
},
  "geometry": {"coordinates":[-94.26945600000001,36.486261],"type":"Point"}
}