{
  "type": "Feature",
  "properties": {
    "iso:country":"US",
    "sg:address":"2839 Hwy 141 S",
    "sg:city":"Paragould",
    "sg:classifiers":[
        {
            "category":"Building & Trades",
            "subcategory":"Electrical",
            "type":"Services"
        }
    ],
    "sg:phone":"+1 870 573 6234",
    "sg:postcode":"72450",
    "sg:province":"AR",
    "sg:tags":[
        "electric",
        "contractor"
    ],
    "wof:name":"Gary's Electric",
    "wof:placetype":"venue"
},
  "geometry": {"coordinates":[-90.67299,36.036583],"type":"Point"}
}