{
  "type": "Feature",
  "properties": {
    "addr:full":"1400 E Rolling Hills Dr Fayetteville AR 72703",
    "addr:housenumber":"1400",
    "addr:postcode":"72703",
    "addr:street":"E Rolling Hills Dr",
    "iso:country":"US",
    "sg:address":"1400 E Rolling Hills Dr",
    "sg:city":"Fayetteville",
    "sg:classifiers":[
        {
            "category":"Organizations",
            "subcategory":"Religious Organization",
            "type":"Services"
        }
    ],
    "sg:phone":"+1 479 521 2660",
    "sg:postcode":"72703",
    "sg:province":"AR",
    "wof:name":"Rolling Hills Baptist Church",
    "wof:placetype":"venue"
},
  "geometry": {"coordinates":[-94.137863,36.105265],"type":"Point"}
}