{
  "type": "Feature",
  "properties": {
    "iso:country":"US",
    "sg:address":"11 Ashley Dr",
    "sg:city":"Batesville",
    "sg:classifiers":[
        {
            "category":"Food & Beverages",
            "subcategory":"Groceries & Convenience Stores",
            "type":"Retail Goods"
        }
    ],
    "sg:phone":"+1 870 793 6835",
    "sg:postcode":"72501",
    "sg:province":"AR",
    "wof:name":"Spring Valley Coastal Fd Mart",
    "wof:placetype":"venue"
},
  "geometry": {"coordinates":[-91.60368,35.812384],"type":"Point"}
}