{
  "type": "Feature",
  "properties": {
    "addr:full":"2 Oak Grove Cir Apt 6 Cabot AR 72023",
    "addr:housenumber":"2;6",
    "addr:postcode":"72023",
    "addr:street":"Oak Grove Cir Apt",
    "iso:country":"US",
    "sg:address":"2 Oak Grove Cir Apt 6",
    "sg:city":"Cabot",
    "sg:classifiers":[
        {
            "category":"Insurance",
            "subcategory":"Hazard Insurance",
            "type":"Services"
        }
    ],
    "sg:phone":"+1 501 941 2416",
    "sg:postcode":"72023",
    "sg:province":"AR",
    "wof:name":"Srader Enterprises",
    "wof:placetype":"venue"
},
  "geometry": {"coordinates":[-92.021111,34.978851],"type":"Point"}
}