{
  "type": "Feature",
  "properties": {
    "iso:country":"US",
    "sg:address":"128 Spring St",
    "sg:city":"Eureka Springs",
    "sg:classifiers":[
        {
            "category":"Home & Garden",
            "subcategory":"Garden Supply",
            "type":"Retail Goods"
        }
    ],
    "sg:phone":"+1 479 253 5858",
    "sg:postcode":"72632",
    "sg:province":"AR",
    "sg:tags":[
        "nursery",
        "statuary",
        "accessory"
    ],
    "wof:name":"Garden Pleasures",
    "wof:placetype":"venue"
},
  "geometry": {"coordinates":[-93.737511,36.404955],"type":"Point"}
}