{
  "type": "Feature",
  "properties": {
    "iso:country":"US",
    "sg:address":"527 N 4th",
    "sg:city":"West Helena",
    "sg:classifiers":[
        {
            "category":"Food & Beverages",
            "subcategory":"Groceries & Convenience Stores",
            "type":"Retail Goods"
        }
    ],
    "sg:phone":"+1 870 572 5337",
    "sg:postcode":"72390",
    "sg:province":"AR",
    "wof:name":"Parker & Associates",
    "wof:placetype":"venue"
},
  "geometry": {"coordinates":[-90.641372,34.553659],"type":"Point"}
}