{
  "type": "Feature",
  "properties": {
    "iso:country":"US",
    "sg:address":"406 E 22nd St",
    "sg:city":"Stuttgart",
    "sg:classifiers":[
        {
            "category":"Retail",
            "subcategory":"Portrait Studio",
            "type":"Services"
        }
    ],
    "sg:phone":"+1 870 672 9929",
    "sg:postcode":"72160",
    "sg:province":"AR",
    "sg:tags":[
        "photo"
    ],
    "wof:name":"P C A Portrait Studio",
    "wof:placetype":"venue"
},
  "geometry": {"coordinates":[-91.54873000000001,34.479203],"type":"Point"}
}