{
  "type": "Feature",
  "properties": {
    "addr:full":"2602 E Central Ave Bentonville AR 72712",
    "addr:housenumber":"2602",
    "addr:postcode":"72712",
    "addr:street":"E Central Ave",
    "iso:country":"US",
    "sg:address":"2602 E Central Ave",
    "sg:city":"Bentonville",
    "sg:classifiers":[
        {
            "category":"Real Estate",
            "subcategory":"Real Estate Agent",
            "type":"Services"
        }
    ],
    "sg:phone":"+1 479 273 0675",
    "sg:postcode":"72712",
    "sg:province":"AR",
    "sg:tags":[
        "business"
    ],
    "wof:name":"Appraisals Express of NWA",
    "wof:placetype":"venue"
},
  "geometry": {"coordinates":[-94.17874500000001,36.37078],"type":"Point"}
}