{
  "type": "Feature",
  "properties": {
    "addr:full":"74 Slatey Gap Rd Damascus AR 72039",
    "addr:housenumber":"74",
    "addr:postcode":"72039",
    "addr:street":"Slatey Gap Rd",
    "iso:country":"US",
    "sg:address":"74 Slatey Gap Rd",
    "sg:city":"Damascus",
    "sg:classifiers":[
        {
            "category":"Retail",
            "subcategory":"Auto Repair",
            "type":"Services"
        }
    ],
    "sg:phone":"+1 501 679 7800",
    "sg:postcode":"72039",
    "sg:province":"AR",
    "wof:name":"Arkansas Dielel Performance",
    "wof:placetype":"venue"
},
  "geometry": {"coordinates":[-92.47999,35.263939],"type":"Point"}
}