{
  "type": "Feature",
  "properties": {
    "addr:full":"399 Madison 2790 Huntsville AR 72740",
    "addr:housenumber":"399;2790",
    "addr:postcode":"72740",
    "iso:country":"US",
    "sg:address":"399 Madison 2790",
    "sg:city":"Huntsville",
    "sg:classifiers":[
        {
            "category":"Government",
            "subcategory":"Office",
            "type":"Public Place"
        }
    ],
    "sg:phone":"+1 479 665 4107",
    "sg:postcode":"72740",
    "sg:province":"AR",
    "wof:name":"Jerry Lee Wages",
    "wof:placetype":"venue"
},
  "geometry": {"coordinates":[-93.57527399999999,36.0295],"type":"Point"}
}