{
  "type": "Feature",
  "properties": {
    "iso:country":"US",
    "sg:address":"301 Campbell Rd",
    "sg:city":"N Little Rock",
    "sg:classifiers":[
        {
            "category":"Organizations",
            "subcategory":"Religious Organization",
            "type":"Services"
        }
    ],
    "sg:phone":"+1 501 945 3018",
    "sg:postcode":"72117",
    "sg:province":"AR",
    "sg:tags":[
        "church"
    ],
    "wof:name":"Cornerstone Worship Center",
    "wof:placetype":"venue"
},
  "geometry": {"coordinates":[-92.19283,34.747715],"type":"Point"}
}