{
  "type": "Feature",
  "properties": {
    "iso:country":"US",
    "sg:address":"720 Murray Ave",
    "sg:city":"Wynne",
    "sg:classifiers":[
        {
            "category":"Wholesale",
            "subcategory":"Machinery & Supplies",
            "type":"Manufacturing & Wholesale Goods"
        }
    ],
    "sg:phone":"+1 870 208 8586",
    "sg:postcode":"72396",
    "sg:province":"AR",
    "sg:tags":[
        "equipment",
        "welding"
    ],
    "wof:name":"Makool Welding Supply",
    "wof:placetype":"venue"
},
  "geometry": {"coordinates":[-90.78079099999999,35.245339],"type":"Point"}
}