{
  "type": "Feature",
  "properties": {
    "iso:country":"US",
    "sg:address":"3624 Hwy 16",
    "sg:city":"Pangburn",
    "sg:classifiers":[
        {
            "category":"Freight",
            "type":"Transportation"
        }
    ],
    "sg:phone":"+1 501 728 4800",
    "sg:postcode":"72121",
    "sg:province":"AR",
    "sg:tags":[
        "local",
        "trucking"
    ],
    "wof:name":"C L Johnson Trucking",
    "wof:placetype":"venue"
},
  "geometry": {"coordinates":[-91.825954,35.401949],"type":"Point"}
}