{
  "type": "Feature",
  "properties": {
    "iso:country":"US",
    "sg:address":"15 Davis Hill Rd",
    "sg:city":"Conway",
    "sg:classifiers":[
        {
            "category":"Social Services",
            "subcategory":"Child Care",
            "type":"Services"
        }
    ],
    "sg:phone":"+1 501 329 2102",
    "sg:postcode":"72032",
    "sg:province":"AR",
    "sg:tags":[
        "day"
    ],
    "wof:name":"Country Kids Family Day Care",
    "wof:placetype":"venue"
},
  "geometry": {"coordinates":[-92.323448,35.129537],"type":"Point"}
}