{
  "type": "Feature",
  "properties": {
    "iso:country":"US",
    "sg:address":"1630 S Whitehead Dr",
    "sg:city":"De Witt",
    "sg:classifiers":[
        {
            "category":"Retail",
            "subcategory":"Repair Shop",
            "type":"Services"
        }
    ],
    "sg:phone":"+1 870 946 4399",
    "sg:postcode":"72042",
    "sg:province":"AR",
    "sg:tags":[
        "welding"
    ],
    "wof:name":"Burris Welding & Muffler",
    "wof:placetype":"venue"
},
  "geometry": {"coordinates":[-91.336858,34.279464],"type":"Point"}
}