{
  "type": "Feature",
  "properties": {
    "iso:country":"US",
    "sg:address":"1002 E Huntsville Ave",
    "sg:city":"Springdale",
    "sg:classifiers":[
        {
            "category":"Organizations",
            "subcategory":"Religious Organization",
            "type":"Services"
        }
    ],
    "sg:phone":"+1 479 751 0024",
    "sg:postcode":"72764",
    "sg:province":"AR",
    "wof:name":"Assembly Of God Glad Tidings",
    "wof:placetype":"venue"
},
  "geometry": {"coordinates":[-94.118243,36.188313],"type":"Point"}
}