{
  "type": "Feature",
  "properties": {
    "addr:full":"811 Port Arthur Ave Mena OK 71953",
    "addr:housenumber":"811",
    "addr:postcode":"71953",
    "addr:street":"Port Arthur Ave",
    "iso:country":"US",
    "sg:address":"811 Port Arthur Ave",
    "sg:city":"Mena",
    "sg:classifiers":[
        {
            "category":"Organizations",
            "subcategory":"Religious Organization",
            "type":"Services"
        }
    ],
    "sg:phone":"+1 479 394 2541",
    "sg:postcode":"71953",
    "sg:province":"OK",
    "wof:name":"First Baptist Church",
    "wof:placetype":"venue"
},
  "geometry": {"coordinates":[-94.240742,34.584225],"type":"Point"}
}