{
  "type": "Feature",
  "properties": {
    "iso:country":"US",
    "sg:address":"2825 S Division St",
    "sg:city":"Blytheville",
    "sg:classifiers":[
        {
            "category":"Utilities",
            "subcategory":"Mobile Phone",
            "type":"Services"
        },
        {
            "category":"Communications",
            "subcategory":"Radio Station",
            "type":"Services"
        },
        {
            "category":"Shopping",
            "subcategory":"Mobile Phones",
            "type":"Retail Goods"
        }
    ],
    "sg:phone":"+1 870 763 9441",
    "sg:postcode":"72315",
    "sg:province":"AR",
    "sg:tags":[
        "system",
        "equipment",
        "telephone",
        "cellular",
        "supply"
    ],
    "wof:name":"Mo-Ark Communications",
    "wof:placetype":"venue"
},
  "geometry": {"coordinates":[-89.918587,35.896419],"type":"Point"}
}