{
  "type": "Feature",
  "properties": {
    "addr:full":"1740 S 48th St Springdale AR 72762",
    "addr:housenumber":"1740",
    "addr:postcode":"72762",
    "addr:street":"S 48Th St",
    "iso:country":"US",
    "sg:address":"1740 S 48th St",
    "sg:city":"Springdale",
    "sg:classifiers":[
        {
            "category":"Travel",
            "subcategory":"Hotels & Motels",
            "type":"Entertainment"
        }
    ],
    "sg:phone":"+1 479 872 9100",
    "sg:postcode":"72762",
    "sg:province":"AR",
    "sg:website":"http://marriott.com/SPZRI",
    "wof:name":"Residence Inn-Springdale",
    "wof:placetype":"venue"
},
  "geometry": {"coordinates":[-94.18365900000001,36.170279],"type":"Point"}
}