{
  "type": "Feature",
  "properties": {
    "iso:country":"US",
    "sg:address":"433 Union Rd S",
    "sg:city":"Harrison",
    "sg:classifiers":[
        {
            "category":"Organizations",
            "subcategory":"Religious Organization",
            "type":"Services"
        }
    ],
    "sg:phone":"+1 870 743 1904",
    "sg:postcode":"72601",
    "sg:province":"AR",
    "sg:tags":[
        "church"
    ],
    "wof:name":"Assembly Of God Union Road Chr",
    "wof:placetype":"venue"
},
  "geometry": {"coordinates":[-93.095347,36.225848],"type":"Point"}
}