{
  "type": "Feature",
  "properties": {
    "iso:country":"US",
    "sg:address":"2301 W Walnut St",
    "sg:city":"Rogers",
    "sg:classifiers":[
        {
            "category":"Health Services",
            "subcategory":"Health Practitioner",
            "type":"Services"
        }
    ],
    "sg:phone":"+1 479 631 7678",
    "sg:postcode":"72756",
    "sg:province":"AR",
    "sg:tags":[
        "therapy",
        "physical"
    ],
    "wof:name":"Post 0218 Pediatric Therapy",
    "wof:placetype":"venue"
},
  "geometry": {"coordinates":[-94.151302,36.334299],"type":"Point"}
}