{
  "type": "Feature",
  "properties": {
    "addr:full":"1995 N Center St Elkins AR 72727",
    "addr:housenumber":"1995",
    "addr:postcode":"72727",
    "addr:street":"N Center St",
    "iso:country":"US",
    "sg:address":"1995 N Center St",
    "sg:city":"Elkins",
    "sg:classifiers":[
        {
            "category":"Restaurant",
            "type":"Food & Drink"
        }
    ],
    "sg:phone":"+1 479 643 3500",
    "sg:postcode":"72727",
    "sg:province":"AR",
    "wof:name":"Pizza Junction",
    "wof:placetype":"venue"
},
  "geometry": {"coordinates":[-94.022508,36.02814],"type":"Point"}
}