{
  "type": "Feature",
  "properties": {
    "iso:country":"US",
    "sg:address":"816 W 4th St",
    "sg:city":"Hope",
    "sg:classifiers":[
        {
            "category":"Retail",
            "subcategory":"Repair Shop",
            "type":"Services"
        }
    ],
    "sg:phone":"+1 870 777 2105",
    "sg:postcode":"71801",
    "sg:province":"AR",
    "sg:tags":[
        "upholsterer"
    ],
    "wof:name":"Madlock Upholstery",
    "wof:placetype":"venue"
},
  "geometry": {"coordinates":[-93.599957,33.664164],"type":"Point"}
}