{
  "type": "Feature",
  "properties": {
    "iso:country":"US",
    "sg:address":"406 Pecan",
    "sg:city":"Helena",
    "sg:classifiers":[
        {
            "category":"Animal Shelter",
            "type":"Public Place"
        },
        {
            "category":"Social Services",
            "subcategory":"Adult Care",
            "type":"Services"
        }
    ],
    "sg:phone":"+1 870 338 8447",
    "sg:postcode":"72342",
    "sg:province":"AR",
    "sg:tags":[
        "crisis",
        "intervention"
    ],
    "wof:name":"Angels of Grace Battered Women's Shelter",
    "wof:placetype":"venue"
},
  "geometry": {"coordinates":[-90.588516,34.525969],"type":"Point"}
}