{
  "type": "Feature",
  "properties": {
    "iso:country":"US",
    "sg:address":"5479 W Wheeler Rd",
    "sg:city":"Fayetteville",
    "sg:classifiers":[
        {
            "category":"Building & Trades",
            "subcategory":"Plumbing",
            "type":"Services"
        }
    ],
    "sg:phone":"+1 479 313 5247",
    "sg:postcode":"72704",
    "sg:province":"AR",
    "sg:tags":[
        "conditioning",
        "air",
        "system",
        "contractor"
    ],
    "wof:name":"Fayetteville Heat-N-Air",
    "wof:placetype":"venue"
},
  "geometry": {"coordinates":[-94.239266,36.099489],"type":"Point"}
}