{
  "type": "Feature",
  "properties": {
    "iso:country":"US",
    "sg:address":"197 Hobby Hill Ter",
    "sg:city":"Hot Springs",
    "sg:classifiers":[
        {
            "category":"Manufacturing",
            "subcategory":"Glass & Minerals",
            "type":"Manufacturing & Wholesale Goods"
        }
    ],
    "sg:phone":"+1 501 765 1415",
    "sg:postcode":"71913",
    "sg:province":"AR",
    "sg:tags":[
        "product",
        "marble"
    ],
    "wof:name":"Natural State Construction",
    "wof:placetype":"venue"
},
  "geometry": {"coordinates":[-93.153104,34.455865],"type":"Point"}
}