{
  "type": "Feature",
  "properties": {
    "iso:country":"US",
    "sg:address":"14 Leif Tyler Dr",
    "sg:city":"Sheridan",
    "sg:classifiers":[
        {
            "category":"Building & Trades",
            "subcategory":"Construction",
            "type":"Services"
        }
    ],
    "sg:phone":"+1 870 942 1032",
    "sg:postcode":"72150",
    "sg:province":"AR",
    "sg:tags":[
        "contractor"
    ],
    "wof:name":"Mooney Pressure Washing",
    "wof:placetype":"venue"
},
  "geometry": {"coordinates":[-92.408331,34.29149],"type":"Point"}
}