{
  "type": "Feature",
  "properties": {
    "iso:country":"US",
    "sg:address":"3 Lyndhurst Dr",
    "sg:city":"Bella Vista",
    "sg:classifiers":[
        {
            "category":"Shopping",
            "subcategory":"Used Merchandise",
            "type":"Retail Goods"
        }
    ],
    "sg:phone":"+1 479 855 7130",
    "sg:postcode":"72714",
    "sg:province":"AR",
    "wof:name":"Kay Cornelius",
    "wof:placetype":"venue"
},
  "geometry": {"coordinates":[-94.222556,36.465366],"type":"Point"}
}