{
  "type": "Feature",
  "properties": {
    "addr:full":"178 Block St Marion AR 72364",
    "addr:housenumber":"178",
    "addr:postcode":"72364",
    "addr:street":"Block St",
    "iso:country":"US",
    "sg:address":"178 Block St",
    "sg:city":"Marion",
    "sg:classifiers":[
        {
            "category":"Health Services",
            "subcategory":"Chiropractor",
            "type":"Services"
        }
    ],
    "sg:phone":"+1 870 739 2500",
    "sg:postcode":"72364",
    "sg:province":"AR",
    "wof:name":"Nichols Lawrence S Dr",
    "wof:placetype":"venue"
},
  "geometry": {"coordinates":[-90.20376400000001,35.20833],"type":"Point"}
}