{
  "type": "Feature",
  "properties": {
    "iso:country":"US",
    "sg:address":"1208 Look St",
    "sg:city":"Little Rock",
    "sg:classifiers":[
        {
            "category":"Shopping",
            "subcategory":"Computers & Home Electronics",
            "type":"Retail Goods"
        }
    ],
    "sg:phone":"+1 501 663 2764",
    "sg:postcode":"72204",
    "sg:province":"AR",
    "sg:tags":[
        "used",
        "merchandise"
    ],
    "wof:name":"Pro Net",
    "wof:placetype":"venue"
},
  "geometry": {"coordinates":[-92.340574,34.740362],"type":"Point"}
}