{
  "type": "Feature",
  "properties": {
    "addr:full":"9752 Madison 2405 Huntsville AR 72740",
    "addr:housenumber":"9752",
    "addr:postcode":"2405;72740",
    "addr:street":"Madison",
    "iso:country":"US",
    "sg:address":"9752 Madison 2405",
    "sg:city":"Huntsville",
    "sg:classifiers":[
        {
            "category":"Government",
            "subcategory":"Fire Station",
            "type":"Public Place"
        }
    ],
    "sg:phone":"+1 479 665 2984",
    "sg:postcode":"72740",
    "sg:province":"AR",
    "sg:tags":[
        "protection"
    ],
    "wof:name":"Marble Volunteer Fire Dept",
    "wof:placetype":"venue"
},
  "geometry": {"coordinates":[-93.58671200000001,36.136966],"type":"Point"}
}