{
  "type": "Feature",
  "properties": {
    "iso:country":"US",
    "sg:address":"9752 Madison 2405",
    "sg:city":"Huntsville",
    "sg:classifiers":[
        {
            "category":"Government",
            "subcategory":"Fire Station",
            "type":"Public Place"
        }
    ],
    "sg:phone":"+1 479 665 2984",
    "sg:postcode":"72740",
    "sg:province":"AR",
    "sg:tags":[
        "protection"
    ],
    "wof:name":"Marble Volunteer Fire Dept",
    "wof:placetype":"venue"
},
  "geometry": {"coordinates":[-93.586712,36.136966],"type":"Point"}
}