{
  "type": "Feature",
  "properties": {
    "iso:country":"US",
    "sg:address":"203 NW 16th St",
    "sg:city":"Atkins",
    "sg:classifiers":[
        {
            "category":"Building & Trades",
            "subcategory":"Construction",
            "type":"Services"
        }
    ],
    "sg:phone":"+1 479 641 1151",
    "sg:postcode":"72823",
    "sg:province":"AR",
    "sg:tags":[
        "excavating",
        "contractor"
    ],
    "wof:name":"Bill's Backhoe Svc",
    "wof:placetype":"venue"
},
  "geometry": {"coordinates":[-92.941416,35.258981],"type":"Point"}
}