{
  "type": "Feature",
  "properties": {
    "iso:country":"US",
    "sg:address":"2016 N State Line Ave",
    "sg:city":"Texarkana",
    "sg:classifiers":[
        {
            "category":"Shopping",
            "subcategory":"Clothing, Apparel, & Fashions",
            "type":"Retail Goods"
        }
    ],
    "sg:phone":"+1 870 216 7815",
    "sg:postcode":"71854",
    "sg:province":"AR",
    "wof:name":"Lillies Dress Shop",
    "wof:placetype":"venue"
},
  "geometry": {"coordinates":[-94.043109,33.442949],"type":"Point"}
}