{
  "type": "Feature",
  "properties": {
    "iso:country":"US",
    "sg:address":"Pinnacle Hills Promenade 2203 Promenade Blvd.",
    "sg:city":"Rogers",
    "sg:classifiers":[
        {
            "category":"Restaurant",
            "type":"Food & Drink"
        }
    ],
    "sg:phone":"+1 479 899 6700",
    "sg:postcode":"72758",
    "sg:province":"AR",
    "sg:website":"www.rmcf.com",
    "wof:name":"Rocky Mountain Chocolate Factory",
    "wof:placetype":"venue"
},
  "geometry": {"coordinates":[-94.179139,36.30607],"type":"Point"}
}