{
  "type": "Feature",
  "properties": {
    "addr:full":"915 E Main St Russellville AR 72801",
    "addr:housenumber":"915",
    "addr:postcode":"72801",
    "addr:street":"E Main St",
    "iso:country":"US",
    "sg:address":"915 E Main St",
    "sg:city":"Russellville",
    "sg:classifiers":[
        {
            "category":"Restaurant",
            "type":"Food & Drink"
        }
    ],
    "sg:menulink":"http://www.allmenus.com/ar/illinois/159758-arbys/menu/",
    "sg:phone":"+1 479 967 2520",
    "sg:postcode":"72801",
    "sg:province":"AR",
    "sg:tags":[
        "burger",
        "american"
    ],
    "wof:name":"Arby's",
    "wof:placetype":"venue"
},
  "geometry": {"coordinates":[-93.122878,35.278442],"type":"Point"}
}