{
  "type": "Feature",
  "properties": {
    "iso:country":"US",
    "sg:address":"1409 Lindsey Dr",
    "sg:city":"Pine Bluff",
    "sg:classifiers":[
        {
            "category":"Professional",
            "subcategory":"Business Services",
            "type":"Services"
        }
    ],
    "sg:phone":"+1 870 879 3272",
    "sg:postcode":"71603",
    "sg:province":"AR",
    "wof:name":"Wistera Zine",
    "wof:placetype":"venue"
},
  "geometry": {"coordinates":[-92.009113,34.113378],"type":"Point"}
}