{
  "type": "Feature",
  "properties": {
    "addr:full":"4685 Alcoa Rd Benton AR 72015",
    "addr:housenumber":"4685",
    "addr:postcode":"72015",
    "addr:street":"Alcoa Rd",
    "iso:country":"US",
    "sg:address":"4685 Alcoa Rd",
    "sg:city":"Benton",
    "sg:classifiers":[
        {
            "category":"Wholesale",
            "subcategory":"Machinery & Supplies",
            "type":"Manufacturing & Wholesale Goods"
        }
    ],
    "sg:phone":"+1 501 776 4750",
    "sg:postcode":"72015",
    "sg:province":"AR",
    "sg:tags":[
        "industrial"
    ],
    "wof:name":"CAM Bar",
    "wof:placetype":"venue"
},
  "geometry": {"coordinates":[-92.535329,34.583811],"type":"Point"}
}