{
  "type": "Feature",
  "properties": {
    "addr:full":"696 Whipporwill Salem AR 72576",
    "addr:housenumber":"696",
    "addr:postcode":"72576",
    "addr:street":"Whipporwill",
    "iso:country":"US",
    "sg:address":"696 Whipporwill",
    "sg:city":"Salem",
    "sg:classifiers":[
        {
            "category":"Home & Garden",
            "subcategory":"Building Materials",
            "type":"Retail Goods"
        }
    ],
    "sg:phone":"+1 870 219 7477",
    "sg:postcode":"72576",
    "sg:province":"AR",
    "sg:tags":[
        "awning",
        "canopy"
    ],
    "wof:name":"Awnings and Canvas by DHK Mfg.",
    "wof:placetype":"venue"
},
  "geometry": {"coordinates":[-91.852159,36.313682],"type":"Point"}
}