{
  "type": "Feature",
  "properties": {
    "iso:country":"US",
    "sg:address":"504 N Church St",
    "sg:city":"Atkins",
    "sg:classifiers":[
        {
            "category":"Social Services",
            "subcategory":"Child Care",
            "type":"Services"
        }
    ],
    "sg:phone":"+1 479 641 0749",
    "sg:postcode":"72823",
    "sg:province":"AR",
    "wof:name":"Atkins Learning Ctr II",
    "wof:placetype":"venue"
},
  "geometry": {"coordinates":[-92.937298,35.247226],"type":"Point"}
}