{
  "type": "Feature",
  "properties": {
    "iso:country":"US",
    "sg:address":"794 Cliffside Dr",
    "sg:city":"Fayetteville",
    "sg:classifiers":[
        {
            "category":"Professional",
            "subcategory":"Business Services",
            "type":"Services"
        }
    ],
    "sg:phone":"+1 479 521 1058",
    "sg:postcode":"72701",
    "sg:province":"AR",
    "wof:name":"American Solutions",
    "wof:placetype":"venue"
},
  "geometry": {"coordinates":[-94.113928,36.070751],"type":"Point"}
}