{
  "type": "Feature",
  "properties": {
    "addr:full":"205 N Martin St Warren AR 71671",
    "addr:housenumber":"205",
    "addr:postcode":"71671",
    "addr:street":"N Martin St",
    "iso:country":"US",
    "sg:address":"205 N Martin St",
    "sg:city":"Warren",
    "sg:classifiers":[
        {
            "category":"Wholesale",
            "subcategory":"Construction Materials",
            "type":"Manufacturing & Wholesale Goods"
        },
        {
            "category":"Home & Garden",
            "subcategory":"Building Materials",
            "type":"Retail Goods"
        }
    ],
    "sg:phone":"+1 870 226 6666",
    "sg:postcode":"71671",
    "sg:province":"AR",
    "sg:tags":[
        "lumber"
    ],
    "wof:name":"Arkansas Bradley Building Sup",
    "wof:placetype":"venue"
},
  "geometry": {"coordinates":[-92.07167099999999,33.614816],"type":"Point"}
}