{
  "type": "Feature",
  "properties": {
    "iso:country":"US",
    "sg:address":"1516 E Race Ave",
    "sg:city":"Searcy",
    "sg:classifiers":[
        {
            "category":"Personal",
            "type":"Services"
        }
    ],
    "sg:phone":"+1 501 268 6800",
    "sg:postcode":"72143",
    "sg:province":"AR",
    "sg:tags":[
        "control",
        "weight"
    ],
    "wof:name":"Hypnotherapy Center Of Searcy",
    "wof:placetype":"venue"
},
  "geometry": {"coordinates":[-91.719955,35.250755],"type":"Point"}
}