{
  "type": "Feature",
  "properties": {
    "iso:country":"US",
    "sg:address":"15585 Lynch Rd",
    "sg:city":"Fayetteville",
    "sg:classifiers":[
        {
            "category":"Structure",
            "subcategory":"Office Building",
            "type":"Public Place"
        }
    ],
    "sg:phone":"+1 479 443 7525",
    "sg:postcode":"72704",
    "sg:province":"AR",
    "sg:tags":[
        "park"
    ],
    "wof:name":"Property Hunters",
    "wof:placetype":"venue"
},
  "geometry": {"coordinates":[-94.340982,36.113203],"type":"Point"}
}