{
  "type": "Feature",
  "properties": {
    "iso:country":"US",
    "sg:address":"2283 US Hwy 64",
    "sg:city":"Wynne",
    "sg:classifiers":[
        {
            "category":"Building & Trades",
            "subcategory":"Construction",
            "type":"Services"
        }
    ],
    "sg:phone":"+1 870 208 9611",
    "sg:postcode":"72396",
    "sg:province":"AR",
    "sg:tags":[
        "refinishing"
    ],
    "wof:name":"Midsouth Refinishing",
    "wof:placetype":"venue"
},
  "geometry": {"coordinates":[-90.837606,35.253045],"type":"Point"}
}