{
  "type": "Feature",
  "properties": {
    "addr:full":"101 Issac Perkins Byp Nashville AR 71852",
    "addr:housenumber":"101",
    "addr:postcode":"71852",
    "addr:street":"Byp",
    "iso:country":"US",
    "sg:address":"101 Issac Perkins Byp",
    "sg:city":"Nashville",
    "sg:classifiers":[
        {
            "category":"Government",
            "subcategory":"Fire Station",
            "type":"Public Place"
        }
    ],
    "sg:phone":"+1 870 845 2085",
    "sg:postcode":"71852",
    "sg:province":"AR",
    "sg:tags":[
        "consultant",
        "protection"
    ],
    "wof:name":"Nashville City Of Fire Department Emergency On",
    "wof:placetype":"venue"
},
  "geometry": {"coordinates":[-93.847176,33.948414],"type":"Point"}
}