{
  "type": "Feature",
  "properties": {
    "iso:country":"US",
    "sg:address":"801 Parkway Ave",
    "sg:city":"Conway",
    "sg:classifiers":[
        {
            "category":"Insurance",
            "subcategory":"Insurance Agent",
            "type":"Services"
        }
    ],
    "sg:phone":"+1 501 329 1221",
    "sg:postcode":"72034",
    "sg:province":"AR",
    "wof:name":"Farris Agency Inc",
    "wof:placetype":"venue"
},
  "geometry": {"coordinates":[-92.441876,35.090288],"type":"Point"}
}