{
  "type": "Feature",
  "properties": {
    "iso:country":"US",
    "sg:address":"274 Bradley 18 Rd E",
    "sg:city":"Warren",
    "sg:classifiers":[
        {
            "category":"Organizations",
            "subcategory":"Religious Organization",
            "type":"Services"
        }
    ],
    "sg:phone":"+1 870 226 3773",
    "sg:postcode":"71671",
    "sg:province":"AR",
    "sg:tags":[
        "church"
    ],
    "wof:name":"Faith Freewill Baptist Church",
    "wof:placetype":"venue"
},
  "geometry": {"coordinates":[-92.057044,33.686407],"type":"Point"}
}