{
  "type": "Feature",
  "properties": {
    "addr:full":"11321 W Markham St Little Rock AR 72211",
    "addr:housenumber":"11321",
    "addr:postcode":"72211",
    "addr:street":"W Markham St",
    "iso:country":"US",
    "sg:address":"11321 W Markham St",
    "sg:city":"Little Rock",
    "sg:classifiers":[
        {
            "category":"Professional",
            "type":"Services"
        }
    ],
    "sg:phone":"+1 501 954 9955",
    "sg:postcode":"72211",
    "sg:province":"AR",
    "wof:name":"Tommy Parker",
    "wof:placetype":"venue"
},
  "geometry": {"coordinates":[-92.404335,34.753956],"type":"Point"}
}