{
  "type": "Feature",
  "properties": {
    "iso:country":"US",
    "sg:address":"811 S Houston Ave",
    "sg:city":"Russellville",
    "sg:classifiers":[
        {
            "category":"Building & Trades",
            "subcategory":"Plumbing",
            "type":"Services"
        }
    ],
    "sg:phone":"+1 479 968 1407",
    "sg:postcode":"72801",
    "sg:province":"AR",
    "sg:tags":[
        "plumber",
        "contractor"
    ],
    "wof:name":"Thompson Plumbing & Heating Repair",
    "wof:placetype":"venue"
},
  "geometry": {"coordinates":[-93.14086500000001,35.271403],"type":"Point"}
}