{
  "type": "Feature",
  "properties": {
    "iso:country":"US",
    "sg:address":"200 N Martin St",
    "sg:city":"Warren",
    "sg:classifiers":[
        {
            "category":"Autos & Motor Vehicles",
            "subcategory":"Automobile Sales",
            "type":"Retail Goods"
        }
    ],
    "sg:phone":"+1 870 226 6446",
    "sg:postcode":"71671",
    "sg:province":"AR",
    "wof:name":"Outlaw Auto Sales",
    "wof:placetype":"venue"
},
  "geometry": {"coordinates":[-92.071521,33.614842],"type":"Point"}
}