{
  "type": "Feature",
  "properties": {
    "iso:country":"US",
    "sg:address":"1512 Pinehurst Dr",
    "sg:city":"Malvern",
    "sg:classifiers":[
        {
            "category":"Building & Trades",
            "subcategory":"Plumbing",
            "type":"Services"
        }
    ],
    "sg:phone":"+1 501 332 6102",
    "sg:postcode":"72104",
    "sg:province":"AR",
    "sg:tags":[
        "contractor"
    ],
    "wof:name":"Harry Cummings Plumbing",
    "wof:placetype":"venue"
},
  "geometry": {"coordinates":[-92.829398,34.378075],"type":"Point"}
}