{
  "type": "Feature",
  "properties": {
    "iso:country":"US",
    "sg:address":"3409 Edinburgh Dr",
    "sg:city":"Fort Smith",
    "sg:classifiers":[
        {
            "category":"Building & Trades",
            "subcategory":"Construction",
            "type":"Services"
        }
    ],
    "sg:phone":"+1 479 646 0610",
    "sg:postcode":"72908",
    "sg:province":"AR",
    "sg:tags":[
        "hanging",
        "contractor"
    ],
    "wof:name":"Brooks Painting Ron",
    "wof:placetype":"venue"
},
  "geometry": {"coordinates":[-94.398671,35.297515],"type":"Point"}
}