{
  "type": "Feature",
  "properties": {
    "iso:country":"US",
    "sg:address":"420 Adams Trl",
    "sg:city":"Camden",
    "sg:classifiers":[
        {
            "category":"Restaurant",
            "type":"Food & Drink"
        }
    ],
    "sg:phone":"+1 870 836 4402",
    "sg:postcode":"71701",
    "sg:province":"AR",
    "sg:tags":[
        "barbecue"
    ],
    "wof:name":"Rainbow Fresh Meat & Bar Bq",
    "wof:placetype":"venue"
},
  "geometry": {"coordinates":[-92.979619,33.576225],"type":"Point"}
}