{
  "type": "Feature",
  "properties": {
    "iso:country":"US",
    "sg:address":"1614 W 42nd Ave",
    "sg:city":"Pine Bluff",
    "sg:classifiers":[
        {
            "category":"Health Services",
            "subcategory":"Doctor",
            "type":"Services"
        }
    ],
    "sg:phone":"+1 870 534 6800",
    "sg:postcode":"71603",
    "sg:province":"AR",
    "sg:tags":[
        "medical"
    ],
    "wof:name":"Steve Steve Wright MD",
    "wof:placetype":"venue"
},
  "geometry": {"coordinates":[-92.017867,34.186428],"type":"Point"}
}