{
  "type": "Feature",
  "properties": {
    "iso:country":"US",
    "sg:address":"103 E 3rd Ave",
    "sg:city":"Crossett",
    "sg:classifiers":[
        {
            "category":"Health Services",
            "subcategory":"Doctor",
            "type":"Services"
        }
    ],
    "sg:phone":"+1 870 364 5746",
    "sg:postcode":"71635",
    "sg:province":"AR",
    "sg:tags":[
        "person",
        "medical",
        "consulting"
    ],
    "wof:name":"Barry V Thompson MD",
    "wof:placetype":"venue"
},
  "geometry": {"coordinates":[-91.960112,33.132536],"type":"Point"}
}