{
  "type": "Feature",
  "properties": {
    "iso:country":"US",
    "sg:address":"407 Cemetery Rd",
    "sg:city":"Alpena",
    "sg:classifiers":[
        {
            "category":"Retail",
            "subcategory":"Auto Repair",
            "type":"Services"
        }
    ],
    "sg:phone":"+1 870 437 2989",
    "sg:postcode":"72611",
    "sg:province":"AR",
    "sg:tags":[
        "repairing",
        "automobile"
    ],
    "wof:name":"Ron's Auto Svc",
    "wof:placetype":"venue"
},
  "geometry": {"coordinates":[-93.293021,36.29105],"type":"Point"}
}