{
  "type": "Feature",
  "properties": {
    "iso:country":"US",
    "sg:address":"26 Smoking Oak Rd",
    "sg:city":"Conway",
    "sg:classifiers":[
        {
            "category":"Personal",
            "type":"Services"
        },
        {
            "category":"Professional",
            "subcategory":"Management & Consulting",
            "type":"Services"
        }
    ],
    "sg:phone":"+1 501 327 1010",
    "sg:postcode":"72034",
    "sg:province":"AR",
    "sg:tags":[
        "party",
        "planning"
    ],
    "wof:name":"King's Quest",
    "wof:placetype":"venue"
},
  "geometry": {"coordinates":[-92.465805,35.098878],"type":"Point"}
}