{
  "type": "Feature",
  "properties": {
    "iso:country":"US",
    "sg:address":"190 Deeper Green Rd",
    "sg:city":"Monticello",
    "sg:classifiers":[
        {
            "category":"Organizations",
            "subcategory":"Religious Organization",
            "type":"Services"
        }
    ],
    "sg:phone":"+1 870 460 0404",
    "sg:postcode":"71655",
    "sg:province":"AR",
    "sg:tags":[
        "church"
    ],
    "wof:name":"Apostolic Life Center",
    "wof:placetype":"venue"
},
  "geometry": {"coordinates":[-91.84859,33.62911],"type":"Point"}
}