{
  "type": "Feature",
  "properties": {
    "addr:full":"207 N Pruett St Paragould AR 72450",
    "addr:housenumber":"207",
    "addr:postcode":"72450",
    "addr:street":"N Pruett St",
    "iso:country":"US",
    "sg:address":"207 N Pruett St",
    "sg:city":"Paragould",
    "sg:classifiers":[
        {
            "category":"Home & Garden",
            "subcategory":"Household Appliances",
            "type":"Retail Goods"
        }
    ],
    "sg:phone":"+1 870 239 9090",
    "sg:postcode":"72450",
    "sg:province":"AR",
    "sg:tags":[
        "major"
    ],
    "wof:name":"Huffman's Flea Market",
    "wof:placetype":"venue"
},
  "geometry": {"coordinates":[-90.486135,36.057292],"type":"Point"}
}