{
  "type": "Feature",
  "properties": {
    "iso:country":"US",
    "sg:address":"105 S Avalon St",
    "sg:city":"West Memphis",
    "sg:classifiers":[
        {
            "category":"Professional",
            "subcategory":"Detective & Security Services",
            "type":"Services"
        }
    ],
    "sg:phone":"+1 870 735 3735",
    "sg:postcode":"72301",
    "sg:province":"AR",
    "sg:tags":[
        "car"
    ],
    "wof:name":"Zero Tolerance Investigations",
    "wof:placetype":"venue"
},
  "geometry": {"coordinates":[-90.193634,35.145297],"type":"Point"}
}