{
  "type": "Feature",
  "properties": {
    "addr:full":"1700 Hwy 67 S Newport AR 72473",
    "addr:housenumber":"1700",
    "addr:postcode":"72473",
    "addr:street":"Hwy 67 S",
    "iso:country":"US",
    "sg:address":"1700 Hwy 67 S",
    "sg:city":"Newport",
    "sg:classifiers":[
        {
            "category":"Retail",
            "subcategory":"Auto Repair",
            "type":"Services"
        }
    ],
    "sg:phone":"+1 870 523 4349",
    "sg:postcode":"72473",
    "sg:province":"AR",
    "sg:tags":[
        "automotive"
    ],
    "wof:name":"Newport Wrecker Service",
    "wof:placetype":"venue"
},
  "geometry": {"coordinates":[-91.211067,35.711946],"type":"Point"}
}