{
  "type": "Feature",
  "properties": {
    "iso:country":"US",
    "sg:address":"7419 Alma Hwy",
    "sg:city":"Alma",
    "sg:classifiers":[
        {
            "category":"Professional",
            "subcategory":"Business Services",
            "type":"Services"
        }
    ],
    "sg:phone":"+1 479 783 7580",
    "sg:postcode":"72921",
    "sg:province":"AR",
    "sg:tags":[
        "convention",
        "meeting",
        "facility"
    ],
    "wof:name":"Kincaid Coaches",
    "wof:placetype":"venue"
},
  "geometry": {"coordinates":[-94.25368899999999,35.471796],"type":"Point"}
}