{
  "type": "Feature",
  "properties": {
    "addr:full":"1105 Eastend St Van Buren AR 72956",
    "addr:housenumber":"1105",
    "addr:postcode":"72956",
    "addr:street":"Eastend St",
    "iso:country":"US",
    "sg:address":"1105 Eastend St",
    "sg:city":"Van Buren",
    "sg:classifiers":[
        {
            "category":"Professional",
            "subcategory":"Advertising",
            "type":"Services"
        }
    ],
    "sg:phone":"+1 479 410 3700",
    "sg:postcode":"72956",
    "sg:province":"AR",
    "sg:tags":[
        "mailing",
        "shipping"
    ],
    "wof:name":"Fed Ex",
    "wof:placetype":"venue"
},
  "geometry": {"coordinates":[-94.34785100000001,35.43682],"type":"Point"}
}