{
  "type": "Feature",
  "properties": {
    "iso:country":"US",
    "sg:address":"1519 S Cherry St",
    "sg:city":"Pine Bluff",
    "sg:classifiers":[
        {
            "category":"Food & Beverages",
            "subcategory":"Groceries & Convenience Stores",
            "type":"Retail Goods"
        }
    ],
    "sg:phone":"+1 870 534 7966",
    "sg:postcode":"71601",
    "sg:province":"AR",
    "wof:name":"Shell Git-N-Go",
    "wof:placetype":"venue"
},
  "geometry": {"coordinates":[-92.013415,34.213369],"type":"Point"}
}