{
  "type": "Feature",
  "properties": {
    "iso:country":"US",
    "sg:address":"306 Missile Base Rd",
    "sg:city":"Judsonia",
    "sg:classifiers":[
        {
            "category":"Wholesale",
            "subcategory":"Non-durable Goods",
            "type":"Manufacturing & Wholesale Goods"
        }
    ],
    "sg:phone":"+1 501 729 5022",
    "sg:postcode":"72081",
    "sg:province":"AR",
    "sg:tags":[
        "merchandise",
        "general"
    ],
    "wof:name":"B & M Wholesale",
    "wof:placetype":"venue"
},
  "geometry": {"coordinates":[-91.640958,35.283042],"type":"Point"}
}