{
  "type": "Feature",
  "properties": {
    "iso:country":"US",
    "sg:address":"54 Rosemont Dr",
    "sg:city":"Little Rock",
    "sg:classifiers":[
        {
            "category":"Home & Garden",
            "subcategory":"Furniture",
            "type":"Retail Goods"
        }
    ],
    "sg:phone":"+1 501 666 2099",
    "sg:postcode":"72204",
    "sg:province":"AR",
    "wof:name":"Green Enterprises",
    "wof:placetype":"venue"
},
  "geometry": {"coordinates":[-92.345878,34.730234],"type":"Point"}
}