{
  "type": "Feature",
  "properties": {
    "iso:country":"US",
    "sg:address":"200 E Front St",
    "sg:city":"Altheimer",
    "sg:classifiers":[
        {
            "category":"Food & Beverages",
            "subcategory":"Groceries & Convenience Stores",
            "type":"Retail Goods"
        }
    ],
    "sg:phone":"+1 870 766 8222",
    "sg:postcode":"72004",
    "sg:province":"AR",
    "wof:name":"Thomas Groceries & Gifts 2",
    "wof:placetype":"venue"
},
  "geometry": {"coordinates":[-91.845619,34.320068],"type":"Point"}
}