{
  "type": "Feature",
  "properties": {
    "iso:country":"US",
    "sg:address":"13 Wilson Farm Rd",
    "sg:city":"Greenbrier",
    "sg:classifiers":[
        {
            "category":"Education",
            "subcategory":"Library",
            "type":"Public Place"
        }
    ],
    "sg:phone":"+1 501 679 6344",
    "sg:postcode":"72058",
    "sg:province":"AR",
    "wof:name":"Greenbrier Public Library",
    "wof:placetype":"venue"
},
  "geometry": {"coordinates":[-92.387821,35.222659],"type":"Point"}
}