{
  "type": "Feature",
  "properties": {
    "addr:full":"310 N Jonesboro Ave Russellville AR 72801",
    "addr:housenumber":"310",
    "addr:postcode":"72801",
    "addr:street":"N Jonesboro Ave",
    "iso:country":"US",
    "sg:address":"310 N Jonesboro Ave",
    "sg:city":"Russellville",
    "sg:classifiers":[
        {
            "category":"Railroad",
            "type":"Transportation"
        }
    ],
    "sg:phone":"+1 479 968 4167",
    "sg:postcode":"72801",
    "sg:province":"AR",
    "sg:tags":[
        "operator",
        "line"
    ],
    "wof:name":"Union Pacific Railroad Company",
    "wof:placetype":"venue"
},
  "geometry": {"coordinates":[-93.14112799999999,35.282374],"type":"Point"}
}