{
  "type": "Feature",
  "properties": {
    "iso:country":"US",
    "sg:address":"310 N Jonesboro Ave",
    "sg:city":"Russellville",
    "sg:classifiers":[
        {
            "category":"Railroad",
            "type":"Transportation"
        }
    ],
    "sg:phone":"+1 479 968 4167",
    "sg:postcode":"72801",
    "sg:province":"AR",
    "sg:tags":[
        "operator",
        "line"
    ],
    "wof:name":"Union Pacific Railroad Company",
    "wof:placetype":"venue"
},
  "geometry": {"coordinates":[-93.141128,35.282374],"type":"Point"}
}