{
  "type": "Feature",
  "properties": {
    "iso:country":"US",
    "sg:address":"1031 S Redmond Rd",
    "sg:city":"Jacksonville",
    "sg:classifiers":[
        {
            "category":"Manufacturing",
            "subcategory":"Paper Products",
            "type":"Manufacturing & Wholesale Goods"
        }
    ],
    "sg:phone":"+1 501 982 1573",
    "sg:postcode":"72076",
    "sg:province":"AR",
    "sg:tags":[
        "box"
    ],
    "wof:name":"Smurfit-Stone Container Corp",
    "wof:placetype":"venue"
},
  "geometry": {"coordinates":[-92.121861,34.856242],"type":"Point"}
}