{
  "type": "Feature",
  "properties": {
    "iso:country":"US",
    "sg:address":"1307 Co Rd 124",
    "sg:city":"Oakland",
    "sg:classifiers":[
        {
            "category":"Professional",
            "subcategory":"Accounting & Tax Preparation",
            "type":"Services"
        }
    ],
    "sg:phone":"+1 870 431 5642",
    "sg:postcode":"72661",
    "sg:province":"AR",
    "sg:tags":[
        "return"
    ],
    "wof:name":"Schains Frimel Corporation",
    "wof:placetype":"venue"
},
  "geometry": {"coordinates":[-92.605231,36.46224],"type":"Point"}
}