{
  "type": "Feature",
  "properties": {
    "iso:country":"US",
    "sg:address":"1205 S 11th St",
    "sg:city":"Fort Smith",
    "sg:classifiers":[
        {
            "category":"Retail",
            "subcategory":"Car Wash",
            "type":"Services"
        }
    ],
    "sg:phone":"+1 479 782 2070",
    "sg:postcode":"72901",
    "sg:province":"AR",
    "sg:tags":[
        "automobile",
        "detail",
        "clean"
    ],
    "wof:name":"B & B Detail",
    "wof:placetype":"venue"
},
  "geometry": {"coordinates":[-94.422497,35.373406],"type":"Point"}
}