{
  "type": "Feature",
  "properties": {
    "iso:country":"US",
    "sg:address":"7554 Hwy 5",
    "sg:city":"Mountain View",
    "sg:classifiers":[
        {
            "category":"Organizations",
            "subcategory":"Religious Organization",
            "type":"Services"
        }
    ],
    "sg:phone":"+1 870 269 3585",
    "sg:postcode":"72560",
    "sg:province":"AR",
    "wof:name":"Arbanna Baptist Church",
    "wof:placetype":"venue"
},
  "geometry": {"coordinates":[-91.979812,35.798352],"type":"Point"}
}