{
  "type": "Feature",
  "properties": {
    "iso:country":"US",
    "sg:address":"138 N East Ave",
    "sg:city":"Fayetteville",
    "sg:classifiers":[
        {
            "category":"Banks & Credit Unions",
            "subcategory":"Bank",
            "type":"Services"
        }
    ],
    "sg:phone":"+1 479 582 5626",
    "sg:postcode":"72701",
    "sg:province":"AR",
    "sg:tags":[
        "loan",
        "real estate"
    ],
    "wof:name":"Southern Trust Mortgage",
    "wof:placetype":"venue"
},
  "geometry": {"coordinates":[-94.15954600000001,36.064266],"type":"Point"}
}