{
  "type": "Feature",
  "properties": {
    "addr:full":"260 S 2nd Ave Piggott AR 72454",
    "addr:housenumber":"260",
    "addr:postcode":"72454",
    "addr:street":"S 2Nd Ave",
    "iso:country":"US",
    "sg:address":"260 S 2nd Ave",
    "sg:city":"Piggott",
    "sg:classifiers":[
        {
            "category":"Professional",
            "type":"Services"
        }
    ],
    "sg:phone":"+1 870 598 5867",
    "sg:postcode":"72454",
    "sg:province":"AR",
    "sg:tags":[
        "establishment"
    ],
    "wof:name":"Interactive Systems",
    "wof:placetype":"venue"
},
  "geometry": {"coordinates":[-90.193128,36.380918],"type":"Point"}
}