{
  "type": "Feature",
  "properties": {
    "iso:country":"US",
    "sg:address":"401 S Washington St",
    "sg:city":"Hope",
    "sg:classifiers":[
        {
            "category":"Real Estate",
            "subcategory":"Real Estate Services",
            "type":"Services"
        }
    ],
    "sg:phone":"+1 870 777 2351",
    "sg:postcode":"71801",
    "sg:province":"AR",
    "sg:tags":[
        "company",
        "title"
    ],
    "wof:name":"Hempstead County Abstract Co",
    "wof:placetype":"venue"
},
  "geometry": {"coordinates":[-93.59820999999999,33.664339],"type":"Point"}
}