{
  "type": "Feature",
  "properties": {
    "iso:country":"US",
    "sg:address":"488 Industrial Rd",
    "sg:city":"Grove",
    "sg:classifiers":[
        {
            "category":"Utilities",
            "subcategory":"Water",
            "type":"Services"
        }
    ],
    "sg:phone":"+1 918 786 5051",
    "sg:postcode":"74344",
    "sg:province":"OK",
    "sg:tags":[
        "pump",
        "well",
        "drilling",
        "contractor"
    ],
    "wof:name":"Rapid Drilling",
    "wof:placetype":"venue"
},
  "geometry": {"coordinates":[-94.734596,36.602424],"type":"Point"}
}