{
  "type": "Feature",
  "properties": {
    "iso:country":"US",
    "sg:address":"310 N Arkansas Ave",
    "sg:city":"Russellville",
    "sg:classifiers":[
        {
            "category":"Building & Trades",
            "subcategory":"Equipment Rental",
            "type":"Services"
        }
    ],
    "sg:phone":"+1 479 967 1433",
    "sg:postcode":"72801",
    "sg:province":"AR",
    "sg:tags":[
        "leasing",
        "furniture"
    ],
    "wof:name":"Rent-A-Center",
    "wof:placetype":"venue"
},
  "geometry": {"coordinates":[-93.133556,35.28063],"type":"Point"}
}