{
  "type": "Feature",
  "properties": {
    "iso:country":"US",
    "sg:address":"1337 Highway 49",
    "sg:city":"Marvell",
    "sg:classifiers":[
        {
            "category":"Place Of Worship",
            "subcategory":"Church",
            "type":"Public Place"
        },
        {
            "category":"Place Of Worship",
            "type":"Public Place"
        }
    ],
    "sg:phone":"+1 870 829 3347",
    "sg:postcode":"72366",
    "sg:province":"AR",
    "sg:tags":[
        "churches-apostolic",
        "churches-pentecostal-independent",
        "churches-pentecostal-apostolic",
        "churches-pentecostal"
    ],
    "wof:name":"Apostolic Life Center",
    "wof:placetype":"venue"
},
  "geometry": {"coordinates":[-90.92368399999999,34.561084],"type":"Point"}
}