{
  "type": "Feature",
  "properties": {
    "addr:full":"4315 N County Road 535 Blytheville AR 72315",
    "addr:housenumber":"4315",
    "addr:postcode":"72315",
    "addr:street":"N County Road 535",
    "iso:country":"US",
    "sg:address":"4315 N County Road 535",
    "sg:city":"Blytheville",
    "sg:classifiers":[
        {
            "category":"Place Of Worship",
            "subcategory":"Church",
            "type":"Public Place"
        },
        {
            "category":"Place Of Worship",
            "type":"Public Place"
        }
    ],
    "sg:phone":"+1 870 763 8343",
    "sg:postcode":"72315",
    "sg:province":"AR",
    "sg:tags":[
        "churches-baptist-general",
        "churches-baptist"
    ],
    "wof:name":"Emmanuel Baptist Church",
    "wof:placetype":"venue"
},
  "geometry": {"coordinates":[-90.00021099999999,35.909019],"type":"Point"}
}