{
  "type": "Feature",
  "properties": {
    "addr:full":"1831 Madison 1265 Huntsville AR 72740",
    "addr:housenumber":"1831",
    "addr:postcode":"1265;72740",
    "addr:street":"Madison",
    "iso:country":"US",
    "sg:address":"1831 Madison 1265",
    "sg:city":"Huntsville",
    "sg:classifiers":[
        {
            "category":"Banks & Credit Unions",
            "subcategory":"Bank",
            "type":"Services"
        }
    ],
    "sg:phone":"+1 479 738 5400",
    "sg:postcode":"72740",
    "sg:province":"AR",
    "sg:tags":[
        "loan",
        "real estate"
    ],
    "wof:name":"Progressive Mortgage Lending",
    "wof:placetype":"venue"
},
  "geometry": {"coordinates":[-93.713499,36.133919],"type":"Point"}
}