{
  "type": "Feature",
  "properties": {
    "iso:country":"US",
    "sg:address":"308 W Bond Ave",
    "sg:city":"West Memphis",
    "sg:classifiers":[
        {
            "category":"Professional",
            "subcategory":"Computer Services",
            "type":"Services"
        }
    ],
    "sg:phone":"+1 870 732 6667",
    "sg:postcode":"72301",
    "sg:province":"AR",
    "sg:tags":[
        "consultant",
        "designer"
    ],
    "wof:name":"Unified Computer & Consulting",
    "wof:placetype":"venue"
},
  "geometry": {"coordinates":[-90.190971,35.147917],"type":"Point"}
}