{
  "type": "Feature",
  "properties": {
    "iso:country":"US",
    "sg:address":"400 W Locust St",
    "sg:city":"Blytheville",
    "sg:classifiers":[
        {
            "category":"Manufacturing",
            "subcategory":"Food",
            "type":"Manufacturing & Wholesale Goods"
        }
    ],
    "sg:phone":"+1 870 763 4450",
    "sg:postcode":"72315",
    "sg:province":"AR",
    "sg:tags":[
        "canned",
        "mfg"
    ],
    "wof:name":"Blytheville Canning Co",
    "wof:placetype":"venue"
},
  "geometry": {"coordinates":[-89.90719799999999,35.922561],"type":"Point"}
}