{
  "type": "Feature",
  "properties": {
    "addr:full":"1300 N Center St Lonoke AR 72086",
    "addr:housenumber":"1300",
    "addr:postcode":"72086",
    "addr:street":"N Center St",
    "iso:country":"US",
    "sg:address":"1300 N Center St",
    "sg:city":"Lonoke",
    "sg:classifiers":[
        {
            "category":"Personal",
            "subcategory":"Tanning Parlor",
            "type":"Services"
        }
    ],
    "sg:phone":"+1 501 676 2401",
    "sg:postcode":"72086",
    "sg:province":"AR",
    "sg:tags":[
        "salon"
    ],
    "wof:name":"Xtreme Sun Tanning",
    "wof:placetype":"venue"
},
  "geometry": {"coordinates":[-91.896979,34.794228],"type":"Point"}
}