{
  "type": "Feature",
  "properties": {
    "iso:country":"US",
    "sg:address":"706 Main St",
    "sg:city":"Horatio",
    "sg:classifiers":[
        {
            "category":"Autos & Motor Vehicles",
            "subcategory":"Automobile Sales",
            "type":"Retail Goods"
        }
    ],
    "sg:phone":"+1 870 832 5722",
    "sg:postcode":"71842",
    "sg:province":"AR",
    "sg:tags":[
        "car",
        "dealer"
    ],
    "wof:name":"Danny's Auto Sales",
    "wof:placetype":"venue"
},
  "geometry": {"coordinates":[-94.348529,33.939484],"type":"Point"}
}