{
  "type": "Feature",
  "properties": {
    "iso:country":"US",
    "sg:address":"2260 Craig Ave SW",
    "sg:city":"Camden",
    "sg:classifiers":[
        {
            "category":"Professional",
            "subcategory":"Engineering",
            "type":"Services"
        }
    ],
    "sg:phone":"+1 870 231 4104",
    "sg:postcode":"71701",
    "sg:province":"AR",
    "wof:name":"Project Management Inc",
    "wof:placetype":"venue"
},
  "geometry": {"coordinates":[-92.843851,33.543571],"type":"Point"}
}