{
  "type": "Feature",
  "properties": {
    "iso:country":"US",
    "sg:address":"1908 N Davis St",
    "sg:city":"Lavaca",
    "sg:classifiers":[
        {
            "category":"Manufacturing",
            "subcategory":"Metals",
            "type":"Manufacturing & Wholesale Goods"
        }
    ],
    "sg:phone":"+1 479 674 2427",
    "sg:postcode":"72941",
    "sg:province":"AR",
    "sg:tags":[
        "fabricator",
        "sheet"
    ],
    "wof:name":"Custom Metal Fabricators Inc",
    "wof:placetype":"venue"
},
  "geometry": {"coordinates":[-94.177093,35.351474],"type":"Point"}
}