{
  "type": "Feature",
  "properties": {
    "addr:full":"2820 E Highland Dr Jonesboro AR 72401",
    "addr:housenumber":"2820",
    "addr:postcode":"72401",
    "addr:street":"E Highland Dr",
    "iso:country":"US",
    "sg:address":"2820 E Highland Dr",
    "sg:city":"Jonesboro",
    "sg:classifiers":[
        {
            "category":"Professional",
            "subcategory":"Business Services",
            "type":"Services"
        }
    ],
    "sg:phone":"+1 870 972 8693",
    "sg:postcode":"72401",
    "sg:province":"AR",
    "sg:tags":[
        "painter",
        "sign"
    ],
    "wof:name":"Gibson's Sign-Mart",
    "wof:placetype":"venue"
},
  "geometry": {"coordinates":[-90.671432,35.821236],"type":"Point"}
}