{
  "type": "Feature",
  "properties": {
    "iso:country":"US",
    "sg:address":"510 N 1st St",
    "sg:city":"Glenwood",
    "sg:classifiers":[
        {
            "category":"Government",
            "subcategory":"Office",
            "type":"Public Place"
        },
        {
            "category":"Food & Beverages",
            "subcategory":"Groceries & Convenience Stores",
            "type":"Retail Goods"
        }
    ],
    "sg:phone":"+1 870 356 4355",
    "sg:postcode":"71943",
    "sg:province":"AR",
    "wof:name":"Pike County Fair Association",
    "wof:placetype":"venue"
},
  "geometry": {"coordinates":[-93.554771,34.3298],"type":"Point"}
}