{
  "type": "Feature",
  "properties": {
    "iso:country":"US",
    "sg:address":"41 Dawn Dr W",
    "sg:city":"Mayflower",
    "sg:classifiers":[
        {
            "category":"Home & Garden",
            "subcategory":"Building Materials",
            "type":"Retail Goods"
        },
        {
            "category":"Building & Trades",
            "subcategory":"Construction",
            "type":"Services"
        },
        {
            "category":"Manufacturing",
            "subcategory":"Building Materials",
            "type":"Manufacturing & Wholesale Goods"
        }
    ],
    "sg:phone":"+1 501 470 3965",
    "sg:postcode":"72106",
    "sg:province":"AR",
    "sg:tags":[
        "bathroom",
        "solid",
        "top",
        "counter",
        "surface",
        "contractor",
        "altering",
        "planning",
        "remodeling",
        "kitchen"
    ],
    "wof:name":"Hughes Countertops",
    "wof:placetype":"venue"
},
  "geometry": {"coordinates":[-92.46726099999999,34.972366],"type":"Point"}
}