{
  "type": "Feature",
  "properties": {
    "iso:country":"US",
    "sg:address":"308 N James St",
    "sg:city":"Jacksonville",
    "sg:classifiers":[
        {
            "category":"Health Services",
            "subcategory":"Doctor",
            "type":"Services"
        }
    ],
    "sg:phone":"+1 501 982 7547",
    "sg:postcode":"72076",
    "sg:province":"AR",
    "wof:name":"Cooper JAS M DDS",
    "wof:placetype":"venue"
},
  "geometry": {"coordinates":[-92.11863200000001,34.870343],"type":"Point"}
}