{
  "type": "Feature",
  "properties": {
    "iso:country":"US",
    "sg:address":"9 Lake St",
    "sg:city":"Greenbrier",
    "sg:classifiers":[
        {
            "category":"Personal",
            "subcategory":"Beauty Salon",
            "type":"Services"
        }
    ],
    "sg:phone":"+1 501 679 3220",
    "sg:postcode":"72058",
    "sg:province":"AR",
    "sg:tags":[
        "shop"
    ],
    "wof:name":"Hair Square",
    "wof:placetype":"venue"
},
  "geometry": {"coordinates":[-92.386742,35.216715],"type":"Point"}
}