{
  "type": "Feature",
  "properties": {
    "addr:full":"906 Southwest Dr Jonesboro AR 72401",
    "addr:housenumber":"906",
    "addr:postcode":"72401",
    "addr:street":"Southwest Dr",
    "iso:country":"US",
    "sg:address":"906 Southwest Dr",
    "sg:city":"Jonesboro",
    "sg:classifiers":[
        {
            "category":"Insurance",
            "subcategory":"Title Insurance",
            "type":"Services"
        }
    ],
    "sg:phone":"+1 870 336 2000",
    "sg:postcode":"72401",
    "sg:province":"AR",
    "wof:name":"Professional Title Services of Arkansas",
    "wof:placetype":"venue"
},
  "geometry": {"coordinates":[-90.708618,35.81723],"type":"Point"}
}