{
  "type": "Feature",
  "properties": {
    "addr:full":"2414 S 58th St Fort Smith AR 72903",
    "addr:housenumber":"2414",
    "addr:postcode":"72903",
    "addr:street":"S 58Th St",
    "iso:country":"US",
    "sg:address":"2414 S 58th St",
    "sg:city":"Fort Smith",
    "sg:classifiers":[
        {
            "category":"Health Services",
            "subcategory":"Doctor",
            "type":"Services"
        }
    ],
    "sg:phone":"+1 479 452 3368",
    "sg:postcode":"72903",
    "sg:province":"AR",
    "sg:tags":[
        "dentist"
    ],
    "wof:name":"Robert L Skinner DDS",
    "wof:placetype":"venue"
},
  "geometry": {"coordinates":[-94.368461,35.361064],"type":"Point"}
}