{
  "type": "Feature",
  "properties": {
    "addr:full":"520 W Gaines Ave Monticello AR 71655",
    "addr:housenumber":"520",
    "addr:postcode":"71655",
    "addr:street":"W Gaines Ave",
    "iso:country":"US",
    "sg:address":"520 W Gaines Ave",
    "sg:city":"Monticello",
    "sg:classifiers":[
        {
            "category":"Home & Garden",
            "subcategory":"Household Appliances",
            "type":"Retail Goods"
        }
    ],
    "sg:phone":"+1 870 367 5777",
    "sg:postcode":"71655",
    "sg:province":"AR",
    "wof:name":"Youngs Appliance & Bedding",
    "wof:placetype":"venue"
},
  "geometry": {"coordinates":[-91.797455,33.629394],"type":"Point"}
}