{
  "type": "Feature",
  "properties": {
    "iso:country":"US",
    "sg:address":"402 N Division St",
    "sg:city":"Forrest City",
    "sg:classifiers":[
        {
            "category":"Insurance",
            "subcategory":"Insurance Agent",
            "type":"Services"
        }
    ],
    "sg:phone":"+1 870 633 9944",
    "sg:postcode":"72335",
    "sg:province":"AR",
    "wof:name":"Affordable Insurance Agency",
    "wof:placetype":"venue"
},
  "geometry": {"coordinates":[-90.789715,35.011899],"type":"Point"}
}