{
  "type": "Feature",
  "properties": {
    "iso:country":"US",
    "sg:address":"113 E Parkway Dr",
    "sg:city":"Russellville",
    "sg:classifiers":[
        {
            "category":"Personal",
            "subcategory":"Beauty Salon",
            "type":"Services"
        }
    ],
    "sg:phone":"+1 479 968 8861",
    "sg:postcode":"72801",
    "sg:province":"AR",
    "sg:tags":[
        "shop"
    ],
    "wof:name":"Natural Nails",
    "wof:placetype":"venue"
},
  "geometry": {"coordinates":[-93.133386,35.281326],"type":"Point"}
}