{
  "type": "Feature",
  "properties": {
    "iso:country":"US",
    "sg:address":"1890 Fed-X Dr",
    "sg:city":"Springdale",
    "sg:classifiers":[
        {
            "category":"Wholesale",
            "subcategory":"Machinery & Supplies",
            "type":"Manufacturing & Wholesale Goods"
        }
    ],
    "sg:phone":"+1 479 751 4565",
    "sg:postcode":"72764",
    "sg:province":"AR",
    "sg:tags":[
        "equipment",
        "safety",
        "clothing"
    ],
    "sg:website":"www.themiddletongroup.com",
    "wof:name":"MEMCO Inc",
    "wof:placetype":"venue"
},
  "geometry": {"coordinates":[-94.12742,36.168097],"type":"Point"}
}