{
  "type": "Feature",
  "properties": {
    "iso:country":"US",
    "sg:address":"3311 SW I St",
    "sg:city":"Bentonville",
    "sg:classifiers":[
        {
            "category":"Social Services",
            "type":"Services"
        }
    ],
    "sg:phone":"+1 479 273 1306",
    "sg:postcode":"72712",
    "sg:province":"AR",
    "sg:tags":[
        "organization",
        "welfare"
    ],
    "wof:name":"United Way",
    "wof:placetype":"venue"
},
  "geometry": {"coordinates":[-94.222337,36.338413],"type":"Point"}
}