{
  "type": "Feature",
  "properties": {
    "iso:country":"US",
    "sg:address":"805 S Walton Blvd",
    "sg:city":"Bentonville",
    "sg:classifiers":[
        {
            "category":"Restaurant",
            "type":"Food & Drink"
        }
    ],
    "sg:phone":"+1 479 271 6564",
    "sg:postcode":"72712",
    "sg:province":"AR",
    "sg:tags":[
        "eating"
    ],
    "wof:name":"Baskin-Robbins",
    "wof:placetype":"venue"
},
  "geometry": {"coordinates":[-94.22116800000001,36.366478],"type":"Point"}
}