{
  "type": "Feature",
  "properties": {
    "addr:full":"19682 Nokes Farm Rd Siloam Springs OK 72761",
    "addr:housenumber":"19682",
    "addr:postcode":"72761",
    "addr:street":"Nokes Farm Rd",
    "iso:country":"US",
    "sg:address":"19682 Nokes Farm Rd",
    "sg:city":"Siloam Springs",
    "sg:classifiers":[
        {
            "category":"Professional",
            "type":"Services"
        }
    ],
    "sg:phone":"+1 479 524 3063",
    "sg:postcode":"72761",
    "sg:province":"OK",
    "wof:name":"Us Secret Svc",
    "wof:placetype":"venue"
},
  "geometry": {"coordinates":[-94.47656499999999,36.122642],"type":"Point"}
}