{
  "type": "Feature",
  "properties": {
    "addr:full":"180 Greene Road 818 Paragould AR 72450",
    "addr:housenumber":"180",
    "addr:postcode":"72450",
    "addr:street":"Greene Road 818 Paragould",
    "iso:country":"US",
    "sg:address":"180 Greene Road 818",
    "sg:city":"Paragould",
    "sg:classifiers":[
        {
            "category":"Building & Trades",
            "subcategory":"Construction",
            "type":"Services"
        }
    ],
    "sg:phone":"+1 870 236 9122",
    "sg:postcode":"72450",
    "sg:province":"AR",
    "sg:tags":[
        "roofing",
        "industrial",
        "contractors-commercial",
        "contractor"
    ],
    "wof:name":"Yeargain's Roofing",
    "wof:placetype":"venue"
},
  "geometry": {"coordinates":[-90.456143,36.096414],"type":"Point"}
}