{
  "type": "Feature",
  "properties": {
    "iso:country":"US",
    "sg:address":"155 Front St",
    "sg:city":"Eudora",
    "sg:classifiers":[
        {
            "category":"Organizations",
            "subcategory":"Religious Organization",
            "type":"Services"
        }
    ],
    "sg:phone":"+1 870 355 5546",
    "sg:postcode":"71640",
    "sg:province":"AR",
    "sg:tags":[
        "churches-methodist",
        "place",
        "worship",
        "church"
    ],
    "wof:name":"Bethel Ame Church",
    "wof:placetype":"venue"
},
  "geometry": {"coordinates":[-91.259559,33.110621],"type":"Point"}
}