{
  "type": "Feature",
  "properties": {
    "addr:full":"4953 W State Hwy 118 Tyronza AR 72350",
    "addr:housenumber":"4953",
    "addr:postcode":"72350",
    "addr:street":"W State Hwy 118 Tyronza",
    "iso:country":"US",
    "sg:address":"4953 W State Hwy 118",
    "sg:city":"Tyronza",
    "sg:classifiers":[
        {
            "category":"Home & Garden",
            "subcategory":"Furniture",
            "type":"Retail Goods"
        }
    ],
    "sg:phone":"+1 870 487 2388",
    "sg:postcode":"72350",
    "sg:province":"AR",
    "wof:name":"Creative Custom Cabinets",
    "wof:placetype":"venue"
},
  "geometry": {"coordinates":[-90.254733,35.517939],"type":"Point"}
}