{
  "type": "Feature",
  "properties": {
    "iso:country":"US",
    "sg:address":"2094 Hwy 16",
    "sg:city":"Searcy",
    "sg:classifiers":[
        {
            "category":"Retail",
            "subcategory":"Car Wash",
            "type":"Services"
        },
        {
            "category":"Retail",
            "subcategory":"Auto Repair",
            "type":"Services"
        }
    ],
    "sg:phone":"+1 501 279 9019",
    "sg:postcode":"72143",
    "sg:province":"AR",
    "sg:tags":[
        "carwash",
        "automobile",
        "detail",
        "clean",
        "automotive"
    ],
    "wof:name":"Dave's Auto & Detail",
    "wof:placetype":"venue"
},
  "geometry": {"coordinates":[-91.754089,35.273674],"type":"Point"}
}