{
  "type": "Feature",
  "properties": {
    "iso:country":"US",
    "sg:address":"10779 Haynesville Hwy",
    "sg:city":"Junction City",
    "sg:classifiers":[
        {
            "category":"Professional",
            "type":"Services"
        }
    ],
    "sg:phone":"+1 870 599 4278",
    "sg:postcode":"71749",
    "sg:province":"AR",
    "wof:name":"Greggory G Jolley",
    "wof:placetype":"venue"
},
  "geometry": {"coordinates":[-92.937474,33.039491],"type":"Point"}
}