{
  "type": "Feature",
  "properties": {
    "iso:country":"US",
    "sg:address":"518 Central Ave",
    "sg:city":"Hot Springs",
    "sg:classifiers":[
        {
            "category":"Banks & Credit Unions",
            "subcategory":"Financial Services",
            "type":"Services"
        }
    ],
    "sg:phone":"+1 501 623 5333",
    "sg:postcode":"71901",
    "sg:province":"AR",
    "sg:tags":[
        "international",
        "trade"
    ],
    "wof:name":"Anderson's Trading Co",
    "wof:placetype":"venue"
},
  "geometry": {"coordinates":[-93.054109,34.512519],"type":"Point"}
}