{
  "type": "Feature",
  "properties": {
    "iso:country":"US",
    "sg:address":"6132 Southwest Dr",
    "sg:city":"Jonesboro",
    "sg:classifiers":[
        {
            "category":"Wholesale",
            "subcategory":"Machinery & Supplies",
            "type":"Manufacturing & Wholesale Goods"
        }
    ],
    "sg:phone":"+1 870 972 5522",
    "sg:postcode":"72404",
    "sg:province":"AR",
    "sg:tags":[
        "farm",
        "equipment"
    ],
    "wof:name":"Baltz Equipment Co",
    "wof:placetype":"venue"
},
  "geometry": {"coordinates":[-90.755452,35.777831],"type":"Point"}
}