{
  "type": "Feature",
  "properties": {
    "iso:country":"US",
    "sg:address":"665 Hilltop Ln",
    "sg:city":"Mountain Home",
    "sg:classifiers":[
        {
            "category":"Retail",
            "subcategory":"Auto Repair",
            "type":"Services"
        }
    ],
    "sg:phone":"+1 870 425 0302",
    "sg:postcode":"72653",
    "sg:province":"AR",
    "sg:tags":[
        "automotive"
    ],
    "wof:name":"GL Farris Mobile Home Service",
    "wof:placetype":"venue"
},
  "geometry": {"coordinates":[-92.417825,36.30892],"type":"Point"}
}