{
  "type": "Feature",
  "properties": {
    "iso:country":"US",
    "sg:address":"13909 Chenal Pkwy",
    "sg:city":"Little Rock",
    "sg:classifiers":[
        {
            "category":"Shopping",
            "subcategory":"Department Store",
            "type":"Retail Goods"
        }
    ],
    "sg:phone":"+1 501 312 8000",
    "sg:postcode":"72211",
    "sg:province":"AR",
    "wof:name":"Kohls Department Stores Inc",
    "wof:placetype":"venue"
},
  "geometry": {"coordinates":[-92.431639,34.753426],"type":"Point"}
}