{
  "type": "Feature",
  "properties": {
    "iso:country":"US",
    "sg:address":"3601 Jefferson Ave",
    "sg:city":"Texarkana",
    "sg:classifiers":[
        {
            "category":"Wholesale",
            "subcategory":"Hardware",
            "type":"Manufacturing & Wholesale Goods"
        }
    ],
    "sg:phone":"+1 870 773 1866",
    "sg:postcode":"71854",
    "sg:province":"AR",
    "sg:tags":[
        "tool"
    ],
    "wof:name":"Southern Fastening Systems",
    "wof:placetype":"venue"
},
  "geometry": {"coordinates":[-94.029214,33.458222],"type":"Point"}
}