{
  "type": "Feature",
  "properties": {
    "iso:country":"US",
    "sg:address":"1601 Belmont Dr",
    "sg:city":"Pine Bluff",
    "sg:classifiers":[
        {
            "category":"Organizations",
            "subcategory":"Religious Organization",
            "type":"Services"
        }
    ],
    "sg:phone":"+1 870 534 0141",
    "sg:postcode":"71601",
    "sg:province":"AR",
    "sg:tags":[
        "church"
    ],
    "wof:name":"Prayer & Praise Fellowship",
    "wof:placetype":"venue"
},
  "geometry": {"coordinates":[-91.976508,34.213122],"type":"Point"}
}