{
  "type": "Feature",
  "properties": {
    "iso:country":"US",
    "sg:address":"1467 Kentucky Ave",
    "sg:city":"Morrilton",
    "sg:classifiers":[
        {
            "category":"Wholesale",
            "subcategory":"Hardware",
            "type":"Manufacturing & Wholesale Goods"
        },
        {
            "category":"Home & Garden",
            "subcategory":"Garden Supply",
            "type":"Retail Goods"
        },
        {
            "category":"Retail",
            "subcategory":"Repair Shop",
            "type":"Services"
        }
    ],
    "sg:phone":"+1 501 354 0846",
    "sg:postcode":"72110",
    "sg:province":"AR",
    "sg:tags":[
        "renting",
        "lawn",
        "outdoor",
        "power",
        "landscaping",
        "equipment-sales",
        "equipment",
        "saw"
    ],
    "sg:website":"http://www.stihldealer.net/default-dealer-013059.aspx",
    "wof:name":"Carr's Tool and Equipment Rental",
    "wof:placetype":"venue"
},
  "geometry": {"coordinates":[-92.722397,35.149891],"type":"Point"}
}