{
  "type": "Feature",
  "properties": {
    "iso:country":"US",
    "sg:address":"1457 Grant 535",
    "sg:city":"Hensley",
    "sg:classifiers":[
        {
            "category":"Manufacturing",
            "subcategory":"Buildings",
            "type":"Manufacturing & Wholesale Goods"
        },
        {
            "category":"Manufacturing",
            "subcategory":"Building Materials",
            "type":"Manufacturing & Wholesale Goods"
        }
    ],
    "sg:phone":"+1 870 942 5305",
    "sg:postcode":"72065",
    "sg:province":"AR",
    "sg:tags":[
        "modular",
        "buildings-metal-wholesale",
        "buildings-pre-cut",
        "manufacturer",
        "prefabricated"
    ],
    "wof:name":"Rightway Construction",
    "wof:placetype":"venue"
},
  "geometry": {"coordinates":[-92.372809,34.489779],"type":"Point"}
}