{
  "type": "Feature",
  "properties": {
    "iso:country":"US",
    "sg:address":"1416 S Lee Cir",
    "sg:city":"Blytheville",
    "sg:classifiers":[
        {
            "category":"Organizations",
            "subcategory":"Community Association",
            "type":"Services"
        }
    ],
    "sg:phone":"+1 870 763 3965",
    "sg:postcode":"72315",
    "sg:province":"AR",
    "wof:name":"Kappa Alpha PSI Fraternity",
    "wof:placetype":"venue"
},
  "geometry": {"coordinates":[-89.920267,35.904379],"type":"Point"}
}