{
  "type": "Feature",
  "properties": {
    "iso:country":"US",
    "sg:address":"3700 E Main St",
    "sg:city":"Blytheville",
    "sg:classifiers":[
        {
            "category":"Shopping",
            "subcategory":"Department Store",
            "type":"Retail Goods"
        },
        {
            "category":"Health Services",
            "subcategory":"Optometrist",
            "type":"Services"
        },
        {
            "category":"Shopping",
            "subcategory":"Discount & Variety Stores",
            "type":"Retail Goods"
        },
        {
            "category":"Home & Garden",
            "subcategory":"Furniture",
            "type":"Retail Goods"
        },
        {
            "category":"Professional",
            "subcategory":"Art Services",
            "type":"Services"
        },
        {
            "category":"Autos & Motor Vehicles",
            "subcategory":"Auto Supplies",
            "type":"Retail Goods"
        },
        {
            "category":"Retail",
            "subcategory":"Photofinishing",
            "type":"Services"
        },
        {
            "category":"Shopping",
            "subcategory":"Pharmacy",
            "type":"Retail Goods"
        }
    ],
    "sg:phone":"+1 870 763 0440",
    "sg:postcode":"72315",
    "sg:province":"AR",
    "sg:tags":[
        "photo",
        "photographers-portrait",
        "optical",
        "finishing",
        "tire"
    ],
    "sg:website":"http://www.walmart.com",
    "wof:name":"Walmart Supercenter",
    "wof:placetype":"venue"
},
  "geometry": {"coordinates":[-89.86972299999999,35.928804],"type":"Point"}
}