{
  "type": "Feature",
  "properties": {
    "iso:country":"US",
    "sg:address":"3 Pinewood Dr",
    "sg:city":"Russellville",
    "sg:classifiers":[
        {
            "category":"Professional",
            "subcategory":"Management & Consulting",
            "type":"Services"
        }
    ],
    "sg:phone":"+1 479 968 3280",
    "sg:postcode":"72801",
    "sg:province":"AR",
    "wof:name":"Thurlby Trust",
    "wof:placetype":"venue"
},
  "geometry": {"coordinates":[-93.162331,35.282303],"type":"Point"}
}