{
  "type": "Feature",
  "properties": {
    "iso:country":"US",
    "sg:address":"203 Co Rd 129",
    "sg:city":"Bono",
    "sg:classifiers":[
        {
            "category":"Farming",
            "subcategory":"Farm",
            "type":"Manufacturing & Wholesale Goods"
        }
    ],
    "sg:phone":"+1 870 972 1863",
    "sg:postcode":"72416",
    "sg:province":"AR",
    "sg:tags":[
        "crop",
        "general"
    ],
    "wof:name":"Steve Watkins",
    "wof:placetype":"venue"
},
  "geometry": {"coordinates":[-90.79566199999999,35.885246],"type":"Point"}
}