{
  "type": "Feature",
  "properties": {
    "addr:full":"506 N Locust St North Little Rock AR 72114",
    "addr:housenumber":"506",
    "addr:postcode":"72114",
    "addr:street":"N Locust St",
    "iso:country":"US",
    "sg:address":"506 N Locust St",
    "sg:city":"North Little Rock",
    "sg:classifiers":[
        {
            "category":"Wholesale",
            "subcategory":"Auto Parts",
            "type":"Manufacturing & Wholesale Goods"
        }
    ],
    "sg:phone":"+1 501 372 2191",
    "sg:postcode":"72114",
    "sg:province":"AR",
    "sg:tags":[
        "tire"
    ],
    "wof:name":"Fleet Tire Svc of N Lttle Rock",
    "wof:placetype":"venue"
},
  "geometry": {"coordinates":[-92.26160900000001,34.757582],"type":"Point"}
}