{
  "type": "Feature",
  "properties": {
    "iso:country":"US",
    "sg:address":"407 E Lincoln Ave",
    "sg:city":"Searcy",
    "sg:classifiers":[
        {
            "category":"Manufacturing",
            "subcategory":"Retail Goods",
            "type":"Manufacturing & Wholesale Goods"
        }
    ],
    "sg:phone":"+1 501 268 2225",
    "sg:postcode":"72143",
    "sg:province":"AR",
    "sg:tags":[
        "manufacturer"
    ],
    "wof:name":"HMI Mfg Inc",
    "wof:placetype":"venue"
},
  "geometry": {"coordinates":[-91.73412399999999,35.239886],"type":"Point"}
}