{
  "type": "Feature",
  "properties": {
    "iso:country":"US",
    "sg:address":"514 N 2nd St",
    "sg:city":"Rogers",
    "sg:classifiers":[
        {
            "category":"Building & Trades",
            "subcategory":"Construction",
            "type":"Services"
        }
    ],
    "sg:phone":"+1 479 631 3999",
    "sg:postcode":"72756",
    "sg:province":"AR",
    "sg:tags":[
        "home",
        "builder"
    ],
    "wof:name":"Paradise Home Construction",
    "wof:placetype":"venue"
},
  "geometry": {"coordinates":[-94.116673,36.337746],"type":"Point"}
}