{
  "type": "Feature",
  "properties": {
    "iso:country":"US",
    "sg:address":"206 Brookswood Rd",
    "sg:city":"Sherwood",
    "sg:classifiers":[
        {
            "category":"Insurance",
            "subcategory":"Insurance Agent",
            "type":"Services"
        }
    ],
    "sg:phone":"+1 501 753 9910",
    "sg:postcode":"72120",
    "sg:province":"AR",
    "wof:name":"APS-Insurance",
    "wof:placetype":"venue"
},
  "geometry": {"coordinates":[-92.191076,34.829005],"type":"Point"}
}