{
  "type": "Feature",
  "properties": {
    "addr:full":"2770 State Hwy 19 Murfreesboro AR 71958",
    "addr:housenumber":"2770",
    "addr:postcode":"71958",
    "addr:street":"State Hwy 19",
    "iso:country":"US",
    "sg:address":"2770 State Hwy 19",
    "sg:city":"Murfreesboro",
    "sg:classifiers":[
        {
            "category":"Travel",
            "subcategory":"Hotels & Motels",
            "type":"Entertainment"
        }
    ],
    "sg:phone":"+1 870 285 2255",
    "sg:postcode":"71958",
    "sg:province":"AR",
    "sg:tags":[
        "operation"
    ],
    "wof:name":"Shared Vacation Properties",
    "wof:placetype":"venue"
},
  "geometry": {"coordinates":[-93.70457500000001,34.138389],"type":"Point"}
}