{
  "type": "Feature",
  "properties": {
    "addr:full":"209 Cedar St Lexa AR 72355",
    "addr:housenumber":"209",
    "addr:postcode":"72355",
    "addr:street":"Cedar St",
    "iso:country":"US",
    "sg:address":"209 Cedar St",
    "sg:city":"Lexa",
    "sg:classifiers":[
        {
            "category":"Organizations",
            "subcategory":"Religious Organization",
            "type":"Services"
        }
    ],
    "sg:phone":"+1 870 572 7173",
    "sg:postcode":"72355",
    "sg:province":"AR",
    "sg:tags":[
        "parsonage"
    ],
    "wof:name":"Lexa Baptist Church Parsonage",
    "wof:placetype":"venue"
},
  "geometry": {"coordinates":[-90.752133,34.596748],"type":"Point"}
}