{
  "type": "Feature",
  "properties": {
    "addr:full":"211 Main St Scranton AR 72863",
    "addr:housenumber":"211",
    "addr:postcode":"72863",
    "addr:street":"Main St",
    "iso:country":"US",
    "sg:address":"211 Main St",
    "sg:city":"Scranton",
    "sg:classifiers":[
        {
            "category":"Utilities",
            "subcategory":"Refuse",
            "type":"Services"
        }
    ],
    "sg:phone":"+1 479 938 7035",
    "sg:postcode":"72863",
    "sg:province":"AR",
    "sg:tags":[
        "truck",
        "dump"
    ],
    "wof:name":"Tim Willems",
    "wof:placetype":"venue"
},
  "geometry": {"coordinates":[-93.530773,35.360691],"type":"Point"}
}