{
  "type": "Feature",
  "properties": {
    "iso:country":"US",
    "sg:address":"224 NE 2nd St",
    "sg:city":"Walnut Ridge",
    "sg:classifiers":[
        {
            "category":"Retail",
            "subcategory":"Repair Shop",
            "type":"Services"
        }
    ],
    "sg:phone":"+1 870 886 5957",
    "sg:postcode":"72476",
    "sg:province":"AR",
    "sg:tags":[
        "lock",
        "locksmith"
    ],
    "wof:name":"John S Lock & Key",
    "wof:placetype":"venue"
},
  "geometry": {"coordinates":[-90.953801,36.067823],"type":"Point"}
}