{
  "type": "Feature",
  "properties": {
    "iso:country":"US",
    "sg:address":"5116 Shepherds Way",
    "sg:city":"Harrison",
    "sg:classifiers":[
        {
            "category":"Place Of Worship",
            "subcategory":"Church",
            "type":"Public Place"
        },
        {
            "category":"Place Of Worship",
            "type":"Public Place"
        }
    ],
    "sg:phone":"+1 870 741 3300",
    "sg:postcode":"72601",
    "sg:province":"AR",
    "sg:tags":[
        "churches-salvation",
        "army"
    ],
    "wof:name":"Path, The",
    "wof:placetype":"venue"
},
  "geometry": {"coordinates":[-93.1929,36.240683],"type":"Point"}
}