{
  "type": "Feature",
  "properties": {
    "iso:country":"US",
    "sg:address":"204 E Adams St",
    "sg:city":"Judsonia",
    "sg:classifiers":[
        {
            "category":"Building & Trades",
            "subcategory":"Construction",
            "type":"Services"
        }
    ],
    "sg:phone":"+1 501 729 0005",
    "sg:postcode":"72081",
    "sg:province":"AR",
    "sg:tags":[
        "contractor",
        "painting",
        "hanging"
    ],
    "wof:name":"Margie's Interiors",
    "wof:placetype":"venue"
},
  "geometry": {"coordinates":[-91.638575,35.270161],"type":"Point"}
}