{
  "type": "Feature",
  "properties": {
    "addr:full":"3401 Fair Park Blvd Little Rock AR 72204",
    "addr:housenumber":"3401",
    "addr:postcode":"72204",
    "addr:street":"Fair Park Blvd",
    "iso:country":"US",
    "sg:address":"3401 Fair Park Blvd",
    "sg:city":"Little Rock",
    "sg:classifiers":[
        {
            "category":"Organizations",
            "subcategory":"Religious Organization",
            "type":"Services"
        }
    ],
    "sg:phone":"+1 501 570 0518",
    "sg:postcode":"72204",
    "sg:province":"AR",
    "sg:tags":[
        "church"
    ],
    "wof:name":"LDS Arkansas Little Rock Msn",
    "wof:placetype":"venue"
},
  "geometry": {"coordinates":[-92.33379600000001,34.719588],"type":"Point"}
}