{
  "type": "Feature",
  "properties": {
    "iso:country":"US",
    "sg:address":"119 S Cedar St",
    "sg:city":"De Witt",
    "sg:classifiers":[
        {
            "category":"Restaurant",
            "type":"Food & Drink"
        }
    ],
    "sg:phone":"+1 870 946 4443",
    "sg:postcode":"72042",
    "sg:province":"AR",
    "sg:tags":[
        "eating"
    ],
    "wof:name":"Fairwinds Restaurant",
    "wof:placetype":"venue"
},
  "geometry": {"coordinates":[-91.33122,34.295083],"type":"Point"}
}