{
  "type": "Feature",
  "properties": {
    "addr:full":"412 W Trimble Ave Berryville AR 72616",
    "addr:housenumber":"412",
    "addr:postcode":"72616",
    "addr:street":"W Trimble Ave",
    "iso:country":"US",
    "sg:address":"412 W Trimble Ave",
    "sg:city":"Berryville",
    "sg:classifiers":[
        {
            "category":"Personal",
            "subcategory":"Beauty Salon",
            "type":"Services"
        }
    ],
    "sg:phone":"+1 870 423 7314",
    "sg:postcode":"72616",
    "sg:province":"AR",
    "wof:name":"All About Hair Salon",
    "wof:placetype":"venue"
},
  "geometry": {"coordinates":[-93.57877000000001,36.368631],"type":"Point"}
}