{
  "type": "Feature",
  "properties": {
    "addr:full":"100 N DIXIELAND RD STE C4-8 ROGERS AR 72756",
    "addr:housenumber":"100",
    "addr:postcode":"72756",
    "addr:street":"N Dixieland Rd Ste C4-8",
    "iso:country":"US",
    "sg:address":"100 N DIXIELAND RD STE C4-8",
    "sg:city":"ROGERS",
    "sg:classifiers":[
        {
            "category":"Home & Garden",
            "subcategory":"Household Appliances",
            "type":"Retail Goods"
        },
        {
            "category":"Communications",
            "subcategory":"Radio Station",
            "type":"Services"
        },
        {
            "category":"Shopping",
            "subcategory":"Computers & Home Electronics",
            "type":"Retail Goods"
        },
        {
            "category":"Home & Garden",
            "subcategory":"Furniture",
            "type":"Retail Goods"
        }
    ],
    "sg:phone":"+1 479 636 1900",
    "sg:postcode":"72756",
    "sg:province":"AR",
    "sg:tags":[
        "renting",
        "television",
        "leasing",
        "radio-renting",
        "equipment",
        "rental"
    ],
    "sg:website":"http://www.rentacenter.com/",
    "wof:name":"Rent-A-Center",
    "wof:placetype":"venue"
},
  "geometry": {"coordinates":[-94.14360000000001,36.334011],"type":"Point"}
}