{
  "type": "Feature",
  "properties": {
    "iso:country":"US",
    "sg:address":"405 W Runnels St",
    "sg:city":"Mineral Springs",
    "sg:classifiers":[
        {
            "category":"Restaurant",
            "type":"Food & Drink"
        }
    ],
    "sg:phone":"+1 870 287 4555",
    "sg:postcode":"71851",
    "sg:province":"AR",
    "wof:name":"Cactus Grill",
    "wof:placetype":"venue"
},
  "geometry": {"coordinates":[-93.92227,33.875361],"type":"Point"}
}