{
  "type": "Feature",
  "properties": {
    "iso:country":"US",
    "sg:address":"2960 Columbia Rd 11 E",
    "sg:city":"Magnolia",
    "sg:classifiers":[
        {
            "category":"Manufacturing",
            "subcategory":"Lumber",
            "type":"Manufacturing & Wholesale Goods"
        }
    ],
    "sg:phone":"+1 870 234 3537",
    "sg:postcode":"71753",
    "sg:province":"AR",
    "sg:tags":[
        "forester"
    ],
    "wof:name":"Weyerhaeuser Co",
    "wof:placetype":"venue"
},
  "geometry": {"coordinates":[-93.13507,33.214644],"type":"Point"}
}