{
  "type": "Feature",
  "properties": {
    "addr:full":"305 E Adams St Hamburg AR 71646",
    "addr:housenumber":"305",
    "addr:postcode":"71646",
    "addr:street":"E Adams St",
    "iso:country":"US",
    "sg:address":"305 E Adams St",
    "sg:city":"Hamburg",
    "sg:classifiers":[
        {
            "category":"Government",
            "subcategory":"Police Station",
            "type":"Public Place"
        }
    ],
    "sg:phone":"+1 870 853 8600",
    "sg:postcode":"71646",
    "sg:province":"AR",
    "sg:tags":[
        "department"
    ],
    "wof:name":"Police Departments",
    "wof:placetype":"venue"
},
  "geometry": {"coordinates":[-91.795874,33.22636],"type":"Point"}
}