{
  "type": "Feature",
  "properties": {
    "addr:full":"11039 Beneux Bottom Rd Mulberry AR 72947",
    "addr:housenumber":"11039",
    "addr:postcode":"72947",
    "addr:street":"Beneux Bottom Rd",
    "iso:country":"US",
    "sg:address":"11039 Beneux Bottom Rd",
    "sg:city":"Mulberry",
    "sg:classifiers":[
        {
            "category":"Retail",
            "subcategory":"Auto Repair",
            "type":"Services"
        }
    ],
    "sg:phone":"+1 479 997 2675",
    "sg:postcode":"72947",
    "sg:province":"AR",
    "sg:tags":[
        "wrecker"
    ],
    "wof:name":"M & L Towing & Salvage",
    "wof:placetype":"venue"
},
  "geometry": {"coordinates":[-94.024097,35.538465],"type":"Point"}
}