{
  "type": "Feature",
  "properties": {
    "addr:full":"706 W Pleasure Ave Searcy AR 72143",
    "addr:housenumber":"706",
    "addr:postcode":"72143",
    "addr:street":"W Pleasure Ave",
    "iso:country":"US",
    "sg:address":"706 W Pleasure Ave",
    "sg:city":"Searcy",
    "sg:classifiers":[
        {
            "category":"Building & Trades",
            "subcategory":"Plumbing",
            "type":"Services"
        }
    ],
    "sg:phone":"+1 501 268 4559",
    "sg:postcode":"72143",
    "sg:province":"AR",
    "sg:tags":[
        "air",
        "heating",
        "conditioning",
        "contractor"
    ],
    "wof:name":"Total Comfort Inc",
    "wof:placetype":"venue"
},
  "geometry": {"coordinates":[-91.745195,35.247869],"type":"Point"}
}