{
  "type": "Feature",
  "properties": {
    "iso:country":"US",
    "sg:address":"908 S 12th St",
    "sg:city":"Rogers",
    "sg:classifiers":[
        {
            "category":"Recreation",
            "type":"Entertainment"
        }
    ],
    "sg:phone":"+1 479 633 0662",
    "sg:postcode":"72756",
    "sg:province":"AR",
    "sg:tags":[
        "guide"
    ],
    "wof:name":"Big 1's Striper Guide",
    "wof:placetype":"venue"
},
  "geometry": {"coordinates":[-94.131576,36.324222],"type":"Point"}
}