{
  "type": "Feature",
  "properties": {
    "addr:full":"441 School St Weiner AR 72479",
    "addr:housenumber":"441",
    "addr:postcode":"72479",
    "addr:street":"School St",
    "iso:country":"US",
    "sg:address":"441 School St",
    "sg:city":"Weiner",
    "sg:classifiers":[
        {
            "category":"Organizations",
            "subcategory":"Membership Organization",
            "type":"Services"
        }
    ],
    "sg:phone":"+1 870 684 7750",
    "sg:postcode":"72479",
    "sg:province":"AR",
    "wof:name":"Crowley's Ridge Dev Council",
    "wof:placetype":"venue"
},
  "geometry": {"coordinates":[-90.904664,35.626738],"type":"Point"}
}