{
  "type": "Feature",
  "properties": {
    "iso:country":"US",
    "sg:address":"40 Allen Chapel Rd",
    "sg:city":"Batesville",
    "sg:classifiers":[
        {
            "category":"Government",
            "subcategory":"Office",
            "type":"Public Place"
        }
    ],
    "sg:phone":"+1 870 251 2848",
    "sg:postcode":"72501",
    "sg:province":"AR",
    "sg:tags":[
        "administrative",
        "program",
        "health"
    ],
    "wof:name":"Area X Halth Office-Batesville",
    "wof:placetype":"venue"
},
  "geometry": {"coordinates":[-91.638302,35.737346],"type":"Point"}
}