{
  "type": "Feature",
  "properties": {
    "iso:country":"US",
    "sg:address":"408 W Dickson St",
    "sg:city":"Fayetteville",
    "sg:classifiers":[
        {
            "category":"Restaurant",
            "type":"Food & Drink"
        }
    ],
    "sg:phone":"+1 479 973 6969",
    "sg:postcode":"72701",
    "sg:province":"AR",
    "wof:name":"Brewski's Restauarant & Draft",
    "wof:placetype":"venue"
},
  "geometry": {"coordinates":[-94.165447,36.066447],"type":"Point"}
}