{
  "type": "Feature",
  "properties": {
    "iso:country":"US",
    "sg:address":"525 W Faulkner St",
    "sg:city":"El Dorado",
    "sg:classifiers":[
        {
            "category":"Shopping",
            "subcategory":"Gifts & Souvenirs",
            "type":"Retail Goods"
        }
    ],
    "sg:phone":"+1 870 862 2375",
    "sg:postcode":"71730",
    "sg:province":"AR",
    "wof:name":"Secret Door",
    "wof:placetype":"venue"
},
  "geometry": {"coordinates":[-92.669209,33.21466],"type":"Point"}
}