{
  "type": "Feature",
  "properties": {
    "iso:country":"US",
    "sg:address":"310 East St",
    "sg:city":"Jonesboro",
    "sg:classifiers":[
        {
            "category":"Professional",
            "subcategory":"Business Services",
            "type":"Services"
        },
        {
            "category":"Government",
            "subcategory":"Post Office",
            "type":"Public Place"
        }
    ],
    "sg:phone":"+1 800 275 8777",
    "sg:postcode":"72401",
    "sg:province":"AR",
    "sg:tags":[
        "mail",
        "shipping"
    ],
    "sg:website":"http://www.usps.com",
    "wof:name":"United States Postal Service",
    "wof:placetype":"venue"
},
  "geometry": {"coordinates":[-90.702879,35.840354],"type":"Point"}
}