{
  "type": "Feature",
  "properties": {
    "iso:country":"US",
    "sg:address":"203 Stone St",
    "sg:city":"Jasper",
    "sg:classifiers":[
        {
            "category":"Shopping",
            "subcategory":"Jewelry",
            "type":"Retail Goods"
        }
    ],
    "sg:phone":"+1 870 446 5699",
    "sg:postcode":"72641",
    "sg:province":"AR",
    "sg:tags":[
        "gemologists"
    ],
    "wof:name":"Ozark Rock & Minerals",
    "wof:placetype":"venue"
},
  "geometry": {"coordinates":[-93.18828600000001,36.003101],"type":"Point"}
}