{
  "type": "Feature",
  "properties": {
    "iso:country":"US",
    "sg:address":"24 Wincrest Cir",
    "sg:city":"Sherwood",
    "sg:classifiers":[
        {
            "category":"Personal",
            "subcategory":"Adult",
            "type":"Services"
        }
    ],
    "sg:phone":"+1 501 584 4304",
    "sg:postcode":"72120",
    "sg:province":"AR",
    "sg:tags":[
        "escort"
    ],
    "wof:name":"Southern Belle Escort",
    "wof:placetype":"venue"
},
  "geometry": {"coordinates":[-92.236273,34.88113],"type":"Point"}
}