{
  "type": "Feature",
  "properties": {
    "addr:full":"1102 E Hillsboro St El Dorado AR 71730",
    "addr:housenumber":"1102",
    "addr:postcode":"71730",
    "addr:street":"E Hillsboro St",
    "iso:country":"US",
    "sg:address":"1102 E Hillsboro St",
    "sg:city":"El Dorado",
    "sg:classifiers":[
        {
            "category":"Wholesale",
            "subcategory":"Scrap",
            "type":"Manufacturing & Wholesale Goods"
        }
    ],
    "sg:phone":"+1 870 862 9544",
    "sg:postcode":"71730",
    "sg:province":"AR",
    "sg:tags":[
        "material"
    ],
    "wof:name":"Tillmans Scrap Metal Co",
    "wof:placetype":"venue"
},
  "geometry": {"coordinates":[-92.652833,33.207198],"type":"Point"}
}