{
  "type": "Feature",
  "properties": {
    "iso:country":"US",
    "sg:address":"7 Lawrence Rd 238",
    "sg:city":"Powhatan",
    "sg:classifiers":[
        {
            "category":"Building & Trades",
            "subcategory":"Construction",
            "type":"Services"
        }
    ],
    "sg:phone":"+1 870 878 6000",
    "sg:postcode":"72458",
    "sg:province":"AR",
    "sg:tags":[
        "carpentry",
        "contractor"
    ],
    "wof:name":"Alberda Custom Cabinets",
    "wof:placetype":"venue"
},
  "geometry": {"coordinates":[-91.157103,36.068164],"type":"Point"}
}