{
  "type": "Feature",
  "properties": {
    "addr:full":"1088 Old Hickory Rd Hattieville AR 72063",
    "addr:housenumber":"1088",
    "addr:postcode":"72063",
    "addr:street":"Old Hickory Rd",
    "iso:country":"US",
    "sg:address":"1088 Old Hickory Rd",
    "sg:city":"Hattieville",
    "sg:classifiers":[
        {
            "category":"Wholesale",
            "subcategory":"Durable Goods & Equipment",
            "type":"Manufacturing & Wholesale Goods"
        }
    ],
    "sg:phone":"+1 501 208 0908",
    "sg:postcode":"72063",
    "sg:province":"AR",
    "wof:name":"Hoyts AG Parts & Supply LLC",
    "wof:placetype":"venue"
},
  "geometry": {"coordinates":[-92.772732,35.323009],"type":"Point"}
}