{
  "type": "Feature",
  "properties": {
    "iso:country":"US",
    "sg:address":"3821 S Arkansas Ave",
    "sg:city":"Russellville",
    "sg:classifiers":[
        {
            "category":"Shopping",
            "subcategory":"Party Supplies",
            "type":"Retail Goods"
        }
    ],
    "sg:phone":"+1 479 967 2224",
    "sg:postcode":"72802",
    "sg:province":"AR",
    "sg:tags":[
        "toilets-portable"
    ],
    "wof:name":"On Site Portable Toilets",
    "wof:placetype":"venue"
},
  "geometry": {"coordinates":[-93.139867,35.239764],"type":"Point"}
}