{
  "type": "Feature",
  "properties": {
    "iso:country":"US",
    "sg:address":"1177 Highway 425 S",
    "sg:city":"Monticello",
    "sg:classifiers":[
        {
            "category":"Shopping",
            "subcategory":"Mobile Phones",
            "type":"Retail Goods"
        }
    ],
    "sg:phone":"+1 870 367 1800",
    "sg:postcode":"71655",
    "sg:province":"AR",
    "sg:tags":[
        "home"
    ],
    "wof:name":"Investment Housing Of Monticello",
    "wof:placetype":"venue"
},
  "geometry": {"coordinates":[-91.801166,33.558468],"type":"Point"}
}