{
  "type": "Feature",
  "properties": {
    "addr:full":"1402 Malcolm Ave Newport AR 72112",
    "addr:housenumber":"1402",
    "addr:postcode":"72112",
    "addr:street":"Malcolm Ave",
    "iso:country":"US",
    "sg:address":"1402 Malcolm Ave",
    "sg:city":"Newport",
    "sg:classifiers":[
        {
            "category":"Insurance",
            "subcategory":"Insurance Agent",
            "type":"Services"
        }
    ],
    "sg:phone":"+1 870 523 3254",
    "sg:postcode":"72112",
    "sg:province":"AR",
    "wof:name":"State Farm Insurance",
    "wof:placetype":"venue"
},
  "geometry": {"coordinates":[-91.262942,35.605924],"type":"Point"}
}