{
  "type": "Feature",
  "properties": {
    "addr:full":"3814 Central Ave Hot Springs AR 71913",
    "addr:housenumber":"3814",
    "addr:postcode":"71913",
    "addr:street":"Central Ave",
    "iso:country":"US",
    "sg:address":"3814 Central Ave",
    "sg:city":"Hot Springs",
    "sg:classifiers":[
        {
            "category":"Shopping",
            "subcategory":"Clothing, Apparel, & Fashions",
            "type":"Retail Goods"
        }
    ],
    "sg:phone":"+1 501 525 5088",
    "sg:postcode":"71913",
    "sg:province":"AR",
    "wof:name":"Li Mandri's Men's Store",
    "wof:placetype":"venue"
},
  "geometry": {"coordinates":[-93.061269,34.463141],"type":"Point"}
}