{
  "type": "Feature",
  "properties": {
    "addr:full":"1021 W 3rd St Hope AR 71801",
    "addr:housenumber":"1021",
    "addr:postcode":"71801",
    "addr:street":"W 3Rd St",
    "iso:country":"US",
    "sg:address":"1021 W 3rd St",
    "sg:city":"Hope",
    "sg:classifiers":[
        {
            "category":"Retail",
            "subcategory":"Repair Shop",
            "type":"Services"
        }
    ],
    "sg:phone":"+1 870 777 6180",
    "sg:postcode":"71801",
    "sg:province":"AR",
    "sg:tags":[
        "motors-repairing",
        "marine",
        "outboard",
        "boat",
        "maintenance"
    ],
    "sg:website":"http://www.rothwellmarine.com",
    "wof:name":"Rothwell Marine",
    "wof:placetype":"venue"
},
  "geometry": {"coordinates":[-93.601399,33.665001],"type":"Point"}
}