{
  "type": "Feature",
  "properties": {
    "iso:country":"US",
    "sg:address":"236 Columbia Rd 449",
    "sg:city":"Magnolia",
    "sg:classifiers":[
        {
            "category":"Professional",
            "subcategory":"Business Services",
            "type":"Services"
        }
    ],
    "sg:phone":"+1 870 234 0993",
    "sg:postcode":"71753",
    "sg:province":"AR",
    "sg:tags":[
        "embroidery"
    ],
    "wof:name":"T-Sports",
    "wof:placetype":"venue"
},
  "geometry": {"coordinates":[-93.188493,33.303922],"type":"Point"}
}