{
  "type": "Feature",
  "properties": {
    "addr:full":"100 Benton St Hughes AR 72348",
    "addr:housenumber":"100",
    "addr:postcode":"72348",
    "addr:street":"Benton St",
    "iso:country":"US",
    "sg:address":"100 Benton St",
    "sg:city":"Hughes",
    "sg:classifiers":[
        {
            "category":"Autos & Motor Vehicles",
            "subcategory":"Automobile Sales",
            "type":"Retail Goods"
        }
    ],
    "sg:phone":"+1 870 339 2015",
    "sg:postcode":"72348",
    "sg:province":"AR",
    "sg:tags":[
        "car",
        "dealer"
    ],
    "wof:name":"Depend Auto",
    "wof:placetype":"venue"
},
  "geometry": {"coordinates":[-90.47313,34.94792],"type":"Point"}
}