{
  "type": "Feature",
  "properties": {
    "iso:country":"US",
    "sg:address":"1811 E Main St",
    "sg:city":"Booneville",
    "sg:classifiers":[
        {
            "category":"Retail",
            "subcategory":"Funeral Services",
            "type":"Services"
        }
    ],
    "sg:phone":"+1 479 675 3392",
    "sg:postcode":"72927",
    "sg:province":"AR",
    "sg:tags":[
        "director"
    ],
    "wof:name":"Roller Funeral Home",
    "wof:placetype":"venue"
},
  "geometry": {"coordinates":[-93.899001,35.142635],"type":"Point"}
}