{
  "type": "Feature",
  "properties": {
    "addr:full":"417 E 7th St Texarkana AR 71854",
    "addr:housenumber":"417",
    "addr:postcode":"71854",
    "addr:street":"E 7Th St",
    "iso:country":"US",
    "sg:address":"417 E 7th St",
    "sg:city":"Texarkana",
    "sg:classifiers":[
        {
            "category":"Retail",
            "subcategory":"Self-service Laundry",
            "type":"Services"
        }
    ],
    "sg:phone":"+1 870 772 3290",
    "sg:postcode":"71854",
    "sg:province":"AR",
    "wof:name":"Ye Olde Wash House",
    "wof:placetype":"venue"
},
  "geometry": {"coordinates":[-94.03961700000001,33.428913],"type":"Point"}
}