{
  "type": "Feature",
  "properties": {
    "addr:full":"410 Magnolia Dr Bentonville AR 72712",
    "addr:housenumber":"410",
    "addr:postcode":"72712",
    "addr:street":"Magnolia Dr",
    "iso:country":"US",
    "sg:address":"410 Magnolia Dr",
    "sg:city":"Bentonville",
    "sg:classifiers":[
        {
            "category":"Real Estate",
            "subcategory":"Real Estate Agent",
            "type":"Services"
        }
    ],
    "sg:phone":"+1 479 464 7551",
    "sg:postcode":"72712",
    "sg:province":"AR",
    "wof:name":"Reynolds Enterprises",
    "wof:placetype":"venue"
},
  "geometry": {"coordinates":[-94.217067,36.377588],"type":"Point"}
}