{
  "type": "Feature",
  "properties": {
    "addr:full":"239 Hwy 425 S Monticello AR 71655",
    "addr:housenumber":"239",
    "addr:postcode":"71655",
    "addr:street":"Hwy 425 S",
    "iso:country":"US",
    "sg:address":"239 Hwy 425 S",
    "sg:city":"Monticello",
    "sg:classifiers":[
        {
            "category":"Manufacturing",
            "subcategory":"Food",
            "type":"Manufacturing & Wholesale Goods"
        }
    ],
    "sg:phone":"+1 870 367 2590",
    "sg:postcode":"71655",
    "sg:province":"AR",
    "sg:tags":[
        "product",
        "mfg"
    ],
    "wof:name":"Sara Lee Bakery Group Inc",
    "wof:placetype":"venue"
},
  "geometry": {"coordinates":[-91.80261900000001,33.62668],"type":"Point"}
}