{
  "type": "Feature",
  "properties": {
    "addr:full":"3101 Club Manor Dr Maumelle AR 72113",
    "addr:housenumber":"3101",
    "addr:postcode":"72113",
    "addr:street":"Club Manor Dr Maumelle",
    "iso:country":"US",
    "sg:address":"3101 Club Manor Dr",
    "sg:city":"Maumelle",
    "sg:classifiers":[
        {
            "category":"Personal",
            "subcategory":"Massage",
            "type":"Services"
        },
        {
            "category":"Personal",
            "subcategory":"Beauty Salon",
            "type":"Services"
        },
        {
            "category":"Personal",
            "subcategory":"Day Spa",
            "type":"Services"
        },
        {
            "category":"Personal",
            "subcategory":"Skin Care",
            "type":"Services"
        },
        {
            "category":"Personal",
            "subcategory":"Nail Salon",
            "type":"Services"
        }
    ],
    "sg:phone":"+1 501 588 3137",
    "sg:postcode":"72113",
    "sg:province":"AR",
    "sg:tags":[
        "therapist"
    ],
    "sg:website":"http://www.quyspa.com/main.asp",
    "wof:name":"Quy's Salon & Spa",
    "wof:placetype":"venue"
},
  "geometry": {"coordinates":[-92.4045,34.856831],"type":"Point"}
}