{
  "type": "Feature",
  "properties": {
    "addr:full":"1307 Dunn Cir Alexander AR 72002",
    "addr:housenumber":"1307",
    "addr:postcode":"72002",
    "addr:street":"Dunn Cir Alexander",
    "iso:country":"US",
    "sg:address":"1307 Dunn Cir",
    "sg:city":"Alexander",
    "sg:classifiers":[
        {
            "category":"Government",
            "subcategory":"Fire Station",
            "type":"Public Place"
        }
    ],
    "sg:phone":"+1 501 847 9391",
    "sg:postcode":"72002",
    "sg:province":"AR",
    "sg:tags":[
        "department"
    ],
    "wof:name":"Collegeville Volunteer Fire",
    "wof:placetype":"venue"
},
  "geometry": {"coordinates":[-92.475578,34.648321],"type":"Point"}
}