{
  "type": "Feature",
  "properties": {
    "iso:country":"US",
    "sg:address":"200 W Main St",
    "sg:city":"Blytheville",
    "sg:classifiers":[
        {
            "category":"Personal",
            "subcategory":"Beauty Salon",
            "type":"Services"
        }
    ],
    "sg:phone":"+1 870 763 7178",
    "sg:postcode":"72315",
    "sg:province":"AR",
    "sg:tags":[
        "shop"
    ],
    "wof:name":"Edna's Beauty Salon",
    "wof:placetype":"venue"
},
  "geometry": {"coordinates":[-89.905385,35.927519],"type":"Point"}
}