{
  "type": "Feature",
  "properties": {
    "iso:country":"US",
    "sg:address":"4428 Dawson Dr",
    "sg:city":"North Little Rock",
    "sg:classifiers":[
        {
            "category":"Personal",
            "subcategory":"Beauty Salon",
            "type":"Services"
        }
    ],
    "sg:phone":"+1 501 791 3799",
    "sg:postcode":"72116",
    "sg:province":"AR",
    "sg:tags":[
        "shop"
    ],
    "wof:name":"Dana Faulkner Studio",
    "wof:placetype":"venue"
},
  "geometry": {"coordinates":[-92.224458,34.800657],"type":"Point"}
}