{
  "type": "Feature",
  "properties": {
    "iso:country":"US",
    "sg:address":"805 W Centerton Blvd",
    "sg:city":"Centerton",
    "sg:classifiers":[
        {
            "category":"Personal",
            "type":"Services"
        },
        {
            "category":"Professional",
            "subcategory":"Art Services",
            "type":"Services"
        }
    ],
    "sg:phone":"+1 479 531 8766",
    "sg:postcode":"72719",
    "sg:province":"AR",
    "sg:tags":[
        "photography",
        "videography",
        "wedding"
    ],
    "wof:name":"Ozark Photography",
    "wof:placetype":"venue"
},
  "geometry": {"coordinates":[-94.293984,36.35862],"type":"Point"}
}