{
  "type": "Feature",
  "properties": {
    "addr:full":"908 S Main St Bald Knob AR 72010",
    "addr:housenumber":"908",
    "addr:postcode":"72010",
    "addr:street":"S Main St",
    "iso:country":"US",
    "sg:address":"908 S Main St",
    "sg:city":"Bald Knob",
    "sg:classifiers":[
        {
            "category":"Organizations",
            "subcategory":"Religious Organization",
            "type":"Services"
        }
    ],
    "sg:phone":"+1 501 724 0100",
    "sg:postcode":"72010",
    "sg:province":"AR",
    "sg:tags":[
        "church"
    ],
    "wof:name":"New Testament General Baptist",
    "wof:placetype":"venue"
},
  "geometry": {"coordinates":[-91.563361,35.306288],"type":"Point"}
}