{
  "type": "Feature",
  "properties": {
    "addr:full":"464 E Margaret Pl Fayetteville AR 72703",
    "addr:housenumber":"464",
    "addr:postcode":"72703",
    "addr:street":"E Margaret Pl",
    "iso:country":"US",
    "sg:address":"464 E Margaret Pl",
    "sg:city":"Fayetteville",
    "sg:classifiers":[
        {
            "category":"Professional",
            "type":"Services"
        }
    ],
    "sg:phone":"+1 479 575 9545",
    "sg:postcode":"72703",
    "sg:province":"AR",
    "wof:name":"Steve B Dubois",
    "wof:placetype":"venue"
},
  "geometry": {"coordinates":[-94.150458,36.108364],"type":"Point"}
}