{
  "type": "Feature",
  "properties": {
    "addr:full":"2621 W Main St Ste 4 Russellville AR 72801",
    "addr:housenumber":"2621",
    "addr:postcode":"72801",
    "addr:street":"W Main St Ste 4",
    "iso:country":"US",
    "sg:address":"2621 W Main St Ste 4",
    "sg:city":"Russellville",
    "sg:classifiers":[
        {
            "category":"Health Services",
            "subcategory":"Doctor",
            "type":"Services"
        }
    ],
    "sg:phone":"+1 479 967 3700",
    "sg:postcode":"72801",
    "sg:province":"AR",
    "sg:tags":[
        "psychologist"
    ],
    "wof:name":"Ott Don Psy D",
    "wof:placetype":"venue"
},
  "geometry": {"coordinates":[-93.159108,35.285593],"type":"Point"}
}