{
  "type": "Feature",
  "properties": {
    "iso:country":"US",
    "sg:address":"1101 E Main St",
    "sg:city":"Flippin",
    "sg:classifiers":[
        {
            "category":"Real Estate",
            "subcategory":"Real Estate Services",
            "type":"Services"
        },
        {
            "category":"Real Estate",
            "subcategory":"Real Estate Operator",
            "type":"Services"
        }
    ],
    "sg:phone":"+1 870 453 3962",
    "sg:postcode":"72634",
    "sg:province":"AR",
    "sg:tags":[
        "vacancy",
        "apartment",
        "rental",
        "finder",
        "listing"
    ],
    "wof:name":"Grove Cottage Estates",
    "wof:placetype":"venue"
},
  "geometry": {"coordinates":[-92.583183,36.272091],"type":"Point"}
}