{
  "type": "Feature",
  "properties": {
    "addr:full":"309 W 1st Ave Crossett AR 71635",
    "addr:housenumber":"309",
    "addr:postcode":"71635",
    "addr:street":"W 1St Ave",
    "iso:country":"US",
    "sg:address":"309 W 1st Ave",
    "sg:city":"Crossett",
    "sg:classifiers":[
        {
            "category":"Home & Garden",
            "subcategory":"Building Materials",
            "type":"Retail Goods"
        }
    ],
    "sg:phone":"+1 870 364 3245",
    "sg:postcode":"71635",
    "sg:province":"AR",
    "sg:tags":[
        "covering",
        "wallcoverings-installation",
        "wallpaper",
        "contractor",
        "paint",
        "improvement",
        "painting"
    ],
    "sg:website":"http://national.citysearch.com/profile/external/1511796/crossett_ar/sherwin_williams.html?publisher=yellowpages&reference_id=1&placement=ypwebsitemip",
    "wof:name":"Sherwin-Williams",
    "wof:placetype":"venue"
},
  "geometry": {"coordinates":[-91.964416,33.135288],"type":"Point"}
}