{
  "type": "Feature",
  "properties": {
    "iso:country":"US",
    "sg:address":"89 E Priddy St",
    "sg:city":"Magazine",
    "sg:classifiers":[
        {
            "category":"Banks & Credit Unions",
            "subcategory":"Bank",
            "type":"Services"
        }
    ],
    "sg:phone":"+1 479 969 8102",
    "sg:postcode":"72943",
    "sg:province":"AR",
    "wof:name":"First Western Bank",
    "wof:placetype":"venue"
},
  "geometry": {"coordinates":[-93.806208,35.149897],"type":"Point"}
}