{
  "type": "Feature",
  "properties": {
    "addr:full":"3303 Pinnacle Hills Parkway Rogers AR 72758",
    "addr:housenumber":"3303",
    "addr:postcode":"72758",
    "addr:street":"Pinnacle Hills Parkway",
    "iso:country":"US",
    "sg:address":"3303 Pinnacle Hills Parkway",
    "sg:city":"Rogers",
    "sg:classifiers":[
        {
            "category":"Personal",
            "subcategory":"Day Spa",
            "type":"Services"
        }
    ],
    "sg:phone":"+1 479 845 3293",
    "sg:postcode":"72758",
    "sg:province":"AR",
    "sg:website":"www.embassysuitesnwa.com",
    "wof:name":"Spa Botanica",
    "wof:placetype":"venue"
},
  "geometry": {"coordinates":[-94.186435,36.309886],"type":"Point"}
}