{
  "type": "Feature",
  "properties": {
    "iso:country":"US",
    "sg:address":"601 US Hwy 71",
    "sg:city":"Mena",
    "sg:classifiers":[
        {
            "category":"Retail",
            "subcategory":"Portrait Studio",
            "type":"Services"
        }
    ],
    "sg:phone":"+1 479 394 8000",
    "sg:postcode":"71953",
    "sg:province":"AR",
    "sg:tags":[
        "photographer",
        "photo"
    ],
    "wof:name":"Cunninghams Photography",
    "wof:placetype":"venue"
},
  "geometry": {"coordinates":[-94.223818,34.586471],"type":"Point"}
}