{
  "type": "Feature",
  "properties": {
    "iso:country":"US",
    "sg:address":"39 Capshaw Rd",
    "sg:city":"Rosie",
    "sg:classifiers":[
        {
            "category":"Professional",
            "subcategory":"Business Services",
            "type":"Services"
        },
        {
            "category":"Government",
            "subcategory":"Post Office",
            "type":"Public Place"
        }
    ],
    "sg:phone":"+1 800 275 8777",
    "sg:postcode":"72571",
    "sg:province":"AR",
    "sg:tags":[
        "mail",
        "shipping"
    ],
    "sg:website":"http://www.usps.com",
    "wof:name":"USPS - United States Post Office - Rosie Main Office",
    "wof:placetype":"venue"
},
  "geometry": {"coordinates":[-91.538145,35.668541],"type":"Point"}
}