{
  "type": "Feature",
  "properties": {
    "iso:country":"US",
    "sg:address":"113 W Front St",
    "sg:city":"Portia",
    "sg:classifiers":[
        {
            "category":"Professional",
            "subcategory":"Business Services",
            "type":"Services"
        },
        {
            "category":"Government",
            "subcategory":"Post Office",
            "type":"Public Place"
        }
    ],
    "sg:phone":"+1 800 275 8777",
    "sg:postcode":"72457",
    "sg:province":"AR",
    "sg:tags":[
        "mail",
        "shipping"
    ],
    "sg:website":"http://www.usps.com",
    "wof:name":"USPS - United States Post Office - Portia Main Office",
    "wof:placetype":"venue"
},
  "geometry": {"coordinates":[-91.067696,36.086686],"type":"Point"}
}