{
  "type": "Feature",
  "properties": {
    "iso:country":"US",
    "sg:address":"5204 Pleasant Ln",
    "sg:city":"Rogers",
    "sg:classifiers":[
        {
            "category":"Restaurant",
            "type":"Food & Drink"
        }
    ],
    "sg:phone":"+1 479 636 9582",
    "sg:postcode":"72758",
    "sg:province":"AR",
    "sg:tags":[
        "eating"
    ],
    "wof:name":"Blimpie",
    "wof:placetype":"venue"
},
  "geometry": {"coordinates":[-94.16939600000001,36.285925],"type":"Point"}
}