{
  "type": "Feature",
  "properties": {
    "iso:country":"US",
    "sg:address":"2115 N West Ave",
    "sg:city":"El Dorado",
    "sg:classifiers":[
        {
            "category":"Shopping",
            "subcategory":"Department Store",
            "type":"Retail Goods"
        }
    ],
    "sg:phone":"+1 870 862 4043",
    "sg:postcode":"71730",
    "sg:province":"AR",
    "wof:name":"Wal-Mart",
    "wof:placetype":"venue"
},
  "geometry": {"coordinates":[-92.66545499999999,33.23136],"type":"Point"}
}