{
  "type": "Feature",
  "properties": {
    "iso:country":"US",
    "sg:address":"864 Co Rd 773",
    "sg:city":"Jonesboro",
    "sg:classifiers":[
        {
            "category":"Retail",
            "subcategory":"Repair Shop",
            "type":"Services"
        }
    ],
    "sg:phone":"+1 870 933 8841",
    "sg:postcode":"72401",
    "sg:province":"AR",
    "sg:tags":[
        "taxidermist"
    ],
    "wof:name":"Wilson Taxidermy",
    "wof:placetype":"venue"
},
  "geometry": {"coordinates":[-90.688215,35.930125],"type":"Point"}
}