{
  "type": "Feature",
  "properties": {
    "addr:full":"420 W Broadway West Memphis AR 72301",
    "addr:housenumber":"420",
    "addr:postcode":"72301",
    "addr:street":"W Broadway",
    "iso:country":"US",
    "sg:address":"420 W Broadway",
    "sg:city":"West Memphis",
    "sg:classifiers":[
        {
            "category":"Personal",
            "subcategory":"Beauty Salon",
            "type":"Services"
        }
    ],
    "sg:phone":"+1 870 732 6202",
    "sg:postcode":"72301",
    "sg:province":"AR",
    "wof:name":"Cuts Unlimited",
    "wof:placetype":"venue"
},
  "geometry": {"coordinates":[-90.19392499999999,35.146281],"type":"Point"}
}