{
  "type": "Feature",
  "properties": {
    "iso:country":"US",
    "sg:address":"420 W Broadway",
    "sg:city":"West Memphis",
    "sg:classifiers":[
        {
            "category":"Personal",
            "subcategory":"Beauty Salon",
            "type":"Services"
        }
    ],
    "sg:phone":"+1 870 732 6202",
    "sg:postcode":"72301",
    "sg:province":"AR",
    "wof:name":"Cuts Unlimited",
    "wof:placetype":"venue"
},
  "geometry": {"coordinates":[-90.193925,35.146281],"type":"Point"}
}