{
  "type": "Feature",
  "properties": {
    "iso:country":"US",
    "sg:address":"105 State Hwy 297",
    "sg:city":"Dyess",
    "sg:classifiers":[
        {
            "category":"Government",
            "subcategory":"Post Office",
            "type":"Public Place"
        }
    ],
    "sg:phone":"+1 870 764 2300",
    "sg:postcode":"72330",
    "sg:province":"AR",
    "wof:name":"US Post Office",
    "wof:placetype":"venue"
},
  "geometry": {"coordinates":[-90.21393,35.589971],"type":"Point"}
}