{
  "type": "Feature",
  "properties": {
    "iso:country":"US",
    "sg:address":"924 Spradley Rd",
    "sg:city":"Van Buren",
    "sg:classifiers":[
        {
            "category":"Building & Trades",
            "subcategory":"Construction",
            "type":"Services"
        }
    ],
    "sg:phone":"+1 479 471 0636",
    "sg:postcode":"72956",
    "sg:province":"AR",
    "sg:tags":[
        "house",
        "construct",
        "contractor"
    ],
    "wof:name":"McCarvilles Painting & Roofing",
    "wof:placetype":"venue"
},
  "geometry": {"coordinates":[-94.313948,35.445255],"type":"Point"}
}