{
  "type": "Feature",
  "properties": {
    "iso:country":"US",
    "sg:address":"106 E Center St",
    "sg:city":"Sheridan",
    "sg:classifiers":[
        {
            "category":"Personal",
            "subcategory":"Tanning Parlor",
            "type":"Services"
        }
    ],
    "sg:phone":"+1 870 942 8393",
    "sg:postcode":"72150",
    "sg:province":"AR",
    "sg:tags":[
        "salon"
    ],
    "wof:name":"Buffie's",
    "wof:placetype":"venue"
},
  "geometry": {"coordinates":[-92.40024699999999,34.306808],"type":"Point"}
}