{
  "type": "Feature",
  "properties": {
    "addr:full":"315 Cherry St Helena AR 72342",
    "addr:housenumber":"315",
    "addr:postcode":"72342",
    "addr:street":"Cherry St Helena",
    "iso:country":"US",
    "sg:address":"315 Cherry St",
    "sg:city":"Helena",
    "sg:classifiers":[
        {
            "category":"Shopping",
            "subcategory":"Used Merchandise",
            "type":"Retail Goods"
        }
    ],
    "sg:phone":"+1 870 338 8228",
    "sg:postcode":"72342",
    "sg:province":"AR",
    "sg:tags":[
        "shop",
        "consignment"
    ],
    "wof:name":"Myrna's Klassic Kollections",
    "wof:placetype":"venue"
},
  "geometry": {"coordinates":[-90.586302,34.525726],"type":"Point"}
}