{
  "type": "Feature",
  "properties": {
    "addr:full":"1515 Nelms St Jonesboro AR 72401",
    "addr:housenumber":"1515",
    "addr:postcode":"72401",
    "addr:street":"Nelms St",
    "iso:country":"US",
    "sg:address":"1515 Nelms St",
    "sg:city":"Jonesboro",
    "sg:classifiers":[
        {
            "category":"Professional",
            "type":"Services"
        }
    ],
    "sg:phone":"+1 870 935 4725",
    "sg:postcode":"72401",
    "sg:province":"AR",
    "wof:name":"Frazier Transporation Inc",
    "wof:placetype":"venue"
},
  "geometry": {"coordinates":[-90.662679,35.826727],"type":"Point"}
}