{
  "type": "Feature",
  "properties": {
    "iso:country":"US",
    "sg:address":"19175 State Hwy 74",
    "sg:city":"Elkins",
    "sg:classifiers":[
        {
            "category":"Restaurant",
            "type":"Food & Drink"
        }
    ],
    "sg:phone":"+1 479 582 2232",
    "sg:postcode":"72727",
    "sg:province":"AR",
    "sg:tags":[
        "eating"
    ],
    "wof:name":"Rolling Pin Cafe",
    "wof:placetype":"venue"
},
  "geometry": {"coordinates":[-94.009332,36.026515],"type":"Point"}
}