{
  "type": "Feature",
  "properties": {
    "iso:country":"US",
    "sg:address":"468 Passion Play Rd",
    "sg:city":"Eureka Springs",
    "sg:classifiers":[
        {
            "category":"Travel",
            "subcategory":"Campground",
            "type":"Entertainment"
        }
    ],
    "sg:phone":"+1 479 253 7385",
    "sg:postcode":"72632",
    "sg:province":"AR",
    "wof:name":"Wanderlust Rv Park",
    "wof:placetype":"venue"
},
  "geometry": {"coordinates":[-93.709037,36.392177],"type":"Point"}
}