{
  "type": "Feature",
  "properties": {
    "addr:full":"313 N Market St Benton AR 72015",
    "addr:housenumber":"313",
    "addr:postcode":"72015",
    "addr:street":"N Market St",
    "iso:country":"US",
    "sg:address":"313 N Market St",
    "sg:city":"Benton",
    "sg:classifiers":[
        {
            "category":"Professional",
            "subcategory":"Engineering",
            "type":"Services"
        }
    ],
    "sg:phone":"+1 501 776 3400",
    "sg:postcode":"72015",
    "sg:province":"AR",
    "sg:tags":[
        "remediation",
        "environmental",
        "as",
        "operates",
        "engineer"
    ],
    "wof:name":"Secor International Inc",
    "wof:placetype":"venue"
},
  "geometry": {"coordinates":[-92.58806800000001,34.566523],"type":"Point"}
}