{
  "type": "Feature",
  "properties": {
    "iso:country":"US",
    "sg:address":"11096 Thunder Rd",
    "sg:city":"Fayetteville",
    "sg:classifiers":[
        {
            "category":"Shopping",
            "subcategory":"Computers & Home Electronics",
            "type":"Retail Goods"
        }
    ],
    "sg:phone":"+1 479 443 7059",
    "sg:postcode":"72701",
    "sg:province":"AR",
    "sg:tags":[
        "equipment",
        "dealer"
    ],
    "wof:name":"Economy On-Site Svc Inc",
    "wof:placetype":"venue"
},
  "geometry": {"coordinates":[-94.063804,36.000931],"type":"Point"}
}