{
  "type": "Feature",
  "properties": {
    "iso:country":"US",
    "sg:address":"801 Jackson St",
    "sg:city":"Berryville",
    "sg:classifiers":[
        {
            "category":"Building & Trades",
            "subcategory":"Construction",
            "type":"Services"
        }
    ],
    "sg:phone":"+1 870 423 6074",
    "sg:postcode":"72616",
    "sg:province":"AR",
    "sg:tags":[
        "house"
    ],
    "wof:name":"Mosblech Home",
    "wof:placetype":"venue"
},
  "geometry": {"coordinates":[-93.564454,36.375085],"type":"Point"}
}