{
  "type": "Feature",
  "properties": {
    "iso:country":"US",
    "sg:address":"854 Maple Springs Rd",
    "sg:city":"Russellville",
    "sg:classifiers":[
        {
            "category":"Farming",
            "subcategory":"Livestock Farm",
            "type":"Manufacturing & Wholesale Goods"
        }
    ],
    "sg:phone":"+1 479 967 1751",
    "sg:postcode":"72823",
    "sg:province":"AR",
    "sg:tags":[
        "feedlot",
        "hog",
        "or",
        "beef",
        "cattle"
    ],
    "wof:name":"Mountain Valley Farm",
    "wof:placetype":"venue"
},
  "geometry": {"coordinates":[-93.017302,35.305181],"type":"Point"}
}