{
  "type": "Feature",
  "properties": {
    "iso:country":"US",
    "sg:address":"144 Vineyard Hill Ln",
    "sg:city":"Malvern",
    "sg:classifiers":[
        {
            "category":"Autos & Motor Vehicles",
            "subcategory":"Fuel & Gas Station",
            "type":"Retail Goods"
        }
    ],
    "sg:phone":"+1 501 337 7721",
    "sg:postcode":"72104",
    "sg:province":"AR",
    "sg:tags":[
        "station",
        "gasoline"
    ],
    "wof:name":"Enterprises In BP Outdoor",
    "wof:placetype":"venue"
},
  "geometry": {"coordinates":[-92.777872,34.309055],"type":"Point"}
}