{
  "type": "Feature",
  "properties": {
    "addr:full":"112 N Bettis St Pocahontas AR 72455",
    "addr:housenumber":"112",
    "addr:postcode":"72455",
    "addr:street":"N Bettis St",
    "iso:country":"US",
    "sg:address":"112 N Bettis St",
    "sg:city":"Pocahontas",
    "sg:classifiers":[
        {
            "category":"Banks & Credit Unions",
            "subcategory":"Investment Brokerage",
            "type":"Services"
        }
    ],
    "sg:phone":"+1 870 892 1199",
    "sg:postcode":"72455",
    "sg:province":"AR",
    "sg:tags":[
        "stock",
        "bond"
    ],
    "wof:name":"Mcnabb & Black Financial Svc",
    "wof:placetype":"venue"
},
  "geometry": {"coordinates":[-90.969962,36.260951],"type":"Point"}
}