{
  "type": "Feature",
  "properties": {
    "iso:country":"US",
    "sg:address":"1429 Merrill Dr",
    "sg:city":"Little Rock",
    "sg:classifiers":[
        {
            "category":"Real Estate",
            "subcategory":"Real Estate Agent",
            "type":"Services"
        }
    ],
    "sg:phone":"+1 501 221 3485",
    "sg:postcode":"72211",
    "sg:province":"AR",
    "wof:name":"ERA Armstrong Team Realtors",
    "wof:placetype":"venue"
},
  "geometry": {"coordinates":[-92.396308,34.767582],"type":"Point"}
}