{
  "type": "Feature",
  "properties": {
    "addr:full":"3396 N Futrall Dr Fayetteville AR 72703",
    "addr:housenumber":"3396",
    "addr:postcode":"72703",
    "addr:street":"N Futrall Dr",
    "iso:country":"US",
    "sg:address":"3396 N Futrall Dr",
    "sg:city":"Fayetteville",
    "sg:classifiers":[
        {
            "category":"Social Services",
            "type":"Services"
        }
    ],
    "sg:phone":"+1 479 582 9309",
    "sg:postcode":"72703",
    "sg:province":"AR",
    "wof:name":"Washington County Wic Store 2",
    "wof:placetype":"venue"
},
  "geometry": {"coordinates":[-94.163366,36.11067],"type":"Point"}
}