{
  "type": "Feature",
  "properties": {
    "addr:full":"20340 Blue Springs Rd Springdale AR 72764",
    "addr:housenumber":"20340",
    "addr:postcode":"72764",
    "addr:street":"Blue Springs Rd",
    "iso:country":"US",
    "sg:address":"20340 Blue Springs Rd",
    "sg:city":"Springdale",
    "sg:classifiers":[
        {
            "category":"Transit Center",
            "subcategory":"Freight",
            "type":"Transportation"
        }
    ],
    "sg:phone":"+1 479 751 7587",
    "sg:postcode":"72764",
    "sg:province":"AR",
    "sg:tags":[
        "trucking-light",
        "hauling"
    ],
    "wof:name":"Patrick W Mcfadin",
    "wof:placetype":"venue"
},
  "geometry": {"coordinates":[-94.006186,36.165135],"type":"Point"}
}