{
  "type": "Feature",
  "properties": {
    "iso:country":"US",
    "sg:address":"3613 Colfax Way",
    "sg:city":"Greenwood",
    "sg:classifiers":[
        {
            "category":"Social Services",
            "type":"Services"
        }
    ],
    "sg:phone":"+1 601 807 3951",
    "sg:postcode":"72936",
    "sg:province":"AR",
    "wof:name":"Help For The Homeless",
    "wof:placetype":"venue"
},
  "geometry": {"coordinates":[-94.198398,35.211076],"type":"Point"}
}