{
  "type": "Feature",
  "properties": {
    "iso:country":"US",
    "sg:address":"7714 US Hwy 271",
    "sg:city":"Fort Smith",
    "sg:classifiers":[
        {
            "category":"Manufacturing",
            "subcategory":"Printing",
            "type":"Manufacturing & Wholesale Goods"
        }
    ],
    "sg:phone":"+1 479 646 1400",
    "sg:postcode":"72908",
    "sg:province":"AR",
    "sg:tags":[
        "commercial"
    ],
    "wof:name":"Farr Printing Inc",
    "wof:placetype":"venue"
},
  "geometry": {"coordinates":[-94.422776,35.310946],"type":"Point"}
}