{
  "type": "Feature",
  "properties": {
    "iso:country":"US",
    "sg:address":"1003 W Central Ave",
    "sg:city":"Harrison",
    "sg:classifiers":[
        {
            "category":"Professional",
            "subcategory":"Business Services",
            "type":"Services"
        }
    ],
    "sg:phone":"+1 870 743 1682",
    "sg:postcode":"72601",
    "sg:province":"AR",
    "sg:tags":[
        "agent",
        "real estate"
    ],
    "wof:name":"Grisham Family Ltd Partnership",
    "wof:placetype":"venue"
},
  "geometry": {"coordinates":[-93.11842300000001,36.228756],"type":"Point"}
}