{
  "type": "Feature",
  "properties": {
    "addr:full":"571 Hwy 64 E Conway AR 72058",
    "addr:housenumber":"571",
    "addr:postcode":"72058",
    "addr:street":"Hwy 64 E",
    "iso:country":"US",
    "sg:address":"571 Hwy 64 E",
    "sg:city":"Conway",
    "sg:classifiers":[
        {
            "category":"Home & Garden",
            "subcategory":"Garden Supply",
            "type":"Retail Goods"
        }
    ],
    "sg:phone":"+1 501 327 2362",
    "sg:postcode":"72058",
    "sg:province":"AR",
    "sg:tags":[
        "nurseryman"
    ],
    "wof:name":"Conway Nursery Inc",
    "wof:placetype":"venue"
},
  "geometry": {"coordinates":[-92.320744,35.08029],"type":"Point"}
}