{
  "type": "Feature",
  "properties": {
    "addr:full":"301 E 1st Ave Crossett AR 71635",
    "addr:housenumber":"301",
    "addr:postcode":"71635",
    "addr:street":"E 1St Ave",
    "iso:country":"US",
    "sg:address":"301 E 1st Ave",
    "sg:city":"Crossett",
    "sg:classifiers":[
        {
            "category":"Retail",
            "subcategory":"Auto Rental",
            "type":"Services"
        }
    ],
    "sg:phone":"+1 870 364 7439",
    "sg:postcode":"71635",
    "sg:province":"AR",
    "sg:tags":[
        "passenger",
        "car"
    ],
    "wof:name":"South Arkansas Auto Rentals",
    "wof:placetype":"venue"
},
  "geometry": {"coordinates":[-91.958882,33.135377],"type":"Point"}
}