{
  "type": "Feature",
  "properties": {
    "addr:full":"1973 Lancaster Dr Springdale AR 72762",
    "addr:housenumber":"1973",
    "addr:postcode":"72762",
    "addr:street":"Lancaster Dr",
    "iso:country":"US",
    "sg:address":"1973 Lancaster Dr",
    "sg:city":"Springdale",
    "sg:classifiers":[
        {
            "category":"Shopping",
            "subcategory":"Florist",
            "type":"Retail Goods"
        }
    ],
    "sg:phone":"+1 479 872 8437",
    "sg:postcode":"72762",
    "sg:province":"AR",
    "wof:name":"Hills Floral Group",
    "wof:placetype":"venue"
},
  "geometry": {"coordinates":[-94.151152,36.224834],"type":"Point"}
}