{
  "type": "Feature",
  "properties": {
    "iso:country":"US",
    "sg:address":"3855 Weir Rd",
    "sg:city":"Fayetteville",
    "sg:classifiers":[
        {
            "category":"Building & Trades",
            "subcategory":"Electrical",
            "type":"Services"
        }
    ],
    "sg:phone":"+1 479 521 0710",
    "sg:postcode":"72704",
    "sg:province":"AR",
    "sg:tags":[
        "electrical",
        "electric",
        "contractor"
    ],
    "wof:name":"Mc Farland Electric Inc",
    "wof:placetype":"venue"
},
  "geometry": {"coordinates":[-94.213449,36.110652],"type":"Point"}
}