{
  "type": "Feature",
  "properties": {
    "iso:country":"US",
    "sg:address":"2646 E Joyce Blvd",
    "sg:city":"Fayetteville",
    "sg:classifiers":[
        {
            "category":"Health Services",
            "subcategory":"Dentist",
            "type":"Services"
        }
    ],
    "sg:phone":"+1 479 443 8009",
    "sg:postcode":"72703",
    "sg:province":"AR",
    "wof:name":"Barnes Kellie E DDS",
    "wof:placetype":"venue"
},
  "geometry": {"coordinates":[-94.12300399999999,36.119906],"type":"Point"}
}