{
  "type": "Feature",
  "properties": {
    "addr:full":"11000 Brockington Rd Sherwood AR 72120",
    "addr:postcode":"11000;72120",
    "addr:street":"Brockington Rd",
    "iso:country":"US",
    "sg:address":"11000 Brockington Rd",
    "sg:city":"Sherwood",
    "sg:classifiers":[
        {
            "category":"Building & Trades",
            "subcategory":"Construction",
            "type":"Services"
        }
    ],
    "sg:phone":"+1 501 470 9992",
    "sg:postcode":"72120",
    "sg:province":"AR",
    "sg:tags":[
        "general",
        "contractor"
    ],
    "wof:name":"Jci Construction Inc",
    "wof:placetype":"venue"
},
  "geometry": {"coordinates":[-92.197502,34.852469],"type":"Point"}
}