{
  "type": "Feature",
  "properties": {
    "addr:full":"12800 Highway 35 S Rison AR 71665",
    "addr:housenumber":"12800",
    "addr:postcode":"71665",
    "addr:street":"Highway 35 S Rison",
    "iso:country":"US",
    "sg:address":"12800 Highway 35 S",
    "sg:city":"Rison",
    "sg:classifiers":[
        {
            "category":"Professional",
            "subcategory":"Engineering",
            "type":"Services"
        }
    ],
    "sg:phone":"+1 870 357 8074",
    "sg:postcode":"71665",
    "sg:province":"AR",
    "sg:tags":[
        "aircraft",
        "maintenance"
    ],
    "wof:name":"Banks Small Engine Repair",
    "wof:placetype":"venue"
},
  "geometry": {"coordinates":[-92.05690300000001,33.827883],"type":"Point"}
}