{
  "type": "Feature",
  "properties": {
    "iso:country":"US",
    "sg:address":"3801 W Sunset Ave",
    "sg:city":"Springdale",
    "sg:classifiers":[
        {
            "category":"Professional",
            "subcategory":"Computer Services",
            "type":"Services"
        }
    ],
    "sg:phone":"+1 479 751 3853",
    "sg:postcode":"72762",
    "sg:province":"AR",
    "sg:tags":[
        "website",
        "design"
    ],
    "sg:website":"www.nwamenus.com",
    "wof:name":"NWA Menus",
    "wof:placetype":"venue"
},
  "geometry": {"coordinates":[-94.17425900000001,36.175092],"type":"Point"}
}