{
  "type": "Feature",
  "properties": {
    "iso:country":"US",
    "sg:address":"1305 E Oak St",
    "sg:city":"Conway",
    "sg:classifiers":[
        {
            "category":"Autos & Motor Vehicles",
            "subcategory":"Fuel & Gas Station",
            "type":"Retail Goods"
        }
    ],
    "sg:phone":"+1 501 513 9923",
    "sg:postcode":"72032",
    "sg:province":"AR",
    "sg:tags":[
        "oil"
    ],
    "wof:name":"Satterfield Station",
    "wof:placetype":"venue"
},
  "geometry": {"coordinates":[-92.410667,35.091205],"type":"Point"}
}