{
  "type": "Feature",
  "properties": {
    "iso:country":"US",
    "sg:address":"2901 Zion Rd",
    "sg:city":"Fayetteville",
    "sg:classifiers":[
        {
            "category":"Retail",
            "subcategory":"Laundry & Dry Cleaning",
            "type":"Services"
        }
    ],
    "sg:phone":"+1 479 442 5303",
    "sg:postcode":"72703",
    "sg:province":"AR",
    "sg:tags":[
        "cleaners"
    ],
    "wof:name":"Four Seasons Cleaners-Laundry",
    "wof:placetype":"venue"
},
  "geometry": {"coordinates":[-94.119959,36.129384],"type":"Point"}
}