{
  "type": "Feature",
  "properties": {
    "iso:country":"US",
    "sg:address":"26 E Center St",
    "sg:city":"Fayetteville",
    "sg:classifiers":[
        {
            "category":"Banks & Credit Unions",
            "subcategory":"Financial Services",
            "type":"Services"
        }
    ],
    "sg:phone":"+1 479 521 5300",
    "sg:postcode":"72701",
    "sg:province":"AR",
    "sg:tags":[
        "profit",
        "sharing",
        "plan",
        "pension"
    ],
    "wof:name":"Greenwood & Associates Inc",
    "wof:placetype":"venue"
},
  "geometry": {"coordinates":[-94.159254,36.062609],"type":"Point"}
}