{
  "type": "Feature",
  "properties": {
    "iso:country":"US",
    "sg:address":"4779 N Saint Louis St",
    "sg:city":"Batesville",
    "sg:classifiers":[
        {
            "category":"Building & Trades",
            "subcategory":"Electrical",
            "type":"Services"
        }
    ],
    "sg:phone":"+1 888 827 3322",
    "sg:postcode":"72501",
    "sg:province":"AR",
    "sg:tags":[
        "electrical",
        "contractor"
    ],
    "wof:name":"Electric Company",
    "wof:placetype":"venue"
},
  "geometry": {"coordinates":[-91.577872,35.84775],"type":"Point"}
}