{
  "type": "Feature",
  "properties": {
    "iso:country":"US",
    "sg:address":"1800 N Missouri St",
    "sg:city":"West Memphis",
    "sg:classifiers":[
        {
            "category":"Shopping",
            "subcategory":"Discount & Variety Stores",
            "type":"Retail Goods"
        }
    ],
    "sg:phone":"+1 870 702 6460",
    "sg:postcode":"72301",
    "sg:province":"AR",
    "wof:name":"Dollar Tree",
    "wof:placetype":"venue"
},
  "geometry": {"coordinates":[-90.184681,35.165563],"type":"Point"}
}