{
  "type": "Feature",
  "properties": {
    "iso:country":"US",
    "sg:address":"5219 John F Kennedy Blvd",
    "sg:city":"Sherwood",
    "sg:classifiers":[
        {
            "category":"Insurance",
            "subcategory":"Insurance Agent",
            "type":"Services"
        }
    ],
    "sg:phone":"+1 501 753 6388",
    "sg:postcode":"72116",
    "sg:province":"AR",
    "wof:name":"James D Scott Insurance Inc",
    "wof:placetype":"venue"
},
  "geometry": {"coordinates":[-92.25290699999999,34.804797],"type":"Point"}
}