{
  "type": "Feature",
  "properties": {
    "iso:country":"US",
    "sg:address":"605 Beechwood St",
    "sg:city":"Little Rock",
    "sg:classifiers":[
        {
            "category":"Restaurant",
            "type":"Food & Drink"
        }
    ],
    "sg:phone":"+1 501 603 0238",
    "sg:postcode":"72205",
    "sg:province":"AR",
    "sg:tags":[
        "eating"
    ],
    "wof:name":"Ciao Bacci",
    "wof:placetype":"venue"
},
  "geometry": {"coordinates":[-92.32410299999999,34.757616],"type":"Point"}
}