{
  "type": "Feature",
  "properties": {
    "addr:full":"9100 Highway 63 N Bono AR 72416",
    "addr:housenumber":"9100",
    "addr:postcode":"72416",
    "addr:street":"Highway 63 N",
    "iso:country":"US",
    "sg:address":"9100 Highway 63 N",
    "sg:city":"Bono",
    "sg:classifiers":[
        {
            "category":"Building & Trades",
            "subcategory":"Construction",
            "type":"Services"
        }
    ],
    "sg:phone":"+1 870 935 6125",
    "sg:postcode":"72416",
    "sg:province":"AR",
    "sg:tags":[
        "consultant",
        "industrial",
        "contractors-commercial"
    ],
    "wof:name":"Mcm Contractors Inc",
    "wof:placetype":"venue"
},
  "geometry": {"coordinates":[-90.82307,35.949938],"type":"Point"}
}