{
  "type": "Feature",
  "properties": {
    "iso:country":"US",
    "sg:address":"11 Dogwood Dr",
    "sg:city":"Newport",
    "sg:classifiers":[
        {
            "category":"Professional",
            "subcategory":"Lawyer & Legal Services",
            "type":"Services"
        }
    ],
    "sg:phone":"+1 870 523 3300",
    "sg:postcode":"72112",
    "sg:province":"AR",
    "wof:name":"Phillip Ompfs Hout",
    "wof:placetype":"venue"
},
  "geometry": {"coordinates":[-91.2636,35.60159],"type":"Point"}
}