{
  "type": "Feature",
  "properties": {
    "iso:country":"US",
    "sg:address":"3719 Mounds Rd",
    "sg:city":"Proctor",
    "sg:classifiers":[
        {
            "category":"Manufacturing",
            "subcategory":"Glass & Minerals",
            "type":"Manufacturing & Wholesale Goods"
        }
    ],
    "sg:phone":"+1 870 735 7932",
    "sg:postcode":"72376",
    "sg:province":"AR",
    "sg:tags":[
        "treated",
        "or"
    ],
    "sg:website":"www.generalshale.com",
    "wof:name":"Arkalite",
    "wof:placetype":"venue"
},
  "geometry": {"coordinates":[-90.260229,35.116445],"type":"Point"}
}