{
  "type": "Feature",
  "properties": {
    "addr:full":"1220 N College Ave Fayetteville AR 72703",
    "addr:housenumber":"1220",
    "addr:postcode":"72703",
    "addr:street":"N College Ave",
    "iso:country":"US",
    "sg:address":"1220 N College Ave",
    "sg:city":"Fayetteville",
    "sg:classifiers":[
        {
            "category":"Restaurant",
            "type":"Food & Drink"
        },
        {
            "category":"Shopping",
            "subcategory":"Party Supplies",
            "type":"Retail Goods"
        },
        {
            "category":"Food & Beverages",
            "subcategory":"Bakery",
            "type":"Retail Goods"
        },
        {
            "category":"Bakery",
            "type":"Food & Drink"
        }
    ],
    "sg:phone":"+1 479 442 2166",
    "sg:postcode":"72703",
    "sg:province":"AR",
    "sg:tags":[
        "bakers-wholesale",
        "wedding"
    ],
    "sg:website":"http://www.ricksbakery.com",
    "wof:name":"Rick's Bakery",
    "wof:placetype":"venue"
},
  "geometry": {"coordinates":[-94.156944,36.078938],"type":"Point"}
}