{
  "type": "Feature",
  "properties": {
    "iso:country":"US",
    "sg:address":"5920 S Country Club Blvd",
    "sg:city":"Little Rock",
    "sg:classifiers":[
        {
            "category":"Professional",
            "subcategory":"Management & Consulting",
            "type":"Services"
        }
    ],
    "sg:phone":"+1 501 660 4172",
    "sg:postcode":"72207",
    "sg:province":"AR",
    "sg:tags":[
        "consultant",
        "training"
    ],
    "wof:name":"National Education Training",
    "wof:placetype":"venue"
},
  "geometry": {"coordinates":[-92.33935,34.771779],"type":"Point"}
}