{
  "type": "Feature",
  "properties": {
    "iso:country":"US",
    "sg:address":"301 Main St",
    "sg:city":"Crossett",
    "sg:classifiers":[
        {
            "category":"Shopping",
            "subcategory":"Pharmacy",
            "type":"Retail Goods"
        }
    ],
    "sg:phone":"+1 870 364 3303",
    "sg:postcode":"71635",
    "sg:province":"AR",
    "wof:name":"City Rexall Drug Store",
    "wof:placetype":"venue"
},
  "geometry": {"coordinates":[-91.961518,33.132502],"type":"Point"}
}