{
  "type": "Feature",
  "properties": {
    "addr:full":"8129 Cord Rd Cord AR 72524",
    "addr:housenumber":"8129",
    "addr:postcode":"72524",
    "addr:street":"Cord Rd",
    "iso:country":"US",
    "sg:address":"8129 Cord Rd",
    "sg:city":"Cord",
    "sg:classifiers":[
        {
            "category":"Organizations",
            "subcategory":"Religious Organization",
            "type":"Services"
        }
    ],
    "sg:phone":"+1 870 799 8096",
    "sg:postcode":"72524",
    "sg:province":"AR",
    "sg:tags":[
        "church"
    ],
    "wof:name":"Cord Baptist Church",
    "wof:placetype":"venue"
},
  "geometry": {"coordinates":[-91.34362900000001,35.816247],"type":"Point"}
}