{
  "type": "Feature",
  "properties": {
    "addr:full":"6311 Fieldcrest Dr Fort Smith OK 72916",
    "addr:housenumber":"6311",
    "addr:postcode":"72916",
    "addr:street":"Fieldcrest Dr",
    "iso:country":"US",
    "sg:address":"6311 Fieldcrest Dr",
    "sg:city":"Fort Smith",
    "sg:classifiers":[
        {
            "category":"Communications",
            "subcategory":"Film & Video Production",
            "type":"Services"
        }
    ],
    "sg:phone":"+1 479 459 6400",
    "sg:postcode":"72916",
    "sg:province":"OK",
    "sg:tags":[
        "taping"
    ],
    "wof:name":"Premier Productions",
    "wof:placetype":"venue"
},
  "geometry": {"coordinates":[-94.36570500000001,35.268923],"type":"Point"}
}