{
  "type": "Feature",
  "properties": {
    "iso:country":"US",
    "sg:address":"6311 Fieldcrest Dr",
    "sg:city":"Fort Smith",
    "sg:classifiers":[
        {
            "category":"Communications",
            "subcategory":"Film & Video Production",
            "type":"Services"
        }
    ],
    "sg:phone":"+1 479 459 6400",
    "sg:postcode":"72916",
    "sg:province":"OK",
    "sg:tags":[
        "taping"
    ],
    "wof:name":"Premier Productions",
    "wof:placetype":"venue"
},
  "geometry": {"coordinates":[-94.365705,35.268923],"type":"Point"}
}