{
  "type": "Feature",
  "properties": {
    "iso:country":"US",
    "sg:address":"3955 Central Ave",
    "sg:city":"Hot Springs",
    "sg:classifiers":[
        {
            "category":"Banks & Credit Unions",
            "subcategory":"Bank",
            "type":"Services"
        }
    ],
    "sg:phone":"+1 501 520 0100",
    "sg:postcode":"71913",
    "sg:province":"AR",
    "sg:tags":[
        "cashing",
        "loan",
        "check",
        "broker"
    ],
    "wof:name":"Garland County Cash Advance",
    "wof:placetype":"venue"
},
  "geometry": {"coordinates":[-93.061742,34.458398],"type":"Point"}
}