{
  "type": "Feature",
  "properties": {
    "iso:country":"US",
    "sg:address":"318 Strozier Ln",
    "sg:city":"Barling",
    "sg:classifiers":[
        {
            "category":"Real Estate",
            "subcategory":"Real Estate Operator",
            "type":"Services"
        }
    ],
    "sg:phone":"+1 479 452 8181",
    "sg:postcode":"72923",
    "sg:province":"AR",
    "sg:tags":[
        "apartment"
    ],
    "wof:name":"Ashton Place Manor",
    "wof:placetype":"venue"
},
  "geometry": {"coordinates":[-94.31465300000001,35.325103],"type":"Point"}
}