{
  "type": "Feature",
  "properties": {
    "iso:country":"US",
    "sg:address":"1203 Mountain View Rd",
    "sg:city":"Glenwood",
    "sg:classifiers":[
        {
            "category":"Building & Trades",
            "subcategory":"Landscaping Services",
            "type":"Services"
        }
    ],
    "sg:phone":"+1 870 356 2032",
    "sg:postcode":"71943",
    "sg:province":"AR",
    "sg:tags":[
        "landscape",
        "contractor"
    ],
    "wof:name":"Robertson, Presley B",
    "wof:placetype":"venue"
},
  "geometry": {"coordinates":[-93.54064200000001,34.338568],"type":"Point"}
}