{
  "type": "Feature",
  "properties": {
    "addr:full":"220 W Bond Ave West Memphis AR 72301",
    "addr:housenumber":"220",
    "addr:postcode":"72301",
    "addr:street":"W Bond Ave",
    "iso:country":"US",
    "sg:address":"220 W Bond Ave",
    "sg:city":"West Memphis",
    "sg:classifiers":[
        {
            "category":"Professional",
            "subcategory":"Management & Consulting",
            "type":"Services"
        },
        {
            "category":"Wholesale",
            "subcategory":"Non-durable Goods",
            "type":"Manufacturing & Wholesale Goods"
        }
    ],
    "sg:phone":"+1 870 732 1612",
    "sg:postcode":"72301",
    "sg:province":"AR",
    "sg:tags":[
        "retail",
        "sales",
        "advertising"
    ],
    "wof:name":"Creative Concepts",
    "wof:placetype":"venue"
},
  "geometry": {"coordinates":[-90.188277,35.147948],"type":"Point"}
}