{
  "type": "Feature",
  "properties": {
    "iso:country":"US",
    "sg:address":"531 S Hwy 65 82",
    "sg:city":"Lake Village",
    "sg:classifiers":[
        {
            "category":"Social Services",
            "type":"Services"
        }
    ],
    "sg:phone":"+1 870 265 2445",
    "sg:postcode":"71653",
    "sg:province":"AR",
    "sg:tags":[
        "organization",
        "welfare"
    ],
    "wof:name":"Southeast Arkansas Community",
    "wof:placetype":"venue"
},
  "geometry": {"coordinates":[-91.291877,33.328082],"type":"Point"}
}