{
  "type": "Feature",
  "properties": {
    "addr:full":"682 S Government Ave Fayetteville AR 72701",
    "addr:housenumber":"682",
    "addr:postcode":"72701",
    "addr:street":"S Government Ave",
    "iso:country":"US",
    "sg:address":"682 S Government Ave",
    "sg:city":"Fayetteville",
    "sg:classifiers":[
        {
            "category":"Organizations",
            "subcategory":"Religious Organization",
            "type":"Services"
        }
    ],
    "sg:phone":"+1 479 251 7327",
    "sg:postcode":"72701",
    "sg:province":"AR",
    "sg:tags":[
        "church"
    ],
    "wof:name":"Life Harvester Church",
    "wof:placetype":"venue"
},
  "geometry": {"coordinates":[-94.167699,36.056049],"type":"Point"}
}