{
  "type": "Feature",
  "properties": {
    "iso:country":"US",
    "sg:address":"74 Lake Ice Rd",
    "sg:city":"Higden",
    "sg:classifiers":[
        {
            "category":"Manufacturing",
            "subcategory":"Food",
            "type":"Manufacturing & Wholesale Goods"
        }
    ],
    "sg:phone":"+1 501 825 6560",
    "sg:postcode":"72067",
    "sg:province":"AR",
    "sg:tags":[
        "ice",
        "mfg"
    ],
    "wof:name":"Lake Ice Inc",
    "wof:placetype":"venue"
},
  "geometry": {"coordinates":[-92.204335,35.559094],"type":"Point"}
}