{
  "type": "Feature",
  "properties": {
    "addr:full":"111 E Highland Dr Jonesboro AR 72401",
    "addr:housenumber":"111",
    "addr:postcode":"72401",
    "addr:street":"E Highland Dr",
    "iso:country":"US",
    "sg:address":"111 E Highland Dr",
    "sg:city":"Jonesboro",
    "sg:classifiers":[
        {
            "category":"Restaurant",
            "type":"Food & Drink"
        }
    ],
    "sg:menulink":"http://www.allmenus.com/ar/jonesboro/190390-mcdonalds/menu/",
    "sg:postcode":"72401",
    "sg:province":"AR",
    "sg:tags":[
        "burger",
        "american"
    ],
    "wof:name":"McDonald's",
    "wof:placetype":"venue"
},
  "geometry": {"coordinates":[-90.70552499999999,35.821382],"type":"Point"}
}