{
  "type": "Feature",
  "properties": {
    "iso:country":"US",
    "sg:address":"103 Cherokee Ln",
    "sg:city":"Clarksville",
    "sg:classifiers":[
        {
            "category":"Building & Trades",
            "subcategory":"Construction",
            "type":"Services"
        }
    ],
    "sg:phone":"+1 479 754 7271",
    "sg:postcode":"72830",
    "sg:province":"AR",
    "sg:tags":[
        "general",
        "contractor"
    ],
    "wof:name":"Tri-Systems Inc",
    "wof:placetype":"venue"
},
  "geometry": {"coordinates":[-93.497607,35.475011],"type":"Point"}
}