{
  "type": "Feature",
  "properties": {
    "iso:country":"US",
    "sg:address":"3801 S Camden Rd",
    "sg:city":"Pine Bluff",
    "sg:classifiers":[
        {
            "category":"Shopping",
            "subcategory":"Computers & Home Electronics",
            "type":"Retail Goods"
        }
    ],
    "sg:phone":"+1 870 879 6400",
    "sg:postcode":"71603",
    "sg:province":"AR",
    "sg:tags":[
        "equipment",
        "dealer"
    ],
    "wof:name":"South Arkansas Bus Solutions",
    "wof:placetype":"venue"
},
  "geometry": {"coordinates":[-92.056431,34.195758],"type":"Point"}
}