{
  "type": "Feature",
  "properties": {
    "iso:country":"US",
    "sg:address":"403 W Oak St",
    "sg:city":"El Dorado",
    "sg:classifiers":[
        {
            "category":"Shopping",
            "subcategory":"Pharmacy",
            "type":"Retail Goods"
        }
    ],
    "sg:phone":"+1 870 863 2461",
    "sg:postcode":"71730",
    "sg:province":"AR",
    "wof:name":"Plaza Pharmacy",
    "wof:placetype":"venue"
},
  "geometry": {"coordinates":[-92.667834,33.213462],"type":"Point"}
}