{
  "type": "Feature",
  "properties": {
    "addr:full":"309 S Gunter St Siloam Springs OK 72761",
    "addr:housenumber":"309",
    "addr:postcode":"72761",
    "addr:street":"S Gunter St",
    "iso:country":"US",
    "sg:address":"309 S Gunter St",
    "sg:city":"Siloam Springs",
    "sg:classifiers":[
        {
            "category":"Retail",
            "subcategory":"Auto Repair",
            "type":"Services"
        }
    ],
    "sg:phone":"+1 479 524 5511",
    "sg:postcode":"72761",
    "sg:province":"OK",
    "sg:tags":[
        "machine",
        "automobile",
        "shop"
    ],
    "wof:name":"B & B Machine Shop",
    "wof:placetype":"venue"
},
  "geometry": {"coordinates":[-94.533416,36.182958],"type":"Point"}
}