{
  "type": "Feature",
  "properties": {
    "addr:full":"88 Park Parkin AR 72373",
    "addr:housenumber":"88",
    "addr:postcode":"72373",
    "addr:street":"Park",
    "iso:country":"US",
    "sg:address":"88 Park",
    "sg:city":"Parkin",
    "sg:classifiers":[
        {
            "category":"Place Of Worship",
            "type":"Public Place"
        }
    ],
    "sg:phone":"+1 870 755 5696",
    "sg:postcode":"72373",
    "sg:province":"AR",
    "sg:tags":[
        "church"
    ],
    "wof:name":"Bible Class True Holiness Church",
    "wof:placetype":"venue"
},
  "geometry": {"coordinates":[-90.55416099999999,35.268225],"type":"Point"}
}