{
  "type": "Feature",
  "properties": {
    "iso:country":"US",
    "sg:address":"3860 State Hwy 7",
    "sg:city":"Harrison",
    "sg:classifiers":[
        {
            "category":"Shopping",
            "subcategory":"Bicycles & Sporting Goods",
            "type":"Retail Goods"
        }
    ],
    "sg:phone":"+1 870 741 8507",
    "sg:postcode":"72601",
    "sg:province":"AR",
    "wof:name":"Jack Holt Enterprises Inc",
    "wof:placetype":"venue"
},
  "geometry": {"coordinates":[-93.1216,36.210611],"type":"Point"}
}