{
  "type": "Feature",
  "properties": {
    "iso:country":"US",
    "sg:address":"3138 S Old Missouri Rd",
    "sg:city":"Springdale",
    "sg:classifiers":[
        {
            "category":"Food & Beverages",
            "subcategory":"Groceries & Convenience Stores",
            "type":"Retail Goods"
        }
    ],
    "sg:phone":"+1 479 750 2135",
    "sg:postcode":"72764",
    "sg:province":"AR",
    "wof:name":"La Despensa Latina",
    "wof:placetype":"venue"
},
  "geometry": {"coordinates":[-94.118519,36.156802],"type":"Point"}
}