{
  "type": "Feature",
  "properties": {
    "iso:country":"US",
    "sg:address":"3198 Roseman Rd",
    "sg:city":"Camden",
    "sg:classifiers":[
        {
            "category":"Professional",
            "subcategory":"Business Services",
            "type":"Services"
        }
    ],
    "sg:phone":"+1 870 836 2260",
    "sg:postcode":"71701",
    "sg:province":"AR",
    "wof:name":"Alan Laney",
    "wof:placetype":"venue"
},
  "geometry": {"coordinates":[-92.89213700000001,33.597366],"type":"Point"}
}