{
  "type": "Feature",
  "properties": {
    "addr:full":"103 S Moose St Morrilton AR 72110",
    "addr:housenumber":"103",
    "addr:postcode":"72110",
    "addr:street":"S Moose St",
    "iso:country":"US",
    "sg:address":"103 S Moose St",
    "sg:city":"Morrilton",
    "sg:classifiers":[
        {
            "category":"Health Services",
            "subcategory":"Doctor",
            "type":"Services"
        }
    ],
    "sg:phone":"+1 501 354 3534",
    "sg:postcode":"72110",
    "sg:province":"AR",
    "sg:tags":[
        "physician",
        "surgeon"
    ],
    "wof:name":"Arkansas Wound Care Specialists",
    "wof:placetype":"venue"
},
  "geometry": {"coordinates":[-92.743762,35.152639],"type":"Point"}
}