{
  "type": "Feature",
  "properties": {
    "iso:country":"US",
    "sg:address":"2101 N College Ave",
    "sg:city":"El Dorado",
    "sg:classifiers":[
        {
            "category":"Building & Trades",
            "subcategory":"Plumbing",
            "type":"Services"
        }
    ],
    "sg:phone":"+1 870 862 1113",
    "sg:postcode":"71730",
    "sg:province":"AR",
    "sg:tags":[
        "conditioning",
        "contractor",
        "system",
        "air"
    ],
    "wof:name":"Air Masters Mechanical Inc",
    "wof:placetype":"venue"
},
  "geometry": {"coordinates":[-92.674415,33.233259],"type":"Point"}
}