{
  "type": "Feature",
  "properties": {
    "iso:country":"US",
    "sg:address":"305 E Woodruff Ave",
    "sg:city":"Searcy",
    "sg:classifiers":[
        {
            "category":"Professional",
            "type":"Services"
        }
    ],
    "sg:phone":"+1 501 827 8963",
    "sg:postcode":"72143",
    "sg:province":"AR",
    "sg:tags":[
        "motion",
        "picture",
        "technician"
    ],
    "wof:name":"Bamasaw Film Partners",
    "wof:placetype":"venue"
},
  "geometry": {"coordinates":[-91.733971,35.24591],"type":"Point"}
}