{
  "type": "Feature",
  "properties": {
    "iso:country":"US",
    "sg:address":"201 W Illinois St",
    "sg:city":"Beebe",
    "sg:classifiers":[
        {
            "category":"Government",
            "subcategory":"Police Station",
            "type":"Public Place"
        }
    ],
    "sg:phone":"+1 501 882 3365",
    "sg:postcode":"72012",
    "sg:province":"AR",
    "sg:tags":[
        "department",
        "protection"
    ],
    "wof:name":"Beebe Police Department",
    "wof:placetype":"venue"
},
  "geometry": {"coordinates":[-91.88153800000001,35.070431],"type":"Point"}
}