{
  "type": "Feature",
  "properties": {
    "addr:full":"1311 S 11th St Fort Smith AR 72901",
    "addr:housenumber":"1311",
    "addr:postcode":"72901",
    "addr:street":"S 11Th St",
    "iso:country":"US",
    "sg:address":"1311 S 11th St",
    "sg:city":"Fort Smith",
    "sg:classifiers":[
        {
            "category":"Wholesale",
            "subcategory":"Machinery & Supplies",
            "type":"Manufacturing & Wholesale Goods"
        }
    ],
    "sg:phone":"+1 479 782 5487",
    "sg:postcode":"72901",
    "sg:province":"AR",
    "sg:tags":[
        "equipment",
        "industrial",
        "repair"
    ],
    "wof:name":"Otis Elevator Company",
    "wof:placetype":"venue"
},
  "geometry": {"coordinates":[-94.422612,35.370242],"type":"Point"}
}