{
  "type": "Feature",
  "properties": {
    "iso:country":"US",
    "sg:address":"1901 E Springbrook Ct",
    "sg:city":"Fayetteville",
    "sg:classifiers":[
        {
            "category":"Social Services",
            "subcategory":"Child Care",
            "type":"Services"
        }
    ],
    "sg:phone":"+1 479 582 5196",
    "sg:postcode":"72703",
    "sg:province":"AR",
    "sg:tags":[
        "day"
    ],
    "wof:name":"Pamela Holloway",
    "wof:placetype":"venue"
},
  "geometry": {"coordinates":[-94.133968,36.110085],"type":"Point"}
}