{
  "type": "Feature",
  "properties": {
    "iso:country":"US",
    "sg:address":"56 Steel City Ln",
    "sg:city":"Russellville",
    "sg:classifiers":[
        {
            "category":"Home & Garden",
            "subcategory":"Kitchen Supply",
            "type":"Retail Goods"
        }
    ],
    "sg:phone":"+1 479 967 2755",
    "sg:postcode":"72802",
    "sg:province":"AR",
    "sg:tags":[
        "food",
        "equipment",
        "processing"
    ],
    "wof:name":"Ergo-Tech Inc",
    "wof:placetype":"venue"
},
  "geometry": {"coordinates":[-93.128096,35.306001],"type":"Point"}
}