{
  "type": "Feature",
  "properties": {
    "iso:country":"US",
    "sg:address":"409 Military Rd",
    "sg:city":"Marion",
    "sg:classifiers":[
        {
            "category":"Restaurant",
            "type":"Food & Drink"
        }
    ],
    "sg:phone":"+1 870 739 3943",
    "sg:postcode":"72364",
    "sg:province":"AR",
    "wof:name":"Shake Shack",
    "wof:placetype":"venue"
},
  "geometry": {"coordinates":[-90.20407299999999,35.212919],"type":"Point"}
}