{
  "type": "Feature",
  "properties": {
    "iso:country":"US",
    "sg:address":"323 S Main St",
    "sg:city":"Harrison",
    "sg:classifiers":[
        {
            "category":"Freight",
            "type":"Transportation"
        }
    ],
    "sg:phone":"+1 870 743 1200",
    "sg:postcode":"72601",
    "sg:province":"AR",
    "sg:tags":[
        "trucking"
    ],
    "wof:name":"C & L Trucking",
    "wof:placetype":"venue"
},
  "geometry": {"coordinates":[-93.10549899999999,36.22738],"type":"Point"}
}