{
  "type": "Feature",
  "properties": {
    "iso:country":"US",
    "sg:address":"315 W Main St",
    "sg:city":"Walnut Ridge",
    "sg:classifiers":[
        {
            "category":"Government",
            "subcategory":"Police Station",
            "type":"Public Place"
        }
    ],
    "sg:phone":"+1 870 878 6211",
    "sg:postcode":"72476",
    "sg:province":"AR",
    "sg:tags":[
        "department"
    ],
    "wof:name":"Black Rock Police Dept",
    "wof:placetype":"venue"
},
  "geometry": {"coordinates":[-90.957768,36.069884],"type":"Point"}
}