{
  "type": "Feature",
  "properties": {
    "addr:full":"121 N Oak St Sheridan AR 72150",
    "addr:housenumber":"121",
    "addr:postcode":"72150",
    "addr:street":"N Oak St",
    "iso:country":"US",
    "sg:address":"121 N Oak St",
    "sg:city":"Sheridan",
    "sg:classifiers":[
        {
            "category":"Professional",
            "subcategory":"Lawyer & Legal Services",
            "type":"Services"
        }
    ],
    "sg:phone":"+1 870 942 7799",
    "sg:postcode":"72150",
    "sg:province":"AR",
    "sg:tags":[
        "attorney"
    ],
    "wof:name":"Prosecuting Attorney Hot Check",
    "wof:placetype":"venue"
},
  "geometry": {"coordinates":[-92.40159800000001,34.307637],"type":"Point"}
}