{
  "type": "Feature",
  "properties": {
    "addr:full":"6611 Walcott Rd Paragould AR 72450",
    "addr:housenumber":"6611",
    "addr:postcode":"72450",
    "addr:street":"Walcott Rd",
    "iso:country":"US",
    "sg:address":"6611 Walcott Rd",
    "sg:city":"Paragould",
    "sg:classifiers":[
        {
            "category":"Building & Trades",
            "subcategory":"Construction",
            "type":"Services"
        }
    ],
    "sg:phone":"+1 870 236 2024",
    "sg:postcode":"72450",
    "sg:province":"AR",
    "sg:tags":[
        "water",
        "well",
        "drilling"
    ],
    "wof:name":"Vick's Well Drilling",
    "wof:placetype":"venue"
},
  "geometry": {"coordinates":[-90.572827,36.056378],"type":"Point"}
}