{
  "type": "Feature",
  "properties": {
    "iso:country":"US",
    "sg:address":"119 Dallas 219",
    "sg:city":"Sparkman",
    "sg:classifiers":[
        {
            "category":"Government",
            "subcategory":"Fire Station",
            "type":"Public Place"
        }
    ],
    "sg:phone":"+1 870 687 2660",
    "sg:postcode":"71763",
    "sg:province":"AR",
    "sg:tags":[
        "consultant",
        "protection"
    ],
    "wof:name":"Oauchita Area Col Fire Dept",
    "wof:placetype":"venue"
},
  "geometry": {"coordinates":[-92.754596,33.907434],"type":"Point"}
}