{
  "type": "Feature",
  "properties": {
    "iso:country":"US",
    "sg:address":"111 Court St",
    "sg:city":"Melbourne",
    "sg:classifiers":[
        {
            "category":"Communications",
            "subcategory":"Newspaper",
            "type":"Services"
        }
    ],
    "sg:phone":"+1 870 368 4421",
    "sg:postcode":"72556",
    "sg:province":"AR",
    "wof:name":"Spring River Times",
    "wof:placetype":"venue"
},
  "geometry": {"coordinates":[-91.91033899999999,36.058567],"type":"Point"}
}