{
  "type": "Feature",
  "properties": {
    "iso:country":"US",
    "sg:address":"1304 W Main St",
    "sg:city":"Clarksville",
    "sg:classifiers":[
        {
            "category":"Home & Garden",
            "subcategory":"Building Materials",
            "type":"Retail Goods"
        }
    ],
    "sg:phone":"+1 479 754 6414",
    "sg:postcode":"72830",
    "sg:province":"AR",
    "sg:website":"www.nhci.com",
    "wof:name":"National Home Ctr",
    "wof:placetype":"venue"
},
  "geometry": {"coordinates":[-93.477457,35.471529],"type":"Point"}
}