{
  "type": "Feature",
  "properties": {
    "iso:country":"US",
    "sg:address":"105 S 5th St",
    "sg:city":"Rogers",
    "sg:classifiers":[
        {
            "category":"Banks & Credit Unions",
            "subcategory":"Bank",
            "type":"Services"
        }
    ],
    "sg:phone":"+1 479 936 9675",
    "sg:postcode":"72756",
    "sg:province":"AR",
    "wof:name":"Regions Bank",
    "wof:placetype":"venue"
},
  "geometry": {"coordinates":[-94.12127,36.332393],"type":"Point"}
}