{
  "type": "Feature",
  "properties": {
    "iso:country":"US",
    "sg:address":"1310 Co Rd 813",
    "sg:city":"Lake City",
    "sg:classifiers":[
        {
            "category":"Freight",
            "type":"Transportation"
        }
    ],
    "sg:phone":"+1 870 237 8811",
    "sg:postcode":"72437",
    "sg:province":"AR",
    "sg:tags":[
        "operator",
        "local",
        "trucking"
    ],
    "wof:name":"Fry Brothers Trucking LLC",
    "wof:placetype":"venue"
},
  "geometry": {"coordinates":[-90.447226,35.801808],"type":"Point"}
}