{
  "type": "Feature",
  "properties": {
    "addr:full":"5045 Warden Rd North Little Rock AR 72116",
    "addr:housenumber":"5045",
    "addr:postcode":"72116",
    "addr:street":"Warden Rd",
    "iso:country":"US",
    "sg:address":"5045 Warden Rd",
    "sg:city":"North Little Rock",
    "sg:classifiers":[
        {
            "category":"Autos & Motor Vehicles",
            "subcategory":"Automobile Sales",
            "type":"Retail Goods"
        }
    ],
    "sg:phone":"+1 501 753 9555",
    "sg:postcode":"72116",
    "sg:province":"AR",
    "wof:name":"B M W of Little Rock",
    "wof:placetype":"venue"
},
  "geometry": {"coordinates":[-92.215323,34.801046],"type":"Point"}
}