{
  "type": "Feature",
  "properties": {
    "iso:country":"US",
    "sg:address":"1213 W 18th St",
    "sg:city":"North Little Rock",
    "sg:classifiers":[
        {
            "category":"Personal",
            "subcategory":"Beauty Salon",
            "type":"Services"
        }
    ],
    "sg:phone":"+1 501 758 9377",
    "sg:postcode":"72114",
    "sg:province":"AR",
    "sg:tags":[
        "shop"
    ],
    "wof:name":"Mables Beauty Salon",
    "wof:placetype":"venue"
},
  "geometry": {"coordinates":[-92.280113,34.772407],"type":"Point"}
}