{
  "type": "Feature",
  "properties": {
    "addr:full":"7435 Davenport Dr Jacksonville AR 72076",
    "addr:housenumber":"7435",
    "addr:postcode":"72076",
    "addr:street":"Davenport Dr",
    "iso:country":"US",
    "sg:address":"7435 Davenport Dr",
    "sg:city":"Jacksonville",
    "sg:classifiers":[
        {
            "category":"Utilities",
            "subcategory":"Mobile Phone",
            "type":"Services"
        }
    ],
    "sg:phone":"+1 501 988 0330",
    "sg:postcode":"72076",
    "sg:province":"AR",
    "sg:tags":[
        "telephone",
        "cellular"
    ],
    "wof:name":"American Wireless LLC",
    "wof:placetype":"venue"
},
  "geometry": {"coordinates":[-92.172263,34.933848],"type":"Point"}
}