{
  "type": "Feature",
  "properties": {
    "addr:full":"602 W Union Ave Osceola AR 72370",
    "addr:housenumber":"602",
    "addr:postcode":"72370",
    "addr:street":"W Union Ave",
    "iso:country":"US",
    "sg:address":"602 W Union Ave",
    "sg:city":"Osceola",
    "sg:classifiers":[
        {
            "category":"Health Services",
            "subcategory":"Doctor",
            "type":"Services"
        }
    ],
    "sg:phone":"+1 870 622 0434",
    "sg:postcode":"72370",
    "sg:province":"AR",
    "sg:tags":[
        "physician",
        "surgeon"
    ],
    "wof:name":"SMC Physicians Office",
    "wof:placetype":"venue"
},
  "geometry": {"coordinates":[-89.974735,35.6987],"type":"Point"}
}