{
  "type": "Feature",
  "properties": {
    "iso:country":"US",
    "sg:address":"1314 E Main St",
    "sg:city":"Magnolia",
    "sg:classifiers":[
        {
            "category":"Government",
            "subcategory":"Office",
            "type":"Public Place"
        }
    ],
    "sg:phone":"+1 870 234 6219",
    "sg:postcode":"71753",
    "sg:province":"AR",
    "sg:tags":[
        "medical",
        "administration",
        "business"
    ],
    "wof:name":"Arkansas Spinal Cord Commission",
    "wof:placetype":"venue"
},
  "geometry": {"coordinates":[-93.223703,33.266738],"type":"Point"}
}