{
  "type": "Feature",
  "properties": {
    "iso:country":"US",
    "sg:address":"1302 N West Ave",
    "sg:city":"El Dorado",
    "sg:classifiers":[
        {
            "category":"Banks & Credit Unions",
            "subcategory":"Bank",
            "type":"Services"
        }
    ],
    "sg:phone":"+1 870 862 7332",
    "sg:postcode":"71730",
    "sg:province":"AR",
    "sg:tags":[
        "cashing",
        "check"
    ],
    "wof:name":"C2C Of Ga",
    "wof:placetype":"venue"
},
  "geometry": {"coordinates":[-92.665676,33.223637],"type":"Point"}
}