{
  "type": "Feature",
  "properties": {
    "iso:country":"US",
    "sg:address":"705 N Bloomington St",
    "sg:city":"Lowell",
    "sg:classifiers":[
        {
            "category":"Professional",
            "type":"Services"
        }
    ],
    "sg:phone":"+1 479 659 5385",
    "sg:postcode":"72745",
    "sg:province":"AR",
    "sg:tags":[
        "establishment"
    ],
    "wof:name":"Maru Inc",
    "wof:placetype":"venue"
},
  "geometry": {"coordinates":[-94.136449,36.264079],"type":"Point"}
}