{
  "type": "Feature",
  "properties": {
    "iso:country":"US",
    "sg:address":"5229 W 65th St",
    "sg:city":"Little Rock",
    "sg:classifiers":[
        {
            "category":"Social Services",
            "subcategory":"Child Care",
            "type":"Services"
        }
    ],
    "sg:phone":"+1 501 568 4200",
    "sg:postcode":"72209",
    "sg:province":"AR",
    "sg:tags":[
        "day"
    ],
    "wof:name":"Touched By An Angel Learning C",
    "wof:placetype":"venue"
},
  "geometry": {"coordinates":[-92.33410499999999,34.690441],"type":"Point"}
}