{
  "type": "Feature",
  "properties": {
    "iso:country":"US",
    "sg:address":"20211 Dwight Little Rd",
    "sg:city":"Roland",
    "sg:classifiers":[
        {
            "category":"Building & Trades",
            "subcategory":"Construction",
            "type":"Services"
        }
    ],
    "sg:phone":"+1 501 868 2646",
    "sg:postcode":"72135",
    "sg:province":"AR",
    "sg:tags":[
        "contractor"
    ],
    "wof:name":"Boyles Construction Co",
    "wof:placetype":"venue"
},
  "geometry": {"coordinates":[-92.53765300000001,34.936385],"type":"Point"}
}