{
  "type": "Feature",
  "properties": {
    "addr:full":"3111 Jenny Lind Rd Fort Smith AR 72901",
    "addr:housenumber":"3111",
    "addr:postcode":"72901",
    "addr:street":"Jenny Lind Rd",
    "iso:country":"US",
    "sg:address":"3111 Jenny Lind Rd",
    "sg:city":"Fort Smith",
    "sg:classifiers":[
        {
            "category":"Health Services",
            "subcategory":"Chiropractor",
            "type":"Services"
        }
    ],
    "sg:phone":"+1 479 783 0779",
    "sg:postcode":"72901",
    "sg:province":"AR",
    "wof:name":"Family Chiropractic Clinic",
    "wof:placetype":"venue"
},
  "geometry": {"coordinates":[-94.41314,35.354148],"type":"Point"}
}