{
  "type": "Feature",
  "properties": {
    "iso:country":"US",
    "sg:address":"410 W Trimble Ave",
    "sg:city":"Berryville",
    "sg:classifiers":[
        {
            "category":"Retail",
            "subcategory":"Repair Shop",
            "type":"Services"
        }
    ],
    "sg:phone":"+1 870 423 2772",
    "sg:postcode":"72616",
    "sg:province":"AR",
    "sg:tags":[
        "repairing",
        "lawn",
        "mower"
    ],
    "wof:name":"Jim's Small Engine Svc",
    "wof:placetype":"venue"
},
  "geometry": {"coordinates":[-93.579188,36.369253],"type":"Point"}
}