{
  "type": "Feature",
  "properties": {
    "addr:full":"3120 State Hwy 206 Everton AR 72633",
    "addr:housenumber":"3120",
    "addr:postcode":"72633",
    "addr:street":"State Hwy 206",
    "iso:country":"US",
    "sg:address":"3120 State Hwy 206",
    "sg:city":"Everton",
    "sg:classifiers":[
        {
            "category":"Retail",
            "subcategory":"Repair Shop",
            "type":"Services"
        }
    ],
    "sg:phone":"+1 870 429 5280",
    "sg:postcode":"72633",
    "sg:province":"AR",
    "sg:tags":[
        "welding"
    ],
    "wof:name":"Breedlove Metal Building",
    "wof:placetype":"venue"
},
  "geometry": {"coordinates":[-92.922946,36.144117],"type":"Point"}
}