{
  "type": "Feature",
  "properties": {
    "addr:full":"109 Huntsville Rd Eureka Springs AR 72632",
    "addr:housenumber":"109",
    "addr:postcode":"72632",
    "addr:street":"Huntsville Rd",
    "iso:country":"US",
    "sg:address":"109 Huntsville Rd",
    "sg:city":"Eureka Springs",
    "sg:classifiers":[
        {
            "category":"Travel",
            "subcategory":"Hotels & Motels",
            "type":"Entertainment"
        }
    ],
    "sg:phone":"+1 479 253 6262",
    "sg:postcode":"72632",
    "sg:province":"AR",
    "sg:tags":[
        "operation"
    ],
    "wof:name":"Land O Nod Motel",
    "wof:placetype":"venue"
},
  "geometry": {"coordinates":[-93.739484,36.383587],"type":"Point"}
}