{
  "type": "Feature",
  "properties": {
    "addr:full":"5786 Hwy 62 W Gassville AR 72635",
    "addr:housenumber":"5786",
    "addr:postcode":"72635",
    "addr:street":"Hwy 62 W",
    "iso:country":"US",
    "sg:address":"5786 Hwy 62 W",
    "sg:city":"Gassville",
    "sg:classifiers":[
        {
            "category":"Home & Garden",
            "subcategory":"Mobile Homes",
            "type":"Retail Goods"
        }
    ],
    "sg:phone":"+1 870 430 5000",
    "sg:postcode":"72635",
    "sg:province":"AR",
    "wof:name":"Family Manufactured Homes Inc",
    "wof:placetype":"venue"
},
  "geometry": {"coordinates":[-92.451224,36.297502],"type":"Point"}
}