{
  "type": "Feature",
  "properties": {
    "addr:full":"6404 Pontiac Dr North Little Rock AR 72116",
    "addr:housenumber":"6404",
    "addr:postcode":"72116",
    "addr:street":"Pontiac Dr",
    "iso:country":"US",
    "sg:address":"6404 Pontiac Dr",
    "sg:city":"North Little Rock",
    "sg:classifiers":[
        {
            "category":"Personal",
            "type":"Services"
        }
    ],
    "sg:phone":"+1 501 834 0553",
    "sg:postcode":"72116",
    "sg:province":"AR",
    "wof:name":"Hal Wil Enterprises",
    "wof:placetype":"venue"
},
  "geometry": {"coordinates":[-92.241524,34.813736],"type":"Point"}
}