{
  "type": "Feature",
  "properties": {
    "addr:full":"303 Romance Rd Romance AR 72136",
    "addr:housenumber":"303",
    "addr:postcode":"72136",
    "addr:street":"Romance Rd",
    "iso:country":"US",
    "sg:address":"303 Romance Rd",
    "sg:city":"Romance",
    "sg:classifiers":[
        {
            "category":"Recreation",
            "type":"Entertainment"
        }
    ],
    "sg:phone":"+1 501 556 5066",
    "sg:postcode":"72136",
    "sg:province":"AR",
    "sg:tags":[
        "camps-recreational"
    ],
    "wof:name":"Pat Camp",
    "wof:placetype":"venue"
},
  "geometry": {"coordinates":[-92.002399,35.248841],"type":"Point"}
}