{
  "type": "Feature",
  "properties": {
    "addr:full":"9414 Colonel Glenn Rd Little Rock AR 72204",
    "addr:housenumber":"9414",
    "addr:postcode":"72204",
    "addr:street":"Colonel Glenn Rd",
    "iso:country":"US",
    "sg:address":"9414 Colonel Glenn Rd",
    "sg:city":"Little Rock",
    "sg:classifiers":[
        {
            "category":"Shopping",
            "type":"Retail Goods"
        },
        {
            "category":"Professional",
            "subcategory":"Detective & Security Services",
            "type":"Services"
        }
    ],
    "sg:phone":"+1 501 569 9400",
    "sg:postcode":"72204",
    "sg:province":"AR",
    "sg:tags":[
        "system",
        "computer",
        "network",
        "install",
        "telephone"
    ],
    "sg:website":"www.securevc.com",
    "wof:name":"Secure Vision Communications",
    "wof:placetype":"venue"
},
  "geometry": {"coordinates":[-92.378603,34.710082],"type":"Point"}
}