{
  "type": "Feature",
  "properties": {
    "iso:country":"US",
    "sg:address":"23 Hillside Ave",
    "sg:city":"Eureka Springs",
    "sg:classifiers":[
        {
            "category":"Travel",
            "subcategory":"Hotels & Motels",
            "type":"Entertainment"
        }
    ],
    "sg:phone":"+1 479 253 8688",
    "sg:postcode":"72632",
    "sg:province":"AR",
    "sg:tags":[
        "operation"
    ],
    "sg:website":"www.hiddenspringsbb.com",
    "wof:name":"Hidden Springs Bed & Breakfast",
    "wof:placetype":"venue"
},
  "geometry": {"coordinates":[-93.73431100000001,36.410624],"type":"Point"}
}