{
  "type": "Feature",
  "properties": {
    "addr:full":"104 Woodrock Ln Rogers AR 72756",
    "addr:housenumber":"104",
    "addr:postcode":"72756",
    "addr:street":"Woodrock Ln",
    "iso:country":"US",
    "sg:address":"104 Woodrock Ln",
    "sg:city":"Rogers",
    "sg:classifiers":[
        {
            "category":"Utilities",
            "subcategory":"Mobile Phone",
            "type":"Services"
        }
    ],
    "sg:phone":"+1 479 636 3533",
    "sg:postcode":"72756",
    "sg:province":"AR",
    "sg:tags":[
        "telephone",
        "cellular"
    ],
    "wof:name":"Ptt Connect Inc",
    "wof:placetype":"venue"
},
  "geometry": {"coordinates":[-94.09058,36.32958],"type":"Point"}
}