{
  "type": "Feature",
  "properties": {
    "iso:country":"US",
    "sg:address":"1605 Haynesville Hwy",
    "sg:city":"El Dorado",
    "sg:classifiers":[
        {
            "category":"Building & Trades",
            "subcategory":"Construction",
            "type":"Services"
        }
    ],
    "sg:phone":"+1 870 862 4258",
    "sg:postcode":"71730",
    "sg:province":"AR",
    "sg:tags":[
        "general",
        "contractor"
    ],
    "wof:name":"Milam Construction Co",
    "wof:placetype":"venue"
},
  "geometry": {"coordinates":[-92.693477,33.191941],"type":"Point"}
}