{
  "type": "Feature",
  "properties": {
    "iso:country":"US",
    "sg:address":"814 Hickory Hollow Ln",
    "sg:city":"Russellville",
    "sg:classifiers":[
        {
            "category":"Professional",
            "subcategory":"Business Services",
            "type":"Services"
        }
    ],
    "sg:phone":"+1 479 967 1409",
    "sg:postcode":"72801",
    "sg:province":"AR",
    "wof:name":"Svc Coding Resource Group",
    "wof:placetype":"venue"
},
  "geometry": {"coordinates":[-93.149387,35.272136],"type":"Point"}
}