{
  "type": "Feature",
  "properties": {
    "iso:country":"US",
    "sg:address":"1056 Madison 2230",
    "sg:city":"Huntsville",
    "sg:classifiers":[
        {
            "category":"Building & Trades",
            "subcategory":"Construction",
            "type":"Services"
        }
    ],
    "sg:phone":"+1 479 665 2725",
    "sg:postcode":"72740",
    "sg:province":"AR",
    "sg:tags":[
        "residential"
    ],
    "wof:name":"Timberworks",
    "wof:placetype":"venue"
},
  "geometry": {"coordinates":[-93.590059,36.110754],"type":"Point"}
}