{
  "type": "Feature",
  "properties": {
    "iso:country":"US",
    "sg:address":"1200 N Main St",
    "sg:city":"Benton",
    "sg:classifiers":[
        {
            "category":"Health Services",
            "subcategory":"Doctor",
            "type":"Services"
        }
    ],
    "sg:phone":"+1 501 778 0200",
    "sg:postcode":"72015",
    "sg:province":"AR",
    "sg:tags":[
        "clinic"
    ],
    "wof:name":"Saline County Dialysis",
    "wof:placetype":"venue"
},
  "geometry": {"coordinates":[-92.58715599999999,34.575067],"type":"Point"}
}