{
  "type": "Feature",
  "properties": {
    "iso:country":"US",
    "sg:address":"1609 Dan Ave",
    "sg:city":"Jonesboro",
    "sg:classifiers":[
        {
            "category":"Building & Trades",
            "subcategory":"Construction",
            "type":"Services"
        }
    ],
    "sg:phone":"+1 870 934 0335",
    "sg:postcode":"72401",
    "sg:province":"AR",
    "sg:tags":[
        "concrete",
        "contractor"
    ],
    "sg:website":"www.mobleycontractors.com",
    "wof:name":"Mobley Contractors Inc",
    "wof:placetype":"venue"
},
  "geometry": {"coordinates":[-90.730355,35.84796],"type":"Point"}
}