{
  "type": "Feature",
  "properties": {
    "iso:country":"US",
    "sg:address":"7777 US Hwy 67",
    "sg:city":"Gurdon",
    "sg:classifiers":[
        {
            "category":"Education",
            "subcategory":"School",
            "type":"Public Place"
        }
    ],
    "sg:phone":"+1 870 353 5147",
    "sg:postcode":"71743",
    "sg:province":"AR",
    "wof:name":"Gurdon Public Sch Vocational",
    "wof:placetype":"venue"
},
  "geometry": {"coordinates":[-93.167226,33.915791],"type":"Point"}
}