{
  "type": "Feature",
  "properties": {
    "iso:country":"US",
    "sg:address":"128 Spring Oak Dr",
    "sg:city":"North Little Rock",
    "sg:classifiers":[
        {
            "category":"Professional",
            "subcategory":"Art Services",
            "type":"Services"
        }
    ],
    "sg:phone":"+1 501 835 2123",
    "sg:postcode":"72120",
    "sg:province":"AR",
    "sg:tags":[
        "commercial",
        "design"
    ],
    "wof:name":"On Message Graphic Design",
    "wof:placetype":"venue"
},
  "geometry": {"coordinates":[-92.192505,34.848352],"type":"Point"}
}