{
  "type": "Feature",
  "properties": {
    "iso:country":"US",
    "sg:address":"3901 S University Ave",
    "sg:city":"Little Rock",
    "sg:classifiers":[
        {
            "category":"Building & Trades",
            "subcategory":"Equipment Rental",
            "type":"Services"
        }
    ],
    "sg:phone":"+1 501 568 8000",
    "sg:postcode":"72204",
    "sg:province":"AR",
    "sg:tags":[
        "appliance"
    ],
    "sg:website":"www.shopaarons.com",
    "wof:name":"Aaron's Rental Purchase",
    "wof:placetype":"venue"
},
  "geometry": {"coordinates":[-92.34234,34.716692],"type":"Point"}
}