{
  "type": "Feature",
  "properties": {
    "iso:country":"US",
    "sg:address":"2383 Meeks Creek Rd S",
    "sg:city":"Everton",
    "sg:classifiers":[
        {
            "category":"Farming",
            "subcategory":"Farm",
            "type":"Manufacturing & Wholesale Goods"
        }
    ],
    "sg:phone":"+1 870 429 6326",
    "sg:postcode":"72633",
    "sg:province":"AR",
    "sg:tags":[
        "crop",
        "general"
    ],
    "wof:name":"Young Farms",
    "wof:placetype":"venue"
},
  "geometry": {"coordinates":[-92.95268799999999,36.173207],"type":"Point"}
}