{
  "type": "Feature",
  "properties": {
    "addr:full":"2429 Hwy 5 S Mountain Home AR 72653",
    "addr:housenumber":"2429",
    "addr:postcode":"72653",
    "addr:street":"Hwy 5 S",
    "iso:country":"US",
    "sg:address":"2429 Hwy 5 S",
    "sg:city":"Mountain Home",
    "sg:classifiers":[
        {
            "category":"Professional",
            "subcategory":"Business Services",
            "type":"Services"
        }
    ],
    "sg:phone":"+1 870 425 9769",
    "sg:postcode":"72653",
    "sg:province":"AR",
    "wof:name":"Sign Painters Inc",
    "wof:placetype":"venue"
},
  "geometry": {"coordinates":[-92.35049600000001,36.319551],"type":"Point"}
}