{
  "type": "Feature",
  "properties": {
    "iso:country":"US",
    "sg:address":"960 S Mount Olive St",
    "sg:city":"Siloam Springs",
    "sg:classifiers":[
        {
            "category":"Health Services",
            "subcategory":"Optometrist",
            "type":"Services"
        }
    ],
    "sg:phone":"+1 479 524 5161",
    "sg:postcode":"72761",
    "sg:province":"OK",
    "wof:name":"Roberts-Philpott Eye Assoc",
    "wof:placetype":"venue"
},
  "geometry": {"coordinates":[-94.54155299999999,36.175086],"type":"Point"}
}