{
  "type": "Feature",
  "properties": {
    "addr:full":"34500 Fitzhugh Ln Bigelow AR 72016",
    "addr:housenumber":"34500",
    "addr:postcode":"72016",
    "addr:street":"Fitzhugh Ln",
    "iso:country":"US",
    "sg:address":"34500 Fitzhugh Ln",
    "sg:city":"Bigelow",
    "sg:classifiers":[
        {
            "category":"Building & Trades",
            "subcategory":"Cleaning & Sanitation",
            "type":"Services"
        }
    ],
    "sg:phone":"+1 501 330 2001",
    "sg:postcode":"72016",
    "sg:province":"AR",
    "sg:tags":[
        "janitor"
    ],
    "wof:name":"Fitzhugh & Fitzhugh",
    "wof:placetype":"venue"
},
  "geometry": {"coordinates":[-92.647305,34.916847],"type":"Point"}
}