{
  "type": "Feature",
  "properties": {
    "iso:country":"US",
    "sg:address":"116 Masters Pl",
    "sg:city":"Hot Springs",
    "sg:classifiers":[
        {
            "category":"Organizations",
            "subcategory":"Religious Organization",
            "type":"Services"
        }
    ],
    "sg:phone":"+1 501 623 6380",
    "sg:postcode":"71913",
    "sg:province":"AR",
    "sg:tags":[
        "church"
    ],
    "wof:name":"Rector Heights Baptist Church",
    "wof:placetype":"venue"
},
  "geometry": {"coordinates":[-93.09293599999999,34.495445],"type":"Point"}
}