{
  "type": "Feature",
  "properties": {
    "iso:country":"US",
    "sg:address":"6600 US Hwy 271",
    "sg:city":"Fort Smith",
    "sg:classifiers":[
        {
            "category":"Personal",
            "subcategory":"Beauty Salon",
            "type":"Services"
        }
    ],
    "sg:phone":"+1 479 646 4462",
    "sg:postcode":"72908",
    "sg:province":"AR",
    "wof:name":"Gina's Hair Salon",
    "wof:placetype":"venue"
},
  "geometry": {"coordinates":[-94.424302,35.320166],"type":"Point"}
}