{
  "type": "Feature",
  "properties": {
    "iso:country":"US",
    "sg:address":"4981 State Hwy 392",
    "sg:city":"Harrison",
    "sg:classifiers":[
        {
            "category":"Autos & Motor Vehicles",
            "subcategory":"Automobile Sales",
            "type":"Retail Goods"
        }
    ],
    "sg:phone":"+1 870 743 3346",
    "sg:postcode":"72601",
    "sg:province":"AR",
    "sg:tags":[
        "used"
    ],
    "wof:name":"Cokers Used Cars",
    "wof:placetype":"venue"
},
  "geometry": {"coordinates":[-93.186484,36.235528],"type":"Point"}
}