{
  "type": "Feature",
  "properties": {
    "iso:country":"US",
    "sg:address":"1726 E Mill St",
    "sg:city":"Malvern",
    "sg:classifiers":[
        {
            "category":"Personal",
            "subcategory":"Beauty Salon",
            "type":"Services"
        }
    ],
    "sg:phone":"+1 501 337 9030",
    "sg:postcode":"72104",
    "sg:province":"AR",
    "sg:tags":[
        "shop"
    ],
    "wof:name":"Klassic Kuts & Kurls",
    "wof:placetype":"venue"
},
  "geometry": {"coordinates":[-92.792857,34.354078],"type":"Point"}
}