{
  "type": "Feature",
  "properties": {
    "iso:country":"US",
    "sg:address":"2115 Main Dr",
    "sg:city":"Fayetteville",
    "sg:classifiers":[
        {
            "category":"Shopping",
            "subcategory":"Clothing, Apparel, & Fashions",
            "type":"Retail Goods"
        }
    ],
    "sg:phone":"+1 479 521 5858",
    "sg:postcode":"72704",
    "sg:province":"AR",
    "sg:tags":[
        "furnishing"
    ],
    "wof:name":"Mr B's Big & Tall",
    "wof:placetype":"venue"
},
  "geometry": {"coordinates":[-94.15816100000001,36.133326],"type":"Point"}
}