{
  "type": "Feature",
  "properties": {
    "iso:country":"US",
    "sg:address":"1620 Donaghey Ave",
    "sg:city":"Conway",
    "sg:classifiers":[
        {
            "category":"Social Services",
            "type":"Services"
        }
    ],
    "sg:phone":"+1 501 327 2895",
    "sg:postcode":"72034",
    "sg:province":"AR",
    "sg:tags":[
        "organization",
        "welfare"
    ],
    "wof:name":"Faulkner County Senior Citizen",
    "wof:placetype":"venue"
},
  "geometry": {"coordinates":[-92.45325699999999,35.101653],"type":"Point"}
}