{
  "type": "Feature",
  "properties": {
    "iso:country":"US",
    "sg:address":"9800 Nash Ln",
    "sg:city":"Mabelvale",
    "sg:classifiers":[
        {
            "category":"Organizations",
            "subcategory":"Religious Organization",
            "type":"Services"
        }
    ],
    "sg:phone":"+1 501 455 1347",
    "sg:postcode":"72103",
    "sg:province":"AR",
    "sg:tags":[
        "church"
    ],
    "wof:name":"River Of Life Assembly Of God",
    "wof:placetype":"venue"
},
  "geometry": {"coordinates":[-92.39368899999999,34.662099],"type":"Point"}
}