{
  "type": "Feature",
  "properties": {
    "iso:country":"US",
    "sg:address":"2704 Highway 71 N",
    "sg:city":"Mena",
    "sg:classifiers":[
        {
            "category":"Autos & Motor Vehicles",
            "subcategory":"Automobile Sales",
            "type":"Retail Goods"
        }
    ],
    "sg:phone":"+1 479 394 2341",
    "sg:postcode":"71953",
    "sg:province":"AR",
    "sg:tags":[
        "dealers-used",
        "car",
        "used",
        "cars-wholesale"
    ],
    "wof:name":"Lyle's Used Cars",
    "wof:placetype":"venue"
},
  "geometry": {"coordinates":[-94.152903,34.655952],"type":"Point"}
}