{
  "type": "Feature",
  "properties": {
    "iso:country":"US",
    "sg:address":"3401 Service Loop",
    "sg:city":"West Memphis",
    "sg:classifiers":[
        {
            "category":"Travel",
            "subcategory":"Hotels & Motels",
            "type":"Entertainment"
        }
    ],
    "sg:phone":"+1 870 735 7185",
    "sg:postcode":"72301",
    "sg:province":"AR",
    "wof:name":"Best Western Inn",
    "wof:placetype":"venue"
},
  "geometry": {"coordinates":[-90.146901,35.154945],"type":"Point"}
}