{
  "type": "Feature",
  "properties": {
    "addr:full":"208 S 8th St Rogers AR 72756",
    "addr:housenumber":"208",
    "addr:postcode":"72756",
    "addr:street":"S 8Th St",
    "iso:country":"US",
    "sg:address":"208 S 8th St",
    "sg:city":"Rogers",
    "sg:classifiers":[
        {
            "category":"Travel",
            "subcategory":"Hotels & Motels",
            "type":"Entertainment"
        }
    ],
    "sg:phone":"+1 479 631 1600",
    "sg:postcode":"72756",
    "sg:province":"AR",
    "wof:name":"Kabia Inc",
    "wof:placetype":"venue"
},
  "geometry": {"coordinates":[-94.125658,36.33242],"type":"Point"}
}