{
  "type": "Feature",
  "properties": {
    "addr:full":"416 N Ross Hampton Rd Greenwood AR 72936",
    "addr:housenumber":"416",
    "addr:postcode":"72936",
    "addr:street":"N Ross Hampton Rd",
    "iso:country":"US",
    "sg:address":"416 N Ross Hampton Rd",
    "sg:city":"Greenwood",
    "sg:classifiers":[
        {
            "category":"Building & Trades",
            "subcategory":"Construction",
            "type":"Services"
        }
    ],
    "sg:phone":"+1 479 996 3019",
    "sg:postcode":"72936",
    "sg:province":"AR",
    "sg:tags":[
        "resurfacing",
        "laying",
        "refinishing",
        "floor"
    ],
    "wof:name":"Southwest Floors Inc",
    "wof:placetype":"venue"
},
  "geometry": {"coordinates":[-94.339311,35.221038],"type":"Point"}
}