{
  "type": "Feature",
  "properties": {
    "addr:full":"4410 Spyglass Dr Springdale AR 72764",
    "addr:housenumber":"4410",
    "addr:postcode":"72764",
    "addr:street":"Spyglass Dr",
    "iso:country":"US",
    "sg:address":"4410 Spyglass Dr",
    "sg:city":"Springdale",
    "sg:classifiers":[
        {
            "category":"Professional",
            "subcategory":"Management & Consulting",
            "type":"Services"
        }
    ],
    "sg:phone":"+1 479 751 6292",
    "sg:postcode":"72764",
    "sg:province":"AR",
    "sg:tags":[
        "business"
    ],
    "wof:name":"Basic E D I",
    "wof:placetype":"venue"
},
  "geometry": {"coordinates":[-94.13625500000001,36.143973],"type":"Point"}
}