{
  "type": "Feature",
  "properties": {
    "addr:full":"1020 Lantrip Rd Sherwood AR 72120",
    "addr:housenumber":"1020",
    "addr:postcode":"72120",
    "addr:street":"Lantrip Rd",
    "iso:country":"US",
    "sg:address":"1020 Lantrip Rd",
    "sg:city":"Sherwood",
    "sg:classifiers":[
        {
            "category":"Professional",
            "subcategory":"Detective & Security Services",
            "type":"Services"
        }
    ],
    "sg:phone":"+1 501 733 9512",
    "sg:postcode":"72120",
    "sg:province":"AR",
    "sg:tags":[
        "information",
        "bureau"
    ],
    "wof:name":"Usda Wildlife Svc",
    "wof:placetype":"venue"
},
  "geometry": {"coordinates":[-92.19857,34.824268],"type":"Point"}
}