{
  "type": "Feature",
  "properties": {
    "iso:country":"US",
    "sg:address":"404 W Walnut St",
    "sg:city":"Paris",
    "sg:classifiers":[
        {
            "category":"Professional",
            "type":"Services"
        }
    ],
    "sg:phone":"+1 479 963 2830",
    "sg:postcode":"72855",
    "sg:province":"AR",
    "wof:name":"Seis Pros Svc Inc",
    "wof:placetype":"venue"
},
  "geometry": {"coordinates":[-93.733265,35.292058],"type":"Point"}
}