{
  "type": "Feature",
  "properties": {
    "iso:country":"US",
    "sg:address":"1011 N Walton Blvd",
    "sg:city":"Bentonville",
    "sg:classifiers":[
        {
            "category":"Insurance",
            "subcategory":"Hazard Insurance",
            "type":"Services"
        },
        {
            "category":"Insurance",
            "subcategory":"Insurance Agent",
            "type":"Services"
        },
        {
            "category":"Insurance",
            "subcategory":"Life Insurance",
            "type":"Services"
        }
    ],
    "sg:phone":"+1 479 273 6002",
    "sg:postcode":"72712",
    "sg:province":"AR",
    "sg:tags":[
        "consultant",
        "analyst"
    ],
    "sg:website":"http://affordins.com",
    "wof:name":"Affordable Insurance",
    "wof:placetype":"venue"
},
  "geometry": {"coordinates":[-94.22120700000001,36.382953],"type":"Point"}
}