{
  "type": "Feature",
  "properties": {
    "iso:country":"US",
    "sg:address":"205 Town Hall Dr",
    "sg:city":"Mineral Springs",
    "sg:classifiers":[
        {
            "category":"Government",
            "subcategory":"Office",
            "type":"Public Place"
        }
    ],
    "sg:phone":"+1 870 287 7200",
    "sg:postcode":"71851",
    "sg:province":"AR",
    "sg:tags":[
        "village"
    ],
    "wof:name":"City Of Tollette",
    "wof:placetype":"venue"
},
  "geometry": {"coordinates":[-93.899188,33.815401],"type":"Point"}
}