{
  "type": "Feature",
  "properties": {
    "iso:country":"US",
    "sg:address":"201 N Jeff Davis Ave",
    "sg:city":"Jacksonville",
    "sg:classifiers":[
        {
            "category":"Shopping",
            "subcategory":"Stationery & Office Supplies",
            "type":"Retail Goods"
        }
    ],
    "sg:phone":"+1 501 982 6226",
    "sg:postcode":"72076",
    "sg:province":"AR",
    "wof:name":"Rye Office Products",
    "wof:placetype":"venue"
},
  "geometry": {"coordinates":[-92.120086,34.868106],"type":"Point"}
}