{
  "type": "Feature",
  "properties": {
    "iso:country":"US",
    "sg:address":"2120 S Waldron Rd",
    "sg:city":"Fort Smith",
    "sg:classifiers":[
        {
            "category":"Local Transit",
            "type":"Transportation"
        }
    ],
    "sg:phone":"+1 479 452 3739",
    "sg:postcode":"72903",
    "sg:province":"AR",
    "sg:tags":[
        "limousine"
    ],
    "wof:name":"Star Limousine Services Ltd",
    "wof:placetype":"venue"
},
  "geometry": {"coordinates":[-94.372949,35.362519],"type":"Point"}
}