{
  "type": "Feature",
  "properties": {
    "iso:country":"US",
    "sg:address":"406 NW 14th St",
    "sg:city":"Atkins",
    "sg:classifiers":[
        {
            "category":"Organizations",
            "subcategory":"Religious Organization",
            "type":"Services"
        }
    ],
    "sg:phone":"+1 479 641 7255",
    "sg:postcode":"72823",
    "sg:province":"AR",
    "sg:tags":[
        "church"
    ],
    "wof:name":"Hillcrest Pentecostal Church",
    "wof:placetype":"venue"
},
  "geometry": {"coordinates":[-92.941411,35.256542],"type":"Point"}
}