{
  "type": "Feature",
  "properties": {
    "addr:full":"2600 Midland Blvd Fort Smith AR 72904",
    "addr:housenumber":"2600",
    "addr:postcode":"72904",
    "addr:street":"Midland Blvd",
    "iso:country":"US",
    "sg:address":"2600 Midland Blvd",
    "sg:city":"Fort Smith",
    "sg:classifiers":[
        {
            "category":"Shopping",
            "subcategory":"Department Store",
            "type":"Retail Goods"
        }
    ],
    "sg:phone":"+1 479 785 5964",
    "sg:postcode":"72904",
    "sg:province":"AR",
    "sg:tags":[
        "discount"
    ],
    "wof:name":"Wal-Mart",
    "wof:placetype":"venue"
},
  "geometry": {"coordinates":[-94.39805,35.405965],"type":"Point"}
}