{
  "type": "Feature",
  "properties": {
    "addr:full":"14017 Hwy 298 Benton AR 72019",
    "addr:housenumber":"14017",
    "addr:postcode":"72019",
    "addr:street":"Hwy 298",
    "iso:country":"US",
    "sg:address":"14017 Hwy 298",
    "sg:city":"Benton",
    "sg:classifiers":[
        {
            "category":"Wholesale",
            "subcategory":"Non-durable Goods",
            "type":"Manufacturing & Wholesale Goods"
        }
    ],
    "sg:phone":"+1 501 594 5225",
    "sg:postcode":"72019",
    "sg:province":"AR",
    "wof:name":"Homestead Christmas Tree Farm",
    "wof:placetype":"venue"
},
  "geometry": {"coordinates":[-92.70540699999999,34.707582],"type":"Point"}
}