{
  "type": "Feature",
  "properties": {
    "iso:country":"US",
    "sg:address":"1755 E Rolling Hills Dr",
    "sg:city":"Fayetteville",
    "sg:classifiers":[
        {
            "category":"Organizations",
            "subcategory":"Religious Organization",
            "type":"Services"
        }
    ],
    "sg:phone":"+1 479 442 8164",
    "sg:postcode":"72703",
    "sg:province":"AR",
    "sg:tags":[
        "church"
    ],
    "wof:name":"First Church Christ Scientist",
    "wof:placetype":"venue"
},
  "geometry": {"coordinates":[-94.135916,36.105071],"type":"Point"}
}