{
  "type": "Feature",
  "properties": {
    "addr:full":"2565 Hwy 425 S Monticello AR 71655",
    "addr:housenumber":"2565",
    "addr:postcode":"71655",
    "addr:street":"Hwy 425 S",
    "iso:country":"US",
    "sg:address":"2565 Hwy 425 S",
    "sg:city":"Monticello",
    "sg:classifiers":[
        {
            "category":"Restaurant",
            "type":"Food & Drink"
        }
    ],
    "sg:phone":"+1 870 367 0216",
    "sg:postcode":"71655",
    "sg:province":"AR",
    "sg:tags":[
        "caterer"
    ],
    "wof:name":"Cypress Creek Crawfish & Seafd",
    "wof:placetype":"venue"
},
  "geometry": {"coordinates":[-91.835525,33.47867],"type":"Point"}
}