{
  "type": "Feature",
  "properties": {
    "iso:country":"US",
    "sg:address":"213 W Walnut St",
    "sg:city":"Rogers",
    "sg:classifiers":[
        {
            "category":"Shopping",
            "subcategory":"Clothing, Apparel, & Fashions",
            "type":"Retail Goods"
        }
    ],
    "sg:phone":"+1 479 636 2220",
    "sg:postcode":"72756",
    "sg:province":"AR",
    "sg:tags":[
        "shop",
        "bridal"
    ],
    "wof:name":"By Invitation Only",
    "wof:placetype":"venue"
},
  "geometry": {"coordinates":[-94.118546,36.333266],"type":"Point"}
}