{
  "type": "Feature",
  "properties": {
    "addr:full":"607 N 1st St Ste 2 Jacksonville AR 72076",
    "addr:housenumber":"607",
    "addr:postcode":"72076",
    "addr:street":"N 1St St Ste 2",
    "iso:country":"US",
    "sg:address":"607 N 1st St Ste 2",
    "sg:city":"Jacksonville",
    "sg:classifiers":[
        {
            "category":"Arena",
            "subcategory":"Sports Club",
            "type":"Entertainment"
        }
    ],
    "sg:phone":"+1 501 982 2877",
    "sg:postcode":"72076",
    "sg:province":"AR",
    "sg:tags":[
        "martial art",
        "instruction"
    ],
    "wof:name":"Brown's Mike Taekwondo",
    "wof:placetype":"venue"
},
  "geometry": {"coordinates":[-92.109543,34.872608],"type":"Point"}
}