{
  "type": "Feature",
  "properties": {
    "addr:full":"408 Hearn St Nashville AR 71852",
    "addr:housenumber":"408",
    "addr:postcode":"71852",
    "addr:street":"Hearn St",
    "iso:country":"US",
    "sg:address":"408 Hearn St",
    "sg:city":"Nashville",
    "sg:classifiers":[
        {
            "category":"Organizations",
            "subcategory":"Community Association",
            "type":"Services"
        }
    ],
    "sg:phone":"+1 870 845 2349",
    "sg:postcode":"71852",
    "sg:province":"AR",
    "wof:name":"VFW",
    "wof:placetype":"venue"
},
  "geometry": {"coordinates":[-93.840017,33.948192],"type":"Point"}
}