{
  "type": "Feature",
  "properties": {
    "iso:country":"US",
    "sg:address":"720 Texas St",
    "sg:city":"Hope",
    "sg:classifiers":[
        {
            "category":"Government",
            "subcategory":"Office",
            "type":"Public Place"
        }
    ],
    "sg:phone":"+1 870 777 5742",
    "sg:postcode":"71801",
    "sg:province":"AR",
    "sg:tags":[
        "housing",
        "program"
    ],
    "wof:name":"Hope Housing Authority",
    "wof:placetype":"venue"
},
  "geometry": {"coordinates":[-93.5982,33.66115],"type":"Point"}
}