{
  "type": "Feature",
  "properties": {
    "iso:country":"US",
    "sg:address":"144 Graham Rd",
    "sg:city":"Judsonia",
    "sg:classifiers":[
        {
            "category":"Farming",
            "subcategory":"Farm",
            "type":"Manufacturing & Wholesale Goods"
        }
    ],
    "sg:phone":"+1 501 729 0042",
    "sg:postcode":"72081",
    "sg:province":"AR",
    "wof:name":"Gillam Farms",
    "wof:placetype":"venue"
},
  "geometry": {"coordinates":[-91.65845299999999,35.358495],"type":"Point"}
}