{
  "type": "Feature",
  "properties": {
    "iso:country":"US",
    "sg:address":"221 W Main St",
    "sg:city":"Piggott",
    "sg:classifiers":[
        {
            "category":"Shopping",
            "subcategory":"Antiques",
            "type":"Retail Goods"
        }
    ],
    "sg:phone":"+1 870 598 3359",
    "sg:postcode":"72454",
    "sg:province":"AR",
    "wof:name":"Dragonfly Antiques & Gifts",
    "wof:placetype":"venue"
},
  "geometry": {"coordinates":[-90.191829,36.382693],"type":"Point"}
}