{
  "type": "Feature",
  "properties": {
    "addr:full":"106 Tower Dr Murfreesboro AR 71958",
    "addr:housenumber":"106",
    "addr:postcode":"71958",
    "addr:street":"Tower Dr",
    "iso:country":"US",
    "sg:address":"106 Tower Dr",
    "sg:city":"Murfreesboro",
    "sg:classifiers":[
        {
            "category":"Professional",
            "subcategory":"Business Services",
            "type":"Services"
        }
    ],
    "sg:phone":"+1 870 285 2516",
    "sg:postcode":"71958",
    "sg:province":"AR",
    "wof:name":"Dena White Office",
    "wof:placetype":"venue"
},
  "geometry": {"coordinates":[-93.693174,34.076245],"type":"Point"}
}