{
  "type": "Feature",
  "properties": {
    "iso:country":"US",
    "sg:address":"303 Millsap Rd",
    "sg:city":"Fayetteville",
    "sg:classifiers":[
        {
            "category":"Recreation",
            "type":"Entertainment"
        }
    ],
    "sg:phone":"+1 479 587 7053",
    "sg:postcode":"72703",
    "sg:province":"AR",
    "sg:tags":[
        "club",
        "membership"
    ],
    "wof:name":"GE",
    "wof:placetype":"venue"
},
  "geometry": {"coordinates":[-94.150454,36.114105],"type":"Point"}
}