{
  "type": "Feature",
  "properties": {
    "addr:full":"1205 Kings Way Alma AR 72921",
    "addr:housenumber":"1205",
    "addr:postcode":"72921",
    "addr:street":"Kings Way",
    "iso:country":"US",
    "sg:address":"1205 Kings Way",
    "sg:city":"Alma",
    "sg:classifiers":[
        {
            "category":"Professional",
            "subcategory":"Management & Consulting",
            "type":"Services"
        }
    ],
    "sg:phone":"+1 479 632 4728",
    "sg:postcode":"72921",
    "sg:province":"AR",
    "wof:name":"Joe T Lloyd",
    "wof:placetype":"venue"
},
  "geometry": {"coordinates":[-94.243917,35.500244],"type":"Point"}
}