{
  "type": "Feature",
  "properties": {
    "iso:country":"US",
    "sg:address":"2700 W Commercial St",
    "sg:city":"Ozark",
    "sg:classifiers":[
        {
            "category":"Building & Trades",
            "subcategory":"Plumbing",
            "type":"Services"
        }
    ],
    "sg:phone":"+1 479 667 4080",
    "sg:postcode":"72949",
    "sg:province":"AR",
    "sg:tags":[
        "electrical",
        "contractor"
    ],
    "wof:name":"Milam Heating & Air",
    "wof:placetype":"venue"
},
  "geometry": {"coordinates":[-93.856582,35.490166],"type":"Point"}
}