{
  "type": "Feature",
  "properties": {
    "iso:country":"US",
    "sg:address":"522 W Washington Ave",
    "sg:city":"Jonesboro",
    "sg:classifiers":[
        {
            "category":"Social Services",
            "type":"Services"
        }
    ],
    "sg:phone":"+1 870 935 6621",
    "sg:postcode":"72401",
    "sg:province":"AR",
    "sg:tags":[
        "counselor",
        "marriage",
        "family"
    ],
    "wof:name":"Life Counseling Associates",
    "wof:placetype":"venue"
},
  "geometry": {"coordinates":[-90.70821,35.83845],"type":"Point"}
}