{
  "type": "Feature",
  "properties": {
    "iso:country":"US",
    "sg:address":"103 Round Mountain Rd",
    "sg:city":"Conway",
    "sg:phone":"+1 501 336 0042",
    "sg:postcode":"72034",
    "sg:province":"AR",
    "sg:tags":[
        "distributor",
        "oil",
        "marketer"
    ],
    "wof:name":"Wacaster Oil Co",
    "wof:placetype":"venue"
},
  "geometry": {"coordinates":[-92.43360699999999,35.027682],"type":"Point"}
}