{
  "type": "Feature",
  "properties": {
    "iso:country":"US",
    "sg:address":"202 N Lakeside Dr",
    "sg:city":"De Queen",
    "sg:classifiers":[
        {
            "category":"Retail",
            "subcategory":"Auto Repair",
            "type":"Services"
        }
    ],
    "sg:phone":"+1 870 642 2811",
    "sg:postcode":"71832",
    "sg:province":"AR",
    "sg:tags":[
        "body"
    ],
    "wof:name":"Rickys Body & Glass Shop",
    "wof:placetype":"venue"
},
  "geometry": {"coordinates":[-94.330025,34.039161],"type":"Point"}
}