{
  "type": "Feature",
  "properties": {
    "iso:country":"US",
    "sg:address":"514 W Gaines Ave",
    "sg:city":"Monticello",
    "sg:classifiers":[
        {
            "category":"Shopping",
            "subcategory":"Tobacco",
            "type":"Retail Goods"
        }
    ],
    "sg:phone":"+1 870 367 1220",
    "sg:postcode":"71655",
    "sg:province":"AR",
    "sg:tags":[
        "cigarette",
        "product",
        "cigar",
        "dealer"
    ],
    "wof:name":"Monticello Discount Tobacco",
    "wof:placetype":"venue"
},
  "geometry": {"coordinates":[-91.797631,33.629403],"type":"Point"}
}