{
  "type": "Feature",
  "properties": {
    "addr:full":"729 N 7th St Augusta AR 72006",
    "addr:housenumber":"729",
    "addr:postcode":"72006",
    "addr:street":"N 7Th St",
    "iso:country":"US",
    "sg:address":"729 N 7th St",
    "sg:city":"Augusta",
    "sg:classifiers":[
        {
            "category":"Organizations",
            "subcategory":"Religious Organization",
            "type":"Services"
        }
    ],
    "sg:phone":"+1 870 347 2955",
    "sg:postcode":"72006",
    "sg:province":"AR",
    "sg:tags":[
        "clergy"
    ],
    "wof:name":"First Baptist Church Parsonage",
    "wof:placetype":"venue"
},
  "geometry": {"coordinates":[-91.35960799999999,35.29107],"type":"Point"}
}