{
  "type": "Feature",
  "properties": {
    "addr:full":"1428 Polk Road 33 Vandervoort AR 71972",
    "addr:housenumber":"1428",
    "addr:postcode":"71972",
    "addr:street":"Polk Road 33",
    "iso:country":"US",
    "sg:address":"1428 Polk Road 33",
    "sg:city":"Vandervoort",
    "sg:classifiers":[
        {
            "category":"Government",
            "subcategory":"Office",
            "type":"Public Place"
        }
    ],
    "sg:phone":"+1 870 387 6321",
    "sg:postcode":"71972",
    "sg:province":"AR",
    "sg:tags":[
        "parish",
        "government-county"
    ],
    "wof:name":"James M Watkins",
    "wof:placetype":"venue"
},
  "geometry": {"coordinates":[-94.32406,34.37411],"type":"Point"}
}