{
  "type": "Feature",
  "properties": {
    "iso:country":"US",
    "sg:address":"174 Sylvan Hills Rd",
    "sg:city":"Hot Springs",
    "sg:classifiers":[
        {
            "category":"Manufacturing",
            "subcategory":"Food",
            "type":"Manufacturing & Wholesale Goods"
        },
        {
            "category":"Professional",
            "subcategory":"Advertising",
            "type":"Services"
        }
    ],
    "sg:phone":"+1 501 262 3118",
    "sg:postcode":"71901",
    "sg:province":"AR",
    "sg:tags":[
        "distribution",
        "bottler"
    ],
    "wof:name":"Pepsi Americas Inc",
    "wof:placetype":"venue"
},
  "geometry": {"coordinates":[-92.928821,34.465429],"type":"Point"}
}