{
  "type": "Feature",
  "properties": {
    "iso:country":"US",
    "sg:address":"707 Block St S",
    "sg:city":"Wynne",
    "sg:classifiers":[
        {
            "category":"Social Services",
            "subcategory":"Child Care",
            "type":"Services"
        }
    ],
    "sg:phone":"+1 870 238 3559",
    "sg:postcode":"72396",
    "sg:province":"AR",
    "sg:tags":[
        "kindergarten",
        "academic",
        "school"
    ],
    "wof:name":"Kara's Learning Ctr",
    "wof:placetype":"venue"
},
  "geometry": {"coordinates":[-90.790983,35.219398],"type":"Point"}
}