{
  "type": "Feature",
  "properties": {
    "iso:country":"US",
    "sg:address":"609 W Utah Ranch Rd",
    "sg:city":"Lavaca",
    "sg:classifiers":[
        {
            "category":"Manufacturing",
            "subcategory":"Apparel",
            "type":"Manufacturing & Wholesale Goods"
        }
    ],
    "sg:phone":"+1 479 674 4359",
    "sg:postcode":"72941",
    "sg:province":"AR",
    "sg:tags":[
        "embroidery",
        "mfg"
    ],
    "wof:name":"D & B Creations",
    "wof:placetype":"venue"
},
  "geometry": {"coordinates":[-94.175746,35.351625],"type":"Point"}
}