{
  "type": "Feature",
  "properties": {
    "iso:country":"US",
    "sg:address":"150 Western Hills Cir",
    "sg:city":"Greenbrier",
    "sg:classifiers":[
        {
            "category":"Building & Trades",
            "subcategory":"Construction",
            "type":"Services"
        }
    ],
    "sg:phone":"+1 501 679 2613",
    "sg:postcode":"72058",
    "sg:province":"AR",
    "sg:tags":[
        "excavation",
        "contractor"
    ],
    "wof:name":"Whitley Truck & Dozier Service",
    "wof:placetype":"venue"
},
  "geometry": {"coordinates":[-92.471896,35.204947],"type":"Point"}
}