{
  "type": "Feature",
  "properties": {
    "addr:full":"120 W 5th Ave Pine Bluff AR 71601",
    "addr:housenumber":"120",
    "addr:postcode":"71601",
    "addr:street":"W 5Th Ave",
    "iso:country":"US",
    "sg:address":"120 W 5th Ave",
    "sg:city":"Pine Bluff",
    "sg:classifiers":[
        {
            "category":"Banks & Credit Unions",
            "subcategory":"Bank",
            "type":"Services"
        }
    ],
    "sg:phone":"+1 870 541 8000",
    "sg:postcode":"71601",
    "sg:province":"AR",
    "sg:tags":[
        "national",
        "commercial"
    ],
    "wof:name":"Bank Of America",
    "wof:placetype":"venue"
},
  "geometry": {"coordinates":[-92.004271,34.224804],"type":"Point"}
}