{
  "type": "Feature",
  "properties": {
    "iso:country":"US",
    "sg:address":"701 E Main St Ste 16",
    "sg:city":"Russellville",
    "sg:classifiers":[
        {
            "category":"Professional",
            "subcategory":"Accounting & Tax Preparation",
            "type":"Services"
        }
    ],
    "sg:phone":"+1 479 880 2441",
    "sg:postcode":"72801",
    "sg:province":"AR",
    "sg:tags":[
        "bookkeeping",
        "return",
        "accountants-certified",
        "preparation-business",
        "public"
    ],
    "wof:name":"Debbie Brown Cpa",
    "wof:placetype":"venue"
},
  "geometry": {"coordinates":[-93.125641,35.278519],"type":"Point"}
}