{
  "type": "Feature",
  "properties": {
    "iso:country":"US",
    "sg:address":"5107 Wheeler Ave",
    "sg:city":"Fort Smith",
    "sg:classifiers":[
        {
            "category":"Building & Trades",
            "subcategory":"Construction",
            "type":"Services"
        }
    ],
    "sg:phone":"+1 479 646 4331",
    "sg:postcode":"72901",
    "sg:province":"AR",
    "sg:tags":[
        "steel",
        "erection",
        "rigging",
        "forklift",
        "contractor",
        "crane"
    ],
    "wof:name":"Holmes Erection Inc",
    "wof:placetype":"venue"
},
  "geometry": {"coordinates":[-94.427222,35.334707],"type":"Point"}
}