{
  "type": "Feature",
  "properties": {
    "iso:country":"US",
    "sg:address":"1211 Old Camden Rd",
    "sg:city":"Leola",
    "sg:classifiers":[
        {
            "category":"Organizations",
            "subcategory":"Religious Organization",
            "type":"Services"
        }
    ],
    "sg:phone":"+1 870 765 2305",
    "sg:postcode":"72084",
    "sg:province":"AR",
    "sg:tags":[
        "church"
    ],
    "wof:name":"Lono Missionary Baptist Church",
    "wof:placetype":"venue"
},
  "geometry": {"coordinates":[-92.592957,34.16591],"type":"Point"}
}