{
  "type": "Feature",
  "properties": {
    "iso:country":"US",
    "sg:address":"599 NE J St",
    "sg:city":"Bentonville",
    "sg:classifiers":[
        {
            "category":"Building & Trades",
            "subcategory":"Construction",
            "type":"Services"
        }
    ],
    "sg:phone":"+1 479 273 1843",
    "sg:postcode":"72712",
    "sg:province":"AR",
    "sg:tags":[
        "system",
        "contractor",
        "air conditioning"
    ],
    "wof:name":"Comfort Systems",
    "wof:placetype":"venue"
},
  "geometry": {"coordinates":[-94.19658099999999,36.377238],"type":"Point"}
}