{
  "type": "Feature",
  "properties": {
    "addr:full":"4001 W Main St Russellville AR 72801",
    "addr:housenumber":"4001",
    "addr:postcode":"72801",
    "addr:street":"W Main St",
    "iso:country":"US",
    "sg:address":"4001 W Main St",
    "sg:city":"Russellville",
    "sg:classifiers":[
        {
            "category":"Building & Trades",
            "subcategory":"Landscaping Services",
            "type":"Services"
        },
        {
            "category":"Farming",
            "subcategory":"Nursery",
            "type":"Manufacturing & Wholesale Goods"
        }
    ],
    "sg:phone":"+1 479 968 2101",
    "sg:postcode":"72801",
    "sg:province":"AR",
    "sg:tags":[
        "lawn",
        "tree",
        "grower",
        "nursery-wholesale",
        "nurseries-plants"
    ],
    "wof:name":"Jackson's Greenhouse Nursery",
    "wof:placetype":"venue"
},
  "geometry": {"coordinates":[-93.168037,35.293991],"type":"Point"}
}