{
  "type": "Feature",
  "properties": {
    "addr:full":"1706 SE Walton Blvd Bentonville AR 72712",
    "addr:housenumber":"1706",
    "addr:postcode":"72712",
    "addr:street":"Se Walton Blvd",
    "iso:country":"US",
    "sg:address":"1706 SE Walton Blvd",
    "sg:city":"Bentonville",
    "sg:classifiers":[
        {
            "category":"Wholesale",
            "subcategory":"Machinery & Supplies",
            "type":"Manufacturing & Wholesale Goods"
        }
    ],
    "sg:phone":"+1 479 271 6635",
    "sg:postcode":"72712",
    "sg:province":"AR",
    "sg:tags":[
        "salon",
        "beauty"
    ],
    "wof:name":"Pedi-Spa",
    "wof:placetype":"venue"
},
  "geometry": {"coordinates":[-94.188496,36.335098],"type":"Point"}
}