{
  "type": "Feature",
  "properties": {
    "iso:country":"US",
    "sg:address":"9867 Oakland Rd",
    "sg:city":"Oakland",
    "sg:classifiers":[
        {
            "category":"Professional",
            "subcategory":"Engineering",
            "type":"Services"
        }
    ],
    "sg:phone":"+1 870 425 2700",
    "sg:postcode":"72661",
    "sg:province":"AR",
    "sg:tags":[
        "consulting",
        "engineer"
    ],
    "wof:name":"Corps of Engineers",
    "wof:placetype":"venue"
},
  "geometry": {"coordinates":[-92.627853,36.443378],"type":"Point"}
}