{
  "type": "Feature",
  "properties": {
    "iso:country":"US",
    "sg:address":"3100 Dugan Dr",
    "sg:city":"Little Rock",
    "sg:classifiers":[
        {
            "category":"Freight",
            "type":"Transportation"
        }
    ],
    "sg:phone":"+1 501 372 4044",
    "sg:postcode":"72206",
    "sg:province":"AR",
    "sg:tags":[
        "trucking"
    ],
    "wof:name":"Three Way Transfer Of Arkansas",
    "wof:placetype":"venue"
},
  "geometry": {"coordinates":[-92.248127,34.719139],"type":"Point"}
}