{
  "type": "Feature",
  "properties": {
    "iso:country":"US",
    "sg:address":"1200 John Barrow Rd",
    "sg:city":"Little Rock",
    "sg:classifiers":[
        {
            "category":"Personal",
            "subcategory":"Beauty Salon",
            "type":"Services"
        }
    ],
    "sg:phone":"+1 501 225 2817",
    "sg:postcode":"72205",
    "sg:province":"AR",
    "wof:name":"Salon A",
    "wof:placetype":"venue"
},
  "geometry": {"coordinates":[-92.372295,34.743524],"type":"Point"}
}