{
  "type": "Feature",
  "properties": {
    "addr:full":"1100 US Hwy 71 Mena AR 71953",
    "addr:housenumber":"1100",
    "addr:postcode":"71953",
    "addr:street":"Us Hwy 71",
    "iso:country":"US",
    "sg:address":"1100 US Hwy 71",
    "sg:city":"Mena",
    "sg:classifiers":[
        {
            "category":"Insurance",
            "subcategory":"Insurance Agent",
            "type":"Services"
        }
    ],
    "sg:phone":"+1 479 394 1181",
    "sg:postcode":"71953",
    "sg:province":"AR",
    "wof:name":"Shelter Insurance",
    "wof:placetype":"venue"
},
  "geometry": {"coordinates":[-94.220477,34.586593],"type":"Point"}
}