{
  "type": "Feature",
  "properties": {
    "iso:country":"US",
    "sg:address":"501 E Madison Ave",
    "sg:city":"Berryville",
    "sg:classifiers":[
        {
            "category":"Structure",
            "subcategory":"Office Building",
            "type":"Public Place"
        }
    ],
    "sg:phone":"+1 870 423 3083",
    "sg:postcode":"72616",
    "sg:province":"AR",
    "sg:tags":[
        "park"
    ],
    "wof:name":"C And A Properties",
    "wof:placetype":"venue"
},
  "geometry": {"coordinates":[-93.563192,36.365737],"type":"Point"}
}