{
  "type": "Feature",
  "properties": {
    "iso:country":"US",
    "sg:address":"2200 State Hwy 265 Spr",
    "sg:city":"Springdale",
    "sg:classifiers":[
        {
            "category":"Professional",
            "subcategory":"Management & Consulting",
            "type":"Services"
        }
    ],
    "sg:phone":"+1 479 751 7373",
    "sg:postcode":"72764",
    "sg:province":"AR",
    "sg:tags":[
        "food"
    ],
    "sg:website":"www.swansoncorp.com",
    "wof:name":"Swanson Corp",
    "wof:placetype":"venue"
},
  "geometry": {"coordinates":[-94.10345700000001,36.184343],"type":"Point"}
}