{
  "type": "Feature",
  "properties": {
    "iso:country":"US",
    "sg:address":"121 Valley St",
    "sg:city":"Arkadelphia",
    "sg:classifiers":[
        {
            "category":"Restaurant",
            "type":"Food & Drink"
        }
    ],
    "sg:menulink":"http://www.allmenus.com/ar/caddo/204736-taco-bell/menu/",
    "sg:postcode":"71923",
    "sg:province":"AR",
    "sg:tags":[
        "mexican"
    ],
    "wof:name":"Taco Bell",
    "wof:placetype":"venue"
},
  "geometry": {"coordinates":[-93.071483,34.173274],"type":"Point"}
}