{
  "type": "Feature",
  "properties": {
    "addr:full":"1133 N Jackson St Magnolia AR 71753",
    "addr:housenumber":"1133",
    "addr:postcode":"71753",
    "addr:street":"N Jackson St",
    "iso:country":"US",
    "sg:address":"1133 N Jackson St",
    "sg:city":"Magnolia",
    "sg:classifiers":[
        {
            "category":"Home & Garden",
            "subcategory":"Furniture",
            "type":"Retail Goods"
        }
    ],
    "sg:phone":"+1 870 234 5085",
    "sg:postcode":"71753",
    "sg:province":"AR",
    "wof:name":"Polk's Furniture City Inc",
    "wof:placetype":"venue"
},
  "geometry": {"coordinates":[-93.237201,33.275815],"type":"Point"}
}