{
  "type": "Feature",
  "properties": {
    "iso:country":"US",
    "sg:address":"100 N Currie St",
    "sg:city":"Marion",
    "sg:classifiers":[
        {
            "category":"Education",
            "subcategory":"Library",
            "type":"Public Place"
        }
    ],
    "sg:phone":"+1 870 739 3238",
    "sg:postcode":"72364",
    "sg:province":"AR",
    "wof:name":"Crittenden County Library",
    "wof:placetype":"venue"
},
  "geometry": {"coordinates":[-90.198283,35.215956],"type":"Point"}
}