{
  "type": "Feature",
  "properties": {
    "iso:country":"US",
    "sg:address":"24 Oates Rd",
    "sg:city":"Morrilton",
    "sg:phone":"+1 501 354 4735",
    "sg:postcode":"72110",
    "sg:province":"AR",
    "sg:tags":[
        "farm",
        "soybean",
        "beef",
        "feedlot",
        "cattle"
    ],
    "wof:name":"Oates Calhoun Farms Inc",
    "wof:placetype":"venue"
},
  "geometry": {"coordinates":[-92.754143,35.101813],"type":"Point"}
}