{
  "type": "Feature",
  "properties": {
    "iso:country":"US",
    "sg:address":"2918 Highway 49",
    "sg:city":"Lexa",
    "sg:classifiers":[
        {
            "category":"Manufacturing",
            "subcategory":"Food",
            "type":"Manufacturing & Wholesale Goods"
        },
        {
            "category":"Wholesale",
            "subcategory":"Groceries",
            "type":"Manufacturing & Wholesale Goods"
        },
        {
            "category":"Ice Cream",
            "type":"Food & Drink"
        }
    ],
    "sg:phone":"+1 870 572 3842",
    "sg:postcode":"72355",
    "sg:province":"AR",
    "sg:tags":[
        "frozen",
        "dessert",
        "products-wholesale"
    ],
    "sg:website":"http://www.schwans.com",
    "wof:name":"Schwan's",
    "wof:placetype":"venue"
},
  "geometry": {"coordinates":[-90.715748,34.554764],"type":"Point"}
}