{
  "type": "Feature",
  "properties": {
    "iso:country":"US",
    "sg:address":"6745 Oak Ridge Rd",
    "sg:city":"Ravenden Springs",
    "sg:classifiers":[
        {
            "category":"Personal",
            "subcategory":"Beauty Salon",
            "type":"Services"
        }
    ],
    "sg:phone":"+1 870 869 2881",
    "sg:postcode":"72460",
    "sg:province":"AR",
    "wof:name":"His N Hers Beauty Salon",
    "wof:placetype":"venue"
},
  "geometry": {"coordinates":[-91.19893399999999,36.355405],"type":"Point"}
}