{
  "type": "Feature",
  "properties": {
    "iso:country":"US",
    "sg:address":"1585 Polk Road 23",
    "sg:city":"Cove",
    "sg:classifiers":[
        {
            "category":"Farming",
            "subcategory":"Farm & Veterinary Services",
            "type":"Manufacturing & Wholesale Goods"
        }
    ],
    "sg:phone":"+1 870 387 6300",
    "sg:postcode":"71937",
    "sg:province":"AR",
    "sg:tags":[
        "livestock"
    ],
    "wof:name":"Lowrey Poultry Farm",
    "wof:placetype":"venue"
},
  "geometry": {"coordinates":[-94.332002,34.41159],"type":"Point"}
}