{
  "type": "Feature",
  "properties": {
    "iso:country":"US",
    "sg:address":"118 W Center St",
    "sg:city":"Sheridan",
    "sg:classifiers":[
        {
            "category":"Personal",
            "subcategory":"Beauty Salon",
            "type":"Services"
        }
    ],
    "sg:phone":"+1 870 942 0883",
    "sg:postcode":"72150",
    "sg:province":"AR",
    "wof:name":"All About Hair",
    "wof:placetype":"venue"
},
  "geometry": {"coordinates":[-92.401008,34.306822],"type":"Point"}
}