{
  "type": "Feature",
  "properties": {
    "iso:country":"US",
    "sg:address":"125 Albert Pike Rd",
    "sg:city":"Hot Springs",
    "sg:classifiers":[
        {
            "category":"Retail",
            "subcategory":"Portrait Studio",
            "type":"Services"
        }
    ],
    "sg:phone":"+1 501 624 3195",
    "sg:postcode":"71913",
    "sg:province":"AR",
    "sg:tags":[
        "photographer",
        "design",
        "commercial",
        "photo"
    ],
    "wof:name":"Gary's Studio Of Photography",
    "wof:placetype":"venue"
},
  "geometry": {"coordinates":[-93.07091699999999,34.497051],"type":"Point"}
}