{
  "type": "Feature",
  "properties": {
    "addr:full":"145 US Hwy 62 Avoca AR 72711",
    "addr:housenumber":"145",
    "addr:postcode":"72711",
    "addr:street":"Us Hwy 62",
    "iso:country":"US",
    "sg:address":"145 US Hwy 62",
    "sg:city":"Avoca",
    "sg:classifiers":[
        {
            "category":"Building & Trades",
            "subcategory":"Construction",
            "type":"Services"
        }
    ],
    "sg:phone":"+1 479 631 7415",
    "sg:postcode":"72711",
    "sg:province":"AR",
    "sg:tags":[
        "dock"
    ],
    "wof:name":"Superior Dock Co",
    "wof:placetype":"venue"
},
  "geometry": {"coordinates":[-94.071713,36.405496],"type":"Point"}
}