{
  "type": "Feature",
  "properties": {
    "iso:country":"US",
    "sg:address":"700 S 45th St",
    "sg:city":"Rogers",
    "sg:classifiers":[
        {
            "category":"Communications",
            "type":"Services"
        }
    ],
    "sg:phone":"+1 479 636 6747",
    "sg:postcode":"72758",
    "sg:province":"AR",
    "sg:tags":[
        "communication"
    ],
    "wof:name":"Northwest Arkansas Tower",
    "wof:placetype":"venue"
},
  "geometry": {"coordinates":[-94.179755,36.32997],"type":"Point"}
}