{
  "type": "Feature",
  "properties": {
    "iso:country":"US",
    "sg:address":"1207 Quail Ter",
    "sg:city":"Rogers",
    "sg:classifiers":[
        {
            "category":"Insurance",
            "subcategory":"Insurance Agent",
            "type":"Services"
        }
    ],
    "sg:phone":"+1 479 986 0338",
    "sg:postcode":"72756",
    "sg:province":"AR",
    "wof:name":"Nationwide Insurance",
    "wof:placetype":"venue"
},
  "geometry": {"coordinates":[-94.171869,36.348747],"type":"Point"}
}