{
  "type": "Feature",
  "properties": {
    "iso:country":"US",
    "sg:address":"15100 Jason St",
    "sg:city":"Alexander",
    "sg:classifiers":[
        {
            "category":"Education",
            "subcategory":"School",
            "type":"Public Place"
        }
    ],
    "sg:phone":"+1 501 847 6505",
    "sg:postcode":"72002",
    "sg:province":"AR",
    "wof:name":"Woodland Hills Christian Schl",
    "wof:placetype":"venue"
},
  "geometry": {"coordinates":[-92.445822,34.615779],"type":"Point"}
}