{
  "type": "Feature",
  "properties": {
    "iso:country":"US",
    "sg:address":"202 Ewen St",
    "sg:city":"Weiner",
    "sg:classifiers":[
        {
            "category":"Professional",
            "type":"Services"
        }
    ],
    "sg:phone":"+1 870 684 2205",
    "sg:postcode":"72479",
    "sg:province":"AR",
    "sg:tags":[
        "establishment"
    ],
    "wof:name":"Adm Riceland",
    "wof:placetype":"venue"
},
  "geometry": {"coordinates":[-90.901117,35.618714],"type":"Point"}
}