{
  "type": "Feature",
  "properties": {
    "addr:full":"61 Frizzel Dr Lakeview AR 72642",
    "addr:housenumber":"61",
    "addr:postcode":"72642",
    "addr:street":"Frizzel Dr",
    "iso:country":"US",
    "sg:address":"61 Frizzel Dr",
    "sg:city":"Lakeview",
    "sg:classifiers":[
        {
            "category":"Manufacturing",
            "subcategory":"Buildings",
            "type":"Manufacturing & Wholesale Goods"
        },
        {
            "category":"Building & Trades",
            "subcategory":"Construction",
            "type":"Services"
        }
    ],
    "sg:phone":"+1 870 431 4284",
    "sg:postcode":"72642",
    "sg:province":"AR",
    "sg:tags":[
        "home",
        "builder",
        "contractor"
    ],
    "wof:name":"Bob Ward Construction Inc",
    "wof:placetype":"venue"
},
  "geometry": {"coordinates":[-92.532616,36.373609],"type":"Point"}
}