{
  "type": "Feature",
  "properties": {
    "iso:country":"US",
    "sg:address":"2014 N Church St",
    "sg:city":"Jonesboro",
    "sg:classifiers":[
        {
            "category":"Organizations",
            "subcategory":"Religious Organization",
            "type":"Services"
        }
    ],
    "sg:phone":"+1 870 932 1570",
    "sg:postcode":"72401",
    "sg:province":"AR",
    "sg:tags":[
        "church"
    ],
    "wof:name":"Immanuel Missionary Baptist",
    "wof:placetype":"venue"
},
  "geometry": {"coordinates":[-90.703191,35.861135],"type":"Point"}
}