{
  "type": "Feature",
  "properties": {
    "iso:country":"US",
    "sg:address":"1445 Lee Road 439",
    "sg:city":"Moro",
    "sg:phone":"+1 870 768 4371",
    "sg:postcode":"72368",
    "sg:province":"AR",
    "sg:tags":[
        "product",
        "wheat",
        "farm",
        "food",
        "soybean",
        "rice"
    ],
    "wof:name":"Abraham Huling",
    "wof:placetype":"venue"
},
  "geometry": {"coordinates":[-90.96120500000001,34.82744],"type":"Point"}
}