{
  "type": "Feature",
  "properties": {
    "addr:full":"1123 S University Ave Little Rock AR 72204",
    "addr:housenumber":"1123",
    "addr:postcode":"72204",
    "addr:street":"S University Ave",
    "iso:country":"US",
    "sg:address":"1123 S University Ave",
    "sg:city":"Little Rock",
    "sg:classifiers":[
        {
            "category":"Organizations",
            "subcategory":"Professional Association",
            "type":"Services"
        }
    ],
    "sg:phone":"+1 501 664 8680",
    "sg:postcode":"72204",
    "sg:province":"AR",
    "sg:tags":[
        "business",
        "trade"
    ],
    "wof:name":"Arkansas Grocer & Retail Assn",
    "wof:placetype":"venue"
},
  "geometry": {"coordinates":[-92.341335,34.742513],"type":"Point"}
}