{
  "type": "Feature",
  "properties": {
    "iso:country":"US",
    "sg:address":"2908 Robinson St",
    "sg:city":"Newport",
    "sg:classifiers":[
        {
            "category":"Social Services",
            "subcategory":"Adult Care",
            "type":"Services"
        }
    ],
    "sg:phone":"+1 870 523 3819",
    "sg:postcode":"72112",
    "sg:province":"AR",
    "sg:tags":[
        "home",
        "group"
    ],
    "wof:name":"Jackson County Learning Ctr",
    "wof:placetype":"venue"
},
  "geometry": {"coordinates":[-91.246223,35.612118],"type":"Point"}
}