{
  "type": "Feature",
  "properties": {
    "iso:country":"US",
    "sg:address":"453406 Burbin St",
    "sg:city":"Afton",
    "sg:classifiers":[
        {
            "category":"Building & Trades",
            "subcategory":"Construction",
            "type":"Services"
        }
    ],
    "sg:phone":"+1 918 782 3609",
    "sg:postcode":"74331",
    "sg:province":"OK",
    "sg:tags":[
        "residential"
    ],
    "wof:name":"Anthony A Hoyt",
    "wof:placetype":"venue"
},
  "geometry": {"coordinates":[-94.928651,36.576701],"type":"Point"}
}