{
  "type": "Feature",
  "properties": {
    "addr:full":"501 Bryant Dr Donaldson AR 71941",
    "addr:housenumber":"501",
    "addr:postcode":"71941",
    "addr:street":"Bryant Dr",
    "iso:country":"US",
    "sg:address":"501 Bryant Dr",
    "sg:city":"Donaldson",
    "sg:classifiers":[
        {
            "category":"Government",
            "subcategory":"Post Office",
            "type":"Public Place"
        }
    ],
    "sg:phone":"+1 501 384 5461",
    "sg:postcode":"71941",
    "sg:province":"AR",
    "wof:name":"US Post Office",
    "wof:placetype":"venue"
},
  "geometry": {"coordinates":[-92.917281,34.234247],"type":"Point"}
}