{
  "type": "Feature",
  "properties": {
    "iso:country":"US",
    "sg:address":"2718 N College Ave",
    "sg:city":"Fayetteville",
    "sg:classifiers":[
        {
            "category":"Autos & Motor Vehicles",
            "subcategory":"Automobile Sales",
            "type":"Retail Goods"
        },
        {
            "category":"Retail",
            "subcategory":"Auto Rental",
            "type":"Services"
        }
    ],
    "sg:phone":"+1 479 442 7368",
    "sg:postcode":"72703",
    "sg:province":"AR",
    "sg:tags":[
        "truck",
        "leasing",
        "car"
    ],
    "sg:website":"http://www.enterprise.com/car_rental/deeplinkmap.do?gpbr=5175&bid=004&cnty=US&arc=YPTRL01&cm_mmc=Yellowpages.com-_-IYP-_-Tradelisting-_-branch",
    "wof:name":"Enterprise Rent-A-Car",
    "wof:placetype":"venue"
},
  "geometry": {"coordinates":[-94.15009999999999,36.099958],"type":"Point"}
}