{
  "type": "Feature",
  "properties": {
    "addr:full":"48 Co Rd 7751 Wynne AR 72396",
    "addr:housenumber":"48",
    "addr:postcode":"7751;72396",
    "addr:street":"Co Rd",
    "iso:country":"US",
    "sg:address":"48 Co Rd 7751",
    "sg:city":"Wynne",
    "sg:classifiers":[
        {
            "category":"Building & Trades",
            "subcategory":"Construction",
            "type":"Services"
        }
    ],
    "sg:phone":"+1 870 238 1300",
    "sg:postcode":"72396",
    "sg:province":"AR",
    "sg:tags":[
        "home",
        "builder",
        "residential"
    ],
    "wof:name":"Hendrix Construction LLC",
    "wof:placetype":"venue"
},
  "geometry": {"coordinates":[-90.727197,35.213203],"type":"Point"}
}