{
  "type": "Feature",
  "properties": {
    "addr:full":"263 Lipton Hwy Jersey AR 71651",
    "addr:housenumber":"263",
    "addr:postcode":"71651",
    "addr:street":"Lipton Hwy Jersey",
    "iso:country":"US",
    "sg:address":"263 Lipton Hwy",
    "sg:city":"Jersey",
    "sg:classifiers":[
        {
            "category":"Freight",
            "type":"Transportation"
        }
    ],
    "sg:phone":"+1 870 463 2539",
    "sg:postcode":"71651",
    "sg:province":"AR",
    "sg:tags":[
        "local",
        "trucking"
    ],
    "wof:name":"M & R Enterprises Mb Inc",
    "wof:placetype":"venue"
},
  "geometry": {"coordinates":[-92.342201,33.292004],"type":"Point"}
}