{
  "type": "Feature",
  "properties": {
    "addr:full":"10810 Peach Orchard Rd Bentonville AR 72712",
    "addr:housenumber":"10810",
    "addr:postcode":"72712",
    "addr:street":"Peach Orchard Rd",
    "iso:country":"US",
    "sg:address":"10810 Peach Orchard Rd",
    "sg:city":"Bentonville",
    "sg:classifiers":[
        {
            "category":"Building & Trades",
            "subcategory":"Construction",
            "type":"Services"
        }
    ],
    "sg:phone":"+1 479 273 5974",
    "sg:postcode":"72712",
    "sg:province":"AR",
    "sg:tags":[
        "roofing",
        "contractor"
    ],
    "wof:name":"Brewer's Roofing",
    "wof:placetype":"venue"
},
  "geometry": {"coordinates":[-94.245307,36.381658],"type":"Point"}
}