{
  "type": "Feature",
  "properties": {
    "addr:full":"5741 State Hwy 178 W Lakeview AR 72642",
    "addr:housenumber":"5741",
    "addr:postcode":"72642",
    "addr:street":"State Hwy 178 W",
    "iso:country":"US",
    "sg:address":"5741 State Hwy 178 W",
    "sg:city":"Lakeview",
    "sg:classifiers":[
        {
            "category":"Shopping",
            "subcategory":"Gifts & Souvenirs",
            "type":"Retail Goods"
        }
    ],
    "sg:phone":"+1 870 431 4438",
    "sg:postcode":"72642",
    "sg:province":"AR",
    "sg:tags":[
        "shop"
    ],
    "wof:name":"Creative Gift Studio",
    "wof:placetype":"venue"
},
  "geometry": {"coordinates":[-92.543306,36.369912],"type":"Point"}
}