{
  "type": "Feature",
  "properties": {
    "iso:country":"US",
    "sg:address":"701 S 52nd St",
    "sg:city":"Rogers",
    "sg:classifiers":[
        {
            "category":"Banks & Credit Unions",
            "subcategory":"Bank",
            "type":"Services"
        }
    ],
    "sg:phone":"+1 479 271 4300",
    "sg:postcode":"72758",
    "sg:province":"AR",
    "wof:name":"Bancorpsouth",
    "wof:placetype":"venue"
},
  "geometry": {"coordinates":[-94.1858,36.3265],"type":"Point"}
}