{
  "type": "Feature",
  "properties": {
    "iso:country":"US",
    "sg:address":"240 Trotter Ln",
    "sg:city":"Rogers",
    "sg:classifiers":[
        {
            "category":"Freight",
            "type":"Transportation"
        }
    ],
    "sg:phone":"+1 479 636 3710",
    "sg:postcode":"72756",
    "sg:province":"AR",
    "sg:tags":[
        "operator",
        "trucking"
    ],
    "wof:name":"Trotter",
    "wof:placetype":"venue"
},
  "geometry": {"coordinates":[-94.081756,36.401272],"type":"Point"}
}