{
  "type": "Feature",
  "properties": {
    "iso:country":"US",
    "sg:address":"1595 Falls Blvd N",
    "sg:city":"Wynne",
    "sg:classifiers":[
        {
            "category":"Manufacturing",
            "subcategory":"Glass & Minerals",
            "type":"Manufacturing & Wholesale Goods"
        },
        {
            "category":"Retail",
            "subcategory":"Auto Repair",
            "type":"Services"
        }
    ],
    "sg:phone":"+1 870 238 0250",
    "sg:postcode":"72396",
    "sg:province":"AR",
    "sg:tags":[
        "plate",
        "window",
        "windshield",
        "glass-auto"
    ],
    "wof:name":"Priority Glass",
    "wof:placetype":"venue"
},
  "geometry": {"coordinates":[-90.783314,35.239755],"type":"Point"}
}