{
  "type": "Feature",
  "properties": {
    "addr:full":"5307 Tennessee Ridge Rd Fort Smith OK 72916",
    "addr:housenumber":"5307",
    "addr:postcode":"72916",
    "addr:street":"Tennessee Ridge Rd",
    "iso:country":"US",
    "sg:address":"5307 Tennessee Ridge Rd",
    "sg:city":"Fort Smith",
    "sg:classifiers":[
        {
            "category":"Retail",
            "subcategory":"Laundry & Dry Cleaning",
            "type":"Services"
        }
    ],
    "sg:phone":"+1 479 646 8800",
    "sg:postcode":"72916",
    "sg:province":"OK",
    "sg:tags":[
        "cleaners",
        "rug",
        "carpet"
    ],
    "wof:name":"Chem Dry Carpet & Upholstery",
    "wof:placetype":"venue"
},
  "geometry": {"coordinates":[-94.376367,35.260251],"type":"Point"}
}