{
  "type": "Feature",
  "properties": {
    "iso:country":"US",
    "sg:address":"1063 Main St",
    "sg:city":"Vilonia",
    "sg:classifiers":[
        {
            "category":"Personal",
            "subcategory":"Beauty Salon",
            "type":"Services"
        }
    ],
    "sg:phone":"+1 501 796 8790",
    "sg:postcode":"72173",
    "sg:province":"AR",
    "wof:name":"Valorie's Mane Street Salon",
    "wof:placetype":"venue"
},
  "geometry": {"coordinates":[-92.214081,35.083241],"type":"Point"}
}