{
  "type": "Feature",
  "properties": {
    "iso:country":"US",
    "sg:address":"3011 Cardinal Ln",
    "sg:city":"Lavaca",
    "sg:classifiers":[
        {
            "category":"Farming",
            "subcategory":"Farm",
            "type":"Manufacturing & Wholesale Goods"
        }
    ],
    "sg:phone":"+1 479 674 5378",
    "sg:postcode":"72933",
    "sg:province":"AR",
    "sg:tags":[
        "crop",
        "general"
    ],
    "wof:name":"Howard L Carruth",
    "wof:placetype":"venue"
},
  "geometry": {"coordinates":[-94.147129,35.319907],"type":"Point"}
}