{
  "type": "Feature",
  "properties": {
    "iso:country":"US",
    "sg:address":"1590 Hwy 70 E",
    "sg:city":"Lonoke",
    "sg:classifiers":[
        {
            "category":"Real Estate",
            "subcategory":"Developer",
            "type":"Services"
        }
    ],
    "sg:phone":"+1 501 676 3951",
    "sg:postcode":"72086",
    "sg:province":"AR",
    "sg:tags":[
        "cemetery"
    ],
    "wof:name":"Sunset Memorial Gardens",
    "wof:placetype":"venue"
},
  "geometry": {"coordinates":[-91.867633,34.78351],"type":"Point"}
}