{
  "type": "Feature",
  "properties": {
    "iso:country":"US",
    "sg:address":"12 W Sunbridge Dr",
    "sg:city":"Fayetteville",
    "sg:classifiers":[
        {
            "category":"Insurance",
            "subcategory":"Insurance Agent",
            "type":"Services"
        }
    ],
    "sg:phone":"+1 479 571 1573",
    "sg:postcode":"72703",
    "sg:province":"AR",
    "wof:name":"Adam B Brandes",
    "wof:placetype":"venue"
},
  "geometry": {"coordinates":[-94.157112,36.098044],"type":"Point"}
}