{
  "type": "Feature",
  "properties": {
    "iso:country":"US",
    "sg:address":"1117 Malcolm Ave",
    "sg:city":"Newport",
    "sg:classifiers":[
        {
            "category":"Building & Trades",
            "subcategory":"Plumbing",
            "type":"Services"
        }
    ],
    "sg:phone":"+1 870 523 2776",
    "sg:postcode":"72112",
    "sg:province":"AR",
    "sg:tags":[
        "plumbing",
        "contractor"
    ],
    "wof:name":"Buford's Plumbing-Htg & AC",
    "wof:placetype":"venue"
},
  "geometry": {"coordinates":[-91.26644400000001,35.606273],"type":"Point"}
}