{
  "type": "Feature",
  "properties": {
    "iso:country":"US",
    "sg:address":"507 N Holman St",
    "sg:city":"Brookland",
    "sg:classifiers":[
        {
            "category":"Building & Trades",
            "subcategory":"Electrical",
            "type":"Services"
        }
    ],
    "sg:phone":"+1 870 931 7519",
    "sg:postcode":"72417",
    "sg:province":"AR",
    "sg:tags":[
        "electrical",
        "contractor"
    ],
    "wof:name":"Luna Electric Service",
    "wof:placetype":"venue"
},
  "geometry": {"coordinates":[-90.579115,35.902743],"type":"Point"}
}