{
  "type": "Feature",
  "properties": {
    "iso:country":"US",
    "sg:address":"940 S Division St",
    "sg:city":"Blytheville",
    "sg:classifiers":[
        {
            "category":"Shopping",
            "type":"Retail Goods"
        }
    ],
    "sg:phone":"+1 870 762 2601",
    "sg:postcode":"72315",
    "sg:province":"AR",
    "sg:tags":[
        "monument"
    ],
    "wof:name":"Mc Haney Monuments",
    "wof:placetype":"venue"
},
  "geometry": {"coordinates":[-89.918792,35.918704],"type":"Point"}
}