{
  "type": "Feature",
  "properties": {
    "iso:country":"US",
    "sg:address":"961 Anderson Cir",
    "sg:city":"Heber Springs",
    "sg:classifiers":[
        {
            "category":"Professional",
            "type":"Services"
        }
    ],
    "sg:phone":"+1 501 362 3030",
    "sg:postcode":"72543",
    "sg:province":"AR",
    "wof:name":"Rhonda Ewing",
    "wof:placetype":"venue"
},
  "geometry": {"coordinates":[-92.043663,35.502475],"type":"Point"}
}