{
  "type": "Feature",
  "properties": {
    "addr:full":"19593 Shannon Ln Canehill AR 72717",
    "addr:housenumber":"19593",
    "addr:postcode":"72717",
    "addr:street":"Shannon Ln",
    "iso:country":"US",
    "sg:address":"19593 Shannon Ln",
    "sg:city":"Canehill",
    "sg:classifiers":[
        {
            "category":"Professional",
            "type":"Services"
        }
    ],
    "sg:phone":"+1 479 824 3723",
    "sg:postcode":"72717",
    "sg:province":"AR",
    "wof:name":"Darlene Spencer",
    "wof:placetype":"venue"
},
  "geometry": {"coordinates":[-94.427082,35.889878],"type":"Point"}
}