{
  "type": "Feature",
  "properties": {
    "iso:country":"US",
    "sg:address":"1124 Oak St",
    "sg:city":"Conway",
    "sg:classifiers":[
        {
            "category":"Shopping",
            "subcategory":"Clothing, Apparel, & Fashions",
            "type":"Retail Goods"
        }
    ],
    "sg:phone":"+1 501 329 5058",
    "sg:postcode":"72032",
    "sg:province":"AR",
    "sg:tags":[
        "alteration"
    ],
    "wof:name":"Fit & Fix It",
    "wof:placetype":"venue"
},
  "geometry": {"coordinates":[-92.440004,35.090982],"type":"Point"}
}