{
  "type": "Feature",
  "properties": {
    "addr:full":"249 Dyer St Mountain Home AR 72653",
    "addr:housenumber":"249",
    "addr:postcode":"72653",
    "addr:street":"Dyer St",
    "iso:country":"US",
    "sg:address":"249 Dyer St",
    "sg:city":"Mountain Home",
    "sg:classifiers":[
        {
            "category":"Organizations",
            "subcategory":"Religious Organization",
            "type":"Services"
        }
    ],
    "sg:phone":"+1 870 425 2832",
    "sg:postcode":"72653",
    "sg:province":"AR",
    "sg:tags":[
        "church"
    ],
    "wof:name":"St Peter's Catholic Church",
    "wof:placetype":"venue"
},
  "geometry": {"coordinates":[-92.388645,36.339576],"type":"Point"}
}