{
  "type": "Feature",
  "properties": {
    "iso:country":"US",
    "sg:address":"2810 E Highland Dr",
    "sg:city":"Jonesboro",
    "sg:classifiers":[
        {
            "category":"Banks & Credit Unions",
            "subcategory":"Bank",
            "type":"Services"
        }
    ],
    "sg:phone":"+1 870 972 5200",
    "sg:postcode":"72401",
    "sg:province":"AR",
    "sg:tags":[
        "second",
        "hand"
    ],
    "wof:name":"My Girlfriends Closet",
    "wof:placetype":"venue"
},
  "geometry": {"coordinates":[-90.67074599999999,35.821161],"type":"Point"}
}