{
  "type": "Feature",
  "properties": {
    "addr:full":"803 Airport Ave Springdale AR 72764",
    "addr:housenumber":"803",
    "addr:postcode":"72764",
    "addr:street":"Airport Ave",
    "iso:country":"US",
    "sg:address":"803 Airport Ave",
    "sg:city":"Springdale",
    "sg:classifiers":[
        {
            "category":"Building & Trades",
            "subcategory":"Equipment Rental",
            "type":"Services"
        }
    ],
    "sg:phone":"+1 479 751 3995",
    "sg:postcode":"72764",
    "sg:province":"AR",
    "sg:tags":[
        "aircraft",
        "leasing",
        "charter"
    ],
    "wof:name":"Adventure Flight Aviation Inc",
    "wof:placetype":"venue"
},
  "geometry": {"coordinates":[-94.124438,36.17417],"type":"Point"}
}