{
  "type": "Feature",
  "properties": {
    "addr:full":"6821 S V St Fort Smith AR 72903",
    "addr:housenumber":"6821",
    "addr:postcode":"72903",
    "addr:street":"S V St",
    "iso:country":"US",
    "sg:address":"6821 S V St",
    "sg:city":"Fort Smith",
    "sg:classifiers":[
        {
            "category":"Real Estate",
            "subcategory":"Real Estate Agent",
            "type":"Services"
        }
    ],
    "sg:phone":"+1 479 452 7128",
    "sg:postcode":"72903",
    "sg:province":"AR",
    "wof:name":"Robert J Allen",
    "wof:placetype":"venue"
},
  "geometry": {"coordinates":[-94.355902,35.359041],"type":"Point"}
}