{
  "type": "Feature",
  "properties": {
    "addr:full":"310 E 5th Ave Pine Bluff AR 71601",
    "addr:housenumber":"310",
    "addr:postcode":"71601",
    "addr:street":"E 5Th Ave",
    "iso:country":"US",
    "sg:address":"310 E 5th Ave",
    "sg:city":"Pine Bluff",
    "sg:classifiers":[
        {
            "category":"Restaurant",
            "type":"Food & Drink"
        }
    ],
    "sg:phone":"+1 870 534 9811",
    "sg:postcode":"71601",
    "sg:province":"AR",
    "wof:name":"Sno-White Grill",
    "wof:placetype":"venue"
},
  "geometry": {"coordinates":[-92.000469,34.224738],"type":"Point"}
}