{
  "type": "Feature",
  "properties": {
    "iso:country":"US",
    "sg:address":"8 Westfield Dr",
    "sg:city":"Little Rock",
    "sg:classifiers":[
        {
            "category":"Building & Trades",
            "subcategory":"Construction",
            "type":"Services"
        }
    ],
    "sg:phone":"+1 501 680 4643",
    "sg:postcode":"72210",
    "sg:province":"AR",
    "sg:tags":[
        "hanging",
        "contractor"
    ],
    "wof:name":"AR Professional Painting",
    "wof:placetype":"venue"
},
  "geometry": {"coordinates":[-92.424696,34.664726],"type":"Point"}
}