{
  "type": "Feature",
  "properties": {
    "addr:full":"2109 Whyte Dr North Little Rock AR 72117",
    "addr:housenumber":"2109",
    "addr:postcode":"72117",
    "addr:street":"Whyte Dr",
    "iso:country":"US",
    "sg:address":"2109 Whyte Dr",
    "sg:city":"North Little Rock",
    "sg:classifiers":[
        {
            "category":"Professional",
            "type":"Services"
        }
    ],
    "sg:phone":"+1 501 324 2400",
    "sg:postcode":"72117",
    "sg:province":"AR",
    "wof:name":"Blue Duck Productions",
    "wof:placetype":"venue"
},
  "geometry": {"coordinates":[-92.206301,34.772261],"type":"Point"}
}