{
  "type": "Feature",
  "properties": {
    "iso:country":"US",
    "sg:address":"116 Agee Ave SW",
    "sg:city":"Camden",
    "sg:classifiers":[
        {
            "category":"Utilities",
            "subcategory":"Water",
            "type":"Services"
        }
    ],
    "sg:phone":"+1 870 836 6914",
    "sg:postcode":"71701",
    "sg:province":"AR",
    "sg:tags":[
        "company",
        "sewage"
    ],
    "wof:name":"French Port Water",
    "wof:placetype":"venue"
},
  "geometry": {"coordinates":[-92.84329,33.584311],"type":"Point"}
}