{
  "type": "Feature",
  "properties": {
    "addr:full":"5 Gapview Rd Conway AR 72032",
    "addr:housenumber":"5",
    "addr:postcode":"72032",
    "addr:street":"Gapview Rd",
    "iso:country":"US",
    "sg:address":"5 Gapview Rd",
    "sg:city":"Conway",
    "sg:classifiers":[
        {
            "category":"Shopping",
            "subcategory":"Gifts & Souvenirs",
            "type":"Retail Goods"
        }
    ],
    "sg:phone":"+1 501 327 8049",
    "sg:postcode":"72032",
    "sg:province":"AR",
    "sg:tags":[
        "shop"
    ],
    "wof:name":"Pickles Gap Village",
    "wof:placetype":"venue"
},
  "geometry": {"coordinates":[-92.404273,35.124702],"type":"Point"}
}