{
  "type": "Feature",
  "properties": {
    "iso:country":"US",
    "sg:address":"146 Cherry Spring Rd",
    "sg:city":"Dierks",
    "sg:classifiers":[
        {
            "category":"Utilities",
            "subcategory":"Electric",
            "type":"Services"
        }
    ],
    "sg:phone":"+1 870 286 2302",
    "sg:postcode":"71833",
    "sg:province":"AR",
    "wof:name":"Arkansas Electric",
    "wof:placetype":"venue"
},
  "geometry": {"coordinates":[-94.027567,34.102137],"type":"Point"}
}