{
  "type": "Feature",
  "properties": {
    "iso:country":"US",
    "sg:address":"218 Lower Ridge Rd",
    "sg:city":"Conway",
    "sg:classifiers":[
        {
            "category":"Professional",
            "subcategory":"Detective & Security Services",
            "type":"Services"
        }
    ],
    "sg:phone":"+1 501 327 5326",
    "sg:postcode":"72032",
    "sg:province":"AR",
    "sg:tags":[
        "polygraph"
    ],
    "wof:name":"Bailey's Southwestern Bur",
    "wof:placetype":"venue"
},
  "geometry": {"coordinates":[-92.383223,35.110276],"type":"Point"}
}