{
  "type": "Feature",
  "properties": {
    "iso:country":"US",
    "sg:address":"2100 Hwy 412 E",
    "sg:city":"Siloam Springs",
    "sg:classifiers":[
        {
            "category":"Autos & Motor Vehicles",
            "subcategory":"Automobile Sales",
            "type":"Retail Goods"
        }
    ],
    "sg:phone":"+1 479 524 9701",
    "sg:postcode":"72761",
    "sg:province":"OK",
    "sg:tags":[
        "car",
        "dealer"
    ],
    "wof:name":"2 B's Auto Sales",
    "wof:placetype":"venue"
},
  "geometry": {"coordinates":[-94.521818,36.175242],"type":"Point"}
}