{
  "type": "Feature",
  "properties": {
    "iso:country":"US",
    "sg:address":"5660 Warden Rd",
    "sg:city":"N Little Rock",
    "sg:classifiers":[
        {
            "category":"Autos & Motor Vehicles",
            "subcategory":"Automobile Sales",
            "type":"Retail Goods"
        }
    ],
    "sg:phone":"+1 501 835 9995",
    "sg:postcode":"72116",
    "sg:province":"AR",
    "sg:tags":[
        "car",
        "dealer"
    ],
    "wof:name":"North Point Hyundai North",
    "wof:placetype":"venue"
},
  "geometry": {"coordinates":[-92.209156,34.80781],"type":"Point"}
}