{
  "type": "Feature",
  "properties": {
    "iso:country":"US",
    "sg:address":"6967 Hwy 62 W",
    "sg:city":"Eureka Springs",
    "sg:classifiers":[
        {
            "category":"Building & Trades",
            "subcategory":"Plumbing",
            "type":"Services"
        }
    ],
    "sg:phone":"+1 479 363 0300",
    "sg:postcode":"72632",
    "sg:province":"AR",
    "sg:tags":[
        "contractor"
    ],
    "wof:name":"S & L Mech & Sales",
    "wof:placetype":"venue"
},
  "geometry": {"coordinates":[-93.66658,36.399364],"type":"Point"}
}