{
  "type": "Feature",
  "properties": {
    "addr:full":"1563 W Hudson Rd Rogers AR 72756",
    "addr:housenumber":"1563",
    "addr:postcode":"72756",
    "addr:street":"W Hudson Rd",
    "iso:country":"US",
    "sg:address":"1563 W Hudson Rd",
    "sg:city":"Rogers",
    "sg:classifiers":[
        {
            "category":"Shopping",
            "type":"Retail Goods"
        }
    ],
    "sg:phone":"+1 479 636 5223",
    "sg:postcode":"72756",
    "sg:province":"AR",
    "sg:tags":[
        "merchandise",
        "business"
    ],
    "wof:name":"Northwest Ark Pools & Spa Svcs",
    "wof:placetype":"venue"
},
  "geometry": {"coordinates":[-94.139308,36.35564],"type":"Point"}
}