{
  "type": "Feature",
  "properties": {
    "addr:full":"1609 Brentwood Dr Pine Bluff AR 71601",
    "addr:housenumber":"1609",
    "addr:postcode":"71601",
    "addr:street":"Brentwood Dr",
    "iso:country":"US",
    "sg:address":"1609 Brentwood Dr",
    "sg:city":"Pine Bluff",
    "sg:classifiers":[
        {
            "category":"Personal",
            "subcategory":"Beauty Salon",
            "type":"Services"
        }
    ],
    "sg:phone":"+1 870 536 3811",
    "sg:postcode":"71601",
    "sg:province":"AR",
    "sg:tags":[
        "shop"
    ],
    "wof:name":"Belmont Beauty Salon",
    "wof:placetype":"venue"
},
  "geometry": {"coordinates":[-91.980295,34.213247],"type":"Point"}
}