{
  "type": "Feature",
  "properties": {
    "iso:country":"US",
    "sg:address":"108 Jeffress Curve Rd",
    "sg:city":"Crossett",
    "sg:classifiers":[
        {
            "category":"Professional",
            "subcategory":"Accounting & Tax Preparation",
            "type":"Services"
        }
    ],
    "sg:phone":"+1 870 364 3040",
    "sg:postcode":"71635",
    "sg:province":"AR",
    "sg:tags":[
        "return",
        "preparation-business"
    ],
    "wof:name":"Anns Tax Service",
    "wof:placetype":"venue"
},
  "geometry": {"coordinates":[-92.065229,33.152929],"type":"Point"}
}