{
  "type": "Feature",
  "properties": {
    "iso:country":"US",
    "sg:address":"1900 Grand Ave",
    "sg:city":"Fort Smith",
    "sg:classifiers":[
        {
            "category":"Food & Beverages",
            "subcategory":"Groceries & Convenience Stores",
            "type":"Retail Goods"
        }
    ],
    "sg:phone":"+1 479 782 8404",
    "sg:postcode":"72901",
    "sg:province":"AR",
    "wof:name":"Northside Convenience No 1",
    "wof:placetype":"venue"
},
  "geometry": {"coordinates":[-94.405564,35.386099],"type":"Point"}
}