{
  "type": "Feature",
  "properties": {
    "addr:full":"2301 E Main St Russellville AR 72802",
    "addr:housenumber":"2301",
    "addr:postcode":"72802",
    "addr:street":"E Main St",
    "iso:country":"US",
    "sg:address":"2301 E Main St",
    "sg:city":"Russellville",
    "sg:classifiers":[
        {
            "category":"Utilities",
            "subcategory":"Mobile Phone",
            "type":"Services"
        },
        {
            "category":"Shopping",
            "subcategory":"Mobile Phones",
            "type":"Retail Goods"
        }
    ],
    "sg:phone":"+1 479 964 0099",
    "sg:postcode":"72802",
    "sg:province":"AR",
    "sg:tags":[
        "supply",
        "communication",
        "telephone",
        "wireless",
        "equipment",
        "cellular"
    ],
    "wof:name":"Verizon Wireless",
    "wof:placetype":"venue"
},
  "geometry": {"coordinates":[-93.10694100000001,35.27821],"type":"Point"}
}