{
  "type": "Feature",
  "properties": {
    "iso:country":"US",
    "sg:address":"7 Kingshighway",
    "sg:city":"Eureka Springs",
    "sg:classifiers":[
        {
            "category":"Travel",
            "subcategory":"Hotels & Motels",
            "type":"Entertainment"
        }
    ],
    "sg:phone":"+1 479 253 9649",
    "sg:postcode":"72632",
    "sg:province":"AR",
    "sg:tags":[
        "breakfast",
        "accommodation",
        "bed"
    ],
    "wof:name":"Red Bud Manor Inn",
    "wof:placetype":"venue"
},
  "geometry": {"coordinates":[-93.745925,36.399816],"type":"Point"}
}