{
  "type": "Feature",
  "properties": {
    "iso:country":"US",
    "sg:address":"2907 Kavanaugh Blvd",
    "sg:city":"Little Rock",
    "sg:classifiers":[
        {
            "category":"Professional",
            "subcategory":"Business Services",
            "type":"Services"
        }
    ],
    "sg:phone":"+1 501 664 3445",
    "sg:postcode":"72205",
    "sg:province":"AR",
    "sg:tags":[
        "interior",
        "consultant",
        "design",
        "decorator"
    ],
    "sg:website":"www.hillcrestinteriors.com",
    "wof:name":"Hillcrest Interiors",
    "wof:placetype":"venue"
},
  "geometry": {"coordinates":[-92.325896,34.75837],"type":"Point"}
}