{
  "type": "Feature",
  "properties": {
    "addr:full":"675 Heber Springs Rd Batesville AR 72501",
    "addr:housenumber":"675",
    "addr:postcode":"72501",
    "addr:street":"Heber Springs Rd",
    "iso:country":"US",
    "sg:address":"675 Heber Springs Rd",
    "sg:city":"Batesville",
    "sg:classifiers":[
        {
            "category":"Building & Trades",
            "subcategory":"Landscaping Services",
            "type":"Services"
        }
    ],
    "sg:phone":"+1 870 251 1165",
    "sg:postcode":"72501",
    "sg:province":"AR",
    "sg:tags":[
        "lawn",
        "maintenance",
        "grounds"
    ],
    "wof:name":"Four All Seasons Lawn Care",
    "wof:placetype":"venue"
},
  "geometry": {"coordinates":[-91.655213,35.735395],"type":"Point"}
}