{
  "type": "Feature",
  "properties": {
    "addr:full":"6375 N State Hwy 181 Blytheville AR 72315",
    "addr:housenumber":"6375",
    "addr:postcode":"72315",
    "addr:street":"N State Hwy 181 Blytheville",
    "iso:country":"US",
    "sg:address":"6375 N State Hwy 181",
    "sg:city":"Blytheville",
    "sg:classifiers":[
        {
            "category":"Social Services",
            "subcategory":"Child Care",
            "type":"Services"
        }
    ],
    "sg:phone":"+1 870 532 6777",
    "sg:postcode":"72315",
    "sg:province":"AR",
    "wof:name":"Kids World Learning Ctr",
    "wof:placetype":"venue"
},
  "geometry": {"coordinates":[-89.96544900000001,35.988145],"type":"Point"}
}