{
  "type": "Feature",
  "properties": {
    "addr:full":"2451 S Lincoln St Siloam Springs OK 72761",
    "addr:housenumber":"2451",
    "addr:postcode":"72761",
    "addr:street":"S Lincoln St",
    "iso:country":"US",
    "sg:address":"2451 S Lincoln St",
    "sg:city":"Siloam Springs",
    "sg:classifiers":[
        {
            "category":"Building & Trades",
            "subcategory":"Plumbing",
            "type":"Services"
        }
    ],
    "sg:phone":"+1 479 524 9650",
    "sg:postcode":"72761",
    "sg:province":"OK",
    "sg:tags":[
        "plumbing",
        "contractor"
    ],
    "wof:name":"Allied Plumbing",
    "wof:placetype":"venue"
},
  "geometry": {"coordinates":[-94.528193,36.165124],"type":"Point"}
}