{
  "type": "Feature",
  "properties": {
    "iso:country":"US",
    "sg:address":"116 N Block Ave",
    "sg:city":"Fayetteville",
    "sg:classifiers":[
        {
            "category":"Health Services",
            "subcategory":"Doctor",
            "type":"Services"
        }
    ],
    "sg:phone":"+1 479 443 9801",
    "sg:postcode":"72701",
    "sg:province":"AR",
    "sg:tags":[
        "physician",
        "surgeon"
    ],
    "wof:name":"Kenton Ross Md",
    "wof:placetype":"venue"
},
  "geometry": {"coordinates":[-94.160548,36.0638],"type":"Point"}
}