{
  "type": "Feature",
  "properties": {
    "iso:country":"US",
    "sg:address":"523 N University Ave",
    "sg:city":"Little Rock",
    "sg:classifiers":[
        {
            "category":"Health Services",
            "subcategory":"Doctor",
            "type":"Services"
        }
    ],
    "sg:phone":"+1 501 664 6366",
    "sg:postcode":"72205",
    "sg:province":"AR",
    "wof:name":"Chester F Hight DDS",
    "wof:placetype":"venue"
},
  "geometry": {"coordinates":[-92.340902,34.756424],"type":"Point"}
}