{
  "type": "Feature",
  "properties": {
    "addr:full":"5405 S Caraway Rd Jonesboro AR 72404",
    "addr:housenumber":"5405",
    "addr:postcode":"72404",
    "addr:street":"S Caraway Rd",
    "iso:country":"US",
    "sg:address":"5405 S Caraway Rd",
    "sg:city":"Jonesboro",
    "sg:classifiers":[
        {
            "category":"Retail",
            "subcategory":"Auto Repair",
            "type":"Services"
        }
    ],
    "sg:phone":"+1 870 932 1388",
    "sg:postcode":"72404",
    "sg:province":"AR",
    "sg:tags":[
        "body",
        "automobile",
        "painting",
        "repairing"
    ],
    "wof:name":"Martin D Bryant",
    "wof:placetype":"venue"
},
  "geometry": {"coordinates":[-90.678979,35.775584],"type":"Point"}
}