{
  "type": "Feature",
  "properties": {
    "iso:country":"US",
    "sg:address":"3300 S Elm St",
    "sg:city":"Little Rock",
    "sg:classifiers":[
        {
            "category":"Building & Trades",
            "subcategory":"Construction",
            "type":"Services"
        }
    ],
    "sg:phone":"+1 501 666 8859",
    "sg:postcode":"72204",
    "sg:province":"AR",
    "sg:tags":[
        "foundation"
    ],
    "wof:name":"Wessel Brothers Foundation Co",
    "wof:placetype":"venue"
},
  "geometry": {"coordinates":[-92.319104,34.721527],"type":"Point"}
}