{
  "type": "Feature",
  "properties": {
    "iso:country":"US",
    "sg:address":"201 Roosevelt Rd",
    "sg:city":"Jacksonville",
    "sg:classifiers":[
        {
            "category":"Retail",
            "subcategory":"Repair Shop",
            "type":"Services"
        }
    ],
    "sg:phone":"+1 501 982 7530",
    "sg:postcode":"72076",
    "sg:province":"AR",
    "wof:name":"Lawnmower Dave",
    "wof:placetype":"venue"
},
  "geometry": {"coordinates":[-92.107612,34.861896],"type":"Point"}
}