{
  "type": "Feature",
  "properties": {
    "iso:country":"US",
    "sg:address":"215 W Elm St",
    "sg:city":"Brinkley",
    "sg:classifiers":[
        {
            "category":"Organizations",
            "subcategory":"Religious Organization",
            "type":"Services"
        }
    ],
    "sg:phone":"+1 870 734 2571",
    "sg:postcode":"72021",
    "sg:province":"AR",
    "wof:name":"First Baptist Church",
    "wof:placetype":"venue"
},
  "geometry": {"coordinates":[-91.194427,34.884422],"type":"Point"}
}