{
  "type": "Feature",
  "properties": {
    "addr:full":"107 E Central St Warren AR 71671",
    "addr:housenumber":"107",
    "addr:postcode":"71671",
    "addr:street":"E Central St",
    "iso:country":"US",
    "sg:address":"107 E Central St",
    "sg:city":"Warren",
    "sg:classifiers":[
        {
            "category":"Insurance",
            "subcategory":"Insurance Agent",
            "type":"Services"
        },
        {
            "category":"Insurance",
            "subcategory":"Hazard Insurance",
            "type":"Services"
        },
        {
            "category":"Insurance",
            "subcategory":"Life Insurance",
            "type":"Services"
        }
    ],
    "sg:phone":"+1 870 226 2649",
    "sg:postcode":"71671",
    "sg:province":"AR",
    "sg:tags":[
        "auto",
        "commercial",
        "analyst",
        "business",
        "consultant"
    ],
    "wof:name":"Larance, Tommy",
    "wof:placetype":"venue"
},
  "geometry": {"coordinates":[-92.06428,33.609827],"type":"Point"}
}