{
  "type": "Feature",
  "properties": {
    "addr:full":"500 W Walnut St Paris AR 72855",
    "addr:housenumber":"500",
    "addr:postcode":"72855",
    "addr:street":"W Walnut St",
    "iso:country":"US",
    "sg:address":"500 W Walnut St",
    "sg:city":"Paris",
    "sg:classifiers":[
        {
            "category":"Building & Trades",
            "subcategory":"Plumbing",
            "type":"Services"
        }
    ],
    "sg:phone":"+1 479 963 8821",
    "sg:postcode":"72855",
    "sg:province":"AR",
    "sg:tags":[
        "contractor"
    ],
    "wof:name":"Curtis Heating Cooling PA",
    "wof:placetype":"venue"
},
  "geometry": {"coordinates":[-93.734008,35.292045],"type":"Point"}
}