{
  "type": "Feature",
  "properties": {
    "iso:country":"US",
    "sg:address":"100 N Main St",
    "sg:city":"Harrison",
    "sg:classifiers":[
        {
            "category":"Government",
            "subcategory":"Office",
            "type":"Public Place"
        }
    ],
    "sg:phone":"+1 870 741 5760",
    "sg:postcode":"72601",
    "sg:province":"AR",
    "sg:tags":[
        "executive"
    ],
    "wof:name":"Boone County Road Department",
    "wof:placetype":"venue"
},
  "geometry": {"coordinates":[-93.10739599999999,36.230855],"type":"Point"}
}