{
  "type": "Feature",
  "properties": {
    "iso:country":"US",
    "sg:address":"1105 S Olive St",
    "sg:city":"Pine Bluff",
    "sg:classifiers":[
        {
            "category":"Social Services",
            "subcategory":"Child Care",
            "type":"Services"
        }
    ],
    "sg:phone":"+1 870 536 8482",
    "sg:postcode":"71601",
    "sg:province":"AR",
    "sg:tags":[
        "day"
    ],
    "wof:name":"Winston's Tender Care",
    "wof:placetype":"venue"
},
  "geometry": {"coordinates":[-92.00715,34.218629],"type":"Point"}
}