{
  "type": "Feature",
  "properties": {
    "iso:country":"US",
    "sg:address":"994 Truman St NW",
    "sg:city":"Camden",
    "sg:classifiers":[
        {
            "category":"Professional",
            "subcategory":"Secretarial Services",
            "type":"Services"
        }
    ],
    "sg:phone":"+1 870 836 9284",
    "sg:postcode":"71701",
    "sg:province":"AR",
    "sg:tags":[
        "reporting",
        "court"
    ],
    "wof:name":"Mc Kay Court Reporting Svc",
    "wof:placetype":"venue"
},
  "geometry": {"coordinates":[-92.846279,33.594294],"type":"Point"}
}