{
  "type": "Feature",
  "properties": {
    "addr:full":"2000 E 17th St Little Rock AR 72202",
    "addr:housenumber":"2000",
    "addr:postcode":"72202",
    "addr:street":"E 17Th St",
    "iso:country":"US",
    "sg:address":"2000 E 17th St",
    "sg:city":"Little Rock",
    "sg:classifiers":[
        {
            "category":"Autos & Motor Vehicles",
            "subcategory":"Auto Supplies",
            "type":"Retail Goods"
        },
        {
            "category":"Wholesale",
            "subcategory":"Auto Parts",
            "type":"Manufacturing & Wholesale Goods"
        }
    ],
    "sg:phone":"+1 501 376 8287",
    "sg:postcode":"72202",
    "sg:province":"AR",
    "sg:tags":[
        "repair",
        "tire"
    ],
    "wof:name":"Moore & Robinson Inc",
    "wof:placetype":"venue"
},
  "geometry": {"coordinates":[-92.245606,34.730501],"type":"Point"}
}