{
  "type": "Feature",
  "properties": {
    "iso:country":"US",
    "sg:address":"438 Sturgis Rd",
    "sg:city":"Conway",
    "sg:classifiers":[
        {
            "category":"Building & Trades",
            "subcategory":"Pest Control",
            "type":"Services"
        }
    ],
    "sg:phone":"+1 501 470 1125",
    "sg:postcode":"72034",
    "sg:province":"AR",
    "wof:name":"Laskers Pest & Weed Control",
    "wof:placetype":"venue"
},
  "geometry": {"coordinates":[-92.418441,34.996465],"type":"Point"}
}