{
  "type": "Feature",
  "properties": {
    "iso:country":"US",
    "sg:address":"4135 Malvern Rd",
    "sg:city":"Hot Springs",
    "sg:classifiers":[
        {
            "category":"Retail",
            "subcategory":"Auto Rental",
            "type":"Services"
        }
    ],
    "sg:phone":"+1 501 262 2665",
    "sg:postcode":"71901",
    "sg:province":"AR",
    "sg:tags":[
        "renting",
        "truck",
        "leasing"
    ],
    "wof:name":"Penske Truck Rental",
    "wof:placetype":"venue"
},
  "geometry": {"coordinates":[-92.95254300000001,34.463786],"type":"Point"}
}