{
  "type": "Feature",
  "properties": {
    "addr:full":"5817 S 28th St Fort Smith AR 72908",
    "addr:housenumber":"5817",
    "addr:postcode":"72908",
    "addr:street":"S 28Th St",
    "iso:country":"US",
    "sg:address":"5817 S 28th St",
    "sg:city":"Fort Smith",
    "sg:classifiers":[
        {
            "category":"Manufacturing",
            "subcategory":"Furniture",
            "type":"Manufacturing & Wholesale Goods"
        }
    ],
    "sg:phone":"+1 812 934 7777",
    "sg:postcode":"72908",
    "sg:province":"AR",
    "sg:tags":[
        "hospital",
        "bed",
        "mfg"
    ],
    "wof:name":"Hill-Rom Company Inc",
    "wof:placetype":"venue"
},
  "geometry": {"coordinates":[-94.40444599999999,35.326542],"type":"Point"}
}