{
  "type": "Feature",
  "properties": {
    "iso:country":"US",
    "sg:address":"4405 Peachtree Ave",
    "sg:city":"Jonesboro",
    "sg:classifiers":[
        {
            "category":"Health Services",
            "subcategory":"Health Practitioner",
            "type":"Services"
        }
    ],
    "sg:phone":"+1 870 932 2775",
    "sg:postcode":"72401",
    "sg:province":"AR",
    "wof:name":"Cindy Dean",
    "wof:placetype":"venue"
},
  "geometry": {"coordinates":[-90.645398,35.87539],"type":"Point"}
}