{
  "type": "Feature",
  "properties": {
    "iso:country":"US",
    "sg:address":"1245 Grayson Cir",
    "sg:city":"Malvern",
    "sg:classifiers":[
        {
            "category":"Building & Trades",
            "subcategory":"Construction",
            "type":"Services"
        }
    ],
    "sg:phone":"+1 501 332 3332",
    "sg:postcode":"72104",
    "sg:province":"AR",
    "sg:tags":[
        "roofing",
        "contractor"
    ],
    "wof:name":"James E Kidder & Son Roofing",
    "wof:placetype":"venue"
},
  "geometry": {"coordinates":[-92.81309400000001,34.381434],"type":"Point"}
}