{
  "type": "Feature",
  "properties": {
    "iso:country":"US",
    "sg:address":"1109 S Myrtle St",
    "sg:city":"Warren",
    "sg:classifiers":[
        {
            "category":"Organizations",
            "subcategory":"Religious Organization",
            "type":"Services"
        }
    ],
    "sg:phone":"+1 870 226 2544",
    "sg:postcode":"71671",
    "sg:province":"AR",
    "sg:tags":[
        "place",
        "worship",
        "church"
    ],
    "wof:name":"Holy Deliverance Cogic",
    "wof:placetype":"venue"
},
  "geometry": {"coordinates":[-92.063001,33.602452],"type":"Point"}
}