{
  "type": "Feature",
  "properties": {
    "iso:country":"US",
    "sg:address":"101 S Main St",
    "sg:city":"Spiro",
    "sg:classifiers":[
        {
            "category":"Professional",
            "subcategory":"Accounting & Tax Preparation",
            "type":"Services"
        }
    ],
    "sg:phone":"+1 918 962 2401",
    "sg:postcode":"74959",
    "sg:province":"OK",
    "sg:tags":[
        "accountant"
    ],
    "wof:name":"David F Hedges CPA",
    "wof:placetype":"venue"
},
  "geometry": {"coordinates":[-94.621167,35.241077],"type":"Point"}
}