{
  "type": "Feature",
  "properties": {
    "iso:country":"US",
    "sg:address":"236 Regency Ter",
    "sg:city":"Hot Springs",
    "sg:classifiers":[
        {
            "category":"Building & Trades",
            "subcategory":"Cleaning & Sanitation",
            "type":"Services"
        }
    ],
    "sg:phone":"+1 501 767 5258",
    "sg:postcode":"71913",
    "sg:province":"AR",
    "sg:tags":[
        "janitor"
    ],
    "wof:name":"M & M Office & Home Cleaning",
    "wof:placetype":"venue"
},
  "geometry": {"coordinates":[-93.171571,34.44975],"type":"Point"}
}