{
  "type": "Feature",
  "properties": {
    "iso:country":"US",
    "sg:address":"70 N College Ave",
    "sg:city":"Fayetteville",
    "sg:classifiers":[
        {
            "category":"Insurance",
            "subcategory":"Title Insurance",
            "type":"Services"
        },
        {
            "category":"Real Estate",
            "subcategory":"Real Estate Services",
            "type":"Services"
        }
    ],
    "sg:phone":"+1 479 443 5859",
    "sg:postcode":"72701",
    "sg:province":"AR",
    "sg:tags":[
        "company",
        "carrier"
    ],
    "wof:name":"Pro Land Title Company",
    "wof:placetype":"venue"
},
  "geometry": {"coordinates":[-94.15783999999999,36.063054],"type":"Point"}
}