{
  "type": "Feature",
  "properties": {
    "addr:full":"2201 Lincoln Ave N Little Rock AR 72114",
    "addr:housenumber":"2201",
    "addr:postcode":"72114",
    "addr:street":"Lincoln Ave N",
    "iso:country":"US",
    "sg:address":"2201 Lincoln Ave",
    "sg:city":"N Little Rock",
    "sg:classifiers":[
        {
            "category":"Building & Trades",
            "subcategory":"Plumbing",
            "type":"Services"
        }
    ],
    "sg:phone":"+1 501 225 9644",
    "sg:postcode":"72114",
    "sg:province":"AR",
    "sg:tags":[
        "plumbing",
        "contractor"
    ],
    "wof:name":"Hillcrest Heating & Plumbing",
    "wof:placetype":"venue"
},
  "geometry": {"coordinates":[-92.242002,34.75147],"type":"Point"}
}