{
  "type": "Feature",
  "properties": {
    "iso:country":"US",
    "sg:address":"2137 Cartney Rd",
    "sg:city":"Mountain Home",
    "sg:classifiers":[
        {
            "category":"Professional",
            "type":"Services"
        }
    ],
    "sg:phone":"+1 870 424 4084",
    "sg:postcode":"72653",
    "sg:province":"AR",
    "wof:name":"Kimberly J Adamic",
    "wof:placetype":"venue"
},
  "geometry": {"coordinates":[-92.418039,36.22284],"type":"Point"}
}