{
  "type": "Feature",
  "properties": {
    "iso:country":"US",
    "sg:address":"405 S Grove",
    "sg:city":"Hazen",
    "sg:classifiers":[
        {
            "category":"Professional",
            "type":"Services"
        }
    ],
    "sg:phone":"+1 870 255 4656",
    "sg:postcode":"72064",
    "sg:province":"AR",
    "wof:name":"Bobby Mosby",
    "wof:placetype":"venue"
},
  "geometry": {"coordinates":[-91.57757700000001,34.777085],"type":"Point"}
}