{
  "type": "Feature",
  "properties": {
    "iso:country":"US",
    "sg:address":"53 Pilgrim Rest Rd",
    "sg:city":"Greenbrier",
    "sg:classifiers":[
        {
            "category":"Organizations",
            "subcategory":"Religious Organization",
            "type":"Services"
        }
    ],
    "sg:phone":"+1 501 679 2369",
    "sg:postcode":"72058",
    "sg:province":"AR",
    "wof:name":"Pilgrim Rest Baptist Church",
    "wof:placetype":"venue"
},
  "geometry": {"coordinates":[-92.504278,35.205669],"type":"Point"}
}