{
  "type": "Feature",
  "properties": {
    "addr:full":"36 E Main St Booneville AR 72927",
    "addr:housenumber":"36",
    "addr:postcode":"72927",
    "addr:street":"E Main St",
    "iso:country":"US",
    "sg:address":"36 E Main St",
    "sg:city":"Booneville",
    "sg:classifiers":[
        {
            "category":"Shopping",
            "type":"Retail Goods"
        }
    ],
    "sg:phone":"+1 479 675 5664",
    "sg:postcode":"72927",
    "sg:province":"AR",
    "sg:tags":[
        "cellular",
        "merchandise",
        "telephone"
    ],
    "wof:name":"Russell Cellular Inc",
    "wof:placetype":"venue"
},
  "geometry": {"coordinates":[-93.92147,35.140151],"type":"Point"}
}