{
  "type": "Feature",
  "properties": {
    "addr:full":"1701 S 40th St Springdale AR 72762",
    "addr:housenumber":"1701",
    "addr:postcode":"72762",
    "addr:street":"S 40Th St",
    "iso:country":"US",
    "sg:address":"1701 S 40th St",
    "sg:city":"Springdale",
    "sg:classifiers":[
        {
            "category":"Education",
            "subcategory":"School",
            "type":"Public Place"
        }
    ],
    "sg:phone":"+1 479 750 8874",
    "sg:postcode":"72762",
    "sg:province":"AR",
    "wof:name":"Walker Elementary School",
    "wof:placetype":"venue"
},
  "geometry": {"coordinates":[-94.17465799999999,36.170828],"type":"Point"}
}