{
  "type": "Feature",
  "properties": {
    "addr:full":"3098 Amity Rd Pearcy AR 71964",
    "addr:housenumber":"3098",
    "addr:postcode":"71964",
    "addr:street":"Amity Rd",
    "iso:country":"US",
    "sg:address":"3098 Amity Rd",
    "sg:city":"Pearcy",
    "sg:classifiers":[
        {
            "category":"Manufacturing",
            "subcategory":"Wood Products",
            "type":"Manufacturing & Wholesale Goods"
        }
    ],
    "sg:phone":"+1 501 525 3914",
    "sg:postcode":"71964",
    "sg:province":"AR",
    "wof:name":"Taylor-Made Crafts",
    "wof:placetype":"venue"
},
  "geometry": {"coordinates":[-93.20310000000001,34.400391],"type":"Point"}
}