{
  "type": "Feature",
  "properties": {
    "addr:full":"73 S 6th St Fort Smith AR 72901",
    "addr:housenumber":"73",
    "addr:postcode":"72901",
    "addr:street":"S 6Th St",
    "iso:country":"US",
    "sg:address":"73 S 6th St",
    "sg:city":"Fort Smith",
    "sg:classifiers":[
        {
            "category":"Manufacturing",
            "subcategory":"Food",
            "type":"Manufacturing & Wholesale Goods"
        }
    ],
    "sg:phone":"+1 479 783 5174",
    "sg:postcode":"72901",
    "sg:province":"AR",
    "sg:tags":[
        "bakery",
        "prod",
        "cookie"
    ],
    "wof:name":"Shipley Baking Co LLC",
    "wof:placetype":"venue"
},
  "geometry": {"coordinates":[-94.426897,35.385571],"type":"Point"}
}