{
  "type": "Feature",
  "properties": {
    "addr:full":"1401 E 9th St Little Rock AR 72202",
    "addr:housenumber":"1401",
    "addr:postcode":"72202",
    "addr:street":"E 9Th St",
    "iso:country":"US",
    "sg:address":"1401 E 9th St",
    "sg:city":"Little Rock",
    "sg:classifiers":[
        {
            "category":"Social Services",
            "subcategory":"Child Care",
            "type":"Services"
        }
    ],
    "sg:phone":"+1 501 372 5454",
    "sg:postcode":"72202",
    "sg:province":"AR",
    "wof:name":"Shining Star Christian Daycare",
    "wof:placetype":"venue"
},
  "geometry": {"coordinates":[-92.25452799999999,34.739238],"type":"Point"}
}