{
  "type": "Feature",
  "properties": {
    "iso:country":"US",
    "sg:address":"1753 S 1st St",
    "sg:city":"Rogers",
    "sg:classifiers":[
        {
            "category":"Wholesale",
            "subcategory":"Machinery & Supplies",
            "type":"Manufacturing & Wholesale Goods"
        }
    ],
    "sg:phone":"+1 479 631 5900",
    "sg:postcode":"72756",
    "sg:province":"AR",
    "sg:tags":[
        "equipment",
        "industrial"
    ],
    "wof:name":"Arkansas Mill Supply Company",
    "wof:placetype":"venue"
},
  "geometry": {"coordinates":[-94.117198,36.31866],"type":"Point"}
}