{
  "type": "Feature",
  "properties": {
    "iso:country":"US",
    "sg:address":"89 S Hwy 261",
    "sg:city":"Palestine",
    "sg:classifiers":[
        {
            "category":"Travel",
            "subcategory":"Hotels & Motels",
            "type":"Entertainment"
        }
    ],
    "sg:phone":"+1 870 581 5000",
    "sg:postcode":"72372",
    "sg:province":"AR",
    "wof:name":"Rest Inn Motel",
    "wof:placetype":"venue"
},
  "geometry": {"coordinates":[-90.90666,34.965467],"type":"Point"}
}