{
  "type": "Feature",
  "properties": {
    "iso:country":"US",
    "sg:address":"39 Masters Place Dr",
    "sg:city":"Maumelle",
    "sg:classifiers":[
        {
            "category":"Manufacturing",
            "subcategory":"Retail Goods",
            "type":"Manufacturing & Wholesale Goods"
        }
    ],
    "sg:phone":"+1 501 851 0813",
    "sg:postcode":"72113",
    "sg:province":"AR",
    "sg:tags":[
        "product",
        "mfg"
    ],
    "wof:name":"Garner Air Systems",
    "wof:placetype":"venue"
},
  "geometry": {"coordinates":[-92.416614,34.848361],"type":"Point"}
}