{
  "type": "Feature",
  "properties": {
    "iso:country":"US",
    "sg:address":"5099 Heber Springs Rd W",
    "sg:city":"Quitman",
    "sg:classifiers":[
        {
            "category":"Manufacturing",
            "subcategory":"Tools & Machinery",
            "type":"Manufacturing & Wholesale Goods"
        },
        {
            "category":"Wholesale",
            "subcategory":"Machinery & Supplies",
            "type":"Manufacturing & Wholesale Goods"
        }
    ],
    "sg:phone":"+1 501 589 2553",
    "sg:postcode":"72131",
    "sg:province":"AR",
    "sg:tags":[
        "equipment",
        "industrial"
    ],
    "wof:name":"Central Arkansas Tool Supply, Inc",
    "wof:placetype":"venue"
},
  "geometry": {"coordinates":[-92.190074,35.394904],"type":"Point"}
}