{
  "type": "Feature",
  "properties": {
    "addr:full":"800 S Church St Jonesboro AR 72401",
    "addr:housenumber":"800",
    "addr:postcode":"72401",
    "addr:street":"S Church St",
    "iso:country":"US",
    "sg:address":"800 S Church St",
    "sg:city":"Jonesboro",
    "sg:classifiers":[
        {
            "category":"Health Services",
            "subcategory":"Doctor",
            "type":"Services"
        }
    ],
    "sg:phone":"+1 870 935 3990",
    "sg:postcode":"72401",
    "sg:province":"AR",
    "sg:tags":[
        "physician",
        "surgeon"
    ],
    "sg:website":"www.obgynjonesboro.md",
    "wof:name":"Ob-Gyn Associates LTD",
    "wof:placetype":"venue"
},
  "geometry": {"coordinates":[-90.70402900000001,35.836325],"type":"Point"}
}