{
  "type": "Feature",
  "properties": {
    "iso:country":"US",
    "sg:address":"10401 Colonel Glenn Rd",
    "sg:city":"Little Rock",
    "sg:classifiers":[
        {
            "category":"Building & Trades",
            "subcategory":"Landscaping Services",
            "type":"Services"
        }
    ],
    "sg:phone":"+1 501 217 9100",
    "sg:postcode":"72204",
    "sg:province":"AR",
    "sg:tags":[
        "landscape",
        "contractor"
    ],
    "wof:name":"Fairway Lawns",
    "wof:placetype":"venue"
},
  "geometry": {"coordinates":[-92.394134,34.712411],"type":"Point"}
}