{
  "type": "Feature",
  "properties": {
    "iso:country":"US",
    "sg:address":"4 Wayside Dr",
    "sg:city":"Sherwood",
    "sg:classifiers":[
        {
            "category":"Recreation",
            "type":"Entertainment"
        }
    ],
    "sg:phone":"+1 501 834 2189",
    "sg:postcode":"72120",
    "sg:province":"AR",
    "sg:tags":[
        "entertainers-family",
        "business"
    ],
    "wof:name":"Hiatus Entertainment",
    "wof:placetype":"venue"
},
  "geometry": {"coordinates":[-92.231471,34.857608],"type":"Point"}
}