{
  "type": "Feature",
  "properties": {
    "iso:country":"US",
    "sg:address":"3333 Springhill Dr",
    "sg:city":"N Little Rock",
    "sg:classifiers":[
        {
            "category":"Health Services",
            "subcategory":"Doctor",
            "type":"Services"
        }
    ],
    "sg:phone":"+1 501 202 6800",
    "sg:postcode":"72117",
    "sg:province":"AR",
    "sg:tags":[
        "physician",
        "surgeon"
    ],
    "sg:website":"www.baptisthealth.org",
    "wof:name":"BHMCNLR Emergency Svc",
    "wof:placetype":"venue"
},
  "geometry": {"coordinates":[-92.218148,34.783115],"type":"Point"}
}