{
  "type": "Feature",
  "properties": {
    "addr:full":"620 Hwy 365 Mayflower AR 72106",
    "addr:housenumber":"620",
    "addr:postcode":"72106",
    "addr:street":"Hwy 365",
    "iso:country":"US",
    "sg:address":"620 Hwy 365",
    "sg:city":"Mayflower",
    "sg:classifiers":[
        {
            "category":"Shopping",
            "subcategory":"Tobacco",
            "type":"Retail Goods"
        }
    ],
    "sg:phone":"+1 501 470 0149",
    "sg:postcode":"72106",
    "sg:province":"AR",
    "sg:tags":[
        "product"
    ],
    "wof:name":"Best Price Tobacco Outlet",
    "wof:placetype":"venue"
},
  "geometry": {"coordinates":[-92.42286,34.960412],"type":"Point"}
}