{
  "type": "Feature",
  "properties": {
    "iso:country":"US",
    "sg:address":"2508 Hwy 67 S",
    "sg:city":"Newport",
    "sg:classifiers":[
        {
            "category":"Personal",
            "subcategory":"Barber",
            "type":"Services"
        }
    ],
    "sg:phone":"+1 870 523 9353",
    "sg:postcode":"72473",
    "sg:province":"AR",
    "wof:name":"Jerry's Hairstyling",
    "wof:placetype":"venue"
},
  "geometry": {"coordinates":[-91.211269,35.711633],"type":"Point"}
}