{
  "type": "Feature",
  "properties": {
    "addr:full":"7887 Valentine Ln Harrison AR 72601",
    "addr:housenumber":"7887",
    "addr:postcode":"72601",
    "addr:street":"Valentine Ln",
    "iso:country":"US",
    "sg:address":"7887 Valentine Ln",
    "sg:city":"Harrison",
    "sg:classifiers":[
        {
            "category":"Retail",
            "subcategory":"Laundry & Dry Cleaning",
            "type":"Services"
        },
        {
            "category":"Building & Trades",
            "subcategory":"Cleaning & Sanitation",
            "type":"Services"
        }
    ],
    "sg:phone":"+1 870 741 6458",
    "sg:postcode":"72601",
    "sg:province":"AR",
    "sg:tags":[
        "cleaner",
        "carpet",
        "rug",
        "janitorial"
    ],
    "wof:name":"Acura Services",
    "wof:placetype":"venue"
},
  "geometry": {"coordinates":[-93.223626,36.274297],"type":"Point"}
}