{
  "type": "Feature",
  "properties": {
    "iso:country":"US",
    "sg:address":"4915 Deer Dr",
    "sg:city":"Paron",
    "sg:classifiers":[
        {
            "category":"Building & Trades",
            "subcategory":"Landscaping Services",
            "type":"Services"
        }
    ],
    "sg:phone":"+1 501 821 2303",
    "sg:postcode":"72122",
    "sg:province":"AR",
    "sg:tags":[
        "landscape",
        "contractor"
    ],
    "wof:name":"Cutting Edge Lawn Care",
    "wof:placetype":"venue"
},
  "geometry": {"coordinates":[-92.650674,34.785996],"type":"Point"}
}