{
  "type": "Feature",
  "properties": {
    "addr:full":"1 Merriweather Pond Harrison AR 72601",
    "addr:housenumber":"1",
    "addr:postcode":"72601",
    "addr:street":"Merriweather Pond",
    "iso:country":"US",
    "sg:address":"1 Merriweather Pond",
    "sg:city":"Harrison",
    "sg:classifiers":[
        {
            "category":"Real Estate",
            "subcategory":"Developer",
            "type":"Services"
        }
    ],
    "sg:phone":"+1 870 741 4805",
    "sg:postcode":"72601",
    "sg:province":"AR",
    "wof:name":"Woodcroft",
    "wof:placetype":"venue"
},
  "geometry": {"coordinates":[-93.13673199999999,36.224797],"type":"Point"}
}