{
  "type": "Feature",
  "properties": {
    "addr:full":"526 N Myrtle St Warren AR 71671",
    "addr:housenumber":"526",
    "addr:postcode":"71671",
    "addr:street":"N Myrtle St",
    "iso:country":"US",
    "sg:address":"526 N Myrtle St",
    "sg:city":"Warren",
    "sg:classifiers":[
        {
            "category":"Building & Trades",
            "subcategory":"Construction",
            "type":"Services"
        }
    ],
    "sg:phone":"+1 870 226 3138",
    "sg:postcode":"71671",
    "sg:province":"AR",
    "sg:tags":[
        "welder"
    ],
    "wof:name":"Harvey's Welding Shop",
    "wof:placetype":"venue"
},
  "geometry": {"coordinates":[-92.063016,33.609001],"type":"Point"}
}