{
  "type": "Feature",
  "properties": {
    "addr:full":"4 Forest Brook Ct Little Rock AR 72211",
    "addr:housenumber":"4",
    "addr:postcode":"72211",
    "addr:street":"Forest Brook Ct",
    "iso:country":"US",
    "sg:address":"4 Forest Brook Ct",
    "sg:city":"Little Rock",
    "sg:classifiers":[
        {
            "category":"Professional",
            "type":"Services"
        }
    ],
    "sg:phone":"+1 501 225 6017",
    "sg:postcode":"72211",
    "sg:province":"AR",
    "wof:name":"Donna M Young",
    "wof:placetype":"venue"
},
  "geometry": {"coordinates":[-92.40494700000001,34.7334],"type":"Point"}
}