{
  "type": "Feature",
  "properties": {
    "addr:full":"1901 N Pierce St Little Rock AR 72207",
    "addr:housenumber":"1901",
    "addr:postcode":"72207",
    "addr:street":"N Pierce St",
    "iso:country":"US",
    "sg:address":"1901 N Pierce St",
    "sg:city":"Little Rock",
    "sg:classifiers":[
        {
            "category":"Organizations",
            "subcategory":"Religious Organization",
            "type":"Services"
        }
    ],
    "sg:phone":"+1 501 663 8303",
    "sg:postcode":"72207",
    "sg:province":"AR",
    "sg:website":"www.cbclr.org",
    "wof:name":"Calvary Baptist Church",
    "wof:placetype":"venue"
},
  "geometry": {"coordinates":[-92.33824199999999,34.769777],"type":"Point"}
}