{
  "type": "Feature",
  "properties": {
    "iso:country":"US",
    "sg:address":"104 W 4th St",
    "sg:city":"Weiner",
    "sg:classifiers":[
        {
            "category":"Autos & Motor Vehicles",
            "subcategory":"Motorcycle Sales",
            "type":"Retail Goods"
        }
    ],
    "sg:phone":"+1 870 684 7731",
    "sg:postcode":"72479",
    "sg:province":"AR",
    "sg:tags":[
        "all",
        "terrain"
    ],
    "wof:name":"Exact Ag",
    "wof:placetype":"venue"
},
  "geometry": {"coordinates":[-90.899826,35.621729],"type":"Point"}
}