{
  "type": "Feature",
  "properties": {
    "addr:full":"7110 State Hwy 135 Lake City AR 72437",
    "addr:housenumber":"7110",
    "addr:postcode":"72437",
    "addr:street":"State Hwy 135",
    "iso:country":"US",
    "sg:address":"7110 State Hwy 135",
    "sg:city":"Lake City",
    "sg:phone":"+1 870 239 5432",
    "sg:postcode":"72437",
    "sg:province":"AR",
    "sg:tags":[
        "farm",
        "cotton"
    ],
    "wof:name":"Eugene McNatt",
    "wof:placetype":"venue"
},
  "geometry": {"coordinates":[-90.45143899999999,35.932339],"type":"Point"}
}