{
  "type": "Feature",
  "properties": {
    "addr:full":"155 E Waterman St Dumas AR 71639",
    "addr:housenumber":"155",
    "addr:postcode":"71639",
    "addr:street":"E Waterman St Dumas",
    "iso:country":"US",
    "sg:address":"155 E Waterman St",
    "sg:city":"Dumas",
    "sg:classifiers":[
        {
            "category":"Government",
            "subcategory":"Office",
            "type":"Public Place"
        }
    ],
    "sg:phone":"+1 870 382 6032",
    "sg:postcode":"71639",
    "sg:province":"AR",
    "wof:name":"Desha County Veterans Office",
    "wof:placetype":"venue"
},
  "geometry": {"coordinates":[-91.490582,33.887466],"type":"Point"}
}