{
  "type": "Feature",
  "properties": {
    "iso:country":"US",
    "sg:address":"2702 W 2nd Ave",
    "sg:city":"Pine Bluff",
    "sg:classifiers":[
        {
            "category":"Building & Trades",
            "subcategory":"Construction",
            "type":"Services"
        }
    ],
    "sg:phone":"+1 870 535 2050",
    "sg:postcode":"71601",
    "sg:province":"AR",
    "sg:tags":[
        "general",
        "contractor"
    ],
    "wof:name":"Select Constructors Inc",
    "wof:placetype":"venue"
},
  "geometry": {"coordinates":[-92.032616,34.228642],"type":"Point"}
}