{
  "type": "Feature",
  "properties": {
    "iso:country":"US",
    "sg:address":"1517 Caddo St",
    "sg:city":"Arkadelphia",
    "sg:classifiers":[
        {
            "category":"Retail",
            "subcategory":"Funeral Services",
            "type":"Services"
        }
    ],
    "sg:phone":"+1 870 246 4211",
    "sg:postcode":"71923",
    "sg:province":"AR",
    "wof:name":"Williams Funeral Home",
    "wof:placetype":"venue"
},
  "geometry": {"coordinates":[-93.066346,34.121103],"type":"Point"}
}