{
  "type": "Feature",
  "properties": {
    "iso:country":"US",
    "sg:address":"22 Keswick Ct",
    "sg:city":"Little Rock",
    "sg:classifiers":[
        {
            "category":"Real Estate",
            "subcategory":"Real Estate Operator",
            "type":"Services"
        }
    ],
    "sg:phone":"+1 501 219 1818",
    "sg:postcode":"72212",
    "sg:province":"AR",
    "sg:tags":[
        "building",
        "nonresidential"
    ],
    "wof:name":"E2 Properties LLC",
    "wof:placetype":"venue"
},
  "geometry": {"coordinates":[-92.4229,34.771025],"type":"Point"}
}