{
  "type": "Feature",
  "properties": {
    "addr:full":"2005 E Highland Dr Jonesboro AR 72401",
    "addr:housenumber":"2005",
    "addr:postcode":"72401",
    "addr:street":"E Highland Dr",
    "iso:country":"US",
    "sg:address":"2005 E Highland Dr",
    "sg:city":"Jonesboro",
    "sg:classifiers":[
        {
            "category":"Restaurant",
            "type":"Food & Drink"
        }
    ],
    "sg:phone":"+1 870 910 3900",
    "sg:postcode":"72401",
    "sg:province":"AR",
    "sg:tags":[
        "eating"
    ],
    "wof:name":"Ann's Restaurant",
    "wof:placetype":"venue"
},
  "geometry": {"coordinates":[-90.682221,35.821149],"type":"Point"}
}