{
  "type": "Feature",
  "properties": {
    "iso:country":"US",
    "sg:address":"220 Mockingbird St",
    "sg:city":"Hot Springs",
    "sg:classifiers":[
        {
            "category":"Professional",
            "subcategory":"Research",
            "type":"Services"
        },
        {
            "category":"Social Services",
            "type":"Services"
        }
    ],
    "sg:phone":"+1 501 525 9380",
    "sg:postcode":"71913",
    "sg:province":"AR",
    "sg:tags":[
        "organization",
        "support",
        "group",
        "noncommercial"
    ],
    "wof:name":"Lupus Foundation of America",
    "wof:placetype":"venue"
},
  "geometry": {"coordinates":[-93.067408,34.460531],"type":"Point"}
}