{
  "type": "Feature",
  "properties": {
    "addr:full":"5152 Hwy 51 S Arkadelphia AR 71923",
    "addr:housenumber":"5152",
    "addr:postcode":"71923",
    "addr:street":"Hwy 51 S Arkadelphia",
    "iso:country":"US",
    "sg:address":"5152 Hwy 51 S",
    "sg:city":"Arkadelphia",
    "sg:classifiers":[
        {
            "category":"Wholesale",
            "subcategory":"Drugs",
            "type":"Manufacturing & Wholesale Goods"
        }
    ],
    "sg:phone":"+1 870 246 6990",
    "sg:postcode":"71923",
    "sg:province":"AR",
    "wof:name":"Ka Lancaster Inc",
    "wof:placetype":"venue"
},
  "geometry": {"coordinates":[-93.138351,34.096362],"type":"Point"}
}