{
  "type": "Feature",
  "properties": {
    "addr:full":"1901 Pine Valley Ln Jonesboro AR 72404",
    "addr:housenumber":"1901",
    "addr:postcode":"72404",
    "addr:street":"Pine Valley Ln",
    "iso:country":"US",
    "sg:address":"1901 Pine Valley Ln",
    "sg:city":"Jonesboro",
    "sg:classifiers":[
        {
            "category":"Health Services",
            "subcategory":"Hospital",
            "type":"Services"
        }
    ],
    "sg:phone":"+1 870 268 8077",
    "sg:postcode":"72404",
    "sg:province":"AR",
    "sg:tags":[
        "mental"
    ],
    "wof:name":"Ascent Behavioral Health",
    "wof:placetype":"venue"
},
  "geometry": {"coordinates":[-90.68738500000001,35.774136],"type":"Point"}
}