{
  "type": "Feature",
  "properties": {
    "iso:country":"US",
    "sg:address":"57 Windwood Loop",
    "sg:city":"Conway",
    "sg:classifiers":[
        {
            "category":"Manufacturing",
            "subcategory":"Lumber",
            "type":"Manufacturing & Wholesale Goods"
        }
    ],
    "sg:phone":"+1 501 329 8191",
    "sg:postcode":"72034",
    "sg:province":"AR",
    "sg:tags":[
        "timberland",
        "lumber-wholesale",
        "timber"
    ],
    "wof:name":"Cedar Creek Timber Lands",
    "wof:placetype":"venue"
},
  "geometry": {"coordinates":[-92.419429,35.036024],"type":"Point"}
}