{
  "type": "Feature",
  "properties": {
    "iso:country":"US",
    "sg:address":"900 S Pine St",
    "sg:city":"Little Rock",
    "sg:classifiers":[
        {
            "category":"Education",
            "subcategory":"Special Training",
            "type":"Public Place"
        }
    ],
    "sg:phone":"+1 501 661 4618",
    "sg:postcode":"72204",
    "sg:province":"AR",
    "sg:tags":[
        "assistance",
        "educational",
        "social"
    ],
    "wof:name":"ACi",
    "wof:placetype":"venue"
},
  "geometry": {"coordinates":[-92.316705,34.742708],"type":"Point"}
}