{
  "type": "Feature",
  "properties": {
    "iso:country":"US",
    "sg:address":"2301 N Washington St",
    "sg:city":"Forrest City",
    "sg:classifiers":[
        {
            "category":"Restaurant",
            "type":"Food & Drink"
        }
    ],
    "sg:phone":"+1 870 633 4146",
    "sg:postcode":"72335",
    "sg:province":"AR",
    "wof:name":"Mc Donald's",
    "wof:placetype":"venue"
},
  "geometry": {"coordinates":[-90.789734,35.034346],"type":"Point"}
}