{
  "type": "Feature",
  "properties": {
    "iso:country":"US",
    "sg:address":"930 S Hwy 65 82",
    "sg:city":"Lake Village",
    "sg:classifiers":[
        {
            "category":"Bars & Pubs",
            "type":"Food & Drink"
        }
    ],
    "sg:phone":"+1 870 265 9933",
    "sg:postcode":"71653",
    "sg:province":"AR",
    "sg:tags":[
        "club",
        "drinking",
        "night"
    ],
    "wof:name":"Foxy Lady Club",
    "wof:placetype":"venue"
},
  "geometry": {"coordinates":[-91.292097,33.323463],"type":"Point"}
}