{
  "type": "Feature",
  "properties": {
    "addr:full":"1000 S Shackleford Rd Little Rock AR 72211",
    "addr:housenumber":"1000",
    "addr:postcode":"72211",
    "addr:street":"S Shackleford Rd",
    "iso:country":"US",
    "sg:address":"1000 S Shackleford Rd",
    "sg:city":"Little Rock",
    "sg:classifiers":[
        {
            "category":"Home & Garden",
            "subcategory":"Furniture",
            "type":"Retail Goods"
        }
    ],
    "sg:phone":"+1 501 224 4624",
    "sg:postcode":"72211",
    "sg:province":"AR",
    "sg:tags":[
        "interior",
        "design"
    ],
    "wof:name":"LA-Z-Boy Furniture Galleries",
    "wof:placetype":"venue"
},
  "geometry": {"coordinates":[-92.394211,34.744738],"type":"Point"}
}