{
  "type": "Feature",
  "properties": {
    "addr:full":"202 E Main St Walnut Ridge AR 72476",
    "addr:housenumber":"202",
    "addr:postcode":"72476",
    "addr:street":"E Main St;Ridge",
    "iso:country":"US",
    "sg:address":"202 E Main St",
    "sg:city":"Walnut Ridge",
    "sg:classifiers":[
        {
            "category":"Professional",
            "subcategory":"Business Services",
            "type":"Services"
        }
    ],
    "sg:phone":"+1 870 886 5555",
    "sg:postcode":"72476",
    "sg:province":"AR",
    "wof:name":"Time Temperature",
    "wof:placetype":"venue"
},
  "geometry": {"coordinates":[-90.954427,36.066832],"type":"Point"}
}