{
  "type": "Feature",
  "properties": {
    "iso:country":"US",
    "sg:address":"63901 E 290 Rd",
    "sg:city":"Grove",
    "sg:classifiers":[
        {
            "category":"Home & Garden",
            "subcategory":"Furniture",
            "type":"Retail Goods"
        }
    ],
    "sg:phone":"+1 918 786 7435",
    "sg:postcode":"74344",
    "sg:province":"OK",
    "wof:name":"J & J Furniture",
    "wof:placetype":"venue"
},
  "geometry": {"coordinates":[-94.737869,36.597871],"type":"Point"}
}