{
  "type": "Feature",
  "properties": {
    "addr:full":"30 Woodsdale Dr Holiday Island AR 72631",
    "addr:housenumber":"30",
    "addr:postcode":"72631",
    "addr:street":"Woodsdale Dr",
    "iso:country":"US",
    "sg:address":"30 Woodsdale Dr",
    "sg:city":"Holiday Island",
    "sg:classifiers":[
        {
            "category":"Real Estate",
            "subcategory":"Architect",
            "type":"Services"
        }
    ],
    "sg:phone":"+1 479 236 8577",
    "sg:postcode":"72631",
    "sg:province":"AR",
    "wof:name":"Morrison Architecture",
    "wof:placetype":"venue"
},
  "geometry": {"coordinates":[-93.75828,36.481715],"type":"Point"}
}