{
  "type": "Feature",
  "properties": {
    "iso:country":"US",
    "sg:address":"431 Sylamore Ave",
    "sg:city":"Mountain View",
    "sg:classifiers":[
        {
            "category":"Insurance",
            "subcategory":"Insurance Agent",
            "type":"Services"
        }
    ],
    "sg:phone":"+1 870 269 4357",
    "sg:postcode":"72560",
    "sg:province":"AR",
    "sg:website":"www.whiteriverinsurance.com",
    "wof:name":"White River Insurance",
    "wof:placetype":"venue"
},
  "geometry": {"coordinates":[-92.107146,35.866297],"type":"Point"}
}