{
  "type": "Feature",
  "properties": {
    "iso:country":"US",
    "sg:address":"100 E Pleasure Ave",
    "sg:city":"Searcy",
    "sg:classifiers":[
        {
            "category":"Professional",
            "subcategory":"Accounting & Tax Preparation",
            "type":"Services"
        }
    ],
    "sg:phone":"+1 501 268 0704",
    "sg:postcode":"72143",
    "sg:province":"AR",
    "wof:name":"Turner Burkett & Assoc Cpas",
    "wof:placetype":"venue"
},
  "geometry": {"coordinates":[-91.737556,35.247696],"type":"Point"}
}