{
  "type": "Feature",
  "properties": {
    "iso:country":"US",
    "sg:address":"2423 Hwy 62-412",
    "sg:city":"Highland",
    "sg:classifiers":[
        {
            "category":"Real Estate",
            "subcategory":"Real Estate Agent",
            "type":"Services"
        }
    ],
    "sg:phone":"+1 870 856 8000",
    "sg:postcode":"72542",
    "sg:province":"AR",
    "wof:name":"Ozark Gateway Realty",
    "wof:placetype":"venue"
},
  "geometry": {"coordinates":[-91.50793899999999,36.27296],"type":"Point"}
}