{
  "type": "Feature",
  "properties": {
    "iso:country":"US",
    "sg:address":"4214 S Camden Rd",
    "sg:city":"Pine Bluff",
    "sg:classifiers":[
        {
            "category":"Freight",
            "type":"Transportation"
        }
    ],
    "sg:phone":"+1 870 879 0750",
    "sg:postcode":"71603",
    "sg:province":"AR",
    "sg:tags":[
        "commercial",
        "storage"
    ],
    "sg:website":"www.webbauctionservice.com",
    "wof:name":"U-Lock It Mini Storage",
    "wof:placetype":"venue"
},
  "geometry": {"coordinates":[-92.065581,34.18935],"type":"Point"}
}