{
  "type": "Feature",
  "properties": {
    "iso:country":"US",
    "sg:address":"3012 Scott Salem Rd",
    "sg:city":"Benton",
    "sg:classifiers":[
        {
            "category":"Professional",
            "subcategory":"Art Services",
            "type":"Services"
        }
    ],
    "sg:phone":"+1 501 794 0841",
    "sg:postcode":"72019",
    "sg:province":"AR",
    "sg:tags":[
        "designer",
        "display",
        "producer"
    ],
    "wof:name":"Urban Thread Designs",
    "wof:placetype":"venue"
},
  "geometry": {"coordinates":[-92.545234,34.612331],"type":"Point"}
}