{
  "type": "Feature",
  "properties": {
    "addr:full":"22667 Lakeview Rd Wc 504 Springdale AR 72764",
    "addr:housenumber":"22667;504",
    "addr:postcode":"72764",
    "addr:street":"Lakeview Rd Wc",
    "iso:country":"US",
    "sg:address":"22667 Lakeview Rd Wc 504",
    "sg:city":"Springdale",
    "sg:classifiers":[
        {
            "category":"Shopping",
            "subcategory":"Computers & Home Electronics",
            "type":"Retail Goods"
        }
    ],
    "sg:phone":"+1 479 751 4100",
    "sg:postcode":"72764",
    "sg:province":"AR",
    "sg:tags":[
        "hardware",
        "supply"
    ],
    "wof:name":"King Outdoor Enterprises",
    "wof:placetype":"venue"
},
  "geometry": {"coordinates":[-93.984449,36.209257],"type":"Point"}
}