{
  "type": "Feature",
  "properties": {
    "iso:country":"US",
    "sg:address":"84 Flag Pond Rd",
    "sg:city":"Mayflower",
    "sg:classifiers":[
        {
            "category":"Retail",
            "subcategory":"Auto Repair",
            "type":"Services"
        }
    ],
    "sg:phone":"+1 501 470 3539",
    "sg:postcode":"72106",
    "sg:province":"AR",
    "sg:tags":[
        "automotive"
    ],
    "wof:name":"Pearson & Snowden Electric",
    "wof:placetype":"venue"
},
  "geometry": {"coordinates":[-92.500922,34.967149],"type":"Point"}
}