{
  "type": "Feature",
  "properties": {
    "iso:country":"US",
    "sg:address":"2405 S Thompson St",
    "sg:city":"Springdale",
    "sg:phone":"+1 479 751 3570",
    "sg:postcode":"72764",
    "sg:province":"AR",
    "sg:tags":[
        "food",
        "equipment",
        "processing"
    ],
    "wof:name":"F & H Food Equipment Co",
    "wof:placetype":"venue"
},
  "geometry": {"coordinates":[-94.143629,36.16346],"type":"Point"}
}