{
  "type": "Feature",
  "properties": {
    "iso:country":"US",
    "sg:address":"2210 S Thompson St",
    "sg:city":"Springdale",
    "sg:classifiers":[
        {
            "category":"Professional",
            "subcategory":"Research",
            "type":"Services"
        }
    ],
    "sg:phone":"+1 479 725 2140",
    "sg:postcode":"72764",
    "sg:province":"AR",
    "sg:tags":[
        "affairs",
        "community"
    ],
    "wof:name":"Hope Inc",
    "wof:placetype":"venue"
},
  "geometry": {"coordinates":[-94.142836,36.166422],"type":"Point"}
}