{
  "type": "Feature",
  "properties": {
    "iso:country":"US",
    "sg:address":"424 NW 4th St",
    "sg:city":"Walnut Ridge",
    "sg:classifiers":[
        {
            "category":"Shopping",
            "subcategory":"Gifts & Souvenirs",
            "type":"Retail Goods"
        }
    ],
    "sg:phone":"+1 870 886 6233",
    "sg:postcode":"72476",
    "sg:province":"AR",
    "wof:name":"Special Things",
    "wof:placetype":"venue"
},
  "geometry": {"coordinates":[-90.95556500000001,36.072407],"type":"Point"}
}