{
  "type": "Feature",
  "properties": {
    "addr:full":"18180 Nease Dr Gravette AR 72736",
    "addr:postcode":"18180;72736",
    "addr:street":"Nease Dr",
    "iso:country":"US",
    "sg:address":"18180 Nease Dr",
    "sg:city":"Gravette",
    "sg:classifiers":[
        {
            "category":"Retail",
            "subcategory":"Repair Shop",
            "type":"Services"
        }
    ],
    "sg:phone":"+1 479 787 7770",
    "sg:postcode":"72736",
    "sg:province":"AR",
    "sg:tags":[
        "refinishing",
        "furniture"
    ],
    "wof:name":"Guardsman Furniture Pro",
    "wof:placetype":"venue"
},
  "geometry": {"coordinates":[-94.42780999999999,36.407294],"type":"Point"}
}