{
  "type": "Feature",
  "properties": {
    "iso:country":"US",
    "sg:address":"1209 Hwy 62 E",
    "sg:city":"Mountain Home",
    "sg:classifiers":[
        {
            "category":"Shopping",
            "subcategory":"Bicycles & Sporting Goods",
            "type":"Retail Goods"
        }
    ],
    "sg:phone":"+1 870 425 8111",
    "sg:postcode":"72653",
    "sg:province":"AR",
    "wof:name":"Locker Room",
    "wof:placetype":"venue"
},
  "geometry": {"coordinates":[-92.363305,36.351403],"type":"Point"}
}