{
  "type": "Feature",
  "properties": {
    "iso:country":"US",
    "sg:address":"100 W Oak St",
    "sg:city":"Mc Gehee",
    "sg:classifiers":[
        {
            "category":"Government",
            "subcategory":"Office",
            "type":"Public Place"
        }
    ],
    "sg:phone":"+1 870 222 3910",
    "sg:postcode":"71654",
    "sg:province":"AR",
    "sg:tags":[
        "administration",
        "program",
        "health"
    ],
    "wof:name":"Desha County Health Unit",
    "wof:placetype":"venue"
},
  "geometry": {"coordinates":[-91.396409,33.629139],"type":"Point"}
}