{
  "type": "Feature",
  "properties": {
    "addr:full":"113 State Hwy 337 Higden AR 72067",
    "addr:housenumber":"113",
    "addr:postcode":"72067",
    "addr:street":"State Hwy 337 Higden",
    "iso:country":"US",
    "sg:address":"113 State Hwy 337",
    "sg:city":"Higden",
    "sg:classifiers":[
        {
            "category":"Food & Beverages",
            "subcategory":"Groceries & Convenience Stores",
            "type":"Retail Goods"
        }
    ],
    "sg:phone":"+1 501 654 2563",
    "sg:postcode":"72067",
    "sg:province":"AR",
    "wof:name":"Sugar Loaf One Stop",
    "wof:placetype":"venue"
},
  "geometry": {"coordinates":[-92.270286,35.54214],"type":"Point"}
}