{
  "type": "Feature",
  "properties": {
    "addr:full":"2511 N 2nd St Rogers AR 72756",
    "addr:housenumber":"2511",
    "addr:postcode":"72756",
    "addr:street":"N 2Nd St",
    "iso:country":"US",
    "sg:address":"2511 N 2nd St",
    "sg:city":"Rogers",
    "sg:classifiers":[
        {
            "category":"Shopping",
            "subcategory":"Stationery & Office Supplies",
            "type":"Retail Goods"
        },
        {
            "category":"Personal",
            "subcategory":"Tanning Parlor",
            "type":"Services"
        },
        {
            "category":"Building & Trades",
            "subcategory":"Equipment Rental",
            "type":"Services"
        }
    ],
    "sg:phone":"+1 479 636 5522",
    "sg:postcode":"72756",
    "sg:province":"AR",
    "sg:tags":[
        "salon",
        "salons-equipment"
    ],
    "wof:name":"Ultrasun Professional Tanning Equipment",
    "wof:placetype":"venue"
},
  "geometry": {"coordinates":[-94.116252,36.355247],"type":"Point"}
}