{
  "type": "Feature",
  "properties": {
    "iso:country":"US",
    "sg:address":"38 E Kibler Hwy",
    "sg:city":"Alma",
    "sg:classifiers":[
        {
            "category":"Organizations",
            "subcategory":"Religious Organization",
            "type":"Services"
        }
    ],
    "sg:phone":"+1 479 632 2611",
    "sg:postcode":"72921",
    "sg:province":"AR",
    "wof:name":"Kibler Baptist Church",
    "wof:placetype":"venue"
},
  "geometry": {"coordinates":[-94.231076,35.430553],"type":"Point"}
}