{
  "type": "Feature",
  "properties": {
    "iso:country":"US",
    "sg:address":"54 Cargile Ln",
    "sg:city":"Greenbrier",
    "sg:classifiers":[
        {
            "category":"Shopping",
            "subcategory":"Bicycles & Sporting Goods",
            "type":"Retail Goods"
        },
        {
            "category":"Marine",
            "type":"Transportation"
        }
    ],
    "sg:phone":"+1 501 679 5050",
    "sg:postcode":"72058",
    "sg:province":"AR",
    "sg:tags":[
        "watercraft-personal-renting"
    ],
    "wof:name":"Cadron Creek Outfitters",
    "wof:placetype":"venue"
},
  "geometry": {"coordinates":[-92.387576,35.326645],"type":"Point"}
}