{
  "type": "Feature",
  "properties": {
    "addr:full":"43 Kensington Cir Bella Vista AR 72714",
    "addr:housenumber":"43",
    "addr:postcode":"72714",
    "addr:street":"Kensington Cir",
    "iso:country":"US",
    "sg:address":"43 Kensington Cir",
    "sg:city":"Bella Vista",
    "sg:classifiers":[
        {
            "category":"Real Estate",
            "subcategory":"Real Estate Agent",
            "type":"Services"
        }
    ],
    "sg:phone":"+1 479 855 7866",
    "sg:postcode":"72714",
    "sg:province":"AR",
    "sg:tags":[
        "building",
        "to",
        "rent",
        "government"
    ],
    "wof:name":"Lawrence E McDaniel",
    "wof:placetype":"venue"
},
  "geometry": {"coordinates":[-94.26279700000001,36.451544],"type":"Point"}
}