{
  "type": "Feature",
  "properties": {
    "iso:country":"US",
    "sg:address":"1145 N Magnolia Dr",
    "sg:city":"El Dorado",
    "sg:classifiers":[
        {
            "category":"Building & Trades",
            "subcategory":"Cleaning & Sanitation",
            "type":"Services"
        }
    ],
    "sg:phone":"+1 870 863 0168",
    "sg:postcode":"71730",
    "sg:province":"AR",
    "sg:tags":[
        "maintenance"
    ],
    "wof:name":"TEC",
    "wof:placetype":"venue"
},
  "geometry": {"coordinates":[-92.67564,33.230554],"type":"Point"}
}