{
  "type": "Feature",
  "properties": {
    "addr:full":"295 N Center St Elkins AR 72727",
    "addr:housenumber":"295",
    "addr:postcode":"72727",
    "addr:street":"N Center St",
    "iso:country":"US",
    "sg:address":"295 N Center St",
    "sg:city":"Elkins",
    "sg:classifiers":[
        {
            "category":"Autos & Motor Vehicles",
            "subcategory":"Fuel & Gas Station",
            "type":"Retail Goods"
        }
    ],
    "sg:phone":"+1 479 643 3307",
    "sg:postcode":"72727",
    "sg:province":"AR",
    "sg:tags":[
        "station",
        "gasoline"
    ],
    "wof:name":"Valero Energy Corporation",
    "wof:placetype":"venue"
},
  "geometry": {"coordinates":[-94.00879399999999,36.004207],"type":"Point"}
}