{
  "type": "Feature",
  "properties": {
    "iso:country":"US",
    "sg:address":"601 W Walnut St",
    "sg:city":"Rogers",
    "sg:classifiers":[
        {
            "category":"Insurance",
            "subcategory":"Insurance Agent",
            "type":"Services"
        }
    ],
    "sg:phone":"+1 479 621 6776",
    "sg:postcode":"72756",
    "sg:province":"AR",
    "sg:tags":[
        "adjuster"
    ],
    "wof:name":"Advantage Claim And Mediat",
    "wof:placetype":"venue"
},
  "geometry": {"coordinates":[-94.12252,36.333431],"type":"Point"}
}