{
  "type": "Feature",
  "properties": {
    "addr:full":"2721 Joyce Cir Alexander AR 72002",
    "addr:housenumber":"2721",
    "addr:postcode":"72002",
    "addr:street":"Joyce Cir Alexander",
    "iso:country":"US",
    "sg:address":"2721 Joyce Cir",
    "sg:city":"Alexander",
    "sg:classifiers":[
        {
            "category":"Professional",
            "subcategory":"Employment Agencies",
            "type":"Services"
        }
    ],
    "sg:phone":"+1 501 847 1661",
    "sg:postcode":"72002",
    "sg:province":"AR",
    "sg:tags":[
        "help",
        "supply"
    ],
    "wof:name":"Maids In Arkansas",
    "wof:placetype":"venue"
},
  "geometry": {"coordinates":[-92.51493600000001,34.667159],"type":"Point"}
}