{
  "type": "Feature",
  "properties": {
    "addr:full":"611 N Roseville St Paris AR 72855",
    "addr:housenumber":"611",
    "addr:postcode":"72855",
    "addr:street":"N Roseville St",
    "iso:country":"US",
    "sg:address":"611 N Roseville St",
    "sg:city":"Paris",
    "sg:classifiers":[
        {
            "category":"Farming",
            "subcategory":"Farm",
            "type":"Manufacturing & Wholesale Goods"
        }
    ],
    "sg:phone":"+1 479 963 2067",
    "sg:postcode":"72855",
    "sg:province":"AR",
    "wof:name":"Hudson Farm",
    "wof:placetype":"venue"
},
  "geometry": {"coordinates":[-93.732327,35.296385],"type":"Point"}
}