{
  "type": "Feature",
  "properties": {
    "addr:full":"30 N Meadowcliff Dr Little Rock AR 72209",
    "addr:housenumber":"30",
    "addr:postcode":"72209",
    "addr:street":"N Meadowcliff Dr",
    "iso:country":"US",
    "sg:address":"30 N Meadowcliff Dr",
    "sg:city":"Little Rock",
    "sg:classifiers":[
        {
            "category":"Building & Trades",
            "subcategory":"Construction",
            "type":"Services"
        }
    ],
    "sg:phone":"+1 501 565 0295",
    "sg:postcode":"72209",
    "sg:province":"AR",
    "sg:tags":[
        "contractor"
    ],
    "wof:name":"Pro Concrete Construction",
    "wof:placetype":"venue"
},
  "geometry": {"coordinates":[-92.34915100000001,34.700347],"type":"Point"}
}