{
  "type": "Feature",
  "properties": {
    "iso:country":"US",
    "sg:address":"8915 Park Ave",
    "sg:city":"Hot Springs",
    "sg:classifiers":[
        {
            "category":"Food & Beverages",
            "subcategory":"Liquor & Beverages",
            "type":"Retail Goods"
        }
    ],
    "sg:phone":"+1 501 318 0888",
    "sg:postcode":"71901",
    "sg:province":"AR",
    "sg:tags":[
        "alcoholic"
    ],
    "wof:name":"House of Liquor",
    "wof:placetype":"venue"
},
  "geometry": {"coordinates":[-92.90542,34.616706],"type":"Point"}
}