{
  "type": "Feature",
  "properties": {
    "addr:full":"393 Polk Road 76 E Mena AR 71953",
    "addr:housenumber":"393",
    "addr:postcode":"71953",
    "addr:street":"Polk Road 76 E",
    "iso:country":"US",
    "sg:address":"393 Polk Road 76 E",
    "sg:city":"Mena",
    "sg:classifiers":[
        {
            "category":"Communications",
            "subcategory":"Film & Video Production",
            "type":"Services"
        }
    ],
    "sg:phone":"+1 479 394 6723",
    "sg:postcode":"71953",
    "sg:province":"AR",
    "sg:tags":[
        "motion"
    ],
    "wof:name":"Anders Inc",
    "wof:placetype":"venue"
},
  "geometry": {"coordinates":[-94.18674,34.630291],"type":"Point"}
}