{
  "type": "Feature",
  "properties": {
    "iso:country":"US",
    "sg:address":"201 S Center St",
    "sg:city":"Lonoke",
    "sg:classifiers":[
        {
            "category":"Utilities",
            "subcategory":"Refuse",
            "type":"Services"
        }
    ],
    "sg:phone":"+1 501 676 3779",
    "sg:postcode":"72086",
    "sg:province":"AR",
    "sg:tags":[
        "garbage",
        "collection"
    ],
    "wof:name":"C & S Sanitation Svc",
    "wof:placetype":"venue"
},
  "geometry": {"coordinates":[-91.900084,34.782875],"type":"Point"}
}