{
  "type": "Feature",
  "properties": {
    "addr:full":"2512 E Harding Ave Pine Bluff AR 71601",
    "addr:housenumber":"2512",
    "addr:postcode":"71601",
    "addr:street":"E Harding Ave",
    "iso:country":"US",
    "sg:address":"2512 E Harding Ave",
    "sg:city":"Pine Bluff",
    "sg:classifiers":[
        {
            "category":"Shopping",
            "subcategory":"Used Merchandise",
            "type":"Retail Goods"
        }
    ],
    "sg:phone":"+1 870 536 3348",
    "sg:postcode":"71601",
    "sg:province":"AR",
    "sg:tags":[
        "shop",
        "thrift"
    ],
    "wof:name":"Delta Network Thrift Store",
    "wof:placetype":"venue"
},
  "geometry": {"coordinates":[-91.973968,34.212043],"type":"Point"}
}