{
  "type": "Feature",
  "properties": {
    "addr:full":"69 Stoneledge Dr Maumelle AR 72113",
    "addr:housenumber":"69",
    "addr:postcode":"72113",
    "addr:street":"Stoneledge Dr Maumelle",
    "iso:country":"US",
    "sg:address":"69 Stoneledge Dr",
    "sg:city":"Maumelle",
    "sg:classifiers":[
        {
            "category":"Professional",
            "subcategory":"Accounting & Tax Preparation",
            "type":"Services"
        }
    ],
    "sg:phone":"+1 501 310 8563",
    "sg:postcode":"72113",
    "sg:province":"AR",
    "sg:tags":[
        "return",
        "preparation-business"
    ],
    "wof:name":"Gattinger Tax And Bookkeeping",
    "wof:placetype":"venue"
},
  "geometry": {"coordinates":[-92.410797,34.873225],"type":"Point"}
}