{
  "type": "Feature",
  "properties": {
    "addr:full":"7516 Palm Beach Ave Benton AR 72019",
    "addr:housenumber":"7516",
    "addr:postcode":"72019",
    "addr:street":"Palm Beach Ave",
    "iso:country":"US",
    "sg:address":"7516 Palm Beach Ave",
    "sg:city":"Benton",
    "sg:classifiers":[
        {
            "category":"Health Services",
            "subcategory":"Doctor",
            "type":"Services"
        }
    ],
    "sg:phone":"+1 501 847 9282",
    "sg:postcode":"72019",
    "sg:province":"AR",
    "sg:tags":[
        "medicine",
        "physician",
        "practice",
        "surgeons",
        "family"
    ],
    "wof:name":"D Scott Walsh Md Pa",
    "wof:placetype":"venue"
},
  "geometry": {"coordinates":[-92.522336,34.632971],"type":"Point"}
}