{
  "type": "Feature",
  "properties": {
    "iso:country":"US",
    "sg:address":"760 Turkey Pond Loop",
    "sg:city":"Morrilton",
    "sg:classifiers":[
        {
            "category":"Professional",
            "subcategory":"Advertising",
            "type":"Services"
        }
    ],
    "sg:phone":"+1 501 354 2498",
    "sg:postcode":"72110",
    "sg:province":"AR",
    "sg:tags":[
        "marketing",
        "program"
    ],
    "wof:name":"Dewey Dale Holsted",
    "wof:placetype":"venue"
},
  "geometry": {"coordinates":[-92.737936,35.228817],"type":"Point"}
}