{
  "type": "Feature",
  "properties": {
    "iso:country":"US",
    "sg:address":"2420 Batesville Blvd",
    "sg:city":"Batesville",
    "sg:classifiers":[
        {
            "category":"Autos & Motor Vehicles",
            "subcategory":"Automobile Sales",
            "type":"Retail Goods"
        }
    ],
    "sg:phone":"+1 870 251 3338",
    "sg:postcode":"72501",
    "sg:province":"AR",
    "sg:tags":[
        "car",
        "dealer"
    ],
    "wof:name":"C & C Auto Sales",
    "wof:placetype":"venue"
},
  "geometry": {"coordinates":[-91.61659899999999,35.685641],"type":"Point"}
}