{
  "type": "Feature",
  "properties": {
    "iso:country":"US",
    "sg:address":"430 Helen St",
    "sg:city":"West Helena",
    "sg:classifiers":[
        {
            "category":"Organizations",
            "subcategory":"Community Association",
            "type":"Services"
        }
    ],
    "sg:phone":"+1 870 572 7894",
    "sg:postcode":"72390",
    "sg:province":"AR",
    "wof:name":"National Assoc of Retired",
    "wof:placetype":"venue"
},
  "geometry": {"coordinates":[-90.645097,34.551252],"type":"Point"}
}