{
  "type": "Feature",
  "properties": {
    "iso:country":"US",
    "sg:address":"1115 S School Ave",
    "sg:city":"Fayetteville",
    "sg:classifiers":[
        {
            "category":"Retail",
            "subcategory":"Repair Shop",
            "type":"Services"
        }
    ],
    "sg:phone":"+1 479 527 6309",
    "sg:postcode":"72701",
    "sg:province":"AR",
    "sg:tags":[
        "appliance"
    ],
    "wof:name":"Ingram Appliance Sales & Svc",
    "wof:placetype":"venue"
},
  "geometry": {"coordinates":[-94.164347,36.050586],"type":"Point"}
}