{
  "type": "Feature",
  "properties": {
    "addr:full":"1171 Highway 133 N Crossett AR 71635",
    "addr:housenumber":"1171",
    "addr:postcode":"71635",
    "addr:street":"Highway 133 N",
    "iso:country":"US",
    "sg:address":"1171 Highway 133 N",
    "sg:city":"Crossett",
    "sg:classifiers":[
        {
            "category":"Shopping",
            "subcategory":"Gifts & Souvenirs",
            "type":"Retail Goods"
        },
        {
            "category":"Shopping",
            "subcategory":"Florist",
            "type":"Retail Goods"
        }
    ],
    "sg:phone":"+1 870 364 7703",
    "sg:postcode":"71635",
    "sg:province":"AR",
    "sg:tags":[
        "shop"
    ],
    "wof:name":"Imogene's Florist & Gifts",
    "wof:placetype":"venue"
},
  "geometry": {"coordinates":[-91.947906,33.155293],"type":"Point"}
}