{
  "type": "Feature",
  "properties": {
    "iso:country":"US",
    "sg:address":"1705 Valley View St",
    "sg:city":"Van Buren",
    "sg:classifiers":[
        {
            "category":"Building & Trades",
            "subcategory":"Construction",
            "type":"Services"
        }
    ],
    "sg:phone":"+1 479 471 5758",
    "sg:postcode":"72956",
    "sg:province":"AR",
    "sg:tags":[
        "general"
    ],
    "wof:name":"Danny Stouffer",
    "wof:placetype":"venue"
},
  "geometry": {"coordinates":[-94.373046,35.464419],"type":"Point"}
}