{
  "type": "Feature",
  "properties": {
    "addr:full":"5827 Crystal Hill Rd N Little Rock AR 72118",
    "addr:housenumber":"5827",
    "addr:postcode":"72118",
    "addr:street":"Crystal Hill Rd N",
    "iso:country":"US",
    "sg:address":"5827 Crystal Hill Rd",
    "sg:city":"N Little Rock",
    "sg:classifiers":[
        {
            "category":"Shopping",
            "subcategory":"Bicycles & Sporting Goods",
            "type":"Retail Goods"
        }
    ],
    "sg:phone":"+1 501 758 4958",
    "sg:postcode":"72118",
    "sg:province":"AR",
    "sg:tags":[
        "bait",
        "fishing"
    ],
    "wof:name":"Hatchet Jack's Sports Shop",
    "wof:placetype":"venue"
},
  "geometry": {"coordinates":[-92.33371699999999,34.816891],"type":"Point"}
}