{
  "type": "Feature",
  "properties": {
    "addr:full":"107 Gregory Pl Jacksonville AR 72076",
    "addr:housenumber":"107",
    "addr:postcode":"72076",
    "addr:street":"Gregory Pl",
    "iso:country":"US",
    "sg:address":"107 Gregory Pl",
    "sg:city":"Jacksonville",
    "sg:classifiers":[
        {
            "category":"Shopping",
            "subcategory":"Department Store",
            "type":"Retail Goods"
        }
    ],
    "sg:phone":"+1 501 985 1441",
    "sg:postcode":"72076",
    "sg:province":"AR",
    "sg:website":"www.stagestoresinc.com",
    "wof:name":"Stage",
    "wof:placetype":"venue"
},
  "geometry": {"coordinates":[-92.109669,34.880664],"type":"Point"}
}