{
  "type": "Feature",
  "properties": {
    "addr:full":"1777 Tallgrass Dr Fayetteville AR 72701",
    "addr:housenumber":"1777",
    "addr:postcode":"72701",
    "addr:street":"Tallgrass Dr",
    "iso:country":"US",
    "sg:address":"1777 Tallgrass Dr",
    "sg:city":"Fayetteville",
    "sg:classifiers":[
        {
            "category":"Professional",
            "type":"Services"
        }
    ],
    "sg:phone":"+1 479 251 9173",
    "sg:postcode":"72701",
    "sg:province":"AR",
    "wof:name":"JB Equine Specialties LLC",
    "wof:placetype":"venue"
},
  "geometry": {"coordinates":[-94.087485,36.043808],"type":"Point"}
}