{
  "type": "Feature",
  "properties": {
    "iso:country":"US",
    "sg:address":"901 S Drew St",
    "sg:city":"Star City",
    "sg:classifiers":[
        {
            "category":"Social Services",
            "subcategory":"Child Care",
            "type":"Services"
        }
    ],
    "sg:phone":"+1 870 628 4618",
    "sg:postcode":"71667",
    "sg:province":"AR",
    "sg:tags":[
        "day"
    ],
    "wof:name":"Star City Child Development",
    "wof:placetype":"venue"
},
  "geometry": {"coordinates":[-91.84517099999999,33.933737],"type":"Point"}
}