{
  "type": "Feature",
  "properties": {
    "addr:full":"22254 State Hwy 109 Scranton AR 72863",
    "addr:housenumber":"22254",
    "addr:postcode":"72863",
    "addr:street":"State Hwy 109",
    "iso:country":"US",
    "sg:address":"22254 State Hwy 109",
    "sg:city":"Scranton",
    "sg:classifiers":[
        {
            "category":"Food & Beverages",
            "subcategory":"Groceries & Convenience Stores",
            "type":"Retail Goods"
        }
    ],
    "sg:phone":"+1 479 938 7000",
    "sg:postcode":"72863",
    "sg:province":"AR",
    "sg:tags":[
        "station",
        "gasoline",
        "coin",
        "operate"
    ],
    "wof:name":"Circle S Food Store Inc",
    "wof:placetype":"venue"
},
  "geometry": {"coordinates":[-93.52499,35.337422],"type":"Point"}
}