{
  "type": "Feature",
  "properties": {
    "iso:country":"US",
    "sg:address":"123 Riverview Rd",
    "sg:city":"Morrilton",
    "sg:classifiers":[
        {
            "category":"Education",
            "subcategory":"School",
            "type":"Public Place"
        }
    ],
    "sg:phone":"+1 501 354 0327",
    "sg:postcode":"72110",
    "sg:province":"AR",
    "sg:tags":[
        "religious"
    ],
    "wof:name":"Riverview Baptist Christian Sc",
    "wof:placetype":"venue"
},
  "geometry": {"coordinates":[-92.786361,35.116185],"type":"Point"}
}