{
  "type": "Feature",
  "properties": {
    "addr:full":"212 W Portland Ave Russellville AR 72801",
    "addr:housenumber":"212",
    "addr:postcode":"72801",
    "addr:street":"W Portland Ave",
    "iso:country":"US",
    "sg:address":"212 W Portland Ave",
    "sg:city":"Russellville",
    "sg:classifiers":[
        {
            "category":"Building & Trades",
            "subcategory":"Construction",
            "type":"Services"
        }
    ],
    "sg:phone":"+1 479 968 7500",
    "sg:postcode":"72801",
    "sg:province":"AR",
    "sg:tags":[
        "excavation",
        "contractor"
    ],
    "wof:name":"Cochran Higgs Construction",
    "wof:placetype":"venue"
},
  "geometry": {"coordinates":[-93.167783,35.29155],"type":"Point"}
}