{
  "type": "Feature",
  "properties": {
    "addr:full":"708 Highway 65 S Dumas AR 71639",
    "addr:housenumber":"708",
    "addr:postcode":"71639",
    "addr:street":"Highway 65 S Dumas",
    "iso:country":"US",
    "sg:address":"708 Highway 65 S",
    "sg:city":"Dumas",
    "sg:classifiers":[
        {
            "category":"Food & Beverages",
            "subcategory":"Liquor & Beverages",
            "type":"Retail Goods"
        }
    ],
    "sg:phone":"+1 870 382 2300",
    "sg:postcode":"71639",
    "sg:province":"AR",
    "sg:tags":[
        "store"
    ],
    "wof:name":"Bottle Shop, The",
    "wof:placetype":"venue"
},
  "geometry": {"coordinates":[-91.481632,33.873865],"type":"Point"}
}