{
  "type": "Feature",
  "properties": {
    "iso:country":"US",
    "sg:address":"104 S 5th St",
    "sg:city":"Heber Springs",
    "sg:classifiers":[
        {
            "category":"Professional",
            "subcategory":"Management & Consulting",
            "type":"Services"
        }
    ],
    "sg:phone":"+1 501 206 0081",
    "sg:postcode":"72543",
    "sg:province":"AR",
    "sg:tags":[
        "personnel",
        "consultant"
    ],
    "wof:name":"ESA Employers Staffing-Amrc",
    "wof:placetype":"venue"
},
  "geometry": {"coordinates":[-92.033931,35.49162],"type":"Point"}
}