{
  "type": "Feature",
  "properties": {
    "addr:full":"401 N Greenwood Ave Fort Smith AR 72901",
    "addr:housenumber":"401",
    "addr:postcode":"72901",
    "addr:street":"N Greenwood Ave",
    "iso:country":"US",
    "sg:address":"401 N Greenwood Ave",
    "sg:city":"Fort Smith",
    "sg:classifiers":[
        {
            "category":"Manufacturing",
            "subcategory":"Printing",
            "type":"Manufacturing & Wholesale Goods"
        }
    ],
    "sg:phone":"+1 479 785 5209",
    "sg:postcode":"72901",
    "sg:province":"AR",
    "sg:tags":[
        "lithographic",
        "commercial",
        "photocopying"
    ],
    "wof:name":"Jiffy Print",
    "wof:placetype":"venue"
},
  "geometry": {"coordinates":[-94.403414,35.379978],"type":"Point"}
}