{
  "type": "Feature",
  "properties": {
    "iso:country":"US",
    "sg:address":"80 Thomas Rd",
    "sg:city":"Greenbrier",
    "sg:classifiers":[
        {
            "category":"Autos & Motor Vehicles",
            "subcategory":"Automobile Sales",
            "type":"Retail Goods"
        }
    ],
    "sg:phone":"+1 501 679 4989",
    "sg:postcode":"72058",
    "sg:province":"AR",
    "sg:tags":[
        "used"
    ],
    "wof:name":"Venable Motor Cars Inc",
    "wof:placetype":"venue"
},
  "geometry": {"coordinates":[-92.242822,35.287358],"type":"Point"}
}