{
  "type": "Feature",
  "properties": {
    "iso:country":"US",
    "sg:address":"146 Pullman Rd",
    "sg:city":"De Queen",
    "sg:classifiers":[
        {
            "category":"Retail",
            "subcategory":"Repair Shop",
            "type":"Services"
        }
    ],
    "sg:phone":"+1 870 642 6302",
    "sg:postcode":"71832",
    "sg:province":"AR",
    "wof:name":"J T R Locksmith",
    "wof:placetype":"venue"
},
  "geometry": {"coordinates":[-94.312929,34.111144],"type":"Point"}
}