{
  "type": "Feature",
  "properties": {
    "iso:country":"US",
    "sg:address":"1198 State Hwy 31",
    "sg:city":"Searcy",
    "sg:classifiers":[
        {
            "category":"Organizations",
            "subcategory":"Religious Organization",
            "type":"Services"
        }
    ],
    "sg:phone":"+1 501 796 4823",
    "sg:postcode":"72143",
    "sg:province":"AR",
    "sg:tags":[
        "church"
    ],
    "wof:name":"First Baptist Church Of Floyd",
    "wof:placetype":"venue"
},
  "geometry": {"coordinates":[-91.967743,35.1972],"type":"Point"}
}