{
  "type": "Feature",
  "properties": {
    "iso:country":"US",
    "sg:address":"2205 SE Walton Blvd",
    "sg:city":"Bentonville",
    "sg:classifiers":[
        {
            "category":"Travel",
            "subcategory":"Hotels & Motels",
            "type":"Entertainment"
        },
        {
            "category":"Retail",
            "subcategory":"Event Space",
            "type":"Services"
        }
    ],
    "sg:phone":"+1 479 271 2222",
    "sg:postcode":"72712",
    "sg:province":"AR",
    "sg:tags":[
        "facility",
        "venue",
        "hall",
        "reception",
        "lodging",
        "corporate",
        "banquet"
    ],
    "sg:website":"www.holidayinnexpress.com",
    "wof:name":"Holiday Inn Express Hotel & Suites Bentonville",
    "wof:placetype":"venue"
},
  "geometry": {"coordinates":[-94.187357,36.335142],"type":"Point"}
}