{
  "type": "Feature",
  "properties": {
    "iso:country":"US",
    "sg:address":"3093 E Main St",
    "sg:city":"Russellville",
    "sg:classifiers":[
        {
            "category":"Health Services",
            "subcategory":"Optometrist",
            "type":"Services"
        }
    ],
    "sg:phone":"+1 479 967 0600",
    "sg:postcode":"72802",
    "sg:province":"AR",
    "wof:name":"Family Eye Care Of Russellvile",
    "wof:placetype":"venue"
},
  "geometry": {"coordinates":[-93.093971,35.277916],"type":"Point"}
}