{
  "type": "Feature",
  "properties": {
    "addr:full":"1915 Central Ave Hot Springs National AR 71901",
    "addr:housenumber":"1915",
    "addr:postcode":"71901",
    "addr:street":"Central Ave",
    "iso:country":"US",
    "sg:address":"1915 Central Ave",
    "sg:city":"Hot Springs National",
    "sg:classifiers":[
        {
            "category":"Retail",
            "subcategory":"Auto Repair",
            "type":"Services"
        }
    ],
    "sg:phone":"+1 501 624 5234",
    "sg:postcode":"71901",
    "sg:province":"AR",
    "sg:tags":[
        "body"
    ],
    "wof:name":"Terrys Body Shop",
    "wof:placetype":"venue"
},
  "geometry": {"coordinates":[-93.057761,34.494218],"type":"Point"}
}