{
  "type": "Feature",
  "properties": {
    "iso:country":"US",
    "sg:address":"139 Brownsville Springs Rd",
    "sg:city":"Greers Ferry",
    "sg:classifiers":[
        {
            "category":"Building & Trades",
            "subcategory":"Plumbing",
            "type":"Services"
        }
    ],
    "sg:phone":"+1 501 825 7715",
    "sg:postcode":"72067",
    "sg:province":"AR",
    "sg:tags":[
        "plumbing",
        "contractor"
    ],
    "wof:name":"Newby Plumbing",
    "wof:placetype":"venue"
},
  "geometry": {"coordinates":[-92.063638,35.593816],"type":"Point"}
}