{
  "type": "Feature",
  "properties": {
    "addr:full":"2481 E Grand Ave Hot Springs AR 71901",
    "addr:housenumber":"2481",
    "addr:postcode":"71901",
    "addr:street":"E Grand Ave",
    "iso:country":"US",
    "sg:address":"2481 E Grand Ave",
    "sg:city":"Hot Springs",
    "sg:classifiers":[
        {
            "category":"Real Estate",
            "subcategory":"Real Estate Operator",
            "type":"Services"
        }
    ],
    "sg:phone":"+1 501 525 1559",
    "sg:postcode":"71901",
    "sg:province":"AR",
    "sg:tags":[
        "mobile",
        "home",
        "community"
    ],
    "wof:name":"Morphew Mobile Home Park",
    "wof:placetype":"venue"
},
  "geometry": {"coordinates":[-92.992749,34.505297],"type":"Point"}
}