{
  "type": "Feature",
  "properties": {
    "iso:country":"US",
    "sg:address":"6295 State Hwy 8",
    "sg:city":"Mena",
    "sg:classifiers":[
        {
            "category":"Professional",
            "subcategory":"Management & Consulting",
            "type":"Services"
        }
    ],
    "sg:phone":"+1 479 394 7011",
    "sg:postcode":"71953",
    "sg:province":"OK",
    "sg:tags":[
        "retail",
        "direct",
        "sales"
    ],
    "wof:name":"Black Bear Springs Ex Trnsp",
    "wof:placetype":"venue"
},
  "geometry": {"coordinates":[-93.955609,34.469251],"type":"Point"}
}