{
  "type": "Feature",
  "properties": {
    "addr:full":"215 N 2nd West Helena AR 72390",
    "addr:housenumber":"215",
    "addr:postcode":"72390",
    "addr:street":"N 2Nd West Helena",
    "iso:country":"US",
    "sg:address":"215 N 2nd",
    "sg:city":"West Helena",
    "sg:classifiers":[
        {
            "category":"Social Services",
            "type":"Services"
        }
    ],
    "sg:phone":"+1 870 572 9530",
    "sg:postcode":"72390",
    "sg:province":"AR",
    "sg:tags":[
        "agency",
        "family"
    ],
    "wof:name":"Family Center Inc",
    "wof:placetype":"venue"
},
  "geometry": {"coordinates":[-90.643776,34.547817],"type":"Point"}
}