{
  "type": "Feature",
  "properties": {
    "addr:full":"5047 US Hwy 70 Newhope AR 71959",
    "addr:housenumber":"5047",
    "addr:postcode":"71959",
    "addr:street":"Us Hwy 70 Newhope",
    "iso:country":"US",
    "sg:address":"5047 US Hwy 70",
    "sg:city":"Newhope",
    "sg:classifiers":[
        {
            "category":"Food & Beverages",
            "subcategory":"Groceries & Convenience Stores",
            "type":"Retail Goods"
        }
    ],
    "sg:phone":"+1 870 398 4798",
    "sg:postcode":"71959",
    "sg:province":"AR",
    "wof:name":"Star of West",
    "wof:placetype":"venue"
},
  "geometry": {"coordinates":[-93.832874,34.241062],"type":"Point"}
}