{
  "type": "Feature",
  "properties": {
    "addr:full":"1002 SE 14th St Bentonville AR 72712",
    "addr:housenumber":"1002",
    "addr:postcode":"72712",
    "addr:street":"Se 14Th St",
    "iso:country":"US",
    "sg:address":"1002 SE 14th St",
    "sg:city":"Bentonville",
    "sg:classifiers":[
        {
            "category":"Professional",
            "subcategory":"Management & Consulting",
            "type":"Services"
        },
        {
            "category":"Professional",
            "subcategory":"Employment Agencies",
            "type":"Services"
        }
    ],
    "sg:phone":"+1 479 271 8958",
    "sg:postcode":"72712",
    "sg:province":"AR",
    "sg:tags":[
        "personnel",
        "consultant"
    ],
    "wof:name":"Judge Group",
    "wof:placetype":"venue"
},
  "geometry": {"coordinates":[-94.19709400000001,36.356709],"type":"Point"}
}