{
  "type": "Feature",
  "properties": {
    "addr:full":"190 Spring St Eureka Springs AR 72632",
    "addr:housenumber":"190",
    "addr:postcode":"72632",
    "addr:street":"Spring St",
    "iso:country":"US",
    "sg:address":"190 Spring St",
    "sg:city":"Eureka Springs",
    "sg:classifiers":[
        {
            "category":"Shopping",
            "subcategory":"Used Merchandise",
            "type":"Retail Goods"
        }
    ],
    "sg:phone":"+1 479 253 9586",
    "sg:postcode":"72632",
    "sg:province":"AR",
    "sg:tags":[
        "antique"
    ],
    "wof:name":"Crystal Gardens Antiques",
    "wof:placetype":"venue"
},
  "geometry": {"coordinates":[-93.736726,36.405893],"type":"Point"}
}