{
  "type": "Feature",
  "properties": {
    "iso:country":"US",
    "sg:address":"121 E Main St",
    "sg:city":"Gentry",
    "sg:classifiers":[
        {
            "category":"Real Estate",
            "subcategory":"Real Estate Agent",
            "type":"Services"
        }
    ],
    "sg:phone":"+1 479 736 2005",
    "sg:postcode":"72734",
    "sg:province":"AR",
    "wof:name":"Sheilds Real Estate",
    "wof:placetype":"venue"
},
  "geometry": {"coordinates":[-94.483458,36.267469],"type":"Point"}
}