{
  "type": "Feature",
  "properties": {
    "addr:full":"1823 Grant Ave Jonesboro AR 72401",
    "addr:housenumber":"1823",
    "addr:postcode":"72401",
    "addr:street":"Grant Ave",
    "iso:country":"US",
    "sg:address":"1823 Grant Ave",
    "sg:city":"Jonesboro",
    "sg:classifiers":[
        {
            "category":"Manufacturing",
            "subcategory":"Printing",
            "type":"Manufacturing & Wholesale Goods"
        }
    ],
    "sg:phone":"+1 870 972 8800",
    "sg:postcode":"72401",
    "sg:province":"AR",
    "sg:tags":[
        "printer"
    ],
    "wof:name":"Abs Advantage LLC",
    "wof:placetype":"venue"
},
  "geometry": {"coordinates":[-90.68515600000001,35.818257],"type":"Point"}
}