{
  "type": "Feature",
  "properties": {
    "iso:country":"US",
    "sg:address":"270 E Page Ave",
    "sg:city":"Malvern",
    "sg:classifiers":[
        {
            "category":"Shopping",
            "subcategory":"Beauty & Cosmetics",
            "type":"Retail Goods"
        },
        {
            "category":"Personal",
            "subcategory":"Barber",
            "type":"Services"
        },
        {
            "category":"Personal",
            "subcategory":"Beauty Salon",
            "type":"Services"
        }
    ],
    "sg:phone":"+1 501 337 9660",
    "sg:postcode":"72104",
    "sg:province":"AR",
    "sg:tags":[
        "equipment",
        "perfume",
        "salons-equipment",
        "supply"
    ],
    "wof:name":"Exodus Beauty Supply",
    "wof:placetype":"venue"
},
  "geometry": {"coordinates":[-92.808982,34.3634],"type":"Point"}
}