{
  "type": "Feature",
  "properties": {
    "iso:country":"US",
    "sg:address":"1422 N 8th St",
    "sg:city":"Fort Smith",
    "sg:classifiers":[
        {
            "category":"Social Services",
            "type":"Services"
        }
    ],
    "sg:phone":"+1 479 783 3832",
    "sg:postcode":"72901",
    "sg:province":"AR",
    "sg:tags":[
        "youth",
        "organization",
        "center"
    ],
    "wof:name":"Lincoln Youth Svc Ctr",
    "wof:placetype":"venue"
},
  "geometry": {"coordinates":[-94.412338,35.397089],"type":"Point"}
}