{
  "type": "Feature",
  "properties": {
    "addr:full":"2729 E Nettleton Ave Jonesboro AR 72401",
    "addr:housenumber":"2729",
    "addr:postcode":"72401",
    "addr:street":"E Nettleton Ave",
    "iso:country":"US",
    "sg:address":"2729 E Nettleton Ave",
    "sg:city":"Jonesboro",
    "sg:classifiers":[
        {
            "category":"Arts & Performance",
            "subcategory":"Dance",
            "type":"Entertainment"
        }
    ],
    "sg:phone":"+1 870 932 1632",
    "sg:postcode":"72401",
    "sg:province":"AR",
    "sg:tags":[
        "instruction",
        "dancing"
    ],
    "wof:name":"Jonesboro Studio Of Dance",
    "wof:placetype":"venue"
},
  "geometry": {"coordinates":[-90.67141100000001,35.828377],"type":"Point"}
}