{
  "type": "Feature",
  "properties": {
    "addr:full":"4975 Malvern Rd Hot Springs AR 71901",
    "addr:housenumber":"4975",
    "addr:postcode":"71901",
    "addr:street":"Malvern Rd",
    "iso:country":"US",
    "sg:address":"4975 Malvern Rd",
    "sg:city":"Hot Springs",
    "sg:classifiers":[
        {
            "category":"Freight",
            "type":"Transportation"
        }
    ],
    "sg:phone":"+1 501 844 2045",
    "sg:postcode":"71901",
    "sg:province":"AR",
    "sg:tags":[
        "commercial",
        "storage"
    ],
    "wof:name":"County Line Mini Storage",
    "wof:placetype":"venue"
},
  "geometry": {"coordinates":[-92.91580999999999,34.466178],"type":"Point"}
}