{
  "type": "Feature",
  "properties": {
    "addr:full":"101 Overland Trl White Hall AR 71602",
    "addr:housenumber":"101",
    "addr:postcode":"71602",
    "addr:street":"Overland Trl",
    "iso:country":"US",
    "sg:address":"101 Overland Trl",
    "sg:city":"White Hall",
    "sg:classifiers":[
        {
            "category":"Retail",
            "subcategory":"Repair Shop",
            "type":"Services"
        }
    ],
    "sg:phone":"+1 870 540 9208",
    "sg:postcode":"71602",
    "sg:province":"AR",
    "wof:name":"Last Myle",
    "wof:placetype":"venue"
},
  "geometry": {"coordinates":[-92.08748799999999,34.259551],"type":"Point"}
}