{
  "type": "Feature",
  "properties": {
    "iso:country":"US",
    "sg:address":"101 Overland Trl",
    "sg:city":"White Hall",
    "sg:classifiers":[
        {
            "category":"Retail",
            "subcategory":"Repair Shop",
            "type":"Services"
        }
    ],
    "sg:phone":"+1 870 540 9208",
    "sg:postcode":"71602",
    "sg:province":"AR",
    "wof:name":"Last Myle",
    "wof:placetype":"venue"
},
  "geometry": {"coordinates":[-92.087488,34.259551],"type":"Point"}
}