{
  "type": "Feature",
  "properties": {
    "iso:country":"US",
    "sg:address":"700 W Grove St",
    "sg:city":"El Dorado",
    "sg:classifiers":[
        {
            "category":"Building & Trades",
            "subcategory":"Construction",
            "type":"Services"
        }
    ],
    "sg:phone":"+1 870 862 8011",
    "sg:postcode":"71730",
    "sg:province":"AR",
    "sg:tags":[
        "general",
        "contractor"
    ],
    "wof:name":"Ideal Construction",
    "wof:placetype":"venue"
},
  "geometry": {"coordinates":[-92.672726,33.218379],"type":"Point"}
}