{
  "type": "Feature",
  "properties": {
    "iso:country":"US",
    "sg:address":"45 Carol Ln",
    "sg:city":"Batesville",
    "sg:classifiers":[
        {
            "category":"Shopping",
            "subcategory":"Used Merchandise",
            "type":"Retail Goods"
        }
    ],
    "sg:phone":"+1 870 793 3567",
    "sg:postcode":"72501",
    "sg:province":"AR",
    "wof:name":"Out of Attic",
    "wof:placetype":"venue"
},
  "geometry": {"coordinates":[-91.651693,35.735675],"type":"Point"}
}