{
  "type": "Feature",
  "properties": {
    "iso:country":"US",
    "sg:address":"8602 Mopac Rd",
    "sg:city":"Brinkley",
    "sg:classifiers":[
        {
            "category":"Wholesale",
            "subcategory":"Groceries",
            "type":"Manufacturing & Wholesale Goods"
        }
    ],
    "sg:phone":"+1 870 734 3218",
    "sg:postcode":"72021",
    "sg:province":"AR",
    "sg:tags":[
        "rice"
    ],
    "wof:name":"W & W Partnership",
    "wof:placetype":"venue"
},
  "geometry": {"coordinates":[-91.182687,34.862881],"type":"Point"}
}