{
  "type": "Feature",
  "properties": {
    "iso:country":"US",
    "sg:address":"1208 N Rock St",
    "sg:city":"Sheridan",
    "sg:classifiers":[
        {
            "category":"Restaurant",
            "type":"Food & Drink"
        }
    ],
    "sg:phone":"+1 870 942 5715",
    "sg:postcode":"72150",
    "sg:province":"AR",
    "sg:tags":[
        "eating"
    ],
    "sg:website":"www.pizzapro.com",
    "wof:name":"Pizza Pro Inc",
    "wof:placetype":"venue"
},
  "geometry": {"coordinates":[-92.3954,34.318883],"type":"Point"}
}