{
  "type": "Feature",
  "properties": {
    "iso:country":"US",
    "sg:address":"13409 Cloverdale Rd",
    "sg:city":"Rogers",
    "sg:classifiers":[
        {
            "category":"Autos & Motor Vehicles",
            "subcategory":"Auto Supplies",
            "type":"Retail Goods"
        },
        {
            "category":"Wholesale",
            "subcategory":"Auto Parts",
            "type":"Manufacturing & Wholesale Goods"
        }
    ],
    "sg:phone":"+1 479 636 3225",
    "sg:postcode":"72756",
    "sg:province":"AR",
    "sg:tags":[
        "wheel",
        "automobile",
        "vehicles-supplies",
        "drive",
        "four",
        "equipment",
        "rebuilt-wholesale",
        "supplies-used",
        "truck",
        "rebuilt",
        "manufacturer"
    ],
    "sg:website":"http://www.paylessautosalvage.com",
    "wof:name":"Payless Auto Salvage",
    "wof:placetype":"venue"
},
  "geometry": {"coordinates":[-94.084295,36.368415],"type":"Point"}
}