{
  "type": "Feature",
  "properties": {
    "addr:full":"102 N 1st St Cabot AR 72023",
    "addr:housenumber":"102",
    "addr:postcode":"72023",
    "addr:street":"N 1St St",
    "iso:country":"US",
    "sg:address":"102 N 1st St",
    "sg:city":"Cabot",
    "sg:classifiers":[
        {
            "category":"Restaurant",
            "type":"Food & Drink"
        }
    ],
    "sg:phone":"+1 501 628 5151",
    "sg:postcode":"72023",
    "sg:province":"AR",
    "sg:tags":[
        "eating"
    ],
    "wof:name":"Coffeelicious",
    "wof:placetype":"venue"
},
  "geometry": {"coordinates":[-92.01554299999999,34.974328],"type":"Point"}
}