{
  "type": "Feature",
  "properties": {
    "iso:country":"US",
    "sg:address":"102 N Oak St",
    "sg:city":"Sheridan",
    "sg:classifiers":[
        {
            "category":"Building & Trades",
            "subcategory":"Cleaning & Sanitation",
            "type":"Services"
        }
    ],
    "sg:phone":"+1 870 942 0775",
    "sg:postcode":"72150",
    "sg:province":"AR",
    "sg:tags":[
        "cleaners-interior"
    ],
    "wof:name":"Grove Building Services Inc",
    "wof:placetype":"venue"
},
  "geometry": {"coordinates":[-92.401481,34.306852],"type":"Point"}
}