{
  "type": "Feature",
  "properties": {
    "iso:country":"US",
    "sg:address":"12 Baker Cir",
    "sg:city":"North Little Rock",
    "sg:classifiers":[
        {
            "category":"Personal",
            "subcategory":"Beauty Salon",
            "type":"Services"
        }
    ],
    "sg:phone":"+1 501 771 9958",
    "sg:postcode":"72118",
    "sg:province":"AR",
    "sg:tags":[
        "shop"
    ],
    "wof:name":"Silhouettes Hair Salon Inc",
    "wof:placetype":"venue"
},
  "geometry": {"coordinates":[-92.285737,34.80832],"type":"Point"}
}