{
  "type": "Feature",
  "properties": {
    "addr:full":"517 Hwy 71 SW Mountainburg AR 72946",
    "addr:housenumber":"517",
    "addr:postcode":"72946",
    "addr:street":"Hwy 71 Sw",
    "iso:country":"US",
    "sg:address":"517 Hwy 71 SW",
    "sg:city":"Mountainburg",
    "sg:classifiers":[
        {
            "category":"Personal",
            "subcategory":"Beauty Salon",
            "type":"Services"
        }
    ],
    "sg:phone":"+1 479 369 2080",
    "sg:postcode":"72946",
    "sg:province":"AR",
    "wof:name":"Cathy's Hair Depot",
    "wof:placetype":"venue"
},
  "geometry": {"coordinates":[-94.171381,35.628359],"type":"Point"}
}