{
  "type": "Feature",
  "properties": {
    "iso:country":"US",
    "sg:address":"9300 N Park Rd",
    "sg:city":"Rogers",
    "sg:classifiers":[
        {
            "category":"Recreation",
            "type":"Entertainment"
        }
    ],
    "sg:phone":"+1 479 925 3957",
    "sg:postcode":"72756",
    "sg:province":"AR",
    "sg:tags":[
        "parks"
    ],
    "wof:name":"Prairie Creek Park",
    "wof:placetype":"venue"
},
  "geometry": {"coordinates":[-94.055714,36.34849],"type":"Point"}
}