{
  "type": "Feature",
  "properties": {
    "iso:country":"US",
    "sg:address":"5515 Brown St",
    "sg:city":"Little Rock",
    "sg:classifiers":[
        {
            "category":"Organizations",
            "subcategory":"Religious Organization",
            "type":"Services"
        }
    ],
    "sg:phone":"+1 501 897 1194",
    "sg:postcode":"72206",
    "sg:province":"AR",
    "sg:tags":[
        "church"
    ],
    "wof:name":"Jackson Memorial Church Of God",
    "wof:placetype":"venue"
},
  "geometry": {"coordinates":[-92.225011,34.611344],"type":"Point"}
}