{
  "type": "Feature",
  "properties": {
    "iso:country":"US",
    "sg:address":"359 School Ave",
    "sg:city":"West Fork",
    "sg:classifiers":[
        {
            "category":"Education",
            "subcategory":"School",
            "type":"Public Place"
        }
    ],
    "sg:phone":"+1 479 839 3131",
    "sg:postcode":"72774",
    "sg:province":"AR",
    "wof:name":"West Fork High School",
    "wof:placetype":"venue"
},
  "geometry": {"coordinates":[-94.19114,35.922501],"type":"Point"}
}