{
  "type": "Feature",
  "properties": {
    "iso:country":"US",
    "sg:address":"1104 Poplar Pl",
    "sg:city":"Rogers",
    "sg:classifiers":[
        {
            "category":"Health Services",
            "subcategory":"Doctor",
            "type":"Services"
        }
    ],
    "sg:phone":"+1 479 273 9300",
    "sg:postcode":"72756",
    "sg:province":"AR",
    "sg:tags":[
        "orthodontist"
    ],
    "wof:name":"M S",
    "wof:placetype":"venue"
},
  "geometry": {"coordinates":[-94.130755,36.33142],"type":"Point"}
}