{
  "type": "Feature",
  "properties": {
    "iso:country":"US",
    "sg:address":"401 E 11th St",
    "sg:city":"Stuttgart",
    "sg:classifiers":[
        {
            "category":"Freight",
            "type":"Transportation"
        }
    ],
    "sg:phone":"+1 870 673 1541",
    "sg:postcode":"72160",
    "sg:province":"AR",
    "sg:tags":[
        "operator",
        "trucking"
    ],
    "wof:name":"Pld Transport, Inc.",
    "wof:placetype":"venue"
},
  "geometry": {"coordinates":[-91.548441,34.492866],"type":"Point"}
}