{
  "type": "Feature",
  "properties": {
    "iso:country":"US",
    "sg:address":"1405 N Pierce St",
    "sg:city":"Little Rock",
    "sg:classifiers":[
        {
            "category":"Health Services",
            "subcategory":"Doctor",
            "type":"Services"
        }
    ],
    "sg:phone":"+1 501 603 2147",
    "sg:postcode":"72207",
    "sg:province":"AR",
    "sg:tags":[
        "clinic"
    ],
    "wof:name":"Rivendell Outpatient Clinic",
    "wof:placetype":"venue"
},
  "geometry": {"coordinates":[-92.337861,34.76509],"type":"Point"}
}