{
  "type": "Feature",
  "properties": {
    "addr:full":"534 Maple St Blytheville AR 72315",
    "addr:housenumber":"534",
    "addr:postcode":"72315",
    "addr:street":"Maple St",
    "iso:country":"US",
    "sg:address":"534 Maple St",
    "sg:city":"Blytheville",
    "sg:classifiers":[
        {
            "category":"Organizations",
            "subcategory":"Religious Organization",
            "type":"Services"
        }
    ],
    "sg:phone":"+1 870 762 2667",
    "sg:postcode":"72315",
    "sg:province":"AR",
    "sg:tags":[
        "church"
    ],
    "wof:name":"New Mt Olive Missionary Bptst",
    "wof:placetype":"venue"
},
  "geometry": {"coordinates":[-89.928916,35.922906],"type":"Point"}
}