{
  "type": "Feature",
  "properties": {
    "iso:country":"US",
    "sg:address":"1129 Burnt Bridge Rd",
    "sg:city":"Magnolia",
    "sg:classifiers":[
        {
            "category":"Personal",
            "subcategory":"Beauty Salon",
            "type":"Services"
        }
    ],
    "sg:phone":"+1 870 234 3385",
    "sg:postcode":"71753",
    "sg:province":"AR",
    "wof:name":"Christine's Beauty Shop",
    "wof:placetype":"venue"
},
  "geometry": {"coordinates":[-93.253238,33.258379],"type":"Point"}
}