{
  "type": "Feature",
  "properties": {
    "iso:country":"US",
    "sg:address":"312 Towncenter",
    "sg:city":"Bella Vista",
    "sg:classifiers":[
        {
            "category":"Manufacturing",
            "subcategory":"Printing",
            "type":"Manufacturing & Wholesale Goods"
        }
    ],
    "sg:phone":"+1 479 855 3724",
    "sg:postcode":"72714",
    "sg:province":"AR",
    "sg:tags":[
        "newspaper"
    ],
    "wof:name":"Weekly Vista",
    "wof:placetype":"venue"
},
  "geometry": {"coordinates":[-94.248841,36.47712],"type":"Point"}
}