{
  "type": "Feature",
  "properties": {
    "iso:country":"US",
    "sg:address":"12182 Peach Orchard Rd",
    "sg:city":"Bentonville",
    "sg:classifiers":[
        {
            "category":"Retail",
            "subcategory":"Repair Shop",
            "type":"Services"
        }
    ],
    "sg:phone":"+1 479 271 0032",
    "sg:postcode":"72712",
    "sg:province":"AR",
    "sg:tags":[
        "related"
    ],
    "sg:website":"www.atlaspri.com",
    "wof:name":"Precision Compacting Tech Inc",
    "wof:placetype":"venue"
},
  "geometry": {"coordinates":[-94.229529,36.409553],"type":"Point"}
}