{
  "type": "Feature",
  "properties": {
    "addr:full":"1003 Watson Pl Benton AR 72015",
    "addr:housenumber":"1003",
    "addr:postcode":"72015",
    "addr:street":"Watson Pl",
    "iso:country":"US",
    "sg:address":"1003 Watson Pl",
    "sg:city":"Benton",
    "sg:classifiers":[
        {
            "category":"Professional",
            "type":"Services"
        }
    ],
    "sg:phone":"+1 501 778 0917",
    "sg:postcode":"72015",
    "sg:province":"AR",
    "wof:name":"J Mar Service Co",
    "wof:placetype":"venue"
},
  "geometry": {"coordinates":[-92.56284100000001,34.572922],"type":"Point"}
}