{
  "type": "Feature",
  "properties": {
    "iso:country":"US",
    "sg:address":"16 Acklin Gap Rd",
    "sg:city":"Conway",
    "sg:classifiers":[
        {
            "category":"Professional",
            "subcategory":"Accounting & Tax Preparation",
            "type":"Services"
        }
    ],
    "sg:phone":"+1 501 327 7123",
    "sg:postcode":"72032",
    "sg:province":"AR",
    "sg:tags":[
        "bookkeeping",
        "return",
        "preparation-business"
    ],
    "wof:name":"Syble Williams",
    "wof:placetype":"venue"
},
  "geometry": {"coordinates":[-92.397302,35.13435],"type":"Point"}
}