{
  "type": "Feature",
  "properties": {
    "iso:country":"US",
    "sg:address":"900 W B St",
    "sg:city":"Russellville",
    "sg:classifiers":[
        {
            "category":"Shopping",
            "subcategory":"Jewelry",
            "type":"Retail Goods"
        }
    ],
    "sg:phone":"+1 479 968 3601",
    "sg:postcode":"72801",
    "sg:province":"AR",
    "sg:tags":[
        "jeweler"
    ],
    "wof:name":"Osbornes Downtown",
    "wof:placetype":"venue"
},
  "geometry": {"coordinates":[-93.141691,35.281333],"type":"Point"}
}