{
  "type": "Feature",
  "properties": {
    "iso:country":"US",
    "sg:address":"156 Pearcy Church Pl",
    "sg:city":"Pearcy",
    "sg:classifiers":[
        {
            "category":"Building & Trades",
            "subcategory":"Construction",
            "type":"Services"
        }
    ],
    "sg:phone":"+1 501 767 1748",
    "sg:postcode":"71964",
    "sg:province":"AR",
    "sg:tags":[
        "residential"
    ],
    "wof:name":"Gooden Construction",
    "wof:placetype":"venue"
},
  "geometry": {"coordinates":[-93.288151,34.427785],"type":"Point"}
}