{
  "type": "Feature",
  "properties": {
    "iso:country":"US",
    "sg:address":"44 Cove Dr",
    "sg:city":"N Little Rock",
    "sg:classifiers":[
        {
            "category":"Building & Trades",
            "subcategory":"Equipment Rental",
            "type":"Services"
        }
    ],
    "sg:phone":"+1 501 851 8074",
    "sg:postcode":"72113",
    "sg:province":"AR",
    "sg:tags":[
        "leasing"
    ],
    "wof:name":"Nova Capital Corp",
    "wof:placetype":"venue"
},
  "geometry": {"coordinates":[-92.416173,34.858879],"type":"Point"}
}