{
  "type": "Feature",
  "properties": {
    "iso:country":"US",
    "sg:address":"24 Ravenshoe Rd",
    "sg:city":"Rogers",
    "sg:classifiers":[
        {
            "category":"Education",
            "subcategory":"Special Training",
            "type":"Public Place"
        }
    ],
    "sg:phone":"+1 479 925 4499",
    "sg:postcode":"72756",
    "sg:province":"AR",
    "wof:name":"Sally Jo Zellmer",
    "wof:placetype":"venue"
},
  "geometry": {"coordinates":[-93.986836,36.335604],"type":"Point"}
}