{
  "type": "Feature",
  "properties": {
    "iso:country":"US",
    "sg:address":"54200 E Hwy 85A",
    "sg:city":"Afton",
    "sg:classifiers":[
        {
            "category":"Travel",
            "subcategory":"Hotels & Motels",
            "type":"Entertainment"
        }
    ],
    "sg:phone":"+1 918 257 5188",
    "sg:postcode":"74331",
    "sg:province":"OK",
    "sg:tags":[
        "resort"
    ],
    "wof:name":"Deer Run RV Park",
    "wof:placetype":"venue"
},
  "geometry": {"coordinates":[-94.89901,36.627994],"type":"Point"}
}