{
  "type": "Feature",
  "properties": {
    "addr:full":"4450 E McCain Blvd N Little Rock AR 72117",
    "addr:housenumber":"4450",
    "addr:postcode":"72117",
    "addr:street":"E Mccain Blvd N",
    "iso:country":"US",
    "sg:address":"4450 E McCain Blvd",
    "sg:city":"N Little Rock",
    "sg:classifiers":[
        {
            "category":"Banks & Credit Unions",
            "subcategory":"Bank",
            "type":"Services"
        }
    ],
    "sg:phone":"+1 501 945 4040",
    "sg:postcode":"72117",
    "sg:province":"AR",
    "sg:tags":[
        "state",
        "commercial"
    ],
    "wof:name":"First Arkansas Bank and Trust",
    "wof:placetype":"venue"
},
  "geometry": {"coordinates":[-92.217814,34.789174],"type":"Point"}
}