{
  "type": "Feature",
  "properties": {
    "iso:country":"US",
    "sg:address":"110 S Mustin Lake Rd",
    "sg:city":"Camden",
    "sg:classifiers":[
        {
            "category":"Professional",
            "type":"Services"
        }
    ],
    "sg:phone":"+1 870 574 0711",
    "sg:postcode":"71701",
    "sg:province":"AR",
    "wof:name":"Larry E Cave",
    "wof:placetype":"venue"
},
  "geometry": {"coordinates":[-92.747406,33.570035],"type":"Point"}
}