{
  "type": "Feature",
  "properties": {
    "iso:country":"US",
    "sg:address":"1600 Cantrell Rd",
    "sg:city":"Little Rock",
    "sg:classifiers":[
        {
            "category":"Restaurant",
            "type":"Food & Drink"
        }
    ],
    "sg:phone":"+1 501 376 5975",
    "sg:postcode":"72201",
    "sg:province":"AR",
    "sg:tags":[
        "eating"
    ],
    "wof:name":"Bistro 1600",
    "wof:placetype":"venue"
},
  "geometry": {"coordinates":[-92.290905,34.75391],"type":"Point"}
}