{
  "type": "Feature",
  "properties": {
    "iso:country":"US",
    "sg:address":"1015 N West Ave",
    "sg:city":"El Dorado",
    "sg:classifiers":[
        {
            "category":"Personal",
            "type":"Services"
        }
    ],
    "sg:phone":"+1 870 862 7044",
    "sg:postcode":"71730",
    "sg:province":"AR",
    "sg:tags":[
        "consultant",
        "wedding"
    ],
    "wof:name":"Forever Yours Bridal Cnsltnt",
    "wof:placetype":"venue"
},
  "geometry": {"coordinates":[-92.66545,33.221079],"type":"Point"}
}