{
  "type": "Feature",
  "properties": {
    "iso:country":"US",
    "sg:address":"202 W 3rd St",
    "sg:city":"Fordyce",
    "sg:classifiers":[
        {
            "category":"Government",
            "subcategory":"Office",
            "type":"Public Place"
        }
    ],
    "sg:phone":"+1 870 352 7983",
    "sg:postcode":"71742",
    "sg:province":"AR",
    "sg:tags":[
        "county",
        "taxation"
    ],
    "wof:name":"Dallas County Tax Assessor",
    "wof:placetype":"venue"
},
  "geometry": {"coordinates":[-92.413507,33.812402],"type":"Point"}
}