{
  "type": "Feature",
  "properties": {
    "addr:full":"195 Highland Dr Mountain View AR 72560",
    "addr:housenumber":"195",
    "addr:postcode":"72560",
    "addr:street":"Highland Dr",
    "iso:country":"US",
    "sg:address":"195 Highland Dr",
    "sg:city":"Mountain View",
    "sg:classifiers":[
        {
            "category":"Personal",
            "subcategory":"Beauty Salon",
            "type":"Services"
        }
    ],
    "sg:phone":"+1 870 269 8676",
    "sg:postcode":"72560",
    "sg:province":"AR",
    "sg:tags":[
        "shop"
    ],
    "wof:name":"Lucille's Beauty Shop",
    "wof:placetype":"venue"
},
  "geometry": {"coordinates":[-92.10421599999999,35.893201],"type":"Point"}
}