{
  "type": "Feature",
  "properties": {
    "addr:full":"20213 W Vanzant Rd Springdale AR 72764",
    "addr:housenumber":"20213",
    "addr:postcode":"72764",
    "addr:street":"W Vanzant Rd",
    "iso:country":"US",
    "sg:address":"20213 W Vanzant Rd",
    "sg:city":"Springdale",
    "sg:classifiers":[
        {
            "category":"Farming",
            "subcategory":"Farm & Veterinary Services",
            "type":"Manufacturing & Wholesale Goods"
        }
    ],
    "sg:phone":"+1 479 789 2919",
    "sg:postcode":"72764",
    "sg:province":"AR",
    "sg:tags":[
        "labor",
        "contractor"
    ],
    "wof:name":"Squires Spray Service",
    "wof:placetype":"venue"
},
  "geometry": {"coordinates":[-93.96930500000001,36.165121],"type":"Point"}
}