{
  "type": "Feature",
  "properties": {
    "iso:country":"US",
    "sg:address":"219 N 1st St",
    "sg:city":"Gurdon",
    "sg:classifiers":[
        {
            "category":"Education",
            "subcategory":"School",
            "type":"Public Place"
        }
    ],
    "sg:phone":"+1 870 353 4396",
    "sg:postcode":"71743",
    "sg:province":"AR",
    "wof:name":"Gurdon Alternative School",
    "wof:placetype":"venue"
},
  "geometry": {"coordinates":[-93.15139000000001,33.921311],"type":"Point"}
}