{
  "type": "Feature",
  "properties": {
    "addr:full":"273 Wilson St Greenland AR 72701",
    "addr:housenumber":"273",
    "addr:postcode":"72701",
    "addr:street":"Wilson St",
    "iso:country":"US",
    "sg:address":"273 Wilson St",
    "sg:city":"Greenland",
    "sg:classifiers":[
        {
            "category":"Organizations",
            "subcategory":"Religious Organization",
            "type":"Services"
        }
    ],
    "sg:phone":"+1 479 442 7464",
    "sg:postcode":"72701",
    "sg:province":"AR",
    "sg:tags":[
        "church"
    ],
    "wof:name":"First Baptist Church-Greenland",
    "wof:placetype":"venue"
},
  "geometry": {"coordinates":[-94.17738799999999,35.99451],"type":"Point"}
}