{
  "type": "Feature",
  "properties": {
    "iso:country":"US",
    "sg:address":"1016 S 8th St",
    "sg:city":"Rogers",
    "sg:classifiers":[
        {
            "category":"Manufacturing",
            "subcategory":"Signs",
            "type":"Manufacturing & Wholesale Goods"
        }
    ],
    "sg:phone":"+1 479 636 9439",
    "sg:postcode":"72756",
    "sg:province":"AR",
    "sg:tags":[
        "specialty",
        "mfg"
    ],
    "wof:name":"Sharp Signs",
    "wof:placetype":"venue"
},
  "geometry": {"coordinates":[-94.126024,36.324592],"type":"Point"}
}