{
  "type": "Feature",
  "properties": {
    "addr:full":"19327 James Neal Rd Harrisburg AR 72432",
    "addr:housenumber":"19327",
    "addr:postcode":"72432",
    "addr:street":"James Neal Rd",
    "iso:country":"US",
    "sg:address":"19327 James Neal Rd",
    "sg:city":"Harrisburg",
    "sg:classifiers":[
        {
            "category":"Food & Beverages",
            "subcategory":"Groceries & Convenience Stores",
            "type":"Retail Goods"
        }
    ],
    "sg:phone":"+1 870 578 9209",
    "sg:postcode":"72432",
    "sg:province":"AR",
    "wof:name":"James F White",
    "wof:placetype":"venue"
},
  "geometry": {"coordinates":[-90.69135900000001,35.538644],"type":"Point"}
}