{
  "type": "Feature",
  "properties": {
    "iso:country":"US",
    "sg:address":"221 Highway 463 N Ste B",
    "sg:city":"Trumann",
    "sg:classifiers":[
        {
            "category":"Health Services",
            "subcategory":"Dentist",
            "type":"Services"
        }
    ],
    "sg:phone":"+1 870 483 5011",
    "sg:postcode":"72472",
    "sg:province":"AR",
    "wof:name":"Keith M Mcclung Dds",
    "wof:placetype":"venue"
},
  "geometry": {"coordinates":[-90.520376,35.673436],"type":"Point"}
}