{
  "type": "Feature",
  "properties": {
    "iso:country":"US",
    "sg:address":"816 W Main St",
    "sg:city":"Jacksonville",
    "sg:classifiers":[
        {
            "category":"Fast Food",
            "type":"Food & Drink"
        },
        {
            "category":"Restaurant",
            "type":"Food & Drink"
        }
    ],
    "sg:phone":"+1 501 982 6656",
    "sg:postcode":"72076",
    "sg:province":"AR",
    "sg:tags":[
        "hamburger",
        "hot",
        "dog",
        "american",
        "take",
        "chicken"
    ],
    "sg:website":"http://www.mcdonalds.com",
    "wof:name":"McDonald's",
    "wof:placetype":"venue"
},
  "geometry": {"coordinates":[-92.117876,34.867191],"type":"Point"}
}