{
  "type": "Feature",
  "properties": {
    "iso:country":"US",
    "sg:address":"1304 E Oak St",
    "sg:city":"Conway",
    "sg:classifiers":[
        {
            "category":"Home & Garden",
            "subcategory":"Home Furnishings",
            "type":"Retail Goods"
        }
    ],
    "sg:phone":"+1 501 329 0701",
    "sg:postcode":"72032",
    "sg:province":"AR",
    "wof:name":"Rose Damask",
    "wof:placetype":"venue"
},
  "geometry": {"coordinates":[-92.410663,35.091355],"type":"Point"}
}