{
  "type": "Feature",
  "properties": {
    "iso:country":"US",
    "sg:address":"4043 Genoa Rd",
    "sg:city":"Texarkana",
    "sg:classifiers":[
        {
            "category":"Personal",
            "subcategory":"Beauty Salon",
            "type":"Services"
        }
    ],
    "sg:phone":"+1 870 774 4247",
    "sg:postcode":"71854",
    "sg:province":"AR",
    "wof:name":"Beauties & Beast Hair & Nail",
    "wof:placetype":"venue"
},
  "geometry": {"coordinates":[-93.98701,33.41034],"type":"Point"}
}