{
  "type": "Feature",
  "properties": {
    "iso:country":"US",
    "sg:address":"512 Laser St",
    "sg:city":"Hot Springs National",
    "sg:classifiers":[
        {
            "category":"Real Estate",
            "subcategory":"Developer",
            "type":"Services"
        }
    ],
    "sg:phone":"+1 501 623 3035",
    "sg:postcode":"71901",
    "sg:province":"AR",
    "sg:tags":[
        "cemetery"
    ],
    "wof:name":"Oak Hill Cemetary Assoc I",
    "wof:placetype":"venue"
},
  "geometry": {"coordinates":[-93.053381,34.490932],"type":"Point"}
}