{
  "type": "Feature",
  "properties": {
    "addr:full":"2207 Highway 67 S Pocahontas AR 72455",
    "addr:housenumber":"2207",
    "addr:postcode":"72455",
    "addr:street":"Highway 67 S",
    "iso:country":"US",
    "sg:address":"2207 Highway 67 S",
    "sg:city":"Pocahontas",
    "sg:classifiers":[
        {
            "category":"Restaurant",
            "type":"Food & Drink"
        }
    ],
    "sg:menulink":"http://www.allmenus.com/ar/demun/173993-wendys/menu/",
    "sg:phone":"+1 870 892 4998",
    "sg:postcode":"72455",
    "sg:province":"AR",
    "sg:tags":[
        "burger",
        "american",
        "soup"
    ],
    "wof:name":"Wendy's",
    "wof:placetype":"venue"
},
  "geometry": {"coordinates":[-90.958178,36.243464],"type":"Point"}
}