{
  "type": "Feature",
  "properties": {
    "iso:country":"US",
    "sg:address":"2817 Yuma St",
    "sg:city":"Fort Smith",
    "sg:classifiers":[
        {
            "category":"Building & Trades",
            "subcategory":"Construction",
            "type":"Services"
        }
    ],
    "sg:phone":"+1 479 649 5852",
    "sg:postcode":"72901",
    "sg:province":"AR",
    "sg:tags":[
        "general",
        "contractor"
    ],
    "wof:name":"SSI Customer Care Ctr",
    "wof:placetype":"venue"
},
  "geometry": {"coordinates":[-94.40333800000001,35.32897],"type":"Point"}
}