{
  "type": "Feature",
  "properties": {
    "iso:country":"US",
    "sg:address":"1009 W Scott St",
    "sg:city":"Heber Springs",
    "sg:classifiers":[
        {
            "category":"Organizations",
            "subcategory":"Religious Organization",
            "type":"Services"
        }
    ],
    "sg:phone":"+1 501 362 3000",
    "sg:postcode":"72543",
    "sg:province":"AR",
    "sg:tags":[
        "church"
    ],
    "wof:name":"Vineyard Christian Fellowship",
    "wof:placetype":"venue"
},
  "geometry": {"coordinates":[-92.04118,35.486054],"type":"Point"}
}