{
  "type": "Feature",
  "properties": {
    "iso:country":"US",
    "sg:address":"1403 S Izard St",
    "sg:city":"Little Rock",
    "sg:classifiers":[
        {
            "category":"Organizations",
            "subcategory":"Community Association",
            "type":"Services"
        }
    ],
    "sg:phone":"+1 501 375 7762",
    "sg:postcode":"72202",
    "sg:province":"AR",
    "sg:tags":[
        "fraternal"
    ],
    "wof:name":"Grand Chapter OESPHA",
    "wof:placetype":"venue"
},
  "geometry": {"coordinates":[-92.28250800000001,34.735672],"type":"Point"}
}