{
  "type": "Feature",
  "properties": {
    "iso:country":"US",
    "sg:address":"619 N 18th St",
    "sg:city":"Fort Smith",
    "sg:classifiers":[
        {
            "category":"Building & Trades",
            "subcategory":"Construction",
            "type":"Services"
        }
    ],
    "sg:phone":"+1 479 494 1880",
    "sg:postcode":"72901",
    "sg:province":"AR",
    "sg:tags":[
        "hanging",
        "industrial",
        "contractor"
    ],
    "wof:name":"Ricks Painting",
    "wof:placetype":"venue"
},
  "geometry": {"coordinates":[-94.40924,35.385171],"type":"Point"}
}