{
  "type": "Feature",
  "properties": {
    "addr:full":"501 Commerce Dr Maumelle AR 72113",
    "addr:housenumber":"501",
    "addr:postcode":"72113",
    "addr:street":"Commerce Dr Maumelle",
    "iso:country":"US",
    "sg:address":"501 Commerce Dr",
    "sg:city":"Maumelle",
    "sg:classifiers":[
        {
            "category":"Government",
            "subcategory":"Post Office",
            "type":"Public Place"
        }
    ],
    "sg:phone":"+1 501 000 1111",
    "sg:postcode":"72113",
    "sg:province":"AR",
    "wof:name":"US Post Office",
    "wof:placetype":"venue"
},
  "geometry": {"coordinates":[-92.398405,34.857424],"type":"Point"}
}