{
  "type": "Feature",
  "properties": {
    "addr:full":"501 W Trimble Ave Berryville AR 72616",
    "addr:housenumber":"501",
    "addr:postcode":"72616",
    "addr:street":"W Trimble Ave",
    "iso:country":"US",
    "sg:address":"501 W Trimble Ave",
    "sg:city":"Berryville",
    "sg:classifiers":[
        {
            "category":"Autos & Motor Vehicles",
            "subcategory":"Auto Supplies",
            "type":"Retail Goods"
        },
        {
            "category":"Wholesale",
            "subcategory":"Electrical",
            "type":"Manufacturing & Wholesale Goods"
        }
    ],
    "sg:phone":"+1 870 423 7355",
    "sg:postcode":"72616",
    "sg:province":"AR",
    "sg:tags":[
        "battery",
        "automobile",
        "part",
        "batteries-storage",
        "accessory"
    ],
    "sg:website":"http://www.autozone.com",
    "wof:name":"AutoZone",
    "wof:placetype":"venue"
},
  "geometry": {"coordinates":[-93.57942799999999,36.369881],"type":"Point"}
}