{
  "type": "Feature",
  "properties": {
    "addr:full":"116 S Monroe Ave Plainview AR 72857",
    "addr:housenumber":"116",
    "addr:postcode":"72857",
    "addr:street":"S Monroe Ave",
    "iso:country":"US",
    "sg:address":"116 S Monroe Ave",
    "sg:city":"Plainview",
    "sg:classifiers":[
        {
            "category":"Personal",
            "subcategory":"Beauty Salon",
            "type":"Services"
        }
    ],
    "sg:phone":"+1 479 272 2370",
    "sg:postcode":"72857",
    "sg:province":"AR",
    "sg:tags":[
        "shop"
    ],
    "wof:name":"Sophisticuts",
    "wof:placetype":"venue"
},
  "geometry": {"coordinates":[-93.30056999999999,34.988125],"type":"Point"}
}