{
  "type": "Feature",
  "properties": {
    "iso:country":"US",
    "sg:address":"16662 Bethlehem Rd",
    "sg:city":"Winslow",
    "sg:classifiers":[
        {
            "category":"Health Services",
            "subcategory":"Medical Lab",
            "type":"Services"
        }
    ],
    "sg:phone":"+1 479 839 3812",
    "sg:postcode":"72959",
    "sg:province":"AR",
    "sg:tags":[
        "laboratory",
        "dental"
    ],
    "wof:name":"Halley Dental Lab",
    "wof:placetype":"venue"
},
  "geometry": {"coordinates":[-94.186653,35.863991],"type":"Point"}
}