{
  "type": "Feature",
  "properties": {
    "addr:full":"375 Phillips Road 273 Lexa AR 72355",
    "addr:housenumber":"375",
    "addr:postcode":"72355",
    "addr:street":"Phillips Road 273",
    "iso:country":"US",
    "sg:address":"375 Phillips Road 273",
    "sg:city":"Lexa",
    "sg:classifiers":[
        {
            "category":"Building & Trades",
            "subcategory":"Construction",
            "type":"Services"
        }
    ],
    "sg:phone":"+1 870 572 3933",
    "sg:postcode":"72355",
    "sg:province":"AR",
    "sg:tags":[
        "contractor",
        "grading"
    ],
    "wof:name":"Jwn Construction Inc",
    "wof:placetype":"venue"
},
  "geometry": {"coordinates":[-90.699127,34.55555],"type":"Point"}
}