{
  "type": "Feature",
  "properties": {
    "addr:full":"201 Industrial St Marked Tree AR 72365",
    "addr:housenumber":"201",
    "addr:postcode":"72365",
    "addr:street":"Industrial St",
    "iso:country":"US",
    "sg:address":"201 Industrial St",
    "sg:city":"Marked Tree",
    "sg:classifiers":[
        {
            "category":"Manufacturing",
            "subcategory":"Furniture",
            "type":"Manufacturing & Wholesale Goods"
        }
    ],
    "sg:phone":"+1 870 358 2500",
    "sg:postcode":"72365",
    "sg:province":"AR",
    "wof:name":"Dispatch Furniture",
    "wof:placetype":"venue"
},
  "geometry": {"coordinates":[-90.412542,35.530823],"type":"Point"}
}