{
  "type": "Feature",
  "properties": {
    "iso:country":"US",
    "sg:address":"310 N Pine St",
    "sg:city":"Marvell",
    "sg:classifiers":[
        {
            "category":"Manufacturing",
            "subcategory":"Textiles",
            "type":"Manufacturing & Wholesale Goods"
        }
    ],
    "sg:phone":"+1 870 829 3683",
    "sg:postcode":"72366",
    "sg:province":"AR",
    "sg:tags":[
        "broker",
        "cotton"
    ],
    "wof:name":"The Duffel Company",
    "wof:placetype":"venue"
},
  "geometry": {"coordinates":[-90.911868,34.562039],"type":"Point"}
}