{
  "type": "Feature",
  "properties": {
    "iso:country":"US",
    "sg:address":"111 N Plum St",
    "sg:city":"Bearden",
    "sg:classifiers":[
        {
            "category":"Manufacturing",
            "subcategory":"Lumber",
            "type":"Manufacturing & Wholesale Goods"
        }
    ],
    "sg:phone":"+1 870 687 3611",
    "sg:postcode":"71720",
    "sg:province":"AR",
    "wof:name":"Anthony Timberlands Inc",
    "wof:placetype":"venue"
},
  "geometry": {"coordinates":[-92.617268,33.724885],"type":"Point"}
}