{
  "type": "Feature",
  "properties": {
    "iso:country":"US",
    "sg:address":"1320 Stone St",
    "sg:city":"Jonesboro",
    "sg:classifiers":[
        {
            "category":"Real Estate",
            "subcategory":"Developer",
            "type":"Services"
        }
    ],
    "sg:phone":"+1 870 932 1234",
    "sg:postcode":"72401",
    "sg:province":"AR",
    "sg:tags":[
        "contractor"
    ],
    "wof:name":"Best Roofing Corp",
    "wof:placetype":"venue"
},
  "geometry": {"coordinates":[-90.675661,35.829938],"type":"Point"}
}