{
  "type": "Feature",
  "properties": {
    "iso:country":"US",
    "sg:address":"5270 Sandtown Rd",
    "sg:city":"Batesville",
    "sg:classifiers":[
        {
            "category":"Farming",
            "subcategory":"Livestock Farm",
            "type":"Manufacturing & Wholesale Goods"
        }
    ],
    "sg:phone":"+1 870 283 6847",
    "sg:postcode":"72501",
    "sg:province":"AR",
    "sg:tags":[
        "beef",
        "feedlot",
        "cattle"
    ],
    "wof:name":"Glenn N Smith",
    "wof:placetype":"venue"
},
  "geometry": {"coordinates":[-91.597846,35.896952],"type":"Point"}
}