{
  "type": "Feature",
  "properties": {
    "iso:country":"US",
    "sg:address":"2367 Greene Road 433",
    "sg:city":"Marmaduke",
    "sg:classifiers":[
        {
            "category":"Manufacturing",
            "subcategory":"Glass & Minerals",
            "type":"Manufacturing & Wholesale Goods"
        }
    ],
    "sg:phone":"+1 870 565 5430",
    "sg:postcode":"72443",
    "sg:province":"AR",
    "sg:tags":[
        "cast",
        "stone"
    ],
    "wof:name":"Petracraft Stone",
    "wof:placetype":"venue"
},
  "geometry": {"coordinates":[-90.357513,36.215328],"type":"Point"}
}