{
  "type": "Feature",
  "properties": {
    "iso:country":"US",
    "sg:address":"807 Mine St",
    "sg:city":"Nashville",
    "sg:classifiers":[
        {
            "category":"Home & Garden",
            "subcategory":"Carpets & Floor Coverings",
            "type":"Retail Goods"
        }
    ],
    "sg:phone":"+1 870 845 5641",
    "sg:postcode":"71852",
    "sg:province":"AR",
    "sg:tags":[
        "dealer",
        "rug"
    ],
    "wof:name":"Gary's Carpets",
    "wof:placetype":"venue"
},
  "geometry": {"coordinates":[-93.839339,33.955025],"type":"Point"}
}