{
  "type": "Feature",
  "properties": {
    "iso:country":"US",
    "sg:address":"2500 E Walnut St",
    "sg:city":"Paris",
    "sg:classifiers":[
        {
            "category":"Retail",
            "subcategory":"Auto Repair",
            "type":"Services"
        }
    ],
    "sg:phone":"+1 479 963 8900",
    "sg:postcode":"72855",
    "sg:province":"AR",
    "sg:tags":[
        "body",
        "automobile",
        "painting"
    ],
    "wof:name":"Paris Body Shop",
    "wof:placetype":"venue"
},
  "geometry": {"coordinates":[-93.69918699999999,35.293277],"type":"Point"}
}