{
  "type": "Feature",
  "properties": {
    "iso:country":"US",
    "sg:address":"5106 Wheeler Ave",
    "sg:city":"Fort Smith",
    "sg:classifiers":[
        {
            "category":"Manufacturing",
            "subcategory":"Chemicals & Compounds",
            "type":"Manufacturing & Wholesale Goods"
        }
    ],
    "sg:phone":"+1 479 646 7865",
    "sg:postcode":"72901",
    "sg:province":"AR",
    "sg:tags":[
        "paint",
        "varnish",
        "allied",
        "product"
    ],
    "wof:name":"Ashland Specialty Chemical",
    "wof:placetype":"venue"
},
  "geometry": {"coordinates":[-94.42737200000001,35.334712],"type":"Point"}
}