{
  "type": "Feature",
  "properties": {
    "addr:full":"623 Sherwood Ave Mena AR 71953",
    "addr:housenumber":"623",
    "addr:postcode":"71953",
    "addr:street":"Sherwood Ave",
    "iso:country":"US",
    "sg:address":"623 Sherwood Ave",
    "sg:city":"Mena",
    "sg:classifiers":[
        {
            "category":"Social Services",
            "type":"Services"
        }
    ],
    "sg:phone":"+1 479 394 6017",
    "sg:postcode":"71953",
    "sg:province":"AR",
    "wof:name":"Sun Light Center Inc",
    "wof:placetype":"venue"
},
  "geometry": {"coordinates":[-94.236907,34.582824],"type":"Point"}
}