{
  "type": "Feature",
  "properties": {
    "addr:full":"8808 Pea Ridge Cir Mabelvale AR 72103",
    "addr:housenumber":"8808",
    "addr:postcode":"72103",
    "addr:street":"Pea;Cir",
    "iso:country":"US",
    "sg:address":"8808 Pea Ridge Cir",
    "sg:city":"Mabelvale",
    "sg:classifiers":[
        {
            "category":"Autos & Motor Vehicles",
            "subcategory":"Auto Supplies",
            "type":"Retail Goods"
        }
    ],
    "sg:phone":"+1 501 804 5370",
    "sg:postcode":"72103",
    "sg:province":"AR",
    "sg:tags":[
        "wheel"
    ],
    "wof:name":"2wheel Cruisers Of Little Rock",
    "wof:placetype":"venue"
},
  "geometry": {"coordinates":[-92.376661,34.649635],"type":"Point"}
}