{
  "type": "Feature",
  "properties": {
    "iso:country":"US",
    "sg:address":"4504 E Nettleton Ave",
    "sg:city":"Jonesboro",
    "sg:classifiers":[
        {
            "category":"Real Estate",
            "subcategory":"Real Estate Agent",
            "type":"Services"
        }
    ],
    "sg:phone":"+1 870 336 7653",
    "sg:postcode":"72401",
    "sg:province":"AR",
    "wof:name":"Realty Corp",
    "wof:placetype":"venue"
},
  "geometry": {"coordinates":[-90.652162,35.820672],"type":"Point"}
}