{
  "type": "Feature",
  "properties": {
    "addr:full":"10200 Dollarway Rd White Hall AR 71602",
    "addr:housenumber":"10200",
    "addr:postcode":"71602",
    "addr:street":"Dollarway Rd",
    "iso:country":"US",
    "sg:address":"10200 Dollarway Rd",
    "sg:city":"White Hall",
    "sg:classifiers":[
        {
            "category":"Building & Trades",
            "subcategory":"Landscaping Services",
            "type":"Services"
        }
    ],
    "sg:phone":"+1 870 489 0451",
    "sg:postcode":"71602",
    "sg:province":"AR",
    "sg:tags":[
        "tree"
    ],
    "wof:name":"Mike's Handyman Svc",
    "wof:placetype":"venue"
},
  "geometry": {"coordinates":[-92.10201600000001,34.295683],"type":"Point"}
}