{
  "type": "Feature",
  "properties": {
    "iso:country":"US",
    "sg:address":"601 Linda St",
    "sg:city":"Springdale",
    "sg:classifiers":[
        {
            "category":"Personal",
            "subcategory":"Beauty Salon",
            "type":"Services"
        }
    ],
    "sg:phone":"+1 479 751 8785",
    "sg:postcode":"72764",
    "sg:province":"AR",
    "wof:name":"Cutters Corner",
    "wof:placetype":"venue"
},
  "geometry": {"coordinates":[-94.122643,36.177824],"type":"Point"}
}