{
  "type": "Feature",
  "properties": {
    "iso:country":"US",
    "sg:address":"524 E Court St",
    "sg:city":"Paragould",
    "sg:classifiers":[
        {
            "category":"Organizations",
            "subcategory":"Religious Organization",
            "type":"Services"
        }
    ],
    "sg:phone":"+1 870 236 2060",
    "sg:postcode":"72450",
    "sg:province":"AR",
    "sg:tags":[
        "church"
    ],
    "wof:name":"Griffin Memorial United Meth",
    "wof:placetype":"venue"
},
  "geometry": {"coordinates":[-90.47994,36.056202],"type":"Point"}
}