{
  "type": "Feature",
  "properties": {
    "addr:full":"38 Ridgecrest Dr Cabot AR 72023",
    "addr:housenumber":"38",
    "addr:postcode":"72023",
    "addr:street":"Ridgecrest Dr",
    "iso:country":"US",
    "sg:address":"38 Ridgecrest Dr",
    "sg:city":"Cabot",
    "sg:classifiers":[
        {
            "category":"Wholesale",
            "subcategory":"Home Furnishings",
            "type":"Manufacturing & Wholesale Goods"
        }
    ],
    "sg:phone":"+1 501 843 7909",
    "sg:postcode":"72023",
    "sg:province":"AR",
    "wof:name":"Collage Inc",
    "wof:placetype":"venue"
},
  "geometry": {"coordinates":[-92.060309,35.023006],"type":"Point"}
}