{
  "type": "Feature",
  "properties": {
    "addr:full":"2749 Co Rd 762 Jonesboro AR 72401",
    "addr:housenumber":"2749;762",
    "addr:postcode":"72401",
    "addr:street":"Co Rd",
    "iso:country":"US",
    "sg:address":"2749 Co Rd 762",
    "sg:city":"Jonesboro",
    "sg:classifiers":[
        {
            "category":"Autos & Motor Vehicles",
            "subcategory":"Automobile Sales",
            "type":"Retail Goods"
        }
    ],
    "sg:phone":"+1 870 910 5799",
    "sg:postcode":"72401",
    "sg:province":"AR",
    "sg:tags":[
        "car",
        "dealer"
    ],
    "wof:name":"Pine Log Auto Sales",
    "wof:placetype":"venue"
},
  "geometry": {"coordinates":[-90.622885,35.929348],"type":"Point"}
}