{
  "type": "Feature",
  "properties": {
    "iso:country":"US",
    "sg:address":"4000 Pike Ave",
    "sg:city":"North Little Rock",
    "sg:classifiers":[
        {
            "category":"Manufacturing",
            "subcategory":"Toys & Sporting Goods",
            "type":"Manufacturing & Wholesale Goods"
        }
    ],
    "sg:phone":"+1 501 758 4930",
    "sg:postcode":"72118",
    "sg:province":"AR",
    "sg:tags":[
        "mfg",
        "wood",
        "furniture"
    ],
    "wof:name":"Skatepaigecom",
    "wof:placetype":"venue"
},
  "geometry": {"coordinates":[-92.277843,34.79225],"type":"Point"}
}