{
  "type": "Feature",
  "properties": {
    "addr:full":"14415 Highway 5 Cabot AR 72023",
    "addr:housenumber":"14415",
    "addr:postcode":"72023",
    "addr:street":"Highway 5",
    "iso:country":"US",
    "sg:address":"14415 Highway 5",
    "sg:city":"Cabot",
    "sg:classifiers":[
        {
            "category":"Retail",
            "subcategory":"Storage",
            "type":"Services"
        }
    ],
    "sg:phone":"+1 501 983 9709",
    "sg:postcode":"72023",
    "sg:province":"AR",
    "sg:tags":[
        "self"
    ],
    "wof:name":"Greystone Mini Storage",
    "wof:placetype":"venue"
},
  "geometry": {"coordinates":[-92.07107000000001,34.997736],"type":"Point"}
}