{
  "type": "Feature",
  "properties": {
    "iso:country":"US",
    "sg:address":"14415 Highway 5",
    "sg:city":"Cabot",
    "sg:classifiers":[
        {
            "category":"Retail",
            "subcategory":"Storage",
            "type":"Services"
        }
    ],
    "sg:phone":"+1 501 983 9709",
    "sg:postcode":"72023",
    "sg:province":"AR",
    "sg:tags":[
        "self"
    ],
    "wof:name":"Greystone Mini Storage",
    "wof:placetype":"venue"
},
  "geometry": {"coordinates":[-92.07107,34.997736],"type":"Point"}
}