{
  "type": "Feature",
  "properties": {
    "iso:country":"US",
    "sg:address":"3400 Chapel Heights Dr",
    "sg:city":"Pine Bluff",
    "sg:classifiers":[
        {
            "category":"Education",
            "subcategory":"School",
            "type":"Public Place"
        }
    ],
    "sg:phone":"+1 870 879 0311",
    "sg:postcode":"71603",
    "sg:province":"AR",
    "sg:tags":[
        "academic",
        "special"
    ],
    "wof:name":"Jenkins Secondary School",
    "wof:placetype":"venue"
},
  "geometry": {"coordinates":[-92.073283,34.19491],"type":"Point"}
}