{
  "type": "Feature",
  "properties": {
    "iso:country":"US",
    "sg:address":"2803 SW 14th St",
    "sg:city":"Bentonville",
    "sg:classifiers":[
        {
            "category":"Organizations",
            "subcategory":"Religious Organization",
            "type":"Services"
        }
    ],
    "sg:phone":"+1 479 273 3891",
    "sg:postcode":"72712",
    "sg:province":"AR",
    "wof:name":"God's Lighthouse Church",
    "wof:placetype":"venue"
},
  "geometry": {"coordinates":[-94.243799,36.35762],"type":"Point"}
}