{
  "type": "Feature",
  "properties": {
    "addr:full":"18305 Raines Rd Little Rock AR 72210",
    "addr:housenumber":"18305",
    "addr:postcode":"72210",
    "addr:street":"Raines Rd",
    "iso:country":"US",
    "sg:address":"18305 Raines Rd",
    "sg:city":"Little Rock",
    "sg:classifiers":[
        {
            "category":"Building & Trades",
            "subcategory":"Electrical",
            "type":"Services"
        }
    ],
    "sg:phone":"+1 501 455 1535",
    "sg:postcode":"72210",
    "sg:province":"AR",
    "sg:tags":[
        "electrical",
        "contractor"
    ],
    "wof:name":"ABC Electric Inc",
    "wof:placetype":"venue"
},
  "geometry": {"coordinates":[-92.47422299999999,34.687445],"type":"Point"}
}