{
  "type": "Feature",
  "properties": {
    "iso:country":"US",
    "sg:address":"287 W County Line Rd",
    "sg:city":"Springdale",
    "sg:classifiers":[
        {
            "category":"Wholesale",
            "subcategory":"Construction Materials",
            "type":"Manufacturing & Wholesale Goods"
        },
        {
            "category":"Manufacturing",
            "subcategory":"Building Materials",
            "type":"Manufacturing & Wholesale Goods"
        }
    ],
    "sg:phone":"+1 479 756 3779",
    "sg:postcode":"72764",
    "sg:province":"AR",
    "sg:tags":[
        "repair",
        "product",
        "mfg",
        "member",
        "concrete",
        "s",
        "structural"
    ],
    "wof:name":"Architctural Precast Formworks",
    "wof:placetype":"venue"
},
  "geometry": {"coordinates":[-94.13015,36.210314],"type":"Point"}
}