{
  "type": "Feature",
  "properties": {
    "iso:country":"US",
    "sg:address":"7200 Croxton Rd",
    "sg:city":"Benton",
    "sg:classifiers":[
        {
            "category":"Communications",
            "subcategory":"Film & Video Production",
            "type":"Services"
        }
    ],
    "sg:phone":"+1 501 778 3455",
    "sg:postcode":"72015",
    "sg:province":"AR",
    "sg:tags":[
        "motion"
    ],
    "wof:name":"AGF Productions Inc",
    "wof:placetype":"venue"
},
  "geometry": {"coordinates":[-92.524024,34.486331],"type":"Point"}
}