{
  "type": "Feature",
  "properties": {
    "iso:country":"US",
    "sg:address":"48 Glenn Ln",
    "sg:city":"Greenbrier",
    "sg:classifiers":[
        {
            "category":"Place Of Worship",
            "subcategory":"Church",
            "type":"Public Place"
        },
        {
            "category":"Place Of Worship",
            "type":"Public Place"
        }
    ],
    "sg:phone":"+1 501 679 8950",
    "sg:postcode":"72058",
    "sg:province":"AR",
    "sg:tags":[
        "churches-baptist-general",
        "churches-baptist"
    ],
    "wof:name":"Crosspoint Baptist Church",
    "wof:placetype":"venue"
},
  "geometry": {"coordinates":[-92.380755,35.223407],"type":"Point"}
}