{
  "type": "Feature",
  "properties": {
    "addr:full":"4051 E Kiehl Ave N Little Rock AR 72120",
    "addr:housenumber":"4051",
    "addr:postcode":"72120",
    "addr:street":"E Kiehl Ave N",
    "iso:country":"US",
    "sg:address":"4051 E Kiehl Ave",
    "sg:city":"N Little Rock",
    "sg:classifiers":[
        {
            "category":"Cinema",
            "subcategory":"Movie Rental",
            "type":"Entertainment"
        }
    ],
    "sg:phone":"+1 501 835 6185",
    "sg:postcode":"72120",
    "sg:province":"AR",
    "sg:tags":[
        "leasing",
        "video",
        "disc",
        "tape"
    ],
    "sg:website":"www.moviegallery.com",
    "wof:name":"Movie Gallery",
    "wof:placetype":"venue"
},
  "geometry": {"coordinates":[-92.19077299999999,34.832188],"type":"Point"}
}