{
  "type": "Feature",
  "properties": {
    "iso:country":"US",
    "sg:address":"670 Hwy 71 S",
    "sg:city":"Ashdown",
    "sg:classifiers":[
        {
            "category":"Freight",
            "type":"Transportation"
        }
    ],
    "sg:phone":"+1 870 898 9888",
    "sg:postcode":"71822",
    "sg:province":"AR",
    "sg:tags":[
        "dry",
        "bulk",
        "trucking"
    ],
    "wof:name":"Schwerman Trucking Co",
    "wof:placetype":"venue"
},
  "geometry": {"coordinates":[-94.084172,33.626033],"type":"Point"}
}