{
  "type": "Feature",
  "properties": {
    "iso:country":"US",
    "sg:address":"1130 E Millsap Rd",
    "sg:city":"Fayetteville",
    "sg:classifiers":[
        {
            "category":"Social Services",
            "type":"Services"
        },
        {
            "category":"Personal",
            "type":"Services"
        },
        {
            "category":"Social Services",
            "subcategory":"Child Care",
            "type":"Services"
        }
    ],
    "sg:phone":"+1 479 422 2280",
    "sg:postcode":"72703",
    "sg:province":"AR",
    "sg:tags":[
        "adolescent",
        "family",
        "guidance",
        "worker",
        "counselors-licensed",
        "adoption",
        "individual",
        "marriage",
        "professional",
        "counseling",
        "counselor"
    ],
    "sg:website":"http://www.balanceroad.com",
    "wof:name":"Balance Road Center For Counseling & Social Work",
    "wof:placetype":"venue"
},
  "geometry": {"coordinates":[-94.142846,36.11477],"type":"Point"}
}