{
  "type": "Feature",
  "properties": {
    "iso:country":"US",
    "sg:address":"17 Ozark Dr",
    "sg:city":"Maumelle",
    "sg:classifiers":[
        {
            "category":"Health Services",
            "subcategory":"Health Practitioner",
            "type":"Services"
        }
    ],
    "sg:phone":"+1 501 803 3700",
    "sg:postcode":"72113",
    "sg:province":"AR",
    "wof:name":"Parker Page",
    "wof:placetype":"venue"
},
  "geometry": {"coordinates":[-92.418453,34.856649],"type":"Point"}
}