{
  "type": "Feature",
  "properties": {
    "iso:country":"US",
    "sg:address":"10 Green Oaks Pl",
    "sg:city":"Texarkana",
    "sg:classifiers":[
        {
            "category":"Professional",
            "subcategory":"Business Services",
            "type":"Services"
        }
    ],
    "sg:phone":"+1 870 774 8133",
    "sg:postcode":"71854",
    "sg:province":"AR",
    "sg:tags":[
        "leather"
    ],
    "wof:name":"R & E Leather Sales",
    "wof:placetype":"venue"
},
  "geometry": {"coordinates":[-94.02672099999999,33.442291],"type":"Point"}
}