{
  "type": "Feature",
  "properties": {
    "addr:full":"221 S Main St Pine Bluff AR 71601",
    "addr:housenumber":"221",
    "addr:postcode":"71601",
    "addr:street":"S Main St",
    "iso:country":"US",
    "sg:address":"221 S Main St",
    "sg:city":"Pine Bluff",
    "sg:classifiers":[
        {
            "category":"Professional",
            "type":"Services"
        }
    ],
    "sg:phone":"+1 870 536 1001",
    "sg:postcode":"71601",
    "sg:province":"AR",
    "wof:name":"Westcoast Scooter",
    "wof:placetype":"venue"
},
  "geometry": {"coordinates":[-92.00332899999999,34.227447],"type":"Point"}
}