{
  "type": "Feature",
  "properties": {
    "iso:country":"US",
    "sg:address":"479 Co Rd 209",
    "sg:city":"Eureka Springs",
    "sg:classifiers":[
        {
            "category":"Communications",
            "subcategory":"Film & Video Production",
            "type":"Services"
        }
    ],
    "sg:phone":"+1 479 253 2713",
    "sg:postcode":"72632",
    "sg:province":"AR",
    "sg:tags":[
        "taping"
    ],
    "wof:name":"Eureka Wedding Videos",
    "wof:placetype":"venue"
},
  "geometry": {"coordinates":[-93.683205,36.402604],"type":"Point"}
}