{
  "type": "Feature",
  "properties": {
    "iso:country":"US",
    "sg:address":"161 Polk St N",
    "sg:city":"Mena",
    "sg:classifiers":[
        {
            "category":"Manufacturing",
            "subcategory":"Wood Products",
            "type":"Manufacturing & Wholesale Goods"
        }
    ],
    "sg:phone":"+1 479 437 3207",
    "sg:postcode":"71953",
    "sg:province":"OK",
    "sg:tags":[
        "mfg"
    ],
    "wof:name":"D J Woodcraft LLC",
    "wof:placetype":"venue"
},
  "geometry": {"coordinates":[-94.25129,34.589357],"type":"Point"}
}