{
  "type": "Feature",
  "properties": {
    "iso:country":"US",
    "sg:address":"201 Hwy 412 W",
    "sg:city":"Siloam Springs",
    "sg:classifiers":[
        {
            "category":"Food & Beverages",
            "subcategory":"Groceries & Convenience Stores",
            "type":"Retail Goods"
        }
    ],
    "sg:phone":"+1 479 524 4117",
    "sg:postcode":"72761",
    "sg:province":"OK",
    "sg:tags":[
        "grocer"
    ],
    "wof:name":"IGA Super-Ctr",
    "wof:placetype":"venue"
},
  "geometry": {"coordinates":[-94.54500899999999,36.1732],"type":"Point"}
}