{
  "type": "Feature",
  "properties": {
    "iso:country":"US",
    "sg:address":"717 Zero St",
    "sg:city":"Fort Smith",
    "sg:classifiers":[
        {
            "category":"Building & Trades",
            "subcategory":"Plumbing",
            "type":"Services"
        }
    ],
    "sg:phone":"+1 479 452 3386",
    "sg:postcode":"72901",
    "sg:province":"AR",
    "sg:tags":[
        "heating",
        "contractor"
    ],
    "wof:name":"Fort Smith Heating & AC CO",
    "wof:placetype":"venue"
},
  "geometry": {"coordinates":[-94.428183,35.328383],"type":"Point"}
}