{
  "type": "Feature",
  "properties": {
    "iso:country":"US",
    "sg:address":"1271 Thunder Mountain Rd",
    "sg:city":"Caddo Gap",
    "sg:classifiers":[
        {
            "category":"Personal",
            "type":"Services"
        }
    ],
    "sg:phone":"+1 870 356 5007",
    "sg:postcode":"71935",
    "sg:province":"AR",
    "sg:tags":[
        "therapist",
        "massage"
    ],
    "wof:name":"Care'n Comfort",
    "wof:placetype":"venue"
},
  "geometry": {"coordinates":[-93.584222,34.352332],"type":"Point"}
}