{
  "type": "Feature",
  "properties": {
    "iso:country":"US",
    "sg:address":"199 Harbor Oaks Ln",
    "sg:city":"Mount Ida",
    "sg:classifiers":[
        {
            "category":"Travel",
            "subcategory":"Campground",
            "type":"Entertainment"
        }
    ],
    "sg:phone":"+1 870 867 4451",
    "sg:postcode":"71957",
    "sg:province":"AR",
    "sg:tags":[
        "trailer"
    ],
    "wof:name":"Harbor Oaks Inc",
    "wof:placetype":"venue"
},
  "geometry": {"coordinates":[-93.447063,34.550778],"type":"Point"}
}