{
  "type": "Feature",
  "properties": {
    "iso:country":"US",
    "sg:address":"6117 W 65th St",
    "sg:city":"Little Rock",
    "sg:classifiers":[
        {
            "category":"Freight",
            "type":"Transportation"
        }
    ],
    "sg:phone":"+1 501 565 3194",
    "sg:postcode":"72209",
    "sg:province":"AR",
    "sg:tags":[
        "general"
    ],
    "wof:name":"A Aaakey Mini-Storage",
    "wof:placetype":"venue"
},
  "geometry": {"coordinates":[-92.344131,34.690668],"type":"Point"}
}