{
  "type": "Feature",
  "properties": {
    "iso:country":"US",
    "sg:address":"110 N 1st St",
    "sg:city":"Cabot",
    "sg:classifiers":[
        {
            "category":"Shopping",
            "subcategory":"Gifts & Souvenirs",
            "type":"Retail Goods"
        }
    ],
    "sg:phone":"+1 501 843 0202",
    "sg:postcode":"72023",
    "sg:province":"AR",
    "sg:tags":[
        "shop"
    ],
    "wof:name":"Cabot Collections",
    "wof:placetype":"venue"
},
  "geometry": {"coordinates":[-92.015597,34.974264],"type":"Point"}
}