{
  "type": "Feature",
  "properties": {
    "addr:full":"605 N Dudney Rd Magnolia AR 71753",
    "addr:housenumber":"605",
    "addr:postcode":"71753",
    "addr:street":"N Dudney Rd",
    "iso:country":"US",
    "sg:address":"605 N Dudney Rd",
    "sg:city":"Magnolia",
    "sg:classifiers":[
        {
            "category":"Professional",
            "subcategory":"Accounting & Tax Preparation",
            "type":"Services"
        }
    ],
    "sg:phone":"+1 870 234 2412",
    "sg:postcode":"71753",
    "sg:province":"AR",
    "sg:tags":[
        "return",
        "preparation-business"
    ],
    "wof:name":"Lyn's Tax Service",
    "wof:placetype":"venue"
},
  "geometry": {"coordinates":[-93.232851,33.272022],"type":"Point"}
}