{
  "type": "Feature",
  "properties": {
    "iso:country":"US",
    "sg:address":"4499 Highway 126 N",
    "sg:city":"Gassville",
    "sg:classifiers":[
        {
            "category":"Wholesale",
            "subcategory":"Office Equipment",
            "type":"Manufacturing & Wholesale Goods"
        }
    ],
    "sg:phone":"+1 870 430 5234",
    "sg:postcode":"72635",
    "sg:province":"AR",
    "sg:tags":[
        "sawmill",
        "supply"
    ],
    "wof:name":"David Tucker",
    "wof:placetype":"venue"
},
  "geometry": {"coordinates":[-92.47060999999999,36.350908],"type":"Point"}
}