{
  "type": "Feature",
  "properties": {
    "iso:country":"US",
    "sg:address":"1117 Bethesda Rd",
    "sg:city":"Mena",
    "sg:classifiers":[
        {
            "category":"Building & Trades",
            "subcategory":"Plumbing",
            "type":"Services"
        }
    ],
    "sg:phone":"+1 479 437 3577",
    "sg:postcode":"71953",
    "sg:province":"OK",
    "sg:tags":[
        "plumbing",
        "contractor"
    ],
    "wof:name":"Fagen Plumbing Inc",
    "wof:placetype":"venue"
},
  "geometry": {"coordinates":[-94.240017,34.578297],"type":"Point"}
}