{
  "type": "Feature",
  "properties": {
    "addr:full":"444 N 48th St Springdale AR 72762",
    "addr:housenumber":"444",
    "addr:postcode":"72762",
    "addr:street":"N 48Th St",
    "iso:country":"US",
    "sg:address":"444 N 48th St",
    "sg:city":"Springdale",
    "sg:classifiers":[
        {
            "category":"Professional",
            "subcategory":"Detective & Security Services",
            "type":"Services"
        }
    ],
    "sg:phone":"+1 479 935 9911",
    "sg:postcode":"72762",
    "sg:province":"AR",
    "sg:tags":[
        "system"
    ],
    "sg:website":"www.NwaAlarm.com",
    "wof:name":"Arkansas Security",
    "wof:placetype":"venue"
},
  "geometry": {"coordinates":[-94.18354600000001,36.189333],"type":"Point"}
}