{
  "type": "Feature",
  "properties": {
    "iso:country":"US",
    "sg:address":"835 Co Rd 492",
    "sg:city":"Rector",
    "sg:classifiers":[
        {
            "category":"Food & Beverages",
            "subcategory":"Meat & Fish",
            "type":"Retail Goods"
        }
    ],
    "sg:phone":"+1 870 529 3262",
    "sg:postcode":"72461",
    "sg:province":"AR",
    "wof:name":"Small Junior",
    "wof:placetype":"venue"
},
  "geometry": {"coordinates":[-90.260875,36.33161],"type":"Point"}
}