{
  "type": "Feature",
  "properties": {
    "iso:country":"US",
    "sg:address":"3801 Mabelvale Pike",
    "sg:city":"Little Rock",
    "sg:classifiers":[
        {
            "category":"Building & Trades",
            "subcategory":"Construction",
            "type":"Services"
        }
    ],
    "sg:phone":"+1 501 562 2313",
    "sg:postcode":"72204",
    "sg:province":"AR",
    "sg:tags":[
        "residential"
    ],
    "wof:name":"Southern Pavers",
    "wof:placetype":"venue"
},
  "geometry": {"coordinates":[-92.332775,34.716015],"type":"Point"}
}