{
  "type": "Feature",
  "properties": {
    "iso:country":"US",
    "sg:address":"101 E Walnut St",
    "sg:city":"Tuckerman",
    "sg:classifiers":[
        {
            "category":"Banks & Credit Unions",
            "subcategory":"Bank",
            "type":"Services"
        },
        {
            "category":"Banks & Credit Unions",
            "subcategory":"Financial Services",
            "type":"Services"
        }
    ],
    "sg:phone":"+1 870 349 1333",
    "sg:postcode":"72473",
    "sg:province":"AR",
    "sg:tags":[
        "saving",
        "loan",
        "commercial"
    ],
    "sg:website":"http://www.mandpbank.com",
    "wof:name":"Merchants & Planters Bank",
    "wof:placetype":"venue"
},
  "geometry": {"coordinates":[-91.198692,35.731949],"type":"Point"}
}