{
  "type": "Feature",
  "properties": {
    "iso:country":"US",
    "sg:address":"206 Country Club Pkwy",
    "sg:city":"Maumelle",
    "sg:classifiers":[
        {
            "category":"Building & Trades",
            "subcategory":"Construction",
            "type":"Services"
        }
    ],
    "sg:phone":"+1 501 851 0916",
    "sg:postcode":"72113",
    "sg:province":"AR",
    "sg:tags":[
        "contractor"
    ],
    "wof:name":"Davisbuilt Homes",
    "wof:placetype":"venue"
},
  "geometry": {"coordinates":[-92.401034,34.841366],"type":"Point"}
}