{
  "type": "Feature",
  "properties": {
    "iso:country":"US",
    "sg:address":"310 1st St",
    "sg:city":"Tuckerman",
    "sg:classifiers":[
        {
            "category":"Farming",
            "subcategory":"Farm & Veterinary Services",
            "type":"Manufacturing & Wholesale Goods"
        }
    ],
    "sg:phone":"+1 870 349 2254",
    "sg:postcode":"72473",
    "sg:province":"AR",
    "sg:tags":[
        "drying",
        "grain"
    ],
    "wof:name":"Tuckerman Grain Drying Co-Op",
    "wof:placetype":"venue"
},
  "geometry": {"coordinates":[-91.200277,35.726443],"type":"Point"}
}