{
  "type": "Feature",
  "properties": {
    "addr:full":"314 Melrose St El Dorado AR 71730",
    "addr:housenumber":"314",
    "addr:postcode":"71730",
    "addr:street":"Melrose St",
    "iso:country":"US",
    "sg:address":"314 Melrose St",
    "sg:city":"El Dorado",
    "sg:classifiers":[
        {
            "category":"Shopping",
            "subcategory":"Used Merchandise",
            "type":"Retail Goods"
        }
    ],
    "sg:phone":"+1 870 862 9494",
    "sg:postcode":"71730",
    "sg:province":"AR",
    "sg:tags":[
        "pawnbroker"
    ],
    "wof:name":"Northwest Pawn Inc",
    "wof:placetype":"venue"
},
  "geometry": {"coordinates":[-92.667036,33.227934],"type":"Point"}
}