{
  "type": "Feature",
  "properties": {
    "iso:country":"US",
    "sg:address":"221 Main St",
    "sg:city":"Arkadelphia",
    "sg:classifiers":[
        {
            "category":"Social Services",
            "subcategory":"Child Care",
            "type":"Services"
        }
    ],
    "sg:phone":"+1 870 246 8212",
    "sg:postcode":"71923",
    "sg:province":"AR",
    "sg:tags":[
        "day"
    ],
    "wof:name":"Hours of Joy Child Care Center",
    "wof:placetype":"venue"
},
  "geometry": {"coordinates":[-93.049867,34.119442],"type":"Point"}
}