{
  "type": "Feature",
  "properties": {
    "iso:country":"US",
    "sg:address":"1413 State Hwy 52 W",
    "sg:city":"Crossett",
    "sg:classifiers":[
        {
            "category":"Retail",
            "subcategory":"Laundry & Dry Cleaning",
            "type":"Services"
        }
    ],
    "sg:phone":"+1 870 304 2076",
    "sg:postcode":"71635",
    "sg:province":"AR",
    "wof:name":"A M Company Carpet Cleaning",
    "wof:placetype":"venue"
},
  "geometry": {"coordinates":[-91.924161,33.16919],"type":"Point"}
}