{
  "type": "Feature",
  "properties": {
    "addr:full":"14310 Corvallis Rd Maumelle AR 72113",
    "addr:housenumber":"14310",
    "addr:postcode":"72113",
    "addr:street":"Corvallis Rd",
    "iso:country":"US",
    "sg:address":"14310 Corvallis Rd",
    "sg:city":"Maumelle",
    "sg:classifiers":[
        {
            "category":"Manufacturing",
            "subcategory":"Motor Vehicles & Parts",
            "type":"Manufacturing & Wholesale Goods"
        }
    ],
    "sg:phone":"+1 501 851 2640",
    "sg:postcode":"72113",
    "sg:province":"AR",
    "sg:tags":[
        "auto",
        "mfg",
        "trimming"
    ],
    "wof:name":"Mc Leods British Cars",
    "wof:placetype":"venue"
},
  "geometry": {"coordinates":[-92.393624,34.887547],"type":"Point"}
}