{
  "type": "Feature",
  "properties": {
    "addr:full":"217 W Conway St Benton AR 72015",
    "addr:housenumber":"217",
    "addr:postcode":"72015",
    "addr:street":"W Conway St",
    "iso:country":"US",
    "sg:address":"217 W Conway St",
    "sg:city":"Benton",
    "sg:classifiers":[
        {
            "category":"Real Estate",
            "subcategory":"Real Estate Services",
            "type":"Services"
        },
        {
            "category":"Real Estate",
            "subcategory":"Real Estate Agent",
            "type":"Services"
        }
    ],
    "sg:phone":"+1 501 860 5115",
    "sg:postcode":"72015",
    "sg:province":"AR",
    "sg:tags":[
        "buyer",
        "broker"
    ],
    "wof:name":"Real Estate Services I",
    "wof:placetype":"venue"
},
  "geometry": {"coordinates":[-92.588274,34.565609],"type":"Point"}
}