{
  "type": "Feature",
  "properties": {
    "iso:country":"US",
    "sg:address":"823 State Hwy 130",
    "sg:city":"De Witt",
    "sg:classifiers":[
        {
            "category":"Insurance",
            "subcategory":"Insurance Agent",
            "type":"Services"
        }
    ],
    "sg:phone":"+1 870 946 3338",
    "sg:postcode":"72042",
    "sg:province":"AR",
    "wof:name":"Arkansas County Crop Insurance",
    "wof:placetype":"venue"
},
  "geometry": {"coordinates":[-91.340085,34.287571],"type":"Point"}
}