{
  "type": "Feature",
  "properties": {
    "iso:country":"US",
    "sg:address":"614 N 2nd St",
    "sg:city":"Rogers",
    "sg:classifiers":[
        {
            "category":"Professional",
            "subcategory":"Management & Consulting",
            "type":"Services"
        }
    ],
    "sg:phone":"+1 479 636 1363",
    "sg:postcode":"72756",
    "sg:province":"AR",
    "sg:tags":[
        "eating"
    ],
    "wof:name":"Sherman Tony",
    "wof:placetype":"venue"
},
  "geometry": {"coordinates":[-94.116644,36.338737],"type":"Point"}
}