{
  "type": "Feature",
  "properties": {
    "addr:full":"1424 N Shackleford Rd Little Rock AR 72211",
    "addr:housenumber":"1424",
    "addr:postcode":"72211",
    "addr:street":"N Shackleford Rd",
    "iso:country":"US",
    "sg:address":"1424 N Shackleford Rd",
    "sg:city":"Little Rock",
    "sg:classifiers":[
        {
            "category":"Food & Beverages",
            "subcategory":"Bakery",
            "type":"Retail Goods"
        }
    ],
    "sg:phone":"+1 501 224 1359",
    "sg:postcode":"72211",
    "sg:province":"AR",
    "sg:tags":[
        "doughnut"
    ],
    "wof:name":"Shipley Donuts",
    "wof:placetype":"venue"
},
  "geometry": {"coordinates":[-92.395974,34.766007],"type":"Point"}
}