{
  "type": "Feature",
  "properties": {
    "iso:country":"US",
    "sg:address":"4535 Blankenship Rd",
    "sg:city":"Everton",
    "sg:classifiers":[
        {
            "category":"Farming",
            "subcategory":"Farm",
            "type":"Manufacturing & Wholesale Goods"
        }
    ],
    "sg:phone":"+1 870 429 5254",
    "sg:postcode":"72633",
    "sg:province":"AR",
    "wof:name":"Waggoner Farm And Ranch",
    "wof:placetype":"venue"
},
  "geometry": {"coordinates":[-92.912216,36.1679],"type":"Point"}
}