{
  "type": "Feature",
  "properties": {
    "iso:country":"US",
    "sg:address":"5600 Landers Rd",
    "sg:city":"North Little Rock",
    "sg:classifiers":[
        {
            "category":"Health Services",
            "subcategory":"Optometrist",
            "type":"Services"
        }
    ],
    "sg:phone":"+1 501 955 5544",
    "sg:postcode":"72117",
    "sg:province":"AR",
    "wof:name":"Charles L McWaters",
    "wof:placetype":"venue"
},
  "geometry": {"coordinates":[-92.211883,34.803834],"type":"Point"}
}