{
  "type": "Feature",
  "properties": {
    "iso:country":"US",
    "sg:address":"725 Diane Ln",
    "sg:city":"Conway",
    "sg:classifiers":[
        {
            "category":"Professional",
            "type":"Services"
        }
    ],
    "sg:phone":"+1 501 513 1186",
    "sg:postcode":"72034",
    "sg:province":"AR",
    "wof:name":"Mike L Lemley",
    "wof:placetype":"venue"
},
  "geometry": {"coordinates":[-92.487476,35.072981],"type":"Point"}
}