{
  "type": "Feature",
  "properties": {
    "iso:country":"US",
    "sg:address":"3000 SE 14th St",
    "sg:city":"Bentonville",
    "sg:classifiers":[
        {
            "category":"Autos & Motor Vehicles",
            "subcategory":"Fuel & Gas Station",
            "type":"Retail Goods"
        }
    ],
    "sg:phone":"+1 479 636 7829",
    "sg:postcode":"72712",
    "sg:province":"AR",
    "sg:tags":[
        "station",
        "gasoline"
    ],
    "wof:name":"Family Shop 11",
    "wof:placetype":"venue"
},
  "geometry": {"coordinates":[-94.175578,36.356274],"type":"Point"}
}