{
  "type": "Feature",
  "properties": {
    "iso:country":"US",
    "sg:address":"111 W 3rd St",
    "sg:city":"Grove",
    "sg:classifiers":[
        {
            "category":"Shopping",
            "subcategory":"Jewelry",
            "type":"Retail Goods"
        }
    ],
    "sg:phone":"+1 918 786 6311",
    "sg:postcode":"74344",
    "sg:province":"OK",
    "sg:tags":[
        "repair",
        "precious",
        "mfg",
        "met"
    ],
    "wof:name":"J T Jewelers",
    "wof:placetype":"venue"
},
  "geometry": {"coordinates":[-94.771647,36.593505],"type":"Point"}
}