{
  "type": "Feature",
  "properties": {
    "iso:country":"US",
    "sg:address":"9721 Congo Rd",
    "sg:city":"Benton",
    "sg:classifiers":[
        {
            "category":"Building & Trades",
            "subcategory":"Construction",
            "type":"Services"
        }
    ],
    "sg:phone":"+1 501 316 2304",
    "sg:postcode":"72019",
    "sg:province":"AR",
    "sg:tags":[
        "house"
    ],
    "wof:name":"Hunnicutt Development",
    "wof:placetype":"venue"
},
  "geometry": {"coordinates":[-92.582928,34.657106],"type":"Point"}
}