{
  "type": "Feature",
  "properties": {
    "iso:country":"US",
    "sg:address":"2890 W. Walnut St A-1",
    "sg:city":"Rogers",
    "sg:classifiers":[
        {
            "category":"Insurance",
            "subcategory":"Hazard Insurance",
            "type":"Services"
        }
    ],
    "sg:phone":"+1 479 715 0073",
    "sg:postcode":"72758",
    "sg:province":"AR",
    "wof:name":"Keith Edgeworth - American National Insurance",
    "wof:placetype":"venue"
},
  "geometry": {"coordinates":[-94.1604,36.3338],"type":"Point"}
}