{
  "type": "Feature",
  "properties": {
    "iso:country":"US",
    "sg:address":"220 Tom Ellsworth Dr",
    "sg:city":"Hot Springs",
    "sg:classifiers":[
        {
            "category":"Education",
            "subcategory":"School",
            "type":"Public Place"
        }
    ],
    "sg:phone":"+1 501 623 5661",
    "sg:postcode":"71901",
    "sg:province":"AR",
    "wof:name":"Park Elementary School",
    "wof:placetype":"venue"
},
  "geometry": {"coordinates":[-93.048418,34.527636],"type":"Point"}
}