{
  "type": "Feature",
  "properties": {
    "addr:full":"8570 Cantrell Rd Little Rock AR 72227",
    "addr:housenumber":"8570",
    "addr:postcode":"72227",
    "addr:street":"Cantrell Rd",
    "iso:country":"US",
    "sg:address":"8570 Cantrell Rd",
    "sg:city":"Little Rock",
    "sg:classifiers":[
        {
            "category":"Building & Trades",
            "subcategory":"Landscaping Services",
            "type":"Services"
        }
    ],
    "sg:phone":"+1 501 227 6125",
    "sg:postcode":"72227",
    "sg:province":"AR",
    "sg:tags":[
        "park",
        "recreation",
        "design",
        "sales"
    ],
    "wof:name":"Kyle Recreation Inc",
    "wof:placetype":"venue"
},
  "geometry": {"coordinates":[-92.374787,34.781203],"type":"Point"}
}