{
  "type": "Feature",
  "properties": {
    "iso:country":"US",
    "sg:address":"100 E Railroad Ave",
    "sg:city":"Morrilton",
    "sg:classifiers":[
        {
            "category":"Home & Garden",
            "subcategory":"Building Materials",
            "type":"Retail Goods"
        }
    ],
    "sg:phone":"+1 501 354 5453",
    "sg:postcode":"72110",
    "sg:province":"AR",
    "sg:tags":[
        "glass",
        "window",
        "plate"
    ],
    "wof:name":"Raney Glass & Mirror",
    "wof:placetype":"venue"
},
  "geometry": {"coordinates":[-92.745136,35.152336],"type":"Point"}
}