{
  "type": "Feature",
  "properties": {
    "addr:full":"803 N West Ave El Dorado AR 71730",
    "addr:housenumber":"803",
    "addr:postcode":"71730",
    "addr:street":"N West Ave",
    "iso:country":"US",
    "sg:address":"803 N West Ave",
    "sg:city":"El Dorado",
    "sg:classifiers":[
        {
            "category":"Building & Trades",
            "subcategory":"Equipment Rental",
            "type":"Services"
        }
    ],
    "sg:phone":"+1 870 862 8431",
    "sg:postcode":"71730",
    "sg:province":"AR",
    "sg:tags":[
        "leasing",
        "furniture"
    ],
    "sg:website":"www.rentway.com",
    "wof:name":"Rent Way",
    "wof:placetype":"venue"
},
  "geometry": {"coordinates":[-92.665413,33.219702],"type":"Point"}
}