{
  "type": "Feature",
  "properties": {
    "iso:country":"US",
    "sg:address":"295 Frost Rd",
    "sg:city":"Arkadelphia",
    "sg:classifiers":[
        {
            "category":"Professional",
            "type":"Services"
        }
    ],
    "sg:phone":"+1 870 246 9899",
    "sg:postcode":"71923",
    "sg:province":"AR",
    "wof:name":"Benny Ezell",
    "wof:placetype":"venue"
},
  "geometry": {"coordinates":[-93.06245699999999,34.191953],"type":"Point"}
}