{
  "type": "Feature",
  "properties": {
    "iso:country":"US",
    "sg:address":"3545 Kerr Station Rd",
    "sg:city":"Cabot",
    "sg:classifiers":[
        {
            "category":"Building & Trades",
            "subcategory":"Landscaping Services",
            "type":"Services"
        }
    ],
    "sg:phone":"+1 501 416 1663",
    "sg:postcode":"72023",
    "sg:province":"AR",
    "sg:tags":[
        "lawn",
        "maintenance"
    ],
    "wof:name":"J D Lawn Service",
    "wof:placetype":"venue"
},
  "geometry": {"coordinates":[-92.020712,34.931564],"type":"Point"}
}