{
  "type": "Feature",
  "properties": {
    "addr:full":"90 North Dr Conway AR 72034",
    "addr:housenumber":"90",
    "addr:postcode":"72034",
    "addr:street":"North Dr",
    "iso:country":"US",
    "sg:address":"90 North Dr",
    "sg:city":"Conway",
    "sg:classifiers":[
        {
            "category":"Professional",
            "subcategory":"Computer Services",
            "type":"Services"
        }
    ],
    "sg:phone":"+1 501 470 1907",
    "sg:postcode":"72034",
    "sg:province":"AR",
    "sg:tags":[
        "programing",
        "custom"
    ],
    "wof:name":"Innovtive Solutions Consulting",
    "wof:placetype":"venue"
},
  "geometry": {"coordinates":[-92.441728,34.999464],"type":"Point"}
}