{
  "type": "Feature",
  "properties": {
    "iso:country":"US",
    "sg:address":"150 W Van Buren St",
    "sg:city":"Eureka Springs",
    "sg:classifiers":[
        {
            "category":"Retail",
            "subcategory":"Funeral Services",
            "type":"Services"
        }
    ],
    "sg:phone":"+1 479 253 8927",
    "sg:postcode":"72632",
    "sg:province":"AR",
    "sg:tags":[
        "director"
    ],
    "wof:name":"Nelson Funeral Svc Inc",
    "wof:placetype":"venue"
},
  "geometry": {"coordinates":[-93.745863,36.397311],"type":"Point"}
}