{
  "type": "Feature",
  "properties": {
    "iso:country":"US",
    "sg:address":"509 W 1st St",
    "sg:city":"De Witt",
    "sg:classifiers":[
        {
            "category":"Social Services",
            "subcategory":"Child Care",
            "type":"Services"
        }
    ],
    "sg:phone":"+1 870 946 0323",
    "sg:postcode":"72042",
    "sg:province":"AR",
    "wof:name":"Little Red Schollhouse",
    "wof:placetype":"venue"
},
  "geometry": {"coordinates":[-91.341248,34.294184],"type":"Point"}
}