{
  "type": "Feature",
  "properties": {
    "addr:full":"5459 Central Ave Hot Springs National Park AR 71913",
    "addr:housenumber":"5459",
    "addr:postcode":"71913",
    "addr:street":"Central Ave",
    "iso:country":"US",
    "sg:address":"5459 Central Ave",
    "sg:city":"Hot Springs National Park",
    "sg:classifiers":[
        {
            "category":"Wholesale",
            "subcategory":"Machinery & Supplies",
            "type":"Manufacturing & Wholesale Goods"
        }
    ],
    "sg:phone":"+1 501 525 1412",
    "sg:postcode":"71913",
    "sg:province":"AR",
    "sg:tags":[
        "equipment",
        "establishment"
    ],
    "wof:name":"Davron Beauty Distributers Ark",
    "wof:placetype":"venue"
},
  "geometry": {"coordinates":[-93.09419,34.425008],"type":"Point"}
}