{
  "type": "Feature",
  "properties": {
    "iso:country":"US",
    "sg:address":"5417 Pinnacle Ponte Dr",
    "sg:city":"Rogers",
    "sg:classifiers":[
        {
            "category":"Banks & Credit Unions",
            "subcategory":"Investment Brokerage",
            "type":"Services"
        }
    ],
    "sg:phone":"+1 479 271 4180",
    "sg:postcode":"72758",
    "sg:province":"AR",
    "sg:tags":[
        "funds",
        "mutual"
    ],
    "wof:name":"Barney Smith",
    "wof:placetype":"venue"
},
  "geometry": {"coordinates":[-94.186985,36.31209],"type":"Point"}
}