{
  "type": "Feature",
  "properties": {
    "addr:full":"1898 Rocky Point Rd Judsonia AR 72081",
    "addr:housenumber":"1898",
    "addr:postcode":"72081",
    "addr:street":"Rocky Point Rd",
    "iso:country":"US",
    "sg:address":"1898 Rocky Point Rd",
    "sg:city":"Judsonia",
    "sg:classifiers":[
        {
            "category":"Home & Garden",
            "subcategory":"Mobile Homes",
            "type":"Retail Goods"
        }
    ],
    "sg:phone":"+1 501 729 5226",
    "sg:postcode":"72081",
    "sg:province":"AR",
    "wof:name":"C & G Mobile Homes",
    "wof:placetype":"venue"
},
  "geometry": {"coordinates":[-91.62417499999999,35.305541],"type":"Point"}
}