{
  "type": "Feature",
  "properties": {
    "iso:country":"US",
    "sg:address":"1898 Rocky Point Rd",
    "sg:city":"Judsonia",
    "sg:classifiers":[
        {
            "category":"Home & Garden",
            "subcategory":"Mobile Homes",
            "type":"Retail Goods"
        }
    ],
    "sg:phone":"+1 501 729 5226",
    "sg:postcode":"72081",
    "sg:province":"AR",
    "wof:name":"C & G Mobile Homes",
    "wof:placetype":"venue"
},
  "geometry": {"coordinates":[-91.624175,35.305541],"type":"Point"}
}