{
  "type": "Feature",
  "properties": {
    "iso:country":"US",
    "sg:address":"11800 Chenal Pkwy",
    "sg:city":"Little Rock",
    "sg:classifiers":[
        {
            "category":"Shopping",
            "subcategory":"Computers & Home Electronics",
            "type":"Retail Goods"
        }
    ],
    "sg:phone":"+1 501 227 4177",
    "sg:postcode":"72211",
    "sg:province":"AR",
    "sg:tags":[
        "equipment",
        "product",
        "audio",
        "video"
    ],
    "sg:website":"www.bestbuy.com",
    "wof:name":"Best Buy",
    "wof:placetype":"venue"
},
  "geometry": {"coordinates":[-92.407956,34.749349],"type":"Point"}
}