{
  "type": "Feature",
  "properties": {
    "addr:full":"2117 S Main St Stuttgart AR 72160",
    "addr:housenumber":"2117",
    "addr:postcode":"72160",
    "addr:street":"S Main St",
    "iso:country":"US",
    "sg:address":"2117 S Main St",
    "sg:city":"Stuttgart",
    "sg:classifiers":[
        {
            "category":"Autos & Motor Vehicles",
            "subcategory":"Fuel & Gas Station",
            "type":"Retail Goods"
        },
        {
            "category":"Food & Beverages",
            "subcategory":"Groceries & Convenience Stores",
            "type":"Retail Goods"
        }
    ],
    "sg:phone":"+1 870 673 4341",
    "sg:postcode":"72160",
    "sg:province":"AR",
    "sg:website":"http://www.ezmart.com",
    "wof:name":"E-Z Mart",
    "wof:placetype":"venue"
},
  "geometry": {"coordinates":[-91.55313,34.480379],"type":"Point"}
}