{
  "type": "Feature",
  "properties": {
    "iso:country":"US",
    "sg:address":"102 Cedar St",
    "sg:city":"Crossett",
    "sg:classifiers":[
        {
            "category":"Wholesale",
            "subcategory":"Electrical",
            "type":"Manufacturing & Wholesale Goods"
        }
    ],
    "sg:phone":"+1 870 364 4223",
    "sg:postcode":"71635",
    "sg:province":"AR",
    "sg:tags":[
        "electronic"
    ],
    "wof:name":"K Irby Co",
    "wof:placetype":"venue"
},
  "geometry": {"coordinates":[-91.95493999999999,33.135502],"type":"Point"}
}