{
  "type": "Feature",
  "properties": {
    "iso:country":"US",
    "sg:address":"12 Jefferson Pl",
    "sg:city":"Pine Bluff",
    "sg:classifiers":[
        {
            "category":"Professional",
            "subcategory":"Business Services",
            "type":"Services"
        }
    ],
    "sg:phone":"+1 870 535 1586",
    "sg:postcode":"71603",
    "sg:province":"AR",
    "wof:name":"Pact Ltd Partnership",
    "wof:placetype":"venue"
},
  "geometry": {"coordinates":[-92.02017600000001,34.187617],"type":"Point"}
}