{
  "type": "Feature",
  "properties": {
    "addr:full":"1 Goodart Cir Hickory Ridge AR 72347",
    "addr:housenumber":"1",
    "addr:postcode":"72347",
    "addr:street":"Goodart Cir",
    "iso:country":"US",
    "sg:address":"1 Goodart Cir",
    "sg:city":"Hickory Ridge",
    "sg:classifiers":[
        {
            "category":"Organizations",
            "subcategory":"Religious Organization",
            "type":"Services"
        }
    ],
    "sg:phone":"+1 870 697 2962",
    "sg:postcode":"72347",
    "sg:province":"AR",
    "sg:tags":[
        "clergy"
    ],
    "wof:name":"Hickory Ridge Bapt Parsonage",
    "wof:placetype":"venue"
},
  "geometry": {"coordinates":[-90.98978,35.39713],"type":"Point"}
}