{
  "type": "Feature",
  "properties": {
    "iso:country":"US",
    "sg:address":"5435 Hwy 62 W",
    "sg:city":"Gassville",
    "sg:classifiers":[
        {
            "category":"Shopping",
            "subcategory":"Hobbies, Toys, & Games",
            "type":"Retail Goods"
        }
    ],
    "sg:phone":"+1 870 430 5225",
    "sg:postcode":"72635",
    "sg:province":"AR",
    "sg:tags":[
        "craft",
        "supply"
    ],
    "wof:name":"R Gems Inc",
    "wof:placetype":"venue"
},
  "geometry": {"coordinates":[-92.44808999999999,36.299477],"type":"Point"}
}