{
  "type": "Feature",
  "properties": {
    "addr:full":"12931 Heavenly Way Garfield AR 72732",
    "addr:housenumber":"12931",
    "addr:postcode":"72732",
    "addr:street":"Heavenly Way",
    "iso:country":"US",
    "sg:address":"12931 Heavenly Way",
    "sg:city":"Garfield",
    "sg:classifiers":[
        {
            "category":"Professional",
            "subcategory":"Engineering",
            "type":"Services"
        }
    ],
    "sg:phone":"+1 479 359 2243",
    "sg:postcode":"72732",
    "sg:province":"AR",
    "sg:tags":[
        "consulting",
        "engineer"
    ],
    "wof:name":"Jeff Riedesel",
    "wof:placetype":"venue"
},
  "geometry": {"coordinates":[-93.872778,36.412984],"type":"Point"}
}