{
  "type": "Feature",
  "properties": {
    "iso:country":"US",
    "sg:address":"503 N Pittman St",
    "sg:city":"Prairie Grove",
    "sg:classifiers":[
        {
            "category":"Professional",
            "subcategory":"Accounting & Tax Preparation",
            "type":"Services"
        }
    ],
    "sg:phone":"+1 479 846 3424",
    "sg:postcode":"72753",
    "sg:province":"AR",
    "sg:tags":[
        "accountant"
    ],
    "wof:name":"Pam Doss Accounting",
    "wof:placetype":"venue"
},
  "geometry": {"coordinates":[-94.313411,35.981873],"type":"Point"}
}