{
  "type": "Feature",
  "properties": {
    "addr:full":"2300 E 16th St Russellville AR 72802",
    "addr:housenumber":"2300",
    "addr:postcode":"72802",
    "addr:street":"E 16Th St",
    "iso:country":"US",
    "sg:address":"2300 E 16th St",
    "sg:city":"Russellville",
    "sg:classifiers":[
        {
            "category":"Professional",
            "type":"Services"
        }
    ],
    "sg:phone":"+1 479 968 1455",
    "sg:postcode":"72802",
    "sg:province":"AR",
    "sg:tags":[
        "establishment"
    ],
    "wof:name":"Burnup & Sims Comtec Inc",
    "wof:placetype":"venue"
},
  "geometry": {"coordinates":[-93.107427,35.263579],"type":"Point"}
}