{
  "type": "Feature",
  "properties": {
    "iso:country":"US",
    "sg:address":"410 W Huntington Ave",
    "sg:city":"Jonesboro",
    "sg:classifiers":[
        {
            "category":"Building & Trades",
            "subcategory":"Landscaping Services",
            "type":"Services"
        }
    ],
    "sg:phone":"+1 870 930 0390",
    "sg:postcode":"72401",
    "sg:province":"AR",
    "wof:name":"Ruff Cuts",
    "wof:placetype":"venue"
},
  "geometry": {"coordinates":[-90.710376,35.840447],"type":"Point"}
}