{
  "type": "Feature",
  "properties": {
    "iso:country":"US",
    "sg:address":"701 Wellington Hills Rd",
    "sg:city":"Little Rock",
    "sg:classifiers":[
        {
            "category":"Real Estate",
            "subcategory":"Real Estate Agent",
            "type":"Services"
        }
    ],
    "sg:phone":"+1 501 821 1800",
    "sg:postcode":"72211",
    "sg:province":"AR",
    "sg:tags":[
        "finding",
        "apartment",
        "rental"
    ],
    "wof:name":"Cedars At Wellington Lake",
    "wof:placetype":"venue"
},
  "geometry": {"coordinates":[-92.44552899999999,34.761258],"type":"Point"}
}