{
  "type": "Feature",
  "properties": {
    "iso:country":"US",
    "sg:address":"1010 Cones Rd",
    "sg:city":"Hot Springs National",
    "sg:classifiers":[
        {
            "category":"Real Estate",
            "subcategory":"Real Estate Agent",
            "type":"Services"
        }
    ],
    "sg:phone":"+1 501 318 1317",
    "sg:postcode":"71901",
    "sg:province":"AR",
    "wof:name":"Christopher Homes of Hot Sprng",
    "wof:placetype":"venue"
},
  "geometry": {"coordinates":[-93.024495,34.497661],"type":"Point"}
}