{
  "type": "Feature",
  "properties": {
    "addr:full":"929 Roseclair Dr N Little Rock AR 72117",
    "addr:housenumber":"929",
    "addr:postcode":"72117",
    "addr:street":"Roseclair Dr N",
    "iso:country":"US",
    "sg:address":"929 Roseclair Dr",
    "sg:city":"N Little Rock",
    "sg:classifiers":[
        {
            "category":"Restaurant",
            "type":"Food & Drink"
        }
    ],
    "sg:phone":"+1 501 955 2021",
    "sg:postcode":"72117",
    "sg:province":"AR",
    "wof:name":"Oliver's Catfish",
    "wof:placetype":"venue"
},
  "geometry": {"coordinates":[-92.200762,34.762304],"type":"Point"}
}