{
  "type": "Feature",
  "properties": {
    "iso:country":"US",
    "sg:address":"129 E Buchanan St",
    "sg:city":"Prairie Grove",
    "sg:classifiers":[
        {
            "category":"Professional",
            "subcategory":"Business Services",
            "type":"Services"
        }
    ],
    "sg:phone":"+1 479 267 4447",
    "sg:postcode":"72753",
    "sg:province":"AR",
    "wof:name":"Battlefield Flea Market",
    "wof:placetype":"venue"
},
  "geometry": {"coordinates":[-94.31697,35.975596],"type":"Point"}
}