{
  "type": "Feature",
  "properties": {
    "iso:country":"US",
    "sg:address":"2710 N Woods Ln",
    "sg:city":"Rogers",
    "sg:classifiers":[
        {
            "category":"Education",
            "subcategory":"School",
            "type":"Public Place"
        }
    ],
    "sg:phone":"+1 479 631 3544",
    "sg:postcode":"72756",
    "sg:province":"AR",
    "wof:name":"Rogers Public Schools After School Care Hippy Program",
    "wof:placetype":"venue"
},
  "geometry": {"coordinates":[-94.155425,36.357819],"type":"Point"}
}