{
  "type": "Feature",
  "properties": {
    "iso:country":"US",
    "sg:address":"179 S Hwy 152",
    "sg:city":"Humphrey",
    "sg:phone":"+1 870 873 4280",
    "sg:postcode":"72073",
    "sg:province":"AR",
    "sg:tags":[
        "farm",
        "soybean"
    ],
    "wof:name":"MMr",
    "wof:placetype":"venue"
},
  "geometry": {"coordinates":[-91.639066,34.407707],"type":"Point"}
}