{
  "type": "Feature",
  "properties": {
    "addr:full":"5404 S University Ave Little Rock AR 72209",
    "addr:housenumber":"5404",
    "addr:postcode":"72209",
    "addr:street":"S University Ave",
    "iso:country":"US",
    "sg:address":"5404 S University Ave",
    "sg:city":"Little Rock",
    "sg:classifiers":[
        {
            "category":"Real Estate",
            "subcategory":"Real Estate Agent",
            "type":"Services"
        }
    ],
    "sg:phone":"+1 501 847 2152",
    "sg:postcode":"72209",
    "sg:province":"AR",
    "wof:name":"Buffington Realty Co Mobile Hm",
    "wof:placetype":"venue"
},
  "geometry": {"coordinates":[-92.34533399999999,34.701216],"type":"Point"}
}