{
  "type": "Feature",
  "properties": {
    "addr:full":"1209 Old Charter Ct Little Rock AR 72211",
    "addr:housenumber":"1209",
    "addr:postcode":"72211",
    "addr:street":"Old Charter Ct",
    "iso:country":"US",
    "sg:address":"1209 Old Charter Ct",
    "sg:city":"Little Rock",
    "sg:classifiers":[
        {
            "category":"Education",
            "subcategory":"Special Training",
            "type":"Public Place"
        }
    ],
    "sg:phone":"+1 501 228 6852",
    "sg:postcode":"72211",
    "sg:province":"AR",
    "sg:tags":[
        "vocational",
        "expert"
    ],
    "wof:name":"Richard Marron",
    "wof:placetype":"venue"
},
  "geometry": {"coordinates":[-92.402418,34.763923],"type":"Point"}
}