{
  "type": "Feature",
  "properties": {
    "addr:full":"1117 US Hwy 71 Scn Fayetteville AR 72701",
    "addr:housenumber":"1117",
    "addr:postcode":"72701",
    "addr:street":"Us Hwy 71 Scn",
    "iso:country":"US",
    "sg:address":"1117 US Hwy 71 Scn",
    "sg:city":"Fayetteville",
    "sg:classifiers":[
        {
            "category":"Restaurant",
            "type":"Food & Drink"
        }
    ],
    "sg:phone":"+1 479 273 7701",
    "sg:postcode":"72701",
    "sg:province":"AR",
    "wof:name":"Mazzio's Pizza",
    "wof:placetype":"venue"
},
  "geometry": {"coordinates":[-94.1733,36.012771],"type":"Point"}
}