{
  "type": "Feature",
  "properties": {
    "addr:full":"421 Towson Ave Fort Smith AR 72901",
    "addr:housenumber":"421",
    "addr:postcode":"72901",
    "addr:street":"Towson Ave",
    "iso:country":"US",
    "sg:address":"421 Towson Ave",
    "sg:city":"Fort Smith",
    "sg:classifiers":[
        {
            "category":"Wholesale",
            "subcategory":"Auto Parts",
            "type":"Manufacturing & Wholesale Goods"
        }
    ],
    "sg:phone":"+1 479 782 0301",
    "sg:postcode":"72901",
    "sg:province":"AR",
    "sg:tags":[
        "supply"
    ],
    "wof:name":"Carquest Auto Parts",
    "wof:placetype":"venue"
},
  "geometry": {"coordinates":[-94.421071,35.379498],"type":"Point"}
}