{
  "type": "Feature",
  "properties": {
    "iso:country":"US",
    "sg:address":"131 Irongate St",
    "sg:city":"Hot Springs",
    "sg:classifiers":[
        {
            "category":"Real Estate",
            "subcategory":"Real Estate Agent",
            "type":"Services"
        }
    ],
    "sg:phone":"+1 501 767 5244",
    "sg:postcode":"71913",
    "sg:province":"AR",
    "sg:tags":[
        "appraiser"
    ],
    "wof:name":"Central Arkansas Appraisal Svc",
    "wof:placetype":"venue"
},
  "geometry": {"coordinates":[-93.140729,34.470647],"type":"Point"}
}