{
  "type": "Feature",
  "properties": {
    "iso:country":"US",
    "sg:address":"2905 S Cedar St",
    "sg:city":"Little Rock",
    "sg:classifiers":[
        {
            "category":"Organizations",
            "subcategory":"Non-profit Organization",
            "type":"Services"
        }
    ],
    "sg:phone":"+1 501 661 0651",
    "sg:postcode":"72204",
    "sg:province":"AR",
    "wof:name":"LIONS World Svc For Blind",
    "wof:placetype":"venue"
},
  "geometry": {"coordinates":[-92.318978,34.724463],"type":"Point"}
}