{
  "type": "Feature",
  "properties": {
    "addr:full":"1642 Perry St Helena AR 72342",
    "addr:housenumber":"1642",
    "addr:postcode":"72342",
    "addr:street":"Perry St",
    "iso:country":"US",
    "sg:address":"1642 Perry St",
    "sg:city":"Helena",
    "sg:classifiers":[
        {
            "category":"Organizations",
            "subcategory":"Religious Organization",
            "type":"Services"
        }
    ],
    "sg:phone":"+1 870 338 6024",
    "sg:postcode":"72342",
    "sg:province":"AR",
    "wof:name":"Jehovahs Witnesses",
    "wof:placetype":"venue"
},
  "geometry": {"coordinates":[-90.607663,34.529294],"type":"Point"}
}