{
  "type": "Feature",
  "properties": {
    "iso:country":"US",
    "sg:address":"511 W Front St",
    "sg:city":"Lonoke",
    "sg:classifiers":[
        {
            "category":"Restaurant",
            "type":"Food & Drink"
        }
    ],
    "sg:phone":"+1 501 676 2812",
    "sg:postcode":"72086",
    "sg:province":"AR",
    "sg:tags":[
        "dairy",
        "bar"
    ],
    "wof:name":"Lonoke Dairy Bar",
    "wof:placetype":"venue"
},
  "geometry": {"coordinates":[-91.90490800000001,34.783881],"type":"Point"}
}