{
  "type": "Feature",
  "properties": {
    "iso:country":"US",
    "sg:address":"209 N Walnut St",
    "sg:city":"Harrison",
    "sg:classifiers":[
        {
            "category":"Insurance",
            "subcategory":"Hazard Insurance",
            "type":"Services"
        }
    ],
    "sg:phone":"+1 870 741 5423",
    "sg:postcode":"72601",
    "sg:province":"AR",
    "sg:tags":[
        "commercial",
        "business"
    ],
    "wof:name":"Campbell Insurance",
    "wof:placetype":"venue"
},
  "geometry": {"coordinates":[-93.106052,36.230968],"type":"Point"}
}