{
  "type": "Feature",
  "properties": {
    "iso:country":"US",
    "sg:address":"2650 John Harden Dr",
    "sg:city":"Jacksonville",
    "sg:classifiers":[
        {
            "category":"Insurance",
            "subcategory":"Insurance Agent",
            "type":"Services"
        }
    ],
    "sg:phone":"+1 501 982 8880",
    "sg:postcode":"72076",
    "sg:province":"AR",
    "wof:name":"Schulte Insurance",
    "wof:placetype":"venue"
},
  "geometry": {"coordinates":[-92.102434,34.891432],"type":"Point"}
}