{
  "type": "Feature",
  "properties": {
    "addr:full":"313 E Kentucky St Caraway AR 72419",
    "addr:housenumber":"313",
    "addr:postcode":"72419",
    "addr:street":"E Kentucky St",
    "iso:country":"US",
    "sg:address":"313 E Kentucky St",
    "sg:city":"Caraway",
    "sg:classifiers":[
        {
            "category":"Personal",
            "subcategory":"Tanning Parlor",
            "type":"Services"
        }
    ],
    "sg:phone":"+1 870 482 1000",
    "sg:postcode":"72419",
    "sg:province":"AR",
    "sg:tags":[
        "salon"
    ],
    "wof:name":"Jungle Tanning Salon",
    "wof:placetype":"venue"
},
  "geometry": {"coordinates":[-90.320172,35.760754],"type":"Point"}
}