{
  "type": "Feature",
  "properties": {
    "iso:country":"US",
    "sg:address":"622 Sherris Ln",
    "sg:city":"Benton",
    "sg:classifiers":[
        {
            "category":"Farming",
            "subcategory":"Livestock Farm",
            "type":"Manufacturing & Wholesale Goods"
        }
    ],
    "sg:phone":"+1 501 778 7344",
    "sg:postcode":"72019",
    "sg:province":"AR",
    "sg:tags":[
        "beef",
        "feedlot",
        "cattle"
    ],
    "wof:name":"Denver Rice",
    "wof:placetype":"venue"
},
  "geometry": {"coordinates":[-92.59325699999999,34.579117],"type":"Point"}
}