{
  "type": "Feature",
  "properties": {
    "addr:full":"130 Jung Dr Hot Springs AR 71913",
    "addr:housenumber":"130",
    "addr:postcode":"71913",
    "addr:street":"Jung Dr",
    "iso:country":"US",
    "sg:address":"130 Jung Dr",
    "sg:city":"Hot Springs",
    "sg:classifiers":[
        {
            "category":"Real Estate",
            "subcategory":"Real Estate Operator",
            "type":"Services"
        }
    ],
    "sg:phone":"+1 501 525 5822",
    "sg:postcode":"71913",
    "sg:province":"AR",
    "sg:tags":[
        "mobile",
        "home",
        "community"
    ],
    "wof:name":"Forest Glade Mobile Home Cmnty",
    "wof:placetype":"venue"
},
  "geometry": {"coordinates":[-93.096109,34.451551],"type":"Point"}
}