{
  "type": "Feature",
  "properties": {
    "iso:country":"US",
    "sg:address":"700 N 11th St",
    "sg:city":"Blytheville",
    "sg:classifiers":[
        {
            "category":"Professional",
            "subcategory":"Business Services",
            "type":"Services"
        }
    ],
    "sg:phone":"+1 870 763 8934",
    "sg:postcode":"72315",
    "sg:province":"AR",
    "wof:name":"Gosnell Enterprises Inc",
    "wof:placetype":"venue"
},
  "geometry": {"coordinates":[-89.916597,35.933446],"type":"Point"}
}