{
  "type": "Feature",
  "properties": {
    "addr:full":"370 Bill Henry Rd Monticello AR 71655",
    "addr:housenumber":"370",
    "addr:postcode":"71655",
    "addr:street":"Bill Henry Rd",
    "iso:country":"US",
    "sg:address":"370 Bill Henry Rd",
    "sg:city":"Monticello",
    "sg:classifiers":[
        {
            "category":"Real Estate",
            "subcategory":"Real Estate Operator",
            "type":"Services"
        }
    ],
    "sg:phone":"+1 870 367 3755",
    "sg:postcode":"71655",
    "sg:province":"AR",
    "sg:tags":[
        "apartment"
    ],
    "wof:name":"Billy Hartness Construction Co",
    "wof:placetype":"venue"
},
  "geometry": {"coordinates":[-91.813304,33.747547],"type":"Point"}
}