{
  "type": "Feature",
  "properties": {
    "addr:full":"206 S Elm St Searcy AR 72143",
    "addr:housenumber":"206",
    "addr:postcode":"72143",
    "addr:street":"S Elm St",
    "iso:country":"US",
    "sg:address":"206 S Elm St",
    "sg:city":"Searcy",
    "sg:classifiers":[
        {
            "category":"Professional",
            "type":"Services"
        }
    ],
    "sg:phone":"+1 501 278 4873",
    "sg:postcode":"72143",
    "sg:province":"AR",
    "wof:name":"Barker Tractor",
    "wof:placetype":"venue"
},
  "geometry": {"coordinates":[-91.740578,35.247693],"type":"Point"}
}