{
  "type": "Feature",
  "properties": {
    "addr:full":"2100 Texas St Blytheville AR 72315",
    "addr:housenumber":"2100",
    "addr:postcode":"72315",
    "addr:street":"Texas St",
    "iso:country":"US",
    "sg:address":"2100 Texas St",
    "sg:city":"Blytheville",
    "sg:classifiers":[
        {
            "category":"Shopping",
            "subcategory":"Used Merchandise",
            "type":"Retail Goods"
        },
        {
            "category":"Banks & Credit Unions",
            "subcategory":"Bank",
            "type":"Services"
        },
        {
            "category":"Shopping",
            "subcategory":"Thrift Store",
            "type":"Retail Goods"
        }
    ],
    "sg:phone":"+1 870 532 5333",
    "sg:postcode":"72315",
    "sg:province":"AR",
    "sg:tags":[
        "shop",
        "resale",
        "second",
        "hand"
    ],
    "wof:name":"Abilities Unlimited",
    "wof:placetype":"venue"
},
  "geometry": {"coordinates":[-89.957802,35.950531],"type":"Point"}
}