{
  "type": "Feature",
  "properties": {
    "iso:country":"US",
    "sg:address":"6571 Blacks Ferry Rd",
    "sg:city":"Imboden",
    "sg:classifiers":[
        {
            "category":"Utilities",
            "subcategory":"Electric",
            "type":"Services"
        }
    ],
    "sg:phone":"+1 870 892 8766",
    "sg:postcode":"72434",
    "sg:province":"AR",
    "wof:name":"T&J Contractors Inc",
    "wof:placetype":"venue"
},
  "geometry": {"coordinates":[-91.113128,36.311366],"type":"Point"}
}