{
  "type": "Feature",
  "properties": {
    "addr:full":"803 N Spruce St Harrison AR 72601",
    "addr:housenumber":"803",
    "addr:postcode":"72601",
    "addr:street":"N Spruce St",
    "iso:country":"US",
    "sg:address":"803 N Spruce St",
    "sg:city":"Harrison",
    "sg:classifiers":[
        {
            "category":"Organizations",
            "subcategory":"Religious Organization",
            "type":"Services"
        }
    ],
    "sg:phone":"+1 870 741 2422",
    "sg:postcode":"72601",
    "sg:province":"AR",
    "sg:tags":[
        "church"
    ],
    "wof:name":"Calvary Baptist Church",
    "wof:placetype":"venue"
},
  "geometry": {"coordinates":[-93.11549599999999,36.237349],"type":"Point"}
}