{
  "type": "Feature",
  "properties": {
    "iso:country":"US",
    "sg:address":"3339 Central Ave",
    "sg:city":"Hot Springs",
    "sg:classifiers":[
        {
            "category":"Personal",
            "subcategory":"Tanning Parlor",
            "type":"Services"
        }
    ],
    "sg:phone":"+1 501 318 2900",
    "sg:postcode":"71913",
    "sg:province":"AR",
    "sg:tags":[
        "salon"
    ],
    "wof:name":"24/7 Tanning",
    "wof:placetype":"venue"
},
  "geometry": {"coordinates":[-93.059769,34.475209],"type":"Point"}
}