{
  "type": "Feature",
  "properties": {
    "addr:full":"803 W 1st Ave Crossett AR 71635",
    "addr:housenumber":"803",
    "addr:postcode":"71635",
    "addr:street":"W 1St Ave",
    "iso:country":"US",
    "sg:address":"803 W 1st Ave",
    "sg:city":"Crossett",
    "sg:classifiers":[
        {
            "category":"Manufacturing",
            "subcategory":"Buildings",
            "type":"Manufacturing & Wholesale Goods"
        },
        {
            "category":"Home & Garden",
            "subcategory":"Building Materials",
            "type":"Retail Goods"
        },
        {
            "category":"Building & Trades",
            "subcategory":"Construction",
            "type":"Services"
        }
    ],
    "sg:phone":"+1 870 364 4185",
    "sg:postcode":"71635",
    "sg:province":"AR",
    "sg:tags":[
        "industrial",
        "specialty",
        "builder",
        "system",
        "heating",
        "contractors-commercial",
        "contractor",
        "air conditioning",
        "road"
    ],
    "wof:name":"Ideal Construction Company",
    "wof:placetype":"venue"
},
  "geometry": {"coordinates":[-91.971121,33.135262],"type":"Point"}
}