{
  "type": "Feature",
  "properties": {
    "addr:full":"60 Bledsoe Rd Lc823 Lonoke AR 72086",
    "addr:housenumber":"60",
    "addr:postcode":"72086",
    "addr:street":"Bledsoe Rd",
    "iso:country":"US",
    "sg:address":"60 Bledsoe Rd Lc823",
    "sg:city":"Lonoke",
    "sg:classifiers":[
        {
            "category":"Real Estate",
            "subcategory":"Real Estate Services",
            "type":"Services"
        },
        {
            "category":"Real Estate",
            "subcategory":"Real Estate Agent",
            "type":"Services"
        }
    ],
    "sg:phone":"+1 501 676 3484",
    "sg:postcode":"72086",
    "sg:province":"AR",
    "sg:tags":[
        "management"
    ],
    "wof:name":"Globe Real Estate And Appraisals",
    "wof:placetype":"venue"
},
  "geometry": {"coordinates":[-91.930532,34.690452],"type":"Point"}
}