{
  "type": "Feature",
  "properties": {
    "addr:full":"26807 Goodson Rd Roland AR 72135",
    "addr:housenumber":"26807",
    "addr:postcode":"72135",
    "addr:street":"Goodson Rd Roland",
    "iso:country":"US",
    "sg:address":"26807 Goodson Rd",
    "sg:city":"Roland",
    "sg:classifiers":[
        {
            "category":"Recreation",
            "type":"Entertainment"
        },
        {
            "category":"Retail",
            "subcategory":"Animal Services",
            "type":"Services"
        }
    ],
    "sg:phone":"+1 501 868 7297",
    "sg:postcode":"72135",
    "sg:province":"AR",
    "sg:tags":[
        "pet",
        "boarding",
        "membership",
        "club",
        "sitting"
    ],
    "wof:name":"Canine Country Club Arkansas",
    "wof:placetype":"venue"
},
  "geometry": {"coordinates":[-92.559876,34.839106],"type":"Point"}
}