{
  "type": "Feature",
  "properties": {
    "iso:country":"US",
    "sg:address":"10014 N Rodney Parham Rd",
    "sg:city":"Little Rock",
    "sg:classifiers":[
        {
            "category":"Restaurant",
            "type":"Food & Drink"
        }
    ],
    "sg:phone":"+1 501 225 3030",
    "sg:postcode":"72227",
    "sg:province":"AR",
    "sg:tags":[
        "pizza"
    ],
    "wof:name":"Dominos Pizza",
    "wof:placetype":"venue"
},
  "geometry": {"coordinates":[-92.386708,34.766061],"type":"Point"}
}