{
  "type": "Feature",
  "properties": {
    "iso:country":"US",
    "sg:address":"760 Pierce St",
    "sg:city":"Camden",
    "sg:classifiers":[
        {
            "category":"Social Services",
            "subcategory":"Child Care",
            "type":"Services"
        }
    ],
    "sg:phone":"+1 870 231 4148",
    "sg:postcode":"71701",
    "sg:province":"AR",
    "sg:tags":[
        "day"
    ],
    "wof:name":"Rocking Horse Day Care Home",
    "wof:placetype":"venue"
},
  "geometry": {"coordinates":[-92.84187,33.545789],"type":"Point"}
}