{
  "type": "Feature",
  "properties": {
    "iso:country":"US",
    "sg:address":"3906 Kelley Ave",
    "sg:city":"Springdale",
    "sg:classifiers":[
        {
            "category":"Health Services",
            "subcategory":"Health Practitioner",
            "type":"Services"
        }
    ],
    "sg:phone":"+1 479 750 1413",
    "sg:postcode":"72762",
    "sg:province":"AR",
    "sg:tags":[
        "specialty",
        "outpatient"
    ],
    "wof:name":"HealthSouth",
    "wof:placetype":"venue"
},
  "geometry": {"coordinates":[-94.173468,36.177961],"type":"Point"}
}