{
  "type": "Feature",
  "properties": {
    "iso:country":"US",
    "sg:address":"1488 Harrison St",
    "sg:city":"Batesville",
    "sg:classifiers":[
        {
            "category":"Autos & Motor Vehicles",
            "subcategory":"Auto Supplies",
            "type":"Retail Goods"
        }
    ],
    "sg:phone":"+1 870 793 5527",
    "sg:postcode":"72501",
    "sg:province":"AR",
    "sg:tags":[
        "automobile",
        "parts"
    ],
    "wof:name":"O'REILLY Auto Parts",
    "wof:placetype":"venue"
},
  "geometry": {"coordinates":[-91.638422,35.769556],"type":"Point"}
}