{
  "type": "Feature",
  "properties": {
    "addr:full":"1106 Walnut St Van Buren AR 72956",
    "addr:housenumber":"1106",
    "addr:postcode":"72956",
    "addr:street":"Walnut St",
    "iso:country":"US",
    "sg:address":"1106 Walnut St",
    "sg:city":"Van Buren",
    "sg:classifiers":[
        {
            "category":"Professional",
            "subcategory":"Computer Services",
            "type":"Services"
        }
    ],
    "sg:phone":"+1 479 471 5555",
    "sg:postcode":"72956",
    "sg:province":"AR",
    "wof:name":"Decisionone",
    "wof:placetype":"venue"
},
  "geometry": {"coordinates":[-94.347092,35.435623],"type":"Point"}
}