{
  "type": "Feature",
  "properties": {
    "addr:full":"224 N Barrington Rd Springdale AR 72762",
    "addr:housenumber":"224",
    "addr:postcode":"72762",
    "addr:street":"N Barrington Rd",
    "iso:country":"US",
    "sg:address":"224 N Barrington Rd",
    "sg:city":"Springdale",
    "sg:classifiers":[
        {
            "category":"Professional",
            "subcategory":"Business Services",
            "type":"Services"
        },
        {
            "category":"Government",
            "subcategory":"Post Office",
            "type":"Public Place"
        }
    ],
    "sg:phone":"+1 479 361 2386",
    "sg:postcode":"72762",
    "sg:province":"AR",
    "sg:tags":[
        "mail",
        "shipping"
    ],
    "sg:website":"http://www.usps.com",
    "wof:name":"Us Post Office",
    "wof:placetype":"venue"
},
  "geometry": {"coordinates":[-94.23483,36.178697],"type":"Point"}
}