{
  "type": "Feature",
  "properties": {
    "addr:full":"8601 Hwy 67 Benton AR 72015",
    "addr:housenumber":"8601",
    "addr:postcode":"72015",
    "addr:street":"Hwy 67",
    "iso:country":"US",
    "sg:address":"8601 Hwy 67",
    "sg:city":"Benton",
    "sg:classifiers":[
        {
            "category":"Organizations",
            "subcategory":"Religious Organization",
            "type":"Services"
        }
    ],
    "sg:phone":"+1 501 778 1295",
    "sg:postcode":"72015",
    "sg:province":"AR",
    "sg:tags":[
        "church"
    ],
    "wof:name":"Temple Baptist Church",
    "wof:placetype":"venue"
},
  "geometry": {"coordinates":[-92.66661999999999,34.518046],"type":"Point"}
}