{
  "type": "Feature",
  "properties": {
    "iso:country":"US",
    "sg:address":"105 Library Rd",
    "sg:city":"Dover",
    "sg:classifiers":[
        {
            "category":"Professional",
            "subcategory":"Advertising",
            "type":"Services"
        }
    ],
    "sg:phone":"+1 479 331 3383",
    "sg:postcode":"72837",
    "sg:province":"AR",
    "sg:tags":[
        "counselor"
    ],
    "sg:website":"www.lmistudios.com",
    "wof:name":"LMI Studios/Logomotion Inc",
    "wof:placetype":"venue"
},
  "geometry": {"coordinates":[-93.108643,35.391353],"type":"Point"}
}