{
  "type": "Feature",
  "properties": {
    "iso:country":"US",
    "sg:address":"708 N Bayou Dr",
    "sg:city":"Mountain View",
    "sg:classifiers":[
        {
            "category":"Organizations",
            "subcategory":"Non-profit Organization",
            "type":"Services"
        },
        {
            "category":"Social Services",
            "type":"Services"
        }
    ],
    "sg:phone":"+1 870 269 5566",
    "sg:postcode":"72560",
    "sg:province":"AR",
    "sg:tags":[
        "disability"
    ],
    "wof:name":"Friendship Community Care",
    "wof:placetype":"venue"
},
  "geometry": {"coordinates":[-92.10259499999999,35.875327],"type":"Point"}
}