{
  "type": "Feature",
  "properties": {
    "iso:country":"US",
    "sg:address":"12613 I- 30",
    "sg:city":"Benton",
    "sg:classifiers":[
        {
            "category":"Organizations",
            "subcategory":"Religious Organization",
            "type":"Services"
        }
    ],
    "sg:phone":"+1 501 315 3876",
    "sg:postcode":"72015",
    "sg:province":"AR",
    "sg:tags":[
        "church"
    ],
    "wof:name":"Bible Missionary Chr Parsonage",
    "wof:placetype":"venue"
},
  "geometry": {"coordinates":[-92.644276,34.540936],"type":"Point"}
}