{
  "type": "Feature",
  "properties": {
    "iso:country":"US",
    "sg:address":"410 Choctaw Lndg",
    "sg:city":"Clinton",
    "sg:classifiers":[
        {
            "category":"Building & Trades",
            "subcategory":"Plumbing",
            "type":"Services"
        }
    ],
    "sg:phone":"+1 501 745 5700",
    "sg:postcode":"72031",
    "sg:province":"AR",
    "sg:tags":[
        "mechanical",
        "contractor"
    ],
    "wof:name":"Bates Mechanical Svc",
    "wof:placetype":"venue"
},
  "geometry": {"coordinates":[-92.371643,35.535695],"type":"Point"}
}