{
  "type": "Feature",
  "properties": {
    "iso:country":"US",
    "sg:address":"1205 S Hervey St",
    "sg:city":"Hope",
    "sg:classifiers":[
        {
            "category":"Shopping",
            "subcategory":"Catalog Store",
            "type":"Retail Goods"
        }
    ],
    "sg:phone":"+1 870 777 3442",
    "sg:postcode":"71801",
    "sg:province":"AR",
    "sg:tags":[
        "mail",
        "house"
    ],
    "wof:name":"JC Penney",
    "wof:placetype":"venue"
},
  "geometry": {"coordinates":[-93.593373,33.657408],"type":"Point"}
}