{
  "type": "Feature",
  "properties": {
    "iso:country":"US",
    "sg:address":"2004 Mccartney Camp Rd",
    "sg:city":"Greenwood",
    "sg:classifiers":[
        {
            "category":"Building & Trades",
            "subcategory":"Construction",
            "type":"Services"
        }
    ],
    "sg:phone":"+1 479 597 0062",
    "sg:postcode":"72936",
    "sg:province":"AR",
    "sg:tags":[
        "consultant",
        "industrial",
        "contractors-commercial"
    ],
    "wof:name":"J&J Construction",
    "wof:placetype":"venue"
},
  "geometry": {"coordinates":[-94.08757900000001,35.18218],"type":"Point"}
}