{
  "type": "Feature",
  "properties": {
    "iso:country":"US",
    "sg:address":"5864 Highway 9 N",
    "sg:city":"Camp",
    "sg:classifiers":[
        {
            "category":"Personal",
            "type":"Services"
        },
        {
            "category":"Retail",
            "subcategory":"Auto Repair",
            "type":"Services"
        }
    ],
    "sg:phone":"+1 870 895 4490",
    "sg:postcode":"72520",
    "sg:province":"AR",
    "sg:tags":[
        "towing",
        "road",
        "service-automotive"
    ],
    "wof:name":"Raines Towing",
    "wof:placetype":"venue"
},
  "geometry": {"coordinates":[-91.734359,36.413717],"type":"Point"}
}