{
  "type": "Feature",
  "properties": {
    "iso:country":"US",
    "sg:address":"1411 Country Club Rd",
    "sg:city":"Camden",
    "sg:classifiers":[
        {
            "category":"Health Services",
            "subcategory":"Clinic",
            "type":"Services"
        },
        {
            "category":"Building & Trades",
            "subcategory":"Landscaping Services",
            "type":"Services"
        },
        {
            "category":"Social Services",
            "subcategory":"Job Training",
            "type":"Services"
        },
        {
            "category":"Social Services",
            "subcategory":"Retirement Home",
            "type":"Services"
        },
        {
            "category":"Health Services",
            "subcategory":"Health Practitioner",
            "type":"Services"
        },
        {
            "category":"Social Services",
            "subcategory":"Adult Care",
            "type":"Services"
        }
    ],
    "sg:phone":"+1 870 836 4111",
    "sg:postcode":"71701",
    "sg:province":"AR",
    "sg:tags":[
        "nurses-home",
        "nursing",
        "homes-skilled",
        "facility",
        "addiction-information",
        "convalescent",
        "homes-institutional",
        "gambling",
        "aged",
        "rehabilitation",
        "treatment"
    ],
    "sg:website":"http://www.yorktownnursing.com",
    "wof:name":"Ouachita Nursing & Rehab Center",
    "wof:placetype":"venue"
},
  "geometry": {"coordinates":[-92.855444,33.575745],"type":"Point"}
}