{
  "type": "Feature",
  "properties": {
    "iso:country":"US",
    "sg:address":"105 Mark Ln",
    "sg:city":"Searcy",
    "sg:classifiers":[
        {
            "category":"Building & Trades",
            "subcategory":"Plumbing",
            "type":"Services"
        }
    ],
    "sg:phone":"+1 501 279 9415",
    "sg:postcode":"72143",
    "sg:province":"AR",
    "sg:tags":[
        "contractor"
    ],
    "wof:name":"Able Plumbing",
    "wof:placetype":"venue"
},
  "geometry": {"coordinates":[-91.806602,35.234082],"type":"Point"}
}