{
  "type": "Feature",
  "properties": {
    "addr:full":"6719 Alcoa Rd Benton AR 72015",
    "addr:housenumber":"6719",
    "addr:postcode":"72015",
    "addr:street":"Alcoa Rd",
    "iso:country":"US",
    "sg:address":"6719 Alcoa Rd",
    "sg:city":"Benton",
    "sg:classifiers":[
        {
            "category":"Manufacturing",
            "subcategory":"Electronics",
            "type":"Manufacturing & Wholesale Goods"
        },
        {
            "category":"Building & Trades",
            "subcategory":"Electrical",
            "type":"Services"
        }
    ],
    "sg:phone":"+1 501 565 0404",
    "sg:postcode":"72015",
    "sg:province":"AR",
    "sg:tags":[
        "control",
        "regulator",
        "robotics",
        "system",
        "controls"
    ],
    "sg:website":"http://www.rencocontrols.com",
    "wof:name":"Renco Inc",
    "wof:placetype":"venue"
},
  "geometry": {"coordinates":[-92.534538,34.597011],"type":"Point"}
}