{
  "type": "Feature",
  "properties": {
    "addr:full":"224 N Rosser St Forrest City AR 72335",
    "addr:housenumber":"224",
    "addr:postcode":"72335",
    "addr:street":"N Rosser St",
    "iso:country":"US",
    "sg:address":"224 N Rosser St",
    "sg:city":"Forrest City",
    "sg:classifiers":[
        {
            "category":"Government",
            "subcategory":"Office",
            "type":"Public Place"
        }
    ],
    "sg:phone":"+1 870 633 1315",
    "sg:postcode":"72335",
    "sg:province":"AR",
    "sg:tags":[
        "village"
    ],
    "wof:name":"Forrest City Mosquito Control",
    "wof:placetype":"venue"
},
  "geometry": {"coordinates":[-90.786918,35.010484],"type":"Point"}
}