{
  "type": "Feature",
  "properties": {
    "iso:country":"US",
    "sg:address":"2734 Miller Rd",
    "sg:city":"Lonoke",
    "sg:classifiers":[
        {
            "category":"Real Estate",
            "subcategory":"Architect",
            "type":"Services"
        }
    ],
    "sg:phone":"+1 501 847 6968",
    "sg:postcode":"72086",
    "sg:province":"AR",
    "wof:name":"Bartlett Architecture",
    "wof:placetype":"venue"
},
  "geometry": {"coordinates":[-91.861469,34.762361],"type":"Point"}
}