{
  "type": "Feature",
  "properties": {
    "addr:full":"108 N State St Newport AR 72112",
    "addr:housenumber":"108",
    "addr:postcode":"72112",
    "addr:street":"N State St",
    "iso:country":"US",
    "sg:address":"108 N State St",
    "sg:city":"Newport",
    "sg:classifiers":[
        {
            "category":"Manufacturing",
            "subcategory":"Metals",
            "type":"Manufacturing & Wholesale Goods"
        }
    ],
    "sg:phone":"+1 870 523 5261",
    "sg:postcode":"72112",
    "sg:province":"AR",
    "sg:tags":[
        "fabricator",
        "sheet"
    ],
    "wof:name":"Newport Sheet Metal Inc",
    "wof:placetype":"venue"
},
  "geometry": {"coordinates":[-91.259924,35.606218],"type":"Point"}
}