{
  "type": "Feature",
  "properties": {
    "addr:full":"2369 Ivey Ln Springdale AR 72764",
    "addr:housenumber":"2369",
    "addr:postcode":"72764",
    "addr:street":"Ivey Ln",
    "iso:country":"US",
    "sg:address":"2369 Ivey Ln",
    "sg:city":"Springdale",
    "sg:classifiers":[
        {
            "category":"Retail",
            "subcategory":"Portrait Studio",
            "type":"Services"
        }
    ],
    "sg:phone":"+1 479 582 3686",
    "sg:postcode":"72764",
    "sg:province":"AR",
    "sg:tags":[
        "photo",
        "photographers-portrait"
    ],
    "wof:name":"Raspberry Pond Reflections",
    "wof:placetype":"venue"
},
  "geometry": {"coordinates":[-94.104529,36.14852],"type":"Point"}
}