{
  "type": "Feature",
  "properties": {
    "iso:country":"US",
    "sg:address":"12309 Locust Mountain Bend",
    "sg:city":"Mountainburg",
    "sg:classifiers":[
        {
            "category":"Retail",
            "subcategory":"Auto Repair",
            "type":"Services"
        }
    ],
    "sg:phone":"+1 479 369 4241",
    "sg:postcode":"72946",
    "sg:province":"AR",
    "sg:tags":[
        "automotive"
    ],
    "wof:name":"Earl Sindle Wrecker",
    "wof:placetype":"venue"
},
  "geometry": {"coordinates":[-94.204413,35.611975],"type":"Point"}
}