{
  "type": "Feature",
  "properties": {
    "iso:country":"US",
    "sg:address":"1301 Military Rd",
    "sg:city":"Benton",
    "sg:classifiers":[
        {
            "category":"Autos & Motor Vehicles",
            "subcategory":"Automobile Sales",
            "type":"Retail Goods"
        }
    ],
    "sg:phone":"+1 501 778 0319",
    "sg:postcode":"72015",
    "sg:province":"AR",
    "sg:tags":[
        "car",
        "dealer"
    ],
    "sg:website":"www.carmart.com",
    "wof:name":"Car Mart",
    "wof:placetype":"venue"
},
  "geometry": {"coordinates":[-92.577541,34.576114],"type":"Point"}
}