{
  "type": "Feature",
  "properties": {
    "iso:country":"US",
    "sg:address":"444 Hedgepath Rd",
    "sg:city":"Russellville",
    "sg:classifiers":[
        {
            "category":"Manufacturing",
            "subcategory":"Buildings",
            "type":"Manufacturing & Wholesale Goods"
        },
        {
            "category":"Building & Trades",
            "subcategory":"Construction",
            "type":"Services"
        }
    ],
    "sg:phone":"+1 479 968 1149",
    "sg:postcode":"72802",
    "sg:province":"AR",
    "sg:tags":[
        "industrial",
        "asphalt",
        "contractors-commercial",
        "builder",
        "specialty",
        "system",
        "sealcoating",
        "heating",
        "contractor",
        "home",
        "air conditioning",
        "road",
        "paving"
    ],
    "wof:name":"Blackstone Construction",
    "wof:placetype":"venue"
},
  "geometry": {"coordinates":[-93.099177,35.237189],"type":"Point"}
}