{
  "type": "Feature",
  "properties": {
    "iso:country":"US",
    "sg:address":"1508 Bugscuffle Rd",
    "sg:city":"Lavaca",
    "sg:classifiers":[
        {
            "category":"Wholesale",
            "subcategory":"Machinery & Supplies",
            "type":"Manufacturing & Wholesale Goods"
        }
    ],
    "sg:phone":"+1 479 674 2754",
    "sg:postcode":"72941",
    "sg:province":"AR",
    "sg:tags":[
        "burial",
        "vault"
    ],
    "wof:name":"Lavaca Vault Co",
    "wof:placetype":"venue"
},
  "geometry": {"coordinates":[-94.202573,35.348582],"type":"Point"}
}