{
  "type": "Feature",
  "properties": {
    "iso:country":"US",
    "sg:address":"3216 E Walnut St",
    "sg:city":"Paris",
    "sg:classifiers":[
        {
            "category":"Building & Trades",
            "subcategory":"Cleaning & Sanitation",
            "type":"Services"
        }
    ],
    "sg:phone":"+1 479 963 6548",
    "sg:postcode":"72855",
    "sg:province":"AR",
    "sg:tags":[
        "maintenance"
    ],
    "wof:name":"Amazon Designs",
    "wof:placetype":"venue"
},
  "geometry": {"coordinates":[-93.690209,35.294791],"type":"Point"}
}