{
  "type": "Feature",
  "properties": {
    "addr:full":"3339 Central Ave Hot Springs AR 71913",
    "addr:housenumber":"3339",
    "addr:postcode":"71913",
    "addr:street":"Central Ave",
    "iso:country":"US",
    "sg:address":"3339 Central Ave",
    "sg:city":"Hot Springs",
    "sg:classifiers":[
        {
            "category":"Personal",
            "subcategory":"Beauty Salon",
            "type":"Services"
        }
    ],
    "sg:phone":"+1 501 624 1413",
    "sg:postcode":"71913",
    "sg:province":"AR",
    "sg:tags":[
        "shop",
        "manicuring"
    ],
    "wof:name":"Fancy Nails",
    "wof:placetype":"venue"
},
  "geometry": {"coordinates":[-93.059769,34.475209],"type":"Point"}
}