{
  "type": "Feature",
  "properties": {
    "iso:country":"US",
    "sg:address":"208 S Rockwood Dr",
    "sg:city":"Cabot",
    "sg:classifiers":[
        {
            "category":"Food & Beverages",
            "subcategory":"Groceries & Convenience Stores",
            "type":"Retail Goods"
        }
    ],
    "sg:phone":"+1 501 843 1533",
    "sg:postcode":"72023",
    "sg:province":"AR",
    "sg:website":"www.flashmarketinc.com",
    "wof:name":"Flash Market",
    "wof:placetype":"venue"
},
  "geometry": {"coordinates":[-92.037374,34.978795],"type":"Point"}
}