{
  "type": "Feature",
  "properties": {
    "iso:country":"US",
    "sg:address":"3 Nugget Ct",
    "sg:city":"North Little Rock",
    "sg:classifiers":[
        {
            "category":"Professional",
            "subcategory":"Computer Services",
            "type":"Services"
        }
    ],
    "sg:phone":"+1 501 771 4194",
    "sg:postcode":"72118",
    "sg:province":"AR",
    "sg:tags":[
        "consulting",
        "network"
    ],
    "wof:name":"Infinite Technologies",
    "wof:placetype":"venue"
},
  "geometry": {"coordinates":[-92.338245,34.811054],"type":"Point"}
}