{
  "type": "Feature",
  "properties": {
    "iso:country":"US",
    "sg:address":"675 Peninsula Dr",
    "sg:city":"Hot Springs National",
    "sg:classifiers":[
        {
            "category":"Organizations",
            "subcategory":"Religious Organization",
            "type":"Services"
        }
    ],
    "sg:phone":"+1 501 262 5165",
    "sg:postcode":"71901",
    "sg:province":"AR",
    "wof:name":"3d Success",
    "wof:placetype":"venue"
},
  "geometry": {"coordinates":[-93.049398,34.445915],"type":"Point"}
}