{
  "type": "Feature",
  "properties": {
    "iso:country":"US",
    "sg:address":"620 Ferry St",
    "sg:city":"Little Rock",
    "sg:classifiers":[
        {
            "category":"Professional",
            "subcategory":"Lawyer & Legal Services",
            "type":"Services"
        }
    ],
    "sg:phone":"+1 501 375 3307",
    "sg:postcode":"72202",
    "sg:province":"AR",
    "sg:tags":[
        "attorney"
    ],
    "wof:name":"King Law Firm",
    "wof:placetype":"venue"
},
  "geometry": {"coordinates":[-92.264198,34.741362],"type":"Point"}
}