{
  "type": "Feature",
  "properties": {
    "addr:full":"620 Ferry St Little Rock AR 72202",
    "addr:housenumber":"620",
    "addr:postcode":"72202",
    "addr:street":"Ferry St",
    "iso:country":"US",
    "sg:address":"620 Ferry St",
    "sg:city":"Little Rock",
    "sg:classifiers":[
        {
            "category":"Professional",
            "subcategory":"Lawyer & Legal Services",
            "type":"Services"
        }
    ],
    "sg:phone":"+1 501 375 3307",
    "sg:postcode":"72202",
    "sg:province":"AR",
    "sg:tags":[
        "attorney"
    ],
    "wof:name":"King Law Firm",
    "wof:placetype":"venue"
},
  "geometry": {"coordinates":[-92.26419799999999,34.741362],"type":"Point"}
}