{
  "type": "Feature",
  "properties": {
    "iso:country":"US",
    "sg:address":"270 Cabin Hill Trl",
    "sg:city":"Gamaliel",
    "sg:classifiers":[
        {
            "category":"Professional",
            "subcategory":"Accounting & Tax Preparation",
            "type":"Services"
        }
    ],
    "sg:phone":"+1 870 467 5704",
    "sg:postcode":"72537",
    "sg:province":"AR",
    "wof:name":"Susan Schneider CPA",
    "wof:placetype":"venue"
},
  "geometry": {"coordinates":[-92.23421399999999,36.48013],"type":"Point"}
}