{
  "type": "Feature",
  "properties": {
    "iso:country":"US",
    "sg:address":"25825 I- 30",
    "sg:city":"Alexander",
    "sg:classifiers":[
        {
            "category":"Autos & Motor Vehicles",
            "subcategory":"Automobile Sales",
            "type":"Retail Goods"
        }
    ],
    "sg:phone":"+1 501 315 7007",
    "sg:postcode":"72022",
    "sg:province":"AR",
    "sg:tags":[
        "used"
    ],
    "wof:name":"Mid South Auto Brokers Inc",
    "wof:placetype":"venue"
},
  "geometry": {"coordinates":[-92.450998,34.638342],"type":"Point"}
}