{
  "type": "Feature",
  "properties": {
    "iso:country":"US",
    "sg:address":"308 E Main",
    "sg:city":"Waldo",
    "sg:classifiers":[
        {
            "category":"Government",
            "subcategory":"Office",
            "type":"Public Place"
        }
    ],
    "sg:phone":"+1 870 693 2198",
    "sg:postcode":"71770",
    "sg:province":"AR",
    "sg:tags":[
        "city"
    ],
    "wof:name":"Waldo City Hall",
    "wof:placetype":"venue"
},
  "geometry": {"coordinates":[-93.29305,33.353028],"type":"Point"}
}