{
  "type": "Feature",
  "properties": {
    "iso:country":"US",
    "sg:address":"1007 W 1st Ave",
    "sg:city":"Crossett",
    "sg:classifiers":[
        {
            "category":"Wholesale",
            "subcategory":"Hardware",
            "type":"Manufacturing & Wholesale Goods"
        },
        {
            "category":"Home & Garden",
            "subcategory":"Garden Supply",
            "type":"Retail Goods"
        },
        {
            "category":"Retail",
            "subcategory":"Repair Shop",
            "type":"Services"
        }
    ],
    "sg:phone":"+1 870 364 4888",
    "sg:postcode":"71635",
    "sg:province":"AR",
    "sg:tags":[
        "renting",
        "lawn",
        "outdoor",
        "power",
        "landscaping",
        "equipment-sales",
        "equipment",
        "saw"
    ],
    "sg:website":"http://www.stihldealer.net/default-dealer-011035.aspx",
    "wof:name":"Crossett Marine Sales and Service",
    "wof:placetype":"venue"
},
  "geometry": {"coordinates":[-91.973837,33.13525],"type":"Point"}
}