{
  "type": "Feature",
  "properties": {
    "iso:country":"US",
    "sg:address":"1314 Green",
    "sg:city":"Benton",
    "sg:classifiers":[
        {
            "category":"Professional",
            "type":"Services"
        },
        {
            "category":"Restaurant",
            "type":"Food & Drink"
        },
        {
            "category":"Fast Food",
            "type":"Food & Drink"
        }
    ],
    "sg:phone":"+1 501 315 6800",
    "sg:postcode":"72015",
    "sg:province":"AR",
    "sg:tags":[
        "italian",
        "take",
        "caterer"
    ],
    "wof:name":"Pasta Jack's",
    "wof:placetype":"venue"
},
  "geometry": {"coordinates":[-92.572254,34.57959],"type":"Point"}
}