{
  "type": "Feature",
  "properties": {
    "iso:country":"US",
    "sg:address":"90 Taylor Rd",
    "sg:city":"Rison",
    "sg:classifiers":[
        {
            "category":"Freight",
            "type":"Transportation"
        }
    ],
    "sg:phone":"+1 870 357 2202",
    "sg:postcode":"71665",
    "sg:province":"AR",
    "sg:tags":[
        "local",
        "trucking"
    ],
    "wof:name":"Taylor Trucking",
    "wof:placetype":"venue"
},
  "geometry": {"coordinates":[-91.985103,33.791844],"type":"Point"}
}