{
  "type": "Feature",
  "properties": {
    "addr:full":"10680 Carter Cove Rd Plainview AR 72857",
    "addr:housenumber":"10680",
    "addr:postcode":"72857",
    "addr:street":"Carter Cove Rd",
    "iso:country":"US",
    "sg:address":"10680 Carter Cove Rd",
    "sg:city":"Plainview",
    "sg:classifiers":[
        {
            "category":"Recreation",
            "subcategory":"Campground",
            "type":"Entertainment"
        }
    ],
    "sg:phone":"+1 334 559 1613",
    "sg:postcode":"72857",
    "sg:province":"AR",
    "sg:tags":[
        "recreational",
        "park",
        "vehicle"
    ],
    "wof:name":"Little Rock District Core Of Engineers",
    "wof:placetype":"venue"
},
  "geometry": {"coordinates":[-93.239385,34.963549],"type":"Point"}
}