{
  "type": "Feature",
  "properties": {
    "iso:country":"US",
    "sg:address":"1170 Mill Creek Dr",
    "sg:city":"Russellville",
    "sg:classifiers":[
        {
            "category":"Retail",
            "subcategory":"Repair Shop",
            "type":"Services"
        }
    ],
    "sg:phone":"+1 479 967 3224",
    "sg:postcode":"72847",
    "sg:province":"AR",
    "sg:tags":[
        "electrical"
    ],
    "wof:name":"Tonys Appliance Service",
    "wof:placetype":"venue"
},
  "geometry": {"coordinates":[-93.232028,35.358451],"type":"Point"}
}