{
  "type": "Feature",
  "properties": {
    "iso:country":"US",
    "sg:address":"313 Oak Ave",
    "sg:city":"Mountain View",
    "sg:classifiers":[
        {
            "category":"Retail",
            "subcategory":"Auto Repair",
            "type":"Services"
        }
    ],
    "sg:phone":"+1 870 269 3933",
    "sg:postcode":"72560",
    "sg:province":"AR",
    "sg:tags":[
        "repairing",
        "automobile"
    ],
    "wof:name":"Paul's Automotive",
    "wof:placetype":"venue"
},
  "geometry": {"coordinates":[-92.113636,35.869713],"type":"Point"}
}