{
  "type": "Feature",
  "properties": {
    "iso:country":"US",
    "sg:address":"1847 E Highland Dr",
    "sg:city":"Jonesboro",
    "sg:classifiers":[
        {
            "category":"Shopping",
            "subcategory":"Shoes",
            "type":"Retail Goods"
        }
    ],
    "sg:phone":"+1 870 972 8656",
    "sg:postcode":"72401",
    "sg:province":"AR",
    "sg:website":"www.shoecarnival.com",
    "wof:name":"Shoe Carnival Inc",
    "wof:placetype":"venue"
},
  "geometry": {"coordinates":[-90.686071,35.821152],"type":"Point"}
}