{
  "type": "Feature",
  "properties": {
    "iso:country":"US",
    "sg:address":"80 Columbia Road 49",
    "sg:city":"Stephens",
    "sg:classifiers":[
        {
            "category":"Shopping",
            "subcategory":"Bicycles & Sporting Goods",
            "type":"Retail Goods"
        }
    ],
    "sg:phone":"+1 870 596 2623",
    "sg:postcode":"71764",
    "sg:province":"AR",
    "sg:tags":[
        "equipment",
        "camping"
    ],
    "wof:name":"Jack's Outdoor Products",
    "wof:placetype":"venue"
},
  "geometry": {"coordinates":[-93.049925,33.305149],"type":"Point"}
}