{
  "type": "Feature",
  "properties": {
    "iso:country":"US",
    "sg:address":"113 W Gaines St",
    "sg:city":"Monticello",
    "sg:classifiers":[
        {
            "category":"Restaurant",
            "type":"Food & Drink"
        }
    ],
    "sg:phone":"+1 870 367 1800",
    "sg:postcode":"71655",
    "sg:province":"AR",
    "wof:name":"Beth's Bistro",
    "wof:placetype":"venue"
},
  "geometry": {"coordinates":[-91.791211,33.629039],"type":"Point"}
}