{
  "type": "Feature",
  "properties": {
    "iso:country":"US",
    "sg:address":"1101 E 3rd St",
    "sg:city":"Grove",
    "sg:classifiers":[
        {
            "category":"Wholesale",
            "subcategory":"Hardware",
            "type":"Manufacturing & Wholesale Goods"
        }
    ],
    "sg:phone":"+1 918 786 2201",
    "sg:postcode":"74344",
    "sg:province":"OK",
    "sg:tags":[
        "plumbing",
        "fixture",
        "supply"
    ],
    "wof:name":"Grove-Winnelson Co",
    "wof:placetype":"venue"
},
  "geometry": {"coordinates":[-94.756818,36.595434],"type":"Point"}
}