{
  "type": "Feature",
  "properties": {
    "iso:country":"US",
    "sg:address":"8201 Sanderson Ln",
    "sg:city":"Texarkana",
    "sg:classifiers":[
        {
            "category":"Building & Trades",
            "subcategory":"Construction",
            "type":"Services"
        }
    ],
    "sg:phone":"+1 870 772 4835",
    "sg:postcode":"71854",
    "sg:province":"AR",
    "sg:tags":[
        "excavating",
        "contractor"
    ],
    "wof:name":"Heritage Constructors Inc",
    "wof:placetype":"venue"
},
  "geometry": {"coordinates":[-94.011018,33.498162],"type":"Point"}
}