{
  "type": "Feature",
  "properties": {
    "iso:country":"US",
    "sg:address":"9019 Barber St",
    "sg:city":"Sherwood",
    "sg:classifiers":[
        {
            "category":"Autos & Motor Vehicles",
            "subcategory":"Auto Supplies",
            "type":"Retail Goods"
        }
    ],
    "sg:phone":"+1 501 835 2220",
    "sg:postcode":"72120",
    "sg:province":"AR",
    "sg:tags":[
        "automobile",
        "parts",
        "accessory",
        "part",
        "accessories-wholesale",
        "manufacturer"
    ],
    "wof:name":"Pro Auto Parts Of Arkansas",
    "wof:placetype":"venue"
},
  "geometry": {"coordinates":[-92.224573,34.836806],"type":"Point"}
}