{
  "type": "Feature",
  "properties": {
    "addr:full":"120 E Monroe Ave Lowell AR 72745",
    "addr:housenumber":"120",
    "addr:postcode":"72745",
    "addr:street":"E Monroe Ave",
    "iso:country":"US",
    "sg:address":"120 E Monroe Ave",
    "sg:city":"Lowell",
    "sg:classifiers":[
        {
            "category":"Building & Trades",
            "subcategory":"Equipment Rental",
            "type":"Services"
        }
    ],
    "sg:phone":"+1 479 750 4496",
    "sg:postcode":"72745",
    "sg:province":"AR",
    "sg:tags":[
        "moving",
        "supply"
    ],
    "wof:name":"U-Haul Co",
    "wof:placetype":"venue"
},
  "geometry": {"coordinates":[-94.135181,36.253974],"type":"Point"}
}