{
  "type": "Feature",
  "properties": {
    "iso:country":"US",
    "sg:address":"200 E 3rd St",
    "sg:city":"De Witt",
    "sg:classifiers":[
        {
            "category":"Freight",
            "type":"Transportation"
        }
    ],
    "sg:phone":"+1 870 946 3596",
    "sg:postcode":"72042",
    "sg:province":"AR",
    "sg:tags":[
        "grain",
        "elevator"
    ],
    "wof:name":"Rollison Seed Co",
    "wof:placetype":"venue"
},
  "geometry": {"coordinates":[-91.332513,34.292277],"type":"Point"}
}