{
  "type": "Feature",
  "properties": {
    "addr:full":"200 E 3rd St De Witt AR 72042",
    "addr:housenumber":"200",
    "addr:postcode":"72042",
    "addr:street":"E 3Rd St",
    "iso:country":"US",
    "sg:address":"200 E 3rd St",
    "sg:city":"De Witt",
    "sg:classifiers":[
        {
            "category":"Freight",
            "type":"Transportation"
        }
    ],
    "sg:phone":"+1 870 946 3596",
    "sg:postcode":"72042",
    "sg:province":"AR",
    "sg:tags":[
        "grain",
        "elevator"
    ],
    "wof:name":"Rollison Seed Co",
    "wof:placetype":"venue"
},
  "geometry": {"coordinates":[-91.33251300000001,34.292277],"type":"Point"}
}