{
  "type": "Feature",
  "properties": {
    "addr:full":"65 Cedar Ln London AR 72847",
    "addr:housenumber":"65",
    "addr:postcode":"72847",
    "addr:street":"Cedar Ln",
    "iso:country":"US",
    "sg:address":"65 Cedar Ln",
    "sg:city":"London",
    "sg:classifiers":[
        {
            "category":"Shopping",
            "subcategory":"Used Merchandise",
            "type":"Retail Goods"
        }
    ],
    "sg:phone":"+1 479 293 4191",
    "sg:postcode":"72847",
    "sg:province":"AR",
    "sg:tags":[
        "educational",
        "book"
    ],
    "wof:name":"Finders Keepers",
    "wof:placetype":"venue"
},
  "geometry": {"coordinates":[-93.294481,35.333278],"type":"Point"}
}