{
  "type": "Feature",
  "properties": {
    "iso:country":"US",
    "sg:address":"184 Pugh Rd",
    "sg:city":"Searcy",
    "sg:classifiers":[
        {
            "category":"Shopping",
            "subcategory":"Gifts & Souvenirs",
            "type":"Retail Goods"
        }
    ],
    "sg:phone":"+1 501 268 8932",
    "sg:postcode":"72143",
    "sg:province":"AR",
    "sg:tags":[
        "supply"
    ],
    "wof:name":"Pink Palace Florist",
    "wof:placetype":"venue"
},
  "geometry": {"coordinates":[-91.782124,35.331306],"type":"Point"}
}