{
  "type": "Feature",
  "properties": {
    "iso:country":"US",
    "sg:address":"5 Woodsdale Dr",
    "sg:city":"Eureka Springs",
    "sg:classifiers":[
        {
            "category":"Restaurant",
            "type":"Food & Drink"
        }
    ],
    "sg:phone":"+1 479 253 8981",
    "sg:postcode":"72631",
    "sg:province":"AR",
    "sg:tags":[
        "eating"
    ],
    "wof:name":"Back Porch Restaurant",
    "wof:placetype":"venue"
},
  "geometry": {"coordinates":[-93.76033099999999,36.477511],"type":"Point"}
}