{
  "type": "Feature",
  "properties": {
    "iso:country":"US",
    "sg:address":"4610 Sam Peck Rd",
    "sg:city":"Little Rock",
    "sg:classifiers":[
        {
            "category":"Health Services",
            "subcategory":"Health Practitioner",
            "type":"Services"
        }
    ],
    "sg:phone":"+1 501 225 3601",
    "sg:postcode":"72223",
    "sg:province":"AR",
    "sg:tags":[
        "therapist",
        "physical"
    ],
    "wof:name":"Walker Physical Therapy",
    "wof:placetype":"venue"
},
  "geometry": {"coordinates":[-92.416884,34.792572],"type":"Point"}
}