{
  "type": "Feature",
  "properties": {
    "addr:full":"413 W Court St Paragould AR 72450",
    "addr:housenumber":"413",
    "addr:postcode":"72450",
    "addr:street":"W Court",
    "iso:country":"US",
    "sg:address":"413 W Court St",
    "sg:city":"Paragould",
    "sg:classifiers":[
        {
            "category":"Real Estate",
            "subcategory":"Real Estate Services",
            "type":"Services"
        },
        {
            "category":"Real Estate",
            "subcategory":"Real Estate Agent",
            "type":"Services"
        }
    ],
    "sg:phone":"+1 870 236 1722",
    "sg:postcode":"72450",
    "sg:province":"AR",
    "sg:tags":[
        "buyer",
        "management",
        "broker"
    ],
    "wof:name":"Town & Country Realty",
    "wof:placetype":"venue"
},
  "geometry": {"coordinates":[-90.490419,36.05621],"type":"Point"}
}