{
  "type": "Feature",
  "properties": {
    "iso:country":"US",
    "sg:address":"701 Northshore Dr",
    "sg:city":"Hot Springs National Park",
    "sg:classifiers":[
        {
            "category":"Professional",
            "subcategory":"Lawyer & Legal Services",
            "type":"Services"
        }
    ],
    "sg:phone":"+1 501 767 1460",
    "sg:postcode":"71913",
    "sg:province":"AR",
    "wof:name":"Mark B Chadwick",
    "wof:placetype":"venue"
},
  "geometry": {"coordinates":[-93.125601,34.437512],"type":"Point"}
}