{
  "type": "Feature",
  "properties": {
    "iso:country":"US",
    "sg:address":"1825 E Oak St",
    "sg:city":"Conway",
    "sg:classifiers":[
        {
            "category":"Building & Trades",
            "subcategory":"Equipment Rental",
            "type":"Services"
        },
        {
            "category":"Cinema",
            "subcategory":"Movie Rental",
            "type":"Entertainment"
        }
    ],
    "sg:phone":"+1 501 548 9940",
    "sg:postcode":"72032",
    "sg:province":"AR",
    "sg:tags":[
        "video",
        "disc",
        "leasing",
        "tape"
    ],
    "wof:name":"Starz Video",
    "wof:placetype":"venue"
},
  "geometry": {"coordinates":[-92.402636,35.091034],"type":"Point"}
}