{
  "type": "Feature",
  "properties": {
    "iso:country":"US",
    "sg:address":"1206 Roberta Ann St",
    "sg:city":"Sherwood",
    "sg:classifiers":[
        {
            "category":"Professional",
            "subcategory":"Advertising",
            "type":"Services"
        }
    ],
    "sg:phone":"+1 501 834 8282",
    "sg:postcode":"72120",
    "sg:province":"AR",
    "wof:name":"Double Time Promotions",
    "wof:placetype":"venue"
},
  "geometry": {"coordinates":[-92.2133,34.809806],"type":"Point"}
}