{
  "type": "Feature",
  "properties": {
    "iso:country":"US",
    "sg:address":"2775 Elm Cove",
    "sg:city":"West Memphis",
    "sg:classifiers":[
        {
            "category":"Retail",
            "subcategory":"Repair Shop",
            "type":"Services"
        }
    ],
    "sg:phone":"+1 870 735 0817",
    "sg:postcode":"72301",
    "sg:province":"AR",
    "wof:name":"J&L Machine Works",
    "wof:placetype":"venue"
},
  "geometry": {"coordinates":[-90.151292,35.144807],"type":"Point"}
}