{
  "type": "Feature",
  "properties": {
    "addr:full":"206 Cleveland St Star City AR 71667",
    "addr:housenumber":"206",
    "addr:postcode":"71667",
    "addr:street":"Cleveland St",
    "iso:country":"US",
    "sg:address":"206 Cleveland St",
    "sg:city":"Star City",
    "sg:classifiers":[
        {
            "category":"Education",
            "subcategory":"School",
            "type":"Public Place"
        }
    ],
    "sg:phone":"+1 870 628 5287",
    "sg:postcode":"71667",
    "sg:province":"AR",
    "sg:tags":[
        "educational",
        "program"
    ],
    "wof:name":"Lincoln County Adult Education",
    "wof:placetype":"venue"
},
  "geometry": {"coordinates":[-91.841341,33.941232],"type":"Point"}
}