{
  "type": "Feature",
  "properties": {
    "addr:full":"808 Hobson Ave Hot Springs AR 71913",
    "addr:housenumber":"808",
    "addr:postcode":"71913",
    "addr:street":"Hobson Ave",
    "iso:country":"US",
    "sg:address":"808 Hobson Ave",
    "sg:city":"Hot Springs",
    "sg:classifiers":[
        {
            "category":"Personal",
            "subcategory":"Beauty Salon",
            "type":"Services"
        }
    ],
    "sg:phone":"+1 501 538 4764",
    "sg:postcode":"71913",
    "sg:province":"AR",
    "wof:name":"Hairsayz It All",
    "wof:placetype":"venue"
},
  "geometry": {"coordinates":[-93.068657,34.498128],"type":"Point"}
}