{
  "type": "Feature",
  "properties": {
    "iso:country":"US",
    "sg:address":"8415 W Markham St",
    "sg:city":"Little Rock",
    "sg:classifiers":[
        {
            "category":"Banks & Credit Unions",
            "subcategory":"Bank",
            "type":"Services"
        }
    ],
    "sg:phone":"+1 501 225 6652",
    "sg:postcode":"72205",
    "sg:province":"AR",
    "wof:name":"Metropolitan National Bank",
    "wof:placetype":"venue"
},
  "geometry": {"coordinates":[-92.367535,34.753072],"type":"Point"}
}