{
  "type": "Feature",
  "properties": {
    "iso:country":"US",
    "sg:address":"312 W Dequeen Ave",
    "sg:city":"De Queen",
    "sg:classifiers":[
        {
            "category":"Recreation",
            "type":"Entertainment"
        }
    ],
    "sg:phone":"+1 870 642 2900",
    "sg:postcode":"71832",
    "sg:province":"AR",
    "sg:tags":[
        "club",
        "membership"
    ],
    "wof:name":"Mound Slough Hunting Club",
    "wof:placetype":"venue"
},
  "geometry": {"coordinates":[-94.340461,34.037851],"type":"Point"}
}