{
  "type": "Feature",
  "properties": {
    "iso:country":"US",
    "sg:address":"123 W 14th St",
    "sg:city":"De Witt",
    "sg:classifiers":[
        {
            "category":"Professional",
            "type":"Services"
        }
    ],
    "sg:phone":"+1 870 946 4314",
    "sg:postcode":"72042",
    "sg:province":"AR",
    "wof:name":"Amy Rives",
    "wof:placetype":"venue"
},
  "geometry": {"coordinates":[-91.336214,34.28162],"type":"Point"}
}