{
  "type": "Feature",
  "properties": {
    "iso:country":"US",
    "sg:address":"123 E Roller Ave",
    "sg:city":"Decatur",
    "sg:classifiers":[
        {
            "category":"Insurance",
            "subcategory":"Hazard Insurance",
            "type":"Services"
        }
    ],
    "sg:phone":"+1 479 752 3284",
    "sg:postcode":"72722",
    "sg:province":"AR",
    "sg:tags":[
        "commercial",
        "business"
    ],
    "wof:name":"Grand Insurance & Financial Services Inc",
    "wof:placetype":"venue"
},
  "geometry": {"coordinates":[-94.460406,36.335772],"type":"Point"}
}