{
  "type": "Feature",
  "properties": {
    "addr:full":"4112 Idlewild Ave North Little Rock AR 72116",
    "addr:housenumber":"4112",
    "addr:postcode":"72116",
    "addr:street":"Idlewild Ave",
    "iso:country":"US",
    "sg:address":"4112 Idlewild Ave",
    "sg:city":"North Little Rock",
    "sg:classifiers":[
        {
            "category":"Shopping",
            "subcategory":"Used Merchandise",
            "type":"Retail Goods"
        }
    ],
    "sg:phone":"+1 501 753 6848",
    "sg:postcode":"72116",
    "sg:province":"AR",
    "wof:name":"Olde World Antiques & Collecta",
    "wof:placetype":"venue"
},
  "geometry": {"coordinates":[-92.256709,34.793967],"type":"Point"}
}