{
  "type": "Feature",
  "properties": {
    "iso:country":"US",
    "sg:address":"1264 State Hwy 69 Spr",
    "sg:city":"Trumann",
    "sg:classifiers":[
        {
            "category":"Freight",
            "type":"Transportation"
        }
    ],
    "sg:phone":"+1 870 483 7318",
    "sg:postcode":"72472",
    "sg:province":"AR",
    "sg:tags":[
        "operator",
        "trucking"
    ],
    "wof:name":"Fathom Transport Inc",
    "wof:placetype":"venue"
},
  "geometry": {"coordinates":[-90.499591,35.661905],"type":"Point"}
}