{
  "type": "Feature",
  "properties": {
    "iso:country":"US",
    "sg:address":"903 Yukon Dr",
    "sg:city":"Springdale",
    "sg:classifiers":[
        {
            "category":"Retail",
            "subcategory":"Auto Repair",
            "type":"Services"
        }
    ],
    "sg:phone":"+1 479 756 1801",
    "sg:postcode":"72762",
    "sg:province":"AR",
    "sg:tags":[
        "automotive",
        "customizing"
    ],
    "wof:name":"Every Detail & Accessory Inc",
    "wof:placetype":"venue"
},
  "geometry": {"coordinates":[-94.168272,36.177435],"type":"Point"}
}