{
  "type": "Feature",
  "properties": {
    "iso:country":"US",
    "sg:address":"5401 S Olive St",
    "sg:city":"Pine Bluff",
    "sg:classifiers":[
        {
            "category":"Restaurant",
            "type":"Food & Drink"
        }
    ],
    "sg:phone":"+1 870 534 9464",
    "sg:postcode":"71603",
    "sg:province":"AR",
    "wof:name":"Wing Stop Restaurant",
    "wof:placetype":"venue"
},
  "geometry": {"coordinates":[-92.006508,34.170992],"type":"Point"}
}