{
  "type": "Feature",
  "properties": {
    "addr:full":"3227 Fairplay Rd Benton AR 72019",
    "addr:housenumber":"3227",
    "addr:postcode":"72019",
    "addr:street":"Fairplay Rd",
    "iso:country":"US",
    "sg:address":"3227 Fairplay Rd",
    "sg:city":"Benton",
    "sg:classifiers":[
        {
            "category":"Professional",
            "subcategory":"Engineering",
            "type":"Services"
        }
    ],
    "sg:phone":"+1 501 939 2303",
    "sg:postcode":"72019",
    "sg:province":"AR",
    "sg:tags":[
        "engineer"
    ],
    "wof:name":"Heritage Engineering",
    "wof:placetype":"venue"
},
  "geometry": {"coordinates":[-92.753497,34.536271],"type":"Point"}
}