{
  "type": "Feature",
  "properties": {
    "addr:full":"1888 S State Highway 77 Osceola AR 72370",
    "addr:housenumber":"1888",
    "addr:postcode":"72370",
    "addr:street":"S State Highway 77",
    "iso:country":"US",
    "sg:address":"1888 S State Highway 77",
    "sg:city":"Osceola",
    "sg:classifiers":[
        {
            "category":"Utilities",
            "subcategory":"Water",
            "type":"Services"
        }
    ],
    "sg:phone":"+1 870 531 2158",
    "sg:postcode":"72370",
    "sg:province":"AR",
    "sg:tags":[
        "company-utility",
        "system",
        "supply"
    ],
    "wof:name":"Little River Water District Association",
    "wof:placetype":"venue"
},
  "geometry": {"coordinates":[-90.231268,35.692354],"type":"Point"}
}