{
  "type": "Feature",
  "properties": {
    "iso:country":"US",
    "sg:address":"7114 Macarthur Dr",
    "sg:city":"N Little Rock",
    "sg:classifiers":[
        {
            "category":"Home & Garden",
            "subcategory":"Furniture",
            "type":"Retail Goods"
        }
    ],
    "sg:phone":"+1 501 753 5754",
    "sg:postcode":"72118",
    "sg:province":"AR",
    "wof:name":"Furniture Mall",
    "wof:placetype":"venue"
},
  "geometry": {"coordinates":[-92.311003,34.812445],"type":"Point"}
}