{
  "type": "Feature",
  "properties": {
    "iso:country":"US",
    "sg:address":"1000 Airport Rd",
    "sg:city":"Forrest City",
    "sg:classifiers":[
        {
            "category":"Social Services",
            "type":"Services"
        }
    ],
    "sg:phone":"+1 870 630 2005",
    "sg:postcode":"72335",
    "sg:province":"AR",
    "sg:tags":[
        "organization",
        "welfare"
    ],
    "wof:name":"Eastern Arkansas Enterprise",
    "wof:placetype":"venue"
},
  "geometry": {"coordinates":[-90.801499,35.00618],"type":"Point"}
}