{
  "type": "Feature",
  "properties": {
    "iso:country":"US",
    "sg:address":"402 Stribling Rd",
    "sg:city":"Rogers",
    "sg:classifiers":[
        {
            "category":"Professional",
            "subcategory":"Management & Consulting",
            "type":"Services"
        }
    ],
    "sg:phone":"+1 479 936 8282",
    "sg:postcode":"72756",
    "sg:province":"AR",
    "sg:tags":[
        "marketing",
        "consultant"
    ],
    "wof:name":"Nwa Sales & Marketing",
    "wof:placetype":"venue"
},
  "geometry": {"coordinates":[-94.117575,36.351109],"type":"Point"}
}