{
  "type": "Feature",
  "properties": {
    "iso:country":"US",
    "sg:address":"1412 S 1st St",
    "sg:city":"Rogers",
    "sg:classifiers":[
        {
            "category":"Manufacturing",
            "subcategory":"Glass & Minerals",
            "type":"Manufacturing & Wholesale Goods"
        }
    ],
    "sg:phone":"+1 479 636 0888",
    "sg:postcode":"72756",
    "sg:province":"AR",
    "sg:tags":[
        "flat",
        "product",
        "mfg"
    ],
    "wof:name":"Guardian Auto Glass",
    "wof:placetype":"venue"
},
  "geometry": {"coordinates":[-94.117256,36.318941],"type":"Point"}
}