{
  "type": "Feature",
  "properties": {
    "iso:country":"US",
    "sg:address":"500 S Mount Olive St",
    "sg:city":"Siloam Springs",
    "sg:classifiers":[
        {
            "category":"Health Services",
            "subcategory":"Doctor",
            "type":"Services"
        }
    ],
    "sg:phone":"+1 479 524 8635",
    "sg:postcode":"72761",
    "sg:province":"OK",
    "sg:tags":[
        "osteopathic"
    ],
    "wof:name":"Ralph E Meehan Jr",
    "wof:placetype":"venue"
},
  "geometry": {"coordinates":[-94.541348,36.181472],"type":"Point"}
}