{
  "type": "Feature",
  "properties": {
    "iso:country":"US",
    "sg:address":"126 West Dr",
    "sg:city":"Benton",
    "sg:classifiers":[
        {
            "category":"Place Of Worship",
            "type":"Public Place"
        }
    ],
    "sg:phone":"+1 501 776 3068",
    "sg:postcode":"72015",
    "sg:province":"AR",
    "sg:tags":[
        "church"
    ],
    "wof:name":"New Life Church",
    "wof:placetype":"venue"
},
  "geometry": {"coordinates":[-92.59608799999999,34.563996],"type":"Point"}
}