{
  "type": "Feature",
  "properties": {
    "addr:full":"1000 W Main St Jacksonville AR 72076",
    "addr:housenumber":"1000",
    "addr:postcode":"72076",
    "addr:street":"W Main St",
    "iso:country":"US",
    "sg:address":"1000 W Main St",
    "sg:city":"Jacksonville",
    "sg:classifiers":[
        {
            "category":"Professional",
            "subcategory":"Detective & Security Services",
            "type":"Services"
        }
    ],
    "sg:phone":"+1 501 982 2206",
    "sg:postcode":"72076",
    "sg:province":"AR",
    "sg:tags":[
        "control",
        "monitoring",
        "fire",
        "consultant",
        "alarm",
        "system",
        "equipment"
    ],
    "wof:name":"American Alarm Co Of Arkansas Inc",
    "wof:placetype":"venue"
},
  "geometry": {"coordinates":[-92.118651,34.867224],"type":"Point"}
}