{
  "type": "Feature",
  "properties": {
    "iso:country":"US",
    "sg:address":"905 W Gibson St",
    "sg:city":"Ozark",
    "sg:classifiers":[
        {
            "category":"Building & Trades",
            "subcategory":"Plumbing",
            "type":"Services"
        }
    ],
    "sg:phone":"+1 479 667 2029",
    "sg:postcode":"72949",
    "sg:province":"AR",
    "sg:tags":[
        "contractor"
    ],
    "wof:name":"Wayne Hodges Plumbing",
    "wof:placetype":"venue"
},
  "geometry": {"coordinates":[-93.833045,35.490802],"type":"Point"}
}