{
  "type": "Feature",
  "properties": {
    "addr:full":"3951 W Perry Rd Rogers AR 72756",
    "addr:housenumber":"3951",
    "addr:postcode":"72756",
    "addr:street":"W Perry Rd",
    "iso:country":"US",
    "sg:address":"3951 W Perry Rd",
    "sg:city":"Rogers",
    "sg:classifiers":[
        {
            "category":"Shopping",
            "subcategory":"Clothing, Apparel, & Fashions",
            "type":"Retail Goods"
        }
    ],
    "sg:phone":"+1 479 986 9291",
    "sg:postcode":"72756",
    "sg:province":"AR",
    "sg:tags":[
        "accessory",
        "clothing",
        "women's"
    ],
    "sg:website":"www.nyandcompany.com",
    "wof:name":"New York & Company",
    "wof:placetype":"venue"
},
  "geometry": {"coordinates":[-94.171497,36.301966],"type":"Point"}
}