{
  "type": "Feature",
  "properties": {
    "iso:country":"US",
    "sg:address":"226 Chappel Hill Rd",
    "sg:city":"Hot Springs National Park",
    "sg:classifiers":[
        {
            "category":"Personal",
            "type":"Services"
        }
    ],
    "sg:phone":"+1 501 525 1110",
    "sg:postcode":"71913",
    "sg:province":"AR",
    "wof:name":"Advantage Thrpy/Linda Troutman",
    "wof:placetype":"venue"
},
  "geometry": {"coordinates":[-93.112231,34.466047],"type":"Point"}
}