{
  "type": "Feature",
  "properties": {
    "addr:full":"311 W Main St Mountain View AR 72560",
    "addr:housenumber":"311",
    "addr:postcode":"72560",
    "addr:street":"W Main St",
    "iso:country":"US",
    "sg:address":"311 W Main St",
    "sg:city":"Mountain View",
    "sg:classifiers":[
        {
            "category":"Government",
            "subcategory":"Fire Station",
            "type":"Public Place"
        }
    ],
    "sg:phone":"+1 870 269 3804",
    "sg:postcode":"72560",
    "sg:province":"AR",
    "sg:tags":[
        "department"
    ],
    "wof:name":"Mountain View Fire Dept",
    "wof:placetype":"venue"
},
  "geometry": {"coordinates":[-92.120335,35.868609],"type":"Point"}
}