{
  "type": "Feature",
  "properties": {
    "addr:full":"402 Elm St Marianna AR 72360",
    "addr:housenumber":"402",
    "addr:postcode":"72360",
    "addr:street":"Elm St",
    "iso:country":"US",
    "sg:address":"402 Elm St",
    "sg:city":"Marianna",
    "sg:classifiers":[
        {
            "category":"Shopping",
            "subcategory":"Used Merchandise",
            "type":"Retail Goods"
        }
    ],
    "sg:phone":"+1 870 295 3322",
    "sg:postcode":"72360",
    "sg:province":"AR",
    "sg:tags":[
        "flea",
        "market"
    ],
    "wof:name":"Calvin's Flea Market",
    "wof:placetype":"venue"
},
  "geometry": {"coordinates":[-90.76500799999999,34.785684],"type":"Point"}
}