{
  "type": "Feature",
  "properties": {
    "addr:full":"2341 Hwy 267 S Searcy AR 72143",
    "addr:housenumber":"2341",
    "addr:postcode":"72143",
    "addr:street":"Hwy 267 S",
    "iso:country":"US",
    "sg:address":"2341 Hwy 267 S",
    "sg:city":"Searcy",
    "sg:classifiers":[
        {
            "category":"Manufacturing",
            "subcategory":"Metals",
            "type":"Manufacturing & Wholesale Goods"
        },
        {
            "category":"Retail",
            "subcategory":"Repair Shop",
            "type":"Services"
        }
    ],
    "sg:phone":"+1 501 279 2726",
    "sg:postcode":"72143",
    "sg:province":"AR",
    "sg:tags":[
        "fabricate",
        "welding"
    ],
    "wof:name":"Custom Welding Inc",
    "wof:placetype":"venue"
},
  "geometry": {"coordinates":[-91.780643,35.200501],"type":"Point"}
}