{
  "type": "Feature",
  "properties": {
    "iso:country":"US",
    "sg:address":"14741 McClellan Locker Rd",
    "sg:city":"Canehill",
    "sg:classifiers":[
        {
            "category":"Wholesale",
            "subcategory":"Meat",
            "type":"Manufacturing & Wholesale Goods"
        }
    ],
    "sg:phone":"+1 479 824 3959",
    "sg:postcode":"72717",
    "sg:province":"AR",
    "sg:tags":[
        "poultry",
        "plant",
        "processing"
    ],
    "wof:name":"Mc Clellan Processing Co",
    "wof:placetype":"venue"
},
  "geometry": {"coordinates":[-94.406065,35.900444],"type":"Point"}
}