{
  "type": "Feature",
  "properties": {
    "iso:country":"US",
    "sg:address":"2138 N Garland Ave",
    "sg:city":"Fayetteville",
    "sg:classifiers":[
        {
            "category":"Professional",
            "type":"Services"
        }
    ],
    "sg:phone":"+1 479 444 0523",
    "sg:postcode":"72704",
    "sg:province":"AR",
    "sg:tags":[
        "establishment"
    ],
    "wof:name":"Robert II Bureau",
    "wof:placetype":"venue"
},
  "geometry": {"coordinates":[-94.17482,36.091594],"type":"Point"}
}