{
  "type": "Feature",
  "properties": {
    "iso:country":"US",
    "sg:address":"14149 Old Mill Rd",
    "sg:city":"Elkins",
    "sg:classifiers":[
        {
            "category":"Building & Trades",
            "subcategory":"Landscaping Services",
            "type":"Services"
        }
    ],
    "sg:phone":"+1 479 225 5088",
    "sg:postcode":"72727",
    "sg:province":"AR",
    "sg:tags":[
        "landscape",
        "contractor"
    ],
    "wof:name":"In Green Hydrograss",
    "wof:placetype":"venue"
},
  "geometry": {"coordinates":[-93.962344,36.053841],"type":"Point"}
}