{
  "type": "Feature",
  "properties": {
    "iso:country":"US",
    "sg:address":"487 Lakewood Dr",
    "sg:city":"Clarksville",
    "sg:classifiers":[
        {
            "category":"Recreation",
            "type":"Entertainment"
        }
    ],
    "sg:phone":"+1 479 705 3488",
    "sg:postcode":"72830",
    "sg:province":"AR",
    "sg:tags":[
        "club",
        "membership"
    ],
    "wof:name":"Alltime Family Fitness",
    "wof:placetype":"venue"
},
  "geometry": {"coordinates":[-93.434615,35.532527],"type":"Point"}
}