{
  "type": "Feature",
  "properties": {
    "addr:full":"121 Longleaf Dr Searcy AR 72143",
    "addr:housenumber":"121",
    "addr:postcode":"72143",
    "addr:street":"Longleaf Dr",
    "iso:country":"US",
    "sg:address":"121 Longleaf Dr",
    "sg:city":"Searcy",
    "sg:classifiers":[
        {
            "category":"Building & Trades",
            "subcategory":"Construction",
            "type":"Services"
        }
    ],
    "sg:phone":"+1 501 279 3799",
    "sg:postcode":"72143",
    "sg:province":"AR",
    "sg:tags":[
        "resurfacing",
        "laying",
        "refinishing",
        "floor"
    ],
    "wof:name":"Gym Masters Sports Courts",
    "wof:placetype":"venue"
},
  "geometry": {"coordinates":[-91.789124,35.247432],"type":"Point"}
}