{
  "type": "Feature",
  "properties": {
    "iso:country":"US",
    "sg:address":"104 S 5th St",
    "sg:city":"De Queen",
    "sg:classifiers":[
        {
            "category":"Education",
            "subcategory":"School",
            "type":"Public Place"
        }
    ],
    "sg:phone":"+1 870 642 8804",
    "sg:postcode":"71832",
    "sg:province":"AR",
    "sg:tags":[
        "educational",
        "program"
    ],
    "wof:name":"Fifth Street Adult Education",
    "wof:placetype":"venue"
},
  "geometry": {"coordinates":[-94.342743,34.036574],"type":"Point"}
}