{
  "type": "Feature",
  "properties": {
    "iso:country":"US",
    "sg:address":"1606 Oakwood Ave",
    "sg:city":"Bentonville",
    "sg:classifiers":[
        {
            "category":"Shopping",
            "subcategory":"Hobbies, Toys, & Games",
            "type":"Retail Goods"
        }
    ],
    "sg:phone":"+1 479 544 2424",
    "sg:postcode":"72712",
    "sg:province":"AR",
    "wof:name":"RCMAUCTION.COM",
    "wof:placetype":"venue"
},
  "geometry": {"coordinates":[-94.21738499999999,36.392751],"type":"Point"}
}