{
  "type": "Feature",
  "properties": {
    "iso:country":"US",
    "sg:address":"106 Vine St",
    "sg:city":"Alicia",
    "sg:phone":"+1 870 886 6812",
    "sg:postcode":"72410",
    "sg:province":"AR",
    "sg:tags":[
        "farm",
        "rice",
        "wheat",
        "soybean"
    ],
    "wof:name":"Corbett Stanley Farms",
    "wof:placetype":"venue"
},
  "geometry": {"coordinates":[-91.08441500000001,35.892906],"type":"Point"}
}