{
  "type": "Feature",
  "properties": {
    "addr:full":"22174 State Hwy 303 Hindsville AR 72738",
    "addr:housenumber":"22174",
    "addr:postcode":"72738",
    "addr:street":"State Hwy 303",
    "iso:country":"US",
    "sg:address":"22174 State Hwy 303",
    "sg:city":"Hindsville",
    "sg:classifiers":[
        {
            "category":"Organizations",
            "subcategory":"Religious Organization",
            "type":"Services"
        }
    ],
    "sg:phone":"+1 479 789 2895",
    "sg:postcode":"72738",
    "sg:province":"AR",
    "wof:name":"House of Worship Hindsville",
    "wof:placetype":"venue"
},
  "geometry": {"coordinates":[-93.91476299999999,36.195825],"type":"Point"}
}