{
  "type": "Feature",
  "properties": {
    "iso:country":"US",
    "sg:address":"3331 N Southridge Dr",
    "sg:city":"Fayetteville",
    "sg:classifiers":[
        {
            "category":"Shopping",
            "subcategory":"Stationery & Office Supplies",
            "type":"Retail Goods"
        }
    ],
    "sg:phone":"+1 479 582 1322",
    "sg:postcode":"72703",
    "sg:province":"AR",
    "wof:name":"Bill & Kathy Brown",
    "wof:placetype":"venue"
},
  "geometry": {"coordinates":[-94.132863,36.112319],"type":"Point"}
}