{
  "type": "Feature",
  "properties": {
    "iso:country":"US",
    "sg:address":"1020 Mena St",
    "sg:city":"Mena",
    "sg:classifiers":[
        {
            "category":"Home & Garden",
            "subcategory":"Household Appliances",
            "type":"Retail Goods"
        },
        {
            "category":"Home & Garden",
            "subcategory":"Home Furnishings",
            "type":"Retail Goods"
        },
        {
            "category":"Home & Garden",
            "subcategory":"Carpets & Floor Coverings",
            "type":"Retail Goods"
        },
        {
            "category":"Retail",
            "subcategory":"Laundry & Dry Cleaning",
            "type":"Services"
        },
        {
            "category":"Home & Garden",
            "subcategory":"Furniture",
            "type":"Retail Goods"
        }
    ],
    "sg:phone":"+1 479 394 4332",
    "sg:postcode":"71953",
    "sg:province":"AR",
    "sg:tags":[
        "dryers-dealers",
        "set",
        "freezers-dealers",
        "major",
        "bed",
        "mattress",
        "refrigerator",
        "bedroom",
        "washer",
        "store"
    ],
    "sg:website":"http://www.washburns.com",
    "wof:name":"Washburn's Furniture",
    "wof:placetype":"venue"
},
  "geometry": {"coordinates":[-94.23386600000001,34.581261],"type":"Point"}
}