{
  "type": "Feature",
  "properties": {
    "iso:country":"US",
    "sg:address":"1105 Latigo Trl",
    "sg:city":"Jacksonville",
    "sg:classifiers":[
        {
            "category":"Freight",
            "type":"Transportation"
        }
    ],
    "sg:phone":"+1 501 985 5234",
    "sg:postcode":"72076",
    "sg:province":"AR",
    "sg:tags":[
        "operator",
        "local",
        "trucking"
    ],
    "wof:name":"Jnc Trucking Inc",
    "wof:placetype":"venue"
},
  "geometry": {"coordinates":[-92.097847,34.902738],"type":"Point"}
}