{
  "type": "Feature",
  "properties": {
    "iso:country":"US",
    "sg:address":"139 The Fast Ln",
    "sg:city":"Mena",
    "sg:classifiers":[
        {
            "category":"Professional",
            "subcategory":"Lawyer & Legal Services",
            "type":"Services"
        }
    ],
    "sg:phone":"+1 479 394 1008",
    "sg:postcode":"71953",
    "sg:province":"AR",
    "sg:tags":[
        "attorney"
    ],
    "wof:name":"Danny Miller Law Office",
    "wof:placetype":"venue"
},
  "geometry": {"coordinates":[-94.243719,34.541761],"type":"Point"}
}