{
  "type": "Feature",
  "properties": {
    "iso:country":"US",
    "sg:address":"705 Dover Rd",
    "sg:city":"West Memphis",
    "sg:classifiers":[
        {
            "category":"Shopping",
            "subcategory":"Used Merchandise",
            "type":"Retail Goods"
        }
    ],
    "sg:phone":"+1 870 732 5933",
    "sg:postcode":"72301",
    "sg:province":"AR",
    "sg:tags":[
        "pawnbroker"
    ],
    "wof:name":"Carter's Pawn Shop",
    "wof:placetype":"venue"
},
  "geometry": {"coordinates":[-90.200264,35.161373],"type":"Point"}
}