{
  "type": "Feature",
  "properties": {
    "addr:full":"3811 S Arkansas Ave Russellville AR 72802",
    "addr:housenumber":"3811",
    "addr:postcode":"72802",
    "addr:street":"S Arkansas Ave",
    "iso:country":"US",
    "sg:address":"3811 S Arkansas Ave",
    "sg:city":"Russellville",
    "sg:classifiers":[
        {
            "category":"Banks & Credit Unions",
            "subcategory":"Investment Brokerage",
            "type":"Services"
        }
    ],
    "sg:phone":"+1 479 968 1111",
    "sg:postcode":"72802",
    "sg:province":"AR",
    "sg:tags":[
        "security"
    ],
    "wof:name":"PSI Group Wealth Management",
    "wof:placetype":"venue"
},
  "geometry": {"coordinates":[-93.139736,35.240002],"type":"Point"}
}