{
  "type": "Feature",
  "properties": {
    "iso:country":"US",
    "sg:address":"15 Ludington Cove",
    "sg:city":"Little Rock",
    "sg:classifiers":[
        {
            "category":"Building & Trades",
            "subcategory":"Construction",
            "type":"Services"
        }
    ],
    "sg:phone":"+1 501 590 3232",
    "sg:postcode":"72227",
    "sg:province":"AR",
    "sg:tags":[
        "general",
        "contractor"
    ],
    "wof:name":"J C Construction",
    "wof:placetype":"venue"
},
  "geometry": {"coordinates":[-92.378568,34.770534],"type":"Point"}
}