{
  "type": "Feature",
  "properties": {
    "iso:country":"US",
    "sg:address":"625 N E St",
    "sg:city":"Rogers",
    "sg:classifiers":[
        {
            "category":"Health Services",
            "subcategory":"Chiropractor",
            "type":"Services"
        }
    ],
    "sg:phone":"+1 479 636 0650",
    "sg:postcode":"72756",
    "sg:province":"AR",
    "wof:name":"John Flynn",
    "wof:placetype":"venue"
},
  "geometry": {"coordinates":[-94.109489,36.339694],"type":"Point"}
}