{
  "type": "Feature",
  "properties": {
    "addr:full":"420 W Broadway West Memphis AR 72301",
    "addr:housenumber":"420",
    "addr:postcode":"72301",
    "addr:street":"W Broadway",
    "iso:country":"US",
    "sg:address":"420 W Broadway",
    "sg:city":"West Memphis",
    "sg:classifiers":[
        {
            "category":"Recreation",
            "type":"Entertainment"
        }
    ],
    "sg:phone":"+1 870 733 0076",
    "sg:postcode":"72301",
    "sg:province":"AR",
    "sg:tags":[
        "martial",
        "arts",
        "instruction"
    ],
    "wof:name":"Black Belt Academy",
    "wof:placetype":"venue"
},
  "geometry": {"coordinates":[-90.19392499999999,35.146281],"type":"Point"}
}