{
  "type": "Feature",
  "properties": {
    "addr:full":"4011 Burnville Rd Greenwood AR 72936",
    "addr:housenumber":"4011",
    "addr:postcode":"72936",
    "addr:street":"Burnville Rd",
    "iso:country":"US",
    "sg:address":"4011 Burnville Rd",
    "sg:city":"Greenwood",
    "sg:classifiers":[
        {
            "category":"Home & Garden",
            "subcategory":"Household Appliances",
            "type":"Retail Goods"
        }
    ],
    "sg:phone":"+1 479 996 9288",
    "sg:postcode":"72936",
    "sg:province":"AR",
    "sg:tags":[
        "major",
        "appliances-small"
    ],
    "wof:name":"Sondra Price",
    "wof:placetype":"venue"
},
  "geometry": {"coordinates":[-94.191834,35.187561],"type":"Point"}
}