{
  "type": "Feature",
  "properties": {
    "iso:country":"US",
    "sg:address":"2135 Malcolm Ave",
    "sg:city":"Newport",
    "sg:classifiers":[
        {
            "category":"Health Services",
            "subcategory":"Clinic",
            "type":"Services"
        }
    ],
    "sg:phone":"+1 870 523 8004",
    "sg:postcode":"72112",
    "sg:province":"AR",
    "sg:tags":[
        "information",
        "mental"
    ],
    "wof:name":"Life Strategies of Arkansas",
    "wof:placetype":"venue"
},
  "geometry": {"coordinates":[-91.254144,35.605501],"type":"Point"}
}