{
  "type": "Feature",
  "properties": {
    "iso:country":"US",
    "sg:address":"4810 E Highland Dr",
    "sg:city":"Jonesboro",
    "sg:classifiers":[
        {
            "category":"Wholesale",
            "subcategory":"Groceries",
            "type":"Manufacturing & Wholesale Goods"
        }
    ],
    "sg:phone":"+1 870 974 9957",
    "sg:postcode":"72401",
    "sg:province":"AR",
    "sg:tags":[
        "general"
    ],
    "wof:name":"Bargains Galor",
    "wof:placetype":"venue"
},
  "geometry": {"coordinates":[-90.639864,35.821002],"type":"Point"}
}