{
  "type": "Feature",
  "properties": {
    "addr:full":"17481 Massengill Rd Harrisburg AR 72432",
    "addr:postcode":"17481;72432",
    "addr:street":"Massengill Rd",
    "iso:country":"US",
    "sg:address":"17481 Massengill Rd",
    "sg:city":"Harrisburg",
    "sg:classifiers":[
        {
            "category":"Farming",
            "subcategory":"Livestock Farm",
            "type":"Manufacturing & Wholesale Goods"
        }
    ],
    "sg:phone":"+1 870 578 2342",
    "sg:postcode":"72432",
    "sg:province":"AR",
    "sg:tags":[
        "equine"
    ],
    "wof:name":"Janet Massengill",
    "wof:placetype":"venue"
},
  "geometry": {"coordinates":[-90.722938,35.60726],"type":"Point"}
}