{
  "type": "Feature",
  "properties": {
    "iso:country":"US",
    "sg:address":"1115 S School Ave",
    "sg:city":"Fayetteville",
    "sg:classifiers":[
        {
            "category":"Food & Beverages",
            "subcategory":"Groceries & Convenience Stores",
            "type":"Retail Goods"
        }
    ],
    "sg:phone":"+1 479 571 3663",
    "sg:postcode":"72701",
    "sg:province":"AR",
    "wof:name":"Chicken & More Store",
    "wof:placetype":"venue"
},
  "geometry": {"coordinates":[-94.164347,36.050586],"type":"Point"}
}