{
  "type": "Feature",
  "properties": {
    "addr:full":"1000 Hwy 79 Bus Stuttgart AR 72160",
    "addr:housenumber":"1000",
    "addr:postcode":"72160",
    "addr:street":"Hwy 79 Bus",
    "iso:country":"US",
    "sg:address":"1000 Hwy 79 Bus",
    "sg:city":"Stuttgart",
    "sg:classifiers":[
        {
            "category":"Professional",
            "type":"Services"
        }
    ],
    "sg:phone":"+1 870 672 4322",
    "sg:postcode":"72160",
    "sg:province":"AR",
    "sg:tags":[
        "establishment"
    ],
    "wof:name":"Non Typical Outdoors LLC",
    "wof:placetype":"venue"
},
  "geometry": {"coordinates":[-91.56285699999999,34.479616],"type":"Point"}
}