{
  "type": "Feature",
  "properties": {
    "iso:country":"US",
    "sg:address":"1411 Lovers Ln",
    "sg:city":"Van Buren",
    "sg:classifiers":[
        {
            "category":"Building & Trades",
            "subcategory":"Landscaping Services",
            "type":"Services"
        }
    ],
    "sg:phone":"+1 479 471 7713",
    "sg:postcode":"72956",
    "sg:province":"AR",
    "sg:tags":[
        "landscape"
    ],
    "wof:name":"Creative Landscaping",
    "wof:placetype":"venue"
},
  "geometry": {"coordinates":[-94.370825,35.457902],"type":"Point"}
}