{
  "type": "Feature",
  "properties": {
    "iso:country":"US",
    "sg:address":"370 Star Ln",
    "sg:city":"Eureka Springs",
    "sg:classifiers":[
        {
            "category":"Travel",
            "subcategory":"Hotels & Motels",
            "type":"Entertainment"
        }
    ],
    "sg:phone":"+1 479 253 6056",
    "sg:postcode":"72632",
    "sg:province":"AR",
    "sg:tags":[
        "operation"
    ],
    "wof:name":"Morningstar Retreat",
    "wof:placetype":"venue"
},
  "geometry": {"coordinates":[-93.657634,36.31773],"type":"Point"}
}