{
  "type": "Feature",
  "properties": {
    "addr:full":"52 River Ridge Rd Little Rock AR 72227",
    "addr:housenumber":"52",
    "addr:postcode":"72227",
    "addr:street":"River Ridge Rd",
    "iso:country":"US",
    "sg:address":"52 River Ridge Rd",
    "sg:city":"Little Rock",
    "sg:classifiers":[
        {
            "category":"Banks & Credit Unions",
            "subcategory":"Financial Services",
            "type":"Services"
        }
    ],
    "sg:phone":"+1 501 227 8758",
    "sg:postcode":"72227",
    "sg:province":"AR",
    "sg:tags":[
        "trust",
        "nonprofit",
        "management"
    ],
    "wof:name":"Steuri Family Foundation",
    "wof:placetype":"venue"
},
  "geometry": {"coordinates":[-92.37615,34.791772],"type":"Point"}
}