{
  "type": "Feature",
  "properties": {
    "iso:country":"US",
    "sg:address":"320 Locust St",
    "sg:city":"Conway",
    "sg:classifiers":[
        {
            "category":"Retail",
            "subcategory":"Repair Shop",
            "type":"Services"
        }
    ],
    "sg:phone":"+1 501 327 3619",
    "sg:postcode":"72034",
    "sg:province":"AR",
    "sg:tags":[
        "clocks",
        "parts"
    ],
    "wof:name":"Clock Doc",
    "wof:placetype":"venue"
},
  "geometry": {"coordinates":[-92.440163,35.082282],"type":"Point"}
}