{
  "type": "Feature",
  "properties": {
    "iso:country":"US",
    "sg:address":"5121 Baseline Rd",
    "sg:city":"Little Rock",
    "sg:classifiers":[
        {
            "category":"Organizations",
            "subcategory":"Religious Organization",
            "type":"Services"
        }
    ],
    "sg:phone":"+1 501 562 6813",
    "sg:postcode":"72209",
    "sg:province":"AR",
    "sg:tags":[
        "church"
    ],
    "wof:name":"Evangelist Temple Church-God",
    "wof:placetype":"venue"
},
  "geometry": {"coordinates":[-92.33537800000001,34.668673],"type":"Point"}
}