{
  "type": "Feature",
  "properties": {
    "iso:country":"US",
    "sg:address":"438 Hwy 63 S",
    "sg:city":"Mammoth Spring",
    "sg:classifiers":[
        {
            "category":"Shopping",
            "subcategory":"Used Merchandise",
            "type":"Retail Goods"
        }
    ],
    "sg:phone":"+1 870 625 0521",
    "sg:postcode":"72554",
    "sg:province":"AR",
    "sg:tags":[
        "flea",
        "market"
    ],
    "wof:name":"Cedar Mall",
    "wof:placetype":"venue"
},
  "geometry": {"coordinates":[-91.533509,36.491874],"type":"Point"}
}