{
  "type": "Feature",
  "properties": {
    "iso:country":"US",
    "sg:address":"2800 Cantrell Rd",
    "sg:city":"Little Rock",
    "sg:classifiers":[
        {
            "category":"Utilities",
            "type":"Services"
        }
    ],
    "sg:phone":"+1 501 664 6000",
    "sg:postcode":"72202",
    "sg:province":"AR",
    "sg:tags":[
        "other",
        "electric",
        "combined"
    ],
    "wof:name":"Northeast Craven Utility Co",
    "wof:placetype":"venue"
},
  "geometry": {"coordinates":[-92.307909,34.75994],"type":"Point"}
}