{
  "type": "Feature",
  "properties": {
    "iso:country":"US",
    "sg:address":"504 S US Hwy 165",
    "sg:city":"De Witt",
    "sg:classifiers":[
        {
            "category":"Wholesale",
            "subcategory":"Machinery & Supplies",
            "type":"Manufacturing & Wholesale Goods"
        }
    ],
    "sg:phone":"+1 870 946 3636",
    "sg:postcode":"72042",
    "sg:province":"AR",
    "sg:tags":[
        "grain",
        "elevator"
    ],
    "wof:name":"Vansandt Farm Svc",
    "wof:placetype":"venue"
},
  "geometry": {"coordinates":[-91.350324,34.288046],"type":"Point"}
}