{
  "type": "Feature",
  "properties": {
    "iso:country":"US",
    "sg:address":"2801 Old Greenwood Rd",
    "sg:city":"Fort Smith",
    "sg:classifiers":[
        {
            "category":"Restaurant",
            "type":"Food & Drink"
        }
    ],
    "sg:menulink":"http://www.allmenus.com/ar/upper/54565-blue-plate-diner/menu/",
    "sg:phone":"+1 479 649 6688",
    "sg:postcode":"72903",
    "sg:province":"AR",
    "wof:name":"Blue Plate Diner",
    "wof:placetype":"venue"
},
  "geometry": {"coordinates":[-94.395082,35.356569],"type":"Point"}
}