{
  "type": "Feature",
  "properties": {
    "addr:full":"241 W State Hwy 148 Blytheville AR 72315",
    "addr:housenumber":"241",
    "addr:postcode":"72315",
    "addr:street":"W State Hwy 148 Blytheville",
    "iso:country":"US",
    "sg:address":"241 W State Hwy 148",
    "sg:city":"Blytheville",
    "sg:classifiers":[
        {
            "category":"Food & Beverages",
            "subcategory":"Groceries & Convenience Stores",
            "type":"Retail Goods"
        }
    ],
    "sg:phone":"+1 870 564 2491",
    "sg:postcode":"72315",
    "sg:province":"AR",
    "wof:name":"Perkins Grocery",
    "wof:placetype":"venue"
},
  "geometry": {"coordinates":[-90.067809,35.814286],"type":"Point"}
}