{
  "type": "Feature",
  "properties": {
    "iso:country":"US",
    "sg:address":"314 Lexington Ave",
    "sg:city":"Fort Smith",
    "sg:classifiers":[
        {
            "category":"Health Services",
            "subcategory":"Doctor",
            "type":"Services"
        }
    ],
    "sg:phone":"+1 479 782 1919",
    "sg:postcode":"72901",
    "sg:province":"AR",
    "sg:tags":[
        "clinic"
    ],
    "wof:name":"Fort Smigh Heart & Vascular",
    "wof:placetype":"venue"
},
  "geometry": {"coordinates":[-94.41765100000001,35.380328],"type":"Point"}
}