{
  "type": "Feature",
  "properties": {
    "addr:full":"125 Co Rd 112 Jonesboro AR 72404",
    "addr:housenumber":"125;112",
    "addr:postcode":"72404",
    "addr:street":"Co Rd",
    "iso:country":"US",
    "sg:address":"125 Co Rd 112",
    "sg:city":"Jonesboro",
    "sg:classifiers":[
        {
            "category":"Professional",
            "type":"Services"
        }
    ],
    "sg:phone":"+1 870 933 1898",
    "sg:postcode":"72404",
    "sg:province":"AR",
    "wof:name":"Mitchell T Colburn",
    "wof:placetype":"venue"
},
  "geometry": {"coordinates":[-90.802774,35.845655],"type":"Point"}
}