{
  "type": "Feature",
  "properties": {
    "iso:country":"US",
    "sg:address":"348 Smokey Ln",
    "sg:city":"North Little Rock",
    "sg:classifiers":[
        {
            "category":"Building & Trades",
            "subcategory":"Construction",
            "type":"Services"
        }
    ],
    "sg:phone":"+1 501 945 3122",
    "sg:postcode":"72117",
    "sg:province":"AR",
    "sg:tags":[
        "contractor"
    ],
    "wof:name":"Spartan Construction",
    "wof:placetype":"venue"
},
  "geometry": {"coordinates":[-92.216303,34.79483],"type":"Point"}
}