{
  "type": "Feature",
  "properties": {
    "iso:country":"US",
    "sg:address":"102 W Church Ave",
    "sg:city":"Berryville",
    "sg:classifiers":[
        {
            "category":"Restaurant",
            "type":"Food & Drink"
        }
    ],
    "sg:phone":"+1 870 423 4848",
    "sg:postcode":"72616",
    "sg:province":"AR",
    "sg:tags":[
        "eating"
    ],
    "wof:name":"LA Cabana",
    "wof:placetype":"venue"
},
  "geometry": {"coordinates":[-93.567888,36.3649],"type":"Point"}
}