{
  "type": "Feature",
  "properties": {
    "addr:full":"2404 Main St North Little Rock AR 72114",
    "addr:housenumber":"2404",
    "addr:postcode":"72114",
    "addr:street":"Main St",
    "iso:country":"US",
    "sg:address":"2404 Main St",
    "sg:city":"North Little Rock",
    "sg:classifiers":[
        {
            "category":"Restaurant",
            "type":"Food & Drink"
        }
    ],
    "sg:menulink":"http://www.allmenus.com/ar/hill/133806-waffle-house/menu/",
    "sg:phone":"+1 501 758 3250",
    "sg:postcode":"72114",
    "sg:province":"AR",
    "sg:tags":[
        "american"
    ],
    "wof:name":"Waffle House",
    "wof:placetype":"venue"
},
  "geometry": {"coordinates":[-92.266797,34.777875],"type":"Point"}
}