{
  "type": "Feature",
  "properties": {
    "iso:country":"US",
    "sg:address":"111 N Fulton St",
    "sg:city":"Clarksville",
    "sg:classifiers":[
        {
            "category":"Shopping",
            "subcategory":"Clothing, Apparel, & Fashions",
            "type":"Retail Goods"
        }
    ],
    "sg:phone":"+1 479 754 7331",
    "sg:postcode":"72830",
    "sg:province":"AR",
    "wof:name":"Fashion Outlet",
    "wof:placetype":"venue"
},
  "geometry": {"coordinates":[-93.465721,35.471353],"type":"Point"}
}