{
  "type": "Feature",
  "properties": {
    "iso:country":"US",
    "sg:address":"2450 Hwy 79 N",
    "sg:city":"Camden",
    "sg:classifiers":[
        {
            "category":"Wholesale",
            "subcategory":"Machinery & Supplies",
            "type":"Manufacturing & Wholesale Goods"
        }
    ],
    "sg:phone":"+1 870 574 2238",
    "sg:postcode":"71701",
    "sg:province":"AR",
    "sg:tags":[
        "farm",
        "equipment"
    ],
    "wof:name":"Tac Equipment Co Inc",
    "wof:placetype":"venue"
},
  "geometry": {"coordinates":[-92.768585,33.630026],"type":"Point"}
}