{
  "type": "Feature",
  "properties": {
    "iso:country":"US",
    "sg:address":"213 S Main St",
    "sg:city":"Stuttgart",
    "sg:classifiers":[
        {
            "category":"Shopping",
            "subcategory":"Gifts & Souvenirs",
            "type":"Retail Goods"
        }
    ],
    "sg:phone":"+1 870 673 1300",
    "sg:postcode":"72160",
    "sg:province":"AR",
    "sg:tags":[
        "party",
        "supply"
    ],
    "wof:name":"Party Zone",
    "wof:placetype":"venue"
},
  "geometry": {"coordinates":[-91.552461,34.501073],"type":"Point"}
}