{
  "type": "Feature",
  "properties": {
    "iso:country":"US",
    "sg:address":"3718 John F Kennedy Blvd",
    "sg:city":"N Little Rock",
    "sg:classifiers":[
        {
            "category":"Shopping",
            "subcategory":"Gifts & Souvenirs",
            "type":"Retail Goods"
        }
    ],
    "sg:phone":"+1 501 758 9242",
    "sg:postcode":"72116",
    "sg:province":"AR",
    "sg:tags":[
        "basket",
        "parcel"
    ],
    "wof:name":"Candy Bouquet",
    "wof:placetype":"venue"
},
  "geometry": {"coordinates":[-92.26021799999999,34.789861],"type":"Point"}
}