{
  "type": "Feature",
  "properties": {
    "iso:country":"US",
    "sg:address":"1104 M St",
    "sg:city":"Barling",
    "sg:classifiers":[
        {
            "category":"Building & Trades",
            "subcategory":"Construction",
            "type":"Services"
        }
    ],
    "sg:phone":"+1 479 484 1634",
    "sg:postcode":"72923",
    "sg:province":"AR",
    "sg:tags":[
        "concrete",
        "contractor"
    ],
    "wof:name":"Steve Beam Construction Co",
    "wof:placetype":"venue"
},
  "geometry": {"coordinates":[-94.309324,35.336927],"type":"Point"}
}