{
  "type": "Feature",
  "properties": {
    "addr:full":"3335 Airport Rd Pearcy AR 71964",
    "addr:housenumber":"3335",
    "addr:postcode":"71964",
    "addr:street":"Airport Rd",
    "iso:country":"US",
    "sg:address":"3335 Airport Rd",
    "sg:city":"Pearcy",
    "sg:classifiers":[
        {
            "category":"Utilities",
            "subcategory":"Refuse",
            "type":"Services"
        }
    ],
    "sg:phone":"+1 501 760 4838",
    "sg:postcode":"71964",
    "sg:province":"AR",
    "sg:tags":[
        "system"
    ],
    "wof:name":"Sanitation Serv-All",
    "wof:placetype":"venue"
},
  "geometry": {"coordinates":[-93.20517700000001,34.442717],"type":"Point"}
}