{
  "type": "Feature",
  "properties": {
    "addr:full":"10701 Baseline Rd Little Rock AR 72209",
    "addr:housenumber":"10701",
    "addr:postcode":"72209",
    "addr:street":"Baseline Rd",
    "iso:country":"US",
    "sg:address":"10701 Baseline Rd",
    "sg:city":"Little Rock",
    "sg:classifiers":[
        {
            "category":"Organizations",
            "subcategory":"Religious Organization",
            "type":"Services"
        }
    ],
    "sg:phone":"+1 501 455 0900",
    "sg:postcode":"72209",
    "sg:province":"AR",
    "sg:website":"www.littlerockchurch.org",
    "wof:name":"Little Rock Church",
    "wof:placetype":"venue"
},
  "geometry": {"coordinates":[-92.39684699999999,34.670577],"type":"Point"}
}