{
  "type": "Feature",
  "properties": {
    "addr:full":"606 N Vine St Magnolia AR 71753",
    "addr:housenumber":"606",
    "addr:postcode":"71753",
    "addr:street":"N Vine St",
    "iso:country":"US",
    "sg:address":"606 N Vine St",
    "sg:city":"Magnolia",
    "sg:classifiers":[
        {
            "category":"Retail",
            "subcategory":"Auto Repair",
            "type":"Services"
        }
    ],
    "sg:phone":"+1 870 234 6701",
    "sg:postcode":"71753",
    "sg:province":"AR",
    "sg:tags":[
        "body",
        "automobile",
        "painting"
    ],
    "wof:name":"Hollensworth Body Shop",
    "wof:placetype":"venue"
},
  "geometry": {"coordinates":[-93.243179,33.272597],"type":"Point"}
}