{
  "type": "Feature",
  "properties": {
    "addr:full":"229 Hobson Ave Hot Springs AR 71913",
    "addr:housenumber":"229",
    "addr:postcode":"71913",
    "addr:street":"Hobson Ave",
    "iso:country":"US",
    "sg:address":"229 Hobson Ave",
    "sg:city":"Hot Springs",
    "sg:classifiers":[
        {
            "category":"Professional",
            "subcategory":"Lawyer & Legal Services",
            "type":"Services"
        }
    ],
    "sg:phone":"+1 501 623 4500",
    "sg:postcode":"71913",
    "sg:province":"AR",
    "sg:tags":[
        "attorney"
    ],
    "wof:name":"King Law Offices",
    "wof:placetype":"venue"
},
  "geometry": {"coordinates":[-93.058283,34.497387],"type":"Point"}
}