{
  "type": "Feature",
  "properties": {
    "iso:country":"US",
    "sg:address":"1919 W Sunset Ave",
    "sg:city":"Springdale",
    "sg:classifiers":[
        {
            "category":"Restaurant",
            "type":"Food & Drink"
        }
    ],
    "sg:phone":"+1 479 756 9886",
    "sg:postcode":"72762",
    "sg:province":"AR",
    "sg:tags":[
        "eating"
    ],
    "wof:name":"Butler On The Run",
    "wof:placetype":"venue"
},
  "geometry": {"coordinates":[-94.14772499999999,36.174695],"type":"Point"}
}