{
  "type": "Feature",
  "properties": {
    "addr:full":"3304 Kibler Rd Van Buren AR 72956",
    "addr:housenumber":"3304",
    "addr:postcode":"72956",
    "addr:street":"Kibler Rd",
    "iso:country":"US",
    "sg:address":"3304 Kibler Rd",
    "sg:city":"Van Buren",
    "sg:classifiers":[
        {
            "category":"Organizations",
            "subcategory":"Religious Organization",
            "type":"Services"
        }
    ],
    "sg:phone":"+1 479 474 3588",
    "sg:postcode":"72956",
    "sg:province":"AR",
    "sg:tags":[
        "church"
    ],
    "wof:name":"Church Of God-Kibler Road",
    "wof:placetype":"venue"
},
  "geometry": {"coordinates":[-94.318181,35.43602],"type":"Point"}
}