{
  "type": "Feature",
  "properties": {
    "iso:country":"US",
    "sg:address":"200 N Jefferson Ave",
    "sg:city":"El Dorado",
    "sg:classifiers":[
        {
            "category":"Wholesale",
            "subcategory":"Durable Goods & Equipment",
            "type":"Manufacturing & Wholesale Goods"
        }
    ],
    "sg:phone":"+1 870 862 8807",
    "sg:postcode":"71730",
    "sg:province":"AR",
    "wof:name":"Loutre Land & Timber Company",
    "wof:placetype":"venue"
},
  "geometry": {"coordinates":[-92.662888,33.21328],"type":"Point"}
}