{
  "type": "Feature",
  "properties": {
    "iso:country":"US",
    "sg:address":"120 Beavers Rd",
    "sg:city":"Lake Village",
    "sg:classifiers":[
        {
            "category":"Freight",
            "type":"Transportation"
        }
    ],
    "sg:phone":"+1 870 265 3721",
    "sg:postcode":"71653",
    "sg:province":"AR",
    "sg:tags":[
        "frozen",
        "catfish",
        "refrigerator"
    ],
    "wof:name":"Bennett & Ray Farms LLC",
    "wof:placetype":"venue"
},
  "geometry": {"coordinates":[-91.390781,33.305889],"type":"Point"}
}