{
  "type": "Feature",
  "properties": {
    "addr:full":"4211 Fairview Rd Paragould AR 72450",
    "addr:housenumber":"4211",
    "addr:postcode":"72450",
    "addr:street":"Fairview Rd",
    "iso:country":"US",
    "sg:address":"4211 Fairview Rd",
    "sg:city":"Paragould",
    "sg:classifiers":[
        {
            "category":"Building & Trades",
            "subcategory":"Construction",
            "type":"Services"
        }
    ],
    "sg:phone":"+1 870 239 9216",
    "sg:postcode":"72450",
    "sg:province":"AR",
    "sg:tags":[
        "excavating",
        "contractor"
    ],
    "wof:name":"GCE Inc",
    "wof:placetype":"venue"
},
  "geometry": {"coordinates":[-90.53448299999999,36.081869],"type":"Point"}
}