{
  "type": "Feature",
  "properties": {
    "addr:full":"901 N 47th St Rogers AR 72756",
    "addr:housenumber":"901",
    "addr:postcode":"72756",
    "addr:street":"N 47Th St",
    "iso:country":"US",
    "sg:address":"901 N 47th St",
    "sg:city":"Rogers",
    "sg:classifiers":[
        {
            "category":"Real Estate",
            "subcategory":"Architect",
            "type":"Services"
        }
    ],
    "sg:phone":"+1 479 878 2462",
    "sg:postcode":"72756",
    "sg:province":"AR",
    "wof:name":"Swearinger James P",
    "wof:placetype":"venue"
},
  "geometry": {"coordinates":[-94.18049600000001,36.343601],"type":"Point"}
}