{
  "type": "Feature",
  "properties": {
    "iso:country":"US",
    "sg:address":"2115 Lake Fort Smith Rd",
    "sg:city":"Mountainburg",
    "sg:classifiers":[
        {
            "category":"Retail",
            "subcategory":"Auto Repair",
            "type":"Services"
        }
    ],
    "sg:phone":"+1 479 369 4002",
    "sg:postcode":"72946",
    "sg:province":"AR",
    "sg:tags":[
        "repairing",
        "automobile",
        "general"
    ],
    "wof:name":"Robert's Automotive",
    "wof:placetype":"venue"
},
  "geometry": {"coordinates":[-94.153581,35.651683],"type":"Point"}
}