{
  "type": "Feature",
  "properties": {
    "addr:full":"717 Elkins Rd White Hall AR 71602",
    "addr:housenumber":"717",
    "addr:postcode":"71602",
    "addr:street":"Elkins Rd",
    "iso:country":"US",
    "sg:address":"717 Elkins Rd",
    "sg:city":"White Hall",
    "sg:classifiers":[
        {
            "category":"Professional",
            "type":"Services"
        }
    ],
    "sg:phone":"+1 870 247 4034",
    "sg:postcode":"71602",
    "sg:province":"AR",
    "wof:name":"Dorthy Lockhart",
    "wof:placetype":"venue"
},
  "geometry": {"coordinates":[-92.141473,34.27156],"type":"Point"}
}