{
  "type": "Feature",
  "properties": {
    "iso:country":"US",
    "sg:address":"250 White Dr Country",
    "sg:city":"Batesville",
    "sg:classifiers":[
        {
            "category":"Bars & Pubs",
            "type":"Food & Drink"
        },
        {
            "category":"Organizations",
            "subcategory":"Community Association",
            "type":"Services"
        },
        {
            "category":"Organizations",
            "subcategory":"Membership Organization",
            "type":"Services"
        }
    ],
    "sg:phone":"+1 870 251 9932",
    "sg:postcode":"72501",
    "sg:province":"AR",
    "sg:tags":[
        "club",
        "private"
    ],
    "wof:name":"White River Country Club Inc",
    "wof:placetype":"venue"
},
  "geometry": {"coordinates":[-91.654445,35.78851],"type":"Point"}
}