{
  "type": "Feature",
  "properties": {
    "iso:country":"US",
    "sg:address":"300 Dillard St",
    "sg:city":"Jacksonport",
    "sg:classifiers":[
        {
            "category":"Organizations",
            "subcategory":"Religious Organization",
            "type":"Services"
        }
    ],
    "sg:phone":"+1 870 523 6083",
    "sg:postcode":"72075",
    "sg:province":"AR",
    "sg:tags":[
        "church"
    ],
    "wof:name":"Jacksonport Baptist Church",
    "wof:placetype":"venue"
},
  "geometry": {"coordinates":[-91.30984,35.64156],"type":"Point"}
}