{
  "type": "Feature",
  "properties": {
    "addr:full":"205 N Fredrick Magnolia AR 71753",
    "addr:housenumber":"205",
    "addr:postcode":"71753",
    "addr:street":"N Fredrick Magnolia",
    "iso:country":"US",
    "sg:address":"205 N Fredrick",
    "sg:city":"Magnolia",
    "sg:classifiers":[
        {
            "category":"Deli",
            "type":"Food & Drink"
        },
        {
            "category":"Restaurant",
            "type":"Food & Drink"
        },
        {
            "category":"Bakery",
            "type":"Food & Drink"
        }
    ],
    "sg:phone":"+1 870 234 4571",
    "sg:postcode":"71753",
    "sg:province":"AR",
    "sg:tags":[
        "delicatessen"
    ],
    "sg:website":"http://www.scottsfoods.com",
    "wof:name":"Kroger",
    "wof:placetype":"venue"
},
  "geometry": {"coordinates":[-93.224417,33.267799],"type":"Point"}
}