{
  "type": "Feature",
  "properties": {
    "iso:country":"US",
    "sg:address":"4300 Rixie Rd",
    "sg:city":"N Little Rock",
    "sg:classifiers":[
        {
            "category":"Building & Trades",
            "subcategory":"Construction",
            "type":"Services"
        }
    ],
    "sg:phone":"+1 501 664 2886",
    "sg:postcode":"72117",
    "sg:province":"AR",
    "sg:tags":[
        "insulation",
        "heat",
        "contractor"
    ],
    "sg:website":"www.masco.com",
    "wof:name":"Capitol Insulators",
    "wof:placetype":"venue"
},
  "geometry": {"coordinates":[-92.181431,34.828137],"type":"Point"}
}