{
  "type": "Feature",
  "properties": {
    "iso:country":"US",
    "sg:address":"376 Mill St",
    "sg:city":"Calion",
    "sg:classifiers":[
        {
            "category":"Organizations",
            "subcategory":"Religious Organization",
            "type":"Services"
        }
    ],
    "sg:phone":"+1 870 748 2401",
    "sg:postcode":"71724",
    "sg:province":"AR",
    "sg:tags":[
        "church"
    ],
    "wof:name":"Great Commission Church Of God",
    "wof:placetype":"venue"
},
  "geometry": {"coordinates":[-92.539664,33.332695],"type":"Point"}
}