{
  "type": "Feature",
  "properties": {
    "iso:country":"US",
    "sg:address":"2011 E Parkway Dr",
    "sg:city":"Russellville",
    "sg:classifiers":[
        {
            "category":"Manufacturing",
            "subcategory":"Lumber",
            "type":"Manufacturing & Wholesale Goods"
        }
    ],
    "sg:phone":"+1 479 967 1782",
    "sg:postcode":"72801",
    "sg:province":"AR",
    "sg:tags":[
        "hardwood",
        "flooring"
    ],
    "wof:name":"Sims Flooring Inc",
    "wof:placetype":"venue"
},
  "geometry": {"coordinates":[-93.10683299999999,35.282537],"type":"Point"}
}