{
  "type": "Feature",
  "properties": {
    "iso:country":"US",
    "sg:address":"215 Main St",
    "sg:city":"Stamps",
    "sg:classifiers":[
        {
            "category":"Building & Trades",
            "subcategory":"Equipment Rental",
            "type":"Services"
        }
    ],
    "sg:phone":"+1 870 533 2155",
    "sg:postcode":"71860",
    "sg:province":"AR",
    "sg:tags":[
        "leasing",
        "household",
        "appliance",
        "furnishing",
        "rent",
        "furniture"
    ],
    "wof:name":"Right Choice Rental Inc",
    "wof:placetype":"venue"
},
  "geometry": {"coordinates":[-93.499666,33.362184],"type":"Point"}
}