{
  "type": "Feature",
  "properties": {
    "iso:country":"US",
    "sg:address":"1008 W Pridemore Dr",
    "sg:city":"Lincoln",
    "sg:classifiers":[
        {
            "category":"Shopping",
            "type":"Retail Goods"
        }
    ],
    "sg:phone":"+1 479 824 5517",
    "sg:postcode":"72744",
    "sg:province":"AR",
    "sg:tags":[
        "merchandise"
    ],
    "wof:name":"Uncle Sams Fireworks",
    "wof:placetype":"venue"
},
  "geometry": {"coordinates":[-94.438747,35.958882],"type":"Point"}
}