{
  "type": "Feature",
  "properties": {
    "addr:full":"3060 Albert Pike Rd Hot Springs AR 71913",
    "addr:housenumber":"3060",
    "addr:postcode":"71913",
    "addr:street":"Albert Pike Rd",
    "iso:country":"US",
    "sg:address":"3060 Albert Pike Rd",
    "sg:city":"Hot Springs",
    "sg:classifiers":[
        {
            "category":"Shopping",
            "subcategory":"Discount & Variety Stores",
            "type":"Retail Goods"
        }
    ],
    "sg:phone":"+1 501 767 5660",
    "sg:postcode":"71913",
    "sg:province":"AR",
    "wof:name":"Dollar Deals",
    "wof:placetype":"venue"
},
  "geometry": {"coordinates":[-93.124994,34.502578],"type":"Point"}
}