{
  "type": "Feature",
  "properties": {
    "iso:country":"US",
    "sg:address":"1012 Highway 62 65 N 65 Bus",
    "sg:city":"Harrison",
    "sg:classifiers":[
        {
            "category":"Restaurant",
            "type":"Food & Drink"
        },
        {
            "category":"Bakery",
            "type":"Food & Drink"
        },
        {
            "category":"Food & Beverages",
            "subcategory":"Groceries & Convenience Stores",
            "type":"Retail Goods"
        }
    ],
    "sg:phone":"+1 870 741 6455",
    "sg:postcode":"72601",
    "sg:province":"AR",
    "sg:tags":[
        "shop",
        "sandwich"
    ],
    "sg:website":"http://www.neighborsmill.com",
    "wof:name":"Neighbor's Mill Bakery & Cafe",
    "wof:placetype":"venue"
},
  "geometry": {"coordinates":[-93.104775,36.241164],"type":"Point"}
}