{
  "type": "Feature",
  "properties": {
    "iso:country":"US",
    "sg:address":"1670 White Dr",
    "sg:city":"Batesville",
    "sg:classifiers":[
        {
            "category":"Professional",
            "subcategory":"Business Services",
            "type":"Services"
        }
    ],
    "sg:phone":"+1 870 793 4153",
    "sg:postcode":"72501",
    "sg:province":"AR",
    "sg:tags":[
        "medical",
        "administration"
    ],
    "wof:name":"Arkansas Spinal Cord Commission",
    "wof:placetype":"venue"
},
  "geometry": {"coordinates":[-91.626817,35.791551],"type":"Point"}
}