{
  "type": "Feature",
  "properties": {
    "iso:country":"US",
    "sg:address":"1838 Morning Star Rd",
    "sg:city":"El Dorado",
    "sg:classifiers":[
        {
            "category":"Building & Trades",
            "subcategory":"Construction",
            "type":"Services"
        }
    ],
    "sg:phone":"+1 870 881 0171",
    "sg:postcode":"71730",
    "sg:province":"AR",
    "sg:tags":[
        "hanging",
        "contractor"
    ],
    "wof:name":"Specialized Painting Inc",
    "wof:placetype":"venue"
},
  "geometry": {"coordinates":[-92.688157,33.250005],"type":"Point"}
}