{
  "type": "Feature",
  "properties": {
    "addr:full":"1411 N Hwy 62 65 Harrison AR 72601",
    "addr:housenumber":"1411;65",
    "addr:postcode":"72601",
    "addr:street":"N Hwy 62;Harrison",
    "iso:country":"US",
    "sg:address":"1411 N Hwy 62 65",
    "sg:city":"Harrison",
    "sg:classifiers":[
        {
            "category":"Retail",
            "subcategory":"Laundry & Dry Cleaning",
            "type":"Services"
        }
    ],
    "sg:phone":"+1 870 743 4966",
    "sg:postcode":"72601",
    "sg:province":"AR",
    "sg:tags":[
        "power"
    ],
    "wof:name":"Ironing Unlimited",
    "wof:placetype":"venue"
},
  "geometry": {"coordinates":[-93.140227,36.267109],"type":"Point"}
}