{
  "type": "Feature",
  "properties": {
    "iso:country":"US",
    "sg:address":"100 N Dixieland Rd Ste F3",
    "sg:city":"Rogers",
    "sg:classifiers":[
        {
            "category":"Food & Beverages",
            "subcategory":"Specialty",
            "type":"Retail Goods"
        }
    ],
    "sg:phone":"+1 479 621 9191",
    "sg:postcode":"72756",
    "sg:province":"AR",
    "wof:name":"Halloween Express",
    "wof:placetype":"venue"
},
  "geometry": {"coordinates":[-94.14376,36.334003],"type":"Point"}
}