{
  "type": "Feature",
  "properties": {
    "iso:country":"US",
    "sg:address":"1000 Watson Ave",
    "sg:city":"Springdale",
    "sg:classifiers":[
        {
            "category":"Government",
            "subcategory":"Office",
            "type":"Public Place"
        }
    ],
    "sg:phone":"+1 479 750 8185",
    "sg:postcode":"72764",
    "sg:province":"AR",
    "sg:tags":[
        "village"
    ],
    "wof:name":"Springdale Youth Ctr",
    "wof:placetype":"venue"
},
  "geometry": {"coordinates":[-94.141221,36.177628],"type":"Point"}
}