{
  "type": "Feature",
  "properties": {
    "addr:full":"2743 Lakewood Village Dr North Little Rock AR 72116",
    "addr:housenumber":"2743",
    "addr:postcode":"72116",
    "addr:street":"Lakewood Village Dr",
    "iso:country":"US",
    "sg:address":"2743 Lakewood Village Dr",
    "sg:city":"North Little Rock",
    "sg:classifiers":[
        {
            "category":"Shopping",
            "subcategory":"Pharmacy",
            "type":"Retail Goods"
        }
    ],
    "sg:phone":"+1 501 758 8723",
    "sg:postcode":"72116",
    "sg:province":"AR",
    "wof:name":"USA Drug",
    "wof:placetype":"venue"
},
  "geometry": {"coordinates":[-92.233138,34.797643],"type":"Point"}
}