{
  "type": "Feature",
  "properties": {
    "iso:country":"US",
    "sg:address":"67 Watson Blvd",
    "sg:city":"Pine Bluff",
    "sg:classifiers":[
        {
            "category":"Building & Trades",
            "subcategory":"Landscaping Services",
            "type":"Services"
        }
    ],
    "sg:phone":"+1 870 535 0054",
    "sg:postcode":"71601",
    "sg:province":"AR",
    "sg:tags":[
        "janitorial",
        "maintenance",
        "grounds"
    ],
    "wof:name":"Pro-Cut Bushhogging",
    "wof:placetype":"venue"
},
  "geometry": {"coordinates":[-92.01763099999999,34.245357],"type":"Point"}
}