{
  "type": "Feature",
  "properties": {
    "addr:full":"2800 Lakewood Village Dr N Little Rock AR 72116",
    "addr:housenumber":"2800",
    "addr:postcode":"72116",
    "addr:street":"Lakewood Village Dr N",
    "iso:country":"US",
    "sg:address":"2800 Lakewood Village Dr",
    "sg:city":"N Little Rock",
    "sg:classifiers":[
        {
            "category":"Banks & Credit Unions",
            "subcategory":"Bank",
            "type":"Services"
        }
    ],
    "sg:phone":"+1 501 791 7101",
    "sg:postcode":"72116",
    "sg:province":"AR",
    "sg:tags":[
        "cashing",
        "check"
    ],
    "wof:name":"Cash Technologies",
    "wof:placetype":"venue"
},
  "geometry": {"coordinates":[-92.231369,34.795232],"type":"Point"}
}