{
  "type": "Feature",
  "properties": {
    "iso:country":"US",
    "sg:address":"1886 California Ave SW",
    "sg:city":"Camden",
    "sg:classifiers":[
        {
            "category":"Autos & Motor Vehicles",
            "subcategory":"Automobile Sales",
            "type":"Retail Goods"
        }
    ],
    "sg:phone":"+1 870 818 0159",
    "sg:postcode":"71701",
    "sg:province":"AR",
    "sg:tags":[
        "dealers-used",
        "car",
        "used",
        "cars-wholesale",
        "new"
    ],
    "wof:name":"K & K Auto Sales",
    "wof:placetype":"venue"
},
  "geometry": {"coordinates":[-92.86735,33.549511],"type":"Point"}
}