{
  "type": "Feature",
  "properties": {
    "addr:full":"640 Cherry Ln Malvern AR 72104",
    "addr:housenumber":"640",
    "addr:postcode":"72104",
    "addr:street":"Cherry Ln",
    "iso:country":"US",
    "sg:address":"640 Cherry Ln",
    "sg:city":"Malvern",
    "sg:classifiers":[
        {
            "category":"Shopping",
            "subcategory":"Clothing, Apparel, & Fashions",
            "type":"Retail Goods"
        }
    ],
    "sg:phone":"+1 501 332 2531",
    "sg:postcode":"72104",
    "sg:province":"AR",
    "sg:tags":[
        "personal",
        "business",
        "se"
    ],
    "wof:name":"Esthers Place",
    "wof:placetype":"venue"
},
  "geometry": {"coordinates":[-92.797489,34.363194],"type":"Point"}
}