{
  "type": "Feature",
  "properties": {
    "iso:country":"US",
    "sg:address":"401 N Elm St",
    "sg:city":"Bald Knob",
    "sg:classifiers":[
        {
            "category":"Wholesale",
            "subcategory":"Farm Supplies",
            "type":"Manufacturing & Wholesale Goods"
        }
    ],
    "sg:phone":"+1 501 724 3924",
    "sg:postcode":"72010",
    "sg:province":"AR",
    "sg:tags":[
        "hardware",
        "seed"
    ],
    "wof:name":"J Collison Company Inc",
    "wof:placetype":"venue"
},
  "geometry": {"coordinates":[-91.56881,35.314713],"type":"Point"}
}