{
  "type": "Feature",
  "properties": {
    "addr:full":"13510 Bean Rd Alexander AR 72002",
    "addr:housenumber":"13510",
    "addr:postcode":"72002",
    "addr:street":"Bean Rd",
    "iso:country":"US",
    "sg:address":"13510 Bean Rd",
    "sg:city":"Alexander",
    "sg:classifiers":[
        {
            "category":"Manufacturing",
            "subcategory":"Buildings",
            "type":"Manufacturing & Wholesale Goods"
        },
        {
            "category":"Building & Trades",
            "subcategory":"Construction",
            "type":"Services"
        }
    ],
    "sg:phone":"+1 501 794 2563",
    "sg:postcode":"72002",
    "sg:province":"AR",
    "sg:tags":[
        "home",
        "builder",
        "carpenter",
        "contractor"
    ],
    "wof:name":"Burton Construction",
    "wof:placetype":"venue"
},
  "geometry": {"coordinates":[-92.59585,34.689312],"type":"Point"}
}