{
  "type": "Feature",
  "properties": {
    "iso:country":"US",
    "sg:address":"102 Highway 270",
    "sg:city":"Mena",
    "sg:classifiers":[
        {
            "category":"Restaurant",
            "type":"Food & Drink"
        }
    ],
    "sg:phone":"+1 479 243 0303",
    "sg:postcode":"71953",
    "sg:province":"AR",
    "sg:tags":[
        "pizza"
    ],
    "wof:name":"El Primo Chicago Pizza",
    "wof:placetype":"venue"
},
  "geometry": {"coordinates":[-94.20178,34.643294],"type":"Point"}
}