{
  "type": "Feature",
  "properties": {
    "iso:country":"US",
    "sg:address":"780 Equity Ave",
    "sg:city":"Conway",
    "sg:classifiers":[
        {
            "category":"Manufacturing",
            "subcategory":"Metals",
            "type":"Manufacturing & Wholesale Goods"
        },
        {
            "category":"Professional",
            "type":"Services"
        }
    ],
    "sg:phone":"+1 501 329 2519",
    "sg:postcode":"72032",
    "sg:province":"AR",
    "sg:tags":[
        "fabricator",
        "establishment"
    ],
    "wof:name":"Sfi of Arkansas LLC",
    "wof:placetype":"venue"
},
  "geometry": {"coordinates":[-92.424442,35.066162],"type":"Point"}
}