{
  "type": "Feature",
  "properties": {
    "iso:country":"US",
    "sg:address":"701 W 47th St",
    "sg:city":"N Little Rock",
    "sg:classifiers":[
        {
            "category":"Organizations",
            "subcategory":"Religious Organization",
            "type":"Services"
        }
    ],
    "sg:phone":"+1 501 753 6041",
    "sg:postcode":"72118",
    "sg:province":"AR",
    "sg:tags":[
        "church"
    ],
    "wof:name":"Levy United Methodist Church",
    "wof:placetype":"venue"
},
  "geometry": {"coordinates":[-92.274253,34.797728],"type":"Point"}
}