{
  "type": "Feature",
  "properties": {
    "iso:country":"US",
    "sg:address":"3065 N College Ave #192",
    "sg:city":"Fayetteville",
    "sg:classifiers":[
        {
            "category":"Home & Garden",
            "subcategory":"Home Furnishings",
            "type":"Retail Goods"
        }
    ],
    "sg:phone":"+1 479 283 6958",
    "sg:postcode":"72703",
    "sg:province":"AR",
    "sg:tags":[
        "blinds-venetian",
        "vertical"
    ],
    "wof:name":"A Rs Window Treatments",
    "wof:placetype":"venue"
},
  "geometry": {"coordinates":[-94.145495,36.107699],"type":"Point"}
}