{
  "type": "Feature",
  "properties": {
    "iso:country":"US",
    "sg:address":"1319 S Jefferson St",
    "sg:city":"De Witt",
    "sg:classifiers":[
        {
            "category":"Farming",
            "subcategory":"Farm",
            "type":"Manufacturing & Wholesale Goods"
        }
    ],
    "sg:phone":"+1 870 946 4105",
    "sg:postcode":"72042",
    "sg:province":"AR",
    "sg:tags":[
        "crop",
        "general"
    ],
    "wof:name":"Hxs Inc",
    "wof:placetype":"venue"
},
  "geometry": {"coordinates":[-91.337684,34.282303],"type":"Point"}
}