{
  "type": "Feature",
  "properties": {
    "iso:country":"US",
    "sg:address":"337 Hwy 62 E",
    "sg:city":"Mountain Home",
    "sg:classifiers":[
        {
            "category":"Restaurant",
            "type":"Food & Drink"
        }
    ],
    "sg:phone":"+1 870 425 7877",
    "sg:postcode":"72653",
    "sg:province":"AR",
    "sg:tags":[
        "eating"
    ],
    "wof:name":"El Charro Mexican Restaurant",
    "wof:placetype":"venue"
},
  "geometry": {"coordinates":[-92.382599,36.342124],"type":"Point"}
}