{
  "type": "Feature",
  "properties": {
    "iso:country":"US",
    "sg:address":"3616 Towson Ave",
    "sg:city":"Fort Smith",
    "sg:classifiers":[
        {
            "category":"Building & Trades",
            "subcategory":"Equipment Rental",
            "type":"Services"
        }
    ],
    "sg:phone":"+1 479 785 1966",
    "sg:postcode":"72901",
    "sg:province":"AR",
    "sg:tags":[
        "contractor"
    ],
    "sg:website":"www.rentalservice.com",
    "wof:name":"Rental Service Corp",
    "wof:placetype":"venue"
},
  "geometry": {"coordinates":[-94.422409,35.348825],"type":"Point"}
}