{
  "type": "Feature",
  "properties": {
    "addr:full":"105 Country Club Pkwy # 103 Maumelle AR 72113",
    "addr:housenumber":"105",
    "addr:postcode":"72113",
    "addr:street":"Country Club Pkwy # 103",
    "iso:country":"US",
    "sg:address":"105 Country Club Pkwy # 103",
    "sg:city":"Maumelle",
    "sg:classifiers":[
        {
            "category":"Banks & Credit Unions",
            "subcategory":"Investment Brokerage",
            "type":"Services"
        }
    ],
    "sg:phone":"+1 501 851 2931",
    "sg:postcode":"72113",
    "sg:province":"AR",
    "sg:tags":[
        "security"
    ],
    "sg:website":"http://www.edwardjones.com",
    "wof:name":"Edward Jones 57786",
    "wof:placetype":"venue"
},
  "geometry": {"coordinates":[-92.403374,34.840601],"type":"Point"}
}