{
  "type": "Feature",
  "properties": {
    "iso:country":"US",
    "sg:address":"300 Ponce de Leon Dr",
    "sg:city":"Hot Springs National",
    "sg:classifiers":[
        {
            "category":"Government",
            "subcategory":"Office",
            "type":"Public Place"
        }
    ],
    "sg:phone":"+1 501 922 4250",
    "sg:postcode":"71909",
    "sg:province":"AR",
    "sg:tags":[
        "wildlife",
        "conservation",
        "mineral",
        "land"
    ],
    "wof:name":"Ponce De Leon Golf Course",
    "wof:placetype":"venue"
},
  "geometry": {"coordinates":[-92.89349,34.659797],"type":"Point"}
}