{
  "type": "Feature",
  "properties": {
    "addr:full":"3365 N Fincher Ln Fayetteville AR 72703",
    "addr:housenumber":"3365",
    "addr:postcode":"72703",
    "addr:street":"N Fincher Ln",
    "iso:country":"US",
    "sg:address":"3365 N Fincher Ln",
    "sg:city":"Fayetteville",
    "sg:classifiers":[
        {
            "category":"Building & Trades",
            "subcategory":"Landscaping Services",
            "type":"Services"
        }
    ],
    "sg:phone":"+1 479 443 7755",
    "sg:postcode":"72703",
    "sg:province":"AR",
    "sg:tags":[
        "consultant",
        "lawn",
        "designer",
        "landscape",
        "contractor"
    ],
    "sg:website":"http://www.colonialhillslandscaping.com",
    "wof:name":"Colonial Hills Landscape Inc",
    "wof:placetype":"venue"
},
  "geometry": {"coordinates":[-94.11174099999999,36.111672],"type":"Point"}
}