{
  "type": "Feature",
  "properties": {
    "iso:country":"US",
    "sg:address":"4254 S Arkansas Ave",
    "sg:city":"Russellville",
    "sg:classifiers":[
        {
            "category":"Manufacturing",
            "subcategory":"Rubber & Plastics",
            "type":"Manufacturing & Wholesale Goods"
        }
    ],
    "sg:phone":"+1 479 967 9055",
    "sg:postcode":"72802",
    "sg:province":"AR",
    "sg:tags":[
        "polyethylene",
        "material",
        "prod",
        "plastics-finished-wholesale",
        "manufacturer"
    ],
    "sg:website":"http://www.bkpackaging.com",
    "wof:name":"Dalton - King Packaging, Inc.",
    "wof:placetype":"venue"
},
  "geometry": {"coordinates":[-93.14416799999999,35.228603],"type":"Point"}
}