{
  "type": "Feature",
  "properties": {
    "addr:full":"30 Vilanco Cutoff Vilonia AR 72173",
    "addr:housenumber":"30",
    "addr:postcode":"72173",
    "addr:street":"Vilanco Cutoff",
    "iso:country":"US",
    "sg:address":"30 Vilanco Cutoff",
    "sg:city":"Vilonia",
    "sg:classifiers":[
        {
            "category":"Professional",
            "subcategory":"Advertising",
            "type":"Services"
        }
    ],
    "sg:phone":"+1 501 796 3803",
    "sg:postcode":"72173",
    "sg:province":"AR",
    "sg:tags":[
        "mail",
        "direct"
    ],
    "wof:name":"Cap Media Inc",
    "wof:placetype":"venue"
},
  "geometry": {"coordinates":[-92.170536,35.108071],"type":"Point"}
}