{
  "type": "Feature",
  "properties": {
    "iso:country":"US",
    "sg:address":"20983 W Vanzant Rd",
    "sg:city":"Springdale",
    "sg:classifiers":[
        {
            "category":"Retail",
            "subcategory":"Auto Rental",
            "type":"Services"
        },
        {
            "category":"Retail",
            "subcategory":"Storage",
            "type":"Services"
        }
    ],
    "sg:phone":"+1 479 789 2775",
    "sg:postcode":"72764",
    "sg:province":"AR",
    "sg:tags":[
        "moving-self",
        "truck"
    ],
    "wof:name":"U Haul Moving & Storage",
    "wof:placetype":"venue"
},
  "geometry": {"coordinates":[-93.969031,36.17868],"type":"Point"}
}