{
  "type": "Feature",
  "properties": {
    "iso:country":"US",
    "sg:address":"1915 Towson Ave",
    "sg:city":"Fort Smith",
    "sg:classifiers":[
        {
            "category":"Insurance",
            "subcategory":"Insurance Agent",
            "type":"Services"
        }
    ],
    "sg:phone":"+1 479 441 3000",
    "sg:postcode":"72901",
    "sg:province":"AR",
    "wof:name":"Resolution Enterprises Inc",
    "wof:placetype":"venue"
},
  "geometry": {"coordinates":[-94.42145,35.367946],"type":"Point"}
}