{
  "type": "Feature",
  "properties": {
    "addr:full":"7095 Hwy 223 N Viola AR 72583",
    "addr:housenumber":"7095",
    "addr:postcode":"72583",
    "addr:street":"Hwy 223 N Viola",
    "iso:country":"US",
    "sg:address":"7095 Hwy 223 N",
    "sg:city":"Viola",
    "sg:classifiers":[
        {
            "category":"Freight",
            "type":"Transportation"
        }
    ],
    "sg:phone":"+1 870 458 3114",
    "sg:postcode":"72583",
    "sg:province":"AR",
    "sg:tags":[
        "operator",
        "local",
        "trucking"
    ],
    "wof:name":"Guffey Cattle & Farms LLC",
    "wof:placetype":"venue"
},
  "geometry": {"coordinates":[-91.98181200000001,36.483881],"type":"Point"}
}