{
  "type": "Feature",
  "properties": {
    "iso:country":"US",
    "sg:address":"1810 Bugscuffle Rd",
    "sg:city":"Lavaca",
    "sg:classifiers":[
        {
            "category":"Building & Trades",
            "subcategory":"Construction",
            "type":"Services"
        }
    ],
    "sg:phone":"+1 479 674 2608",
    "sg:postcode":"72941",
    "sg:province":"AR",
    "sg:tags":[
        "carpentry",
        "contractor"
    ],
    "wof:name":"Smithson Construction",
    "wof:placetype":"venue"
},
  "geometry": {"coordinates":[-94.196731,35.348451],"type":"Point"}
}