{
  "type": "Feature",
  "properties": {
    "iso:country":"US",
    "sg:address":"229 E Main St",
    "sg:city":"Gentry",
    "sg:classifiers":[
        {
            "category":"Home & Garden",
            "subcategory":"Hardware",
            "type":"Retail Goods"
        }
    ],
    "sg:phone":"+1 479 736 3000",
    "sg:postcode":"72734",
    "sg:province":"AR",
    "wof:name":"Bever's Ace Hardware",
    "wof:placetype":"venue"
},
  "geometry": {"coordinates":[-94.482124,36.267452],"type":"Point"}
}