{
  "type": "Feature",
  "properties": {
    "iso:country":"US",
    "sg:address":"305 W 22nd St",
    "sg:city":"Stuttgart",
    "sg:classifiers":[
        {
            "category":"Shopping",
            "subcategory":"Beauty & Cosmetics",
            "type":"Retail Goods"
        }
    ],
    "sg:phone":"+1 870 673 4106",
    "sg:postcode":"72160",
    "sg:province":"AR",
    "sg:tags":[
        "merchandise"
    ],
    "sg:website":"www.merlenorman.com",
    "wof:name":"Merle Norman Cosmetics",
    "wof:placetype":"venue"
},
  "geometry": {"coordinates":[-91.554993,34.479472],"type":"Point"}
}