{
  "type": "Feature",
  "properties": {
    "iso:country":"US",
    "sg:address":"8 Brewer Cir",
    "sg:city":"Bentonville",
    "sg:classifiers":[
        {
            "category":"Retail",
            "subcategory":"Laundry & Dry Cleaning",
            "type":"Services"
        }
    ],
    "sg:phone":"+1 479 273 0895",
    "sg:postcode":"72712",
    "sg:province":"AR",
    "sg:tags":[
        "cleaner",
        "fire",
        "damage",
        "rug",
        "water",
        "restoration",
        "carpet"
    ],
    "wof:name":"Majestic Carpet Cleaning Company",
    "wof:placetype":"venue"
},
  "geometry": {"coordinates":[-94.196417,36.396012],"type":"Point"}
}