{
  "type": "Feature",
  "properties": {
    "iso:country":"US",
    "sg:address":"1900 S 17th Pl",
    "sg:city":"Rogers",
    "sg:classifiers":[
        {
            "category":"Professional",
            "type":"Services"
        }
    ],
    "sg:phone":"+1 479 636 3112",
    "sg:postcode":"72758",
    "sg:province":"AR",
    "sg:tags":[
        "establishment"
    ],
    "wof:name":"Time Square",
    "wof:placetype":"venue"
},
  "geometry": {"coordinates":[-94.140315,36.310468],"type":"Point"}
}