{
  "type": "Feature",
  "properties": {
    "iso:country":"US",
    "sg:address":"309 Central Ave",
    "sg:city":"Stamps",
    "sg:classifiers":[
        {
            "category":"Personal",
            "subcategory":"Beauty Salon",
            "type":"Services"
        }
    ],
    "sg:phone":"+1 870 533 9800",
    "sg:postcode":"71860",
    "sg:province":"AR",
    "sg:tags":[
        "shop"
    ],
    "wof:name":"Cathy's Hair & Tanning Salon",
    "wof:placetype":"venue"
},
  "geometry": {"coordinates":[-93.493032,33.36034],"type":"Point"}
}