{
  "type": "Feature",
  "properties": {
    "iso:country":"US",
    "sg:address":"166 N Betty St",
    "sg:city":"Ravenden",
    "sg:classifiers":[
        {
            "category":"Farming",
            "subcategory":"Farm",
            "type":"Manufacturing & Wholesale Goods"
        }
    ],
    "sg:phone":"+1 870 869 3177",
    "sg:postcode":"72459",
    "sg:province":"AR",
    "wof:name":"Clements' Country Inc",
    "wof:placetype":"venue"
},
  "geometry": {"coordinates":[-91.24950699999999,36.237841],"type":"Point"}
}