{
  "type": "Feature",
  "properties": {
    "iso:country":"US",
    "sg:address":"410 Ouachita St",
    "sg:city":"Arkadelphia",
    "sg:classifiers":[
        {
            "category":"Fast Food",
            "type":"Food & Drink"
        },
        {
            "category":"Restaurant",
            "type":"Food & Drink"
        }
    ],
    "sg:phone":"+1 870 245 5534",
    "sg:postcode":"71998",
    "sg:province":"AR",
    "sg:tags":[
        "chicken"
    ],
    "sg:website":"http://www.chick-fil-a.com",
    "wof:name":"Chick-Fil-A",
    "wof:placetype":"venue"
},
  "geometry": {"coordinates":[-93.051344,34.124551],"type":"Point"}
}