{
  "type": "Feature",
  "properties": {
    "iso:country":"US",
    "sg:address":"821 Hogan Ln",
    "sg:city":"Conway",
    "sg:classifiers":[
        {
            "category":"Cinema",
            "subcategory":"Movie Rental",
            "type":"Entertainment"
        }
    ],
    "sg:phone":"+1 501 327 1414",
    "sg:postcode":"72034",
    "sg:province":"AR",
    "sg:tags":[
        "leasing",
        "video",
        "disc",
        "tape"
    ],
    "wof:name":"Family Entertainment Superstre",
    "wof:placetype":"venue"
},
  "geometry": {"coordinates":[-92.497976,35.091597],"type":"Point"}
}