{
  "type": "Feature",
  "properties": {
    "iso:country":"US",
    "sg:address":"537 Polk Road 69",
    "sg:city":"Mena",
    "sg:classifiers":[
        {
            "category":"Manufacturing",
            "subcategory":"Buildings",
            "type":"Manufacturing & Wholesale Goods"
        },
        {
            "category":"Building & Trades",
            "subcategory":"Construction",
            "type":"Services"
        }
    ],
    "sg:phone":"+1 479 394 7084",
    "sg:postcode":"71953",
    "sg:province":"AR",
    "sg:tags":[
        "home",
        "builder",
        "contractor"
    ],
    "wof:name":"Ryan''S Construction",
    "wof:placetype":"venue"
},
  "geometry": {"coordinates":[-93.956211,34.54342],"type":"Point"}
}