{
  "type": "Feature",
  "properties": {
    "iso:country":"US",
    "sg:address":"5511 W Republican Rd",
    "sg:city":"Jacksonville",
    "sg:classifiers":[
        {
            "category":"Building & Trades",
            "subcategory":"Construction",
            "type":"Services"
        }
    ],
    "sg:phone":"+1 501 988 2929",
    "sg:postcode":"72076",
    "sg:province":"AR",
    "sg:tags":[
        "contractor"
    ],
    "wof:name":"Marble Shop",
    "wof:placetype":"venue"
},
  "geometry": {"coordinates":[-92.181983,34.940785],"type":"Point"}
}