{
  "type": "Feature",
  "properties": {
    "addr:full":"1730 E Highland Dr Jonesboro AR 72401",
    "addr:housenumber":"1730",
    "addr:postcode":"72401",
    "addr:street":"E Highland Dr",
    "iso:country":"US",
    "sg:address":"1730 E Highland Dr",
    "sg:city":"Jonesboro",
    "sg:classifiers":[
        {
            "category":"Restaurant",
            "type":"Food & Drink"
        }
    ],
    "sg:menulink":"http://www.allmenus.com/ar/jonesboro/121608-fazolis/menu/",
    "sg:phone":"+1 870 931 1300",
    "sg:postcode":"72401",
    "sg:province":"AR",
    "sg:tags":[
        "italian"
    ],
    "wof:name":"Fazoli's",
    "wof:placetype":"venue"
},
  "geometry": {"coordinates":[-90.686384,35.821223],"type":"Point"}
}