{
  "type": "Feature",
  "properties": {
    "iso:country":"US",
    "sg:address":"410 W 3rd St",
    "sg:city":"Little Rock",
    "sg:classifiers":[
        {
            "category":"Professional",
            "subcategory":"Management & Consulting",
            "type":"Services"
        }
    ],
    "sg:phone":"+1 501 375 1233",
    "sg:postcode":"72201",
    "sg:province":"AR",
    "wof:name":"Rounsavall Investigations",
    "wof:placetype":"venue"
},
  "geometry": {"coordinates":[-92.27475099999999,34.74676],"type":"Point"}
}