{
  "type": "Feature",
  "properties": {
    "iso:country":"US",
    "sg:address":"714 Short St",
    "sg:city":"England",
    "sg:classifiers":[
        {
            "category":"Retail",
            "subcategory":"Repair Shop",
            "type":"Services"
        },
        {
            "category":"Professional",
            "subcategory":"Detective & Security Services",
            "type":"Services"
        }
    ],
    "sg:phone":"+1 501 842 8422",
    "sg:postcode":"72046",
    "sg:province":"AR",
    "sg:tags":[
        "skip",
        "tracing",
        "bail",
        "bond"
    ],
    "wof:name":"Harper Bail Bond Arvis",
    "wof:placetype":"venue"
},
  "geometry": {"coordinates":[-91.968537,34.53823],"type":"Point"}
}