{
  "type": "Feature",
  "properties": {
    "iso:country":"US",
    "sg:address":"15765 Promised Land Ln N",
    "sg:city":"Trumann",
    "sg:classifiers":[
        {
            "category":"Organizations",
            "subcategory":"Religious Organization",
            "type":"Services"
        }
    ],
    "sg:phone":"+1 870 483 2343",
    "sg:postcode":"72472",
    "sg:province":"AR",
    "wof:name":"First General Baptist Church",
    "wof:placetype":"venue"
},
  "geometry": {"coordinates":[-90.57140800000001,35.678091],"type":"Point"}
}