{
  "type": "Feature",
  "properties": {
    "addr:full":"6632 Holt Ave E Lead Hill AR 72644",
    "addr:housenumber":"6632",
    "addr:postcode":"72644",
    "addr:street":"Holt Ave E",
    "iso:country":"US",
    "sg:address":"6632 Holt Ave E",
    "sg:city":"Lead Hill",
    "sg:classifiers":[
        {
            "category":"Organizations",
            "subcategory":"Religious Organization",
            "type":"Services"
        }
    ],
    "sg:phone":"+1 870 436 5619",
    "sg:postcode":"72644",
    "sg:province":"AR",
    "wof:name":"Southside Baptist Church",
    "wof:placetype":"venue"
},
  "geometry": {"coordinates":[-92.90707999999999,36.395727],"type":"Point"}
}