{
  "type": "Feature",
  "properties": {
    "iso:country":"US",
    "sg:address":"106 E Cedar St",
    "sg:city":"Warren",
    "sg:classifiers":[
        {
            "category":"Restaurant",
            "type":"Food & Drink"
        }
    ],
    "sg:phone":"+1 870 226 3920",
    "sg:postcode":"71671",
    "sg:province":"AR",
    "sg:tags":[
        "shop",
        "sandwich",
        "eating"
    ],
    "wof:name":"The Sandwich Shop",
    "wof:placetype":"venue"
},
  "geometry": {"coordinates":[-92.064199,33.61441],"type":"Point"}
}