{
  "type": "Feature",
  "properties": {
    "iso:country":"US",
    "sg:address":"501 Woodlane Dr",
    "sg:city":"Little Rock",
    "sg:classifiers":[
        {
            "category":"Health Services",
            "subcategory":"Hospital",
            "type":"Services"
        },
        {
            "category":"Social Services",
            "type":"Services"
        }
    ],
    "sg:phone":"+1 501 372 7062",
    "sg:postcode":"72201",
    "sg:province":"AR",
    "sg:tags":[
        "mental",
        "association",
        "trade"
    ],
    "sg:website":"www.mhca.org",
    "wof:name":"Mental Health Council Arkansas",
    "wof:placetype":"venue"
},
  "geometry": {"coordinates":[-92.287965,34.745411],"type":"Point"}
}