{
  "type": "Feature",
  "properties": {
    "iso:country":"US",
    "sg:address":"368 Polk Road 50",
    "sg:city":"Mena",
    "sg:classifiers":[
        {
            "category":"Organizations",
            "subcategory":"Membership Organization",
            "type":"Services"
        }
    ],
    "sg:phone":"+1 479 394 5682",
    "sg:postcode":"71953",
    "sg:province":"OK",
    "sg:tags":[
        "society",
        "humane"
    ],
    "wof:name":"Humane Society Of The Ouachita",
    "wof:placetype":"venue"
},
  "geometry": {"coordinates":[-94.28737700000001,34.552444],"type":"Point"}
}