{
  "type": "Feature",
  "properties": {
    "addr:full":"3 Rackwick Cir Bella Vista AR 72715",
    "addr:housenumber":"3",
    "addr:postcode":"72715",
    "addr:street":"Rackwick Cir",
    "iso:country":"US",
    "sg:address":"3 Rackwick Cir",
    "sg:city":"Bella Vista",
    "sg:classifiers":[
        {
            "category":"Professional",
            "subcategory":"Research",
            "type":"Services"
        }
    ],
    "sg:phone":"+1 479 855 6096",
    "sg:postcode":"72715",
    "sg:province":"AR",
    "sg:tags":[
        "fund"
    ],
    "wof:name":"Ransom Group",
    "wof:placetype":"venue"
},
  "geometry": {"coordinates":[-94.361192,36.463879],"type":"Point"}
}