{
  "type": "Feature",
  "properties": {
    "iso:country":"US",
    "sg:address":"320 W Boswell St",
    "sg:city":"Batesville",
    "sg:classifiers":[
        {
            "category":"Home & Garden",
            "subcategory":"Building Materials",
            "type":"Retail Goods"
        }
    ],
    "sg:phone":"+1 870 793 6211",
    "sg:postcode":"72501",
    "sg:province":"AR",
    "sg:tags":[
        "glass",
        "window",
        "plate"
    ],
    "wof:name":"Abe's Glass & Lock Co",
    "wof:placetype":"venue"
},
  "geometry": {"coordinates":[-91.655136,35.766975],"type":"Point"}
}