{
  "type": "Feature",
  "properties": {
    "addr:full":"2010 Brazil Ave Fort Smith AR 72908",
    "addr:housenumber":"2010",
    "addr:postcode":"72908",
    "addr:street":"Brazil Ave",
    "iso:country":"US",
    "sg:address":"2010 Brazil Ave",
    "sg:city":"Fort Smith",
    "sg:classifiers":[
        {
            "category":"Health Services",
            "subcategory":"Nursing And Care Facility",
            "type":"Services"
        }
    ],
    "sg:phone":"+1 479 646 9739",
    "sg:postcode":"72908",
    "sg:province":"AR",
    "sg:tags":[
        "intermediate"
    ],
    "wof:name":"Brazil Group Home",
    "wof:placetype":"venue"
},
  "geometry": {"coordinates":[-94.417672,35.326153],"type":"Point"}
}