{
  "type": "Feature",
  "properties": {
    "iso:country":"US",
    "sg:address":"230 Walnut",
    "sg:city":"Helena",
    "sg:classifiers":[
        {
            "category":"Retail",
            "subcategory":"Funeral Services",
            "type":"Services"
        }
    ],
    "sg:phone":"+1 870 338 8080",
    "sg:postcode":"72342",
    "sg:province":"AR",
    "sg:tags":[
        "director",
        "embalmer"
    ],
    "wof:name":"J M Calhoun Funeral Home Inc",
    "wof:placetype":"venue"
},
  "geometry": {"coordinates":[-90.58734699999999,34.524031],"type":"Point"}
}