{
  "type": "Feature",
  "properties": {
    "addr:full":"3737 E Broad St Texarkana AR 71854",
    "addr:housenumber":"3737",
    "addr:postcode":"71854",
    "addr:street":"E Broad St",
    "iso:country":"US",
    "sg:address":"3737 E Broad St",
    "sg:city":"Texarkana",
    "sg:classifiers":[
        {
            "category":"Government",
            "subcategory":"Office",
            "type":"Public Place"
        }
    ],
    "sg:phone":"+1 870 779 1141",
    "sg:postcode":"71854",
    "sg:province":"AR",
    "wof:name":"Arkansas Service For The Blind",
    "wof:placetype":"venue"
},
  "geometry": {"coordinates":[-94.00465199999999,33.452228],"type":"Point"}
}