{
  "type": "Feature",
  "properties": {
    "addr:full":"502 Hwy 425 S Monticello AR 71655",
    "addr:housenumber":"502",
    "addr:postcode":"71655",
    "addr:street":"Hwy 425 S",
    "iso:country":"US",
    "sg:address":"502 Hwy 425 S",
    "sg:city":"Monticello",
    "sg:classifiers":[
        {
            "category":"Retail",
            "subcategory":"Auto Rental",
            "type":"Services"
        }
    ],
    "sg:phone":"+1 870 460 0871",
    "sg:postcode":"71655",
    "sg:province":"AR",
    "sg:tags":[
        "renting",
        "truck",
        "leasing"
    ],
    "wof:name":"U-Haul Co",
    "wof:placetype":"venue"
},
  "geometry": {"coordinates":[-91.802837,33.623108],"type":"Point"}
}