{
  "type": "Feature",
  "properties": {
    "iso:country":"US",
    "sg:address":"2213 E Harding Ave",
    "sg:city":"Pine Bluff",
    "sg:classifiers":[
        {
            "category":"Restaurant",
            "type":"Food & Drink"
        }
    ],
    "sg:phone":"+1 870 536 3838",
    "sg:postcode":"71601",
    "sg:province":"AR",
    "sg:tags":[
        "eating"
    ],
    "wof:name":"Hardees",
    "wof:placetype":"venue"
},
  "geometry": {"coordinates":[-91.978376,34.213206],"type":"Point"}
}