{
  "type": "Feature",
  "properties": {
    "iso:country":"US",
    "sg:address":"207 Sugartree Ln",
    "sg:city":"Mena",
    "sg:classifiers":[
        {
            "category":"Farming",
            "subcategory":"Farm",
            "type":"Manufacturing & Wholesale Goods"
        }
    ],
    "sg:phone":"+1 479 437 3231",
    "sg:postcode":"71953",
    "sg:province":"AR",
    "wof:name":"Blind Squirrel Ranch",
    "wof:placetype":"venue"
},
  "geometry": {"coordinates":[-94.15160299999999,34.529164],"type":"Point"}
}