{
  "type": "Feature",
  "properties": {
    "iso:country":"US",
    "sg:address":"344 Hwy 64 E",
    "sg:city":"Conway",
    "sg:classifiers":[
        {
            "category":"Home & Garden",
            "subcategory":"Garden Supply",
            "type":"Retail Goods"
        }
    ],
    "sg:phone":"+1 501 450 7313",
    "sg:postcode":"72032",
    "sg:province":"AR",
    "wof:name":"Paulks Nursery",
    "wof:placetype":"venue"
},
  "geometry": {"coordinates":[-92.349236,35.085553],"type":"Point"}
}