{
  "type": "Feature",
  "properties": {
    "iso:country":"US",
    "sg:address":"405 S Midway",
    "sg:city":"Marvell",
    "sg:classifiers":[
        {
            "category":"Education",
            "subcategory":"Library",
            "type":"Public Place"
        },
        {
            "category":"Personal",
            "type":"Services"
        }
    ],
    "sg:phone":"+1 870 829 2971",
    "sg:postcode":"72366",
    "sg:province":"AR",
    "wof:name":"Tri-County Genealogy Society",
    "wof:placetype":"venue"
},
  "geometry": {"coordinates":[-90.910465,34.556227],"type":"Point"}
}