{
  "type": "Feature",
  "properties": {
    "iso:country":"US",
    "sg:address":"7624 W 40th St",
    "sg:city":"Little Rock",
    "sg:classifiers":[
        {
            "category":"Organizations",
            "subcategory":"Religious Organization",
            "type":"Services"
        }
    ],
    "sg:phone":"+1 501 565 4622",
    "sg:postcode":"72204",
    "sg:province":"AR",
    "sg:tags":[
        "church"
    ],
    "wof:name":"Rosedale Baptist Church Inc",
    "wof:placetype":"venue"
},
  "geometry": {"coordinates":[-92.360924,34.716866],"type":"Point"}
}