{
  "type": "Feature",
  "properties": {
    "addr:full":"601 Highway 71 N Mena AR 71953",
    "addr:housenumber":"601",
    "addr:postcode":"71953",
    "addr:street":"Highway 71 N",
    "iso:country":"US",
    "sg:address":"601 Highway 71 N",
    "sg:city":"Mena",
    "sg:classifiers":[
        {
            "category":"Personal",
            "subcategory":"Beauty Salon",
            "type":"Services"
        }
    ],
    "sg:phone":"+1 479 394 2374",
    "sg:postcode":"71953",
    "sg:province":"AR",
    "wof:name":"Yankee Clipper",
    "wof:placetype":"venue"
},
  "geometry": {"coordinates":[-94.20478799999999,34.594341],"type":"Point"}
}