{
  "type": "Feature",
  "properties": {
    "iso:country":"US",
    "sg:address":"4201 John Barrow Rd",
    "sg:city":"Little Rock",
    "sg:classifiers":[
        {
            "category":"Organizations",
            "subcategory":"Non-profit Organization",
            "type":"Services"
        }
    ],
    "sg:phone":"+1 501 562 0507",
    "sg:postcode":"72204",
    "sg:province":"AR",
    "sg:tags":[
        "info",
        "addiction",
        "abuse",
        "treatment",
        "drug"
    ],
    "wof:name":"Sober Living Inc",
    "wof:placetype":"venue"
},
  "geometry": {"coordinates":[-92.373257,34.713547],"type":"Point"}
}