{
  "type": "Feature",
  "properties": {
    "iso:country":"US",
    "sg:address":"100 N Aster St",
    "sg:city":"Greenwood",
    "sg:classifiers":[
        {
            "category":"Shopping",
            "subcategory":"Used Merchandise",
            "type":"Retail Goods"
        }
    ],
    "sg:phone":"+1 479 996 8930",
    "sg:postcode":"72936",
    "sg:province":"AR",
    "wof:name":"Nanas Attic",
    "wof:placetype":"venue"
},
  "geometry": {"coordinates":[-94.254509,35.215151],"type":"Point"}
}