{
  "type": "Feature",
  "properties": {
    "addr:full":"7010 Ford Rd Hensley AR 72065",
    "addr:housenumber":"7010",
    "addr:postcode":"72065",
    "addr:street":"Ford Rd",
    "iso:country":"US",
    "sg:address":"7010 Ford Rd",
    "sg:city":"Hensley",
    "sg:classifiers":[
        {
            "category":"Social Services",
            "subcategory":"Child Care",
            "type":"Services"
        }
    ],
    "sg:phone":"+1 501 888 3046",
    "sg:postcode":"72065",
    "sg:province":"AR",
    "sg:tags":[
        "day"
    ],
    "wof:name":"Miss Debbies Day Care",
    "wof:placetype":"venue"
},
  "geometry": {"coordinates":[-92.363073,34.535844],"type":"Point"}
}