{
  "type": "Feature",
  "properties": {
    "iso:country":"US",
    "sg:address":"1711 Country Club Rd",
    "sg:city":"Paragould",
    "sg:classifiers":[
        {
            "category":"Building & Trades",
            "subcategory":"Construction",
            "type":"Services"
        }
    ],
    "sg:phone":"+1 870 236 2170",
    "sg:postcode":"72450",
    "sg:province":"AR",
    "sg:tags":[
        "concrete",
        "contractor"
    ],
    "wof:name":"G & G Construction & Concrete",
    "wof:placetype":"venue"
},
  "geometry": {"coordinates":[-90.509875,36.070859],"type":"Point"}
}