{
  "type": "Feature",
  "properties": {
    "iso:country":"US",
    "sg:address":"3511 SE J St",
    "sg:city":"Bentonville",
    "sg:classifiers":[
        {
            "category":"Home & Garden",
            "subcategory":"Building Materials",
            "type":"Retail Goods"
        }
    ],
    "sg:phone":"+1 479 273 5188",
    "sg:postcode":"72712",
    "sg:province":"AR",
    "sg:tags":[
        "paint"
    ],
    "wof:name":"AWC Paint Ctr",
    "wof:placetype":"venue"
},
  "geometry": {"coordinates":[-94.197487,36.337294],"type":"Point"}
}