{
  "type": "Feature",
  "properties": {
    "iso:country":"US",
    "sg:address":"10301 Maumelle Blvd",
    "sg:city":"N Little Rock",
    "sg:classifiers":[
        {
            "category":"Communications",
            "subcategory":"Radio Station",
            "type":"Services"
        }
    ],
    "sg:phone":"+1 501 812 9700",
    "sg:postcode":"72113",
    "sg:province":"AR",
    "sg:tags":[
        "company",
        "broadcasting"
    ],
    "wof:name":"KWLR",
    "wof:placetype":"venue"
},
  "geometry": {"coordinates":[-92.371253,34.822504],"type":"Point"}
}