{
  "type": "Feature",
  "properties": {
    "iso:country":"US",
    "sg:address":"110 E 3rd St",
    "sg:city":"Grove",
    "sg:phone":"+1 918 786 7070",
    "sg:postcode":"74344",
    "sg:province":"OK",
    "sg:website":"http://www.centercinemas.com/grove/",
    "wof:name":"Grove Cinema 6",
    "wof:placetype":"venue"
},
  "geometry": {"coordinates":[-94.76794,36.593456],"type":"Point"}
}