{
  "type": "Feature",
  "properties": {
    "addr:full":"5800 Commerce Ct Sherwood AR 72120",
    "addr:housenumber":"5800",
    "addr:postcode":"72120",
    "addr:street":"Commerce Ct",
    "iso:country":"US",
    "sg:address":"5800 Commerce Ct",
    "sg:city":"Sherwood",
    "sg:classifiers":[
        {
            "category":"Manufacturing",
            "subcategory":"Apparel",
            "type":"Manufacturing & Wholesale Goods"
        }
    ],
    "sg:phone":"+1 501 833 2105",
    "sg:postcode":"72120",
    "sg:province":"AR",
    "sg:tags":[
        "closet",
        "accessory"
    ],
    "sg:website":"www.closetfactory.com",
    "wof:name":"Closet Factory",
    "wof:placetype":"venue"
},
  "geometry": {"coordinates":[-92.199645,34.823481],"type":"Point"}
}