{
  "type": "Feature",
  "properties": {
    "iso:country":"US",
    "sg:address":"1117 Washington St",
    "sg:city":"Little Rock",
    "sg:classifiers":[
        {
            "category":"Recreation",
            "type":"Entertainment"
        }
    ],
    "sg:phone":"+1 501 372 9242",
    "sg:postcode":"72204",
    "sg:province":"AR",
    "sg:tags":[
        "club",
        "membership"
    ],
    "wof:name":"Falcon Riders",
    "wof:placetype":"venue"
},
  "geometry": {"coordinates":[-92.323648,34.741398],"type":"Point"}
}