{
  "type": "Feature",
  "properties": {
    "iso:country":"US",
    "sg:address":"1003 Pratt Cir",
    "sg:city":"Jonesboro",
    "sg:classifiers":[
        {
            "category":"Building & Trades",
            "subcategory":"Construction",
            "type":"Services"
        }
    ],
    "sg:phone":"+1 870 935 8042",
    "sg:postcode":"72401",
    "sg:province":"AR",
    "sg:tags":[
        "masonry",
        "contractor"
    ],
    "wof:name":"R & G Masonry",
    "wof:placetype":"venue"
},
  "geometry": {"coordinates":[-90.691348,35.860377],"type":"Point"}
}