{
  "type": "Feature",
  "properties": {
    "iso:country":"US",
    "sg:address":"218 E Emma Ave",
    "sg:city":"Springdale",
    "sg:classifiers":[
        {
            "category":"Shopping",
            "subcategory":"Gifts & Souvenirs",
            "type":"Retail Goods"
        }
    ],
    "sg:phone":"+1 479 756 9985",
    "sg:postcode":"72764",
    "sg:province":"AR",
    "sg:tags":[
        "shop",
        "sewing",
        "alteration"
    ],
    "wof:name":"Bella's Clothing & Gifts",
    "wof:placetype":"venue"
},
  "geometry": {"coordinates":[-94.129204,36.184799],"type":"Point"}
}