{
  "type": "Feature",
  "properties": {
    "addr:full":"1663 N Heights Ave Batesville AR 72501",
    "addr:housenumber":"1663",
    "addr:postcode":"72501",
    "addr:street":"N Heights Ave",
    "iso:country":"US",
    "sg:address":"1663 N Heights Ave",
    "sg:city":"Batesville",
    "sg:classifiers":[
        {
            "category":"Professional",
            "type":"Services"
        }
    ],
    "sg:phone":"+1 870 793 9887",
    "sg:postcode":"72501",
    "sg:province":"AR",
    "wof:name":"Johnathan Abbott",
    "wof:placetype":"venue"
},
  "geometry": {"coordinates":[-91.659274,35.782835],"type":"Point"}
}