{
  "type": "Feature",
  "properties": {
    "addr:full":"130 School Dr Wickes AR 71973",
    "addr:housenumber":"130",
    "addr:postcode":"71973",
    "addr:street":"School Dr Wickes",
    "iso:country":"US",
    "sg:address":"130 School Dr",
    "sg:city":"Wickes",
    "sg:classifiers":[
        {
            "category":"Education",
            "subcategory":"School",
            "type":"Public Place"
        }
    ],
    "sg:phone":"+1 870 385 2346",
    "sg:postcode":"71973",
    "sg:province":"AR",
    "wof:name":"Wickes Elementary School",
    "wof:placetype":"venue"
},
  "geometry": {"coordinates":[-94.33259700000001,34.298129],"type":"Point"}
}