{
  "type": "Feature",
  "properties": {
    "iso:country":"US",
    "sg:address":"700 W B St",
    "sg:city":"Russellville",
    "sg:classifiers":[
        {
            "category":"Professional",
            "subcategory":"Lawyer & Legal Services",
            "type":"Services"
        }
    ],
    "sg:phone":"+1 479 968 5400",
    "sg:postcode":"72801",
    "sg:province":"AR",
    "sg:tags":[
        "attorney"
    ],
    "wof:name":"Jon R Sanford Pa",
    "wof:placetype":"venue"
},
  "geometry": {"coordinates":[-93.139783,35.280758],"type":"Point"}
}