{
  "type": "Feature",
  "properties": {
    "iso:country":"US",
    "sg:address":"4012 W Mount Comfort Rd",
    "sg:city":"Fayetteville",
    "sg:classifiers":[
        {
            "category":"Manufacturing",
            "subcategory":"Toys & Sporting Goods",
            "type":"Manufacturing & Wholesale Goods"
        }
    ],
    "sg:phone":"+1 479 443 1858",
    "sg:postcode":"72704",
    "sg:province":"AR",
    "sg:tags":[
        "mfg"
    ],
    "wof:name":"B B W Investments Inc",
    "wof:placetype":"venue"
},
  "geometry": {"coordinates":[-94.21684,36.092757],"type":"Point"}
}