{
  "type": "Feature",
  "properties": {
    "iso:country":"US",
    "sg:address":"791 Walker St",
    "sg:city":"Centerton",
    "sg:classifiers":[
        {
            "category":"Banks & Credit Unions",
            "subcategory":"Investment Brokerage",
            "type":"Services"
        }
    ],
    "sg:phone":"+1 479 381 6191",
    "sg:postcode":"72719",
    "sg:province":"AR",
    "sg:tags":[
        "trust"
    ],
    "wof:name":"Servant's Heart Of Northwest Arkansas, Inc.",
    "wof:placetype":"venue"
},
  "geometry": {"coordinates":[-94.290795,36.368829],"type":"Point"}
}