{
  "type": "Feature",
  "properties": {
    "iso:country":"US",
    "sg:address":"303 W Stillwell Ave",
    "sg:city":"De Queen",
    "sg:classifiers":[
        {
            "category":"Recreation",
            "type":"Entertainment"
        }
    ],
    "sg:phone":"+1 870 584 3343",
    "sg:postcode":"71832",
    "sg:province":"AR",
    "sg:tags":[
        "martial",
        "arts",
        "instruction"
    ],
    "wof:name":"De Queen Taekwondo Academy",
    "wof:placetype":"venue"
},
  "geometry": {"coordinates":[-94.341458,34.036672],"type":"Point"}
}