{
  "type": "Feature",
  "properties": {
    "addr:full":"103 E 35th St Texarkana AR 71854",
    "addr:housenumber":"103",
    "addr:postcode":"71854",
    "addr:street":"E 35Th St",
    "iso:country":"US",
    "sg:address":"103 E 35th St",
    "sg:city":"Texarkana",
    "sg:classifiers":[
        {
            "category":"Wholesale",
            "subcategory":"Motor Vehicles",
            "type":"Manufacturing & Wholesale Goods"
        }
    ],
    "sg:phone":"+1 870 779 1108",
    "sg:postcode":"71854",
    "sg:province":"AR",
    "wof:name":"Texarkana Wholesale",
    "wof:placetype":"venue"
},
  "geometry": {"coordinates":[-94.041814,33.45675],"type":"Point"}
}