{
  "type": "Feature",
  "properties": {
    "iso:country":"US",
    "sg:address":"212 Brookswood Rd",
    "sg:city":"Sherwood",
    "sg:classifiers":[
        {
            "category":"Autos & Motor Vehicles",
            "subcategory":"Automobile Sales",
            "type":"Retail Goods"
        }
    ],
    "sg:phone":"+1 501 231 4888",
    "sg:postcode":"72120",
    "sg:province":"AR",
    "sg:tags":[
        "new",
        "car"
    ],
    "wof:name":"Harvey Penn Auto Sales",
    "wof:placetype":"venue"
},
  "geometry": {"coordinates":[-92.191103,34.829735],"type":"Point"}
}