{
  "type": "Feature",
  "properties": {
    "iso:country":"US",
    "sg:address":"309 W Van Buren",
    "sg:city":"Eureka Springs",
    "sg:classifiers":[
        {
            "category":"Bars & Pubs",
            "type":"Food & Drink"
        }
    ],
    "sg:phone":"+1 479 253 8102",
    "sg:postcode":"72632",
    "sg:province":"AR",
    "sg:tags":[
        "bar"
    ],
    "wof:name":"Center Street South Rest & Bar",
    "wof:placetype":"venue"
},
  "geometry": {"coordinates":[-93.770016,36.421148],"type":"Point"}
}