{
  "type": "Feature",
  "properties": {
    "iso:country":"US",
    "sg:address":"825 N Greenwich Ave",
    "sg:city":"Russellville",
    "sg:classifiers":[
        {
            "category":"Social Services",
            "subcategory":"Child Care",
            "type":"Services"
        }
    ],
    "sg:phone":"+1 479 968 4545",
    "sg:postcode":"72801",
    "sg:province":"AR",
    "sg:tags":[
        "day"
    ],
    "wof:name":"A Happy Campers Pre Schl Nurs",
    "wof:placetype":"venue"
},
  "geometry": {"coordinates":[-93.125441,35.286764],"type":"Point"}
}