{
  "type": "Feature",
  "properties": {
    "addr:full":"8607 Linda Ln Little Rock AR 72227",
    "addr:housenumber":"8607",
    "addr:postcode":"72227",
    "addr:street":"Linda Ln",
    "iso:country":"US",
    "sg:address":"8607 Linda Ln",
    "sg:city":"Little Rock",
    "sg:classifiers":[
        {
            "category":"Shopping",
            "subcategory":"Computers & Home Electronics",
            "type":"Retail Goods"
        }
    ],
    "sg:phone":"+1 501 352 0485",
    "sg:postcode":"72227",
    "sg:province":"AR",
    "sg:tags":[
        "equipment",
        "satellite",
        "system"
    ],
    "wof:name":"Wolf Satellite",
    "wof:placetype":"venue"
},
  "geometry": {"coordinates":[-92.370147,34.762887],"type":"Point"}
}