{
  "type": "Feature",
  "properties": {
    "iso:country":"US",
    "sg:address":"709 W Commercial St",
    "sg:city":"Ozark",
    "sg:classifiers":[
        {
            "category":"Restaurant",
            "type":"Food & Drink"
        }
    ],
    "sg:menulink":"http://www.allmenus.com/ar/white-oak/231335-sonic/menu/",
    "sg:phone":"+1 479 667 1176",
    "sg:postcode":"72949",
    "sg:province":"AR",
    "sg:tags":[
        "burger",
        "american"
    ],
    "wof:name":"Sonic",
    "wof:placetype":"venue"
},
  "geometry": {"coordinates":[-93.832134,35.487507],"type":"Point"}
}