{
  "type": "Feature",
  "properties": {
    "iso:country":"US",
    "sg:address":"606 W Commerce Dr 3",
    "sg:city":"Bryant",
    "sg:classifiers":[
        {
            "category":"Insurance",
            "subcategory":"Insurance Agent",
            "type":"Services"
        },
        {
            "category":"Insurance",
            "subcategory":"Hazard Insurance",
            "type":"Services"
        },
        {
            "category":"Insurance",
            "subcategory":"Title Insurance",
            "type":"Services"
        },
        {
            "category":"Insurance",
            "subcategory":"Health Insurance",
            "type":"Services"
        },
        {
            "category":"Insurance",
            "subcategory":"Life Insurance",
            "type":"Services"
        }
    ],
    "sg:phone":"+1 501 847 8155",
    "sg:postcode":"72022",
    "sg:province":"AR",
    "sg:tags":[
        "business",
        "auto",
        "commercial",
        "homeowner",
        "property",
        "casualty"
    ],
    "sg:website":"http://www.farmersagent.com/rjones6",
    "wof:name":"Jones, Ronald - Farmers Insurance",
    "wof:placetype":"venue"
},
  "geometry": {"coordinates":[-92.501941,34.621],"type":"Point"}
}