{
  "type": "Feature",
  "properties": {
    "iso:country":"US",
    "sg:address":"908 Queen Annes Lace Dr",
    "sg:city":"Fayetteville",
    "sg:classifiers":[
        {
            "category":"Professional",
            "type":"Services"
        }
    ],
    "sg:phone":"+1 479 251 7450",
    "sg:postcode":"72704",
    "sg:province":"AR",
    "sg:tags":[
        "establishment"
    ],
    "wof:name":"Tintagel Net Solutions Group",
    "wof:placetype":"venue"
},
  "geometry": {"coordinates":[-94.222669,36.077307],"type":"Point"}
}