{
  "type": "Feature",
  "properties": {
    "addr:full":"120 N Thompson St Springdale AR 72764",
    "addr:housenumber":"120",
    "addr:postcode":"72764",
    "addr:street":"N Thompson St",
    "iso:country":"US",
    "sg:address":"120 N Thompson St",
    "sg:city":"Springdale",
    "sg:classifiers":[
        {
            "category":"Food & Beverages",
            "subcategory":"Groceries & Convenience Stores",
            "type":"Retail Goods"
        }
    ],
    "sg:phone":"+1 479 751 2463",
    "sg:postcode":"72764",
    "sg:province":"AR",
    "sg:tags":[
        "grocer"
    ],
    "wof:name":"Tienda LA Esultana",
    "wof:placetype":"venue"
},
  "geometry": {"coordinates":[-94.138533,36.186343],"type":"Point"}
}