{
  "type": "Feature",
  "properties": {
    "addr:full":"1624 Fresno St Fort Smith AR 72901",
    "addr:housenumber":"1624",
    "addr:postcode":"72901",
    "addr:street":"Fresno St",
    "iso:country":"US",
    "sg:address":"1624 Fresno St",
    "sg:city":"Fort Smith",
    "sg:classifiers":[
        {
            "category":"Banks & Credit Unions",
            "subcategory":"Bank",
            "type":"Services"
        }
    ],
    "sg:phone":"+1 479 561 0039",
    "sg:postcode":"72901",
    "sg:province":"AR",
    "sg:tags":[
        "banking",
        "system"
    ],
    "wof:name":"Veri-Check",
    "wof:placetype":"venue"
},
  "geometry": {"coordinates":[-94.41328799999999,35.351655],"type":"Point"}
}