{
  "type": "Feature",
  "properties": {
    "iso:country":"US",
    "sg:address":"1028 2nd St",
    "sg:city":"Earle",
    "sg:classifiers":[
        {
            "category":"Retail",
            "subcategory":"Repair Shop",
            "type":"Services"
        }
    ],
    "sg:phone":"+1 870 792 8717",
    "sg:postcode":"72331",
    "sg:province":"AR",
    "sg:tags":[
        "appliance"
    ],
    "wof:name":"Vaughn Appliance Co",
    "wof:placetype":"venue"
},
  "geometry": {"coordinates":[-90.464344,35.270827],"type":"Point"}
}