{
  "type": "Feature",
  "properties": {
    "iso:country":"US",
    "sg:address":"305 S Whitehead Dr",
    "sg:city":"De Witt",
    "sg:classifiers":[
        {
            "category":"Food & Beverages",
            "subcategory":"Groceries & Convenience Stores",
            "type":"Retail Goods"
        }
    ],
    "sg:phone":"+1 870 946 2095",
    "sg:postcode":"72042",
    "sg:province":"AR",
    "sg:tags":[
        "grocer"
    ],
    "wof:name":"Kroger",
    "wof:placetype":"venue"
},
  "geometry": {"coordinates":[-91.324364,34.291436],"type":"Point"}
}