{
  "type": "Feature",
  "properties": {
    "iso:country":"US",
    "sg:address":"2701 Carma St",
    "sg:city":"Benton",
    "sg:classifiers":[
        {
            "category":"Building & Trades",
            "subcategory":"Landscaping Services",
            "type":"Services"
        }
    ],
    "sg:phone":"+1 501 778 8071",
    "sg:postcode":"72015",
    "sg:province":"AR",
    "sg:tags":[
        "tree"
    ],
    "wof:name":"Moore Affordable Tree Service",
    "wof:placetype":"venue"
},
  "geometry": {"coordinates":[-92.556845,34.534733],"type":"Point"}
}