{
  "type": "Feature",
  "properties": {
    "iso:country":"US",
    "sg:address":"630 E Wood St",
    "sg:city":"Ashdown",
    "sg:classifiers":[
        {
            "category":"Manufacturing",
            "subcategory":"Rubber & Plastics",
            "type":"Manufacturing & Wholesale Goods"
        }
    ],
    "sg:phone":"+1 870 898 8411",
    "sg:postcode":"71822",
    "sg:province":"AR",
    "sg:tags":[
        "grease",
        "seal"
    ],
    "wof:name":"John Crane Inc",
    "wof:placetype":"venue"
},
  "geometry": {"coordinates":[-94.12283100000001,33.667357],"type":"Point"}
}