{
  "type": "Feature",
  "properties": {
    "addr:full":"4401 Spring Cliff Loop Rogers AR 72756",
    "addr:housenumber":"4401",
    "addr:postcode":"72756",
    "addr:street":"Spring Cliff Loop",
    "iso:country":"US",
    "sg:address":"4401 Spring Cliff Loop",
    "sg:city":"Rogers",
    "sg:classifiers":[
        {
            "category":"Professional",
            "subcategory":"Business Services",
            "type":"Services"
        }
    ],
    "sg:phone":"+1 479 631 1014",
    "sg:postcode":"72756",
    "sg:province":"AR",
    "wof:name":"Meyer Group",
    "wof:placetype":"venue"
},
  "geometry": {"coordinates":[-94.128101,36.384077],"type":"Point"}
}