{
  "type": "Feature",
  "properties": {
    "iso:country":"US",
    "sg:address":"2001 State Highway 22 W",
    "sg:city":"Dardanelle",
    "sg:classifiers":[
        {
            "category":"Autos & Motor Vehicles",
            "subcategory":"Fuel & Gas Station",
            "type":"Retail Goods"
        },
        {
            "category":"Food & Beverages",
            "subcategory":"Groceries & Convenience Stores",
            "type":"Retail Goods"
        }
    ],
    "sg:phone":"+1 479 229 2575",
    "sg:postcode":"72834",
    "sg:province":"AR",
    "wof:name":"Westside Citgo",
    "wof:placetype":"venue"
},
  "geometry": {"coordinates":[-93.232354,35.26072],"type":"Point"}
}