{
  "type": "Feature",
  "properties": {
    "iso:country":"US",
    "sg:address":"406 S Walton Blvd",
    "sg:city":"Bentonville",
    "sg:classifiers":[
        {
            "category":"Shopping",
            "subcategory":"Optical Goods",
            "type":"Retail Goods"
        }
    ],
    "sg:phone":"+1 479 254 8857",
    "sg:postcode":"72712",
    "sg:province":"AR",
    "wof:name":"Mills Eye Care",
    "wof:placetype":"venue"
},
  "geometry": {"coordinates":[-94.221505,36.369553],"type":"Point"}
}