{
  "type": "Feature",
  "properties": {
    "addr:full":"406 S Walton Blvd Bentonville AR 72712",
    "addr:housenumber":"406",
    "addr:postcode":"72712",
    "addr:street":"S Walton Blvd",
    "iso:country":"US",
    "sg:address":"406 S Walton Blvd",
    "sg:city":"Bentonville",
    "sg:classifiers":[
        {
            "category":"Shopping",
            "subcategory":"Optical Goods",
            "type":"Retail Goods"
        }
    ],
    "sg:phone":"+1 479 254 8857",
    "sg:postcode":"72712",
    "sg:province":"AR",
    "wof:name":"Mills Eye Care",
    "wof:placetype":"venue"
},
  "geometry": {"coordinates":[-94.22150499999999,36.369553],"type":"Point"}
}