{
  "type": "Feature",
  "properties": {
    "addr:full":"2114 Howard St Little Rock AR 72202",
    "addr:housenumber":"2114",
    "addr:postcode":"72202",
    "addr:street":"Howard St",
    "iso:country":"US",
    "sg:address":"2114 Howard St",
    "sg:city":"Little Rock",
    "sg:classifiers":[
        {
            "category":"Health Services",
            "subcategory":"Clinic",
            "type":"Services"
        }
    ],
    "sg:phone":"+1 501 375 5814",
    "sg:postcode":"72202",
    "sg:province":"AR",
    "sg:tags":[
        "home"
    ],
    "wof:name":"International Caregivers Inc",
    "wof:placetype":"venue"
},
  "geometry": {"coordinates":[-92.298562,34.730699],"type":"Point"}
}