{
  "type": "Feature",
  "properties": {
    "iso:country":"US",
    "sg:address":"200 W Capitol Ave",
    "sg:city":"Little Rock",
    "sg:classifiers":[
        {
            "category":"Professional",
            "subcategory":"Lawyer & Legal Services",
            "type":"Services"
        }
    ],
    "sg:phone":"+1 501 371 0808",
    "sg:postcode":"72201",
    "sg:province":"AR",
    "sg:tags":[
        "attorney"
    ],
    "sg:website":"www.wlj.com",
    "wof:name":"Wright Lindsey & Jennings LLP",
    "wof:placetype":"venue"
},
  "geometry": {"coordinates":[-92.27347899999999,34.744482],"type":"Point"}
}