{
  "type": "Feature",
  "properties": {
    "iso:country":"US",
    "sg:address":"620 E Main St",
    "sg:city":"Blytheville",
    "sg:classifiers":[
        {
            "category":"Autos & Motor Vehicles",
            "subcategory":"Auto Supplies",
            "type":"Retail Goods"
        }
    ],
    "sg:phone":"+1 870 762 0775",
    "sg:postcode":"72315",
    "sg:province":"AR",
    "sg:tags":[
        "automobile",
        "part"
    ],
    "sg:website":"http://www.oreillyauto.com?utm_source=yellowpages&utm_medium=iyp&utm_campaign=802",
    "wof:name":"O'Reilly Auto Parts",
    "wof:placetype":"venue"
},
  "geometry": {"coordinates":[-89.89446599999999,35.927419],"type":"Point"}
}