{
  "type": "Feature",
  "properties": {
    "addr:full":"1520 Fourche Ave Perryville AR 72126",
    "addr:housenumber":"1520",
    "addr:postcode":"72126",
    "addr:street":"Fourche Ave",
    "iso:country":"US",
    "sg:address":"1520 Fourche Ave",
    "sg:city":"Perryville",
    "sg:classifiers":[
        {
            "category":"Organizations",
            "subcategory":"Religious Organization",
            "type":"Services"
        }
    ],
    "sg:phone":"+1 501 889 3340",
    "sg:postcode":"72126",
    "sg:province":"AR",
    "sg:tags":[
        "church"
    ],
    "wof:name":"Second Baptist Church",
    "wof:placetype":"venue"
},
  "geometry": {"coordinates":[-92.794783,35.017849],"type":"Point"}
}