{
  "type": "Feature",
  "properties": {
    "addr:full":"1713 W Dewitt Henry Dr Beebe AR 72012",
    "addr:housenumber":"1713",
    "addr:postcode":"72012",
    "addr:street":"W;Henry Dr",
    "iso:country":"US",
    "sg:address":"1713 W Dewitt Henry Dr",
    "sg:city":"Beebe",
    "sg:classifiers":[
        {
            "category":"Retail",
            "subcategory":"Auto Repair",
            "type":"Services"
        }
    ],
    "sg:phone":"+1 501 882 3511",
    "sg:postcode":"72012",
    "sg:province":"AR",
    "sg:tags":[
        "automotive",
        "exhaust"
    ],
    "wof:name":"Razorback Quik Lube",
    "wof:placetype":"venue"
},
  "geometry": {"coordinates":[-91.902109,35.073091],"type":"Point"}
}