{
  "type": "Feature",
  "properties": {
    "iso:country":"US",
    "sg:address":"323 Center St",
    "sg:city":"Little Rock",
    "sg:classifiers":[
        {
            "category":"Government",
            "subcategory":"Court House",
            "type":"Public Place"
        }
    ],
    "sg:phone":"+1 501 682 2007",
    "sg:postcode":"72201",
    "sg:province":"AR",
    "sg:tags":[
        "state",
        "counsel"
    ],
    "sg:website":"www.ag.state.ar.us",
    "wof:name":"Attorney General",
    "wof:placetype":"venue"
},
  "geometry": {"coordinates":[-92.273095,34.746461],"type":"Point"}
}