{
  "type": "Feature",
  "properties": {
    "addr:full":"12 Nannie Goat Ln Vilonia AR 72173",
    "addr:housenumber":"12",
    "addr:postcode":"72173",
    "addr:street":"Nannie Goat Ln",
    "iso:country":"US",
    "sg:address":"12 Nannie Goat Ln",
    "sg:city":"Vilonia",
    "sg:classifiers":[
        {
            "category":"Real Estate",
            "subcategory":"Real Estate Services",
            "type":"Services"
        },
        {
            "category":"Real Estate",
            "subcategory":"Real Estate Agent",
            "type":"Services"
        }
    ],
    "sg:phone":"+1 501 796 4111",
    "sg:postcode":"72173",
    "sg:province":"AR",
    "sg:tags":[
        "buyer",
        "broker"
    ],
    "wof:name":"Abr",
    "wof:placetype":"venue"
},
  "geometry": {"coordinates":[-92.21836399999999,35.017602],"type":"Point"}
}