{
  "type": "Feature",
  "properties": {
    "iso:country":"US",
    "sg:address":"115 N 3rd St",
    "sg:city":"De Queen",
    "sg:classifiers":[
        {
            "category":"Government",
            "subcategory":"Court House",
            "type":"Public Place"
        }
    ],
    "sg:phone":"+1 870 584 7311",
    "sg:postcode":"71832",
    "sg:province":"AR",
    "sg:tags":[
        "county"
    ],
    "wof:name":"Sevier County District Court",
    "wof:placetype":"venue"
},
  "geometry": {"coordinates":[-94.340413,34.037634],"type":"Point"}
}