{
  "type": "Feature",
  "properties": {
    "iso:country":"US",
    "sg:address":"1715 W Main St",
    "sg:city":"Heber Springs",
    "sg:classifiers":[
        {
            "category":"Health Services",
            "subcategory":"Doctor",
            "type":"Services"
        }
    ],
    "sg:phone":"+1 501 362 0606",
    "sg:postcode":"72543",
    "sg:province":"AR",
    "sg:tags":[
        "physician",
        "surgeon"
    ],
    "wof:name":"Arkansas Otolaryngology Ctr Pa",
    "wof:placetype":"venue"
},
  "geometry": {"coordinates":[-92.04900000000001,35.492416],"type":"Point"}
}