{
  "type": "Feature",
  "properties": {
    "iso:country":"US",
    "sg:address":"909 E Dixon Rd",
    "sg:city":"Little Rock",
    "sg:classifiers":[
        {
            "category":"Retail",
            "subcategory":"Repair Shop",
            "type":"Services"
        }
    ],
    "sg:phone":"+1 501 490 1721",
    "sg:postcode":"72206",
    "sg:province":"AR",
    "sg:tags":[
        "generator",
        "air"
    ],
    "wof:name":"Electric Motor Service Co Inc",
    "wof:placetype":"venue"
},
  "geometry": {"coordinates":[-92.249164,34.672191],"type":"Point"}
}