{
  "type": "Feature",
  "properties": {
    "addr:full":"222 Angel Ln Austin AR 72007",
    "addr:housenumber":"222",
    "addr:postcode":"72007",
    "addr:street":"Angel Ln",
    "iso:country":"US",
    "sg:address":"222 Angel Ln",
    "sg:city":"Austin",
    "sg:classifiers":[
        {
            "category":"Building & Trades",
            "subcategory":"Construction",
            "type":"Services"
        }
    ],
    "sg:phone":"+1 501 843 2879",
    "sg:postcode":"72007",
    "sg:province":"AR",
    "sg:tags":[
        "house"
    ],
    "wof:name":"Henderson Construction",
    "wof:placetype":"venue"
},
  "geometry": {"coordinates":[-91.934494,34.950068],"type":"Point"}
}