{
  "type": "Feature",
  "properties": {
    "iso:country":"US",
    "sg:address":"25 S Main St",
    "sg:city":"Strawberry",
    "sg:classifiers":[
        {
            "category":"Real Estate",
            "subcategory":"Real Estate Operator",
            "type":"Services"
        }
    ],
    "sg:phone":"+1 870 528 1500",
    "sg:postcode":"72469",
    "sg:province":"AR",
    "sg:tags":[
        "building",
        "apartment"
    ],
    "wof:name":"Strawberry Fields Apartments",
    "wof:placetype":"venue"
},
  "geometry": {"coordinates":[-91.321167,35.967277],"type":"Point"}
}