{
  "type": "Feature",
  "properties": {
    "addr:full":"12312 Chenal Pkwy Little Rock AR 72211",
    "addr:housenumber":"12312",
    "addr:postcode":"72211",
    "addr:street":"Chenal Pkwy",
    "iso:country":"US",
    "sg:address":"12312 Chenal Pkwy",
    "sg:city":"Little Rock",
    "sg:classifiers":[
        {
            "category":"Restaurant",
            "type":"Food & Drink"
        }
    ],
    "sg:menulink":"http://www.allmenus.com/ar/little-rock/61160-firehouse-subs/menu/",
    "sg:phone":"+1 501 228 5553",
    "sg:postcode":"72211",
    "sg:province":"AR",
    "sg:tags":[
        "wrap",
        "american",
        "sandwich"
    ],
    "wof:name":"Firehouse Subs",
    "wof:placetype":"venue"
},
  "geometry": {"coordinates":[-92.409154,34.749501],"type":"Point"}
}