{
  "type": "Feature",
  "properties": {
    "iso:country":"US",
    "sg:address":"216 Jasmine Ln",
    "sg:city":"Alma",
    "sg:classifiers":[
        {
            "category":"Shopping",
            "type":"Retail Goods"
        }
    ],
    "sg:phone":"+1 479 632 2876",
    "sg:postcode":"72921",
    "sg:province":"AR",
    "sg:tags":[
        "merchandise"
    ],
    "wof:name":"Centers Machine",
    "wof:placetype":"venue"
},
  "geometry": {"coordinates":[-94.227207,35.508566],"type":"Point"}
}