{
  "type": "Feature",
  "properties": {
    "iso:country":"US",
    "sg:address":"3237 Albert Pike Rd",
    "sg:city":"Hot Springs",
    "sg:classifiers":[
        {
            "category":"Organizations",
            "subcategory":"Community Association",
            "type":"Services"
        }
    ],
    "sg:phone":"+1 501 767 1346",
    "sg:postcode":"71913",
    "sg:province":"AR",
    "sg:tags":[
        "military"
    ],
    "wof:name":"American Legion",
    "wof:placetype":"venue"
},
  "geometry": {"coordinates":[-93.12914499999999,34.505755],"type":"Point"}
}