{
  "type": "Feature",
  "properties": {
    "iso:country":"US",
    "sg:address":"8025 Magnolia Ln",
    "sg:city":"Rogers",
    "sg:classifiers":[
        {
            "category":"Manufacturing",
            "subcategory":"Buildings",
            "type":"Manufacturing & Wholesale Goods"
        },
        {
            "category":"Building & Trades",
            "subcategory":"Construction",
            "type":"Services"
        }
    ],
    "sg:phone":"+1 479 925 3980",
    "sg:postcode":"72756",
    "sg:province":"AR",
    "sg:tags":[
        "home",
        "builder",
        "contractor"
    ],
    "wof:name":"Isbell Construction",
    "wof:placetype":"venue"
},
  "geometry": {"coordinates":[-94.019377,36.321472],"type":"Point"}
}