{
  "type": "Feature",
  "properties": {
    "addr:full":"1801 Kathleen St Jonesboro AR 72401",
    "addr:housenumber":"1801",
    "addr:postcode":"72401",
    "addr:street":"Kathleen St",
    "iso:country":"US",
    "sg:address":"1801 Kathleen St",
    "sg:city":"Jonesboro",
    "sg:classifiers":[
        {
            "category":"Shopping",
            "subcategory":"Discount & Variety Stores",
            "type":"Retail Goods"
        }
    ],
    "sg:phone":"+1 870 935 3220",
    "sg:postcode":"72401",
    "sg:province":"AR",
    "sg:tags":[
        "merchandise",
        "general"
    ],
    "wof:name":"Tibbs Auto Body & Sales",
    "wof:placetype":"venue"
},
  "geometry": {"coordinates":[-90.640973,35.827119],"type":"Point"}
}