{
  "type": "Feature",
  "properties": {
    "addr:full":"3018 S Midland Dr Pine Bluff AR 71603",
    "addr:housenumber":"3018",
    "addr:postcode":"71603",
    "addr:street":"S Midland Dr",
    "iso:country":"US",
    "sg:address":"3018 S Midland Dr",
    "sg:city":"Pine Bluff",
    "sg:classifiers":[
        {
            "category":"Home & Garden",
            "subcategory":"Building Materials",
            "type":"Retail Goods"
        }
    ],
    "sg:phone":"+1 870 536 3676",
    "sg:postcode":"71603",
    "sg:province":"AR",
    "sg:tags":[
        "hardware"
    ],
    "wof:name":"Anderson Door and Hardware",
    "wof:placetype":"venue"
},
  "geometry": {"coordinates":[-92.03830600000001,34.197335],"type":"Point"}
}