{
  "type": "Feature",
  "properties": {
    "addr:full":"407 2nd Dell AR 72315",
    "addr:housenumber":"407",
    "addr:postcode":"72315",
    "addr:street":"2Nd Dell",
    "iso:country":"US",
    "sg:address":"407 2nd",
    "sg:city":"Dell",
    "sg:classifiers":[
        {
            "category":"Government",
            "subcategory":"Police Station",
            "type":"Public Place"
        }
    ],
    "sg:phone":"+1 870 564 9026",
    "sg:postcode":"72315",
    "sg:province":"AR",
    "sg:tags":[
        "department"
    ],
    "wof:name":"City Of Dell Police Dept",
    "wof:placetype":"venue"
},
  "geometry": {"coordinates":[-90.04091200000001,35.855471],"type":"Point"}
}