{
  "type": "Feature",
  "properties": {
    "addr:full":"929 S College St Mountain Home AR 72653",
    "addr:housenumber":"929",
    "addr:postcode":"72653",
    "addr:street":"S College St",
    "iso:country":"US",
    "sg:address":"929 S College St",
    "sg:city":"Mountain Home",
    "sg:classifiers":[
        {
            "category":"Social Services",
            "subcategory":"Child Care",
            "type":"Services"
        }
    ],
    "sg:phone":"+1 870 424 5755",
    "sg:postcode":"72653",
    "sg:province":"AR",
    "sg:tags":[
        "day"
    ],
    "wof:name":"Open Arms Learning Center",
    "wof:placetype":"venue"
},
  "geometry": {"coordinates":[-92.38069400000001,36.332483],"type":"Point"}
}