{
  "type": "Feature",
  "properties": {
    "iso:country":"US",
    "sg:address":"701 Green Mountain Dr",
    "sg:city":"Little Rock",
    "sg:classifiers":[
        {
            "category":"Manufacturing",
            "subcategory":"Retail Goods",
            "type":"Manufacturing & Wholesale Goods"
        }
    ],
    "sg:phone":"+1 501 224 9435",
    "sg:postcode":"72211",
    "sg:province":"AR",
    "sg:tags":[
        "manufacturer"
    ],
    "wof:name":"S & W Inc",
    "wof:placetype":"venue"
},
  "geometry": {"coordinates":[-92.401366,34.759866],"type":"Point"}
}