{
  "type": "Feature",
  "properties": {
    "iso:country":"US",
    "sg:address":"114 E Broadway",
    "sg:city":"Glenwood",
    "sg:classifiers":[
        {
            "category":"Restaurant",
            "type":"Food & Drink"
        }
    ],
    "sg:phone":"+1 870 356 5112",
    "sg:postcode":"71943",
    "sg:province":"AR",
    "wof:name":"Susie's Kountry Kitchen",
    "wof:placetype":"venue"
},
  "geometry": {"coordinates":[-93.550942,34.326325],"type":"Point"}
}