{
  "type": "Feature",
  "properties": {
    "iso:country":"US",
    "sg:address":"522 Arkansas St",
    "sg:city":"Helena",
    "sg:classifiers":[
        {
            "category":"Organizations",
            "subcategory":"Religious Organization",
            "type":"Services"
        }
    ],
    "sg:phone":"+1 870 338 3221",
    "sg:postcode":"72342",
    "sg:province":"AR",
    "wof:name":"New Light Baptist Church",
    "wof:placetype":"venue"
},
  "geometry": {"coordinates":[-90.590035,34.521515],"type":"Point"}
}