{
  "type": "Feature",
  "properties": {
    "iso:country":"US",
    "sg:address":"128 Spring Oak Dr",
    "sg:city":"North Little Rock",
    "sg:classifiers":[
        {
            "category":"Utilities",
            "subcategory":"Cable",
            "type":"Services"
        },
        {
            "category":"Building & Trades",
            "subcategory":"Electrical",
            "type":"Services"
        }
    ],
    "sg:phone":"+1 501 835 3785",
    "sg:postcode":"72120",
    "sg:province":"AR",
    "sg:tags":[
        "television"
    ],
    "wof:name":"Cat 5 Cable Co",
    "wof:placetype":"venue"
},
  "geometry": {"coordinates":[-92.192505,34.848352],"type":"Point"}
}