{
  "type": "Feature",
  "properties": {
    "iso:country":"US",
    "sg:address":"802 Peach St",
    "sg:city":"Prattsville",
    "sg:classifiers":[
        {
            "category":"Personal",
            "subcategory":"Beauty Salon",
            "type":"Services"
        }
    ],
    "sg:phone":"+1 870 699 4588",
    "sg:postcode":"72129",
    "sg:province":"AR",
    "wof:name":"Lady Di's Beauty Shop",
    "wof:placetype":"venue"
},
  "geometry": {"coordinates":[-92.551901,34.313286],"type":"Point"}
}