{
  "type": "Feature",
  "properties": {
    "iso:country":"US",
    "sg:address":"1213 W Central St",
    "sg:city":"Warren",
    "sg:classifiers":[
        {
            "category":"Retail",
            "subcategory":"Auto Repair",
            "type":"Services"
        }
    ],
    "sg:phone":"+1 870 226 6644",
    "sg:postcode":"71671",
    "sg:province":"AR",
    "sg:tags":[
        "repairing",
        "automobile"
    ],
    "wof:name":"Renae Allen Car Care Ctr",
    "wof:placetype":"venue"
},
  "geometry": {"coordinates":[-92.086603,33.609683],"type":"Point"}
}