{
  "type": "Feature",
  "properties": {
    "addr:full":"5705 S 28th St Fort Smith AR 72908",
    "addr:housenumber":"5705",
    "addr:postcode":"72908",
    "addr:street":"S 28Th St",
    "iso:country":"US",
    "sg:address":"5705 S 28th St",
    "sg:city":"Fort Smith",
    "sg:classifiers":[
        {
            "category":"Building & Trades",
            "subcategory":"Cleaning & Sanitation",
            "type":"Services"
        }
    ],
    "sg:phone":"+1 479 646 0767",
    "sg:postcode":"72908",
    "sg:province":"AR",
    "sg:tags":[
        "janitor"
    ],
    "wof:name":"Pro Clean Janitorial Svc",
    "wof:placetype":"venue"
},
  "geometry": {"coordinates":[-94.40447,35.325782],"type":"Point"}
}