{
  "type": "Feature",
  "properties": {
    "iso:country":"US",
    "sg:address":"6109 E 9th St",
    "sg:city":"Texarkana",
    "sg:classifiers":[
        {
            "category":"Freight",
            "type":"Transportation"
        }
    ],
    "sg:phone":"+1 870 773 2283",
    "sg:postcode":"71854",
    "sg:province":"AR",
    "sg:tags":[
        "trucking"
    ],
    "wof:name":"W J Little Trucking",
    "wof:placetype":"venue"
},
  "geometry": {"coordinates":[-93.969544,33.429872],"type":"Point"}
}