{
  "type": "Feature",
  "properties": {
    "iso:country":"US",
    "sg:address":"18808 State Hwy 107",
    "sg:city":"Jacksonville",
    "sg:classifiers":[
        {
            "category":"Building & Trades",
            "subcategory":"Construction",
            "type":"Services"
        }
    ],
    "sg:phone":"+1 501 833 0444",
    "sg:postcode":"72076",
    "sg:province":"AR",
    "sg:tags":[
        "maker",
        "cabinet"
    ],
    "wof:name":"Lee's Cabinetry",
    "wof:placetype":"venue"
},
  "geometry": {"coordinates":[-92.182237,34.90723],"type":"Point"}
}