{
  "type": "Feature",
  "properties": {
    "iso:country":"US",
    "sg:address":"7212 Geyer Springs Rd",
    "sg:city":"Little Rock",
    "sg:classifiers":[
        {
            "category":"Utilities",
            "subcategory":"Mobile Phone",
            "type":"Services"
        },
        {
            "category":"Wholesale",
            "subcategory":"Electrical",
            "type":"Manufacturing & Wholesale Goods"
        }
    ],
    "sg:phone":"+1 501 562 5600",
    "sg:postcode":"72209",
    "sg:province":"AR",
    "sg:tags":[
        "communication",
        "electronic",
        "radiotelephone"
    ],
    "wof:name":"Headz Up II Barber Shop",
    "wof:placetype":"venue"
},
  "geometry": {"coordinates":[-92.34368000000001,34.683762],"type":"Point"}
}