{
  "type": "Feature",
  "properties": {
    "iso:country":"US",
    "sg:address":"3567 State Hwy 351",
    "sg:city":"Jonesboro",
    "sg:classifiers":[
        {
            "category":"Building & Trades",
            "subcategory":"Plumbing",
            "type":"Services"
        }
    ],
    "sg:phone":"+1 870 931 6515",
    "sg:postcode":"72401",
    "sg:province":"AR",
    "sg:tags":[
        "conditioning",
        "air",
        "system",
        "contractor"
    ],
    "wof:name":"Frank's Heat & Air",
    "wof:placetype":"venue"
},
  "geometry": {"coordinates":[-90.648341,35.896513],"type":"Point"}
}