{
  "type": "Feature",
  "properties": {
    "addr:full":"838 N State Line Ave Texarkana AR 71854",
    "addr:housenumber":"838",
    "addr:postcode":"71854",
    "addr:street":"N State Line Ave",
    "iso:country":"US",
    "sg:address":"838 N State Line Ave",
    "sg:city":"Texarkana",
    "sg:classifiers":[
        {
            "category":"Banks & Credit Unions",
            "subcategory":"Bank",
            "type":"Services"
        }
    ],
    "sg:phone":"+1 870 779 4947",
    "sg:postcode":"71854",
    "sg:province":"AR",
    "sg:tags":[
        "cashing",
        "check"
    ],
    "wof:name":"Checkmate",
    "wof:placetype":"venue"
},
  "geometry": {"coordinates":[-94.043025,33.430399],"type":"Point"}
}