{
  "type": "Feature",
  "properties": {
    "iso:country":"US",
    "sg:address":"1098 Main St",
    "sg:city":"Vilonia",
    "sg:classifiers":[
        {
            "category":"Shopping",
            "subcategory":"Music",
            "type":"Retail Goods"
        },
        {
            "category":"Cinema",
            "subcategory":"Movie Rental",
            "type":"Entertainment"
        }
    ],
    "sg:phone":"+1 501 796 4170",
    "sg:postcode":"72173",
    "sg:province":"AR",
    "sg:tags":[
        "leasing",
        "video",
        "disc",
        "tape"
    ],
    "wof:name":"Show Biz Video",
    "wof:placetype":"venue"
},
  "geometry": {"coordinates":[-92.208745,35.083732],"type":"Point"}
}