{
  "type": "Feature",
  "properties": {
    "iso:country":"US",
    "sg:address":"18 Ponderosa Dr",
    "sg:city":"Lonoke",
    "sg:classifiers":[
        {
            "category":"Farming",
            "subcategory":"Farm",
            "type":"Manufacturing & Wholesale Goods"
        }
    ],
    "sg:phone":"+1 501 676 3902",
    "sg:postcode":"72086",
    "sg:province":"AR",
    "wof:name":"Mc Gee Farms",
    "wof:placetype":"venue"
},
  "geometry": {"coordinates":[-91.905555,34.776207],"type":"Point"}
}