{
  "type": "Feature",
  "properties": {
    "iso:country":"US",
    "sg:address":"12 Pepsi Cola Rd",
    "sg:city":"Batesville",
    "sg:classifiers":[
        {
            "category":"Manufacturing",
            "subcategory":"Tools & Machinery",
            "type":"Manufacturing & Wholesale Goods"
        }
    ],
    "sg:phone":"+1 870 251 3266",
    "sg:postcode":"72501",
    "sg:province":"AR",
    "sg:tags":[
        "machine",
        "shop",
        "industrial",
        "mfg"
    ],
    "wof:name":"Hytec Machine Co",
    "wof:placetype":"venue"
},
  "geometry": {"coordinates":[-91.636071,35.727987],"type":"Point"}
}