{
  "type": "Feature",
  "properties": {
    "iso:country":"US",
    "sg:address":"10912 Hwy 270",
    "sg:city":"Malvern",
    "sg:classifiers":[
        {
            "category":"Manufacturing",
            "subcategory":"Metals",
            "type":"Manufacturing & Wholesale Goods"
        }
    ],
    "sg:phone":"+1 501 332 6600",
    "sg:postcode":"72104",
    "sg:province":"AR",
    "wof:name":"DLM Inc",
    "wof:placetype":"venue"
},
  "geometry": {"coordinates":[-92.71192000000001,34.354422],"type":"Point"}
}