{
  "type": "Feature",
  "properties": {
    "iso:country":"US",
    "sg:address":"602 W Arch Ave",
    "sg:city":"Searcy",
    "sg:classifiers":[
        {
            "category":"Social Services",
            "subcategory":"Adult Care",
            "type":"Services"
        }
    ],
    "sg:phone":"+1 501 268 5638",
    "sg:postcode":"72143",
    "sg:province":"AR",
    "sg:tags":[
        "organization",
        "senior",
        "citizen"
    ],
    "wof:name":"White River Area Agency-Aging",
    "wof:placetype":"venue"
},
  "geometry": {"coordinates":[-91.74294399999999,35.25017],"type":"Point"}
}