{
  "type": "Feature",
  "properties": {
    "iso:country":"US",
    "sg:address":"403 Court St",
    "sg:city":"Harrisburg",
    "sg:classifiers":[
        {
            "category":"Personal",
            "subcategory":"Barber",
            "type":"Services"
        }
    ],
    "sg:phone":"+1 870 578 5952",
    "sg:postcode":"72432",
    "sg:province":"AR",
    "wof:name":"Murray's City Barber Shop",
    "wof:placetype":"venue"
},
  "geometry": {"coordinates":[-90.716972,35.562861],"type":"Point"}
}