{
  "type": "Feature",
  "properties": {
    "iso:country":"US",
    "sg:address":"9005 Lew Dr",
    "sg:city":"Little Rock",
    "sg:classifiers":[
        {
            "category":"Health Services",
            "subcategory":"Clinic",
            "type":"Services"
        },
        {
            "category":"Social Services",
            "type":"Services"
        }
    ],
    "sg:phone":"+1 501 565 4374",
    "sg:postcode":"72209",
    "sg:province":"AR",
    "sg:tags":[
        "deaf",
        "facility"
    ],
    "wof:name":"Little Rock Assoc Of The Deaf",
    "wof:placetype":"venue"
},
  "geometry": {"coordinates":[-92.340255,34.666998],"type":"Point"}
}