{
  "type": "Feature",
  "properties": {
    "iso:country":"US",
    "sg:address":"421 Stratford Ct",
    "sg:city":"Jacksonville",
    "sg:classifiers":[
        {
            "category":"Organizations",
            "subcategory":"Religious Organization",
            "type":"Services"
        }
    ],
    "sg:phone":"+1 501 985 9687",
    "sg:postcode":"72076",
    "sg:province":"AR",
    "wof:name":"Covenant Keepers International",
    "wof:placetype":"venue"
},
  "geometry": {"coordinates":[-92.10628,34.870263],"type":"Point"}
}