{
  "type": "Feature",
  "properties": {
    "iso:country":"US",
    "sg:address":"10415 Curtis Ln",
    "sg:city":"Omaha",
    "sg:classifiers":[
        {
            "category":"Personal",
            "subcategory":"Beauty Salon",
            "type":"Services"
        }
    ],
    "sg:phone":"+1 870 426 5391",
    "sg:postcode":"72662",
    "sg:province":"AR",
    "sg:tags":[
        "hair",
        "stylist"
    ],
    "wof:name":"Willies Hair Shoppe",
    "wof:placetype":"venue"
},
  "geometry": {"coordinates":[-93.186158,36.43449],"type":"Point"}
}