{
  "type": "Feature",
  "properties": {
    "iso:country":"US",
    "sg:address":"657 Jim Bellinger Rd",
    "sg:city":"Clinton",
    "sg:phone":"+1 501 745 8251",
    "sg:postcode":"72031",
    "sg:province":"AR",
    "sg:tags":[
        "equipment",
        "supply"
    ],
    "wof:name":"Restaurant Equipment Exchange",
    "wof:placetype":"venue"
},
  "geometry": {"coordinates":[-92.459,35.593731],"type":"Point"}
}