{
  "type": "Feature",
  "properties": {
    "iso:country":"US",
    "sg:address":"6517 Norman Rd",
    "sg:city":"North Little Rock",
    "sg:classifiers":[
        {
            "category":"Retail",
            "subcategory":"Repair Shop",
            "type":"Services"
        }
    ],
    "sg:phone":"+1 501 758 4764",
    "sg:postcode":"72118",
    "sg:province":"AR",
    "wof:name":"D S Satellite",
    "wof:placetype":"venue"
},
  "geometry": {"coordinates":[-92.34444000000001,34.826918],"type":"Point"}
}