{
  "type": "Feature",
  "properties": {
    "iso:country":"US",
    "sg:address":"18100 Kanis Rd",
    "sg:city":"Little Rock",
    "sg:classifiers":[
        {
            "category":"Retail",
            "subcategory":"Auto Repair",
            "type":"Services"
        }
    ],
    "sg:phone":"+1 501 821 2639",
    "sg:postcode":"72223",
    "sg:province":"AR",
    "sg:tags":[
        "body",
        "general"
    ],
    "wof:name":"Advanced Paint & Body Inc",
    "wof:placetype":"venue"
},
  "geometry": {"coordinates":[-92.481386,34.759661],"type":"Point"}
}