{
  "type": "Feature",
  "properties": {
    "iso:country":"US",
    "sg:address":"4305 Mount Holly Rd",
    "sg:city":"El Dorado",
    "sg:classifiers":[
        {
            "category":"Food & Beverages",
            "subcategory":"Groceries & Convenience Stores",
            "type":"Retail Goods"
        }
    ],
    "sg:phone":"+1 870 863 9692",
    "sg:postcode":"71730",
    "sg:province":"AR",
    "sg:tags":[
        "grocer"
    ],
    "wof:name":"Parks Country Store",
    "wof:placetype":"venue"
},
  "geometry": {"coordinates":[-92.73265,33.245999],"type":"Point"}
}