{
  "type": "Feature",
  "properties": {
    "iso:country":"US",
    "sg:address":"5917 W 12th St",
    "sg:city":"Little Rock",
    "sg:classifiers":[
        {
            "category":"Utilities",
            "subcategory":"Mobile Phone",
            "type":"Services"
        }
    ],
    "sg:phone":"+1 501 296 9385",
    "sg:postcode":"72204",
    "sg:province":"AR",
    "sg:tags":[
        "telephone",
        "cellular"
    ],
    "wof:name":"Elite Wireless",
    "wof:placetype":"venue"
},
  "geometry": {"coordinates":[-92.340972,34.741321],"type":"Point"}
}