{
  "type": "Feature",
  "properties": {
    "iso:country":"US",
    "sg:address":"4733 Alma Hwy",
    "sg:city":"Van Buren",
    "sg:classifiers":[
        {
            "category":"Autos & Motor Vehicles",
            "subcategory":"Automobile Sales",
            "type":"Retail Goods"
        }
    ],
    "sg:phone":"+1 479 471 0878",
    "sg:postcode":"72956",
    "sg:province":"AR",
    "sg:tags":[
        "car",
        "dealer"
    ],
    "wof:name":"On The Spot Auto Sales",
    "wof:placetype":"venue"
},
  "geometry": {"coordinates":[-94.293766,35.456951],"type":"Point"}
}