{
  "type": "Feature",
  "properties": {
    "addr:full":"7924 Cantrell Rd Little Rock AR 72227",
    "addr:housenumber":"7924",
    "addr:postcode":"72227",
    "addr:street":"Cantrell Rd",
    "iso:country":"US",
    "sg:address":"7924 Cantrell Rd",
    "sg:city":"Little Rock",
    "sg:classifiers":[
        {
            "category":"Health Services",
            "subcategory":"Doctor",
            "type":"Services"
        }
    ],
    "sg:phone":"+1 501 225 0113",
    "sg:postcode":"72227",
    "sg:province":"AR",
    "sg:tags":[
        "dentist"
    ],
    "wof:name":"Blake H Weber Pa",
    "wof:placetype":"venue"
},
  "geometry": {"coordinates":[-92.362416,34.775829],"type":"Point"}
}