{
  "type": "Feature",
  "properties": {
    "iso:country":"US",
    "sg:address":"2302 Shady Grove Rd",
    "sg:city":"Stuttgart",
    "sg:classifiers":[
        {
            "category":"Shopping",
            "subcategory":"Crafts & Fabrics",
            "type":"Retail Goods"
        },
        {
            "category":"Professional",
            "subcategory":"Art Services",
            "type":"Services"
        }
    ],
    "sg:phone":"+1 870 673 7374",
    "sg:postcode":"72160",
    "sg:province":"AR",
    "sg:tags":[
        "punching",
        "design",
        "embroidery"
    ],
    "wof:name":"Arkansas Custom Embroider",
    "wof:placetype":"venue"
},
  "geometry": {"coordinates":[-91.568807,34.478237],"type":"Point"}
}