{
  "type": "Feature",
  "properties": {
    "addr:full":"655 French Rd Bee Branch AR 72013",
    "addr:housenumber":"655",
    "addr:postcode":"72013",
    "addr:street":"French Rd",
    "iso:country":"US",
    "sg:address":"655 French Rd",
    "sg:city":"Bee Branch",
    "sg:classifiers":[
        {
            "category":"Professional",
            "subcategory":"Employment Agencies",
            "type":"Services"
        }
    ],
    "sg:phone":"+1 501 654 2350",
    "sg:postcode":"72013",
    "sg:province":"AR",
    "sg:tags":[
        "help",
        "supply"
    ],
    "wof:name":"Don French",
    "wof:placetype":"venue"
},
  "geometry": {"coordinates":[-92.463718,35.434564],"type":"Point"}
}