{
  "type": "Feature",
  "properties": {
    "iso:country":"US",
    "sg:address":"102 E Laurel St",
    "sg:city":"Prescott",
    "sg:classifiers":[
        {
            "category":"Organizations",
            "subcategory":"Religious Organization",
            "type":"Services"
        }
    ],
    "sg:phone":"+1 870 887 5868",
    "sg:postcode":"71857",
    "sg:province":"AR",
    "sg:tags":[
        "church"
    ],
    "wof:name":"Park Missionary Baptist Church",
    "wof:placetype":"venue"
},
  "geometry": {"coordinates":[-93.377985,33.804056],"type":"Point"}
}