{
  "type": "Feature",
  "properties": {
    "iso:country":"US",
    "sg:address":"11301 State Hwy 72",
    "sg:city":"Centerton",
    "sg:classifiers":[
        {
            "category":"Organizations",
            "subcategory":"Community Association",
            "type":"Services"
        }
    ],
    "sg:phone":"+1 479 795 4320",
    "sg:postcode":"72712",
    "sg:province":"AR",
    "sg:tags":[
        "club"
    ],
    "wof:name":"Ingram Futbol Club",
    "wof:placetype":"venue"
},
  "geometry": {"coordinates":[-94.27469000000001,36.380054],"type":"Point"}
}