{
  "type": "Feature",
  "properties": {
    "addr:full":"11102 Hwy 167 N Sheridan AR 72150",
    "addr:housenumber":"11102",
    "addr:postcode":"72150",
    "addr:street":"Hwy 167 N",
    "iso:country":"US",
    "sg:address":"11102 Hwy 167 N",
    "sg:city":"Sheridan",
    "sg:classifiers":[
        {
            "category":"Manufacturing",
            "subcategory":"Glass & Minerals",
            "type":"Manufacturing & Wholesale Goods"
        }
    ],
    "sg:phone":"+1 870 942 2819",
    "sg:postcode":"72150",
    "sg:province":"AR",
    "sg:tags":[
        "tank",
        "septic",
        "concrete",
        "shelter",
        "mfg",
        "also",
        "storm"
    ],
    "wof:name":"Herron Concrete Products Inc",
    "wof:placetype":"venue"
},
  "geometry": {"coordinates":[-92.352571,34.446171],"type":"Point"}
}