{
  "type": "Feature",
  "properties": {
    "iso:country":"US",
    "sg:address":"1100 Theil Rd",
    "sg:city":"Paragould",
    "sg:classifiers":[
        {
            "category":"Restaurant",
            "type":"Food & Drink"
        }
    ],
    "sg:phone":"+1 870 239 5553",
    "sg:postcode":"72450",
    "sg:province":"AR",
    "sg:tags":[
        "banquet",
        "rooms"
    ],
    "wof:name":"Carol & Co",
    "wof:placetype":"venue"
},
  "geometry": {"coordinates":[-90.499979,36.074403],"type":"Point"}
}