{
  "type": "Feature",
  "properties": {
    "iso:country":"US",
    "sg:address":"1301 S Lincoln Ave",
    "sg:city":"Star City",
    "sg:classifiers":[
        {
            "category":"Home & Garden",
            "subcategory":"Hardware",
            "type":"Retail Goods"
        }
    ],
    "sg:phone":"+1 870 628 5128",
    "sg:postcode":"71667",
    "sg:province":"AR",
    "sg:tags":[
        "prod",
        "petroleum",
        "supply"
    ],
    "wof:name":"Matthews Inc",
    "wof:placetype":"venue"
},
  "geometry": {"coordinates":[-91.843704,33.927354],"type":"Point"}
}