{
  "type": "Feature",
  "properties": {
    "iso:country":"US",
    "sg:address":"1670 S Pleasant St",
    "sg:city":"Springdale",
    "sg:classifiers":[
        {
            "category":"Real Estate",
            "subcategory":"Real Estate Operator",
            "type":"Services"
        }
    ],
    "sg:phone":"+1 479 750 3030",
    "sg:postcode":"72764",
    "sg:province":"AR",
    "sg:tags":[
        "building",
        "apartment"
    ],
    "wof:name":"Pleasant Point Apartment Cmnty",
    "wof:placetype":"venue"
},
  "geometry": {"coordinates":[-94.143619,36.170984],"type":"Point"}
}