{
  "type": "Feature",
  "properties": {
    "addr:full":"3130 N 40th St Springdale AR 72762",
    "addr:housenumber":"3130",
    "addr:postcode":"72762",
    "addr:street":"N 40Th St",
    "iso:country":"US",
    "sg:address":"3130 N 40th St",
    "sg:city":"Springdale",
    "sg:classifiers":[
        {
            "category":"Building & Trades",
            "subcategory":"Cleaning & Sanitation",
            "type":"Services"
        }
    ],
    "sg:phone":"+1 479 751 2472",
    "sg:postcode":"72762",
    "sg:province":"AR",
    "sg:tags":[
        "maintenance"
    ],
    "wof:name":"Deweys Cleaning Svc",
    "wof:placetype":"venue"
},
  "geometry": {"coordinates":[-94.17377500000001,36.211389],"type":"Point"}
}