{
  "type": "Feature",
  "properties": {
    "iso:country":"US",
    "sg:address":"104 S Elm St",
    "sg:city":"Hope",
    "sg:classifiers":[
        {
            "category":"Retail",
            "subcategory":"Car Wash",
            "type":"Services"
        }
    ],
    "sg:phone":"+1 870 777 4671",
    "sg:postcode":"71801",
    "sg:province":"AR",
    "sg:tags":[
        "polishing",
        "washing"
    ],
    "wof:name":"Sheltered Workshop",
    "wof:placetype":"venue"
},
  "geometry": {"coordinates":[-93.59352699999999,33.668666],"type":"Point"}
}