{
  "type": "Feature",
  "properties": {
    "iso:country":"US",
    "sg:address":"62552 E 254 Rd",
    "sg:city":"Grove",
    "sg:classifiers":[
        {
            "category":"Building & Trades",
            "subcategory":"Construction",
            "type":"Services"
        }
    ],
    "sg:phone":"+1 918 787 4186",
    "sg:postcode":"74344",
    "sg:province":"OK",
    "sg:tags":[
        "hanging",
        "contractor"
    ],
    "wof:name":"Better Painting Services Inc",
    "wof:placetype":"venue"
},
  "geometry": {"coordinates":[-94.758889,36.64848],"type":"Point"}
}