{
  "type": "Feature",
  "properties": {
    "iso:country":"US",
    "sg:address":"128 Bailey St",
    "sg:city":"Searcy",
    "sg:classifiers":[
        {
            "category":"Personal",
            "subcategory":"Beauty Salon",
            "type":"Services"
        }
    ],
    "sg:phone":"+1 501 268 4674",
    "sg:postcode":"72143",
    "sg:province":"AR",
    "sg:tags":[
        "shop"
    ],
    "wof:name":"Taylor Equipment Repair",
    "wof:placetype":"venue"
},
  "geometry": {"coordinates":[-91.71461499999999,35.217682],"type":"Point"}
}