{
  "type": "Feature",
  "properties": {
    "addr:full":"331 E 13th St Hope AR 71801",
    "addr:housenumber":"331",
    "addr:postcode":"71801",
    "addr:street":"E 13Th St",
    "iso:country":"US",
    "sg:address":"331 E 13th St",
    "sg:city":"Hope",
    "sg:classifiers":[
        {
            "category":"Organizations",
            "subcategory":"Non-profit Organization",
            "type":"Services"
        }
    ],
    "sg:phone":"+1 870 285 2591",
    "sg:postcode":"71801",
    "sg:province":"AR",
    "sg:tags":[
        "charity",
        "foundations-educational",
        "philanthropic",
        "research"
    ],
    "wof:name":"Jtpa West Central Arkansas",
    "wof:placetype":"venue"
},
  "geometry": {"coordinates":[-93.58563100000001,33.657371],"type":"Point"}
}