{
  "type": "Feature",
  "properties": {
    "addr:full":"23233 I- 30 Bryant AR 72022",
    "addr:housenumber":"23233;30",
    "addr:postcode":"72022",
    "addr:street":"I",
    "iso:country":"US",
    "sg:address":"23233 I- 30",
    "sg:city":"Bryant",
    "sg:classifiers":[
        {
            "category":"Health Services",
            "subcategory":"Chiropractor",
            "type":"Services"
        }
    ],
    "sg:phone":"+1 501 847 7246",
    "sg:postcode":"72022",
    "sg:province":"AR",
    "wof:name":"Chiropractic Health Ctr",
    "wof:placetype":"venue"
},
  "geometry": {"coordinates":[-92.49191,34.622158],"type":"Point"}
}