{
  "type": "Feature",
  "properties": {
    "iso:country":"US",
    "sg:address":"1628 E Page Ave",
    "sg:city":"Malvern",
    "sg:classifiers":[
        {
            "category":"Health Services",
            "subcategory":"Doctor",
            "type":"Services"
        }
    ],
    "sg:phone":"+1 501 332 5236",
    "sg:postcode":"72104",
    "sg:province":"AR",
    "sg:tags":[
        "psychiatry",
        "physician",
        "surgeon",
        "surgeons"
    ],
    "wof:name":"Community Counseling Centers Of Chicago, Inc.",
    "wof:placetype":"venue"
},
  "geometry": {"coordinates":[-92.793476,34.364943],"type":"Point"}
}