{
  "type": "Feature",
  "properties": {
    "addr:full":"466 Hwy 225 E Greenbrier AR 72058",
    "addr:housenumber":"466",
    "addr:postcode":"72058",
    "addr:street":"Hwy 225 E",
    "iso:country":"US",
    "sg:address":"466 Hwy 225 E",
    "sg:city":"Greenbrier",
    "sg:classifiers":[
        {
            "category":"Retail",
            "subcategory":"Repair Shop",
            "type":"Services"
        }
    ],
    "sg:phone":"+1 501 679 5268",
    "sg:postcode":"72058",
    "sg:province":"AR",
    "wof:name":"Anthony Luce Taxidermy",
    "wof:placetype":"venue"
},
  "geometry": {"coordinates":[-92.292756,35.247319],"type":"Point"}
}