{
  "type": "Feature",
  "properties": {
    "addr:full":"440 S Main St Eudora AR 71640",
    "addr:housenumber":"440",
    "addr:postcode":"71640",
    "addr:street":"S Main St",
    "iso:country":"US",
    "sg:address":"440 S Main St",
    "sg:city":"Eudora",
    "sg:classifiers":[
        {
            "category":"Retail",
            "subcategory":"Auto Repair",
            "type":"Services"
        }
    ],
    "sg:phone":"+1 870 355 4840",
    "sg:postcode":"71640",
    "sg:province":"AR",
    "sg:tags":[
        "body",
        "automobile",
        "painting"
    ],
    "wof:name":"Petty's Body Shop",
    "wof:placetype":"venue"
},
  "geometry": {"coordinates":[-91.26202499999999,33.106967],"type":"Point"}
}