{
  "type": "Feature",
  "properties": {
    "iso:country":"US",
    "sg:address":"3301 N 6th St",
    "sg:city":"Fort Smith",
    "sg:classifiers":[
        {
            "category":"Shopping",
            "subcategory":"Used Merchandise",
            "type":"Retail Goods"
        }
    ],
    "sg:phone":"+1 479 784 9301",
    "sg:postcode":"72904",
    "sg:province":"AR",
    "sg:tags":[
        "appliance"
    ],
    "wof:name":"Reliable Appliances",
    "wof:placetype":"venue"
},
  "geometry": {"coordinates":[-94.39563200000001,35.413309],"type":"Point"}
}