{
  "type": "Feature",
  "properties": {
    "iso:country":"US",
    "sg:address":"300 W Dickson St",
    "sg:city":"Fayetteville",
    "sg:classifiers":[
        {
            "category":"Coffee & Tea",
            "type":"Food & Drink"
        },
        {
            "category":"Restaurant",
            "type":"Food & Drink"
        }
    ],
    "sg:phone":"+1 479 442 9682",
    "sg:postcode":"72701",
    "sg:province":"AR",
    "sg:tags":[
        "espresso"
    ],
    "wof:name":"Early Berlin",
    "wof:placetype":"venue"
},
  "geometry": {"coordinates":[-94.162987,36.066399],"type":"Point"}
}