{
  "type": "Feature",
  "properties": {
    "iso:country":"US",
    "sg:address":"2900 Horizon Dr",
    "sg:city":"Bryant",
    "sg:classifiers":[
        {
            "category":"Restaurant",
            "type":"Food & Drink"
        }
    ],
    "sg:menulink":"http://www.allmenus.com/ar/bryant/58102-dominos-pizza/menu/",
    "sg:phone":"+1 501 847 6100",
    "sg:postcode":"72022",
    "sg:province":"AR",
    "sg:tags":[
        "american",
        "wing",
        "pizza"
    ],
    "wof:name":"Domino's Pizza",
    "wof:placetype":"venue"
},
  "geometry": {"coordinates":[-92.497411,34.620993],"type":"Point"}
}