{
  "type": "Feature",
  "properties": {
    "iso:country":"US",
    "sg:address":"501 Albert Pike Rd",
    "sg:city":"Hot Springs",
    "sg:classifiers":[
        {
            "category":"Retail",
            "subcategory":"Laundry & Dry Cleaning",
            "type":"Services"
        }
    ],
    "sg:phone":"+1 501 623 6940",
    "sg:postcode":"71913",
    "sg:province":"AR",
    "sg:tags":[
        "garment",
        "cleaners",
        "plant",
        "agent",
        "drycleaning"
    ],
    "wof:name":"Taylors Cleaners Incorporated",
    "wof:placetype":"venue"
},
  "geometry": {"coordinates":[-93.074623,34.49639],"type":"Point"}
}