{
  "type": "Feature",
  "properties": {
    "iso:country":"US",
    "sg:address":"104 Academy Dr",
    "sg:city":"Paragould",
    "sg:classifiers":[
        {
            "category":"Health Services",
            "subcategory":"Doctor",
            "type":"Services"
        },
        {
            "category":"Health Services",
            "subcategory":"Clinic",
            "type":"Services"
        },
        {
            "category":"Community Center",
            "type":"Public Place"
        },
        {
            "category":"Health Services",
            "subcategory":"Chiropractor",
            "type":"Services"
        }
    ],
    "sg:phone":"+1 870 236 8201",
    "sg:postcode":"72450",
    "sg:province":"AR",
    "sg:tags":[
        "physician",
        "medical",
        "surgeon",
        "chiropractic"
    ],
    "wof:name":"K E Chester Dc",
    "wof:placetype":"venue"
},
  "geometry": {"coordinates":[-90.559389,36.065499],"type":"Point"}
}