{
  "type": "Feature",
  "properties": {
    "addr:full":"2011 Junction City Rd El Dorado AR 71730",
    "addr:housenumber":"2011",
    "addr:postcode":"71730",
    "addr:street":"Junction City Rd",
    "iso:country":"US",
    "sg:address":"2011 Junction City Rd",
    "sg:city":"El Dorado",
    "sg:classifiers":[
        {
            "category":"Restaurant",
            "type":"Food & Drink"
        }
    ],
    "sg:phone":"+1 870 862 3460",
    "sg:postcode":"71730",
    "sg:province":"AR",
    "wof:name":"Huddle House",
    "wof:placetype":"venue"
},
  "geometry": {"coordinates":[-92.64541699999999,33.202668],"type":"Point"}
}