{
  "type": "Feature",
  "properties": {
    "addr:full":"219 S Main St Warren AR 71671",
    "addr:housenumber":"219",
    "addr:postcode":"71671",
    "addr:street":"S Main St",
    "iso:country":"US",
    "sg:address":"219 S Main St",
    "sg:city":"Warren",
    "sg:classifiers":[
        {
            "category":"Restaurant",
            "type":"Food & Drink"
        }
    ],
    "sg:phone":"+1 870 226 5002",
    "sg:postcode":"71671",
    "sg:province":"AR",
    "sg:tags":[
        "mexican"
    ],
    "wof:name":"Su Tienda Mexicana",
    "wof:placetype":"venue"
},
  "geometry": {"coordinates":[-92.06432,33.611165],"type":"Point"}
}