{
  "type": "Feature",
  "properties": {
    "iso:country":"US",
    "sg:address":"200 Main St",
    "sg:city":"Scranton",
    "sg:classifiers":[
        {
            "category":"Organizations",
            "subcategory":"Religious Organization",
            "type":"Services"
        }
    ],
    "sg:phone":"+1 479 938 2821",
    "sg:postcode":"72863",
    "sg:province":"AR",
    "sg:tags":[
        "church"
    ],
    "wof:name":"St Ignatius Church",
    "wof:placetype":"venue"
},
  "geometry": {"coordinates":[-93.531857,35.360841],"type":"Point"}
}