{
  "type": "Feature",
  "properties": {
    "addr:full":"123 S East St Benton AR 72015",
    "addr:housenumber":"123",
    "addr:postcode":"72015",
    "addr:street":"S East St",
    "iso:country":"US",
    "sg:address":"123 S East St",
    "sg:city":"Benton",
    "sg:classifiers":[
        {
            "category":"Autos & Motor Vehicles",
            "subcategory":"Fuel & Gas Station",
            "type":"Retail Goods"
        }
    ],
    "sg:phone":"+1 501 778 2878",
    "sg:postcode":"72015",
    "sg:province":"AR",
    "sg:tags":[
        "oil"
    ],
    "wof:name":"Shell",
    "wof:placetype":"venue"
},
  "geometry": {"coordinates":[-92.585701,34.563177],"type":"Point"}
}