{
  "type": "Feature",
  "properties": {
    "addr:full":"2360 Heber Springs Rd N Tumbling Shoals AR 72581",
    "addr:housenumber":"2360",
    "addr:postcode":"72581",
    "addr:street":"Heber Springs Rd N Tumbling",
    "iso:country":"US",
    "sg:address":"2360 Heber Springs Rd N",
    "sg:city":"Tumbling Shoals",
    "sg:classifiers":[
        {
            "category":"Building & Trades",
            "subcategory":"Construction",
            "type":"Services"
        },
        {
            "category":"Home & Garden",
            "subcategory":"Furniture",
            "type":"Retail Goods"
        }
    ],
    "sg:phone":"+1 501 362 6545",
    "sg:postcode":"72581",
    "sg:province":"AR",
    "sg:tags":[
        "shop",
        "cabinet",
        "maker",
        "custom"
    ],
    "wof:name":"Ricky Logan Cabinet Shop",
    "wof:placetype":"venue"
},
  "geometry": {"coordinates":[-91.931985,35.577032],"type":"Point"}
}