{
  "type": "Feature",
  "properties": {
    "addr:full":"1180 Collier Dr Conway AR 72032",
    "addr:housenumber":"1180",
    "addr:postcode":"72032",
    "addr:street":"Collier Dr",
    "iso:country":"US",
    "sg:address":"1180 Collier Dr",
    "sg:city":"Conway",
    "sg:classifiers":[
        {
            "category":"Professional",
            "subcategory":"Computer Services",
            "type":"Services"
        }
    ],
    "sg:phone":"+1 501 329 9144",
    "sg:postcode":"72032",
    "sg:province":"AR",
    "sg:tags":[
        "repair"
    ],
    "sg:website":"www.tcworks.net",
    "wof:name":"Computer Works",
    "wof:placetype":"venue"
},
  "geometry": {"coordinates":[-92.424277,35.094328],"type":"Point"}
}