{
  "type": "Feature",
  "properties": {
    "iso:country":"US",
    "sg:address":"500 Morgan St",
    "sg:city":"Newark",
    "sg:classifiers":[
        {
            "category":"Shopping",
            "subcategory":"Florist",
            "type":"Retail Goods"
        }
    ],
    "sg:phone":"+1 870 799 8612",
    "sg:postcode":"72562",
    "sg:province":"AR",
    "wof:name":"The Master's Garden",
    "wof:placetype":"venue"
},
  "geometry": {"coordinates":[-91.44714399999999,35.701721],"type":"Point"}
}