{
  "type": "Feature",
  "properties": {
    "iso:country":"US",
    "sg:address":"302 E Iowa St",
    "sg:city":"Dermott",
    "sg:classifiers":[
        {
            "category":"Home & Garden",
            "subcategory":"Building Materials",
            "type":"Retail Goods"
        }
    ],
    "sg:phone":"+1 870 538 5274",
    "sg:postcode":"71638",
    "sg:province":"AR",
    "sg:tags":[
        "equipment",
        "electric",
        "supply"
    ],
    "wof:name":"Payne's Lumber & Hardware",
    "wof:placetype":"venue"
},
  "geometry": {"coordinates":[-91.433504,33.52803],"type":"Point"}
}