{
  "type": "Feature",
  "properties": {
    "iso:country":"US",
    "sg:address":"801 Shaver St",
    "sg:city":"Springdale",
    "sg:classifiers":[
        {
            "category":"Structure",
            "subcategory":"Office Building",
            "type":"Public Place"
        }
    ],
    "sg:phone":"+1 479 756 2884",
    "sg:postcode":"72762",
    "sg:province":"AR",
    "sg:tags":[
        "park"
    ],
    "wof:name":"Steele Properties",
    "wof:placetype":"venue"
},
  "geometry": {"coordinates":[-94.169601,36.18058],"type":"Point"}
}