{
  "type": "Feature",
  "properties": {
    "iso:country":"US",
    "sg:address":"344 Peaceful Valley Rd",
    "sg:city":"Dover",
    "sg:classifiers":[
        {
            "category":"Retail",
            "subcategory":"Auto Repair",
            "type":"Services"
        }
    ],
    "sg:phone":"+1 479 331 4866",
    "sg:postcode":"72837",
    "sg:province":"AR",
    "sg:tags":[
        "repairing",
        "automobile"
    ],
    "wof:name":"Dover Auto Salvage",
    "wof:placetype":"venue"
},
  "geometry": {"coordinates":[-93.120064,35.39299],"type":"Point"}
}