{
  "type": "Feature",
  "properties": {
    "addr:full":"705 W Redbud Ln Alma AR 72921",
    "addr:housenumber":"705",
    "addr:postcode":"72921",
    "addr:street":"W Redbud Ln",
    "iso:country":"US",
    "sg:address":"705 W Redbud Ln",
    "sg:city":"Alma",
    "sg:classifiers":[
        {
            "category":"Organizations",
            "subcategory":"Religious Organization",
            "type":"Services"
        }
    ],
    "sg:phone":"+1 479 632 3512",
    "sg:postcode":"72921",
    "sg:province":"AR",
    "wof:name":"Kibler Freewill Baptist",
    "wof:placetype":"venue"
},
  "geometry": {"coordinates":[-94.243008,35.436192],"type":"Point"}
}