{
  "type": "Feature",
  "properties": {
    "iso:country":"US",
    "sg:address":"474 E Main St",
    "sg:city":"Piggott",
    "sg:classifiers":[
        {
            "category":"Personal",
            "subcategory":"Beauty Salon",
            "type":"Services"
        }
    ],
    "sg:phone":"+1 870 598 3130",
    "sg:postcode":"72454",
    "sg:province":"AR",
    "wof:name":"Carmel & Co",
    "wof:placetype":"venue"
},
  "geometry": {"coordinates":[-90.18539,36.381972],"type":"Point"}
}