{
  "type": "Feature",
  "properties": {
    "iso:country":"US",
    "sg:address":"1811 Timberline Dr",
    "sg:city":"Texarkana",
    "sg:classifiers":[
        {
            "category":"Farming",
            "subcategory":"Farm",
            "type":"Manufacturing & Wholesale Goods"
        }
    ],
    "sg:phone":"+1 870 772 1964",
    "sg:postcode":"71854",
    "sg:province":"AR",
    "sg:tags":[
        "crop",
        "general"
    ],
    "wof:name":"River Bend Farms Inc",
    "wof:placetype":"venue"
},
  "geometry": {"coordinates":[-94.022825,33.465104],"type":"Point"}
}