{
  "type": "Feature",
  "properties": {
    "iso:country":"US",
    "sg:address":"1000 W Elm St",
    "sg:city":"Corning",
    "sg:classifiers":[
        {
            "category":"Retail",
            "subcategory":"Funeral Services",
            "type":"Services"
        }
    ],
    "sg:phone":"+1 870 857 3596",
    "sg:postcode":"72422",
    "sg:province":"AR",
    "sg:tags":[
        "director",
        "embalmer",
        "plans-pre-arranged"
    ],
    "wof:name":"Ermert Funeral Home Inc",
    "wof:placetype":"venue"
},
  "geometry": {"coordinates":[-90.585419,36.410252],"type":"Point"}
}