{
  "type": "Feature",
  "properties": {
    "iso:country":"US",
    "sg:address":"4248 Lawson Rd",
    "sg:city":"El Dorado",
    "sg:classifiers":[
        {
            "category":"Food & Beverages",
            "subcategory":"Groceries & Convenience Stores",
            "type":"Retail Goods"
        }
    ],
    "sg:phone":"+1 870 962 3501",
    "sg:postcode":"71730",
    "sg:province":"AR",
    "sg:tags":[
        "grocer"
    ],
    "wof:name":"Snack Shack",
    "wof:placetype":"venue"
},
  "geometry": {"coordinates":[-92.443137,33.158212],"type":"Point"}
}