{
  "type": "Feature",
  "properties": {
    "addr:full":"611 S 4th St Van Buren AR 72956",
    "addr:housenumber":"611",
    "addr:postcode":"72956",
    "addr:street":"S 4Th St",
    "iso:country":"US",
    "sg:address":"611 S 4th St",
    "sg:city":"Van Buren",
    "sg:classifiers":[
        {
            "category":"Wholesale",
            "subcategory":"Fruits & Vegetables",
            "type":"Manufacturing & Wholesale Goods"
        }
    ],
    "sg:phone":"+1 479 471 5145",
    "sg:postcode":"72956",
    "sg:province":"AR",
    "wof:name":"Metro Produce Inc",
    "wof:placetype":"venue"
},
  "geometry": {"coordinates":[-94.349912,35.430005],"type":"Point"}
}