{
  "type": "Feature",
  "properties": {
    "iso:country":"US",
    "sg:address":"8556 W McNelly Rd",
    "sg:city":"Bentonville",
    "sg:classifiers":[
        {
            "category":"Education",
            "subcategory":"Dance Studio",
            "type":"Public Place"
        }
    ],
    "sg:phone":"+1 479 464 9973",
    "sg:postcode":"72712",
    "sg:province":"AR",
    "sg:tags":[
        "instruction",
        "dancing"
    ],
    "wof:name":"Asprire Gymnastics",
    "wof:placetype":"venue"
},
  "geometry": {"coordinates":[-94.216864,36.424549],"type":"Point"}
}