{
  "type": "Feature",
  "properties": {
    "iso:country":"US",
    "sg:address":"1510 N West Ave",
    "sg:city":"El Dorado",
    "sg:classifiers":[
        {
            "category":"Banks & Credit Unions",
            "subcategory":"Bank",
            "type":"Services"
        }
    ],
    "sg:phone":"+1 870 863 3181",
    "sg:postcode":"71730",
    "sg:province":"AR",
    "wof:name":"Bancorp South Bank",
    "wof:placetype":"venue"
},
  "geometry": {"coordinates":[-92.665682,33.225335],"type":"Point"}
}