{
  "type": "Feature",
  "properties": {
    "iso:country":"US",
    "sg:address":"48 E Township St",
    "sg:city":"Fayetteville",
    "sg:classifiers":[
        {
            "category":"Personal",
            "subcategory":"Tattoo Parlor",
            "type":"Services"
        }
    ],
    "sg:phone":"+1 479 935 4778",
    "sg:postcode":"72703",
    "sg:province":"AR",
    "wof:name":"Infinity Tattoo",
    "wof:placetype":"venue"
},
  "geometry": {"coordinates":[-94.15728,36.095291],"type":"Point"}
}