{
  "type": "Feature",
  "properties": {
    "iso:country":"US",
    "sg:address":"2801 Alma Hwy",
    "sg:city":"Van Buren",
    "sg:classifiers":[
        {
            "category":"Personal",
            "subcategory":"Beauty Salon",
            "type":"Services"
        }
    ],
    "sg:phone":"+1 479 410 2602",
    "sg:postcode":"72956",
    "sg:province":"AR",
    "wof:name":"Tangles",
    "wof:placetype":"venue"
},
  "geometry": {"coordinates":[-94.328093,35.442153],"type":"Point"}
}