{
  "type": "Feature",
  "properties": {
    "iso:country":"US",
    "sg:address":"4694 State Hwy 163",
    "sg:city":"Jonesboro",
    "sg:classifiers":[
        {
            "category":"Personal",
            "subcategory":"Beauty Salon",
            "type":"Services"
        }
    ],
    "sg:phone":"+1 870 802 4202",
    "sg:postcode":"72404",
    "sg:province":"AR",
    "sg:tags":[
        "shop"
    ],
    "wof:name":"Ransones Hair Care",
    "wof:placetype":"venue"
},
  "geometry": {"coordinates":[-90.66106600000001,35.707261],"type":"Point"}
}