{
  "type": "Feature",
  "properties": {
    "iso:country":"US",
    "sg:address":"116 S Broadway St",
    "sg:city":"Siloam Springs",
    "sg:classifiers":[
        {
            "category":"Personal",
            "type":"Services"
        }
    ],
    "sg:phone":"+1 479 549 3000",
    "sg:postcode":"72761",
    "sg:province":"OK",
    "sg:tags":[
        "therapist",
        "massage"
    ],
    "wof:name":"Advocating Massage",
    "wof:placetype":"venue"
},
  "geometry": {"coordinates":[-94.540681,36.184982],"type":"Point"}
}