{
  "type": "Feature",
  "properties": {
    "iso:country":"US",
    "sg:address":"23 Hatfield Dr",
    "sg:city":"Little Rock",
    "sg:classifiers":[
        {
            "category":"Organizations",
            "subcategory":"Non-profit Organization",
            "type":"Services"
        }
    ],
    "sg:phone":"+1 501 562 7000",
    "sg:postcode":"72209",
    "sg:province":"AR",
    "sg:tags":[
        "information",
        "alcoholism",
        "treatment"
    ],
    "wof:name":"Sobriety First",
    "wof:placetype":"venue"
},
  "geometry": {"coordinates":[-92.36645900000001,34.666082],"type":"Point"}
}