{
  "type": "Feature",
  "properties": {
    "iso:country":"US",
    "sg:address":"2210 S 8th St",
    "sg:city":"Rogers",
    "sg:classifiers":[
        {
            "category":"Autos & Motor Vehicles",
            "subcategory":"Automobile Sales",
            "type":"Retail Goods"
        }
    ],
    "sg:phone":"+1 479 986 0288",
    "sg:postcode":"72758",
    "sg:province":"AR",
    "sg:tags":[
        "car",
        "dealer"
    ],
    "wof:name":"Chuck's Used Cars",
    "wof:placetype":"venue"
},
  "geometry": {"coordinates":[-94.126611,36.303556],"type":"Point"}
}