{
  "type": "Feature",
  "properties": {
    "iso:country":"US",
    "sg:address":"625 Sadie Ln",
    "sg:city":"Centerton",
    "sg:classifiers":[
        {
            "category":"Organizations",
            "subcategory":"Religious Organization",
            "type":"Services"
        }
    ],
    "sg:phone":"+1 479 795 0482",
    "sg:postcode":"72719",
    "sg:province":"AR",
    "wof:name":"Oklahoma Tulsa Mission",
    "wof:placetype":"venue"
},
  "geometry": {"coordinates":[-94.28573799999999,36.364648],"type":"Point"}
}