{
  "type": "Feature",
  "properties": {
    "iso:country":"US",
    "sg:address":"912 W 6th Ave",
    "sg:city":"Pine Bluff",
    "sg:classifiers":[
        {
            "category":"Education",
            "subcategory":"School",
            "type":"Public Place"
        }
    ],
    "sg:phone":"+1 870 534 5823",
    "sg:postcode":"71601",
    "sg:province":"AR",
    "wof:name":"Jefferson County Adult Edctn",
    "wof:placetype":"venue"
},
  "geometry": {"coordinates":[-92.012553,34.223746],"type":"Point"}
}