{
  "type": "Feature",
  "properties": {
    "iso:country":"US",
    "sg:address":"85 Batesville Blvd",
    "sg:city":"Batesville",
    "sg:classifiers":[
        {
            "category":"Shopping",
            "subcategory":"Discount & Variety Stores",
            "type":"Retail Goods"
        }
    ],
    "sg:phone":"+1 870 698 9229",
    "sg:postcode":"72501",
    "sg:province":"AR",
    "sg:tags":[
        "merchandise",
        "general"
    ],
    "wof:name":"S & S Liquidations",
    "wof:placetype":"venue"
},
  "geometry": {"coordinates":[-91.641073,35.755676],"type":"Point"}
}