{
  "type": "Feature",
  "properties": {
    "iso:country":"US",
    "sg:address":"304 Poinsett St",
    "sg:city":"Marked Tree",
    "sg:classifiers":[
        {
            "category":"Real Estate",
            "subcategory":"Developer",
            "type":"Services"
        }
    ],
    "sg:phone":"+1 870 358 2487",
    "sg:postcode":"72365",
    "sg:province":"AR",
    "sg:tags":[
        "cemetery"
    ],
    "wof:name":"Cemetery Nichols Assoc",
    "wof:placetype":"venue"
},
  "geometry": {"coordinates":[-90.422938,35.529385],"type":"Point"}
}