{
  "type": "Feature",
  "properties": {
    "iso:country":"US",
    "sg:address":"2015 Fuller",
    "sg:city":"Mountain Home",
    "sg:classifiers":[
        {
            "category":"Wholesale",
            "subcategory":"Construction Materials",
            "type":"Manufacturing & Wholesale Goods"
        }
    ],
    "sg:phone":"+1 870 424 4686",
    "sg:postcode":"72653",
    "sg:province":"AR",
    "wof:name":"Don Young Company Incorporated",
    "wof:placetype":"venue"
},
  "geometry": {"coordinates":[-92.40215999999999,36.32232],"type":"Point"}
}