{
  "type": "Feature",
  "properties": {
    "iso:country":"US",
    "sg:address":"1600 S Jackson Ave",
    "sg:city":"El Dorado",
    "sg:classifiers":[
        {
            "category":"Wholesale",
            "subcategory":"Scrap",
            "type":"Manufacturing & Wholesale Goods"
        }
    ],
    "sg:phone":"+1 870 881 4187",
    "sg:postcode":"71730",
    "sg:province":"AR",
    "sg:tags":[
        "recycling",
        "center"
    ],
    "wof:name":"El Dorado Recycling Ctr",
    "wof:placetype":"venue"
},
  "geometry": {"coordinates":[-92.66132899999999,33.194571],"type":"Point"}
}