{
  "type": "Feature",
  "properties": {
    "iso:country":"US",
    "sg:address":"1615 S Arkansas Ave",
    "sg:city":"Russellville",
    "sg:classifiers":[
        {
            "category":"Sports & Exercise",
            "subcategory":"Gym",
            "type":"Entertainment"
        }
    ],
    "sg:phone":"+1 479 967 2837",
    "sg:postcode":"72801",
    "sg:province":"AR",
    "sg:tags":[
        "fitness",
        "physical",
        "facility"
    ],
    "wof:name":"Head To Toe",
    "wof:placetype":"venue"
},
  "geometry": {"coordinates":[-93.134203,35.263947],"type":"Point"}
}