{
  "type": "Feature",
  "properties": {
    "iso:country":"US",
    "sg:address":"1123 S University Ave",
    "sg:city":"Little Rock",
    "sg:classifiers":[
        {
            "category":"Organizations",
            "subcategory":"Professional Association",
            "type":"Services"
        }
    ],
    "sg:phone":"+1 501 663 8444",
    "sg:postcode":"72204",
    "sg:province":"AR",
    "wof:name":"Arkansas Manufactured Housing",
    "wof:placetype":"venue"
},
  "geometry": {"coordinates":[-92.341335,34.742513],"type":"Point"}
}