{
  "type": "Feature",
  "properties": {
    "iso:country":"US",
    "sg:address":"3701 Jenny Lind Rd",
    "sg:city":"Fort Smith",
    "sg:classifiers":[
        {
            "category":"Retail",
            "subcategory":"Laundry & Dry Cleaning",
            "type":"Services"
        }
    ],
    "sg:phone":"+1 479 646 9191",
    "sg:postcode":"72901",
    "sg:province":"AR",
    "wof:name":"Day & Nite Cleaners Inc",
    "wof:placetype":"venue"
},
  "geometry": {"coordinates":[-94.413517,35.347583],"type":"Point"}
}