{
  "type": "Feature",
  "properties": {
    "addr:full":"1502 W Main St Corning AR 72422",
    "addr:housenumber":"1502",
    "addr:postcode":"72422",
    "addr:street":"W Main St",
    "iso:country":"US",
    "sg:address":"1502 W Main St",
    "sg:city":"Corning",
    "sg:classifiers":[
        {
            "category":"Autos & Motor Vehicles",
            "subcategory":"Automobile Sales",
            "type":"Retail Goods"
        }
    ],
    "sg:phone":"+1 870 857 3964",
    "sg:postcode":"72422",
    "sg:province":"AR",
    "sg:tags":[
        "used"
    ],
    "wof:name":"Knobel Auto Sales",
    "wof:placetype":"venue"
},
  "geometry": {"coordinates":[-90.59322899999999,36.411419],"type":"Point"}
}