{
  "type": "Feature",
  "properties": {
    "iso:country":"US",
    "sg:address":"500 S University Ave",
    "sg:city":"Little Rock",
    "sg:classifiers":[
        {
            "category":"Health Services",
            "subcategory":"Doctor",
            "type":"Services"
        }
    ],
    "sg:phone":"+1 501 664 2434",
    "sg:postcode":"72205",
    "sg:province":"AR",
    "sg:tags":[
        "medical"
    ],
    "wof:name":"Vinsant Kurtis S",
    "wof:placetype":"venue"
},
  "geometry": {"coordinates":[-92.34134,34.747693],"type":"Point"}
}