{
  "type": "Feature",
  "properties": {
    "iso:country":"US",
    "sg:address":"1351 Cyro Rd",
    "sg:city":"Osceola",
    "sg:classifiers":[
        {
            "category":"Government",
            "subcategory":"Office",
            "type":"Public Place"
        }
    ],
    "sg:phone":"+1 870 563 5366",
    "sg:postcode":"72370",
    "sg:province":"AR",
    "sg:website":"www.dcc.com",
    "wof:name":"Community Punishment Dept",
    "wof:placetype":"venue"
},
  "geometry": {"coordinates":[-89.984294,35.683019],"type":"Point"}
}