{
  "type": "Feature",
  "properties": {
    "addr:full":"1919 W Sunset Ave Springdale AR 72762",
    "addr:housenumber":"1919",
    "addr:postcode":"72762",
    "addr:street":"W Sunset Ave",
    "iso:country":"US",
    "sg:address":"1919 W Sunset Ave",
    "sg:city":"Springdale",
    "sg:classifiers":[
        {
            "category":"Fast Food",
            "type":"Food & Drink"
        },
        {
            "category":"Restaurant",
            "type":"Food & Drink"
        },
        {
            "category":"Food & Beverages",
            "subcategory":"Groceries & Convenience Stores",
            "type":"Retail Goods"
        }
    ],
    "sg:phone":"+1 479 751 9800",
    "sg:postcode":"72762",
    "sg:province":"AR",
    "sg:tags":[
        "shop",
        "sandwich",
        "take"
    ],
    "sg:website":"http://www.schlotzskys.com",
    "wof:name":"Schlotzsky's",
    "wof:placetype":"venue"
},
  "geometry": {"coordinates":[-94.15169,36.174782],"type":"Point"}
}