{
  "type": "Feature",
  "properties": {
    "iso:country":"US",
    "sg:address":"334 Pitman Rd",
    "sg:city":"Pitman",
    "sg:classifiers":[
        {
            "category":"Organizations",
            "subcategory":"Community Association",
            "type":"Services"
        }
    ],
    "sg:phone":"+1 856 589 9682",
    "sg:postcode":"72444",
    "sg:province":"AR",
    "sg:tags":[
        "fraternal"
    ],
    "wof:name":"Pitman Masonic Temple Assn",
    "wof:placetype":"venue"
},
  "geometry": {"coordinates":[-90.83766799999999,36.460434],"type":"Point"}
}