{
  "type": "Feature",
  "properties": {
    "addr:full":"516 W North St Lincoln AR 72744",
    "addr:housenumber":"516",
    "addr:postcode":"72744",
    "addr:street":"W North St",
    "iso:country":"US",
    "sg:address":"516 W North St",
    "sg:city":"Lincoln",
    "sg:classifiers":[
        {
            "category":"Professional",
            "type":"Services"
        }
    ],
    "sg:phone":"+1 479 824 2010",
    "sg:postcode":"72744",
    "sg:province":"AR",
    "wof:name":"Karen Karnes",
    "wof:placetype":"venue"
},
  "geometry": {"coordinates":[-94.430261,35.951784],"type":"Point"}
}