{
  "type": "Feature",
  "properties": {
    "iso:country":"US",
    "sg:address":"317 Hwy 425 S",
    "sg:city":"Monticello",
    "sg:classifiers":[
        {
            "category":"Travel",
            "subcategory":"Hotels & Motels",
            "type":"Entertainment"
        }
    ],
    "sg:phone":"+1 870 367 1881",
    "sg:postcode":"71655",
    "sg:province":"AR",
    "sg:tags":[
        "operation"
    ],
    "wof:name":"Days Inn",
    "wof:placetype":"venue"
},
  "geometry": {"coordinates":[-91.802639,33.624886],"type":"Point"}
}