{
  "type": "Feature",
  "properties": {
    "addr:full":"720 Summerhill Dr Gassville AR 72635",
    "addr:housenumber":"720",
    "addr:postcode":"72635",
    "addr:street":"Summerhill Dr",
    "iso:country":"US",
    "sg:address":"720 Summerhill Dr",
    "sg:city":"Gassville",
    "sg:classifiers":[
        {
            "category":"Recreation",
            "type":"Entertainment"
        }
    ],
    "sg:phone":"+1 870 435 2467",
    "sg:postcode":"72635",
    "sg:province":"AR",
    "sg:tags":[
        "party",
        "fishing"
    ],
    "wof:name":"Professional Fishing Service",
    "wof:placetype":"venue"
},
  "geometry": {"coordinates":[-92.482877,36.29235],"type":"Point"}
}