{
  "type": "Feature",
  "properties": {
    "iso:country":"US",
    "sg:address":"1285 E Millsap Rd",
    "sg:city":"Fayetteville",
    "sg:classifiers":[
        {
            "category":"Organizations",
            "subcategory":"Religious Organization",
            "type":"Services"
        }
    ],
    "sg:phone":"+1 479 527 0008",
    "sg:postcode":"72703",
    "sg:province":"AR",
    "wof:name":"Worldwide Missionary Evangelism",
    "wof:placetype":"venue"
},
  "geometry": {"coordinates":[-94.14277,36.114776],"type":"Point"}
}