{
  "type": "Feature",
  "properties": {
    "iso:country":"US",
    "sg:address":"1949 Stratsman Ln",
    "sg:city":"Cave Springs",
    "sg:classifiers":[
        {
            "category":"Building & Trades",
            "subcategory":"Plumbing",
            "type":"Services"
        }
    ],
    "sg:phone":"+1 479 248 7247",
    "sg:postcode":"72718",
    "sg:province":"AR",
    "sg:tags":[
        "contractor"
    ],
    "wof:name":"Air Temp Control",
    "wof:placetype":"venue"
},
  "geometry": {"coordinates":[-94.203435,36.279111],"type":"Point"}
}