{
  "type": "Feature",
  "properties": {
    "iso:country":"US",
    "sg:address":"105 N Missouri Ave",
    "sg:city":"Corning",
    "sg:classifiers":[
        {
            "category":"Fast Food",
            "type":"Food & Drink"
        },
        {
            "category":"Restaurant",
            "type":"Food & Drink"
        },
        {
            "category":"Food & Beverages",
            "subcategory":"Groceries & Convenience Stores",
            "type":"Retail Goods"
        }
    ],
    "sg:phone":"+1 870 857 9113",
    "sg:postcode":"72422",
    "sg:province":"AR",
    "sg:tags":[
        "shop",
        "american",
        "sandwich",
        "take"
    ],
    "sg:website":"http://www.subway.com",
    "wof:name":"Subway",
    "wof:placetype":"venue"
},
  "geometry": {"coordinates":[-90.58640200000001,36.412381],"type":"Point"}
}