{
  "type": "Feature",
  "properties": {
    "iso:country":"US",
    "sg:address":"308 Engelberg Rd",
    "sg:city":"Pocahontas",
    "sg:classifiers":[
        {
            "category":"Retail",
            "subcategory":"Repair Shop",
            "type":"Services"
        }
    ],
    "sg:phone":"+1 870 892 3591",
    "sg:postcode":"72455",
    "sg:province":"AR",
    "wof:name":"Snodgrass Electronics",
    "wof:placetype":"venue"
},
  "geometry": {"coordinates":[-90.939806,36.288423],"type":"Point"}
}