{
  "type": "Feature",
  "properties": {
    "iso:country":"US",
    "sg:address":"305 N Main St",
    "sg:city":"Atkins",
    "sg:classifiers":[
        {
            "category":"Government",
            "subcategory":"Office",
            "type":"Public Place"
        },
        {
            "category":"Government",
            "subcategory":"Police Station",
            "type":"Public Place"
        }
    ],
    "sg:phone":"+1 479 641 1811",
    "sg:postcode":"72843",
    "sg:province":"AR",
    "sg:tags":[
        "department"
    ],
    "wof:name":"Atkins Police Department",
    "wof:placetype":"venue"
},
  "geometry": {"coordinates":[-92.875427,35.425749],"type":"Point"}
}