{
  "type": "Feature",
  "properties": {
    "iso:country":"US",
    "sg:address":"407 S Air Base Hwy",
    "sg:city":"Blytheville",
    "sg:classifiers":[
        {
            "category":"Personal",
            "subcategory":"Beauty Salon",
            "type":"Services"
        }
    ],
    "sg:phone":"+1 870 532 2455",
    "sg:postcode":"72315",
    "sg:province":"AR",
    "sg:tags":[
        "shop"
    ],
    "wof:name":"Hair Styling Center",
    "wof:placetype":"venue"
},
  "geometry": {"coordinates":[-89.96518,35.956141],"type":"Point"}
}