{
  "type": "Feature",
  "properties": {
    "iso:country":"US",
    "sg:address":"5700 E 9th St",
    "sg:city":"Texarkana",
    "sg:classifiers":[
        {
            "category":"Wholesale",
            "subcategory":"Hardware",
            "type":"Manufacturing & Wholesale Goods"
        },
        {
            "category":"Home & Garden",
            "subcategory":"Garden Supply",
            "type":"Retail Goods"
        },
        {
            "category":"Retail",
            "subcategory":"Repair Shop",
            "type":"Services"
        }
    ],
    "sg:phone":"+1 870 772 7061",
    "sg:postcode":"71854",
    "sg:province":"AR",
    "sg:tags":[
        "renting",
        "lawn",
        "outdoor",
        "power",
        "landscaping",
        "equipment-sales",
        "equipment",
        "saw"
    ],
    "sg:website":"http://www.stihlusa.com/",
    "wof:name":"Mills Outdoor Power Equipment",
    "wof:placetype":"venue"
},
  "geometry": {"coordinates":[-93.97305299999999,33.429958],"type":"Point"}
}