{
  "type": "Feature",
  "properties": {
    "iso:country":"US",
    "sg:address":"178 W Cadron Ridge Rd",
    "sg:city":"Greenbrier",
    "sg:classifiers":[
        {
            "category":"Building & Trades",
            "subcategory":"Construction",
            "type":"Services"
        },
        {
            "category":"Manufacturing",
            "subcategory":"Building Materials",
            "type":"Manufacturing & Wholesale Goods"
        }
    ],
    "sg:phone":"+1 501 371 9033",
    "sg:postcode":"72058",
    "sg:province":"AR",
    "sg:tags":[
        "plastering",
        "coating",
        "contractor",
        "exterior",
        "distributor",
        "stucco",
        "manufacturer"
    ],
    "wof:name":"Buddy Oliver Plastering",
    "wof:placetype":"venue"
},
  "geometry": {"coordinates":[-92.422544,35.160201],"type":"Point"}
}