{
  "type": "Feature",
  "properties": {
    "addr:full":"1171 Hwy 62 W Pocahontas AR 72455",
    "addr:housenumber":"1171",
    "addr:postcode":"72455",
    "addr:street":"Hwy 62 W",
    "iso:country":"US",
    "sg:address":"1171 Hwy 62 W",
    "sg:city":"Pocahontas",
    "sg:classifiers":[
        {
            "category":"Shopping",
            "type":"Retail Goods"
        }
    ],
    "sg:phone":"+1 870 892 2255",
    "sg:postcode":"72455",
    "sg:province":"AR",
    "sg:tags":[
        "cellular",
        "merchandise",
        "telephone"
    ],
    "wof:name":"Cellular Mobility Inc",
    "wof:placetype":"venue"
},
  "geometry": {"coordinates":[-90.977236,36.253867],"type":"Point"}
}