{
  "type": "Feature",
  "properties": {
    "addr:full":"5217 Bass Alexander AR 72002",
    "addr:housenumber":"5217",
    "addr:postcode":"72002",
    "addr:street":"Bass Alexander",
    "iso:country":"US",
    "sg:address":"5217 Bass",
    "sg:city":"Alexander",
    "sg:classifiers":[
        {
            "category":"Government",
            "subcategory":"Court House",
            "type":"Public Place"
        }
    ],
    "sg:phone":"+1 501 681 7577",
    "sg:postcode":"72002",
    "sg:province":"AR",
    "sg:tags":[
        "justice"
    ],
    "wof:name":"Howell Barbara Justice Of The Peace",
    "wof:placetype":"venue"
},
  "geometry": {"coordinates":[-92.639898,34.725788],"type":"Point"}
}