{
  "type": "Feature",
  "properties": {
    "iso:country":"US",
    "sg:address":"2358 N Blue Mesa Dr",
    "sg:city":"Fayetteville",
    "sg:classifiers":[
        {
            "category":"Shopping",
            "subcategory":"Jewelry",
            "type":"Retail Goods"
        }
    ],
    "sg:phone":"+1 479 521 7172",
    "sg:postcode":"72703",
    "sg:province":"AR",
    "wof:name":"Bracelets & More Inc",
    "wof:placetype":"venue"
},
  "geometry": {"coordinates":[-94.110053,36.091205],"type":"Point"}
}