{
  "type": "Feature",
  "properties": {
    "iso:country":"US",
    "sg:address":"8148 Catfish Rd",
    "sg:city":"Booneville",
    "sg:classifiers":[
        {
            "category":"Building & Trades",
            "subcategory":"Landscaping Services",
            "type":"Services"
        }
    ],
    "sg:phone":"+1 479 996 8077",
    "sg:postcode":"72927",
    "sg:province":"AR",
    "sg:tags":[
        "sod",
        "sodding"
    ],
    "wof:name":"J & H Sod Farm",
    "wof:placetype":"venue"
},
  "geometry": {"coordinates":[-94.024607,35.205625],"type":"Point"}
}