{
  "type": "Feature",
  "properties": {
    "iso:country":"US",
    "sg:address":"901 S Moose St",
    "sg:city":"Morrilton",
    "sg:classifiers":[
        {
            "category":"Building & Trades",
            "subcategory":"Construction",
            "type":"Services"
        }
    ],
    "sg:phone":"+1 501 354 0227",
    "sg:postcode":"72110",
    "sg:province":"AR",
    "sg:tags":[
        "hanging",
        "contractor"
    ],
    "wof:name":"Ernesto Nevarez",
    "wof:placetype":"venue"
},
  "geometry": {"coordinates":[-92.742148,35.143425],"type":"Point"}
}