{
  "type": "Feature",
  "properties": {
    "iso:country":"US",
    "sg:address":"500 W 6th St",
    "sg:city":"Russellville",
    "sg:classifiers":[
        {
            "category":"Recreation",
            "type":"Entertainment"
        }
    ],
    "sg:phone":"+1 479 890 5114",
    "sg:postcode":"72801",
    "sg:province":"AR",
    "sg:tags":[
        "instruction",
        "yoga"
    ],
    "wof:name":"A Zakharian",
    "wof:placetype":"venue"
},
  "geometry": {"coordinates":[-93.138447,35.273361],"type":"Point"}
}