{
  "type": "Feature",
  "properties": {
    "iso:country":"US",
    "sg:address":"320 Executive Ct",
    "sg:city":"Little Rock",
    "sg:classifiers":[
        {
            "category":"Professional",
            "subcategory":"Accounting & Tax Preparation",
            "type":"Services"
        }
    ],
    "sg:phone":"+1 501 225 3927",
    "sg:postcode":"72205",
    "sg:province":"AR",
    "sg:tags":[
        "bookkeeping",
        "general"
    ],
    "wof:name":"Financial Express",
    "wof:placetype":"venue"
},
  "geometry": {"coordinates":[-92.390412,34.753302],"type":"Point"}
}