{
  "type": "Feature",
  "properties": {
    "iso:country":"US",
    "sg:address":"1515 Aldersgate Rd",
    "sg:city":"Little Rock",
    "sg:classifiers":[
        {
            "category":"Health Services",
            "subcategory":"Doctor",
            "type":"Services"
        }
    ],
    "sg:phone":"+1 501 975 1539",
    "sg:postcode":"72205",
    "sg:province":"AR",
    "wof:name":"Dunlap Bryan DDS PA",
    "wof:placetype":"venue"
},
  "geometry": {"coordinates":[-92.389867,34.741879],"type":"Point"}
}