{
  "type": "Feature",
  "properties": {
    "iso:country":"US",
    "sg:address":"529 State Hwy 23",
    "sg:city":"Eureka Springs",
    "sg:classifiers":[
        {
            "category":"Home & Garden",
            "subcategory":"Building Materials",
            "type":"Retail Goods"
        }
    ],
    "sg:phone":"+1 479 253 1226",
    "sg:postcode":"72632",
    "sg:province":"AR",
    "sg:tags":[
        "glass",
        "window",
        "plate"
    ],
    "wof:name":"Phoenix Fiber Glass",
    "wof:placetype":"venue"
},
  "geometry": {"coordinates":[-93.752908,36.367289],"type":"Point"}
}