{
  "type": "Feature",
  "properties": {
    "iso:country":"US",
    "sg:address":"1110 Matt Ln",
    "sg:city":"Hensley",
    "sg:classifiers":[
        {
            "category":"Building & Trades",
            "subcategory":"Landscaping Services",
            "type":"Services"
        }
    ],
    "sg:phone":"+1 501 847 6807",
    "sg:postcode":"72065",
    "sg:province":"AR",
    "wof:name":"Certified Landscapes of Ark",
    "wof:placetype":"venue"
},
  "geometry": {"coordinates":[-92.273313,34.556553],"type":"Point"}
}