{
  "type": "Feature",
  "properties": {
    "iso:country":"US",
    "sg:address":"369 Oakhaven Rd",
    "sg:city":"Hope",
    "sg:classifiers":[
        {
            "category":"Professional",
            "subcategory":"Advertising",
            "type":"Services"
        }
    ],
    "sg:phone":"+1 870 777 2627",
    "sg:postcode":"71801",
    "sg:province":"AR",
    "wof:name":"Natural Choices",
    "wof:placetype":"venue"
},
  "geometry": {"coordinates":[-93.619978,33.72878],"type":"Point"}
}