{
  "type": "Feature",
  "properties": {
    "addr:full":"1316 Stone St Jonesboro AR 72401",
    "addr:housenumber":"1316",
    "addr:postcode":"72401",
    "addr:street":"Stone St",
    "iso:country":"US",
    "sg:address":"1316 Stone St",
    "sg:city":"Jonesboro",
    "sg:classifiers":[
        {
            "category":"Sports & Exercise",
            "subcategory":"Gym",
            "type":"Entertainment"
        }
    ],
    "sg:phone":"+1 870 931 1901",
    "sg:postcode":"72401",
    "sg:province":"AR",
    "sg:tags":[
        "club",
        "health",
        "studio",
        "gymnasium"
    ],
    "wof:name":"Body Fit Gym",
    "wof:placetype":"venue"
},
  "geometry": {"coordinates":[-90.675656,35.830015],"type":"Point"}
}