{
  "type": "Feature",
  "properties": {
    "iso:country":"US",
    "sg:address":"1104 N Illinois St",
    "sg:city":"Harrisburg",
    "sg:classifiers":[
        {
            "category":"Restaurant",
            "type":"Food & Drink"
        }
    ],
    "sg:menulink":"http://www.allmenus.com/ar/bolivar/111667-subway/menu/",
    "sg:phone":"+1 870 578 9999",
    "sg:postcode":"72432",
    "sg:province":"AR",
    "sg:tags":[
        "american",
        "sandwich"
    ],
    "wof:name":"Subway",
    "wof:placetype":"venue"
},
  "geometry": {"coordinates":[-90.723597,35.575512],"type":"Point"}
}