{
  "type": "Feature",
  "properties": {
    "iso:country":"US",
    "sg:address":"1000 E Matthews Ave",
    "sg:city":"Jonesboro",
    "sg:classifiers":[
        {
            "category":"Health Services",
            "subcategory":"Health Practitioner",
            "type":"Services"
        }
    ],
    "sg:phone":"+1 870 931 4045",
    "sg:postcode":"72401",
    "sg:province":"AR",
    "sg:tags":[
        "therapist",
        "physical"
    ],
    "wof:name":"Healthsouth Rehabilitation Ctr",
    "wof:placetype":"venue"
},
  "geometry": {"coordinates":[-90.69519699999999,35.835724],"type":"Point"}
}