{
  "type": "Feature",
  "properties": {
    "iso:country":"US",
    "sg:address":"225 Turner Cir",
    "sg:city":"Forrest City",
    "sg:classifiers":[
        {
            "category":"Home & Garden",
            "subcategory":"Building Materials",
            "type":"Retail Goods"
        }
    ],
    "sg:phone":"+1 870 633 4010",
    "sg:postcode":"72335",
    "sg:province":"AR",
    "sg:tags":[
        "mixed",
        "concrete"
    ],
    "wof:name":"Arkansas Concrete",
    "wof:placetype":"venue"
},
  "geometry": {"coordinates":[-90.80194,35.011361],"type":"Point"}
}