{
  "type": "Feature",
  "properties": {
    "iso:country":"US",
    "sg:address":"700 SE 5th St",
    "sg:city":"Bentonville",
    "sg:phone":"+1 479 254 7050",
    "sg:postcode":"72712",
    "sg:province":"AR",
    "sg:tags":[
        "product",
        "petroleum"
    ],
    "wof:name":"Pennzoil - Quaker State Co",
    "wof:placetype":"venue"
},
  "geometry": {"coordinates":[-94.200604,36.367613],"type":"Point"}
}