{
  "type": "Feature",
  "properties": {
    "iso:country":"US",
    "sg:address":"4039 State Hwy 36",
    "sg:city":"Searcy",
    "sg:classifiers":[
        {
            "category":"Organizations",
            "subcategory":"Religious Organization",
            "type":"Services"
        }
    ],
    "sg:phone":"+1 501 305 3052",
    "sg:postcode":"72143",
    "sg:province":"AR",
    "sg:tags":[
        "church"
    ],
    "wof:name":"Crosby Church Of Christ",
    "wof:placetype":"venue"
},
  "geometry": {"coordinates":[-91.888528,35.262716],"type":"Point"}
}