{
  "type": "Feature",
  "properties": {
    "addr:full":"107 Knight St Pocola OK 74902",
    "addr:housenumber":"107",
    "addr:postcode":"74902",
    "addr:street":"Knight St",
    "iso:country":"US",
    "sg:address":"107 Knight St",
    "sg:city":"Pocola",
    "sg:classifiers":[
        {
            "category":"Freight",
            "type":"Transportation"
        }
    ],
    "sg:phone":"+1 918 626 3801",
    "sg:postcode":"74902",
    "sg:province":"OK",
    "sg:tags":[
        "operator",
        "local",
        "trucking"
    ],
    "wof:name":"William Slate Trucking",
    "wof:placetype":"venue"
},
  "geometry": {"coordinates":[-94.445075,35.305786],"type":"Point"}
}