{
  "type": "Feature",
  "properties": {
    "addr:full":"413 Garland Ave Hot Springs National Park AR 71913",
    "addr:housenumber":"413",
    "addr:postcode":"71913",
    "addr:street":"Garland Ave",
    "iso:country":"US",
    "sg:address":"413 Garland Ave",
    "sg:city":"Hot Springs National Park",
    "sg:classifiers":[
        {
            "category":"Manufacturing",
            "subcategory":"Tools & Machinery",
            "type":"Manufacturing & Wholesale Goods"
        }
    ],
    "sg:phone":"+1 501 609 0031",
    "sg:postcode":"71913",
    "sg:province":"AR",
    "sg:tags":[
        "machine",
        "shop"
    ],
    "wof:name":"American Eagle Mac Sh & ME Fab",
    "wof:placetype":"venue"
},
  "geometry": {"coordinates":[-93.063776,34.499793],"type":"Point"}
}