{
  "type": "Feature",
  "properties": {
    "iso:country":"US",
    "sg:address":"237 Klenc Rd",
    "sg:city":"Springdale",
    "sg:classifiers":[
        {
            "category":"Food & Beverages",
            "subcategory":"Groceries & Convenience Stores",
            "type":"Retail Goods"
        }
    ],
    "sg:phone":"+1 479 361 2281",
    "sg:postcode":"72762",
    "sg:province":"AR",
    "wof:name":"Market Vision Consulting Inc",
    "wof:placetype":"venue"
},
  "geometry": {"coordinates":[-94.245826,36.174948],"type":"Point"}
}