{
  "type": "Feature",
  "properties": {
    "iso:country":"US",
    "sg:address":"1799 State Hwy 1",
    "sg:city":"Harrisburg",
    "sg:classifiers":[
        {
            "category":"Organizations",
            "subcategory":"Religious Organization",
            "type":"Services"
        }
    ],
    "sg:phone":"+1 870 578 9374",
    "sg:postcode":"72432",
    "sg:province":"AR",
    "sg:tags":[
        "church"
    ],
    "wof:name":"Lebanon Baptist Church",
    "wof:placetype":"venue"
},
  "geometry": {"coordinates":[-90.737191,35.47276],"type":"Point"}
}