{
  "type": "Feature",
  "properties": {
    "iso:country":"US",
    "sg:address":"15204 Cross Over Rd",
    "sg:city":"Gravette",
    "sg:classifiers":[
        {
            "category":"Farming",
            "subcategory":"Livestock Farm",
            "type":"Manufacturing & Wholesale Goods"
        }
    ],
    "sg:phone":"+1 479 787 5119",
    "sg:postcode":"72736",
    "sg:province":"AR",
    "sg:tags":[
        "beef",
        "feedlot",
        "cattle"
    ],
    "wof:name":"D & J Farms",
    "wof:placetype":"venue"
},
  "geometry": {"coordinates":[-94.36631300000001,36.439294],"type":"Point"}
}