{
  "type": "Feature",
  "properties": {
    "iso:country":"US",
    "sg:address":"127 Rabbit Rd",
    "sg:city":"El Dorado",
    "sg:classifiers":[
        {
            "category":"Freight",
            "type":"Transportation"
        }
    ],
    "sg:phone":"+1 870 863 0177",
    "sg:postcode":"71730",
    "sg:province":"AR",
    "sg:tags":[
        "operator",
        "local",
        "trucking"
    ],
    "wof:name":"T K Trucking",
    "wof:placetype":"venue"
},
  "geometry": {"coordinates":[-92.646251,33.113783],"type":"Point"}
}