{
  "type": "Feature",
  "properties": {
    "iso:country":"US",
    "sg:address":"804 W Denver St",
    "sg:city":"Greenwood",
    "sg:classifiers":[
        {
            "category":"Shopping",
            "type":"Retail Goods"
        }
    ],
    "sg:phone":"+1 479 996 9754",
    "sg:postcode":"72936",
    "sg:province":"AR",
    "sg:tags":[
        "merchandise"
    ],
    "wof:name":"Professional Hearing Systems",
    "wof:placetype":"venue"
},
  "geometry": {"coordinates":[-94.268581,35.215969],"type":"Point"}
}