{
  "type": "Feature",
  "properties": {
    "iso:country":"US",
    "sg:address":"1916 W Sunset Ave",
    "sg:city":"Springdale",
    "sg:classifiers":[
        {
            "category":"Autos & Motor Vehicles",
            "subcategory":"Auto Supplies",
            "type":"Retail Goods"
        },
        {
            "category":"Professional",
            "subcategory":"Art Services",
            "type":"Services"
        },
        {
            "category":"Professional",
            "subcategory":"Printing & Photocopies",
            "type":"Services"
        },
        {
            "category":"Professional",
            "subcategory":"Advertising",
            "type":"Services"
        },
        {
            "category":"Manufacturing",
            "subcategory":"Signs",
            "type":"Manufacturing & Wholesale Goods"
        }
    ],
    "sg:phone":"+1 866 254 2657",
    "sg:postcode":"72762",
    "sg:province":"AR",
    "sg:tags":[
        "lettering",
        "product",
        "designer",
        "advertising-promotional",
        "producer",
        "specialty",
        "flag",
        "truck",
        "pennant",
        "banners",
        "painting",
        "display"
    ],
    "sg:website":"http://ad.doubleclick.net/clk;226206195;50079909;l?http://fastsigns.com/279",
    "wof:name":"FASTSIGNS",
    "wof:placetype":"venue"
},
  "geometry": {"coordinates":[-94.151691,36.174782],"type":"Point"}
}