{
  "type": "Feature",
  "properties": {
    "addr:full":"801 N West Ave El Dorado AR 71730",
    "addr:housenumber":"801",
    "addr:postcode":"71730",
    "addr:street":"N West Ave",
    "iso:country":"US",
    "sg:address":"801 N West Ave",
    "sg:city":"El Dorado",
    "sg:classifiers":[
        {
            "category":"Retail",
            "subcategory":"Repair Shop",
            "type":"Services"
        }
    ],
    "sg:phone":"+1 870 862 8370",
    "sg:postcode":"71730",
    "sg:province":"AR",
    "sg:tags":[
        "lock",
        "locksmith"
    ],
    "wof:name":"KERR Safe & Lock Co",
    "wof:placetype":"venue"
},
  "geometry": {"coordinates":[-92.665487,33.21973],"type":"Point"}
}