{
  "type": "Feature",
  "properties": {
    "addr:full":"1602 Main St Crossett AR 71635",
    "addr:housenumber":"1602",
    "addr:postcode":"71635",
    "addr:street":"Main St",
    "iso:country":"US",
    "sg:address":"1602 Main St",
    "sg:city":"Crossett",
    "sg:classifiers":[
        {
            "category":"Health Services",
            "subcategory":"Optometrist",
            "type":"Services"
        }
    ],
    "sg:phone":"+1 870 364 8996",
    "sg:postcode":"71635",
    "sg:province":"AR",
    "wof:name":"Buck & Smith Eye Care Center",
    "wof:placetype":"venue"
},
  "geometry": {"coordinates":[-91.95849,33.115043],"type":"Point"}
}