{
  "type": "Feature",
  "properties": {
    "addr:full":"1864 State Hwy 35 Monticello AR 71655",
    "addr:housenumber":"1864",
    "addr:postcode":"71655",
    "addr:street":"State Hwy 35",
    "iso:country":"US",
    "sg:address":"1864 State Hwy 35",
    "sg:city":"Monticello",
    "sg:classifiers":[
        {
            "category":"Professional",
            "type":"Services"
        }
    ],
    "sg:phone":"+1 870 367 8517",
    "sg:postcode":"71655",
    "sg:province":"AR",
    "wof:name":"New Care",
    "wof:placetype":"venue"
},
  "geometry": {"coordinates":[-91.747614,33.619236],"type":"Point"}
}