{
  "type": "Feature",
  "properties": {
    "iso:country":"US",
    "sg:address":"3601 Bracy Rd",
    "sg:city":"Little Rock",
    "sg:classifiers":[
        {
            "category":"Shopping",
            "subcategory":"Bicycles & Sporting Goods",
            "type":"Retail Goods"
        }
    ],
    "sg:phone":"+1 501 888 4618",
    "sg:postcode":"72206",
    "sg:province":"AR",
    "sg:tags":[
        "bait",
        "fishing"
    ],
    "wof:name":"Bracy Rd Sporting Goods",
    "wof:placetype":"venue"
},
  "geometry": {"coordinates":[-92.325067,34.58928],"type":"Point"}
}