{
  "type": "Feature",
  "properties": {
    "iso:country":"US",
    "sg:address":"481 L P Mann Dr",
    "sg:city":"Marion",
    "sg:classifiers":[
        {
            "category":"Retail",
            "subcategory":"Auto Repair",
            "type":"Services"
        }
    ],
    "sg:phone":"+1 870 739 2174",
    "sg:postcode":"72364",
    "sg:province":"AR",
    "wof:name":"Browns Auto Exchange",
    "wof:placetype":"venue"
},
  "geometry": {"coordinates":[-90.197783,35.198272],"type":"Point"}
}