{
  "type": "Feature",
  "properties": {
    "iso:country":"US",
    "sg:address":"22269 Highway 9",
    "sg:city":"Paron",
    "sg:classifiers":[
        {
            "category":"Social Services",
            "subcategory":"Child Care",
            "type":"Services"
        }
    ],
    "sg:phone":"+1 501 594 5668",
    "sg:postcode":"72122",
    "sg:province":"AR",
    "sg:tags":[
        "nursery",
        "day"
    ],
    "wof:name":"Paron Headstart",
    "wof:placetype":"venue"
},
  "geometry": {"coordinates":[-92.761595,34.738992],"type":"Point"}
}