{
  "type": "Feature",
  "properties": {
    "iso:country":"US",
    "sg:address":"151 Wahpeton Hill Rd",
    "sg:city":"Hardy",
    "sg:classifiers":[
        {
            "category":"Place Of Worship",
            "subcategory":"Church",
            "type":"Public Place"
        },
        {
            "category":"Place Of Worship",
            "type":"Public Place"
        }
    ],
    "sg:phone":"+1 870 856 3426",
    "sg:postcode":"72542",
    "sg:province":"AR",
    "sg:tags":[
        "churches-presbyterian-arp",
        "churches-presbyterian"
    ],
    "wof:name":"Spring River Presbytiran Church",
    "wof:placetype":"venue"
},
  "geometry": {"coordinates":[-91.486542,36.311768],"type":"Point"}
}