{
  "type": "Feature",
  "properties": {
    "iso:country":"US",
    "sg:address":"809 Bristol Square St",
    "sg:city":"Waldron",
    "sg:classifiers":[
        {
            "category":"Real Estate",
            "subcategory":"Real Estate Operator",
            "type":"Services"
        }
    ],
    "sg:phone":"+1 479 637 4433",
    "sg:postcode":"72958",
    "sg:province":"AR",
    "sg:tags":[
        "apartment"
    ],
    "wof:name":"Bristol Square Apartments",
    "wof:placetype":"venue"
},
  "geometry": {"coordinates":[-94.099492,34.894152],"type":"Point"}
}