{
  "type": "Feature",
  "properties": {
    "iso:country":"US",
    "sg:address":"10 River Oaks Cir",
    "sg:city":"Little Rock",
    "sg:classifiers":[
        {
            "category":"Home & Garden",
            "subcategory":"Garden Supply",
            "type":"Retail Goods"
        }
    ],
    "sg:phone":"+1 501 663 3358",
    "sg:postcode":"72207",
    "sg:province":"AR",
    "sg:tags":[
        "nurseryman"
    ],
    "wof:name":"Novaca Tree Farm",
    "wof:placetype":"venue"
},
  "geometry": {"coordinates":[-92.35534800000001,34.785852],"type":"Point"}
}