{
  "type": "Feature",
  "properties": {
    "addr:full":"8800 Asher Ave Little Rock AR 72204",
    "addr:housenumber":"8800",
    "addr:postcode":"72204",
    "addr:street":"Asher Ave",
    "iso:country":"US",
    "sg:address":"8800 Asher Ave",
    "sg:city":"Little Rock",
    "sg:classifiers":[
        {
            "category":"Autos & Motor Vehicles",
            "subcategory":"Auto Supplies",
            "type":"Retail Goods"
        }
    ],
    "sg:phone":"+1 501 565 3247",
    "sg:postcode":"72204",
    "sg:province":"AR",
    "wof:name":"Autozone 35",
    "wof:placetype":"venue"
},
  "geometry": {"coordinates":[-92.37373700000001,34.710485],"type":"Point"}
}