{
  "type": "Feature",
  "properties": {
    "iso:country":"US",
    "sg:address":"9101 US Hwy 71",
    "sg:city":"Fort Smith",
    "sg:classifiers":[
        {
            "category":"Shopping",
            "subcategory":"Tobacco",
            "type":"Retail Goods"
        }
    ],
    "sg:phone":"+1 479 648 0806",
    "sg:postcode":"72908",
    "sg:province":"AR",
    "sg:tags":[
        "cigarette",
        "product",
        "cigar",
        "dealer"
    ],
    "wof:name":"Discount Tobacco Of Ft Smith",
    "wof:placetype":"venue"
},
  "geometry": {"coordinates":[-94.388266,35.297379],"type":"Point"}
}