{
  "type": "Feature",
  "properties": {
    "addr:full":"150 Creech Rd Quitman AR 72131",
    "addr:housenumber":"150",
    "addr:postcode":"72131",
    "addr:street":"Creech Rd",
    "iso:country":"US",
    "sg:address":"150 Creech Rd",
    "sg:city":"Quitman",
    "sg:classifiers":[
        {
            "category":"Professional",
            "type":"Services"
        }
    ],
    "sg:phone":"+1 501 589 2088",
    "sg:postcode":"72131",
    "sg:province":"AR",
    "wof:name":"Cabana Mobile Est",
    "wof:placetype":"venue"
},
  "geometry": {"coordinates":[-92.191125,35.460835],"type":"Point"}
}