{
  "type": "Feature",
  "properties": {
    "iso:country":"US",
    "sg:address":"402 Main St",
    "sg:city":"Van Buren",
    "sg:classifiers":[
        {
            "category":"Shopping",
            "subcategory":"Used Merchandise",
            "type":"Retail Goods"
        },
        {
            "category":"Wholesale",
            "subcategory":"Durable Goods & Equipment",
            "type":"Manufacturing & Wholesale Goods"
        }
    ],
    "sg:phone":"+1 479 474 4808",
    "sg:postcode":"72956",
    "sg:province":"AR",
    "sg:tags":[
        "antique"
    ],
    "wof:name":"Antique Warehouse Arkansas Inc",
    "wof:placetype":"venue"
},
  "geometry": {"coordinates":[-94.354685,35.435112],"type":"Point"}
}