{
  "type": "Feature",
  "properties": {
    "iso:country":"US",
    "sg:address":"426 Helen St",
    "sg:city":"West Helena",
    "sg:classifiers":[
        {
            "category":"Shopping",
            "subcategory":"Shoes",
            "type":"Retail Goods"
        }
    ],
    "sg:phone":"+1 870 572 2977",
    "sg:postcode":"72390",
    "sg:province":"AR",
    "wof:name":"Footworks",
    "wof:placetype":"venue"
},
  "geometry": {"coordinates":[-90.645097,34.551316],"type":"Point"}
}