{
  "type": "Feature",
  "properties": {
    "iso:country":"US",
    "sg:address":"1821 Pamela Way",
    "sg:city":"Alexander",
    "sg:classifiers":[
        {
            "category":"Building & Trades",
            "subcategory":"Landscaping Services",
            "type":"Services"
        }
    ],
    "sg:phone":"+1 501 847 3017",
    "sg:postcode":"72002",
    "sg:province":"AR",
    "wof:name":"Wells Lawn & Landscape",
    "wof:placetype":"venue"
},
  "geometry": {"coordinates":[-92.506487,34.67314],"type":"Point"}
}