{
  "type": "Feature",
  "properties": {
    "addr:full":"16101 Cantrell Rd Little Rock AR 72223",
    "addr:housenumber":"16101",
    "addr:postcode":"72223",
    "addr:street":"Cantrell Rd",
    "iso:country":"US",
    "sg:address":"16101 Cantrell Rd",
    "sg:city":"Little Rock",
    "sg:classifiers":[
        {
            "category":"Restaurant",
            "type":"Food & Drink"
        }
    ],
    "sg:phone":"+1 501 868 3250",
    "sg:postcode":"72223",
    "sg:province":"AR",
    "wof:name":"Razorback Pizza",
    "wof:placetype":"venue"
},
  "geometry": {"coordinates":[-92.45033599999999,34.803167],"type":"Point"}
}