{
  "type": "Feature",
  "properties": {
    "iso:country":"US",
    "sg:address":"1006 W Main St",
    "sg:city":"Mountain View",
    "sg:classifiers":[
        {
            "category":"Wholesale",
            "subcategory":"Farm Supplies",
            "type":"Manufacturing & Wholesale Goods"
        },
        {
            "category":"Shopping",
            "type":"Retail Goods"
        }
    ],
    "sg:phone":"+1 870 269 3356",
    "sg:postcode":"72560",
    "sg:province":"AR",
    "sg:tags":[
        "feed",
        "merchandise"
    ],
    "wof:name":"North Arkansas Farm Supply",
    "wof:placetype":"venue"
},
  "geometry": {"coordinates":[-92.135628,35.864475],"type":"Point"}
}