{
  "type": "Feature",
  "properties": {
    "addr:full":"1558 W Storage Dr Fayetteville AR 72701",
    "addr:housenumber":"1558",
    "addr:postcode":"72701",
    "addr:street":"W Storage Dr",
    "iso:country":"US",
    "sg:address":"1558 W Storage Dr",
    "sg:city":"Fayetteville",
    "sg:classifiers":[
        {
            "category":"Social Services",
            "subcategory":"Job Training",
            "type":"Services"
        }
    ],
    "sg:phone":"+1 479 582 2492",
    "sg:postcode":"72701",
    "sg:province":"AR",
    "sg:tags":[
        "rehabilitation"
    ],
    "wof:name":"Progressive Plastic & Pkg Inc",
    "wof:placetype":"venue"
},
  "geometry": {"coordinates":[-94.183421,36.054692],"type":"Point"}
}