{
  "type": "Feature",
  "properties": {
    "addr:full":"117 E 2nd Junction City AR 71749",
    "addr:housenumber":"117",
    "addr:postcode":"71749",
    "addr:street":"E 2Nd",
    "iso:country":"US",
    "sg:address":"117 E 2nd",
    "sg:city":"Junction City",
    "sg:classifiers":[
        {
            "category":"Building & Trades",
            "subcategory":"Plumbing",
            "type":"Services"
        }
    ],
    "sg:phone":"+1 870 924 4058",
    "sg:postcode":"71749",
    "sg:province":"AR",
    "sg:tags":[
        "conditioning",
        "air",
        "system",
        "contractor"
    ],
    "wof:name":"Midsouth Heating & Air Cond",
    "wof:placetype":"venue"
},
  "geometry": {"coordinates":[-92.724585,33.015435],"type":"Point"}
}