{
  "type": "Feature",
  "properties": {
    "iso:country":"US",
    "sg:address":"849 E Main St",
    "sg:city":"Blytheville",
    "sg:classifiers":[
        {
            "category":"Banks & Credit Unions",
            "subcategory":"Bank",
            "type":"Services"
        }
    ],
    "sg:phone":"+1 870 762 5513",
    "sg:postcode":"72315",
    "sg:province":"AR",
    "sg:tags":[
        "loan"
    ],
    "wof:name":"Cash 4U",
    "wof:placetype":"venue"
},
  "geometry": {"coordinates":[-89.890475,35.927242],"type":"Point"}
}