{
  "type": "Feature",
  "properties": {
    "iso:country":"US",
    "sg:address":"5716 N Locust St",
    "sg:city":"N Little Rock",
    "sg:classifiers":[
        {
            "category":"Shopping",
            "subcategory":"Hobbies, Toys, & Games",
            "type":"Retail Goods"
        }
    ],
    "sg:phone":"+1 501 753 1813",
    "sg:postcode":"72116",
    "sg:province":"AR",
    "sg:tags":[
        "supply"
    ],
    "wof:name":"Grand Cypress Game Supply Co",
    "wof:placetype":"venue"
},
  "geometry": {"coordinates":[-92.255954,34.808885],"type":"Point"}
}