{
  "type": "Feature",
  "properties": {
    "addr:full":"17020 Speaker Ln Little Rock AR 72206",
    "addr:housenumber":"17020",
    "addr:postcode":"72206",
    "addr:street":"Speaker Ln",
    "iso:country":"US",
    "sg:address":"17020 Speaker Ln",
    "sg:city":"Little Rock",
    "sg:classifiers":[
        {
            "category":"Professional",
            "subcategory":"Business Services",
            "type":"Services"
        }
    ],
    "sg:phone":"+1 501 888 2587",
    "sg:postcode":"72206",
    "sg:province":"AR",
    "sg:tags":[
        "lecture",
        "bureau",
        "seminar"
    ],
    "wof:name":"John Philpot Co",
    "wof:placetype":"venue"
},
  "geometry": {"coordinates":[-92.320397,34.595445],"type":"Point"}
}