{
  "type": "Feature",
  "properties": {
    "iso:country":"US",
    "sg:address":"157 S Main St",
    "sg:city":"Mountain Home",
    "sg:classifiers":[
        {
            "category":"Restaurant",
            "type":"Food & Drink"
        }
    ],
    "sg:phone":"+1 870 425 5367",
    "sg:postcode":"72653",
    "sg:province":"AR",
    "wof:name":"Mr Leo's",
    "wof:placetype":"venue"
},
  "geometry": {"coordinates":[-92.385188,36.339315],"type":"Point"}
}