{
  "type": "Feature",
  "properties": {
    "iso:country":"US",
    "sg:address":"203 E Main St",
    "sg:city":"Flippin",
    "sg:classifiers":[
        {
            "category":"Real Estate",
            "subcategory":"Real Estate Agent",
            "type":"Services"
        }
    ],
    "sg:phone":"+1 870 453 7368",
    "sg:postcode":"72634",
    "sg:province":"AR",
    "sg:tags":[
        "agency",
        "rental"
    ],
    "wof:name":"Best Rental",
    "wof:placetype":"venue"
},
  "geometry": {"coordinates":[-92.598938,36.277719],"type":"Point"}
}