{
  "type": "Feature",
  "properties": {
    "addr:full":"2210 Fianna Oaks Dr Fort Smith AR 72908",
    "addr:housenumber":"2210",
    "addr:postcode":"72908",
    "addr:street":"Fianna Oaks Dr",
    "iso:country":"US",
    "sg:address":"2210 Fianna Oaks Dr",
    "sg:city":"Fort Smith",
    "sg:classifiers":[
        {
            "category":"Retail",
            "subcategory":"Veterinary Services",
            "type":"Services"
        }
    ],
    "sg:phone":"+1 479 646 2300",
    "sg:postcode":"72908",
    "sg:province":"AR",
    "sg:tags":[
        "hospital",
        "animal"
    ],
    "wof:name":"Fianna Hills Pet Hospital",
    "wof:placetype":"venue"
},
  "geometry": {"coordinates":[-94.412459,35.299561],"type":"Point"}
}