{
  "type": "Feature",
  "properties": {
    "addr:full":"508 E Booth Rd Searcy AR 72143",
    "addr:housenumber":"508",
    "addr:postcode":"72143",
    "addr:street":"E Booth Rd",
    "iso:country":"US",
    "sg:address":"508 E Booth Rd",
    "sg:city":"Searcy",
    "sg:classifiers":[
        {
            "category":"Freight",
            "type":"Transportation"
        }
    ],
    "sg:phone":"+1 501 268 5444",
    "sg:postcode":"72143",
    "sg:province":"AR",
    "sg:tags":[
        "commercial",
        "storage",
        "special",
        "general"
    ],
    "wof:name":"Grassy Knoll Holdings Mini",
    "wof:placetype":"venue"
},
  "geometry": {"coordinates":[-91.730193,35.224184],"type":"Point"}
}