{
  "type": "Feature",
  "properties": {
    "iso:country":"US",
    "sg:address":"1804 Martha Dr",
    "sg:city":"Little Rock",
    "sg:classifiers":[
        {
            "category":"Freight",
            "type":"Transportation"
        }
    ],
    "sg:phone":"+1 501 312 9245",
    "sg:postcode":"72212",
    "sg:province":"AR",
    "sg:tags":[
        "operator",
        "trucking"
    ],
    "wof:name":"D&B Express Inc",
    "wof:placetype":"venue"
},
  "geometry": {"coordinates":[-92.416129,34.77118],"type":"Point"}
}