{
  "type": "Feature",
  "properties": {
    "addr:full":"209 Co Rd 381 Wynne AR 72396",
    "addr:housenumber":"209;381",
    "addr:postcode":"72396",
    "addr:street":"Co Rd",
    "iso:country":"US",
    "sg:address":"209 Co Rd 381",
    "sg:city":"Wynne",
    "sg:classifiers":[
        {
            "category":"Banks & Credit Unions",
            "subcategory":"Financial Services",
            "type":"Services"
        }
    ],
    "sg:phone":"+1 870 238 5382",
    "sg:postcode":"72396",
    "sg:province":"AR",
    "sg:tags":[
        "investor"
    ],
    "wof:name":"Delta Ladies Investments Club",
    "wof:placetype":"venue"
},
  "geometry": {"coordinates":[-90.745317,35.258591],"type":"Point"}
}