{
  "type": "Feature",
  "properties": {
    "iso:country":"US",
    "sg:address":"8625 Southridge Dr",
    "sg:city":"Fort Smith",
    "sg:classifiers":[
        {
            "category":"Retail",
            "subcategory":"Repair Shop",
            "type":"Services"
        }
    ],
    "sg:phone":"+1 479 646 5255",
    "sg:postcode":"72908",
    "sg:province":"AR",
    "sg:tags":[
        "upholsterer"
    ],
    "wof:name":"Brettco Alterations Custom",
    "wof:placetype":"venue"
},
  "geometry": {"coordinates":[-94.421259,35.30211],"type":"Point"}
}