{
  "type": "Feature",
  "properties": {
    "iso:country":"US",
    "sg:address":"414 E 3rd St",
    "sg:city":"Grove",
    "sg:classifiers":[
        {
            "category":"Personal",
            "subcategory":"Beauty Salon",
            "type":"Services"
        }
    ],
    "sg:phone":"+1 918 787 2484",
    "sg:postcode":"74344",
    "sg:province":"OK",
    "wof:name":"Salon Fusion",
    "wof:placetype":"venue"
},
  "geometry": {"coordinates":[-94.764321,36.597953],"type":"Point"}
}