{
  "type": "Feature",
  "properties": {
    "iso:country":"US",
    "sg:address":"207 S 3rd St",
    "sg:city":"Van Buren",
    "sg:classifiers":[
        {
            "category":"Professional",
            "subcategory":"Business Services",
            "type":"Services"
        },
        {
            "category":"Wholesale",
            "subcategory":"Durable Goods & Equipment",
            "type":"Manufacturing & Wholesale Goods"
        }
    ],
    "sg:phone":"+1 479 474 9291",
    "sg:postcode":"72956",
    "sg:province":"AR",
    "sg:tags":[
        "fire",
        "extinguisher"
    ],
    "wof:name":"Universal Fire Equipment Inc",
    "wof:placetype":"venue"
},
  "geometry": {"coordinates":[-94.354083,35.432163],"type":"Point"}
}