{
  "type": "Feature",
  "properties": {
    "addr:full":"500 N Olive St N Little Rock AR 72114",
    "addr:housenumber":"500",
    "addr:postcode":"72114",
    "addr:street":"N Olive St N",
    "iso:country":"US",
    "sg:address":"500 N Olive St",
    "sg:city":"N Little Rock",
    "sg:classifiers":[
        {
            "category":"Wholesale",
            "subcategory":"Hardware",
            "type":"Manufacturing & Wholesale Goods"
        }
    ],
    "sg:phone":"+1 501 372 7127",
    "sg:postcode":"72114",
    "sg:province":"AR",
    "sg:tags":[
        "fastener"
    ],
    "sg:website":"www.starboltco.com",
    "wof:name":"Star Bolt & Screw Co Inc",
    "wof:placetype":"venue"
},
  "geometry": {"coordinates":[-92.26406799999999,34.758973],"type":"Point"}
}