{
  "type": "Feature",
  "properties": {
    "iso:country":"US",
    "sg:address":"755 W 2nd St",
    "sg:city":"Waldron",
    "sg:classifiers":[
        {
            "category":"Shopping",
            "subcategory":"Department Store",
            "type":"Retail Goods"
        }
    ],
    "sg:phone":"+1 479 637 4454",
    "sg:postcode":"72958",
    "sg:province":"AR",
    "wof:name":"El Solecito",
    "wof:placetype":"venue"
},
  "geometry": {"coordinates":[-94.099407,34.900207],"type":"Point"}
}