{
  "type": "Feature",
  "properties": {
    "iso:country":"US",
    "sg:address":"6 E 7th St",
    "sg:city":"Mountain Home",
    "sg:classifiers":[
        {
            "category":"Professional",
            "type":"Services"
        }
    ],
    "sg:phone":"+1 870 424 0107",
    "sg:postcode":"72653",
    "sg:province":"AR",
    "sg:tags":[
        "establishment"
    ],
    "wof:name":"Mack Reynolds AP",
    "wof:placetype":"venue"
},
  "geometry": {"coordinates":[-92.385287,36.334644],"type":"Point"}
}