{
  "type": "Feature",
  "properties": {
    "iso:country":"US",
    "sg:address":"21101 McPherson Rd",
    "sg:city":"Mabelvale",
    "sg:classifiers":[
        {
            "category":"Shopping",
            "subcategory":"Hobbies, Toys, & Games",
            "type":"Retail Goods"
        }
    ],
    "sg:phone":"+1 501 602 0128",
    "sg:postcode":"72103",
    "sg:province":"AR",
    "wof:name":"Patsy Hobby",
    "wof:placetype":"venue"
},
  "geometry": {"coordinates":[-92.39035800000001,34.561206],"type":"Point"}
}