{
  "type": "Feature",
  "properties": {
    "iso:country":"US",
    "sg:address":"2408 Belair Dr",
    "sg:city":"Magnolia",
    "sg:classifiers":[
        {
            "category":"Banks & Credit Unions",
            "subcategory":"Bank",
            "type":"Services"
        }
    ],
    "sg:phone":"+1 870 234 4960",
    "sg:postcode":"71753",
    "sg:province":"AR",
    "sg:tags":[
        "mortgage"
    ],
    "wof:name":"Denise Waterfield",
    "wof:placetype":"venue"
},
  "geometry": {"coordinates":[-93.22159,33.291444],"type":"Point"}
}