{
  "type": "Feature",
  "properties": {
    "iso:country":"US",
    "sg:address":"10551 E McNeely Rd",
    "sg:city":"Pea Ridge",
    "sg:classifiers":[
        {
            "category":"Farming",
            "subcategory":"Dairy Farm",
            "type":"Manufacturing & Wholesale Goods"
        }
    ],
    "sg:phone":"+1 479 451 8784",
    "sg:postcode":"72751",
    "sg:province":"AR",
    "wof:name":"Farmers Insurance",
    "wof:placetype":"venue"
},
  "geometry": {"coordinates":[-94.146619,36.457193],"type":"Point"}
}