{
  "type": "Feature",
  "properties": {
    "addr:full":"1014 N Main St Jay OK 74346",
    "addr:housenumber":"1014",
    "addr:postcode":"74346",
    "addr:street":"N Main St",
    "iso:country":"US",
    "sg:address":"1014 N Main St",
    "sg:city":"Jay",
    "sg:classifiers":[
        {
            "category":"Real Estate",
            "subcategory":"Real Estate Agent",
            "type":"Services"
        }
    ],
    "sg:phone":"+1 918 253 4133",
    "sg:postcode":"74346",
    "sg:province":"OK",
    "sg:website":"www.hendrenauctions.com",
    "wof:name":"Hendren Real Estate",
    "wof:placetype":"venue"
},
  "geometry": {"coordinates":[-94.782228,36.431717],"type":"Point"}
}