{
  "type": "Feature",
  "properties": {
    "iso:country":"US",
    "sg:address":"8606 Peters Rd",
    "sg:city":"Cabot",
    "sg:classifiers":[
        {
            "category":"Building & Trades",
            "subcategory":"Electrical",
            "type":"Services"
        },
        {
            "category":"Wholesale",
            "subcategory":"Electrical",
            "type":"Manufacturing & Wholesale Goods"
        }
    ],
    "sg:phone":"+1 501 985 0015",
    "sg:postcode":"72023",
    "sg:province":"AR",
    "sg:tags":[
        "lighting",
        "signal",
        "contractor",
        "traffic",
        "sign"
    ],
    "wof:name":"LEG Enterprises Inc",
    "wof:placetype":"venue"
},
  "geometry": {"coordinates":[-92.11203500000001,34.954785],"type":"Point"}
}