{
  "type": "Feature",
  "properties": {
    "addr:full":"906 NW 13th St Bentonville AR 72712",
    "addr:housenumber":"906",
    "addr:postcode":"72712",
    "addr:street":"Nw 13Th St",
    "iso:country":"US",
    "sg:address":"906 NW 13th St",
    "sg:city":"Bentonville",
    "sg:classifiers":[
        {
            "category":"Personal",
            "type":"Services"
        },
        {
            "category":"Sports & Exercise",
            "subcategory":"Gym",
            "type":"Entertainment"
        }
    ],
    "sg:phone":"+1 479 464 9993",
    "sg:postcode":"72712",
    "sg:province":"AR",
    "sg:tags":[
        "planning",
        "party",
        "instruction",
        "gymnastics",
        "event"
    ],
    "sg:website":"http://www.aspiregymnasticsacademy.com",
    "wof:name":"Aspire Gymnastics Academy L.L.C",
    "wof:placetype":"venue"
},
  "geometry": {"coordinates":[-94.221228,36.387843],"type":"Point"}
}