{
  "type": "Feature",
  "properties": {
    "iso:country":"US",
    "sg:address":"1925 N Calion Rd",
    "sg:city":"El Dorado",
    "sg:classifiers":[
        {
            "category":"Shopping",
            "subcategory":"Gifts & Souvenirs",
            "type":"Retail Goods"
        }
    ],
    "sg:phone":"+1 870 862 6217",
    "sg:postcode":"71730",
    "sg:province":"AR",
    "wof:name":"Armoire",
    "wof:placetype":"venue"
},
  "geometry": {"coordinates":[-92.653695,33.252512],"type":"Point"}
}