{
  "type": "Feature",
  "properties": {
    "iso:country":"US",
    "sg:address":"410 1st St NW",
    "sg:city":"Bearden",
    "sg:classifiers":[
        {
            "category":"Autos & Motor Vehicles",
            "subcategory":"Automobile Sales",
            "type":"Retail Goods"
        }
    ],
    "sg:phone":"+1 870 687 2103",
    "sg:postcode":"71720",
    "sg:province":"AR",
    "sg:tags":[
        "car",
        "dealer"
    ],
    "wof:name":"Cleo's Used Cars",
    "wof:placetype":"venue"
},
  "geometry": {"coordinates":[-92.62347699999999,33.721149],"type":"Point"}
}