{
  "type": "Feature",
  "properties": {
    "iso:country":"US",
    "sg:address":"120 S 2nd St",
    "sg:city":"Rogers",
    "sg:classifiers":[
        {
            "category":"Insurance",
            "subcategory":"Insurance Agent",
            "type":"Services"
        },
        {
            "category":"Insurance",
            "subcategory":"Hazard Insurance",
            "type":"Services"
        }
    ],
    "sg:phone":"+1 479 636 0198",
    "sg:postcode":"72756",
    "sg:province":"AR",
    "sg:tags":[
        "insured",
        "property",
        "adjuster",
        "replacement"
    ],
    "wof:name":"S B Howard & Co Inc",
    "wof:placetype":"venue"
},
  "geometry": {"coordinates":[-94.117423,36.332917],"type":"Point"}
}