{
  "type": "Feature",
  "properties": {
    "iso:country":"US",
    "sg:address":"869 Mountain Springs Rd",
    "sg:city":"Cabot",
    "sg:classifiers":[
        {
            "category":"Professional",
            "type":"Services"
        }
    ],
    "sg:phone":"+1 501 941 7509",
    "sg:postcode":"72023",
    "sg:province":"AR",
    "sg:tags":[
        "establishment"
    ],
    "wof:name":"K Mann",
    "wof:placetype":"venue"
},
  "geometry": {"coordinates":[-92.028256,34.98886],"type":"Point"}
}