{
  "type": "Feature",
  "properties": {
    "iso:country":"US",
    "sg:address":"5005 Madison 2035",
    "sg:city":"Huntsville",
    "sg:classifiers":[
        {
            "category":"Banks & Credit Unions",
            "subcategory":"Investment Brokerage",
            "type":"Services"
        }
    ],
    "sg:phone":"+1 479 738 1298",
    "sg:postcode":"72740",
    "sg:province":"AR",
    "wof:name":"Edward Jones Co",
    "wof:placetype":"venue"
},
  "geometry": {"coordinates":[-93.719442,36.081877],"type":"Point"}
}