{
  "type": "Feature",
  "properties": {
    "iso:country":"US",
    "sg:address":"1314 S 4th St",
    "sg:city":"Nashville",
    "sg:classifiers":[
        {
            "category":"Retail",
            "subcategory":"Storage",
            "type":"Services"
        }
    ],
    "sg:phone":"+1 870 845 3560",
    "sg:postcode":"71852",
    "sg:province":"AR",
    "sg:tags":[
        "household",
        "commercial"
    ],
    "wof:name":"Carlton Mini-Storage",
    "wof:placetype":"venue"
},
  "geometry": {"coordinates":[-93.850905,33.933317],"type":"Point"}
}