{
  "type": "Feature",
  "properties": {
    "iso:country":"US",
    "sg:address":"1104 J St",
    "sg:city":"Barling",
    "sg:classifiers":[
        {
            "category":"Professional",
            "type":"Services"
        }
    ],
    "sg:phone":"+1 479 478 9260",
    "sg:postcode":"72923",
    "sg:province":"AR",
    "wof:name":"Armstrong Allen & Green",
    "wof:placetype":"venue"
},
  "geometry": {"coordinates":[-94.308908,35.335016],"type":"Point"}
}