{
  "type": "Feature",
  "properties": {
    "addr:full":"108 Campbell Dr Beebe AR 72012",
    "addr:housenumber":"108",
    "addr:postcode":"72012",
    "addr:street":"Campbell Dr",
    "iso:country":"US",
    "sg:address":"108 Campbell Dr",
    "sg:city":"Beebe",
    "sg:classifiers":[
        {
            "category":"Building & Trades",
            "subcategory":"Construction",
            "type":"Services"
        }
    ],
    "sg:phone":"+1 501 882 3787",
    "sg:postcode":"72012",
    "sg:province":"AR",
    "sg:tags":[
        "contractor"
    ],
    "wof:name":"Cossey Construction",
    "wof:placetype":"venue"
},
  "geometry": {"coordinates":[-91.910459,35.075956],"type":"Point"}
}