{
  "type": "Feature",
  "properties": {
    "iso:country":"US",
    "sg:address":"4503 E Broadway St",
    "sg:city":"North Little Rock",
    "sg:classifiers":[
        {
            "category":"Autos & Motor Vehicles",
            "subcategory":"Auto Supplies",
            "type":"Retail Goods"
        }
    ],
    "sg:phone":"+1 501 945 1960",
    "sg:postcode":"72117",
    "sg:province":"AR",
    "wof:name":"OReilly Auto Parts",
    "wof:placetype":"venue"
},
  "geometry": {"coordinates":[-92.215521,34.757585],"type":"Point"}
}