{
  "type": "Feature",
  "properties": {
    "addr:full":"61 E Main St Ashdown AR 71822",
    "addr:housenumber":"61",
    "addr:postcode":"71822",
    "addr:street":"E Main St",
    "iso:country":"US",
    "sg:address":"61 E Main St",
    "sg:city":"Ashdown",
    "sg:classifiers":[
        {
            "category":"Social Services",
            "type":"Services"
        }
    ],
    "sg:phone":"+1 870 898 6070",
    "sg:postcode":"71822",
    "sg:province":"AR",
    "sg:tags":[
        "organization",
        "welfare"
    ],
    "wof:name":"Domestic Violence Prevention",
    "wof:placetype":"venue"
},
  "geometry": {"coordinates":[-94.131139,33.674442],"type":"Point"}
}