{
  "type": "Feature",
  "properties": {
    "addr:full":"1803 Broadway St Little Rock AR 72206",
    "addr:housenumber":"1803",
    "addr:postcode":"72206",
    "addr:street":"Broadway St",
    "iso:country":"US",
    "sg:address":"1803 Broadway St",
    "sg:city":"Little Rock",
    "sg:classifiers":[
        {
            "category":"Real Estate",
            "subcategory":"Real Estate Agent",
            "type":"Services"
        }
    ],
    "sg:phone":"+1 501 399 9700",
    "sg:postcode":"72206",
    "sg:province":"AR",
    "wof:name":"Tony Curtis Realtors",
    "wof:placetype":"venue"
},
  "geometry": {"coordinates":[-92.278457,34.730636],"type":"Point"}
}