{
  "type": "Feature",
  "properties": {
    "iso:country":"US",
    "sg:address":"304 E Main St",
    "sg:city":"Hardy",
    "sg:classifiers":[
        {
            "category":"Personal",
            "subcategory":"Beauty Salon",
            "type":"Services"
        }
    ],
    "sg:phone":"+1 870 856 4247",
    "sg:postcode":"72542",
    "sg:province":"AR",
    "wof:name":"Hardy House Salon",
    "wof:placetype":"venue"
},
  "geometry": {"coordinates":[-91.48005000000001,36.315621],"type":"Point"}
}