{
  "type": "Feature",
  "properties": {
    "iso:country":"US",
    "sg:address":"1808 S Park Ave",
    "sg:city":"Stuttgart",
    "sg:classifiers":[
        {
            "category":"Organizations",
            "subcategory":"Religious Organization",
            "type":"Services"
        }
    ],
    "sg:phone":"+1 870 673 4423",
    "sg:postcode":"72160",
    "sg:province":"AR",
    "wof:name":"Outreach Ministry",
    "wof:placetype":"venue"
},
  "geometry": {"coordinates":[-91.54073,34.485608],"type":"Point"}
}