{
  "type": "Feature",
  "properties": {
    "iso:country":"US",
    "sg:address":"860 Hwy 62 E",
    "sg:city":"Mountain Home",
    "sg:classifiers":[
        {
            "category":"Personal",
            "subcategory":"Beauty Salon",
            "type":"Services"
        }
    ],
    "sg:phone":"+1 870 424 7077",
    "sg:postcode":"72653",
    "sg:province":"AR",
    "wof:name":"Wavelengths",
    "wof:placetype":"venue"
},
  "geometry": {"coordinates":[-92.376206,36.346213],"type":"Point"}
}