{
  "type": "Feature",
  "properties": {
    "addr:full":"15550 Lawson Rd Little Rock AR 72210",
    "addr:housenumber":"15550",
    "addr:postcode":"72210",
    "addr:street":"Lawson Rd",
    "iso:country":"US",
    "sg:address":"15550 Lawson Rd",
    "sg:city":"Little Rock",
    "sg:classifiers":[
        {
            "category":"Manufacturing",
            "subcategory":"Glass & Minerals",
            "type":"Manufacturing & Wholesale Goods"
        }
    ],
    "sg:phone":"+1 501 225 0101",
    "sg:postcode":"72210",
    "sg:province":"AR",
    "sg:tags":[
        "ready",
        "concrete",
        "mfg"
    ],
    "wof:name":"Martin Marietta Aggregates",
    "wof:placetype":"venue"
},
  "geometry": {"coordinates":[-92.451849,34.707498],"type":"Point"}
}