{
  "type": "Feature",
  "properties": {
    "iso:country":"US",
    "sg:address":"21157 N Springlake Rd",
    "sg:city":"Hensley",
    "sg:classifiers":[
        {
            "category":"Personal",
            "type":"Services"
        },
        {
            "category":"Professional",
            "subcategory":"Art Services",
            "type":"Services"
        }
    ],
    "sg:phone":"+1 501 920 2022",
    "sg:postcode":"72065",
    "sg:province":"AR",
    "sg:tags":[
        "photography",
        "videography",
        "wedding"
    ],
    "wof:name":"Perfect Angle Photography",
    "wof:placetype":"venue"
},
  "geometry": {"coordinates":[-92.319284,34.557354],"type":"Point"}
}