{
  "type": "Feature",
  "properties": {
    "iso:country":"US",
    "sg:address":"519 Latham Dr",
    "sg:city":"Lowell",
    "sg:classifiers":[
        {
            "category":"Health Services",
            "subcategory":"Doctor",
            "type":"Services"
        }
    ],
    "sg:phone":"+1 479 750 0125",
    "sg:postcode":"72745",
    "sg:province":"AR",
    "wof:name":"Schmieding Developmental Center",
    "wof:placetype":"venue"
},
  "geometry": {"coordinates":[-94.14700000000001,36.2494],"type":"Point"}
}