{
  "type": "Feature",
  "properties": {
    "iso:country":"US",
    "sg:address":"2601 W Dixon Rd",
    "sg:city":"Little Rock",
    "sg:classifiers":[
        {
            "category":"Wholesale",
            "subcategory":"Home Furnishings",
            "type":"Manufacturing & Wholesale Goods"
        }
    ],
    "sg:phone":"+1 501 888 5368",
    "sg:postcode":"72206",
    "sg:province":"AR",
    "wof:name":"Leroy Smith",
    "wof:placetype":"venue"
},
  "geometry": {"coordinates":[-92.288786,34.65886],"type":"Point"}
}