{
  "type": "Feature",
  "properties": {
    "iso:country":"US",
    "sg:address":"940 W Scenic Dr",
    "sg:city":"N Little Rock",
    "sg:classifiers":[
        {
            "category":"Real Estate",
            "subcategory":"Real Estate Operator",
            "type":"Services"
        }
    ],
    "sg:phone":"+1 501 812 6612",
    "sg:postcode":"72118",
    "sg:province":"AR",
    "sg:tags":[
        "apartment"
    ],
    "wof:name":"Ridge At North Little Rock",
    "wof:placetype":"venue"
},
  "geometry": {"coordinates":[-92.293606,34.784957],"type":"Point"}
}