{
  "type": "Feature",
  "properties": {
    "addr:full":"101 N 10th St Fort Smith AR 72901",
    "addr:housenumber":"101",
    "addr:postcode":"72901",
    "addr:street":"N 10Th St",
    "iso:country":"US",
    "sg:address":"101 N 10th St",
    "sg:city":"Fort Smith",
    "sg:classifiers":[
        {
            "category":"Professional",
            "subcategory":"Business Services",
            "type":"Services"
        }
    ],
    "sg:phone":"+1 479 782 6300",
    "sg:postcode":"72901",
    "sg:province":"AR",
    "wof:name":"J and J Bail Bond",
    "wof:placetype":"venue"
},
  "geometry": {"coordinates":[-94.420052,35.38639],"type":"Point"}
}