{
  "type": "Feature",
  "properties": {
    "addr:full":"1 Natural Resource Dr Little Rock AR 72205",
    "addr:housenumber":"1",
    "addr:postcode":"72205",
    "addr:street":"Natural Resource Dr",
    "iso:country":"US",
    "sg:address":"1 Natural Resource Dr",
    "sg:city":"Little Rock",
    "sg:classifiers":[
        {
            "category":"Government",
            "subcategory":"Office",
            "type":"Public Place"
        }
    ],
    "sg:phone":"+1 501 682 0790",
    "sg:postcode":"72205",
    "sg:province":"AR",
    "wof:name":"Egg Council",
    "wof:placetype":"venue"
},
  "geometry": {"coordinates":[-92.38945699999999,34.757757],"type":"Point"}
}