{
  "type": "Feature",
  "properties": {
    "addr:full":"3 Triangle Ln Batesville AR 72501",
    "addr:housenumber":"3",
    "addr:postcode":"72501",
    "addr:street":"Triangle Ln",
    "iso:country":"US",
    "sg:address":"3 Triangle Ln",
    "sg:city":"Batesville",
    "sg:classifiers":[
        {
            "category":"Restaurant",
            "type":"Food & Drink"
        }
    ],
    "sg:phone":"+1 870 793 7330",
    "sg:postcode":"72501",
    "sg:province":"AR",
    "sg:tags":[
        "eating"
    ],
    "wof:name":"Triangle Cafe",
    "wof:placetype":"venue"
},
  "geometry": {"coordinates":[-91.639369,35.739659],"type":"Point"}
}