{
  "type": "Feature",
  "properties": {
    "iso:country":"US",
    "sg:address":"203 Rice St",
    "sg:city":"Berryville",
    "sg:classifiers":[
        {
            "category":"Health Services",
            "subcategory":"Doctor",
            "type":"Services"
        }
    ],
    "sg:phone":"+1 870 423 3338",
    "sg:postcode":"72616",
    "sg:province":"AR",
    "sg:tags":[
        "medical"
    ],
    "wof:name":"S J C - Berryville Gen Surgery",
    "wof:placetype":"venue"
},
  "geometry": {"coordinates":[-93.553011,36.358833],"type":"Point"}
}