{
  "type": "Feature",
  "properties": {
    "addr:full":"2307 N Dixieland Rd Rogers AR 72756",
    "addr:housenumber":"2307",
    "addr:postcode":"72756",
    "addr:street":"N Dixieland Rd",
    "iso:country":"US",
    "sg:address":"2307 N Dixieland Rd",
    "sg:city":"Rogers",
    "sg:classifiers":[
        {
            "category":"Retail",
            "subcategory":"Self-service Laundry",
            "type":"Services"
        }
    ],
    "sg:phone":"+1 479 636 5566",
    "sg:postcode":"72756",
    "sg:province":"AR",
    "sg:tags":[
        "coin"
    ],
    "wof:name":"Clothes Line Coin Laundry",
    "wof:placetype":"venue"
},
  "geometry": {"coordinates":[-94.14307599999999,36.353365],"type":"Point"}
}