{
  "type": "Feature",
  "properties": {
    "iso:country":"US",
    "sg:address":"205 Texas Ave",
    "sg:city":"N Little Rock",
    "sg:classifiers":[
        {
            "category":"Shopping",
            "type":"Retail Goods"
        }
    ],
    "sg:phone":"+1 501 771 4723",
    "sg:postcode":"72118",
    "sg:province":"AR",
    "sg:tags":[
        "cosmetic",
        "perfume"
    ],
    "wof:name":"Mary Kay Cosmetics Nesbit Gina",
    "wof:placetype":"venue"
},
  "geometry": {"coordinates":[-92.284278,34.81232],"type":"Point"}
}