{
  "type": "Feature",
  "properties": {
    "addr:full":"5012 Hwy 294 Jacksonville AR 72076",
    "addr:housenumber":"5012",
    "addr:postcode":"72076",
    "addr:street":"Hwy 294",
    "iso:country":"US",
    "sg:address":"5012 Hwy 294",
    "sg:city":"Jacksonville",
    "sg:classifiers":[
        {
            "category":"Manufacturing",
            "subcategory":"Tools & Machinery",
            "type":"Manufacturing & Wholesale Goods"
        }
    ],
    "sg:phone":"+1 501 982 4145",
    "sg:postcode":"72076",
    "sg:province":"AR",
    "sg:tags":[
        "machine",
        "shop"
    ],
    "wof:name":"Slantco Machine & Tool",
    "wof:placetype":"venue"
},
  "geometry": {"coordinates":[-92.060041,34.849067],"type":"Point"}
}