{
  "type": "Feature",
  "properties": {
    "iso:country":"US",
    "sg:address":"1604 W 42nd Ave",
    "sg:city":"Pine Bluff",
    "sg:classifiers":[
        {
            "category":"Health Services",
            "subcategory":"Medical Lab",
            "type":"Services"
        }
    ],
    "sg:phone":"+1 870 850 7868",
    "sg:postcode":"71603",
    "sg:province":"AR",
    "sg:tags":[
        "laboratory"
    ],
    "wof:name":"Dynacare",
    "wof:placetype":"venue"
},
  "geometry": {"coordinates":[-92.017901,34.186429],"type":"Point"}
}