{
  "type": "Feature",
  "properties": {
    "iso:country":"US",
    "sg:address":"5296 Co Rd 2",
    "sg:city":"Fulton",
    "sg:classifiers":[
        {
            "category":"Organizations",
            "subcategory":"Religious Organization",
            "type":"Services"
        }
    ],
    "sg:phone":"+1 870 777 8835",
    "sg:postcode":"71838",
    "sg:province":"AR",
    "wof:name":"St Luke No 2 Missionary Baptst",
    "wof:placetype":"venue"
},
  "geometry": {"coordinates":[-93.73186,33.63197],"type":"Point"}
}