{
  "type": "Feature",
  "properties": {
    "iso:country":"US",
    "sg:address":"1614 N Rock St",
    "sg:city":"Sheridan",
    "sg:classifiers":[
        {
            "category":"Autos & Motor Vehicles",
            "subcategory":"Automobile Sales",
            "type":"Retail Goods"
        }
    ],
    "sg:phone":"+1 870 942 5713",
    "sg:postcode":"72150",
    "sg:province":"AR",
    "sg:tags":[
        "car",
        "dealer"
    ],
    "wof:name":"Sizemore Metal Products",
    "wof:placetype":"venue"
},
  "geometry": {"coordinates":[-92.39556899999999,34.320954],"type":"Point"}
}