{
  "type": "Feature",
  "properties": {
    "addr:full":"3601 Jefferson Ave #3 Texarkana AR 71854",
    "addr:housenumber":"3601",
    "addr:postcode":"71854",
    "addr:street":"Jefferson Ave # 3",
    "iso:country":"US",
    "sg:address":"3601 Jefferson Ave #3",
    "sg:city":"Texarkana",
    "sg:classifiers":[
        {
            "category":"Building & Trades",
            "subcategory":"Construction",
            "type":"Services"
        }
    ],
    "sg:phone":"+1 870 772 5137",
    "sg:postcode":"71854",
    "sg:province":"AR",
    "sg:tags":[
        "system",
        "contractor",
        "air conditioning"
    ],
    "sg:website":"http://www.ruudac.com",
    "wof:name":"Cook's Heat & Air Conditioning",
    "wof:placetype":"venue"
},
  "geometry": {"coordinates":[-94.02926600000001,33.457359],"type":"Point"}
}