{
  "type": "Feature",
  "properties": {
    "iso:country":"US",
    "sg:address":"2847 State Hwy 25 B N",
    "sg:city":"Heber Springs",
    "sg:classifiers":[
        {
            "category":"Real Estate",
            "subcategory":"Architect",
            "type":"Services"
        }
    ],
    "sg:phone":"+1 501 362 0700",
    "sg:postcode":"72543",
    "sg:province":"AR",
    "wof:name":"Jimmy Hudspeth Architect",
    "wof:placetype":"venue"
},
  "geometry": {"coordinates":[-92.025066,35.516622],"type":"Point"}
}