{
  "type": "Feature",
  "properties": {
    "iso:country":"US",
    "sg:address":"310 Akers Rd",
    "sg:city":"Hot Springs",
    "sg:classifiers":[
        {
            "category":"Building & Trades",
            "subcategory":"Landscaping Services",
            "type":"Services"
        }
    ],
    "sg:phone":"+1 501 844 9259",
    "sg:postcode":"71901",
    "sg:province":"AR",
    "sg:tags":[
        "landscape",
        "contractor"
    ],
    "wof:name":"Coster Landscaping & Sprinkler",
    "wof:placetype":"venue"
},
  "geometry": {"coordinates":[-92.949156,34.457794],"type":"Point"}
}