{
  "type": "Feature",
  "properties": {
    "addr:full":"909 Killough Rd N Wynne AR 72396",
    "addr:housenumber":"909",
    "addr:postcode":"72396",
    "addr:street":"Killough Rd N",
    "iso:country":"US",
    "sg:address":"909 Killough Rd N",
    "sg:city":"Wynne",
    "sg:classifiers":[
        {
            "category":"Autos & Motor Vehicles",
            "subcategory":"Automobile Sales",
            "type":"Retail Goods"
        }
    ],
    "sg:phone":"+1 870 238 3478",
    "sg:postcode":"72396",
    "sg:province":"AR",
    "sg:tags":[
        "new",
        "car"
    ],
    "wof:name":"Mason Chrysler",
    "wof:placetype":"venue"
},
  "geometry": {"coordinates":[-90.775291,35.229207],"type":"Point"}
}