{
  "type": "Feature",
  "properties": {
    "iso:country":"US",
    "sg:address":"212 N Pruett St",
    "sg:city":"Paragould",
    "sg:classifiers":[
        {
            "category":"Sports & Exercise",
            "subcategory":"Gym",
            "type":"Entertainment"
        }
    ],
    "sg:phone":"+1 870 236 7878",
    "sg:postcode":"72450",
    "sg:province":"AR",
    "sg:tags":[
        "club",
        "health",
        "studio",
        "gymnasium"
    ],
    "sg:website":"www.jazzercise.com",
    "wof:name":"Jazzercise",
    "wof:placetype":"venue"
},
  "geometry": {"coordinates":[-90.486222,36.057369],"type":"Point"}
}