{
  "type": "Feature",
  "properties": {
    "addr:full":"2600 Rogers Ave Fort Smith AR 72901",
    "addr:housenumber":"2600",
    "addr:postcode":"72901",
    "addr:street":"Rogers Ave",
    "iso:country":"US",
    "sg:address":"2600 Rogers Ave",
    "sg:city":"Fort Smith",
    "sg:classifiers":[
        {
            "category":"Professional",
            "subcategory":"Advertising",
            "type":"Services"
        }
    ],
    "sg:phone":"+1 479 783 0159",
    "sg:postcode":"72901",
    "sg:province":"AR",
    "sg:tags":[
        "counselor"
    ],
    "sg:website":"www.brannonandassociates.com",
    "wof:name":"Brannon & Assoc Inc",
    "wof:placetype":"venue"
},
  "geometry": {"coordinates":[-94.404006,35.376024],"type":"Point"}
}