{
  "type": "Feature",
  "properties": {
    "iso:country":"US",
    "sg:address":"721 Park Ave",
    "sg:city":"Hot Springs",
    "sg:classifiers":[
        {
            "category":"Organizations",
            "subcategory":"Religious Organization",
            "type":"Services"
        }
    ],
    "sg:phone":"+1 501 623 2545",
    "sg:postcode":"71901",
    "sg:province":"AR",
    "sg:tags":[
        "church"
    ],
    "wof:name":"Park Place Baptist Church",
    "wof:placetype":"venue"
},
  "geometry": {"coordinates":[-93.052801,34.525743],"type":"Point"}
}