{
  "type": "Feature",
  "properties": {
    "iso:country":"US",
    "sg:address":"2516 Alma Hwy",
    "sg:city":"Van Buren",
    "sg:classifiers":[
        {
            "category":"Organizations",
            "subcategory":"Religious Organization",
            "type":"Services"
        }
    ],
    "sg:phone":"+1 479 474 1186",
    "sg:postcode":"72956",
    "sg:province":"AR",
    "sg:tags":[
        "church"
    ],
    "wof:name":"Church-The Nazarene Van Buren",
    "wof:placetype":"venue"
},
  "geometry": {"coordinates":[-94.33262499999999,35.439064],"type":"Point"}
}