{
  "type": "Feature",
  "properties": {
    "iso:country":"US",
    "sg:address":"220 E Emma Ave",
    "sg:city":"Springdale",
    "sg:classifiers":[
        {
            "category":"Shopping",
            "subcategory":"Clothing, Apparel, & Fashions",
            "type":"Retail Goods"
        }
    ],
    "sg:phone":"+1 479 756 0555",
    "sg:postcode":"72764",
    "sg:province":"AR",
    "sg:tags":[
        "shop",
        "bridal"
    ],
    "wof:name":"Mi Lady N Lace",
    "wof:placetype":"venue"
},
  "geometry": {"coordinates":[-94.129521,36.18513],"type":"Point"}
}