{
  "type": "Feature",
  "properties": {
    "addr:full":"5412 Shearwood Dr Rogers AR 72758",
    "addr:housenumber":"5412",
    "addr:postcode":"72758",
    "addr:street":"Shearwood Dr",
    "iso:country":"US",
    "sg:address":"5412 Shearwood Dr",
    "sg:city":"Rogers",
    "sg:classifiers":[
        {
            "category":"Retail",
            "subcategory":"Laundry & Dry Cleaning",
            "type":"Services"
        },
        {
            "category":"Building & Trades",
            "subcategory":"Cleaning & Sanitation",
            "type":"Services"
        }
    ],
    "sg:phone":"+1 479 616 0190",
    "sg:postcode":"72758",
    "sg:province":"AR",
    "sg:tags":[
        "cleaner",
        "house"
    ],
    "wof:name":"Pro Clean",
    "wof:placetype":"venue"
},
  "geometry": {"coordinates":[-94.20722000000001,36.286937],"type":"Point"}
}