{
  "type": "Feature",
  "properties": {
    "iso:country":"US",
    "sg:address":"2714 Highway 9 S",
    "sg:city":"Salem",
    "sg:classifiers":[
        {
            "category":"Manufacturing",
            "subcategory":"Tools & Machinery",
            "type":"Manufacturing & Wholesale Goods"
        },
        {
            "category":"Home & Garden",
            "subcategory":"Home Furnishings",
            "type":"Retail Goods"
        },
        {
            "category":"Wholesale",
            "subcategory":"Photographic Equipment",
            "type":"Manufacturing & Wholesale Goods"
        }
    ],
    "sg:phone":"+1 870 895 3697",
    "sg:postcode":"72576",
    "sg:province":"AR",
    "sg:tags":[
        "building",
        "bulldozer",
        "construction",
        "excavating"
    ],
    "wof:name":"Bishop Dozing",
    "wof:placetype":"venue"
},
  "geometry": {"coordinates":[-91.85382199999999,36.329073],"type":"Point"}
}