{
  "type": "Feature",
  "properties": {
    "addr:full":"17325 Hwy 66 Mountain View AR 72560",
    "addr:housenumber":"17325",
    "addr:postcode":"72560",
    "addr:street":"Hwy 66 Mountain View",
    "iso:country":"US",
    "sg:address":"17325 Hwy 66",
    "sg:city":"Mountain View",
    "sg:classifiers":[
        {
            "category":"Building & Trades",
            "subcategory":"Equipment Rental",
            "type":"Services"
        }
    ],
    "sg:phone":"+1 870 269 2656",
    "sg:postcode":"72560",
    "sg:province":"AR",
    "sg:tags":[
        "yard"
    ],
    "wof:name":"Mountain View Mini Storage",
    "wof:placetype":"venue"
},
  "geometry": {"coordinates":[-92.166236,35.86862],"type":"Point"}
}