{
  "type": "Feature",
  "properties": {
    "iso:country":"US",
    "sg:address":"121 Main St SE",
    "sg:city":"Gravette",
    "sg:classifiers":[
        {
            "category":"Restaurant",
            "type":"Food & Drink"
        }
    ],
    "sg:phone":"+1 479 787 5533",
    "sg:postcode":"72736",
    "sg:province":"AR",
    "wof:name":"Snorky's Pizzeria",
    "wof:placetype":"venue"
},
  "geometry": {"coordinates":[-94.453029,36.422222],"type":"Point"}
}