{
  "type": "Feature",
  "properties": {
    "iso:country":"US",
    "sg:address":"301 Cornbridge Rd",
    "sg:city":"Mineral Springs",
    "sg:classifiers":[
        {
            "category":"Organizations",
            "subcategory":"Community Association",
            "type":"Services"
        }
    ],
    "sg:phone":"+1 870 287 4881",
    "sg:postcode":"71851",
    "sg:province":"AR",
    "sg:tags":[
        "club"
    ],
    "wof:name":"Zero Hunting Club Inc",
    "wof:placetype":"venue"
},
  "geometry": {"coordinates":[-93.993574,33.897528],"type":"Point"}
}