{
  "type": "Feature",
  "properties": {
    "iso:country":"US",
    "sg:address":"8517 Geyer Springs Rd",
    "sg:city":"Little Rock",
    "sg:classifiers":[
        {
            "category":"Building & Trades",
            "subcategory":"Equipment Rental",
            "type":"Services"
        }
    ],
    "sg:phone":"+1 501 562 7368",
    "sg:postcode":"72209",
    "sg:province":"AR",
    "sg:tags":[
        "television"
    ],
    "wof:name":"Furniture & Appliances Now",
    "wof:placetype":"venue"
},
  "geometry": {"coordinates":[-92.344156,34.671295],"type":"Point"}
}