{
  "type": "Feature",
  "properties": {
    "iso:country":"US",
    "sg:address":"2418 W Valley Dr",
    "sg:city":"Fayetteville",
    "sg:classifiers":[
        {
            "category":"Building & Trades",
            "subcategory":"Landscaping Services",
            "type":"Services"
        }
    ],
    "sg:phone":"+1 479 443 4298",
    "sg:postcode":"72703",
    "sg:province":"AR",
    "wof:name":"Hackler Stump Removal",
    "wof:placetype":"venue"
},
  "geometry": {"coordinates":[-94.1965,36.079389],"type":"Point"}
}