{
  "type": "Feature",
  "properties": {
    "iso:country":"US",
    "sg:address":"930 Paradise Ln",
    "sg:city":"Huntsville",
    "sg:classifiers":[
        {
            "category":"Organizations",
            "subcategory":"Political Organization",
            "type":"Services"
        }
    ],
    "sg:phone":"+1 479 738 6505",
    "sg:postcode":"72740",
    "sg:province":"AR",
    "wof:name":"Hathorn For Lt Governor",
    "wof:placetype":"venue"
},
  "geometry": {"coordinates":[-93.72548,36.07865],"type":"Point"}
}