{
  "type": "Feature",
  "properties": {
    "iso:country":"US",
    "sg:address":"2104 Oakwood Ave",
    "sg:city":"Bentonville",
    "sg:classifiers":[
        {
            "category":"Food & Beverages",
            "subcategory":"Specialty",
            "type":"Retail Goods"
        }
    ],
    "sg:phone":"+1 479 273 5253",
    "sg:postcode":"72712",
    "sg:province":"AR",
    "sg:tags":[
        "health",
        "diet"
    ],
    "wof:name":"Shaklee Distributor",
    "wof:placetype":"venue"
},
  "geometry": {"coordinates":[-94.21611900000001,36.39535],"type":"Point"}
}