{
  "type": "Feature",
  "properties": {
    "iso:country":"US",
    "sg:address":"1641 Hwy 282",
    "sg:city":"Van Buren",
    "sg:classifiers":[
        {
            "category":"Organizations",
            "subcategory":"Religious Organization",
            "type":"Services"
        }
    ],
    "sg:phone":"+1 479 474 5485",
    "sg:postcode":"72956",
    "sg:province":"AR",
    "wof:name":"Jehovahs Witnesses",
    "wof:placetype":"venue"
},
  "geometry": {"coordinates":[-94.30312,35.46778],"type":"Point"}
}