{
  "type": "Feature",
  "properties": {
    "iso:country":"US",
    "sg:address":"10550 N Highway 265 S",
    "sg:city":"Fayetteville",
    "sg:classifiers":[
        {
            "category":"Home & Garden",
            "subcategory":"Building Materials",
            "type":"Retail Goods"
        },
        {
            "category":"Building & Trades",
            "subcategory":"Construction",
            "type":"Services"
        }
    ],
    "sg:phone":"+1 479 444 0232",
    "sg:postcode":"72701",
    "sg:province":"AR",
    "sg:tags":[
        "concrete",
        "staining",
        "contractor"
    ],
    "wof:name":"Johnson Concrete",
    "wof:placetype":"venue"
},
  "geometry": {"coordinates":[-94.204497,35.994482],"type":"Point"}
}