{
  "type": "Feature",
  "properties": {
    "iso:country":"US",
    "sg:address":"41 Arcadia Cir",
    "sg:city":"Bryant",
    "sg:classifiers":[
        {
            "category":"Farming",
            "subcategory":"Farm",
            "type":"Manufacturing & Wholesale Goods"
        }
    ],
    "sg:phone":"+1 501 847 4863",
    "sg:postcode":"72022",
    "sg:province":"AR",
    "wof:name":"Scoggins Farms",
    "wof:placetype":"venue"
},
  "geometry": {"coordinates":[-92.485421,34.599752],"type":"Point"}
}