{
  "type": "Feature",
  "properties": {
    "iso:country":"US",
    "sg:address":"405 N Arkansas Ave",
    "sg:city":"Russellville",
    "sg:classifiers":[
        {
            "category":"Shopping",
            "subcategory":"Discount & Variety Stores",
            "type":"Retail Goods"
        }
    ],
    "sg:phone":"+1 479 968 1787",
    "sg:postcode":"72801",
    "sg:province":"AR",
    "wof:name":"ALCO Discount Store",
    "wof:placetype":"venue"
},
  "geometry": {"coordinates":[-93.133656,35.28226],"type":"Point"}
}