{
  "type": "Feature",
  "properties": {
    "iso:country":"US",
    "sg:address":"913 W Main St",
    "sg:city":"Cabot",
    "sg:classifiers":[
        {
            "category":"Insurance",
            "subcategory":"Insurance Agent",
            "type":"Services"
        }
    ],
    "sg:phone":"+1 501 843 0304",
    "sg:postcode":"72023",
    "sg:province":"AR",
    "wof:name":"Shelter Insurance",
    "wof:placetype":"venue"
},
  "geometry": {"coordinates":[-92.02940099999999,34.978338],"type":"Point"}
}