{
  "type": "Feature",
  "properties": {
    "iso:country":"US",
    "sg:address":"3001 W Wedington Dr",
    "sg:city":"Fayetteville",
    "sg:classifiers":[
        {
            "category":"Real Estate",
            "subcategory":"Real Estate Operator",
            "type":"Services"
        }
    ],
    "sg:phone":"+1 479 521 7206",
    "sg:postcode":"72701",
    "sg:province":"AR",
    "sg:tags":[
        "apartment"
    ],
    "sg:website":"http://www.dewarnet.net",
    "wof:name":"Maple Manor Apts",
    "wof:placetype":"venue"
},
  "geometry": {"coordinates":[-94.202179,36.07832],"type":"Point"}
}