{
  "type": "Feature",
  "properties": {
    "iso:country":"US",
    "sg:address":"39 Windsor Ct",
    "sg:city":"Little Rock",
    "sg:classifiers":[
        {
            "category":"Wholesale",
            "subcategory":"Metals & Minerals",
            "type":"Manufacturing & Wholesale Goods"
        }
    ],
    "sg:phone":"+1 501 455 5652",
    "sg:postcode":"72212",
    "sg:province":"AR",
    "sg:tags":[
        "center"
    ],
    "wof:name":"Production Supply Company",
    "wof:placetype":"venue"
},
  "geometry": {"coordinates":[-92.423628,34.773578],"type":"Point"}
}