{
  "type": "Feature",
  "properties": {
    "iso:country":"US",
    "sg:address":"14 Leeward Ct",
    "sg:city":"Maumelle",
    "sg:classifiers":[
        {
            "category":"Communications",
            "subcategory":"Television Station",
            "type":"Services"
        }
    ],
    "sg:phone":"+1 501 590 9622",
    "sg:postcode":"72113",
    "sg:province":"AR",
    "sg:tags":[
        "network"
    ],
    "wof:name":"Russell Communications",
    "wof:placetype":"venue"
},
  "geometry": {"coordinates":[-92.409752,34.839218],"type":"Point"}
}