{
  "type": "Feature",
  "properties": {
    "iso:country":"US",
    "sg:address":"25 Oakwood Rd",
    "sg:city":"Little Rock",
    "sg:classifiers":[
        {
            "category":"Manufacturing",
            "subcategory":"Printing",
            "type":"Manufacturing & Wholesale Goods"
        }
    ],
    "sg:phone":"+1 501 280 0583",
    "sg:postcode":"72202",
    "sg:province":"AR",
    "sg:tags":[
        "printer"
    ],
    "wof:name":"Davco Graphics",
    "wof:placetype":"venue"
},
  "geometry": {"coordinates":[-92.311029,34.761085],"type":"Point"}
}