{
  "type": "Feature",
  "properties": {
    "iso:country":"US",
    "sg:address":"1325 N Saint Louis St",
    "sg:city":"Batesville",
    "sg:classifiers":[
        {
            "category":"Travel",
            "subcategory":"Hotels & Motels",
            "type":"Entertainment"
        }
    ],
    "sg:phone":"+1 870 698 1800",
    "sg:postcode":"72501",
    "sg:province":"AR",
    "wof:name":"Ramada Inn",
    "wof:placetype":"venue"
},
  "geometry": {"coordinates":[-91.63599000000001,35.792757],"type":"Point"}
}