{
  "type": "Feature",
  "properties": {
    "iso:country":"US",
    "sg:address":"608 Cedar Dr",
    "sg:city":"West Helena",
    "sg:classifiers":[
        {
            "category":"Professional",
            "subcategory":"Computer Services",
            "type":"Services"
        }
    ],
    "sg:phone":"+1 870 572 2427",
    "sg:postcode":"72390",
    "sg:province":"AR",
    "sg:tags":[
        "design",
        "system",
        "programing",
        "custom"
    ],
    "wof:name":"Porter Enterprises",
    "wof:placetype":"venue"
},
  "geometry": {"coordinates":[-90.639432,34.551097],"type":"Point"}
}