{
  "type": "Feature",
  "properties": {
    "addr:full":"7325 Kanis Rd Little Rock AR 72204",
    "addr:housenumber":"7325",
    "addr:postcode":"72204",
    "addr:street":"Kanis Rd",
    "iso:country":"US",
    "sg:address":"7325 Kanis Rd",
    "sg:city":"Little Rock",
    "sg:classifiers":[
        {
            "category":"Building & Trades",
            "subcategory":"Construction",
            "type":"Services"
        }
    ],
    "sg:phone":"+1 501 664 8880",
    "sg:postcode":"72204",
    "sg:province":"AR",
    "sg:tags":[
        "marble",
        "terrazzo"
    ],
    "sg:website":"www.marblerenewal.net",
    "wof:name":"Marble Renewal LLC",
    "wof:placetype":"venue"
},
  "geometry": {"coordinates":[-92.356086,34.741831],"type":"Point"}
}