{
  "type": "Feature",
  "properties": {
    "addr:full":"91 Hwy 287 Greenbrier AR 72058",
    "addr:postcode":"72058",
    "addr:street":"91 Hwy 287",
    "iso:country":"US",
    "sg:address":"91 Hwy 287",
    "sg:city":"Greenbrier",
    "sg:classifiers":[
        {
            "category":"Organizations",
            "subcategory":"Religious Organization",
            "type":"Services"
        }
    ],
    "sg:phone":"+1 501 679 7064",
    "sg:postcode":"72058",
    "sg:province":"AR",
    "sg:tags":[
        "church"
    ],
    "wof:name":"Faith Abundant General Baptist",
    "wof:placetype":"venue"
},
  "geometry": {"coordinates":[-92.38369400000001,35.189199],"type":"Point"}
}