{
  "type": "Feature",
  "properties": {
    "addr:full":"405 N Banks St Malvern AR 72104",
    "addr:housenumber":"405",
    "addr:postcode":"72104",
    "addr:street":"N Banks St",
    "iso:country":"US",
    "sg:address":"405 N Banks St",
    "sg:city":"Malvern",
    "sg:classifiers":[
        {
            "category":"Shopping",
            "subcategory":"Hobbies, Toys, & Games",
            "type":"Retail Goods"
        },
        {
            "category":"Shopping",
            "subcategory":"Crafts & Fabrics",
            "type":"Retail Goods"
        }
    ],
    "sg:phone":"+1 501 337 4365",
    "sg:postcode":"72104",
    "sg:province":"AR",
    "sg:tags":[
        "shop",
        "hobby",
        "model",
        "supply"
    ],
    "wof:name":"Auto Craft Collision",
    "wof:placetype":"venue"
},
  "geometry": {"coordinates":[-92.801841,34.369772],"type":"Point"}
}