{
  "type": "Feature",
  "properties": {
    "addr:full":"158 State Hwy 23 Eureka Springs AR 72632",
    "addr:housenumber":"158",
    "addr:postcode":"72632",
    "addr:street":"State Hwy 23",
    "iso:country":"US",
    "sg:address":"158 State Hwy 23",
    "sg:city":"Eureka Springs",
    "sg:classifiers":[
        {
            "category":"Professional",
            "type":"Services"
        }
    ],
    "sg:phone":"+1 479 253 5646",
    "sg:postcode":"72632",
    "sg:province":"AR",
    "sg:tags":[
        "establishment"
    ],
    "wof:name":"Advanced Composites Materials",
    "wof:placetype":"venue"
},
  "geometry": {"coordinates":[-93.742195,36.397048],"type":"Point"}
}