{
  "type": "Feature",
  "properties": {
    "iso:country":"US",
    "sg:address":"49 E 27th Cir",
    "sg:city":"Fayetteville",
    "sg:classifiers":[
        {
            "category":"Professional",
            "subcategory":"Detective & Security Services",
            "type":"Services"
        }
    ],
    "sg:phone":"+1 479 575 0466",
    "sg:postcode":"72701",
    "sg:province":"AR",
    "sg:tags":[
        "information",
        "bureau"
    ],
    "wof:name":"R&N Services Inc",
    "wof:placetype":"venue"
},
  "geometry": {"coordinates":[-94.161379,36.034081],"type":"Point"}
}