{
  "type": "Feature",
  "properties": {
    "iso:country":"US",
    "sg:address":"319 President Clinton Ave",
    "sg:city":"Little Rock",
    "sg:classifiers":[
        {
            "category":"Professional",
            "subcategory":"Lawyer & Legal Services",
            "type":"Services"
        }
    ],
    "sg:phone":"+1 501 374 3559",
    "sg:postcode":"72201",
    "sg:province":"AR",
    "sg:tags":[
        "attorney"
    ],
    "wof:name":"Craig Lambert",
    "wof:placetype":"venue"
},
  "geometry": {"coordinates":[-92.266907,34.747562],"type":"Point"}
}