{
  "type": "Feature",
  "properties": {
    "iso:country":"US",
    "sg:address":"4217 S Thompson St",
    "sg:city":"Springdale",
    "sg:classifiers":[
        {
            "category":"Home & Garden",
            "subcategory":"Furniture",
            "type":"Retail Goods"
        },
        {
            "category":"Home & Garden",
            "subcategory":"Home Furnishings",
            "type":"Retail Goods"
        },
        {
            "category":"Home & Garden",
            "subcategory":"Carpets & Floor Coverings",
            "type":"Retail Goods"
        }
    ],
    "sg:phone":"+1 479 872 6900",
    "sg:postcode":"72764",
    "sg:province":"AR",
    "sg:tags":[
        "bedroom",
        "set",
        "store",
        "bed",
        "mattress"
    ],
    "wof:name":"Mattress King Sleep Center",
    "wof:placetype":"venue"
},
  "geometry": {"coordinates":[-94.14406,36.145961],"type":"Point"}
}