{
  "type": "Feature",
  "properties": {
    "addr:full":"219 W Main St Bradford AR 72020",
    "addr:housenumber":"219",
    "addr:postcode":"72020",
    "addr:street":"W Main St",
    "iso:country":"US",
    "sg:address":"219 W Main St",
    "sg:city":"Bradford",
    "sg:classifiers":[
        {
            "category":"Education",
            "subcategory":"Library",
            "type":"Public Place"
        }
    ],
    "sg:phone":"+1 501 344 2558",
    "sg:postcode":"72020",
    "sg:province":"AR",
    "wof:name":"Bradford Public Library",
    "wof:placetype":"venue"
},
  "geometry": {"coordinates":[-91.45675300000001,35.423643],"type":"Point"}
}