{
  "type": "Feature",
  "properties": {
    "iso:country":"US",
    "sg:address":"219 W Main St",
    "sg:city":"Bradford",
    "sg:classifiers":[
        {
            "category":"Education",
            "subcategory":"Library",
            "type":"Public Place"
        }
    ],
    "sg:phone":"+1 501 344 2558",
    "sg:postcode":"72020",
    "sg:province":"AR",
    "wof:name":"Bradford Public Library",
    "wof:placetype":"venue"
},
  "geometry": {"coordinates":[-91.456753,35.423643],"type":"Point"}
}