{
  "type": "Feature",
  "properties": {
    "addr:full":"8 Pine Mountain Rd Little Rock AR 72223",
    "addr:housenumber":"8",
    "addr:postcode":"72223",
    "addr:street":"Pine Mountain Rd",
    "iso:country":"US",
    "sg:address":"8 Pine Mountain Rd",
    "sg:city":"Little Rock",
    "sg:classifiers":[
        {
            "category":"Organizations",
            "subcategory":"Religious Organization",
            "type":"Services"
        }
    ],
    "sg:phone":"+1 501 868 7740",
    "sg:postcode":"72223",
    "sg:province":"AR",
    "wof:name":"Redemption Life Ministries",
    "wof:placetype":"venue"
},
  "geometry": {"coordinates":[-92.433352,34.804883],"type":"Point"}
}