{
  "type": "Feature",
  "properties": {
    "addr:full":"211 E Harrell Dr Russellville AR 72802",
    "addr:housenumber":"211",
    "addr:postcode":"72802",
    "addr:street":"E Harrell Dr",
    "iso:country":"US",
    "sg:address":"211 E Harrell Dr",
    "sg:city":"Russellville",
    "sg:classifiers":[
        {
            "category":"Bars & Pubs",
            "type":"Food & Drink"
        }
    ],
    "sg:menulink":"http://www.allmenus.com/ar/illinois/33832-cracker-barrel-old-country-store/menu/",
    "sg:phone":"+1 479 968 5983",
    "sg:postcode":"72802",
    "sg:province":"AR",
    "sg:tags":[
        "american",
        "southern"
    ],
    "wof:name":"Cracker Barrel Old Country Store",
    "wof:placetype":"venue"
},
  "geometry": {"coordinates":[-93.13475800000001,35.302418],"type":"Point"}
}