{
  "type": "Feature",
  "properties": {
    "iso:country":"US",
    "sg:address":"300 W Arch Ave",
    "sg:city":"Searcy",
    "sg:classifiers":[
        {
            "category":"Government",
            "subcategory":"Police Station",
            "type":"Public Place"
        }
    ],
    "sg:phone":"+1 501 268 3531",
    "sg:postcode":"72143",
    "sg:province":"AR",
    "sg:tags":[
        "department"
    ],
    "wof:name":"Searcy Police Dept",
    "wof:placetype":"venue"
},
  "geometry": {"coordinates":[-91.739685,35.250106],"type":"Point"}
}