{
  "type": "Feature",
  "properties": {
    "iso:country":"US",
    "sg:address":"817 Pumpkin Center Rd",
    "sg:city":"Clinton",
    "sg:classifiers":[
        {
            "category":"Farming",
            "subcategory":"Fish & Marine Products",
            "type":"Manufacturing & Wholesale Goods"
        }
    ],
    "sg:phone":"+1 501 745 7030",
    "sg:postcode":"72031",
    "sg:province":"AR",
    "wof:name":"Gillam Farms",
    "wof:placetype":"venue"
},
  "geometry": {"coordinates":[-92.687526,35.644709],"type":"Point"}
}