{
  "type": "Feature",
  "properties": {
    "iso:country":"US",
    "sg:address":"314 Park Ave",
    "sg:city":"Huntsville",
    "sg:classifiers":[
        {
            "category":"Retail",
            "subcategory":"Auto Repair",
            "type":"Services"
        }
    ],
    "sg:phone":"+1 479 738 1655",
    "sg:postcode":"72740",
    "sg:province":"AR",
    "sg:tags":[
        "wrecker"
    ],
    "wof:name":"Wendell's Towing",
    "wof:placetype":"venue"
},
  "geometry": {"coordinates":[-93.737975,36.08859],"type":"Point"}
}