{
  "type": "Feature",
  "properties": {
    "iso:country":"US",
    "sg:address":"201 NE 1st St",
    "sg:city":"Atkins",
    "sg:classifiers":[
        {
            "category":"Shopping",
            "subcategory":"Used Merchandise",
            "type":"Retail Goods"
        }
    ],
    "sg:phone":"+1 479 641 0069",
    "sg:postcode":"72823",
    "sg:province":"AR",
    "sg:tags":[
        "antique"
    ],
    "wof:name":"Antique Connections",
    "wof:placetype":"venue"
},
  "geometry": {"coordinates":[-92.936315,35.243094],"type":"Point"}
}