{
  "type": "Feature",
  "properties": {
    "iso:country":"US",
    "sg:address":"1800 Freyaldenhoven Ln",
    "sg:city":"Conway",
    "sg:classifiers":[
        {
            "category":"Education",
            "subcategory":"School",
            "type":"Public Place"
        }
    ],
    "sg:phone":"+1 501 450 6645",
    "sg:postcode":"72032",
    "sg:province":"AR",
    "sg:website":"www.conwaypublicschools.com",
    "wof:name":"Theodore Jones Elementary Schl",
    "wof:placetype":"venue"
},
  "geometry": {"coordinates":[-92.414376,35.101248],"type":"Point"}
}