{
  "type": "Feature",
  "properties": {
    "addr:full":"190 Plateau Ln Pocahontas AR 72455",
    "addr:housenumber":"190",
    "addr:postcode":"72455",
    "addr:street":"Plateau Ln",
    "iso:country":"US",
    "sg:address":"190 Plateau Ln",
    "sg:city":"Pocahontas",
    "sg:classifiers":[
        {
            "category":"Real Estate",
            "subcategory":"Real Estate Operator",
            "type":"Services"
        }
    ],
    "sg:phone":"+1 573 448 3357",
    "sg:postcode":"72455",
    "sg:province":"AR",
    "sg:tags":[
        "apartment"
    ],
    "wof:name":"Rolling Hills Of Pocahontas Limited Partnership",
    "wof:placetype":"venue"
},
  "geometry": {"coordinates":[-91.04431599999999,36.295661],"type":"Point"}
}