{
  "type": "Feature",
  "properties": {
    "addr:full":"215 Bayou Two Rd Lonoke AR 72086",
    "addr:housenumber":"215",
    "addr:postcode":"72086",
    "addr:street":"Bayou Two Rd",
    "iso:country":"US",
    "sg:address":"215 Bayou Two Rd",
    "sg:city":"Lonoke",
    "sg:classifiers":[
        {
            "category":"Building & Trades",
            "subcategory":"Construction",
            "type":"Services"
        }
    ],
    "sg:phone":"+1 501 944 1396",
    "sg:postcode":"72086",
    "sg:province":"AR",
    "sg:tags":[
        "water",
        "restoration",
        "damage"
    ],
    "wof:name":"Absolute Water Restoration",
    "wof:placetype":"venue"
},
  "geometry": {"coordinates":[-91.980627,34.854174],"type":"Point"}
}