{
  "type": "Feature",
  "properties": {
    "iso:country":"US",
    "sg:address":"2411 Hinson Rd",
    "sg:city":"El Dorado",
    "sg:classifiers":[
        {
            "category":"Wholesale",
            "subcategory":"Construction Materials",
            "type":"Manufacturing & Wholesale Goods"
        }
    ],
    "sg:phone":"+1 870 863 5033",
    "sg:postcode":"71730",
    "sg:province":"AR",
    "wof:name":"Classic Marble & Granite",
    "wof:placetype":"venue"
},
  "geometry": {"coordinates":[-92.701016,33.15652],"type":"Point"}
}