{
  "type": "Feature",
  "properties": {
    "addr:full":"1419 E Ave El Dorado AR 71730",
    "addr:housenumber":"1419",
    "addr:postcode":"71730",
    "addr:street":"E Ave",
    "iso:country":"US",
    "sg:address":"1419 E Ave",
    "sg:city":"El Dorado",
    "sg:classifiers":[
        {
            "category":"Organizations",
            "subcategory":"Religious Organization",
            "type":"Services"
        }
    ],
    "sg:phone":"+1 870 862 8956",
    "sg:postcode":"71730",
    "sg:province":"AR",
    "sg:tags":[
        "church"
    ],
    "wof:name":"Miles Memorial Church Of God",
    "wof:placetype":"venue"
},
  "geometry": {"coordinates":[-92.667738,33.196911],"type":"Point"}
}