{
  "type": "Feature",
  "properties": {
    "addr:full":"10468 Hwy 229 S Leola AR 72084",
    "addr:housenumber":"10468",
    "addr:postcode":"72084",
    "addr:street":"Hwy 229 S Leola",
    "iso:country":"US",
    "sg:address":"10468 Hwy 229 S",
    "sg:city":"Leola",
    "sg:classifiers":[
        {
            "category":"Manufacturing",
            "subcategory":"Lumber",
            "type":"Manufacturing & Wholesale Goods"
        }
    ],
    "sg:phone":"+1 870 765 2211",
    "sg:postcode":"72084",
    "sg:province":"AR",
    "sg:tags":[
        "planing",
        "mills",
        "sawmill"
    ],
    "wof:name":"H G Toler & Son Lumber Co",
    "wof:placetype":"venue"
},
  "geometry": {"coordinates":[-92.596571,34.180486],"type":"Point"}
}