{
  "type": "Feature",
  "properties": {
    "iso:country":"US",
    "sg:address":"245 E North St",
    "sg:city":"Mountain Home",
    "sg:classifiers":[
        {
            "category":"Organizations",
            "subcategory":"Religious Organization",
            "type":"Services"
        }
    ],
    "sg:phone":"+1 870 425 4330",
    "sg:postcode":"72653",
    "sg:province":"AR",
    "sg:tags":[
        "church"
    ],
    "sg:website":"www.mtnhomechurchofchrist.com",
    "wof:name":"Mountain Home Church Of Christ",
    "wof:placetype":"venue"
},
  "geometry": {"coordinates":[-92.38300099999999,36.343697],"type":"Point"}
}