{
  "type": "Feature",
  "properties": {
    "iso:country":"US",
    "sg:address":"2870 Strong Hwy",
    "sg:city":"El Dorado",
    "sg:classifiers":[
        {
            "category":"Organizations",
            "subcategory":"Religious Organization",
            "type":"Services"
        }
    ],
    "sg:phone":"+1 870 864 9181",
    "sg:postcode":"71730",
    "sg:province":"AR",
    "sg:tags":[
        "church"
    ],
    "wof:name":"Good Samaritin Church",
    "wof:placetype":"venue"
},
  "geometry": {"coordinates":[-92.565383,33.16252],"type":"Point"}
}