{
  "type": "Feature",
  "properties": {
    "iso:country":"US",
    "sg:address":"30 Sallent Ln",
    "sg:city":"Hot Springs Vlg",
    "sg:classifiers":[
        {
            "category":"Professional",
            "subcategory":"Business Services",
            "type":"Services"
        }
    ],
    "sg:phone":"+1 501 915 9949",
    "sg:postcode":"71909",
    "sg:province":"AR",
    "sg:tags":[
        "cashing",
        "protection",
        "check",
        "system"
    ],
    "wof:name":"Merchant Services Unlimited",
    "wof:placetype":"venue"
},
  "geometry": {"coordinates":[-93.04378699999999,34.674463],"type":"Point"}
}