{
  "type": "Feature",
  "properties": {
    "addr:full":"124 Oak St Conway AR 72032",
    "addr:housenumber":"124",
    "addr:postcode":"72032",
    "addr:street":"Oak St",
    "iso:country":"US",
    "sg:address":"124 Oak St",
    "sg:city":"Conway",
    "sg:classifiers":[
        {
            "category":"Wholesale",
            "subcategory":"Office Equipment",
            "type":"Manufacturing & Wholesale Goods"
        }
    ],
    "sg:phone":"+1 501 329 4242",
    "sg:postcode":"72032",
    "sg:province":"AR",
    "wof:name":"Accounting Shop",
    "wof:placetype":"venue"
},
  "geometry": {"coordinates":[-92.428146,35.091712],"type":"Point"}
}