{
  "type": "Feature",
  "properties": {
    "iso:country":"US",
    "sg:address":"557 Locust St",
    "sg:city":"Conway",
    "sg:classifiers":[
        {
            "category":"Professional",
            "subcategory":"Lawyer & Legal Services",
            "type":"Services"
        }
    ],
    "sg:phone":"+1 501 932 1007",
    "sg:postcode":"72034",
    "sg:province":"AR",
    "sg:tags":[
        "plan"
    ],
    "wof:name":"Hiland Law Firm",
    "wof:placetype":"venue"
},
  "geometry": {"coordinates":[-92.44114999999999,35.086038],"type":"Point"}
}