{
  "type": "Feature",
  "properties": {
    "iso:country":"US",
    "sg:address":"2910 E Harding Ave",
    "sg:city":"Pine Bluff",
    "sg:classifiers":[
        {
            "category":"Shopping",
            "subcategory":"Stationery & Office Supplies",
            "type":"Retail Goods"
        }
    ],
    "sg:phone":"+1 870 534 7600",
    "sg:postcode":"71601",
    "sg:province":"AR",
    "sg:website":"www.staples.com",
    "wof:name":"Staples",
    "wof:placetype":"venue"
},
  "geometry": {"coordinates":[-91.973001,34.210982],"type":"Point"}
}