{
  "type": "Feature",
  "properties": {
    "iso:country":"US",
    "sg:address":"726 W Walnut St",
    "sg:city":"Rogers",
    "sg:classifiers":[
        {
            "category":"Taxi",
            "type":"Transportation"
        }
    ],
    "sg:phone":"+1 479 872 6600",
    "sg:postcode":"72756",
    "sg:province":"AR",
    "sg:tags":[
        "taxicab",
        "local",
        "passenger"
    ],
    "wof:name":"Tony CS Taxi Cab",
    "wof:placetype":"venue"
},
  "geometry": {"coordinates":[-94.125187,36.333364],"type":"Point"}
}