{
  "type": "Feature",
  "properties": {
    "iso:country":"US",
    "sg:address":"667 Creek Rd",
    "sg:city":"Benton",
    "sg:classifiers":[
        {
            "category":"Professional",
            "subcategory":"Business Services",
            "type":"Services"
        }
    ],
    "sg:phone":"+1 501 794 1736",
    "sg:postcode":"72015",
    "sg:province":"AR",
    "wof:name":"B&B Pool Service",
    "wof:placetype":"venue"
},
  "geometry": {"coordinates":[-92.63523,34.520725],"type":"Point"}
}