{
  "type": "Feature",
  "properties": {
    "iso:country":"US",
    "sg:address":"601 W Maple Ave Ste 401B",
    "sg:city":"Springdale",
    "sg:classifiers":[
        {
            "category":"Health Services",
            "subcategory":"Doctor",
            "type":"Services"
        },
        {
            "category":"Personal",
            "subcategory":"Hair Removal",
            "type":"Services"
        }
    ],
    "sg:phone":"+1 479 751 8895",
    "sg:postcode":"72764",
    "sg:province":"AR",
    "sg:tags":[
        "laser"
    ],
    "wof:name":"Tejada Skin Care and Laser Clinic",
    "wof:placetype":"venue"
},
  "geometry": {"coordinates":[-94.135953,36.18125],"type":"Point"}
}