{
  "type": "Feature",
  "properties": {
    "iso:country":"US",
    "sg:address":"1701 N Missouri St",
    "sg:city":"West Memphis",
    "sg:classifiers":[
        {
            "category":"Cinema",
            "subcategory":"Movie Rental",
            "type":"Entertainment"
        }
    ],
    "sg:phone":"+1 870 735 1057",
    "sg:postcode":"72301",
    "sg:province":"AR",
    "sg:tags":[
        "leasing",
        "video",
        "disc",
        "tape"
    ],
    "wof:name":"Great Games",
    "wof:placetype":"venue"
},
  "geometry": {"coordinates":[-90.184697,35.164732],"type":"Point"}
}