{
  "type": "Feature",
  "properties": {
    "iso:country":"US",
    "sg:address":"401 N 3rd St",
    "sg:city":"Mc Gehee",
    "sg:classifiers":[
        {
            "category":"Organizations",
            "subcategory":"Religious Organization",
            "type":"Services"
        }
    ],
    "sg:phone":"+1 870 222 3389",
    "sg:postcode":"71654",
    "sg:province":"AR",
    "sg:tags":[
        "church"
    ],
    "wof:name":"St Marys Catholic Church",
    "wof:placetype":"venue"
},
  "geometry": {"coordinates":[-91.39988,33.631299],"type":"Point"}
}