{
  "type": "Feature",
  "properties": {
    "addr:full":"1900 S 1st St Rogers AR 72758",
    "addr:housenumber":"1900",
    "addr:postcode":"72758",
    "addr:street":"S 1St St",
    "iso:country":"US",
    "sg:address":"1900 S 1st St",
    "sg:city":"Rogers",
    "sg:classifiers":[
        {
            "category":"Personal",
            "subcategory":"Beauty Salon",
            "type":"Services"
        }
    ],
    "sg:phone":"+1 479 636 1426",
    "sg:postcode":"72758",
    "sg:province":"AR",
    "sg:tags":[
        "shop"
    ],
    "wof:name":"Mindy's Hair Salon",
    "wof:placetype":"venue"
},
  "geometry": {"coordinates":[-94.11741000000001,36.311392],"type":"Point"}
}