{
  "type": "Feature",
  "properties": {
    "iso:country":"US",
    "sg:address":"11 E 3rd St",
    "sg:city":"Grove",
    "sg:classifiers":[
        {
            "category":"Government",
            "subcategory":"Police Station",
            "type":"Public Place"
        }
    ],
    "sg:phone":"+1 918 786 6121",
    "sg:postcode":"74344",
    "sg:province":"OK",
    "sg:tags":[
        "department",
        "protection"
    ],
    "wof:name":"Grove City Police Dept",
    "wof:placetype":"venue"
},
  "geometry": {"coordinates":[-94.769198,36.59353],"type":"Point"}
}