{
  "type": "Feature",
  "properties": {
    "iso:country":"US",
    "sg:address":"6917 Geyer Springs Rd",
    "sg:city":"Little Rock",
    "sg:classifiers":[
        {
            "category":"Autos & Motor Vehicles",
            "subcategory":"Automobile Sales",
            "type":"Retail Goods"
        }
    ],
    "sg:phone":"+1 501 562 5438",
    "sg:postcode":"72209",
    "sg:province":"AR",
    "sg:tags":[
        "car",
        "dealer"
    ],
    "wof:name":"MNK Used Cars Inc",
    "wof:placetype":"venue"
},
  "geometry": {"coordinates":[-92.343477,34.686116],"type":"Point"}
}