{
  "type": "Feature",
  "properties": {
    "iso:country":"US",
    "sg:address":"8 Halstead Cir",
    "sg:city":"Rogers",
    "sg:classifiers":[
        {
            "category":"Food & Beverages",
            "subcategory":"Bakery",
            "type":"Retail Goods"
        }
    ],
    "sg:phone":"+1 479 631 8285",
    "sg:postcode":"72756",
    "sg:province":"AR",
    "sg:tags":[
        "baker"
    ],
    "wof:name":"George Weston Foods Inc",
    "wof:placetype":"venue"
},
  "geometry": {"coordinates":[-94.160877,36.334577],"type":"Point"}
}