{
  "type": "Feature",
  "properties": {
    "addr:full":"175 Ouachita 408 Camden AR 71701",
    "addr:housenumber":"175;408",
    "addr:postcode":"71701",
    "addr:street":"Ouachita",
    "iso:country":"US",
    "sg:address":"175 Ouachita 408",
    "sg:city":"Camden",
    "sg:classifiers":[
        {
            "category":"Organizations",
            "subcategory":"Religious Organization",
            "type":"Services"
        }
    ],
    "sg:phone":"+1 870 574 1062",
    "sg:postcode":"71701",
    "sg:province":"AR",
    "wof:name":"Grove Pleasant Baptist Church",
    "wof:placetype":"venue"
},
  "geometry": {"coordinates":[-92.778363,33.677263],"type":"Point"}
}