{
  "type": "Feature",
  "properties": {
    "iso:country":"US",
    "sg:address":"3010 State Hwy 22 E",
    "sg:city":"Branch",
    "sg:classifiers":[
        {
            "category":"Government",
            "subcategory":"Office",
            "type":"Public Place"
        }
    ],
    "sg:phone":"+1 479 965 2191",
    "sg:postcode":"72928",
    "sg:province":"AR",
    "sg:tags":[
        "educational",
        "program",
        "administrative"
    ],
    "wof:name":"West Arkansas Education Co-Op",
    "wof:placetype":"venue"
},
  "geometry": {"coordinates":[-93.92954,35.306119],"type":"Point"}
}