{
  "type": "Feature",
  "properties": {
    "addr:full":"2231 E Grand Ave Hot Springs AR 71901",
    "addr:housenumber":"2231",
    "addr:postcode":"71901",
    "addr:street":"E Grand Ave",
    "iso:country":"US",
    "sg:address":"2231 E Grand Ave",
    "sg:city":"Hot Springs",
    "sg:classifiers":[
        {
            "category":"Organizations",
            "subcategory":"Community Association",
            "type":"Services"
        }
    ],
    "sg:phone":"+1 501 623 5190",
    "sg:postcode":"71901",
    "sg:province":"AR",
    "sg:tags":[
        "military"
    ],
    "sg:website":"www.vfw.org",
    "wof:name":"Veterans Of Foreign Wars",
    "wof:placetype":"venue"
},
  "geometry": {"coordinates":[-93.00768600000001,34.506145],"type":"Point"}
}