{
  "type": "Feature",
  "properties": {
    "iso:country":"US",
    "sg:address":"320 S Main St",
    "sg:city":"Benton",
    "sg:classifiers":[
        {
            "category":"Building & Trades",
            "subcategory":"Plumbing",
            "type":"Services"
        }
    ],
    "sg:phone":"+1 501 315 2831",
    "sg:postcode":"72015",
    "sg:province":"AR",
    "sg:tags":[
        "heating",
        "contractor"
    ],
    "wof:name":"Benton Sheet Metal Inc",
    "wof:placetype":"venue"
},
  "geometry": {"coordinates":[-92.586899,34.561123],"type":"Point"}
}