{
  "type": "Feature",
  "properties": {
    "iso:country":"US",
    "sg:address":"2856 State Hwy 8",
    "sg:city":"Mena",
    "sg:classifiers":[
        {
            "category":"Airport",
            "type":"Transportation"
        }
    ],
    "sg:phone":"+1 479 243 0072",
    "sg:postcode":"71953",
    "sg:province":"OK",
    "sg:tags":[
        "aircraft",
        "painting",
        "refinishing"
    ],
    "wof:name":"D & T Aircraft Painting",
    "wof:placetype":"venue"
},
  "geometry": {"coordinates":[-94.191291,34.547566],"type":"Point"}
}