{
  "type": "Feature",
  "properties": {
    "addr:full":"202 Bishop St Little Rock AR 72201",
    "addr:housenumber":"202",
    "addr:postcode":"72201",
    "addr:street":"Bishop St",
    "iso:country":"US",
    "sg:address":"202 Bishop St",
    "sg:city":"Little Rock",
    "sg:classifiers":[
        {
            "category":"Building & Trades",
            "subcategory":"Pest Control",
            "type":"Services"
        }
    ],
    "sg:phone":"+1 501 375 0788",
    "sg:postcode":"72201",
    "sg:province":"AR",
    "sg:tags":[
        "termite"
    ],
    "wof:name":"Currys Trmt/PST Cntrl Co of",
    "wof:placetype":"venue"
},
  "geometry": {"coordinates":[-92.29005100000001,34.749082],"type":"Point"}
}