{
  "type": "Feature",
  "properties": {
    "iso:country":"US",
    "sg:address":"401 N 2nd St",
    "sg:city":"Paragould",
    "sg:classifiers":[
        {
            "category":"Personal",
            "subcategory":"Beauty Salon",
            "type":"Services"
        }
    ],
    "sg:phone":"+1 870 239 5369",
    "sg:postcode":"72450",
    "sg:province":"AR",
    "wof:name":"Deb's Hair Inc",
    "wof:placetype":"venue"
},
  "geometry": {"coordinates":[-90.48729400000001,36.059235],"type":"Point"}
}