{
  "type": "Feature",
  "properties": {
    "iso:country":"US",
    "sg:address":"22430 I- 30",
    "sg:city":"Bryant",
    "sg:classifiers":[
        {
            "category":"Home & Garden",
            "subcategory":"Furniture",
            "type":"Retail Goods"
        }
    ],
    "sg:phone":"+1 501 847 9595",
    "sg:postcode":"72022",
    "sg:province":"AR",
    "wof:name":"Bedding Mart",
    "wof:placetype":"venue"
},
  "geometry": {"coordinates":[-92.50285,34.616669],"type":"Point"}
}