{
  "type": "Feature",
  "properties": {
    "iso:country":"US",
    "sg:address":"1800 S Stirman Ave",
    "sg:city":"Fayetteville",
    "sg:classifiers":[
        {
            "category":"Professional",
            "type":"Services"
        },
        {
            "category":"Structure",
            "subcategory":"Office Building",
            "type":"Public Place"
        },
        {
            "category":"Retail",
            "subcategory":"Auto Rental",
            "type":"Services"
        },
        {
            "category":"Structure",
            "subcategory":"Warehouse",
            "type":"Public Place"
        },
        {
            "category":"Retail",
            "subcategory":"Storage",
            "type":"Services"
        }
    ],
    "sg:phone":"+1 479 571 8700",
    "sg:postcode":"72701",
    "sg:province":"AR",
    "sg:tags":[
        "recreational",
        "warehouses-merchandise",
        "space",
        "household",
        "material",
        "commercial",
        "truck",
        "campers-storage",
        "vehicle",
        "moving",
        "desk",
        "services-labor",
        "self",
        "boat"
    ],
    "sg:website":"http://www.levistorage.com",
    "wof:name":"Levi Storage Center",
    "wof:placetype":"venue"
},
  "geometry": {"coordinates":[-94.175107,36.04513],"type":"Point"}
}