{
  "type": "Feature",
  "properties": {
    "iso:country":"US",
    "sg:address":"8821 Geyer Springs Rd",
    "sg:city":"Little Rock",
    "sg:classifiers":[
        {
            "category":"Shopping",
            "subcategory":"Discount & Variety Stores",
            "type":"Retail Goods"
        }
    ],
    "sg:phone":"+1 501 570 0233",
    "sg:postcode":"72209",
    "sg:province":"AR",
    "sg:tags":[
        "merchandise",
        "general"
    ],
    "wof:name":"99 Cents Plus Discount",
    "wof:placetype":"venue"
},
  "geometry": {"coordinates":[-92.344245,34.669905],"type":"Point"}
}