{
  "type": "Feature",
  "properties": {
    "addr:full":"1701 E 22nd St Little Rock AR 72206",
    "addr:housenumber":"1701",
    "addr:postcode":"72206",
    "addr:street":"E 22Nd St",
    "iso:country":"US",
    "sg:address":"1701 E 22nd St",
    "sg:city":"Little Rock",
    "sg:classifiers":[
        {
            "category":"Manufacturing",
            "subcategory":"Metals",
            "type":"Manufacturing & Wholesale Goods"
        }
    ],
    "sg:phone":"+1 501 372 3441",
    "sg:postcode":"72206",
    "sg:province":"AR",
    "sg:tags":[
        "trim",
        "frame",
        "door",
        "sash"
    ],
    "wof:name":"National Custom Hollow Metal",
    "wof:placetype":"venue"
},
  "geometry": {"coordinates":[-92.25223699999999,34.726731],"type":"Point"}
}