{
  "type": "Feature",
  "properties": {
    "iso:country":"US",
    "sg:address":"114 Union Ln",
    "sg:city":"El Dorado",
    "sg:classifiers":[
        {
            "category":"Building & Trades",
            "subcategory":"Construction",
            "type":"Services"
        }
    ],
    "sg:phone":"+1 870 862 0240",
    "sg:postcode":"71730",
    "sg:province":"AR",
    "sg:tags":[
        "house"
    ],
    "wof:name":"Harrell & Goodman Inc",
    "wof:placetype":"venue"
},
  "geometry": {"coordinates":[-92.5708,33.225348],"type":"Point"}
}