{
  "type": "Feature",
  "properties": {
    "iso:country":"US",
    "sg:address":"5 Holly Springs Ct",
    "sg:city":"Little Rock",
    "sg:classifiers":[
        {
            "category":"Professional",
            "subcategory":"Management & Consulting",
            "type":"Services"
        }
    ],
    "sg:phone":"+1 501 224 0106",
    "sg:postcode":"72212",
    "sg:province":"AR",
    "sg:tags":[
        "business"
    ],
    "wof:name":"Harpool Family Enterprises LLC",
    "wof:placetype":"venue"
},
  "geometry": {"coordinates":[-92.42524299999999,34.786186],"type":"Point"}
}