{
  "type": "Feature",
  "properties": {
    "iso:country":"US",
    "sg:address":"11401 W Markham St",
    "sg:city":"Little Rock",
    "sg:classifiers":[
        {
            "category":"Retail",
            "subcategory":"Car Wash",
            "type":"Services"
        }
    ],
    "sg:phone":"+1 501 224 7566",
    "sg:postcode":"72211",
    "sg:province":"AR",
    "sg:tags":[
        "carwash"
    ],
    "wof:name":"P KS Auto Spa",
    "wof:placetype":"venue"
},
  "geometry": {"coordinates":[-92.404082,34.753956],"type":"Point"}
}