{
  "type": "Feature",
  "properties": {
    "iso:country":"US",
    "sg:address":"403 Sherwood Ave",
    "sg:city":"Mena",
    "sg:classifiers":[
        {
            "category":"Food & Beverages",
            "subcategory":"Groceries & Convenience Stores",
            "type":"Retail Goods"
        }
    ],
    "sg:phone":"+1 479 394 3535",
    "sg:postcode":"71953",
    "sg:province":"OK",
    "sg:tags":[
        "grocer"
    ],
    "wof:name":"Brantley's Warehouse Foods",
    "wof:placetype":"venue"
},
  "geometry": {"coordinates":[-94.234687,34.584063],"type":"Point"}
}