{
  "type": "Feature",
  "properties": {
    "addr:full":"160 Pearcy Church Pl Pearcy AR 71964",
    "addr:housenumber":"160",
    "addr:postcode":"71964",
    "addr:street":"Pearcy Church Pl",
    "iso:country":"US",
    "sg:address":"160 Pearcy Church Pl",
    "sg:city":"Pearcy",
    "sg:classifiers":[
        {
            "category":"Building & Trades",
            "subcategory":"Construction",
            "type":"Services"
        }
    ],
    "sg:phone":"+1 501 545 0151",
    "sg:postcode":"71964",
    "sg:province":"AR",
    "sg:tags":[
        "tile",
        "dealer"
    ],
    "wof:name":"Hughes Renovating",
    "wof:placetype":"venue"
},
  "geometry": {"coordinates":[-93.288237,34.427772],"type":"Point"}
}