{
  "type": "Feature",
  "properties": {
    "iso:country":"US",
    "sg:address":"311 Meeks Rd",
    "sg:city":"Okolona",
    "sg:classifiers":[
        {
            "category":"Manufacturing",
            "subcategory":"Lumber",
            "type":"Manufacturing & Wholesale Goods"
        }
    ],
    "sg:phone":"+1 870 379 2025",
    "sg:postcode":"71962",
    "sg:province":"AR",
    "sg:tags":[
        "logging"
    ],
    "wof:name":"Leepers Logging",
    "wof:placetype":"venue"
},
  "geometry": {"coordinates":[-93.392257,34.042756],"type":"Point"}
}