{
  "type": "Feature",
  "properties": {
    "iso:country":"US",
    "sg:address":"2641 Rogers Ave",
    "sg:city":"Fort Smith",
    "sg:classifiers":[
        {
            "category":"Social Services",
            "type":"Services"
        }
    ],
    "sg:phone":"+1 479 783 7722",
    "sg:postcode":"72901",
    "sg:province":"AR",
    "sg:tags":[
        "instruction",
        "health",
        "care"
    ],
    "wof:name":"Alta Healthcare Management",
    "wof:placetype":"venue"
},
  "geometry": {"coordinates":[-94.404215,35.376228],"type":"Point"}
}