{
  "type": "Feature",
  "properties": {
    "addr:full":"210 E C St Russellville AR 72801",
    "addr:housenumber":"210",
    "addr:postcode":"72801",
    "addr:street":"E C St",
    "iso:country":"US",
    "sg:address":"210 E C St",
    "sg:city":"Russellville",
    "sg:classifiers":[
        {
            "category":"Building & Trades",
            "subcategory":"Construction",
            "type":"Services"
        }
    ],
    "sg:phone":"+1 479 968 5338",
    "sg:postcode":"72801",
    "sg:province":"AR",
    "sg:tags":[
        "contractor"
    ],
    "wof:name":"Keener Construction Co",
    "wof:placetype":"venue"
},
  "geometry": {"coordinates":[-93.13186399999999,35.280107],"type":"Point"}
}