{
  "type": "Feature",
  "properties": {
    "iso:country":"US",
    "sg:address":"590 W Mark St",
    "sg:city":"Batesville",
    "sg:classifiers":[
        {
            "category":"Organizations",
            "subcategory":"Religious Organization",
            "type":"Services"
        }
    ],
    "sg:phone":"+1 870 793 5280",
    "sg:postcode":"72501",
    "sg:province":"AR",
    "sg:tags":[
        "church"
    ],
    "wof:name":"New Testament Holiness Church",
    "wof:placetype":"venue"
},
  "geometry": {"coordinates":[-91.663257,35.77965],"type":"Point"}
}