{
  "type": "Feature",
  "properties": {
    "iso:country":"US",
    "sg:address":"518 W 9th St",
    "sg:city":"Little Rock",
    "sg:classifiers":[
        {
            "category":"Professional",
            "subcategory":"Art Services",
            "type":"Services"
        }
    ],
    "sg:phone":"+1 501 372 5892",
    "sg:postcode":"72201",
    "sg:province":"AR",
    "sg:tags":[
        "photographer"
    ],
    "wof:name":"Bill Parsons Photography",
    "wof:placetype":"venue"
},
  "geometry": {"coordinates":[-92.277092,34.741007],"type":"Point"}
}