{
  "type": "Feature",
  "properties": {
    "iso:country":"US",
    "sg:address":"6009 Green Valley Ave",
    "sg:city":"North Little Rock",
    "sg:classifiers":[
        {
            "category":"Education",
            "subcategory":"School",
            "type":"Public Place"
        }
    ],
    "sg:phone":"+1 501 758 2082",
    "sg:postcode":"72118",
    "sg:province":"AR",
    "sg:tags":[
        "center",
        "learning"
    ],
    "wof:name":"Pathway To Success Lrng Ctr",
    "wof:placetype":"venue"
},
  "geometry": {"coordinates":[-92.282634,34.810311],"type":"Point"}
}