{
  "type": "Feature",
  "properties": {
    "iso:country":"US",
    "sg:address":"2619 S Caraway Rd",
    "sg:city":"Jonesboro",
    "sg:classifiers":[
        {
            "category":"Shopping",
            "subcategory":"Clothing, Apparel, & Fashions",
            "type":"Retail Goods"
        }
    ],
    "sg:phone":"+1 870 268 8668",
    "sg:postcode":"72401",
    "sg:province":"AR",
    "sg:tags":[
        "clothing",
        "store"
    ],
    "wof:name":"Scrubs for Less",
    "wof:placetype":"venue"
},
  "geometry": {"coordinates":[-90.678016,35.813705],"type":"Point"}
}