{
  "type": "Feature",
  "properties": {
    "iso:country":"US",
    "sg:address":"3512 Ragweed Valley Rd",
    "sg:city":"Royal",
    "sg:classifiers":[
        {
            "category":"Manufacturing",
            "subcategory":"Glass & Minerals",
            "type":"Manufacturing & Wholesale Goods"
        }
    ],
    "sg:phone":"+1 501 991 3886",
    "sg:postcode":"71968",
    "sg:province":"AR",
    "sg:tags":[
        "product",
        "nonmetallic",
        "mfg"
    ],
    "wof:name":"David Harris",
    "wof:placetype":"venue"
},
  "geometry": {"coordinates":[-93.392867,34.489419],"type":"Point"}
}