{
  "type": "Feature",
  "properties": {
    "iso:country":"US",
    "sg:address":"203 E Pine St",
    "sg:city":"Rogers",
    "sg:classifiers":[
        {
            "category":"Autos & Motor Vehicles",
            "subcategory":"Automobile Sales",
            "type":"Retail Goods"
        }
    ],
    "sg:phone":"+1 479 986 9009",
    "sg:postcode":"72756",
    "sg:province":"AR",
    "sg:tags":[
        "car",
        "used"
    ],
    "wof:name":"R & R Auto Sales",
    "wof:placetype":"venue"
},
  "geometry": {"coordinates":[-94.11579500000001,36.327849],"type":"Point"}
}