{
  "type": "Feature",
  "properties": {
    "iso:country":"US",
    "sg:address":"2901 Medical Center Dr",
    "sg:city":"Pocahontas",
    "sg:classifiers":[
        {
            "category":"Wholesale",
            "subcategory":"Medical Equipment & Supplies",
            "type":"Manufacturing & Wholesale Goods"
        },
        {
            "category":"Shopping",
            "subcategory":"Pharmacy",
            "type":"Retail Goods"
        },
        {
            "category":"Community Center",
            "type":"Public Place"
        }
    ],
    "sg:phone":"+1 870 892 4495",
    "sg:postcode":"72455",
    "sg:province":"AR",
    "sg:tags":[
        "home",
        "care",
        "health",
        "first",
        "aid"
    ],
    "wof:name":"Medical Center Pharmacy",
    "wof:placetype":"venue"
},
  "geometry": {"coordinates":[-90.997467,36.290298],"type":"Point"}
}