{
  "type": "Feature",
  "properties": {
    "addr:full":"871 Park Ave Hot Springs National AR 71901",
    "addr:housenumber":"871",
    "addr:postcode":"71901",
    "addr:street":"Park Ave",
    "iso:country":"US",
    "sg:address":"871 Park Ave",
    "sg:city":"Hot Springs National",
    "sg:classifiers":[
        {
            "category":"Retail",
            "subcategory":"Self-service Laundry",
            "type":"Services"
        }
    ],
    "sg:phone":"+1 501 623 6054",
    "sg:postcode":"71901",
    "sg:province":"AR",
    "sg:tags":[
        "coin"
    ],
    "wof:name":"CA Lin Inc",
    "wof:placetype":"venue"
},
  "geometry": {"coordinates":[-93.050405,34.529022],"type":"Point"}
}