{
  "type": "Feature",
  "properties": {
    "addr:full":"204 E Lincoln St Hamburg AR 71646",
    "addr:housenumber":"204",
    "addr:postcode":"71646",
    "addr:street":"E Lincoln St",
    "iso:country":"US",
    "sg:address":"204 E Lincoln St",
    "sg:city":"Hamburg",
    "sg:classifiers":[
        {
            "category":"Professional",
            "subcategory":"Lawyer & Legal Services",
            "type":"Services"
        }
    ],
    "sg:phone":"+1 870 853 8225",
    "sg:postcode":"71646",
    "sg:province":"AR",
    "sg:tags":[
        "attorney",
        "practice"
    ],
    "wof:name":"John R Byrd Attorney",
    "wof:placetype":"venue"
},
  "geometry": {"coordinates":[-91.796645,33.225718],"type":"Point"}
}