{
  "type": "Feature",
  "properties": {
    "iso:country":"US",
    "sg:address":"8 Shackleford Plz",
    "sg:city":"Little Rock",
    "sg:classifiers":[
        {
            "category":"Social Services",
            "type":"Services"
        }
    ],
    "sg:phone":"+1 501 228 7197",
    "sg:postcode":"72211",
    "sg:province":"AR",
    "sg:tags":[
        "organization",
        "welfare"
    ],
    "wof:name":"Community Resource Group Inc",
    "wof:placetype":"venue"
},
  "geometry": {"coordinates":[-92.397531,34.766281],"type":"Point"}
}