{
  "type": "Feature",
  "properties": {
    "iso:country":"US",
    "sg:address":"2349 Green Acres",
    "sg:city":"Fayetteville",
    "sg:classifiers":[
        {
            "category":"Mining & Drilling",
            "type":"Manufacturing & Wholesale Goods"
        }
    ],
    "sg:phone":"+1 479 582 9444",
    "sg:postcode":"72703",
    "sg:province":"AR",
    "sg:tags":[
        "oil",
        "gas",
        "producer"
    ],
    "wof:name":"RDM Oil",
    "wof:placetype":"venue"
},
  "geometry": {"coordinates":[-94.157368,36.095258],"type":"Point"}
}