{
  "type": "Feature",
  "properties": {
    "iso:country":"US",
    "sg:address":"1221 S Main St",
    "sg:city":"Hope",
    "sg:classifiers":[
        {
            "category":"Professional",
            "subcategory":"Lawyer & Legal Services",
            "type":"Services"
        },
        {
            "category":"Banks & Credit Unions",
            "subcategory":"Financial Services",
            "type":"Services"
        }
    ],
    "sg:phone":"+1 870 777 5483",
    "sg:postcode":"71801",
    "sg:province":"AR",
    "sg:tags":[
        "attorney",
        "practice",
        "bankruptcy"
    ],
    "wof:name":"William Moritz",
    "wof:placetype":"venue"
},
  "geometry": {"coordinates":[-93.588544,33.658129],"type":"Point"}
}