{
  "type": "Feature",
  "properties": {
    "iso:country":"US",
    "sg:address":"414 W Maple St",
    "sg:city":"Dermott",
    "sg:classifiers":[
        {
            "category":"Personal",
            "subcategory":"Beauty Salon",
            "type":"Services"
        }
    ],
    "sg:phone":"+1 870 538 3406",
    "sg:postcode":"71638",
    "sg:province":"AR",
    "wof:name":"Jackie's Beauty Salon/Home",
    "wof:placetype":"venue"
},
  "geometry": {"coordinates":[-91.439621,33.530986],"type":"Point"}
}