{
  "type": "Feature",
  "properties": {
    "iso:country":"US",
    "sg:address":"504 N Montgomery St",
    "sg:city":"Clarksville",
    "sg:classifiers":[
        {
            "category":"Personal",
            "subcategory":"Beauty Salon",
            "type":"Services"
        }
    ],
    "sg:phone":"+1 479 754 2285",
    "sg:postcode":"72830",
    "sg:province":"AR",
    "wof:name":"House Of Cut & Style",
    "wof:placetype":"venue"
},
  "geometry": {"coordinates":[-93.473754,35.478685],"type":"Point"}
}