{
  "type": "Feature",
  "properties": {
    "iso:country":"US",
    "sg:address":"328 Dillard Ave",
    "sg:city":"Forrest City",
    "sg:classifiers":[
        {
            "category":"Farming",
            "subcategory":"Farm",
            "type":"Manufacturing & Wholesale Goods"
        }
    ],
    "sg:phone":"+1 870 633 9291",
    "sg:postcode":"72335",
    "sg:province":"AR",
    "wof:name":"Heritage Farms",
    "wof:placetype":"venue"
},
  "geometry": {"coordinates":[-90.787148,35.011561],"type":"Point"}
}