{
  "type": "Feature",
  "properties": {
    "iso:country":"US",
    "sg:address":"1501 Gary St",
    "sg:city":"Fort Smith",
    "sg:classifiers":[
        {
            "category":"Organizations",
            "subcategory":"Membership Organization",
            "type":"Services"
        }
    ],
    "sg:phone":"+1 479 646 9290",
    "sg:postcode":"72901",
    "sg:province":"AR",
    "wof:name":"Free & Accepted Masonic Lodge",
    "wof:placetype":"venue"
},
  "geometry": {"coordinates":[-94.419453,35.34933],"type":"Point"}
}