{
  "type": "Feature",
  "properties": {
    "iso:country":"US",
    "sg:address":"690 Sfc 718",
    "sg:city":"Forrest City",
    "sg:classifiers":[
        {
            "category":"Retail",
            "subcategory":"Repair Shop",
            "type":"Services"
        }
    ],
    "sg:phone":"+1 870 633 2465",
    "sg:postcode":"72335",
    "sg:province":"AR",
    "sg:tags":[
        "lock",
        "locksmith"
    ],
    "wof:name":"Wayde's Lock Shop",
    "wof:placetype":"venue"
},
  "geometry": {"coordinates":[-90.7619,34.97284],"type":"Point"}
}