{
  "type": "Feature",
  "properties": {
    "addr:full":"4026 Hwy 234 Foreman AR 71836",
    "addr:housenumber":"4026",
    "addr:postcode":"71836",
    "addr:street":"Hwy 234 Foreman",
    "iso:country":"US",
    "sg:address":"4026 Hwy 234",
    "sg:city":"Foreman",
    "sg:classifiers":[
        {
            "category":"Freight",
            "type":"Transportation"
        }
    ],
    "sg:phone":"+1 870 381 7524",
    "sg:postcode":"71836",
    "sg:province":"AR",
    "sg:tags":[
        "operator",
        "local",
        "trucking"
    ],
    "wof:name":"Double J Trucking",
    "wof:placetype":"venue"
},
  "geometry": {"coordinates":[-94.42167000000001,33.83664],"type":"Point"}
}