{
  "type": "Feature",
  "properties": {
    "addr:full":"13215 Wallin Mountain Rd West Fork AR 72774",
    "addr:housenumber":"13215",
    "addr:postcode":"72774",
    "addr:street":"Wallin Mountain Rd",
    "iso:country":"US",
    "sg:address":"13215 Wallin Mountain Rd",
    "sg:city":"West Fork",
    "sg:classifiers":[
        {
            "category":"Manufacturing",
            "subcategory":"Rubber & Plastics",
            "type":"Manufacturing & Wholesale Goods"
        }
    ],
    "sg:phone":"+1 479 839 2726",
    "sg:postcode":"72774",
    "sg:province":"AR",
    "sg:tags":[
        "personal",
        "leather",
        "fixture",
        "plumbing",
        "mfg"
    ],
    "wof:name":"Fannings Cultered Marble Inc",
    "wof:placetype":"venue"
},
  "geometry": {"coordinates":[-94.126515,35.974581],"type":"Point"}
}