{
  "type": "Feature",
  "properties": {
    "addr:full":"314 S Adams Ave Camden AR 71701",
    "addr:housenumber":"314",
    "addr:postcode":"71701",
    "addr:street":"S Adams Ave",
    "iso:country":"US",
    "sg:address":"314 S Adams Ave",
    "sg:city":"Camden",
    "sg:classifiers":[
        {
            "category":"Organizations",
            "subcategory":"Community Association",
            "type":"Services"
        }
    ],
    "sg:phone":"+1 870 836 6426",
    "sg:postcode":"71701",
    "sg:province":"AR",
    "sg:tags":[
        "chamber",
        "commerce"
    ],
    "sg:website":"http://www.growingcamden.com",
    "wof:name":"Chamber Of Cmmerce Camden Area",
    "wof:placetype":"venue"
},
  "geometry": {"coordinates":[-92.82763199999999,33.581173],"type":"Point"}
}