{
  "type": "Feature",
  "properties": {
    "addr:full":"302 E Front St Altheimer AR 72004",
    "addr:housenumber":"302",
    "addr:postcode":"72004",
    "addr:street":"E Front St",
    "iso:country":"US",
    "sg:address":"302 E Front St",
    "sg:city":"Altheimer",
    "sg:classifiers":[
        {
            "category":"Banks & Credit Unions",
            "subcategory":"Bank",
            "type":"Services"
        }
    ],
    "sg:phone":"+1 870 766 8474",
    "sg:postcode":"72004",
    "sg:province":"AR",
    "wof:name":"First National Bank",
    "wof:placetype":"venue"
},
  "geometry": {"coordinates":[-91.84511500000001,34.320702],"type":"Point"}
}