{
  "type": "Feature",
  "properties": {
    "iso:country":"US",
    "sg:address":"1630 S 8th St",
    "sg:city":"Rogers",
    "sg:classifiers":[
        {
            "category":"Professional",
            "subcategory":"Lawyer & Legal Services",
            "type":"Services"
        }
    ],
    "sg:phone":"+1 479 936 8229",
    "sg:postcode":"72756",
    "sg:province":"AR",
    "sg:tags":[
        "naturalization",
        "immigration"
    ],
    "wof:name":"Morales Immigration & Tax",
    "wof:placetype":"venue"
},
  "geometry": {"coordinates":[-94.126316,36.315806],"type":"Point"}
}