{
  "type": "Feature",
  "properties": {
    "addr:full":"801 E Emma Ave Springdale AR 72764",
    "addr:housenumber":"801",
    "addr:postcode":"72764",
    "addr:street":"E Emma Ave",
    "iso:country":"US",
    "sg:address":"801 E Emma Ave",
    "sg:city":"Springdale",
    "sg:classifiers":[
        {
            "category":"Professional",
            "subcategory":"Lawyer & Legal Services",
            "type":"Services"
        }
    ],
    "sg:phone":"+1 479 756 2284",
    "sg:postcode":"72764",
    "sg:province":"AR",
    "sg:tags":[
        "personal",
        "attorney",
        "injury",
        "law"
    ],
    "wof:name":"Huggins & Huggins",
    "wof:placetype":"venue"
},
  "geometry": {"coordinates":[-94.12200199999999,36.184711],"type":"Point"}
}