{
  "type": "Feature",
  "properties": {
    "iso:country":"US",
    "sg:address":"309 Leatherwood Cir",
    "sg:city":"Mountain Home",
    "sg:classifiers":[
        {
            "category":"Real Estate",
            "subcategory":"Real Estate Operator",
            "type":"Services"
        }
    ],
    "sg:phone":"+1 870 425 5008",
    "sg:postcode":"72653",
    "sg:province":"AR",
    "sg:tags":[
        "apartment"
    ],
    "wof:name":"Arrowhead Apartments",
    "wof:placetype":"venue"
},
  "geometry": {"coordinates":[-92.360192,36.342325],"type":"Point"}
}