{
  "type": "Feature",
  "properties": {
    "iso:country":"US",
    "sg:address":"211 2nd St",
    "sg:city":"Green Forest",
    "sg:classifiers":[
        {
            "category":"Professional",
            "subcategory":"Accounting & Tax Preparation",
            "type":"Services"
        }
    ],
    "sg:phone":"+1 870 438 6422",
    "sg:postcode":"72638",
    "sg:province":"AR",
    "sg:tags":[
        "return",
        "filing"
    ],
    "wof:name":"H & R Block Tax Svc",
    "wof:placetype":"venue"
},
  "geometry": {"coordinates":[-93.433798,36.334672],"type":"Point"}
}