{
  "type": "Feature",
  "properties": {
    "addr:full":"1 Grey Rd N Little Rock AR 72117",
    "addr:housenumber":"1",
    "addr:postcode":"72117",
    "addr:street":"Grey Rd N",
    "iso:country":"US",
    "sg:address":"1 Grey Rd",
    "sg:city":"N Little Rock",
    "sg:classifiers":[
        {
            "category":"Travel",
            "subcategory":"Hotels & Motels",
            "type":"Entertainment"
        }
    ],
    "sg:phone":"+1 501 945 0141",
    "sg:postcode":"72117",
    "sg:province":"AR",
    "wof:name":"Super 8 Motel-Airport",
    "wof:placetype":"venue"
},
  "geometry": {"coordinates":[-92.201708,34.777294],"type":"Point"}
}