{
  "type": "Feature",
  "properties": {
    "iso:country":"US",
    "sg:address":"201 W Antigo St",
    "sg:city":"Stamps",
    "sg:classifiers":[
        {
            "category":"Wholesale",
            "subcategory":"Construction Materials",
            "type":"Manufacturing & Wholesale Goods"
        }
    ],
    "sg:phone":"+1 870 533 2990",
    "sg:postcode":"71860",
    "sg:province":"AR",
    "sg:tags":[
        "fence"
    ],
    "wof:name":"Dandy Fence Co",
    "wof:placetype":"venue"
},
  "geometry": {"coordinates":[-93.505367,33.365885],"type":"Point"}
}