{
  "type": "Feature",
  "properties": {
    "iso:country":"US",
    "sg:address":"507 S 18th St",
    "sg:city":"West Memphis",
    "sg:classifiers":[
        {
            "category":"Food & Beverages",
            "subcategory":"Groceries & Convenience Stores",
            "type":"Retail Goods"
        }
    ],
    "sg:phone":"+1 870 735 3910",
    "sg:postcode":"72301",
    "sg:province":"AR",
    "sg:tags":[
        "grocer"
    ],
    "wof:name":"E Z Way Food Market",
    "wof:placetype":"venue"
},
  "geometry": {"coordinates":[-90.162892,35.140425],"type":"Point"}
}