{
  "type": "Feature",
  "properties": {
    "iso:country":"US",
    "sg:address":"1000 US Hwy 71 Bus",
    "sg:city":"Fayetteville",
    "sg:classifiers":[
        {
            "category":"Shopping",
            "subcategory":"Hobbies, Toys, & Games",
            "type":"Retail Goods"
        }
    ],
    "sg:phone":"+1 479 521 5421",
    "sg:postcode":"72701",
    "sg:province":"AR",
    "sg:tags":[
        "store"
    ],
    "wof:name":"Kb Toys",
    "wof:placetype":"venue"
},
  "geometry": {"coordinates":[-94.157094,36.077231],"type":"Point"}
}