{
  "type": "Feature",
  "properties": {
    "iso:country":"US",
    "sg:address":"1004 Falls Blvd N",
    "sg:city":"Wynne",
    "sg:classifiers":[
        {
            "category":"Manufacturing",
            "subcategory":"Tobacco Products",
            "type":"Manufacturing & Wholesale Goods"
        },
        {
            "category":"Shopping",
            "subcategory":"Tobacco",
            "type":"Retail Goods"
        }
    ],
    "sg:phone":"+1 870 238 6363",
    "sg:postcode":"72396",
    "sg:province":"AR",
    "sg:tags":[
        "cigarette",
        "cigar",
        "manufacturer",
        "tobacco-wholesale"
    ],
    "sg:website":"http://www.fcgrocery.com",
    "wof:name":"Tobacco Superstore",
    "wof:placetype":"venue"
},
  "geometry": {"coordinates":[-90.785402,35.230288],"type":"Point"}
}