{
  "type": "Feature",
  "properties": {
    "addr:full":"999 Schneider Dr Malvern AR 72104",
    "addr:housenumber":"999",
    "addr:postcode":"72104",
    "addr:street":"Schneider Dr",
    "iso:country":"US",
    "sg:address":"999 Schneider Dr",
    "sg:city":"Malvern",
    "sg:classifiers":[
        {
            "category":"Shopping",
            "subcategory":"Pharmacy",
            "type":"Retail Goods"
        }
    ],
    "sg:phone":"+1 501 337 9503",
    "sg:postcode":"72104",
    "sg:province":"AR",
    "wof:name":"Phelans Disc Phrm & Med Rentl",
    "wof:placetype":"venue"
},
  "geometry": {"coordinates":[-92.785495,34.360776],"type":"Point"}
}