{
  "type": "Feature",
  "properties": {
    "iso:country":"US",
    "sg:address":"4 Saratoga Ct",
    "sg:city":"North Little Rock",
    "sg:classifiers":[
        {
            "category":"Recreation",
            "type":"Entertainment"
        },
        {
            "category":"Shopping",
            "subcategory":"Bicycles & Sporting Goods",
            "type":"Retail Goods"
        }
    ],
    "sg:phone":"+1 501 834 2509",
    "sg:postcode":"72116",
    "sg:province":"AR",
    "sg:tags":[
        "parachute",
        "transportation"
    ],
    "wof:name":"Central Arkansas Parachute Ctr",
    "wof:placetype":"venue"
},
  "geometry": {"coordinates":[-92.244282,34.821418],"type":"Point"}
}