{
  "type": "Feature",
  "properties": {
    "iso:country":"US",
    "sg:address":"7310 US Hwy 271",
    "sg:city":"Fort Smith",
    "sg:classifiers":[
        {
            "category":"Building & Trades",
            "subcategory":"Pest Control",
            "type":"Services"
        }
    ],
    "sg:phone":"+1 479 783 1822",
    "sg:postcode":"72908",
    "sg:province":"AR",
    "wof:name":"Extermco Termite & Pest Cntrl",
    "wof:placetype":"venue"
},
  "geometry": {"coordinates":[-94.423432,35.315831],"type":"Point"}
}