{
  "type": "Feature",
  "properties": {
    "addr:full":"531 Porter St Helena AR 72342",
    "addr:housenumber":"531",
    "addr:postcode":"72342",
    "addr:street":"Porter St",
    "iso:country":"US",
    "sg:address":"531 Porter St",
    "sg:city":"Helena",
    "sg:classifiers":[
        {
            "category":"Retail",
            "subcategory":"Repair Shop",
            "type":"Services"
        }
    ],
    "sg:phone":"+1 870 338 7375",
    "sg:postcode":"72342",
    "sg:province":"AR",
    "sg:tags":[
        "upholsterer"
    ],
    "wof:name":"Odessa Nealy Upholstery Shop",
    "wof:placetype":"venue"
},
  "geometry": {"coordinates":[-90.588903,34.527991],"type":"Point"}
}