{
  "type": "Feature",
  "properties": {
    "addr:full":"309 Main St Lake Village AR 71653",
    "addr:housenumber":"309",
    "addr:postcode":"71653",
    "addr:street":"Main St",
    "iso:country":"US",
    "sg:address":"309 Main St",
    "sg:city":"Lake Village",
    "sg:classifiers":[
        {
            "category":"Retail",
            "subcategory":"Laundry & Dry Cleaning",
            "type":"Services"
        }
    ],
    "sg:phone":"+1 870 265 2899",
    "sg:postcode":"71653",
    "sg:province":"AR",
    "sg:tags":[
        "drycleaning",
        "plant"
    ],
    "wof:name":"First Choice Cleaners",
    "wof:placetype":"venue"
},
  "geometry": {"coordinates":[-91.283993,33.331316],"type":"Point"}
}