{
  "type": "Feature",
  "properties": {
    "iso:country":"US",
    "sg:address":"2405 Military Rd",
    "sg:city":"Jacksonville",
    "sg:classifiers":[
        {
            "category":"Building & Trades",
            "subcategory":"Construction",
            "type":"Services"
        }
    ],
    "sg:phone":"+1 501 457 5451",
    "sg:postcode":"72076",
    "sg:province":"AR",
    "sg:tags":[
        "general",
        "contractor"
    ],
    "wof:name":"Affordable Construction",
    "wof:placetype":"venue"
},
  "geometry": {"coordinates":[-92.091734,34.852136],"type":"Point"}
}