{
  "type": "Feature",
  "properties": {
    "iso:country":"US",
    "sg:address":"245 Hobson Ave",
    "sg:city":"Hot Springs National Park",
    "sg:classifiers":[
        {
            "category":"Insurance",
            "subcategory":"Insurance Agent",
            "type":"Services"
        }
    ],
    "sg:phone":"+1 501 321 0457",
    "sg:postcode":"71913",
    "sg:province":"AR",
    "wof:name":"Professional Beneft Fincl Svc",
    "wof:placetype":"venue"
},
  "geometry": {"coordinates":[-93.059185,34.497412],"type":"Point"}
}