{
  "type": "Feature",
  "properties": {
    "iso:country":"US",
    "sg:address":"2190 N Central Ave",
    "sg:city":"Batesville",
    "sg:classifiers":[
        {
            "category":"Autos & Motor Vehicles",
            "subcategory":"Motorcycle Sales",
            "type":"Retail Goods"
        }
    ],
    "sg:phone":"+1 870 793 3506",
    "sg:postcode":"72501",
    "sg:province":"AR",
    "sg:tags":[
        "stove",
        "wood"
    ],
    "wof:name":"Arnold Cycles",
    "wof:placetype":"venue"
},
  "geometry": {"coordinates":[-91.661506,35.785089],"type":"Point"}
}