{
  "type": "Feature",
  "properties": {
    "iso:country":"US",
    "sg:address":"412 State Hwy 23",
    "sg:city":"Pompton Lakes",
    "sg:classifiers":[
        {
            "category":"Personal",
            "subcategory":"Beauty Salon",
            "type":"Services"
        }
    ],
    "sg:phone":"+1 973 831 4556",
    "sg:postcode":"72927",
    "sg:province":"AR",
    "wof:name":"Hair & Us Inc",
    "wof:placetype":"venue"
},
  "geometry": {"coordinates":[-93.921641,35.141651],"type":"Point"}
}