{
  "type": "Feature",
  "properties": {
    "iso:country":"US",
    "sg:address":"3531 Polk Road 54",
    "sg:city":"Mena",
    "sg:classifiers":[
        {
            "category":"Banks & Credit Unions",
            "subcategory":"Financial Services",
            "type":"Services"
        }
    ],
    "sg:phone":"+1 479 243 0473",
    "sg:postcode":"71953",
    "sg:province":"AR",
    "sg:tags":[
        "trust",
        "management"
    ],
    "wof:name":"Johnson Richard G & Trudy A Tr",
    "wof:placetype":"venue"
},
  "geometry": {"coordinates":[-94.170715,34.551362],"type":"Point"}
}