{
  "type": "Feature",
  "properties": {
    "iso:country":"US",
    "sg:address":"18705 Farm Hill Rd",
    "sg:city":"Harrisburg",
    "sg:classifiers":[
        {
            "category":"Retail",
            "subcategory":"Repair Shop",
            "type":"Services"
        }
    ],
    "sg:phone":"+1 870 578 2277",
    "sg:postcode":"72432",
    "sg:province":"AR",
    "wof:name":"Drakes Speedo & Tach",
    "wof:placetype":"venue"
},
  "geometry": {"coordinates":[-90.701761,35.49207],"type":"Point"}
}