{
  "type": "Feature",
  "properties": {
    "addr:full":"22816 State Rte 7 N Dover AR 72837",
    "addr:housenumber":"22816",
    "addr:postcode":"72837",
    "addr:street":"State Rte 7 N",
    "iso:country":"US",
    "sg:address":"22816 State Rte 7 N",
    "sg:city":"Dover",
    "sg:classifiers":[
        {
            "category":"Food & Beverages",
            "subcategory":"Groceries & Convenience Stores",
            "type":"Retail Goods"
        },
        {
            "category":"Travel",
            "subcategory":"Hotels & Motels",
            "type":"Entertainment"
        }
    ],
    "sg:phone":"+1 479 331 3261",
    "sg:postcode":"72837",
    "sg:province":"AR",
    "sg:tags":[
        "rental",
        "eating",
        "trailer",
        "utility"
    ],
    "wof:name":"Mack's Pines",
    "wof:placetype":"venue"
},
  "geometry": {"coordinates":[-93.09014000000001,35.548874],"type":"Point"}
}