{
  "type": "Feature",
  "properties": {
    "iso:country":"US",
    "sg:address":"715 W Broadway",
    "sg:city":"Spiro",
    "sg:classifiers":[
        {
            "category":"Social Services",
            "subcategory":"Child Care",
            "type":"Services"
        }
    ],
    "sg:phone":"+1 918 962 2823",
    "sg:postcode":"74959",
    "sg:province":"OK",
    "sg:tags":[
        "day"
    ],
    "wof:name":"Little Hearts Day Care Center",
    "wof:placetype":"venue"
},
  "geometry": {"coordinates":[-94.62763699999999,35.241148],"type":"Point"}
}