{
  "type": "Feature",
  "properties": {
    "iso:country":"US",
    "sg:address":"12 Mishemokwa Dr",
    "sg:city":"Cherokee Village",
    "sg:classifiers":[
        {
            "category":"Freight",
            "type":"Transportation"
        }
    ],
    "sg:phone":"+1 870 257 4901",
    "sg:postcode":"72529",
    "sg:province":"AR",
    "sg:tags":[
        "trucking"
    ],
    "wof:name":"L M Transport",
    "wof:placetype":"venue"
},
  "geometry": {"coordinates":[-91.592325,36.292122],"type":"Point"}
}