{
  "type": "Feature",
  "properties": {
    "iso:country":"US",
    "sg:address":"713 Stony Ridge Rd",
    "sg:city":"Heber Springs",
    "sg:classifiers":[
        {
            "category":"Recreation",
            "type":"Entertainment"
        }
    ],
    "sg:phone":"+1 501 362 7943",
    "sg:postcode":"72543",
    "sg:province":"AR",
    "sg:tags":[
        "club",
        "membership"
    ],
    "wof:name":"Gfwac Medley Club Inc",
    "wof:placetype":"venue"
},
  "geometry": {"coordinates":[-92.10796499999999,35.505268],"type":"Point"}
}