{
  "type": "Feature",
  "properties": {
    "addr:full":"5700 W 10th St Little Rock AR 72204",
    "addr:housenumber":"5700",
    "addr:postcode":"72204",
    "addr:street":"W 10Th St",
    "iso:country":"US",
    "sg:address":"5700 W 10th St",
    "sg:city":"Little Rock",
    "sg:classifiers":[
        {
            "category":"Freight",
            "type":"Transportation"
        }
    ],
    "sg:phone":"+1 501 664 6000",
    "sg:postcode":"72204",
    "sg:province":"AR",
    "sg:tags":[
        "commercial",
        "storage"
    ],
    "wof:name":"A A Storage",
    "wof:placetype":"venue"
},
  "geometry": {"coordinates":[-92.335967,34.743083],"type":"Point"}
}