{
  "type": "Feature",
  "properties": {
    "iso:country":"US",
    "sg:address":"8762 E Wagon Wheel Rd",
    "sg:city":"Springdale",
    "sg:classifiers":[
        {
            "category":"Organizations",
            "subcategory":"Religious Organization",
            "type":"Services"
        }
    ],
    "sg:phone":"+1 479 751 6775",
    "sg:postcode":"72762",
    "sg:province":"AR",
    "wof:name":"Spring Creek Baptist Church",
    "wof:placetype":"venue"
},
  "geometry": {"coordinates":[-94.192239,36.226611],"type":"Point"}
}