{
  "type": "Feature",
  "properties": {
    "iso:country":"US",
    "sg:address":"455 Hogan Ln",
    "sg:city":"Conway",
    "sg:classifiers":[
        {
            "category":"Health Services",
            "subcategory":"Doctor",
            "type":"Services"
        },
        {
            "category":"Health Services",
            "subcategory":"Clinic",
            "type":"Services"
        },
        {
            "category":"Community Center",
            "type":"Public Place"
        }
    ],
    "sg:phone":"+1 501 513 0799",
    "sg:postcode":"72034",
    "sg:province":"AR",
    "sg:tags":[
        "physician",
        "stomach",
        "gastroenterology",
        "medical",
        "surgeons",
        "intestines"
    ],
    "wof:name":"Conway Endoscopy Ctr",
    "wof:placetype":"venue"
},
  "geometry": {"coordinates":[-92.498093,35.085318],"type":"Point"}
}