{
  "type": "Feature",
  "properties": {
    "iso:country":"US",
    "sg:address":"1722 N College Ave",
    "sg:city":"Fayetteville",
    "sg:classifiers":[
        {
            "category":"Wholesale",
            "subcategory":"Durable Goods & Equipment",
            "type":"Manufacturing & Wholesale Goods"
        }
    ],
    "sg:phone":"+1 479 521 4999",
    "sg:postcode":"72703",
    "sg:province":"AR",
    "sg:tags":[
        "merchant",
        "to",
        "distribution",
        "mass"
    ],
    "wof:name":"Hannover House",
    "wof:placetype":"venue"
},
  "geometry": {"coordinates":[-94.155214,36.085409],"type":"Point"}
}