{
  "type": "Feature",
  "properties": {
    "addr:full":"501 S 1st St Jacksonville AR 72076",
    "addr:housenumber":"501",
    "addr:postcode":"72076",
    "addr:street":"S 1St St",
    "iso:country":"US",
    "sg:address":"501 S 1st St",
    "sg:city":"Jacksonville",
    "sg:classifiers":[
        {
            "category":"Social Services",
            "subcategory":"Child Care",
            "type":"Services"
        }
    ],
    "sg:phone":"+1 501 982 0878",
    "sg:postcode":"72076",
    "sg:province":"AR",
    "wof:name":"Quality Child Care Inc",
    "wof:placetype":"venue"
},
  "geometry": {"coordinates":[-92.116984,34.861672],"type":"Point"}
}