{
  "type": "Feature",
  "properties": {
    "iso:country":"US",
    "sg:address":"380 W 24th St",
    "sg:city":"Fayetteville",
    "sg:classifiers":[
        {
            "category":"Autos & Motor Vehicles",
            "subcategory":"Auto Supplies",
            "type":"Retail Goods"
        }
    ],
    "sg:phone":"+1 479 695 1366",
    "sg:postcode":"72701",
    "sg:province":"AR",
    "sg:tags":[
        "automobile",
        "parts"
    ],
    "wof:name":"Freenergy Group",
    "wof:placetype":"venue"
},
  "geometry": {"coordinates":[-94.167726,36.037426],"type":"Point"}
}