{
  "type": "Feature",
  "properties": {
    "iso:country":"US",
    "sg:address":"3810 Hwy 167",
    "sg:city":"Ash Flat",
    "sg:classifiers":[
        {
            "category":"Retail",
            "subcategory":"Veterinary Services",
            "type":"Services"
        }
    ],
    "sg:phone":"+1 870 994 2733",
    "sg:postcode":"72513",
    "sg:province":"AR",
    "wof:name":"Moodys Tri Cnty Veterinary Svc",
    "wof:placetype":"venue"
},
  "geometry": {"coordinates":[-91.620687,36.189572],"type":"Point"}
}