{
  "type": "Feature",
  "properties": {
    "iso:country":"US",
    "sg:address":"5704 State Hwy 7",
    "sg:city":"Harrison",
    "sg:classifiers":[
        {
            "category":"Farming",
            "subcategory":"Livestock Farm",
            "type":"Manufacturing & Wholesale Goods"
        }
    ],
    "sg:phone":"+1 870 741 3082",
    "sg:postcode":"72601",
    "sg:province":"AR",
    "sg:tags":[
        "beef",
        "feedlot",
        "cattle"
    ],
    "wof:name":"Carr Farms Company",
    "wof:placetype":"venue"
},
  "geometry": {"coordinates":[-93.12341499999999,36.181824],"type":"Point"}
}