{
  "type": "Feature",
  "properties": {
    "iso:country":"US",
    "sg:address":"110 S Allis St",
    "sg:city":"England",
    "sg:classifiers":[
        {
            "category":"Personal",
            "subcategory":"Barber",
            "type":"Services"
        }
    ],
    "sg:phone":"+1 501 842 1999",
    "sg:postcode":"72046",
    "sg:province":"AR",
    "sg:tags":[
        "shop"
    ],
    "wof:name":"Whole Armor Dsngs II Beauty Ba",
    "wof:placetype":"venue"
},
  "geometry": {"coordinates":[-91.970588,34.544527],"type":"Point"}
}