{
  "type": "Feature",
  "properties": {
    "addr:full":"1702 Weeks Ln Fort Smith AR 72903",
    "addr:housenumber":"1702",
    "addr:postcode":"72903",
    "addr:street":"Weeks Ln",
    "iso:country":"US",
    "sg:address":"1702 Weeks Ln",
    "sg:city":"Fort Smith",
    "sg:classifiers":[
        {
            "category":"Professional",
            "subcategory":"Lawyer & Legal Services",
            "type":"Services"
        }
    ],
    "sg:phone":"+1 479 452 0154",
    "sg:postcode":"72903",
    "sg:province":"AR",
    "sg:tags":[
        "attorney"
    ],
    "wof:name":"David T Westmoreland",
    "wof:placetype":"venue"
},
  "geometry": {"coordinates":[-94.361963,35.364976],"type":"Point"}
}