{
  "type": "Feature",
  "properties": {
    "iso:country":"US",
    "sg:address":"3420 Kerr Station Rd",
    "sg:city":"Cabot",
    "sg:classifiers":[
        {
            "category":"Manufacturing",
            "subcategory":"Building Materials",
            "type":"Manufacturing & Wholesale Goods"
        }
    ],
    "sg:phone":"+1 501 941 4483",
    "sg:postcode":"72023",
    "sg:province":"AR",
    "sg:tags":[
        "member",
        "mfg",
        "wood",
        "structural"
    ],
    "wof:name":"Cabot Truss",
    "wof:placetype":"venue"
},
  "geometry": {"coordinates":[-92.02070999999999,34.932451],"type":"Point"}
}