{
  "type": "Feature",
  "properties": {
    "addr:full":"195 Co Rd 121 Bono AR 72416",
    "addr:housenumber":"195",
    "addr:postcode":"72416",
    "addr:street":"Co Rd 121",
    "iso:country":"US",
    "sg:address":"195 Co Rd 121",
    "sg:city":"Bono",
    "sg:classifiers":[
        {
            "category":"Professional",
            "subcategory":"Management & Consulting",
            "type":"Services"
        }
    ],
    "sg:phone":"+1 870 933 0090",
    "sg:postcode":"72416",
    "sg:province":"AR",
    "wof:name":"Xat Consulting Inc",
    "wof:placetype":"venue"
},
  "geometry": {"coordinates":[-90.792672,35.883997],"type":"Point"}
}