{
  "type": "Feature",
  "properties": {
    "iso:country":"US",
    "sg:address":"7500 Jenny Lind Rd",
    "sg:city":"Fort Smith",
    "sg:classifiers":[
        {
            "category":"Real Estate",
            "subcategory":"Real Estate Operator",
            "type":"Services"
        }
    ],
    "sg:phone":"+1 479 649 8400",
    "sg:postcode":"72908",
    "sg:province":"AR",
    "sg:tags":[
        "building",
        "apartment"
    ],
    "wof:name":"Chapelridge Apartments",
    "wof:placetype":"venue"
},
  "geometry": {"coordinates":[-94.413646,35.321481],"type":"Point"}
}