{
  "type": "Feature",
  "properties": {
    "addr:full":"1757 N Crossover Rd Fayetteville AR 72701",
    "addr:housenumber":"1757",
    "addr:postcode":"72701",
    "addr:street":"N Crossover Rd",
    "iso:country":"US",
    "sg:address":"1757 N Crossover Rd",
    "sg:city":"Fayetteville",
    "sg:classifiers":[
        {
            "category":"Manufacturing",
            "subcategory":"Metals",
            "type":"Manufacturing & Wholesale Goods"
        }
    ],
    "sg:phone":"+1 479 521 5887",
    "sg:postcode":"72701",
    "sg:province":"AR",
    "sg:tags":[
        "steel",
        "distributor",
        "warehouse",
        "erectors",
        "mill"
    ],
    "wof:name":"Elite Steel Erectors Inc",
    "wof:placetype":"venue"
},
  "geometry": {"coordinates":[-94.121391,36.083934],"type":"Point"}
}