{
  "type": "Feature",
  "properties": {
    "iso:country":"US",
    "sg:address":"136 Hoagland Rd",
    "sg:city":"Donaldson",
    "sg:classifiers":[
        {
            "category":"Professional",
            "type":"Services"
        }
    ],
    "sg:phone":"+1 501 384 2788",
    "sg:postcode":"71941",
    "sg:province":"AR",
    "wof:name":"Grant Davis",
    "wof:placetype":"venue"
},
  "geometry": {"coordinates":[-92.97153900000001,34.253679],"type":"Point"}
}