{
  "type": "Feature",
  "properties": {
    "iso:country":"US",
    "sg:address":"230 Ouachita Ave",
    "sg:city":"Hot Springs National",
    "sg:classifiers":[
        {
            "category":"Bars & Pubs",
            "type":"Food & Drink"
        }
    ],
    "sg:phone":"+1 501 624 6686",
    "sg:postcode":"71901",
    "sg:province":"AR",
    "sg:tags":[
        "drinking"
    ],
    "wof:name":"Confettis",
    "wof:placetype":"venue"
},
  "geometry": {"coordinates":[-93.055468,34.507726],"type":"Point"}
}