{
  "type": "Feature",
  "properties": {
    "iso:country":"US",
    "sg:address":"119 N Market St",
    "sg:city":"Benton",
    "sg:classifiers":[
        {
            "category":"Shopping",
            "type":"Retail Goods"
        }
    ],
    "sg:phone":"+1 501 315 4830",
    "sg:postcode":"72015",
    "sg:province":"AR",
    "sg:tags":[
        "cosmetic",
        "perfume"
    ],
    "sg:website":"www.merlenorman.com",
    "wof:name":"Merle Norman Cosmetics",
    "wof:placetype":"venue"
},
  "geometry": {"coordinates":[-92.58817000000001,34.56436],"type":"Point"}
}