{
  "type": "Feature",
  "properties": {
    "iso:country":"US",
    "sg:address":"1306 W 4th St",
    "sg:city":"Little Rock",
    "sg:classifiers":[
        {
            "category":"Organizations",
            "subcategory":"Non-profit Organization",
            "type":"Services"
        }
    ],
    "sg:phone":"+1 501 375 2358",
    "sg:postcode":"72201",
    "sg:province":"AR",
    "sg:website":"www.aref.org",
    "wof:name":"Arkansas Rural Endowment Fund",
    "wof:placetype":"venue"
},
  "geometry": {"coordinates":[-92.28627899999999,34.747334],"type":"Point"}
}