{
  "type": "Feature",
  "properties": {
    "iso:country":"US",
    "sg:address":"2719 E Nettleton Ave",
    "sg:city":"Jonesboro",
    "sg:classifiers":[
        {
            "category":"Organizations",
            "subcategory":"Community Association",
            "type":"Services"
        }
    ],
    "sg:phone":"+1 870 932 6784",
    "sg:postcode":"72401",
    "sg:province":"AR",
    "wof:name":"Jonesboro Softball Association",
    "wof:placetype":"venue"
},
  "geometry": {"coordinates":[-90.67231099999999,35.828304],"type":"Point"}
}