{
  "type": "Feature",
  "properties": {
    "addr:full":"7830 US Hwy 70 N Little Rock AR 72117",
    "addr:housenumber":"7830",
    "addr:postcode":"72117",
    "addr:street":"Us Hwy 70 N",
    "iso:country":"US",
    "sg:address":"7830 US Hwy 70",
    "sg:city":"N Little Rock",
    "sg:classifiers":[
        {
            "category":"Autos & Motor Vehicles",
            "subcategory":"Automobile Sales",
            "type":"Retail Goods"
        }
    ],
    "sg:phone":"+1 501 945 7618",
    "sg:postcode":"72117",
    "sg:province":"AR",
    "sg:tags":[
        "car",
        "used",
        "dealer"
    ],
    "wof:name":"K & B Trucks & Cars",
    "wof:placetype":"venue"
},
  "geometry": {"coordinates":[-92.173894,34.769243],"type":"Point"}
}