{
  "type": "Feature",
  "properties": {
    "iso:country":"US",
    "sg:address":"426 Holden Ave",
    "sg:city":"Booneville",
    "sg:classifiers":[
        {
            "category":"Social Services",
            "type":"Services"
        }
    ],
    "sg:phone":"+1 479 675 3883",
    "sg:postcode":"72927",
    "sg:province":"AR",
    "sg:tags":[
        "organization",
        "welfare"
    ],
    "wof:name":"Arvac Inc",
    "wof:placetype":"venue"
},
  "geometry": {"coordinates":[-93.916568,35.14126],"type":"Point"}
}