{
  "type": "Feature",
  "properties": {
    "iso:country":"US",
    "sg:address":"423 Co Rd 136",
    "sg:city":"Holiday Island",
    "sg:classifiers":[
        {
            "category":"Travel",
            "subcategory":"Hotels & Motels",
            "type":"Entertainment"
        }
    ],
    "sg:phone":"+1 479 253 2018",
    "sg:postcode":"72631",
    "sg:province":"AR",
    "sg:tags":[
        "chalet",
        "rental",
        "cabin"
    ],
    "wof:name":"Ozark Cabins",
    "wof:placetype":"venue"
},
  "geometry": {"coordinates":[-93.840199,36.438182],"type":"Point"}
}