{
  "type": "Feature",
  "properties": {
    "iso:country":"US",
    "sg:address":"1217 Stone St",
    "sg:city":"Jonesboro",
    "sg:classifiers":[
        {
            "category":"Freight",
            "type":"Transportation"
        }
    ],
    "sg:phone":"+1 870 932 3998",
    "sg:postcode":"72404",
    "sg:province":"AR",
    "sg:tags":[
        "operator",
        "arrangement",
        "trucking"
    ],
    "wof:name":"Twin Oaks Logistics",
    "wof:placetype":"venue"
},
  "geometry": {"coordinates":[-90.67577199999999,35.83104],"type":"Point"}
}