{
  "type": "Feature",
  "properties": {
    "addr:full":"3900 Petro Rd West Memphis AR 72301",
    "addr:housenumber":"3900",
    "addr:postcode":"72301",
    "addr:street":"Petro Rd",
    "iso:country":"US",
    "sg:address":"3900 Petro Rd",
    "sg:city":"West Memphis",
    "sg:classifiers":[
        {
            "category":"Food & Beverages",
            "subcategory":"Specialty",
            "type":"Retail Goods"
        }
    ],
    "sg:phone":"+1 870 702 7177",
    "sg:postcode":"72301",
    "sg:province":"AR",
    "wof:name":"Truckers Choice Nutritional",
    "wof:placetype":"venue"
},
  "geometry": {"coordinates":[-90.136984,35.153584],"type":"Point"}
}