{
  "type": "Feature",
  "properties": {
    "iso:country":"US",
    "sg:address":"6 Chalk Rd",
    "sg:city":"Rose Bud",
    "sg:classifiers":[
        {
            "category":"Farming",
            "subcategory":"Dairy Farm",
            "type":"Manufacturing & Wholesale Goods"
        }
    ],
    "sg:phone":"+1 501 556 3007",
    "sg:postcode":"72137",
    "sg:province":"AR",
    "wof:name":"Heartland Dairy & Produce Farm",
    "wof:placetype":"venue"
},
  "geometry": {"coordinates":[-92.036891,35.389955],"type":"Point"}
}