{
  "type": "Feature",
  "properties": {
    "iso:country":"US",
    "sg:address":"315 Cornerstone Blvd",
    "sg:city":"Hot Springs",
    "sg:classifiers":[
        {
            "category":"Shopping",
            "type":"Retail Goods"
        }
    ],
    "sg:phone":"+1 501 520 5618",
    "sg:postcode":"71913",
    "sg:province":"AR",
    "sg:tags":[
        "pet",
        "shop"
    ],
    "wof:name":"PETCO",
    "wof:placetype":"venue"
},
  "geometry": {"coordinates":[-93.06023500000001,34.460807],"type":"Point"}
}