{
  "type": "Feature",
  "properties": {
    "iso:country":"US",
    "sg:address":"207 N Ok St",
    "sg:city":"West Memphis",
    "sg:classifiers":[
        {
            "category":"Professional",
            "subcategory":"Testing Lab",
            "type":"Services"
        }
    ],
    "sg:phone":"+1 870 702 1097",
    "sg:postcode":"72301",
    "sg:province":"AR",
    "sg:tags":[
        "laboratory"
    ],
    "wof:name":"Ntertek Caleb Brett USA Inc",
    "wof:placetype":"venue"
},
  "geometry": {"coordinates":[-90.144685,35.148872],"type":"Point"}
}