{
  "type": "Feature",
  "properties": {
    "addr:full":"20825 Gem Rd Lincoln AR 72744",
    "addr:housenumber":"20825",
    "addr:postcode":"72744",
    "addr:street":"Gem Rd",
    "iso:country":"US",
    "sg:address":"20825 Gem Rd",
    "sg:city":"Lincoln",
    "sg:classifiers":[
        {
            "category":"Recreation",
            "type":"Entertainment"
        }
    ],
    "sg:phone":"+1 479 824 5027",
    "sg:postcode":"72744",
    "sg:province":"AR",
    "sg:tags":[
        "paint",
        "ball",
        "sport"
    ],
    "wof:name":"Stone Ridge Paint Ball",
    "wof:placetype":"venue"
},
  "geometry": {"coordinates":[-94.447631,36.003201],"type":"Point"}
}