{
  "type": "Feature",
  "properties": {
    "iso:country":"US",
    "sg:address":"1101 W Front St",
    "sg:city":"Heber Springs",
    "sg:classifiers":[
        {
            "category":"Utilities",
            "subcategory":"Water",
            "type":"Services"
        }
    ],
    "sg:phone":"+1 501 362 3422",
    "sg:postcode":"72543",
    "sg:province":"AR",
    "sg:tags":[
        "company",
        "sewage"
    ],
    "wof:name":"City Water Works",
    "wof:placetype":"venue"
},
  "geometry": {"coordinates":[-92.040935,35.499247],"type":"Point"}
}