{
  "type": "Feature",
  "properties": {
    "iso:country":"US",
    "sg:address":"1415 Cole St",
    "sg:city":"Jonesboro",
    "sg:classifiers":[
        {
            "category":"Utilities",
            "subcategory":"Mobile Phone",
            "type":"Services"
        }
    ],
    "sg:phone":"+1 870 932 5633",
    "sg:postcode":"72401",
    "sg:province":"AR",
    "sg:tags":[
        "telephone",
        "cellular"
    ],
    "wof:name":"Haven Communications",
    "wof:placetype":"venue"
},
  "geometry": {"coordinates":[-90.712414,35.828462],"type":"Point"}
}