{
  "type": "Feature",
  "properties": {
    "iso:country":"US",
    "sg:address":"24 Capitol Mall",
    "sg:city":"Little Rock",
    "sg:classifiers":[
        {
            "category":"Professional",
            "subcategory":"Management & Consulting",
            "type":"Services"
        }
    ],
    "sg:phone":"+1 501 244 9600",
    "sg:postcode":"72201",
    "sg:province":"AR",
    "sg:tags":[
        "counselor",
        "public",
        "relations"
    ],
    "wof:name":"Impact Management Group Inc",
    "wof:placetype":"venue"
},
  "geometry": {"coordinates":[-92.292033,34.746655],"type":"Point"}
}