{
  "type": "Feature",
  "properties": {
    "iso:country":"US",
    "sg:address":"61290 E 315 Rd",
    "sg:city":"Grove",
    "sg:classifiers":[
        {
            "category":"Organizations",
            "subcategory":"Religious Organization",
            "type":"Services"
        }
    ],
    "sg:phone":"+1 918 786 2127",
    "sg:postcode":"74344",
    "sg:province":"OK",
    "sg:tags":[
        "church"
    ],
    "wof:name":"Independent Assembly House",
    "wof:placetype":"venue"
},
  "geometry": {"coordinates":[-94.78584499999999,36.561198],"type":"Point"}
}