{
  "type": "Feature",
  "properties": {
    "iso:country":"US",
    "sg:address":"10319 Hwy 79 W",
    "sg:city":"Moro",
    "sg:classifiers":[
        {
            "category":"Farming",
            "subcategory":"Farm",
            "type":"Manufacturing & Wholesale Goods"
        }
    ],
    "sg:phone":"+1 870 768 4846",
    "sg:postcode":"72368",
    "sg:province":"AR",
    "sg:tags":[
        "crop",
        "general"
    ],
    "wof:name":"South Side Farms Inc",
    "wof:placetype":"venue"
},
  "geometry": {"coordinates":[-90.954137,34.775371],"type":"Point"}
}