{
  "type": "Feature",
  "properties": {
    "iso:country":"US",
    "sg:address":"515 N 6th St",
    "sg:city":"Fort Smith",
    "sg:classifiers":[
        {
            "category":"Insurance",
            "subcategory":"Insurance Agent",
            "type":"Services"
        }
    ],
    "sg:phone":"+1 479 452 8351",
    "sg:postcode":"72901",
    "sg:province":"AR",
    "wof:name":"United American Insurance Co",
    "wof:placetype":"venue"
},
  "geometry": {"coordinates":[-94.42095,35.391784],"type":"Point"}
}