{
  "type": "Feature",
  "properties": {
    "iso:country":"US",
    "sg:address":"602 S University Ave",
    "sg:city":"Little Rock",
    "sg:classifiers":[
        {
            "category":"Retail",
            "subcategory":"Auto Repair",
            "type":"Services"
        }
    ],
    "sg:phone":"+1 501 660 6228",
    "sg:postcode":"72205",
    "sg:province":"AR",
    "sg:tags":[
        "repairing",
        "automobile"
    ],
    "wof:name":"Sears Auto & Tire Ctr",
    "wof:placetype":"venue"
},
  "geometry": {"coordinates":[-92.34138,34.746434],"type":"Point"}
}