{
  "type": "Feature",
  "properties": {
    "iso:country":"US",
    "sg:address":"1122 Malcolm Ave",
    "sg:city":"Newport",
    "sg:classifiers":[
        {
            "category":"Health Services",
            "subcategory":"Doctor",
            "type":"Services"
        },
        {
            "category":"Personal",
            "subcategory":"Massage",
            "type":"Services"
        },
        {
            "category":"Health Services",
            "subcategory":"Clinic",
            "type":"Services"
        },
        {
            "category":"Health Services",
            "subcategory":"Health Practitioner",
            "type":"Services"
        },
        {
            "category":"Health Services",
            "subcategory":"Chiropractor",
            "type":"Services"
        }
    ],
    "sg:phone":"+1 870 523 2225",
    "sg:postcode":"72112",
    "sg:province":"AR",
    "sg:tags":[
        "physician",
        "chiropractic",
        "medical",
        "therapist",
        "therapy",
        "acupuncture",
        "surgeon",
        "physical"
    ],
    "sg:website":"http://www.drwhybrew.com",
    "wof:name":"Chiropractic Health Center PA",
    "wof:placetype":"venue"
},
  "geometry": {"coordinates":[-91.266642,35.60625],"type":"Point"}
}