{
  "type": "Feature",
  "properties": {
    "addr:full":"164 Sandy Ford Rd Beebe AR 72012",
    "addr:housenumber":"164",
    "addr:postcode":"72012",
    "addr:street":"Sandy Ford Rd",
    "iso:country":"US",
    "sg:address":"164 Sandy Ford Rd",
    "sg:city":"Beebe",
    "sg:classifiers":[
        {
            "category":"Professional",
            "type":"Services"
        }
    ],
    "sg:phone":"+1 501 882 7489",
    "sg:postcode":"72012",
    "sg:province":"AR",
    "sg:tags":[
        "establishment"
    ],
    "wof:name":"IMS",
    "wof:placetype":"venue"
},
  "geometry": {"coordinates":[-91.927205,35.137848],"type":"Point"}
}