{
  "type": "Feature",
  "properties": {
    "iso:country":"US",
    "sg:address":"614 Ashley Road 249",
    "sg:city":"Crossett",
    "sg:classifiers":[
        {
            "category":"Bus Charters",
            "type":"Transportation"
        }
    ],
    "sg:phone":"+1 870 304 3301",
    "sg:postcode":"71635",
    "sg:province":"AR",
    "sg:tags":[
        "rental"
    ],
    "wof:name":"Ark-LA Charter & Travel Inc",
    "wof:placetype":"venue"
},
  "geometry": {"coordinates":[-91.955692,33.083092],"type":"Point"}
}