{
  "type": "Feature",
  "properties": {
    "iso:country":"US",
    "sg:address":"1519 West Rd",
    "sg:city":"Mountain Home",
    "sg:classifiers":[
        {
            "category":"Shopping",
            "subcategory":"Clothing, Apparel, & Fashions",
            "type":"Retail Goods"
        }
    ],
    "sg:phone":"+1 870 425 6149",
    "sg:postcode":"72653",
    "sg:province":"AR",
    "wof:name":"P JS Bridal Fashions & Design",
    "wof:placetype":"venue"
},
  "geometry": {"coordinates":[-92.42374100000001,36.33638],"type":"Point"}
}