{
  "type": "Feature",
  "properties": {
    "addr:full":"501 E Rush Ave Harrison AR 72601",
    "addr:housenumber":"501",
    "addr:postcode":"72601",
    "addr:street":"E Rush Ave",
    "iso:country":"US",
    "sg:address":"501 E Rush Ave",
    "sg:city":"Harrison",
    "sg:classifiers":[
        {
            "category":"Social Services",
            "type":"Services"
        }
    ],
    "sg:phone":"+1 870 741 1377",
    "sg:postcode":"72601",
    "sg:province":"AR",
    "wof:name":"Senior Center Club Inc",
    "wof:placetype":"venue"
},
  "geometry": {"coordinates":[-93.100234,36.23061],"type":"Point"}
}