{
  "type": "Feature",
  "properties": {
    "iso:country":"US",
    "sg:address":"792 Hwy 258",
    "sg:city":"Bald Knob",
    "sg:classifiers":[
        {
            "category":"Autos & Motor Vehicles",
            "subcategory":"Auto Supplies",
            "type":"Retail Goods"
        }
    ],
    "sg:phone":"+1 501 724 5362",
    "sg:postcode":"72010",
    "sg:province":"AR",
    "wof:name":"Byrds Chevey Truck Parts",
    "wof:placetype":"venue"
},
  "geometry": {"coordinates":[-91.614008,35.34805],"type":"Point"}
}