{
  "type": "Feature",
  "properties": {
    "addr:full":"3769 N Saint Louis St Batesville AR 72501",
    "addr:housenumber":"3769",
    "addr:postcode":"72501",
    "addr:street":"N Saint Louis St",
    "iso:country":"US",
    "sg:address":"3769 N Saint Louis St",
    "sg:city":"Batesville",
    "sg:classifiers":[
        {
            "category":"Shopping",
            "type":"Retail Goods"
        }
    ],
    "sg:phone":"+1 870 793 2478",
    "sg:postcode":"72501",
    "sg:province":"AR",
    "sg:tags":[
        "farm",
        "pet",
        "food",
        "supply"
    ],
    "wof:name":"S & R Farm & Pet Supply Inc",
    "wof:placetype":"venue"
},
  "geometry": {"coordinates":[-91.594084,35.822254],"type":"Point"}
}