{
  "type": "Feature",
  "properties": {
    "addr:full":"2713 SE I St Bentonville AR 72712",
    "addr:housenumber":"2713",
    "addr:postcode":"72712",
    "addr:street":"Se I St",
    "iso:country":"US",
    "sg:address":"2713 SE I St",
    "sg:city":"Bentonville",
    "sg:classifiers":[
        {
            "category":"Home & Garden",
            "subcategory":"Furniture",
            "type":"Retail Goods"
        }
    ],
    "sg:phone":"+1 479 715 6445",
    "sg:postcode":"72712",
    "sg:province":"AR",
    "sg:tags":[
        "store"
    ],
    "wof:name":"Rack Furniture for Children",
    "wof:placetype":"venue"
},
  "geometry": {"coordinates":[-94.19944,36.343589],"type":"Point"}
}