{
  "type": "Feature",
  "properties": {
    "addr:full":"5434 Wheeler Ave Fort Smith AR 72901",
    "addr:housenumber":"5434",
    "addr:postcode":"72901",
    "addr:street":"Wheeler Ave",
    "iso:country":"US",
    "sg:address":"5434 Wheeler Ave",
    "sg:city":"Fort Smith",
    "sg:classifiers":[
        {
            "category":"Building & Trades",
            "subcategory":"Plumbing",
            "type":"Services"
        }
    ],
    "sg:phone":"+1 479 646 2954",
    "sg:postcode":"72901",
    "sg:province":"AR",
    "sg:tags":[
        "sheet",
        "work",
        "metal",
        "contractor"
    ],
    "wof:name":"Burgess Co Inc Sheet Metal Div",
    "wof:placetype":"venue"
},
  "geometry": {"coordinates":[-94.42752299999999,35.33091],"type":"Point"}
}