{
  "type": "Feature",
  "properties": {
    "iso:country":"US",
    "sg:address":"2104 S Turner St",
    "sg:city":"Springdale",
    "sg:classifiers":[
        {
            "category":"Retail",
            "subcategory":"Funeral Services",
            "type":"Services"
        }
    ],
    "sg:phone":"+1 479 751 3500",
    "sg:postcode":"72764",
    "sg:province":"AR",
    "wof:name":"Northwest Arkansas Embalming",
    "wof:placetype":"venue"
},
  "geometry": {"coordinates":[-94.134885,36.16427],"type":"Point"}
}