{
  "type": "Feature",
  "properties": {
    "iso:country":"US",
    "sg:address":"605 N C St",
    "sg:city":"Fort Smith",
    "sg:classifiers":[
        {
            "category":"Communications",
            "type":"Services"
        }
    ],
    "sg:phone":"+1 479 782 1350",
    "sg:postcode":"72901",
    "sg:province":"AR",
    "wof:name":"Spiker Communications",
    "wof:placetype":"venue"
},
  "geometry": {"coordinates":[-94.422158,35.389138],"type":"Point"}
}