{
  "type": "Feature",
  "properties": {
    "addr:full":"3686 N Front St Fayetteville AR 72703",
    "addr:housenumber":"3686",
    "addr:postcode":"72703",
    "addr:street":"N Front St",
    "iso:country":"US",
    "sg:address":"3686 N Front St",
    "sg:city":"Fayetteville",
    "sg:classifiers":[
        {
            "category":"Social Services",
            "subcategory":"Child Care",
            "type":"Services"
        }
    ],
    "sg:phone":"+1 479 444 8130",
    "sg:postcode":"72703",
    "sg:province":"AR",
    "sg:tags":[
        "kindergarten",
        "preschool"
    ],
    "sg:website":"http://www.lapetite.com",
    "wof:name":"La Petite Academy",
    "wof:placetype":"venue"
},
  "geometry": {"coordinates":[-94.144379,36.117113],"type":"Point"}
}