{
  "type": "Feature",
  "properties": {
    "iso:country":"US",
    "sg:address":"593 W Broadway",
    "sg:city":"West Memphis",
    "sg:classifiers":[
        {
            "category":"Wholesale",
            "subcategory":"Auto Parts",
            "type":"Manufacturing & Wholesale Goods"
        }
    ],
    "sg:phone":"+1 870 735 3702",
    "sg:postcode":"72301",
    "sg:province":"AR",
    "sg:tags":[
        "supply"
    ],
    "wof:name":"NAPA Auto Parts",
    "wof:placetype":"venue"
},
  "geometry": {"coordinates":[-90.197479,35.146294],"type":"Point"}
}