{
  "type": "Feature",
  "properties": {
    "addr:full":"821 S Main St Searcy AR 72143",
    "addr:housenumber":"821",
    "addr:postcode":"72143",
    "addr:street":"S Main St",
    "iso:country":"US",
    "sg:address":"821 S Main St",
    "sg:city":"Searcy",
    "sg:classifiers":[
        {
            "category":"Autos & Motor Vehicles",
            "subcategory":"Auto Supplies",
            "type":"Retail Goods"
        },
        {
            "category":"Retail",
            "subcategory":"Auto Repair",
            "type":"Services"
        }
    ],
    "sg:phone":"+1 501 279 3388",
    "sg:postcode":"72143",
    "sg:province":"AR",
    "sg:tags":[
        "body",
        "lettering",
        "automobile",
        "truck",
        "painting",
        "repairing"
    ],
    "wof:name":"Truman Baker Body Shop Inc",
    "wof:placetype":"venue"
},
  "geometry": {"coordinates":[-91.73627,35.253824],"type":"Point"}
}