{
  "type": "Feature",
  "properties": {
    "iso:country":"US",
    "sg:address":"711 Greene Rd 811",
    "sg:city":"Rector",
    "sg:phone":"+1 870 522 3379",
    "sg:postcode":"72461",
    "sg:province":"AR",
    "sg:tags":[
        "farm",
        "soybean",
        "cotton"
    ],
    "wof:name":"Agee Farms",
    "wof:placetype":"venue"
},
  "geometry": {"coordinates":[-90.281165,36.171744],"type":"Point"}
}