{
  "type": "Feature",
  "properties": {
    "addr:full":"445 White Dr Batesville AR 72501",
    "addr:housenumber":"445",
    "addr:postcode":"72501",
    "addr:street":"White Dr",
    "iso:country":"US",
    "sg:address":"445 White Dr",
    "sg:city":"Batesville",
    "sg:classifiers":[
        {
            "category":"Education",
            "subcategory":"School",
            "type":"Public Place"
        }
    ],
    "sg:phone":"+1 870 698 1053",
    "sg:postcode":"72501",
    "sg:province":"AR",
    "wof:name":"Landmark Baptist Academy",
    "wof:placetype":"venue"
},
  "geometry": {"coordinates":[-91.655254,35.788567],"type":"Point"}
}