{
  "type": "Feature",
  "properties": {
    "iso:country":"US",
    "sg:address":"508 W Grober St",
    "sg:city":"Paris",
    "sg:classifiers":[
        {
            "category":"Local Transit",
            "type":"Transportation"
        }
    ],
    "sg:phone":"+1 479 963 6800",
    "sg:postcode":"72855",
    "sg:province":"AR",
    "sg:tags":[
        "public"
    ],
    "wof:name":"Emergency Dispatch Services",
    "wof:placetype":"venue"
},
  "geometry": {"coordinates":[-93.735224,35.28896],"type":"Point"}
}