{
  "type": "Feature",
  "properties": {
    "iso:country":"US",
    "sg:address":"121 E Thompson St",
    "sg:city":"Amity",
    "sg:classifiers":[
        {
            "category":"Government",
            "subcategory":"Police Station",
            "type":"Public Place"
        }
    ],
    "sg:phone":"+1 870 342 5832",
    "sg:postcode":"71921",
    "sg:province":"AR",
    "sg:tags":[
        "department"
    ],
    "wof:name":"Amity Police Dept",
    "wof:placetype":"venue"
},
  "geometry": {"coordinates":[-93.46066,34.264742],"type":"Point"}
}