{
  "type": "Feature",
  "properties": {
    "iso:country":"US",
    "sg:address":"409 W Maple Ave",
    "sg:city":"Springdale",
    "sg:classifiers":[
        {
            "category":"Health Services",
            "subcategory":"Clinic",
            "type":"Services"
        }
    ],
    "sg:phone":"+1 479 751 1601",
    "sg:postcode":"72764",
    "sg:province":"AR",
    "sg:tags":[
        "welfare"
    ],
    "wof:name":"Communities Home Health Therapy",
    "wof:placetype":"venue"
},
  "geometry": {"coordinates":[-94.134298,36.181352],"type":"Point"}
}