{
  "type": "Feature",
  "properties": {
    "addr:full":"210 Fairoaks Pl Hot Springs National AR 71901",
    "addr:housenumber":"210",
    "addr:postcode":"71901",
    "addr:street":"Fairoaks Pl",
    "iso:country":"US",
    "sg:address":"210 Fairoaks Pl",
    "sg:city":"Hot Springs National",
    "sg:classifiers":[
        {
            "category":"Sports & Exercise",
            "subcategory":"Gym",
            "type":"Entertainment"
        }
    ],
    "sg:phone":"+1 501 623 1049",
    "sg:postcode":"71901",
    "sg:province":"AR",
    "sg:tags":[
        "fitness",
        "physical",
        "facility"
    ],
    "wof:name":"Jazzercise",
    "wof:placetype":"venue"
},
  "geometry": {"coordinates":[-93.027455,34.488867],"type":"Point"}
}