{
  "type": "Feature",
  "properties": {
    "iso:country":"US",
    "sg:address":"1223 N 49th St",
    "sg:city":"Fort Smith",
    "sg:classifiers":[
        {
            "category":"Building & Trades",
            "subcategory":"Cleaning & Sanitation",
            "type":"Services"
        }
    ],
    "sg:phone":"+1 479 782 5280",
    "sg:postcode":"72904",
    "sg:province":"AR",
    "sg:tags":[
        "duct",
        "air"
    ],
    "wof:name":"Dust Management Inc",
    "wof:placetype":"venue"
},
  "geometry": {"coordinates":[-94.378042,35.389432],"type":"Point"}
}