{
  "type": "Feature",
  "properties": {
    "iso:country":"US",
    "sg:address":"7100 Kelly Rd",
    "sg:city":"North Little Rock",
    "sg:classifiers":[
        {
            "category":"Professional",
            "type":"Services"
        }
    ],
    "sg:phone":"+1 501 753 0823",
    "sg:postcode":"72118",
    "sg:province":"AR",
    "wof:name":"Jerry Toward",
    "wof:placetype":"venue"
},
  "geometry": {"coordinates":[-92.33493900000001,34.828348],"type":"Point"}
}