{
  "type": "Feature",
  "properties": {
    "iso:country":"US",
    "sg:address":"816 W Walnut St",
    "sg:city":"Rogers",
    "sg:classifiers":[
        {
            "category":"Food & Beverages",
            "subcategory":"Bakery",
            "type":"Retail Goods"
        }
    ],
    "sg:phone":"+1 479 636 6056",
    "sg:postcode":"72756",
    "sg:province":"AR",
    "sg:tags":[
        "doughnut"
    ],
    "wof:name":"Marian's Doughnuts",
    "wof:placetype":"venue"
},
  "geometry": {"coordinates":[-94.126819,36.333433],"type":"Point"}
}