{
  "type": "Feature",
  "properties": {
    "iso:country":"US",
    "sg:address":"630 W Main St",
    "sg:city":"Jacksonville",
    "sg:classifiers":[
        {
            "category":"Shopping",
            "subcategory":"Pharmacy",
            "type":"Retail Goods"
        }
    ],
    "sg:phone":"+1 501 982 2117",
    "sg:postcode":"72076",
    "sg:province":"AR",
    "wof:name":"Chambers Drug Store",
    "wof:placetype":"venue"
},
  "geometry": {"coordinates":[-92.118391,34.867286],"type":"Point"}
}