{
  "type": "Feature",
  "properties": {
    "iso:country":"US",
    "sg:address":"2167 E Wolf Creek Dr",
    "sg:city":"Fayetteville",
    "sg:classifiers":[
        {
            "category":"Organizations",
            "subcategory":"Religious Organization",
            "type":"Services"
        }
    ],
    "sg:phone":"+1 479 521 2933",
    "sg:postcode":"72703",
    "sg:province":"AR",
    "wof:name":"Jerome St Columbia",
    "wof:placetype":"venue"
},
  "geometry": {"coordinates":[-94.130348,36.109216],"type":"Point"}
}