{
  "type": "Feature",
  "properties": {
    "iso:country":"US",
    "sg:address":"301 N Main St",
    "sg:city":"Harrisburg",
    "sg:classifiers":[
        {
            "category":"Utilities",
            "subcategory":"Water",
            "type":"Services"
        }
    ],
    "sg:phone":"+1 870 578 6170",
    "sg:postcode":"72432",
    "sg:province":"AR",
    "sg:tags":[
        "pump",
        "well",
        "drilling",
        "contractor"
    ],
    "wof:name":"Rice Well Company Inc",
    "wof:placetype":"venue"
},
  "geometry": {"coordinates":[-90.717201,35.56422],"type":"Point"}
}