{
  "type": "Feature",
  "properties": {
    "iso:country":"US",
    "sg:address":"3141 Harrison St",
    "sg:city":"Batesville",
    "sg:classifiers":[
        {
            "category":"Autos & Motor Vehicles",
            "subcategory":"Automobile Sales",
            "type":"Retail Goods"
        }
    ],
    "sg:phone":"+1 870 698 9277",
    "sg:postcode":"72501",
    "sg:province":"AR",
    "sg:tags":[
        "dealers-used",
        "car",
        "used",
        "cars-wholesale",
        "new"
    ],
    "wof:name":"White River Auto Sales",
    "wof:placetype":"venue"
},
  "geometry": {"coordinates":[-91.614083,35.764778],"type":"Point"}
}