{
  "type": "Feature",
  "properties": {
    "addr:full":"5310 Columbia Rd 79 Magnolia AR 71753",
    "addr:housenumber":"5310;79",
    "addr:postcode":"71753",
    "addr:street":"Columbia Rd;Magnolia",
    "iso:country":"US",
    "sg:address":"5310 Columbia Rd 79",
    "sg:city":"Magnolia",
    "sg:classifiers":[
        {
            "category":"Manufacturing",
            "subcategory":"Chemicals & Compounds",
            "type":"Manufacturing & Wholesale Goods"
        }
    ],
    "sg:phone":"+1 870 547 3592",
    "sg:postcode":"71753",
    "sg:province":"AR",
    "sg:tags":[
        "industrial",
        "gas",
        "mfg"
    ],
    "wof:name":"Air Products",
    "wof:placetype":"venue"
},
  "geometry": {"coordinates":[-93.227959,33.17621],"type":"Point"}
}