{
  "type": "Feature",
  "properties": {
    "iso:country":"US",
    "sg:address":"400 N Main St",
    "sg:city":"Nashville",
    "sg:classifiers":[
        {
            "category":"Banks & Credit Unions",
            "subcategory":"Bank",
            "type":"Services"
        }
    ],
    "sg:phone":"+1 870 722 2313",
    "sg:postcode":"71852",
    "sg:province":"AR",
    "sg:tags":[
        "loan",
        "real estate"
    ],
    "wof:name":"Citizens National Bank",
    "wof:placetype":"venue"
},
  "geometry": {"coordinates":[-93.847042,33.947053],"type":"Point"}
}