{
  "type": "Feature",
  "properties": {
    "addr:full":"2915 E Moore Ave Searcy AR 72143",
    "addr:housenumber":"2915",
    "addr:postcode":"72143",
    "addr:street":"E Moore Ave",
    "iso:country":"US",
    "sg:address":"2915 E Moore Ave",
    "sg:city":"Searcy",
    "sg:classifiers":[
        {
            "category":"Health Services",
            "subcategory":"Doctor",
            "type":"Services"
        }
    ],
    "sg:phone":"+1 501 268 5115",
    "sg:postcode":"72143",
    "sg:province":"AR",
    "sg:tags":[
        "dentist"
    ],
    "wof:name":"Scott Eichhorn DDS",
    "wof:placetype":"venue"
},
  "geometry": {"coordinates":[-91.70114,35.253709],"type":"Point"}
}