{
  "type": "Feature",
  "properties": {
    "iso:country":"US",
    "sg:address":"44 Spring Lake Dr",
    "sg:city":"Mountain Home",
    "sg:classifiers":[
        {
            "category":"Building & Trades",
            "subcategory":"Electrical",
            "type":"Services"
        }
    ],
    "sg:phone":"+1 870 425 4612",
    "sg:postcode":"72653",
    "sg:province":"AR",
    "sg:tags":[
        "electric",
        "contractor"
    ],
    "wof:name":"Scarlett Electric",
    "wof:placetype":"venue"
},
  "geometry": {"coordinates":[-92.41829799999999,36.362515],"type":"Point"}
}