{
  "type": "Feature",
  "properties": {
    "iso:country":"US",
    "sg:address":"525 Western Ave",
    "sg:city":"Conway",
    "sg:classifiers":[
        {
            "category":"Health Services",
            "subcategory":"Doctor",
            "type":"Services"
        }
    ],
    "sg:phone":"+1 501 327 7306",
    "sg:postcode":"72034",
    "sg:province":"AR",
    "sg:tags":[
        "medical"
    ],
    "wof:name":"Phillip Gullic",
    "wof:placetype":"venue"
},
  "geometry": {"coordinates":[-92.456976,35.085516],"type":"Point"}
}