{
  "type": "Feature",
  "properties": {
    "iso:country":"US",
    "sg:address":"706 W Grove St",
    "sg:city":"El Dorado",
    "sg:classifiers":[
        {
            "category":"Health Services",
            "subcategory":"Doctor",
            "type":"Services"
        }
    ],
    "sg:phone":"+1 870 863 8444",
    "sg:postcode":"71730",
    "sg:province":"AR",
    "sg:tags":[
        "clinic",
        "medical"
    ],
    "wof:name":"South Arkansas Women's Clinic",
    "wof:placetype":"venue"
},
  "geometry": {"coordinates":[-92.672726,33.218379],"type":"Point"}
}