{
  "type": "Feature",
  "properties": {
    "addr:full":"978 Hale Rd Elkins AR 72727",
    "addr:housenumber":"978",
    "addr:postcode":"72727",
    "addr:street":"Hale Rd",
    "iso:country":"US",
    "sg:address":"978 Hale Rd",
    "sg:city":"Elkins",
    "sg:classifiers":[
        {
            "category":"Manufacturing",
            "subcategory":"Textiles",
            "type":"Manufacturing & Wholesale Goods"
        }
    ],
    "sg:phone":"+1 479 443 2168",
    "sg:postcode":"72727",
    "sg:province":"AR",
    "sg:tags":[
        "textiles-manufacturers"
    ],
    "wof:name":"Experienced Denim",
    "wof:placetype":"venue"
},
  "geometry": {"coordinates":[-93.971069,36.091686],"type":"Point"}
}