{
  "type": "Feature",
  "properties": {
    "iso:country":"US",
    "sg:address":"1111 Claycut Cir",
    "sg:city":"North Little Rock",
    "sg:classifiers":[
        {
            "category":"Professional",
            "type":"Services"
        }
    ],
    "sg:phone":"+1 501 804 7048",
    "sg:postcode":"72116",
    "sg:province":"AR",
    "wof:name":"T Speed Broadband Com",
    "wof:placetype":"venue"
},
  "geometry": {"coordinates":[-92.25463999999999,34.817401],"type":"Point"}
}