{
  "type": "Feature",
  "properties": {
    "iso:country":"US",
    "sg:address":"23716 W Cincinnati Rd",
    "sg:city":"Summers",
    "sg:classifiers":[
        {
            "category":"Building & Trades",
            "subcategory":"Construction",
            "type":"Services"
        },
        {
            "category":"Retail",
            "subcategory":"Auto Repair",
            "type":"Services"
        }
    ],
    "sg:phone":"+1 479 824 5738",
    "sg:postcode":"72769",
    "sg:province":"AR",
    "sg:tags":[
        "machine",
        "automobile",
        "welder",
        "shop"
    ],
    "wof:name":"S And W Engineering, Incorporated",
    "wof:placetype":"venue"
},
  "geometry": {"coordinates":[-94.527031,36.040633],"type":"Point"}
}