{
  "type": "Feature",
  "properties": {
    "iso:country":"US",
    "sg:address":"824 Central Ave",
    "sg:city":"Hot Springs National",
    "sg:classifiers":[
        {
            "category":"Health Services",
            "subcategory":"Health Practitioner",
            "type":"Services"
        }
    ],
    "sg:phone":"+1 501 321 6191",
    "sg:postcode":"71901",
    "sg:province":"AR",
    "wof:name":"Cherryl Mslpc Wooldridge",
    "wof:placetype":"venue"
},
  "geometry": {"coordinates":[-93.054437,34.508751],"type":"Point"}
}