{
  "type": "Feature",
  "properties": {
    "iso:country":"US",
    "sg:address":"102 Wyatt St",
    "sg:city":"Bono",
    "sg:classifiers":[
        {
            "category":"Professional",
            "type":"Services"
        }
    ],
    "sg:phone":"+1 870 932 5390",
    "sg:postcode":"72416",
    "sg:province":"AR",
    "wof:name":"Max Moore Jr",
    "wof:placetype":"venue"
},
  "geometry": {"coordinates":[-90.791512,35.910854],"type":"Point"}
}