{
  "type": "Feature",
  "properties": {
    "iso:country":"US",
    "sg:address":"861 Christopher Dr",
    "sg:city":"Quitman",
    "sg:classifiers":[
        {
            "category":"Building & Trades",
            "subcategory":"Landscaping Services",
            "type":"Services"
        }
    ],
    "sg:phone":"+1 501 362 4165",
    "sg:postcode":"72131",
    "sg:province":"AR",
    "sg:tags":[
        "landscape"
    ],
    "wof:name":"Shaws Landscaping",
    "wof:placetype":"venue"
},
  "geometry": {"coordinates":[-92.208802,35.519043],"type":"Point"}
}