{
  "type": "Feature",
  "properties": {
    "iso:country":"US",
    "sg:address":"50 Old 38 N",
    "sg:city":"Austin",
    "sg:classifiers":[
        {
            "category":"Organizations",
            "subcategory":"Religious Organization",
            "type":"Services"
        }
    ],
    "sg:phone":"+1 501 843 5101",
    "sg:postcode":"72007",
    "sg:province":"AR",
    "wof:name":"Old Austin Baptist Church",
    "wof:placetype":"venue"
},
  "geometry": {"coordinates":[-91.967467,34.98313],"type":"Point"}
}