{
  "type": "Feature",
  "properties": {
    "addr:full":"1901 E Mission Blvd Fayetteville AR 72703",
    "addr:housenumber":"1901",
    "addr:postcode":"72703",
    "addr:street":"E Mission Blvd",
    "iso:country":"US",
    "sg:address":"1901 E Mission Blvd",
    "sg:city":"Fayetteville",
    "sg:classifiers":[
        {
            "category":"Food & Beverages",
            "subcategory":"Groceries & Convenience Stores",
            "type":"Retail Goods"
        }
    ],
    "sg:phone":"+1 479 521 1656",
    "sg:postcode":"72703",
    "sg:province":"AR",
    "wof:name":"Dillons",
    "wof:placetype":"venue"
},
  "geometry": {"coordinates":[-94.132164,36.087179],"type":"Point"}
}