{
  "type": "Feature",
  "properties": {
    "iso:country":"US",
    "sg:address":"1104 Oak Meadow Blvd",
    "sg:city":"Jonesboro",
    "sg:classifiers":[
        {
            "category":"Professional",
            "subcategory":"Management & Consulting",
            "type":"Services"
        }
    ],
    "sg:phone":"+1 870 935 1398",
    "sg:postcode":"72401",
    "sg:province":"AR",
    "wof:name":"JM Marketing Strategies LLC",
    "wof:placetype":"venue"
},
  "geometry": {"coordinates":[-90.68123799999999,35.830436],"type":"Point"}
}