{
  "type": "Feature",
  "properties": {
    "addr:full":"112 Block St Marion AR 72364",
    "addr:housenumber":"112",
    "addr:postcode":"72364",
    "addr:street":"Block St",
    "iso:country":"US",
    "sg:address":"112 Block St",
    "sg:city":"Marion",
    "sg:classifiers":[
        {
            "category":"Cinema",
            "subcategory":"Movie Rental",
            "type":"Entertainment"
        }
    ],
    "sg:phone":"+1 870 739 1483",
    "sg:postcode":"72364",
    "sg:province":"AR",
    "sg:tags":[
        "video",
        "tape"
    ],
    "wof:name":"Entertainment Video",
    "wof:placetype":"venue"
},
  "geometry": {"coordinates":[-90.204331,35.209946],"type":"Point"}
}