{
  "type": "Feature",
  "properties": {
    "addr:full":"204 SW 20th St Bentonville AR 72712",
    "addr:housenumber":"204",
    "addr:postcode":"72712",
    "addr:street":"Sw 20Th St",
    "iso:country":"US",
    "sg:address":"204 SW 20th St",
    "sg:city":"Bentonville",
    "sg:classifiers":[
        {
            "category":"Wholesale",
            "subcategory":"Chemicals & Plastics",
            "type":"Manufacturing & Wholesale Goods"
        }
    ],
    "sg:phone":"+1 479 273 1118",
    "sg:postcode":"72712",
    "sg:province":"AR",
    "sg:tags":[
        "equipment",
        "manufacturer",
        "supplies-wholesale",
        "pool",
        "swimming"
    ],
    "wof:name":"Graham Crackers Backyard-Patio",
    "wof:placetype":"venue"
},
  "geometry": {"coordinates":[-94.210814,36.349761],"type":"Point"}
}