{
  "type": "Feature",
  "properties": {
    "addr:full":"53 Grant 18 Grapevine AR 72057",
    "addr:housenumber":"53;18",
    "addr:postcode":"72057",
    "addr:street":"Grant",
    "iso:country":"US",
    "sg:address":"53 Grant 18",
    "sg:city":"Grapevine",
    "sg:classifiers":[
        {
            "category":"Food & Beverages",
            "subcategory":"Groceries & Convenience Stores",
            "type":"Retail Goods"
        }
    ],
    "sg:phone":"+1 870 942 7475",
    "sg:postcode":"72057",
    "sg:province":"AR",
    "sg:tags":[
        "grocer"
    ],
    "wof:name":"Mullins Grocery",
    "wof:placetype":"venue"
},
  "geometry": {"coordinates":[-92.31474,34.147257],"type":"Point"}
}