{
  "type": "Feature",
  "properties": {
    "iso:country":"US",
    "sg:address":"706 S Main St",
    "sg:city":"Mountain Home",
    "sg:classifiers":[
        {
            "category":"Health Services",
            "subcategory":"Medical Lab",
            "type":"Services"
        },
        {
            "category":"Health Services",
            "subcategory":"Doctor",
            "type":"Services"
        }
    ],
    "sg:phone":"+1 870 425 5888",
    "sg:postcode":"72653",
    "sg:province":"AR",
    "sg:tags":[
        "laboratory",
        "dental"
    ],
    "wof:name":"Mountain Home Dental Arts",
    "wof:placetype":"venue"
},
  "geometry": {"coordinates":[-92.385396,36.334671],"type":"Point"}
}