{
  "type": "Feature",
  "properties": {
    "iso:country":"US",
    "sg:address":"9 Fernwood Dr",
    "sg:city":"Conway",
    "sg:classifiers":[
        {
            "category":"Professional",
            "subcategory":"Accounting & Tax Preparation",
            "type":"Services"
        }
    ],
    "sg:phone":"+1 501 329 9804",
    "sg:postcode":"72034",
    "sg:province":"AR",
    "sg:tags":[
        "bookkeeping"
    ],
    "wof:name":"Hamilton Financial Company",
    "wof:placetype":"venue"
},
  "geometry": {"coordinates":[-92.466988,35.098714],"type":"Point"}
}