{
  "type": "Feature",
  "properties": {
    "iso:country":"US",
    "sg:address":"811 E Oak St",
    "sg:city":"Conway",
    "sg:classifiers":[
        {
            "category":"Autos & Motor Vehicles",
            "subcategory":"Fuel & Gas Station",
            "type":"Retail Goods"
        }
    ],
    "sg:phone":"+1 501 329 6600",
    "sg:postcode":"72032",
    "sg:province":"AR",
    "sg:tags":[
        "oil"
    ],
    "wof:name":"Doublebee's Exxon",
    "wof:placetype":"venue"
},
  "geometry": {"coordinates":[-92.420988,35.091468],"type":"Point"}
}