{
  "type": "Feature",
  "properties": {
    "addr:full":"269 Millwood Cir Maumelle AR 72113",
    "addr:housenumber":"269",
    "addr:postcode":"72113",
    "addr:street":"Millwood Cir",
    "iso:country":"US",
    "sg:address":"269 Millwood Cir",
    "sg:city":"Maumelle",
    "sg:classifiers":[
        {
            "category":"Retail",
            "subcategory":"Veterinary Services",
            "type":"Services"
        }
    ],
    "sg:phone":"+1 501 851 4060",
    "sg:postcode":"72113",
    "sg:province":"AR",
    "sg:tags":[
        "veterinarian",
        "animal"
    ],
    "wof:name":"Maumelle Animal Clinic",
    "wof:placetype":"venue"
},
  "geometry": {"coordinates":[-92.404245,34.857427],"type":"Point"}
}