{
  "type": "Feature",
  "properties": {
    "iso:country":"US",
    "sg:address":"3715 N Business Dr",
    "sg:city":"Fayetteville",
    "sg:classifiers":[
        {
            "category":"Real Estate",
            "subcategory":"Architect",
            "type":"Services"
        }
    ],
    "sg:phone":"+1 479 251 0909",
    "sg:postcode":"72703",
    "sg:province":"AR",
    "wof:name":"Mobley Architects Inc",
    "wof:placetype":"venue"
},
  "geometry": {"coordinates":[-94.13091900000001,36.118179],"type":"Point"}
}