{
  "type": "Feature",
  "properties": {
    "addr:full":"408 Janssen Ave Mena AR 71953",
    "addr:housenumber":"408",
    "addr:postcode":"71953",
    "addr:street":"Janssen Ave",
    "iso:country":"US",
    "sg:address":"408 Janssen Ave",
    "sg:city":"Mena",
    "sg:classifiers":[
        {
            "category":"Banks & Credit Unions",
            "subcategory":"Investment Brokerage",
            "type":"Services"
        }
    ],
    "sg:phone":"+1 479 394 6670",
    "sg:postcode":"71953",
    "sg:province":"AR",
    "sg:tags":[
        "security"
    ],
    "wof:name":"A G Edwards & Sons Inc",
    "wof:placetype":"venue"
},
  "geometry": {"coordinates":[-94.235333,34.584713],"type":"Point"}
}