{
  "type": "Feature",
  "properties": {
    "addr:full":"104 N Hyatt St Monticello AR 71655",
    "addr:housenumber":"104",
    "addr:postcode":"71655",
    "addr:street":"N Hyatt St",
    "iso:country":"US",
    "sg:address":"104 N Hyatt St",
    "sg:city":"Monticello",
    "sg:classifiers":[
        {
            "category":"Building & Trades",
            "subcategory":"Construction",
            "type":"Services"
        }
    ],
    "sg:phone":"+1 870 367 6566",
    "sg:postcode":"71655",
    "sg:province":"AR",
    "sg:tags":[
        "house"
    ],
    "wof:name":"Wilmont Construction Co",
    "wof:placetype":"venue"
},
  "geometry": {"coordinates":[-91.795725,33.629216],"type":"Point"}
}