{
  "type": "Feature",
  "properties": {
    "addr:full":"2301 S 56th St Fort Smith AR 72903",
    "addr:housenumber":"2301",
    "addr:postcode":"72903",
    "addr:street":"S 56Th St",
    "iso:country":"US",
    "sg:address":"2301 S 56th St",
    "sg:city":"Fort Smith",
    "sg:classifiers":[
        {
            "category":"Personal",
            "type":"Services"
        }
    ],
    "sg:phone":"+1 479 484 7667",
    "sg:postcode":"72903",
    "sg:province":"AR",
    "wof:name":"Malibu Tanning & Apparel",
    "wof:placetype":"venue"
},
  "geometry": {"coordinates":[-94.370814,35.360581],"type":"Point"}
}