{
  "type": "Feature",
  "properties": {
    "iso:country":"US",
    "sg:address":"9621 Tall Timber Blvd",
    "sg:city":"Little Rock",
    "sg:classifiers":[
        {
            "category":"Organizations",
            "subcategory":"Religious Organization",
            "type":"Services"
        }
    ],
    "sg:phone":"+1 501 455 0296",
    "sg:postcode":"72204",
    "sg:province":"AR",
    "sg:website":"www.bdclr.org",
    "wof:name":"Bible Doctrine Church",
    "wof:placetype":"venue"
},
  "geometry": {"coordinates":[-92.382094,34.701501],"type":"Point"}
}