{
  "type": "Feature",
  "properties": {
    "iso:country":"US",
    "sg:address":"12227 Macarthur Dr",
    "sg:city":"N Little Rock",
    "sg:classifiers":[
        {
            "category":"Autos & Motor Vehicles",
            "subcategory":"Automobile Sales",
            "type":"Retail Goods"
        }
    ],
    "sg:phone":"+1 501 851 7844",
    "sg:postcode":"72118",
    "sg:province":"AR",
    "sg:tags":[
        "car",
        "dealer"
    ],
    "wof:name":"Premier Auto & Wholesale",
    "wof:placetype":"venue"
},
  "geometry": {"coordinates":[-92.341192,34.849432],"type":"Point"}
}