{
  "type": "Feature",
  "properties": {
    "addr:full":"4330 Park Ave Hot Springs AR 71901",
    "addr:housenumber":"4330",
    "addr:postcode":"71901",
    "addr:street":"Park Ave",
    "iso:country":"US",
    "sg:address":"4330 Park Ave",
    "sg:city":"Hot Springs",
    "sg:classifiers":[
        {
            "category":"Food & Beverages",
            "subcategory":"Bakery",
            "type":"Retail Goods"
        }
    ],
    "sg:phone":"+1 501 609 9466",
    "sg:postcode":"71901",
    "sg:province":"AR",
    "sg:tags":[
        "doughnut"
    ],
    "wof:name":"Bo's Donut Shop",
    "wof:placetype":"venue"
},
  "geometry": {"coordinates":[-92.986208,34.575055],"type":"Point"}
}