{
  "type": "Feature",
  "properties": {
    "iso:country":"US",
    "sg:address":"10701 Chicot Rd",
    "sg:city":"Mabelvale",
    "sg:classifiers":[
        {
            "category":"Building & Trades",
            "subcategory":"Electrical",
            "type":"Services"
        }
    ],
    "sg:phone":"+1 501 650 1902",
    "sg:postcode":"72103",
    "sg:province":"AR",
    "sg:tags":[
        "industrial",
        "electrician",
        "contractors-commercial",
        "electric"
    ],
    "wof:name":"Actium Electric Company",
    "wof:placetype":"venue"
},
  "geometry": {"coordinates":[-92.36324399999999,34.65332],"type":"Point"}
}