{
  "type": "Feature",
  "properties": {
    "addr:full":"5804 N Woodview Dr North Little Rock AR 72120",
    "addr:housenumber":"5804",
    "addr:postcode":"72120",
    "addr:street":"N Woodview Dr",
    "iso:country":"US",
    "sg:address":"5804 N Woodview Dr",
    "sg:city":"North Little Rock",
    "sg:classifiers":[
        {
            "category":"Professional",
            "subcategory":"Computer Services",
            "type":"Services"
        }
    ],
    "sg:phone":"+1 501 835 4282",
    "sg:postcode":"72120",
    "sg:province":"AR",
    "sg:tags":[
        "newspaper",
        "related",
        "pub"
    ],
    "wof:name":"Norris Consulting & Design",
    "wof:placetype":"venue"
},
  "geometry": {"coordinates":[-92.199896,34.831307],"type":"Point"}
}