{
  "type": "Feature",
  "properties": {
    "iso:country":"US",
    "sg:address":"300 E New Hope Rd",
    "sg:city":"Rogers",
    "sg:classifiers":[
        {
            "category":"Manufacturing",
            "subcategory":"Furniture",
            "type":"Manufacturing & Wholesale Goods"
        },
        {
            "category":"Building & Trades",
            "subcategory":"Construction",
            "type":"Services"
        }
    ],
    "sg:phone":"+1 479 621 0049",
    "sg:postcode":"72758",
    "sg:province":"AR",
    "sg:tags":[
        "product",
        "wood",
        "maker",
        "cabinet",
        "mfg"
    ],
    "wof:name":"Timber Mill Wood Products Inc",
    "wof:placetype":"venue"
},
  "geometry": {"coordinates":[-94.11282300000001,36.311468],"type":"Point"}
}