{
  "type": "Feature",
  "properties": {
    "iso:country":"US",
    "sg:address":"600 E Hillsboro St",
    "sg:city":"El Dorado",
    "sg:classifiers":[
        {
            "category":"Autos & Motor Vehicles",
            "subcategory":"Automobile Sales",
            "type":"Retail Goods"
        }
    ],
    "sg:phone":"+1 870 864 0460",
    "sg:postcode":"71730",
    "sg:province":"AR",
    "sg:tags":[
        "car",
        "used",
        "dealer"
    ],
    "wof:name":"Hudson's Used Cars",
    "wof:placetype":"venue"
},
  "geometry": {"coordinates":[-92.658122,33.207422],"type":"Point"}
}