{
  "type": "Feature",
  "properties": {
    "iso:country":"US",
    "sg:address":"44 Mountain View Rd",
    "sg:city":"Drasco",
    "sg:classifiers":[
        {
            "category":"Building & Trades",
            "subcategory":"Construction",
            "type":"Services"
        }
    ],
    "sg:phone":"+1 870 668 3580",
    "sg:postcode":"72530",
    "sg:province":"AR",
    "sg:tags":[
        "paving",
        "contractor"
    ],
    "wof:name":"Pro Pavers Inc",
    "wof:placetype":"venue"
},
  "geometry": {"coordinates":[-91.92916,35.654987],"type":"Point"}
}