{
  "type": "Feature",
  "properties": {
    "addr:full":"105 N Jefferson St Magnolia AR 71753",
    "addr:housenumber":"105",
    "addr:postcode":"71753",
    "addr:street":"N Jefferson St",
    "iso:country":"US",
    "sg:address":"105 N Jefferson St",
    "sg:city":"Magnolia",
    "sg:classifiers":[
        {
            "category":"Shopping",
            "type":"Retail Goods"
        }
    ],
    "sg:phone":"+1 870 235 9894",
    "sg:postcode":"71753",
    "sg:province":"AR",
    "sg:tags":[
        "merchandise"
    ],
    "wof:name":"Melissas Custom Framing",
    "wof:placetype":"venue"
},
  "geometry": {"coordinates":[-93.24140300000001,33.267458],"type":"Point"}
}