{
  "type": "Feature",
  "properties": {
    "addr:full":"442 W Cato Springs Rd Fayetteville AR 72701",
    "addr:housenumber":"442",
    "addr:postcode":"72701",
    "addr:street":"W Cato Springs Rd",
    "iso:country":"US",
    "sg:address":"442 W Cato Springs Rd",
    "sg:city":"Fayetteville",
    "sg:classifiers":[
        {
            "category":"Home & Garden",
            "subcategory":"Garden Supply",
            "type":"Retail Goods"
        }
    ],
    "sg:phone":"+1 479 587 0569",
    "sg:postcode":"72701",
    "sg:province":"AR",
    "sg:tags":[
        "sprinkler"
    ],
    "wof:name":"Matthews Irrigation",
    "wof:placetype":"venue"
},
  "geometry": {"coordinates":[-94.166488,36.041125],"type":"Point"}
}