{
  "type": "Feature",
  "properties": {
    "iso:country":"US",
    "sg:address":"60 State Hwy 184",
    "sg:city":"Parkin",
    "sg:classifiers":[
        {
            "category":"Recreation",
            "type":"Entertainment"
        },
        {
            "category":"Travel",
            "subcategory":"Campground",
            "type":"Entertainment"
        }
    ],
    "sg:phone":"+1 870 755 2119",
    "sg:postcode":"72373",
    "sg:province":"AR",
    "sg:tags":[
        "camp",
        "parks"
    ],
    "wof:name":"Parkin Archeological State Pk",
    "wof:placetype":"venue"
},
  "geometry": {"coordinates":[-90.55445,35.27672],"type":"Point"}
}