{
  "type": "Feature",
  "properties": {
    "iso:country":"US",
    "sg:address":"1610 S Arkansas Ave",
    "sg:city":"Russellville",
    "sg:classifiers":[
        {
            "category":"Shopping",
            "subcategory":"Clothing, Apparel, & Fashions",
            "type":"Retail Goods"
        }
    ],
    "sg:phone":"+1 479 967 9557",
    "sg:postcode":"72801",
    "sg:province":"AR",
    "wof:name":"Puff's Wearhouse Co",
    "wof:placetype":"venue"
},
  "geometry": {"coordinates":[-93.134351,35.263996],"type":"Point"}
}