{
  "type": "Feature",
  "properties": {
    "addr:full":"113 Highway 70 W Glenwood AR 71943",
    "addr:housenumber":"113",
    "addr:postcode":"71943",
    "addr:street":"Highway 70 W",
    "iso:country":"US",
    "sg:address":"113 Highway 70 W",
    "sg:city":"Glenwood",
    "sg:classifiers":[
        {
            "category":"Wholesale",
            "subcategory":"Hardware",
            "type":"Manufacturing & Wholesale Goods"
        },
        {
            "category":"Home & Garden",
            "subcategory":"Garden Supply",
            "type":"Retail Goods"
        },
        {
            "category":"Retail",
            "subcategory":"Repair Shop",
            "type":"Services"
        }
    ],
    "sg:phone":"+1 870 356 5403",
    "sg:postcode":"71943",
    "sg:province":"AR",
    "sg:tags":[
        "renting",
        "lawn",
        "outdoor",
        "power",
        "landscaping",
        "equipment-sales",
        "equipment",
        "saw"
    ],
    "sg:website":"http://www.stihlusa.com/",
    "wof:name":"The Shop",
    "wof:placetype":"venue"
},
  "geometry": {"coordinates":[-93.54616,34.321293],"type":"Point"}
}