{
  "type": "Feature",
  "properties": {
    "iso:country":"US",
    "sg:address":"231 W Barnett St",
    "sg:city":"Kensett",
    "sg:classifiers":[
        {
            "category":"Building & Trades",
            "subcategory":"Plumbing",
            "type":"Services"
        }
    ],
    "sg:phone":"+1 501 742 1288",
    "sg:postcode":"72082",
    "sg:province":"AR",
    "sg:tags":[
        "plumbing",
        "contractor"
    ],
    "wof:name":"Mitchell's Plumbing",
    "wof:placetype":"venue"
},
  "geometry": {"coordinates":[-91.671672,35.231943],"type":"Point"}
}