{
  "type": "Feature",
  "properties": {
    "iso:country":"US",
    "sg:address":"12 Quail Dr",
    "sg:city":"Rogers",
    "sg:classifiers":[
        {
            "category":"Shopping",
            "subcategory":"Crafts & Fabrics",
            "type":"Retail Goods"
        }
    ],
    "sg:phone":"+1 479 925 4168",
    "sg:postcode":"72758",
    "sg:province":"AR",
    "sg:tags":[
        "sewing"
    ],
    "wof:name":"Fabric Design Workroom",
    "wof:placetype":"venue"
},
  "geometry": {"coordinates":[-94.055951,36.29144],"type":"Point"}
}