{
  "type": "Feature",
  "properties": {
    "iso:country":"US",
    "sg:address":"601 N 13th St",
    "sg:city":"Rogers",
    "sg:classifiers":[
        {
            "category":"Shopping",
            "subcategory":"Stationery & Office Supplies",
            "type":"Retail Goods"
        }
    ],
    "sg:phone":"+1 479 636 3481",
    "sg:postcode":"72756",
    "sg:province":"AR",
    "sg:tags":[
        "equipment"
    ],
    "sg:website":"www.mosercorporation.com",
    "wof:name":"Moser Corporation",
    "wof:placetype":"venue"
},
  "geometry": {"coordinates":[-94.1343,36.340302],"type":"Point"}
}