{
  "type": "Feature",
  "properties": {
    "iso:country":"US",
    "sg:address":"1620 Brentwood Dr",
    "sg:city":"Pine Bluff",
    "sg:classifiers":[
        {
            "category":"Shopping",
            "subcategory":"Tobacco",
            "type":"Retail Goods"
        }
    ],
    "sg:phone":"+1 870 536 7627",
    "sg:postcode":"71601",
    "sg:province":"AR",
    "sg:tags":[
        "cigarette",
        "product",
        "cigar",
        "dealer"
    ],
    "wof:name":"Tobacco Superstores Inc",
    "wof:placetype":"venue"
},
  "geometry": {"coordinates":[-91.980448,34.213452],"type":"Point"}
}