{
  "type": "Feature",
  "properties": {
    "iso:country":"US",
    "sg:address":"2863 N Old Missouri Rd",
    "sg:city":"Fayetteville",
    "sg:classifiers":[
        {
            "category":"Professional",
            "subcategory":"Advertising",
            "type":"Services"
        }
    ],
    "sg:phone":"+1 479 444 6427",
    "sg:postcode":"72703",
    "sg:province":"AR",
    "sg:tags":[
        "agency",
        "specialty"
    ],
    "wof:name":"Art Works",
    "wof:placetype":"venue"
},
  "geometry": {"coordinates":[-94.133163,36.104031],"type":"Point"}
}