{
  "type": "Feature",
  "properties": {
    "iso:country":"US",
    "sg:address":"505 N Shady Ave",
    "sg:city":"Fayetteville",
    "sg:classifiers":[
        {
            "category":"Professional",
            "type":"Services"
        }
    ],
    "sg:phone":"+1 479 973 2900",
    "sg:postcode":"72701",
    "sg:province":"AR",
    "wof:name":"Edifice LLC",
    "wof:placetype":"venue"
},
  "geometry": {"coordinates":[-94.163251,36.070941],"type":"Point"}
}