{
  "type": "Feature",
  "properties": {
    "addr:full":"4333 E Main St Blytheville AR 72315",
    "addr:housenumber":"4333",
    "addr:postcode":"72315",
    "addr:street":"E Main St",
    "iso:country":"US",
    "sg:address":"4333 E Main St",
    "sg:city":"Blytheville",
    "sg:classifiers":[
        {
            "category":"Manufacturing",
            "subcategory":"Metals",
            "type":"Manufacturing & Wholesale Goods"
        },
        {
            "category":"Building & Trades",
            "subcategory":"Construction",
            "type":"Services"
        },
        {
            "category":"Manufacturing",
            "subcategory":"Building Materials",
            "type":"Manufacturing & Wholesale Goods"
        }
    ],
    "sg:phone":"+1 870 763 2654",
    "sg:postcode":"72315",
    "sg:province":"AR",
    "sg:tags":[
        "sheet",
        "specialty",
        "work",
        "heating",
        "system",
        "fabricator",
        "contractor",
        "air conditioning"
    ],
    "wof:name":"Allen Air Conditioning & Sheet Metal",
    "wof:placetype":"venue"
},
  "geometry": {"coordinates":[-89.849729,35.92838],"type":"Point"}
}