{
  "type": "Feature",
  "properties": {
    "iso:country":"US",
    "sg:address":"1219 Hwy 9",
    "sg:city":"Morrilton",
    "sg:classifiers":[
        {
            "category":"Professional",
            "subcategory":"Accounting & Tax Preparation",
            "type":"Services"
        }
    ],
    "sg:phone":"+1 501 354 8035",
    "sg:postcode":"72110",
    "sg:province":"AR",
    "sg:tags":[
        "return",
        "filing"
    ],
    "wof:name":"Workers Income Tax Svc",
    "wof:placetype":"venue"
},
  "geometry": {"coordinates":[-92.72042399999999,35.152398],"type":"Point"}
}