{
  "type": "Feature",
  "properties": {
    "addr:full":"91 E Neal St Farmington AR 72730",
    "addr:housenumber":"91",
    "addr:postcode":"72730",
    "addr:street":"E Neal St",
    "iso:country":"US",
    "sg:address":"91 E Neal St",
    "sg:city":"Farmington",
    "sg:classifiers":[
        {
            "category":"Health Services",
            "subcategory":"Health Practitioner",
            "type":"Services"
        },
        {
            "category":"Health Services",
            "subcategory":"Doctor",
            "type":"Services"
        }
    ],
    "sg:phone":"+1 479 267 4673",
    "sg:postcode":"72730",
    "sg:province":"AR",
    "sg:tags":[
        "occupational",
        "therapist",
        "medical"
    ],
    "wof:name":"Hope For Tomorrow Pediatrics",
    "wof:placetype":"venue"
},
  "geometry": {"coordinates":[-94.237016,36.041522],"type":"Point"}
}