{
  "type": "Feature",
  "properties": {
    "addr:full":"406 N Moss St Searcy AR 72143",
    "addr:housenumber":"406",
    "addr:postcode":"72143",
    "addr:street":"N Moss St",
    "iso:country":"US",
    "sg:address":"406 N Moss St",
    "sg:city":"Searcy",
    "sg:classifiers":[
        {
            "category":"Retail",
            "subcategory":"Animal Services",
            "type":"Services"
        }
    ],
    "sg:phone":"+1 501 279 1312",
    "sg:postcode":"72143",
    "sg:province":"AR",
    "sg:tags":[
        "pet",
        "grooming",
        "washing"
    ],
    "wof:name":"Pup E Cuts",
    "wof:placetype":"venue"
},
  "geometry": {"coordinates":[-91.718507,35.252034],"type":"Point"}
}