{
  "type": "Feature",
  "properties": {
    "addr:full":"901 W Wilson Ave Harrison AR 72601",
    "addr:housenumber":"901",
    "addr:postcode":"72601",
    "addr:street":"W Wilson Ave",
    "iso:country":"US",
    "sg:address":"901 W Wilson Ave",
    "sg:city":"Harrison",
    "sg:classifiers":[
        {
            "category":"Autos & Motor Vehicles",
            "subcategory":"Automobile Sales",
            "type":"Retail Goods"
        }
    ],
    "sg:phone":"+1 870 743 6953",
    "sg:postcode":"72601",
    "sg:province":"AR",
    "sg:tags":[
        "new",
        "car"
    ],
    "wof:name":"Kings Cars",
    "wof:placetype":"venue"
},
  "geometry": {"coordinates":[-93.118111,36.21925],"type":"Point"}
}