{
  "type": "Feature",
  "properties": {
    "iso:country":"US",
    "sg:address":"828 N Washington St",
    "sg:city":"Forrest City",
    "sg:classifiers":[
        {
            "category":"Home & Garden",
            "subcategory":"Household Appliances",
            "type":"Retail Goods"
        }
    ],
    "sg:phone":"+1 870 633 5710",
    "sg:postcode":"72335",
    "sg:province":"AR",
    "wof:name":"Sears Authorized Retail Dealer",
    "wof:placetype":"venue"
},
  "geometry": {"coordinates":[-90.78720199999999,35.016319],"type":"Point"}
}