{
  "type": "Feature",
  "properties": {
    "iso:country":"US",
    "sg:address":"460 Thunderbird Loop",
    "sg:city":"Traskwood",
    "sg:classifiers":[
        {
            "category":"Building & Trades",
            "subcategory":"Construction",
            "type":"Services"
        }
    ],
    "sg:phone":"+1 501 332 2666",
    "sg:postcode":"72167",
    "sg:province":"AR",
    "sg:tags":[
        "hanging",
        "contractor"
    ],
    "wof:name":"Smart Painting Randy",
    "wof:placetype":"venue"
},
  "geometry": {"coordinates":[-92.713799,34.46265],"type":"Point"}
}