{
  "type": "Feature",
  "properties": {
    "iso:country":"US",
    "sg:address":"121 W Township St",
    "sg:city":"Fayetteville",
    "sg:classifiers":[
        {
            "category":"Social Services",
            "type":"Services"
        },
        {
            "category":"Health Services",
            "subcategory":"Clinic",
            "type":"Services"
        }
    ],
    "sg:phone":"+1 479 571 3391",
    "sg:postcode":"72703",
    "sg:province":"AR",
    "sg:tags":[
        "welfare"
    ],
    "wof:name":"Outcomes Inc",
    "wof:placetype":"venue"
},
  "geometry": {"coordinates":[-94.156187,36.095222],"type":"Point"}
}