{
  "type": "Feature",
  "properties": {
    "iso:country":"US",
    "sg:address":"101 Hillwood St",
    "sg:city":"Hot Springs",
    "sg:classifiers":[
        {
            "category":"Autos & Motor Vehicles",
            "subcategory":"Auto Supplies",
            "type":"Retail Goods"
        }
    ],
    "sg:phone":"+1 501 623 1168",
    "sg:postcode":"71901",
    "sg:province":"AR",
    "sg:tags":[
        "battery"
    ],
    "wof:name":"Power Stroke Batteries",
    "wof:placetype":"venue"
},
  "geometry": {"coordinates":[-93.050576,34.49772],"type":"Point"}
}