{
  "type": "Feature",
  "properties": {
    "addr:full":"40 Patton Ln Greenbrier AR 72058",
    "addr:housenumber":"40",
    "addr:postcode":"72058",
    "addr:street":"Patton Ln",
    "iso:country":"US",
    "sg:address":"40 Patton Ln",
    "sg:city":"Greenbrier",
    "sg:classifiers":[
        {
            "category":"Real Estate",
            "subcategory":"Real Estate Agent",
            "type":"Services"
        }
    ],
    "sg:phone":"+1 501 679 0606",
    "sg:postcode":"72058",
    "sg:province":"AR",
    "wof:name":"Alix",
    "wof:placetype":"venue"
},
  "geometry": {"coordinates":[-92.444059,35.179437],"type":"Point"}
}