{
  "type": "Feature",
  "properties": {
    "iso:country":"US",
    "sg:address":"1921 N Main St",
    "sg:city":"N Little Rock",
    "sg:classifiers":[
        {
            "category":"Insurance",
            "subcategory":"Insurance Agent",
            "type":"Services"
        }
    ],
    "sg:phone":"+1 501 758 1778",
    "sg:postcode":"72114",
    "sg:province":"AR",
    "wof:name":"American Home Life Insurance",
    "wof:placetype":"venue"
},
  "geometry": {"coordinates":[-92.26707399999999,34.773079],"type":"Point"}
}