{
  "type": "Feature",
  "properties": {
    "iso:country":"US",
    "sg:address":"222 N Pine St",
    "sg:city":"Magnolia",
    "sg:classifiers":[
        {
            "category":"Health Services",
            "subcategory":"Nursing And Care Facility",
            "type":"Services"
        },
        {
            "category":"Health Services",
            "subcategory":"Hospital",
            "type":"Services"
        }
    ],
    "sg:phone":"+1 870 901 0500",
    "sg:postcode":"71753",
    "sg:province":"AR",
    "sg:tags":[
        "hospice",
        "specialty"
    ],
    "wof:name":"Serenity Hospice",
    "wof:placetype":"venue"
},
  "geometry": {"coordinates":[-93.238125,33.268976],"type":"Point"}
}