{
  "type": "Feature",
  "properties": {
    "iso:country":"US",
    "sg:address":"2006 E Main St",
    "sg:city":"Mountain View",
    "sg:classifiers":[
        {
            "category":"Government",
            "subcategory":"Fire Station",
            "type":"Public Place"
        }
    ],
    "sg:phone":"+1 870 269 2626",
    "sg:postcode":"72560",
    "sg:province":"AR",
    "sg:tags":[
        "department",
        "city",
        "volunteer"
    ],
    "wof:name":"Mountain View Vlntr Fire Dept",
    "wof:placetype":"venue"
},
  "geometry": {"coordinates":[-92.0877,35.858238],"type":"Point"}
}