{
  "type": "Feature",
  "properties": {
    "addr:full":"606 Lawrence St Batesville AR 72501",
    "addr:housenumber":"606",
    "addr:postcode":"72501",
    "addr:street":"Lawrence St",
    "iso:country":"US",
    "sg:address":"606 Lawrence St",
    "sg:city":"Batesville",
    "sg:classifiers":[
        {
            "category":"Utilities",
            "subcategory":"Natural Gas",
            "type":"Services"
        }
    ],
    "sg:phone":"+1 870 523 2794",
    "sg:postcode":"72501",
    "sg:province":"AR",
    "sg:tags":[
        "transmission",
        "pipeline"
    ],
    "wof:name":"Arkla Gas Company",
    "wof:placetype":"venue"
},
  "geometry": {"coordinates":[-91.64755,35.766673],"type":"Point"}
}