{
  "type": "Feature",
  "properties": {
    "addr:full":"27 Kings River Rd N Little Rock AR 72116",
    "addr:housenumber":"27",
    "addr:postcode":"72116",
    "addr:street":"Kings River Rd N",
    "iso:country":"US",
    "sg:address":"27 Kings River Rd",
    "sg:city":"N Little Rock",
    "sg:classifiers":[
        {
            "category":"Professional",
            "subcategory":"Computer Services",
            "type":"Services"
        }
    ],
    "sg:phone":"+1 501 791 2228",
    "sg:postcode":"72116",
    "sg:province":"AR",
    "sg:tags":[
        "consultant",
        "designer"
    ],
    "wof:name":"Intellimark",
    "wof:placetype":"venue"
},
  "geometry": {"coordinates":[-92.241876,34.806217],"type":"Point"}
}