{
  "type": "Feature",
  "properties": {
    "addr:full":"2111 Race St Jonesboro AR 72401",
    "addr:housenumber":"2111",
    "addr:postcode":"72401",
    "addr:street":"Race St",
    "iso:country":"US",
    "sg:address":"2111 Race St",
    "sg:city":"Jonesboro",
    "sg:classifiers":[
        {
            "category":"Wholesale",
            "subcategory":"Office Equipment",
            "type":"Manufacturing & Wholesale Goods"
        }
    ],
    "sg:phone":"+1 870 932 6910",
    "sg:postcode":"72401",
    "sg:province":"AR",
    "sg:tags":[
        "machine",
        "duplicating",
        "copying"
    ],
    "wof:name":"Danka",
    "wof:placetype":"venue"
},
  "geometry": {"coordinates":[-90.680538,35.813938],"type":"Point"}
}