{
  "type": "Feature",
  "properties": {
    "iso:country":"US",
    "sg:address":"9841 Neal Rd",
    "sg:city":"Cedarville",
    "sg:classifiers":[
        {
            "category":"Shopping",
            "subcategory":"Shoes",
            "type":"Retail Goods"
        }
    ],
    "sg:phone":"+1 479 410 1356",
    "sg:postcode":"72932",
    "sg:province":"AR",
    "wof:name":"Double H Enterprises of NW AR",
    "wof:placetype":"venue"
},
  "geometry": {"coordinates":[-94.347998,35.575836],"type":"Point"}
}