{
  "type": "Feature",
  "properties": {
    "addr:full":"268 Kelsey Ln Farmington AR 72730",
    "addr:housenumber":"268",
    "addr:postcode":"72730",
    "addr:street":"Kelsey Ln",
    "iso:country":"US",
    "sg:address":"268 Kelsey Ln",
    "sg:city":"Farmington",
    "sg:classifiers":[
        {
            "category":"Building & Trades",
            "subcategory":"Plumbing",
            "type":"Services"
        }
    ],
    "sg:phone":"+1 479 267 5758",
    "sg:postcode":"72730",
    "sg:province":"AR",
    "sg:tags":[
        "plumbing",
        "contractor"
    ],
    "wof:name":"S & S Plumbing",
    "wof:placetype":"venue"
},
  "geometry": {"coordinates":[-94.23381999999999,36.052268],"type":"Point"}
}