{
  "type": "Feature",
  "properties": {
    "iso:country":"US",
    "sg:address":"307 S Center Hill Rd",
    "sg:city":"Paragould",
    "sg:classifiers":[
        {
            "category":"Retail",
            "subcategory":"Laundry & Dry Cleaning",
            "type":"Services"
        },
        {
            "category":"Building & Trades",
            "subcategory":"Cleaning & Sanitation",
            "type":"Services"
        },
        {
            "category":"Building & Trades",
            "subcategory":"Construction",
            "type":"Services"
        },
        {
            "category":"Home & Garden",
            "subcategory":"Carpets & Floor Coverings",
            "type":"Retail Goods"
        }
    ],
    "sg:phone":"+1 870 236 7606",
    "sg:postcode":"72450",
    "sg:province":"AR",
    "sg:tags":[
        "cleaner",
        "upholstery",
        "refinishing",
        "cleaners-water",
        "rug",
        "extraction",
        "sealing",
        "tile-cleaning"
    ],
    "wof:name":"Razorback Carpet Cleaning",
    "wof:placetype":"venue"
},
  "geometry": {"coordinates":[-90.544206,36.056524],"type":"Point"}
}