{
  "type": "Feature",
  "properties": {
    "iso:country":"US",
    "sg:address":"415 Highway 278 E",
    "sg:city":"Camden",
    "sg:classifiers":[
        {
            "category":"Building & Trades",
            "subcategory":"Construction",
            "type":"Services"
        }
    ],
    "sg:phone":"+1 870 574 1840",
    "sg:postcode":"71701",
    "sg:province":"AR",
    "sg:tags":[
        "contractor",
        "paving",
        "asphalt",
        "sealcoating"
    ],
    "wof:name":"Jet Asphalt & Rock Co.",
    "wof:placetype":"venue"
},
  "geometry": {"coordinates":[-92.751617,33.60627],"type":"Point"}
}