{
  "type": "Feature",
  "properties": {
    "iso:country":"US",
    "sg:address":"110 Ramblewood Dr",
    "sg:city":"Blytheville",
    "sg:classifiers":[
        {
            "category":"Building & Trades",
            "subcategory":"Construction",
            "type":"Services"
        }
    ],
    "sg:phone":"+1 866 805 4967",
    "sg:postcode":"72315",
    "sg:province":"AR",
    "sg:tags":[
        "contractor",
        "maker",
        "cabinet"
    ],
    "wof:name":"L.A.N. Custom Woodworks",
    "wof:placetype":"venue"
},
  "geometry": {"coordinates":[-89.89949,35.959509],"type":"Point"}
}