{
  "type": "Feature",
  "properties": {
    "addr:full":"108 Donnie Ct Hot Springs AR 71913",
    "addr:housenumber":"108",
    "addr:postcode":"71913",
    "addr:street":"Donnie Ct",
    "iso:country":"US",
    "sg:address":"108 Donnie Ct",
    "sg:city":"Hot Springs",
    "sg:classifiers":[
        {
            "category":"Organizations",
            "subcategory":"Religious Organization",
            "type":"Services"
        }
    ],
    "sg:phone":"+1 501 625 3258",
    "sg:postcode":"71913",
    "sg:province":"AR",
    "sg:tags":[
        "church"
    ],
    "wof:name":"Serbian Orthodox Chr-St George",
    "wof:placetype":"venue"
},
  "geometry": {"coordinates":[-93.102615,34.484896],"type":"Point"}
}