{
  "type": "Feature",
  "properties": {
    "addr:full":"3007 S 18th St Fort Smith AR 72901",
    "addr:housenumber":"3007",
    "addr:postcode":"72901",
    "addr:street":"S 18Th St",
    "iso:country":"US",
    "sg:address":"3007 S 18th St",
    "sg:city":"Fort Smith",
    "sg:classifiers":[
        {
            "category":"Professional",
            "subcategory":"Computer Services",
            "type":"Services"
        }
    ],
    "sg:phone":"+1 479 783 4201",
    "sg:postcode":"72901",
    "sg:province":"AR",
    "sg:tags":[
        "internet"
    ],
    "wof:name":"Espy & Espy",
    "wof:placetype":"venue"
},
  "geometry": {"coordinates":[-94.41578699999999,35.354535],"type":"Point"}
}