{
  "type": "Feature",
  "properties": {
    "addr:full":"7627 Hardin Dr North Little Rock AR 72117",
    "addr:housenumber":"7627",
    "addr:postcode":"72117",
    "addr:street":"Hardin Dr",
    "iso:country":"US",
    "sg:address":"7627 Hardin Dr",
    "sg:city":"North Little Rock",
    "sg:classifiers":[
        {
            "category":"Building & Trades",
            "subcategory":"Construction",
            "type":"Services"
        }
    ],
    "sg:phone":"+1 501 835 7300",
    "sg:postcode":"72117",
    "sg:province":"AR",
    "sg:tags":[
        "damaged",
        "restoration",
        "structure"
    ],
    "wof:name":"Lemmons Construction",
    "wof:placetype":"venue"
},
  "geometry": {"coordinates":[-92.192695,34.82358],"type":"Point"}
}