{
  "type": "Feature",
  "properties": {
    "iso:country":"US",
    "sg:address":"4884 Hwy 201 N",
    "sg:city":"Mountain Home",
    "sg:classifiers":[
        {
            "category":"Building & Trades",
            "subcategory":"Plumbing",
            "type":"Services"
        }
    ],
    "sg:phone":"+1 870 425 5386",
    "sg:postcode":"72653",
    "sg:province":"AR",
    "sg:tags":[
        "air",
        "heating",
        "conditioning",
        "contractor"
    ],
    "wof:name":"Stans Heating & AC Svc",
    "wof:placetype":"venue"
},
  "geometry": {"coordinates":[-92.360562,36.396896],"type":"Point"}
}