{
  "type": "Feature",
  "properties": {
    "iso:country":"US",
    "sg:address":"805 Lewis St",
    "sg:city":"Little Rock",
    "sg:classifiers":[
        {
            "category":"Building & Trades",
            "subcategory":"Cleaning & Sanitation",
            "type":"Services"
        }
    ],
    "sg:phone":"+1 501 664 4098",
    "sg:postcode":"72204",
    "sg:province":"AR",
    "sg:tags":[
        "maintenance"
    ],
    "wof:name":"Rivercity Service Company",
    "wof:placetype":"venue"
},
  "geometry": {"coordinates":[-92.31986000000001,34.743362],"type":"Point"}
}