{
  "type": "Feature",
  "properties": {
    "addr:full":"1405 Bittle St Jonesboro AR 72401",
    "addr:housenumber":"1405",
    "addr:postcode":"72401",
    "addr:street":"Bittle St",
    "iso:country":"US",
    "sg:address":"1405 Bittle St",
    "sg:city":"Jonesboro",
    "sg:classifiers":[
        {
            "category":"Government",
            "subcategory":"Office",
            "type":"Public Place"
        }
    ],
    "sg:phone":"+1 870 931 3693",
    "sg:postcode":"72401",
    "sg:province":"AR",
    "sg:tags":[
        "county"
    ],
    "wof:name":"Craighead County Home Base",
    "wof:placetype":"venue"
},
  "geometry": {"coordinates":[-90.673355,35.828342],"type":"Point"}
}