{
  "type": "Feature",
  "properties": {
    "iso:country":"US",
    "sg:address":"14415 Highway 107",
    "sg:city":"Jacksonville",
    "sg:classifiers":[
        {
            "category":"Home & Garden",
            "subcategory":"Garden Supply",
            "type":"Retail Goods"
        },
        {
            "category":"Shopping",
            "subcategory":"Gifts & Souvenirs",
            "type":"Retail Goods"
        },
        {
            "category":"Shopping",
            "subcategory":"Crafts & Fabrics",
            "type":"Retail Goods"
        },
        {
            "category":"Shopping",
            "subcategory":"Florist",
            "type":"Retail Goods"
        }
    ],
    "sg:phone":"+1 501 833 2323",
    "sg:postcode":"72076",
    "sg:province":"AR",
    "sg:tags":[
        "plant",
        "etc-retail",
        "dried",
        "basket",
        "trees-silk",
        "flowers"
    ],
    "sg:website":"http://www.northpulaskiflorist.com",
    "wof:name":"North Pulaski Flower Shoppe",
    "wof:placetype":"venue"
},
  "geometry": {"coordinates":[-92.197717,34.867536],"type":"Point"}
}