{
  "type": "Feature",
  "properties": {
    "addr:full":"29 del Tara Dr Jacksonville AR 72076",
    "addr:housenumber":"29",
    "addr:postcode":"72076",
    "addr:street":"Del Tara Dr",
    "iso:country":"US",
    "sg:address":"29 del Tara Dr",
    "sg:city":"Jacksonville",
    "sg:classifiers":[
        {
            "category":"Real Estate",
            "subcategory":"Real Estate Agent",
            "type":"Services"
        }
    ],
    "sg:phone":"+1 501 982 3291",
    "sg:postcode":"72076",
    "sg:province":"AR",
    "wof:name":"Monroes Rntl Prpts Notary Svcs",
    "wof:placetype":"venue"
},
  "geometry": {"coordinates":[-92.15679900000001,34.866207],"type":"Point"}
}