{
  "type": "Feature",
  "properties": {
    "iso:country":"US",
    "sg:address":"23400 Hugh Taylor Rd",
    "sg:city":"Little Rock",
    "sg:classifiers":[
        {
            "category":"Retail",
            "subcategory":"Animal Services",
            "type":"Services"
        }
    ],
    "sg:phone":"+1 501 407 0058",
    "sg:postcode":"72210",
    "sg:province":"AR",
    "sg:tags":[
        "farm"
    ],
    "wof:name":"Daniels Horse Center Inc",
    "wof:placetype":"venue"
},
  "geometry": {"coordinates":[-92.452854,34.70817],"type":"Point"}
}