{
  "type": "Feature",
  "properties": {
    "iso:country":"US",
    "sg:address":"1101 Front St",
    "sg:city":"Conway",
    "sg:classifiers":[
        {
            "category":"Building & Trades",
            "subcategory":"Plumbing",
            "type":"Services"
        }
    ],
    "sg:phone":"+1 501 329 2951",
    "sg:postcode":"72032",
    "sg:province":"AR",
    "sg:tags":[
        "contractor",
        "system",
        "air conditioning"
    ],
    "sg:website":"http://www.freyaldenhoven.com",
    "wof:name":"Freyaldenhoven Heating & Cooling",
    "wof:placetype":"venue"
},
  "geometry": {"coordinates":[-92.442104,35.09339],"type":"Point"}
}