{
  "type": "Feature",
  "properties": {
    "addr:full":"1825 S Pulaski St Little Rock AR 72206",
    "addr:housenumber":"1825",
    "addr:postcode":"72206",
    "addr:street":"S Pulaski St",
    "iso:country":"US",
    "sg:address":"1825 S Pulaski St",
    "sg:city":"Little Rock",
    "sg:classifiers":[
        {
            "category":"Organizations",
            "subcategory":"Religious Organization",
            "type":"Services"
        }
    ],
    "sg:phone":"+1 501 374 3528",
    "sg:postcode":"72206",
    "sg:province":"AR",
    "wof:name":"Union AME Church",
    "wof:placetype":"venue"
},
  "geometry": {"coordinates":[-92.287882,34.733081],"type":"Point"}
}