{
  "type": "Feature",
  "properties": {
    "iso:country":"US",
    "sg:address":"7 Indian Wells Dr",
    "sg:city":"Holiday Island",
    "sg:classifiers":[
        {
            "category":"Professional",
            "type":"Services"
        }
    ],
    "sg:phone":"+1 479 253 5623",
    "sg:postcode":"72631",
    "sg:province":"AR",
    "sg:tags":[
        "establishment"
    ],
    "wof:name":"Walling Group",
    "wof:placetype":"venue"
},
  "geometry": {"coordinates":[-93.723975,36.458243],"type":"Point"}
}