{
  "type": "Feature",
  "properties": {
    "addr:full":"1706 Old Greensboro Rd Jonesboro AR 72401",
    "addr:housenumber":"1706",
    "addr:postcode":"72401",
    "addr:street":"Old Greensboro Rd",
    "iso:country":"US",
    "sg:address":"1706 Old Greensboro Rd",
    "sg:city":"Jonesboro",
    "sg:classifiers":[
        {
            "category":"Autos & Motor Vehicles",
            "subcategory":"Automobile Sales",
            "type":"Retail Goods"
        }
    ],
    "sg:phone":"+1 870 932 3015",
    "sg:postcode":"72401",
    "sg:province":"AR",
    "sg:tags":[
        "dealers-used",
        "car",
        "used",
        "cars-wholesale",
        "new"
    ],
    "wof:name":"Scallions Craig Auto Sales",
    "wof:placetype":"venue"
},
  "geometry": {"coordinates":[-90.656385,35.857461],"type":"Point"}
}