{
  "type": "Feature",
  "properties": {
    "iso:country":"US",
    "sg:address":"710 W 3rd St",
    "sg:city":"Hope",
    "sg:classifiers":[
        {
            "category":"Shopping",
            "type":"Retail Goods"
        }
    ],
    "sg:phone":"+1 870 722 5220",
    "sg:postcode":"71801",
    "sg:province":"AR",
    "sg:tags":[
        "paging",
        "cellular"
    ],
    "wof:name":"Pagers Plus",
    "wof:placetype":"venue"
},
  "geometry": {"coordinates":[-93.598661,33.665399],"type":"Point"}
}