{
  "type": "Feature",
  "properties": {
    "iso:country":"US",
    "sg:address":"513 N Williams St",
    "sg:city":"Carlisle",
    "sg:classifiers":[
        {
            "category":"Health Services",
            "subcategory":"Dentist",
            "type":"Services"
        }
    ],
    "sg:phone":"+1 870 552 3500",
    "sg:postcode":"72024",
    "sg:province":"AR",
    "wof:name":"Inman Family Dental Clinic",
    "wof:placetype":"venue"
},
  "geometry": {"coordinates":[-91.747615,34.78676],"type":"Point"}
}