{
  "type": "Feature",
  "properties": {
    "iso:country":"US",
    "sg:address":"1986 Sfc 415",
    "sg:city":"Forrest City",
    "sg:classifiers":[
        {
            "category":"Personal",
            "subcategory":"Beauty Salon",
            "type":"Services"
        }
    ],
    "sg:phone":"+1 870 633 9177",
    "sg:postcode":"72335",
    "sg:province":"AR",
    "sg:tags":[
        "shop"
    ],
    "wof:name":"Dottie Hatcher",
    "wof:placetype":"venue"
},
  "geometry": {"coordinates":[-90.712332,35.120923],"type":"Point"}
}