{
  "type": "Feature",
  "properties": {
    "iso:country":"US",
    "sg:address":"2827 Military Rd",
    "sg:city":"Benton",
    "sg:classifiers":[
        {
            "category":"Education",
            "subcategory":"Dance Studio",
            "type":"Public Place"
        }
    ],
    "sg:phone":"+1 501 860 8277",
    "sg:postcode":"72015",
    "sg:province":"AR",
    "wof:name":"Laura Stilwell Dance Company",
    "wof:placetype":"venue"
},
  "geometry": {"coordinates":[-92.561548,34.58811],"type":"Point"}
}