{
  "type": "Feature",
  "properties": {
    "addr:full":"210 Michelle Ave White Hall AR 71602",
    "addr:housenumber":"210",
    "addr:postcode":"71602",
    "addr:street":"Michelle Ave",
    "iso:country":"US",
    "sg:address":"210 Michelle Ave",
    "sg:city":"White Hall",
    "sg:classifiers":[
        {
            "category":"Social Services",
            "subcategory":"Child Care",
            "type":"Services"
        }
    ],
    "sg:phone":"+1 870 247 3366",
    "sg:postcode":"71602",
    "sg:province":"AR",
    "sg:tags":[
        "day"
    ],
    "wof:name":"Ms B's School Days",
    "wof:placetype":"venue"
},
  "geometry": {"coordinates":[-92.09447299999999,34.277128],"type":"Point"}
}