{
  "type": "Feature",
  "properties": {
    "iso:country":"US",
    "sg:address":"200 E Martin Luther King Jr Blvd",
    "sg:city":"Texarkana",
    "sg:classifiers":[
        {
            "category":"Banks & Credit Unions",
            "subcategory":"Bank",
            "type":"Services"
        }
    ],
    "sg:phone":"+1 870 773 6226",
    "sg:postcode":"71854",
    "sg:province":"AR",
    "wof:name":"Miller County Teachers Federal Credit Union",
    "wof:placetype":"venue"
},
  "geometry": {"coordinates":[-94.042252,33.428848],"type":"Point"}
}