{
  "type": "Feature",
  "properties": {
    "iso:country":"US",
    "sg:address":"3905 US Hwy 63",
    "sg:city":"Black Rock",
    "sg:classifiers":[
        {
            "category":"Airport",
            "type":"Transportation"
        }
    ],
    "sg:phone":"+1 870 878 6366",
    "sg:postcode":"72415",
    "sg:province":"AR",
    "sg:tags":[
        "aircraft",
        "maintenance"
    ],
    "wof:name":"Rotor Craft Inc",
    "wof:placetype":"venue"
},
  "geometry": {"coordinates":[-91.159759,36.14774],"type":"Point"}
}