{
  "type": "Feature",
  "properties": {
    "iso:country":"US",
    "sg:address":"1800 Van Buren Ave",
    "sg:city":"Mountain Home",
    "sg:classifiers":[
        {
            "category":"Manufacturing",
            "subcategory":"Printing",
            "type":"Manufacturing & Wholesale Goods"
        }
    ],
    "sg:phone":"+1 870 424 2217",
    "sg:postcode":"72653",
    "sg:province":"AR",
    "sg:tags":[
        "lithographic",
        "c",
        "commercial",
        "typesetting"
    ],
    "wof:name":"Pau Nan Printing Co",
    "wof:placetype":"venue"
},
  "geometry": {"coordinates":[-92.39564,36.36034],"type":"Point"}
}