{
  "type": "Feature",
  "properties": {
    "addr:full":"108 W Thompson St Amity AR 71921",
    "addr:housenumber":"108",
    "addr:postcode":"71921",
    "addr:street":"W Thompson St",
    "iso:country":"US",
    "sg:address":"108 W Thompson St",
    "sg:city":"Amity",
    "sg:classifiers":[
        {
            "category":"Shopping",
            "type":"Retail Goods"
        }
    ],
    "sg:phone":"+1 870 342 5050",
    "sg:postcode":"71921",
    "sg:province":"AR",
    "sg:tags":[
        "merchandise"
    ],
    "wof:name":"Susies House of Critters",
    "wof:placetype":"venue"
},
  "geometry": {"coordinates":[-93.461122,34.26502],"type":"Point"}
}