{
  "type": "Feature",
  "properties": {
    "addr:full":"1435 State Hwy 21 Kingston AR 72742",
    "addr:housenumber":"1435",
    "addr:postcode":"72742",
    "addr:street":"State Hwy 21",
    "iso:country":"US",
    "sg:address":"1435 State Hwy 21",
    "sg:city":"Kingston",
    "sg:classifiers":[
        {
            "category":"Shopping",
            "type":"Retail Goods"
        }
    ],
    "sg:phone":"+1 479 665 4186",
    "sg:postcode":"72742",
    "sg:province":"AR",
    "sg:tags":[
        "farm",
        "merchandise",
        "supply"
    ],
    "wof:name":"Armer Feed",
    "wof:placetype":"venue"
},
  "geometry": {"coordinates":[-93.473084,36.029281],"type":"Point"}
}