{
  "type": "Feature",
  "properties": {
    "iso:country":"US",
    "sg:address":"2070 State Hwy 35",
    "sg:city":"Lake Village",
    "sg:phone":"+1 870 538 5159",
    "sg:postcode":"71653",
    "sg:province":"AR",
    "sg:tags":[
        "beef",
        "farm",
        "soybean",
        "cattle",
        "rice",
        "cotton"
    ],
    "wof:name":"Mencer Farms",
    "wof:placetype":"venue"
},
  "geometry": {"coordinates":[-91.269096,33.482977],"type":"Point"}
}