{
  "type": "Feature",
  "properties": {
    "iso:country":"US",
    "sg:address":"309 E Broadway St",
    "sg:city":"Morrilton",
    "sg:classifiers":[
        {
            "category":"Banks & Credit Unions",
            "subcategory":"Bank",
            "type":"Services"
        }
    ],
    "sg:phone":"+1 501 477 5310",
    "sg:postcode":"72110",
    "sg:province":"AR",
    "wof:name":"Arvest Bank",
    "wof:placetype":"venue"
},
  "geometry": {"coordinates":[-92.742441,35.152523],"type":"Point"}
}