{
  "type": "Feature",
  "properties": {
    "addr:full":"1390 California Ave SW Camden AR 71701",
    "addr:housenumber":"1390",
    "addr:postcode":"71701",
    "addr:street":"California Ave Sw",
    "iso:country":"US",
    "sg:address":"1390 California Ave SW",
    "sg:city":"Camden",
    "sg:classifiers":[
        {
            "category":"Farming",
            "subcategory":"Nursery",
            "type":"Manufacturing & Wholesale Goods"
        },
        {
            "category":"Manufacturing",
            "subcategory":"Paper Products",
            "type":"Manufacturing & Wholesale Goods"
        }
    ],
    "sg:phone":"+1 870 836 0486",
    "sg:postcode":"71701",
    "sg:province":"AR",
    "sg:tags":[
        "bamboo",
        "tree",
        "nurseries-plants"
    ],
    "wof:name":"Southern Gardeners",
    "wof:placetype":"venue"
},
  "geometry": {"coordinates":[-92.854581,33.558582],"type":"Point"}
}