{
  "type": "Feature",
  "properties": {
    "addr:full":"2705 S Knoxville Ave Russellville AR 72802",
    "addr:housenumber":"2705",
    "addr:postcode":"72802",
    "addr:street":"S Knoxville Ave",
    "iso:country":"US",
    "sg:address":"2705 S Knoxville Ave",
    "sg:city":"Russellville",
    "sg:classifiers":[
        {
            "category":"Autos & Motor Vehicles",
            "subcategory":"Motorcycle Sales",
            "type":"Retail Goods"
        }
    ],
    "sg:phone":"+1 479 968 7233",
    "sg:postcode":"72802",
    "sg:province":"AR",
    "sg:tags":[
        "scooter"
    ],
    "wof:name":"Yamaha Kawasaki-Russellville",
    "wof:placetype":"venue"
},
  "geometry": {"coordinates":[-93.121095,35.253934],"type":"Point"}
}