{
  "type": "Feature",
  "properties": {
    "addr:full":"2106 S Caraway Rd Jonesboro AR 72401",
    "addr:housenumber":"2106",
    "addr:postcode":"72401",
    "addr:street":"S Caraway Rd",
    "iso:country":"US",
    "sg:address":"2106 S Caraway Rd",
    "sg:city":"Jonesboro",
    "sg:classifiers":[
        {
            "category":"Personal",
            "subcategory":"Beauty Salon",
            "type":"Services"
        }
    ],
    "sg:phone":"+1 870 802 1094",
    "sg:postcode":"72401",
    "sg:province":"AR",
    "sg:tags":[
        "shop"
    ],
    "wof:name":"Supercuts",
    "wof:placetype":"venue"
},
  "geometry": {"coordinates":[-90.67780500000001,35.819645],"type":"Point"}
}