{
  "type": "Feature",
  "properties": {
    "addr:full":"401 Commerce Dr Maumelle AR 72113",
    "addr:housenumber":"401",
    "addr:postcode":"72113",
    "addr:street":"Commerce Dr Maumelle",
    "iso:country":"US",
    "sg:address":"401 Commerce Dr",
    "sg:city":"Maumelle",
    "sg:classifiers":[
        {
            "category":"Social Services",
            "subcategory":"Child Care",
            "type":"Services"
        },
        {
            "category":"Education",
            "subcategory":"Preschool",
            "type":"Public Place"
        }
    ],
    "sg:phone":"+1 501 851 6578",
    "sg:postcode":"72113",
    "sg:province":"AR",
    "sg:tags":[
        "kindergarten"
    ],
    "sg:website":"http://www.brightideasco.net",
    "wof:name":"Bright Ideas Enrichment Center",
    "wof:placetype":"venue"
},
  "geometry": {"coordinates":[-92.399399,34.857491],"type":"Point"}
}