{
  "type": "Feature",
  "properties": {
    "addr:full":"4975 Malvern Rd Hot Springs AR 71901",
    "addr:housenumber":"4975",
    "addr:postcode":"71901",
    "addr:street":"Malvern Rd",
    "iso:country":"US",
    "sg:address":"4975 Malvern Rd",
    "sg:city":"Hot Springs",
    "sg:classifiers":[
        {
            "category":"Building & Trades",
            "subcategory":"Construction",
            "type":"Services"
        }
    ],
    "sg:phone":"+1 501 262 2809",
    "sg:postcode":"71901",
    "sg:province":"AR",
    "sg:tags":[
        "paving",
        "contractor"
    ],
    "wof:name":"SWC Asphalt Paving",
    "wof:placetype":"venue"
},
  "geometry": {"coordinates":[-92.91580999999999,34.466178],"type":"Point"}
}