{
  "type": "Feature",
  "properties": {
    "addr:full":"14717 State Hwy 107 Jacksonville AR 72076",
    "addr:housenumber":"14717",
    "addr:postcode":"72076",
    "addr:street":"State Hwy 107",
    "iso:country":"US",
    "sg:address":"14717 State Hwy 107",
    "sg:city":"Jacksonville",
    "sg:classifiers":[
        {
            "category":"Autos & Motor Vehicles",
            "subcategory":"Automobile Sales",
            "type":"Retail Goods"
        },
        {
            "category":"Retail",
            "subcategory":"Auto Repair",
            "type":"Services"
        }
    ],
    "sg:phone":"+1 501 833 8600",
    "sg:postcode":"72076",
    "sg:province":"AR",
    "sg:tags":[
        "body",
        "car",
        "dealer"
    ],
    "wof:name":"Brant's Collision Repair",
    "wof:placetype":"venue"
},
  "geometry": {"coordinates":[-92.17780399999999,34.881879],"type":"Point"}
}