{
  "type": "Feature",
  "properties": {
    "iso:country":"US",
    "sg:address":"2041 Greene 765 Rd",
    "sg:city":"Paragould",
    "sg:classifiers":[
        {
            "category":"Freight",
            "type":"Transportation"
        }
    ],
    "sg:phone":"+1 870 240 4353",
    "sg:postcode":"72450",
    "sg:province":"AR",
    "sg:tags":[
        "operator",
        "trucking"
    ],
    "wof:name":"TNT Hotshots",
    "wof:placetype":"venue"
},
  "geometry": {"coordinates":[-90.54904000000001,36.009861],"type":"Point"}
}