{
  "type": "Feature",
  "properties": {
    "iso:country":"US",
    "sg:address":"710 S Porter St",
    "sg:city":"Stuttgart",
    "sg:classifiers":[
        {
            "category":"Professional",
            "subcategory":"Business Services",
            "type":"Services"
        }
    ],
    "sg:phone":"+1 870 673 6499",
    "sg:postcode":"72160",
    "sg:province":"AR",
    "wof:name":"Sincerely Susans",
    "wof:placetype":"venue"
},
  "geometry": {"coordinates":[-91.555216,34.496404],"type":"Point"}
}