{
  "type": "Feature",
  "properties": {
    "addr:full":"10820 Zuber Rd Alexander AR 72002",
    "addr:housenumber":"10820",
    "addr:postcode":"72002",
    "addr:street":"Zuber Rd",
    "iso:country":"US",
    "sg:address":"10820 Zuber Rd",
    "sg:city":"Alexander",
    "sg:classifiers":[
        {
            "category":"Farming",
            "subcategory":"Nursery",
            "type":"Manufacturing & Wholesale Goods"
        }
    ],
    "sg:phone":"+1 501 316 1421",
    "sg:postcode":"72002",
    "sg:province":"AR",
    "sg:tags":[
        "ornamental"
    ],
    "wof:name":"Windy Oaks Farm",
    "wof:placetype":"venue"
},
  "geometry": {"coordinates":[-92.54754,34.659647],"type":"Point"}
}