{
  "type": "Feature",
  "properties": {
    "iso:country":"US",
    "sg:address":"1400 Phyllis St",
    "sg:city":"Bentonville",
    "sg:classifiers":[
        {
            "category":"Restaurant",
            "type":"Food & Drink"
        }
    ],
    "sg:phone":"+1 479 271 8133",
    "sg:postcode":"72712",
    "sg:province":"AR",
    "wof:name":"Subway Sandwiches & Salads",
    "wof:placetype":"venue"
},
  "geometry": {"coordinates":[-94.179655,36.358834],"type":"Point"}
}