{
  "type": "Feature",
  "properties": {
    "iso:country":"US",
    "sg:address":"1403 John Barrow Rd",
    "sg:city":"Little Rock",
    "sg:classifiers":[
        {
            "category":"Restaurant",
            "type":"Food & Drink"
        }
    ],
    "sg:phone":"+1 501 219 4277",
    "sg:postcode":"72204",
    "sg:province":"AR",
    "wof:name":"O B's Hamburgers",
    "wof:placetype":"venue"
},
  "geometry": {"coordinates":[-92.372258,34.739473],"type":"Point"}
}