{
  "type": "Feature",
  "properties": {
    "iso:country":"US",
    "sg:address":"520 N College Ave",
    "sg:city":"Fayetteville",
    "sg:classifiers":[
        {
            "category":"Retail",
            "subcategory":"Repair Shop",
            "type":"Services"
        }
    ],
    "sg:phone":"+1 479 443 2222",
    "sg:postcode":"72701",
    "sg:province":"AR",
    "sg:tags":[
        "radios-citizens",
        "radio",
        "band"
    ],
    "wof:name":"Smith Two-Way Radio Service",
    "wof:placetype":"venue"
},
  "geometry": {"coordinates":[-94.157692,36.070171],"type":"Point"}
}