{
  "type": "Feature",
  "properties": {
    "addr:full":"704 E Canal Ave Wynne AR 72396",
    "addr:housenumber":"704",
    "addr:postcode":"72396",
    "addr:street":"E Canal Ave",
    "iso:country":"US",
    "sg:address":"704 E Canal Ave",
    "sg:city":"Wynne",
    "sg:classifiers":[
        {
            "category":"Government",
            "subcategory":"Office",
            "type":"Public Place"
        }
    ],
    "sg:phone":"+1 870 238 2101",
    "sg:postcode":"72396",
    "sg:province":"AR",
    "sg:tags":[
        "county",
        "administrative",
        "program",
        "health"
    ],
    "wof:name":"Cross County Health Unit",
    "wof:placetype":"venue"
},
  "geometry": {"coordinates":[-90.78643700000001,35.221623],"type":"Point"}
}