{
  "type": "Feature",
  "properties": {
    "iso:country":"US",
    "sg:address":"2528 N West Ave",
    "sg:city":"El Dorado",
    "sg:classifiers":[
        {
            "category":"Shopping",
            "subcategory":"Musical Instruments",
            "type":"Retail Goods"
        }
    ],
    "sg:phone":"+1 870 862 7500",
    "sg:postcode":"71730",
    "sg:province":"AR",
    "sg:tags":[
        "repair"
    ],
    "wof:name":"Roys Piano & Service",
    "wof:placetype":"venue"
},
  "geometry": {"coordinates":[-92.665597,33.23724],"type":"Point"}
}