{
  "type": "Feature",
  "properties": {
    "addr:full":"1318 S Main St Hope AR 71801",
    "addr:housenumber":"1318",
    "addr:postcode":"71801",
    "addr:street":"S Main St",
    "iso:country":"US",
    "sg:address":"1318 S Main St",
    "sg:city":"Hope",
    "sg:classifiers":[
        {
            "category":"Personal",
            "subcategory":"Beauty Salon",
            "type":"Services"
        }
    ],
    "sg:phone":"+1 870 777 5988",
    "sg:postcode":"71801",
    "sg:province":"AR",
    "wof:name":"Main Attraction Hair Salon",
    "wof:placetype":"venue"
},
  "geometry": {"coordinates":[-93.588309,33.657161],"type":"Point"}
}