{
  "type": "Feature",
  "properties": {
    "iso:country":"US",
    "sg:address":"10184 Oklahoma Dr",
    "sg:city":"Rogers",
    "sg:classifiers":[
        {
            "category":"Professional",
            "subcategory":"Detective & Security Services",
            "type":"Services"
        }
    ],
    "sg:phone":"+1 479 631 6843",
    "sg:postcode":"72758",
    "sg:province":"AR",
    "sg:tags":[
        "information",
        "bureau"
    ],
    "wof:name":"New Beginnings Service",
    "wof:placetype":"venue"
},
  "geometry": {"coordinates":[-94.06594,36.286901],"type":"Point"}
}