{
  "type": "Feature",
  "properties": {
    "iso:country":"US",
    "sg:address":"9772 Maumelle Blvd",
    "sg:city":"N Little Rock",
    "sg:classifiers":[
        {
            "category":"Insurance",
            "subcategory":"Insurance Agent",
            "type":"Services"
        }
    ],
    "sg:phone":"+1 501 537 0532",
    "sg:postcode":"72113",
    "sg:province":"AR",
    "wof:name":"Financial Advisory Group Inc",
    "wof:placetype":"venue"
},
  "geometry": {"coordinates":[-92.36455599999999,34.817686],"type":"Point"}
}