{
  "type": "Feature",
  "properties": {
    "addr:full":"3400 John Barrow Rd Little Rock AR 72204",
    "addr:housenumber":"3400",
    "addr:postcode":"72204",
    "addr:street":"John Barrow Rd",
    "iso:country":"US",
    "sg:address":"3400 John Barrow Rd",
    "sg:city":"Little Rock",
    "sg:classifiers":[
        {
            "category":"Retail",
            "subcategory":"Auto Repair",
            "type":"Services"
        }
    ],
    "sg:phone":"+1 501 562 2630",
    "sg:postcode":"72204",
    "sg:province":"AR",
    "sg:tags":[
        "wrecker"
    ],
    "wof:name":"Independent Towing",
    "wof:placetype":"venue"
},
  "geometry": {"coordinates":[-92.372981,34.721622],"type":"Point"}
}