{
  "type": "Feature",
  "properties": {
    "addr:full":"111 E 1st St S Prescott AR 71857",
    "addr:housenumber":"111",
    "addr:postcode":"71857",
    "addr:street":"E 1St St S",
    "iso:country":"US",
    "sg:address":"111 E 1st St S",
    "sg:city":"Prescott",
    "sg:classifiers":[
        {
            "category":"Retail",
            "subcategory":"Laundry & Dry Cleaning",
            "type":"Services"
        }
    ],
    "sg:phone":"+1 870 887 2412",
    "sg:postcode":"71857",
    "sg:province":"AR",
    "sg:tags":[
        "drycleaning",
        "plant"
    ],
    "wof:name":"J & M Cleaners",
    "wof:placetype":"venue"
},
  "geometry": {"coordinates":[-93.38065,33.802103],"type":"Point"}
}