{
  "type": "Feature",
  "properties": {
    "addr:full":"7926 US Hwy 79 Pine Bluff AR 71603",
    "addr:housenumber":"7926",
    "addr:postcode":"71603",
    "addr:street":"Us Hwy 79",
    "iso:country":"US",
    "sg:address":"7926 US Hwy 79",
    "sg:city":"Pine Bluff",
    "sg:classifiers":[
        {
            "category":"Farming",
            "subcategory":"Livestock Farm",
            "type":"Manufacturing & Wholesale Goods"
        }
    ],
    "sg:phone":"+1 870 879 2051",
    "sg:postcode":"71603",
    "sg:province":"AR",
    "sg:tags":[
        "beef",
        "feedlot",
        "cattle"
    ],
    "wof:name":"Thomas Ashcraft",
    "wof:placetype":"venue"
},
  "geometry": {"coordinates":[-92.10193599999999,34.146825],"type":"Point"}
}