{
  "type": "Feature",
  "properties": {
    "iso:country":"US",
    "sg:address":"1911 Vera St",
    "sg:city":"Magnolia",
    "sg:classifiers":[
        {
            "category":"Organizations",
            "subcategory":"Religious Organization",
            "type":"Services"
        }
    ],
    "sg:phone":"+1 870 234 6152",
    "sg:postcode":"71753",
    "sg:province":"AR",
    "sg:tags":[
        "church"
    ],
    "wof:name":"Sunny Acres Church Of Christ",
    "wof:placetype":"venue"
},
  "geometry": {"coordinates":[-93.214565,33.280492],"type":"Point"}
}