{
  "type": "Feature",
  "properties": {
    "iso:country":"US",
    "sg:address":"713 Quandt Ave",
    "sg:city":"Springdale",
    "sg:classifiers":[
        {
            "category":"Health Services",
            "subcategory":"Doctor",
            "type":"Services"
        }
    ],
    "sg:phone":"+1 479 750 2080",
    "sg:postcode":"72764",
    "sg:province":"AR",
    "sg:tags":[
        "physician",
        "surgeon"
    ],
    "wof:name":"Springdale ENT & Hearing",
    "wof:placetype":"venue"
},
  "geometry": {"coordinates":[-94.138804,36.178779],"type":"Point"}
}