{
  "type": "Feature",
  "properties": {
    "iso:country":"US",
    "sg:address":"1705 E 5th St",
    "sg:city":"North Little Rock",
    "sg:classifiers":[
        {
            "category":"Wholesale",
            "subcategory":"Auto Parts",
            "type":"Manufacturing & Wholesale Goods"
        }
    ],
    "sg:phone":"+1 501 374 4825",
    "sg:postcode":"72114",
    "sg:province":"AR",
    "sg:tags":[
        "repair",
        "se",
        "nonresidential"
    ],
    "wof:name":"Cruzen Equipment Co Inc",
    "wof:placetype":"venue"
},
  "geometry": {"coordinates":[-92.249744,34.757408],"type":"Point"}
}