{
  "type": "Feature",
  "properties": {
    "addr:full":"1705 E 5th St North Little Rock AR 72114",
    "addr:housenumber":"1705",
    "addr:postcode":"72114",
    "addr:street":"E 5Th St",
    "iso:country":"US",
    "sg:address":"1705 E 5th St",
    "sg:city":"North Little Rock",
    "sg:classifiers":[
        {
            "category":"Wholesale",
            "subcategory":"Auto Parts",
            "type":"Manufacturing & Wholesale Goods"
        }
    ],
    "sg:phone":"+1 501 374 4825",
    "sg:postcode":"72114",
    "sg:province":"AR",
    "sg:tags":[
        "repair",
        "se",
        "nonresidential"
    ],
    "wof:name":"Cruzen Equipment Co Inc",
    "wof:placetype":"venue"
},
  "geometry": {"coordinates":[-92.24974400000001,34.757408],"type":"Point"}
}