{
  "type": "Feature",
  "properties": {
    "addr:full":"106 Lower Dam Pike Arkadelphia AR 71923",
    "addr:housenumber":"106",
    "addr:postcode":"71923",
    "addr:street":"Lower Dam Pike",
    "iso:country":"US",
    "sg:address":"106 Lower Dam Pike",
    "sg:city":"Arkadelphia",
    "sg:classifiers":[
        {
            "category":"Social Services",
            "type":"Services"
        }
    ],
    "sg:phone":"+1 870 245 2121",
    "sg:postcode":"71923",
    "sg:province":"AR",
    "sg:tags":[
        "product",
        "disability",
        "developmentally",
        "disabled",
        "need",
        "special"
    ],
    "wof:name":"Rainbow Of Challenges Inc",
    "wof:placetype":"venue"
},
  "geometry": {"coordinates":[-93.071718,34.18574],"type":"Point"}
}