{
  "type": "Feature",
  "properties": {
    "iso:country":"US",
    "sg:address":"115 Canal Rd",
    "sg:city":"Menifee",
    "sg:classifiers":[
        {
            "category":"Manufacturing",
            "subcategory":"Paper Products",
            "type":"Manufacturing & Wholesale Goods"
        }
    ],
    "sg:phone":"+1 501 354 9700",
    "sg:postcode":"72107",
    "sg:province":"AR",
    "wof:name":"International Paper Co",
    "wof:placetype":"venue"
},
  "geometry": {"coordinates":[-92.535134,35.123768],"type":"Point"}
}