{
  "type": "Feature",
  "properties": {
    "iso:country":"US",
    "sg:address":"143 Highway 8 N",
    "sg:city":"Warren",
    "sg:classifiers":[
        {
            "category":"Manufacturing",
            "subcategory":"Lumber",
            "type":"Manufacturing & Wholesale Goods"
        }
    ],
    "sg:phone":"+1 870 226 5451",
    "sg:postcode":"71671",
    "sg:province":"AR",
    "sg:tags":[
        "logging"
    ],
    "wof:name":"Bimac Inc",
    "wof:placetype":"venue"
},
  "geometry": {"coordinates":[-92.075924,33.634944],"type":"Point"}
}