{
  "type": "Feature",
  "properties": {
    "iso:country":"US",
    "sg:address":"2704 Phillips Dr",
    "sg:city":"Jonesboro",
    "sg:classifiers":[
        {
            "category":"Personal",
            "type":"Services"
        }
    ],
    "sg:phone":"+1 870 926 3900",
    "sg:postcode":"72401",
    "sg:province":"AR",
    "sg:tags":[
        "credit",
        "debt",
        "counseling"
    ],
    "wof:name":"New Horizon",
    "wof:placetype":"venue"
},
  "geometry": {"coordinates":[-90.67376899999999,35.809545],"type":"Point"}
}