{
  "type": "Feature",
  "properties": {
    "addr:full":"997 Main St Vilonia AR 72173",
    "addr:housenumber":"997",
    "addr:postcode":"72173",
    "addr:street":"Main St",
    "iso:country":"US",
    "sg:address":"997 Main St",
    "sg:city":"Vilonia",
    "sg:classifiers":[
        {
            "category":"Manufacturing",
            "subcategory":"Buildings",
            "type":"Manufacturing & Wholesale Goods"
        },
        {
            "category":"Home & Garden",
            "subcategory":"Building Materials",
            "type":"Retail Goods"
        },
        {
            "category":"Military Area",
            "subcategory":"Armory",
            "type":"Public Place"
        },
        {
            "category":"Building & Trades",
            "subcategory":"Construction",
            "type":"Services"
        }
    ],
    "sg:phone":"+1 501 796 2225",
    "sg:postcode":"72173",
    "sg:province":"AR",
    "sg:tags":[
        "repair",
        "builder",
        "fence-sales",
        "fence",
        "contractor"
    ],
    "wof:name":"G & S Fencing",
    "wof:placetype":"venue"
},
  "geometry": {"coordinates":[-92.225967,35.08213],"type":"Point"}
}