{
  "type": "Feature",
  "properties": {
    "addr:full":"329 N West Ave Fayetteville AR 72701",
    "addr:housenumber":"329",
    "addr:postcode":"72701",
    "addr:street":"N West Ave",
    "iso:country":"US",
    "sg:address":"329 N West Ave",
    "sg:city":"Fayetteville",
    "sg:classifiers":[
        {
            "category":"Shopping",
            "type":"Retail Goods"
        }
    ],
    "sg:phone":"+1 479 409 3772",
    "sg:postcode":"72701",
    "sg:province":"AR",
    "sg:tags":[
        "wedding",
        "supply"
    ],
    "wof:name":"Gelateria Peatro Scarpino",
    "wof:placetype":"venue"
},
  "geometry": {"coordinates":[-94.165447,36.066447],"type":"Point"}
}