{
  "type": "Feature",
  "properties": {
    "iso:country":"US",
    "sg:address":"204 W Railroad Ave",
    "sg:city":"Morrilton",
    "sg:classifiers":[
        {
            "category":"Building & Trades",
            "subcategory":"Construction",
            "type":"Services"
        }
    ],
    "sg:phone":"+1 501 354 6511",
    "sg:postcode":"72110",
    "sg:province":"AR",
    "sg:tags":[
        "heavy"
    ],
    "wof:name":"Crow",
    "wof:placetype":"venue"
},
  "geometry": {"coordinates":[-92.745847,35.152487],"type":"Point"}
}