{
  "type": "Feature",
  "properties": {
    "iso:country":"US",
    "sg:address":"1002 Pecan St",
    "sg:city":"Helena",
    "sg:classifiers":[
        {
            "category":"Personal",
            "subcategory":"Beauty Salon",
            "type":"Services"
        }
    ],
    "sg:phone":"+1 870 338 9701",
    "sg:postcode":"72342",
    "sg:province":"AR",
    "sg:tags":[
        "shop"
    ],
    "wof:name":"Marie's House Style",
    "wof:placetype":"venue"
},
  "geometry": {"coordinates":[-90.588387,34.533493],"type":"Point"}
}