{
  "type": "Feature",
  "properties": {
    "addr:full":"2210 State Hwy 25 B N Heber Springs AR 72543",
    "addr:housenumber":"2210;b",
    "addr:postcode":"72543",
    "addr:street":"State Hwy 25;N Heber Springs",
    "iso:country":"US",
    "sg:address":"2210 State Hwy 25 B N",
    "sg:city":"Heber Springs",
    "sg:classifiers":[
        {
            "category":"Shopping",
            "subcategory":"Tobacco",
            "type":"Retail Goods"
        }
    ],
    "sg:phone":"+1 501 362 6288",
    "sg:postcode":"72543",
    "sg:province":"AR",
    "sg:tags":[
        "product"
    ],
    "wof:name":"Heber Springs Discount Tobacco",
    "wof:placetype":"venue"
},
  "geometry": {"coordinates":[-92.029175,35.513234],"type":"Point"}
}