{
  "type": "Feature",
  "properties": {
    "iso:country":"US",
    "sg:address":"709 S Maple St",
    "sg:city":"Stuttgart",
    "sg:phone":"+1 870 673 1252",
    "sg:postcode":"72160",
    "sg:province":"AR",
    "sg:tags":[
        "farm",
        "rice",
        "soybean",
        "cotton"
    ],
    "wof:name":"Chris Stone",
    "wof:placetype":"venue"
},
  "geometry": {"coordinates":[-91.553866,34.496444],"type":"Point"}
}