{
  "type": "Feature",
  "properties": {
    "addr:full":"379 Military Rd Marion AR 72364",
    "addr:housenumber":"379",
    "addr:postcode":"72364",
    "addr:street":"Military Rd",
    "iso:country":"US",
    "sg:address":"379 Military Rd",
    "sg:city":"Marion",
    "sg:classifiers":[
        {
            "category":"Professional",
            "subcategory":"Lawyer & Legal Services",
            "type":"Services"
        }
    ],
    "sg:phone":"+1 870 739 2277",
    "sg:postcode":"72364",
    "sg:province":"AR",
    "sg:tags":[
        "attorney"
    ],
    "wof:name":"Thorne Law Firm",
    "wof:placetype":"venue"
},
  "geometry": {"coordinates":[-90.19100899999999,35.212244],"type":"Point"}
}