{
  "type": "Feature",
  "properties": {
    "addr:full":"815 Weston St Pea Ridge AR 72751",
    "addr:housenumber":"815",
    "addr:postcode":"72751",
    "addr:street":"Weston St",
    "iso:country":"US",
    "sg:address":"815 Weston St",
    "sg:city":"Pea Ridge",
    "sg:classifiers":[
        {
            "category":"Organizations",
            "subcategory":"Religious Organization",
            "type":"Services"
        }
    ],
    "sg:phone":"+1 479 451 8273",
    "sg:postcode":"72751",
    "sg:province":"AR",
    "wof:name":"Weston St Chapel",
    "wof:placetype":"venue"
},
  "geometry": {"coordinates":[-94.122589,36.447726],"type":"Point"}
}