{
  "type": "Feature",
  "properties": {
    "iso:country":"US",
    "sg:address":"118 Stella St",
    "sg:city":"Hot Springs",
    "sg:classifiers":[
        {
            "category":"Building & Trades",
            "subcategory":"Construction",
            "type":"Services"
        }
    ],
    "sg:phone":"+1 501 262 3658",
    "sg:postcode":"71901",
    "sg:province":"AR",
    "sg:tags":[
        "roofing",
        "contractor"
    ],
    "wof:name":"Freet Roofing",
    "wof:placetype":"venue"
},
  "geometry": {"coordinates":[-92.98635400000001,34.480069],"type":"Point"}
}