{
  "type": "Feature",
  "properties": {
    "addr:full":"2218 N College Ave Fayetteville AR 72703",
    "addr:housenumber":"2218",
    "addr:postcode":"72703",
    "addr:street":"N College Ave",
    "iso:country":"US",
    "sg:address":"2218 N College Ave",
    "sg:city":"Fayetteville",
    "sg:classifiers":[
        {
            "category":"Shopping",
            "subcategory":"Clothing, Apparel, & Fashions",
            "type":"Retail Goods"
        },
        {
            "category":"Banks & Credit Unions",
            "subcategory":"Investment Brokerage",
            "type":"Services"
        },
        {
            "category":"Shopping",
            "subcategory":"Computers & Home Electronics",
            "type":"Retail Goods"
        }
    ],
    "sg:phone":"+1 479 856 6000",
    "sg:postcode":"72703",
    "sg:province":"AR",
    "sg:tags":[
        "dvd",
        "sale",
        "dvds-rental",
        "lingerie",
        "tape",
        "video"
    ],
    "wof:name":"Seductions Lingerie & Video",
    "wof:placetype":"venue"
},
  "geometry": {"coordinates":[-94.153519,36.091984],"type":"Point"}
}