{
  "type": "Feature",
  "properties": {
    "iso:country":"US",
    "sg:address":"402 Main St P.O. Box 399",
    "sg:city":"Arkadelphia",
    "sg:classifiers":[
        {
            "category":"Professional",
            "subcategory":"Lawyer & Legal Services",
            "type":"Services"
        }
    ],
    "sg:phone":"+1 870 246 5886",
    "sg:postcode":"71923",
    "sg:province":"AR",
    "sg:tags":[
        "attorney",
        "criminal",
        "personal",
        "injury",
        "law",
        "bankruptcy"
    ],
    "wof:name":"Mathis, Winston C - Mathis Law Firm",
    "wof:placetype":"venue"
},
  "geometry": {"coordinates":[-93.051323,34.119541],"type":"Point"}
}