{
  "type": "Feature",
  "properties": {
    "addr:full":"4004 Harrisburg Rd Jonesboro AR 72404",
    "addr:housenumber":"4004",
    "addr:postcode":"72404",
    "addr:street":"Harrisburg Rd",
    "iso:country":"US",
    "sg:address":"4004 Harrisburg Rd",
    "sg:city":"Jonesboro",
    "sg:classifiers":[
        {
            "category":"Home & Garden",
            "subcategory":"Home Furnishings",
            "type":"Retail Goods"
        }
    ],
    "sg:phone":"+1 870 932 7930",
    "sg:postcode":"72404",
    "sg:province":"AR",
    "wof:name":"Southern Oak Interiors",
    "wof:placetype":"venue"
},
  "geometry": {"coordinates":[-90.68727,35.790192],"type":"Point"}
}