{
  "type": "Feature",
  "properties": {
    "iso:country":"US",
    "sg:address":"1416 Silver Falls",
    "sg:city":"Conway",
    "sg:classifiers":[
        {
            "category":"Insurance",
            "subcategory":"Insurance Agent",
            "type":"Services"
        }
    ],
    "sg:phone":"+1 501 733 6826",
    "sg:postcode":"72032",
    "sg:province":"AR",
    "wof:name":"Mutual Of Omaha Insurance Co",
    "wof:placetype":"venue"
},
  "geometry": {"coordinates":[-92.408632,35.077982],"type":"Point"}
}