{
  "type": "Feature",
  "properties": {
    "iso:country":"US",
    "sg:address":"6410 State Hwy 178 W",
    "sg:city":"Lakeview",
    "sg:classifiers":[
        {
            "category":"Real Estate",
            "subcategory":"Real Estate Agent",
            "type":"Services"
        }
    ],
    "sg:phone":"+1 870 431 7000",
    "sg:postcode":"72642",
    "sg:province":"AR",
    "wof:name":"Arkansas Ozarks Realty",
    "wof:placetype":"venue"
},
  "geometry": {"coordinates":[-92.552306,36.36644],"type":"Point"}
}