{
  "type": "Feature",
  "properties": {
    "addr:full":"24 Champions Blvd Rogers AR 72758",
    "addr:housenumber":"24",
    "addr:postcode":"72758",
    "addr:street":"Champions Blvd",
    "iso:country":"US",
    "sg:address":"24 Champions Blvd",
    "sg:city":"Rogers",
    "sg:classifiers":[
        {
            "category":"Education",
            "subcategory":"Library",
            "type":"Public Place"
        }
    ],
    "sg:phone":"+1 479 273 9069",
    "sg:postcode":"72758",
    "sg:province":"AR",
    "wof:name":"Archer Library",
    "wof:placetype":"venue"
},
  "geometry": {"coordinates":[-94.193299,36.296665],"type":"Point"}
}