{
  "type": "Feature",
  "properties": {
    "iso:country":"US",
    "sg:address":"201 N 2nd St",
    "sg:city":"Paragould",
    "sg:classifiers":[
        {
            "category":"Autos & Motor Vehicles",
            "subcategory":"Fuel & Gas Station",
            "type":"Retail Goods"
        }
    ],
    "sg:phone":"+1 870 239 8190",
    "sg:postcode":"72450",
    "sg:province":"AR",
    "sg:tags":[
        "oil"
    ],
    "wof:name":"Ebco 2nd & Poplar",
    "wof:placetype":"venue"
},
  "geometry": {"coordinates":[-90.487347,36.057252],"type":"Point"}
}