{
  "type": "Feature",
  "properties": {
    "iso:country":"US",
    "sg:address":"114 W 3rd St",
    "sg:city":"Fordyce",
    "sg:classifiers":[
        {
            "category":"Shopping",
            "subcategory":"Crafts & Fabrics",
            "type":"Retail Goods"
        }
    ],
    "sg:phone":"+1 870 352 8400",
    "sg:postcode":"71742",
    "sg:province":"AR",
    "sg:tags":[
        "piece"
    ],
    "wof:name":"Fabric and Gift Shop",
    "wof:placetype":"venue"
},
  "geometry": {"coordinates":[-92.412563,33.812879],"type":"Point"}
}