{
  "type": "Feature",
  "properties": {
    "iso:country":"US",
    "sg:address":"22213 State Hwy 107",
    "sg:city":"Jacksonville",
    "sg:classifiers":[
        {
            "category":"Autos & Motor Vehicles",
            "subcategory":"Automobile Sales",
            "type":"Retail Goods"
        },
        {
            "category":"Wholesale",
            "subcategory":"Motor Vehicles",
            "type":"Manufacturing & Wholesale Goods"
        }
    ],
    "sg:phone":"+1 501 988 2979",
    "sg:postcode":"72076",
    "sg:province":"AR",
    "sg:tags":[
        "car",
        "dealer"
    ],
    "wof:name":"Brockinton Herring Motors Inc",
    "wof:placetype":"venue"
},
  "geometry": {"coordinates":[-92.169111,34.925168],"type":"Point"}
}