{
  "type": "Feature",
  "properties": {
    "iso:country":"US",
    "sg:address":"120 Amanda Pl",
    "sg:city":"Hot Springs",
    "sg:classifiers":[
        {
            "category":"Wholesale",
            "subcategory":"Construction Materials",
            "type":"Manufacturing & Wholesale Goods"
        },
        {
            "category":"Manufacturing",
            "subcategory":"Lumber",
            "type":"Manufacturing & Wholesale Goods"
        }
    ],
    "sg:phone":"+1 501 262 5594",
    "sg:postcode":"71901",
    "sg:province":"AR",
    "sg:tags":[
        "timberland",
        "operation",
        "timber",
        "company",
        "tract"
    ],
    "wof:name":"Jester Timber",
    "wof:placetype":"venue"
},
  "geometry": {"coordinates":[-92.92251400000001,34.470576],"type":"Point"}
}