{
  "type": "Feature",
  "properties": {
    "iso:country":"US",
    "sg:address":"557 Locust St",
    "sg:city":"Conway",
    "sg:classifiers":[
        {
            "category":"Professional",
            "subcategory":"Lawyer & Legal Services",
            "type":"Services"
        }
    ],
    "sg:phone":"+1 501 932 7626",
    "sg:postcode":"72034",
    "sg:province":"AR",
    "sg:tags":[
        "attorney"
    ],
    "wof:name":"Hyden Miron & Foster",
    "wof:placetype":"venue"
},
  "geometry": {"coordinates":[-92.441227,35.085938],"type":"Point"}
}