{
  "type": "Feature",
  "properties": {
    "iso:country":"US",
    "sg:address":"351 Township Rd",
    "sg:city":"Pocahontas",
    "sg:classifiers":[
        {
            "category":"Organizations",
            "subcategory":"Membership Organization",
            "type":"Services"
        }
    ],
    "sg:phone":"+1 870 892 3604",
    "sg:postcode":"72455",
    "sg:province":"AR",
    "wof:name":"Natural State Water Protection",
    "wof:placetype":"venue"
},
  "geometry": {"coordinates":[-91.142702,36.421312],"type":"Point"}
}