{
  "type": "Feature",
  "properties": {
    "addr:full":"1031 E Main St Blytheville AR 72315",
    "addr:housenumber":"1031",
    "addr:postcode":"72315",
    "addr:street":"E Main St",
    "iso:country":"US",
    "sg:address":"1031 E Main St",
    "sg:city":"Blytheville",
    "sg:classifiers":[
        {
            "category":"Restaurant",
            "type":"Food & Drink"
        }
    ],
    "sg:menulink":"http://www.allmenus.com/ar/chickasawba/190330-mcdonalds/menu/",
    "sg:postcode":"72315",
    "sg:province":"AR",
    "sg:tags":[
        "burger",
        "american"
    ],
    "wof:name":"McDonald's",
    "wof:placetype":"venue"
},
  "geometry": {"coordinates":[-89.893075,35.927362],"type":"Point"}
}