{
  "type": "Feature",
  "properties": {
    "iso:country":"US",
    "sg:address":"2724 Old Uniontown Rd",
    "sg:city":"Van Buren",
    "sg:classifiers":[
        {
            "category":"Food & Beverages",
            "subcategory":"Groceries & Convenience Stores",
            "type":"Retail Goods"
        }
    ],
    "sg:phone":"+1 479 474 5882",
    "sg:postcode":"72956",
    "sg:province":"AR",
    "wof:name":"Union Station",
    "wof:placetype":"venue"
},
  "geometry": {"coordinates":[-94.369951,35.481208],"type":"Point"}
}