{
  "type": "Feature",
  "properties": {
    "iso:country":"US",
    "sg:address":"1300 S Falls Blvd",
    "sg:city":"Wynne",
    "sg:classifiers":[
        {
            "category":"Communications",
            "subcategory":"Radio Station",
            "type":"Services"
        }
    ],
    "sg:phone":"+1 870 208 8759",
    "sg:postcode":"72396",
    "sg:province":"AR",
    "sg:tags":[
        "company",
        "broadcasting"
    ],
    "wof:name":"KWYN Radio Station",
    "wof:placetype":"venue"
},
  "geometry": {"coordinates":[-90.789094,35.212192],"type":"Point"}
}