{
  "type": "Feature",
  "properties": {
    "iso:country":"US",
    "sg:address":"1405 W 19th St",
    "sg:city":"El Dorado",
    "sg:classifiers":[
        {
            "category":"Building & Trades",
            "subcategory":"Landscaping Services",
            "type":"Services"
        }
    ],
    "sg:phone":"+1 870 863 8407",
    "sg:postcode":"71730",
    "sg:province":"AR",
    "sg:tags":[
        "tree"
    ],
    "wof:name":"Mac's Tree Svc Inc",
    "wof:placetype":"venue"
},
  "geometry": {"coordinates":[-92.68223999999999,33.243775],"type":"Point"}
}