{
  "type": "Feature",
  "properties": {
    "iso:country":"US",
    "sg:address":"3623 West Chestnut",
    "sg:city":"Rogers",
    "sg:classifiers":[
        {
            "category":"Arts & Performance",
            "subcategory":"Arts Center",
            "type":"Entertainment"
        }
    ],
    "sg:postcode":"72756",
    "sg:province":"AR",
    "sg:tags":[
        "performing"
    ],
    "sg:website":"danceandswing.biz",
    "wof:name":"Dance and Swing",
    "wof:placetype":"venue"
},
  "geometry": {"coordinates":[-94.168998,36.335611],"type":"Point"}
}