{
  "type": "Feature",
  "properties": {
    "addr:full":"803 Harkrider St Conway AR 72032",
    "addr:housenumber":"803",
    "addr:postcode":"72032",
    "addr:street":"Harkrider St",
    "iso:country":"US",
    "sg:address":"803 Harkrider St",
    "sg:city":"Conway",
    "sg:phone":"+1 501 513 0170",
    "sg:postcode":"72032",
    "sg:province":"AR",
    "sg:tags":[
        "product",
        "petroleum"
    ],
    "wof:name":"Lion Oil Company",
    "wof:placetype":"venue"
},
  "geometry": {"coordinates":[-92.436764,35.091782],"type":"Point"}
}