{
  "type": "Feature",
  "properties": {
    "iso:country":"US",
    "sg:address":"1229 Co Rd 663",
    "sg:city":"Oak Grove",
    "sg:classifiers":[
        {
            "category":"Travel",
            "subcategory":"Campground",
            "type":"Entertainment"
        }
    ],
    "sg:phone":"+1 870 749 2377",
    "sg:postcode":"72660",
    "sg:province":"AR",
    "sg:tags":[
        "trailer"
    ],
    "wof:name":"Outdoor Resorts Of The Ozarks",
    "wof:placetype":"venue"
},
  "geometry": {"coordinates":[-93.308415,36.483521],"type":"Point"}
}