{
  "type": "Feature",
  "properties": {
    "addr:full":"124 E Moultrie Dr Blytheville AR 72315",
    "addr:housenumber":"124",
    "addr:postcode":"72315",
    "addr:street":"E Moultrie Dr Blytheville",
    "iso:country":"US",
    "sg:address":"124 E Moultrie Dr",
    "sg:city":"Blytheville",
    "sg:classifiers":[
        {
            "category":"Professional",
            "type":"Services"
        }
    ],
    "sg:phone":"+1 870 763 7473",
    "sg:postcode":"72315",
    "sg:province":"AR",
    "wof:name":"Somebody Else Handyman Service",
    "wof:placetype":"venue"
},
  "geometry": {"coordinates":[-89.902204,35.936474],"type":"Point"}
}