{
  "type": "Feature",
  "properties": {
    "addr:full":"1905 Community St Texarkana AR 71854",
    "addr:housenumber":"1905",
    "addr:postcode":"71854",
    "addr:street":"Community St",
    "iso:country":"US",
    "sg:address":"1905 Community St",
    "sg:city":"Texarkana",
    "sg:classifiers":[
        {
            "category":"Retail",
            "subcategory":"Auto Repair",
            "type":"Services"
        }
    ],
    "sg:phone":"+1 870 773 7738",
    "sg:postcode":"71854",
    "sg:province":"AR",
    "sg:tags":[
        "transmission"
    ],
    "wof:name":"J C's Transmissions",
    "wof:placetype":"venue"
},
  "geometry": {"coordinates":[-94.035769,33.402026],"type":"Point"}
}