{
  "type": "Feature",
  "properties": {
    "iso:country":"US",
    "sg:address":"303 W Capitol Ave",
    "sg:city":"Little Rock",
    "sg:classifiers":[
        {
            "category":"Professional",
            "subcategory":"Credit Reporting & Collection",
            "type":"Services"
        }
    ],
    "sg:phone":"+1 501 375 1565",
    "sg:postcode":"72201",
    "sg:province":"AR",
    "sg:tags":[
        "bureau"
    ],
    "wof:name":"Transunion LLC",
    "wof:placetype":"venue"
},
  "geometry": {"coordinates":[-92.274062,34.744485],"type":"Point"}
}