{
  "type": "Feature",
  "properties": {
    "iso:country":"US",
    "sg:address":"336 Oxford Cv",
    "sg:city":"Jonesboro",
    "sg:classifiers":[
        {
            "category":"Structure",
            "subcategory":"Office Building",
            "type":"Public Place"
        }
    ],
    "sg:phone":"+1 870 931 5918",
    "sg:postcode":"72404",
    "sg:province":"AR",
    "sg:tags":[
        "park"
    ],
    "wof:name":"Teamwork Properties",
    "wof:placetype":"venue"
},
  "geometry": {"coordinates":[-90.711142,35.79768],"type":"Point"}
}