{
  "type": "Feature",
  "properties": {
    "iso:country":"US",
    "sg:address":"916 Dyer St",
    "sg:city":"Malvern",
    "sg:classifiers":[
        {
            "category":"Freight",
            "type":"Transportation"
        }
    ],
    "sg:phone":"+1 501 337 7740",
    "sg:postcode":"72104",
    "sg:province":"AR",
    "sg:tags":[
        "trucking"
    ],
    "wof:name":"K & M Express Inc",
    "wof:placetype":"venue"
},
  "geometry": {"coordinates":[-92.810745,34.360058],"type":"Point"}
}