{
  "type": "Feature",
  "properties": {
    "iso:country":"US",
    "sg:address":"7289 Harrison St",
    "sg:city":"Sulphur Rock",
    "sg:classifiers":[
        {
            "category":"Wholesale",
            "subcategory":"Electrical",
            "type":"Manufacturing & Wholesale Goods"
        }
    ],
    "sg:phone":"+1 870 799 3800",
    "sg:postcode":"72579",
    "sg:province":"AR",
    "sg:tags":[
        "fire",
        "alarm",
        "system"
    ],
    "wof:name":"Extreme Apparatus",
    "wof:placetype":"venue"
},
  "geometry": {"coordinates":[-91.499308,35.743969],"type":"Point"}
}