{
  "type": "Feature",
  "properties": {
    "iso:country":"US",
    "sg:address":"12297 Hwy 84",
    "sg:city":"Bismarck",
    "sg:classifiers":[
        {
            "category":"Building & Trades",
            "subcategory":"Construction",
            "type":"Services"
        }
    ],
    "sg:phone":"+1 501 865 4546",
    "sg:postcode":"71929",
    "sg:province":"AR",
    "sg:tags":[
        "grading",
        "contractor"
    ],
    "wof:name":"Hot Springs County Road Dept",
    "wof:placetype":"venue"
},
  "geometry": {"coordinates":[-93.163273,34.320124],"type":"Point"}
}