{
  "type": "Feature",
  "properties": {
    "iso:country":"US",
    "sg:address":"2080 S Armstrong Rd",
    "sg:city":"Fayetteville",
    "sg:classifiers":[
        {
            "category":"Organizations",
            "subcategory":"Membership Organization",
            "type":"Services"
        },
        {
            "category":"Arena",
            "subcategory":"Sports Club",
            "type":"Entertainment"
        }
    ],
    "sg:phone":"+1 479 521 7897",
    "sg:postcode":"72701",
    "sg:province":"AR",
    "sg:tags":[
        "athletic"
    ],
    "wof:name":"Babe Ruth Baseball Park",
    "wof:placetype":"venue"
},
  "geometry": {"coordinates":[-94.13600700000001,36.041362],"type":"Point"}
}