{
  "type": "Feature",
  "properties": {
    "iso:country":"US",
    "sg:address":"408 S Reynolds Rd",
    "sg:city":"Bryant",
    "sg:classifiers":[
        {
            "category":"Social Services",
            "subcategory":"Child Care",
            "type":"Services"
        }
    ],
    "sg:phone":"+1 501 847 3016",
    "sg:postcode":"72022",
    "sg:province":"AR",
    "wof:name":"Jelly Bean Junction",
    "wof:placetype":"venue"
},
  "geometry": {"coordinates":[-92.489853,34.591612],"type":"Point"}
}