{
  "type": "Feature",
  "properties": {
    "iso:country":"US",
    "sg:address":"279 Madison 8615",
    "sg:city":"Huntsville",
    "sg:classifiers":[
        {
            "category":"Retail",
            "subcategory":"Auto Repair",
            "type":"Services"
        }
    ],
    "sg:phone":"+1 479 789 5336",
    "sg:postcode":"72740",
    "sg:province":"AR",
    "wof:name":"Todd's Service Center",
    "wof:placetype":"venue"
},
  "geometry": {"coordinates":[-93.797311,36.23391],"type":"Point"}
}