{
  "type": "Feature",
  "properties": {
    "addr:full":"1122 3rd St Earle AR 72331",
    "addr:housenumber":"1122",
    "addr:postcode":"72331",
    "addr:street":"3Rd St",
    "iso:country":"US",
    "sg:address":"1122 3rd St",
    "sg:city":"Earle",
    "sg:classifiers":[
        {
            "category":"Freight",
            "type":"Transportation"
        }
    ],
    "sg:phone":"+1 870 792 7765",
    "sg:postcode":"72331",
    "sg:province":"AR",
    "sg:tags":[
        "operator",
        "local",
        "trucking"
    ],
    "wof:name":"G&D Crosby Trucking Inc",
    "wof:placetype":"venue"
},
  "geometry": {"coordinates":[-90.466137,35.271771],"type":"Point"}
}