{
  "type": "Feature",
  "properties": {
    "iso:country":"US",
    "sg:address":"301 N Chestnut St",
    "sg:city":"Warren",
    "sg:classifiers":[
        {
            "category":"Education",
            "subcategory":"School",
            "type":"Public Place"
        }
    ],
    "sg:phone":"+1 870 226 3472",
    "sg:postcode":"71671",
    "sg:province":"AR",
    "sg:tags":[
        "child",
        "day",
        "care"
    ],
    "wof:name":"Me We Daycare",
    "wof:placetype":"venue"
},
  "geometry": {"coordinates":[-92.06187199999999,33.61736],"type":"Point"}
}