{
  "type": "Feature",
  "properties": {
    "addr:full":"201 N 10th St Arkadelphia AR 71923",
    "addr:housenumber":"201",
    "addr:postcode":"71923",
    "addr:street":"N 10Th St",
    "iso:country":"US",
    "sg:address":"201 N 10th St",
    "sg:city":"Arkadelphia",
    "sg:classifiers":[
        {
            "category":"Professional",
            "subcategory":"Lawyer & Legal Services",
            "type":"Services"
        }
    ],
    "sg:phone":"+1 870 246 9868",
    "sg:postcode":"71923",
    "sg:province":"AR",
    "sg:tags":[
        "attorney"
    ],
    "wof:name":"Henry Morgan",
    "wof:placetype":"venue"
},
  "geometry": {"coordinates":[-93.05709299999999,34.12316],"type":"Point"}
}