{
  "type": "Feature",
  "properties": {
    "iso:country":"US",
    "sg:address":"2821 Port Rd",
    "sg:city":"Pine Bluff",
    "sg:classifiers":[
        {
            "category":"Wholesale",
            "subcategory":"Beer",
            "type":"Manufacturing & Wholesale Goods"
        }
    ],
    "sg:phone":"+1 870 536 0460",
    "sg:postcode":"71601",
    "sg:province":"AR",
    "sg:tags":[
        "ale"
    ],
    "wof:name":"Three Rivers Distributing Co",
    "wof:placetype":"venue"
},
  "geometry": {"coordinates":[-91.970183,34.228966],"type":"Point"}
}