{
  "type": "Feature",
  "properties": {
    "iso:country":"US",
    "sg:address":"1107 SW 2nd St",
    "sg:city":"Bentonville",
    "sg:classifiers":[
        {
            "category":"Social Services",
            "type":"Services"
        },
        {
            "category":"Professional",
            "subcategory":"Employment Agencies",
            "type":"Services"
        }
    ],
    "sg:phone":"+1 479 273 9991",
    "sg:postcode":"72712",
    "sg:province":"AR",
    "sg:tags":[
        "workers'",
        "placement",
        "volunteer"
    ],
    "wof:name":"Off The Grid Foundation",
    "wof:placetype":"venue"
},
  "geometry": {"coordinates":[-94.224099,36.371671],"type":"Point"}
}