{
  "type": "Feature",
  "properties": {
    "iso:country":"US",
    "sg:address":"5508 Pinnacle Point Dr Ste B",
    "sg:city":"Rogers",
    "sg:classifiers":[
        {
            "category":"Retail",
            "subcategory":"Portrait Studio",
            "type":"Services"
        },
        {
            "category":"Professional",
            "subcategory":"Art Services",
            "type":"Services"
        }
    ],
    "sg:phone":"+1 479 845 0055",
    "sg:postcode":"72758",
    "sg:province":"AR",
    "sg:tags":[
        "photographers-portrait",
        "darkroom",
        "rental",
        "photography",
        "photographic",
        "store"
    ],
    "sg:website":"www.studio55photos.com",
    "wof:name":"Studio 55",
    "wof:placetype":"venue"
},
  "geometry": {"coordinates":[-94.189598,36.312],"type":"Point"}
}