{
  "type": "Feature",
  "properties": {
    "iso:country":"US",
    "sg:address":"412 W Gilson Ave",
    "sg:city":"De Queen",
    "sg:classifiers":[
        {
            "category":"Restaurant",
            "type":"Food & Drink"
        }
    ],
    "sg:phone":"+1 870 642 9684",
    "sg:postcode":"71832",
    "sg:province":"AR",
    "sg:tags":[
        "eating"
    ],
    "wof:name":"Rameriz Vincencio",
    "wof:placetype":"venue"
},
  "geometry": {"coordinates":[-94.342539,34.035793],"type":"Point"}
}