{
  "type": "Feature",
  "properties": {
    "iso:country":"US",
    "sg:address":"1104 Layman Dr",
    "sg:city":"Jonesboro",
    "sg:classifiers":[
        {
            "category":"Food & Beverages",
            "subcategory":"Liquor & Beverages",
            "type":"Retail Goods"
        },
        {
            "category":"Food & Beverages",
            "subcategory":"Groceries & Convenience Stores",
            "type":"Retail Goods"
        }
    ],
    "sg:phone":"+1 870 815 0337",
    "sg:postcode":"72404",
    "sg:province":"AR",
    "sg:tags":[
        "juice",
        "bottler",
        "beverages-distributors"
    ],
    "wof:name":"Juice Plus",
    "wof:placetype":"venue"
},
  "geometry": {"coordinates":[-90.724545,35.792397],"type":"Point"}
}