{
  "type": "Feature",
  "properties": {
    "addr:full":"180 Randall Dixon Rd Center Ridge AR 72027",
    "addr:housenumber":"180",
    "addr:postcode":"72027",
    "addr:street":"Randall Dixon Rd",
    "iso:country":"US",
    "sg:address":"180 Randall Dixon Rd",
    "sg:city":"Center Ridge",
    "sg:classifiers":[
        {
            "category":"Farming",
            "subcategory":"Dairy Farm",
            "type":"Manufacturing & Wholesale Goods"
        }
    ],
    "sg:phone":"+1 501 893 2482",
    "sg:postcode":"72027",
    "sg:province":"AR",
    "wof:name":"Dixon Dairy Farm",
    "wof:placetype":"venue"
},
  "geometry": {"coordinates":[-92.58393100000001,35.349152],"type":"Point"}
}