{
  "type": "Feature",
  "properties": {
    "iso:country":"US",
    "sg:address":"139 Hellams Ln",
    "sg:city":"Mena",
    "sg:classifiers":[
        {
            "category":"Travel",
            "subcategory":"Hotels & Motels",
            "type":"Entertainment"
        }
    ],
    "sg:phone":"+1 479 394 4471",
    "sg:postcode":"71953",
    "sg:province":"AR",
    "sg:tags":[
        "operation"
    ],
    "wof:name":"A Mews Inc",
    "wof:placetype":"venue"
},
  "geometry": {"coordinates":[-94.343066,34.689707],"type":"Point"}
}