{
  "type": "Feature",
  "properties": {
    "iso:country":"US",
    "sg:address":"200 S Moseley Rd",
    "sg:city":"Fordyce",
    "sg:classifiers":[
        {
            "category":"Farming",
            "subcategory":"Nursery",
            "type":"Manufacturing & Wholesale Goods"
        }
    ],
    "sg:phone":"+1 870 352 5650",
    "sg:postcode":"71742",
    "sg:province":"AR",
    "sg:tags":[
        "greenhouse"
    ],
    "wof:name":"Paul's Plants",
    "wof:placetype":"venue"
},
  "geometry": {"coordinates":[-92.43047,33.80916],"type":"Point"}
}