{
  "type": "Feature",
  "properties": {
    "iso:country":"US",
    "sg:address":"14844 N Oak St",
    "sg:city":"Garfield",
    "sg:classifiers":[
        {
            "category":"Autos & Motor Vehicles",
            "subcategory":"Automobile Sales",
            "type":"Retail Goods"
        }
    ],
    "sg:phone":"+1 479 359 9222",
    "sg:postcode":"72732",
    "sg:province":"AR",
    "sg:tags":[
        "classic"
    ],
    "wof:name":"4-B's Auto Sales",
    "wof:placetype":"venue"
},
  "geometry": {"coordinates":[-93.973813,36.449265],"type":"Point"}
}