{
  "type": "Feature",
  "properties": {
    "addr:full":"710 S Caraway Rd Jonesboro AR 72401",
    "addr:housenumber":"710",
    "addr:postcode":"72401",
    "addr:street":"S Caraway Rd",
    "iso:country":"US",
    "sg:address":"710 S Caraway Rd",
    "sg:city":"Jonesboro",
    "sg:classifiers":[
        {
            "category":"Restaurant",
            "type":"Food & Drink"
        }
    ],
    "sg:menulink":"http://www.allmenus.com/ar/jonesboro/173969-wendys/menu/",
    "sg:phone":"+1 870 932 0071",
    "sg:postcode":"72401",
    "sg:province":"AR",
    "sg:tags":[
        "burger",
        "american",
        "soup"
    ],
    "wof:name":"Wendy's",
    "wof:placetype":"venue"
},
  "geometry": {"coordinates":[-90.67728700000001,35.837843],"type":"Point"}
}