{
  "type": "Feature",
  "properties": {
    "iso:country":"US",
    "sg:address":"215 Bell St",
    "sg:city":"Trumann",
    "sg:classifiers":[
        {
            "category":"Wholesale",
            "subcategory":"Machinery & Supplies",
            "type":"Manufacturing & Wholesale Goods"
        }
    ],
    "sg:phone":"+1 870 483 7606",
    "sg:postcode":"72472",
    "sg:province":"AR",
    "sg:tags":[
        "material",
        "ink"
    ],
    "wof:name":"MFA Inc",
    "wof:placetype":"venue"
},
  "geometry": {"coordinates":[-90.515494,35.665655],"type":"Point"}
}