{
  "type": "Feature",
  "properties": {
    "iso:country":"US",
    "sg:address":"5309 Bryant Pl",
    "sg:city":"Springdale",
    "sg:classifiers":[
        {
            "category":"Building & Trades",
            "subcategory":"Construction",
            "type":"Services"
        }
    ],
    "sg:phone":"+1 479 756 4169",
    "sg:postcode":"72764",
    "sg:province":"AR",
    "sg:tags":[
        "fire",
        "restoration",
        "damage"
    ],
    "wof:name":"Servicemaster By Quality",
    "wof:placetype":"venue"
},
  "geometry": {"coordinates":[-94.149284,36.13734],"type":"Point"}
}