{
  "type": "Feature",
  "properties": {
    "iso:country":"US",
    "sg:address":"6208 Greenbank Rd",
    "sg:city":"North Little Rock",
    "sg:classifiers":[
        {
            "category":"Manufacturing",
            "subcategory":"Electronics",
            "type":"Manufacturing & Wholesale Goods"
        }
    ],
    "sg:phone":"+1 501 771 2907",
    "sg:postcode":"72118",
    "sg:province":"AR",
    "sg:tags":[
        "electronic",
        "component",
        "mfg"
    ],
    "wof:name":"R T Electrical Sales Inc",
    "wof:placetype":"venue"
},
  "geometry": {"coordinates":[-92.259346,34.81169],"type":"Point"}
}