{
  "type": "Feature",
  "properties": {
    "addr:full":"109 Bradford Ln Mc Rae AR 72102",
    "addr:housenumber":"109",
    "addr:postcode":"72102",
    "addr:street":"Bradford Ln Mc Rae",
    "iso:country":"US",
    "sg:address":"109 Bradford Ln",
    "sg:city":"Mc Rae",
    "sg:classifiers":[
        {
            "category":"Recreation",
            "type":"Entertainment"
        }
    ],
    "sg:phone":"+1 501 726 0012",
    "sg:postcode":"72102",
    "sg:province":"AR",
    "sg:tags":[
        "guide"
    ],
    "wof:name":"Graco Fishing & Rental Tools",
    "wof:placetype":"venue"
},
  "geometry": {"coordinates":[-91.829256,35.125926],"type":"Point"}
}