{
  "type": "Feature",
  "properties": {
    "iso:country":"US",
    "sg:address":"11715 Rainwood Rd",
    "sg:city":"Little Rock",
    "sg:classifiers":[
        {
            "category":"Insurance",
            "subcategory":"Insurance Agent",
            "type":"Services"
        }
    ],
    "sg:phone":"+1 501 224 0070",
    "sg:postcode":"72212",
    "sg:province":"AR",
    "wof:name":"State Farm Insurance",
    "wof:placetype":"venue"
},
  "geometry": {"coordinates":[-92.401923,34.768726],"type":"Point"}
}