{
  "type": "Feature",
  "properties": {
    "iso:country":"US",
    "sg:address":"2805 N Dixieland Rd",
    "sg:city":"Rogers",
    "sg:classifiers":[
        {
            "category":"Organizations",
            "subcategory":"Religious Organization",
            "type":"Services"
        }
    ],
    "sg:phone":"+1 479 936 9838",
    "sg:postcode":"72756",
    "sg:province":"AR",
    "sg:tags":[
        "church"
    ],
    "sg:website":"www.lds.org",
    "wof:name":"Church Of Jesus Christ Of Lds",
    "wof:placetype":"venue"
},
  "geometry": {"coordinates":[-94.142974,36.359045],"type":"Point"}
}