{
  "type": "Feature",
  "properties": {
    "iso:country":"US",
    "sg:address":"501 Hickory Ave",
    "sg:city":"Mena",
    "sg:classifiers":[
        {
            "category":"Government",
            "subcategory":"Office",
            "type":"Public Place"
        }
    ],
    "sg:phone":"+1 479 394 2333",
    "sg:postcode":"71953",
    "sg:province":"OK",
    "sg:tags":[
        "state",
        "taxation"
    ],
    "wof:name":"Revenue Dept",
    "wof:placetype":"venue"
},
  "geometry": {"coordinates":[-94.23898699999999,34.587517],"type":"Point"}
}