{
  "type": "Feature",
  "properties": {
    "iso:country":"US",
    "sg:address":"13313 Green Rd",
    "sg:city":"West Fork",
    "sg:classifiers":[
        {
            "category":"Building & Trades",
            "subcategory":"Construction",
            "type":"Services"
        }
    ],
    "sg:phone":"+1 479 839 3330",
    "sg:postcode":"72774",
    "sg:province":"AR",
    "sg:tags":[
        "hanging",
        "painter",
        "contractor"
    ],
    "wof:name":"C R Painting",
    "wof:placetype":"venue"
},
  "geometry": {"coordinates":[-94.141782,35.923438],"type":"Point"}
}