{
  "type": "Feature",
  "properties": {
    "iso:country":"US",
    "sg:address":"1403 S Edgewood St",
    "sg:city":"Hope",
    "sg:classifiers":[
        {
            "category":"Shopping",
            "type":"Retail Goods"
        }
    ],
    "sg:phone":"+1 870 777 1848",
    "sg:postcode":"71801",
    "sg:province":"AR",
    "sg:tags":[
        "merchandise"
    ],
    "wof:name":"Extreme Athletic Corp",
    "wof:placetype":"venue"
},
  "geometry": {"coordinates":[-93.582752,33.656152],"type":"Point"}
}