{
  "type": "Feature",
  "properties": {
    "iso:country":"US",
    "sg:address":"257 Country Club Rd",
    "sg:city":"Winthrop",
    "sg:classifiers":[
        {
            "category":"Real Estate",
            "subcategory":"Real Estate Agent",
            "type":"Services"
        }
    ],
    "sg:phone":"+1 870 381 7600",
    "sg:postcode":"71866",
    "sg:province":"AR",
    "wof:name":"Blackmon Real Estate Svc",
    "wof:placetype":"venue"
},
  "geometry": {"coordinates":[-94.411337,33.920957],"type":"Point"}
}