{
  "type": "Feature",
  "properties": {
    "addr:full":"173 S 3rd Ave Piggott AR 72454",
    "addr:housenumber":"173",
    "addr:postcode":"72454",
    "addr:street":"S 3Rd Ave",
    "iso:country":"US",
    "sg:address":"173 S 3rd Ave",
    "sg:city":"Piggott",
    "sg:classifiers":[
        {
            "category":"Insurance",
            "subcategory":"Insurance Agent",
            "type":"Services"
        }
    ],
    "sg:phone":"+1 870 598 2808",
    "sg:postcode":"72454",
    "sg:province":"AR",
    "sg:tags":[
        "agency"
    ],
    "sg:website":"http://www.statefarm.com",
    "wof:name":"State Farm Insurance",
    "wof:placetype":"venue"
},
  "geometry": {"coordinates":[-90.193088,36.382435],"type":"Point"}
}