{
  "type": "Feature",
  "properties": {
    "iso:country":"US",
    "sg:address":"110 Huntsville Rd",
    "sg:city":"Eureka Springs",
    "sg:classifiers":[
        {
            "category":"Travel",
            "subcategory":"Hotels & Motels",
            "type":"Entertainment"
        }
    ],
    "sg:phone":"+1 479 253 8992",
    "sg:postcode":"72632",
    "sg:province":"AR",
    "sg:tags":[
        "operation"
    ],
    "wof:name":"Travelodge",
    "wof:placetype":"venue"
},
  "geometry": {"coordinates":[-93.739485,36.383587],"type":"Point"}
}