{
  "type": "Feature",
  "properties": {
    "iso:country":"US",
    "sg:address":"353 Cash Rd NW",
    "sg:city":"Camden",
    "sg:classifiers":[
        {
            "category":"Shopping",
            "subcategory":"Pharmacy",
            "type":"Retail Goods"
        }
    ],
    "sg:phone":"+1 870 836 2727",
    "sg:postcode":"71701",
    "sg:province":"AR",
    "wof:name":"Morrison's Pharmacies",
    "wof:placetype":"venue"
},
  "geometry": {"coordinates":[-92.850847,33.588233],"type":"Point"}
}