{
  "type": "Feature",
  "properties": {
    "iso:country":"US",
    "sg:address":"100 N Detroit Ave",
    "sg:city":"Russellville",
    "sg:classifiers":[
        {
            "category":"Autos & Motor Vehicles",
            "subcategory":"Motorcycle Sales",
            "type":"Retail Goods"
        }
    ],
    "sg:phone":"+1 479 890 6334",
    "sg:postcode":"72801",
    "sg:province":"AR",
    "wof:name":"Hubbard ATV",
    "wof:placetype":"venue"
},
  "geometry": {"coordinates":[-93.129474,35.279088],"type":"Point"}
}