{
  "type": "Feature",
  "properties": {
    "iso:country":"US",
    "sg:address":"2493 Hwy 63",
    "sg:city":"Hardy",
    "sg:classifiers":[
        {
            "category":"Autos & Motor Vehicles",
            "subcategory":"Automobile Sales",
            "type":"Retail Goods"
        }
    ],
    "sg:phone":"+1 870 856 2550",
    "sg:postcode":"72542",
    "sg:province":"AR",
    "sg:tags":[
        "car",
        "dealer"
    ],
    "wof:name":"Sparks Auto Sales",
    "wof:placetype":"venue"
},
  "geometry": {"coordinates":[-91.439336,36.299019],"type":"Point"}
}