{
  "type": "Feature",
  "properties": {
    "iso:country":"US",
    "sg:address":"107 W Bean St",
    "sg:city":"Lincoln",
    "sg:classifiers":[
        {
            "category":"Education",
            "subcategory":"Library",
            "type":"Public Place"
        }
    ],
    "sg:phone":"+1 479 824 3294",
    "sg:postcode":"72744",
    "sg:province":"AR",
    "wof:name":"Lincoln Public Library",
    "wof:placetype":"venue"
},
  "geometry": {"coordinates":[-94.423773,35.949914],"type":"Point"}
}