{
  "type": "Feature",
  "properties": {
    "iso:country":"US",
    "sg:address":"308 1st Ave NE",
    "sg:city":"Gravette",
    "sg:classifiers":[
        {
            "category":"Shopping",
            "subcategory":"Florist",
            "type":"Retail Goods"
        }
    ],
    "sg:phone":"+1 479 787 7773",
    "sg:postcode":"72736",
    "sg:province":"AR",
    "wof:name":"Gravette Florist",
    "wof:placetype":"venue"
},
  "geometry": {"coordinates":[-94.45311,36.425061],"type":"Point"}
}