{
  "type": "Feature",
  "properties": {
    "addr:full":"4700 Highway 412 E Paragould AR 72450",
    "addr:housenumber":"4700",
    "addr:postcode":"72450",
    "addr:street":"Highway 412 E Paragould",
    "iso:country":"US",
    "sg:address":"4700 Highway 412 E",
    "sg:city":"Paragould",
    "sg:classifiers":[
        {
            "category":"Health Services",
            "subcategory":"Clinic",
            "type":"Services"
        }
    ],
    "sg:phone":"+1 870 240 8402",
    "sg:postcode":"72450",
    "sg:province":"AR",
    "sg:tags":[
        "welfare"
    ],
    "wof:name":"N Ea Clinic Paragould",
    "wof:placetype":"venue"
},
  "geometry": {"coordinates":[-90.420714,36.052496],"type":"Point"}
}