{
  "type": "Feature",
  "properties": {
    "iso:country":"US",
    "sg:address":"4581 White Oak Rd",
    "sg:city":"Harrison",
    "sg:classifiers":[
        {
            "category":"Professional",
            "type":"Services"
        }
    ],
    "sg:phone":"+1 870 743 4016",
    "sg:postcode":"72601",
    "sg:province":"AR",
    "wof:name":"Plum Crazy Inc",
    "wof:placetype":"venue"
},
  "geometry": {"coordinates":[-93.005164,36.274558],"type":"Point"}
}