{
  "type": "Feature",
  "properties": {
    "addr:full":"915 S Maple St Harrison AR 72601",
    "addr:housenumber":"915",
    "addr:postcode":"72601",
    "addr:street":"S Maple St",
    "iso:country":"US",
    "sg:address":"915 S Maple St",
    "sg:city":"Harrison",
    "sg:classifiers":[
        {
            "category":"Organizations",
            "subcategory":"Religious Organization",
            "type":"Services"
        }
    ],
    "sg:phone":"+1 870 741 5757",
    "sg:postcode":"72601",
    "sg:province":"AR",
    "wof:name":"First Christian Church",
    "wof:placetype":"venue"
},
  "geometry": {"coordinates":[-93.113553,36.220439],"type":"Point"}
}