{
  "type": "Feature",
  "properties": {
    "addr:full":"711 Fayetteville Rd Van Buren AR 72956",
    "addr:housenumber":"711",
    "addr:postcode":"72956",
    "addr:street":"Fayetteville Rd",
    "iso:country":"US",
    "sg:address":"711 Fayetteville Rd",
    "sg:city":"Van Buren",
    "sg:classifiers":[
        {
            "category":"Shopping",
            "subcategory":"Florist",
            "type":"Retail Goods"
        }
    ],
    "sg:phone":"+1 479 474 9990",
    "sg:postcode":"72956",
    "sg:province":"AR",
    "wof:name":"Flowers By Grace",
    "wof:placetype":"venue"
},
  "geometry": {"coordinates":[-94.354263,35.44471],"type":"Point"}
}