{
  "type": "Feature",
  "properties": {
    "addr:full":"3195 N College Ave Fayetteville AR 72703",
    "addr:housenumber":"3195",
    "addr:postcode":"72703",
    "addr:street":"N College Ave",
    "iso:country":"US",
    "sg:address":"3195 N College Ave",
    "sg:city":"Fayetteville",
    "sg:classifiers":[
        {
            "category":"Autos & Motor Vehicles",
            "subcategory":"Automobile Sales",
            "type":"Retail Goods"
        },
        {
            "category":"Retail",
            "subcategory":"Auto Repair",
            "type":"Services"
        }
    ],
    "sg:phone":"+1 479 442 7800",
    "sg:postcode":"72703",
    "sg:province":"AR",
    "sg:tags":[
        "repairing",
        "used",
        "supply",
        "automotive",
        "dealers-used",
        "car",
        "new",
        "cars-wholesale",
        "tune",
        "service-equipment"
    ],
    "sg:website":"http://www.superiorkia.com",
    "wof:name":"Superior Kia - New & Used Cars",
    "wof:placetype":"venue"
},
  "geometry": {"coordinates":[-94.145149,36.10968],"type":"Point"}
}