{
  "type": "Feature",
  "properties": {
    "iso:country":"US",
    "sg:address":"701 N Reynolds Rd",
    "sg:city":"Bryant",
    "sg:classifiers":[
        {
            "category":"Manufacturing",
            "subcategory":"Signs",
            "type":"Manufacturing & Wholesale Goods"
        },
        {
            "category":"Professional",
            "subcategory":"Art Services",
            "type":"Services"
        }
    ],
    "sg:phone":"+1 501 653 4444",
    "sg:postcode":"72022",
    "sg:province":"AR",
    "sg:tags":[
        "commercial",
        "design"
    ],
    "wof:name":"L Graphics",
    "wof:placetype":"venue"
},
  "geometry": {"coordinates":[-92.489763,34.599908],"type":"Point"}
}