{
  "type": "Feature",
  "properties": {
    "iso:country":"US",
    "sg:address":"2605 Charter Oak Dr",
    "sg:city":"Little Rock",
    "sg:classifiers":[
        {
            "category":"Professional",
            "subcategory":"Research",
            "type":"Services"
        }
    ],
    "sg:phone":"+1 501 228 5001",
    "sg:postcode":"72227",
    "sg:province":"AR",
    "sg:tags":[
        "nonphysical",
        "commercial",
        "business"
    ],
    "wof:name":"United Spectrographics Inc",
    "wof:placetype":"venue"
},
  "geometry": {"coordinates":[-92.382876,34.780874],"type":"Point"}
}