{
  "type": "Feature",
  "properties": {
    "iso:country":"US",
    "sg:address":"12 Fayetteville Rd",
    "sg:city":"Van Buren",
    "sg:classifiers":[
        {
            "category":"Manufacturing",
            "subcategory":"Furniture",
            "type":"Manufacturing & Wholesale Goods"
        },
        {
            "category":"Building & Trades",
            "subcategory":"Construction",
            "type":"Services"
        }
    ],
    "sg:phone":"+1 479 474 9874",
    "sg:postcode":"72956",
    "sg:province":"AR",
    "sg:tags":[
        "cabinet",
        "maker",
        "mfg"
    ],
    "wof:name":"Elmer's Cabinet Shop",
    "wof:placetype":"venue"
},
  "geometry": {"coordinates":[-94.352618,35.436878],"type":"Point"}
}