{
  "type": "Feature",
  "properties": {
    "iso:country":"US",
    "sg:address":"220 E Clark St",
    "sg:city":"Nashville",
    "sg:classifiers":[
        {
            "category":"Building & Trades",
            "subcategory":"Construction",
            "type":"Services"
        }
    ],
    "sg:phone":"+1 870 845 0120",
    "sg:postcode":"71852",
    "sg:province":"AR",
    "sg:tags":[
        "general",
        "contractor"
    ],
    "wof:name":"Young Love Construction",
    "wof:placetype":"venue"
},
  "geometry": {"coordinates":[-93.845918,33.944526],"type":"Point"}
}