{
  "type": "Feature",
  "properties": {
    "iso:country":"US",
    "sg:address":"3020 S Olive St",
    "sg:city":"Pine Bluff",
    "sg:classifiers":[
        {
            "category":"Banks & Credit Unions",
            "subcategory":"Investment Brokerage",
            "type":"Services"
        }
    ],
    "sg:phone":"+1 870 534 6833",
    "sg:postcode":"71603",
    "sg:province":"AR",
    "sg:tags":[
        "security"
    ],
    "wof:name":"Edward Jones 08816",
    "wof:placetype":"venue"
},
  "geometry": {"coordinates":[-92.007091,34.198752],"type":"Point"}
}