{
  "type": "Feature",
  "properties": {
    "iso:country":"US",
    "sg:address":"1908 W C Pl",
    "sg:city":"Russellville",
    "sg:classifiers":[
        {
            "category":"Building & Trades",
            "subcategory":"Plumbing",
            "type":"Services"
        }
    ],
    "sg:phone":"+1 479 968 1282",
    "sg:postcode":"72801",
    "sg:province":"AR",
    "sg:tags":[
        "septic"
    ],
    "wof:name":"Arkansas Valley Rooter/Murdock",
    "wof:placetype":"venue"
},
  "geometry": {"coordinates":[-93.15124,35.286376],"type":"Point"}
}