{
  "type": "Feature",
  "properties": {
    "iso:country":"US",
    "sg:address":"5600 John F Kennedy Blvd",
    "sg:city":"N Little Rock",
    "sg:classifiers":[
        {
            "category":"Wholesale",
            "subcategory":"Computers",
            "type":"Manufacturing & Wholesale Goods"
        }
    ],
    "sg:phone":"+1 501 812 5753",
    "sg:postcode":"72116",
    "sg:province":"AR",
    "sg:tags":[
        "information",
        "retrieval"
    ],
    "wof:name":"Real-Time Information Svc",
    "wof:placetype":"venue"
},
  "geometry": {"coordinates":[-92.25013199999999,34.807112],"type":"Point"}
}