{
  "type": "Feature",
  "properties": {
    "iso:country":"US",
    "sg:address":"821 Hogan Ln",
    "sg:city":"Conway",
    "sg:classifiers":[
        {
            "category":"Personal",
            "type":"Services"
        }
    ],
    "sg:phone":"+1 501 764 0002",
    "sg:postcode":"72034",
    "sg:province":"AR",
    "wof:name":"Eurosun",
    "wof:placetype":"venue"
},
  "geometry": {"coordinates":[-92.49797599999999,35.091597],"type":"Point"}
}