{
  "type": "Feature",
  "properties": {
    "addr:full":"11448 W David O Dodd Rd Little Rock AR 72204",
    "addr:housenumber":"11448",
    "addr:postcode":"72204",
    "addr:street":"W David O Dodd Rd",
    "iso:country":"US",
    "sg:address":"11448 W David O Dodd Rd",
    "sg:city":"Little Rock",
    "sg:classifiers":[
        {
            "category":"Building & Trades",
            "subcategory":"Construction",
            "type":"Services"
        }
    ],
    "sg:phone":"+1 501 407 9561",
    "sg:postcode":"72204",
    "sg:province":"AR",
    "sg:tags":[
        "house"
    ],
    "wof:name":"Paul M James Construction LLC",
    "wof:placetype":"venue"
},
  "geometry": {"coordinates":[-92.403429,34.69629],"type":"Point"}
}