{
  "type": "Feature",
  "properties": {
    "iso:country":"US",
    "sg:address":"618 Hillcrest St",
    "sg:city":"Monticello",
    "sg:classifiers":[
        {
            "category":"Retail",
            "subcategory":"Repair Shop",
            "type":"Services"
        },
        {
            "category":"Professional",
            "subcategory":"Detective & Security Services",
            "type":"Services"
        }
    ],
    "sg:phone":"+1 870 367 7374",
    "sg:postcode":"71655",
    "sg:province":"AR",
    "sg:tags":[
        "skip",
        "tracing",
        "bail",
        "bond"
    ],
    "wof:name":"Bob Cole Bail Bond Inc",
    "wof:placetype":"venue"
},
  "geometry": {"coordinates":[-91.780468,33.614412],"type":"Point"}
}