{
  "type": "Feature",
  "properties": {
    "addr:full":"706 Calvin Avery Dr West Memphis AR 72301",
    "addr:housenumber":"706",
    "addr:postcode":"72301",
    "addr:street":"Calvin Avery Dr",
    "iso:country":"US",
    "sg:address":"706 Calvin Avery Dr",
    "sg:city":"West Memphis",
    "sg:classifiers":[
        {
            "category":"Real Estate",
            "subcategory":"Real Estate Agent",
            "type":"Services"
        }
    ],
    "sg:phone":"+1 870 735 7345",
    "sg:postcode":"72301",
    "sg:province":"AR",
    "sg:tags":[
        "appraiser"
    ],
    "wof:name":"Crews Appraisal & Real Estate",
    "wof:placetype":"venue"
},
  "geometry": {"coordinates":[-90.199906,35.14552],"type":"Point"}
}