{
  "type": "Feature",
  "properties": {
    "iso:country":"US",
    "sg:address":"300 S Rodney Parham Rd",
    "sg:city":"Little Rock",
    "sg:classifiers":[
        {
            "category":"Wholesale",
            "subcategory":"Medical Equipment & Supplies",
            "type":"Manufacturing & Wholesale Goods"
        }
    ],
    "sg:phone":"+1 501 227 8220",
    "sg:postcode":"72205",
    "sg:province":"AR",
    "wof:name":"P&H Ostomy & Health Services",
    "wof:placetype":"venue"
},
  "geometry": {"coordinates":[-92.364638,34.751764],"type":"Point"}
}