{
  "type": "Feature",
  "properties": {
    "addr:full":"2100 S Main St Grove OK 74344",
    "addr:housenumber":"2100",
    "addr:postcode":"74344",
    "addr:street":"S Main St Grove",
    "iso:country":"US",
    "sg:address":"2100 S Main St",
    "sg:city":"Grove",
    "sg:classifiers":[
        {
            "category":"Sports & Exercise",
            "subcategory":"Gym",
            "type":"Entertainment"
        }
    ],
    "sg:phone":"+1 918 786 6400",
    "sg:postcode":"74344",
    "sg:province":"OK",
    "sg:tags":[
        "shop",
        "fitness",
        "physical",
        "beauty",
        "facility"
    ],
    "wof:name":"Curves For Women",
    "wof:placetype":"venue"
},
  "geometry": {"coordinates":[-94.769093,36.58007],"type":"Point"}
}