{
  "type": "Feature",
  "properties": {
    "addr:full":"5711 Pritchard Rd N Little Rock AR 72117",
    "addr:housenumber":"5711",
    "addr:postcode":"72117",
    "addr:street":"Pritchard Rd N",
    "iso:country":"US",
    "sg:address":"5711 Pritchard Rd",
    "sg:city":"N Little Rock",
    "sg:classifiers":[
        {
            "category":"Travel",
            "subcategory":"Hotels & Motels",
            "type":"Entertainment"
        }
    ],
    "sg:phone":"+1 501 945 0080",
    "sg:postcode":"72117",
    "sg:province":"AR",
    "wof:name":"Red Roof-North Little Rock",
    "wof:placetype":"venue"
},
  "geometry": {"coordinates":[-92.206508,34.777797],"type":"Point"}
}