{
  "type": "Feature",
  "properties": {
    "addr:full":"323 Hwy 425 S Monticello AR 71655",
    "addr:housenumber":"323",
    "addr:postcode":"71655",
    "addr:street":"Hwy 425 S",
    "iso:country":"US",
    "sg:address":"323 Hwy 425 S",
    "sg:city":"Monticello",
    "sg:classifiers":[
        {
            "category":"Autos & Motor Vehicles",
            "subcategory":"Auto Supplies",
            "type":"Retail Goods"
        }
    ],
    "sg:phone":"+1 870 367 2401",
    "sg:postcode":"71655",
    "sg:province":"AR",
    "sg:tags":[
        "tire"
    ],
    "wof:name":"Monticello Tire & Svc Inc",
    "wof:placetype":"venue"
},
  "geometry": {"coordinates":[-91.80264699999999,33.624762],"type":"Point"}
}