{
  "type": "Feature",
  "properties": {
    "addr:full":"407 Pine St Omaha AR 72662",
    "addr:housenumber":"407",
    "addr:postcode":"72662",
    "addr:street":"Pine St",
    "iso:country":"US",
    "sg:address":"407 Pine St",
    "sg:city":"Omaha",
    "sg:classifiers":[
        {
            "category":"Professional",
            "subcategory":"Advertising",
            "type":"Services"
        }
    ],
    "sg:phone":"+1 870 426 3721",
    "sg:postcode":"72662",
    "sg:province":"AR",
    "sg:tags":[
        "distribution"
    ],
    "wof:name":"KAT Distributing",
    "wof:placetype":"venue"
},
  "geometry": {"coordinates":[-93.18795799999999,36.453122],"type":"Point"}
}