{
  "type": "Feature",
  "properties": {
    "addr:full":"104 Gibson Hill Rd Ash Flat AR 72513",
    "addr:housenumber":"104",
    "addr:postcode":"72513",
    "addr:street":"Gibson Hill Rd",
    "iso:country":"US",
    "sg:address":"104 Gibson Hill Rd",
    "sg:city":"Ash Flat",
    "sg:classifiers":[
        {
            "category":"Retail",
            "subcategory":"Auto Repair",
            "type":"Services"
        }
    ],
    "sg:phone":"+1 870 994 7041",
    "sg:postcode":"72513",
    "sg:province":"AR",
    "sg:tags":[
        "general"
    ],
    "wof:name":"Tk Auto Repair",
    "wof:placetype":"venue"
},
  "geometry": {"coordinates":[-91.662492,36.264668],"type":"Point"}
}