{
  "type": "Feature",
  "properties": {
    "addr:full":"2000 Bishop Rd Bryant AR 72022",
    "addr:housenumber":"2000",
    "addr:postcode":"72022",
    "addr:street":"Bishop Rd",
    "iso:country":"US",
    "sg:address":"2000 Bishop Rd",
    "sg:city":"Bryant",
    "sg:classifiers":[
        {
            "category":"Real Estate",
            "subcategory":"Real Estate Operator",
            "type":"Services"
        }
    ],
    "sg:phone":"+1 501 847 8151",
    "sg:postcode":"72022",
    "sg:province":"AR",
    "sg:tags":[
        "building",
        "apartment"
    ],
    "wof:name":"Pinewood Manor Apartments",
    "wof:placetype":"venue"
},
  "geometry": {"coordinates":[-92.502191,34.612264],"type":"Point"}
}