{
  "type": "Feature",
  "properties": {
    "iso:country":"US",
    "sg:address":"1696 N Center St",
    "sg:city":"Lonoke",
    "sg:classifiers":[
        {
            "category":"Restaurant",
            "type":"Food & Drink"
        }
    ],
    "sg:phone":"+1 501 676 3991",
    "sg:postcode":"72086",
    "sg:province":"AR",
    "sg:tags":[
        "mexican"
    ],
    "wof:name":"El Dorado Mexican Restaurant",
    "wof:placetype":"venue"
},
  "geometry": {"coordinates":[-91.889466,34.801304],"type":"Point"}
}