{
  "type": "Feature",
  "properties": {
    "iso:country":"US",
    "sg:address":"114 E 3rd St",
    "sg:city":"Yellville",
    "sg:classifiers":[
        {
            "category":"Banks & Credit Unions",
            "subcategory":"Bank",
            "type":"Services"
        }
    ],
    "sg:phone":"+1 870 449 8707",
    "sg:postcode":"72687",
    "sg:province":"AR",
    "sg:tags":[
        "depository",
        "banking"
    ],
    "wof:name":"Yellville Escrow Service",
    "wof:placetype":"venue"
},
  "geometry": {"coordinates":[-92.682789,36.226743],"type":"Point"}
}