{
  "type": "Feature",
  "properties": {
    "iso:country":"US",
    "sg:address":"903 S 4th St",
    "sg:city":"Van Buren",
    "sg:classifiers":[
        {
            "category":"Shopping",
            "type":"Retail Goods"
        }
    ],
    "sg:phone":"+1 479 471 0590",
    "sg:postcode":"72956",
    "sg:province":"AR",
    "sg:tags":[
        "candle"
    ],
    "wof:name":"Sandessence Candles",
    "wof:placetype":"venue"
},
  "geometry": {"coordinates":[-94.348564,35.428542],"type":"Point"}
}