{
  "type": "Feature",
  "properties": {
    "iso:country":"US",
    "sg:address":"602 Arkansas Blvd",
    "sg:city":"Texarkana",
    "sg:classifiers":[
        {
            "category":"Organizations",
            "subcategory":"Religious Organization",
            "type":"Services"
        }
    ],
    "sg:phone":"+1 870 773 4244",
    "sg:postcode":"71854",
    "sg:province":"AR",
    "sg:tags":[
        "church"
    ],
    "wof:name":"Arkansas Boulevard Church",
    "wof:placetype":"venue"
},
  "geometry": {"coordinates":[-94.036824,33.460151],"type":"Point"}
}