{
  "type": "Feature",
  "properties": {
    "addr:full":"421 W Stephenson Ave Harrison AR 72601",
    "addr:housenumber":"421",
    "addr:postcode":"72601",
    "addr:street":"W Stephenson Ave",
    "iso:country":"US",
    "sg:address":"421 W Stephenson Ave",
    "sg:city":"Harrison",
    "sg:classifiers":[
        {
            "category":"Retail",
            "subcategory":"Laundry & Dry Cleaning",
            "type":"Services"
        }
    ],
    "sg:phone":"+1 870 365 0585",
    "sg:postcode":"72601",
    "sg:province":"AR",
    "wof:name":"Patsys Upholstery & Leather",
    "wof:placetype":"venue"
},
  "geometry": {"coordinates":[-93.111469,36.229896],"type":"Point"}
}