{
  "type": "Feature",
  "properties": {
    "iso:country":"US",
    "sg:address":"104 Foster St",
    "sg:city":"Hot Springs National Park",
    "sg:classifiers":[
        {
            "category":"Building & Trades",
            "subcategory":"Construction",
            "type":"Services"
        }
    ],
    "sg:phone":"+1 501 767 5952",
    "sg:postcode":"71913",
    "sg:province":"AR",
    "sg:tags":[
        "contractor"
    ],
    "wof:name":"A 1 Tile Company",
    "wof:placetype":"venue"
},
  "geometry": {"coordinates":[-93.140112,34.47339],"type":"Point"}
}