{
  "type": "Feature",
  "properties": {
    "iso:country":"US",
    "sg:address":"5940 E Highland Dr",
    "sg:city":"Jonesboro",
    "sg:classifiers":[
        {
            "category":"Transit Center",
            "subcategory":"Freight",
            "type":"Transportation"
        },
        {
            "category":"Freight",
            "type":"Transportation"
        }
    ],
    "sg:phone":"+1 870 932 0127",
    "sg:postcode":"72401",
    "sg:province":"AR",
    "sg:tags":[
        "local",
        "trucking-motor",
        "trucking"
    ],
    "sg:website":"http://www.myyellow.com",
    "wof:name":"Yellow Transportation",
    "wof:placetype":"venue"
},
  "geometry": {"coordinates":[-90.669277,35.821146],"type":"Point"}
}