{
  "type": "Feature",
  "properties": {
    "iso:country":"US",
    "sg:address":"571 Oakland Ave",
    "sg:city":"Helena",
    "sg:classifiers":[
        {
            "category":"Food & Beverages",
            "subcategory":"Groceries & Convenience Stores",
            "type":"Retail Goods"
        }
    ],
    "sg:phone":"+1 870 338 3912",
    "sg:postcode":"72342",
    "sg:province":"AR",
    "wof:name":"Midland Heights Conoco",
    "wof:placetype":"venue"
},
  "geometry": {"coordinates":[-90.613034,34.536619],"type":"Point"}
}