{
  "type": "Feature",
  "properties": {
    "iso:country":"US",
    "sg:address":"5300 W Markham St",
    "sg:city":"Little Rock",
    "sg:classifiers":[
        {
            "category":"Retail",
            "subcategory":"Animal Services",
            "type":"Services"
        }
    ],
    "sg:phone":"+1 501 663 4630",
    "sg:postcode":"72205",
    "sg:province":"AR",
    "wof:name":"Sirius Spa",
    "wof:placetype":"venue"
},
  "geometry": {"coordinates":[-92.333565,34.752001],"type":"Point"}
}