{
  "type": "Feature",
  "properties": {
    "iso:country":"US",
    "sg:address":"1621 S Cherry St",
    "sg:city":"Pine Bluff",
    "sg:classifiers":[
        {
            "category":"Retail",
            "subcategory":"Funeral Services",
            "type":"Services"
        }
    ],
    "sg:phone":"+1 870 534 2120",
    "sg:postcode":"71601",
    "sg:province":"AR",
    "sg:tags":[
        "director"
    ],
    "wof:name":"Hale-South Funeral Home Inc",
    "wof:placetype":"venue"
},
  "geometry": {"coordinates":[-92.01340399999999,34.212329],"type":"Point"}
}