{
  "type": "Feature",
  "properties": {
    "iso:country":"US",
    "sg:address":"6882 Congo Rd",
    "sg:city":"Benton",
    "sg:classifiers":[
        {
            "category":"Shopping",
            "type":"Retail Goods"
        }
    ],
    "sg:phone":"+1 501 316 7700",
    "sg:postcode":"72019",
    "sg:province":"AR",
    "sg:tags":[
        "feed",
        "pet",
        "horse",
        "supply",
        "equipment"
    ],
    "wof:name":"Bar None Feed",
    "wof:placetype":"venue"
},
  "geometry": {"coordinates":[-92.57171,34.623181],"type":"Point"}
}