{
  "type": "Feature",
  "properties": {
    "addr:full":"2100 Meadowlane Dr Fordyce AR 71742",
    "addr:housenumber":"2100",
    "addr:postcode":"71742",
    "addr:street":"Meadowlane Dr Fordyce",
    "iso:country":"US",
    "sg:address":"2100 Meadowlane Dr",
    "sg:city":"Fordyce",
    "sg:classifiers":[
        {
            "category":"Restaurant",
            "type":"Food & Drink"
        }
    ],
    "sg:phone":"+1 870 352 2040",
    "sg:postcode":"71742",
    "sg:province":"AR",
    "wof:name":"Fordyce Restaurant",
    "wof:placetype":"venue"
},
  "geometry": {"coordinates":[-92.437279,33.816101],"type":"Point"}
}