{
  "type": "Feature",
  "properties": {
    "iso:country":"US",
    "sg:address":"557 W Willoughby Rd",
    "sg:city":"Fayetteville",
    "sg:classifiers":[
        {
            "category":"Professional",
            "subcategory":"Engineering",
            "type":"Services"
        },
        {
            "category":"Professional",
            "subcategory":"Management & Consulting",
            "type":"Services"
        }
    ],
    "sg:phone":"+1 479 587 8113",
    "sg:postcode":"72701",
    "sg:province":"AR",
    "sg:tags":[
        "business",
        "engineer"
    ],
    "wof:name":"Linton D Scott Consulting",
    "wof:placetype":"venue"
},
  "geometry": {"coordinates":[-94.172316,36.020807],"type":"Point"}
}