{
  "type": "Feature",
  "properties": {
    "iso:country":"US",
    "sg:address":"316 N Main St",
    "sg:city":"Fordyce",
    "sg:classifiers":[
        {
            "category":"Banks & Credit Unions",
            "subcategory":"Bank",
            "type":"Services"
        }
    ],
    "sg:phone":"+1 870 352 5600",
    "sg:postcode":"71742",
    "sg:province":"AR",
    "sg:tags":[
        "state",
        "commercial"
    ],
    "wof:name":"Pine State Bank of Fordyce",
    "wof:placetype":"venue"
},
  "geometry": {"coordinates":[-92.412863,33.813621],"type":"Point"}
}