{
  "type": "Feature",
  "properties": {
    "iso:country":"US",
    "sg:address":"1410 S Main St",
    "sg:city":"Stuttgart",
    "sg:classifiers":[
        {
            "category":"Insurance",
            "subcategory":"Insurance Agent",
            "type":"Services"
        }
    ],
    "sg:phone":"+1 870 673 2595",
    "sg:postcode":"72160",
    "sg:province":"AR",
    "wof:name":"Shelter Insurance",
    "wof:placetype":"venue"
},
  "geometry": {"coordinates":[-91.552937,34.49],"type":"Point"}
}