{
  "type": "Feature",
  "properties": {
    "addr:full":"405 Atlanta St SE Gravette AR 72736",
    "addr:housenumber":"405",
    "addr:postcode":"72736",
    "addr:street":"Atlanta St Se",
    "iso:country":"US",
    "sg:address":"405 Atlanta St SE",
    "sg:city":"Gravette",
    "sg:classifiers":[
        {
            "category":"Retail",
            "subcategory":"Funeral Services",
            "type":"Services"
        }
    ],
    "sg:phone":"+1 479 787 5311",
    "sg:postcode":"72736",
    "sg:province":"AR",
    "sg:tags":[
        "director"
    ],
    "wof:name":"Callison-Lough Funeral Svc",
    "wof:placetype":"venue"
},
  "geometry": {"coordinates":[-94.44977,36.421319],"type":"Point"}
}