{
  "type": "Feature",
  "properties": {
    "addr:full":"1025 Dowdy Loop Russellville AR 72802",
    "addr:housenumber":"1025",
    "addr:postcode":"72802",
    "addr:street":"Dowdy Loop",
    "iso:country":"US",
    "sg:address":"1025 Dowdy Loop",
    "sg:city":"Russellville",
    "sg:classifiers":[
        {
            "category":"Manufacturing",
            "subcategory":"Buildings",
            "type":"Manufacturing & Wholesale Goods"
        },
        {
            "category":"Building & Trades",
            "subcategory":"Construction",
            "type":"Services"
        }
    ],
    "sg:phone":"+1 479 967 4057",
    "sg:postcode":"72802",
    "sg:province":"AR",
    "sg:tags":[
        "home",
        "builder",
        "contractor"
    ],
    "wof:name":"Jmax Investments",
    "wof:placetype":"venue"
},
  "geometry": {"coordinates":[-93.18389000000001,35.289267],"type":"Point"}
}