{
  "type": "Feature",
  "properties": {
    "iso:country":"US",
    "sg:address":"1116 Marion Anderson Rd",
    "sg:city":"Hot Springs National Park",
    "sg:classifiers":[
        {
            "category":"Building & Trades",
            "subcategory":"Construction",
            "type":"Services"
        }
    ],
    "sg:phone":"+1 501 760 3855",
    "sg:postcode":"71913",
    "sg:province":"AR",
    "sg:tags":[
        "house"
    ],
    "wof:name":"Blair Petty Construction",
    "wof:placetype":"venue"
},
  "geometry": {"coordinates":[-93.123251,34.451749],"type":"Point"}
}