{
  "type": "Feature",
  "properties": {
    "addr:full":"810 4th Ave Conway AR 72032",
    "addr:housenumber":"810",
    "addr:postcode":"72032",
    "addr:street":"4Th Ave",
    "iso:country":"US",
    "sg:address":"810 4th Ave",
    "sg:city":"Conway",
    "sg:classifiers":[
        {
            "category":"Shopping",
            "subcategory":"Hobbies, Toys, & Games",
            "type":"Retail Goods"
        }
    ],
    "sg:phone":"+1 501 327 7001",
    "sg:postcode":"72032",
    "sg:province":"AR",
    "sg:tags":[
        "arts",
        "craft",
        "indian"
    ],
    "wof:name":"Clarks Indian Arts & Crafts",
    "wof:placetype":"venue"
},
  "geometry": {"coordinates":[-92.42441599999999,35.091493],"type":"Point"}
}