{
  "type": "Feature",
  "properties": {
    "iso:country":"US",
    "sg:address":"1107 State Hwy 17",
    "sg:city":"Brinkley",
    "sg:classifiers":[
        {
            "category":"Restaurant",
            "type":"Food & Drink"
        }
    ],
    "sg:phone":"+1 870 734 9965",
    "sg:postcode":"72021",
    "sg:province":"AR",
    "wof:name":"Gene's Bbq & Family Restaurant",
    "wof:placetype":"venue"
},
  "geometry": {"coordinates":[-91.195421,34.873865],"type":"Point"}
}