{
  "type": "Feature",
  "properties": {
    "iso:country":"US",
    "sg:address":"108 S Washington St",
    "sg:city":"Hope",
    "sg:classifiers":[
        {
            "category":"Personal",
            "subcategory":"Barber",
            "type":"Services"
        }
    ],
    "sg:phone":"+1 870 777 8875",
    "sg:postcode":"71801",
    "sg:province":"AR",
    "sg:tags":[
        "shop",
        "beauty"
    ],
    "wof:name":"Cw Styling Salon",
    "wof:placetype":"venue"
},
  "geometry": {"coordinates":[-93.599231,33.667137],"type":"Point"}
}