{
  "type": "Feature",
  "properties": {
    "iso:country":"US",
    "sg:address":"10809 Executive Center Dr",
    "sg:city":"Little Rock",
    "sg:classifiers":[
        {
            "category":"Professional",
            "subcategory":"Engineering",
            "type":"Services"
        }
    ],
    "sg:phone":"+1 501 219 0614",
    "sg:postcode":"72211",
    "sg:province":"AR",
    "wof:name":"Tanner Engineering Consultants",
    "wof:placetype":"venue"
},
  "geometry": {"coordinates":[-92.395923,34.739191],"type":"Point"}
}