{
  "type": "Feature",
  "properties": {
    "iso:country":"US",
    "sg:address":"1515 Dave Ward Dr",
    "sg:city":"Conway",
    "sg:classifiers":[
        {
            "category":"Restaurant",
            "type":"Food & Drink"
        }
    ],
    "sg:phone":"+1 501 329 3473",
    "sg:postcode":"72034",
    "sg:province":"AR",
    "wof:name":"Fireman Dave's Kountry Cookin",
    "wof:placetype":"venue"
},
  "geometry": {"coordinates":[-92.443409,35.068113],"type":"Point"}
}