{
  "type": "Feature",
  "properties": {
    "iso:country":"US",
    "sg:address":"2005 N Main St",
    "sg:city":"N Little Rock",
    "sg:classifiers":[
        {
            "category":"Personal",
            "type":"Services"
        }
    ],
    "sg:phone":"+1 501 771 9099",
    "sg:postcode":"72114",
    "sg:province":"AR",
    "sg:tags":[
        "wedding",
        "chapel"
    ],
    "wof:name":"LA Vada's",
    "wof:placetype":"venue"
},
  "geometry": {"coordinates":[-92.267025,34.774219],"type":"Point"}
}