{
  "type": "Feature",
  "properties": {
    "iso:country":"US",
    "sg:address":"20 N Bumble Bee Rd",
    "sg:city":"Glenwood",
    "sg:classifiers":[
        {
            "category":"Farming",
            "subcategory":"Livestock Farm",
            "type":"Manufacturing & Wholesale Goods"
        },
        {
            "category":"Farming",
            "subcategory":"Farm",
            "type":"Manufacturing & Wholesale Goods"
        }
    ],
    "sg:phone":"+1 870 356 5457",
    "sg:postcode":"71943",
    "sg:province":"AR",
    "wof:name":"Knight's Hog Farm",
    "wof:placetype":"venue"
},
  "geometry": {"coordinates":[-93.473832,34.355986],"type":"Point"}
}