{
  "type": "Feature",
  "properties": {
    "iso:country":"US",
    "sg:address":"435 Hwy 425 S",
    "sg:city":"Monticello",
    "sg:classifiers":[
        {
            "category":"Restaurant",
            "type":"Food & Drink"
        }
    ],
    "sg:phone":"+1 870 367 9229",
    "sg:postcode":"71655",
    "sg:province":"AR",
    "wof:name":"Taco Bell",
    "wof:placetype":"venue"
},
  "geometry": {"coordinates":[-91.80285499999999,33.62404],"type":"Point"}
}