{
  "type": "Feature",
  "properties": {
    "addr:full":"128 Bus Hwy 412 Huntsville AR 72740",
    "addr:housenumber":"128",
    "addr:postcode":"72740",
    "addr:street":"Bus Hwy 412",
    "iso:country":"US",
    "sg:address":"128 Bus Hwy 412",
    "sg:city":"Huntsville",
    "sg:classifiers":[
        {
            "category":"Home & Garden",
            "subcategory":"Garden Supply",
            "type":"Retail Goods"
        }
    ],
    "sg:phone":"+1 479 738 6474",
    "sg:postcode":"72740",
    "sg:province":"AR",
    "sg:tags":[
        "ornament"
    ],
    "wof:name":"Bypass Treasures",
    "wof:placetype":"venue"
},
  "geometry": {"coordinates":[-93.768117,36.113242],"type":"Point"}
}