{
  "type": "Feature",
  "properties": {
    "iso:country":"US",
    "sg:address":"15 Hoggard Ln",
    "sg:city":"Enola",
    "sg:classifiers":[
        {
            "category":"Travel",
            "subcategory":"Hotels & Motels",
            "type":"Entertainment"
        }
    ],
    "sg:phone":"+1 501 849 3381",
    "sg:postcode":"72047",
    "sg:province":"AR",
    "sg:tags":[
        "resort"
    ],
    "wof:name":"King Lewellin Resort Inc",
    "wof:placetype":"venue"
},
  "geometry": {"coordinates":[-92.212537,35.222156],"type":"Point"}
}