{
  "type": "Feature",
  "properties": {
    "iso:country":"US",
    "sg:address":"13 Hunt Dr",
    "sg:city":"Cabot",
    "sg:classifiers":[
        {
            "category":"Autos & Motor Vehicles",
            "subcategory":"Automobile Sales",
            "type":"Retail Goods"
        }
    ],
    "sg:phone":"+1 501 843 3179",
    "sg:postcode":"72023",
    "sg:province":"AR",
    "sg:tags":[
        "car",
        "dealer"
    ],
    "wof:name":"C & G Auto Sales",
    "wof:placetype":"venue"
},
  "geometry": {"coordinates":[-91.996382,34.921604],"type":"Point"}
}