{
  "type": "Feature",
  "properties": {
    "iso:country":"US",
    "sg:address":"811 Highway 65 S",
    "sg:city":"Dumas",
    "sg:classifiers":[
        {
            "category":"Health Services",
            "subcategory":"Clinic",
            "type":"Services"
        },
        {
            "category":"Community Center",
            "type":"Public Place"
        },
        {
            "category":"Health Services",
            "subcategory":"Hospital",
            "type":"Services"
        }
    ],
    "sg:phone":"+1 870 382 4303",
    "sg:postcode":"71639",
    "sg:province":"AR",
    "sg:tags":[
        "medical",
        "surgery"
    ],
    "sg:website":"http://www.deltamem.org",
    "wof:name":"Delta Memorial Hospital",
    "wof:placetype":"venue"
},
  "geometry": {"coordinates":[-91.490172,33.89928],"type":"Point"}
}