{
  "type": "Feature",
  "properties": {
    "iso:country":"US",
    "sg:address":"614 W Keiser Ave",
    "sg:city":"Osceola",
    "sg:classifiers":[
        {
            "category":"Home & Garden",
            "subcategory":"Building Materials",
            "type":"Retail Goods"
        }
    ],
    "sg:phone":"+1 870 563 6800",
    "sg:postcode":"72370",
    "sg:province":"AR",
    "sg:tags":[
        "glass",
        "window",
        "plate"
    ],
    "wof:name":"Ace Glass",
    "wof:placetype":"venue"
},
  "geometry": {"coordinates":[-89.975599,35.697723],"type":"Point"}
}