{
  "type": "Feature",
  "properties": {
    "iso:country":"US",
    "sg:address":"226 W Van Buren",
    "sg:city":"Eureka Springs",
    "sg:classifiers":[
        {
            "category":"Restaurant",
            "type":"Food & Drink"
        },
        {
            "category":"Autos & Motor Vehicles",
            "subcategory":"Fuel & Gas Station",
            "type":"Retail Goods"
        }
    ],
    "sg:phone":"+1 479 253 7560",
    "sg:postcode":"72632",
    "sg:province":"AR",
    "sg:tags":[
        "station",
        "gasoline",
        "out"
    ],
    "wof:name":"Tad's Quickstop",
    "wof:placetype":"venue"
},
  "geometry": {"coordinates":[-93.747543,36.399682],"type":"Point"}
}