{
  "type": "Feature",
  "properties": {
    "addr:full":"303 College Rd W Omaha AR 72662",
    "addr:housenumber":"303",
    "addr:postcode":"72662",
    "addr:street":"College Rd",
    "iso:country":"US",
    "sg:address":"303 College Rd W",
    "sg:city":"Omaha",
    "sg:classifiers":[
        {
            "category":"Retail",
            "subcategory":"Auto Repair",
            "type":"Services"
        }
    ],
    "sg:phone":"+1 870 426 4311",
    "sg:postcode":"72662",
    "sg:province":"AR",
    "sg:tags":[
        "general"
    ],
    "wof:name":"Youngs Tradition",
    "wof:placetype":"venue"
},
  "geometry": {"coordinates":[-93.20190100000001,36.449202],"type":"Point"}
}