{
  "type": "Feature",
  "properties": {
    "addr:full":"3000 N 6th St Fort Smith AR 72904",
    "addr:housenumber":"3000",
    "addr:postcode":"72904",
    "addr:street":"N 6Th St",
    "iso:country":"US",
    "sg:address":"3000 N 6th St",
    "sg:city":"Fort Smith",
    "sg:classifiers":[
        {
            "category":"Autos & Motor Vehicles",
            "subcategory":"Automobile Sales",
            "type":"Retail Goods"
        }
    ],
    "sg:phone":"+1 479 782 9292",
    "sg:postcode":"72904",
    "sg:province":"AR",
    "sg:tags":[
        "car",
        "dealer"
    ],
    "wof:name":"A & Z Auto Sales",
    "wof:placetype":"venue"
},
  "geometry": {"coordinates":[-94.40127099999999,35.40853],"type":"Point"}
}