{
  "type": "Feature",
  "properties": {
    "addr:full":"215 Westfork St Alma AR 72921",
    "addr:housenumber":"215",
    "addr:postcode":"72921",
    "addr:street":"Westfork St",
    "iso:country":"US",
    "sg:address":"215 Westfork St",
    "sg:city":"Alma",
    "sg:classifiers":[
        {
            "category":"Personal",
            "subcategory":"Beauty Salon",
            "type":"Services"
        }
    ],
    "sg:phone":"+1 479 632 5769",
    "sg:postcode":"72921",
    "sg:province":"AR",
    "wof:name":"Hair Depot",
    "wof:placetype":"venue"
},
  "geometry": {"coordinates":[-94.22634499999999,35.48159],"type":"Point"}
}