{
  "type": "Feature",
  "properties": {
    "iso:country":"US",
    "sg:address":"125 Watson Rd",
    "sg:city":"Batesville",
    "sg:classifiers":[
        {
            "category":"Real Estate",
            "subcategory":"Real Estate Agent",
            "type":"Services"
        }
    ],
    "sg:phone":"+1 870 698 2026",
    "sg:postcode":"72501",
    "sg:province":"AR",
    "wof:name":"Re/Max",
    "wof:placetype":"venue"
},
  "geometry": {"coordinates":[-91.52263499999999,35.760745],"type":"Point"}
}