{
  "type": "Feature",
  "properties": {
    "iso:country":"US",
    "sg:address":"3261 Hwy 79 S",
    "sg:city":"Camden",
    "sg:classifiers":[
        {
            "category":"Organizations",
            "subcategory":"Religious Organization",
            "type":"Services"
        }
    ],
    "sg:phone":"+1 870 836 9142",
    "sg:postcode":"71701",
    "sg:province":"AR",
    "sg:tags":[
        "church"
    ],
    "wof:name":"Sweethome Baptist Church",
    "wof:placetype":"venue"
},
  "geometry": {"coordinates":[-92.945885,33.496485],"type":"Point"}
}