{
  "type": "Feature",
  "properties": {
    "addr:full":"4 Vintage Pt Rogers AR 72758",
    "addr:housenumber":"4",
    "addr:postcode":"72758",
    "addr:street":"Vintage Pt",
    "iso:country":"US",
    "sg:address":"4 Vintage Pt",
    "sg:city":"Rogers",
    "sg:classifiers":[
        {
            "category":"Shopping",
            "type":"Retail Goods"
        }
    ],
    "sg:phone":"+1 479 271 8258",
    "sg:postcode":"72758",
    "sg:province":"AR",
    "sg:tags":[
        "merchandise"
    ],
    "wof:name":"Champion Home Systems",
    "wof:placetype":"venue"
},
  "geometry": {"coordinates":[-94.194242,36.294881],"type":"Point"}
}