{
  "type": "Feature",
  "properties": {
    "iso:country":"US",
    "sg:address":"3 Shannon Dr",
    "sg:city":"Little Rock",
    "sg:classifiers":[
        {
            "category":"Building & Trades",
            "subcategory":"Construction",
            "type":"Services"
        }
    ],
    "sg:phone":"+1 501 225 7335",
    "sg:postcode":"72207",
    "sg:province":"AR",
    "sg:tags":[
        "contractor"
    ],
    "wof:name":"Petty Roofing",
    "wof:placetype":"venue"
},
  "geometry": {"coordinates":[-92.346371,34.767585],"type":"Point"}
}