{
  "type": "Feature",
  "properties": {
    "iso:country":"US",
    "sg:address":"3 Club Rd",
    "sg:city":"Horseshoe Bend",
    "sg:classifiers":[
        {
            "category":"Professional",
            "type":"Services"
        }
    ],
    "sg:phone":"+1 870 670 4148",
    "sg:postcode":"72512",
    "sg:province":"AR",
    "wof:name":"American Land Company",
    "wof:placetype":"venue"
},
  "geometry": {"coordinates":[-91.764013,36.229143],"type":"Point"}
}