{
  "type": "Feature",
  "properties": {
    "iso:country":"US",
    "sg:address":"2408 N Vine St",
    "sg:city":"Magnolia",
    "sg:classifiers":[
        {
            "category":"Building & Trades",
            "subcategory":"Construction",
            "type":"Services"
        }
    ],
    "sg:phone":"+1 870 901 7900",
    "sg:postcode":"71753",
    "sg:province":"AR",
    "sg:tags":[
        "concrete",
        "contractor"
    ],
    "wof:name":"Smith's Ready Mix Inc",
    "wof:placetype":"venue"
},
  "geometry": {"coordinates":[-93.248527,33.291234],"type":"Point"}
}