{
  "type": "Feature",
  "properties": {
    "addr:full":"1323 State Hwy 25 B N Heber Springs AR 72543",
    "addr:housenumber":"1323;b",
    "addr:postcode":"72543",
    "addr:street":"State Hwy 25;N Heber Springs",
    "iso:country":"US",
    "sg:address":"1323 State Hwy 25 B N",
    "sg:city":"Heber Springs",
    "sg:classifiers":[
        {
            "category":"Cinema",
            "subcategory":"Movie Rental",
            "type":"Entertainment"
        }
    ],
    "sg:phone":"+1 501 362 6556",
    "sg:postcode":"72543",
    "sg:province":"AR",
    "sg:tags":[
        "video",
        "tape"
    ],
    "wof:name":"Shows To Go",
    "wof:placetype":"venue"
},
  "geometry": {"coordinates":[-92.029291,35.50955],"type":"Point"}
}