{
  "type": "Feature",
  "properties": {
    "iso:country":"US",
    "sg:address":"3009 Turman Dr #C",
    "sg:city":"Jonesboro",
    "sg:classifiers":[
        {
            "category":"Real Estate",
            "subcategory":"Real Estate Services",
            "type":"Services"
        },
        {
            "category":"Real Estate",
            "subcategory":"Surveying",
            "type":"Services"
        },
        {
            "category":"Real Estate",
            "subcategory":"Real Estate Agent",
            "type":"Services"
        },
        {
            "category":"Professional",
            "subcategory":"Business Services",
            "type":"Services"
        }
    ],
    "sg:phone":"+1 870 934 1105",
    "sg:postcode":"72404",
    "sg:province":"AR",
    "sg:tags":[
        "consultant",
        "appraisers-business",
        "industrial",
        "commercial",
        "appraiser"
    ],
    "sg:website":"http://www.despainappraisalservice.com",
    "wof:name":"Despain Appraisal",
    "wof:placetype":"venue"
},
  "geometry": {"coordinates":[-90.668194,35.794559],"type":"Point"}
}