{
  "type": "Feature",
  "properties": {
    "iso:country":"US",
    "sg:address":"3308 E 6th St",
    "sg:city":"Russellville",
    "sg:classifiers":[
        {
            "category":"Retail",
            "subcategory":"Car Wash",
            "type":"Services"
        }
    ],
    "sg:phone":"+1 479 968 8868",
    "sg:postcode":"72802",
    "sg:province":"AR",
    "sg:tags":[
        "carwash"
    ],
    "wof:name":"Arkansas Tinting & Auto Glass",
    "wof:placetype":"venue"
},
  "geometry": {"coordinates":[-93.086096,35.270528],"type":"Point"}
}