{
  "type": "Feature",
  "properties": {
    "addr:full":"11501 Southridge Dr Little Rock AR 72212",
    "addr:housenumber":"11501",
    "addr:postcode":"72212",
    "addr:street":"Southridge Dr",
    "iso:country":"US",
    "sg:address":"11501 Southridge Dr",
    "sg:city":"Little Rock",
    "sg:classifiers":[
        {
            "category":"Wholesale",
            "subcategory":"Durable Goods & Equipment",
            "type":"Manufacturing & Wholesale Goods"
        }
    ],
    "sg:phone":"+1 501 224 7929",
    "sg:postcode":"72212",
    "sg:province":"AR",
    "wof:name":"National Badges",
    "wof:placetype":"venue"
},
  "geometry": {"coordinates":[-92.41605300000001,34.803527],"type":"Point"}
}