{
  "type": "Feature",
  "properties": {
    "iso:country":"US",
    "sg:address":"6 Rillington Cir",
    "sg:city":"Bella Vista",
    "sg:classifiers":[
        {
            "category":"Professional",
            "type":"Services"
        }
    ],
    "sg:phone":"+1 479 876 5812",
    "sg:postcode":"72714",
    "sg:province":"AR",
    "wof:name":"Fireflies LLC",
    "wof:placetype":"venue"
},
  "geometry": {"coordinates":[-94.191279,36.444886],"type":"Point"}
}