{
  "type": "Feature",
  "properties": {
    "addr:full":"871 Heather Cir Conway AR 72034",
    "addr:housenumber":"871",
    "addr:postcode":"72034",
    "addr:street":"Heather Cir",
    "iso:country":"US",
    "sg:address":"871 Heather Cir",
    "sg:city":"Conway",
    "sg:classifiers":[
        {
            "category":"Education",
            "subcategory":"Special Training",
            "type":"Public Place"
        }
    ],
    "sg:phone":"+1 501 336 9924",
    "sg:postcode":"72034",
    "sg:province":"AR",
    "wof:name":"American Guild of Organis",
    "wof:placetype":"venue"
},
  "geometry": {"coordinates":[-92.474767,35.092389],"type":"Point"}
}