{
  "type": "Feature",
  "properties": {
    "iso:country":"US",
    "sg:address":"2600 E Parkway Dr",
    "sg:city":"Russellville",
    "sg:classifiers":[
        {
            "category":"Professional",
            "subcategory":"Employment Agencies",
            "type":"Services"
        }
    ],
    "sg:phone":"+1 479 967 5544",
    "sg:postcode":"72802",
    "sg:province":"AR",
    "wof:name":"Staffmark",
    "wof:placetype":"venue"
},
  "geometry": {"coordinates":[-93.10533700000001,35.28244],"type":"Point"}
}