{
  "type": "Feature",
  "properties": {
    "iso:country":"US",
    "sg:address":"818 Towson Ave",
    "sg:city":"Fort Smith",
    "sg:classifiers":[
        {
            "category":"Retail",
            "subcategory":"Repair Shop",
            "type":"Services"
        },
        {
            "category":"Wholesale",
            "subcategory":"Electrical",
            "type":"Manufacturing & Wholesale Goods"
        }
    ],
    "sg:phone":"+1 479 750 2828",
    "sg:postcode":"72901",
    "sg:province":"AR",
    "sg:tags":[
        "e",
        "system",
        "contractor",
        "equipment",
        "telephone",
        "electronic"
    ],
    "sg:website":"www.clearcomm.net",
    "wof:name":"Clear Communications Inc",
    "wof:placetype":"venue"
},
  "geometry": {"coordinates":[-94.421368,35.375655],"type":"Point"}
}