{
  "type": "Feature",
  "properties": {
    "iso:country":"US",
    "sg:address":"923 Dodson Ave",
    "sg:city":"Fort Smith",
    "sg:classifiers":[
        {
            "category":"Retail",
            "subcategory":"Auto Repair",
            "type":"Services"
        },
        {
            "category":"Autos & Motor Vehicles",
            "subcategory":"Auto Supplies",
            "type":"Retail Goods"
        }
    ],
    "sg:phone":"+1 479 782 2749",
    "sg:postcode":"72901",
    "sg:province":"AR",
    "sg:tags":[
        "alternator",
        "automotive",
        "generator"
    ],
    "wof:name":"Alternator Starter Exchange",
    "wof:placetype":"venue"
},
  "geometry": {"coordinates":[-94.42426,35.372107],"type":"Point"}
}