{
  "type": "Feature",
  "properties": {
    "iso:country":"US",
    "sg:address":"304 Calvert Rd",
    "sg:city":"Forrest City",
    "sg:classifiers":[
        {
            "category":"Real Estate",
            "subcategory":"Real Estate Operator",
            "type":"Services"
        }
    ],
    "sg:phone":"+1 870 633 3164",
    "sg:postcode":"72335",
    "sg:province":"AR",
    "sg:tags":[
        "property",
        "lessor"
    ],
    "wof:name":"Spybuck Farms Inc",
    "wof:placetype":"venue"
},
  "geometry": {"coordinates":[-90.787696,35.028491],"type":"Point"}
}