{
  "type": "Feature",
  "properties": {
    "iso:country":"US",
    "sg:address":"1020 Main St",
    "sg:city":"Conway",
    "sg:classifiers":[
        {
            "category":"Manufacturing",
            "subcategory":"Printing",
            "type":"Manufacturing & Wholesale Goods"
        }
    ],
    "sg:phone":"+1 501 327 5671",
    "sg:postcode":"72032",
    "sg:province":"AR",
    "sg:tags":[
        "newspaper"
    ],
    "wof:name":"Arkansas Democrat-Gazette",
    "wof:placetype":"venue"
},
  "geometry": {"coordinates":[-92.43828000000001,35.09015],"type":"Point"}
}