{
  "type": "Feature",
  "properties": {
    "iso:country":"US",
    "sg:address":"5234 US Hwy 71",
    "sg:city":"Cove",
    "sg:classifiers":[
        {
            "category":"Organizations",
            "subcategory":"Religious Organization",
            "type":"Services"
        }
    ],
    "sg:phone":"+1 870 387 5881",
    "sg:postcode":"71937",
    "sg:province":"AR",
    "sg:tags":[
        "church"
    ],
    "wof:name":"Christ's Church",
    "wof:placetype":"venue"
},
  "geometry": {"coordinates":[-94.394249,34.459233],"type":"Point"}
}