{
  "type": "Feature",
  "properties": {
    "iso:country":"US",
    "sg:address":"723 Garrison Ave",
    "sg:city":"Fort Smith",
    "sg:classifiers":[
        {
            "category":"Banks & Credit Unions",
            "subcategory":"Investment Brokerage",
            "type":"Services"
        }
    ],
    "sg:phone":"+1 479 494 1075",
    "sg:postcode":"72901",
    "sg:province":"AR",
    "sg:tags":[
        "security"
    ],
    "wof:name":"Morgan Keegan & Company Inc",
    "wof:placetype":"venue"
},
  "geometry": {"coordinates":[-94.423564,35.386226],"type":"Point"}
}