{
  "type": "Feature",
  "properties": {
    "iso:country":"US",
    "sg:address":"1513 98th St NW",
    "sg:city":"Grove",
    "sg:classifiers":[
        {
            "category":"Autos & Motor Vehicles",
            "subcategory":"Boat Sales",
            "type":"Retail Goods"
        }
    ],
    "sg:phone":"+1 918 786 2885",
    "sg:postcode":"74344",
    "sg:province":"OK",
    "sg:tags":[
        "repair"
    ],
    "wof:name":"Edgewater Resort Marina",
    "wof:placetype":"venue"
},
  "geometry": {"coordinates":[-94.811612,36.625345],"type":"Point"}
}