{
  "type": "Feature",
  "properties": {
    "iso:country":"US",
    "sg:address":"3544 US Hwy 71",
    "sg:city":"Mena",
    "sg:classifiers":[
        {
            "category":"Restaurant",
            "type":"Food & Drink"
        }
    ],
    "sg:phone":"+1 479 394 4079",
    "sg:postcode":"71953",
    "sg:province":"AR",
    "wof:name":"Fish Net On The Hill",
    "wof:placetype":"venue"
},
  "geometry": {"coordinates":[-94.201832,34.642562],"type":"Point"}
}