{
  "type": "Feature",
  "properties": {
    "iso:country":"US",
    "sg:address":"622 Cattle Dr",
    "sg:city":"Lowell",
    "sg:classifiers":[
        {
            "category":"Health Services",
            "subcategory":"Chiropractor",
            "type":"Services"
        }
    ],
    "sg:phone":"+1 479 659 8889",
    "sg:postcode":"72745",
    "sg:province":"AR",
    "sg:tags":[
        "chiropractic"
    ],
    "wof:name":"Dr Debra A Schaefer Pc",
    "wof:placetype":"venue"
},
  "geometry": {"coordinates":[-94.12351,36.278866],"type":"Point"}
}