{
  "type": "Feature",
  "properties": {
    "addr:full":"820B W Matthews Ave Jonesboro AR 72401",
    "addr:housenumber":"820b",
    "addr:postcode":"72401",
    "addr:street":"W Matthews Ave",
    "iso:country":"US",
    "sg:address":"820B W Matthews Ave",
    "sg:city":"Jonesboro",
    "sg:classifiers":[
        {
            "category":"Health Services",
            "subcategory":"Dentist",
            "type":"Services"
        }
    ],
    "sg:phone":"+1 870 931 3377",
    "sg:postcode":"72401",
    "sg:province":"AR",
    "sg:website":"http://www.CliftonCHigginsDDS.com",
    "wof:name":"Higgins Clifton C DDS",
    "wof:placetype":"venue"
},
  "geometry": {"coordinates":[-90.71480099999999,35.835869],"type":"Point"}
}