{
  "type": "Feature",
  "properties": {
    "addr:full":"1605 E Booth Rd Searcy AR 72143",
    "addr:housenumber":"1605",
    "addr:postcode":"72143",
    "addr:street":"E Booth Rd",
    "iso:country":"US",
    "sg:address":"1605 E Booth Rd",
    "sg:city":"Searcy",
    "sg:classifiers":[
        {
            "category":"Wholesale",
            "subcategory":"Furniture",
            "type":"Manufacturing & Wholesale Goods"
        }
    ],
    "sg:phone":"+1 501 268 8221",
    "sg:postcode":"72143",
    "sg:province":"AR",
    "wof:name":"Cousins' Office Furniture",
    "wof:placetype":"venue"
},
  "geometry": {"coordinates":[-91.72412,35.2239],"type":"Point"}
}