{
  "type": "Feature",
  "properties": {
    "iso:country":"US",
    "sg:address":"233 E Main St",
    "sg:city":"Farmington",
    "sg:classifiers":[
        {
            "category":"Shopping",
            "subcategory":"Clothing, Apparel, & Fashions",
            "type":"Retail Goods"
        }
    ],
    "sg:phone":"+1 479 267 5887",
    "sg:postcode":"72730",
    "sg:province":"AR",
    "wof:name":"Yours Truly Formal Wear",
    "wof:placetype":"venue"
},
  "geometry": {"coordinates":[-94.228946,36.045764],"type":"Point"}
}