{
  "type": "Feature",
  "properties": {
    "iso:country":"US",
    "sg:address":"3303 E Roosevelt Rd",
    "sg:city":"Little Rock",
    "sg:classifiers":[
        {
            "category":"Professional",
            "subcategory":"Business Services",
            "type":"Services"
        }
    ],
    "sg:phone":"+1 501 907 6670",
    "sg:postcode":"72206",
    "sg:province":"AR",
    "wof:name":"Business & Ind Ctr",
    "wof:placetype":"venue"
},
  "geometry": {"coordinates":[-92.239932,34.720198],"type":"Point"}
}