{
  "type": "Feature",
  "properties": {
    "addr:full":"2078 Arlie Moore Rd Bismarck AR 71929",
    "addr:housenumber":"2078",
    "addr:postcode":"71929",
    "addr:street":"Arlie Moore Rd",
    "iso:country":"US",
    "sg:address":"2078 Arlie Moore Rd",
    "sg:city":"Bismarck",
    "sg:classifiers":[
        {
            "category":"Social Services",
            "type":"Services"
        },
        {
            "category":"Real Estate",
            "subcategory":"Developer",
            "type":"Services"
        }
    ],
    "sg:phone":"+1 501 865 1883",
    "sg:postcode":"71929",
    "sg:province":"AR",
    "wof:name":"Central Arkansas Development Council",
    "wof:placetype":"venue"
},
  "geometry": {"coordinates":[-93.163372,34.284106],"type":"Point"}
}