{
  "type": "Feature",
  "properties": {
    "iso:country":"US",
    "sg:address":"10 Rolling L Ln",
    "sg:city":"Greenbrier",
    "sg:classifiers":[
        {
            "category":"Wholesale",
            "subcategory":"Machinery & Supplies",
            "type":"Manufacturing & Wholesale Goods"
        }
    ],
    "sg:phone":"+1 501 679 4515",
    "sg:postcode":"72058",
    "sg:province":"AR",
    "sg:tags":[
        "trailer",
        "mach"
    ],
    "wof:name":"Rolling L Trailers",
    "wof:placetype":"venue"
},
  "geometry": {"coordinates":[-92.389111,35.285954],"type":"Point"}
}