{
  "type": "Feature",
  "properties": {
    "iso:country":"US",
    "sg:address":"6146 Rex Rd",
    "sg:city":"Clinton",
    "sg:classifiers":[
        {
            "category":"Arena",
            "subcategory":"Horse Racetrack",
            "type":"Entertainment"
        }
    ],
    "sg:phone":"+1 501 745 7513",
    "sg:postcode":"72031",
    "sg:province":"AR",
    "sg:tags":[
        "rental"
    ],
    "wof:name":"Rv Campground",
    "wof:placetype":"venue"
},
  "geometry": {"coordinates":[-92.746393,35.584206],"type":"Point"}
}