{
  "type": "Feature",
  "properties": {
    "iso:country":"US",
    "sg:address":"3949 N Crossover Rd",
    "sg:city":"Fayetteville",
    "sg:classifiers":[
        {
            "category":"Professional",
            "subcategory":"Accounting & Tax Preparation",
            "type":"Services"
        }
    ],
    "sg:phone":"+1 479 582 4399",
    "sg:postcode":"72703",
    "sg:province":"AR",
    "wof:name":"Richard Brown",
    "wof:placetype":"venue"
},
  "geometry": {"coordinates":[-94.11948,36.121127],"type":"Point"}
}