{
  "type": "Feature",
  "properties": {
    "iso:country":"US",
    "sg:address":"125 Morgan Rd",
    "sg:city":"Batesville",
    "sg:classifiers":[
        {
            "category":"Farming",
            "subcategory":"Farm",
            "type":"Manufacturing & Wholesale Goods"
        }
    ],
    "sg:phone":"+1 870 799 8740",
    "sg:postcode":"72501",
    "sg:province":"AR",
    "sg:tags":[
        "crop",
        "general"
    ],
    "wof:name":"Donald Coleman & Sons Farms",
    "wof:placetype":"venue"
},
  "geometry": {"coordinates":[-91.558271,35.766873],"type":"Point"}
}