{
  "type": "Feature",
  "properties": {
    "addr:full":"1000 W A Ave North Little Rock AR 72116",
    "addr:housenumber":"1000",
    "addr:postcode":"72116",
    "addr:street":"W A Ave",
    "iso:country":"US",
    "sg:address":"1000 W A Ave",
    "sg:city":"North Little Rock",
    "sg:classifiers":[
        {
            "category":"Shopping",
            "subcategory":"Gifts & Souvenirs",
            "type":"Retail Goods"
        }
    ],
    "sg:phone":"+1 501 758 9209",
    "sg:postcode":"72116",
    "sg:province":"AR",
    "wof:name":"Enluxe",
    "wof:placetype":"venue"
},
  "geometry": {"coordinates":[-92.270658,34.783651],"type":"Point"}
}