{
  "type": "Feature",
  "properties": {
    "iso:country":"US",
    "sg:address":"3 Rolling Ln",
    "sg:city":"Little Rock",
    "sg:classifiers":[
        {
            "category":"Retail",
            "subcategory":"Laundry & Dry Cleaning",
            "type":"Services"
        }
    ],
    "sg:phone":"+1 501 868 2668",
    "sg:postcode":"72209",
    "sg:province":"AR",
    "sg:tags":[
        "drycleaning",
        "plant"
    ],
    "wof:name":"Village Cleaners",
    "wof:placetype":"venue"
},
  "geometry": {"coordinates":[-92.335215,34.700928],"type":"Point"}
}