{
  "type": "Feature",
  "properties": {
    "addr:full":"13005 Kanis Rd Little Rock AR 72211",
    "addr:housenumber":"13005",
    "addr:postcode":"72211",
    "addr:street":"Kanis Rd",
    "iso:country":"US",
    "sg:address":"13005 Kanis Rd",
    "sg:city":"Little Rock",
    "sg:classifiers":[
        {
            "category":"Retail",
            "subcategory":"Auto Repair",
            "type":"Services"
        }
    ],
    "sg:phone":"+1 501 225 3974",
    "sg:postcode":"72211",
    "sg:province":"AR",
    "sg:tags":[
        "automotive"
    ],
    "wof:name":"Metro Towing & Recovery",
    "wof:placetype":"venue"
},
  "geometry": {"coordinates":[-92.424616,34.743967],"type":"Point"}
}