{
  "type": "Feature",
  "properties": {
    "iso:country":"US",
    "sg:address":"1008 N Hico St",
    "sg:city":"Siloam Springs",
    "sg:classifiers":[
        {
            "category":"Building & Trades",
            "subcategory":"Landscaping Services",
            "type":"Services"
        }
    ],
    "sg:phone":"+1 479 524 8082",
    "sg:postcode":"72761",
    "sg:province":"OK",
    "sg:tags":[
        "lawn",
        "garden"
    ],
    "wof:name":"Eden Ltd",
    "wof:placetype":"venue"
},
  "geometry": {"coordinates":[-94.53222599999999,36.192473],"type":"Point"}
}