{
  "type": "Feature",
  "properties": {
    "iso:country":"US",
    "sg:address":"3 Feather Dr",
    "sg:city":"Morrilton",
    "sg:classifiers":[
        {
            "category":"Professional",
            "subcategory":"Business Services",
            "type":"Services"
        }
    ],
    "sg:phone":"+1 501 354 6693",
    "sg:postcode":"72110",
    "sg:province":"AR",
    "wof:name":"Arkansas Rodeo Assoc",
    "wof:placetype":"venue"
},
  "geometry": {"coordinates":[-92.736636,35.217924],"type":"Point"}
}