{
  "type": "Feature",
  "properties": {
    "iso:country":"US",
    "sg:address":"206 Lunen St",
    "sg:city":"Melbourne",
    "sg:classifiers":[
        {
            "category":"Government",
            "subcategory":"Post Office",
            "type":"Public Place"
        }
    ],
    "sg:phone":"+1 870 368 7706",
    "sg:postcode":"72556",
    "sg:province":"AR",
    "wof:name":"US Post Office",
    "wof:placetype":"venue"
},
  "geometry": {"coordinates":[-91.905998,36.061344],"type":"Point"}
}