{
  "type": "Feature",
  "properties": {
    "addr:full":"750 Enterprise Ave Conway AR 72032",
    "addr:housenumber":"750",
    "addr:postcode":"72032",
    "addr:street":"Enterprise Ave",
    "iso:country":"US",
    "sg:address":"750 Enterprise Ave",
    "sg:city":"Conway",
    "sg:classifiers":[
        {
            "category":"Wholesale",
            "subcategory":"Machinery & Supplies",
            "type":"Manufacturing & Wholesale Goods"
        },
        {
            "category":"Manufacturing",
            "subcategory":"Tools & Machinery",
            "type":"Manufacturing & Wholesale Goods"
        }
    ],
    "sg:phone":"+1 501 327 3605",
    "sg:postcode":"72032",
    "sg:province":"AR",
    "sg:tags":[
        "equipment",
        "industrial",
        "welding"
    ],
    "wof:name":"Welsco Inc 6",
    "wof:placetype":"venue"
},
  "geometry": {"coordinates":[-92.427516,35.068469],"type":"Point"}
}