{
  "type": "Feature",
  "properties": {
    "iso:country":"US",
    "sg:address":"17 Gorrion Ln",
    "sg:city":"Hot Springs National",
    "sg:classifiers":[
        {
            "category":"Shopping",
            "subcategory":"Jewelry",
            "type":"Retail Goods"
        }
    ],
    "sg:phone":"+1 501 922 3979",
    "sg:postcode":"71909",
    "sg:province":"AR",
    "sg:tags":[
        "equipment",
        "stone",
        "gem",
        "golfing"
    ],
    "wof:name":"Clarke Fairway Shoppe",
    "wof:placetype":"venue"
},
  "geometry": {"coordinates":[-92.903142,34.650585],"type":"Point"}
}