{
  "type": "Feature",
  "properties": {
    "addr:full":"4330 Central Ave Hot Springs National Park AR 71913",
    "addr:housenumber":"4330",
    "addr:postcode":"71913",
    "addr:street":"Central Ave",
    "iso:country":"US",
    "sg:address":"4330 Central Ave",
    "sg:city":"Hot Springs National Park",
    "sg:classifiers":[
        {
            "category":"Manufacturing",
            "subcategory":"Apparel",
            "type":"Manufacturing & Wholesale Goods"
        }
    ],
    "sg:phone":"+1 501 525 0835",
    "sg:postcode":"71913",
    "sg:province":"AR",
    "sg:tags":[
        "furnishing",
        "mfg"
    ],
    "wof:name":"Van Heusen",
    "wof:placetype":"venue"
},
  "geometry": {"coordinates":[-93.07302,34.452353],"type":"Point"}
}