{
  "type": "Feature",
  "properties": {
    "iso:country":"US",
    "sg:address":"1370 S Old Missouri Rd",
    "sg:city":"Springdale",
    "sg:classifiers":[
        {
            "category":"Building & Trades",
            "subcategory":"Equipment Rental",
            "type":"Services"
        },
        {
            "category":"Airport",
            "type":"Transportation"
        }
    ],
    "sg:phone":"+1 479 845 1080",
    "sg:postcode":"72764",
    "sg:province":"AR",
    "sg:tags":[
        "aircraft",
        "leasing",
        "charter",
        "maintenance"
    ],
    "sg:website":"www.pinnacleairservices.com",
    "wof:name":"Pinnacle Air Executive Jet",
    "wof:placetype":"venue"
},
  "geometry": {"coordinates":[-94.116587,36.177115],"type":"Point"}
}