{
  "type": "Feature",
  "properties": {
    "iso:country":"US",
    "sg:address":"1314 Twin Oaks Ave",
    "sg:city":"Jonesboro",
    "sg:classifiers":[
        {
            "category":"Professional",
            "subcategory":"Management & Consulting",
            "type":"Services"
        }
    ],
    "sg:phone":"+1 870 932 5020",
    "sg:postcode":"72401",
    "sg:province":"AR",
    "sg:tags":[
        "business"
    ],
    "wof:name":"Smith Consulting Associates",
    "wof:placetype":"venue"
},
  "geometry": {"coordinates":[-90.72511299999999,35.818377],"type":"Point"}
}