{
  "type": "Feature",
  "properties": {
    "iso:country":"US",
    "sg:address":"399 Pearl St",
    "sg:city":"Marianna",
    "sg:classifiers":[
        {
            "category":"Farming",
            "subcategory":"Farm",
            "type":"Manufacturing & Wholesale Goods"
        }
    ],
    "sg:phone":"+1 870 295 3590",
    "sg:postcode":"72360",
    "sg:province":"AR",
    "sg:tags":[
        "crop",
        "general"
    ],
    "wof:name":"David Griffith Farms",
    "wof:placetype":"venue"
},
  "geometry": {"coordinates":[-90.761839,34.782184],"type":"Point"}
}