{
  "type": "Feature",
  "properties": {
    "addr:full":"714 Barranger Rd Bismarck AR 71929",
    "addr:housenumber":"714",
    "addr:postcode":"71929",
    "addr:street":"Barranger Rd",
    "iso:country":"US",
    "sg:address":"714 Barranger Rd",
    "sg:city":"Bismarck",
    "sg:classifiers":[
        {
            "category":"Transit Center",
            "subcategory":"Freight",
            "type":"Transportation"
        },
        {
            "category":"Freight",
            "type":"Transportation"
        }
    ],
    "sg:phone":"+1 501 865 3057",
    "sg:postcode":"71929",
    "sg:province":"AR",
    "sg:tags":[
        "local",
        "trucking-motor",
        "trucking"
    ],
    "wof:name":"Pilcher Trucking",
    "wof:placetype":"venue"
},
  "geometry": {"coordinates":[-93.083232,34.317347],"type":"Point"}
}