{
  "type": "Feature",
  "properties": {
    "addr:full":"613 Orchard Dr Berryville AR 72616",
    "addr:housenumber":"613",
    "addr:postcode":"72616",
    "addr:street":"Orchard Dr",
    "iso:country":"US",
    "sg:address":"613 Orchard Dr",
    "sg:city":"Berryville",
    "sg:classifiers":[
        {
            "category":"Health Services",
            "subcategory":"Doctor",
            "type":"Services"
        }
    ],
    "sg:phone":"+1 870 423 7171",
    "sg:postcode":"72616",
    "sg:province":"AR",
    "sg:tags":[
        "clinic"
    ],
    "wof:name":"St John's Clinic-Berryville",
    "wof:placetype":"venue"
},
  "geometry": {"coordinates":[-93.55078,36.35765],"type":"Point"}
}