{
  "type": "Feature",
  "properties": {
    "iso:country":"US",
    "sg:address":"507 S Neal St",
    "sg:city":"Prairie Grove",
    "sg:classifiers":[
        {
            "category":"Real Estate",
            "subcategory":"Real Estate Operator",
            "type":"Services"
        }
    ],
    "sg:phone":"+1 479 846 4359",
    "sg:postcode":"72753",
    "sg:province":"AR",
    "sg:tags":[
        "building",
        "nonresidential"
    ],
    "wof:name":"J Robison Properties Inc",
    "wof:placetype":"venue"
},
  "geometry": {"coordinates":[-94.314983,35.970604],"type":"Point"}
}