{
  "type": "Feature",
  "properties": {
    "iso:country":"US",
    "sg:address":"445 Lawrence Rd 534",
    "sg:city":"Hoxie",
    "sg:classifiers":[
        {
            "category":"Farming",
            "subcategory":"Livestock Farm",
            "type":"Manufacturing & Wholesale Goods"
        }
    ],
    "sg:phone":"+1 870 886 6304",
    "sg:postcode":"72433",
    "sg:province":"AR",
    "sg:tags":[
        "wheat",
        "beef",
        "soybean",
        "cattle",
        "rice",
        "feedlot"
    ],
    "wof:name":"Mike Wright",
    "wof:placetype":"venue"
},
  "geometry": {"coordinates":[-91.05489,35.974958],"type":"Point"}
}