{
  "type": "Feature",
  "properties": {
    "addr:full":"1077 Main St Vilonia AR 72173",
    "addr:housenumber":"1077",
    "addr:postcode":"72173",
    "addr:street":"Main St",
    "iso:country":"US",
    "sg:address":"1077 Main St",
    "sg:city":"Vilonia",
    "sg:classifiers":[
        {
            "category":"Shopping",
            "subcategory":"Florist",
            "type":"Retail Goods"
        }
    ],
    "sg:phone":"+1 501 796 4849",
    "sg:postcode":"72173",
    "sg:province":"AR",
    "wof:name":"Modern Woodmen Of America",
    "wof:placetype":"venue"
},
  "geometry": {"coordinates":[-92.210819,35.08359],"type":"Point"}
}