{
  "type": "Feature",
  "properties": {
    "iso:country":"US",
    "sg:address":"1900 Higginson St",
    "sg:city":"Searcy",
    "sg:classifiers":[
        {
            "category":"Building & Trades",
            "subcategory":"Plumbing",
            "type":"Services"
        }
    ],
    "sg:phone":"+1 501 268 6563",
    "sg:postcode":"72143",
    "sg:province":"AR",
    "sg:tags":[
        "air",
        "conditioning",
        "supply",
        "system",
        "contractor"
    ],
    "wof:name":"P S Air Inc",
    "wof:placetype":"venue"
},
  "geometry": {"coordinates":[-91.725745,35.225831],"type":"Point"}
}