{
  "type": "Feature",
  "properties": {
    "iso:country":"US",
    "sg:address":"34 W Tennessee St",
    "sg:city":"Marianna",
    "sg:classifiers":[
        {
            "category":"Personal",
            "subcategory":"Beauty Salon",
            "type":"Services"
        }
    ],
    "sg:phone":"+1 870 295 5155",
    "sg:postcode":"72360",
    "sg:province":"AR",
    "sg:tags":[
        "shop"
    ],
    "wof:name":"Paulas",
    "wof:placetype":"venue"
},
  "geometry": {"coordinates":[-90.75837,34.772372],"type":"Point"}
}