{
  "type": "Feature",
  "properties": {
    "addr:full":"548 Dave Creek Pkwy Fairfield Bay AR 72088",
    "addr:housenumber":"548",
    "addr:postcode":"72088",
    "addr:street":"Dave Creek Pkwy",
    "iso:country":"US",
    "sg:address":"548 Dave Creek Pkwy",
    "sg:city":"Fairfield Bay",
    "sg:classifiers":[
        {
            "category":"Retail",
            "subcategory":"Repair Shop",
            "type":"Services"
        }
    ],
    "sg:phone":"+1 501 884 6000",
    "sg:postcode":"72088",
    "sg:province":"AR",
    "sg:tags":[
        "lock",
        "locksmith"
    ],
    "wof:name":"Doc Holiday Locksmith",
    "wof:placetype":"venue"
},
  "geometry": {"coordinates":[-92.26913999999999,35.605893],"type":"Point"}
}