{
  "type": "Feature",
  "properties": {
    "iso:country":"US",
    "sg:address":"420 Holcomb St",
    "sg:city":"Springdale",
    "sg:classifiers":[
        {
            "category":"Professional",
            "subcategory":"Accounting & Tax Preparation",
            "type":"Services"
        }
    ],
    "sg:phone":"+1 479 756 2700",
    "sg:postcode":"72764",
    "sg:province":"AR",
    "sg:tags":[
        "return"
    ],
    "wof:name":"Wanda C Sampson CPA",
    "wof:placetype":"venue"
},
  "geometry": {"coordinates":[-94.131466,36.181492],"type":"Point"}
}