{
  "type": "Feature",
  "properties": {
    "addr:full":"831 Alabama Ave Earle AR 72331",
    "addr:housenumber":"831",
    "addr:postcode":"72331",
    "addr:street":"Alabama Ave",
    "iso:country":"US",
    "sg:address":"831 Alabama Ave",
    "sg:city":"Earle",
    "sg:classifiers":[
        {
            "category":"Organizations",
            "subcategory":"Religious Organization",
            "type":"Services"
        }
    ],
    "sg:phone":"+1 870 792 7590",
    "sg:postcode":"72331",
    "sg:province":"AR",
    "wof:name":"First Baptist Missionary",
    "wof:placetype":"venue"
},
  "geometry": {"coordinates":[-90.462182,35.268457],"type":"Point"}
}