{
  "type": "Feature",
  "properties": {
    "iso:country":"US",
    "sg:address":"115 S Main St",
    "sg:city":"Grove",
    "sg:classifiers":[
        {
            "category":"Home & Garden",
            "subcategory":"Building Materials",
            "type":"Retail Goods"
        }
    ],
    "sg:phone":"+1 918 786 2658",
    "sg:postcode":"74344",
    "sg:province":"OK",
    "sg:website":"www.sancolumber.com",
    "wof:name":"Sanco Lumber Inc",
    "wof:placetype":"venue"
},
  "geometry": {"coordinates":[-94.769436,36.595471],"type":"Point"}
}