{
  "type": "Feature",
  "properties": {
    "iso:country":"US",
    "sg:address":"109 SE 8th St",
    "sg:city":"Bentonville",
    "sg:classifiers":[
        {
            "category":"Military Area",
            "type":"Public Place"
        }
    ],
    "sg:phone":"+1 479 273 5331",
    "sg:postcode":"72712",
    "sg:province":"AR",
    "sg:tags":[
        "force",
        "armed",
        "recruiting"
    ],
    "wof:name":"Arkansas Department Of National Guard",
    "wof:placetype":"venue"
},
  "geometry": {"coordinates":[-94.20889200000001,36.364248],"type":"Point"}
}