{
  "type": "Feature",
  "properties": {
    "addr:full":"8501 Dreher Ln Little Rock AR 72209",
    "addr:housenumber":"8501",
    "addr:postcode":"72209",
    "addr:street":"Dreher Ln",
    "iso:country":"US",
    "sg:address":"8501 Dreher Ln",
    "sg:city":"Little Rock",
    "sg:classifiers":[
        {
            "category":"Real Estate",
            "subcategory":"Real Estate Operator",
            "type":"Services"
        }
    ],
    "sg:phone":"+1 501 562 9489",
    "sg:postcode":"72209",
    "sg:province":"AR",
    "sg:tags":[
        "apartment"
    ],
    "wof:name":"Mc Cormick Rentals",
    "wof:placetype":"venue"
},
  "geometry": {"coordinates":[-92.33523599999999,34.672181],"type":"Point"}
}