{
  "type": "Feature",
  "properties": {
    "iso:country":"US",
    "sg:address":"1221 W Walnut St",
    "sg:city":"Rogers",
    "sg:classifiers":[
        {
            "category":"Travel",
            "subcategory":"Travel Agent",
            "type":"Entertainment"
        }
    ],
    "sg:phone":"+1 479 631 0800",
    "sg:postcode":"72756",
    "sg:province":"AR",
    "sg:tags":[
        "tour",
        "agency",
        "bureau"
    ],
    "wof:name":"Travel Connection Ltd the",
    "wof:placetype":"venue"
},
  "geometry": {"coordinates":[-94.13339999999999,36.333599],"type":"Point"}
}