{
  "type": "Feature",
  "properties": {
    "iso:country":"US",
    "sg:address":"460 Hwy 21 N",
    "sg:city":"Berryville",
    "sg:classifiers":[
        {
            "category":"Retail",
            "subcategory":"Animal Services",
            "type":"Services"
        }
    ],
    "sg:phone":"+1 870 423 6341",
    "sg:postcode":"72616",
    "sg:province":"AR",
    "sg:tags":[
        "pet",
        "grooming",
        "washing"
    ],
    "wof:name":"Diana's Grooming & Boarding",
    "wof:placetype":"venue"
},
  "geometry": {"coordinates":[-93.56726500000001,36.3688],"type":"Point"}
}