{
  "type": "Feature",
  "properties": {
    "addr:full":"273 Solomon Grove Rd Damascus AR 72039",
    "addr:housenumber":"273",
    "addr:postcode":"72039",
    "addr:street":"Solomon Grove Rd",
    "iso:country":"US",
    "sg:address":"273 Solomon Grove Rd",
    "sg:city":"Damascus",
    "sg:classifiers":[
        {
            "category":"Organizations",
            "subcategory":"Religious Organization",
            "type":"Services"
        }
    ],
    "sg:phone":"+1 501 335 7256",
    "sg:postcode":"72039",
    "sg:province":"AR",
    "sg:tags":[
        "church"
    ],
    "wof:name":"Solomon Grove Baptist Church",
    "wof:placetype":"venue"
},
  "geometry": {"coordinates":[-92.43931000000001,35.313526],"type":"Point"}
}