{
  "type": "Feature",
  "properties": {
    "iso:country":"US",
    "sg:address":"364 W 4th St",
    "sg:city":"Waldron",
    "sg:classifiers":[
        {
            "category":"Personal",
            "subcategory":"Beauty Salon",
            "type":"Services"
        }
    ],
    "sg:phone":"+1 479 637 4477",
    "sg:postcode":"72958",
    "sg:province":"AR",
    "sg:tags":[
        "shop"
    ],
    "wof:name":"Judys Beauty Shop",
    "wof:placetype":"venue"
},
  "geometry": {"coordinates":[-94.095463,34.898754],"type":"Point"}
}