{
  "type": "Feature",
  "properties": {
    "addr:full":"958 Pioneer Trail Dr Mountain Home AR 72653",
    "addr:housenumber":"958",
    "addr:postcode":"72653",
    "addr:street":"Pioneer Trail Dr",
    "iso:country":"US",
    "sg:address":"958 Pioneer Trail Dr",
    "sg:city":"Mountain Home",
    "sg:classifiers":[
        {
            "category":"Building & Trades",
            "subcategory":"Construction",
            "type":"Services"
        }
    ],
    "sg:phone":"+1 870 492 6579",
    "sg:postcode":"72653",
    "sg:province":"AR",
    "sg:tags":[
        "general",
        "contractor"
    ],
    "wof:name":"Bliss Construction",
    "wof:placetype":"venue"
},
  "geometry": {"coordinates":[-92.34569999999999,36.368939],"type":"Point"}
}