{
  "type": "Feature",
  "properties": {
    "iso:country":"US",
    "sg:address":"75 Redleaf Cir",
    "sg:city":"Little Rock",
    "sg:classifiers":[
        {
            "category":"Professional",
            "type":"Services"
        }
    ],
    "sg:phone":"+1 501 455 9704",
    "sg:postcode":"72210",
    "sg:province":"AR",
    "wof:name":"Hogwash 1 Inc",
    "wof:placetype":"venue"
},
  "geometry": {"coordinates":[-92.416907,34.675759],"type":"Point"}
}