{
  "type": "Feature",
  "properties": {
    "iso:country":"US",
    "sg:address":"2811 Fayetteville Rd",
    "sg:city":"Van Buren",
    "sg:classifiers":[
        {
            "category":"Organizations",
            "subcategory":"Religious Organization",
            "type":"Services"
        }
    ],
    "sg:phone":"+1 479 474 7770",
    "sg:postcode":"72956",
    "sg:province":"AR",
    "sg:tags":[
        "church"
    ],
    "wof:name":"Light House Baptist Church",
    "wof:placetype":"venue"
},
  "geometry": {"coordinates":[-94.356146,35.475966],"type":"Point"}
}