{
  "type": "Feature",
  "properties": {
    "addr:full":"110 Mitchell Ln Beebe AR 72012",
    "addr:housenumber":"110",
    "addr:postcode":"72012",
    "addr:street":"Mitchell Ln",
    "iso:country":"US",
    "sg:address":"110 Mitchell Ln",
    "sg:city":"Beebe",
    "sg:classifiers":[
        {
            "category":"Building & Trades",
            "subcategory":"Construction",
            "type":"Services"
        }
    ],
    "sg:phone":"+1 501 791 2289",
    "sg:postcode":"72012",
    "sg:province":"AR",
    "sg:tags":[
        "specializing",
        "work",
        "commercial",
        "contractor",
        "general",
        "utility"
    ],
    "wof:name":"K & E Construction Inc",
    "wof:placetype":"venue"
},
  "geometry": {"coordinates":[-91.872168,35.05353],"type":"Point"}
}