{
  "type": "Feature",
  "properties": {
    "iso:country":"US",
    "sg:address":"2503 Chaffin Ln",
    "sg:city":"Magnolia",
    "sg:classifiers":[
        {
            "category":"Mining & Drilling",
            "type":"Manufacturing & Wholesale Goods"
        }
    ],
    "sg:phone":"+1 870 234 1566",
    "sg:postcode":"71753",
    "sg:province":"AR",
    "sg:tags":[
        "oil",
        "gas",
        "producer"
    ],
    "wof:name":"SHERIDAN Energy",
    "wof:placetype":"venue"
},
  "geometry": {"coordinates":[-93.22059900000001,33.292549],"type":"Point"}
}