{
  "type": "Feature",
  "properties": {
    "iso:country":"US",
    "sg:address":"61 Acklin Gap Rd",
    "sg:city":"Conway",
    "sg:classifiers":[
        {
            "category":"Communications",
            "type":"Services"
        }
    ],
    "sg:phone":"+1 501 329 4126",
    "sg:postcode":"72032",
    "sg:province":"AR",
    "sg:tags":[
        "carrier",
        "radiotelephone",
        "communications-common"
    ],
    "wof:name":"Global Tower",
    "wof:placetype":"venue"
},
  "geometry": {"coordinates":[-92.38958,35.134159],"type":"Point"}
}