{
  "type": "Feature",
  "properties": {
    "addr:full":"3133 Mount Tabor Rd Cabot AR 72023",
    "addr:housenumber":"3133",
    "addr:postcode":"72023",
    "addr:street":"Mount Tabor Rd",
    "iso:country":"US",
    "sg:address":"3133 Mount Tabor Rd",
    "sg:city":"Cabot",
    "sg:classifiers":[
        {
            "category":"Building & Trades",
            "subcategory":"Construction",
            "type":"Services"
        }
    ],
    "sg:phone":"+1 501 605 0563",
    "sg:postcode":"72023",
    "sg:province":"AR",
    "sg:tags":[
        "maker",
        "cabinet"
    ],
    "wof:name":"Custom Cabinets Triple R",
    "wof:placetype":"venue"
},
  "geometry": {"coordinates":[-91.962596,34.908915],"type":"Point"}
}