{
  "type": "Feature",
  "properties": {
    "addr:full":"308 E Main St Norman AR 71960",
    "addr:housenumber":"308",
    "addr:postcode":"71960",
    "addr:street":"E Main St",
    "iso:country":"US",
    "sg:address":"308 E Main St",
    "sg:city":"Norman",
    "sg:classifiers":[
        {
            "category":"Restaurant",
            "type":"Food & Drink"
        }
    ],
    "sg:phone":"+1 870 334 2331",
    "sg:postcode":"71960",
    "sg:province":"AR",
    "wof:name":"Melba's Country Cooking",
    "wof:placetype":"venue"
},
  "geometry": {"coordinates":[-93.67995500000001,34.454952],"type":"Point"}
}