{
  "type": "Feature",
  "properties": {
    "iso:country":"US",
    "sg:address":"597 Magnetic Dr",
    "sg:city":"Eureka Springs",
    "sg:classifiers":[
        {
            "category":"Travel",
            "subcategory":"Hotels & Motels",
            "type":"Entertainment"
        }
    ],
    "sg:phone":"+1 479 363 9396",
    "sg:postcode":"72632",
    "sg:province":"AR",
    "sg:tags":[
        "breakfast",
        "accommodation",
        "bed"
    ],
    "wof:name":"Belle Springs B & B & Cottages",
    "wof:placetype":"venue"
},
  "geometry": {"coordinates":[-93.72153400000001,36.404702],"type":"Point"}
}