{
  "type": "Feature",
  "properties": {
    "addr:full":"3712 Woodland Heights Rd Little Rock AR 72212",
    "addr:housenumber":"3712",
    "addr:postcode":"72212",
    "addr:street":"Woodland Heights Rd",
    "iso:country":"US",
    "sg:address":"3712 Woodland Heights Rd",
    "sg:city":"Little Rock",
    "sg:classifiers":[
        {
            "category":"Retail",
            "subcategory":"Veterinary Services",
            "type":"Services"
        }
    ],
    "sg:phone":"+1 501 225 2600",
    "sg:postcode":"72212",
    "sg:province":"AR",
    "wof:name":"Pleasant Vly Vtrinarian Clinic",
    "wof:placetype":"venue"
},
  "geometry": {"coordinates":[-92.401872,34.790345],"type":"Point"}
}