{
  "type": "Feature",
  "properties": {
    "iso:country":"US",
    "sg:address":"2606 W Main St",
    "sg:city":"Russellville",
    "sg:classifiers":[
        {
            "category":"Professional",
            "subcategory":"Business Services",
            "type":"Services"
        }
    ],
    "sg:phone":"+1 479 968 5392",
    "sg:postcode":"72801",
    "sg:province":"AR",
    "wof:name":"Guthries RE & Auctn Svc",
    "wof:placetype":"venue"
},
  "geometry": {"coordinates":[-93.15893,35.285658],"type":"Point"}
}