{
  "type": "Feature",
  "properties": {
    "iso:country":"US",
    "sg:address":"204 N 2nd St",
    "sg:city":"Mc Gehee",
    "sg:classifiers":[
        {
            "category":"Social Services",
            "type":"Services"
        }
    ],
    "sg:phone":"+1 870 222 3702",
    "sg:postcode":"71654",
    "sg:province":"AR",
    "wof:name":"Boys & Girls Club",
    "wof:placetype":"venue"
},
  "geometry": {"coordinates":[-91.39765,33.629967],"type":"Point"}
}