{
  "type": "Feature",
  "properties": {
    "iso:country":"US",
    "sg:address":"3476 Ozark Acres Dr",
    "sg:city":"Bentonville",
    "sg:classifiers":[
        {
            "category":"Food & Beverages",
            "subcategory":"Groceries & Convenience Stores",
            "type":"Retail Goods"
        }
    ],
    "sg:phone":"+1 479 464 4478",
    "sg:postcode":"72712",
    "sg:province":"AR",
    "sg:tags":[
        "product"
    ],
    "wof:name":"Tyson Foods Inc",
    "wof:placetype":"venue"
},
  "geometry": {"coordinates":[-94.218709,36.311385],"type":"Point"}
}