{
  "type": "Feature",
  "properties": {
    "iso:country":"US",
    "sg:address":"2321 N Highway 79",
    "sg:city":"Fordyce",
    "sg:classifiers":[
        {
            "category":"Structure",
            "subcategory":"Restrooms",
            "type":"Public Place"
        },
        {
            "category":"Home & Garden",
            "subcategory":"Building Materials",
            "type":"Retail Goods"
        }
    ],
    "sg:phone":"+1 870 352 7365",
    "sg:postcode":"71742",
    "sg:province":"AR",
    "sg:tags":[
        "treating",
        "lumber",
        "lumber-used"
    ],
    "wof:name":"Spearks Kiln & Service",
    "wof:placetype":"venue"
},
  "geometry": {"coordinates":[-92.37196,33.845181],"type":"Point"}
}