{
  "type": "Feature",
  "properties": {
    "iso:country":"US",
    "sg:address":"27 Rahling Cir",
    "sg:city":"Little Rock",
    "sg:classifiers":[
        {
            "category":"Personal",
            "subcategory":"Tanning Parlor",
            "type":"Services"
        }
    ],
    "sg:phone":"+1 501 975 4684",
    "sg:postcode":"72223",
    "sg:province":"AR",
    "sg:tags":[
        "salon"
    ],
    "wof:name":"Hottie Body Inc",
    "wof:placetype":"venue"
},
  "geometry": {"coordinates":[-92.456932,34.770479],"type":"Point"}
}