{
  "type": "Feature",
  "properties": {
    "iso:country":"US",
    "sg:address":"301 Arrowhead Dr",
    "sg:city":"Hot Springs",
    "sg:classifiers":[
        {
            "category":"Personal",
            "type":"Services"
        }
    ],
    "sg:phone":"+1 501 318 1597",
    "sg:postcode":"71913",
    "sg:province":"AR",
    "sg:tags":[
        "wedding",
        "chapel"
    ],
    "wof:name":"Wedding Ceremony Svc",
    "wof:placetype":"venue"
},
  "geometry": {"coordinates":[-93.166009,34.487996],"type":"Point"}
}