{
  "type": "Feature",
  "properties": {
    "iso:country":"US",
    "sg:address":"577 E Millsap Rd",
    "sg:city":"Fayetteville",
    "sg:classifiers":[
        {
            "category":"Shopping",
            "type":"Retail Goods"
        }
    ],
    "sg:phone":"+1 479 966 4622",
    "sg:postcode":"72703",
    "sg:province":"AR",
    "sg:tags":[
        "item",
        "boutique"
    ],
    "wof:name":"Tesori",
    "wof:placetype":"venue"
},
  "geometry": {"coordinates":[-94.149967,36.114274],"type":"Point"}
}