{
  "type": "Feature",
  "properties": {
    "iso:country":"US",
    "sg:address":"8112 Pinnacle Valley Rd",
    "sg:city":"Little Rock",
    "sg:classifiers":[
        {
            "category":"Farming",
            "subcategory":"Farm",
            "type":"Manufacturing & Wholesale Goods"
        }
    ],
    "sg:phone":"+1 501 868 8296",
    "sg:postcode":"72223",
    "sg:province":"AR",
    "sg:tags":[
        "crop",
        "general"
    ],
    "wof:name":"Flatrock Farms LLC",
    "wof:placetype":"venue"
},
  "geometry": {"coordinates":[-92.436076,34.824056],"type":"Point"}
}