{
  "type": "Feature",
  "properties": {
    "iso:country":"US",
    "sg:address":"1318 Pine St",
    "sg:city":"Arkadelphia",
    "sg:classifiers":[
        {
            "category":"Shopping",
            "subcategory":"Used Merchandise",
            "type":"Retail Goods"
        }
    ],
    "sg:phone":"+1 870 246 4852",
    "sg:postcode":"71923",
    "sg:province":"AR",
    "sg:tags":[
        "repair"
    ],
    "wof:name":"Waites Gun & Pawn Inc",
    "wof:placetype":"venue"
},
  "geometry": {"coordinates":[-93.06272800000001,34.122661],"type":"Point"}
}