{
  "type": "Feature",
  "properties": {
    "iso:country":"US",
    "sg:address":"907 S 22nd St",
    "sg:city":"Arkadelphia",
    "sg:classifiers":[
        {
            "category":"Retail",
            "subcategory":"Repair Shop",
            "type":"Services"
        }
    ],
    "sg:phone":"+1 870 246 4289",
    "sg:postcode":"71923",
    "sg:province":"AR",
    "sg:tags":[
        "welding"
    ],
    "wof:name":"Bbs Welding Specialist",
    "wof:placetype":"venue"
},
  "geometry": {"coordinates":[-93.076177,34.113851],"type":"Point"}
}