{
  "type": "Feature",
  "properties": {
    "iso:country":"US",
    "sg:address":"138 San Jose Dr",
    "sg:city":"Springdale",
    "sg:classifiers":[
        {
            "category":"Professional",
            "subcategory":"Accounting & Tax Preparation",
            "type":"Services"
        }
    ],
    "sg:phone":"+1 479 751 3173",
    "sg:postcode":"72764",
    "sg:province":"AR",
    "wof:name":"CPA Kenny Sexton",
    "wof:placetype":"venue"
},
  "geometry": {"coordinates":[-94.151627,36.136149],"type":"Point"}
}