{
  "type": "Feature",
  "properties": {
    "iso:country":"US",
    "sg:address":"907 Moss",
    "sg:city":"Pangburn",
    "sg:classifiers":[
        {
            "category":"Personal",
            "subcategory":"Beauty Salon",
            "type":"Services"
        }
    ],
    "sg:phone":"+1 501 728 2226",
    "sg:postcode":"72121",
    "sg:province":"AR",
    "sg:tags":[
        "shop"
    ],
    "wof:name":"Back Porch Cut & Curl",
    "wof:placetype":"venue"
},
  "geometry": {"coordinates":[-91.838241,35.430665],"type":"Point"}
}