{
  "type": "Feature",
  "properties": {
    "iso:country":"US",
    "sg:address":"1028 N Missouri St",
    "sg:city":"West Memphis",
    "sg:classifiers":[
        {
            "category":"Professional",
            "subcategory":"Accounting & Tax Preparation",
            "type":"Services"
        }
    ],
    "sg:phone":"+1 870 735 2187",
    "sg:postcode":"72301",
    "sg:province":"AR",
    "sg:tags":[
        "return",
        "filing"
    ],
    "wof:name":"Lonnie Taylor Public Accntnt",
    "wof:placetype":"venue"
},
  "geometry": {"coordinates":[-90.184818,35.157433],"type":"Point"}
}