{
  "type": "Feature",
  "properties": {
    "iso:country":"US",
    "sg:address":"307 W Parker St",
    "sg:city":"Plumerville",
    "sg:classifiers":[
        {
            "category":"Manufacturing",
            "subcategory":"Motor Vehicles & Parts",
            "type":"Manufacturing & Wholesale Goods"
        }
    ],
    "sg:phone":"+1 501 354 8805",
    "sg:postcode":"72127",
    "sg:province":"AR",
    "sg:tags":[
        "equipment",
        "transportation"
    ],
    "sg:website":"www.ponderosatrailers.com",
    "wof:name":"Central Arkansas Fabrication",
    "wof:placetype":"venue"
},
  "geometry": {"coordinates":[-92.645065,35.16508],"type":"Point"}
}