{
  "type": "Feature",
  "properties": {
    "iso:country":"US",
    "sg:address":"508 Fairway Cir",
    "sg:city":"Springdale",
    "sg:classifiers":[
        {
            "category":"Organizations",
            "subcategory":"Religious Organization",
            "type":"Services"
        }
    ],
    "sg:phone":"+1 479 751 0338",
    "sg:postcode":"72764",
    "sg:province":"AR",
    "wof:name":"Red Dixon Evangelistic As",
    "wof:placetype":"venue"
},
  "geometry": {"coordinates":[-94.142586,36.146029],"type":"Point"}
}