{
  "type": "Feature",
  "properties": {
    "iso:country":"US",
    "sg:address":"1011 S 25th St",
    "sg:city":"Van Buren",
    "sg:classifiers":[
        {
            "category":"Retail",
            "subcategory":"Repair Shop",
            "type":"Services"
        }
    ],
    "sg:phone":"+1 479 474 2676",
    "sg:postcode":"72956",
    "sg:province":"AR",
    "sg:tags":[
        "scale",
        "commercial"
    ],
    "wof:name":"Mosman Scale Company Inc",
    "wof:placetype":"venue"
},
  "geometry": {"coordinates":[-94.333287,35.421853],"type":"Point"}
}