{
  "type": "Feature",
  "properties": {
    "addr:full":"117 W Center Cave City AR 72521",
    "addr:housenumber":"117",
    "addr:postcode":"72521",
    "addr:street":"W Center",
    "iso:country":"US",
    "sg:address":"117 W Center",
    "sg:city":"Cave City",
    "sg:classifiers":[
        {
            "category":"Cinema",
            "subcategory":"Movie Rental",
            "type":"Entertainment"
        }
    ],
    "sg:phone":"+1 870 283 5772",
    "sg:postcode":"72521",
    "sg:province":"AR",
    "sg:tags":[
        "leasing",
        "video",
        "disc",
        "tape"
    ],
    "wof:name":"Front Row Video",
    "wof:placetype":"venue"
},
  "geometry": {"coordinates":[-91.55341900000001,35.941919],"type":"Point"}
}