{
  "type": "Feature",
  "properties": {
    "iso:country":"US",
    "sg:address":"414 Polk Road 7",
    "sg:city":"Wickes",
    "sg:classifiers":[
        {
            "category":"Building & Trades",
            "subcategory":"Cleaning & Sanitation",
            "type":"Services"
        }
    ],
    "sg:phone":"+1 870 385 2202",
    "sg:postcode":"71973",
    "sg:province":"AR",
    "sg:tags":[
        "janitorial"
    ],
    "wof:name":"Bonnie E Richardson",
    "wof:placetype":"venue"
},
  "geometry": {"coordinates":[-94.374495,34.292606],"type":"Point"}
}