{
  "type": "Feature",
  "properties": {
    "addr:full":"577 Weston St Pea Ridge AR 72751",
    "addr:housenumber":"577",
    "addr:postcode":"72751",
    "addr:street":"Weston St",
    "iso:country":"US",
    "sg:address":"577 Weston St",
    "sg:city":"Pea Ridge",
    "sg:classifiers":[
        {
            "category":"Organizations",
            "subcategory":"Religious Organization",
            "type":"Services"
        }
    ],
    "sg:phone":"+1 479 451 8153",
    "sg:postcode":"72751",
    "sg:province":"AR",
    "sg:tags":[
        "church"
    ],
    "wof:name":"Assembly Of God Church",
    "wof:placetype":"venue"
},
  "geometry": {"coordinates":[-94.122811,36.443269],"type":"Point"}
}