{
  "type": "Feature",
  "properties": {
    "iso:country":"US",
    "sg:address":"1001 Maple Valley Rd",
    "sg:city":"Alma",
    "sg:classifiers":[
        {
            "category":"Organizations",
            "subcategory":"Religious Organization",
            "type":"Services"
        }
    ],
    "sg:phone":"+1 479 632 3226",
    "sg:postcode":"72921",
    "sg:province":"AR",
    "sg:tags":[
        "church"
    ],
    "wof:name":"Sovereign Grace Missionary Bpt",
    "wof:placetype":"venue"
},
  "geometry": {"coordinates":[-94.24727,35.493506],"type":"Point"}
}