{
  "type": "Feature",
  "properties": {
    "addr:full":"1005 Beau Terre Dr Bentonville AR 72712",
    "addr:housenumber":"1005",
    "addr:postcode":"72712",
    "addr:street":"Beau Terre Dr",
    "iso:country":"US",
    "sg:address":"1005 Beau Terre Dr",
    "sg:city":"Bentonville",
    "sg:classifiers":[
        {
            "category":"Professional",
            "subcategory":"Business Services",
            "type":"Services"
        }
    ],
    "sg:phone":"+1 479 855 9000",
    "sg:postcode":"72712",
    "sg:province":"AR",
    "wof:name":"Vr Business Brokers",
    "wof:placetype":"venue"
},
  "geometry": {"coordinates":[-94.171181,36.382306],"type":"Point"}
}