{
  "type": "Feature",
  "properties": {
    "addr:full":"3214 Old Warren Rd Pine Bluff AR 71603",
    "addr:housenumber":"3214",
    "addr:postcode":"71603",
    "addr:street":"Old Warren Rd",
    "iso:country":"US",
    "sg:address":"3214 Old Warren Rd",
    "sg:city":"Pine Bluff",
    "sg:classifiers":[
        {
            "category":"Recreation",
            "type":"Entertainment"
        }
    ],
    "sg:phone":"+1 870 541 0747",
    "sg:postcode":"71603",
    "sg:province":"AR",
    "wof:name":"Skateland",
    "wof:placetype":"venue"
},
  "geometry": {"coordinates":[-92.030891,34.197197],"type":"Point"}
}