{
  "type": "Feature",
  "properties": {
    "iso:country":"US",
    "sg:address":"3911 NE Kensington Ave",
    "sg:city":"Bentonville",
    "sg:classifiers":[
        {
            "category":"Building & Trades",
            "subcategory":"Construction",
            "type":"Services"
        }
    ],
    "sg:phone":"+1 479 271 0908",
    "sg:postcode":"72712",
    "sg:province":"AR",
    "sg:tags":[
        "house"
    ],
    "wof:name":"Kimberlys Homes Inc",
    "wof:placetype":"venue"
},
  "geometry": {"coordinates":[-94.1617,36.384328],"type":"Point"}
}