{
  "type": "Feature",
  "properties": {
    "iso:country":"US",
    "sg:address":"2001 Ramsgate Way",
    "sg:city":"Fort Smith",
    "sg:classifiers":[
        {
            "category":"Shopping",
            "subcategory":"Clothing, Apparel, & Fashions",
            "type":"Retail Goods"
        }
    ],
    "sg:phone":"+1 479 648 6741",
    "sg:postcode":"72908",
    "sg:province":"AR",
    "wof:name":"Tracy Davis Creations",
    "wof:placetype":"venue"
},
  "geometry": {"coordinates":[-94.414869,35.285948],"type":"Point"}
}