{
  "type": "Feature",
  "properties": {
    "iso:country":"US",
    "sg:address":"200 W 6th St",
    "sg:city":"North Little Rock",
    "sg:classifiers":[
        {
            "category":"Organizations",
            "subcategory":"Religious Organization",
            "type":"Services"
        }
    ],
    "sg:phone":"+1 501 372 1007",
    "sg:postcode":"72114",
    "sg:province":"AR",
    "wof:name":"White Rose Mssnary Bptst Chrch",
    "wof:placetype":"venue"
},
  "geometry": {"coordinates":[-92.270035,34.759091],"type":"Point"}
}