{
  "type": "Feature",
  "properties": {
    "addr:full":"800 Clinton St Arkadelphia AR 71923",
    "addr:housenumber":"800",
    "addr:postcode":"71923",
    "addr:street":"Clinton St",
    "iso:country":"US",
    "sg:address":"800 Clinton St",
    "sg:city":"Arkadelphia",
    "sg:classifiers":[
        {
            "category":"Retail",
            "subcategory":"Auto Repair",
            "type":"Services"
        }
    ],
    "sg:phone":"+1 870 246 2724",
    "sg:postcode":"71923",
    "sg:province":"AR",
    "sg:tags":[
        "repairing",
        "automobile",
        "general"
    ],
    "wof:name":"Adair's Automotive",
    "wof:placetype":"venue"
},
  "geometry": {"coordinates":[-93.056365,34.120354],"type":"Point"}
}