{
  "type": "Feature",
  "properties": {
    "iso:country":"US",
    "sg:address":"2605 S Thompson St",
    "sg:city":"Springdale",
    "sg:classifiers":[
        {
            "category":"Autos & Motor Vehicles",
            "subcategory":"Automobile Sales",
            "type":"Retail Goods"
        }
    ],
    "sg:phone":"+1 479 750 9800",
    "sg:postcode":"72764",
    "sg:province":"AR",
    "sg:tags":[
        "car",
        "dealer"
    ],
    "wof:name":"Baker's Auto Ctr",
    "wof:placetype":"venue"
},
  "geometry": {"coordinates":[-94.143638,36.163138],"type":"Point"}
}