{
  "type": "Feature",
  "properties": {
    "iso:country":"US",
    "sg:address":"2733 E Nettleton Ave",
    "sg:city":"Jonesboro",
    "sg:classifiers":[
        {
            "category":"Restaurant",
            "type":"Food & Drink"
        }
    ],
    "sg:phone":"+1 870 931 3287",
    "sg:postcode":"72401",
    "sg:province":"AR",
    "wof:name":"Mc Kay's Restaurant",
    "wof:placetype":"venue"
},
  "geometry": {"coordinates":[-90.672128,35.828303],"type":"Point"}
}