{
  "type": "Feature",
  "properties": {
    "iso:country":"US",
    "sg:address":"1106 S Old Missouri Rd",
    "sg:city":"Springdale",
    "sg:classifiers":[
        {
            "category":"Airport",
            "type":"Transportation"
        }
    ],
    "sg:phone":"+1 479 751 7233",
    "sg:postcode":"72764",
    "sg:province":"AR",
    "sg:tags":[
        "support",
        "airline"
    ],
    "wof:name":"Max's Aviation Inc",
    "wof:placetype":"venue"
},
  "geometry": {"coordinates":[-94.116399,36.180607],"type":"Point"}
}