{
  "type": "Feature",
  "properties": {
    "iso:country":"US",
    "sg:address":"14 W Summit Cove",
    "sg:city":"Cabot",
    "sg:classifiers":[
        {
            "category":"Real Estate",
            "subcategory":"Developer",
            "type":"Services"
        }
    ],
    "sg:phone":"+1 501 843 2774",
    "sg:postcode":"72023",
    "sg:province":"AR",
    "wof:name":"Chimney Rock LLC",
    "wof:placetype":"venue"
},
  "geometry": {"coordinates":[-92.038872,34.990985],"type":"Point"}
}