{
  "type": "Feature",
  "properties": {
    "addr:full":"139 High School Dr Arkadelphia AR 71923",
    "addr:housenumber":"139",
    "addr:postcode":"71923",
    "addr:street":"High School Dr",
    "iso:country":"US",
    "sg:address":"139 High School Dr",
    "sg:city":"Arkadelphia",
    "sg:classifiers":[
        {
            "category":"Organizations",
            "subcategory":"Religious Organization",
            "type":"Services"
        }
    ],
    "sg:phone":"+1 870 246 5049",
    "sg:postcode":"71923",
    "sg:province":"AR",
    "sg:tags":[
        "church"
    ],
    "wof:name":"New Life Church",
    "wof:placetype":"venue"
},
  "geometry": {"coordinates":[-93.097527,34.119478],"type":"Point"}
}