{
  "type": "Feature",
  "properties": {
    "iso:country":"US",
    "sg:address":"5105 Free Ferry Rd",
    "sg:city":"Fort Smith",
    "sg:classifiers":[
        {
            "category":"Freight",
            "type":"Transportation"
        }
    ],
    "sg:phone":"+1 479 484 1818",
    "sg:postcode":"72903",
    "sg:province":"AR",
    "sg:tags":[
        "general"
    ],
    "wof:name":"C D Warehouse",
    "wof:placetype":"venue"
},
  "geometry": {"coordinates":[-94.376049,35.37452],"type":"Point"}
}