{
  "type": "Feature",
  "properties": {
    "iso:country":"US",
    "sg:address":"75 Mesero Way",
    "sg:city":"Hot Springs National",
    "sg:classifiers":[
        {
            "category":"Shopping",
            "subcategory":"Jewelry",
            "type":"Retail Goods"
        }
    ],
    "sg:phone":"+1 501 922 6534",
    "sg:postcode":"71909",
    "sg:province":"AR",
    "wof:name":"Shoredrive Inc",
    "wof:placetype":"venue"
},
  "geometry": {"coordinates":[-92.95954999999999,34.687466],"type":"Point"}
}