{
  "type": "Feature",
  "properties": {
    "iso:country":"US",
    "sg:address":"416 N Bloomington St",
    "sg:city":"Lowell",
    "sg:classifiers":[
        {
            "category":"Shopping",
            "subcategory":"Computers & Home Electronics",
            "type":"Retail Goods"
        }
    ],
    "sg:phone":"+1 479 659 8870",
    "sg:postcode":"72745",
    "sg:province":"AR",
    "wof:name":"Norwood-Lowell Tv",
    "wof:placetype":"venue"
},
  "geometry": {"coordinates":[-94.136803,36.260502],"type":"Point"}
}