{
  "type": "Feature",
  "properties": {
    "iso:country":"US",
    "sg:address":"456 N Anna Strong Cir",
    "sg:city":"Marianna",
    "sg:classifiers":[
        {
            "category":"Health Services",
            "subcategory":"Clinic",
            "type":"Services"
        }
    ],
    "sg:phone":"+1 870 298 2735",
    "sg:postcode":"72360",
    "sg:province":"AR",
    "wof:name":"Arkansas Minority Health",
    "wof:placetype":"venue"
},
  "geometry": {"coordinates":[-90.77338899999999,34.768684],"type":"Point"}
}