{
  "type": "Feature",
  "properties": {
    "iso:country":"US",
    "sg:address":"3020 Airport Rd",
    "sg:city":"Pearcy",
    "sg:classifiers":[
        {
            "category":"Retail",
            "subcategory":"Storage",
            "type":"Services"
        }
    ],
    "sg:phone":"+1 501 760 1400",
    "sg:postcode":"71964",
    "sg:province":"AR",
    "sg:tags":[
        "household",
        "commercial"
    ],
    "wof:name":"S & S Mini's",
    "wof:placetype":"venue"
},
  "geometry": {"coordinates":[-93.193518,34.445561],"type":"Point"}
}