{
  "type": "Feature",
  "properties": {
    "iso:country":"US",
    "sg:address":"415 Bent Tree Ct",
    "sg:city":"Russellville",
    "sg:classifiers":[
        {
            "category":"Building & Trades",
            "subcategory":"Construction",
            "type":"Services"
        }
    ],
    "sg:phone":"+1 479 890 5696",
    "sg:postcode":"72802",
    "sg:province":"AR",
    "sg:tags":[
        "residential"
    ],
    "wof:name":"Bent Tree Hmes In Russellville",
    "wof:placetype":"venue"
},
  "geometry": {"coordinates":[-93.158608,35.262301],"type":"Point"}
}