{
  "type": "Feature",
  "properties": {
    "iso:country":"US",
    "sg:address":"3949 Highway 135 N",
    "sg:city":"Paragould",
    "sg:classifiers":[
        {
            "category":"Autos & Motor Vehicles",
            "subcategory":"Automobile Sales",
            "type":"Retail Goods"
        }
    ],
    "sg:phone":"+1 870 236 6498",
    "sg:postcode":"72450",
    "sg:province":"AR",
    "sg:tags":[
        "dealers-used",
        "car",
        "used",
        "cars-wholesale"
    ],
    "wof:name":"Willcockson's Auto Sales",
    "wof:placetype":"venue"
},
  "geometry": {"coordinates":[-90.504504,36.101174],"type":"Point"}
}