{
  "type": "Feature",
  "properties": {
    "iso:country":"US",
    "sg:address":"8401 Gaddy Koonce Rd",
    "sg:city":"Pine Bluff",
    "sg:classifiers":[
        {
            "category":"Building & Trades",
            "subcategory":"Electrical",
            "type":"Services"
        }
    ],
    "sg:phone":"+1 870 879 5710",
    "sg:postcode":"71603",
    "sg:province":"AR",
    "sg:tags":[
        "electrical",
        "contractor"
    ],
    "wof:name":"Kimbrell Electric",
    "wof:placetype":"venue"
},
  "geometry": {"coordinates":[-92.11014,34.118647],"type":"Point"}
}