{
  "type": "Feature",
  "properties": {
    "addr:full":"5704 Ridgeview Dr Jonesboro AR 72404",
    "addr:housenumber":"5704",
    "addr:postcode":"72404",
    "addr:street":"Ridgeview Dr",
    "iso:country":"US",
    "sg:address":"5704 Ridgeview Dr",
    "sg:city":"Jonesboro",
    "sg:classifiers":[
        {
            "category":"Professional",
            "subcategory":"Business Services",
            "type":"Services"
        },
        {
            "category":"Health Services",
            "subcategory":"Doctor",
            "type":"Services"
        }
    ],
    "sg:phone":"+1 870 972 5400",
    "sg:postcode":"72404",
    "sg:province":"AR",
    "sg:tags":[
        "mobile",
        "physician",
        "surgeon",
        "x"
    ],
    "wof:name":"Mobile Radiology Services Inc",
    "wof:placetype":"venue"
},
  "geometry": {"coordinates":[-90.722854,35.772667],"type":"Point"}
}