{
  "type": "Feature",
  "properties": {
    "iso:country":"US",
    "sg:address":"81 Riverwood Ave",
    "sg:city":"West Fork",
    "sg:classifiers":[
        {
            "category":"Building & Trades",
            "subcategory":"Construction",
            "type":"Services"
        }
    ],
    "sg:phone":"+1 479 839 4026",
    "sg:postcode":"72774",
    "sg:province":"AR",
    "sg:tags":[
        "house"
    ],
    "wof:name":"Litke Enterprises",
    "wof:placetype":"venue"
},
  "geometry": {"coordinates":[-94.184955,35.935138],"type":"Point"}
}