{
  "type": "Feature",
  "properties": {
    "iso:country":"US",
    "sg:address":"605 Hwy 62 E",
    "sg:city":"Harrison",
    "sg:classifiers":[
        {
            "category":"Building & Trades",
            "subcategory":"Landscaping Services",
            "type":"Services"
        }
    ],
    "sg:phone":"+1 870 426 3511",
    "sg:postcode":"72601",
    "sg:province":"AR",
    "wof:name":"Randalph Enterprises",
    "wof:placetype":"venue"
},
  "geometry": {"coordinates":[-93.081521,36.219754],"type":"Point"}
}