{
  "type": "Feature",
  "properties": {
    "iso:country":"US",
    "sg:address":"408 S 1st St",
    "sg:city":"Glenwood",
    "sg:classifiers":[
        {
            "category":"Retail",
            "subcategory":"Laundry & Dry Cleaning",
            "type":"Services"
        }
    ],
    "sg:phone":"+1 870 356 4661",
    "sg:postcode":"71943",
    "sg:province":"AR",
    "sg:tags":[
        "laundries-self"
    ],
    "wof:name":"Wash World Inc",
    "wof:placetype":"venue"
},
  "geometry": {"coordinates":[-93.54924699999999,34.324648],"type":"Point"}
}