{
  "type": "Feature",
  "properties": {
    "iso:country":"US",
    "sg:address":"11301 Geyer Springs Rd",
    "sg:city":"Little Rock",
    "sg:classifiers":[
        {
            "category":"Education",
            "subcategory":"School",
            "type":"Public Place"
        }
    ],
    "sg:phone":"+1 501 565 3276",
    "sg:postcode":"72209",
    "sg:province":"AR",
    "sg:website":"www.southwestchristianacademy.com",
    "wof:name":"Southwest Christian Academy",
    "wof:placetype":"venue"
},
  "geometry": {"coordinates":[-92.345297,34.649722],"type":"Point"}
}