{
  "type": "Feature",
  "properties": {
    "iso:country":"US",
    "sg:address":"501 N Main St",
    "sg:city":"Nashville",
    "sg:classifiers":[
        {
            "category":"Real Estate",
            "subcategory":"Real Estate Agent",
            "type":"Services"
        }
    ],
    "sg:phone":"+1 870 845 1188",
    "sg:postcode":"71852",
    "sg:province":"AR",
    "sg:website":"www.stavelyandassociates.com",
    "wof:name":"Stavely & Assoc Real Estate",
    "wof:placetype":"venue"
},
  "geometry": {"coordinates":[-93.84686499999999,33.950974],"type":"Point"}
}