{
  "type": "Feature",
  "properties": {
    "iso:country":"US",
    "sg:address":"5902 E 49th St",
    "sg:city":"N Little Rock",
    "sg:classifiers":[
        {
            "category":"Organizations",
            "subcategory":"Religious Organization",
            "type":"Services"
        }
    ],
    "sg:phone":"+1 501 945 2349",
    "sg:postcode":"72117",
    "sg:province":"AR",
    "sg:tags":[
        "church"
    ],
    "wof:name":"First Baptist Chr",
    "wof:placetype":"venue"
},
  "geometry": {"coordinates":[-92.19644,34.799541],"type":"Point"}
}