{
  "type": "Feature",
  "properties": {
    "iso:country":"US",
    "sg:address":"8109 Interstate Dr",
    "sg:city":"Little Rock",
    "sg:classifiers":[
        {
            "category":"Wholesale",
            "subcategory":"Meat",
            "type":"Manufacturing & Wholesale Goods"
        }
    ],
    "sg:phone":"+1 501 565 5000",
    "sg:postcode":"72209",
    "sg:province":"AR",
    "sg:tags":[
        "broker"
    ],
    "wof:name":"Proctor & Assoc",
    "wof:placetype":"venue"
},
  "geometry": {"coordinates":[-92.31201,34.682662],"type":"Point"}
}