{
  "type": "Feature",
  "properties": {
    "iso:country":"US",
    "sg:address":"600 E Main St",
    "sg:city":"Siloam Springs",
    "sg:classifiers":[
        {
            "category":"Retail",
            "subcategory":"Auto Repair",
            "type":"Services"
        }
    ],
    "sg:phone":"+1 479 524 0039",
    "sg:postcode":"72761",
    "sg:province":"OK",
    "sg:tags":[
        "wrecker"
    ],
    "wof:name":"Shepherd's Automotive & Tow",
    "wof:placetype":"venue"
},
  "geometry": {"coordinates":[-94.537241,36.184118],"type":"Point"}
}