{
  "type": "Feature",
  "properties": {
    "iso:country":"US",
    "sg:address":"101 Blevins St",
    "sg:city":"Alpena",
    "sg:classifiers":[
        {
            "category":"Building & Trades",
            "subcategory":"Construction",
            "type":"Services"
        }
    ],
    "sg:phone":"+1 870 437 2526",
    "sg:postcode":"72611",
    "sg:province":"AR",
    "sg:tags":[
        "utility",
        "general",
        "municipal",
        "contractor"
    ],
    "wof:name":"R Davidson Construction Co",
    "wof:placetype":"venue"
},
  "geometry": {"coordinates":[-93.29950100000001,36.292491],"type":"Point"}
}