{
  "type": "Feature",
  "properties": {
    "iso:country":"US",
    "sg:address":"3907 S Camden Rd",
    "sg:city":"Pine Bluff",
    "sg:classifiers":[
        {
            "category":"Restaurant",
            "type":"Food & Drink"
        }
    ],
    "sg:phone":"+1 870 879 3070",
    "sg:postcode":"71603",
    "sg:province":"AR",
    "wof:name":"Bogard's Restaurant",
    "wof:placetype":"venue"
},
  "geometry": {"coordinates":[-92.0557,34.196205],"type":"Point"}
}