{
  "type": "Feature",
  "properties": {
    "iso:country":"US",
    "sg:address":"14 W 3rd St",
    "sg:city":"Grove",
    "sg:classifiers":[
        {
            "category":"Manufacturing",
            "subcategory":"Printing",
            "type":"Manufacturing & Wholesale Goods"
        }
    ],
    "sg:phone":"+1 918 786 9051",
    "sg:postcode":"74344",
    "sg:province":"OK",
    "sg:tags":[
        "newspaper"
    ],
    "wof:name":"Grand Lake Shoppers Guid",
    "wof:placetype":"venue"
},
  "geometry": {"coordinates":[-94.770065,36.593365],"type":"Point"}
}