{
  "type": "Feature",
  "properties": {
    "addr:full":"1500 S Main St Pine Bluff AR 71601",
    "addr:housenumber":"1500",
    "addr:postcode":"71601",
    "addr:street":"S Main St",
    "iso:country":"US",
    "sg:address":"1500 S Main St",
    "sg:city":"Pine Bluff",
    "sg:classifiers":[
        {
            "category":"Autos & Motor Vehicles",
            "subcategory":"Auto Supplies",
            "type":"Retail Goods"
        }
    ],
    "sg:phone":"+1 870 534 3976",
    "sg:postcode":"71601",
    "sg:province":"AR",
    "wof:name":"OReilly Auto Parts",
    "wof:placetype":"venue"
},
  "geometry": {"coordinates":[-92.00326,34.213429],"type":"Point"}
}