{
  "type": "Feature",
  "properties": {
    "iso:country":"US",
    "sg:address":"17 E Main St",
    "sg:city":"Ash Flat",
    "sg:classifiers":[
        {
            "category":"Real Estate",
            "subcategory":"Real Estate Services",
            "type":"Services"
        }
    ],
    "sg:phone":"+1 870 994 7753",
    "sg:postcode":"72513",
    "sg:province":"AR",
    "sg:tags":[
        "company",
        "title"
    ],
    "wof:name":"Ozark Title Co",
    "wof:placetype":"venue"
},
  "geometry": {"coordinates":[-91.608629,36.224039],"type":"Point"}
}