{
  "type": "Feature",
  "properties": {
    "addr:full":"2981 E State Hwy 150 Blytheville AR 72315",
    "addr:housenumber":"2981",
    "addr:postcode":"72315",
    "addr:street":"E State Hwy 150",
    "iso:country":"US",
    "sg:address":"2981 E State Hwy 150",
    "sg:city":"Blytheville",
    "sg:classifiers":[
        {
            "category":"Wholesale",
            "subcategory":"Farm Supplies",
            "type":"Manufacturing & Wholesale Goods"
        }
    ],
    "sg:phone":"+1 870 763 4627",
    "sg:postcode":"72315",
    "sg:province":"AR",
    "wof:name":"Uap Midsouth Yarbro",
    "wof:placetype":"venue"
},
  "geometry": {"coordinates":[-89.90586500000001,35.98043],"type":"Point"}
}