{
  "type": "Feature",
  "properties": {
    "iso:country":"US",
    "sg:address":"2981 E State Hwy 150",
    "sg:city":"Blytheville",
    "sg:classifiers":[
        {
            "category":"Wholesale",
            "subcategory":"Farm Supplies",
            "type":"Manufacturing & Wholesale Goods"
        }
    ],
    "sg:phone":"+1 870 763 4627",
    "sg:postcode":"72315",
    "sg:province":"AR",
    "wof:name":"Uap Midsouth Yarbro",
    "wof:placetype":"venue"
},
  "geometry": {"coordinates":[-89.905865,35.98043],"type":"Point"}
}