{
  "type": "Feature",
  "properties": {
    "iso:country":"US",
    "sg:address":"148 E Van Buren",
    "sg:city":"Eureka Springs",
    "sg:classifiers":[
        {
            "category":"Restaurant",
            "type":"Food & Drink"
        }
    ],
    "sg:phone":"+1 479 253 6106",
    "sg:postcode":"72632",
    "sg:province":"AR",
    "sg:website":"www.mcdonalds.com",
    "wof:name":"Mc Donald's",
    "wof:placetype":"venue"
},
  "geometry": {"coordinates":[-93.728613,36.393063],"type":"Point"}
}