{
  "type": "Feature",
  "properties": {
    "addr:full":"15 Summerdale Ln Little Rock AR 72223",
    "addr:housenumber":"15",
    "addr:postcode":"72223",
    "addr:street":"Summerdale Ln",
    "iso:country":"US",
    "sg:address":"15 Summerdale Ln",
    "sg:city":"Little Rock",
    "sg:classifiers":[
        {
            "category":"Building & Trades",
            "subcategory":"Construction",
            "type":"Services"
        }
    ],
    "sg:phone":"+1 501 221 9882",
    "sg:postcode":"72223",
    "sg:province":"AR",
    "sg:tags":[
        "house"
    ],
    "wof:name":"Shields-Harrison Cstm Hm Bldrs",
    "wof:placetype":"venue"
},
  "geometry": {"coordinates":[-92.41325500000001,34.792743],"type":"Point"}
}