{
  "type": "Feature",
  "properties": {
    "iso:country":"US",
    "sg:address":"141 Arch St",
    "sg:city":"Eudora",
    "sg:classifiers":[
        {
            "category":"Bars & Pubs",
            "type":"Food & Drink"
        },
        {
            "category":"Organizations",
            "subcategory":"Community Association",
            "type":"Services"
        }
    ],
    "sg:phone":"+1 870 355 4661",
    "sg:postcode":"71640",
    "sg:province":"AR",
    "sg:tags":[
        "club",
        "night"
    ],
    "wof:name":"Silver D Club The",
    "wof:placetype":"venue"
},
  "geometry": {"coordinates":[-91.264037,33.122661],"type":"Point"}
}