{
  "type": "Feature",
  "properties": {
    "iso:country":"US",
    "sg:address":"507 Jason Cir",
    "sg:city":"Bono",
    "sg:classifiers":[
        {
            "category":"Professional",
            "subcategory":"Art Services",
            "type":"Services"
        }
    ],
    "sg:phone":"+1 870 910 5770",
    "sg:postcode":"72416",
    "sg:province":"AR",
    "sg:tags":[
        "designer",
        "display",
        "producer"
    ],
    "wof:name":"Carr S Creative Designs",
    "wof:placetype":"venue"
},
  "geometry": {"coordinates":[-90.789085,35.908339],"type":"Point"}
}