{
  "type": "Feature",
  "properties": {
    "iso:country":"US",
    "sg:address":"819 Old Wire Rd",
    "sg:city":"Springdale",
    "sg:classifiers":[
        {
            "category":"Restaurant",
            "type":"Food & Drink"
        }
    ],
    "sg:phone":"+1 479 750 0070",
    "sg:postcode":"72764",
    "sg:province":"AR",
    "sg:tags":[
        "delicatessen"
    ],
    "wof:name":"Arkansas Deli Provisions",
    "wof:placetype":"venue"
},
  "geometry": {"coordinates":[-94.120378,36.200774],"type":"Point"}
}