{
  "type": "Feature",
  "properties": {
    "addr:full":"10102 Dobby Dr Little Rock AR 72206",
    "addr:housenumber":"10102",
    "addr:postcode":"72206",
    "addr:street":"Dobby Dr",
    "iso:country":"US",
    "sg:address":"10102 Dobby Dr",
    "sg:city":"Little Rock",
    "sg:classifiers":[
        {
            "category":"Professional",
            "subcategory":"Business Services",
            "type":"Services"
        }
    ],
    "sg:phone":"+1 501 888 4276",
    "sg:postcode":"72206",
    "sg:province":"AR",
    "wof:name":"Coles Systems",
    "wof:placetype":"venue"
},
  "geometry": {"coordinates":[-92.305998,34.659732],"type":"Point"}
}