{
  "type": "Feature",
  "properties": {
    "addr:full":"907 Central Blvd Bull Shoals AR 72619",
    "addr:housenumber":"907",
    "addr:postcode":"72619",
    "addr:street":"Central Blvd;Shoals",
    "iso:country":"US",
    "sg:address":"907 Central Blvd",
    "sg:city":"Bull Shoals",
    "sg:classifiers":[
        {
            "category":"Banks & Credit Unions",
            "subcategory":"Bank",
            "type":"Services"
        }
    ],
    "sg:phone":"+1 870 445 4505",
    "sg:postcode":"72619",
    "sg:province":"AR",
    "wof:name":"First Security Bank",
    "wof:placetype":"venue"
},
  "geometry": {"coordinates":[-92.578074,36.383715],"type":"Point"}
}