{
  "type": "Feature",
  "properties": {
    "addr:full":"1536 County Road 418 Rector AR 72461",
    "addr:housenumber":"1536",
    "addr:postcode":"72461",
    "addr:street":"County Road 418 Rector",
    "iso:country":"US",
    "sg:address":"1536 County Road 418",
    "sg:city":"Rector",
    "sg:classifiers":[
        {
            "category":"Health Services",
            "subcategory":"Optometrist",
            "type":"Services"
        }
    ],
    "sg:phone":"+1 870 566 2051",
    "sg:postcode":"72461",
    "sg:province":"AR",
    "wof:name":"Marilyn Carter",
    "wof:placetype":"venue"
},
  "geometry": {"coordinates":[-90.325665,36.29566],"type":"Point"}
}