{
  "type": "Feature",
  "properties": {
    "addr:full":"401 N Fredrick Magnolia AR 71753",
    "addr:housenumber":"401",
    "addr:postcode":"71753",
    "addr:street":"N Fredrick Magnolia",
    "iso:country":"US",
    "sg:address":"401 N Fredrick",
    "sg:city":"Magnolia",
    "sg:classifiers":[
        {
            "category":"Shopping",
            "subcategory":"Department Store",
            "type":"Retail Goods"
        }
    ],
    "sg:phone":"+1 870 234 1997",
    "sg:postcode":"71753",
    "sg:province":"AR",
    "wof:name":"Stage",
    "wof:placetype":"venue"
},
  "geometry": {"coordinates":[-93.22434199999999,33.270214],"type":"Point"}
}