{
  "type": "Feature",
  "properties": {
    "iso:country":"US",
    "sg:address":"344 Mathis Rd",
    "sg:city":"Lonoke",
    "sg:classifiers":[
        {
            "category":"Farming",
            "subcategory":"Farm",
            "type":"Manufacturing & Wholesale Goods"
        }
    ],
    "sg:phone":"+1 501 676 3604",
    "sg:postcode":"72086",
    "sg:province":"AR",
    "sg:tags":[
        "crop",
        "general"
    ],
    "wof:name":"Hauk Farms",
    "wof:placetype":"venue"
},
  "geometry": {"coordinates":[-91.970916,34.842406],"type":"Point"}
}