{
  "type": "Feature",
  "properties": {
    "iso:country":"US",
    "sg:address":"1 Airport Blvd",
    "sg:city":"Bentonville",
    "sg:classifiers":[
        {
            "category":"Coffee & Tea",
            "type":"Food & Drink"
        }
    ],
    "sg:menulink":"http://www.allmenus.com/ar/siloam-springs/121494-the-coffee-beanery/menu/",
    "sg:phone":"+1 479 205 0006",
    "sg:postcode":"72712",
    "sg:province":"AR",
    "sg:tags":[
        "american",
        "diner"
    ],
    "wof:name":"The Coffee Beanery",
    "wof:placetype":"venue"
},
  "geometry": {"coordinates":[-94.29428799999999,36.27143],"type":"Point"}
}