{
  "type": "Feature",
  "properties": {
    "addr:full":"103 Joes Ln Judsonia AR 72081",
    "addr:housenumber":"103",
    "addr:postcode":"72081",
    "addr:street":"Joes Ln",
    "iso:country":"US",
    "sg:address":"103 Joes Ln",
    "sg:city":"Judsonia",
    "sg:classifiers":[
        {
            "category":"Building & Trades",
            "subcategory":"Construction",
            "type":"Services"
        }
    ],
    "sg:phone":"+1 501 593 5287",
    "sg:postcode":"72081",
    "sg:province":"AR",
    "sg:tags":[
        "wallcoverings-installation",
        "wallpaper",
        "painting",
        "contractor"
    ],
    "wof:name":"Anthony Book Painting",
    "wof:placetype":"venue"
},
  "geometry": {"coordinates":[-91.602372,35.296819],"type":"Point"}
}