{
  "type": "Feature",
  "properties": {
    "iso:country":"US",
    "sg:address":"101 E Clifton St",
    "sg:city":"Morrilton",
    "sg:classifiers":[
        {
            "category":"Organizations",
            "subcategory":"Religious Organization",
            "type":"Services"
        }
    ],
    "sg:phone":"+1 501 354 2117",
    "sg:postcode":"72110",
    "sg:province":"AR",
    "wof:name":"Calvary Baptist Church",
    "wof:placetype":"venue"
},
  "geometry": {"coordinates":[-92.74413199999999,35.157135],"type":"Point"}
}