{
  "type": "Feature",
  "properties": {
    "addr:full":"807 Court St Conway AR 72032",
    "addr:housenumber":"807",
    "addr:postcode":"72032",
    "addr:street":"Court St",
    "iso:country":"US",
    "sg:address":"807 Court St",
    "sg:city":"Conway",
    "sg:classifiers":[
        {
            "category":"Place Of Worship",
            "type":"Public Place"
        },
        {
            "category":"Shopping",
            "subcategory":"Thrift Store",
            "type":"Retail Goods"
        },
        {
            "category":"Banks & Credit Unions",
            "subcategory":"Bank",
            "type":"Services"
        },
        {
            "category":"Shopping",
            "subcategory":"Used Merchandise",
            "type":"Retail Goods"
        }
    ],
    "sg:phone":"+1 501 329 3158",
    "sg:postcode":"72032",
    "sg:province":"AR",
    "sg:tags":[
        "shop",
        "resale",
        "second",
        "church",
        "hand"
    ],
    "sg:website":"http://www.salvationarmysouth.org",
    "wof:name":"Salvation Army Thrift Store & Pick Up",
    "wof:placetype":"venue"
},
  "geometry": {"coordinates":[-92.438045,35.090223],"type":"Point"}
}