{
  "type": "Feature",
  "properties": {
    "iso:country":"US",
    "sg:address":"107 E Parkway Dr",
    "sg:city":"Russellville",
    "sg:classifiers":[
        {
            "category":"Insurance",
            "subcategory":"Insurance Agent",
            "type":"Services"
        }
    ],
    "sg:phone":"+1 479 967 2767",
    "sg:postcode":"72801",
    "sg:province":"AR",
    "wof:name":"Advantage One",
    "wof:placetype":"venue"
},
  "geometry": {"coordinates":[-93.133517,35.281331],"type":"Point"}
}