{
  "type": "Feature",
  "properties": {
    "iso:country":"US",
    "sg:address":"1012 N 4th",
    "sg:city":"West Helena",
    "sg:classifiers":[
        {
            "category":"Recreation",
            "type":"Entertainment"
        }
    ],
    "sg:phone":"+1 870 572 2202",
    "sg:postcode":"72390",
    "sg:province":"AR",
    "sg:tags":[
        "stable"
    ],
    "wof:name":"Horses To Harleys",
    "wof:placetype":"venue"
},
  "geometry": {"coordinates":[-90.643677,34.566138],"type":"Point"}
}