{
  "type": "Feature",
  "properties": {
    "addr:full":"232 S Bridge St Jonesboro AR 72401",
    "addr:housenumber":"232",
    "addr:postcode":"72401",
    "addr:street":"S Bridge St",
    "iso:country":"US",
    "sg:address":"232 S Bridge St",
    "sg:city":"Jonesboro",
    "sg:classifiers":[
        {
            "category":"Social Services",
            "subcategory":"Child Care",
            "type":"Services"
        }
    ],
    "sg:phone":"+1 870 268 0112",
    "sg:postcode":"72401",
    "sg:province":"AR",
    "sg:tags":[
        "day"
    ],
    "wof:name":"Divine Wisdom Childcare",
    "wof:placetype":"venue"
},
  "geometry": {"coordinates":[-90.699566,35.84158],"type":"Point"}
}