{
  "type": "Feature",
  "properties": {
    "iso:country":"US",
    "sg:address":"126 Hwy 89 S",
    "sg:city":"Mayflower",
    "sg:classifiers":[
        {
            "category":"Building & Trades",
            "subcategory":"Construction",
            "type":"Services"
        }
    ],
    "sg:phone":"+1 501 470 3463",
    "sg:postcode":"72106",
    "sg:province":"AR",
    "sg:tags":[
        "waterproofing",
        "contractor"
    ],
    "wof:name":"Southwest Waterproofing",
    "wof:placetype":"venue"
},
  "geometry": {"coordinates":[-92.398953,34.966732],"type":"Point"}
}