{
  "type": "Feature",
  "properties": {
    "addr:full":"1450 Rainbow Rd Heber Springs AR 72543",
    "addr:housenumber":"1450",
    "addr:postcode":"72543",
    "addr:street":"Rainbow Rd",
    "iso:country":"US",
    "sg:address":"1450 Rainbow Rd",
    "sg:city":"Heber Springs",
    "sg:classifiers":[
        {
            "category":"Manufacturing",
            "subcategory":"Tools & Machinery",
            "type":"Manufacturing & Wholesale Goods"
        }
    ],
    "sg:phone":"+1 501 362 6920",
    "sg:postcode":"72543",
    "sg:province":"AR",
    "sg:tags":[
        "instrument",
        "mfg"
    ],
    "wof:name":"Boston Scientific Corporation",
    "wof:placetype":"venue"
},
  "geometry": {"coordinates":[-91.956964,35.519964],"type":"Point"}
}