{
  "type": "Feature",
  "properties": {
    "iso:country":"US",
    "sg:address":"809 Parkway Ave",
    "sg:city":"Conway",
    "sg:classifiers":[
        {
            "category":"Wholesale",
            "subcategory":"Durable Goods & Equipment",
            "type":"Manufacturing & Wholesale Goods"
        }
    ],
    "sg:phone":"+1 501 327 8082",
    "sg:postcode":"72034",
    "sg:province":"AR",
    "sg:tags":[
        "representative",
        "manufacturer"
    ],
    "wof:name":"Delta Technologies",
    "wof:placetype":"venue"
},
  "geometry": {"coordinates":[-92.441893,35.09016],"type":"Point"}
}