{
  "type": "Feature",
  "properties": {
    "iso:country":"US",
    "sg:address":"2513 Atlanta St",
    "sg:city":"Blytheville",
    "sg:classifiers":[
        {
            "category":"Organizations",
            "subcategory":"Non-profit Organization",
            "type":"Services"
        }
    ],
    "sg:phone":"+1 870 762 2386",
    "sg:postcode":"72315",
    "sg:province":"AR",
    "sg:tags":[
        "human"
    ],
    "wof:name":"Arkansas Human Development Inc",
    "wof:placetype":"venue"
},
  "geometry": {"coordinates":[-89.954013,35.962693],"type":"Point"}
}