{
  "type": "Feature",
  "properties": {
    "addr:full":"533 N 5th St Blytheville AR 72315",
    "addr:housenumber":"533",
    "addr:postcode":"72315",
    "addr:street":"N 5Th St",
    "iso:country":"US",
    "sg:address":"533 N 5th St",
    "sg:city":"Blytheville",
    "sg:classifiers":[
        {
            "category":"Health Services",
            "subcategory":"Health Practitioner",
            "type":"Services"
        }
    ],
    "sg:phone":"+1 870 762 5657",
    "sg:postcode":"72315",
    "sg:province":"AR",
    "sg:tags":[
        "hypnotist"
    ],
    "wof:name":"Kathey's Hypnosis Ctr",
    "wof:placetype":"venue"
},
  "geometry": {"coordinates":[-89.90817,35.932053],"type":"Point"}
}