{
  "type": "Feature",
  "properties": {
    "iso:country":"US",
    "sg:address":"437 Stony Ridge Rd",
    "sg:city":"Heber Springs",
    "sg:classifiers":[
        {
            "category":"Insurance",
            "subcategory":"Insurance Agent",
            "type":"Services"
        }
    ],
    "sg:phone":"+1 501 362 2366",
    "sg:postcode":"72543",
    "sg:province":"AR",
    "wof:name":"Shawn Teague Inc",
    "wof:placetype":"venue"
},
  "geometry": {"coordinates":[-92.11172000000001,35.497488],"type":"Point"}
}