{
  "type": "Feature",
  "properties": {
    "iso:country":"US",
    "sg:address":"317 N Lakeside Dr",
    "sg:city":"De Queen",
    "sg:classifiers":[
        {
            "category":"Autos & Motor Vehicles",
            "subcategory":"Automobile Sales",
            "type":"Retail Goods"
        }
    ],
    "sg:phone":"+1 870 642 2144",
    "sg:postcode":"71832",
    "sg:province":"AR",
    "sg:tags":[
        "building",
        "operator",
        "used",
        "nonresidential"
    ],
    "wof:name":"Gentrys Preowned Trading Post",
    "wof:placetype":"venue"
},
  "geometry": {"coordinates":[-94.33011999999999,34.039948],"type":"Point"}
}