{
  "type": "Feature",
  "properties": {
    "iso:country":"US",
    "sg:address":"8399 N Hwy 1",
    "sg:city":"Colt",
    "sg:classifiers":[
        {
            "category":"Autos & Motor Vehicles",
            "subcategory":"Automobile Sales",
            "type":"Retail Goods"
        }
    ],
    "sg:phone":"+1 870 633 6950",
    "sg:postcode":"72326",
    "sg:province":"AR",
    "sg:tags":[
        "car",
        "dealer"
    ],
    "wof:name":"Cleggs Auto Sales",
    "wof:placetype":"venue"
},
  "geometry": {"coordinates":[-90.811619,35.123333],"type":"Point"}
}