{
  "type": "Feature",
  "properties": {
    "addr:full":"253 Hwy 70 Glenwood AR 71943",
    "addr:housenumber":"253",
    "addr:postcode":"71943",
    "addr:street":"Hwy 70",
    "iso:country":"US",
    "sg:address":"253 Hwy 70",
    "sg:city":"Glenwood",
    "sg:classifiers":[
        {
            "category":"Health Services",
            "subcategory":"Doctor",
            "type":"Services"
        }
    ],
    "sg:phone":"+1 870 356 2488",
    "sg:postcode":"71943",
    "sg:province":"AR",
    "sg:tags":[
        "physician",
        "surgeon"
    ],
    "wof:name":"Gary Gehrki MD",
    "wof:placetype":"venue"
},
  "geometry": {"coordinates":[-93.406387,34.372824],"type":"Point"}
}