{
  "type": "Feature",
  "properties": {
    "iso:country":"US",
    "sg:address":"1238 Country Club Rd",
    "sg:city":"Camden",
    "sg:classifiers":[
        {
            "category":"Personal",
            "type":"Services"
        }
    ],
    "sg:phone":"+1 870 836 6500",
    "sg:postcode":"71701",
    "sg:province":"AR",
    "sg:tags":[
        "therapist",
        "massage"
    ],
    "wof:name":"Girlfriends",
    "wof:placetype":"venue"
},
  "geometry": {"coordinates":[-92.85216699999999,33.577664],"type":"Point"}
}