{
  "type": "Feature",
  "properties": {
    "addr:full":"260 W Court St Piggott AR 72454",
    "addr:housenumber":"260",
    "addr:postcode":"72454",
    "addr:street":"W Court St",
    "iso:country":"US",
    "sg:address":"260 W Court St",
    "sg:city":"Piggott",
    "sg:classifiers":[
        {
            "category":"Restaurant",
            "type":"Food & Drink"
        }
    ],
    "sg:phone":"+1 870 598 5753",
    "sg:postcode":"72454",
    "sg:province":"AR",
    "sg:tags":[
        "eating"
    ],
    "wof:name":"Outdoors Indoors",
    "wof:placetype":"venue"
},
  "geometry": {"coordinates":[-90.192306,36.381679],"type":"Point"}
}