{
  "type": "Feature",
  "properties": {
    "iso:country":"US",
    "sg:address":"100 W Main St",
    "sg:city":"Russellville",
    "sg:classifiers":[
        {
            "category":"Government",
            "subcategory":"Court House",
            "type":"Public Place"
        },
        {
            "category":"Government",
            "subcategory":"Office",
            "type":"Public Place"
        }
    ],
    "sg:phone":"+1 479 968 7499",
    "sg:postcode":"72801",
    "sg:province":"AR",
    "wof:name":"Pope County Circuit Clerk Ofc",
    "wof:placetype":"venue"
},
  "geometry": {"coordinates":[-93.13436,35.278158],"type":"Point"}
}