{
  "type": "Feature",
  "properties": {
    "iso:country":"US",
    "sg:address":"1902 Franklin Ave",
    "sg:city":"Mountain Home",
    "sg:classifiers":[
        {
            "category":"Farming",
            "subcategory":"Farm",
            "type":"Manufacturing & Wholesale Goods"
        }
    ],
    "sg:phone":"+1 870 425 9655",
    "sg:postcode":"72653",
    "sg:province":"AR",
    "sg:tags":[
        "crop",
        "general"
    ],
    "wof:name":"Rex M Tullis",
    "wof:placetype":"venue"
},
  "geometry": {"coordinates":[-92.39680799999999,36.360349],"type":"Point"}
}