{
  "type": "Feature",
  "properties": {
    "iso:country":"US",
    "sg:address":"337 W Liberty St",
    "sg:city":"El Dorado",
    "sg:classifiers":[
        {
            "category":"Personal",
            "subcategory":"Barber",
            "type":"Services"
        }
    ],
    "sg:phone":"+1 870 881 0000",
    "sg:postcode":"71730",
    "sg:province":"AR",
    "sg:tags":[
        "shop"
    ],
    "wof:name":"Resters Part III Barbr College",
    "wof:placetype":"venue"
},
  "geometry": {"coordinates":[-92.666777,33.216945],"type":"Point"}
}