{
  "type": "Feature",
  "properties": {
    "iso:country":"US",
    "sg:address":"2118 Gate Nine Rd",
    "sg:city":"Greenwood",
    "sg:classifiers":[
        {
            "category":"Building & Trades",
            "subcategory":"Construction",
            "type":"Services"
        }
    ],
    "sg:phone":"+1 479 996 4188",
    "sg:postcode":"72936",
    "sg:province":"AR",
    "sg:tags":[
        "paving",
        "road",
        "contractor"
    ],
    "wof:name":"Apac",
    "wof:placetype":"venue"
},
  "geometry": {"coordinates":[-94.32322,35.241906],"type":"Point"}
}