{
  "type": "Feature",
  "properties": {
    "iso:country":"US",
    "sg:address":"2765 Malvern Ave",
    "sg:city":"Hot Springs",
    "sg:classifiers":[
        {
            "category":"Organizations",
            "subcategory":"Religious Organization",
            "type":"Services"
        }
    ],
    "sg:phone":"+1 501 262 5640",
    "sg:postcode":"71901",
    "sg:province":"AR",
    "sg:tags":[
        "church"
    ],
    "wof:name":"Church Of Jesus Christ Of Lds",
    "wof:placetype":"venue"
},
  "geometry": {"coordinates":[-93.00725799999999,34.470388],"type":"Point"}
}