{
  "type": "Feature",
  "properties": {
    "iso:country":"US",
    "sg:address":"3816 N Gulley Rd",
    "sg:city":"Fayetteville",
    "sg:classifiers":[
        {
            "category":"Professional",
            "subcategory":"Management & Consulting",
            "type":"Services"
        }
    ],
    "sg:phone":"+1 479 443 4679",
    "sg:postcode":"72703",
    "sg:province":"AR",
    "sg:tags":[
        "business"
    ],
    "wof:name":"Cdb Consulting",
    "wof:placetype":"venue"
},
  "geometry": {"coordinates":[-94.092529,36.12258],"type":"Point"}
}