{
  "type": "Feature",
  "properties": {
    "iso:country":"US",
    "sg:address":"5805 Dollarway Rd",
    "sg:city":"White Hall",
    "sg:classifiers":[
        {
            "category":"Food & Beverages",
            "subcategory":"Groceries & Convenience Stores",
            "type":"Retail Goods"
        }
    ],
    "sg:phone":"+1 870 247 5916",
    "sg:postcode":"71602",
    "sg:province":"AR",
    "wof:name":"Brookshire Food 104",
    "wof:placetype":"venue"
},
  "geometry": {"coordinates":[-92.061388,34.244496],"type":"Point"}
}