{
  "type": "Feature",
  "properties": {
    "iso:country":"US",
    "sg:address":"3210 S Walton Blvd",
    "sg:city":"Bentonville",
    "sg:classifiers":[
        {
            "category":"Banks & Credit Unions",
            "subcategory":"Bank",
            "type":"Services"
        }
    ],
    "sg:phone":"+1 479 271 0397",
    "sg:postcode":"72712",
    "sg:province":"AR",
    "sg:website":"www.simmonsfirst.com",
    "wof:name":"Simmons First",
    "wof:placetype":"venue"
},
  "geometry": {"coordinates":[-94.21113099999999,36.340199],"type":"Point"}
}