{
  "type": "Feature",
  "properties": {
    "iso:country":"US",
    "sg:address":"3523 Highway 90",
    "sg:city":"Delaplaine",
    "sg:classifiers":[
        {
            "category":"Professional",
            "subcategory":"Business Services",
            "type":"Services"
        },
        {
            "category":"Government",
            "subcategory":"Post Office",
            "type":"Public Place"
        }
    ],
    "sg:phone":"+1 800 275 8777",
    "sg:postcode":"72425",
    "sg:province":"AR",
    "sg:tags":[
        "mail",
        "shipping"
    ],
    "sg:website":"http://www.usps.com",
    "wof:name":"USPS - United States Post Office - Delaplaine Main Office",
    "wof:placetype":"venue"
},
  "geometry": {"coordinates":[-90.792543,36.185538],"type":"Point"}
}