{
  "type": "Feature",
  "properties": {
    "iso:country":"US",
    "sg:address":"9623 Highway 107",
    "sg:city":"Sherwood",
    "sg:classifiers":[
        {
            "category":"Insurance",
            "subcategory":"Hazard Insurance",
            "type":"Services"
        },
        {
            "category":"Insurance",
            "subcategory":"Insurance Agent",
            "type":"Services"
        },
        {
            "category":"Insurance",
            "subcategory":"Life Insurance",
            "type":"Services"
        },
        {
            "category":"Insurance",
            "subcategory":"Title Insurance",
            "type":"Services"
        }
    ],
    "sg:phone":"+1 501 835 3436",
    "sg:postcode":"72120",
    "sg:province":"AR",
    "sg:tags":[
        "auto",
        "homeowner"
    ],
    "sg:website":"http://www.nationwide.com/agent/Sherwood-ARKANSAS-insurance-agent/mike-eberle/office.html",
    "wof:name":"Michael W. Eberle - Nationwide Insurance",
    "wof:placetype":"venue"
},
  "geometry": {"coordinates":[-92.231551,34.84279],"type":"Point"}
}