{
  "type": "Feature",
  "properties": {
    "iso:country":"US",
    "sg:address":"24 Gore Ln",
    "sg:city":"Bella Vista",
    "sg:classifiers":[
        {
            "category":"Shopping",
            "type":"Retail Goods"
        }
    ],
    "sg:phone":"+1 479 855 2807",
    "sg:postcode":"72714",
    "sg:province":"AR",
    "sg:tags":[
        "merchandise"
    ],
    "wof:name":"Amko",
    "wof:placetype":"venue"
},
  "geometry": {"coordinates":[-94.268626,36.478291],"type":"Point"}
}