{
  "type": "Feature",
  "properties": {
    "iso:country":"US",
    "sg:address":"12 Mckissic Creek Rd",
    "sg:city":"Bentonville",
    "sg:classifiers":[
        {
            "category":"Transit Center",
            "subcategory":"Freight",
            "type":"Transportation"
        },
        {
            "category":"Freight",
            "type":"Transportation"
        }
    ],
    "sg:phone":"+1 479 254 0212",
    "sg:postcode":"72712",
    "sg:province":"AR",
    "sg:tags":[
        "local",
        "trucking-motor",
        "trucking"
    ],
    "wof:name":"Shaffer Trucking",
    "wof:placetype":"venue"
},
  "geometry": {"coordinates":[-94.220156,36.413008],"type":"Point"}
}