{
  "type": "Feature",
  "properties": {
    "addr:full":"511 Union St Dardanelle AR 72834",
    "addr:housenumber":"511",
    "addr:postcode":"72834",
    "addr:street":"Union St",
    "iso:country":"US",
    "sg:address":"511 Union St",
    "sg:city":"Dardanelle",
    "sg:classifiers":[
        {
            "category":"Professional",
            "type":"Services"
        },
        {
            "category":"Restaurant",
            "type":"Food & Drink"
        },
        {
            "category":"Fast Food",
            "type":"Food & Drink"
        }
    ],
    "sg:phone":"+1 479 229 3517",
    "sg:postcode":"72834",
    "sg:province":"AR",
    "sg:tags":[
        "delivery",
        "style",
        "take",
        "family",
        "pizza"
    ],
    "sg:website":"http://www.pizzahut.com",
    "wof:name":"Pizza Hut",
    "wof:placetype":"venue"
},
  "geometry": {"coordinates":[-93.161058,35.221774],"type":"Point"}
}