{
  "type": "Feature",
  "properties": {
    "iso:country":"US",
    "sg:address":"201 Greene Rd 712",
    "sg:city":"Paragould",
    "sg:classifiers":[
        {
            "category":"Wholesale",
            "subcategory":"Auto Parts",
            "type":"Manufacturing & Wholesale Goods"
        }
    ],
    "sg:phone":"+1 870 335 9854",
    "sg:postcode":"72450",
    "sg:province":"AR",
    "sg:tags":[
        "used",
        "supply"
    ],
    "wof:name":"Arnolds Hubcap Junction",
    "wof:placetype":"venue"
},
  "geometry": {"coordinates":[-90.635523,36.07084],"type":"Point"}
}