{
  "type": "Feature",
  "properties": {
    "addr:full":"4509 W Poplar St Rogers AR 72758",
    "addr:housenumber":"4509",
    "addr:postcode":"72758",
    "addr:street":"W Poplar St",
    "iso:country":"US",
    "sg:address":"4509 W Poplar St",
    "sg:city":"Rogers",
    "sg:classifiers":[
        {
            "category":"Restaurant",
            "type":"Food & Drink"
        }
    ],
    "sg:menulink":"http://www.allmenus.com/ar/cave-springs/97875-outback-steakhouse/menu/",
    "sg:phone":"+1 479 936 7660",
    "sg:postcode":"72758",
    "sg:province":"AR",
    "sg:tags":[
        "american",
        "steakhouse"
    ],
    "wof:name":"Outback Steakhouse",
    "wof:placetype":"venue"
},
  "geometry": {"coordinates":[-94.181651,36.332292],"type":"Point"}
}