{
  "type": "Feature",
  "properties": {
    "iso:country":"US",
    "sg:address":"9625 Old Olvey Rd",
    "sg:city":"Harrison",
    "sg:classifiers":[
        {
            "category":"Professional",
            "subcategory":"Business Services",
            "type":"Services"
        }
    ],
    "sg:phone":"+1 870 743 2593",
    "sg:postcode":"72601",
    "sg:province":"AR",
    "wof:name":"Bobby C Kimes",
    "wof:placetype":"venue"
},
  "geometry": {"coordinates":[-92.967516,36.192005],"type":"Point"}
}