{
  "type": "Feature",
  "properties": {
    "addr:full":"1916 Links Cir Jonesboro AR 72404",
    "addr:housenumber":"1916",
    "addr:postcode":"72404",
    "addr:street":"Links Cir",
    "iso:country":"US",
    "sg:address":"1916 Links Cir",
    "sg:city":"Jonesboro",
    "sg:classifiers":[
        {
            "category":"Professional",
            "subcategory":"Business Services",
            "type":"Services"
        }
    ],
    "sg:phone":"+1 870 268 1088",
    "sg:postcode":"72404",
    "sg:province":"AR",
    "wof:name":"Wilcon Enterprises Inc",
    "wof:placetype":"venue"
},
  "geometry": {"coordinates":[-90.678658,35.793307],"type":"Point"}
}