{
  "type": "Feature",
  "properties": {
    "iso:country":"US",
    "sg:address":"622 S 21st St",
    "sg:city":"Fort Smith",
    "sg:classifiers":[
        {
            "category":"Insurance",
            "subcategory":"Insurance Agent",
            "type":"Services"
        }
    ],
    "sg:phone":"+1 479 783 0140",
    "sg:postcode":"72901",
    "sg:province":"AR",
    "wof:name":"Byron Ware Insurance",
    "wof:placetype":"venue"
},
  "geometry": {"coordinates":[-94.41066600000001,35.377329],"type":"Point"}
}