{
  "type": "Feature",
  "properties": {
    "iso:country":"US",
    "sg:address":"369 Central Ave",
    "sg:city":"Hot Springs",
    "sg:classifiers":[
        {
            "category":"Professional",
            "subcategory":"Business Services",
            "type":"Services"
        }
    ],
    "sg:phone":"+1 501 624 3383",
    "sg:postcode":"71901",
    "sg:province":"AR",
    "sg:tags":[
        "information",
        "bureau",
        "convention"
    ],
    "wof:name":"Fordyce Bathhouse Visitor Cntr",
    "wof:placetype":"venue"
},
  "geometry": {"coordinates":[-93.053683,34.514419],"type":"Point"}
}