{
  "type": "Feature",
  "properties": {
    "iso:country":"US",
    "sg:address":"2101 Morningside Dr",
    "sg:city":"Wynne",
    "sg:classifiers":[
        {
            "category":"Building & Trades",
            "subcategory":"Landscaping Services",
            "type":"Services"
        }
    ],
    "sg:phone":"+1 870 208 8888",
    "sg:postcode":"72396",
    "sg:province":"AR",
    "sg:tags":[
        "lawn",
        "maintenance"
    ],
    "wof:name":"Grass Roots Gallery",
    "wof:placetype":"venue"
},
  "geometry": {"coordinates":[-90.768389,35.227922],"type":"Point"}
}