{
  "type": "Feature",
  "properties": {
    "iso:country":"US",
    "sg:address":"45 Market Plz",
    "sg:city":"N Little Rock",
    "sg:classifiers":[
        {
            "category":"Restaurant",
            "type":"Food & Drink"
        }
    ],
    "sg:phone":"+1 501 945 5676",
    "sg:postcode":"72117",
    "sg:province":"AR",
    "sg:tags":[
        "eating"
    ],
    "wof:name":"Market Cafe",
    "wof:placetype":"venue"
},
  "geometry": {"coordinates":[-92.203097,34.786102],"type":"Point"}
}