{
  "type": "Feature",
  "properties": {
    "iso:country":"US",
    "sg:address":"4703 W Jackman Trl",
    "sg:city":"Benton",
    "sg:classifiers":[
        {
            "category":"Building & Trades",
            "subcategory":"Plumbing",
            "type":"Services"
        }
    ],
    "sg:phone":"+1 501 351 5724",
    "sg:postcode":"72019",
    "sg:province":"AR",
    "sg:tags":[
        "conditioning",
        "air",
        "system",
        "contractor"
    ],
    "wof:name":"All Star Air & Refrigeration",
    "wof:placetype":"venue"
},
  "geometry": {"coordinates":[-92.658392,34.556008],"type":"Point"}
}