{
  "type": "Feature",
  "properties": {
    "iso:country":"US",
    "sg:address":"1621 E Hillsboro St",
    "sg:city":"El Dorado",
    "sg:classifiers":[
        {
            "category":"Organizations",
            "subcategory":"Religious Organization",
            "type":"Services"
        }
    ],
    "sg:phone":"+1 870 862 1360",
    "sg:postcode":"71730",
    "sg:province":"AR",
    "sg:tags":[
        "church"
    ],
    "wof:name":"Union Mission Baptist Church",
    "wof:placetype":"venue"
},
  "geometry": {"coordinates":[-92.643517,33.206955],"type":"Point"}
}