{
  "type": "Feature",
  "properties": {
    "iso:country":"US",
    "sg:address":"1113 N 6th St",
    "sg:city":"Fort Smith",
    "sg:classifiers":[
        {
            "category":"Building & Trades",
            "subcategory":"Landscaping Services",
            "type":"Services"
        }
    ],
    "sg:phone":"+1 479 522 1856",
    "sg:postcode":"72901",
    "sg:province":"AR",
    "sg:tags":[
        "landscape",
        "contractor"
    ],
    "wof:name":"Rickey's Yard Care & Constr",
    "wof:placetype":"venue"
},
  "geometry": {"coordinates":[-94.41655900000001,35.396315],"type":"Point"}
}