{
  "type": "Feature",
  "properties": {
    "iso:country":"US",
    "sg:address":"10110 W Markham St",
    "sg:city":"Little Rock",
    "sg:classifiers":[
        {
            "category":"Wholesale",
            "subcategory":"Office Equipment",
            "type":"Manufacturing & Wholesale Goods"
        },
        {
            "category":"Shopping",
            "type":"Retail Goods"
        }
    ],
    "sg:phone":"+1 501 312 0050",
    "sg:postcode":"72205",
    "sg:province":"AR",
    "sg:tags":[
        "photocopying",
        "blueprinting",
        "merchandise",
        "supply"
    ],
    "sg:website":"www.arkansasblueprint.com",
    "wof:name":"Arkansas Blueprint Co",
    "wof:placetype":"venue"
},
  "geometry": {"coordinates":[-92.388754,34.753918],"type":"Point"}
}