{
  "type": "Feature",
  "properties": {
    "addr:full":"401 S Vine St Stuttgart AR 72160",
    "addr:housenumber":"401",
    "addr:postcode":"72160",
    "addr:street":"S Vine St",
    "iso:country":"US",
    "sg:address":"401 S Vine St",
    "sg:city":"Stuttgart",
    "sg:classifiers":[
        {
            "category":"Government",
            "subcategory":"Office",
            "type":"Public Place"
        }
    ],
    "sg:phone":"+1 870 673 1971",
    "sg:postcode":"72160",
    "sg:province":"AR",
    "sg:tags":[
        "township",
        "government-city",
        "village"
    ],
    "wof:name":"City Of Stuttgart",
    "wof:placetype":"venue"
},
  "geometry": {"coordinates":[-91.54286999999999,34.49902],"type":"Point"}
}