{
  "type": "Feature",
  "properties": {
    "iso:country":"US",
    "sg:address":"910 Townsend Ln",
    "sg:city":"Pocahontas",
    "sg:classifiers":[
        {
            "category":"Home & Garden",
            "subcategory":"Garden Supply",
            "type":"Retail Goods"
        }
    ],
    "sg:phone":"+1 870 892 5111",
    "sg:postcode":"72455",
    "sg:province":"AR",
    "wof:name":"Fertilizer Building",
    "wof:placetype":"venue"
},
  "geometry": {"coordinates":[-91.012642,36.451346],"type":"Point"}
}