{
  "type": "Feature",
  "properties": {
    "iso:country":"US",
    "sg:address":"222 E Washington St",
    "sg:city":"Camden",
    "sg:classifiers":[
        {
            "category":"Restaurant",
            "type":"Food & Drink"
        }
    ],
    "sg:phone":"+1 870 836 7608",
    "sg:postcode":"71701",
    "sg:province":"AR",
    "sg:tags":[
        "asian",
        "chinese",
        "pan"
    ],
    "wof:name":"Rainbow Chinese Restaurant",
    "wof:placetype":"venue"
},
  "geometry": {"coordinates":[-92.828547,33.586464],"type":"Point"}
}