{
  "type": "Feature",
  "properties": {
    "iso:country":"US",
    "sg:address":"1049 Wilburn Rd",
    "sg:city":"Heber Springs",
    "sg:classifiers":[
        {
            "category":"Real Estate",
            "subcategory":"Real Estate Agent",
            "type":"Services"
        }
    ],
    "sg:phone":"+1 501 362 8784",
    "sg:postcode":"72543",
    "sg:province":"AR",
    "sg:tags":[
        "appraiser"
    ],
    "wof:name":"Davis Appraisals",
    "wof:placetype":"venue"
},
  "geometry": {"coordinates":[-91.97717900000001,35.493385],"type":"Point"}
}