{
  "type": "Feature",
  "properties": {
    "iso:country":"US",
    "sg:address":"1008 Azure Hills Dr",
    "sg:city":"Van Buren",
    "sg:classifiers":[
        {
            "category":"Professional",
            "subcategory":"Engineering",
            "type":"Services"
        }
    ],
    "sg:phone":"+1 479 474 3398",
    "sg:postcode":"72956",
    "sg:province":"AR",
    "wof:name":"McBrayer Engineering Inc",
    "wof:placetype":"venue"
},
  "geometry": {"coordinates":[-94.375759,35.459324],"type":"Point"}
}