{
  "type": "Feature",
  "properties": {
    "addr:full":"1114 Wagon Wheel Rd Springdale AR 72764",
    "addr:housenumber":"1114",
    "addr:postcode":"72764",
    "addr:street":"Wagon Wheel Rd",
    "iso:country":"US",
    "sg:address":"1114 Wagon Wheel Rd",
    "sg:city":"Springdale",
    "sg:classifiers":[
        {
            "category":"Freight",
            "type":"Transportation"
        }
    ],
    "sg:phone":"+1 479 750 1700",
    "sg:postcode":"72764",
    "sg:province":"AR",
    "sg:tags":[
        "commercial",
        "storage"
    ],
    "wof:name":"Appalachian Self Storage",
    "wof:placetype":"venue"
},
  "geometry": {"coordinates":[-94.138305,36.22136],"type":"Point"}
}