{
  "type": "Feature",
  "properties": {
    "addr:full":"61 E Main St Booneville AR 72927",
    "addr:housenumber":"61",
    "addr:postcode":"72927",
    "addr:street":"E Main St",
    "iso:country":"US",
    "sg:address":"61 E Main St",
    "sg:city":"Booneville",
    "sg:classifiers":[
        {
            "category":"Food & Beverages",
            "subcategory":"Groceries & Convenience Stores",
            "type":"Retail Goods"
        }
    ],
    "sg:phone":"+1 479 675 4076",
    "sg:postcode":"72927",
    "sg:province":"AR",
    "wof:name":"Bk's Quick Mart",
    "wof:placetype":"venue"
},
  "geometry": {"coordinates":[-93.921053,35.140129],"type":"Point"}
}