{
  "type": "Feature",
  "properties": {
    "iso:country":"US",
    "sg:address":"203 Deaderick Rd",
    "sg:city":"Forrest City",
    "sg:classifiers":[
        {
            "category":"Restaurant",
            "type":"Food & Drink"
        }
    ],
    "sg:phone":"+1 870 633 2359",
    "sg:postcode":"72335",
    "sg:province":"AR",
    "sg:website":"www.blimpie.com",
    "wof:name":"Blimpie Subs & Salads",
    "wof:placetype":"venue"
},
  "geometry": {"coordinates":[-90.792591,35.029849],"type":"Point"}
}