{
  "type": "Feature",
  "properties": {
    "iso:country":"US",
    "sg:address":"205 Park Ave",
    "sg:city":"Scranton",
    "sg:classifiers":[
        {
            "category":"Government",
            "subcategory":"Fire Station",
            "type":"Public Place"
        }
    ],
    "sg:phone":"+1 479 938 7647",
    "sg:postcode":"72863",
    "sg:province":"AR",
    "sg:tags":[
        "department"
    ],
    "wof:name":"Scranton Fire Dept",
    "wof:placetype":"venue"
},
  "geometry": {"coordinates":[-93.536754,35.359121],"type":"Point"}
}