{
  "type": "Feature",
  "properties": {
    "iso:country":"US",
    "sg:address":"31 W Main St",
    "sg:city":"Booneville",
    "sg:classifiers":[
        {
            "category":"Health Services",
            "subcategory":"Nursing And Care Facility",
            "type":"Services"
        }
    ],
    "sg:phone":"+1 479 675 1370",
    "sg:postcode":"72927",
    "sg:province":"AR",
    "sg:tags":[
        "hospice"
    ],
    "wof:name":"Peachtree Hospice",
    "wof:placetype":"venue"
},
  "geometry": {"coordinates":[-93.922739,35.140377],"type":"Point"}
}