{
  "type": "Feature",
  "properties": {
    "iso:country":"US",
    "sg:address":"202 W Jackson St",
    "sg:city":"Harrisburg",
    "sg:classifiers":[
        {
            "category":"Professional",
            "subcategory":"Business Services",
            "type":"Services"
        }
    ],
    "sg:phone":"+1 870 578 3397",
    "sg:postcode":"72432",
    "sg:province":"AR",
    "wof:name":"Lcm Inc",
    "wof:placetype":"venue"
},
  "geometry": {"coordinates":[-90.724257,35.565149],"type":"Point"}
}