{
  "type": "Feature",
  "properties": {
    "iso:country":"US",
    "sg:address":"135 Central Ave",
    "sg:city":"Hot Springs National",
    "sg:classifiers":[
        {
            "category":"Travel",
            "subcategory":"Hotels & Motels",
            "type":"Entertainment"
        }
    ],
    "sg:phone":"+1 501 624 5521",
    "sg:postcode":"71901",
    "sg:province":"AR",
    "sg:tags":[
        "operation",
        "eating"
    ],
    "wof:name":"Downtowner Motor Inn",
    "wof:placetype":"venue"
},
  "geometry": {"coordinates":[-93.05548,34.518389],"type":"Point"}
}