{
  "type": "Feature",
  "properties": {
    "iso:country":"US",
    "sg:address":"507 E 1st Ave",
    "sg:city":"Crossett",
    "sg:classifiers":[
        {
            "category":"Retail",
            "subcategory":"Laundry & Dry Cleaning",
            "type":"Services"
        }
    ],
    "sg:phone":"+1 870 364 6107",
    "sg:postcode":"71635",
    "sg:province":"AR",
    "sg:tags":[
        "cleaners"
    ],
    "wof:name":"One Hour Martanizing",
    "wof:placetype":"venue"
},
  "geometry": {"coordinates":[-91.955592,33.135544],"type":"Point"}
}