{
  "type": "Feature",
  "properties": {
    "iso:country":"US",
    "sg:address":"113 Front St",
    "sg:city":"Rector",
    "sg:classifiers":[
        {
            "category":"Shopping",
            "subcategory":"Gifts & Souvenirs",
            "type":"Retail Goods"
        }
    ],
    "sg:phone":"+1 870 595 3290",
    "sg:postcode":"72461",
    "sg:province":"AR",
    "sg:tags":[
        "shop"
    ],
    "wof:name":"Now & Then",
    "wof:placetype":"venue"
},
  "geometry": {"coordinates":[-90.29177799999999,36.263039],"type":"Point"}
}