{
  "type": "Feature",
  "properties": {
    "iso:country":"US",
    "sg:address":"496 N Vinity Rd",
    "sg:city":"Searcy",
    "sg:classifiers":[
        {
            "category":"Building & Trades",
            "subcategory":"Electrical",
            "type":"Services"
        }
    ],
    "sg:phone":"+1 501 268 2131",
    "sg:postcode":"72143",
    "sg:province":"AR",
    "sg:tags":[
        "electric",
        "contractor"
    ],
    "wof:name":"Clairday Electric Co",
    "wof:placetype":"venue"
},
  "geometry": {"coordinates":[-91.775662,35.137556],"type":"Point"}
}