{
  "type": "Feature",
  "properties": {
    "addr:full":"1097 US Hwy 278 Monticello AR 71655",
    "addr:housenumber":"1097",
    "addr:postcode":"71655",
    "addr:street":"Us Hwy 278",
    "iso:country":"US",
    "sg:address":"1097 US Hwy 278",
    "sg:city":"Monticello",
    "sg:classifiers":[
        {
            "category":"Building & Trades",
            "subcategory":"Construction",
            "type":"Services"
        }
    ],
    "sg:phone":"+1 870 460 0405",
    "sg:postcode":"71655",
    "sg:province":"AR",
    "wof:name":"Martin Marietta",
    "wof:placetype":"venue"
},
  "geometry": {"coordinates":[-91.817751,33.632303],"type":"Point"}
}