{
  "type": "Feature",
  "properties": {
    "iso:country":"US",
    "sg:address":"11108 N Highway 348",
    "sg:city":"Mountainburg",
    "sg:classifiers":[
        {
            "category":"Manufacturing",
            "subcategory":"Buildings",
            "type":"Manufacturing & Wholesale Goods"
        },
        {
            "category":"Building & Trades",
            "subcategory":"Construction",
            "type":"Services"
        }
    ],
    "sg:phone":"+1 479 369 2074",
    "sg:postcode":"72946",
    "sg:province":"AR",
    "sg:tags":[
        "home",
        "builder",
        "contractor"
    ],
    "sg:website":"http://www.ccartwright.com",
    "wof:name":"Cartwright Construction",
    "wof:placetype":"venue"
},
  "geometry": {"coordinates":[-94.17435,35.599609],"type":"Point"}
}