{
  "type": "Feature",
  "properties": {
    "addr:full":"1010 Greyhound Dr Marmaduke AR 72443",
    "addr:housenumber":"1010",
    "addr:postcode":"72443",
    "addr:street":"Greyhound Dr",
    "iso:country":"US",
    "sg:address":"1010 Greyhound Dr",
    "sg:city":"Marmaduke",
    "sg:classifiers":[
        {
            "category":"Education",
            "subcategory":"School",
            "type":"Public Place"
        }
    ],
    "sg:phone":"+1 870 597 4693",
    "sg:postcode":"72443",
    "sg:province":"AR",
    "sg:tags":[
        "high"
    ],
    "sg:website":"http://www.mhs.nesc.k12.ar.us",
    "wof:name":"Marmaduke High School",
    "wof:placetype":"venue"
},
  "geometry": {"coordinates":[-90.39420699999999,36.19299],"type":"Point"}
}