{
  "type": "Feature",
  "properties": {
    "iso:country":"US",
    "sg:address":"2106 E 6th Ave",
    "sg:city":"Pine Bluff",
    "sg:classifiers":[
        {
            "category":"Organizations",
            "subcategory":"Non-profit Organization",
            "type":"Services"
        }
    ],
    "sg:phone":"+1 870 535 3535",
    "sg:postcode":"71601",
    "sg:province":"AR",
    "sg:tags":[
        "human"
    ],
    "wof:name":"Human Development Research Adm",
    "wof:placetype":"venue"
},
  "geometry": {"coordinates":[-91.981559,34.224144],"type":"Point"}
}