{
  "type": "Feature",
  "properties": {
    "addr:full":"1039 S Gutensohn Rd Springdale AR 72762",
    "addr:housenumber":"1039",
    "addr:postcode":"72762",
    "addr:street":"S Gutensohn Rd",
    "iso:country":"US",
    "sg:address":"1039 S Gutensohn Rd",
    "sg:city":"Springdale",
    "sg:classifiers":[
        {
            "category":"Sports & Exercise",
            "subcategory":"Gym",
            "type":"Entertainment"
        }
    ],
    "sg:phone":"+1 479 927 2567",
    "sg:postcode":"72762",
    "sg:province":"AR",
    "sg:tags":[
        "club",
        "health",
        "studio",
        "gymnasium"
    ],
    "wof:name":"Hard Body Gym",
    "wof:placetype":"venue"
},
  "geometry": {"coordinates":[-94.161277,36.175183],"type":"Point"}
}