{
  "type": "Feature",
  "properties": {
    "iso:country":"US",
    "sg:address":"7971 Hopewell Rd",
    "sg:city":"Harrison",
    "sg:classifiers":[
        {
            "category":"Farming",
            "subcategory":"Poultry Farm",
            "type":"Manufacturing & Wholesale Goods"
        }
    ],
    "sg:phone":"+1 870 741 5947",
    "sg:postcode":"72601",
    "sg:province":"AR",
    "wof:name":"Early Bird Farms, Inc.",
    "wof:placetype":"venue"
},
  "geometry": {"coordinates":[-93.087417,36.344502],"type":"Point"}
}