{
  "type": "Feature",
  "properties": {
    "iso:country":"US",
    "sg:address":"99 Shiloh Rd",
    "sg:city":"Pocahontas",
    "sg:classifiers":[
        {
            "category":"Building & Trades",
            "subcategory":"Plumbing",
            "type":"Services"
        }
    ],
    "sg:phone":"+1 870 892 8501",
    "sg:postcode":"72455",
    "sg:province":"AR",
    "sg:tags":[
        "plumbing",
        "contractor"
    ],
    "wof:name":"Lane's Plumbing Heating & Air",
    "wof:placetype":"venue"
},
  "geometry": {"coordinates":[-91.031902,36.30445],"type":"Point"}
}