{
  "type": "Feature",
  "properties": {
    "iso:country":"US",
    "sg:address":"231 Red Oak Dr",
    "sg:city":"Hot Springs",
    "sg:classifiers":[
        {
            "category":"Building & Trades",
            "subcategory":"Landscaping Services",
            "type":"Services"
        }
    ],
    "sg:phone":"+1 501 262 1162",
    "sg:postcode":"71913",
    "sg:province":"AR",
    "sg:tags":[
        "tree"
    ],
    "wof:name":"Aaron's No Problem Tree Svc",
    "wof:placetype":"venue"
},
  "geometry": {"coordinates":[-93.02685099999999,34.420545],"type":"Point"}
}