{
  "type": "Feature",
  "properties": {
    "iso:country":"US",
    "sg:address":"119 Northridge Rd",
    "sg:city":"Booneville",
    "sg:classifiers":[
        {
            "category":"Shopping",
            "subcategory":"Computers & Home Electronics",
            "type":"Retail Goods"
        }
    ],
    "sg:phone":"+1 479 675 4087",
    "sg:postcode":"72927",
    "sg:province":"AR",
    "wof:name":"Scott Satellite Systems",
    "wof:placetype":"venue"
},
  "geometry": {"coordinates":[-93.929342,35.182946],"type":"Point"}
}