{
  "type": "Feature",
  "properties": {
    "iso:country":"US",
    "sg:address":"1506 S Wood St",
    "sg:city":"Stuttgart",
    "sg:classifiers":[
        {
            "category":"Professional",
            "type":"Services"
        }
    ],
    "sg:phone":"+1 870 673 8891",
    "sg:postcode":"72160",
    "sg:province":"AR",
    "sg:tags":[
        "establishment"
    ],
    "wof:name":"Arkansas Lubricate Co",
    "wof:placetype":"venue"
},
  "geometry": {"coordinates":[-91.545636,34.488903],"type":"Point"}
}