{
  "type": "Feature",
  "properties": {
    "iso:country":"US",
    "sg:address":"722 Elmo St",
    "sg:city":"Malvern",
    "sg:classifiers":[
        {
            "category":"Building & Trades",
            "subcategory":"Construction",
            "type":"Services"
        }
    ],
    "sg:phone":"+1 501 332 7298",
    "sg:postcode":"72104",
    "sg:province":"AR",
    "sg:tags":[
        "hanging",
        "contractor"
    ],
    "wof:name":"Don Davy",
    "wof:placetype":"venue"
},
  "geometry": {"coordinates":[-92.818118,34.37269],"type":"Point"}
}