{
  "type": "Feature",
  "properties": {
    "iso:country":"US",
    "sg:address":"1401 W 6th St",
    "sg:city":"Little Rock",
    "sg:classifiers":[
        {
            "category":"Organizations",
            "subcategory":"Professional Association",
            "type":"Services"
        }
    ],
    "sg:phone":"+1 501 661 1111",
    "sg:postcode":"72201",
    "sg:province":"AR",
    "wof:name":"American Institute-Architects",
    "wof:placetype":"venue"
},
  "geometry": {"coordinates":[-92.287351,34.745334],"type":"Point"}
}