{
  "type": "Feature",
  "properties": {
    "iso:country":"US",
    "sg:address":"106 W Adams St",
    "sg:city":"Hamburg",
    "sg:classifiers":[
        {
            "category":"Personal",
            "subcategory":"Beauty Salon",
            "type":"Services"
        }
    ],
    "sg:phone":"+1 870 853 8335",
    "sg:postcode":"71646",
    "sg:province":"AR",
    "wof:name":"Ooh La La",
    "wof:placetype":"venue"
},
  "geometry": {"coordinates":[-91.797917,33.226395],"type":"Point"}
}