{
  "type": "Feature",
  "properties": {
    "iso:country":"US",
    "sg:address":"12705 Schaberg Rd",
    "sg:city":"Mountainburg",
    "sg:classifiers":[
        {
            "category":"Government",
            "subcategory":"Court House",
            "type":"Public Place"
        },
        {
            "category":"Recreation",
            "type":"Entertainment"
        },
        {
            "category":"Travel",
            "subcategory":"Hotels & Motels",
            "type":"Entertainment"
        }
    ],
    "sg:phone":"+1 479 369 1211",
    "sg:postcode":"72946",
    "sg:province":"AR",
    "sg:tags":[
        "cottage",
        "chalet",
        "camps-recreational",
        "cabin"
    ],
    "wof:name":"Barney H Larue",
    "wof:placetype":"venue"
},
  "geometry": {"coordinates":[-94.149349,35.724919],"type":"Point"}
}