{
  "type": "Feature",
  "properties": {
    "addr:full":"2626 Millbrook Dr Benton AR 72015",
    "addr:housenumber":"2626",
    "addr:postcode":"72015",
    "addr:street":"Millbrook Dr",
    "iso:country":"US",
    "sg:address":"2626 Millbrook Dr",
    "sg:city":"Benton",
    "sg:classifiers":[
        {
            "category":"Education",
            "subcategory":"Preschool",
            "type":"Public Place"
        }
    ],
    "sg:phone":"+1 501 860 6507",
    "sg:postcode":"72015",
    "sg:province":"AR",
    "sg:tags":[
        "kindergarten"
    ],
    "wof:name":"Ms Jenn's Jumpstart Preschool",
    "wof:placetype":"venue"
},
  "geometry": {"coordinates":[-92.549074,34.58675],"type":"Point"}
}