{
  "type": "Feature",
  "properties": {
    "iso:country":"US",
    "sg:address":"209 N Main St",
    "sg:city":"Jay",
    "sg:classifiers":[
        {
            "category":"Banks & Credit Unions",
            "subcategory":"Investment Brokerage",
            "type":"Services"
        }
    ],
    "sg:phone":"+1 918 253 2561",
    "sg:postcode":"74346",
    "sg:province":"OK",
    "sg:tags":[
        "security"
    ],
    "wof:name":"Edward Jones 15263",
    "wof:placetype":"venue"
},
  "geometry": {"coordinates":[-94.788239,36.42513],"type":"Point"}
}