{
  "type": "Feature",
  "properties": {
    "addr:full":"201 Pennington Dr Paris AR 72855",
    "addr:housenumber":"201",
    "addr:postcode":"72855",
    "addr:street":"Pennington Dr",
    "iso:country":"US",
    "sg:address":"201 Pennington Dr",
    "sg:city":"Paris",
    "sg:classifiers":[
        {
            "category":"Structure",
            "subcategory":"Warehouse",
            "type":"Public Place"
        },
        {
            "category":"Retail",
            "subcategory":"Storage",
            "type":"Services"
        }
    ],
    "sg:phone":"+1 479 963 1004",
    "sg:postcode":"72855",
    "sg:province":"AR",
    "sg:tags":[
        "self",
        "warehouses-public-commercial"
    ],
    "wof:name":"South Side Storage",
    "wof:placetype":"venue"
},
  "geometry": {"coordinates":[-93.735919,35.290396],"type":"Point"}
}