{
  "type": "Feature",
  "properties": {
    "iso:country":"US",
    "sg:address":"212 Brookswood Rd",
    "sg:city":"Sherwood",
    "sg:classifiers":[
        {
            "category":"Autos & Motor Vehicles",
            "subcategory":"Automobile Sales",
            "type":"Retail Goods"
        }
    ],
    "sg:phone":"+1 501 834 7707",
    "sg:postcode":"72120",
    "sg:province":"AR",
    "sg:tags":[
        "car",
        "dealer"
    ],
    "wof:name":"Osborn Car Co",
    "wof:placetype":"venue"
},
  "geometry": {"coordinates":[-92.19107,34.829148],"type":"Point"}
}