{
  "type": "Feature",
  "properties": {
    "iso:country":"US",
    "sg:address":"10 Dana St",
    "sg:city":"Highland",
    "sg:classifiers":[
        {
            "category":"Shopping",
            "subcategory":"Used Merchandise",
            "type":"Retail Goods"
        }
    ],
    "sg:phone":"+1 870 856 3350",
    "sg:postcode":"72513",
    "sg:province":"AR",
    "sg:tags":[
        "furniture"
    ],
    "wof:name":"Horrell's Used Furniture",
    "wof:placetype":"venue"
},
  "geometry": {"coordinates":[-91.535381,36.259901],"type":"Point"}
}