{
  "type": "Feature",
  "properties": {
    "iso:country":"US",
    "sg:address":"1700 Doctors Dr",
    "sg:city":"Pine Bluff",
    "sg:classifiers":[
        {
            "category":"Health Services",
            "subcategory":"Doctor",
            "type":"Services"
        }
    ],
    "sg:phone":"+1 870 536 2960",
    "sg:postcode":"71603",
    "sg:province":"AR",
    "sg:tags":[
        "dentist"
    ],
    "wof:name":"Tom R Doherty DMD",
    "wof:placetype":"venue"
},
  "geometry": {"coordinates":[-92.01828999999999,34.185703],"type":"Point"}
}