{
  "type": "Feature",
  "properties": {
    "iso:country":"US",
    "sg:address":"2710 Otis Corley Dr",
    "sg:city":"Bentonville",
    "sg:classifiers":[
        {
            "category":"Personal",
            "type":"Services"
        }
    ],
    "sg:phone":"+1 479 521 9824",
    "sg:postcode":"72712",
    "sg:province":"AR",
    "sg:tags":[
        "mover"
    ],
    "sg:website":"www.wintermoving.com",
    "wof:name":"Winter Moving & Storage",
    "wof:placetype":"venue"
},
  "geometry": {"coordinates":[-94.190399,36.3438],"type":"Point"}
}