{
  "type": "Feature",
  "properties": {
    "iso:country":"US",
    "sg:address":"3575 Larch Pl",
    "sg:city":"Springdale",
    "sg:classifiers":[
        {
            "category":"Arts & Performance",
            "subcategory":"Theater",
            "type":"Entertainment"
        }
    ],
    "sg:phone":"+1 479 872 1137",
    "sg:postcode":"72764",
    "sg:province":"AR",
    "sg:tags":[
        "group"
    ],
    "wof:name":"Be A Star Karaoke",
    "wof:placetype":"venue"
},
  "geometry": {"coordinates":[-94.091257,36.175735],"type":"Point"}
}