{
  "type": "Feature",
  "properties": {
    "iso:country":"US",
    "sg:address":"333 Co Rd 405",
    "sg:city":"Berryville",
    "sg:classifiers":[
        {
            "category":"Professional",
            "type":"Services"
        }
    ],
    "sg:phone":"+1 870 423 2027",
    "sg:postcode":"72616",
    "sg:province":"AR",
    "wof:name":"Dale Headings",
    "wof:placetype":"venue"
},
  "geometry": {"coordinates":[-93.556223,36.436493],"type":"Point"}
}