{
  "type": "Feature",
  "properties": {
    "addr:full":"5558 Walden St Lowell AR 72745",
    "addr:housenumber":"5558",
    "addr:postcode":"72745",
    "addr:street":"Walden St",
    "iso:country":"US",
    "sg:address":"5558 Walden St",
    "sg:city":"Lowell",
    "sg:classifiers":[
        {
            "category":"Retail",
            "subcategory":"Auto Repair",
            "type":"Services"
        }
    ],
    "sg:phone":"+1 479 751 0841",
    "sg:postcode":"72745",
    "sg:province":"AR",
    "sg:tags":[
        "body",
        "automobile",
        "painting",
        "repairing"
    ],
    "wof:name":"Dannys Auto Body",
    "wof:placetype":"venue"
},
  "geometry": {"coordinates":[-94.141443,36.234817],"type":"Point"}
}