{
  "type": "Feature",
  "properties": {
    "addr:full":"6810 Arch St Little Rock AR 72206",
    "addr:housenumber":"6810",
    "addr:postcode":"72206",
    "addr:street":"Arch St",
    "iso:country":"US",
    "sg:address":"6810 Arch St",
    "sg:city":"Little Rock",
    "sg:classifiers":[
        {
            "category":"Retail",
            "subcategory":"Auto Repair",
            "type":"Services"
        }
    ],
    "sg:phone":"+1 501 562 3311",
    "sg:postcode":"72206",
    "sg:province":"AR",
    "sg:tags":[
        "automobile",
        "motor",
        "rebuilding"
    ],
    "wof:name":"Simplex Motor Parts Co",
    "wof:placetype":"venue"
},
  "geometry": {"coordinates":[-92.297235,34.686194],"type":"Point"}
}