{
  "type": "Feature",
  "properties": {
    "iso:country":"US",
    "sg:address":"301 Kings Row Dr",
    "sg:city":"Little Rock",
    "sg:classifiers":[
        {
            "category":"Building & Trades",
            "subcategory":"Construction",
            "type":"Services"
        }
    ],
    "sg:phone":"+1 501 663 3860",
    "sg:postcode":"72207",
    "sg:province":"AR",
    "sg:tags":[
        "general",
        "contractor"
    ],
    "wof:name":"Construction Network",
    "wof:placetype":"venue"
},
  "geometry": {"coordinates":[-92.354143,34.771893],"type":"Point"}
}