{
  "type": "Feature",
  "properties": {
    "iso:country":"US",
    "sg:address":"7600 State Hwy 107",
    "sg:city":"N Little Rock",
    "sg:classifiers":[
        {
            "category":"Professional",
            "subcategory":"Lawyer & Legal Services",
            "type":"Services"
        }
    ],
    "sg:phone":"+1 501 221 3200",
    "sg:postcode":"72120",
    "sg:province":"AR",
    "sg:tags":[
        "attorney"
    ],
    "wof:name":"Keech Law Firm",
    "wof:placetype":"venue"
},
  "geometry": {"coordinates":[-92.231285,34.822445],"type":"Point"}
}