{
  "type": "Feature",
  "properties": {
    "iso:country":"US",
    "sg:address":"815 E Wood St",
    "sg:city":"Paris",
    "sg:classifiers":[
        {
            "category":"Autos & Motor Vehicles",
            "subcategory":"Automobile Sales",
            "type":"Retail Goods"
        }
    ],
    "sg:phone":"+1 479 963 2891",
    "sg:postcode":"72855",
    "sg:province":"AR",
    "sg:tags":[
        "dealers-used",
        "cars-wholesale"
    ],
    "sg:website":"http://www.kochworks.com",
    "wof:name":"Tommy L Koch",
    "wof:placetype":"venue"
},
  "geometry": {"coordinates":[-93.722807,35.298198],"type":"Point"}
}