{
  "type": "Feature",
  "properties": {
    "addr:full":"4717 W 65th St Little Rock AR 72209",
    "addr:housenumber":"4717",
    "addr:postcode":"72209",
    "addr:street":"W 65Th St",
    "iso:country":"US",
    "sg:address":"4717 W 65th St",
    "sg:city":"Little Rock",
    "sg:classifiers":[
        {
            "category":"Autos & Motor Vehicles",
            "subcategory":"Automobile Sales",
            "type":"Retail Goods"
        }
    ],
    "sg:phone":"+1 501 562 3443",
    "sg:postcode":"72209",
    "sg:province":"AR",
    "sg:tags":[
        "car",
        "dealer"
    ],
    "wof:name":"Best Way Used Cars",
    "wof:placetype":"venue"
},
  "geometry": {"coordinates":[-92.330634,34.690173],"type":"Point"}
}