{
  "type": "Feature",
  "properties": {
    "addr:full":"310 SW 6th St Walnut Ridge AR 72476",
    "addr:housenumber":"310",
    "addr:postcode":"72476",
    "addr:street":"Sw 6Th St",
    "iso:country":"US",
    "sg:address":"310 SW 6th St",
    "sg:city":"Walnut Ridge",
    "sg:classifiers":[
        {
            "category":"Restaurant",
            "type":"Food & Drink"
        }
    ],
    "sg:phone":"+1 870 886 2004",
    "sg:postcode":"72476",
    "sg:province":"AR",
    "wof:name":"Ole Hickory Bar-B-Que",
    "wof:placetype":"venue"
},
  "geometry": {"coordinates":[-90.96173899999999,36.07097],"type":"Point"}
}