{
  "type": "Feature",
  "properties": {
    "iso:country":"US",
    "sg:address":"6100 Bottorff Rd",
    "sg:city":"Pangburn",
    "sg:classifiers":[
        {
            "category":"Farming",
            "subcategory":"Farm",
            "type":"Manufacturing & Wholesale Goods"
        }
    ],
    "sg:phone":"+1 501 728 4620",
    "sg:postcode":"72121",
    "sg:province":"AR",
    "wof:name":"S & G Farms",
    "wof:placetype":"venue"
},
  "geometry": {"coordinates":[-91.803894,35.491469],"type":"Point"}
}