{
  "type": "Feature",
  "properties": {
    "addr:full":"2107 Sandstone Ridge Rd Charleston AR 72933",
    "addr:housenumber":"2107",
    "addr:postcode":"72933",
    "addr:street":"Sandstone Ridge Rd",
    "iso:country":"US",
    "sg:address":"2107 Sandstone Ridge Rd",
    "sg:city":"Charleston",
    "sg:classifiers":[
        {
            "category":"Farming",
            "subcategory":"Farm",
            "type":"Manufacturing & Wholesale Goods"
        }
    ],
    "sg:phone":"+1 479 965 7452",
    "sg:postcode":"72933",
    "sg:province":"AR",
    "wof:name":"Grubbs Farm",
    "wof:placetype":"venue"
},
  "geometry": {"coordinates":[-93.97773100000001,35.385374],"type":"Point"}
}