{
  "type": "Feature",
  "properties": {
    "addr:full":"229 Co Rd 3012 Eureka Springs AR 72632",
    "addr:housenumber":"229",
    "addr:postcode":"3012;72632",
    "addr:street":"Co Rd",
    "iso:country":"US",
    "sg:address":"229 Co Rd 3012",
    "sg:city":"Eureka Springs",
    "sg:classifiers":[
        {
            "category":"Travel",
            "subcategory":"Hotels & Motels",
            "type":"Entertainment"
        }
    ],
    "sg:phone":"+1 479 253 4918",
    "sg:postcode":"72632",
    "sg:province":"AR",
    "sg:tags":[
        "operation"
    ],
    "wof:name":"Apple Annies Bed & Breakfast",
    "wof:placetype":"venue"
},
  "geometry": {"coordinates":[-93.72364899999999,36.375845],"type":"Point"}
}