{
  "type": "Feature",
  "properties": {
    "addr:full":"113 Valley Dr Helena AR 72342",
    "addr:housenumber":"113",
    "addr:postcode":"72342",
    "addr:street":"Valley Dr",
    "iso:country":"US",
    "sg:address":"113 Valley Dr",
    "sg:city":"Helena",
    "sg:classifiers":[
        {
            "category":"Manufacturing",
            "subcategory":"Signs",
            "type":"Manufacturing & Wholesale Goods"
        }
    ],
    "sg:phone":"+1 870 338 3853",
    "sg:postcode":"72342",
    "sg:province":"AR",
    "sg:tags":[
        "specialty",
        "mfg"
    ],
    "wof:name":"Spakes Signs",
    "wof:placetype":"venue"
},
  "geometry": {"coordinates":[-90.610533,34.541083],"type":"Point"}
}