{
  "type": "Feature",
  "properties": {
    "iso:country":"US",
    "sg:address":"3184 Cotton Rd",
    "sg:city":"Magazine",
    "sg:classifiers":[
        {
            "category":"Banks & Credit Unions",
            "subcategory":"Financial Services",
            "type":"Services"
        }
    ],
    "sg:phone":"+1 479 969 2997",
    "sg:postcode":"72943",
    "sg:province":"AR",
    "sg:tags":[
        "trust",
        "management"
    ],
    "wof:name":"Sims National",
    "wof:placetype":"venue"
},
  "geometry": {"coordinates":[-93.833302,35.179668],"type":"Point"}
}