{
  "type": "Feature",
  "properties": {
    "iso:country":"US",
    "sg:address":"10801 Executive Center Dr",
    "sg:city":"Little Rock",
    "sg:classifiers":[
        {
            "category":"Manufacturing",
            "subcategory":"Buildings",
            "type":"Manufacturing & Wholesale Goods"
        },
        {
            "category":"Banks & Credit Unions",
            "subcategory":"Bank",
            "type":"Services"
        }
    ],
    "sg:phone":"+1 501 224 1061",
    "sg:postcode":"72211",
    "sg:province":"AR",
    "sg:tags":[
        "prefab",
        "financing"
    ],
    "wof:name":"Green Tree Servicing",
    "wof:placetype":"venue"
},
  "geometry": {"coordinates":[-92.395985,34.739262],"type":"Point"}
}