{
  "type": "Feature",
  "properties": {
    "iso:country":"US",
    "sg:address":"2800 Gap Rd",
    "sg:city":"Batesville",
    "sg:classifiers":[
        {
            "category":"Building & Trades",
            "subcategory":"Construction",
            "type":"Services"
        }
    ],
    "sg:phone":"+1 870 698 5700",
    "sg:postcode":"72501",
    "sg:province":"AR",
    "sg:tags":[
        "contractor"
    ],
    "wof:name":"Service Environmental Company",
    "wof:placetype":"venue"
},
  "geometry": {"coordinates":[-91.518447,35.725762],"type":"Point"}
}