{
  "type": "Feature",
  "properties": {
    "addr:full":"2800 Gap Rd Batesville AR 72501",
    "addr:housenumber":"2800",
    "addr:postcode":"72501",
    "addr:street":"Gap Rd",
    "iso:country":"US",
    "sg:address":"2800 Gap Rd",
    "sg:city":"Batesville",
    "sg:classifiers":[
        {
            "category":"Building & Trades",
            "subcategory":"Construction",
            "type":"Services"
        }
    ],
    "sg:phone":"+1 870 698 5700",
    "sg:postcode":"72501",
    "sg:province":"AR",
    "sg:tags":[
        "contractor"
    ],
    "wof:name":"Service Environmental Company",
    "wof:placetype":"venue"
},
  "geometry": {"coordinates":[-91.51844699999999,35.725762],"type":"Point"}
}