{
  "type": "Feature",
  "properties": {
    "addr:full":"19812 Highway 62 Garfield AR 72732",
    "addr:housenumber":"19812",
    "addr:postcode":"72732",
    "addr:street":"Highway 62",
    "iso:country":"US",
    "sg:address":"19812 Highway 62",
    "sg:city":"Garfield",
    "sg:classifiers":[
        {
            "category":"Utilities",
            "subcategory":"Water",
            "type":"Services"
        },
        {
            "category":"Utilities",
            "type":"Services"
        }
    ],
    "sg:phone":"+1 479 656 3349",
    "sg:postcode":"72732",
    "sg:province":"AR",
    "sg:tags":[
        "company-utility",
        "contractor"
    ],
    "wof:name":"Gateway Public Water Authority",
    "wof:placetype":"venue"
},
  "geometry": {"coordinates":[-93.949219,36.476634],"type":"Point"}
}