{
  "type": "Feature",
  "properties": {
    "iso:country":"US",
    "sg:address":"319 N Main St",
    "sg:city":"Cave City",
    "sg:classifiers":[
        {
            "category":"Real Estate",
            "subcategory":"Real Estate Agent",
            "type":"Services"
        }
    ],
    "sg:phone":"+1 870 283 7212",
    "sg:postcode":"72521",
    "sg:province":"AR",
    "wof:name":"P Rafter Real Estate",
    "wof:placetype":"venue"
},
  "geometry": {"coordinates":[-91.548925,35.943742],"type":"Point"}
}