{
  "type": "Feature",
  "properties": {
    "iso:country":"US",
    "sg:address":"12076 State Hwy 170",
    "sg:city":"Farmington",
    "sg:classifiers":[
        {
            "category":"Retail",
            "subcategory":"Auto Repair",
            "type":"Services"
        }
    ],
    "sg:phone":"+1 479 267 2440",
    "sg:postcode":"72730",
    "sg:province":"AR",
    "sg:tags":[
        "wheel",
        "axle",
        "alignment"
    ],
    "wof:name":"Dells-Computerized 4 Wheel",
    "wof:placetype":"venue"
},
  "geometry": {"coordinates":[-94.249483,36.02087],"type":"Point"}
}