{
  "type": "Feature",
  "properties": {
    "iso:country":"US",
    "sg:address":"1818 N Washington St",
    "sg:city":"Magnolia",
    "sg:classifiers":[
        {
            "category":"Building & Trades",
            "subcategory":"Construction",
            "type":"Services"
        }
    ],
    "sg:phone":"+1 870 234 4140",
    "sg:postcode":"71753",
    "sg:province":"AR",
    "sg:tags":[
        "contractor"
    ],
    "wof:name":"De Loach Construction Co",
    "wof:placetype":"venue"
},
  "geometry": {"coordinates":[-93.23811000000001,33.286345],"type":"Point"}
}