{
  "type": "Feature",
  "properties": {
    "iso:country":"US",
    "sg:address":"2086 Bridgeton Ct",
    "sg:city":"Fayetteville",
    "sg:classifiers":[
        {
            "category":"Professional",
            "subcategory":"Business Services",
            "type":"Services"
        }
    ],
    "sg:phone":"+1 479 443 1874",
    "sg:postcode":"72701",
    "sg:province":"AR",
    "wof:name":"Wellspring Group LLC",
    "wof:placetype":"venue"
},
  "geometry": {"coordinates":[-94.096295,36.088074],"type":"Point"}
}