{
  "type": "Feature",
  "properties": {
    "iso:country":"US",
    "sg:address":"300 W Broadway",
    "sg:city":"Spiro",
    "sg:classifiers":[
        {
            "category":"Social Services",
            "subcategory":"Child Care",
            "type":"Services"
        }
    ],
    "sg:phone":"+1 918 962 3995",
    "sg:postcode":"74959",
    "sg:province":"OK",
    "sg:tags":[
        "kindergarten",
        "academic",
        "school"
    ],
    "wof:name":"Kibois Head Start",
    "wof:placetype":"venue"
},
  "geometry": {"coordinates":[-94.624707,35.241075],"type":"Point"}
}