{
  "type": "Feature",
  "properties": {
    "iso:country":"US",
    "sg:address":"715 W Park St",
    "sg:city":"Paragould",
    "sg:classifiers":[
        {
            "category":"Real Estate",
            "subcategory":"Developer",
            "type":"Services"
        }
    ],
    "sg:phone":"+1 870 239 5631",
    "sg:postcode":"72450",
    "sg:province":"AR",
    "wof:name":"B&D Development LLC",
    "wof:placetype":"venue"
},
  "geometry": {"coordinates":[-90.496075,36.049586],"type":"Point"}
}