{
  "type": "Feature",
  "properties": {
    "iso:country":"US",
    "sg:address":"515 Willmuth",
    "sg:city":"Brinkley",
    "sg:classifiers":[
        {
            "category":"Building & Trades",
            "subcategory":"Plumbing",
            "type":"Services"
        }
    ],
    "sg:phone":"+1 870 734 3367",
    "sg:postcode":"72021",
    "sg:province":"AR",
    "sg:tags":[
        "contractor"
    ],
    "wof:name":"Miley & Holloway Heating & Air",
    "wof:placetype":"venue"
},
  "geometry": {"coordinates":[-91.19775300000001,34.892304],"type":"Point"}
}