{
  "type": "Feature",
  "properties": {
    "iso:country":"US",
    "sg:address":"2575 N Keystone Xing",
    "sg:city":"Fayetteville",
    "sg:classifiers":[
        {
            "category":"Professional",
            "subcategory":"Lawyer & Legal Services",
            "type":"Services"
        }
    ],
    "sg:phone":"+1 479 442 6213",
    "sg:postcode":"72703",
    "sg:province":"AR",
    "sg:tags":[
        "attorney",
        "practice"
    ],
    "sg:website":"http://www.ballandmourton.com",
    "wof:name":"Ball & Mourton Ltd, P",
    "wof:placetype":"venue"
},
  "geometry": {"coordinates":[-94.159614,36.099154],"type":"Point"}
}