{
  "type": "Feature",
  "properties": {
    "iso:country":"US",
    "sg:address":"408 S Bradley St",
    "sg:city":"Warren",
    "sg:classifiers":[
        {
            "category":"Education",
            "subcategory":"School",
            "type":"Public Place"
        }
    ],
    "sg:phone":"+1 870 226 8512",
    "sg:postcode":"71671",
    "sg:province":"AR",
    "wof:name":"Eastside Elementary School",
    "wof:placetype":"venue"
},
  "geometry": {"coordinates":[-92.058727,33.611009],"type":"Point"}
}