{
  "type": "Feature",
  "properties": {
    "addr:full":"811 Prince St Pocahontas AR 72455",
    "addr:housenumber":"811",
    "addr:postcode":"72455",
    "addr:street":"Prince St",
    "iso:country":"US",
    "sg:address":"811 Prince St",
    "sg:city":"Pocahontas",
    "sg:classifiers":[
        {
            "category":"Personal",
            "subcategory":"Beauty Salon",
            "type":"Services"
        },
        {
            "category":"Personal",
            "subcategory":"Barber",
            "type":"Services"
        }
    ],
    "sg:phone":"+1 870 248 0018",
    "sg:postcode":"72455",
    "sg:province":"AR",
    "wof:name":"Reflections Hair Salon",
    "wof:placetype":"venue"
},
  "geometry": {"coordinates":[-90.961506,36.248009],"type":"Point"}
}