{
  "type": "Feature",
  "properties": {
    "iso:country":"US",
    "sg:address":"9 Maumelle Curve Ct",
    "sg:city":"Maumelle",
    "sg:classifiers":[
        {
            "category":"Wholesale",
            "subcategory":"Farm Supplies",
            "type":"Manufacturing & Wholesale Goods"
        }
    ],
    "sg:phone":"+1 501 791 3484",
    "sg:postcode":"72113",
    "sg:province":"AR",
    "sg:tags":[
        "machinery"
    ],
    "wof:name":"Lesco Service Center 572",
    "wof:placetype":"venue"
},
  "geometry": {"coordinates":[-92.375037,34.826771],"type":"Point"}
}