{
  "type": "Feature",
  "properties": {
    "iso:country":"US",
    "sg:address":"15008 Jack Crabtree Rd",
    "sg:city":"Bentonville",
    "sg:classifiers":[
        {
            "category":"Food & Beverages",
            "subcategory":"Groceries & Convenience Stores",
            "type":"Retail Goods"
        }
    ],
    "sg:phone":"+1 479 451 1941",
    "sg:postcode":"72712",
    "sg:province":"AR",
    "sg:tags":[
        "station",
        "gasoline"
    ],
    "wof:name":"Tillmans Country Market Inc",
    "wof:placetype":"venue"
},
  "geometry": {"coordinates":[-94.176489,36.453592],"type":"Point"}
}