{
  "type": "Feature",
  "properties": {
    "addr:full":"1521 Merrill Dr Little Rock AR 72211",
    "addr:housenumber":"1521",
    "addr:postcode":"72211",
    "addr:street":"Merrill Dr",
    "iso:country":"US",
    "sg:address":"1521 Merrill Dr",
    "sg:city":"Little Rock",
    "sg:classifiers":[
        {
            "category":"Professional",
            "subcategory":"Lawyer & Legal Services",
            "type":"Services"
        }
    ],
    "sg:phone":"+1 501 374 8335",
    "sg:postcode":"72211",
    "sg:province":"AR",
    "wof:name":"Randall S Bueter",
    "wof:placetype":"venue"
},
  "geometry": {"coordinates":[-92.39792,34.767395],"type":"Point"}
}