{
  "type": "Feature",
  "properties": {
    "addr:full":"4831 Armour St Fort Smith AR 72904",
    "addr:housenumber":"4831",
    "addr:postcode":"72904",
    "addr:street":"Armour St",
    "iso:country":"US",
    "sg:address":"4831 Armour St",
    "sg:city":"Fort Smith",
    "sg:classifiers":[
        {
            "category":"Government",
            "subcategory":"Office",
            "type":"Public Place"
        }
    ],
    "sg:phone":"+1 479 785 2328",
    "sg:postcode":"72904",
    "sg:province":"AR",
    "wof:name":"US Financial Dept",
    "wof:placetype":"venue"
},
  "geometry": {"coordinates":[-94.379313,35.409263],"type":"Point"}
}