{
  "type": "Feature",
  "properties": {
    "iso:country":"US",
    "sg:address":"136 Cypress Dr",
    "sg:city":"Maumelle",
    "sg:classifiers":[
        {
            "category":"Food & Beverages",
            "subcategory":"Groceries & Convenience Stores",
            "type":"Retail Goods"
        }
    ],
    "sg:phone":"+1 501 734 4050",
    "sg:postcode":"72113",
    "sg:province":"AR",
    "sg:tags":[
        "grocer"
    ],
    "wof:name":"Belcher's Food Ctr",
    "wof:placetype":"venue"
},
  "geometry": {"coordinates":[-92.418199,34.851941],"type":"Point"}
}