{
  "type": "Feature",
  "properties": {
    "addr:full":"350 Fredonia St Springdale AR 72762",
    "addr:housenumber":"350",
    "addr:postcode":"72762",
    "addr:street":"Fredonia St",
    "iso:country":"US",
    "sg:address":"350 Fredonia St",
    "sg:city":"Springdale",
    "sg:classifiers":[
        {
            "category":"Building & Trades",
            "subcategory":"Electrical",
            "type":"Services"
        },
        {
            "category":"Building & Trades",
            "subcategory":"Construction",
            "type":"Services"
        }
    ],
    "sg:phone":"+1 479 750 1672",
    "sg:postcode":"72762",
    "sg:province":"AR",
    "sg:tags":[
        "electrical",
        "dry wall",
        "contractor"
    ],
    "wof:name":"Craine's Electric & Drywall",
    "wof:placetype":"venue"
},
  "geometry": {"coordinates":[-94.19718899999999,36.205643],"type":"Point"}
}