{
  "type": "Feature",
  "properties": {
    "iso:country":"US",
    "sg:address":"4397 Spring Cliff Loop",
    "sg:city":"Rogers",
    "sg:classifiers":[
        {
            "category":"Professional",
            "type":"Services"
        }
    ],
    "sg:phone":"+1 479 621 0279",
    "sg:postcode":"72756",
    "sg:province":"AR",
    "wof:name":"Robert L Griffith",
    "wof:placetype":"venue"
},
  "geometry": {"coordinates":[-94.127978,36.384087],"type":"Point"}
}