{
  "type": "Feature",
  "properties": {
    "iso:country":"US",
    "sg:address":"5109 Warden Rd",
    "sg:city":"N Little Rock",
    "sg:classifiers":[
        {
            "category":"Retail",
            "subcategory":"Veterinary Services",
            "type":"Services"
        }
    ],
    "sg:phone":"+1 501 812 5678",
    "sg:postcode":"72116",
    "sg:province":"AR",
    "sg:tags":[
        "veterinarian"
    ],
    "wof:name":"Interstate Animal Clinic",
    "wof:placetype":"venue"
},
  "geometry": {"coordinates":[-92.215738,34.800503],"type":"Point"}
}