{
  "type": "Feature",
  "properties": {
    "iso:country":"US",
    "sg:address":"106 Devon Cove",
    "sg:city":"Jacksonville",
    "sg:classifiers":[
        {
            "category":"Building & Trades",
            "subcategory":"Cleaning & Sanitation",
            "type":"Services"
        }
    ],
    "sg:phone":"+1 501 985 0444",
    "sg:postcode":"72076",
    "sg:province":"AR",
    "sg:tags":[
        "janitor"
    ],
    "wof:name":"Awning Cleaners Of Arkansas",
    "wof:placetype":"venue"
},
  "geometry": {"coordinates":[-92.10608999999999,34.873514],"type":"Point"}
}