{
  "type": "Feature",
  "properties": {
    "iso:country":"US",
    "sg:address":"7713 Williamsburg Rd",
    "sg:city":"Fort Smith",
    "sg:classifiers":[
        {
            "category":"Professional",
            "type":"Services"
        }
    ],
    "sg:phone":"+1 479 452 2064",
    "sg:postcode":"72903",
    "sg:province":"AR",
    "wof:name":"H2 Hamm Shutters Inc",
    "wof:placetype":"venue"
},
  "geometry": {"coordinates":[-94.346119,35.355999],"type":"Point"}
}