{
  "type": "Feature",
  "properties": {
    "addr:full":"309 Lookout Pt Hot Springs National Park AR 71913",
    "addr:housenumber":"309",
    "addr:postcode":"71913",
    "addr:street":"Lookout Pt",
    "iso:country":"US",
    "sg:address":"309 Lookout Pt",
    "sg:city":"Hot Springs National Park",
    "sg:classifiers":[
        {
            "category":"Freight",
            "type":"Transportation"
        }
    ],
    "sg:phone":"+1 501 525 9508",
    "sg:postcode":"71913",
    "sg:province":"AR",
    "sg:tags":[
        "general"
    ],
    "wof:name":"Mini Storage",
    "wof:placetype":"venue"
},
  "geometry": {"coordinates":[-93.07764299999999,34.429086],"type":"Point"}
}