{
  "type": "Feature",
  "properties": {
    "iso:country":"US",
    "sg:address":"101 Atlanta St SE",
    "sg:city":"Gravette",
    "sg:classifiers":[
        {
            "category":"Home & Garden",
            "subcategory":"Building Materials",
            "type":"Retail Goods"
        }
    ],
    "sg:phone":"+1 479 787 5923",
    "sg:postcode":"72736",
    "sg:province":"AR",
    "sg:tags":[
        "lumber"
    ],
    "wof:name":"Gravette Building Supl",
    "wof:placetype":"venue"
},
  "geometry": {"coordinates":[-94.453274,36.421445],"type":"Point"}
}