{
  "type": "Feature",
  "properties": {
    "iso:country":"US",
    "sg:address":"704 Bird St",
    "sg:city":"Benton",
    "sg:classifiers":[
        {
            "category":"Real Estate",
            "subcategory":"Real Estate Operator",
            "type":"Services"
        }
    ],
    "sg:phone":"+1 501 860 6117",
    "sg:postcode":"72015",
    "sg:province":"AR",
    "sg:tags":[
        "building",
        "apartment"
    ],
    "wof:name":"Civitan Apartments Inc",
    "wof:placetype":"venue"
},
  "geometry": {"coordinates":[-92.60398,34.558297],"type":"Point"}
}