{
  "type": "Feature",
  "properties": {
    "addr:full":"205 Mockingbird Ln Rison AR 71665",
    "addr:housenumber":"205",
    "addr:postcode":"71665",
    "addr:street":"Mockingbird Ln",
    "iso:country":"US",
    "sg:address":"205 Mockingbird Ln",
    "sg:city":"Rison",
    "sg:classifiers":[
        {
            "category":"Organizations",
            "subcategory":"Community Association",
            "type":"Services"
        }
    ],
    "sg:phone":"+1 870 325 7111",
    "sg:postcode":"71665",
    "sg:province":"AR",
    "sg:tags":[
        "club"
    ],
    "wof:name":"Promise Land Hunting Club",
    "wof:placetype":"venue"
},
  "geometry": {"coordinates":[-92.19650300000001,33.952618],"type":"Point"}
}