{
  "type": "Feature",
  "properties": {
    "iso:country":"US",
    "sg:address":"501 Access Rd",
    "sg:city":"Van Buren",
    "sg:classifiers":[
        {
            "category":"Manufacturing",
            "subcategory":"Signs",
            "type":"Manufacturing & Wholesale Goods"
        }
    ],
    "sg:phone":"+1 479 474 8581",
    "sg:postcode":"72956",
    "sg:province":"AR",
    "wof:name":"Sign Art Advertising",
    "wof:placetype":"venue"
},
  "geometry": {"coordinates":[-94.36891799999999,35.463861],"type":"Point"}
}