{
  "type": "Feature",
  "properties": {
    "addr:full":"701 N Falls Blvd Wynne AR 72396",
    "addr:housenumber":"701",
    "addr:postcode":"72396",
    "addr:street":"N Falls Blvd",
    "iso:country":"US",
    "sg:address":"701 N Falls Blvd",
    "sg:city":"Wynne",
    "sg:classifiers":[
        {
            "category":"Retail",
            "subcategory":"Laundry & Dry Cleaning",
            "type":"Services"
        }
    ],
    "sg:phone":"+1 870 238 8830",
    "sg:postcode":"72396",
    "sg:province":"AR",
    "sg:tags":[
        "cleaners"
    ],
    "wof:name":"Clothesline Cleaners",
    "wof:placetype":"venue"
},
  "geometry": {"coordinates":[-90.78587899999999,35.22806],"type":"Point"}
}