{
  "type": "Feature",
  "properties": {
    "iso:country":"US",
    "sg:address":"1401 Garfield Dr",
    "sg:city":"Little Rock",
    "sg:classifiers":[
        {
            "category":"Professional",
            "subcategory":"Business Services",
            "type":"Services"
        }
    ],
    "sg:phone":"+1 501 615 1090",
    "sg:postcode":"72204",
    "sg:province":"AR",
    "wof:name":"City of Faith Prison",
    "wof:placetype":"venue"
},
  "geometry": {"coordinates":[-92.342633,34.73919],"type":"Point"}
}