{
  "type": "Feature",
  "properties": {
    "iso:country":"US",
    "sg:address":"9718 N Point Rd",
    "sg:city":"Roland",
    "sg:classifiers":[
        {
            "category":"Wholesale",
            "subcategory":"Home Furnishings",
            "type":"Manufacturing & Wholesale Goods"
        }
    ],
    "sg:phone":"+1 501 868 9890",
    "sg:postcode":"72135",
    "sg:province":"AR",
    "sg:tags":[
        "interior",
        "designer",
        "decorator",
        "business"
    ],
    "wof:name":"Karens Custom Windows",
    "wof:placetype":"venue"
},
  "geometry": {"coordinates":[-92.55686799999999,34.832279],"type":"Point"}
}