{
  "type": "Feature",
  "properties": {
    "iso:country":"US",
    "sg:address":"900 S Main St",
    "sg:city":"Bentonville",
    "sg:classifiers":[
        {
            "category":"Building & Trades",
            "subcategory":"Cleaning & Sanitation",
            "type":"Services"
        },
        {
            "category":"Retail",
            "subcategory":"Laundry & Dry Cleaning",
            "type":"Services"
        }
    ],
    "sg:phone":"+1 479 273 5925",
    "sg:postcode":"72712",
    "sg:province":"AR",
    "sg:tags":[
        "cleaners",
        "rug",
        "maintenance",
        "carpet"
    ],
    "wof:name":"Marvin's Carpet Care",
    "wof:placetype":"venue"
},
  "geometry": {"coordinates":[-94.209098,36.363081],"type":"Point"}
}