{
  "type": "Feature",
  "properties": {
    "addr:full":"41 W Cherry St Alma AR 72921",
    "addr:housenumber":"41",
    "addr:postcode":"72921",
    "addr:street":"W Cherry St",
    "iso:country":"US",
    "sg:address":"41 W Cherry St",
    "sg:city":"Alma",
    "sg:classifiers":[
        {
            "category":"Wholesale",
            "subcategory":"Office Equipment",
            "type":"Manufacturing & Wholesale Goods"
        }
    ],
    "sg:phone":"+1 479 986 9888",
    "sg:postcode":"72921",
    "sg:province":"AR",
    "wof:name":"J C R Company",
    "wof:placetype":"venue"
},
  "geometry": {"coordinates":[-94.22262499999999,35.480572],"type":"Point"}
}