{
  "type": "Feature",
  "properties": {
    "addr:full":"200 W Capitol Ave Little Rock AR 72201",
    "addr:housenumber":"200",
    "addr:postcode":"72201",
    "addr:street":"W Capitol Ave",
    "iso:country":"US",
    "sg:address":"200 W Capitol Ave",
    "sg:city":"Little Rock",
    "sg:classifiers":[
        {
            "category":"Professional",
            "subcategory":"Lawyer & Legal Services",
            "type":"Services"
        }
    ],
    "sg:phone":"+1 501 375 2301",
    "sg:postcode":"72201",
    "sg:province":"AR",
    "sg:tags":[
        "attorney"
    ],
    "sg:website":"www.shultslaw.com",
    "wof:name":"Shults Law Firm",
    "wof:placetype":"venue"
},
  "geometry": {"coordinates":[-92.27347899999999,34.744482],"type":"Point"}
}