{
  "type": "Feature",
  "properties": {
    "addr:full":"701 6th St Conway AR 72032",
    "addr:housenumber":"701",
    "addr:postcode":"72032",
    "addr:street":"6Th St",
    "iso:country":"US",
    "sg:address":"701 6th St",
    "sg:city":"Conway",
    "sg:classifiers":[
        {
            "category":"Retail",
            "subcategory":"Auto Repair",
            "type":"Services"
        }
    ],
    "sg:phone":"+1 501 450 7587",
    "sg:postcode":"72032",
    "sg:province":"AR",
    "sg:tags":[
        "replacement",
        "contractor",
        "glass",
        "trade"
    ],
    "wof:name":"Conway Glass Tinting",
    "wof:placetype":"venue"
},
  "geometry": {"coordinates":[-92.43599399999999,35.084488],"type":"Point"}
}