{
  "type": "Feature",
  "properties": {
    "addr:full":"410 N Arkansas Ave Fayetteville AR 72701",
    "addr:housenumber":"410",
    "addr:postcode":"72701",
    "addr:street":"N Arkansas Ave",
    "iso:country":"US",
    "sg:address":"410 N Arkansas Ave",
    "sg:city":"Fayetteville",
    "sg:classifiers":[
        {
            "category":"Health Services",
            "subcategory":"Health Practitioner",
            "type":"Services"
        },
        {
            "category":"Communications",
            "type":"Services"
        }
    ],
    "sg:phone":"+1 479 575 4509",
    "sg:postcode":"72701",
    "sg:province":"AR",
    "sg:tags":[
        "pathologist",
        "speech-language",
        "myofunctional",
        "therapy"
    ],
    "wof:name":"Speech & Hearing Clinic",
    "wof:placetype":"venue"
},
  "geometry": {"coordinates":[-94.168469,36.069318],"type":"Point"}
}