{
  "type": "Feature",
  "properties": {
    "addr:full":"711 Albert Pike Rd Hot Springs AR 71913",
    "addr:housenumber":"711",
    "addr:postcode":"71913",
    "addr:street":"Albert Pike Rd",
    "iso:country":"US",
    "sg:address":"711 Albert Pike Rd",
    "sg:city":"Hot Springs",
    "sg:classifiers":[
        {
            "category":"Health Services",
            "subcategory":"Chiropractor",
            "type":"Services"
        }
    ],
    "sg:phone":"+1 501 623 1255",
    "sg:postcode":"71913",
    "sg:province":"AR",
    "wof:name":"Family Care Chiropractic Ctr",
    "wof:placetype":"venue"
},
  "geometry": {"coordinates":[-93.077067,34.495396],"type":"Point"}
}