{
  "type": "Feature",
  "properties": {
    "iso:country":"US",
    "sg:address":"1113 S Pulaski St",
    "sg:city":"Little Rock",
    "sg:classifiers":[
        {
            "category":"Banks & Credit Unions",
            "subcategory":"Investment Brokerage",
            "type":"Services"
        }
    ],
    "sg:phone":"+1 501 838 9567",
    "sg:postcode":"72202",
    "sg:province":"AR",
    "wof:name":"Blessed Investments",
    "wof:placetype":"venue"
},
  "geometry": {"coordinates":[-92.286631,34.739339],"type":"Point"}
}