{
  "type": "Feature",
  "properties": {
    "addr:full":"1315 W 1st St El Dorado AR 71730",
    "addr:housenumber":"1315",
    "addr:postcode":"71730",
    "addr:street":"W 1St St",
    "iso:country":"US",
    "sg:address":"1315 W 1st St",
    "sg:city":"El Dorado",
    "sg:classifiers":[
        {
            "category":"Real Estate",
            "subcategory":"Real Estate Operator",
            "type":"Services"
        }
    ],
    "sg:phone":"+1 870 862 6061",
    "sg:postcode":"71730",
    "sg:province":"AR",
    "sg:tags":[
        "building",
        "apartment"
    ],
    "wof:name":"Neal Haygood Garden Apartments",
    "wof:placetype":"venue"
},
  "geometry": {"coordinates":[-92.678629,33.206593],"type":"Point"}
}