{
  "type": "Feature",
  "properties": {
    "addr:full":"2407 S Thompson St Springdale AR 72764",
    "addr:housenumber":"2407",
    "addr:postcode":"72764",
    "addr:street":"S Thompson St",
    "iso:country":"US",
    "sg:address":"2407 S Thompson St",
    "sg:city":"Springdale",
    "sg:classifiers":[
        {
            "category":"Home & Garden",
            "subcategory":"Furniture",
            "type":"Retail Goods"
        }
    ],
    "sg:phone":"+1 479 751 6411",
    "sg:postcode":"72764",
    "sg:province":"AR",
    "wof:name":"E Z Credit Furniture",
    "wof:placetype":"venue"
},
  "geometry": {"coordinates":[-94.143629,36.163481],"type":"Point"}
}