{
  "type": "Feature",
  "properties": {
    "iso:country":"US",
    "sg:address":"514 E Russell St",
    "sg:city":"Nashville",
    "sg:classifiers":[
        {
            "category":"Wholesale",
            "subcategory":"Construction Materials",
            "type":"Manufacturing & Wholesale Goods"
        }
    ],
    "sg:phone":"+1 870 845 4365",
    "sg:postcode":"71852",
    "sg:province":"AR",
    "sg:tags":[
        "timberland",
        "company",
        "timber"
    ],
    "wof:name":"Masey Pulpwood Co",
    "wof:placetype":"venue"
},
  "geometry": {"coordinates":[-93.84261600000001,33.934423],"type":"Point"}
}