{
  "type": "Feature",
  "properties": {
    "addr:full":"132 Moseley Ln Conway AR 72032",
    "addr:housenumber":"132",
    "addr:postcode":"72032",
    "addr:street":"Moseley Ln",
    "iso:country":"US",
    "sg:address":"132 Moseley Ln",
    "sg:city":"Conway",
    "sg:classifiers":[
        {
            "category":"Building & Trades",
            "subcategory":"Construction",
            "type":"Services"
        }
    ],
    "sg:phone":"+1 501 993 9040",
    "sg:postcode":"72032",
    "sg:province":"AR",
    "sg:tags":[
        "wallcoverings-installation",
        "wallpaper",
        "painting",
        "contractor"
    ],
    "wof:name":"Baldwin Painting",
    "wof:placetype":"venue"
},
  "geometry": {"coordinates":[-92.36372799999999,35.117025],"type":"Point"}
}