{
  "type": "Feature",
  "properties": {
    "iso:country":"US",
    "sg:address":"8105 Stanton Rd",
    "sg:city":"Little Rock",
    "sg:classifiers":[
        {
            "category":"Social Services",
            "subcategory":"Child Care",
            "type":"Services"
        }
    ],
    "sg:phone":"+1 501 562 3226",
    "sg:postcode":"72209",
    "sg:province":"AR",
    "sg:tags":[
        "day"
    ],
    "wof:name":"Lynn's Wonderland Daycare",
    "wof:placetype":"venue"
},
  "geometry": {"coordinates":[-92.332824,34.674787],"type":"Point"}
}