{
  "type": "Feature",
  "properties": {
    "iso:country":"US",
    "sg:address":"2101 W Main St",
    "sg:city":"Russellville",
    "sg:classifiers":[
        {
            "category":"Health Services",
            "subcategory":"Chiropractor",
            "type":"Services"
        }
    ],
    "sg:phone":"+1 479 968 1181",
    "sg:postcode":"72801",
    "sg:province":"AR",
    "wof:name":"Brown Chiropractic Clinic",
    "wof:placetype":"venue"
},
  "geometry": {"coordinates":[-93.153775,35.284031],"type":"Point"}
}