{
  "type": "Feature",
  "properties": {
    "addr:full":"6 Longview Rd North Little Rock AR 72118",
    "addr:housenumber":"6",
    "addr:postcode":"72118",
    "addr:street":"Longview Rd",
    "iso:country":"US",
    "sg:address":"6 Longview Rd",
    "sg:city":"North Little Rock",
    "sg:classifiers":[
        {
            "category":"Organizations",
            "subcategory":"Religious Organization",
            "type":"Services"
        }
    ],
    "sg:phone":"+1 501 758 8141",
    "sg:postcode":"72118",
    "sg:province":"AR",
    "wof:name":"Liberty Fellowship Ministry",
    "wof:placetype":"venue"
},
  "geometry": {"coordinates":[-92.283331,34.783908],"type":"Point"}
}