{
  "type": "Feature",
  "properties": {
    "iso:country":"US",
    "sg:address":"226 Shady Ln",
    "sg:city":"Concord",
    "sg:classifiers":[
        {
            "category":"Autos & Motor Vehicles",
            "subcategory":"Automobile Sales",
            "type":"Retail Goods"
        }
    ],
    "sg:phone":"+1 870 668 3666",
    "sg:postcode":"72523",
    "sg:province":"AR",
    "sg:tags":[
        "new",
        "car"
    ],
    "wof:name":"Harry Lewis Jr",
    "wof:placetype":"venue"
},
  "geometry": {"coordinates":[-91.862935,35.659172],"type":"Point"}
}