{
  "type": "Feature",
  "properties": {
    "addr:full":"27 Lafayette Dr Stamps AR 71860",
    "addr:housenumber":"27",
    "addr:postcode":"71860",
    "addr:street":"Lafayette Dr Stamps",
    "iso:country":"US",
    "sg:address":"27 Lafayette Dr",
    "sg:city":"Stamps",
    "sg:classifiers":[
        {
            "category":"Farming",
            "subcategory":"Livestock Farm",
            "type":"Manufacturing & Wholesale Goods"
        }
    ],
    "sg:phone":"+1 870 533 2128",
    "sg:postcode":"71860",
    "sg:province":"AR",
    "sg:tags":[
        "specialty",
        "animal"
    ],
    "wof:name":"Honey Rogers Farm",
    "wof:placetype":"venue"
},
  "geometry": {"coordinates":[-93.481872,33.368759],"type":"Point"}
}