{
  "type": "Feature",
  "properties": {
    "addr:full":"502 Richie Rd Cabot AR 72023",
    "addr:housenumber":"502",
    "addr:postcode":"72023",
    "addr:street":"Richie Rd",
    "iso:country":"US",
    "sg:address":"502 Richie Rd",
    "sg:city":"Cabot",
    "sg:classifiers":[
        {
            "category":"Recreation",
            "type":"Entertainment"
        }
    ],
    "sg:phone":"+1 501 843 1225",
    "sg:postcode":"72023",
    "sg:province":"AR",
    "sg:tags":[
        "parks"
    ],
    "wof:name":"Cabot Parks & Rec Activities",
    "wof:placetype":"venue"
},
  "geometry": {"coordinates":[-92.031775,34.968163],"type":"Point"}
}