{
  "type": "Feature",
  "properties": {
    "iso:country":"US",
    "sg:address":"104 1st St",
    "sg:city":"Wickes",
    "sg:classifiers":[
        {
            "category":"Social Services",
            "subcategory":"Child Care",
            "type":"Services"
        }
    ],
    "sg:phone":"+1 870 385 7111",
    "sg:postcode":"71973",
    "sg:province":"AR",
    "sg:tags":[
        "nursery",
        "day"
    ],
    "wof:name":"Wickes Child",
    "wof:placetype":"venue"
},
  "geometry": {"coordinates":[-94.33763999999999,34.304452],"type":"Point"}
}