{
  "type": "Feature",
  "properties": {
    "iso:country":"US",
    "sg:address":"2701 Mockingbird Ln",
    "sg:city":"Paragould",
    "sg:classifiers":[
        {
            "category":"Building & Trades",
            "subcategory":"Construction",
            "type":"Services"
        }
    ],
    "sg:phone":"+1 870 239 0734",
    "sg:postcode":"72450",
    "sg:province":"AR",
    "sg:tags":[
        "contractor"
    ],
    "wof:name":"Randy Lively Siding",
    "wof:placetype":"venue"
},
  "geometry": {"coordinates":[-90.51297,36.027232],"type":"Point"}
}