{
  "type": "Feature",
  "properties": {
    "iso:country":"US",
    "sg:address":"6333 Zinc Rd",
    "sg:city":"Harrison",
    "sg:classifiers":[
        {
            "category":"Organizations",
            "subcategory":"Religious Organization",
            "type":"Services"
        }
    ],
    "sg:phone":"+1 870 427 2819",
    "sg:postcode":"72601",
    "sg:province":"AR",
    "wof:name":"Christian Identity Ministries",
    "wof:placetype":"venue"
},
  "geometry": {"coordinates":[-92.925698,36.291384],"type":"Point"}
}