{
  "type": "Feature",
  "properties": {
    "iso:country":"US",
    "sg:address":"914 S Rogers St",
    "sg:city":"Clarksville",
    "sg:classifiers":[
        {
            "category":"Professional",
            "subcategory":"Employment Agencies",
            "type":"Services"
        }
    ],
    "sg:phone":"+1 479 754 7861",
    "sg:postcode":"72830",
    "sg:province":"AR",
    "sg:tags":[
        "help",
        "supply"
    ],
    "wof:name":"Manpower",
    "wof:placetype":"venue"
},
  "geometry": {"coordinates":[-93.45923000000001,35.46239],"type":"Point"}
}