{
  "type": "Feature",
  "properties": {
    "iso:country":"US",
    "sg:address":"4514 State Hwy 284",
    "sg:city":"Wynne",
    "sg:classifiers":[
        {
            "category":"Government",
            "subcategory":"Office",
            "type":"Public Place"
        }
    ],
    "sg:phone":"+1 870 238 2188",
    "sg:postcode":"72396",
    "sg:province":"AR",
    "sg:tags":[
        "state",
        "park"
    ],
    "wof:name":"Louisiana Purchase State Park",
    "wof:placetype":"venue"
},
  "geometry": {"coordinates":[-90.735035,35.150711],"type":"Point"}
}