{
  "type": "Feature",
  "properties": {
    "iso:country":"US",
    "sg:address":"217 W Chestnut St",
    "sg:city":"Rogers",
    "sg:classifiers":[
        {
            "category":"Social Services",
            "type":"Services"
        }
    ],
    "sg:phone":"+1 479 631 8223",
    "sg:postcode":"72756",
    "sg:province":"AR",
    "sg:tags":[
        "agency",
        "adoption"
    ],
    "wof:name":"American Inc",
    "wof:placetype":"venue"
},
  "geometry": {"coordinates":[-94.11836,36.334311],"type":"Point"}
}