{
  "type": "Feature",
  "properties": {
    "addr:full":"6110 T P White Dr Cabot AR 72023",
    "addr:housenumber":"6110",
    "addr:postcode":"72023",
    "addr:street":"T P White Dr",
    "iso:country":"US",
    "sg:address":"6110 T P White Dr",
    "sg:city":"Cabot",
    "sg:classifiers":[
        {
            "category":"Communications",
            "subcategory":"Radio Station",
            "type":"Services"
        }
    ],
    "sg:phone":"+1 501 982 1160",
    "sg:postcode":"72023",
    "sg:province":"AR",
    "sg:tags":[
        "company",
        "broadcasting"
    ],
    "wof:name":"Little Rock Ar Fam Group",
    "wof:placetype":"venue"
},
  "geometry": {"coordinates":[-92.08167400000001,34.921561],"type":"Point"}
}