{
  "type": "Feature",
  "properties": {
    "iso:country":"US",
    "sg:address":"3016 S University Ave",
    "sg:city":"Little Rock",
    "sg:classifiers":[
        {
            "category":"Personal",
            "subcategory":"Shoe Repair & Shine",
            "type":"Services"
        }
    ],
    "sg:phone":"+1 501 565 6534",
    "sg:postcode":"72204",
    "sg:province":"AR",
    "sg:tags":[
        "repairing",
        "boot"
    ],
    "wof:name":"Rodgers Shoe Svc",
    "wof:placetype":"venue"
},
  "geometry": {"coordinates":[-92.342112,34.72505],"type":"Point"}
}