{
  "type": "Feature",
  "properties": {
    "addr:full":"419 E Main St Prescott AR 71857",
    "addr:housenumber":"419",
    "addr:postcode":"71857",
    "addr:street":"E Main St",
    "iso:country":"US",
    "sg:address":"419 E Main St",
    "sg:city":"Prescott",
    "sg:classifiers":[
        {
            "category":"Social Services",
            "type":"Services"
        }
    ],
    "sg:phone":"+1 870 887 5171",
    "sg:postcode":"71857",
    "sg:province":"AR",
    "sg:tags":[
        "counseling",
        "senior",
        "citizen"
    ],
    "wof:name":"Senior Swadc Citizens Center",
    "wof:placetype":"venue"
},
  "geometry": {"coordinates":[-93.377937,33.799785],"type":"Point"}
}