{
  "type": "Feature",
  "properties": {
    "addr:full":"3300 Pinnacle Hills Pkwy Rogers AR 72758",
    "addr:housenumber":"3300",
    "addr:postcode":"72758",
    "addr:street":"Pinnacle Hills Pkwy",
    "iso:country":"US",
    "sg:address":"3300 Pinnacle Hills Pkwy",
    "sg:city":"Rogers",
    "sg:classifiers":[
        {
            "category":"Restaurant",
            "type":"Food & Drink"
        }
    ],
    "sg:menulink":"http://www.allmenus.com/ar/cave-springs/98336-carrabbas/menu/",
    "sg:phone":"+1 479 273 2962",
    "sg:postcode":"72758",
    "sg:province":"AR",
    "sg:tags":[
        "italian"
    ],
    "wof:name":"Carrabba's",
    "wof:placetype":"venue"
},
  "geometry": {"coordinates":[-94.187011,36.305448],"type":"Point"}
}