{
  "type": "Feature",
  "properties": {
    "iso:country":"US",
    "sg:address":"3713 Macarthur Dr",
    "sg:city":"North Little Rock",
    "sg:classifiers":[
        {
            "category":"Personal",
            "subcategory":"Beauty Salon",
            "type":"Services"
        }
    ],
    "sg:phone":"+1 501 771 7515",
    "sg:postcode":"72118",
    "sg:province":"AR",
    "sg:tags":[
        "shop"
    ],
    "wof:name":"Hair By Emily",
    "wof:placetype":"venue"
},
  "geometry": {"coordinates":[-92.283117,34.789389],"type":"Point"}
}