{
  "type": "Feature",
  "properties": {
    "addr:full":"1480 Salem Rd Benton AR 72019",
    "addr:housenumber":"1480",
    "addr:postcode":"72019",
    "addr:street":"Salem Rd",
    "iso:country":"US",
    "sg:address":"1480 Salem Rd",
    "sg:city":"Benton",
    "sg:classifiers":[
        {
            "category":"Professional",
            "subcategory":"Engineering",
            "type":"Services"
        },
        {
            "category":"Retail",
            "subcategory":"Repair Shop",
            "type":"Services"
        }
    ],
    "sg:phone":"+1 501 794 0652",
    "sg:postcode":"72019",
    "sg:province":"AR",
    "sg:tags":[
        "machines-repair",
        "refrigeration",
        "ice",
        "engineer"
    ],
    "wof:name":"Southwest Ice",
    "wof:placetype":"venue"
},
  "geometry": {"coordinates":[-92.552778,34.628789],"type":"Point"}
}