{
  "type": "Feature",
  "properties": {
    "addr:full":"7878 Highway 1 N Colt AR 72326",
    "addr:housenumber":"7878",
    "addr:postcode":"72326",
    "addr:street":"Highway 1 N",
    "iso:country":"US",
    "sg:address":"7878 Highway 1 N",
    "sg:city":"Colt",
    "sg:classifiers":[
        {
            "category":"Manufacturing",
            "subcategory":"Food",
            "type":"Manufacturing & Wholesale Goods"
        },
        {
            "category":"Wholesale",
            "subcategory":"Groceries",
            "type":"Manufacturing & Wholesale Goods"
        }
    ],
    "sg:phone":"+1 870 630 0914",
    "sg:postcode":"72326",
    "sg:province":"AR",
    "sg:tags":[
        "product",
        "products-wholesale"
    ],
    "wof:name":"S & S Sales Inc",
    "wof:placetype":"venue"
},
  "geometry": {"coordinates":[-90.811668,35.106173],"type":"Point"}
}