{
  "type": "Feature",
  "properties": {
    "iso:country":"US",
    "sg:address":"1421 Military Rd",
    "sg:city":"Benton",
    "sg:classifiers":[
        {
            "category":"Shopping",
            "subcategory":"Books",
            "type":"Retail Goods"
        }
    ],
    "sg:phone":"+1 501 778 5116",
    "sg:postcode":"72015",
    "sg:province":"AR",
    "sg:tags":[
        "dealer"
    ],
    "wof:name":"Hastings Books Music & Video",
    "wof:placetype":"venue"
},
  "geometry": {"coordinates":[-92.57879699999999,34.574776],"type":"Point"}
}