{
  "type": "Feature",
  "properties": {
    "iso:country":"US",
    "sg:address":"2001 S 4th St",
    "sg:city":"Van Buren",
    "sg:classifiers":[
        {
            "category":"Autos & Motor Vehicles",
            "subcategory":"Auto Supplies",
            "type":"Retail Goods"
        },
        {
            "category":"Manufacturing",
            "subcategory":"Tools & Machinery",
            "type":"Manufacturing & Wholesale Goods"
        }
    ],
    "sg:phone":"+1 479 410 4337",
    "sg:postcode":"72956",
    "sg:province":"AR",
    "sg:tags":[
        "filter",
        "gas",
        "mfg"
    ],
    "wof:name":"Air Filter Systems Inc",
    "wof:placetype":"venue"
},
  "geometry": {"coordinates":[-94.33827100000001,35.421594],"type":"Point"}
}