{
  "type": "Feature",
  "properties": {
    "iso:country":"US",
    "sg:address":"110 Broad St",
    "sg:city":"Batesville",
    "sg:classifiers":[
        {
            "category":"Government",
            "subcategory":"Office",
            "type":"Public Place"
        }
    ],
    "sg:phone":"+1 870 793 8823",
    "sg:postcode":"72501",
    "sg:province":"AR",
    "sg:tags":[
        "policy"
    ],
    "wof:name":"Tax Collector",
    "wof:placetype":"venue"
},
  "geometry": {"coordinates":[-91.653155,35.770491],"type":"Point"}
}