{
  "type": "Feature",
  "properties": {
    "iso:country":"US",
    "sg:address":"908 N Main St",
    "sg:city":"Hamburg",
    "sg:classifiers":[
        {
            "category":"Local Transit",
            "type":"Transportation"
        }
    ],
    "sg:phone":"+1 870 853 4800",
    "sg:postcode":"71646",
    "sg:province":"AR",
    "sg:tags":[
        "passenger"
    ],
    "wof:name":"Southark EMS",
    "wof:placetype":"venue"
},
  "geometry": {"coordinates":[-91.79731099999999,33.233313],"type":"Point"}
}