{
  "type": "Feature",
  "properties": {
    "iso:country":"US",
    "sg:address":"600 Hickory St",
    "sg:city":"Crossett",
    "sg:classifiers":[
        {
            "category":"Freight",
            "type":"Transportation"
        }
    ],
    "sg:phone":"+1 870 364 4077",
    "sg:postcode":"71635",
    "sg:province":"AR",
    "sg:tags":[
        "operator",
        "local",
        "trucking"
    ],
    "wof:name":"Brooks Hauling",
    "wof:placetype":"venue"
},
  "geometry": {"coordinates":[-91.95338599999999,33.128831],"type":"Point"}
}