{
  "type": "Feature",
  "properties": {
    "iso:country":"US",
    "sg:address":"3400 SE Macy Rd Ste 30",
    "sg:city":"Bentonville",
    "sg:classifiers":[
        {
            "category":"Health Services",
            "subcategory":"Chiropractor",
            "type":"Services"
        }
    ],
    "sg:phone":"+1 479 273 5855",
    "sg:postcode":"72712",
    "sg:province":"AR",
    "sg:website":"www.bentonvillechiropractic.com",
    "wof:name":"Bentonville Chiropractic",
    "wof:placetype":"venue"
},
  "geometry": {"coordinates":[-94.20907,36.338375],"type":"Point"}
}