{
  "type": "Feature",
  "properties": {
    "iso:country":"US",
    "sg:address":"2008 Wilkins Ave",
    "sg:city":"Jonesboro",
    "sg:classifiers":[
        {
            "category":"Personal",
            "subcategory":"Beauty Salon",
            "type":"Services"
        }
    ],
    "sg:phone":"+1 870 336 1444",
    "sg:postcode":"72401",
    "sg:province":"AR",
    "wof:name":"Follicles",
    "wof:placetype":"venue"
},
  "geometry": {"coordinates":[-90.68213299999999,35.824922],"type":"Point"}
}