{
  "type": "Feature",
  "properties": {
    "iso:country":"US",
    "sg:address":"3678 Ferren Trl",
    "sg:city":"Searcy",
    "sg:classifiers":[
        {
            "category":"Shopping",
            "subcategory":"Used Merchandise",
            "type":"Retail Goods"
        }
    ],
    "sg:phone":"+1 501 368 0130",
    "sg:postcode":"72143",
    "sg:province":"AR",
    "sg:tags":[
        "shop",
        "consignment"
    ],
    "wof:name":"A Rare Find",
    "wof:placetype":"venue"
},
  "geometry": {"coordinates":[-91.684364,35.250596],"type":"Point"}
}