{
  "type": "Feature",
  "properties": {
    "iso:country":"US",
    "sg:address":"220 Cambridge Place Dr",
    "sg:city":"Little Rock",
    "sg:phone":"+1 501 225 4011",
    "sg:postcode":"72227",
    "sg:province":"AR",
    "sg:tags":[
        "farm",
        "wheat",
        "soybean"
    ],
    "wof:name":"Keys Family Ltd Partnership",
    "wof:placetype":"venue"
},
  "geometry": {"coordinates":[-92.389825,34.78434],"type":"Point"}
}