{
  "type": "Feature",
  "properties": {
    "iso:country":"US",
    "sg:address":"1420 N State Line Ave",
    "sg:city":"Texarkana",
    "sg:classifiers":[
        {
            "category":"Shopping",
            "subcategory":"Florist",
            "type":"Retail Goods"
        }
    ],
    "sg:phone":"+1 870 772 4747",
    "sg:postcode":"71854",
    "sg:province":"AR",
    "wof:name":"Benita's Blossoms",
    "wof:placetype":"venue"
},
  "geometry": {"coordinates":[-94.04303299999999,33.437471],"type":"Point"}
}