{
  "type": "Feature",
  "properties": {
    "addr:full":"3041 W 28th Ave Pine Bluff AR 71603",
    "addr:housenumber":"3041",
    "addr:postcode":"71603",
    "addr:street":"W 28Th Ave",
    "iso:country":"US",
    "sg:address":"3041 W 28th Ave",
    "sg:city":"Pine Bluff",
    "sg:classifiers":[
        {
            "category":"Personal",
            "subcategory":"Beauty Salon",
            "type":"Services"
        }
    ],
    "sg:phone":"+1 870 535 4299",
    "sg:postcode":"71603",
    "sg:province":"AR",
    "sg:tags":[
        "shop"
    ],
    "wof:name":"Bobbies Head Quarters Salon",
    "wof:placetype":"venue"
},
  "geometry": {"coordinates":[-92.03557000000001,34.201975],"type":"Point"}
}