{
  "type": "Feature",
  "properties": {
    "iso:country":"US",
    "sg:address":"2410 N Dudney Rd",
    "sg:city":"Magnolia",
    "sg:classifiers":[
        {
            "category":"Restaurant",
            "type":"Food & Drink"
        }
    ],
    "sg:phone":"+1 870 234 1319",
    "sg:postcode":"71753",
    "sg:province":"AR",
    "wof:name":"Ole Feed House",
    "wof:placetype":"venue"
},
  "geometry": {"coordinates":[-93.216177,33.288468],"type":"Point"}
}