{
  "type": "Feature",
  "properties": {
    "iso:country":"US",
    "sg:address":"2707 Browns Ln",
    "sg:city":"Jonesboro",
    "sg:classifiers":[
        {
            "category":"Health Services",
            "subcategory":"Hospital",
            "type":"Services"
        }
    ],
    "sg:phone":"+1 870 972 4976",
    "sg:postcode":"72401",
    "sg:province":"AR",
    "sg:tags":[
        "mental"
    ],
    "wof:name":"Harmony House",
    "wof:placetype":"venue"
},
  "geometry": {"coordinates":[-90.68702399999999,35.812591],"type":"Point"}
}