{
  "type": "Feature",
  "properties": {
    "addr:full":"6201 Batesville Blvd Pleasant Plains AR 72568",
    "addr:housenumber":"6201",
    "addr:postcode":"72568",
    "addr:street":"Batesville Blvd",
    "iso:country":"US",
    "sg:address":"6201 Batesville Blvd",
    "sg:city":"Pleasant Plains",
    "sg:classifiers":[
        {
            "category":"Restaurant",
            "type":"Food & Drink"
        }
    ],
    "sg:phone":"+1 501 345 3474",
    "sg:postcode":"72568",
    "sg:province":"AR",
    "wof:name":"Crick's Country Catfish",
    "wof:placetype":"venue"
},
  "geometry": {"coordinates":[-91.620446,35.572254],"type":"Point"}
}