{
  "type": "Feature",
  "properties": {
    "iso:country":"US",
    "sg:address":"1000 Main St",
    "sg:city":"Little Rock",
    "sg:classifiers":[
        {
            "category":"Autos & Motor Vehicles",
            "subcategory":"Automobile Sales",
            "type":"Retail Goods"
        }
    ],
    "sg:phone":"+1 501 374 4848",
    "sg:postcode":"72202",
    "sg:province":"AR",
    "sg:tags":[
        "car",
        "dealer"
    ],
    "wof:name":"Cook Jeep Chrysler Inc",
    "wof:placetype":"venue"
},
  "geometry": {"coordinates":[-92.27223499999999,34.738353],"type":"Point"}
}