{
  "type": "Feature",
  "properties": {
    "iso:country":"US",
    "sg:address":"2499 Harris Dr",
    "sg:city":"Fayetteville",
    "sg:classifiers":[
        {
            "category":"Freight",
            "type":"Transportation"
        }
    ],
    "sg:phone":"+1 479 442 3487",
    "sg:postcode":"72701",
    "sg:province":"AR",
    "sg:tags":[
        "trucking"
    ],
    "wof:name":"R D Ramey Enterprises",
    "wof:placetype":"venue"
},
  "geometry": {"coordinates":[-94.049865,36.031132],"type":"Point"}
}