{
  "type": "Feature",
  "properties": {
    "iso:country":"US",
    "sg:address":"1305 Arkansas Blvd",
    "sg:city":"Texarkana",
    "sg:classifiers":[
        {
            "category":"Insurance",
            "subcategory":"Insurance Agent",
            "type":"Services"
        }
    ],
    "sg:phone":"+1 870 772 8654",
    "sg:postcode":"71854",
    "sg:province":"TX",
    "wof:name":"S & S Crop Insurance Inc",
    "wof:placetype":"venue"
},
  "geometry": {"coordinates":[-94.028605,33.46084],"type":"Point"}
}