{
  "type": "Feature",
  "properties": {
    "iso:country":"US",
    "sg:address":"2702 Eidson St",
    "sg:city":"Springdale",
    "sg:classifiers":[
        {
            "category":"Airline",
            "type":"Transportation"
        }
    ],
    "sg:phone":"+1 479 750 9191",
    "sg:postcode":"72762",
    "sg:province":"AR",
    "sg:tags":[
        "aircraft-charter",
        "leasing",
        "rental"
    ],
    "sg:website":"http://www.crownaviation.net",
    "wof:name":"Crown Aviation Incorporated",
    "wof:placetype":"venue"
},
  "geometry": {"coordinates":[-94.178917,36.161623],"type":"Point"}
}