{
  "type": "Feature",
  "properties": {
    "iso:country":"US",
    "sg:address":"621 Highway 71 N",
    "sg:city":"Alma",
    "sg:classifiers":[
        {
            "category":"Fast Food",
            "type":"Food & Drink"
        },
        {
            "category":"Restaurant",
            "type":"Food & Drink"
        }
    ],
    "sg:phone":"+1 479 632 2222",
    "sg:postcode":"72921",
    "sg:province":"AR",
    "sg:tags":[
        "pizza",
        "take",
        "italian"
    ],
    "sg:website":"http://www.mazzios.com/",
    "wof:name":"Mazzios Italian Eatery",
    "wof:placetype":"venue"
},
  "geometry": {"coordinates":[-94.226117,35.490493],"type":"Point"}
}