{
  "type": "Feature",
  "properties": {
    "iso:country":"US",
    "sg:address":"8743 Edgemont Rd",
    "sg:city":"Greers Ferry",
    "sg:classifiers":[
        {
            "category":"Education",
            "subcategory":"Library",
            "type":"Public Place"
        }
    ],
    "sg:phone":"+1 501 825 8677",
    "sg:postcode":"72067",
    "sg:province":"AR",
    "wof:name":"Greers Ferry Public Library",
    "wof:placetype":"venue"
},
  "geometry": {"coordinates":[-92.176722,35.580566],"type":"Point"}
}