{
  "type": "Feature",
  "properties": {
    "iso:country":"US",
    "sg:address":"345 Jay St",
    "sg:city":"Benton",
    "sg:classifiers":[
        {
            "category":"Professional",
            "subcategory":"Business Services",
            "type":"Services"
        }
    ],
    "sg:phone":"+1 501 315 0148",
    "sg:postcode":"72015",
    "sg:province":"AR",
    "wof:name":"F & G Enterprises Inc",
    "wof:placetype":"venue"
},
  "geometry": {"coordinates":[-92.63948600000001,34.518031],"type":"Point"}
}