{
  "type": "Feature",
  "properties": {
    "iso:country":"US",
    "sg:address":"491 Hwy 64 E",
    "sg:city":"Conway",
    "sg:classifiers":[
        {
            "category":"Retail",
            "subcategory":"Auto Rental",
            "type":"Services"
        }
    ],
    "sg:phone":"+1 501 336 0187",
    "sg:postcode":"72032",
    "sg:province":"AR",
    "sg:tags":[
        "renting",
        "truck",
        "leasing"
    ],
    "wof:name":"U-Haul Co",
    "wof:placetype":"venue"
},
  "geometry": {"coordinates":[-92.32796500000001,35.083194],"type":"Point"}
}