{
  "type": "Feature",
  "properties": {
    "addr:full":"1421 N Division St Forrest City AR 72335",
    "addr:housenumber":"1421",
    "addr:postcode":"72335",
    "addr:street":"N Division St",
    "iso:country":"US",
    "sg:address":"1421 N Division St",
    "sg:city":"Forrest City",
    "sg:classifiers":[
        {
            "category":"Real Estate",
            "subcategory":"Real Estate Operator",
            "type":"Services"
        }
    ],
    "sg:phone":"+1 870 633 1601",
    "sg:postcode":"72335",
    "sg:province":"AR",
    "sg:tags":[
        "apartment"
    ],
    "wof:name":"Manor House Apartments",
    "wof:placetype":"venue"
},
  "geometry": {"coordinates":[-90.789894,35.022744],"type":"Point"}
}