{
  "type": "Feature",
  "properties": {
    "iso:country":"US",
    "sg:address":"4444 Rushing Rd",
    "sg:city":"Dover",
    "sg:classifiers":[
        {
            "category":"Professional",
            "type":"Services"
        }
    ],
    "sg:phone":"+1 479 331 2758",
    "sg:postcode":"72837",
    "sg:province":"AR",
    "sg:tags":[
        "establishment"
    ],
    "wof:name":"Smart Corp",
    "wof:placetype":"venue"
},
  "geometry": {"coordinates":[-93.188712,35.44657],"type":"Point"}
}