{
  "type": "Feature",
  "properties": {
    "addr:full":"1212 Medallion Dr Jonesboro AR 72404",
    "addr:housenumber":"1212",
    "addr:postcode":"72404",
    "addr:street":"Medallion Dr",
    "iso:country":"US",
    "sg:address":"1212 Medallion Dr",
    "sg:city":"Jonesboro",
    "sg:classifiers":[
        {
            "category":"Professional",
            "subcategory":"Management & Consulting",
            "type":"Services"
        }
    ],
    "sg:phone":"+1 870 972 6619",
    "sg:postcode":"72404",
    "sg:province":"AR",
    "wof:name":"Ch & Assoc LLC",
    "wof:placetype":"venue"
},
  "geometry": {"coordinates":[-90.69204000000001,35.801527],"type":"Point"}
}