{
  "type": "Feature",
  "properties": {
    "iso:country":"US",
    "sg:address":"1309 S Mitchell Ave",
    "sg:city":"Lincoln",
    "sg:classifiers":[
        {
            "category":"Government",
            "subcategory":"Office",
            "type":"Public Place"
        }
    ],
    "sg:phone":"+1 479 824 2585",
    "sg:postcode":"72744",
    "sg:province":"AR",
    "sg:tags":[
        "village"
    ],
    "wof:name":"Lincoln City Waste Water Plant",
    "wof:placetype":"venue"
},
  "geometry": {"coordinates":[-94.421852,35.933384],"type":"Point"}
}