{
  "type": "Feature",
  "properties": {
    "addr:full":"295 School Rd Charlotte AR 72522",
    "addr:housenumber":"295",
    "addr:postcode":"72522",
    "addr:street":"School Rd",
    "iso:country":"US",
    "sg:address":"295 School Rd",
    "sg:city":"Charlotte",
    "sg:classifiers":[
        {
            "category":"Education",
            "subcategory":"School",
            "type":"Public Place"
        }
    ],
    "sg:phone":"+1 870 799 2414",
    "sg:postcode":"72522",
    "sg:province":"AR",
    "wof:name":"Cord Charlotte Pre School",
    "wof:placetype":"venue"
},
  "geometry": {"coordinates":[-91.43887599999999,35.816755],"type":"Point"}
}