{
  "type": "Feature",
  "properties": {
    "iso:country":"US",
    "sg:address":"5949 N US Hwy 61",
    "sg:city":"Blytheville",
    "sg:classifiers":[
        {
            "category":"Home & Garden",
            "subcategory":"Building Materials",
            "type":"Retail Goods"
        }
    ],
    "sg:phone":"+1 870 763 2879",
    "sg:postcode":"72315",
    "sg:province":"AR",
    "sg:tags":[
        "paint"
    ],
    "wof:name":"Parrott's Auto Paint & Supls",
    "wof:placetype":"venue"
},
  "geometry": {"coordinates":[-89.910016,35.967266],"type":"Point"}
}