{
  "type": "Feature",
  "properties": {
    "iso:country":"US",
    "sg:address":"101 W Ash St",
    "sg:city":"Blytheville",
    "sg:classifiers":[
        {
            "category":"Professional",
            "subcategory":"Accounting & Tax Preparation",
            "type":"Services"
        }
    ],
    "sg:phone":"+1 870 763 1355",
    "sg:postcode":"72315",
    "sg:province":"AR",
    "sg:tags":[
        "bookkeeping",
        "return",
        "billing",
        "preparation-business"
    ],
    "wof:name":"Richardson Income Tax Service",
    "wof:placetype":"venue"
},
  "geometry": {"coordinates":[-89.902718,35.926472],"type":"Point"}
}