{
  "type": "Feature",
  "properties": {
    "addr:full":"101 W Ash St Blytheville AR 72315",
    "addr:housenumber":"101",
    "addr:postcode":"72315",
    "addr:street":"W Ash St",
    "iso:country":"US",
    "sg:address":"101 W Ash St",
    "sg:city":"Blytheville",
    "sg:classifiers":[
        {
            "category":"Professional",
            "subcategory":"Accounting & Tax Preparation",
            "type":"Services"
        }
    ],
    "sg:phone":"+1 870 763 1355",
    "sg:postcode":"72315",
    "sg:province":"AR",
    "sg:tags":[
        "bookkeeping",
        "return",
        "billing",
        "preparation-business"
    ],
    "wof:name":"Richardson Income Tax Service",
    "wof:placetype":"venue"
},
  "geometry": {"coordinates":[-89.90271799999999,35.926472],"type":"Point"}
}