{
  "type": "Feature",
  "properties": {
    "iso:country":"US",
    "sg:address":"1700 Celia Rd",
    "sg:city":"Pine Bluff",
    "sg:classifiers":[
        {
            "category":"Freight",
            "type":"Transportation"
        }
    ],
    "sg:phone":"+1 870 536 3461",
    "sg:postcode":"71601",
    "sg:province":"AR",
    "sg:tags":[
        "petroleum",
        "liquid",
        "transport"
    ],
    "wof:name":"Davison Terminal Services",
    "wof:placetype":"venue"
},
  "geometry": {"coordinates":[-91.89564,34.214591],"type":"Point"}
}