{
  "type": "Feature",
  "properties": {
    "iso:country":"US",
    "sg:address":"1404 N College Ave",
    "sg:city":"Fayetteville",
    "sg:classifiers":[
        {
            "category":"Professional",
            "type":"Services"
        }
    ],
    "sg:phone":"+1 479 575 0111",
    "sg:postcode":"72703",
    "sg:province":"AR",
    "sg:tags":[
        "establishment"
    ],
    "wof:name":"Green Door",
    "wof:placetype":"venue"
},
  "geometry": {"coordinates":[-94.156742,36.080005],"type":"Point"}
}