{
  "type": "Feature",
  "properties": {
    "addr:full":"390 E 1st St Emmet AR 71835",
    "addr:housenumber":"390",
    "addr:postcode":"71835",
    "addr:street":"E 1St St",
    "iso:country":"US",
    "sg:address":"390 E 1st St",
    "sg:city":"Emmet",
    "sg:classifiers":[
        {
            "category":"Utilities",
            "subcategory":"Natural Gas",
            "type":"Services"
        }
    ],
    "sg:phone":"+1 870 887 2022",
    "sg:postcode":"71835",
    "sg:province":"AR",
    "sg:tags":[
        "company"
    ],
    "wof:name":"Center Point Engery",
    "wof:placetype":"venue"
},
  "geometry": {"coordinates":[-93.47145999999999,33.729562],"type":"Point"}
}