{
  "type": "Feature",
  "properties": {
    "iso:country":"US",
    "sg:address":"21000 Alpha Way",
    "sg:city":"Mountainburg",
    "sg:classifiers":[
        {
            "category":"Organizations",
            "subcategory":"Religious Organization",
            "type":"Services"
        }
    ],
    "sg:phone":"+1 479 369 2915",
    "sg:postcode":"72946",
    "sg:province":"AR",
    "sg:tags":[
        "church"
    ],
    "wof:name":"Philadelphia Church",
    "wof:placetype":"venue"
},
  "geometry": {"coordinates":[-94.12211499999999,35.731715],"type":"Point"}
}