{
  "type": "Feature",
  "properties": {
    "iso:country":"US",
    "sg:address":"10 Dogwood Ridge",
    "sg:city":"Eureka Springs",
    "sg:classifiers":[
        {
            "category":"Travel",
            "subcategory":"Hotels & Motels",
            "type":"Entertainment"
        }
    ],
    "sg:phone":"+1 479 253 9565",
    "sg:postcode":"72632",
    "sg:province":"AR",
    "sg:tags":[
        "breakfast",
        "accommodation",
        "bed"
    ],
    "wof:name":"Eureka Sunset Bed & Breakfast",
    "wof:placetype":"venue"
},
  "geometry": {"coordinates":[-93.75888999999999,36.405755],"type":"Point"}
}