{
  "type": "Feature",
  "properties": {
    "addr:full":"1801 S 31st St Fort Smith AR 72901",
    "addr:housenumber":"1801",
    "addr:postcode":"72901",
    "addr:street":"S 31St St",
    "iso:country":"US",
    "sg:address":"1801 S 31st St",
    "sg:city":"Fort Smith",
    "sg:classifiers":[
        {
            "category":"Recreation",
            "type":"Entertainment"
        }
    ],
    "sg:phone":"+1 479 785 1044",
    "sg:postcode":"72901",
    "sg:province":"AR",
    "sg:tags":[
        "club",
        "baseball"
    ],
    "wof:name":"Fort Smith Church League",
    "wof:placetype":"venue"
},
  "geometry": {"coordinates":[-94.39945899999999,35.364896],"type":"Point"}
}