{
  "type": "Feature",
  "properties": {
    "iso:country":"US",
    "sg:address":"1900 Louisiana St",
    "sg:city":"Little Rock",
    "sg:classifiers":[
        {
            "category":"Utilities",
            "subcategory":"Electric",
            "type":"Services"
        }
    ],
    "sg:phone":"+1 501 377 4000",
    "sg:postcode":"72206",
    "sg:province":"AR",
    "wof:name":"Entergy",
    "wof:placetype":"venue"
},
  "geometry": {"coordinates":[-92.274926,34.729729],"type":"Point"}
}