{
  "type": "Feature",
  "properties": {
    "iso:country":"US",
    "sg:address":"11006 Hunters Point Rd",
    "sg:city":"Fort Smith",
    "sg:classifiers":[
        {
            "category":"Real Estate",
            "subcategory":"Real Estate Agent",
            "type":"Services"
        }
    ],
    "sg:phone":"+1 479 452 0818",
    "sg:postcode":"72903",
    "sg:province":"AR",
    "wof:name":"Cherie Jones Realty Inc",
    "wof:placetype":"venue"
},
  "geometry": {"coordinates":[-94.309495,35.348103],"type":"Point"}
}