{
  "type": "Feature",
  "properties": {
    "addr:full":"180 Little River 177 Foreman AR 71836",
    "addr:housenumber":"180;177",
    "addr:postcode":"71836",
    "addr:street":"Little River",
    "iso:country":"US",
    "sg:address":"180 Little River 177",
    "sg:city":"Foreman",
    "sg:classifiers":[
        {
            "category":"Farming",
            "subcategory":"Dairy Farm",
            "type":"Manufacturing & Wholesale Goods"
        },
        {
            "category":"Farming",
            "subcategory":"Farm",
            "type":"Manufacturing & Wholesale Goods"
        }
    ],
    "sg:phone":"+1 870 542 7297",
    "sg:postcode":"71836",
    "sg:province":"AR",
    "wof:name":"E F Southerland",
    "wof:placetype":"venue"
},
  "geometry": {"coordinates":[-94.359953,33.696782],"type":"Point"}
}