{
  "type": "Feature",
  "properties": {
    "iso:country":"US",
    "sg:address":"2503 S Elm St",
    "sg:city":"Siloam Springs",
    "sg:classifiers":[
        {
            "category":"Organizations",
            "subcategory":"Religious Organization",
            "type":"Services"
        }
    ],
    "sg:phone":"+1 479 524 4306",
    "sg:postcode":"72761",
    "sg:province":"OK",
    "sg:tags":[
        "church"
    ],
    "sg:website":"www.lds.org",
    "wof:name":"Church Of Jesus Christ Of Lds",
    "wof:placetype":"venue"
},
  "geometry": {"coordinates":[-94.54605599999999,36.165088],"type":"Point"}
}