{
  "type": "Feature",
  "properties": {
    "addr:full":"4721 Grand Ave Fort Smith AR 72904",
    "addr:housenumber":"4721",
    "addr:postcode":"72904",
    "addr:street":"Grand Ave",
    "iso:country":"US",
    "sg:address":"4721 Grand Ave",
    "sg:city":"Fort Smith",
    "sg:classifiers":[
        {
            "category":"Shopping",
            "subcategory":"Bicycles & Sporting Goods",
            "type":"Retail Goods"
        }
    ],
    "sg:phone":"+1 479 782 8844",
    "sg:postcode":"72904",
    "sg:province":"AR",
    "wof:name":"K & L Pawn Guns & Stuff Inc",
    "wof:placetype":"venue"
},
  "geometry": {"coordinates":[-94.379097,35.385545],"type":"Point"}
}