{
  "type": "Feature",
  "properties": {
    "addr:full":"451 N Washington Ave El Dorado AR 71730",
    "addr:housenumber":"451",
    "addr:postcode":"71730",
    "addr:street":"N Washington Ave",
    "iso:country":"US",
    "sg:address":"451 N Washington Ave",
    "sg:city":"El Dorado",
    "sg:classifiers":[
        {
            "category":"Professional",
            "subcategory":"Accounting & Tax Preparation",
            "type":"Services"
        }
    ],
    "sg:phone":"+1 870 862 7936",
    "sg:postcode":"71730",
    "sg:province":"AR",
    "wof:name":"Benny F Cox",
    "wof:placetype":"venue"
},
  "geometry": {"coordinates":[-92.663667,33.214949],"type":"Point"}
}