{
  "type": "Feature",
  "properties": {
    "iso:country":"US",
    "sg:address":"100 Greenwood Ave",
    "sg:city":"Hot Springs National Park",
    "sg:classifiers":[
        {
            "category":"Health Services",
            "subcategory":"Health Practitioner",
            "type":"Services"
        }
    ],
    "sg:phone":"+1 501 622 4663",
    "sg:postcode":"71913",
    "sg:province":"AR",
    "sg:tags":[
        "therapy",
        "physical"
    ],
    "wof:name":"Levi/Sint Jsphs Rhbltation Ctr",
    "wof:placetype":"venue"
},
  "geometry": {"coordinates":[-93.060891,34.494389],"type":"Point"}
}