{
  "type": "Feature",
  "properties": {
    "addr:full":"421 Issac Perkins Blvd Nashville AR 71852",
    "addr:housenumber":"421",
    "addr:postcode":"71852",
    "addr:street":"Issac Perkins Blvd",
    "iso:country":"US",
    "sg:address":"421 Issac Perkins Blvd",
    "sg:city":"Nashville",
    "sg:classifiers":[
        {
            "category":"Shopping",
            "subcategory":"Discount & Variety Stores",
            "type":"Retail Goods"
        }
    ],
    "sg:phone":"+1 870 845 2305",
    "sg:postcode":"71852",
    "sg:province":"AR",
    "wof:name":"Dollar General",
    "wof:placetype":"venue"
},
  "geometry": {"coordinates":[-93.84361699999999,33.948012],"type":"Point"}
}