{
  "type": "Feature",
  "properties": {
    "addr:full":"2414 W Center St Beebe AR 72012",
    "addr:housenumber":"2414",
    "addr:postcode":"72012",
    "addr:street":"W Center St",
    "iso:country":"US",
    "sg:address":"2414 W Center St",
    "sg:city":"Beebe",
    "sg:classifiers":[
        {
            "category":"Shopping",
            "subcategory":"Books",
            "type":"Retail Goods"
        }
    ],
    "sg:phone":"+1 501 882 0055",
    "sg:postcode":"72012",
    "sg:province":"AR",
    "sg:tags":[
        "store"
    ],
    "wof:name":"Text Book Corner",
    "wof:placetype":"venue"
},
  "geometry": {"coordinates":[-91.91121800000001,35.069019],"type":"Point"}
}