{
  "type": "Feature",
  "properties": {
    "iso:country":"US",
    "sg:address":"325 W Shelton St",
    "sg:city":"Monticello",
    "sg:classifiers":[
        {
            "category":"Health Services",
            "subcategory":"Hospital",
            "type":"Services"
        }
    ],
    "sg:phone":"+1 870 367 7384",
    "sg:postcode":"71655",
    "sg:province":"AR",
    "sg:tags":[
        "ambulance"
    ],
    "wof:name":"Monticello Ambulance Service",
    "wof:placetype":"venue"
},
  "geometry": {"coordinates":[-91.79490699999999,33.627716],"type":"Point"}
}