{
  "type": "Feature",
  "properties": {
    "addr:full":"3049 E Robinson Ave Springdale AR 72764",
    "addr:housenumber":"3049",
    "addr:postcode":"72764",
    "addr:street":"E Robinson Ave",
    "iso:country":"US",
    "sg:address":"3049 E Robinson Ave",
    "sg:city":"Springdale",
    "sg:classifiers":[
        {
            "category":"Personal",
            "subcategory":"Barber",
            "type":"Services"
        }
    ],
    "sg:phone":"+1 479 751 8558",
    "sg:postcode":"72764",
    "sg:province":"AR",
    "wof:name":"Meeker Barber Ctr",
    "wof:placetype":"venue"
},
  "geometry": {"coordinates":[-94.094796,36.166316],"type":"Point"}
}