{
  "type": "Feature",
  "properties": {
    "iso:country":"US",
    "sg:address":"1207 NW 9th St",
    "sg:city":"Bentonville",
    "sg:classifiers":[
        {
            "category":"Professional",
            "subcategory":"Business Services",
            "type":"Services"
        }
    ],
    "sg:phone":"+1 479 464 7222",
    "sg:postcode":"72712",
    "sg:province":"AR",
    "sg:tags":[
        "organizing",
        "services-household"
    ],
    "wof:name":"Byland Management",
    "wof:placetype":"venue"
},
  "geometry": {"coordinates":[-94.225081,36.381814],"type":"Point"}
}