{
  "type": "Feature",
  "properties": {
    "addr:full":"722 Circle Dr Berryville AR 72616",
    "addr:housenumber":"722",
    "addr:postcode":"72616",
    "addr:street":"Circle Dr",
    "iso:country":"US",
    "sg:address":"722 Circle Dr",
    "sg:city":"Berryville",
    "sg:classifiers":[
        {
            "category":"Health Services",
            "subcategory":"Doctor",
            "type":"Services"
        }
    ],
    "sg:phone":"+1 870 423 4435",
    "sg:postcode":"72616",
    "sg:province":"AR",
    "sg:tags":[
        "physician",
        "surgeon"
    ],
    "wof:name":"Ozark Orthopedic Assoc",
    "wof:placetype":"venue"
},
  "geometry": {"coordinates":[-93.56155699999999,36.357051],"type":"Point"}
}