{
  "type": "Feature",
  "properties": {
    "iso:country":"US",
    "sg:address":"300 Highway 71 S",
    "sg:city":"Mena",
    "sg:classifiers":[
        {
            "category":"Banks & Credit Unions",
            "subcategory":"Bank",
            "type":"Services"
        }
    ],
    "sg:phone":"+1 479 394 5161",
    "sg:postcode":"71953",
    "sg:province":"AR",
    "sg:tags":[
        "saving",
        "commercial"
    ],
    "wof:name":"Chambers Bank",
    "wof:placetype":"venue"
},
  "geometry": {"coordinates":[-94.233377,34.584263],"type":"Point"}
}