{
  "type": "Feature",
  "properties": {
    "iso:country":"US",
    "sg:address":"14124 Helenwood Dr",
    "sg:city":"North Little Rock",
    "sg:classifiers":[
        {
            "category":"Personal",
            "type":"Services"
        }
    ],
    "sg:phone":"+1 501 803 9048",
    "sg:postcode":"72118",
    "sg:province":"AR",
    "wof:name":"Ultimate Tan",
    "wof:placetype":"venue"
},
  "geometry": {"coordinates":[-92.32134600000001,34.876115],"type":"Point"}
}