{
  "type": "Feature",
  "properties": {
    "iso:country":"US",
    "sg:address":"310 N 13th St",
    "sg:city":"Rogers",
    "sg:classifiers":[
        {
            "category":"Insurance",
            "subcategory":"Health Insurance",
            "type":"Services"
        },
        {
            "category":"Food & Beverages",
            "subcategory":"Groceries & Convenience Stores",
            "type":"Retail Goods"
        }
    ],
    "sg:phone":"+1 479 636 7331",
    "sg:postcode":"72756",
    "sg:province":"AR",
    "sg:tags":[
        "market"
    ],
    "wof:name":"Rogers Health Food Store",
    "wof:placetype":"venue"
},
  "geometry": {"coordinates":[-94.133904,36.336399],"type":"Point"}
}