{
  "type": "Feature",
  "properties": {
    "addr:full":"117 Hempstead 349 Rd Nashville AR 71852",
    "addr:housenumber":"117;349",
    "addr:postcode":"71852",
    "addr:street":"Hempstead;Rd",
    "iso:country":"US",
    "sg:address":"117 Hempstead 349 Rd",
    "sg:city":"Nashville",
    "sg:classifiers":[
        {
            "category":"Farming",
            "subcategory":"Farm",
            "type":"Manufacturing & Wholesale Goods"
        }
    ],
    "sg:phone":"+1 870 845 5645",
    "sg:postcode":"71852",
    "sg:province":"AR",
    "wof:name":"Chad's Family Farm",
    "wof:placetype":"venue"
},
  "geometry": {"coordinates":[-93.78249099999999,33.967425],"type":"Point"}
}