{
  "type": "Feature",
  "properties": {
    "iso:country":"US",
    "sg:address":"2303 Old Smackover Rd SE",
    "sg:city":"Camden",
    "sg:classifiers":[
        {
            "category":"Home & Garden",
            "subcategory":"Building Materials",
            "type":"Retail Goods"
        }
    ],
    "sg:phone":"+1 870 231 9772",
    "sg:postcode":"71701",
    "sg:province":"AR",
    "wof:name":"Gross & Janes Co",
    "wof:placetype":"venue"
},
  "geometry": {"coordinates":[-92.823812,33.54142],"type":"Point"}
}