{
  "type": "Feature",
  "properties": {
    "addr:full":"10320 Stagecoach Rd Little Rock AR 72210",
    "addr:housenumber":"10320",
    "addr:postcode":"72210",
    "addr:street":"Stagecoach Rd",
    "iso:country":"US",
    "sg:address":"10320 Stagecoach Rd",
    "sg:city":"Little Rock",
    "sg:classifiers":[
        {
            "category":"Restaurant",
            "type":"Food & Drink"
        }
    ],
    "sg:menulink":"http://www.allmenus.com/ar/little-rock/66671-pizza-pro/menu/",
    "sg:phone":"+1 501 455 8070",
    "sg:postcode":"72210",
    "sg:province":"AR",
    "sg:tags":[
        "american",
        "pizza"
    ],
    "wof:name":"Pizza Pro",
    "wof:placetype":"venue"
},
  "geometry": {"coordinates":[-92.427576,34.65766],"type":"Point"}
}