{
  "type": "Feature",
  "properties": {
    "iso:country":"US",
    "sg:address":"2923 Lakewood Village Dr",
    "sg:city":"N Little Rock",
    "sg:classifiers":[
        {
            "category":"Shopping",
            "subcategory":"Discount & Variety Stores",
            "type":"Retail Goods"
        }
    ],
    "sg:phone":"+1 501 975 5454",
    "sg:postcode":"72116",
    "sg:province":"AR",
    "sg:tags":[
        "merchandise",
        "general"
    ],
    "wof:name":"Dollar Store Express",
    "wof:placetype":"venue"
},
  "geometry": {"coordinates":[-92.232028,34.796984],"type":"Point"}
}