{
  "type": "Feature",
  "properties": {
    "iso:country":"US",
    "sg:address":"101 Main St",
    "sg:city":"Wickes",
    "sg:classifiers":[
        {
            "category":"Recreation",
            "type":"Entertainment"
        }
    ],
    "sg:phone":"+1 870 385 2255",
    "sg:postcode":"71973",
    "sg:province":"AR",
    "sg:tags":[
        "concessionaire"
    ],
    "wof:name":"John Bell Concessions & Empor",
    "wof:placetype":"venue"
},
  "geometry": {"coordinates":[-94.336988,34.301898],"type":"Point"}
}