{
  "type": "Feature",
  "properties": {
    "addr:full":"706 W Michigan St Stuttgart AR 72160",
    "addr:housenumber":"706",
    "addr:postcode":"72160",
    "addr:street":"W Michigan St",
    "iso:country":"US",
    "sg:address":"706 W Michigan St",
    "sg:city":"Stuttgart",
    "sg:classifiers":[
        {
            "category":"Restaurant",
            "type":"Food & Drink"
        }
    ],
    "sg:menulink":"http://www.allmenus.com/ar/gum-pond/153579-western-sizzlin/menu/",
    "sg:phone":"+1 870 673 1893",
    "sg:postcode":"72160",
    "sg:province":"AR",
    "sg:tags":[
        "american",
        "steakhouse"
    ],
    "wof:name":"Western Sizzlin",
    "wof:placetype":"venue"
},
  "geometry": {"coordinates":[-91.558987,34.509555],"type":"Point"}
}