{
  "type": "Feature",
  "properties": {
    "addr:full":"208 Scott St Ward AR 72176",
    "addr:housenumber":"208",
    "addr:postcode":"72176",
    "addr:street":"Scott St",
    "iso:country":"US",
    "sg:address":"208 Scott St",
    "sg:city":"Ward",
    "sg:classifiers":[
        {
            "category":"Place Of Worship",
            "subcategory":"Church",
            "type":"Public Place"
        },
        {
            "category":"Place Of Worship",
            "type":"Public Place"
        }
    ],
    "sg:phone":"+1 501 843 5648",
    "sg:postcode":"72176",
    "sg:province":"AR",
    "sg:tags":[
        "churches-baptist-general",
        "churches-baptist"
    ],
    "sg:website":"http://www.abc-usa.org",
    "wof:name":"First Baptist Church",
    "wof:placetype":"venue"
},
  "geometry": {"coordinates":[-91.94893,35.028144],"type":"Point"}
}