{
  "type": "Feature",
  "properties": {
    "iso:country":"US",
    "sg:address":"1701 Phyllis St",
    "sg:city":"Bentonville",
    "sg:classifiers":[
        {
            "category":"Wholesale",
            "subcategory":"Groceries",
            "type":"Manufacturing & Wholesale Goods"
        }
    ],
    "sg:phone":"+1 479 464 7669",
    "sg:postcode":"72712",
    "sg:province":"AR",
    "sg:tags":[
        "food",
        "broker"
    ],
    "wof:name":"Acosta Sales",
    "wof:placetype":"venue"
},
  "geometry": {"coordinates":[-94.17984,36.35843],"type":"Point"}
}