{
  "type": "Feature",
  "properties": {
    "iso:country":"US",
    "sg:address":"220 W Commercial St",
    "sg:city":"Ozark",
    "sg:classifiers":[
        {
            "category":"Professional",
            "subcategory":"Lawyer & Legal Services",
            "type":"Services"
        }
    ],
    "sg:phone":"+1 479 667 5591",
    "sg:postcode":"72949",
    "sg:province":"AR",
    "sg:tags":[
        "attorney"
    ],
    "wof:name":"Franklin County Attorney",
    "wof:placetype":"venue"
},
  "geometry": {"coordinates":[-93.827026,35.486948],"type":"Point"}
}