{
  "type": "Feature",
  "properties": {
    "addr:full":"1115 E Huntington Dr Fayetteville AR 72701",
    "addr:housenumber":"1115",
    "addr:postcode":"72701",
    "addr:street":"E Huntington Dr",
    "iso:country":"US",
    "sg:address":"1115 E Huntington Dr",
    "sg:city":"Fayetteville",
    "sg:classifiers":[
        {
            "category":"Wholesale",
            "subcategory":"Office Equipment",
            "type":"Manufacturing & Wholesale Goods"
        },
        {
            "category":"Shopping",
            "subcategory":"Computers & Home Electronics",
            "type":"Retail Goods"
        }
    ],
    "sg:phone":"+1 479 521 9204",
    "sg:postcode":"72701",
    "sg:province":"AR",
    "sg:tags":[
        "scanning",
        "printer",
        "plotting",
        "supply"
    ],
    "wof:name":"Kopies Plus",
    "wof:placetype":"venue"
},
  "geometry": {"coordinates":[-94.108689,36.082336],"type":"Point"}
}