{
  "type": "Feature",
  "properties": {
    "iso:country":"US",
    "sg:address":"1114 Poplar Pl",
    "sg:city":"Rogers",
    "sg:classifiers":[
        {
            "category":"Health Services",
            "subcategory":"Doctor",
            "type":"Services"
        }
    ],
    "sg:phone":"+1 479 636 9235",
    "sg:postcode":"72756",
    "sg:province":"AR",
    "sg:tags":[
        "clinic"
    ],
    "wof:name":"Tree Of Life Family Health Ctr",
    "wof:placetype":"venue"
},
  "geometry": {"coordinates":[-94.130754,36.331443],"type":"Point"}
}