{
  "type": "Feature",
  "properties": {
    "addr:full":"19 N 5th St Fort Smith AR 72901",
    "addr:housenumber":"19",
    "addr:postcode":"72901",
    "addr:street":"N 5Th St",
    "iso:country":"US",
    "sg:address":"19 N 5th St",
    "sg:city":"Fort Smith",
    "sg:classifiers":[
        {
            "category":"Retail",
            "subcategory":"Laundry & Dry Cleaning",
            "type":"Services"
        }
    ],
    "sg:phone":"+1 479 783 3409",
    "sg:postcode":"72901",
    "sg:province":"AR",
    "sg:tags":[
        "launderers",
        "industrial",
        "rental",
        "linen",
        "supply"
    ],
    "wof:name":"Fort Smith Linen & Indus Svc",
    "wof:placetype":"venue"
},
  "geometry": {"coordinates":[-94.42555299999999,35.388589],"type":"Point"}
}