{
  "type": "Feature",
  "properties": {
    "iso:country":"US",
    "sg:address":"1500 W Dewitt Henry Dr",
    "sg:city":"Beebe",
    "sg:classifiers":[
        {
            "category":"Manufacturing",
            "subcategory":"Metals",
            "type":"Manufacturing & Wholesale Goods"
        },
        {
            "category":"Building & Trades",
            "subcategory":"Construction",
            "type":"Services"
        }
    ],
    "sg:phone":"+1 501 882 6313",
    "sg:postcode":"72012",
    "sg:province":"AR",
    "sg:tags":[
        "prefabricated",
        "contractor",
        "mfg"
    ],
    "sg:website":"www.a-s.com",
    "wof:name":"A & S Building Systems LP",
    "wof:placetype":"venue"
},
  "geometry": {"coordinates":[-91.90054,35.074352],"type":"Point"}
}