{
  "type": "Feature",
  "properties": {
    "addr:full":"1500 W Dewitt Henry Dr Beebe AR 72012",
    "addr:housenumber":"1500",
    "addr:postcode":"72012",
    "addr:street":"W;Henry Dr",
    "iso:country":"US",
    "sg:address":"1500 W Dewitt Henry Dr",
    "sg:city":"Beebe",
    "sg:classifiers":[
        {
            "category":"Manufacturing",
            "subcategory":"Metals",
            "type":"Manufacturing & Wholesale Goods"
        },
        {
            "category":"Building & Trades",
            "subcategory":"Construction",
            "type":"Services"
        }
    ],
    "sg:phone":"+1 501 882 6313",
    "sg:postcode":"72012",
    "sg:province":"AR",
    "sg:tags":[
        "prefabricated",
        "contractor",
        "mfg"
    ],
    "sg:website":"www.a-s.com",
    "wof:name":"A & S Building Systems LP",
    "wof:placetype":"venue"
},
  "geometry": {"coordinates":[-91.90054000000001,35.074352],"type":"Point"}
}