{
  "type": "Feature",
  "properties": {
    "iso:country":"US",
    "sg:address":"817 W 23rd St",
    "sg:city":"North Little Rock",
    "sg:classifiers":[
        {
            "category":"Shopping",
            "subcategory":"Bicycles & Sporting Goods",
            "type":"Retail Goods"
        }
    ],
    "sg:phone":"+1 501 812 6308",
    "sg:postcode":"72114",
    "sg:province":"AR",
    "sg:tags":[
        "hunting",
        "accessory"
    ],
    "wof:name":"Aquasource of Arkansas",
    "wof:placetype":"venue"
},
  "geometry": {"coordinates":[-92.275426,34.776834],"type":"Point"}
}