{
  "type": "Feature",
  "properties": {
    "iso:country":"US",
    "sg:address":"2888 Hwy 70 E",
    "sg:city":"Lonoke",
    "sg:classifiers":[
        {
            "category":"Utilities",
            "subcategory":"Fuel Oil & Lpg",
            "type":"Services"
        }
    ],
    "sg:phone":"+1 501 676 6513",
    "sg:postcode":"72086",
    "sg:province":"AR",
    "sg:tags":[
        "propane",
        "gas"
    ],
    "wof:name":"Ferrellgas",
    "wof:placetype":"venue"
},
  "geometry": {"coordinates":[-91.85413800000001,34.783199],"type":"Point"}
}