{
  "type": "Feature",
  "properties": {
    "iso:country":"US",
    "sg:address":"510 E College St",
    "sg:city":"Batesville",
    "sg:classifiers":[
        {
            "category":"Insurance",
            "subcategory":"Hazard Insurance",
            "type":"Services"
        }
    ],
    "sg:phone":"+1 870 698 9420",
    "sg:postcode":"72501",
    "sg:province":"AR",
    "sg:tags":[
        "commercial",
        "business"
    ],
    "sg:website":"http://www.citizensfidelityinsurance.com",
    "wof:name":"Citizens Fidelity Insurance Company",
    "wof:placetype":"venue"
},
  "geometry": {"coordinates":[-91.649451,35.771443],"type":"Point"}
}