{
  "type": "Feature",
  "properties": {
    "iso:country":"US",
    "sg:address":"3 Sharondale Ct",
    "sg:city":"Maumelle",
    "sg:classifiers":[
        {
            "category":"Manufacturing",
            "subcategory":"Musical Instruments",
            "type":"Manufacturing & Wholesale Goods"
        }
    ],
    "sg:phone":"+1 501 851 0144",
    "sg:postcode":"72113",
    "sg:province":"AR",
    "sg:tags":[
        "instruments-industrial-repairing"
    ],
    "wof:name":"T & M Enterprises",
    "wof:placetype":"venue"
},
  "geometry": {"coordinates":[-92.406675,34.841208],"type":"Point"}
}