{
  "type": "Feature",
  "properties": {
    "addr:full":"5954 State Hwy 29 Blevins AR 71825",
    "addr:housenumber":"5954",
    "addr:postcode":"71825",
    "addr:street":"State Hwy 29 Blevins",
    "iso:country":"US",
    "sg:address":"5954 State Hwy 29",
    "sg:city":"Blevins",
    "sg:classifiers":[
        {
            "category":"Education",
            "subcategory":"School",
            "type":"Public Place"
        }
    ],
    "sg:phone":"+1 870 874 2281",
    "sg:postcode":"71825",
    "sg:province":"AR",
    "sg:website":"www.hornet.com",
    "wof:name":"Blevins High School",
    "wof:placetype":"venue"
},
  "geometry": {"coordinates":[-93.571309,33.877133],"type":"Point"}
}