{
  "type": "Feature",
  "properties": {
    "iso:country":"US",
    "sg:address":"301 Stearns Pt",
    "sg:city":"Hot Springs National Park",
    "sg:classifiers":[
        {
            "category":"Travel",
            "subcategory":"Hotels & Motels",
            "type":"Entertainment"
        }
    ],
    "sg:phone":"+1 501 760 1341",
    "sg:postcode":"71913",
    "sg:province":"AR",
    "sg:tags":[
        "operation"
    ],
    "wof:name":"Lady of Lake",
    "wof:placetype":"venue"
},
  "geometry": {"coordinates":[-93.123772,34.479583],"type":"Point"}
}