{
  "type": "Feature",
  "properties": {
    "iso:country":"US",
    "sg:address":"1512 Dewey Ave",
    "sg:city":"Newport",
    "sg:classifiers":[
        {
            "category":"Food & Beverages",
            "subcategory":"Groceries & Convenience Stores",
            "type":"Retail Goods"
        }
    ],
    "sg:phone":"+1 870 217 0070",
    "sg:postcode":"72112",
    "sg:province":"AR",
    "wof:name":"CCW Snack Shop",
    "wof:placetype":"venue"
},
  "geometry": {"coordinates":[-91.291182,35.599623],"type":"Point"}
}