{
  "type": "Feature",
  "properties": {
    "iso:country":"US",
    "sg:address":"303 Main Ave",
    "sg:city":"Dierks",
    "sg:classifiers":[
        {
            "category":"Personal",
            "subcategory":"Barber",
            "type":"Services"
        }
    ],
    "sg:phone":"+1 870 286 5697",
    "sg:postcode":"71833",
    "sg:province":"AR",
    "wof:name":"Cuts Of Joy",
    "wof:placetype":"venue"
},
  "geometry": {"coordinates":[-94.01695599999999,34.120285],"type":"Point"}
}