{
  "type": "Feature",
  "properties": {
    "iso:country":"US",
    "sg:address":"3109 State Hwy 25 B N",
    "sg:city":"Heber Springs",
    "sg:classifiers":[
        {
            "category":"Shopping",
            "subcategory":"Used Merchandise",
            "type":"Retail Goods"
        }
    ],
    "sg:phone":"+1 501 206 8076",
    "sg:postcode":"72543",
    "sg:province":"AR",
    "sg:tags":[
        "shop",
        "consignment"
    ],
    "wof:name":"Good Deals Consignment",
    "wof:placetype":"venue"
},
  "geometry": {"coordinates":[-92.018455,35.516064],"type":"Point"}
}