{
  "type": "Feature",
  "properties": {
    "iso:country":"US",
    "sg:address":"506 Main St",
    "sg:city":"Van Buren",
    "sg:classifiers":[
        {
            "category":"Shopping",
            "subcategory":"Hobbies, Toys, & Games",
            "type":"Retail Goods"
        }
    ],
    "sg:phone":"+1 479 474 2368",
    "sg:postcode":"72956",
    "sg:province":"AR",
    "sg:tags":[
        "craft",
        "supply"
    ],
    "wof:name":"Art Treasures",
    "wof:placetype":"venue"
},
  "geometry": {"coordinates":[-94.354097,35.435533],"type":"Point"}
}