{
  "type": "Feature",
  "properties": {
    "addr:full":"206 N 2nd St Blytheville AR 72315",
    "addr:housenumber":"206",
    "addr:postcode":"72315",
    "addr:street":"N 2Nd St",
    "iso:country":"US",
    "sg:address":"206 N 2nd St",
    "sg:city":"Blytheville",
    "sg:classifiers":[
        {
            "category":"Banks & Credit Unions",
            "subcategory":"Investment Brokerage",
            "type":"Services"
        }
    ],
    "sg:phone":"+1 870 838 0001",
    "sg:postcode":"72315",
    "sg:province":"AR",
    "sg:tags":[
        "security"
    ],
    "wof:name":"A G Edwards & Sons Inc",
    "wof:placetype":"venue"
},
  "geometry": {"coordinates":[-89.904149,35.929154],"type":"Point"}
}