{
  "type": "Feature",
  "properties": {
    "addr:full":"530 Madison St Springdale OK 72761",
    "addr:housenumber":"530",
    "addr:postcode":"72761",
    "addr:street":"Madison St",
    "iso:country":"US",
    "sg:address":"530 Madison St",
    "sg:city":"Springdale",
    "sg:classifiers":[
        {
            "category":"Building & Trades",
            "subcategory":"Construction",
            "type":"Services"
        }
    ],
    "sg:phone":"+1 479 756 9999",
    "sg:postcode":"72761",
    "sg:province":"OK",
    "sg:tags":[
        "concrete",
        "contractor"
    ],
    "wof:name":"Bowman Concrete Curbing Inc",
    "wof:placetype":"venue"
},
  "geometry": {"coordinates":[-94.539058,36.189457],"type":"Point"}
}