{
  "type": "Feature",
  "properties": {
    "iso:country":"US",
    "sg:address":"1300 Ouachita 4",
    "sg:city":"Camden",
    "sg:classifiers":[
        {
            "category":"Restaurant",
            "type":"Food & Drink"
        }
    ],
    "sg:menulink":"http://www.allmenus.com/ar/jefferson/159767-arbys/menu/",
    "sg:phone":"+1 318 371 3796",
    "sg:postcode":"71701",
    "sg:province":"AR",
    "sg:tags":[
        "burger",
        "american"
    ],
    "wof:name":"Arby's",
    "wof:placetype":"venue"
},
  "geometry": {"coordinates":[-93.00964399999999,33.530445],"type":"Point"}
}