{
  "type": "Feature",
  "properties": {
    "iso:country":"US",
    "sg:address":"5 Natchez Ln",
    "sg:city":"Alexander",
    "sg:classifiers":[
        {
            "category":"Shopping",
            "subcategory":"Clothing, Apparel, & Fashions",
            "type":"Retail Goods"
        }
    ],
    "sg:phone":"+1 501 776 2920",
    "sg:postcode":"72002",
    "sg:province":"AR",
    "sg:tags":[
        "clothing",
        "boys'"
    ],
    "wof:name":"Military Surplus",
    "wof:placetype":"venue"
},
  "geometry": {"coordinates":[-92.432457,34.636581],"type":"Point"}
}