{
  "type": "Feature",
  "properties": {
    "addr:full":"30 Maumelle Curve Ct N Little Rock AR 72113",
    "addr:housenumber":"30",
    "addr:postcode":"72113",
    "addr:street":"Maumelle Curve Ct N",
    "iso:country":"US",
    "sg:address":"30 Maumelle Curve Ct",
    "sg:city":"N Little Rock",
    "sg:classifiers":[
        {
            "category":"Manufacturing",
            "subcategory":"Glass & Minerals",
            "type":"Manufacturing & Wholesale Goods"
        }
    ],
    "sg:phone":"+1 501 758 8641",
    "sg:postcode":"72113",
    "sg:province":"AR",
    "wof:name":"Soos Stained Glass Inc",
    "wof:placetype":"venue"
},
  "geometry": {"coordinates":[-92.375101,34.825373],"type":"Point"}
}