{
  "type": "Feature",
  "properties": {
    "iso:country":"US",
    "sg:address":"4703 Hwy 60",
    "sg:city":"Van Buren",
    "sg:classifiers":[
        {
            "category":"Freight",
            "type":"Transportation"
        }
    ],
    "sg:phone":"+1 479 410 2411",
    "sg:postcode":"72956",
    "sg:province":"AR",
    "sg:tags":[
        "arrangement"
    ],
    "wof:name":"CSC Enterprises Inc",
    "wof:placetype":"venue"
},
  "geometry": {"coordinates":[-94.29778,35.468448],"type":"Point"}
}