{
  "type": "Feature",
  "properties": {
    "iso:country":"US",
    "sg:address":"1023 N 15th St",
    "sg:city":"Arkadelphia",
    "sg:classifiers":[
        {
            "category":"Shopping",
            "subcategory":"Catalog Store",
            "type":"Retail Goods"
        }
    ],
    "sg:phone":"+1 870 246 9243",
    "sg:postcode":"71923",
    "sg:province":"AR",
    "sg:tags":[
        "mail",
        "house"
    ],
    "wof:name":"Ricky Green Intl Outdoor Adven",
    "wof:placetype":"venue"
},
  "geometry": {"coordinates":[-93.065145,34.132081],"type":"Point"}
}