{
  "type": "Feature",
  "properties": {
    "iso:country":"US",
    "sg:address":"26715 Neighborhood Dr",
    "sg:city":"Hensley",
    "sg:classifiers":[
        {
            "category":"Arts & Performance",
            "subcategory":"Theater",
            "type":"Entertainment"
        }
    ],
    "sg:phone":"+1 501 888 4788",
    "sg:postcode":"72065",
    "sg:province":"AR",
    "sg:tags":[
        "group"
    ],
    "wof:name":"Openeye Music Group Inc",
    "wof:placetype":"venue"
},
  "geometry": {"coordinates":[-92.341587,34.507018],"type":"Point"}
}