{
  "type": "Feature",
  "properties": {
    "addr:full":"1410 Academy St Eudora AR 71640",
    "addr:housenumber":"1410",
    "addr:postcode":"71640",
    "addr:street":"Academy St",
    "iso:country":"US",
    "sg:address":"1410 Academy St",
    "sg:city":"Eudora",
    "sg:classifiers":[
        {
            "category":"Organizations",
            "subcategory":"Religious Organization",
            "type":"Services"
        }
    ],
    "sg:phone":"+1 870 355 8330",
    "sg:postcode":"71640",
    "sg:province":"AR",
    "sg:tags":[
        "churches-baptist",
        "church"
    ],
    "wof:name":"Saint Paul Baptist Church",
    "wof:placetype":"venue"
},
  "geometry": {"coordinates":[-91.258583,33.124457],"type":"Point"}
}