{
  "type": "Feature",
  "properties": {
    "addr:full":"24581 Highway 14 E Trumann AR 72472",
    "addr:housenumber":"24581",
    "addr:postcode":"72472",
    "addr:street":"Highway 14 E Trumann",
    "iso:country":"US",
    "sg:address":"24581 Highway 14 E",
    "sg:city":"Trumann",
    "sg:classifiers":[
        {
            "category":"Food & Beverages",
            "subcategory":"Groceries & Convenience Stores",
            "type":"Retail Goods"
        }
    ],
    "sg:phone":"+1 870 593 2288",
    "sg:postcode":"72472",
    "sg:province":"AR",
    "wof:name":"Hyneman Store",
    "wof:placetype":"venue"
},
  "geometry": {"coordinates":[-90.607652,35.549032],"type":"Point"}
}