{
  "type": "Feature",
  "properties": {
    "iso:country":"US",
    "sg:address":"1701 Kimberling Hill Dr",
    "sg:city":"Alma",
    "sg:classifiers":[
        {
            "category":"Real Estate",
            "subcategory":"Real Estate Operator",
            "type":"Services"
        }
    ],
    "sg:phone":"+1 479 632 2370",
    "sg:postcode":"72921",
    "sg:province":"AR",
    "sg:tags":[
        "building",
        "nonresidential"
    ],
    "wof:name":"Dfw Properties LLC",
    "wof:placetype":"venue"
},
  "geometry": {"coordinates":[-94.232309,35.505226],"type":"Point"}
}