{
  "type": "Feature",
  "properties": {
    "iso:country":"US",
    "sg:address":"2611 Birch St",
    "sg:city":"Benton",
    "sg:classifiers":[
        {
            "category":"Building & Trades",
            "subcategory":"Construction",
            "type":"Services"
        }
    ],
    "sg:phone":"+1 501 847 0611",
    "sg:postcode":"72019",
    "sg:province":"AR",
    "sg:tags":[
        "repairing",
        "remodeling",
        "contractor"
    ],
    "wof:name":"Bryant Fence Co",
    "wof:placetype":"venue"
},
  "geometry": {"coordinates":[-92.523032,34.625106],"type":"Point"}
}