{
  "type": "Feature",
  "properties": {
    "iso:country":"US",
    "sg:address":"204 W Main St",
    "sg:city":"Russellville",
    "sg:classifiers":[
        {
            "category":"Banks & Credit Unions",
            "subcategory":"Bank",
            "type":"Services"
        }
    ],
    "sg:phone":"+1 479 968 1126",
    "sg:postcode":"72801",
    "sg:province":"AR",
    "sg:tags":[
        "depository",
        "banking"
    ],
    "wof:name":"Escrow Services Of Arkansas",
    "wof:placetype":"venue"
},
  "geometry": {"coordinates":[-93.135194,35.278507],"type":"Point"}
}