{
  "type": "Feature",
  "properties": {
    "addr:full":"214 E Highland Ave Malvern AR 72104",
    "addr:housenumber":"214",
    "addr:postcode":"72104",
    "addr:street":"E Highland Ave",
    "iso:country":"US",
    "sg:address":"214 E Highland Ave",
    "sg:city":"Malvern",
    "sg:classifiers":[
        {
            "category":"Shopping",
            "subcategory":"Musical Instruments",
            "type":"Retail Goods"
        }
    ],
    "sg:phone":"+1 501 337 4177",
    "sg:postcode":"72104",
    "sg:province":"AR",
    "sg:tags":[
        "music",
        "dealer"
    ],
    "wof:name":"Malvern Music Co",
    "wof:placetype":"venue"
},
  "geometry": {"coordinates":[-92.809448,34.356362],"type":"Point"}
}