{
  "type": "Feature",
  "properties": {
    "iso:country":"US",
    "sg:address":"200 E 8th Ave",
    "sg:city":"Pine Bluff",
    "sg:classifiers":[
        {
            "category":"Government",
            "subcategory":"Office",
            "type":"Public Place"
        }
    ],
    "sg:phone":"+1 870 543 1820",
    "sg:postcode":"71601",
    "sg:province":"AR",
    "sg:tags":[
        "city",
        "planning",
        "dev"
    ],
    "wof:name":"Pine Bluff Community Dev Dept",
    "wof:placetype":"venue"
},
  "geometry": {"coordinates":[-92.000525,34.221661],"type":"Point"}
}