{
  "type": "Feature",
  "properties": {
    "iso:country":"US",
    "sg:address":"5 Country Oaks Dr",
    "sg:city":"Little Rock",
    "sg:classifiers":[
        {
            "category":"Professional",
            "subcategory":"Business Services",
            "type":"Services"
        }
    ],
    "sg:phone":"+1 501 821 4755",
    "sg:postcode":"72223",
    "sg:province":"AR",
    "wof:name":"Ms Services Group LLC",
    "wof:placetype":"venue"
},
  "geometry": {"coordinates":[-92.475359,34.750798],"type":"Point"}
}