{
  "type": "Feature",
  "properties": {
    "addr:full":"121 W 4th St Rector AR 72461",
    "addr:housenumber":"121",
    "addr:postcode":"72461",
    "addr:street":"W 4Th St",
    "iso:country":"US",
    "sg:address":"121 W 4th St",
    "sg:city":"Rector",
    "sg:classifiers":[
        {
            "category":"Education",
            "subcategory":"Library",
            "type":"Public Place"
        }
    ],
    "sg:phone":"+1 870 595 2410",
    "sg:postcode":"72461",
    "sg:province":"AR",
    "wof:name":"Rector Branch Library",
    "wof:placetype":"venue"
},
  "geometry": {"coordinates":[-90.29372100000001,36.263623],"type":"Point"}
}