{
  "type": "Feature",
  "properties": {
    "addr:full":"100 Edgewood St Hot Springs National AR 71901",
    "addr:housenumber":"100",
    "addr:postcode":"71901",
    "addr:street":"Edgewood St",
    "iso:country":"US",
    "sg:address":"100 Edgewood St",
    "sg:city":"Hot Springs National",
    "sg:classifiers":[
        {
            "category":"Professional",
            "subcategory":"Business Services",
            "type":"Services"
        }
    ],
    "sg:phone":"+1 501 624 4677",
    "sg:postcode":"71901",
    "sg:province":"AR",
    "wof:name":"Shang Hai Restaurant",
    "wof:placetype":"venue"
},
  "geometry": {"coordinates":[-93.044034,34.530152],"type":"Point"}
}