{
  "type": "Feature",
  "properties": {
    "iso:country":"US",
    "sg:address":"13 School Dr",
    "sg:city":"Greenbrier",
    "sg:classifiers":[
        {
            "category":"Education",
            "subcategory":"School",
            "type":"Public Place"
        }
    ],
    "sg:phone":"+1 501 679 2113",
    "sg:postcode":"72058",
    "sg:province":"AR",
    "wof:name":"Greenbrier Middle School",
    "wof:placetype":"venue"
},
  "geometry": {"coordinates":[-92.388905,35.232122],"type":"Point"}
}