{
  "type": "Feature",
  "properties": {
    "addr:full":"1505 Evans St Arkadelphia AR 71923",
    "addr:housenumber":"1505",
    "addr:postcode":"71923",
    "addr:street":"Evans St",
    "iso:country":"US",
    "sg:address":"1505 Evans St",
    "sg:city":"Arkadelphia",
    "sg:classifiers":[
        {
            "category":"Travel",
            "subcategory":"Campground",
            "type":"Entertainment"
        }
    ],
    "sg:phone":"+1 870 246 6265",
    "sg:postcode":"71923",
    "sg:province":"AR",
    "wof:name":"Robert Leverne",
    "wof:placetype":"venue"
},
  "geometry": {"coordinates":[-93.067111,34.127538],"type":"Point"}
}