{
  "type": "Feature",
  "properties": {
    "addr:full":"118 Katie Ln Monticello AR 71655",
    "addr:housenumber":"118",
    "addr:postcode":"71655",
    "addr:street":"Katie Ln",
    "iso:country":"US",
    "sg:address":"118 Katie Ln",
    "sg:city":"Monticello",
    "sg:classifiers":[
        {
            "category":"Wholesale",
            "subcategory":"Metals & Minerals",
            "type":"Manufacturing & Wholesale Goods"
        }
    ],
    "sg:phone":"+1 870 367 6614",
    "sg:postcode":"71655",
    "sg:province":"AR",
    "wof:name":"Metal Concepts Inc",
    "wof:placetype":"venue"
},
  "geometry": {"coordinates":[-91.81049299999999,33.654888],"type":"Point"}
}