{
  "type": "Feature",
  "properties": {
    "iso:country":"US",
    "sg:address":"32 S Main Ave",
    "sg:city":"Fayetteville",
    "sg:classifiers":[
        {
            "category":"Retail",
            "subcategory":"Auto Repair",
            "type":"Services"
        }
    ],
    "sg:phone":"+1 479 527 0037",
    "sg:postcode":"72701",
    "sg:province":"AR",
    "sg:tags":[
        "repairing",
        "automobile"
    ],
    "wof:name":"C & C Garage",
    "wof:placetype":"venue"
},
  "geometry": {"coordinates":[-94.173925,35.993724],"type":"Point"}
}