{
  "type": "Feature",
  "properties": {
    "iso:country":"US",
    "sg:address":"8740 Maumelle Blvd",
    "sg:city":"N Little Rock",
    "sg:classifiers":[
        {
            "category":"Home & Garden",
            "subcategory":"Building Materials",
            "type":"Retail Goods"
        }
    ],
    "sg:phone":"+1 501 758 5050",
    "sg:postcode":"72113",
    "sg:province":"AR",
    "sg:tags":[
        "windows"
    ],
    "wof:name":"Pella Window Store",
    "wof:placetype":"venue"
},
  "geometry": {"coordinates":[-92.361149,34.812528],"type":"Point"}
}