{
  "type": "Feature",
  "properties": {
    "addr:full":"203 Fir St Waldron AR 72958",
    "addr:housenumber":"203",
    "addr:postcode":"72958",
    "addr:street":"Fir St",
    "iso:country":"US",
    "sg:address":"203 Fir St",
    "sg:city":"Waldron",
    "sg:classifiers":[
        {
            "category":"Manufacturing",
            "subcategory":"Tools & Machinery",
            "type":"Manufacturing & Wholesale Goods"
        }
    ],
    "sg:phone":"+1 479 637 4152",
    "sg:postcode":"72958",
    "sg:province":"AR",
    "sg:tags":[
        "devices"
    ],
    "sg:website":"www.thermo.com",
    "wof:name":"Thermo Electron Corp",
    "wof:placetype":"venue"
},
  "geometry": {"coordinates":[-94.10078300000001,34.900095],"type":"Point"}
}