{
  "type": "Feature",
  "properties": {
    "iso:country":"US",
    "sg:address":"303 S Thompson St",
    "sg:city":"Springdale",
    "sg:classifiers":[
        {
            "category":"Shopping",
            "subcategory":"Florist",
            "type":"Retail Goods"
        }
    ],
    "sg:phone":"+1 479 756 2023",
    "sg:postcode":"72764",
    "sg:province":"AR",
    "wof:name":"Liberty Belle Flowers & Gifts",
    "wof:placetype":"venue"
},
  "geometry": {"coordinates":[-94.138397,36.183201],"type":"Point"}
}