{
  "type": "Feature",
  "properties": {
    "iso:country":"US",
    "sg:address":"421 E 9th St",
    "sg:city":"Rector",
    "sg:classifiers":[
        {
            "category":"Autos & Motor Vehicles",
            "subcategory":"Auto Supplies",
            "type":"Retail Goods"
        }
    ],
    "sg:phone":"+1 870 595 3563",
    "sg:postcode":"72461",
    "sg:province":"AR",
    "sg:tags":[
        "automobile",
        "parts"
    ],
    "sg:website":"www.glensain.com",
    "wof:name":"Glen Sain Motor Sales",
    "wof:placetype":"venue"
},
  "geometry": {"coordinates":[-90.28843500000001,36.259075],"type":"Point"}
}