{
  "type": "Feature",
  "properties": {
    "addr:full":"1105 Fairview Rd SW Camden AR 71701",
    "addr:housenumber":"1105",
    "addr:postcode":"71701",
    "addr:street":"Fairview Rd Sw",
    "iso:country":"US",
    "sg:address":"1105 Fairview Rd SW",
    "sg:city":"Camden",
    "sg:classifiers":[
        {
            "category":"Banks & Credit Unions",
            "subcategory":"Bank",
            "type":"Services"
        }
    ],
    "sg:phone":"+1 870 231 9387",
    "sg:postcode":"71701",
    "sg:province":"AR",
    "wof:name":"First Bank",
    "wof:placetype":"venue"
},
  "geometry": {"coordinates":[-92.826385,33.535786],"type":"Point"}
}