{
  "type": "Feature",
  "properties": {
    "addr:full":"1400 S Cross St Little Rock AR 72202",
    "addr:housenumber":"1400",
    "addr:postcode":"72202",
    "addr:street":"S Cross St",
    "iso:country":"US",
    "sg:address":"1400 S Cross St",
    "sg:city":"Little Rock",
    "sg:classifiers":[
        {
            "category":"Organizations",
            "subcategory":"Religious Organization",
            "type":"Services"
        }
    ],
    "sg:phone":"+1 501 374 1753",
    "sg:postcode":"72202",
    "sg:province":"AR",
    "sg:tags":[
        "church"
    ],
    "wof:name":"New Jerusalem Baptist Church",
    "wof:placetype":"venue"
},
  "geometry": {"coordinates":[-92.28613199999999,34.73614],"type":"Point"}
}