{
  "type": "Feature",
  "properties": {
    "iso:country":"US",
    "sg:address":"130 Midge Langley Rd",
    "sg:city":"Searcy",
    "sg:classifiers":[
        {
            "category":"Building & Trades",
            "subcategory":"Construction",
            "type":"Services"
        }
    ],
    "sg:phone":"+1 501 827 2856",
    "sg:postcode":"72143",
    "sg:province":"AR",
    "sg:tags":[
        "system",
        "contractor",
        "air conditioning"
    ],
    "wof:name":"Air Man Heating & Air",
    "wof:placetype":"venue"
},
  "geometry": {"coordinates":[-91.975773,35.308919],"type":"Point"}
}