{
  "type": "Feature",
  "properties": {
    "addr:full":"520 Mena St Mena OK 71953",
    "addr:housenumber":"520",
    "addr:postcode":"71953",
    "addr:street":"Mena St",
    "iso:country":"US",
    "sg:address":"520 Mena St",
    "sg:city":"Mena",
    "sg:classifiers":[
        {
            "category":"Airport",
            "type":"Transportation"
        }
    ],
    "sg:phone":"+1 479 394 4077",
    "sg:postcode":"71953",
    "sg:province":"OK",
    "wof:name":"City of Mena Arkansas",
    "wof:placetype":"venue"
},
  "geometry": {"coordinates":[-94.237482,34.585775],"type":"Point"}
}