{
  "type": "Feature",
  "properties": {
    "iso:country":"US",
    "sg:address":"707 S Mount Olive St",
    "sg:city":"Siloam Springs",
    "sg:classifiers":[
        {
            "category":"Travel",
            "subcategory":"Travel Agent",
            "type":"Entertainment"
        }
    ],
    "sg:phone":"+1 479 524 6167",
    "sg:postcode":"72761",
    "sg:province":"OK",
    "sg:tags":[
        "agency",
        "bureau"
    ],
    "wof:name":"Lynda's Travel Svc",
    "wof:placetype":"venue"
},
  "geometry": {"coordinates":[-94.54132799999999,36.179138],"type":"Point"}
}