{
  "type": "Feature",
  "properties": {
    "iso:country":"US",
    "sg:address":"4206 W Markham St",
    "sg:city":"Little Rock",
    "sg:classifiers":[
        {
            "category":"Professional",
            "type":"Services"
        }
    ],
    "sg:phone":"+1 501 376 9241",
    "sg:postcode":"72205",
    "sg:province":"AR",
    "wof:name":"Gary D Gray I",
    "wof:placetype":"venue"
},
  "geometry": {"coordinates":[-92.319735,34.751596],"type":"Point"}
}