{
  "type": "Feature",
  "properties": {
    "iso:country":"US",
    "sg:address":"401 Main St",
    "sg:city":"Lake Village",
    "sg:classifiers":[
        {
            "category":"Shopping",
            "subcategory":"Pharmacy",
            "type":"Retail Goods"
        }
    ],
    "sg:phone":"+1 870 265 2220",
    "sg:postcode":"71653",
    "sg:province":"AR",
    "wof:name":"Hunter's Pharmacy",
    "wof:placetype":"venue"
},
  "geometry": {"coordinates":[-91.28504100000001,33.33157],"type":"Point"}
}