{
  "type": "Feature",
  "properties": {
    "iso:country":"US",
    "sg:address":"1224 Franklin St",
    "sg:city":"North Little Rock",
    "sg:classifiers":[
        {
            "category":"Organizations",
            "subcategory":"Religious Organization",
            "type":"Services"
        }
    ],
    "sg:phone":"+1 501 375 2347",
    "sg:postcode":"72114",
    "sg:province":"AR",
    "wof:name":"Barring Cross Baptist Church",
    "wof:placetype":"venue"
},
  "geometry": {"coordinates":[-92.281735,34.766386],"type":"Point"}
}