{
  "type": "Feature",
  "properties": {
    "iso:country":"US",
    "sg:address":"393 Reganda Springs Trl",
    "sg:city":"Caddo Gap",
    "sg:classifiers":[
        {
            "category":"Health Services",
            "subcategory":"Medical Lab",
            "type":"Services"
        }
    ],
    "sg:phone":"+1 870 356 2242",
    "sg:postcode":"71935",
    "sg:province":"AR",
    "sg:tags":[
        "laboratory",
        "dental"
    ],
    "wof:name":"Ora Craft Dental Laboratories",
    "wof:placetype":"venue"
},
  "geometry": {"coordinates":[-93.666289,34.364831],"type":"Point"}
}