{
  "type": "Feature",
  "properties": {
    "addr:full":"1499 Highway 82 Byp W Magnolia AR 71753",
    "addr:housenumber":"1499",
    "addr:postcode":"71753",
    "addr:street":"Highway 82 Byp W Magnolia",
    "iso:country":"US",
    "sg:address":"1499 Highway 82 Byp W",
    "sg:city":"Magnolia",
    "sg:classifiers":[
        {
            "category":"Transit Center",
            "subcategory":"Freight",
            "type":"Transportation"
        },
        {
            "category":"Freight",
            "type":"Transportation"
        }
    ],
    "sg:phone":"+1 870 234 3094",
    "sg:postcode":"71753",
    "sg:province":"AR",
    "sg:tags":[
        "trucking-light",
        "trucking",
        "local",
        "trucking-motor",
        "hauling"
    ],
    "wof:name":"Larry Fowler Trucking, Inc",
    "wof:placetype":"venue"
},
  "geometry": {"coordinates":[-93.171583,33.252396],"type":"Point"}
}