{
  "type": "Feature",
  "properties": {
    "addr:full":"219 Church St Salem AR 72576",
    "addr:housenumber":"219",
    "addr:postcode":"72576",
    "addr:street":"Church St",
    "iso:country":"US",
    "sg:address":"219 Church St",
    "sg:city":"Salem",
    "sg:classifiers":[
        {
            "category":"Retail",
            "subcategory":"Repair Shop",
            "type":"Services"
        },
        {
            "category":"Professional",
            "subcategory":"Detective & Security Services",
            "type":"Services"
        }
    ],
    "sg:phone":"+1 870 895 3101",
    "sg:postcode":"72576",
    "sg:province":"AR",
    "sg:tags":[
        "skip",
        "tracing",
        "bail",
        "bond"
    ],
    "wof:name":"Je Bonding Incorporated",
    "wof:placetype":"venue"
},
  "geometry": {"coordinates":[-91.821015,36.371045],"type":"Point"}
}