{
  "type": "Feature",
  "properties": {
    "addr:full":"9210 Oak Grove Ln Little Rock AR 72209",
    "addr:housenumber":"9210",
    "addr:postcode":"72209",
    "addr:street":"Oak Grove Ln",
    "iso:country":"US",
    "sg:address":"9210 Oak Grove Ln",
    "sg:city":"Little Rock",
    "sg:classifiers":[
        {
            "category":"Building & Trades",
            "subcategory":"Construction",
            "type":"Services"
        }
    ],
    "sg:phone":"+1 501 565 0418",
    "sg:postcode":"72209",
    "sg:province":"AR",
    "sg:tags":[
        "marking",
        "maintenance",
        "parking"
    ],
    "wof:name":"Stripe A Lot",
    "wof:placetype":"venue"
},
  "geometry": {"coordinates":[-92.357826,34.667208],"type":"Point"}
}