{
  "type": "Feature",
  "properties": {
    "iso:country":"US",
    "sg:address":"34 S Sunland Dr",
    "sg:city":"Cabot",
    "sg:classifiers":[
        {
            "category":"Shopping",
            "subcategory":"Gifts & Souvenirs",
            "type":"Retail Goods"
        }
    ],
    "sg:phone":"+1 501 843 0603",
    "sg:postcode":"72023",
    "sg:province":"AR",
    "wof:name":"Gifts Plus",
    "wof:placetype":"venue"
},
  "geometry": {"coordinates":[-92.044049,34.990932],"type":"Point"}
}