{
  "type": "Feature",
  "properties": {
    "addr:full":"109 S Adams Ave Camden AR 71701",
    "addr:housenumber":"109",
    "addr:postcode":"71701",
    "addr:street":"S Adams Ave",
    "iso:country":"US",
    "sg:address":"109 S Adams Ave",
    "sg:city":"Camden",
    "sg:classifiers":[
        {
            "category":"Insurance",
            "subcategory":"Insurance Agent",
            "type":"Services"
        }
    ],
    "sg:phone":"+1 870 836 3406",
    "sg:postcode":"71701",
    "sg:province":"AR",
    "sg:tags":[
        "consultant",
        "analyst"
    ],
    "wof:name":"Dunn Insurance Agency",
    "wof:placetype":"venue"
},
  "geometry": {"coordinates":[-92.829645,33.585937],"type":"Point"}
}