{
  "type": "Feature",
  "properties": {
    "addr:full":"6230 Catcher Xing Van Buren AR 72956",
    "addr:postcode":"6230;72956",
    "addr:street":"Catcher Xing",
    "iso:country":"US",
    "sg:address":"6230 Catcher Xing",
    "sg:city":"Van Buren",
    "sg:classifiers":[
        {
            "category":"Retail",
            "subcategory":"Repair Shop",
            "type":"Services"
        }
    ],
    "sg:phone":"+1 479 783 2279",
    "sg:postcode":"72956",
    "sg:province":"AR",
    "wof:name":"Rooter Drain",
    "wof:placetype":"venue"
},
  "geometry": {"coordinates":[-94.272229,35.398744],"type":"Point"}
}