{
  "type": "Feature",
  "properties": {
    "iso:country":"US",
    "sg:address":"1310 W Robinson Ave",
    "sg:city":"Springdale",
    "sg:classifiers":[
        {
            "category":"Professional",
            "subcategory":"Management & Consulting",
            "type":"Services"
        }
    ],
    "sg:phone":"+1 479 725 1015",
    "sg:postcode":"72764",
    "sg:province":"AR",
    "sg:tags":[
        "consultant",
        "educational"
    ],
    "sg:website":"www.ucp.org",
    "wof:name":"Conductive Education Of Nw Ar",
    "wof:placetype":"venue"
},
  "geometry": {"coordinates":[-94.146322,36.167514],"type":"Point"}
}