{
  "type": "Feature",
  "properties": {
    "addr:full":"1176 State Highway 7 N Dardanelle AR 72834",
    "addr:housenumber":"1176",
    "addr:postcode":"72834",
    "addr:street":"State Highway 7 N",
    "iso:country":"US",
    "sg:address":"1176 State Highway 7 N",
    "sg:city":"Dardanelle",
    "sg:classifiers":[
        {
            "category":"Restaurant",
            "type":"Food & Drink"
        }
    ],
    "sg:phone":"+1 479 229 2331",
    "sg:postcode":"72834",
    "sg:province":"AR",
    "wof:name":"Dari-Delite",
    "wof:placetype":"venue"
},
  "geometry": {"coordinates":[-93.154815,35.20437],"type":"Point"}
}