{
  "type": "Feature",
  "properties": {
    "addr:full":"219 Main St Stamps AR 71860",
    "addr:housenumber":"219",
    "addr:postcode":"71860",
    "addr:street":"Main St",
    "iso:country":"US",
    "sg:address":"219 Main St",
    "sg:city":"Stamps",
    "sg:classifiers":[
        {
            "category":"Retail",
            "subcategory":"Portrait Studio",
            "type":"Services"
        }
    ],
    "sg:phone":"+1 870 533 2582",
    "sg:postcode":"71860",
    "sg:province":"AR",
    "sg:tags":[
        "photographer"
    ],
    "wof:name":"Bill Russell's Photography",
    "wof:placetype":"venue"
},
  "geometry": {"coordinates":[-93.499566,33.362147],"type":"Point"}
}