{
  "type": "Feature",
  "properties": {
    "addr:full":"5000 W Markham St Little Rock AR 72205",
    "addr:housenumber":"5000",
    "addr:postcode":"72205",
    "addr:street":"W Markham St",
    "iso:country":"US",
    "sg:address":"5000 W Markham St",
    "sg:city":"Little Rock",
    "sg:classifiers":[
        {
            "category":"Restaurant",
            "type":"Food & Drink"
        }
    ],
    "sg:phone":"+1 501 664 0351",
    "sg:postcode":"72205",
    "sg:province":"AR",
    "wof:name":"Mc Donald's",
    "wof:placetype":"venue"
},
  "geometry": {"coordinates":[-92.33039599999999,34.751908],"type":"Point"}
}