{
  "type": "Feature",
  "properties": {
    "iso:country":"US",
    "sg:address":"104 W Stephenson Ave",
    "sg:city":"Harrison",
    "sg:classifiers":[
        {
            "category":"Professional",
            "type":"Services"
        }
    ],
    "sg:phone":"+1 870 743 9517",
    "sg:postcode":"72601",
    "sg:province":"AR",
    "wof:name":"Fond Memories",
    "wof:placetype":"venue"
},
  "geometry": {"coordinates":[-93.108565,36.229705],"type":"Point"}
}