{
  "type": "Feature",
  "properties": {
    "addr:full":"696 Co Rd 344 Piggott AR 72454",
    "addr:housenumber":"696",
    "addr:postcode":"72454",
    "addr:street":"Co Rd 344 Piggott",
    "iso:country":"US",
    "sg:address":"696 Co Rd 344",
    "sg:city":"Piggott",
    "sg:classifiers":[
        {
            "category":"Professional",
            "subcategory":"Management & Consulting",
            "type":"Services"
        }
    ],
    "sg:phone":"+1 870 598 1705",
    "sg:postcode":"72454",
    "sg:province":"AR",
    "sg:tags":[
        "business"
    ],
    "wof:name":"Daronda Blevins Education Ctr",
    "wof:placetype":"venue"
},
  "geometry": {"coordinates":[-90.185833,36.418276],"type":"Point"}
}