{
  "type": "Feature",
  "properties": {
    "addr:full":"9035 Evans Ln Harrisburg AR 72432",
    "addr:housenumber":"9035",
    "addr:postcode":"72432",
    "addr:street":"Evans Ln",
    "iso:country":"US",
    "sg:address":"9035 Evans Ln",
    "sg:city":"Harrisburg",
    "sg:classifiers":[
        {
            "category":"Farming",
            "subcategory":"Farm",
            "type":"Manufacturing & Wholesale Goods"
        }
    ],
    "sg:phone":"+1 870 578 5694",
    "sg:postcode":"72432",
    "sg:province":"AR",
    "sg:tags":[
        "crop",
        "general"
    ],
    "wof:name":"Pretty Creek Farms Inc",
    "wof:placetype":"venue"
},
  "geometry": {"coordinates":[-90.749139,35.585394],"type":"Point"}
}