{
  "type": "Feature",
  "properties": {
    "addr:full":"23 Charles St Conway AR 72032",
    "addr:housenumber":"23",
    "addr:postcode":"72032",
    "addr:street":"Charles St",
    "iso:country":"US",
    "sg:address":"23 Charles St",
    "sg:city":"Conway",
    "sg:classifiers":[
        {
            "category":"Retail",
            "subcategory":"Repair Shop",
            "type":"Services"
        }
    ],
    "sg:phone":"+1 501 336 9330",
    "sg:postcode":"72032",
    "sg:province":"AR",
    "sg:tags":[
        "merchandise"
    ],
    "wof:name":"Art Store Frameworks",
    "wof:placetype":"venue"
},
  "geometry": {"coordinates":[-92.41470700000001,35.043236],"type":"Point"}
}