{
  "type": "Feature",
  "properties": {
    "iso:country":"US",
    "sg:address":"125 E Township St",
    "sg:city":"Fayetteville",
    "sg:classifiers":[
        {
            "category":"Real Estate",
            "subcategory":"Real Estate Agent",
            "type":"Services"
        }
    ],
    "sg:phone":"+1 479 521 6411",
    "sg:postcode":"72703",
    "sg:province":"AR",
    "sg:tags":[
        "appraiser"
    ],
    "wof:name":"Appraisal Services Co",
    "wof:placetype":"venue"
},
  "geometry": {"coordinates":[-94.152764,36.095053],"type":"Point"}
}