{
  "type": "Feature",
  "properties": {
    "addr:full":"12 Redwing Dr Cherokee Village AR 72529",
    "addr:housenumber":"12",
    "addr:postcode":"72529",
    "addr:street":"Redwing Dr Cherokee Village",
    "iso:country":"US",
    "sg:address":"12 Redwing Dr",
    "sg:city":"Cherokee Village",
    "sg:classifiers":[
        {
            "category":"Building & Trades",
            "subcategory":"Cleaning & Sanitation",
            "type":"Services"
        }
    ],
    "sg:phone":"+1 870 257 2460",
    "sg:postcode":"72529",
    "sg:province":"AR",
    "sg:tags":[
        "polishing",
        "waxing",
        "floor"
    ],
    "wof:name":"Combs Floor Cleaning",
    "wof:placetype":"venue"
},
  "geometry": {"coordinates":[-91.54772199999999,36.32925],"type":"Point"}
}