{
  "type": "Feature",
  "properties": {
    "addr:full":"205 W 2nd Fordyce AR 71742",
    "addr:housenumber":"205",
    "addr:postcode":"71742",
    "addr:street":"W 2Nd Fordyce",
    "iso:country":"US",
    "sg:address":"205 W 2nd",
    "sg:city":"Fordyce",
    "sg:classifiers":[
        {
            "category":"Home & Garden",
            "subcategory":"Building Materials",
            "type":"Retail Goods"
        }
    ],
    "sg:phone":"+1 870 352 5023",
    "sg:postcode":"71742",
    "sg:province":"AR",
    "sg:tags":[
        "glass",
        "window",
        "plate"
    ],
    "wof:name":"Tri County Auto Glass",
    "wof:placetype":"venue"
},
  "geometry": {"coordinates":[-92.412817,33.811414],"type":"Point"}
}