{
  "type": "Feature",
  "properties": {
    "iso:country":"US",
    "sg:address":"1003 US Hwy 63",
    "sg:city":"Walnut Ridge",
    "sg:classifiers":[
        {
            "category":"Food & Beverages",
            "subcategory":"Groceries & Convenience Stores",
            "type":"Retail Goods"
        }
    ],
    "sg:phone":"+1 870 886 9829",
    "sg:postcode":"72415",
    "sg:province":"AR",
    "wof:name":"South Point Tiger Express Inc",
    "wof:placetype":"venue"
},
  "geometry": {"coordinates":[-90.91068,36.012186],"type":"Point"}
}