{
  "type": "Feature",
  "properties": {
    "iso:country":"US",
    "sg:address":"5009 W Short Barraque St",
    "sg:city":"White Hall",
    "sg:classifiers":[
        {
            "category":"Retail",
            "subcategory":"Auto Repair",
            "type":"Services"
        }
    ],
    "sg:phone":"+1 870 534 2999",
    "sg:postcode":"71602",
    "sg:province":"AR",
    "sg:tags":[
        "repairing",
        "automobile",
        "radiator"
    ],
    "wof:name":"Stan's One Day Radiator Shop",
    "wof:placetype":"venue"
},
  "geometry": {"coordinates":[-92.059621,34.229889],"type":"Point"}
}