{
  "type": "Feature",
  "properties": {
    "addr:full":"900 W Johnson Ave Jonesboro AR 72401",
    "addr:housenumber":"900",
    "addr:postcode":"72401",
    "addr:street":"W Johnson Ave",
    "iso:country":"US",
    "sg:address":"900 W Johnson Ave",
    "sg:city":"Jonesboro",
    "sg:classifiers":[
        {
            "category":"Retail",
            "subcategory":"Auto Rental",
            "type":"Services"
        }
    ],
    "sg:phone":"+1 870 935 1424",
    "sg:postcode":"72401",
    "sg:province":"AR",
    "sg:tags":[
        "tr",
        "trucking",
        "truck",
        "operator",
        "local",
        "utility"
    ],
    "wof:name":"Carco Sales Lease",
    "wof:placetype":"venue"
},
  "geometry": {"coordinates":[-90.71816699999999,35.846483],"type":"Point"}
}