{
  "type": "Feature",
  "properties": {
    "iso:country":"US",
    "sg:address":"1104 S Maple St",
    "sg:city":"Stuttgart",
    "sg:classifiers":[
        {
            "category":"Building & Trades",
            "subcategory":"Construction",
            "type":"Services"
        }
    ],
    "sg:phone":"+1 870 673 7317",
    "sg:postcode":"72160",
    "sg:province":"AR",
    "sg:tags":[
        "house"
    ],
    "wof:name":"Hhi Inc",
    "wof:placetype":"venue"
},
  "geometry": {"coordinates":[-91.554107,34.492964],"type":"Point"}
}