{
  "type": "Feature",
  "properties": {
    "addr:full":"106 1st Ave NE Gravette AR 72736",
    "addr:housenumber":"106",
    "addr:postcode":"72736",
    "addr:street":"1St Ave Ne",
    "iso:country":"US",
    "sg:address":"106 1st Ave NE",
    "sg:city":"Gravette",
    "sg:classifiers":[
        {
            "category":"Food & Beverages",
            "subcategory":"Bakery",
            "type":"Retail Goods"
        }
    ],
    "sg:phone":"+1 479 787 6200",
    "sg:postcode":"72736",
    "sg:province":"AR",
    "wof:name":"Brick Oven",
    "wof:placetype":"venue"
},
  "geometry": {"coordinates":[-94.453154,36.42316],"type":"Point"}
}