{
  "type": "Feature",
  "properties": {
    "iso:country":"US",
    "sg:address":"30 Gap Rd",
    "sg:city":"Batesville",
    "sg:classifiers":[
        {
            "category":"Place Of Worship",
            "subcategory":"Church",
            "type":"Public Place"
        },
        {
            "category":"Place Of Worship",
            "type":"Public Place"
        }
    ],
    "sg:phone":"+1 870 793 4688",
    "sg:postcode":"72501",
    "sg:province":"AR",
    "sg:tags":[
        "churches-seventh-day",
        "adventist",
        "christian",
        "churches-advent"
    ],
    "sg:website":"http://www.adventist.org",
    "wof:name":"Seventh-Day Adventist Chu",
    "wof:placetype":"venue"
},
  "geometry": {"coordinates":[-91.598822,35.768504],"type":"Point"}
}