{
  "type": "Feature",
  "properties": {
    "addr:full":"135 Joan Camden AR 71701",
    "addr:housenumber":"135",
    "addr:postcode":"71701",
    "addr:street":"Joan Camden",
    "iso:country":"US",
    "sg:address":"135 Joan",
    "sg:city":"Camden",
    "sg:classifiers":[
        {
            "category":"Professional",
            "type":"Services"
        }
    ],
    "sg:phone":"+1 870 574 0877",
    "sg:postcode":"71701",
    "sg:province":"AR",
    "wof:name":"Family Network Resources Inc",
    "wof:placetype":"venue"
},
  "geometry": {"coordinates":[-92.76661799999999,33.646258],"type":"Point"}
}