{
  "type": "Feature",
  "properties": {
    "iso:country":"US",
    "sg:address":"2468 Murdoch Rd",
    "sg:city":"Atkins",
    "sg:classifiers":[
        {
            "category":"Recreation",
            "subcategory":"Sailing Club",
            "type":"Entertainment"
        }
    ],
    "sg:phone":"+1 479 641 1052",
    "sg:postcode":"72823",
    "sg:province":"AR",
    "sg:tags":[
        "rope",
        "splicing"
    ],
    "wof:name":"Circle Dot Splicing Inc",
    "wof:placetype":"venue"
},
  "geometry": {"coordinates":[-92.911739,35.298149],"type":"Point"}
}