{
  "type": "Feature",
  "properties": {
    "addr:full":"11104 N Rodney Parham Rd Little Rock AR 72212",
    "addr:housenumber":"11104",
    "addr:postcode":"72212",
    "addr:street":"N;Parham Rd",
    "iso:country":"US",
    "sg:address":"11104 N Rodney Parham Rd",
    "sg:city":"Little Rock",
    "sg:classifiers":[
        {
            "category":"Autos & Motor Vehicles",
            "subcategory":"Auto Supplies",
            "type":"Retail Goods"
        }
    ],
    "sg:phone":"+1 501 227 0506",
    "sg:postcode":"72212",
    "sg:province":"AR",
    "sg:tags":[
        "repair",
        "r",
        "automotive",
        "general"
    ],
    "wof:name":"Firestone",
    "wof:placetype":"venue"
},
  "geometry": {"coordinates":[-92.396671,34.771572],"type":"Point"}
}