{
  "type": "Feature",
  "properties": {
    "addr:full":"200 E Line Rd Searcy AR 72143",
    "addr:housenumber":"200",
    "addr:postcode":"72143",
    "addr:street":"E Line Rd",
    "iso:country":"US",
    "sg:address":"200 E Line Rd",
    "sg:city":"Searcy",
    "sg:classifiers":[
        {
            "category":"Autos & Motor Vehicles",
            "subcategory":"Automobile Sales",
            "type":"Retail Goods"
        }
    ],
    "sg:phone":"+1 501 279 7987",
    "sg:postcode":"72143",
    "sg:province":"AR",
    "sg:tags":[
        "car",
        "dealer"
    ],
    "wof:name":"Best Chance Finance Auto Sales",
    "wof:placetype":"venue"
},
  "geometry": {"coordinates":[-91.682266,35.247278],"type":"Point"}
}