{
  "type": "Feature",
  "properties": {
    "addr:full":"918 US Hwy 67 N Walnut Ridge AR 72476",
    "addr:housenumber":"918",
    "addr:postcode":"72476",
    "addr:street":"Us Hwy 67 N Walnut Ridge",
    "iso:country":"US",
    "sg:address":"918 US Hwy 67 N",
    "sg:city":"Walnut Ridge",
    "sg:classifiers":[
        {
            "category":"Shopping",
            "subcategory":"Discount & Variety Stores",
            "type":"Retail Goods"
        }
    ],
    "sg:phone":"+1 870 886 8655",
    "sg:postcode":"72476",
    "sg:province":"AR",
    "wof:name":"Dollar General",
    "wof:placetype":"venue"
},
  "geometry": {"coordinates":[-90.955037,36.076789],"type":"Point"}
}