{
  "type": "Feature",
  "properties": {
    "iso:country":"US",
    "sg:address":"30145 Thorn Rd",
    "sg:city":"Trumann",
    "sg:classifiers":[
        {
            "category":"Manufacturing",
            "subcategory":"Textiles",
            "type":"Manufacturing & Wholesale Goods"
        }
    ],
    "sg:phone":"+1 870 483 7702",
    "sg:postcode":"72472",
    "sg:province":"AR",
    "sg:tags":[
        "broker",
        "cotton"
    ],
    "wof:name":"Dennis Penter Farms Inc",
    "wof:placetype":"venue"
},
  "geometry": {"coordinates":[-90.500032,35.671589],"type":"Point"}
}