{
  "type": "Feature",
  "properties": {
    "addr:full":"401 Grant 72 Sheridan AR 72150",
    "addr:housenumber":"401;72",
    "addr:postcode":"72150",
    "addr:street":"Grant",
    "iso:country":"US",
    "sg:address":"401 Grant 72",
    "sg:city":"Sheridan",
    "sg:classifiers":[
        {
            "category":"Manufacturing",
            "subcategory":"Lumber",
            "type":"Manufacturing & Wholesale Goods"
        }
    ],
    "sg:phone":"+1 870 942 3790",
    "sg:postcode":"72150",
    "sg:province":"AR",
    "sg:tags":[
        "logging"
    ],
    "wof:name":"James D Ozment Logging Inc",
    "wof:placetype":"venue"
},
  "geometry": {"coordinates":[-92.307732,34.314339],"type":"Point"}
}