{
  "type": "Feature",
  "properties": {
    "iso:country":"US",
    "sg:address":"311 E 10th Ave",
    "sg:city":"Foreman",
    "sg:classifiers":[
        {
            "category":"Education",
            "subcategory":"School",
            "type":"Public Place"
        }
    ],
    "sg:phone":"+1 870 542 7214",
    "sg:postcode":"71836",
    "sg:province":"AR",
    "wof:name":"Foreman Upper Elementary",
    "wof:placetype":"venue"
},
  "geometry": {"coordinates":[-94.407792,33.730601],"type":"Point"}
}