{
  "type": "Feature",
  "properties": {
    "addr:full":"1306 Highway 193 Wynne AR 72396",
    "addr:housenumber":"1306",
    "addr:postcode":"72396",
    "addr:street":"Highway 193",
    "iso:country":"US",
    "sg:address":"1306 Highway 193",
    "sg:city":"Wynne",
    "sg:classifiers":[
        {
            "category":"Home & Garden",
            "subcategory":"Garden Supply",
            "type":"Retail Goods"
        }
    ],
    "sg:phone":"+1 870 238 7895",
    "sg:postcode":"72396",
    "sg:province":"AR",
    "sg:tags":[
        "fertilizer"
    ],
    "wof:name":"Cross County Farmers Assn",
    "wof:placetype":"venue"
},
  "geometry": {"coordinates":[-90.92691000000001,35.235447],"type":"Point"}
}