{
  "type": "Feature",
  "properties": {
    "iso:country":"US",
    "sg:address":"38 Hightrail Dr",
    "sg:city":"Maumelle",
    "sg:classifiers":[
        {
            "category":"Banks & Credit Unions",
            "subcategory":"Investment Brokerage",
            "type":"Services"
        }
    ],
    "sg:phone":"+1 501 851 6454",
    "sg:postcode":"72113",
    "sg:province":"AR",
    "wof:name":"JKW Investments",
    "wof:placetype":"venue"
},
  "geometry": {"coordinates":[-92.407479,34.860437],"type":"Point"}
}