{
  "type": "Feature",
  "properties": {
    "iso:country":"US",
    "sg:address":"2735 Shadybrooke Ln",
    "sg:city":"Van Buren",
    "sg:classifiers":[
        {
            "category":"Retail",
            "subcategory":"Auto Repair",
            "type":"Services"
        }
    ],
    "sg:phone":"+1 479 410 4186",
    "sg:postcode":"72956",
    "sg:province":"AR",
    "sg:tags":[
        "body",
        "automobile",
        "painting"
    ],
    "wof:name":"H & H Custom Auto",
    "wof:placetype":"venue"
},
  "geometry": {"coordinates":[-94.310903,35.476188],"type":"Point"}
}