{
  "type": "Feature",
  "properties": {
    "iso:country":"US",
    "sg:address":"1727 Blacksnake Rd",
    "sg:city":"Hot Springs National Park",
    "sg:classifiers":[
        {
            "category":"Professional",
            "subcategory":"Business Services",
            "type":"Services"
        }
    ],
    "sg:phone":"+1 501 760 1742",
    "sg:postcode":"71913",
    "sg:province":"AR",
    "sg:tags":[
        "development",
        "information",
        "research"
    ],
    "wof:name":"Peoples Development Company",
    "wof:placetype":"venue"
},
  "geometry": {"coordinates":[-93.149503,34.511743],"type":"Point"}
}