{
  "type": "Feature",
  "properties": {
    "iso:country":"US",
    "sg:address":"900 Cedar Grove Rd",
    "sg:city":"Floral",
    "sg:classifiers":[
        {
            "category":"Farming",
            "subcategory":"Livestock Farm",
            "type":"Manufacturing & Wholesale Goods"
        }
    ],
    "sg:phone":"+1 501 345 2660",
    "sg:postcode":"72534",
    "sg:province":"AR",
    "sg:tags":[
        "general"
    ],
    "wof:name":"Pearson Carlis",
    "wof:placetype":"venue"
},
  "geometry": {"coordinates":[-91.74118,35.55248],"type":"Point"}
}