{
  "type": "Feature",
  "properties": {
    "addr:full":"703 E Line Rd Searcy AR 72143",
    "addr:housenumber":"703",
    "addr:postcode":"72143",
    "addr:street":"E Line Rd",
    "iso:country":"US",
    "sg:address":"703 E Line Rd",
    "sg:city":"Searcy",
    "sg:classifiers":[
        {
            "category":"Utilities",
            "subcategory":"Fuel Oil & Lpg",
            "type":"Services"
        }
    ],
    "sg:phone":"+1 501 268 4242",
    "sg:postcode":"72143",
    "sg:province":"AR",
    "sg:tags":[
        "propane",
        "gas"
    ],
    "wof:name":"Ferrellgas",
    "wof:placetype":"venue"
},
  "geometry": {"coordinates":[-91.690423,35.239905],"type":"Point"}
}