{
  "type": "Feature",
  "properties": {
    "addr:full":"4642 Alma Hwy Van Buren AR 72956",
    "addr:housenumber":"4642",
    "addr:postcode":"72956",
    "addr:street":"Alma Hwy",
    "iso:country":"US",
    "sg:address":"4642 Alma Hwy",
    "sg:city":"Van Buren",
    "sg:classifiers":[
        {
            "category":"Home & Garden",
            "subcategory":"Mobile Homes",
            "type":"Retail Goods"
        }
    ],
    "sg:phone":"+1 479 474 7088",
    "sg:postcode":"72956",
    "sg:province":"AR",
    "wof:name":"Van Alma Quality Homes",
    "wof:placetype":"venue"
},
  "geometry": {"coordinates":[-94.30022700000001,35.454436],"type":"Point"}
}