{
  "type": "Feature",
  "properties": {
    "addr:full":"1414 N Bankhead Carlisle AR 72024",
    "addr:housenumber":"1414",
    "addr:postcode":"72024",
    "addr:street":"N",
    "iso:country":"US",
    "sg:address":"1414 N Bankhead",
    "sg:city":"Carlisle",
    "sg:classifiers":[
        {
            "category":"Place Of Worship",
            "subcategory":"Church",
            "type":"Public Place"
        },
        {
            "category":"Place Of Worship",
            "type":"Public Place"
        }
    ],
    "sg:phone":"+1 870 552 3100",
    "sg:postcode":"72024",
    "sg:province":"AR",
    "sg:tags":[
        "churches-baptist-general",
        "churches-baptist"
    ],
    "wof:name":"Immanuel Baptist Church",
    "wof:placetype":"venue"
},
  "geometry": {"coordinates":[-91.750556,34.796066],"type":"Point"}
}