{
  "type": "Feature",
  "properties": {
    "iso:country":"US",
    "sg:address":"2420 Rogers Ave",
    "sg:city":"Fort Smith",
    "sg:classifiers":[
        {
            "category":"Health Services",
            "subcategory":"Doctor",
            "type":"Services"
        }
    ],
    "sg:phone":"+1 479 782 4000",
    "sg:postcode":"72901",
    "sg:province":"AR",
    "sg:tags":[
        "medical"
    ],
    "wof:name":"Family Medical Care",
    "wof:placetype":"venue"
},
  "geometry": {"coordinates":[-94.405866,35.376816],"type":"Point"}
}