{
  "type": "Feature",
  "properties": {
    "addr:full":"6009 C W Post Rd Jonesboro AR 72401",
    "addr:housenumber":"6009",
    "addr:postcode":"72401",
    "addr:street":"C W Post Rd",
    "iso:country":"US",
    "sg:address":"6009 C W Post Rd",
    "sg:city":"Jonesboro",
    "sg:classifiers":[
        {
            "category":"Social Services",
            "subcategory":"Job Training",
            "type":"Services"
        }
    ],
    "sg:phone":"+1 870 934 0854",
    "sg:postcode":"72401",
    "sg:province":"AR",
    "sg:tags":[
        "rehabilitation"
    ],
    "wof:name":"Northeast Arkansas Regional",
    "wof:placetype":"venue"
},
  "geometry": {"coordinates":[-90.622401,35.806322],"type":"Point"}
}