{
  "type": "Feature",
  "properties": {
    "iso:country":"US",
    "sg:address":"448 State Hwy 91",
    "sg:city":"Walnut Ridge",
    "sg:classifiers":[
        {
            "category":"Organizations",
            "subcategory":"Religious Organization",
            "type":"Services"
        }
    ],
    "sg:phone":"+1 870 886 5093",
    "sg:postcode":"72476",
    "sg:province":"AR",
    "sg:tags":[
        "church"
    ],
    "wof:name":"Oak Grove Church Of Christ",
    "wof:placetype":"venue"
},
  "geometry": {"coordinates":[-90.95271200000001,36.065332],"type":"Point"}
}