{
  "type": "Feature",
  "properties": {
    "iso:country":"US",
    "sg:address":"1143 Bradley 25 Rd N",
    "sg:city":"Warren",
    "sg:classifiers":[
        {
            "category":"Retail",
            "subcategory":"Laundry & Dry Cleaning",
            "type":"Services"
        }
    ],
    "sg:phone":"+1 870 226 3302",
    "sg:postcode":"71671",
    "sg:province":"AR",
    "sg:tags":[
        "cleaner",
        "rug",
        "carpet"
    ],
    "wof:name":"Steamers Carpet Care",
    "wof:placetype":"venue"
},
  "geometry": {"coordinates":[-92.123884,33.540402],"type":"Point"}
}