{
  "type": "Feature",
  "properties": {
    "iso:country":"US",
    "sg:address":"108 S Oak St",
    "sg:city":"Jacksonville",
    "sg:classifiers":[
        {
            "category":"Education",
            "subcategory":"School",
            "type":"Public Place"
        }
    ],
    "sg:phone":"+1 501 982 6571",
    "sg:postcode":"72076",
    "sg:province":"AR",
    "sg:tags":[
        "elementary"
    ],
    "wof:name":"Jacksonville Elementary School",
    "wof:placetype":"venue"
},
  "geometry": {"coordinates":[-92.10924799999999,34.86439],"type":"Point"}
}