{
  "type": "Feature",
  "properties": {
    "iso:country":"US",
    "sg:address":"25 Gap Rd",
    "sg:city":"Batesville",
    "sg:classifiers":[
        {
            "category":"Health Services",
            "subcategory":"Hospital",
            "type":"Services"
        }
    ],
    "sg:phone":"+1 870 793 8900",
    "sg:postcode":"72501",
    "sg:province":"AR",
    "sg:tags":[
        "mental"
    ],
    "wof:name":"Health Resources Of Arkansas",
    "wof:placetype":"venue"
},
  "geometry": {"coordinates":[-91.598764,35.768564],"type":"Point"}
}