{
  "type": "Feature",
  "properties": {
    "iso:country":"US",
    "sg:address":"9171 Lee Harris Rd",
    "sg:city":"Bentonville",
    "sg:classifiers":[
        {
            "category":"Farming",
            "subcategory":"Poultry Farm",
            "type":"Manufacturing & Wholesale Goods"
        }
    ],
    "sg:phone":"+1 479 795 4341",
    "sg:postcode":"72712",
    "sg:province":"AR",
    "sg:tags":[
        "egg"
    ],
    "wof:name":"C&C Turkey Farms Inc",
    "wof:placetype":"venue"
},
  "geometry": {"coordinates":[-94.28152,36.308146],"type":"Point"}
}