{
  "type": "Feature",
  "properties": {
    "addr:full":"710 W Tulsa St Siloam Springs OK 72761",
    "addr:housenumber":"710",
    "addr:postcode":"72761",
    "addr:street":"W Tulsa St",
    "iso:country":"US",
    "sg:address":"710 W Tulsa St",
    "sg:city":"Siloam Springs",
    "sg:classifiers":[
        {
            "category":"Shopping",
            "type":"Retail Goods"
        }
    ],
    "sg:phone":"+1 479 524 9513",
    "sg:postcode":"72761",
    "sg:province":"OK",
    "sg:tags":[
        "merchandise"
    ],
    "wof:name":"Aquarium",
    "wof:placetype":"venue"
},
  "geometry": {"coordinates":[-94.54774399999999,36.177981],"type":"Point"}
}