{
  "type": "Feature",
  "properties": {
    "iso:country":"US",
    "sg:address":"15010 W Polk Rd",
    "sg:city":"Alexander",
    "sg:classifiers":[
        {
            "category":"Building & Trades",
            "subcategory":"Construction",
            "type":"Services"
        }
    ],
    "sg:phone":"+1 501 653 0355",
    "sg:postcode":"72002",
    "sg:province":"AR",
    "sg:tags":[
        "contractor"
    ],
    "wof:name":"Complete Building Svc Inc",
    "wof:placetype":"venue"
},
  "geometry": {"coordinates":[-92.44325600000001,34.587107],"type":"Point"}
}