{
  "type": "Feature",
  "properties": {
    "iso:country":"US",
    "sg:address":"12404 Watson Rd",
    "sg:city":"Sherwood",
    "sg:classifiers":[
        {
            "category":"Organizations",
            "subcategory":"Non-profit Organization",
            "type":"Services"
        }
    ],
    "sg:phone":"+1 501 835 3218",
    "sg:postcode":"72120",
    "sg:province":"AR",
    "sg:tags":[
        "charity",
        "foundations-educational",
        "philanthropic",
        "research"
    ],
    "wof:name":"Mauldin Scholarship Charitable",
    "wof:placetype":"venue"
},
  "geometry": {"coordinates":[-92.237819,34.921158],"type":"Point"}
}