{
  "type": "Feature",
  "properties": {
    "iso:country":"US",
    "sg:address":"194 Spring St",
    "sg:city":"Eureka Springs",
    "sg:classifiers":[
        {
            "category":"Education",
            "subcategory":"Library",
            "type":"Public Place"
        }
    ],
    "sg:phone":"+1 479 253 8754",
    "sg:postcode":"72632",
    "sg:province":"AR",
    "wof:name":"Eureka Springs Public Library",
    "wof:placetype":"venue"
},
  "geometry": {"coordinates":[-93.736805,36.405772],"type":"Point"}
}