{
  "type": "Feature",
  "properties": {
    "iso:country":"US",
    "sg:address":"3405 Atwood Rd",
    "sg:city":"Little Rock",
    "sg:classifiers":[
        {
            "category":"Restaurant",
            "type":"Food & Drink"
        }
    ],
    "sg:phone":"+1 501 888 4998",
    "sg:postcode":"72206",
    "sg:province":"AR",
    "wof:name":"Fat Boys Barbecue",
    "wof:placetype":"venue"
},
  "geometry": {"coordinates":[-92.32276,34.611165],"type":"Point"}
}