{
  "type": "Feature",
  "properties": {
    "addr:full":"1100 N 7th St West Memphis AR 72301",
    "addr:housenumber":"1100",
    "addr:postcode":"72301",
    "addr:street":"N 7Th St",
    "iso:country":"US",
    "sg:address":"1100 N 7th St",
    "sg:city":"West Memphis",
    "sg:classifiers":[
        {
            "category":"Manufacturing",
            "subcategory":"Chemicals & Compounds",
            "type":"Manufacturing & Wholesale Goods"
        }
    ],
    "sg:phone":"+1 870 733 1397",
    "sg:postcode":"72301",
    "sg:province":"AR",
    "sg:tags":[
        "lithographing",
        "ink"
    ],
    "wof:name":"Flint Ink Corp",
    "wof:placetype":"venue"
},
  "geometry": {"coordinates":[-90.175871,35.157232],"type":"Point"}
}