{
  "type": "Feature",
  "properties": {
    "addr:full":"3201 Walnut St Fort Smith AR 72904",
    "addr:housenumber":"3201",
    "addr:postcode":"72904",
    "addr:street":"Walnut St",
    "iso:country":"US",
    "sg:address":"3201 Walnut St",
    "sg:city":"Fort Smith",
    "sg:classifiers":[
        {
            "category":"Organizations",
            "subcategory":"Religious Organization",
            "type":"Services"
        }
    ],
    "sg:phone":"+1 479 783 8351",
    "sg:postcode":"72904",
    "sg:province":"AR",
    "wof:name":"Lao Baptist Church",
    "wof:placetype":"venue"
},
  "geometry": {"coordinates":[-94.396271,35.422466],"type":"Point"}
}