{
  "type": "Feature",
  "properties": {
    "iso:country":"US",
    "sg:address":"822 Barkada Rd",
    "sg:city":"Monticello",
    "sg:classifiers":[
        {
            "category":"Food & Beverages",
            "subcategory":"Fruits & Vegetables",
            "type":"Retail Goods"
        }
    ],
    "sg:phone":"+1 870 367 7078",
    "sg:postcode":"71655",
    "sg:province":"AR",
    "wof:name":"EDS Produce",
    "wof:placetype":"venue"
},
  "geometry": {"coordinates":[-91.801347,33.640824],"type":"Point"}
}