{
  "type": "Feature",
  "properties": {
    "iso:country":"US",
    "sg:address":"87 Recorder Ln",
    "sg:city":"Russellville",
    "sg:classifiers":[
        {
            "category":"Professional",
            "subcategory":"Business Services",
            "type":"Services"
        }
    ],
    "sg:phone":"+1 479 968 5215",
    "sg:postcode":"72802",
    "sg:province":"AR",
    "sg:tags":[
        "recording",
        "studio"
    ],
    "wof:name":"John's Recording Studio & Sls",
    "wof:placetype":"venue"
},
  "geometry": {"coordinates":[-93.119527,35.303678],"type":"Point"}
}