{
  "type": "Feature",
  "properties": {
    "addr:full":"655 Simon Rd Conway AR 72032",
    "addr:housenumber":"655",
    "addr:postcode":"72032",
    "addr:street":"Simon Rd",
    "iso:country":"US",
    "sg:address":"655 Simon Rd",
    "sg:city":"Conway",
    "sg:classifiers":[
        {
            "category":"Retail",
            "subcategory":"Auto Repair",
            "type":"Services"
        }
    ],
    "sg:phone":"+1 501 679 5167",
    "sg:postcode":"72032",
    "sg:province":"AR",
    "sg:tags":[
        "wrecker"
    ],
    "wof:name":"Jones Discount Towing",
    "wof:placetype":"venue"
},
  "geometry": {"coordinates":[-92.407386,35.090431],"type":"Point"}
}