{
  "type": "Feature",
  "properties": {
    "addr:full":"3501 Tulsa St Fort Smith AR 72903",
    "addr:housenumber":"3501",
    "addr:postcode":"72903",
    "addr:street":"Tulsa St",
    "iso:country":"US",
    "sg:address":"3501 Tulsa St",
    "sg:city":"Fort Smith",
    "sg:classifiers":[
        {
            "category":"Manufacturing",
            "subcategory":"Metals",
            "type":"Manufacturing & Wholesale Goods"
        }
    ],
    "sg:phone":"+1 479 646 1651",
    "sg:postcode":"72903",
    "sg:province":"AR",
    "sg:tags":[
        "steel",
        "product",
        "wire",
        "mfg"
    ],
    "wof:name":"American Appliance Products",
    "wof:placetype":"venue"
},
  "geometry": {"coordinates":[-94.394593,35.334709],"type":"Point"}
}