{
  "type": "Feature",
  "properties": {
    "iso:country":"US",
    "sg:address":"8206 State Hwy 107",
    "sg:city":"North Little Rock",
    "sg:classifiers":[
        {
            "category":"Real Estate",
            "subcategory":"Real Estate Services",
            "type":"Services"
        }
    ],
    "sg:phone":"+1 501 834 2111",
    "sg:postcode":"72120",
    "sg:province":"AR",
    "sg:tags":[
        "company",
        "title"
    ],
    "wof:name":"Global Title Co Inc",
    "wof:placetype":"venue"
},
  "geometry": {"coordinates":[-92.231351,34.831538],"type":"Point"}
}