{
  "type": "Feature",
  "properties": {
    "iso:country":"US",
    "sg:address":"900 W 3rd St",
    "sg:city":"Little Rock",
    "sg:classifiers":[
        {
            "category":"Professional",
            "subcategory":"Lawyer & Legal Services",
            "type":"Services"
        }
    ],
    "sg:phone":"+1 501 372 3330",
    "sg:postcode":"72201",
    "sg:province":"AR",
    "sg:tags":[
        "attorney"
    ],
    "wof:name":"Daniel M Traylor",
    "wof:placetype":"venue"
},
  "geometry": {"coordinates":[-92.28143300000001,34.747596],"type":"Point"}
}