{
  "type": "Feature",
  "properties": {
    "iso:country":"US",
    "sg:address":"1939 S N St",
    "sg:city":"Rogers",
    "sg:classifiers":[
        {
            "category":"Building & Trades",
            "subcategory":"Plumbing",
            "type":"Services"
        }
    ],
    "sg:phone":"+1 479 636 0942",
    "sg:postcode":"72758",
    "sg:province":"AR",
    "sg:tags":[
        "plumbing",
        "contractor"
    ],
    "wof:name":"Trotters Plumbing Inc",
    "wof:placetype":"venue"
},
  "geometry": {"coordinates":[-94.098813,36.31081],"type":"Point"}
}