{
  "type": "Feature",
  "properties": {
    "iso:country":"US",
    "sg:address":"4801 N Hills Blvd",
    "sg:city":"Sherwood",
    "sg:classifiers":[
        {
            "category":"Real Estate",
            "subcategory":"Real Estate Operator",
            "type":"Services"
        }
    ],
    "sg:phone":"+1 501 753 1653",
    "sg:postcode":"72116",
    "sg:province":"AR",
    "sg:tags":[
        "apartment"
    ],
    "wof:name":"Lakewood House",
    "wof:placetype":"venue"
},
  "geometry": {"coordinates":[-92.23809799999999,34.798983],"type":"Point"}
}