{
  "type": "Feature",
  "properties": {
    "iso:country":"US",
    "sg:address":"1500 Merrywood Dr",
    "sg:city":"Jonesboro",
    "sg:classifiers":[
        {
            "category":"Retail",
            "subcategory":"Repair Shop",
            "type":"Services"
        }
    ],
    "sg:phone":"+1 870 935 0988",
    "sg:postcode":"72401",
    "sg:province":"AR",
    "sg:tags":[
        "resale",
        "industrial",
        "machinery"
    ],
    "wof:name":"American Machine Tools",
    "wof:placetype":"venue"
},
  "geometry": {"coordinates":[-90.694314,35.827693],"type":"Point"}
}