{
  "type": "Feature",
  "properties": {
    "iso:country":"US",
    "sg:address":"78 Vines Dr",
    "sg:city":"Norman",
    "sg:classifiers":[
        {
            "category":"Personal",
            "subcategory":"Beauty Salon",
            "type":"Services"
        }
    ],
    "sg:phone":"+1 870 334 2621",
    "sg:postcode":"71960",
    "sg:province":"AR",
    "wof:name":"Jennifer's Hair & Tanning Sln",
    "wof:placetype":"venue"
},
  "geometry": {"coordinates":[-93.654359,34.446456],"type":"Point"}
}