{
  "type": "Feature",
  "properties": {
    "addr:full":"3907 Todd St Van Buren AR 72956",
    "addr:housenumber":"3907",
    "addr:postcode":"72956",
    "addr:street":"Todd St",
    "iso:country":"US",
    "sg:address":"3907 Todd St",
    "sg:city":"Van Buren",
    "sg:classifiers":[
        {
            "category":"Building & Trades",
            "subcategory":"Construction",
            "type":"Services"
        }
    ],
    "sg:phone":"+1 479 474 2615",
    "sg:postcode":"72956",
    "sg:province":"AR",
    "sg:tags":[
        "residential"
    ],
    "wof:name":"McDaniel Construction",
    "wof:placetype":"venue"
},
  "geometry": {"coordinates":[-94.311897,35.430132],"type":"Point"}
}