{
  "type": "Feature",
  "properties": {
    "iso:country":"US",
    "sg:address":"1019 N Walton Blvd",
    "sg:city":"Bentonville",
    "sg:classifiers":[
        {
            "category":"Home & Garden",
            "subcategory":"Home Furnishings",
            "type":"Retail Goods"
        }
    ],
    "sg:phone":"+1 479 254 3490",
    "sg:postcode":"72712",
    "sg:province":"AR",
    "wof:name":"Brinkmann Corporation",
    "wof:placetype":"venue"
},
  "geometry": {"coordinates":[-94.221188,36.383706],"type":"Point"}
}