{
  "type": "Feature",
  "properties": {
    "iso:country":"US",
    "sg:address":"4501 John F Kennedy Blvd",
    "sg:city":"N Little Rock",
    "sg:classifiers":[
        {
            "category":"Personal",
            "subcategory":"Beauty Salon",
            "type":"Services"
        }
    ],
    "sg:phone":"+1 501 791 0555",
    "sg:postcode":"72116",
    "sg:province":"AR",
    "wof:name":"Lisa KAYS",
    "wof:placetype":"venue"
},
  "geometry": {"coordinates":[-92.25584499999999,34.79723],"type":"Point"}
}