{
  "type": "Feature",
  "properties": {
    "iso:country":"US",
    "sg:address":"2 Halsted Cir",
    "sg:city":"Rogers",
    "sg:classifiers":[
        {
            "category":"Health Services",
            "subcategory":"Doctor",
            "type":"Services"
        }
    ],
    "sg:phone":"+1 888 279 1201",
    "sg:postcode":"72756",
    "sg:province":"AR",
    "sg:tags":[
        "physician",
        "reconstructive",
        "surgeons",
        "cosmetic",
        "hand",
        "pediatrics-plastic",
        "surgery",
        "plastic",
        "surgeon"
    ],
    "sg:website":"http://www.aldersonplasticsurgery.com",
    "wof:name":"Plastic Surgery Clinic Of Northwest Arkansas The",
    "wof:placetype":"venue"
},
  "geometry": {"coordinates":[-94.159782,36.33503],"type":"Point"}
}