{
  "type": "Feature",
  "properties": {
    "iso:country":"US",
    "sg:address":"4005 State Hwy 161",
    "sg:city":"North Little Rock",
    "sg:classifiers":[
        {
            "category":"Freight",
            "type":"Transportation"
        }
    ],
    "sg:phone":"+1 501 945 5555",
    "sg:postcode":"72117",
    "sg:province":"AR",
    "sg:tags":[
        "local",
        "except",
        "trucking"
    ],
    "wof:name":"Wca Waste Corporation",
    "wof:placetype":"venue"
},
  "geometry": {"coordinates":[-92.204931,34.782362],"type":"Point"}
}