{
  "type": "Feature",
  "properties": {
    "addr:full":"12700 Bart Moreland Dr Roland AR 72135",
    "addr:housenumber":"12700",
    "addr:postcode":"72135",
    "addr:street":"Bart Moreland Dr Roland",
    "iso:country":"US",
    "sg:address":"12700 Bart Moreland Dr",
    "sg:city":"Roland",
    "sg:classifiers":[
        {
            "category":"Social Services",
            "subcategory":"Adult Care",
            "type":"Services"
        }
    ],
    "sg:phone":"+1 501 868 8152",
    "sg:postcode":"72135",
    "sg:province":"AR",
    "sg:tags":[
        "residential",
        "aged",
        "homes-institutional"
    ],
    "wof:name":"Pi Kappa Alpha House Corp",
    "wof:placetype":"venue"
},
  "geometry": {"coordinates":[-92.48709100000001,34.870628],"type":"Point"}
}