{
  "type": "Feature",
  "properties": {
    "iso:country":"US",
    "sg:address":"31140 Hwy 85",
    "sg:city":"Ketchum",
    "sg:classifiers":[
        {
            "category":"Building & Trades",
            "subcategory":"Construction",
            "type":"Services"
        }
    ],
    "sg:phone":"+1 918 782 3868",
    "sg:postcode":"74331",
    "sg:province":"OK",
    "sg:tags":[
        "excavating",
        "contractor"
    ],
    "wof:name":"Septics-R-Us",
    "wof:placetype":"venue"
},
  "geometry": {"coordinates":[-94.988603,36.565987],"type":"Point"}
}