{
  "type": "Feature",
  "properties": {
    "iso:country":"US",
    "sg:address":"19185 State Hwy 303",
    "sg:city":"Rogers",
    "sg:classifiers":[
        {
            "category":"Professional",
            "subcategory":"Management & Consulting",
            "type":"Services"
        }
    ],
    "sg:phone":"+1 479 925 1839",
    "sg:postcode":"72756",
    "sg:province":"AR",
    "wof:name":"L & G Land Management Inc",
    "wof:placetype":"venue"
},
  "geometry": {"coordinates":[-93.958012,36.319952],"type":"Point"}
}