{
  "type": "Feature",
  "properties": {
    "iso:country":"US",
    "sg:address":"301 S James St",
    "sg:city":"Jacksonville",
    "sg:classifiers":[
        {
            "category":"Restaurant",
            "type":"Food & Drink"
        }
    ],
    "sg:phone":"+1 501 985 5286",
    "sg:postcode":"72076",
    "sg:province":"AR",
    "sg:tags":[
        "eating"
    ],
    "wof:name":"Happy Family Restaurant",
    "wof:placetype":"venue"
},
  "geometry": {"coordinates":[-92.118838,34.864979],"type":"Point"}
}