{
  "type": "Feature",
  "properties": {
    "iso:country":"US",
    "sg:address":"228 Town Park Dr",
    "sg:city":"Mountain Home",
    "sg:classifiers":[
        {
            "category":"Manufacturing",
            "subcategory":"Tools & Machinery",
            "type":"Manufacturing & Wholesale Goods"
        }
    ],
    "sg:phone":"+1 870 425 3031",
    "sg:postcode":"72653",
    "sg:province":"AR",
    "sg:tags":[
        "machine",
        "shop"
    ],
    "wof:name":"Native Eng & Mfg Co",
    "wof:placetype":"venue"
},
  "geometry": {"coordinates":[-92.422968,36.311774],"type":"Point"}
}