{
  "type": "Feature",
  "properties": {
    "iso:country":"US",
    "sg:address":"720 N 11th St",
    "sg:city":"Fort Smith",
    "sg:classifiers":[
        {
            "category":"Restaurant",
            "type":"Food & Drink"
        }
    ],
    "sg:phone":"+1 479 783 5139",
    "sg:postcode":"72901",
    "sg:province":"AR",
    "sg:tags":[
        "eating"
    ],
    "wof:name":"Tortilleria Hot",
    "wof:placetype":"venue"
},
  "geometry": {"coordinates":[-94.414767,35.390061],"type":"Point"}
}