{
  "type": "Feature",
  "properties": {
    "addr:full":"3400 W Hillsboro St El Dorado AR 71730",
    "addr:housenumber":"3400",
    "addr:postcode":"71730",
    "addr:street":"W Hillsboro St",
    "iso:country":"US",
    "sg:address":"3400 W Hillsboro St",
    "sg:city":"El Dorado",
    "sg:classifiers":[
        {
            "category":"Banks & Credit Unions",
            "subcategory":"Bank",
            "type":"Services"
        }
    ],
    "sg:phone":"+1 870 863 7237",
    "sg:postcode":"71730",
    "sg:province":"AR",
    "sg:tags":[
        "loan"
    ],
    "wof:name":"Farm Credit Svc",
    "wof:placetype":"venue"
},
  "geometry": {"coordinates":[-92.711546,33.208054],"type":"Point"}
}