{
  "type": "Feature",
  "properties": {
    "iso:country":"US",
    "sg:address":"3228 N State Line Ave",
    "sg:city":"Texarkana",
    "sg:classifiers":[
        {
            "category":"Banks & Credit Unions",
            "subcategory":"Bank",
            "type":"Services"
        }
    ],
    "sg:phone":"+1 870 774 6730",
    "sg:postcode":"71854",
    "sg:province":"AR",
    "sg:tags":[
        "personal",
        "institution"
    ],
    "wof:name":"Advance America",
    "wof:placetype":"venue"
},
  "geometry": {"coordinates":[-94.043037,33.454048],"type":"Point"}
}