{
  "type": "Feature",
  "properties": {
    "addr:full":"7836 Powell Dr North Little Rock AR 72120",
    "addr:housenumber":"7836",
    "addr:postcode":"72120",
    "addr:street":"Powell Dr",
    "iso:country":"US",
    "sg:address":"7836 Powell Dr",
    "sg:city":"North Little Rock",
    "sg:classifiers":[
        {
            "category":"Restaurant",
            "type":"Food & Drink"
        }
    ],
    "sg:phone":"+1 501 834 1795",
    "sg:postcode":"72120",
    "sg:province":"AR",
    "sg:tags":[
        "eating"
    ],
    "wof:name":"Cechwooz Cuisine",
    "wof:placetype":"venue"
},
  "geometry": {"coordinates":[-92.217101,34.825921],"type":"Point"}
}