{
  "type": "Feature",
  "properties": {
    "addr:full":"11279 E Apple Hill Rd Prairie Grove AR 72753",
    "addr:housenumber":"11279",
    "addr:postcode":"72753",
    "addr:street":"E Apple Hill Rd",
    "iso:country":"US",
    "sg:address":"11279 E Apple Hill Rd",
    "sg:city":"Prairie Grove",
    "sg:classifiers":[
        {
            "category":"Manufacturing",
            "subcategory":"Tools & Machinery",
            "type":"Manufacturing & Wholesale Goods"
        }
    ],
    "sg:phone":"+1 479 846 2214",
    "sg:postcode":"72753",
    "sg:province":"AR",
    "sg:tags":[
        "backhoe"
    ],
    "wof:name":"Gordon Backhoe Service",
    "wof:placetype":"venue"
},
  "geometry": {"coordinates":[-94.340816,35.963776],"type":"Point"}
}