{
  "type": "Feature",
  "properties": {
    "iso:country":"US",
    "sg:address":"2005 W Beebe Capps Expy",
    "sg:city":"Searcy",
    "sg:classifiers":[
        {
            "category":"Food & Beverages",
            "subcategory":"Groceries & Convenience Stores",
            "type":"Retail Goods"
        }
    ],
    "sg:phone":"+1 501 368 0688",
    "sg:postcode":"72143",
    "sg:province":"AR",
    "wof:name":"A C Stores",
    "wof:placetype":"venue"
},
  "geometry": {"coordinates":[-91.758993,35.247117],"type":"Point"}
}