{
  "type": "Feature",
  "properties": {
    "iso:country":"US",
    "sg:address":"510 S Main St",
    "sg:city":"Pine Bluff",
    "sg:classifiers":[
        {
            "category":"Professional",
            "subcategory":"Research",
            "type":"Services"
        }
    ],
    "sg:phone":"+1 870 535 0110",
    "sg:postcode":"71601",
    "sg:province":"AR",
    "sg:tags":[
        "foundation",
        "philanthropic"
    ],
    "wof:name":"Industrial Foundation Jffrsn",
    "wof:placetype":"venue"
},
  "geometry": {"coordinates":[-92.00350899999999,34.223913],"type":"Point"}
}