{
  "type": "Feature",
  "properties": {
    "addr:full":"3207 Independence St Fort Smith AR 72903",
    "addr:housenumber":"3207",
    "addr:postcode":"72903",
    "addr:street":"Independence St",
    "iso:country":"US",
    "sg:address":"3207 Independence St",
    "sg:city":"Fort Smith",
    "sg:classifiers":[
        {
            "category":"Social Services",
            "subcategory":"Child Care",
            "type":"Services"
        }
    ],
    "sg:phone":"+1 479 646 6605",
    "sg:postcode":"72903",
    "sg:province":"AR",
    "sg:tags":[
        "day"
    ],
    "wof:name":"Sey-Mck Inc",
    "wof:placetype":"venue"
},
  "geometry": {"coordinates":[-94.39833400000001,35.348624],"type":"Point"}
}