{
  "type": "Feature",
  "properties": {
    "iso:country":"US",
    "sg:address":"3207 Independence St",
    "sg:city":"Fort Smith",
    "sg:classifiers":[
        {
            "category":"Social Services",
            "subcategory":"Child Care",
            "type":"Services"
        }
    ],
    "sg:phone":"+1 479 646 6605",
    "sg:postcode":"72903",
    "sg:province":"AR",
    "sg:tags":[
        "day"
    ],
    "wof:name":"Sey-Mck Inc",
    "wof:placetype":"venue"
},
  "geometry": {"coordinates":[-94.398334,35.348624],"type":"Point"}
}