{
  "type": "Feature",
  "properties": {
    "iso:country":"US",
    "sg:address":"705 Grandview Dr",
    "sg:city":"Mc Gehee",
    "sg:phone":"+1 870 222 5328",
    "sg:postcode":"71654",
    "sg:province":"AR",
    "sg:tags":[
        "farm",
        "soybean"
    ],
    "wof:name":"Talmadge Robertson",
    "wof:placetype":"venue"
},
  "geometry": {"coordinates":[-91.40635899999999,33.63115],"type":"Point"}
}