{
  "type": "Feature",
  "properties": {
    "iso:country":"US",
    "sg:address":"106 S Main St",
    "sg:city":"Pine Bluff",
    "sg:classifiers":[
        {
            "category":"Professional",
            "subcategory":"Accounting & Tax Preparation",
            "type":"Services"
        }
    ],
    "sg:phone":"+1 870 535 8000",
    "sg:postcode":"71601",
    "sg:province":"AR",
    "wof:name":"Alan K Minor CPA",
    "wof:placetype":"venue"
},
  "geometry": {"coordinates":[-92.003456,34.228376],"type":"Point"}
}