{
  "type": "Feature",
  "properties": {
    "iso:country":"US",
    "sg:address":"7 Adams St",
    "sg:city":"Wilson",
    "sg:phone":"+1 870 655 8549",
    "sg:postcode":"72395",
    "sg:province":"AR",
    "sg:tags":[
        "farm",
        "soybean"
    ],
    "wof:name":"Henry T Carr & Son",
    "wof:placetype":"venue"
},
  "geometry": {"coordinates":[-90.042288,35.569703],"type":"Point"}
}