{
  "type": "Feature",
  "properties": {
    "iso:country":"US",
    "sg:address":"911 Oak St",
    "sg:city":"Conway",
    "sg:classifiers":[
        {
            "category":"Wholesale",
            "subcategory":"Auto Parts",
            "type":"Manufacturing & Wholesale Goods"
        }
    ],
    "sg:phone":"+1 501 329 5691",
    "sg:postcode":"72032",
    "sg:province":"AR",
    "wof:name":"Newberry Parts Company",
    "wof:placetype":"venue"
},
  "geometry": {"coordinates":[-92.437574,35.091642],"type":"Point"}
}