{
  "type": "Feature",
  "properties": {
    "iso:country":"US",
    "sg:address":"216 S 13th St",
    "sg:city":"Rogers",
    "sg:classifiers":[
        {
            "category":"Shopping",
            "subcategory":"Pharmacy",
            "type":"Retail Goods"
        }
    ],
    "sg:phone":"+1 479 621 0400",
    "sg:postcode":"72758",
    "sg:province":"AR",
    "sg:tags":[
        "drugstore"
    ],
    "wof:name":"Allcare Pharmacy Plus",
    "wof:placetype":"venue"
},
  "geometry": {"coordinates":[-94.134804,36.332401],"type":"Point"}
}