{
  "type": "Feature",
  "properties": {
    "iso:country":"US",
    "sg:address":"3008 Market St",
    "sg:city":"Pine Bluff",
    "sg:classifiers":[
        {
            "category":"Travel",
            "subcategory":"Hotels & Motels",
            "type":"Entertainment"
        }
    ],
    "sg:phone":"+1 870 540 0008",
    "sg:postcode":"71601",
    "sg:province":"AR",
    "wof:name":"Super 8 Motel",
    "wof:placetype":"venue"
},
  "geometry": {"coordinates":[-91.97152800000001,34.212986],"type":"Point"}
}