{
  "type": "Feature",
  "properties": {
    "addr:full":"15904 Valley Dr Alexander AR 72002",
    "addr:housenumber":"15904",
    "addr:postcode":"72002",
    "addr:street":"Valley Dr Alexander",
    "iso:country":"US",
    "sg:address":"15904 Valley Dr",
    "sg:city":"Alexander",
    "sg:classifiers":[
        {
            "category":"Professional",
            "type":"Services"
        }
    ],
    "sg:phone":"+1 501 847 1854",
    "sg:postcode":"72002",
    "sg:province":"AR",
    "wof:name":"Charlotte Baker",
    "wof:placetype":"venue"
},
  "geometry": {"coordinates":[-92.45420799999999,34.606808],"type":"Point"}
}