{
  "type": "Feature",
  "properties": {
    "iso:country":"US",
    "sg:address":"15904 Valley Dr",
    "sg:city":"Alexander",
    "sg:classifiers":[
        {
            "category":"Professional",
            "type":"Services"
        }
    ],
    "sg:phone":"+1 501 847 1854",
    "sg:postcode":"72002",
    "sg:province":"AR",
    "wof:name":"Charlotte Baker",
    "wof:placetype":"venue"
},
  "geometry": {"coordinates":[-92.454208,34.606808],"type":"Point"}
}