{
  "type": "Feature",
  "properties": {
    "addr:full":"5511 Walsh Ln Rogers AR 72758",
    "addr:housenumber":"5511",
    "addr:postcode":"72758",
    "addr:street":"Walsh Ln",
    "iso:country":"US",
    "sg:address":"5511 Walsh Ln",
    "sg:city":"Rogers",
    "sg:classifiers":[
        {
            "category":"Health Services",
            "subcategory":"Doctor",
            "type":"Services"
        },
        {
            "category":"Health Services",
            "subcategory":"Health Practitioner",
            "type":"Services"
        }
    ],
    "sg:phone":"+1 479 845 0896",
    "sg:postcode":"72758",
    "sg:province":"AR",
    "sg:tags":[
        "medicine",
        "sport",
        "therapy",
        "physical"
    ],
    "wof:name":"Trinity Rehabilitation At Pinnacle Point",
    "wof:placetype":"venue"
},
  "geometry": {"coordinates":[-94.19095299999999,36.310657],"type":"Point"}
}