{
  "type": "Feature",
  "properties": {
    "iso:country":"US",
    "sg:address":"5903 Highway 90 W",
    "sg:city":"Pocahontas",
    "sg:classifiers":[
        {
            "category":"Shopping",
            "subcategory":"Bicycles & Sporting Goods",
            "type":"Retail Goods"
        },
        {
            "category":"Parking",
            "subcategory":"Bicycle",
            "type":"Transportation"
        }
    ],
    "sg:phone":"+1 870 892 5668",
    "sg:postcode":"72455",
    "sg:province":"AR",
    "sg:tags":[
        "shop",
        "security",
        "system",
        "rack"
    ],
    "wof:name":"Sago Sales & Services Inc",
    "wof:placetype":"venue"
},
  "geometry": {"coordinates":[-90.92974700000001,36.208557],"type":"Point"}
}