{
  "type": "Feature",
  "properties": {
    "iso:country":"US",
    "sg:address":"319 N Washington",
    "sg:city":"Magnolia",
    "sg:classifiers":[
        {
            "category":"Professional",
            "subcategory":"Lawyer & Legal Services",
            "type":"Services"
        }
    ],
    "sg:phone":"+1 870 234 4781",
    "sg:postcode":"71753",
    "sg:province":"AR",
    "sg:tags":[
        "attorney",
        "practice",
        "plan"
    ],
    "sg:website":"http://www.davidpricelaw.com",
    "wof:name":"Price David P",
    "wof:placetype":"venue"
},
  "geometry": {"coordinates":[-93.240335,33.269372],"type":"Point"}
}