{
  "type": "Feature",
  "properties": {
    "iso:country":"US",
    "sg:address":"1401 E 6th Ave",
    "sg:city":"Pine Bluff",
    "sg:classifiers":[
        {
            "category":"Organizations",
            "subcategory":"Religious Organization",
            "type":"Services"
        }
    ],
    "sg:phone":"+1 870 534 6512",
    "sg:postcode":"71601",
    "sg:province":"AR",
    "wof:name":"Second Baptist Church",
    "wof:placetype":"venue"
},
  "geometry": {"coordinates":[-91.98863799999999,34.223987],"type":"Point"}
}