{
  "type": "Feature",
  "properties": {
    "addr:full":"1400 Sulphur Springs Rd Malvern AR 72104",
    "addr:housenumber":"1400",
    "addr:postcode":"72104",
    "addr:street":"Sulphur Springs Rd",
    "iso:country":"US",
    "sg:address":"1400 Sulphur Springs Rd",
    "sg:city":"Malvern",
    "sg:classifiers":[
        {
            "category":"Place Of Worship",
            "subcategory":"Church",
            "type":"Public Place"
        },
        {
            "category":"Place Of Worship",
            "type":"Public Place"
        }
    ],
    "sg:phone":"+1 501 337 1808",
    "sg:postcode":"72104",
    "sg:province":"AR",
    "sg:tags":[
        "churches-baptist-general",
        "churches-baptist"
    ],
    "wof:name":"Trinity Baptist Church",
    "wof:placetype":"venue"
},
  "geometry": {"coordinates":[-92.796516,34.346779],"type":"Point"}
}