{
  "type": "Feature",
  "properties": {
    "addr:full":"104 W Locke Ave De Queen AR 71832",
    "addr:housenumber":"104",
    "addr:postcode":"71832",
    "addr:street":"W Locke Ave De Queen",
    "iso:country":"US",
    "sg:address":"104 W Locke Ave",
    "sg:city":"De Queen",
    "sg:classifiers":[
        {
            "category":"Recreation",
            "type":"Entertainment"
        }
    ],
    "sg:phone":"+1 870 584 3135",
    "sg:postcode":"71832",
    "sg:province":"AR",
    "sg:tags":[
        "club",
        "membership"
    ],
    "wof:name":"Crossfork Hunting Club",
    "wof:placetype":"venue"
},
  "geometry": {"coordinates":[-94.347409,34.038349],"type":"Point"}
}