{
  "type": "Feature",
  "properties": {
    "iso:country":"US",
    "sg:address":"2005 E Central Ave",
    "sg:city":"Bentonville",
    "sg:classifiers":[
        {
            "category":"Professional",
            "subcategory":"Business Services",
            "type":"Services"
        }
    ],
    "sg:phone":"+1 479 254 8722",
    "sg:postcode":"72712",
    "sg:province":"AR",
    "sg:tags":[
        "interior",
        "consultant",
        "design",
        "decorator"
    ],
    "wof:name":"Gracious Living Interiors",
    "wof:placetype":"venue"
},
  "geometry": {"coordinates":[-94.183774,36.371021],"type":"Point"}
}