{
  "type": "Feature",
  "properties": {
    "addr:full":"4400 Memorial Dr Blytheville AR 72315",
    "addr:housenumber":"4400",
    "addr:postcode":"72315",
    "addr:street":"Memorial Dr Blytheville",
    "iso:country":"US",
    "sg:address":"4400 Memorial Dr",
    "sg:city":"Blytheville",
    "sg:classifiers":[
        {
            "category":"Personal",
            "subcategory":"Beauty Salon",
            "type":"Services"
        }
    ],
    "sg:phone":"+1 870 763 8335",
    "sg:postcode":"72315",
    "sg:province":"AR",
    "sg:tags":[
        "shop"
    ],
    "wof:name":"New Beginnings Beauty Salon",
    "wof:placetype":"venue"
},
  "geometry": {"coordinates":[-89.956858,35.959192],"type":"Point"}
}