{
  "type": "Feature",
  "properties": {
    "iso:country":"US",
    "sg:address":"7824 US Hwy 71",
    "sg:city":"Fort Smith",
    "sg:classifiers":[
        {
            "category":"Autos & Motor Vehicles",
            "subcategory":"Automobile Sales",
            "type":"Retail Goods"
        }
    ],
    "sg:phone":"+1 479 649 8227",
    "sg:postcode":"72908",
    "sg:province":"AR",
    "sg:tags":[
        "car",
        "dealer"
    ],
    "wof:name":"Floyd Traylor Used Cars",
    "wof:placetype":"venue"
},
  "geometry": {"coordinates":[-94.397912,35.310776],"type":"Point"}
}