{
  "type": "Feature",
  "properties": {
    "iso:country":"US",
    "sg:address":"3777 Harrison St",
    "sg:city":"Batesville",
    "sg:classifiers":[
        {
            "category":"Restaurant",
            "type":"Food & Drink"
        }
    ],
    "sg:phone":"+1 870 793 2022",
    "sg:postcode":"72501",
    "sg:province":"AR",
    "sg:tags":[
        "eating"
    ],
    "wof:name":"Fred's Fish House",
    "wof:placetype":"venue"
},
  "geometry": {"coordinates":[-91.597344,35.768845],"type":"Point"}
}