{
  "type": "Feature",
  "properties": {
    "iso:country":"US",
    "sg:address":"1721 Towson Ave",
    "sg:city":"Fort Smith",
    "sg:classifiers":[
        {
            "category":"Retail",
            "subcategory":"Auto Repair",
            "type":"Services"
        }
    ],
    "sg:phone":"+1 479 783 8505",
    "sg:postcode":"72901",
    "sg:province":"AR",
    "sg:tags":[
        "road"
    ],
    "wof:name":"Robert's Performance Wrecker",
    "wof:placetype":"venue"
},
  "geometry": {"coordinates":[-94.42146200000001,35.36757],"type":"Point"}
}