{
  "type": "Feature",
  "properties": {
    "iso:country":"US",
    "sg:address":"1104 Markham St",
    "sg:city":"Conway",
    "sg:classifiers":[
        {
            "category":"Professional",
            "type":"Services"
        },
        {
            "category":"Utilities",
            "subcategory":"Fuel Oil & Lpg",
            "type":"Services"
        },
        {
            "category":"Building & Trades",
            "subcategory":"Equipment Rental",
            "type":"Services"
        }
    ],
    "sg:phone":"+1 501 450 7721",
    "sg:postcode":"72032",
    "sg:province":"AR",
    "sg:tags":[
        "development",
        "field",
        "exploration",
        "gas"
    ],
    "wof:name":"Welltec",
    "wof:placetype":"venue"
},
  "geometry": {"coordinates":[-92.43991,35.093479],"type":"Point"}
}