{
  "type": "Feature",
  "properties": {
    "iso:country":"US",
    "sg:address":"14 Parkstone Cir",
    "sg:city":"N Little Rock",
    "sg:classifiers":[
        {
            "category":"Manufacturing",
            "subcategory":"Chemicals & Compounds",
            "type":"Manufacturing & Wholesale Goods"
        }
    ],
    "sg:phone":"+1 501 758 8635",
    "sg:postcode":"72116",
    "sg:province":"AR",
    "sg:tags":[
        "miller",
        "drug"
    ],
    "sg:website":"www.blansettpharmaceutical.com",
    "wof:name":"Blansett Pharmacal Co",
    "wof:placetype":"venue"
},
  "geometry": {"coordinates":[-92.222675,34.79811],"type":"Point"}
}