{
  "type": "Feature",
  "properties": {
    "iso:country":"US",
    "sg:address":"124 S Main St",
    "sg:city":"Spiro",
    "sg:classifiers":[
        {
            "category":"Retail",
            "subcategory":"Repair Shop",
            "type":"Services"
        }
    ],
    "sg:phone":"+1 918 962 2091",
    "sg:postcode":"74959",
    "sg:province":"OK",
    "sg:tags":[
        "television",
        "radio"
    ],
    "wof:name":"Adams TV Svc",
    "wof:placetype":"venue"
},
  "geometry": {"coordinates":[-94.621092,35.24081],"type":"Point"}
}