{
  "type": "Feature",
  "properties": {
    "addr:full":"795 N Broadway Ave Booneville AR 72927",
    "addr:housenumber":"795",
    "addr:postcode":"72927",
    "addr:street":"N Broadway Ave",
    "iso:country":"US",
    "sg:address":"795 N Broadway Ave",
    "sg:city":"Booneville",
    "sg:classifiers":[
        {
            "category":"Building & Trades",
            "subcategory":"Construction",
            "type":"Services"
        }
    ],
    "sg:phone":"+1 479 675 3514",
    "sg:postcode":"72927",
    "sg:province":"AR",
    "sg:tags":[
        "excavation",
        "contractor"
    ],
    "wof:name":"Napier Services",
    "wof:placetype":"venue"
},
  "geometry": {"coordinates":[-93.92153399999999,35.144421],"type":"Point"}
}