{
  "type": "Feature",
  "properties": {
    "iso:country":"US",
    "sg:address":"2770 Hwy 160 E",
    "sg:city":"Hermitage",
    "sg:classifiers":[
        {
            "category":"Freight",
            "type":"Transportation"
        }
    ],
    "sg:phone":"+1 870 463 8982",
    "sg:postcode":"71647",
    "sg:province":"AR",
    "sg:tags":[
        "operator",
        "local",
        "trucking"
    ],
    "wof:name":"Buford Sonny Rainey Truck",
    "wof:placetype":"venue"
},
  "geometry": {"coordinates":[-92.075102,33.347901],"type":"Point"}
}