{
  "type": "Feature",
  "properties": {
    "iso:country":"US",
    "sg:address":"108 W Walnut St",
    "sg:city":"Rogers",
    "sg:classifiers":[
        {
            "category":"Home & Garden",
            "subcategory":"Home Furnishings",
            "type":"Retail Goods"
        }
    ],
    "sg:phone":"+1 479 636 1173",
    "sg:postcode":"72756",
    "sg:province":"AR",
    "sg:tags":[
        "venetian",
        "blind"
    ],
    "wof:name":"Blind Co",
    "wof:placetype":"venue"
},
  "geometry": {"coordinates":[-94.117304,36.333018],"type":"Point"}
}