{
  "type": "Feature",
  "properties": {
    "iso:country":"US",
    "sg:address":"3733 N Business Dr",
    "sg:city":"Fayetteville",
    "sg:classifiers":[
        {
            "category":"Health Services",
            "subcategory":"Doctor",
            "type":"Services"
        }
    ],
    "sg:phone":"+1 479 571 8585",
    "sg:postcode":"72703",
    "sg:province":"AR",
    "sg:tags":[
        "physician",
        "surgeon"
    ],
    "wof:name":"R Douglas Vanderpool MD",
    "wof:placetype":"venue"
},
  "geometry": {"coordinates":[-94.130856,36.120042],"type":"Point"}
}