{
  "type": "Feature",
  "properties": {
    "iso:country":"US",
    "sg:address":"803 N Buerkle St",
    "sg:city":"Stuttgart",
    "sg:classifiers":[
        {
            "category":"Food & Beverages",
            "subcategory":"Groceries & Convenience Stores",
            "type":"Retail Goods"
        }
    ],
    "sg:phone":"+1 870 673 1717",
    "sg:postcode":"72160",
    "sg:province":"AR",
    "wof:name":"Alps Foods",
    "wof:placetype":"venue"
},
  "geometry": {"coordinates":[-91.55777500000001,34.509514],"type":"Point"}
}