{
  "type": "Feature",
  "properties": {
    "iso:country":"US",
    "sg:address":"201 E Illinois St",
    "sg:city":"Caraway",
    "sg:classifiers":[
        {
            "category":"Organizations",
            "subcategory":"Religious Organization",
            "type":"Services"
        }
    ],
    "sg:phone":"+1 870 482 3544",
    "sg:postcode":"72419",
    "sg:province":"AR",
    "sg:tags":[
        "church"
    ],
    "wof:name":"Caraway United Methodist Chr",
    "wof:placetype":"venue"
},
  "geometry": {"coordinates":[-90.321587,35.758713],"type":"Point"}
}