{
  "type": "Feature",
  "properties": {
    "iso:country":"US",
    "sg:address":"1202 W Commercial St",
    "sg:city":"Ozark",
    "sg:classifiers":[
        {
            "category":"Manufacturing",
            "subcategory":"Rubber & Plastics",
            "type":"Manufacturing & Wholesale Goods"
        },
        {
            "category":"Autos & Motor Vehicles",
            "subcategory":"Auto Supplies",
            "type":"Retail Goods"
        },
        {
            "category":"Retail",
            "subcategory":"Auto Repair",
            "type":"Services"
        }
    ],
    "sg:phone":"+1 479 667 2955",
    "sg:postcode":"72949",
    "sg:province":"AR",
    "sg:tags":[
        "recap",
        "retread",
        "tires-wholesale",
        "tire",
        "manufacturer"
    ],
    "sg:website":"http://www.coopertire.com/html/",
    "wof:name":"Steven's Tire Sales LLC",
    "wof:placetype":"venue"
},
  "geometry": {"coordinates":[-93.83696399999999,35.488052],"type":"Point"}
}