{
  "type": "Feature",
  "properties": {
    "iso:country":"US",
    "sg:address":"512 W 18th St",
    "sg:city":"North Little Rock",
    "sg:classifiers":[
        {
            "category":"Personal",
            "subcategory":"Beauty Salon",
            "type":"Services"
        }
    ],
    "sg:phone":"+1 501 375 6963",
    "sg:postcode":"72114",
    "sg:province":"AR",
    "sg:tags":[
        "shop"
    ],
    "wof:name":"New Attitude",
    "wof:placetype":"venue"
},
  "geometry": {"coordinates":[-92.272447,34.772055],"type":"Point"}
}