{
  "type": "Feature",
  "properties": {
    "addr:full":"109 Military Rd Jacksonville AR 72076",
    "addr:housenumber":"109",
    "addr:postcode":"72076",
    "addr:street":"Military Rd",
    "iso:country":"US",
    "sg:address":"109 Military Rd",
    "sg:city":"Jacksonville",
    "sg:classifiers":[
        {
            "category":"Organizations",
            "subcategory":"Community Association",
            "type":"Services"
        }
    ],
    "sg:phone":"+1 501 985 0522",
    "sg:postcode":"72076",
    "sg:province":"AR",
    "wof:name":"Arkansas Fraternal Order",
    "wof:placetype":"venue"
},
  "geometry": {"coordinates":[-92.112531,34.852048],"type":"Point"}
}