{
  "type": "Feature",
  "properties": {
    "iso:country":"US",
    "sg:address":"222 Webber St",
    "sg:city":"West Fork",
    "sg:classifiers":[
        {
            "category":"Recreation",
            "type":"Entertainment"
        },
        {
            "category":"Social Services",
            "type":"Services"
        }
    ],
    "sg:phone":"+1 479 839 3407",
    "sg:postcode":"72774",
    "sg:province":"AR",
    "sg:tags":[
        "hall",
        "center",
        "community",
        "auditorium"
    ],
    "wof:name":"West Fork Community Center",
    "wof:placetype":"venue"
},
  "geometry": {"coordinates":[-94.187518,35.927591],"type":"Point"}
}