{
  "type": "Feature",
  "properties": {
    "iso:country":"US",
    "sg:address":"1009 W Main St",
    "sg:city":"Walnut Ridge",
    "sg:classifiers":[
        {
            "category":"Social Services",
            "type":"Services"
        }
    ],
    "sg:phone":"+1 870 886 3553",
    "sg:postcode":"72476",
    "sg:province":"AR",
    "sg:tags":[
        "probation"
    ],
    "wof:name":"Probation & Parole Office",
    "wof:placetype":"venue"
},
  "geometry": {"coordinates":[-90.963943,36.074491],"type":"Point"}
}