{
  "type": "Feature",
  "properties": {
    "addr:full":"39 Courtside Loop Little Rock AR 72210",
    "addr:housenumber":"39",
    "addr:postcode":"72210",
    "addr:street":"Courtside Loop",
    "iso:country":"US",
    "sg:address":"39 Courtside Loop",
    "sg:city":"Little Rock",
    "sg:classifiers":[
        {
            "category":"Professional",
            "subcategory":"Business Services",
            "type":"Services"
        }
    ],
    "sg:phone":"+1 501 407 0613",
    "sg:postcode":"72210",
    "sg:province":"AR",
    "wof:name":"W&K Enterprises LLC",
    "wof:placetype":"venue"
},
  "geometry": {"coordinates":[-92.431223,34.658821],"type":"Point"}
}