{
  "type": "Feature",
  "properties": {
    "iso:country":"US",
    "sg:address":"207 Owens St",
    "sg:city":"Ward",
    "sg:classifiers":[
        {
            "category":"Sports & Exercise",
            "subcategory":"Sports Center",
            "type":"Entertainment"
        }
    ],
    "sg:phone":"+1 501 941 2727",
    "sg:postcode":"72176",
    "sg:province":"AR",
    "wof:name":"Bell's Farrier Service",
    "wof:placetype":"venue"
},
  "geometry": {"coordinates":[-91.949228,35.02887],"type":"Point"}
}