{
  "type": "Feature",
  "properties": {
    "iso:country":"US",
    "sg:address":"8925 Gardner Rd",
    "sg:city":"Little Rock",
    "sg:classifiers":[
        {
            "category":"Retail",
            "subcategory":"Repair Shop",
            "type":"Services"
        }
    ],
    "sg:phone":"+1 501 565 5155",
    "sg:postcode":"72209",
    "sg:province":"AR",
    "sg:tags":[
        "television",
        "radio"
    ],
    "wof:name":"Freddie's TV & VCR Repair",
    "wof:placetype":"venue"
},
  "geometry": {"coordinates":[-92.357941,34.667515],"type":"Point"}
}