{
  "type": "Feature",
  "properties": {
    "addr:full":"2405 Long Creek Rd Alpena AR 72611",
    "addr:housenumber":"2405",
    "addr:postcode":"72611",
    "addr:street":"Long Creek Rd",
    "iso:country":"US",
    "sg:address":"2405 Long Creek Rd",
    "sg:city":"Alpena",
    "sg:classifiers":[
        {
            "category":"Farming",
            "subcategory":"Livestock Farm",
            "type":"Manufacturing & Wholesale Goods"
        }
    ],
    "sg:phone":"+1 870 437 2436",
    "sg:postcode":"72611",
    "sg:province":"AR",
    "sg:tags":[
        "beef",
        "feedlot",
        "cattle"
    ],
    "wof:name":"Widners Long Creek Farms",
    "wof:placetype":"venue"
},
  "geometry": {"coordinates":[-93.288867,36.31208],"type":"Point"}
}