{
  "type": "Feature",
  "properties": {
    "iso:country":"US",
    "sg:address":"7608 Georgia Ridge Rd",
    "sg:city":"Alma",
    "sg:classifiers":[
        {
            "category":"Professional",
            "type":"Services"
        }
    ],
    "sg:phone":"+1 479 997 1566",
    "sg:postcode":"72921",
    "sg:province":"AR",
    "sg:tags":[
        "establishment"
    ],
    "wof:name":"Spinoli",
    "wof:placetype":"venue"
},
  "geometry": {"coordinates":[-94.137265,35.53365],"type":"Point"}
}