{
  "type": "Feature",
  "properties": {
    "addr:full":"34101 Kanis Rd Paron AR 72122",
    "addr:postcode":"34101;72122",
    "addr:street":"Kanis Rd",
    "iso:country":"US",
    "sg:address":"34101 Kanis Rd",
    "sg:city":"Paron",
    "sg:classifiers":[
        {
            "category":"Building & Trades",
            "subcategory":"Construction",
            "type":"Services"
        }
    ],
    "sg:phone":"+1 501 821 7133",
    "sg:postcode":"72122",
    "sg:province":"AR",
    "sg:tags":[
        "general",
        "contractor"
    ],
    "wof:name":"Boyles Construction",
    "wof:placetype":"venue"
},
  "geometry": {"coordinates":[-92.611587,34.788828],"type":"Point"}
}