{
  "type": "Feature",
  "properties": {
    "iso:country":"US",
    "sg:address":"3417 E 54th St",
    "sg:city":"Texarkana",
    "sg:classifiers":[
        {
            "category":"Real Estate",
            "subcategory":"Developer",
            "type":"Services"
        }
    ],
    "sg:phone":"+1 870 774 8001",
    "sg:postcode":"71854",
    "sg:province":"TX",
    "sg:website":"www.osbornedev.com",
    "wof:name":"Osborne Development",
    "wof:placetype":"venue"
},
  "geometry": {"coordinates":[-94.00607,33.474295],"type":"Point"}
}