{
  "type": "Feature",
  "properties": {
    "iso:country":"US",
    "sg:address":"199 Hwy 223 S",
    "sg:city":"Viola",
    "sg:classifiers":[
        {
            "category":"Recreation",
            "type":"Entertainment"
        }
    ],
    "sg:phone":"+1 870 458 2723",
    "sg:postcode":"72583",
    "sg:province":"AR",
    "sg:tags":[
        "center"
    ],
    "wof:name":"Viola Activity Ctr",
    "wof:placetype":"venue"
},
  "geometry": {"coordinates":[-91.982192,36.393696],"type":"Point"}
}