{
  "type": "Feature",
  "properties": {
    "addr:full":"1015 N Arkansas Ave Russellville AR 72801",
    "addr:housenumber":"1015",
    "addr:postcode":"72801",
    "addr:street":"N Arkansas Ave",
    "iso:country":"US",
    "sg:address":"1015 N Arkansas Ave",
    "sg:city":"Russellville",
    "sg:classifiers":[
        {
            "category":"Home & Garden",
            "subcategory":"Household Appliances",
            "type":"Retail Goods"
        }
    ],
    "sg:phone":"+1 479 967 7231",
    "sg:postcode":"72801",
    "sg:province":"AR",
    "sg:tags":[
        "cleaners",
        "vacuum"
    ],
    "wof:name":"Russellville Cleaning Systems",
    "wof:placetype":"venue"
},
  "geometry": {"coordinates":[-93.133473,35.288296],"type":"Point"}
}