{
  "type": "Feature",
  "properties": {
    "iso:country":"US",
    "sg:address":"207 E 15th St",
    "sg:city":"Little Rock",
    "sg:classifiers":[
        {
            "category":"Restaurant",
            "type":"Food & Drink"
        }
    ],
    "sg:phone":"+1 501 374 5707",
    "sg:postcode":"72202",
    "sg:province":"AR",
    "wof:name":"Lindsey's Hospitality House",
    "wof:placetype":"venue"
},
  "geometry": {"coordinates":[-92.270706,34.733976],"type":"Point"}
}