{
  "type": "Feature",
  "properties": {
    "iso:country":"US",
    "sg:address":"1301 W 40th Ave",
    "sg:city":"Pine Bluff",
    "sg:classifiers":[
        {
            "category":"Sports & Exercise",
            "subcategory":"Gym",
            "type":"Entertainment"
        }
    ],
    "sg:phone":"+1 870 541 7890",
    "sg:postcode":"71603",
    "sg:province":"AR",
    "sg:tags":[
        "medical",
        "fitness",
        "physical",
        "facility"
    ],
    "wof:name":"Jrmc Wellness Center",
    "wof:placetype":"venue"
},
  "geometry": {"coordinates":[-92.019982,34.189119],"type":"Point"}
}