{
  "type": "Feature",
  "properties": {
    "addr:full":"6821 Jenny Lind Rd Fort Smith AR 72908",
    "addr:housenumber":"6821",
    "addr:postcode":"72908",
    "addr:street":"Jenny Lind Rd",
    "iso:country":"US",
    "sg:address":"6821 Jenny Lind Rd",
    "sg:city":"Fort Smith",
    "sg:classifiers":[
        {
            "category":"Government",
            "subcategory":"Office",
            "type":"Public Place"
        }
    ],
    "sg:phone":"+1 479 783 6464",
    "sg:postcode":"72908",
    "sg:province":"AR",
    "sg:tags":[
        "city",
        "program"
    ],
    "wof:name":"Fort Smith Transportation Dept",
    "wof:placetype":"venue"
},
  "geometry": {"coordinates":[-94.413054,35.316089],"type":"Point"}
}