{
  "type": "Feature",
  "properties": {
    "iso:country":"US",
    "sg:address":"100 Ashley Ln",
    "sg:city":"El Dorado",
    "sg:classifiers":[
        {
            "category":"Wholesale",
            "subcategory":"Hardware",
            "type":"Manufacturing & Wholesale Goods"
        }
    ],
    "sg:phone":"+1 870 863 4800",
    "sg:postcode":"71730",
    "sg:province":"AR",
    "sg:tags":[
        "fastener"
    ],
    "sg:website":"www.fastenal.com",
    "wof:name":"Fastenal Co",
    "wof:placetype":"venue"
},
  "geometry": {"coordinates":[-92.61850200000001,33.191808],"type":"Point"}
}