{
  "type": "Feature",
  "properties": {
    "addr:full":"3203 NE Red Hawk Dr Bentonville AR 72712",
    "addr:housenumber":"3203",
    "addr:postcode":"72712",
    "addr:street":"Ne Red Hawk Dr",
    "iso:country":"US",
    "sg:address":"3203 NE Red Hawk Dr",
    "sg:city":"Bentonville",
    "sg:classifiers":[
        {
            "category":"Professional",
            "subcategory":"Management & Consulting",
            "type":"Services"
        }
    ],
    "sg:phone":"+1 479 271 0067",
    "sg:postcode":"72712",
    "sg:province":"AR",
    "wof:name":"Rew Marketing",
    "wof:placetype":"venue"
},
  "geometry": {"coordinates":[-94.174284,36.384738],"type":"Point"}
}