{
  "type": "Feature",
  "properties": {
    "addr:full":"1009 N Molly Ct Fayetteville AR 72701",
    "addr:housenumber":"1009",
    "addr:postcode":"72701",
    "addr:street":"N Molly Ct",
    "iso:country":"US",
    "sg:address":"1009 N Molly Ct",
    "sg:city":"Fayetteville",
    "sg:classifiers":[
        {
            "category":"Real Estate",
            "subcategory":"Real Estate Operator",
            "type":"Services"
        }
    ],
    "sg:phone":"+1 479 443 3103",
    "sg:postcode":"72701",
    "sg:province":"AR",
    "sg:tags":[
        "townhouses"
    ],
    "wof:name":"Molly Court Town Homes",
    "wof:placetype":"venue"
},
  "geometry": {"coordinates":[-94.167649,36.07648],"type":"Point"}
}