{
  "type": "Feature",
  "properties": {
    "iso:country":"US",
    "sg:address":"400 Helen St",
    "sg:city":"West Helena",
    "sg:classifiers":[
        {
            "category":"Professional",
            "subcategory":"Accounting & Tax Preparation",
            "type":"Services"
        }
    ],
    "sg:phone":"+1 870 572 9800",
    "sg:postcode":"72390",
    "sg:province":"AR",
    "sg:tags":[
        "accountant"
    ],
    "wof:name":"Van Goode Jr CPA",
    "wof:placetype":"venue"
},
  "geometry": {"coordinates":[-90.645172,34.551735],"type":"Point"}
}