{
  "type": "Feature",
  "properties": {
    "addr:full":"5308 Village Pkwy Rogers AR 72758",
    "addr:housenumber":"5308",
    "addr:postcode":"72758",
    "addr:street":"Village Pkwy",
    "iso:country":"US",
    "sg:address":"5308 Village Pkwy",
    "sg:city":"Rogers",
    "sg:classifiers":[
        {
            "category":"Shopping",
            "subcategory":"Computers & Home Electronics",
            "type":"Retail Goods"
        }
    ],
    "sg:phone":"+1 479 254 0114",
    "sg:postcode":"72758",
    "sg:province":"AR",
    "sg:tags":[
        "software"
    ],
    "wof:name":"Vision Chain",
    "wof:placetype":"venue"
},
  "geometry": {"coordinates":[-94.188159,36.317338],"type":"Point"}
}