{
  "type": "Feature",
  "properties": {
    "iso:country":"US",
    "sg:address":"157 Madison St",
    "sg:city":"Nashville",
    "sg:classifiers":[
        {
            "category":"Personal",
            "subcategory":"Beauty Salon",
            "type":"Services"
        }
    ],
    "sg:phone":"+1 870 845 2497",
    "sg:postcode":"71852",
    "sg:province":"AR",
    "sg:tags":[
        "hair",
        "stylist"
    ],
    "wof:name":"Sandra's Hair Salon",
    "wof:placetype":"venue"
},
  "geometry": {"coordinates":[-93.949562,34.030884],"type":"Point"}
}