{
  "type": "Feature",
  "properties": {
    "addr:full":"501 W 2nd Ave Pine Bluff AR 71601",
    "addr:housenumber":"501",
    "addr:postcode":"71601",
    "addr:street":"W 2Nd Ave",
    "iso:country":"US",
    "sg:address":"501 W 2nd Ave",
    "sg:city":"Pine Bluff",
    "sg:classifiers":[
        {
            "category":"Social Services",
            "subcategory":"Child Care",
            "type":"Services"
        }
    ],
    "sg:phone":"+1 870 536 3636",
    "sg:postcode":"71601",
    "sg:province":"AR",
    "sg:tags":[
        "day"
    ],
    "wof:name":"Bright Start Learning Developm",
    "wof:placetype":"venue"
},
  "geometry": {"coordinates":[-92.008562,34.228404],"type":"Point"}
}