{
  "type": "Feature",
  "properties": {
    "addr:full":"915 Main St Melbourne AR 72556",
    "addr:housenumber":"915",
    "addr:postcode":"72556",
    "addr:street":"Main St",
    "iso:country":"US",
    "sg:address":"915 Main St",
    "sg:city":"Melbourne",
    "sg:classifiers":[
        {
            "category":"Education",
            "subcategory":"Library",
            "type":"Public Place"
        }
    ],
    "sg:phone":"+1 870 368 7467",
    "sg:postcode":"72556",
    "sg:province":"AR",
    "wof:name":"Melbourne Public Library",
    "wof:placetype":"venue"
},
  "geometry": {"coordinates":[-91.888769,36.058707],"type":"Point"}
}