{
  "type": "Feature",
  "properties": {
    "addr:full":"718 Sfc 704 Forrest City AR 72335",
    "addr:housenumber":"718;704",
    "addr:postcode":"72335",
    "addr:street":"Sfc",
    "iso:country":"US",
    "sg:address":"718 Sfc 704",
    "sg:city":"Forrest City",
    "sg:classifiers":[
        {
            "category":"Organizations",
            "subcategory":"Religious Organization",
            "type":"Services"
        }
    ],
    "sg:phone":"+1 870 633 6797",
    "sg:postcode":"72335",
    "sg:province":"AR",
    "sg:tags":[
        "church"
    ],
    "wof:name":"Valley View Christian Ctr",
    "wof:placetype":"venue"
},
  "geometry": {"coordinates":[-90.75021599999999,34.990803],"type":"Point"}
}