{
  "type": "Feature",
  "properties": {
    "iso:country":"US",
    "sg:address":"105 Stoney Point Ests",
    "sg:city":"Beebe",
    "sg:classifiers":[
        {
            "category":"Wholesale",
            "subcategory":"Sporting Goods",
            "type":"Manufacturing & Wholesale Goods"
        }
    ],
    "sg:phone":"+1 501 882 2026",
    "sg:postcode":"72012",
    "sg:province":"AR",
    "wof:name":"Echo Calls",
    "wof:placetype":"venue"
},
  "geometry": {"coordinates":[-91.94377,35.088639],"type":"Point"}
}