{
  "type": "Feature",
  "properties": {
    "iso:country":"US",
    "sg:address":"606 Hornbeck Ave",
    "sg:city":"Mena",
    "sg:classifiers":[
        {
            "category":"Manufacturing",
            "subcategory":"Lumber",
            "type":"Manufacturing & Wholesale Goods"
        }
    ],
    "sg:phone":"+1 479 394 3820",
    "sg:postcode":"71953",
    "sg:province":"OK",
    "sg:tags":[
        "government"
    ],
    "wof:name":"US Forest Svc Work Ctr",
    "wof:placetype":"venue"
},
  "geometry": {"coordinates":[-94.22555199999999,34.583098],"type":"Point"}
}