{
  "type": "Feature",
  "properties": {
    "addr:full":"1215 W Hillsboro St El Dorado AR 71730",
    "addr:housenumber":"1215",
    "addr:postcode":"71730",
    "addr:street":"W Hillsboro St",
    "iso:country":"US",
    "sg:address":"1215 W Hillsboro St",
    "sg:city":"El Dorado",
    "sg:classifiers":[
        {
            "category":"Bars & Pubs",
            "type":"Food & Drink"
        }
    ],
    "sg:phone":"+1 870 862 1118",
    "sg:postcode":"71730",
    "sg:province":"AR",
    "sg:tags":[
        "drinking"
    ],
    "wof:name":"Trackside",
    "wof:placetype":"venue"
},
  "geometry": {"coordinates":[-92.68012400000001,33.207481],"type":"Point"}
}