{
  "type": "Feature",
  "properties": {
    "addr:full":"715 Hobson Ave Hot Springs National Park AR 71913",
    "addr:housenumber":"715",
    "addr:postcode":"71913",
    "addr:street":"Hobson Ave",
    "iso:country":"US",
    "sg:address":"715 Hobson Ave",
    "sg:city":"Hot Springs National Park",
    "sg:classifiers":[
        {
            "category":"Professional",
            "subcategory":"Accounting & Tax Preparation",
            "type":"Services"
        }
    ],
    "sg:phone":"+1 501 321 9999",
    "sg:postcode":"71913",
    "sg:province":"AR",
    "wof:name":"Goslee and Goslee Accountants",
    "wof:placetype":"venue"
},
  "geometry": {"coordinates":[-93.067407,34.497957],"type":"Point"}
}