{
  "type": "Feature",
  "properties": {
    "iso:country":"US",
    "sg:address":"1002 1st St",
    "sg:city":"Horseshoe Bend",
    "sg:classifiers":[
        {
            "category":"Organizations",
            "subcategory":"Religious Organization",
            "type":"Services"
        }
    ],
    "sg:phone":"+1 870 670 5896",
    "sg:postcode":"72512",
    "sg:province":"AR",
    "sg:tags":[
        "church"
    ],
    "wof:name":"St Mary Of The Mount Catholic",
    "wof:placetype":"venue"
},
  "geometry": {"coordinates":[-91.756615,36.214683],"type":"Point"}
}