{
  "type": "Feature",
  "properties": {
    "iso:country":"US",
    "sg:address":"101 N Spring St",
    "sg:city":"Searcy",
    "sg:classifiers":[
        {
            "category":"Utilities",
            "subcategory":"Telephone",
            "type":"Services"
        }
    ],
    "sg:phone":"+1 501 268 1417",
    "sg:postcode":"72143",
    "sg:province":"AR",
    "sg:tags":[
        "mobile",
        "cellular"
    ],
    "wof:name":"Ozark Mobilephone",
    "wof:placetype":"venue"
},
  "geometry": {"coordinates":[-91.737549,35.249641],"type":"Point"}
}