{
  "type": "Feature",
  "properties": {
    "iso:country":"US",
    "sg:address":"1240 W Olive St",
    "sg:city":"Rogers",
    "sg:classifiers":[
        {
            "category":"Retail",
            "subcategory":"Self-service Laundry",
            "type":"Services"
        }
    ],
    "sg:phone":"+1 479 636 2589",
    "sg:postcode":"72756",
    "sg:province":"AR",
    "wof:name":"Neway Self Svc Laundry Ctr",
    "wof:placetype":"venue"
},
  "geometry": {"coordinates":[-94.131484,36.340993],"type":"Point"}
}