{
  "type": "Feature",
  "properties": {
    "addr:full":"117 E 6th St Mountain Home AR 72653",
    "addr:housenumber":"117",
    "addr:postcode":"72653",
    "addr:street":"E 6Th St",
    "iso:country":"US",
    "sg:address":"117 E 6th St",
    "sg:city":"Mountain Home",
    "sg:classifiers":[
        {
            "category":"Social Services",
            "type":"Services"
        }
    ],
    "sg:phone":"+1 870 424 7576",
    "sg:postcode":"72653",
    "sg:province":"AR",
    "sg:tags":[
        "crisis",
        "intervention"
    ],
    "wof:name":"Serenity Inc",
    "wof:placetype":"venue"
},
  "geometry": {"coordinates":[-92.383726,36.335467],"type":"Point"}
}