{
  "type": "Feature",
  "properties": {
    "addr:full":"620 Louis St El Dorado AR 71730",
    "addr:housenumber":"620",
    "addr:postcode":"71730",
    "addr:street":"Louis St",
    "iso:country":"US",
    "sg:address":"620 Louis St",
    "sg:city":"El Dorado",
    "sg:classifiers":[
        {
            "category":"Arts & Performance",
            "subcategory":"Theater",
            "type":"Entertainment"
        }
    ],
    "sg:phone":"+1 870 881 8302",
    "sg:postcode":"71730",
    "sg:province":"AR",
    "sg:tags":[
        "group"
    ],
    "wof:name":"Mark White",
    "wof:placetype":"venue"
},
  "geometry": {"coordinates":[-92.643475,33.205752],"type":"Point"}
}