{
  "type": "Feature",
  "properties": {
    "iso:country":"US",
    "sg:address":"1360 US Hwy 49 S",
    "sg:city":"Paragould",
    "sg:classifiers":[
        {
            "category":"Retail",
            "subcategory":"Auto Rental",
            "type":"Services"
        }
    ],
    "sg:phone":"+1 870 335 2208",
    "sg:postcode":"72450",
    "sg:province":"AR",
    "sg:tags":[
        "renting",
        "truck",
        "leasing"
    ],
    "wof:name":"U-Haul Co",
    "wof:placetype":"venue"
},
  "geometry": {"coordinates":[-90.507211,36.048595],"type":"Point"}
}