{
  "type": "Feature",
  "properties": {
    "addr:full":"5411 Southwest Dr Jonesboro AR 72404",
    "addr:housenumber":"5411",
    "addr:postcode":"72404",
    "addr:street":"Southwest Dr",
    "iso:country":"US",
    "sg:address":"5411 Southwest Dr",
    "sg:city":"Jonesboro",
    "sg:classifiers":[
        {
            "category":"Food & Beverages",
            "subcategory":"Groceries & Convenience Stores",
            "type":"Retail Goods"
        }
    ],
    "sg:phone":"+1 870 933 6447",
    "sg:postcode":"72404",
    "sg:province":"AR",
    "wof:name":"Deb's Place",
    "wof:placetype":"venue"
},
  "geometry": {"coordinates":[-90.75253499999999,35.777916],"type":"Point"}
}