{
  "type": "Feature",
  "properties": {
    "iso:country":"US",
    "sg:address":"155 Bradley Road 186",
    "sg:city":"Hermitage",
    "sg:classifiers":[
        {
            "category":"Organizations",
            "subcategory":"Religious Organization",
            "type":"Services"
        }
    ],
    "sg:phone":"+1 870 463 8220",
    "sg:postcode":"71647",
    "sg:province":"AR",
    "sg:tags":[
        "church"
    ],
    "wof:name":"Landmark Baptist Church",
    "wof:placetype":"venue"
},
  "geometry": {"coordinates":[-92.21658499999999,33.446492],"type":"Point"}
}