{
  "type": "Feature",
  "properties": {
    "iso:country":"US",
    "sg:address":"11225 Huron Ln",
    "sg:city":"Little Rock",
    "sg:classifiers":[
        {
            "category":"Professional",
            "subcategory":"Business Services",
            "type":"Services"
        }
    ],
    "sg:phone":"+1 501 823 4729",
    "sg:postcode":"72211",
    "sg:province":"AR",
    "sg:tags":[
        "broker"
    ],
    "wof:name":"Ray M & A",
    "wof:placetype":"venue"
},
  "geometry": {"coordinates":[-92.398692,34.76665],"type":"Point"}
}