{
  "type": "Feature",
  "properties": {
    "addr:full":"703 Hwy 64 E Conway AR 72032",
    "addr:housenumber":"703",
    "addr:postcode":"72032",
    "addr:street":"Hwy 64 E",
    "iso:country":"US",
    "sg:address":"703 Hwy 64 E",
    "sg:city":"Conway",
    "sg:classifiers":[
        {
            "category":"Wholesale",
            "subcategory":"Motor Vehicles",
            "type":"Manufacturing & Wholesale Goods"
        }
    ],
    "sg:phone":"+1 501 796 2812",
    "sg:postcode":"72032",
    "sg:province":"AR",
    "sg:tags":[
        "auction",
        "automobile"
    ],
    "sg:website":"www.copart.com",
    "wof:name":"Copart Salvage Auto Auctions",
    "wof:placetype":"venue"
},
  "geometry": {"coordinates":[-92.29638300000001,35.078574],"type":"Point"}
}