{
  "type": "Feature",
  "properties": {
    "addr:full":"406 W Central Ave Harrison AR 72601",
    "addr:housenumber":"406",
    "addr:postcode":"72601",
    "addr:street":"W Central Ave",
    "iso:country":"US",
    "sg:address":"406 W Central Ave",
    "sg:city":"Harrison",
    "sg:classifiers":[
        {
            "category":"Restaurant",
            "type":"Food & Drink"
        }
    ],
    "sg:menulink":"http://www.allmenus.com/ar/south-harrison/111689-subway/menu/",
    "sg:phone":"+1 870 743 3834",
    "sg:postcode":"72601",
    "sg:province":"AR",
    "sg:tags":[
        "american",
        "sandwich"
    ],
    "wof:name":"Subway",
    "wof:placetype":"venue"
},
  "geometry": {"coordinates":[-93.105492,36.229175],"type":"Point"}
}