{
  "type": "Feature",
  "properties": {
    "iso:country":"US",
    "sg:address":"5020 North Shore Drive, Ste 1",
    "sg:city":"North Little Rock",
    "sg:classifiers":[
        {
            "category":"Professional",
            "subcategory":"Computer Services",
            "type":"Services"
        }
    ],
    "sg:phone":"+1 501 221 4112",
    "sg:postcode":"72118",
    "sg:province":"AR",
    "sg:tags":[
        "it-management",
        "consultants"
    ],
    "sg:website":"http://www.edafio.com",
    "wof:name":"Edafio Technologies",
    "wof:placetype":"venue"
},
  "geometry": {"coordinates":[-92.27634399999999,34.793687],"type":"Point"}
}