{
  "type": "Feature",
  "properties": {
    "iso:country":"US",
    "sg:address":"3865 Highway 278 W",
    "sg:city":"Hope",
    "sg:classifiers":[
        {
            "category":"Farming",
            "subcategory":"Farm",
            "type":"Manufacturing & Wholesale Goods"
        }
    ],
    "sg:phone":"+1 870 777 2245",
    "sg:postcode":"71801",
    "sg:province":"AR",
    "wof:name":"Glanton Plantation & Farms",
    "wof:placetype":"venue"
},
  "geometry": {"coordinates":[-93.629727,33.688593],"type":"Point"}
}