{
  "type": "Feature",
  "properties": {
    "iso:country":"US",
    "sg:address":"2200 State Hwy 265 Spr",
    "sg:city":"Springdale",
    "sg:classifiers":[
        {
            "category":"Retail",
            "subcategory":"Laundry & Dry Cleaning",
            "type":"Services"
        }
    ],
    "sg:phone":"+1 479 750 3352",
    "sg:postcode":"72764",
    "sg:province":"AR",
    "sg:tags":[
        "uniform",
        "supply"
    ],
    "wof:name":"Aramark Uniform Svc",
    "wof:placetype":"venue"
},
  "geometry": {"coordinates":[-94.103457,36.184343],"type":"Point"}
}