{
  "type": "Feature",
  "properties": {
    "iso:country":"US",
    "sg:address":"15 Green Valley Dr",
    "sg:city":"Mountain Home",
    "sg:classifiers":[
        {
            "category":"Health Services",
            "subcategory":"Doctor",
            "type":"Services"
        }
    ],
    "sg:phone":"+1 870 425 6991",
    "sg:postcode":"72653",
    "sg:province":"AR",
    "sg:tags":[
        "physician",
        "medical",
        "surgeon"
    ],
    "wof:name":"Abraham Medical Center",
    "wof:placetype":"venue"
},
  "geometry": {"coordinates":[-92.384189,36.353555],"type":"Point"}
}