{
  "type": "Feature",
  "properties": {
    "iso:country":"US",
    "sg:address":"3201 State Hwy 25 B N",
    "sg:city":"Heber Springs",
    "sg:classifiers":[
        {
            "category":"Shopping",
            "type":"Retail Goods"
        }
    ],
    "sg:phone":"+1 501 362 0015",
    "sg:postcode":"72543",
    "sg:province":"AR",
    "sg:tags":[
        "feed",
        "farm",
        "supply"
    ],
    "wof:name":"Caldwell Feed",
    "wof:placetype":"venue"
},
  "geometry": {"coordinates":[-92.018022,35.516118],"type":"Point"}
}