{
  "type": "Feature",
  "properties": {
    "iso:country":"US",
    "sg:address":"403 W Allen Ave",
    "sg:city":"Jonesboro",
    "sg:classifiers":[
        {
            "category":"Organizations",
            "subcategory":"Religious Organization",
            "type":"Services"
        }
    ],
    "sg:phone":"+1 870 935 2334",
    "sg:postcode":"72401",
    "sg:province":"AR",
    "sg:tags":[
        "church"
    ],
    "wof:name":"New Mt Zion Baptist Church",
    "wof:placetype":"venue"
},
  "geometry": {"coordinates":[-90.71276,35.848985],"type":"Point"}
}