{
  "type": "Feature",
  "properties": {
    "addr:full":"227 Apricot Ln Berryville AR 72616",
    "addr:housenumber":"227",
    "addr:postcode":"72616",
    "addr:street":"Apricot Ln",
    "iso:country":"US",
    "sg:address":"227 Apricot Ln",
    "sg:city":"Berryville",
    "sg:classifiers":[
        {
            "category":"Retail",
            "subcategory":"Repair Shop",
            "type":"Services"
        }
    ],
    "sg:phone":"+1 870 423 2037",
    "sg:postcode":"72616",
    "sg:province":"AR",
    "sg:tags":[
        "welding"
    ],
    "wof:name":"Warren Welding Inc",
    "wof:placetype":"venue"
},
  "geometry": {"coordinates":[-93.558497,36.324574],"type":"Point"}
}