{
  "type": "Feature",
  "properties": {
    "iso:country":"US",
    "sg:address":"110 Mount Tabor St",
    "sg:city":"Hot Springs",
    "sg:classifiers":[
        {
            "category":"Restaurant",
            "type":"Food & Drink"
        }
    ],
    "sg:phone":"+1 501 760 3221",
    "sg:postcode":"71913",
    "sg:province":"AR",
    "sg:tags":[
        "caterer"
    ],
    "wof:name":"Thyme To Savor",
    "wof:placetype":"venue"
},
  "geometry": {"coordinates":[-93.111349,34.492945],"type":"Point"}
}