{
  "type": "Feature",
  "properties": {
    "iso:country":"US",
    "sg:address":"14600 State Hwy 107",
    "sg:city":"Gravel Ridge",
    "sg:classifiers":[
        {
            "category":"Banks & Credit Unions",
            "subcategory":"Bank",
            "type":"Services"
        }
    ],
    "sg:phone":"+1 501 834 2555",
    "sg:postcode":"72076",
    "sg:province":"AR",
    "sg:tags":[
        "commercial"
    ],
    "wof:name":"Eagle Bank & Trust Co",
    "wof:placetype":"venue"
},
  "geometry": {"coordinates":[-92.19164499999999,34.880235],"type":"Point"}
}