{
  "type": "Feature",
  "properties": {
    "iso:country":"US",
    "sg:address":"101 S Broadway St",
    "sg:city":"Hughes",
    "sg:classifiers":[
        {
            "category":"Utilities",
            "subcategory":"Water",
            "type":"Services"
        }
    ],
    "sg:phone":"+1 870 339 2094",
    "sg:postcode":"72348",
    "sg:province":"AR",
    "sg:tags":[
        "company",
        "sewage"
    ],
    "wof:name":"Hughes Community Water",
    "wof:placetype":"venue"
},
  "geometry": {"coordinates":[-90.471301,34.953441],"type":"Point"}
}