{
  "type": "Feature",
  "properties": {
    "iso:country":"US",
    "sg:address":"16315 Crystal Valley Rd",
    "sg:city":"Little Rock",
    "sg:classifiers":[
        {
            "category":"Professional",
            "subcategory":"Business Services",
            "type":"Services"
        }
    ],
    "sg:phone":"+1 501 407 8180",
    "sg:postcode":"72210",
    "sg:province":"AR",
    "sg:tags":[
        "equipment",
        "mfg",
        "lighting",
        "vehicle"
    ],
    "wof:name":"G P S International Consulting",
    "wof:placetype":"venue"
},
  "geometry": {"coordinates":[-92.443033,34.686376],"type":"Point"}
}