{
  "type": "Feature",
  "properties": {
    "iso:country":"US",
    "sg:address":"8601 N Highway 79",
    "sg:city":"Sherrill",
    "sg:classifiers":[
        {
            "category":"Farming",
            "subcategory":"Farm",
            "type":"Manufacturing & Wholesale Goods"
        }
    ],
    "sg:phone":"+1 870 766 8973",
    "sg:postcode":"72152",
    "sg:province":"AR",
    "wof:name":"Garrett Farm",
    "wof:placetype":"venue"
},
  "geometry": {"coordinates":[-91.961197,34.300797],"type":"Point"}
}