{
  "type": "Feature",
  "properties": {
    "iso:country":"US",
    "sg:address":"4600 Slaytonville Rd",
    "sg:city":"Hackett",
    "sg:classifiers":[
        {
            "category":"Retail",
            "subcategory":"Auto Repair",
            "type":"Services"
        }
    ],
    "sg:phone":"+1 501 638 7435",
    "sg:postcode":"72937",
    "sg:province":"AR",
    "sg:tags":[
        "automotive"
    ],
    "wof:name":"Razorback Radiator",
    "wof:placetype":"venue"
},
  "geometry": {"coordinates":[-94.411454,35.153697],"type":"Point"}
}