{
  "type": "Feature",
  "properties": {
    "addr:full":"14639 S Wimpy Jones Rd Garfield AR 72732",
    "addr:housenumber":"14639",
    "addr:postcode":"72732",
    "addr:street":"S Wimpy Jones Rd",
    "iso:country":"US",
    "sg:address":"14639 S Wimpy Jones Rd",
    "sg:city":"Garfield",
    "sg:classifiers":[
        {
            "category":"Government",
            "subcategory":"Fire Station",
            "type":"Public Place"
        }
    ],
    "sg:phone":"+1 479 359 3134",
    "sg:postcode":"72732",
    "sg:province":"AR",
    "sg:tags":[
        "department"
    ],
    "wof:name":"NEBCO",
    "wof:placetype":"venue"
},
  "geometry": {"coordinates":[-93.981877,36.443661],"type":"Point"}
}