{
  "type": "Feature",
  "properties": {
    "iso:country":"US",
    "sg:address":"400 Hardin Rd",
    "sg:city":"Little Rock",
    "sg:classifiers":[
        {
            "category":"Wholesale",
            "subcategory":"Electrical",
            "type":"Manufacturing & Wholesale Goods"
        }
    ],
    "sg:phone":"+1 877 728 3191",
    "sg:postcode":"72211",
    "sg:province":"AR",
    "sg:tags":[
        "electronic",
        "merchandise"
    ],
    "wof:name":"Expanets Inc",
    "wof:placetype":"venue"
},
  "geometry": {"coordinates":[-92.398459,34.74865],"type":"Point"}
}