{
  "type": "Feature",
  "properties": {
    "iso:country":"US",
    "sg:address":"300 W Emerson St",
    "sg:city":"Paragould",
    "sg:classifiers":[
        {
            "category":"Banks & Credit Unions",
            "subcategory":"Financial Services",
            "type":"Services"
        }
    ],
    "sg:phone":"+1 870 236 7623",
    "sg:postcode":"72450",
    "sg:province":"AR",
    "sg:tags":[
        "company",
        "holding"
    ],
    "wof:name":"Spring River Bankshares",
    "wof:placetype":"venue"
},
  "geometry": {"coordinates":[-90.489437,36.055569],"type":"Point"}
}