{
  "type": "Feature",
  "properties": {
    "iso:country":"US",
    "sg:address":"207 Jones Ln",
    "sg:city":"Morrilton",
    "sg:classifiers":[
        {
            "category":"Building & Trades",
            "subcategory":"Landscaping Services",
            "type":"Services"
        }
    ],
    "sg:phone":"+1 501 727 5567",
    "sg:postcode":"72110",
    "sg:province":"AR",
    "sg:tags":[
        "grass"
    ],
    "wof:name":"Jones Cecil & Sons Sod Farms",
    "wof:placetype":"venue"
},
  "geometry": {"coordinates":[-92.89108,35.145658],"type":"Point"}
}