{
  "type": "Feature",
  "properties": {
    "addr:full":"2407 NW Linebarger Ln Bentonville AR 72712",
    "addr:housenumber":"2407",
    "addr:postcode":"72712",
    "addr:street":"Nw Linebarger Ln",
    "iso:country":"US",
    "sg:address":"2407 NW Linebarger Ln",
    "sg:city":"Bentonville",
    "sg:classifiers":[
        {
            "category":"Building & Trades",
            "subcategory":"Construction",
            "type":"Services"
        }
    ],
    "sg:phone":"+1 479 271 6069",
    "sg:postcode":"72712",
    "sg:province":"AR",
    "sg:tags":[
        "excavating",
        "contractor"
    ],
    "wof:name":"Cooper Excavating Inc",
    "wof:placetype":"venue"
},
  "geometry": {"coordinates":[-94.21360799999999,36.401273],"type":"Point"}
}