{
  "type": "Feature",
  "properties": {
    "addr:full":"2807 W 17th St Russellville AR 72802",
    "addr:housenumber":"2807",
    "addr:postcode":"72802",
    "addr:street":"W 17Th St",
    "iso:country":"US",
    "sg:address":"2807 W 17th St",
    "sg:city":"Russellville",
    "sg:classifiers":[
        {
            "category":"Freight",
            "type":"Transportation"
        }
    ],
    "sg:phone":"+1 479 967 9874",
    "sg:postcode":"72802",
    "sg:province":"AR",
    "sg:tags":[
        "general"
    ],
    "wof:name":"Burns Storage Buildings",
    "wof:placetype":"venue"
},
  "geometry": {"coordinates":[-93.16307399999999,35.263625],"type":"Point"}
}