{
  "type": "Feature",
  "properties": {
    "addr:full":"19 S Block Ave Fayetteville AR 72701",
    "addr:housenumber":"19",
    "addr:postcode":"72701",
    "addr:street":"S Block Ave",
    "iso:country":"US",
    "sg:address":"19 S Block Ave",
    "sg:city":"Fayetteville",
    "sg:classifiers":[
        {
            "category":"Professional",
            "subcategory":"Business Services",
            "type":"Services"
        }
    ],
    "sg:phone":"+1 479 442 4999",
    "sg:postcode":"72701",
    "sg:province":"AR",
    "sg:tags":[
        "interior",
        "consultant",
        "design",
        "decorator"
    ],
    "wof:name":"Kimberly Harper Interiors",
    "wof:placetype":"venue"
},
  "geometry": {"coordinates":[-94.16063200000001,36.062059],"type":"Point"}
}