{
  "type": "Feature",
  "properties": {
    "iso:country":"US",
    "sg:address":"209 W Sunbridge Dr",
    "sg:city":"Fayetteville",
    "sg:classifiers":[
        {
            "category":"Shopping",
            "subcategory":"Clothing, Apparel, & Fashions",
            "type":"Retail Goods"
        }
    ],
    "sg:phone":"+1 479 521 6340",
    "sg:postcode":"72703",
    "sg:province":"AR",
    "sg:tags":[
        "various",
        "sportswear",
        "camping"
    ],
    "wof:name":"Packrat Outdoor Center Inc",
    "wof:placetype":"venue"
},
  "geometry": {"coordinates":[-94.158769,36.097925],"type":"Point"}
}