{
  "type": "Feature",
  "properties": {
    "iso:country":"US",
    "sg:address":"109 N Jefferson",
    "sg:city":"Magnolia",
    "sg:classifiers":[
        {
            "category":"Shopping",
            "subcategory":"Clothing, Apparel, & Fashions",
            "type":"Retail Goods"
        },
        {
            "category":"Shopping",
            "subcategory":"Shoes",
            "type":"Retail Goods"
        }
    ],
    "sg:phone":"+1 870 234 2932",
    "sg:postcode":"71753",
    "sg:province":"AR",
    "sg:tags":[
        "apparel",
        "store",
        "women's"
    ],
    "wof:name":"Buffaloe's 2 Dept Store",
    "wof:placetype":"venue"
},
  "geometry": {"coordinates":[-93.241409,33.267216],"type":"Point"}
}