{
  "type": "Feature",
  "properties": {
    "addr:full":"104 SE Executive Dr Bentonville AR 72712",
    "addr:housenumber":"104",
    "addr:postcode":"72712",
    "addr:street":"Se Executive Dr",
    "iso:country":"US",
    "sg:address":"104 SE Executive Dr",
    "sg:city":"Bentonville",
    "sg:classifiers":[
        {
            "category":"Manufacturing",
            "subcategory":"Petroleum Products",
            "type":"Manufacturing & Wholesale Goods"
        }
    ],
    "sg:phone":"+1 479 464 8808",
    "sg:postcode":"72712",
    "sg:province":"AR",
    "sg:tags":[
        "contract"
    ],
    "wof:name":"Hyi",
    "wof:placetype":"venue"
},
  "geometry": {"coordinates":[-94.209732,36.346928],"type":"Point"}
}