{
  "type": "Feature",
  "properties": {
    "addr:full":"301 County Line Rd Rose Bud AR 72137",
    "addr:housenumber":"301",
    "addr:postcode":"72137",
    "addr:street":"County Line Rd",
    "iso:country":"US",
    "sg:address":"301 County Line Rd",
    "sg:city":"Rose Bud",
    "sg:classifiers":[
        {
            "category":"Building & Trades",
            "subcategory":"Construction",
            "type":"Services"
        }
    ],
    "sg:phone":"+1 501 556 5536",
    "sg:postcode":"72137",
    "sg:province":"AR",
    "sg:tags":[
        "house"
    ],
    "wof:name":"Hendrix Construction",
    "wof:placetype":"venue"
},
  "geometry": {"coordinates":[-91.939235,35.349079],"type":"Point"}
}