{
  "type": "Feature",
  "properties": {
    "addr:full":"319 Highway 14 S 2 Yellville AR 72687",
    "addr:housenumber":"319;2",
    "addr:postcode":"72687",
    "addr:street":"Highway 14 S",
    "iso:country":"US",
    "sg:address":"319 Highway 14 S 2",
    "sg:city":"Yellville",
    "sg:classifiers":[
        {
            "category":"Professional",
            "subcategory":"Accounting & Tax Preparation",
            "type":"Services"
        },
        {
            "category":"Banks & Credit Unions",
            "subcategory":"Financial Services",
            "type":"Services"
        }
    ],
    "sg:phone":"+1 870 449 5555",
    "sg:postcode":"72687",
    "sg:province":"AR",
    "sg:tags":[
        "return",
        "preparation-business",
        "taxes-consultants",
        "loan",
        "reporting",
        "representative",
        "alternative",
        "bookkeeping"
    ],
    "sg:website":"http://www.hrblock.com",
    "wof:name":"H&R Block",
    "wof:placetype":"venue"
},
  "geometry": {"coordinates":[-92.684753,36.22672],"type":"Point"}
}