{
  "type": "Feature",
  "properties": {
    "addr:full":"115 Barrow Hill Rd Forrest City AR 72335",
    "addr:housenumber":"115",
    "addr:postcode":"72335",
    "addr:street":"Barrow Hill Rd",
    "iso:country":"US",
    "sg:address":"115 Barrow Hill Rd",
    "sg:city":"Forrest City",
    "sg:classifiers":[
        {
            "category":"Travel",
            "subcategory":"Hotels & Motels",
            "type":"Entertainment"
        }
    ],
    "sg:phone":"+1 870 633 0042",
    "sg:postcode":"72335",
    "sg:province":"AR",
    "sg:tags":[
        "operation"
    ],
    "wof:name":"Comfort Inn",
    "wof:placetype":"venue"
},
  "geometry": {"coordinates":[-90.78839000000001,35.042719],"type":"Point"}
}