{
  "type": "Feature",
  "properties": {
    "iso:country":"US",
    "sg:address":"507 W 7th St",
    "sg:city":"Little Rock",
    "sg:classifiers":[
        {
            "category":"Retail",
            "subcategory":"Auto Repair",
            "type":"Services"
        }
    ],
    "sg:phone":"+1 501 376 3966",
    "sg:postcode":"72201",
    "sg:province":"AR",
    "sg:tags":[
        "body"
    ],
    "wof:name":"Rufus Fender Mender",
    "wof:placetype":"venue"
},
  "geometry": {"coordinates":[-92.276855,34.74283],"type":"Point"}
}