{
  "type": "Feature",
  "properties": {
    "iso:country":"US",
    "sg:address":"1185 Highway 62 E",
    "sg:city":"Yellville",
    "sg:classifiers":[
        {
            "category":"Insurance",
            "subcategory":"Hazard Insurance",
            "type":"Services"
        }
    ],
    "sg:phone":"+1 870 449 4081",
    "sg:postcode":"72687",
    "sg:province":"AR",
    "sg:tags":[
        "commercial",
        "business"
    ],
    "sg:website":"http://www.arfb.com",
    "wof:name":"Marion County",
    "wof:placetype":"venue"
},
  "geometry": {"coordinates":[-92.65190800000001,36.235929],"type":"Point"}
}