{
  "type": "Feature",
  "properties": {
    "iso:country":"US",
    "sg:address":"1 Park St",
    "sg:city":"Wilson",
    "sg:classifiers":[
        {
            "category":"Education",
            "subcategory":"Library",
            "type":"Public Place"
        }
    ],
    "sg:phone":"+1 870 655 8414",
    "sg:postcode":"72395",
    "sg:province":"AR",
    "wof:name":"Wilson Branch Library",
    "wof:placetype":"venue"
},
  "geometry": {"coordinates":[-90.042921,35.569445],"type":"Point"}
}