{
  "type": "Feature",
  "properties": {
    "addr:full":"222 N Phoenix Ave Russellville AR 72801",
    "addr:housenumber":"222",
    "addr:postcode":"72801",
    "addr:street":"N Phoenix Ave",
    "iso:country":"US",
    "sg:address":"222 N Phoenix Ave",
    "sg:city":"Russellville",
    "sg:classifiers":[
        {
            "category":"Personal",
            "subcategory":"Beauty Salon",
            "type":"Services"
        }
    ],
    "sg:phone":"+1 479 858 7075",
    "sg:postcode":"72801",
    "sg:province":"AR",
    "wof:name":"Skin & Body",
    "wof:placetype":"venue"
},
  "geometry": {"coordinates":[-93.147352,35.283679],"type":"Point"}
}