{
  "type": "Feature",
  "properties": {
    "addr:full":"7015 Russwood Ln E Mabelvale AR 72103",
    "addr:housenumber":"7015",
    "addr:postcode":"72103",
    "addr:street":"Russwood Ln E Mabelvale",
    "iso:country":"US",
    "sg:address":"7015 Russwood Ln E",
    "sg:city":"Mabelvale",
    "sg:classifiers":[
        {
            "category":"Professional",
            "subcategory":"Advertising",
            "type":"Services"
        }
    ],
    "sg:phone":"+1 501 261 7155",
    "sg:postcode":"72103",
    "sg:province":"AR",
    "sg:tags":[
        "agency"
    ],
    "wof:name":"Infuze Data Systems Limited Liability Co",
    "wof:placetype":"venue"
},
  "geometry": {"coordinates":[-92.35768400000001,34.606468],"type":"Point"}
}