{
  "type": "Feature",
  "properties": {
    "addr:full":"1524 Dr Martin Luther King Dr Little Rock AR 72202",
    "addr:housenumber":"1524",
    "addr:postcode":"72202",
    "addr:street":"Dr Martin Luther King Dr",
    "iso:country":"US",
    "sg:address":"1524 Dr Martin Luther King Dr",
    "sg:city":"Little Rock",
    "sg:classifiers":[
        {
            "category":"Personal",
            "subcategory":"Beauty Salon",
            "type":"Services"
        }
    ],
    "sg:phone":"+1 501 372 8756",
    "sg:postcode":"72202",
    "sg:province":"AR",
    "wof:name":"B M Style Crest Beauty Salon",
    "wof:placetype":"venue"
},
  "geometry": {"coordinates":[-92.289406,34.73649],"type":"Point"}
}