{
  "type": "Feature",
  "properties": {
    "iso:country":"US",
    "sg:address":"1509 Mart Dr",
    "sg:city":"Little Rock",
    "sg:classifiers":[
        {
            "category":"Professional",
            "subcategory":"Business Services",
            "type":"Services"
        }
    ],
    "sg:phone":"+1 501 664 1008",
    "sg:postcode":"72202",
    "sg:province":"AR",
    "sg:tags":[
        "designer",
        "consultant",
        "linen",
        "r",
        "design",
        "furnishing",
        "interior",
        "home",
        "decorator"
    ],
    "wof:name":"W Randall Byars Interiors & FI",
    "wof:placetype":"venue"
},
  "geometry": {"coordinates":[-92.311062,34.763956],"type":"Point"}
}