{
  "type": "Feature",
  "properties": {
    "iso:country":"US",
    "sg:address":"600 US Hwy 71",
    "sg:city":"Mena",
    "sg:classifiers":[
        {
            "category":"Banks & Credit Unions",
            "subcategory":"Bank",
            "type":"Services"
        }
    ],
    "sg:phone":"+1 479 394 3838",
    "sg:postcode":"71953",
    "sg:province":"OK",
    "wof:name":"First National Bank In Mena",
    "wof:placetype":"venue"
},
  "geometry": {"coordinates":[-94.223838,34.58662],"type":"Point"}
}