{
  "type": "Feature",
  "properties": {
    "iso:country":"US",
    "sg:address":"410 N Marr St",
    "sg:city":"Pocahontas",
    "sg:classifiers":[
        {
            "category":"Social Services",
            "type":"Services"
        }
    ],
    "sg:phone":"+1 870 892 3451",
    "sg:postcode":"72455",
    "sg:province":"AR",
    "sg:tags":[
        "youth",
        "organization",
        "center"
    ],
    "wof:name":"Consolidated Youth Svc",
    "wof:placetype":"venue"
},
  "geometry": {"coordinates":[-90.969398,36.262874],"type":"Point"}
}