{
  "type": "Feature",
  "properties": {
    "iso:country":"US",
    "sg:address":"1323 S Avalon St",
    "sg:city":"West Memphis",
    "sg:classifiers":[
        {
            "category":"Food & Beverages",
            "subcategory":"Groceries & Convenience Stores",
            "type":"Retail Goods"
        }
    ],
    "sg:phone":"+1 870 732 3638",
    "sg:postcode":"72301",
    "sg:province":"AR",
    "wof:name":"Avalon Mart",
    "wof:placetype":"venue"
},
  "geometry": {"coordinates":[-90.193697,35.129777],"type":"Point"}
}