{
  "type": "Feature",
  "properties": {
    "iso:country":"US",
    "sg:address":"25891 S 623 Rd",
    "sg:city":"Grove",
    "sg:classifiers":[
        {
            "category":"Health Services",
            "subcategory":"Health Practitioner",
            "type":"Services"
        }
    ],
    "sg:phone":"+1 918 786 8089",
    "sg:postcode":"74344",
    "sg:province":"OK",
    "wof:name":"Herbal Discoveries Plus",
    "wof:placetype":"venue"
},
  "geometry": {"coordinates":[-94.764388,36.640692],"type":"Point"}
}