{
  "type": "Feature",
  "properties": {
    "addr:full":"4132 E McCain Blvd North Little Rock AR 72117",
    "addr:housenumber":"4132",
    "addr:postcode":"72117",
    "addr:street":"E Mccain Blvd",
    "iso:country":"US",
    "sg:address":"4132 E McCain Blvd",
    "sg:city":"North Little Rock",
    "sg:classifiers":[
        {
            "category":"Shopping",
            "subcategory":"Department Store",
            "type":"Retail Goods"
        }
    ],
    "sg:phone":"+1 501 945 5520",
    "sg:postcode":"72117",
    "sg:province":"AR",
    "wof:name":"TJ Maxx",
    "wof:placetype":"venue"
},
  "geometry": {"coordinates":[-92.22443,34.789603],"type":"Point"}
}