{
  "type": "Feature",
  "properties": {
    "iso:country":"US",
    "sg:address":"4019 Remington Dr",
    "sg:city":"Fayetteville",
    "sg:classifiers":[
        {
            "category":"Personal",
            "subcategory":"Beauty Salon",
            "type":"Services"
        }
    ],
    "sg:phone":"+1 479 443 9573",
    "sg:postcode":"72703",
    "sg:province":"AR",
    "sg:tags":[
        "shop"
    ],
    "wof:name":"Arkansas Laser Solutions",
    "wof:placetype":"venue"
},
  "geometry": {"coordinates":[-94.14131500000001,36.123961],"type":"Point"}
}