{
  "type": "Feature",
  "properties": {
    "addr:full":"6811 Lois Ln Alexander AR 72002",
    "addr:housenumber":"6811",
    "addr:postcode":"72002",
    "addr:street":"Lois Ln",
    "iso:country":"US",
    "sg:address":"6811 Lois Ln",
    "sg:city":"Alexander",
    "sg:classifiers":[
        {
            "category":"Retail",
            "subcategory":"Animal Services",
            "type":"Services"
        }
    ],
    "sg:phone":"+1 501 847 0725",
    "sg:postcode":"72002",
    "sg:province":"AR",
    "wof:name":"D & G Varmint Control",
    "wof:placetype":"venue"
},
  "geometry": {"coordinates":[-92.477272,34.655866],"type":"Point"}
}