{
  "type": "Feature",
  "properties": {
    "iso:country":"US",
    "sg:address":"4 River Oaks Cir",
    "sg:city":"Little Rock",
    "sg:classifiers":[
        {
            "category":"Wholesale",
            "subcategory":"Durable Goods & Equipment",
            "type":"Manufacturing & Wholesale Goods"
        }
    ],
    "sg:phone":"+1 501 664 1163",
    "sg:postcode":"72207",
    "sg:province":"AR",
    "wof:name":"Bursary The",
    "wof:placetype":"venue"
},
  "geometry": {"coordinates":[-92.35513,34.785823],"type":"Point"}
}