{
  "type": "Feature",
  "properties": {
    "addr:full":"1027 S 25th St Van Buren AR 72956",
    "addr:housenumber":"1027",
    "addr:postcode":"72956",
    "addr:street":"S 25Th St",
    "iso:country":"US",
    "sg:address":"1027 S 25th St",
    "sg:city":"Van Buren",
    "sg:classifiers":[
        {
            "category":"Wholesale",
            "subcategory":"Machinery & Supplies",
            "type":"Manufacturing & Wholesale Goods"
        }
    ],
    "sg:phone":"+1 479 474 6061",
    "sg:postcode":"72956",
    "sg:province":"AR",
    "sg:tags":[
        "bearing"
    ],
    "wof:name":"Bates Sales Co",
    "wof:placetype":"venue"
},
  "geometry": {"coordinates":[-94.33328899999999,35.421791],"type":"Point"}
}