{
  "type": "Feature",
  "properties": {
    "addr:full":"2019 Park Ridge Dr Van Buren AR 72956",
    "addr:housenumber":"2019",
    "addr:postcode":"72956",
    "addr:street":"Park Ridge Dr",
    "iso:country":"US",
    "sg:address":"2019 Park Ridge Dr",
    "sg:city":"Van Buren",
    "sg:classifiers":[
        {
            "category":"Professional",
            "subcategory":"Secretarial Services",
            "type":"Services"
        }
    ],
    "sg:phone":"+1 479 471 9651",
    "sg:postcode":"72956",
    "sg:province":"AR",
    "sg:tags":[
        "hearing",
        "reporter"
    ],
    "wof:name":"Judith M Jones",
    "wof:placetype":"venue"
},
  "geometry": {"coordinates":[-94.396152,35.464979],"type":"Point"}
}