{
  "type": "Feature",
  "properties": {
    "addr:full":"139 Dj Dr Nashville AR 71852",
    "addr:housenumber":"139",
    "addr:postcode":"71852",
    "addr:street":"Dj Dr",
    "iso:country":"US",
    "sg:address":"139 Dj Dr",
    "sg:city":"Nashville",
    "sg:classifiers":[
        {
            "category":"Arts & Performance",
            "subcategory":"Theater",
            "type":"Entertainment"
        }
    ],
    "sg:phone":"+1 870 557 0569",
    "sg:postcode":"71852",
    "sg:province":"AR",
    "sg:tags":[
        "equipment",
        "supply",
        "theatrical"
    ],
    "wof:name":"The Children Playhouse Theatre",
    "wof:placetype":"venue"
},
  "geometry": {"coordinates":[-93.860518,33.938696],"type":"Point"}
}