{
  "type": "Feature",
  "properties": {
    "addr:full":"1609 E 9th St Little Rock AR 72202",
    "addr:housenumber":"1609",
    "addr:postcode":"72202",
    "addr:street":"E 9Th St",
    "iso:country":"US",
    "sg:address":"1609 E 9th St",
    "sg:city":"Little Rock",
    "sg:classifiers":[
        {
            "category":"Wholesale",
            "subcategory":"Construction Materials",
            "type":"Manufacturing & Wholesale Goods"
        }
    ],
    "sg:phone":"+1 501 375 0060",
    "sg:postcode":"72202",
    "sg:province":"AR",
    "sg:tags":[
        "brick",
        "common",
        "face"
    ],
    "sg:website":"www.antiquebrickinc.com",
    "wof:name":"Antique Brick Inc",
    "wof:placetype":"venue"
},
  "geometry": {"coordinates":[-92.25354299999999,34.739215],"type":"Point"}
}