{
  "type": "Feature",
  "properties": {
    "iso:country":"US",
    "sg:address":"3 Stanwood Loop",
    "sg:city":"North Little Rock",
    "sg:classifiers":[
        {
            "category":"Communications",
            "subcategory":"Film & Video Production",
            "type":"Services"
        }
    ],
    "sg:phone":"+1 501 758 4175",
    "sg:postcode":"72118",
    "sg:province":"AR",
    "sg:tags":[
        "motion"
    ],
    "wof:name":"Polta Productions",
    "wof:placetype":"venue"
},
  "geometry": {"coordinates":[-92.252459,34.82269],"type":"Point"}
}