{
  "type": "Feature",
  "properties": {
    "iso:country":"US",
    "sg:address":"207 Calloway Ave",
    "sg:city":"Sherwood",
    "sg:classifiers":[
        {
            "category":"Building & Trades",
            "subcategory":"Cleaning & Sanitation",
            "type":"Services"
        }
    ],
    "sg:phone":"+1 501 835 4846",
    "sg:postcode":"72120",
    "sg:province":"AR",
    "sg:tags":[
        "fireplace",
        "chimney"
    ],
    "wof:name":"Mary Poppins Chimney Sweep Co",
    "wof:placetype":"venue"
},
  "geometry": {"coordinates":[-92.198616,34.834845],"type":"Point"}
}