{
  "type": "Feature",
  "properties": {
    "iso:country":"US",
    "sg:address":"904 Red Oak Dr",
    "sg:city":"Siloam Springs",
    "sg:classifiers":[
        {
            "category":"Shopping",
            "type":"Retail Goods"
        }
    ],
    "sg:phone":"+1 479 524 5816",
    "sg:postcode":"72761",
    "sg:province":"OK",
    "sg:tags":[
        "trophy",
        "medal",
        "merchandise",
        "award"
    ],
    "wof:name":"Award's Plus",
    "wof:placetype":"venue"
},
  "geometry": {"coordinates":[-94.533947,36.157712],"type":"Point"}
}