{
  "type": "Feature",
  "properties": {
    "iso:country":"US",
    "sg:address":"507 Church Ave",
    "sg:city":"Mena",
    "sg:classifiers":[
        {
            "category":"Government",
            "subcategory":"Office",
            "type":"Public Place"
        }
    ],
    "sg:phone":"+1 479 394 8147",
    "sg:postcode":"71953",
    "sg:province":"OK",
    "wof:name":"Polk County Veterans Svc Offc",
    "wof:placetype":"venue"
},
  "geometry": {"coordinates":[-94.238405,34.586735],"type":"Point"}
}