{
  "type": "Feature",
  "properties": {
    "iso:country":"US",
    "sg:address":"1906 Hwy 290",
    "sg:city":"Hot Springs",
    "sg:classifiers":[
        {
            "category":"Wholesale",
            "subcategory":"Construction Materials",
            "type":"Manufacturing & Wholesale Goods"
        }
    ],
    "sg:phone":"+1 501 262 5425",
    "sg:postcode":"71913",
    "sg:province":"AR",
    "sg:tags":[
        "lumber"
    ],
    "sg:website":"www.anthonytimberlands.com",
    "wof:name":"Anthony Timberlands Inc",
    "wof:placetype":"venue"
},
  "geometry": {"coordinates":[-93.039125,34.40486],"type":"Point"}
}