{
  "type": "Feature",
  "properties": {
    "addr:full":"5401 Central Ave Hot Springs AR 71913",
    "addr:housenumber":"5401",
    "addr:postcode":"71913",
    "addr:street":"Central Ave",
    "iso:country":"US",
    "sg:address":"5401 Central Ave",
    "sg:city":"Hot Springs",
    "sg:classifiers":[
        {
            "category":"Insurance",
            "subcategory":"Insurance Agent",
            "type":"Services"
        }
    ],
    "sg:phone":"+1 501 525 9444",
    "sg:postcode":"71913",
    "sg:province":"AR",
    "wof:name":"Shelter Insurance",
    "wof:placetype":"venue"
},
  "geometry": {"coordinates":[-93.09195699999999,34.426317],"type":"Point"}
}