{
  "type": "Feature",
  "properties": {
    "iso:country":"US",
    "sg:address":"5109 Warden Rd",
    "sg:city":"North Little Rock",
    "sg:classifiers":[
        {
            "category":"Autos & Motor Vehicles",
            "subcategory":"Auto Supplies",
            "type":"Retail Goods"
        }
    ],
    "sg:phone":"+1 501 758 2906",
    "sg:postcode":"72116",
    "sg:province":"AR",
    "wof:name":"NAPA Auto Parts",
    "wof:placetype":"venue"
},
  "geometry": {"coordinates":[-92.215738,34.800503],"type":"Point"}
}