{
  "type": "Feature",
  "properties": {
    "iso:country":"US",
    "sg:address":"2 Sileby Ln",
    "sg:city":"Bella Vista",
    "sg:classifiers":[
        {
            "category":"Building & Trades",
            "subcategory":"Construction",
            "type":"Services"
        }
    ],
    "sg:phone":"+1 479 876 6096",
    "sg:postcode":"72714",
    "sg:province":"AR",
    "sg:tags":[
        "residential",
        "commercial"
    ],
    "wof:name":"C and C Quality Inc",
    "wof:placetype":"venue"
},
  "geometry": {"coordinates":[-94.223399,36.498408],"type":"Point"}
}