{
  "type": "Feature",
  "properties": {
    "iso:country":"US",
    "sg:address":"3469 State Hwy 163",
    "sg:city":"Jonesboro",
    "sg:classifiers":[
        {
            "category":"Farming",
            "subcategory":"Aquatic Farm",
            "type":"Manufacturing & Wholesale Goods"
        }
    ],
    "sg:phone":"+1 870 932 0373",
    "sg:postcode":"72404",
    "sg:province":"AR",
    "wof:name":"Stark Fish Farm",
    "wof:placetype":"venue"
},
  "geometry": {"coordinates":[-90.663606,35.7341],"type":"Point"}
}