{
  "type": "Feature",
  "properties": {
    "iso:country":"US",
    "sg:address":"2267 Timberlake Dr",
    "sg:city":"Royal",
    "sg:classifiers":[
        {
            "category":"Shopping",
            "subcategory":"Crafts & Fabrics",
            "type":"Retail Goods"
        }
    ],
    "sg:phone":"+1 501 525 2611",
    "sg:postcode":"71968",
    "sg:province":"AR",
    "sg:tags":[
        "monogram"
    ],
    "wof:name":"Royal Embroidery",
    "wof:placetype":"venue"
},
  "geometry": {"coordinates":[-93.191602,34.476521],"type":"Point"}
}