{
  "type": "Feature",
  "properties": {
    "iso:country":"US",
    "sg:address":"3641 State Hwy 8",
    "sg:city":"Mena",
    "sg:classifiers":[
        {
            "category":"Retail",
            "subcategory":"Auto Repair",
            "type":"Services"
        }
    ],
    "sg:phone":"+1 479 394 6121",
    "sg:postcode":"71953",
    "sg:province":"AR",
    "sg:tags":[
        "repairing",
        "automobile",
        "general"
    ],
    "wof:name":"Don's Auto Repair & Sales",
    "wof:placetype":"venue"
},
  "geometry": {"coordinates":[-94.140065,34.536706],"type":"Point"}
}