{
  "type": "Feature",
  "properties": {
    "iso:country":"US",
    "sg:address":"717 Craighead Rd",
    "sg:city":"Jonesboro",
    "sg:classifiers":[
        {
            "category":"Health Services",
            "subcategory":"Medical Lab",
            "type":"Services"
        }
    ],
    "sg:phone":"+1 870 933 8797",
    "sg:postcode":"72401",
    "sg:province":"AR",
    "sg:tags":[
        "detection",
        "equipment",
        "drug"
    ],
    "wof:name":"On Site Drug Screening LLC",
    "wof:placetype":"venue"
},
  "geometry": {"coordinates":[-90.714718,35.814223],"type":"Point"}
}