{
  "type": "Feature",
  "properties": {
    "iso:country":"US",
    "sg:address":"4180 W Sunset Ave",
    "sg:city":"Springdale",
    "sg:classifiers":[
        {
            "category":"Wholesale",
            "subcategory":"Motor Vehicles",
            "type":"Manufacturing & Wholesale Goods"
        },
        {
            "category":"Manufacturing",
            "subcategory":"Tools & Machinery",
            "type":"Manufacturing & Wholesale Goods"
        }
    ],
    "sg:phone":"+1 479 751 9771",
    "sg:postcode":"72762",
    "sg:province":"AR",
    "sg:tags":[
        "farm",
        "equipment",
        "body",
        "truck"
    ],
    "sg:website":"www.chandlerequipment.com",
    "wof:name":"Chandler Equipment  Inc",
    "wof:placetype":"venue"
},
  "geometry": {"coordinates":[-94.180376,36.175334],"type":"Point"}
}