{
  "type": "Feature",
  "properties": {
    "addr:full":"1830 W Hillsboro St El Dorado AR 71730",
    "addr:housenumber":"1830",
    "addr:postcode":"71730",
    "addr:street":"W Hillsboro St",
    "iso:country":"US",
    "sg:address":"1830 W Hillsboro St",
    "sg:city":"El Dorado",
    "sg:classifiers":[
        {
            "category":"Autos & Motor Vehicles",
            "subcategory":"Automobile Sales",
            "type":"Retail Goods"
        }
    ],
    "sg:phone":"+1 870 862 2900",
    "sg:postcode":"71730",
    "sg:province":"AR",
    "sg:tags":[
        "car",
        "dealer"
    ],
    "wof:name":"Teague Toyota Inc",
    "wof:placetype":"venue"
},
  "geometry": {"coordinates":[-92.684637,33.207669],"type":"Point"}
}