{
  "type": "Feature",
  "properties": {
    "iso:country":"US",
    "sg:address":"5313 Park Ave",
    "sg:city":"Hot Springs National",
    "sg:classifiers":[
        {
            "category":"Building & Trades",
            "subcategory":"Cleaning & Sanitation",
            "type":"Services"
        }
    ],
    "sg:phone":"+1 501 623 3437",
    "sg:postcode":"71901",
    "sg:province":"AR",
    "wof:name":"David F Burroughs",
    "wof:placetype":"venue"
},
  "geometry": {"coordinates":[-92.969569,34.586438],"type":"Point"}
}