{
  "type": "Feature",
  "properties": {
    "addr:full":"5313 Park Ave Hot Springs National AR 71901",
    "addr:housenumber":"5313",
    "addr:postcode":"71901",
    "addr:street":"Park Ave",
    "iso:country":"US",
    "sg:address":"5313 Park Ave",
    "sg:city":"Hot Springs National",
    "sg:classifiers":[
        {
            "category":"Building & Trades",
            "subcategory":"Cleaning & Sanitation",
            "type":"Services"
        }
    ],
    "sg:phone":"+1 501 623 3437",
    "sg:postcode":"71901",
    "sg:province":"AR",
    "wof:name":"David F Burroughs",
    "wof:placetype":"venue"
},
  "geometry": {"coordinates":[-92.96956900000001,34.586438],"type":"Point"}
}