{
  "type": "Feature",
  "properties": {
    "iso:country":"US",
    "sg:address":"3267 Peeler Bend Rd",
    "sg:city":"Benton",
    "sg:classifiers":[
        {
            "category":"Building & Trades",
            "subcategory":"Construction",
            "type":"Services"
        }
    ],
    "sg:phone":"+1 501 860 7315",
    "sg:postcode":"72019",
    "sg:province":"AR",
    "wof:name":"R & S Paving LLC",
    "wof:placetype":"venue"
},
  "geometry": {"coordinates":[-92.62477800000001,34.588045],"type":"Point"}
}