{
  "type": "Feature",
  "properties": {
    "iso:country":"US",
    "sg:address":"485 E Chestnut St",
    "sg:city":"Batesville",
    "sg:classifiers":[
        {
            "category":"Education",
            "subcategory":"Special Training",
            "type":"Public Place"
        }
    ],
    "sg:phone":"+1 870 612 5850",
    "sg:postcode":"72501",
    "sg:province":"AR",
    "sg:tags":[
        "educational"
    ],
    "wof:name":"Patricia T Whitfield",
    "wof:placetype":"venue"
},
  "geometry": {"coordinates":[-91.654177,35.775761],"type":"Point"}
}