{
  "type": "Feature",
  "properties": {
    "iso:country":"US",
    "sg:address":"3711 E Nettleton Ave",
    "sg:city":"Jonesboro",
    "sg:classifiers":[
        {
            "category":"Government",
            "subcategory":"Office",
            "type":"Public Place"
        }
    ],
    "sg:phone":"+1 870 932 1573",
    "sg:postcode":"72401",
    "sg:province":"AR",
    "sg:tags":[
        "state"
    ],
    "sg:website":"www.legaudit.state.ar.us",
    "wof:name":"Legislative Audit Div",
    "wof:placetype":"venue"
},
  "geometry": {"coordinates":[-90.659924,35.827495],"type":"Point"}
}