{
  "type": "Feature",
  "properties": {
    "iso:country":"US",
    "sg:address":"1709 Wheaton Trce",
    "sg:city":"Fort Smith",
    "sg:classifiers":[
        {
            "category":"Real Estate",
            "subcategory":"Real Estate Agent",
            "type":"Services"
        }
    ],
    "sg:phone":"+1 479 646 0277",
    "sg:postcode":"72908",
    "sg:province":"AR",
    "wof:name":"R & R Investments Inc",
    "wof:placetype":"venue"
},
  "geometry": {"coordinates":[-94.417995,35.280726],"type":"Point"}
}