{
  "type": "Feature",
  "properties": {
    "addr:full":"208 W Broadway Ave Forrest City AR 72335",
    "addr:housenumber":"208",
    "addr:postcode":"72335",
    "addr:street":"W Broadway Ave",
    "iso:country":"US",
    "sg:address":"208 W Broadway Ave",
    "sg:city":"Forrest City",
    "sg:classifiers":[
        {
            "category":"Home & Garden",
            "subcategory":"Hardware",
            "type":"Retail Goods"
        }
    ],
    "sg:phone":"+1 870 633 2202",
    "sg:postcode":"72335",
    "sg:province":"AR",
    "wof:name":"True Value Hardware",
    "wof:placetype":"venue"
},
  "geometry": {"coordinates":[-90.78727000000001,35.00855],"type":"Point"}
}