{
  "type": "Feature",
  "properties": {
    "addr:full":"406 W Sunset Ave Springdale AR 72764",
    "addr:housenumber":"406",
    "addr:postcode":"72764",
    "addr:street":"W Sunset Ave",
    "iso:country":"US",
    "sg:address":"406 W Sunset Ave",
    "sg:city":"Springdale",
    "sg:classifiers":[
        {
            "category":"Wholesale",
            "subcategory":"Office Equipment",
            "type":"Manufacturing & Wholesale Goods"
        }
    ],
    "sg:phone":"+1 479 751 4554",
    "sg:postcode":"72764",
    "sg:province":"AR",
    "sg:tags":[
        "scanning",
        "code",
        "bar"
    ],
    "wof:name":"Abe Tech",
    "wof:placetype":"venue"
},
  "geometry": {"coordinates":[-94.136805,36.174544],"type":"Point"}
}