{
  "type": "Feature",
  "properties": {
    "iso:country":"US",
    "sg:address":"2009 W Main St",
    "sg:city":"Russellville",
    "sg:classifiers":[
        {
            "category":"Health Services",
            "subcategory":"Health Practitioner",
            "type":"Services"
        }
    ],
    "sg:phone":"+1 479 968 7250",
    "sg:postcode":"72801",
    "sg:province":"AR",
    "sg:tags":[
        "audiologists"
    ],
    "wof:name":"Russellville Hearing Aid Ctr",
    "wof:placetype":"venue"
},
  "geometry": {"coordinates":[-93.152789,35.283651],"type":"Point"}
}