{
  "type": "Feature",
  "properties": {
    "iso:country":"US",
    "sg:address":"123 E Bell St",
    "sg:city":"Sheridan",
    "sg:classifiers":[
        {
            "category":"Shopping",
            "subcategory":"Used Merchandise",
            "type":"Retail Goods"
        }
    ],
    "sg:phone":"+1 501 241 0970",
    "sg:postcode":"72150",
    "sg:province":"AR",
    "sg:tags":[
        "clothing"
    ],
    "wof:name":"Courtesy Consignments",
    "wof:placetype":"venue"
},
  "geometry": {"coordinates":[-92.400057,34.307889],"type":"Point"}
}