{
  "type": "Feature",
  "properties": {
    "addr:full":"500 Coley Dr Mountain Home AR 72653",
    "addr:housenumber":"500",
    "addr:postcode":"72653",
    "addr:street":"Coley Dr",
    "iso:country":"US",
    "sg:address":"500 Coley Dr",
    "sg:city":"Mountain Home",
    "sg:classifiers":[
        {
            "category":"Retail",
            "subcategory":"Veterinary Services",
            "type":"Services"
        }
    ],
    "sg:phone":"+1 870 425 0035",
    "sg:postcode":"72653",
    "sg:province":"AR",
    "wof:name":"Slone Pet Clinic",
    "wof:placetype":"venue"
},
  "geometry": {"coordinates":[-92.38396400000001,36.350864],"type":"Point"}
}