{
  "type": "Feature",
  "properties": {
    "iso:country":"US",
    "sg:address":"10123 Hopewell Rd N",
    "sg:city":"Harrison",
    "sg:classifiers":[
        {
            "category":"Retail",
            "subcategory":"Repair Shop",
            "type":"Services"
        }
    ],
    "sg:phone":"+1 870 741 2554",
    "sg:postcode":"72601",
    "sg:province":"AR",
    "sg:tags":[
        "television",
        "radio"
    ],
    "wof:name":"White Technical",
    "wof:placetype":"venue"
},
  "geometry": {"coordinates":[-93.09308,36.337435],"type":"Point"}
}