{
  "type": "Feature",
  "properties": {
    "iso:country":"US",
    "sg:address":"122 W 6th St",
    "sg:city":"Fayetteville",
    "sg:classifiers":[
        {
            "category":"Shopping",
            "subcategory":"Bicycles & Sporting Goods",
            "type":"Retail Goods"
        }
    ],
    "sg:phone":"+1 479 442 7338",
    "sg:postcode":"72701",
    "sg:province":"AR",
    "sg:tags":[
        "repair"
    ],
    "wof:name":"Pauls Hitech Pro Shop",
    "wof:placetype":"venue"
},
  "geometry": {"coordinates":[-94.161783,36.056466],"type":"Point"}
}