{
  "type": "Feature",
  "properties": {
    "addr:full":"923 Hickory St Texarkana AR 71854",
    "addr:housenumber":"923",
    "addr:postcode":"71854",
    "addr:street":"Hickory St",
    "iso:country":"US",
    "sg:address":"923 Hickory St",
    "sg:city":"Texarkana",
    "sg:classifiers":[
        {
            "category":"Wholesale",
            "subcategory":"Construction Materials",
            "type":"Manufacturing & Wholesale Goods"
        }
    ],
    "sg:phone":"+1 870 772 7091",
    "sg:postcode":"71854",
    "sg:province":"AR",
    "wof:name":"Gifford Hill & Co",
    "wof:placetype":"venue"
},
  "geometry": {"coordinates":[-94.03633499999999,33.430965],"type":"Point"}
}