{
  "type": "Feature",
  "properties": {
    "addr:full":"402 N Tate Rd Norphlet AR 71759",
    "addr:housenumber":"402",
    "addr:postcode":"71759",
    "addr:street":"N Tate Rd",
    "iso:country":"US",
    "sg:address":"402 N Tate Rd",
    "sg:city":"Norphlet",
    "sg:classifiers":[
        {
            "category":"Building & Trades",
            "subcategory":"Pest Control",
            "type":"Services"
        }
    ],
    "sg:phone":"+1 870 546 2639",
    "sg:postcode":"71759",
    "sg:province":"AR",
    "sg:tags":[
        "deodorizing",
        "disinfecting"
    ],
    "wof:name":"Lark Aire Svc",
    "wof:placetype":"venue"
},
  "geometry": {"coordinates":[-92.65063000000001,33.320627],"type":"Point"}
}