{
  "type": "Feature",
  "properties": {
    "addr:full":"4800 E 19th St N Little Rock AR 72117",
    "addr:housenumber":"4800",
    "addr:postcode":"72117",
    "addr:street":"E 19Th St N",
    "iso:country":"US",
    "sg:address":"4800 E 19th St",
    "sg:city":"N Little Rock",
    "sg:classifiers":[
        {
            "category":"Health Services",
            "subcategory":"Doctor",
            "type":"Services"
        }
    ],
    "sg:phone":"+1 501 945 7743",
    "sg:postcode":"72117",
    "sg:province":"AR",
    "sg:tags":[
        "clinic",
        "medical"
    ],
    "wof:name":"Saint Vincent Glenview Clinic",
    "wof:placetype":"venue"
},
  "geometry": {"coordinates":[-92.208213,34.770714],"type":"Point"}
}