{
  "type": "Feature",
  "properties": {
    "addr:full":"12310 Stagecoach Rd Little Rock AR 72210",
    "addr:housenumber":"12310",
    "addr:postcode":"72210",
    "addr:street":"Stagecoach Rd",
    "iso:country":"US",
    "sg:address":"12310 Stagecoach Rd",
    "sg:city":"Little Rock",
    "sg:classifiers":[
        {
            "category":"Shopping",
            "subcategory":"Florist",
            "type":"Retail Goods"
        }
    ],
    "sg:phone":"+1 501 407 0050",
    "sg:postcode":"72210",
    "sg:province":"AR",
    "wof:name":"Coy's Flowers",
    "wof:placetype":"venue"
},
  "geometry": {"coordinates":[-92.443248,34.646696],"type":"Point"}
}