{
  "type": "Feature",
  "properties": {
    "iso:country":"US",
    "sg:address":"386 Levee Rd",
    "sg:city":"Proctor",
    "sg:classifiers":[
        {
            "category":"Freight",
            "type":"Transportation"
        }
    ],
    "sg:phone":"+1 870 735 5707",
    "sg:postcode":"72376",
    "sg:province":"AR",
    "sg:tags":[
        "operator",
        "local",
        "trucking"
    ],
    "wof:name":"Rj Trucking",
    "wof:placetype":"venue"
},
  "geometry": {"coordinates":[-90.280287,35.057605],"type":"Point"}
}