{
  "type": "Feature",
  "properties": {
    "iso:country":"US",
    "sg:address":"1108 W 41st St",
    "sg:city":"N Little Rock",
    "sg:classifiers":[
        {
            "category":"Building & Trades",
            "subcategory":"Construction",
            "type":"Services"
        }
    ],
    "sg:phone":"+1 501 563 8862",
    "sg:postcode":"72118",
    "sg:province":"AR",
    "sg:tags":[
        "roofing",
        "contractor"
    ],
    "wof:name":"Choctaw Roofing",
    "wof:placetype":"venue"
},
  "geometry": {"coordinates":[-92.278797,34.792762],"type":"Point"}
}