{
  "type": "Feature",
  "properties": {
    "iso:country":"US",
    "sg:address":"1626 Hwy 9",
    "sg:city":"Morrilton",
    "sg:classifiers":[
        {
            "category":"Food & Beverages",
            "subcategory":"Groceries & Convenience Stores",
            "type":"Retail Goods"
        }
    ],
    "sg:phone":"+1 501 354 3248",
    "sg:postcode":"72110",
    "sg:province":"AR",
    "wof:name":"Kroger",
    "wof:placetype":"venue"
},
  "geometry": {"coordinates":[-92.717591,35.179653],"type":"Point"}
}