{
  "type": "Feature",
  "properties": {
    "iso:country":"US",
    "sg:address":"2115 Manhattan St",
    "sg:city":"Harrison",
    "sg:classifiers":[
        {
            "category":"Professional",
            "subcategory":"Management & Consulting",
            "type":"Services"
        }
    ],
    "sg:phone":"+1 870 365 0259",
    "sg:postcode":"72601",
    "sg:province":"AR",
    "sg:tags":[
        "consultant",
        "business"
    ],
    "wof:name":"Lindsey Management",
    "wof:placetype":"venue"
},
  "geometry": {"coordinates":[-93.13887699999999,36.252388],"type":"Point"}
}