{
  "type": "Feature",
  "properties": {
    "iso:country":"US",
    "sg:address":"702 Glasgow Ln",
    "sg:city":"Bentonville",
    "sg:classifiers":[
        {
            "category":"Professional",
            "subcategory":"Management & Consulting",
            "type":"Services"
        },
        {
            "category":"Professional",
            "subcategory":"Advertising",
            "type":"Services"
        }
    ],
    "sg:phone":"+1 479 633 1000",
    "sg:postcode":"72712",
    "sg:province":"AR",
    "sg:tags":[
        "marketing",
        "program",
        "consultant"
    ],
    "wof:name":"Earth View Products",
    "wof:placetype":"venue"
},
  "geometry": {"coordinates":[-94.245492,36.365928],"type":"Point"}
}