{
  "type": "Feature",
  "properties": {
    "addr:full":"110 Thompson Ln Searcy AR 72143",
    "addr:housenumber":"110",
    "addr:postcode":"72143",
    "addr:street":"Thompson Ln",
    "iso:country":"US",
    "sg:address":"110 Thompson Ln",
    "sg:city":"Searcy",
    "sg:classifiers":[
        {
            "category":"Cinema",
            "subcategory":"Movie Rental",
            "type":"Entertainment"
        }
    ],
    "sg:phone":"+1 501 796 8268",
    "sg:postcode":"72143",
    "sg:province":"AR",
    "sg:tags":[
        "video",
        "tape"
    ],
    "wof:name":"Savy Soaps and Gifts",
    "wof:placetype":"venue"
},
  "geometry": {"coordinates":[-91.96431,35.196312],"type":"Point"}
}