{
  "type": "Feature",
  "properties": {
    "iso:country":"US",
    "sg:address":"7402 Interstate Dr",
    "sg:city":"Little Rock",
    "sg:classifiers":[
        {
            "category":"Organizations",
            "subcategory":"Labor Organization",
            "type":"Services"
        }
    ],
    "sg:phone":"+1 501 565 0768",
    "sg:postcode":"72209",
    "sg:province":"AR",
    "wof:name":"Little Rock Electrical Joint",
    "wof:placetype":"venue"
},
  "geometry": {"coordinates":[-92.317843,34.680114],"type":"Point"}
}