{
  "type": "Feature",
  "properties": {
    "addr:full":"401 Erwin St Des Arc AR 72040",
    "addr:housenumber":"401",
    "addr:postcode":"72040",
    "addr:street":"Erwin St",
    "iso:country":"US",
    "sg:address":"401 Erwin St",
    "sg:city":"Des Arc",
    "sg:classifiers":[
        {
            "category":"Organizations",
            "subcategory":"Religious Organization",
            "type":"Services"
        }
    ],
    "sg:phone":"+1 870 256 4230",
    "sg:postcode":"72040",
    "sg:province":"AR",
    "sg:tags":[
        "church"
    ],
    "wof:name":"Des Arc First Baptist Church",
    "wof:placetype":"venue"
},
  "geometry": {"coordinates":[-91.497635,34.975944],"type":"Point"}
}