{
  "type": "Feature",
  "properties": {
    "iso:country":"US",
    "sg:address":"1007 US Hwy 71",
    "sg:city":"Mena",
    "sg:classifiers":[
        {
            "category":"Autos & Motor Vehicles",
            "subcategory":"Automobile Sales",
            "type":"Retail Goods"
        }
    ],
    "sg:phone":"+1 479 394 0505",
    "sg:postcode":"71953",
    "sg:province":"AR",
    "sg:tags":[
        "car",
        "dealer"
    ],
    "wof:name":"Mena Motor Co",
    "wof:placetype":"venue"
},
  "geometry": {"coordinates":[-94.221152,34.586465],"type":"Point"}
}