{
  "type": "Feature",
  "properties": {
    "iso:country":"US",
    "sg:address":"325 Tylar Rd",
    "sg:city":"Wilburn",
    "sg:classifiers":[
        {
            "category":"Professional",
            "type":"Services"
        }
    ],
    "sg:phone":"+1 501 362 3032",
    "sg:postcode":"72179",
    "sg:province":"AR",
    "wof:name":"Shannon Jennings",
    "wof:placetype":"venue"
},
  "geometry": {"coordinates":[-91.87610599999999,35.511894],"type":"Point"}
}