{
  "type": "Feature",
  "properties": {
    "iso:country":"US",
    "sg:address":"351 E Main St",
    "sg:city":"Farmington",
    "sg:classifiers":[
        {
            "category":"Retail",
            "subcategory":"Auto Repair",
            "type":"Services"
        }
    ],
    "sg:phone":"+1 479 267 2260",
    "sg:postcode":"72730",
    "sg:province":"AR",
    "sg:tags":[
        "repairing",
        "automobile",
        "truck"
    ],
    "sg:website":"http://clickserve.dartsearch.net/link/click?lid=43000000313867406&ds_s_kwgid=58000000006820725&ds_e_matchtype={MatchType}&ds_e_kwdid={OrderItemId}&ds_e_adid={AdId}&ds_url_v=2",
    "wof:name":"Jeff's Auto Repair",
    "wof:placetype":"venue"
},
  "geometry": {"coordinates":[-94.22714999999999,36.046331],"type":"Point"}
}