{
  "type": "Feature",
  "properties": {
    "iso:country":"US",
    "sg:address":"311 Union St",
    "sg:city":"Dardanelle",
    "sg:classifiers":[
        {
            "category":"Home & Garden",
            "subcategory":"Furniture",
            "type":"Retail Goods"
        }
    ],
    "sg:phone":"+1 479 229 4700",
    "sg:postcode":"72834",
    "sg:province":"AR",
    "wof:name":"Room 2 Room",
    "wof:placetype":"venue"
},
  "geometry": {"coordinates":[-93.158112,35.22274],"type":"Point"}
}