{
  "type": "Feature",
  "properties": {
    "iso:country":"US",
    "sg:address":"2270 E Van Buren",
    "sg:city":"Eureka Springs",
    "sg:classifiers":[
        {
            "category":"Restaurant",
            "type":"Food & Drink"
        }
    ],
    "sg:phone":"+1 479 253 7192",
    "sg:postcode":"72632",
    "sg:province":"AR",
    "wof:name":"Miceli's Italian Restaurant",
    "wof:placetype":"venue"
},
  "geometry": {"coordinates":[-93.733325,36.389016],"type":"Point"}
}