{
  "type": "Feature",
  "properties": {
    "iso:country":"US",
    "sg:address":"1007 S Franklin St",
    "sg:city":"Blytheville",
    "sg:classifiers":[
        {
            "category":"Social Services",
            "subcategory":"Child Care",
            "type":"Services"
        }
    ],
    "sg:phone":"+1 870 762 2096",
    "sg:postcode":"72315",
    "sg:province":"AR",
    "sg:tags":[
        "nursery",
        "day"
    ],
    "sg:website":"http://eclkc.ohs.acf.hhs.gov/hslc/",
    "wof:name":"Franklin Head Start",
    "wof:placetype":"venue"
},
  "geometry": {"coordinates":[-89.900865,35.918619],"type":"Point"}
}