{
  "type": "Feature",
  "properties": {
    "iso:country":"US",
    "sg:address":"1295 Wiley Dr",
    "sg:city":"Piggott",
    "sg:classifiers":[
        {
            "category":"Restaurant",
            "type":"Food & Drink"
        }
    ],
    "sg:phone":"+1 870 598 0209",
    "sg:postcode":"72454",
    "sg:province":"AR",
    "sg:tags":[
        "eating"
    ],
    "wof:name":"Pa & Granny's Kitchen",
    "wof:placetype":"venue"
},
  "geometry": {"coordinates":[-90.203372,36.37647],"type":"Point"}
}