{
  "type": "Feature",
  "properties": {
    "addr:full":"7001 John F Kennedy Blvd N Little Rock AR 72116",
    "addr:housenumber":"7001",
    "addr:postcode":"72116",
    "addr:street":"John F Kennedy Blvd N",
    "iso:country":"US",
    "sg:address":"7001 John F Kennedy Blvd",
    "sg:city":"N Little Rock",
    "sg:classifiers":[
        {
            "category":"Banks & Credit Unions",
            "subcategory":"Bank",
            "type":"Services"
        }
    ],
    "sg:phone":"+1 501 835 7132",
    "sg:postcode":"72116",
    "sg:province":"AR",
    "sg:website":"www.usbank.com",
    "wof:name":"US Bank",
    "wof:placetype":"venue"
},
  "geometry": {"coordinates":[-92.236672,34.818969],"type":"Point"}
}