{
  "type": "Feature",
  "properties": {
    "addr:full":"321 W B St Russellville AR 72801",
    "addr:housenumber":"321",
    "addr:postcode":"72801",
    "addr:street":"W B St",
    "iso:country":"US",
    "sg:address":"321 W B St",
    "sg:city":"Russellville",
    "sg:classifiers":[
        {
            "category":"Shopping",
            "subcategory":"Gifts & Souvenirs",
            "type":"Retail Goods"
        }
    ],
    "sg:phone":"+1 479 967 0644",
    "sg:postcode":"72801",
    "sg:province":"AR",
    "wof:name":"Station House",
    "wof:placetype":"venue"
},
  "geometry": {"coordinates":[-93.13581000000001,35.279471],"type":"Point"}
}