{
  "type": "Feature",
  "properties": {
    "iso:country":"US",
    "sg:address":"317 Nordin Ln",
    "sg:city":"Russellville",
    "sg:classifiers":[
        {
            "category":"Health Services",
            "subcategory":"Dentist",
            "type":"Services"
        }
    ],
    "sg:phone":"+1 479 968 4134",
    "sg:postcode":"72802",
    "sg:province":"AR",
    "wof:name":"Griffin Doug Dds",
    "wof:placetype":"venue"
},
  "geometry": {"coordinates":[-93.16601900000001,35.264726],"type":"Point"}
}