{
  "type": "Feature",
  "properties": {
    "iso:country":"US",
    "sg:address":"1335 Airport Rd",
    "sg:city":"Hot Springs",
    "sg:classifiers":[
        {
            "category":"Health Services",
            "subcategory":"Podiatrist",
            "type":"Services"
        }
    ],
    "sg:phone":"+1 501 624 2831",
    "sg:postcode":"71913",
    "sg:province":"AR",
    "sg:tags":[
        "medical"
    ],
    "wof:name":"Hot Springs Foot Clinic",
    "wof:placetype":"venue"
},
  "geometry": {"coordinates":[-93.128558,34.471163],"type":"Point"}
}