{
  "type": "Feature",
  "properties": {
    "addr:full":"1520 Market St Little Rock AR 72211",
    "addr:housenumber":"1520",
    "addr:postcode":"72211",
    "addr:street":"Market St",
    "iso:country":"US",
    "sg:address":"1520 Market St",
    "sg:city":"Little Rock",
    "sg:classifiers":[
        {
            "category":"Restaurant",
            "type":"Food & Drink"
        }
    ],
    "sg:phone":"+1 501 223 5414",
    "sg:postcode":"72211",
    "sg:province":"AR",
    "wof:name":"Mi Ranchito 5 Mexican Rstrnt",
    "wof:placetype":"venue"
},
  "geometry": {"coordinates":[-92.398394,34.767277],"type":"Point"}
}