{
  "type": "Feature",
  "properties": {
    "addr:full":"1377 Highway 425 S Monticello AR 71655",
    "addr:housenumber":"1377",
    "addr:postcode":"71655",
    "addr:street":"Highway 425 S",
    "iso:country":"US",
    "sg:address":"1377 Highway 425 S",
    "sg:city":"Monticello",
    "sg:classifiers":[
        {
            "category":"Food & Beverages",
            "subcategory":"Groceries & Convenience Stores",
            "type":"Retail Goods"
        }
    ],
    "sg:phone":"+1 870 367 8431",
    "sg:postcode":"71655",
    "sg:province":"AR",
    "wof:name":"Cracker Box",
    "wof:placetype":"venue"
},
  "geometry": {"coordinates":[-91.801489,33.547895],"type":"Point"}
}