{
  "type": "Feature",
  "properties": {
    "addr:full":"609 S Bloomington St Lowell AR 72745",
    "addr:housenumber":"609",
    "addr:postcode":"72745",
    "addr:street":"S Bloomington St",
    "iso:country":"US",
    "sg:address":"609 S Bloomington St",
    "sg:city":"Lowell",
    "sg:classifiers":[
        {
            "category":"Recreation",
            "subcategory":"Boat Charter",
            "type":"Entertainment"
        }
    ],
    "sg:phone":"+1 479 750 7070",
    "sg:postcode":"72745",
    "sg:province":"AR",
    "sg:tags":[
        "boating"
    ],
    "wof:name":"Boats 4 You",
    "wof:placetype":"venue"
},
  "geometry": {"coordinates":[-94.136747,36.248886],"type":"Point"}
}