{
  "type": "Feature",
  "properties": {
    "iso:country":"US",
    "sg:address":"605 Park Terrace Dr",
    "sg:city":"White Hall",
    "sg:classifiers":[
        {
            "category":"Building & Trades",
            "subcategory":"Landscaping Services",
            "type":"Services"
        }
    ],
    "sg:phone":"+1 870 247 0916",
    "sg:postcode":"71602",
    "sg:province":"AR",
    "sg:tags":[
        "landscape",
        "contractor"
    ],
    "wof:name":"Prestige One Landscaping",
    "wof:placetype":"venue"
},
  "geometry": {"coordinates":[-92.09808,34.274377],"type":"Point"}
}