{
  "type": "Feature",
  "properties": {
    "iso:country":"US",
    "sg:address":"201 S Chester St",
    "sg:city":"Little Rock",
    "sg:classifiers":[
        {
            "category":"Professional",
            "subcategory":"Lawyer & Legal Services",
            "type":"Services"
        }
    ],
    "sg:phone":"+1 501 378 7755",
    "sg:postcode":"72201",
    "sg:province":"AR",
    "wof:name":"Steven Napper LTD",
    "wof:placetype":"venue"
},
  "geometry": {"coordinates":[-92.281335,34.748086],"type":"Point"}
}