{
  "type": "Feature",
  "properties": {
    "iso:country":"US",
    "sg:address":"523 Jenkins St SW",
    "sg:city":"Camden",
    "sg:classifiers":[
        {
            "category":"Professional",
            "type":"Services"
        }
    ],
    "sg:phone":"+1 870 231 6167",
    "sg:postcode":"71701",
    "sg:province":"AR",
    "wof:name":"Mike Kordsmeier",
    "wof:placetype":"venue"
},
  "geometry": {"coordinates":[-92.8372,33.53841],"type":"Point"}
}