{
  "type": "Feature",
  "properties": {
    "addr:full":"626 Malvern Ave Hot Springs National AR 71901",
    "addr:housenumber":"626",
    "addr:postcode":"71901",
    "addr:street":"Malvern Ave",
    "iso:country":"US",
    "sg:address":"626 Malvern Ave",
    "sg:city":"Hot Springs National",
    "sg:classifiers":[
        {
            "category":"Recreation",
            "type":"Entertainment"
        }
    ],
    "sg:phone":"+1 501 321 2255",
    "sg:postcode":"71901",
    "sg:province":"AR",
    "wof:name":"Gravity Golf Teaching Systems",
    "wof:placetype":"venue"
},
  "geometry": {"coordinates":[-93.049362,34.50596],"type":"Point"}
}