{
  "type": "Feature",
  "properties": {
    "iso:country":"US",
    "sg:address":"529 Holcomb St",
    "sg:city":"Springdale",
    "sg:classifiers":[
        {
            "category":"Real Estate",
            "subcategory":"Real Estate Services",
            "type":"Services"
        },
        {
            "category":"Real Estate",
            "subcategory":"Real Estate Agent",
            "type":"Services"
        }
    ],
    "sg:phone":"+1 479 756 1497",
    "sg:postcode":"72764",
    "sg:province":"AR",
    "sg:tags":[
        "buyer",
        "broker"
    ],
    "wof:name":"Real Estate Online",
    "wof:placetype":"venue"
},
  "geometry": {"coordinates":[-94.131414,36.180729],"type":"Point"}
}