{
  "type": "Feature",
  "properties": {
    "iso:country":"US",
    "sg:address":"3339 Central Ave",
    "sg:city":"Hot Springs",
    "sg:classifiers":[
        {
            "category":"Shopping",
            "subcategory":"Bicycles & Sporting Goods",
            "type":"Retail Goods"
        }
    ],
    "sg:phone":"+1 501 623 5425",
    "sg:postcode":"71913",
    "sg:province":"AR",
    "wof:name":"Soccer World",
    "wof:placetype":"venue"
},
  "geometry": {"coordinates":[-93.059769,34.475209],"type":"Point"}
}