{
  "type": "Feature",
  "properties": {
    "addr:full":"711 E Short Mountain St Paris AR 72855",
    "addr:housenumber":"711",
    "addr:postcode":"72855",
    "addr:street":"E Short Mountain St",
    "iso:country":"US",
    "sg:address":"711 E Short Mountain St",
    "sg:city":"Paris",
    "sg:classifiers":[
        {
            "category":"Building & Trades",
            "subcategory":"Construction",
            "type":"Services"
        }
    ],
    "sg:phone":"+1 479 963 2704",
    "sg:postcode":"72855",
    "sg:province":"AR",
    "sg:tags":[
        "contractor"
    ],
    "wof:name":"Harkness Roofing",
    "wof:placetype":"venue"
},
  "geometry": {"coordinates":[-93.72374499999999,35.293685],"type":"Point"}
}