{
  "type": "Feature",
  "properties": {
    "iso:country":"US",
    "sg:address":"200 S College Ave",
    "sg:city":"Fayetteville",
    "sg:classifiers":[
        {
            "category":"Autos & Motor Vehicles",
            "subcategory":"Fuel & Gas Station",
            "type":"Retail Goods"
        },
        {
            "category":"Autos & Motor Vehicles",
            "subcategory":"Auto Supplies",
            "type":"Retail Goods"
        }
    ],
    "sg:phone":"+1 479 442 9536",
    "sg:postcode":"72701",
    "sg:province":"AR",
    "sg:tags":[
        "tire"
    ],
    "wof:name":"Psi Fayettville",
    "wof:placetype":"venue"
},
  "geometry": {"coordinates":[-94.15799,36.06086],"type":"Point"}
}