{
  "type": "Feature",
  "properties": {
    "iso:country":"US",
    "sg:address":"2305 Vicksburg St",
    "sg:city":"Fort Smith",
    "sg:classifiers":[
        {
            "category":"Building & Trades",
            "subcategory":"Construction",
            "type":"Services"
        }
    ],
    "sg:phone":"+1 479 646 4095",
    "sg:postcode":"72901",
    "sg:province":"AR",
    "sg:tags":[
        "general",
        "contractor"
    ],
    "wof:name":"Coats Construction Inc",
    "wof:placetype":"venue"
},
  "geometry": {"coordinates":[-94.407536,35.332653],"type":"Point"}
}