{
  "type": "Feature",
  "properties": {
    "addr:full":"8331 Hwy 115 Pocahontas AR 72455",
    "addr:housenumber":"8331",
    "addr:postcode":"72455",
    "addr:street":"Hwy 115",
    "iso:country":"US",
    "sg:address":"8331 Hwy 115",
    "sg:city":"Pocahontas",
    "sg:classifiers":[
        {
            "category":"Food & Beverages",
            "subcategory":"Groceries & Convenience Stores",
            "type":"Retail Goods"
        }
    ],
    "sg:phone":"+1 870 647 1215",
    "sg:postcode":"72455",
    "sg:province":"AR",
    "wof:name":"Country Family Health Food Str",
    "wof:placetype":"venue"
},
  "geometry": {"coordinates":[-90.92771,36.36434],"type":"Point"}
}