{
  "type": "Feature",
  "properties": {
    "addr:full":"1216 S Rogers St Clarksville AR 72830",
    "addr:housenumber":"1216",
    "addr:postcode":"72830",
    "addr:street":"S Rogers St",
    "iso:country":"US",
    "sg:address":"1216 S Rogers St",
    "sg:city":"Clarksville",
    "sg:classifiers":[
        {
            "category":"Professional",
            "subcategory":"Accounting & Tax Preparation",
            "type":"Services"
        }
    ],
    "sg:phone":"+1 479 754 2478",
    "sg:postcode":"72830",
    "sg:province":"AR",
    "sg:tags":[
        "accountant"
    ],
    "wof:name":"King & Jacobs",
    "wof:placetype":"venue"
},
  "geometry": {"coordinates":[-93.460083,35.459779],"type":"Point"}
}