{
  "type": "Feature",
  "properties": {
    "addr:full":"212 N 34th St Rogers AR 72756",
    "addr:housenumber":"212",
    "addr:postcode":"72756",
    "addr:street":"N 34Th St",
    "iso:country":"US",
    "sg:address":"212 N 34th St",
    "sg:city":"Rogers",
    "sg:classifiers":[
        {
            "category":"Insurance",
            "subcategory":"Insurance Agent",
            "type":"Services"
        }
    ],
    "sg:phone":"+1 479 621 9971",
    "sg:postcode":"72756",
    "sg:province":"AR",
    "wof:name":"Gene Long Insurance",
    "wof:placetype":"venue"
},
  "geometry": {"coordinates":[-94.166684,36.334674],"type":"Point"}
}