{
  "type": "Feature",
  "properties": {
    "iso:country":"US",
    "sg:address":"320 N Constitution Ave",
    "sg:city":"Ashdown",
    "sg:classifiers":[
        {
            "category":"Retail",
            "subcategory":"Laundry & Dry Cleaning",
            "type":"Services"
        }
    ],
    "sg:phone":"+1 870 898 2826",
    "sg:postcode":"71822",
    "sg:province":"AR",
    "sg:tags":[
        "cleaners"
    ],
    "wof:name":"Ayer's Cleaners",
    "wof:placetype":"venue"
},
  "geometry": {"coordinates":[-94.13136299999999,33.674176],"type":"Point"}
}