{
  "type": "Feature",
  "properties": {
    "addr:full":"113 W South St Lincoln AR 72744",
    "addr:housenumber":"113",
    "addr:postcode":"72744",
    "addr:street":"W South St",
    "iso:country":"US",
    "sg:address":"113 W South St",
    "sg:city":"Lincoln",
    "sg:classifiers":[
        {
            "category":"Farming",
            "subcategory":"Poultry Farm",
            "type":"Manufacturing & Wholesale Goods"
        }
    ],
    "sg:phone":"+1 479 824 3267",
    "sg:postcode":"72744",
    "sg:province":"AR",
    "sg:website":"www.tysons.com",
    "wof:name":"Tyson Foods Inc",
    "wof:placetype":"venue"
},
  "geometry": {"coordinates":[-94.42389300000001,35.94089],"type":"Point"}
}