{
  "type": "Feature",
  "properties": {
    "iso:country":"US",
    "sg:address":"1302 Wilmar Cir",
    "sg:city":"Jonesboro",
    "sg:classifiers":[
        {
            "category":"Organizations",
            "subcategory":"Religious Organization",
            "type":"Services"
        }
    ],
    "sg:phone":"+1 870 932 2583",
    "sg:postcode":"72401",
    "sg:province":"AR",
    "sg:tags":[
        "clergy"
    ],
    "wof:name":"Measure Of Faith Ministries",
    "wof:placetype":"venue"
},
  "geometry": {"coordinates":[-90.718508,35.830071],"type":"Point"}
}