{
  "type": "Feature",
  "properties": {
    "iso:country":"US",
    "sg:address":"503 W Main St",
    "sg:city":"Mountain View",
    "sg:classifiers":[
        {
            "category":"Shopping",
            "type":"Retail Goods"
        }
    ],
    "sg:phone":"+1 870 269 6996",
    "sg:postcode":"72560",
    "sg:province":"AR",
    "sg:tags":[
        "hearing",
        "equipment",
        "supply",
        "impaired"
    ],
    "wof:name":"Triplet Hearing Ctr",
    "wof:placetype":"venue"
},
  "geometry": {"coordinates":[-92.129831,35.865887],"type":"Point"}
}