{
  "type": "Feature",
  "properties": {
    "addr:full":"1700 Broadway St Little Rock AR 72206",
    "addr:housenumber":"1700",
    "addr:postcode":"72206",
    "addr:street":"Broadway St",
    "iso:country":"US",
    "sg:address":"1700 Broadway St",
    "sg:city":"Little Rock",
    "sg:classifiers":[
        {
            "category":"Manufacturing",
            "subcategory":"Glass & Minerals",
            "type":"Manufacturing & Wholesale Goods"
        }
    ],
    "sg:phone":"+1 501 244 2410",
    "sg:postcode":"72206",
    "sg:province":"AR",
    "sg:tags":[
        "product",
        "mfg"
    ],
    "wof:name":"Stained Glass Monkey",
    "wof:placetype":"venue"
},
  "geometry": {"coordinates":[-92.278403,34.732085],"type":"Point"}
}