{
  "type": "Feature",
  "properties": {
    "addr:full":"210 S State St Little Rock AR 72201",
    "addr:housenumber":"210",
    "addr:postcode":"72201",
    "addr:street":"S State St",
    "iso:country":"US",
    "sg:address":"210 S State St",
    "sg:city":"Little Rock",
    "sg:classifiers":[
        {
            "category":"Professional",
            "subcategory":"Lawyer & Legal Services",
            "type":"Services"
        }
    ],
    "sg:phone":"+1 501 376 0886",
    "sg:postcode":"72201",
    "sg:province":"AR",
    "sg:tags":[
        "attorney"
    ],
    "wof:name":"Brent Baber Law Firm",
    "wof:placetype":"venue"
},
  "geometry": {"coordinates":[-92.279127,34.747388],"type":"Point"}
}