{
  "type": "Feature",
  "properties": {
    "iso:country":"US",
    "sg:address":"579 Cain Rd",
    "sg:city":"Griffithville",
    "sg:classifiers":[
        {
            "category":"Farming",
            "subcategory":"Farm & Veterinary Services",
            "type":"Manufacturing & Wholesale Goods"
        }
    ],
    "sg:phone":"+1 501 323 4313",
    "sg:postcode":"72060",
    "sg:province":"AR",
    "sg:tags":[
        "crop"
    ],
    "wof:name":"Skunkworks Aviation",
    "wof:placetype":"venue"
},
  "geometry": {"coordinates":[-91.599917,35.06411],"type":"Point"}
}