{
  "type": "Feature",
  "properties": {
    "iso:country":"US",
    "sg:address":"3309 John Barrow Rd",
    "sg:city":"Little Rock",
    "sg:classifiers":[
        {
            "category":"Social Services",
            "subcategory":"Child Care",
            "type":"Services"
        }
    ],
    "sg:phone":"+1 501 312 2229",
    "sg:postcode":"72204",
    "sg:province":"AR",
    "wof:name":"Grandma's House & Learning Ctr",
    "wof:placetype":"venue"
},
  "geometry": {"coordinates":[-92.372877,34.722587],"type":"Point"}
}