{
  "type": "Feature",
  "properties": {
    "iso:country":"US",
    "sg:address":"107 N Ash St",
    "sg:city":"Sheridan",
    "sg:classifiers":[
        {
            "category":"Autos & Motor Vehicles",
            "subcategory":"Automobile Sales",
            "type":"Retail Goods"
        }
    ],
    "sg:phone":"+1 870 942 8819",
    "sg:postcode":"72150",
    "sg:province":"AR",
    "sg:tags":[
        "used"
    ],
    "wof:name":"Sheridan Auto Sales",
    "wof:placetype":"venue"
},
  "geometry": {"coordinates":[-92.392712,34.307932],"type":"Point"}
}