{
  "type": "Feature",
  "properties": {
    "iso:country":"US",
    "sg:address":"1702 S Walton Blvd",
    "sg:city":"Bentonville",
    "sg:classifiers":[
        {
            "category":"Restaurant",
            "type":"Food & Drink"
        }
    ],
    "sg:phone":"+1 479 464 9091",
    "sg:postcode":"72712",
    "sg:province":"AR",
    "wof:name":"Hawgtown Pizza",
    "wof:placetype":"venue"
},
  "geometry": {"coordinates":[-94.210798,36.353914],"type":"Point"}
}