{
  "type": "Feature",
  "properties": {
    "iso:country":"US",
    "sg:address":"1307 Malcolm Ave",
    "sg:city":"Newport",
    "sg:classifiers":[
        {
            "category":"Organizations",
            "subcategory":"Religious Organization",
            "type":"Services"
        }
    ],
    "sg:phone":"+1 870 523 2423",
    "sg:postcode":"72112",
    "sg:province":"AR",
    "wof:name":"First Baptist Church Solid ROC",
    "wof:placetype":"venue"
},
  "geometry": {"coordinates":[-91.26408,35.606138],"type":"Point"}
}