{
  "type": "Feature",
  "properties": {
    "addr:full":"2119 Wheeler Ave Fort Smith AR 72901",
    "addr:housenumber":"2119",
    "addr:postcode":"72901",
    "addr:street":"Wheeler Ave",
    "iso:country":"US",
    "sg:address":"2119 Wheeler Ave",
    "sg:city":"Fort Smith",
    "sg:classifiers":[
        {
            "category":"Shopping",
            "subcategory":"Discount & Variety Stores",
            "type":"Retail Goods"
        }
    ],
    "sg:phone":"+1 479 782 4548",
    "sg:postcode":"72901",
    "sg:province":"AR",
    "sg:tags":[
        "merchandise",
        "general"
    ],
    "wof:name":"Superior Supply",
    "wof:placetype":"venue"
},
  "geometry": {"coordinates":[-94.426247,35.360954],"type":"Point"}
}