{
  "type": "Feature",
  "properties": {
    "iso:country":"US",
    "sg:address":"6105 Highway 178 W",
    "sg:city":"Lakeview",
    "sg:classifiers":[
        {
            "category":"Food & Beverages",
            "subcategory":"Liquor & Beverages",
            "type":"Retail Goods"
        },
        {
            "category":"Wholesale",
            "subcategory":"Wine & Distilled Alcoholic Beverages",
            "type":"Manufacturing & Wholesale Goods"
        }
    ],
    "sg:phone":"+1 870 431 5300",
    "sg:postcode":"72642",
    "sg:province":"AR",
    "sg:tags":[
        "liquors-wholesale",
        "store"
    ],
    "wof:name":"B & D Liquors Inc",
    "wof:placetype":"venue"
},
  "geometry": {"coordinates":[-92.549317,36.367047],"type":"Point"}
}