{
  "type": "Feature",
  "properties": {
    "iso:country":"US",
    "sg:address":"10900 Short Marche Rd",
    "sg:city":"Maumelle",
    "sg:classifiers":[
        {
            "category":"Government",
            "subcategory":"Office",
            "type":"Public Place"
        }
    ],
    "sg:phone":"+1 501 851 4298",
    "sg:postcode":"72113",
    "sg:province":"AR",
    "wof:name":"Bill Buford",
    "wof:placetype":"venue"
},
  "geometry": {"coordinates":[-92.355354,34.846696],"type":"Point"}
}