{
  "type": "Feature",
  "properties": {
    "addr:full":"10900 Short Marche Rd Maumelle AR 72113",
    "addr:housenumber":"10900",
    "addr:postcode":"72113",
    "addr:street":"Short Marche Rd",
    "iso:country":"US",
    "sg:address":"10900 Short Marche Rd",
    "sg:city":"Maumelle",
    "sg:classifiers":[
        {
            "category":"Government",
            "subcategory":"Office",
            "type":"Public Place"
        }
    ],
    "sg:phone":"+1 501 851 4298",
    "sg:postcode":"72113",
    "sg:province":"AR",
    "wof:name":"Bill Buford",
    "wof:placetype":"venue"
},
  "geometry": {"coordinates":[-92.35535400000001,34.846696],"type":"Point"}
}