{
  "type": "Feature",
  "properties": {
    "iso:country":"US",
    "sg:address":"1020 3rd St",
    "sg:city":"Newport",
    "sg:classifiers":[
        {
            "category":"Food & Beverages",
            "subcategory":"Groceries & Convenience Stores",
            "type":"Retail Goods"
        }
    ],
    "sg:phone":"+1 870 523 8310",
    "sg:postcode":"72112",
    "sg:province":"AR",
    "wof:name":"Delta Express",
    "wof:placetype":"venue"
},
  "geometry": {"coordinates":[-91.287795,35.601098],"type":"Point"}
}