{
  "type": "Feature",
  "properties": {
    "iso:country":"US",
    "sg:address":"17 Churchwell Dr",
    "sg:city":"Bentonville",
    "sg:classifiers":[
        {
            "category":"Food & Beverages",
            "subcategory":"Bakery",
            "type":"Retail Goods"
        }
    ],
    "sg:phone":"+1 479 464 8348",
    "sg:postcode":"72712",
    "sg:province":"AR",
    "sg:tags":[
        "baker"
    ],
    "wof:name":"Mrs Smith's Bakery",
    "wof:placetype":"venue"
},
  "geometry": {"coordinates":[-94.16842800000001,36.379854],"type":"Point"}
}