{
  "type": "Feature",
  "properties": {
    "iso:country":"US",
    "sg:address":"906 S Barnes St",
    "sg:city":"De Witt",
    "sg:phone":"+1 870 946 1654",
    "sg:postcode":"72042",
    "sg:province":"AR",
    "sg:tags":[
        "farm",
        "rice"
    ],
    "wof:name":"Triple W Farm Ms",
    "wof:placetype":"venue"
},
  "geometry": {"coordinates":[-91.349084,34.286362],"type":"Point"}
}