{
  "type": "Feature",
  "properties": {
    "addr:full":"632 W Broadway St N Little Rock AR 72114",
    "addr:housenumber":"632",
    "addr:postcode":"72114",
    "addr:street":"W Broadway St N",
    "iso:country":"US",
    "sg:address":"632 W Broadway St",
    "sg:city":"N Little Rock",
    "sg:classifiers":[
        {
            "category":"Insurance",
            "subcategory":"Insurance Agent",
            "type":"Services"
        }
    ],
    "sg:phone":"+1 501 375 5512",
    "sg:postcode":"72114",
    "sg:province":"AR",
    "wof:name":"American General Life Ins Co",
    "wof:placetype":"venue"
},
  "geometry": {"coordinates":[-92.273793,34.756509],"type":"Point"}
}