{
  "type": "Feature",
  "properties": {
    "iso:country":"US",
    "sg:address":"417 N Spruce St",
    "sg:city":"Searcy",
    "sg:classifiers":[
        {
            "category":"Government",
            "subcategory":"Office",
            "type":"Public Place"
        }
    ],
    "sg:phone":"+1 501 268 8761",
    "sg:postcode":"72143",
    "sg:province":"AR",
    "wof:name":"White County Warrants Div",
    "wof:placetype":"venue"
},
  "geometry": {"coordinates":[-91.738632,35.251474],"type":"Point"}
}