{
  "type": "Feature",
  "properties": {
    "addr:full":"1720 Walnut Grove Rd Little Rock AR 72223",
    "addr:housenumber":"1720",
    "addr:postcode":"72223",
    "addr:street":"Walnut Grove Rd",
    "iso:country":"US",
    "sg:address":"1720 Walnut Grove Rd",
    "sg:city":"Little Rock",
    "sg:classifiers":[
        {
            "category":"Health Services",
            "subcategory":"Doctor",
            "type":"Services"
        }
    ],
    "sg:phone":"+1 501 821 3997",
    "sg:postcode":"72223",
    "sg:province":"AR",
    "wof:name":"M B Ashcraft DDS Ms",
    "wof:placetype":"venue"
},
  "geometry": {"coordinates":[-92.512158,34.766478],"type":"Point"}
}