{
  "type": "Feature",
  "properties": {
    "iso:country":"US",
    "sg:address":"1013 Jefferson St",
    "sg:city":"Springdale",
    "sg:classifiers":[
        {
            "category":"Manufacturing",
            "subcategory":"Pet Food",
            "type":"Manufacturing & Wholesale Goods"
        },
        {
            "category":"Shopping",
            "subcategory":"Pets & Pet Supplies",
            "type":"Retail Goods"
        },
        {
            "category":"Food & Beverages",
            "subcategory":"Supermarket",
            "type":"Retail Goods"
        }
    ],
    "sg:phone":"+1 479 751 4506",
    "sg:postcode":"72764",
    "sg:province":"AR",
    "sg:tags":[
        "feed",
        "supplement",
        "concentrate",
        "foods-wholesale",
        "super",
        "store",
        "manufacturer"
    ],
    "sg:website":"http://www.tripletwhitetails.com",
    "wof:name":"Triple T Foods",
    "wof:placetype":"venue"
},
  "geometry": {"coordinates":[-94.123458,36.195572],"type":"Point"}
}