{
  "type": "Feature",
  "properties": {
    "addr:full":"172 Paul Addition Rd Searcy AR 72143",
    "addr:housenumber":"172",
    "addr:postcode":"72143",
    "addr:street":"Paul Addition Rd",
    "iso:country":"US",
    "sg:address":"172 Paul Addition Rd",
    "sg:city":"Searcy",
    "sg:classifiers":[
        {
            "category":"Banks & Credit Unions",
            "subcategory":"Investment Brokerage",
            "type":"Services"
        }
    ],
    "sg:phone":"+1 501 368 0867",
    "sg:postcode":"72143",
    "sg:province":"AR",
    "sg:tags":[
        "consultant",
        "planning",
        "financial"
    ],
    "wof:name":"Paradigm Financial Group",
    "wof:placetype":"venue"
},
  "geometry": {"coordinates":[-91.811763,35.25229],"type":"Point"}
}