{
  "type": "Feature",
  "properties": {
    "iso:country":"US",
    "sg:address":"10301 N Rodney Parham Rd",
    "sg:city":"Little Rock",
    "sg:classifiers":[
        {
            "category":"Shopping",
            "subcategory":"Jewelry",
            "type":"Retail Goods"
        }
    ],
    "sg:phone":"+1 501 221 2420",
    "sg:postcode":"72227",
    "sg:province":"AR",
    "sg:tags":[
        "jeweler"
    ],
    "sg:website":"www.reidvining.com",
    "wof:name":"Reid-Vining Jewelers",
    "wof:placetype":"venue"
},
  "geometry": {"coordinates":[-92.388451,34.767079],"type":"Point"}
}