{
  "type": "Feature",
  "properties": {
    "iso:country":"US",
    "sg:address":"100 Springwood Rd",
    "sg:city":"Hot Springs National Park",
    "sg:classifiers":[
        {
            "category":"Shopping",
            "type":"Retail Goods"
        }
    ],
    "sg:phone":"+1 501 767 9120",
    "sg:postcode":"71913",
    "sg:province":"AR",
    "sg:tags":[
        "merchandise"
    ],
    "wof:name":"Aquatox Inc",
    "wof:placetype":"venue"
},
  "geometry": {"coordinates":[-93.139615,34.473287],"type":"Point"}
}