{
  "type": "Feature",
  "properties": {
    "iso:country":"US",
    "sg:address":"1404 S Pleasant St",
    "sg:city":"Springdale",
    "sg:classifiers":[
        {
            "category":"Wholesale",
            "subcategory":"Machinery & Supplies",
            "type":"Manufacturing & Wholesale Goods"
        }
    ],
    "sg:phone":"+1 479 756 9424",
    "sg:postcode":"72764",
    "sg:province":"AR",
    "sg:tags":[
        "chemical",
        "equipment",
        "industrial"
    ],
    "wof:name":"Airgas",
    "wof:placetype":"venue"
},
  "geometry": {"coordinates":[-94.14357099999999,36.172897],"type":"Point"}
}