{
  "type": "Feature",
  "properties": {
    "addr:full":"22456 E War Eagle Rd Springdale AR 72764",
    "addr:housenumber":"22456",
    "addr:postcode":"72764",
    "addr:street":"E War Eagle Rd",
    "iso:country":"US",
    "sg:address":"22456 E War Eagle Rd",
    "sg:city":"Springdale",
    "sg:classifiers":[
        {
            "category":"Utilities",
            "subcategory":"Sewage",
            "type":"Services"
        }
    ],
    "sg:phone":"+1 479 872 1747",
    "sg:postcode":"72764",
    "sg:province":"AR",
    "sg:tags":[
        "system",
        "sewerage"
    ],
    "wof:name":"O M I",
    "wof:placetype":"venue"
},
  "geometry": {"coordinates":[-93.982465,36.206859],"type":"Point"}
}