{
  "type": "Feature",
  "properties": {
    "addr:full":"542 Edwards Rd Alma AR 72921",
    "addr:housenumber":"542",
    "addr:postcode":"72921",
    "addr:street":"Edwards Rd",
    "iso:country":"US",
    "sg:address":"542 Edwards Rd",
    "sg:city":"Alma",
    "sg:classifiers":[
        {
            "category":"Sports & Exercise",
            "subcategory":"Golf",
            "type":"Entertainment"
        }
    ],
    "sg:phone":"+1 479 632 8857",
    "sg:postcode":"72921",
    "sg:province":"AR",
    "sg:tags":[
        "course"
    ],
    "sg:website":"www.golfeaglecrest.com",
    "wof:name":"Eagle Crest Golf Course",
    "wof:placetype":"venue"
},
  "geometry": {"coordinates":[-94.181673,35.493165],"type":"Point"}
}