{
  "type": "Feature",
  "properties": {
    "addr:full":"2113 E Broad St Texarkana AR 71854",
    "addr:housenumber":"2113",
    "addr:postcode":"71854",
    "addr:street":"E Broad St",
    "iso:country":"US",
    "sg:address":"2113 E Broad St",
    "sg:city":"Texarkana",
    "sg:classifiers":[
        {
            "category":"Retail",
            "subcategory":"Auto Rental",
            "type":"Services"
        }
    ],
    "sg:phone":"+1 870 772 1917",
    "sg:postcode":"71854",
    "sg:province":"AR",
    "sg:tags":[
        "truck"
    ],
    "wof:name":"Budget",
    "wof:placetype":"venue"
},
  "geometry": {"coordinates":[-94.01863400000001,33.439481],"type":"Point"}
}