{
  "type": "Feature",
  "properties": {
    "iso:country":"US",
    "sg:address":"3 Northwood Dr",
    "sg:city":"Conway",
    "sg:classifiers":[
        {
            "category":"Professional",
            "type":"Services"
        }
    ],
    "sg:phone":"+1 501 505 8773",
    "sg:postcode":"72034",
    "sg:province":"AR",
    "wof:name":"Danny M Rasmussen",
    "wof:placetype":"venue"
},
  "geometry": {"coordinates":[-92.479688,35.099202],"type":"Point"}
}