{
  "type": "Feature",
  "properties": {
    "iso:country":"US",
    "sg:address":"600 S Jackson Ave",
    "sg:city":"Russellville",
    "sg:classifiers":[
        {
            "category":"Freight",
            "type":"Transportation"
        }
    ],
    "sg:phone":"+1 479 967 5992",
    "sg:postcode":"72801",
    "sg:province":"AR",
    "sg:tags":[
        "hauler",
        "contract"
    ],
    "wof:name":"Dwights Trucking",
    "wof:placetype":"venue"
},
  "geometry": {"coordinates":[-93.121989,35.272845],"type":"Point"}
}