{
  "type": "Feature",
  "properties": {
    "iso:country":"US",
    "sg:address":"121 Edwards St",
    "sg:city":"White Hall",
    "sg:classifiers":[
        {
            "category":"Organizations",
            "subcategory":"Community Association",
            "type":"Services"
        }
    ],
    "sg:phone":"+1 870 247 1249",
    "sg:postcode":"71602",
    "sg:province":"AR",
    "wof:name":"Epsilon Sgma Alpha Intrtrntnal",
    "wof:placetype":"venue"
},
  "geometry": {"coordinates":[-92.087102,34.248215],"type":"Point"}
}