{
  "type": "Feature",
  "properties": {
    "iso:country":"US",
    "sg:address":"6308 Shannon Rd",
    "sg:city":"Pine Bluff",
    "sg:classifiers":[
        {
            "category":"Home & Garden",
            "subcategory":"Building Materials",
            "type":"Retail Goods"
        }
    ],
    "sg:phone":"+1 870 879 2509",
    "sg:postcode":"71603",
    "sg:province":"AR",
    "wof:name":"Standard Building Materials Co",
    "wof:placetype":"venue"
},
  "geometry": {"coordinates":[-92.076207,34.204562],"type":"Point"}
}