{
  "type": "Feature",
  "properties": {
    "iso:country":"US",
    "sg:address":"2110 E Matthews Ave",
    "sg:city":"Jonesboro",
    "sg:classifiers":[
        {
            "category":"Professional",
            "subcategory":"Lawyer & Legal Services",
            "type":"Services"
        }
    ],
    "sg:phone":"+1 870 931 2100",
    "sg:postcode":"72401",
    "sg:province":"AR",
    "sg:tags":[
        "attorney"
    ],
    "wof:name":"Mark Rees Law Offices",
    "wof:placetype":"venue"
},
  "geometry": {"coordinates":[-90.675316,35.834475],"type":"Point"}
}