{
  "type": "Feature",
  "properties": {
    "addr:full":"1708 Biscayne Ln Jonesboro AR 72401",
    "addr:housenumber":"1708",
    "addr:postcode":"72401",
    "addr:street":"Biscayne Ln",
    "iso:country":"US",
    "sg:address":"1708 Biscayne Ln",
    "sg:city":"Jonesboro",
    "sg:classifiers":[
        {
            "category":"Professional",
            "subcategory":"Accounting & Tax Preparation",
            "type":"Services"
        }
    ],
    "sg:phone":"+1 870 802 2600",
    "sg:postcode":"72401",
    "sg:province":"AR",
    "sg:tags":[
        "return"
    ],
    "wof:name":"Arkansas Tax Assoc",
    "wof:placetype":"venue"
},
  "geometry": {"coordinates":[-90.73726000000001,35.824175],"type":"Point"}
}