{
  "type": "Feature",
  "properties": {
    "addr:full":"469 J E Clark Cove Marion AR 72364",
    "addr:housenumber":"469",
    "addr:postcode":"72364",
    "addr:street":"J E Clark Cove",
    "iso:country":"US",
    "sg:address":"469 J E Clark Cove",
    "sg:city":"Marion",
    "sg:classifiers":[
        {
            "category":"Building & Trades",
            "subcategory":"Cleaning & Sanitation",
            "type":"Services"
        }
    ],
    "sg:phone":"+1 870 739 1393",
    "sg:postcode":"72364",
    "sg:province":"AR",
    "sg:tags":[
        "maintenance"
    ],
    "wof:name":"Roger Smith Janitorial",
    "wof:placetype":"venue"
},
  "geometry": {"coordinates":[-90.19674500000001,35.198943],"type":"Point"}
}