{
  "type": "Feature",
  "properties": {
    "addr:full":"100 S 4th St Fort Smith AR 72901",
    "addr:housenumber":"100",
    "addr:postcode":"72901",
    "addr:street":"S 4Th St",
    "iso:country":"US",
    "sg:address":"100 S 4th St",
    "sg:city":"Fort Smith",
    "sg:classifiers":[
        {
            "category":"Museum",
            "type":"Entertainment"
        }
    ],
    "sg:phone":"+1 479 783 0205",
    "sg:postcode":"72901",
    "sg:province":"AR",
    "wof:name":"Fort Smith Trolley Museum",
    "wof:placetype":"venue"
},
  "geometry": {"coordinates":[-94.429394,35.386335],"type":"Point"}
}