{
  "type": "Feature",
  "properties": {
    "iso:country":"US",
    "sg:address":"100 N Main St",
    "sg:city":"Strawberry",
    "sg:classifiers":[
        {
            "category":"Government",
            "subcategory":"Post Office",
            "type":"Public Place"
        }
    ],
    "sg:phone":"+1 870 528 3315",
    "sg:postcode":"72469",
    "sg:province":"AR",
    "sg:tags":[
        "postal",
        "us"
    ],
    "wof:name":"US Post Office",
    "wof:placetype":"venue"
},
  "geometry": {"coordinates":[-91.321819,35.969313],"type":"Point"}
}