{
  "type": "Feature",
  "properties": {
    "addr:full":"905 Elm St Batesville AR 72501",
    "addr:housenumber":"905",
    "addr:postcode":"72501",
    "addr:street":"Elm St",
    "iso:country":"US",
    "sg:address":"905 Elm St",
    "sg:city":"Batesville",
    "sg:classifiers":[
        {
            "category":"Shopping",
            "type":"Retail Goods"
        }
    ],
    "sg:phone":"+1 870 698 0171",
    "sg:postcode":"72501",
    "sg:province":"AR",
    "sg:tags":[
        "cosmetic",
        "perfume"
    ],
    "wof:name":"Lakenya's Beauty Supply",
    "wof:placetype":"venue"
},
  "geometry": {"coordinates":[-91.64740999999999,35.777264],"type":"Point"}
}