{
  "type": "Feature",
  "properties": {
    "iso:country":"US",
    "sg:address":"603 Main St",
    "sg:city":"Hardy",
    "sg:classifiers":[
        {
            "category":"Shopping",
            "subcategory":"Books",
            "type":"Retail Goods"
        }
    ],
    "sg:phone":"+1 870 856 4977",
    "sg:postcode":"72542",
    "sg:province":"AR",
    "wof:name":"Bibles Books Gifts & Crafts",
    "wof:placetype":"venue"
},
  "geometry": {"coordinates":[-91.47566999999999,36.31512],"type":"Point"}
}