{
  "type": "Feature",
  "properties": {
    "iso:country":"US",
    "sg:address":"805 Main St",
    "sg:city":"Crossett",
    "sg:classifiers":[
        {
            "category":"Shopping",
            "type":"Retail Goods"
        },
        {
            "category":"Shopping",
            "subcategory":"Clothing, Apparel, & Fashions",
            "type":"Retail Goods"
        }
    ],
    "sg:phone":"+1 870 364 2113",
    "sg:postcode":"71635",
    "sg:province":"AR",
    "sg:tags":[
        "perfume",
        "cosmetic",
        "accessory"
    ],
    "wof:name":"Merle Norman Cosmetics",
    "wof:placetype":"venue"
},
  "geometry": {"coordinates":[-91.961198,33.125456],"type":"Point"}
}