{
  "type": "Feature",
  "properties": {
    "iso:country":"US",
    "sg:address":"735 Orchard Rd",
    "sg:city":"Hector",
    "sg:classifiers":[
        {
            "category":"Building & Trades",
            "subcategory":"Construction",
            "type":"Services"
        }
    ],
    "sg:phone":"+1 479 331 4923",
    "sg:postcode":"72843",
    "sg:province":"AR",
    "sg:tags":[
        "system",
        "contractor",
        "air conditioning"
    ],
    "sg:website":"http://www.heil-hvac.com",
    "wof:name":"Alexander's Heat & Air Sales & Service",
    "wof:placetype":"venue"
},
  "geometry": {"coordinates":[-92.928106,35.480047],"type":"Point"}
}