{
  "type": "Feature",
  "properties": {
    "addr:full":"2531 Catcher Rd Van Buren AR 72956",
    "addr:housenumber":"2531",
    "addr:postcode":"72956",
    "addr:street":"Catcher Rd",
    "iso:country":"US",
    "sg:address":"2531 Catcher Rd",
    "sg:city":"Van Buren",
    "sg:classifiers":[
        {
            "category":"Organizations",
            "subcategory":"Religious Organization",
            "type":"Services"
        }
    ],
    "sg:phone":"+1 479 474 2976",
    "sg:postcode":"72956",
    "sg:province":"AR",
    "wof:name":"New Hope United Methodist C Hu",
    "wof:placetype":"venue"
},
  "geometry": {"coordinates":[-94.276809,35.398402],"type":"Point"}
}