{
  "type": "Feature",
  "properties": {
    "addr:full":"610 Honeysuckle Ln Cabot AR 72023",
    "addr:housenumber":"610",
    "addr:postcode":"72023",
    "addr:street":"Honeysuckle Ln",
    "iso:country":"US",
    "sg:address":"610 Honeysuckle Ln",
    "sg:city":"Cabot",
    "sg:classifiers":[
        {
            "category":"Building & Trades",
            "subcategory":"Construction",
            "type":"Services"
        }
    ],
    "sg:phone":"+1 501 843 5782",
    "sg:postcode":"72023",
    "sg:province":"AR",
    "sg:tags":[
        "commercial",
        "contractor"
    ],
    "wof:name":"Yankee Construction Inc",
    "wof:placetype":"venue"
},
  "geometry": {"coordinates":[-91.996105,34.963524],"type":"Point"}
}