{
  "type": "Feature",
  "properties": {
    "iso:country":"US",
    "sg:address":"4900 Rogers Ave",
    "sg:city":"Fort Smith",
    "sg:classifiers":[
        {
            "category":"Wholesale",
            "subcategory":"Stationery",
            "type":"Manufacturing & Wholesale Goods"
        },
        {
            "category":"Shopping",
            "type":"Retail Goods"
        }
    ],
    "sg:phone":"+1 479 452 6288",
    "sg:postcode":"72903",
    "sg:province":"AR",
    "sg:tags":[
        "educational",
        "toy",
        "game",
        "school",
        "supply"
    ],
    "wof:name":"Learning Oasis",
    "wof:placetype":"venue"
},
  "geometry": {"coordinates":[-94.375153,35.36395],"type":"Point"}
}