{
  "type": "Feature",
  "properties": {
    "addr:full":"14 Kingshighway Eureka Springs AR 72632",
    "addr:housenumber":"14",
    "addr:postcode":"72632",
    "addr:street":"Kingshighway",
    "iso:country":"US",
    "sg:address":"14 Kingshighway",
    "sg:city":"Eureka Springs",
    "sg:classifiers":[
        {
            "category":"Professional",
            "subcategory":"Business Services",
            "type":"Services"
        }
    ],
    "sg:phone":"+1 479 253 2037",
    "sg:postcode":"72632",
    "sg:province":"AR",
    "wof:name":"Roger & Davina Lockhart F",
    "wof:placetype":"venue"
},
  "geometry": {"coordinates":[-93.74482500000001,36.401139],"type":"Point"}
}