{
  "type": "Feature",
  "properties": {
    "iso:country":"US",
    "sg:address":"5300 Hoover St",
    "sg:city":"White Hall",
    "sg:classifiers":[
        {
            "category":"Organizations",
            "subcategory":"Labor Organization",
            "type":"Services"
        }
    ],
    "sg:phone":"+1 870 247 9987",
    "sg:postcode":"71602",
    "sg:province":"AR",
    "wof:name":"Upiu-IBEW Labor Temple of Pine",
    "wof:placetype":"venue"
},
  "geometry": {"coordinates":[-92.058646,34.23903],"type":"Point"}
}