{
  "type": "Feature",
  "properties": {
    "addr:full":"212 E Elm St Rogers AR 72756",
    "addr:housenumber":"212",
    "addr:postcode":"72756",
    "addr:street":"E Elm St",
    "iso:country":"US",
    "sg:address":"212 E Elm St",
    "sg:city":"Rogers",
    "sg:classifiers":[
        {
            "category":"Farming",
            "subcategory":"Poultry Farm",
            "type":"Manufacturing & Wholesale Goods"
        }
    ],
    "sg:phone":"+1 479 636 1620",
    "sg:postcode":"72756",
    "sg:province":"AR",
    "sg:tags":[
        "poultry-wholesale"
    ],
    "sg:website":"http://www.tyson.com",
    "wof:name":"Tyson",
    "wof:placetype":"venue"
},
  "geometry": {"coordinates":[-94.115236,36.331874],"type":"Point"}
}