{
  "type": "Feature",
  "properties": {
    "addr:full":"470 N Washington Ave El Dorado AR 71730",
    "addr:housenumber":"470",
    "addr:postcode":"71730",
    "addr:street":"N Washington Ave",
    "iso:country":"US",
    "sg:address":"470 N Washington Ave",
    "sg:city":"El Dorado",
    "sg:classifiers":[
        {
            "category":"Professional",
            "subcategory":"Employment Agencies",
            "type":"Services"
        }
    ],
    "sg:phone":"+1 870 864 7082",
    "sg:postcode":"71730",
    "sg:province":"AR",
    "sg:tags":[
        "consultant",
        "search",
        "executive"
    ],
    "wof:name":"Care Net",
    "wof:placetype":"venue"
},
  "geometry": {"coordinates":[-92.66381699999999,33.214637],"type":"Point"}
}