{
  "type": "Feature",
  "properties": {
    "iso:country":"US",
    "sg:address":"1510 Success St",
    "sg:city":"Corning",
    "sg:classifiers":[
        {
            "category":"Manufacturing",
            "subcategory":"Pet Food",
            "type":"Manufacturing & Wholesale Goods"
        }
    ],
    "sg:phone":"+1 870 857 3164",
    "sg:postcode":"72422",
    "sg:province":"AR",
    "sg:tags":[
        "feed"
    ],
    "wof:name":"Sam & Sam's Products Inc",
    "wof:placetype":"venue"
},
  "geometry": {"coordinates":[-90.592968,36.412424],"type":"Point"}
}