{
  "type": "Feature",
  "properties": {
    "iso:country":"US",
    "sg:address":"1757 N Crossover Rd",
    "sg:city":"Fayetteville",
    "sg:classifiers":[
        {
            "category":"Retail",
            "subcategory":"Car Wash",
            "type":"Services"
        }
    ],
    "sg:phone":"+1 479 695 1750",
    "sg:postcode":"72701",
    "sg:province":"AR",
    "sg:tags":[
        "polishing",
        "washing"
    ],
    "wof:name":"Wash World LLC",
    "wof:placetype":"venue"
},
  "geometry": {"coordinates":[-94.121426,36.084819],"type":"Point"}
}