{
  "type": "Feature",
  "properties": {
    "iso:country":"US",
    "sg:address":"16889 Heritage Bay Rd",
    "sg:city":"Rogers",
    "sg:classifiers":[
        {
            "category":"Organizations",
            "subcategory":"Professional Association",
            "type":"Services"
        }
    ],
    "sg:phone":"+1 479 925 2863",
    "sg:postcode":"72756",
    "sg:province":"AR",
    "wof:name":"Heritage Bay Condominium Assn",
    "wof:placetype":"venue"
},
  "geometry": {"coordinates":[-94.007621,36.331183],"type":"Point"}
}