{
  "type": "Feature",
  "properties": {
    "iso:country":"US",
    "sg:address":"494 S Hopewell Loop",
    "sg:city":"Atkins",
    "sg:classifiers":[
        {
            "category":"Building & Trades",
            "subcategory":"Construction",
            "type":"Services"
        }
    ],
    "sg:phone":"+1 479 641 1418",
    "sg:postcode":"72823",
    "sg:province":"AR",
    "sg:tags":[
        "home",
        "general",
        "family",
        "contractor"
    ],
    "wof:name":"Hegeman Bill Construction",
    "wof:placetype":"venue"
},
  "geometry": {"coordinates":[-92.91630000000001,35.258393],"type":"Point"}
}