{
  "type": "Feature",
  "properties": {
    "addr:full":"4516 W 6th Ave White Hall AR 71602",
    "addr:housenumber":"4516",
    "addr:postcode":"71602",
    "addr:street":"W 6Th Ave",
    "iso:country":"US",
    "sg:address":"4516 W 6th Ave",
    "sg:city":"White Hall",
    "sg:classifiers":[
        {
            "category":"Retail",
            "subcategory":"Auto Repair",
            "type":"Services"
        }
    ],
    "sg:phone":"+1 870 879 1158",
    "sg:postcode":"71602",
    "sg:province":"AR",
    "sg:tags":[
        "repairing",
        "automobile"
    ],
    "wof:name":"Matthews Auto Repair & Wrecker",
    "wof:placetype":"venue"
},
  "geometry": {"coordinates":[-92.055403,34.223748],"type":"Point"}
}