{
  "type": "Feature",
  "properties": {
    "iso:country":"US",
    "sg:address":"2503 W 28th Ave",
    "sg:city":"Pine Bluff",
    "sg:classifiers":[
        {
            "category":"Personal",
            "subcategory":"Beauty Salon",
            "type":"Services"
        }
    ],
    "sg:phone":"+1 870 850 0665",
    "sg:postcode":"71603",
    "sg:province":"AR",
    "wof:name":"Terri Lynn's Saloon",
    "wof:placetype":"venue"
},
  "geometry": {"coordinates":[-92.029042,34.201864],"type":"Point"}
}