{
  "type": "Feature",
  "properties": {
    "addr:full":"2300 E Highland Dr Jonesboro AR 72401",
    "addr:housenumber":"2300",
    "addr:postcode":"72401",
    "addr:street":"E Highland Dr",
    "iso:country":"US",
    "sg:address":"2300 E Highland Dr",
    "sg:city":"Jonesboro",
    "sg:classifiers":[
        {
            "category":"Shopping",
            "subcategory":"Department Store",
            "type":"Retail Goods"
        }
    ],
    "sg:phone":"+1 870 802 4361",
    "sg:postcode":"72401",
    "sg:province":"AR",
    "sg:tags":[
        "shop"
    ],
    "sg:website":"www.pier1.com",
    "wof:name":"Pier 1 Imports",
    "wof:placetype":"venue"
},
  "geometry": {"coordinates":[-90.67783300000001,35.821217],"type":"Point"}
}