{
  "type": "Feature",
  "properties": {
    "iso:country":"US",
    "sg:address":"1265 Cash Rd SW",
    "sg:city":"Camden",
    "sg:classifiers":[
        {
            "category":"Home & Garden",
            "subcategory":"Carpets & Floor Coverings",
            "type":"Retail Goods"
        }
    ],
    "sg:phone":"+1 870 837 2542",
    "sg:postcode":"71701",
    "sg:province":"AR",
    "sg:tags":[
        "dealer",
        "rug"
    ],
    "wof:name":"Bo Kirby's Carpet",
    "wof:placetype":"venue"
},
  "geometry": {"coordinates":[-92.853879,33.56237],"type":"Point"}
}