{
  "type": "Feature",
  "properties": {
    "iso:country":"US",
    "sg:address":"322 Towson Ave",
    "sg:city":"Fort Smith",
    "sg:classifiers":[
        {
            "category":"Autos & Motor Vehicles",
            "subcategory":"Automobile Sales",
            "type":"Retail Goods"
        }
    ],
    "sg:phone":"+1 479 785 0341",
    "sg:postcode":"72901",
    "sg:province":"AR",
    "sg:tags":[
        "used"
    ],
    "wof:name":"Name Brand Auto Sales",
    "wof:placetype":"venue"
},
  "geometry": {"coordinates":[-94.42119099999999,35.380482],"type":"Point"}
}