{
  "type": "Feature",
  "properties": {
    "addr:full":"22010 Colonel Glenn Rd Little Rock AR 72210",
    "addr:housenumber":"22010",
    "addr:postcode":"72210",
    "addr:street":"Colonel Glenn Rd",
    "iso:country":"US",
    "sg:address":"22010 Colonel Glenn Rd",
    "sg:city":"Little Rock",
    "sg:classifiers":[
        {
            "category":"Professional",
            "subcategory":"Detective & Security Services",
            "type":"Services"
        }
    ],
    "sg:phone":"+1 501 821 8092",
    "sg:postcode":"72210",
    "sg:province":"AR",
    "sg:tags":[
        "control",
        "equipment",
        "retail",
        "system"
    ],
    "wof:name":"Sound Security Service Inc",
    "wof:placetype":"venue"
},
  "geometry": {"coordinates":[-92.522524,34.740945],"type":"Point"}
}