{
  "type": "Feature",
  "properties": {
    "iso:country":"US",
    "sg:address":"209 Morrow St N",
    "sg:city":"Mena",
    "sg:classifiers":[
        {
            "category":"Health Services",
            "subcategory":"Doctor",
            "type":"Services"
        },
        {
            "category":"Health Services",
            "subcategory":"Clinic",
            "type":"Services"
        },
        {
            "category":"Community Center",
            "type":"Public Place"
        }
    ],
    "sg:phone":"+1 479 394 4703",
    "sg:postcode":"71953",
    "sg:province":"AR",
    "sg:tags":[
        "physician",
        "family",
        "medical",
        "practice",
        "surgeons",
        "medicine"
    ],
    "wof:name":"Rich Mountain Family Medical Clinic",
    "wof:placetype":"venue"
},
  "geometry": {"coordinates":[-94.222517,34.586814],"type":"Point"}
}