{
  "type": "Feature",
  "properties": {
    "iso:country":"US",
    "sg:address":"3401 S 79th St",
    "sg:city":"Fort Smith",
    "sg:classifiers":[
        {
            "category":"Freight",
            "type":"Transportation"
        }
    ],
    "sg:phone":"+1 479 649 6699",
    "sg:postcode":"72903",
    "sg:province":"AR",
    "sg:tags":[
        "mover",
        "moving"
    ],
    "wof:name":"Two Men and A Truck",
    "wof:placetype":"venue"
},
  "geometry": {"coordinates":[-94.344973,35.348818],"type":"Point"}
}