{
  "type": "Feature",
  "properties": {
    "iso:country":"US",
    "sg:address":"37 Eagle Mountain Blvd",
    "sg:city":"Batesville",
    "sg:classifiers":[
        {
            "category":"Personal",
            "subcategory":"Nail Salon",
            "type":"Services"
        }
    ],
    "sg:phone":"+1 870 612 9999",
    "sg:postcode":"72501",
    "sg:province":"AR",
    "wof:name":"Nailsville",
    "wof:placetype":"venue"
},
  "geometry": {"coordinates":[-91.612764,35.765111],"type":"Point"}
}