{
  "type": "Feature",
  "properties": {
    "iso:country":"US",
    "sg:address":"4820 Francis St",
    "sg:city":"North Little Rock",
    "sg:classifiers":[
        {
            "category":"Building & Trades",
            "subcategory":"Landscaping Services",
            "type":"Services"
        }
    ],
    "sg:phone":"+1 501 258 2683",
    "sg:postcode":"72118",
    "sg:province":"AR",
    "sg:tags":[
        "landscape"
    ],
    "wof:name":"Handy Lawn Care Plus",
    "wof:placetype":"venue"
},
  "geometry": {"coordinates":[-92.281005,34.799562],"type":"Point"}
}