{
  "type": "Feature",
  "properties": {
    "iso:country":"US",
    "sg:address":"221 E Capitol Ave",
    "sg:city":"Little Rock",
    "sg:classifiers":[
        {
            "category":"Utilities",
            "subcategory":"Water",
            "type":"Services"
        }
    ],
    "sg:phone":"+1 501 372 5161",
    "sg:postcode":"72202",
    "sg:province":"AR",
    "sg:tags":[
        "company",
        "sewage"
    ],
    "sg:website":"www.carkw.com",
    "wof:name":"Central Arkansas Water",
    "wof:placetype":"venue"
},
  "geometry": {"coordinates":[-92.269495,34.743869],"type":"Point"}
}