{
  "type": "Feature",
  "properties": {
    "addr:full":"150 Ernestway St Hot Springs National Park AR 71913",
    "addr:housenumber":"150",
    "addr:postcode":"71913",
    "addr:street":"Ernestway St;Park",
    "iso:country":"US",
    "sg:address":"150 Ernestway St",
    "sg:city":"Hot Springs National Park",
    "sg:classifiers":[
        {
            "category":"Building & Trades",
            "subcategory":"Construction",
            "type":"Services"
        }
    ],
    "sg:phone":"+1 501 767 6054",
    "sg:postcode":"71913",
    "sg:province":"AR",
    "sg:tags":[
        "nonresidential",
        "contractor"
    ],
    "wof:name":"Blue Sky Construction",
    "wof:placetype":"venue"
},
  "geometry": {"coordinates":[-93.13591099999999,34.470921],"type":"Point"}
}