{
  "type": "Feature",
  "properties": {
    "iso:country":"US",
    "sg:address":"3863 Treat Ln",
    "sg:city":"Springdale",
    "sg:classifiers":[
        {
            "category":"Building & Trades",
            "subcategory":"Landscaping Services",
            "type":"Services"
        }
    ],
    "sg:phone":"+1 479 927 0111",
    "sg:postcode":"72762",
    "sg:province":"AR",
    "sg:tags":[
        "lawn",
        "landscape",
        "maintenance",
        "contractor"
    ],
    "sg:website":"http://www.scotts.com",
    "wof:name":"Scotts Lawn Service",
    "wof:placetype":"venue"
},
  "geometry": {"coordinates":[-94.174015,36.185047],"type":"Point"}
}