{
  "type": "Feature",
  "properties": {
    "iso:country":"US",
    "sg:address":"4210 W 28th Ave",
    "sg:city":"Pine Bluff",
    "sg:classifiers":[
        {
            "category":"Organizations",
            "subcategory":"Religious Organization",
            "type":"Services"
        }
    ],
    "sg:phone":"+1 870 267 1266",
    "sg:postcode":"71603",
    "sg:province":"AR",
    "wof:name":"Christian Jubilee Center",
    "wof:placetype":"venue"
},
  "geometry": {"coordinates":[-92.048327,34.201761],"type":"Point"}
}