{
  "type": "Feature",
  "properties": {
    "iso:country":"US",
    "sg:address":"113 Greenwood Ave",
    "sg:city":"Lepanto",
    "sg:classifiers":[
        {
            "category":"Government",
            "subcategory":"City Hall",
            "type":"Public Place"
        }
    ],
    "sg:phone":"+1 870 475 3161",
    "sg:postcode":"72354",
    "sg:province":"AR",
    "wof:name":"Lepanto City Hall Fax Line",
    "wof:placetype":"venue"
},
  "geometry": {"coordinates":[-90.330823,35.613095],"type":"Point"}
}