{
  "type": "Feature",
  "properties": {
    "addr:full":"622 S 2nd St Rogers AR 72756",
    "addr:housenumber":"622",
    "addr:postcode":"72756",
    "addr:street":"S 2Nd St",
    "iso:country":"US",
    "sg:address":"622 S 2nd St",
    "sg:city":"Rogers",
    "sg:classifiers":[
        {
            "category":"Building & Trades",
            "subcategory":"Construction",
            "type":"Services"
        }
    ],
    "sg:phone":"+1 479 621 9772",
    "sg:postcode":"72756",
    "sg:province":"AR",
    "sg:tags":[
        "durable",
        "good",
        "painter",
        "special"
    ],
    "wof:name":"Rolando's Painting",
    "wof:placetype":"venue"
},
  "geometry": {"coordinates":[-94.118239,36.32794],"type":"Point"}
}