{
  "type": "Feature",
  "properties": {
    "iso:country":"US",
    "sg:address":"5201 Village Pkwy",
    "sg:city":"Rogers",
    "sg:classifiers":[
        {
            "category":"Organizations",
            "subcategory":"Professional Association",
            "type":"Services"
        }
    ],
    "sg:phone":"+1 479 986 3747",
    "sg:postcode":"72758",
    "sg:province":"AR",
    "sg:tags":[
        "business"
    ],
    "wof:name":"S C O R E 0511",
    "wof:placetype":"venue"
},
  "geometry": {"coordinates":[-94.186872,36.317581],"type":"Point"}
}