{
  "type": "Feature",
  "properties": {
    "addr:full":"508 SW 14th St Bentonville AR 72712",
    "addr:housenumber":"508",
    "addr:postcode":"72712",
    "addr:street":"Sw 14Th St",
    "iso:country":"US",
    "sg:address":"508 SW 14th St",
    "sg:city":"Bentonville",
    "sg:classifiers":[
        {
            "category":"Home & Garden",
            "subcategory":"Building Materials",
            "type":"Retail Goods"
        }
    ],
    "sg:phone":"+1 479 273 0160",
    "sg:postcode":"72712",
    "sg:province":"AR",
    "sg:tags":[
        "glass",
        "window",
        "tinting",
        "plate"
    ],
    "sg:website":"www.glasstint.com",
    "wof:name":"Arkansas Glass & Tinting",
    "wof:placetype":"venue"
},
  "geometry": {"coordinates":[-94.21456999999999,36.357021],"type":"Point"}
}