{
  "type": "Feature",
  "properties": {
    "iso:country":"US",
    "sg:address":"1125 S Independence Ave",
    "sg:city":"Russellville",
    "sg:classifiers":[
        {
            "category":"Professional",
            "type":"Services"
        }
    ],
    "sg:phone":"+1 479 967 1143",
    "sg:postcode":"72801",
    "sg:province":"AR",
    "wof:name":"Friendship Service",
    "wof:placetype":"venue"
},
  "geometry": {"coordinates":[-93.142798,35.267233],"type":"Point"}
}