{
  "type": "Feature",
  "properties": {
    "iso:country":"US",
    "sg:address":"2748 State Hwy 319",
    "sg:city":"Austin",
    "sg:classifiers":[
        {
            "category":"Professional",
            "type":"Services"
        }
    ],
    "sg:phone":"+1 501 843 1025",
    "sg:postcode":"72007",
    "sg:province":"AR",
    "wof:name":"David Thomasson",
    "wof:placetype":"venue"
},
  "geometry": {"coordinates":[-91.981569,35.04175],"type":"Point"}
}