{
  "type": "Feature",
  "properties": {
    "addr:full":"1601 Greene Rd 729 Paragould AR 72450",
    "addr:housenumber":"1601",
    "addr:postcode":"72450",
    "addr:street":"Greene Rd 729",
    "iso:country":"US",
    "sg:address":"1601 Greene Rd 729",
    "sg:city":"Paragould",
    "sg:classifiers":[
        {
            "category":"Freight",
            "type":"Transportation"
        }
    ],
    "sg:phone":"+1 870 236 9227",
    "sg:postcode":"72450",
    "sg:province":"AR",
    "sg:tags":[
        "trucking"
    ],
    "wof:name":"R & S Materials",
    "wof:placetype":"venue"
},
  "geometry": {"coordinates":[-90.55839899999999,35.994677],"type":"Point"}
}