{
  "type": "Feature",
  "properties": {
    "iso:country":"US",
    "sg:address":"3815 E Huntsville Rd",
    "sg:city":"Fayetteville",
    "sg:classifiers":[
        {
            "category":"Shopping",
            "subcategory":"Used Merchandise",
            "type":"Retail Goods"
        }
    ],
    "sg:phone":"+1 479 527 3944",
    "sg:postcode":"72701",
    "sg:province":"AR",
    "sg:tags":[
        "antique"
    ],
    "wof:name":"Red Barn Antiques",
    "wof:placetype":"venue"
},
  "geometry": {"coordinates":[-94.106383,36.053776],"type":"Point"}
}