{
  "type": "Feature",
  "properties": {
    "iso:country":"US",
    "sg:address":"605 N 2nd St",
    "sg:city":"Blytheville",
    "sg:classifiers":[
        {
            "category":"Health Services",
            "subcategory":"Doctor",
            "type":"Services"
        }
    ],
    "sg:phone":"+1 870 763 1520",
    "sg:postcode":"72315",
    "sg:province":"AR",
    "sg:tags":[
        "physician",
        "medical",
        "surgeons",
        "internal",
        "medicine",
        "surgeon"
    ],
    "wof:name":"Internal Medicine Associates",
    "wof:placetype":"venue"
},
  "geometry": {"coordinates":[-89.90422100000001,35.932936],"type":"Point"}
}