{
  "type": "Feature",
  "properties": {
    "iso:country":"US",
    "sg:address":"2308 Cottonwood Pl",
    "sg:city":"Springdale",
    "sg:classifiers":[
        {
            "category":"Building & Trades",
            "subcategory":"Pest Control",
            "type":"Services"
        }
    ],
    "sg:phone":"+1 479 756 9289",
    "sg:postcode":"72762",
    "sg:province":"AR",
    "wof:name":"Pest Birds of Arkansas Inc",
    "wof:placetype":"venue"
},
  "geometry": {"coordinates":[-94.16293,36.145559],"type":"Point"}
}