{
  "type": "Feature",
  "properties": {
    "iso:country":"US",
    "sg:address":"22075 Sawmill Rd",
    "sg:city":"Siloam Springs",
    "sg:classifiers":[
        {
            "category":"Farming",
            "subcategory":"Farm & Veterinary Services",
            "type":"Manufacturing & Wholesale Goods"
        }
    ],
    "sg:phone":"+1 479 524 5351",
    "sg:postcode":"72761",
    "sg:province":"OK",
    "sg:tags":[
        "preparation",
        "soil"
    ],
    "wof:name":"Pauls Lime and Fertelizer",
    "wof:placetype":"venue"
},
  "geometry": {"coordinates":[-94.526015,36.134623],"type":"Point"}
}