{
  "type": "Feature",
  "properties": {
    "iso:country":"US",
    "sg:address":"717 SW 5th St",
    "sg:city":"Walnut Ridge",
    "sg:classifiers":[
        {
            "category":"Building & Trades",
            "subcategory":"Plumbing",
            "type":"Services"
        }
    ],
    "sg:phone":"+1 870 886 5358",
    "sg:postcode":"72476",
    "sg:province":"AR",
    "sg:tags":[
        "contractor"
    ],
    "wof:name":"Moody Bbby Gene Son Plbg Sewer",
    "wof:placetype":"venue"
},
  "geometry": {"coordinates":[-90.965469,36.066727],"type":"Point"}
}