{
  "type": "Feature",
  "properties": {
    "iso:country":"US",
    "sg:address":"206 Cherry St",
    "sg:city":"Green Forest",
    "sg:classifiers":[
        {
            "category":"Real Estate",
            "subcategory":"Real Estate Operator",
            "type":"Services"
        }
    ],
    "sg:phone":"+1 870 438 6558",
    "sg:postcode":"72638",
    "sg:province":"AR",
    "sg:tags":[
        "building",
        "apartment"
    ],
    "wof:name":"Oak Hills Apartments Inc",
    "wof:placetype":"venue"
},
  "geometry": {"coordinates":[-93.43436800000001,36.339319],"type":"Point"}
}