{
  "type": "Feature",
  "properties": {
    "addr:full":"200 E Arkansas Ave Star City AR 71667",
    "addr:housenumber":"200",
    "addr:postcode":"71667",
    "addr:street":"E Arkansas Ave",
    "iso:country":"US",
    "sg:address":"200 E Arkansas Ave",
    "sg:city":"Star City",
    "sg:classifiers":[
        {
            "category":"Personal",
            "subcategory":"Beauty Salon",
            "type":"Services"
        }
    ],
    "sg:phone":"+1 870 628 3310",
    "sg:postcode":"71667",
    "sg:province":"AR",
    "wof:name":"KUT & KURL",
    "wof:placetype":"venue"
},
  "geometry": {"coordinates":[-91.843024,33.942548],"type":"Point"}
}