{
  "type": "Feature",
  "properties": {
    "iso:country":"US",
    "sg:address":"2230 Wood St",
    "sg:city":"Jonesboro",
    "sg:classifiers":[
        {
            "category":"Building & Trades",
            "subcategory":"Construction",
            "type":"Services"
        }
    ],
    "sg:phone":"+1 870 972 8002",
    "sg:postcode":"72401",
    "sg:province":"AR",
    "sg:tags":[
        "house"
    ],
    "wof:name":"Topp Gunn Home Improvement",
    "wof:placetype":"venue"
},
  "geometry": {"coordinates":[-90.72055,35.818875],"type":"Point"}
}