{
  "type": "Feature",
  "properties": {
    "addr:full":"1632 S 56th St Springdale AR 72762",
    "addr:housenumber":"1632",
    "addr:postcode":"72762",
    "addr:street":"S 56Th St",
    "iso:country":"US",
    "sg:address":"1632 S 56th St",
    "sg:city":"Springdale",
    "sg:classifiers":[
        {
            "category":"Building & Trades",
            "subcategory":"Landscaping Services",
            "type":"Services"
        }
    ],
    "sg:phone":"+1 479 443 2763",
    "sg:postcode":"72762",
    "sg:province":"AR",
    "sg:tags":[
        "lawn",
        "designer",
        "consultant",
        "contractor",
        "maintenance",
        "landscape"
    ],
    "sg:website":"http://www.allaroundlandscaping.com",
    "wof:name":"All Around Landscaping Inc",
    "wof:placetype":"venue"
},
  "geometry": {"coordinates":[-94.192589,36.171583],"type":"Point"}
}