{
  "type": "Feature",
  "properties": {
    "iso:country":"US",
    "sg:address":"2318 W 28th Ave",
    "sg:city":"Pine Bluff",
    "sg:classifiers":[
        {
            "category":"Retail",
            "subcategory":"Laundry & Dry Cleaning",
            "type":"Services"
        }
    ],
    "sg:phone":"+1 870 536 6266",
    "sg:postcode":"71603",
    "sg:province":"AR",
    "wof:name":"Ed's Cleaners",
    "wof:placetype":"venue"
},
  "geometry": {"coordinates":[-92.026816,34.201742],"type":"Point"}
}