{
  "type": "Feature",
  "properties": {
    "iso:country":"US",
    "sg:address":"155 Farris Rd",
    "sg:city":"Conway",
    "sg:classifiers":[
        {
            "category":"Retail",
            "subcategory":"Laundry & Dry Cleaning",
            "type":"Services"
        }
    ],
    "sg:phone":"+1 501 450 0012",
    "sg:postcode":"72034",
    "sg:province":"AR",
    "sg:tags":[
        "laundries-self",
        "operated",
        "washer",
        "dryer",
        "coin"
    ],
    "wof:name":"Fun Wash",
    "wof:placetype":"venue"
},
  "geometry": {"coordinates":[-92.463088,35.078386],"type":"Point"}
}