{
  "type": "Feature",
  "properties": {
    "iso:country":"US",
    "sg:address":"290 Rocky Mountain Way",
    "sg:city":"Hot Springs National Park",
    "sg:classifiers":[
        {
            "category":"Building & Trades",
            "subcategory":"Construction",
            "type":"Services"
        }
    ],
    "sg:phone":"+1 501 520 4100",
    "sg:postcode":"71913",
    "sg:province":"AR",
    "sg:tags":[
        "contractor"
    ],
    "wof:name":"J & K Insulation Inc",
    "wof:placetype":"venue"
},
  "geometry": {"coordinates":[-93.169424,34.400693],"type":"Point"}
}