{
  "type": "Feature",
  "properties": {
    "iso:country":"US",
    "sg:address":"4313 W Markham St",
    "sg:city":"Little Rock",
    "sg:classifiers":[
        {
            "category":"Government",
            "subcategory":"Office",
            "type":"Public Place"
        }
    ],
    "sg:phone":"+1 501 686 9300",
    "sg:postcode":"72205",
    "sg:province":"AR",
    "sg:tags":[
        "state",
        "program"
    ],
    "wof:name":"Rehabilitation Services",
    "wof:placetype":"venue"
},
  "geometry": {"coordinates":[-92.32174,34.751528],"type":"Point"}
}