{
  "type": "Feature",
  "properties": {
    "iso:country":"US",
    "sg:address":"2004 Turtle Creek Rd",
    "sg:city":"Jonesboro",
    "sg:classifiers":[
        {
            "category":"Real Estate",
            "subcategory":"Developer",
            "type":"Services"
        }
    ],
    "sg:phone":"+1 870 933 7232",
    "sg:postcode":"72404",
    "sg:province":"AR",
    "wof:name":"Matt Jones Properties",
    "wof:placetype":"venue"
},
  "geometry": {"coordinates":[-90.73816600000001,35.814374],"type":"Point"}
}