{
  "type": "Feature",
  "properties": {
    "iso:country":"US",
    "sg:address":"3160 Diamond Hill Dr",
    "sg:city":"Alexander",
    "sg:classifiers":[
        {
            "category":"Insurance",
            "subcategory":"Hazard Insurance",
            "type":"Services"
        }
    ],
    "sg:phone":"+1 501 653 2589",
    "sg:postcode":"72002",
    "sg:province":"AR",
    "sg:tags":[
        "bond"
    ],
    "wof:name":"Buddy York Bail Bonds",
    "wof:placetype":"venue"
},
  "geometry": {"coordinates":[-92.46866,34.665599],"type":"Point"}
}