{
  "type": "Feature",
  "properties": {
    "iso:country":"US",
    "sg:address":"11525 Cantrell Rd",
    "sg:city":"Little Rock",
    "sg:classifiers":[
        {
            "category":"Restaurant",
            "type":"Food & Drink"
        }
    ],
    "sg:menulink":"http://www.allmenus.com/ar/little-rock/161178-cheeburger-cheeburger/menu/",
    "sg:phone":"+1 501 490 2433",
    "sg:postcode":"72212",
    "sg:province":"AR",
    "sg:tags":[
        "burger",
        "american",
        "diner"
    ],
    "wof:name":"Cheeburger Cheeburger",
    "wof:placetype":"venue"
},
  "geometry": {"coordinates":[-92.39994299999999,34.793887],"type":"Point"}
}