{
  "type": "Feature",
  "properties": {
    "addr:full":"2101 SE Walton Blvd Bentonville AR 72712",
    "addr:housenumber":"2101",
    "addr:postcode":"72712",
    "addr:street":"Se Walton Blvd",
    "iso:country":"US",
    "sg:address":"2101 SE Walton Blvd",
    "sg:city":"Bentonville",
    "sg:classifiers":[
        {
            "category":"Restaurant",
            "type":"Food & Drink"
        }
    ],
    "sg:phone":"+1 479 271 6288",
    "sg:postcode":"72712",
    "sg:province":"AR",
    "sg:tags":[
        "buffet",
        "chinese"
    ],
    "wof:name":"Lin's Garden Chinese Restaurant",
    "wof:placetype":"venue"
},
  "geometry": {"coordinates":[-94.1889,36.335164],"type":"Point"}
}