{
  "type": "Feature",
  "properties": {
    "addr:full":"2674 Prim Rd Prim AR 72130",
    "addr:postcode":"2674;72130",
    "addr:street":"Prim Rd",
    "iso:country":"US",
    "sg:address":"2674 Prim Rd",
    "sg:city":"Prim",
    "sg:classifiers":[
        {
            "category":"Building & Trades",
            "subcategory":"Construction",
            "type":"Services"
        }
    ],
    "sg:phone":"+1 870 307 1773",
    "sg:postcode":"72130",
    "sg:province":"AR",
    "sg:tags":[
        "house"
    ],
    "wof:name":"Norvell Construction",
    "wof:placetype":"venue"
},
  "geometry": {"coordinates":[-92.084975,35.666447],"type":"Point"}
}