{
  "type": "Feature",
  "properties": {
    "iso:country":"US",
    "sg:address":"1610 Fayetteville Rd",
    "sg:city":"Van Buren",
    "sg:classifiers":[
        {
            "category":"Restaurant",
            "type":"Food & Drink"
        }
    ],
    "sg:menulink":"http://www.allmenus.com/ar/van-buren/174002-wendys/menu/",
    "sg:phone":"+1 479 471 7323",
    "sg:postcode":"72956",
    "sg:province":"AR",
    "sg:tags":[
        "burger",
        "american",
        "soup"
    ],
    "wof:name":"Wendy's",
    "wof:placetype":"venue"
},
  "geometry": {"coordinates":[-94.356525,35.459663],"type":"Point"}
}