{
  "type": "Feature",
  "properties": {
    "iso:country":"US",
    "sg:address":"2402 Wildwood Ave",
    "sg:city":"Sherwood",
    "sg:classifiers":[
        {
            "category":"Professional",
            "subcategory":"Management & Consulting",
            "type":"Services"
        }
    ],
    "sg:phone":"+1 501 835 5448",
    "sg:postcode":"72120",
    "sg:province":"AR",
    "sg:tags":[
        "consultant",
        "educational"
    ],
    "wof:name":"Educational Services-Visually",
    "wof:placetype":"venue"
},
  "geometry": {"coordinates":[-92.20563199999999,34.814269],"type":"Point"}
}