{
  "type": "Feature",
  "properties": {
    "iso:country":"US",
    "sg:address":"984 S Falls Blvd",
    "sg:city":"Wynne",
    "sg:classifiers":[
        {
            "category":"Autos & Motor Vehicles",
            "subcategory":"Automobile Sales",
            "type":"Retail Goods"
        }
    ],
    "sg:phone":"+1 870 238 9679",
    "sg:postcode":"72396",
    "sg:province":"AR",
    "sg:tags":[
        "car",
        "dealer"
    ],
    "wof:name":"City Auto Sales",
    "wof:placetype":"venue"
},
  "geometry": {"coordinates":[-90.787582,35.216181],"type":"Point"}
}