{
  "type": "Feature",
  "properties": {
    "addr:full":"4010 W 12th St Little Rock AR 72204",
    "addr:housenumber":"4010",
    "addr:postcode":"72204",
    "addr:street":"W 12Th St",
    "iso:country":"US",
    "sg:address":"4010 W 12th St",
    "sg:city":"Little Rock",
    "sg:classifiers":[
        {
            "category":"Shopping",
            "subcategory":"Pharmacy",
            "type":"Retail Goods"
        }
    ],
    "sg:phone":"+1 501 663 9497",
    "sg:postcode":"72204",
    "sg:province":"AR",
    "sg:website":"www.usadrug.com",
    "wof:name":"USA Drug Express",
    "wof:placetype":"venue"
},
  "geometry": {"coordinates":[-92.318888,34.740625],"type":"Point"}
}