{
  "type": "Feature",
  "properties": {
    "addr:full":"1825 Whispering Pine Rd Little Rock AR 72210",
    "addr:housenumber":"1825",
    "addr:postcode":"72210",
    "addr:street":"Whispering Pine Rd",
    "iso:country":"US",
    "sg:address":"1825 Whispering Pine Rd",
    "sg:city":"Little Rock",
    "sg:classifiers":[
        {
            "category":"Building & Trades",
            "subcategory":"Construction",
            "type":"Services"
        }
    ],
    "sg:phone":"+1 501 821 4436",
    "sg:postcode":"72210",
    "sg:province":"AR",
    "sg:tags":[
        "general",
        "contractor"
    ],
    "wof:name":"V R Smith & Sons Inc",
    "wof:placetype":"venue"
},
  "geometry": {"coordinates":[-92.54440200000001,34.753299],"type":"Point"}
}