{
  "type": "Feature",
  "properties": {
    "iso:country":"US",
    "sg:address":"1408 W Emma Ave",
    "sg:city":"Springdale",
    "sg:classifiers":[
        {
            "category":"Food & Beverages",
            "subcategory":"Groceries & Convenience Stores",
            "type":"Retail Goods"
        }
    ],
    "sg:phone":"+1 479 751 7739",
    "sg:postcode":"72764",
    "sg:province":"AR",
    "wof:name":"Tottys Minit Stop",
    "wof:placetype":"venue"
},
  "geometry": {"coordinates":[-94.145697,36.185266],"type":"Point"}
}