{
  "type": "Feature",
  "properties": {
    "addr:full":"2200 State Hwy 265 Spr Springdale AR 72764",
    "addr:housenumber":"2200",
    "addr:postcode":"72764",
    "addr:street":"State Hwy 265 Spr",
    "iso:country":"US",
    "sg:address":"2200 State Hwy 265 Spr",
    "sg:city":"Springdale",
    "sg:classifiers":[
        {
            "category":"Wholesale",
            "subcategory":"Office Equipment",
            "type":"Manufacturing & Wholesale Goods"
        }
    ],
    "sg:phone":"+1 479 582 4044",
    "sg:postcode":"72764",
    "sg:province":"AR",
    "sg:tags":[
        "machine",
        "duplicating",
        "copying"
    ],
    "wof:name":"Ikon Office Solutions",
    "wof:placetype":"venue"
},
  "geometry": {"coordinates":[-94.10345700000001,36.184343],"type":"Point"}
}