{
  "type": "Feature",
  "properties": {
    "iso:country":"US",
    "sg:address":"400 President Clinton Ave",
    "sg:city":"Little Rock",
    "sg:classifiers":[
        {
            "category":"Restaurant",
            "type":"Food & Drink"
        }
    ],
    "sg:phone":"+1 501 376 2326",
    "sg:postcode":"72201",
    "sg:province":"AR",
    "sg:tags":[
        "eating"
    ],
    "wof:name":"Andina Cafe & Coffee Rostery",
    "wof:placetype":"venue"
},
  "geometry": {"coordinates":[-92.266103,34.747523],"type":"Point"}
}