{
  "type": "Feature",
  "properties": {
    "iso:country":"US",
    "sg:address":"1805 S Pleasant St",
    "sg:city":"Springdale",
    "sg:classifiers":[
        {
            "category":"Professional",
            "type":"Services"
        }
    ],
    "sg:phone":"+1 479 751 4828",
    "sg:postcode":"72764",
    "sg:province":"AR",
    "sg:tags":[
        "establishment"
    ],
    "wof:name":"Skelton Brothers Inc",
    "wof:placetype":"venue"
},
  "geometry": {"coordinates":[-94.143495,36.169979],"type":"Point"}
}