{
  "type": "Feature",
  "properties": {
    "iso:country":"US",
    "sg:address":"1009 N Missouri Ave",
    "sg:city":"Corning",
    "sg:classifiers":[
        {
            "category":"Wholesale",
            "subcategory":"Machinery & Supplies",
            "type":"Manufacturing & Wholesale Goods"
        }
    ],
    "sg:phone":"+1 870 857 5225",
    "sg:postcode":"72422",
    "sg:province":"AR",
    "sg:tags":[
        "farm",
        "equipment"
    ],
    "wof:name":"Blankenship Equipment",
    "wof:placetype":"venue"
},
  "geometry": {"coordinates":[-90.58624399999999,36.420989],"type":"Point"}
}