{
  "type": "Feature",
  "properties": {
    "iso:country":"US",
    "sg:address":"721 S 7th St",
    "sg:city":"Arkadelphia",
    "sg:classifiers":[
        {
            "category":"Sports & Exercise",
            "subcategory":"Gym",
            "type":"Entertainment"
        }
    ],
    "sg:phone":"+1 870 245 0044",
    "sg:postcode":"71923",
    "sg:province":"AR",
    "sg:tags":[
        "club",
        "health",
        "studio",
        "gymnasium"
    ],
    "wof:name":"Curves",
    "wof:placetype":"venue"
},
  "geometry": {"coordinates":[-93.054949,34.114988],"type":"Point"}
}