{
  "type": "Feature",
  "properties": {
    "iso:country":"US",
    "sg:address":"1920 S Main St",
    "sg:city":"Searcy",
    "sg:classifiers":[
        {
            "category":"Wholesale",
            "subcategory":"Hardware",
            "type":"Manufacturing & Wholesale Goods"
        },
        {
            "category":"Home & Garden",
            "subcategory":"Garden Supply",
            "type":"Retail Goods"
        },
        {
            "category":"Retail",
            "subcategory":"Repair Shop",
            "type":"Services"
        }
    ],
    "sg:phone":"+1 501 268 1987",
    "sg:postcode":"72143",
    "sg:province":"AR",
    "sg:tags":[
        "renting",
        "lawn",
        "outdoor",
        "power",
        "landscaping",
        "equipment-sales",
        "equipment",
        "saw"
    ],
    "sg:website":"http://www.stihldealer.net/default-dealer-012251.aspx",
    "wof:name":"Henard Utility Products, Inc",
    "wof:placetype":"venue"
},
  "geometry": {"coordinates":[-91.731407,35.277435],"type":"Point"}
}