{
  "type": "Feature",
  "properties": {
    "addr:full":"210 Quapaw Ave Hot Springs National AR 71901",
    "addr:housenumber":"210",
    "addr:postcode":"71901",
    "addr:street":"Quapaw Ave",
    "iso:country":"US",
    "sg:address":"210 Quapaw Ave",
    "sg:city":"Hot Springs National",
    "sg:classifiers":[
        {
            "category":"Travel",
            "subcategory":"Hotels & Motels",
            "type":"Entertainment"
        }
    ],
    "sg:phone":"+1 501 321 2817",
    "sg:postcode":"71901",
    "sg:province":"AR",
    "sg:tags":[
        "operation"
    ],
    "wof:name":"Courts Ozark",
    "wof:placetype":"venue"
},
  "geometry": {"coordinates":[-93.05664899999999,34.509587],"type":"Point"}
}