{
  "type": "Feature",
  "properties": {
    "iso:country":"US",
    "sg:address":"1695 Smoke Ridge Rd",
    "sg:city":"Malvern",
    "sg:classifiers":[
        {
            "category":"Professional",
            "type":"Services"
        }
    ],
    "sg:phone":"+1 501 332 5347",
    "sg:postcode":"72104",
    "sg:province":"AR",
    "wof:name":"Phillip H Rodgers",
    "wof:placetype":"venue"
},
  "geometry": {"coordinates":[-92.851353,34.447263],"type":"Point"}
}