{
  "type": "Feature",
  "properties": {
    "addr:full":"207 Gillham Rd Beebe AR 72012",
    "addr:housenumber":"207",
    "addr:postcode":"72012",
    "addr:street":"Gillham Rd",
    "iso:country":"US",
    "sg:address":"207 Gillham Rd",
    "sg:city":"Beebe",
    "sg:classifiers":[
        {
            "category":"Freight",
            "type":"Transportation"
        }
    ],
    "sg:phone":"+1 501 882 2081",
    "sg:postcode":"72012",
    "sg:province":"AR",
    "sg:tags":[
        "distance",
        "long",
        "trucking"
    ],
    "wof:name":"Black Trucking",
    "wof:placetype":"venue"
},
  "geometry": {"coordinates":[-91.98875700000001,35.090287],"type":"Point"}
}