{
  "type": "Feature",
  "properties": {
    "addr:full":"3001 State Hwy 25 B N Heber Springs AR 72543",
    "addr:housenumber":"3001;b",
    "addr:postcode":"72543",
    "addr:street":"State Hwy 25;N Heber Springs",
    "iso:country":"US",
    "sg:address":"3001 State Hwy 25 B N",
    "sg:city":"Heber Springs",
    "sg:classifiers":[
        {
            "category":"Personal",
            "type":"Services"
        },
        {
            "category":"Restaurant",
            "type":"Food & Drink"
        }
    ],
    "sg:phone":"+1 501 362 9702",
    "sg:postcode":"72543",
    "sg:province":"AR",
    "wof:name":"Mc Pherson's Restaurant",
    "wof:placetype":"venue"
},
  "geometry": {"coordinates":[-92.021263,35.516246],"type":"Point"}
}