{
  "type": "Feature",
  "properties": {
    "addr:full":"190 Wilson Mill Rd Monticello AR 71655",
    "addr:housenumber":"190",
    "addr:postcode":"71655",
    "addr:street":"Wilson Mill Rd",
    "iso:country":"US",
    "sg:address":"190 Wilson Mill Rd",
    "sg:city":"Monticello",
    "sg:classifiers":[
        {
            "category":"Manufacturing",
            "subcategory":"Lumber",
            "type":"Manufacturing & Wholesale Goods"
        }
    ],
    "sg:phone":"+1 870 367 2436",
    "sg:postcode":"71655",
    "sg:province":"AR",
    "sg:tags":[
        "hardwood",
        "flooring",
        "mfg"
    ],
    "wof:name":"Maxwell Hardwood Inc",
    "wof:placetype":"venue"
},
  "geometry": {"coordinates":[-91.79268999999999,33.57934],"type":"Point"}
}