{
  "type": "Feature",
  "properties": {
    "iso:country":"US",
    "sg:address":"160 Morphew Rd",
    "sg:city":"Hot Springs National Park",
    "sg:classifiers":[
        {
            "category":"Real Estate",
            "subcategory":"Real Estate Operator",
            "type":"Services"
        }
    ],
    "sg:phone":"+1 501 767 9700",
    "sg:postcode":"71913",
    "sg:province":"AR",
    "sg:tags":[
        "building",
        "apartment"
    ],
    "wof:name":"Chapel Ridge Apartments",
    "wof:placetype":"venue"
},
  "geometry": {"coordinates":[-93.13292,34.459267],"type":"Point"}
}