{
  "type": "Feature",
  "properties": {
    "iso:country":"US",
    "sg:address":"7401 Asher Ave",
    "sg:city":"Little Rock",
    "sg:classifiers":[
        {
            "category":"Government",
            "subcategory":"Post Office",
            "type":"Public Place"
        }
    ],
    "sg:phone":"+1 501 000 1111",
    "sg:postcode":"72204",
    "sg:province":"AR",
    "wof:name":"US Post Office",
    "wof:placetype":"venue"
},
  "geometry": {"coordinates":[-92.357658,34.715858],"type":"Point"}
}