{
  "type": "Feature",
  "properties": {
    "addr:full":"3 Beaconsfield Ln Bella Vista AR 72714",
    "addr:housenumber":"3",
    "addr:postcode":"72714",
    "addr:street":"Beaconsfield Ln",
    "iso:country":"US",
    "sg:address":"3 Beaconsfield Ln",
    "sg:city":"Bella Vista",
    "sg:classifiers":[
        {
            "category":"Building & Trades",
            "subcategory":"Construction",
            "type":"Services"
        }
    ],
    "sg:phone":"+1 479 876 5355",
    "sg:postcode":"72714",
    "sg:province":"AR",
    "sg:tags":[
        "house"
    ],
    "wof:name":"Farrer Homes Brent",
    "wof:placetype":"venue"
},
  "geometry": {"coordinates":[-94.230554,36.470664],"type":"Point"}
}