{
  "type": "Feature",
  "properties": {
    "iso:country":"US",
    "sg:address":"116 E 10th St",
    "sg:city":"Mountain Home",
    "sg:classifiers":[
        {
            "category":"Retail",
            "subcategory":"Animal Services",
            "type":"Services"
        }
    ],
    "sg:phone":"+1 870 424 2799",
    "sg:postcode":"72653",
    "sg:province":"AR",
    "sg:tags":[
        "pet",
        "grooming",
        "washing"
    ],
    "wof:name":"Heliana's Grooming",
    "wof:placetype":"venue"
},
  "geometry": {"coordinates":[-92.384481,36.33134],"type":"Point"}
}