{
  "type": "Feature",
  "properties": {
    "addr:full":"116 E 10th St Mountain Home AR 72653",
    "addr:housenumber":"116",
    "addr:postcode":"72653",
    "addr:street":"E 10Th St",
    "iso:country":"US",
    "sg:address":"116 E 10th St",
    "sg:city":"Mountain Home",
    "sg:classifiers":[
        {
            "category":"Retail",
            "subcategory":"Animal Services",
            "type":"Services"
        }
    ],
    "sg:phone":"+1 870 424 2799",
    "sg:postcode":"72653",
    "sg:province":"AR",
    "sg:tags":[
        "pet",
        "grooming",
        "washing"
    ],
    "wof:name":"Heliana's Grooming",
    "wof:placetype":"venue"
},
  "geometry": {"coordinates":[-92.38448099999999,36.33134],"type":"Point"}
}