{
  "type": "Feature",
  "properties": {
    "addr:full":"11220 N Rodney Parham Rd Little Rock AR 72212",
    "addr:housenumber":"11220",
    "addr:postcode":"72212",
    "addr:street":"N;Parham Rd",
    "iso:country":"US",
    "sg:address":"11220 N Rodney Parham Rd",
    "sg:city":"Little Rock",
    "sg:classifiers":[
        {
            "category":"Travel",
            "subcategory":"Travel Agent",
            "type":"Entertainment"
        }
    ],
    "sg:phone":"+1 501 223 4722",
    "sg:postcode":"72212",
    "sg:province":"AR",
    "sg:tags":[
        "agency",
        "bureau"
    ],
    "wof:name":"World Wide Travel Svc",
    "wof:placetype":"venue"
},
  "geometry": {"coordinates":[-92.39971300000001,34.772082],"type":"Point"}
}