{
  "type": "Feature",
  "properties": {
    "iso:country":"US",
    "sg:address":"5259 Hwy 67 S",
    "sg:city":"Pocahontas",
    "sg:classifiers":[
        {
            "category":"Cinema",
            "subcategory":"Movie Theater",
            "type":"Entertainment"
        }
    ],
    "sg:phone":"+1 870 892 8096",
    "sg:postcode":"72455",
    "sg:province":"AR",
    "wof:name":"Cinema City Twin Cinema",
    "wof:placetype":"venue"
},
  "geometry": {"coordinates":[-90.95871699999999,36.198773],"type":"Point"}
}