{
  "type": "Feature",
  "properties": {
    "iso:country":"US",
    "sg:address":"803 S 3rd St",
    "sg:city":"Arkadelphia",
    "sg:classifiers":[
        {
            "category":"Retail",
            "subcategory":"Auto Repair",
            "type":"Services"
        }
    ],
    "sg:phone":"+1 870 246 2669",
    "sg:postcode":"71923",
    "sg:province":"AR",
    "sg:tags":[
        "wrecker",
        "general"
    ],
    "wof:name":"Boyer's Auto Repair & Wrecker",
    "wof:placetype":"venue"
},
  "geometry": {"coordinates":[-93.050202,34.113378],"type":"Point"}
}