{
  "type": "Feature",
  "properties": {
    "iso:country":"US",
    "sg:address":"5021 Baseline Rd",
    "sg:city":"Little Rock",
    "sg:classifiers":[
        {
            "category":"Banks & Credit Unions",
            "subcategory":"Investment Brokerage",
            "type":"Services"
        }
    ],
    "sg:phone":"+1 501 562 3366",
    "sg:postcode":"72209",
    "sg:province":"AR",
    "sg:tags":[
        "consultant",
        "planning",
        "financial"
    ],
    "wof:name":"Mattingly Financial Svc",
    "wof:placetype":"venue"
},
  "geometry": {"coordinates":[-92.335555,34.668834],"type":"Point"}
}