{
  "type": "Feature",
  "properties": {
    "iso:country":"US",
    "sg:address":"1322 Main St",
    "sg:city":"Van Buren",
    "sg:classifiers":[
        {
            "category":"Home & Garden",
            "subcategory":"Furniture",
            "type":"Retail Goods"
        }
    ],
    "sg:phone":"+1 479 410 2016",
    "sg:postcode":"72956",
    "sg:province":"AR",
    "sg:tags":[
        "bed"
    ],
    "wof:name":"Royal Mattress Center",
    "wof:placetype":"venue"
},
  "geometry": {"coordinates":[-94.344857,35.436564],"type":"Point"}
}