{
  "type": "Feature",
  "properties": {
    "iso:country":"US",
    "sg:address":"5706 Sue Ln",
    "sg:city":"Lavaca",
    "sg:classifiers":[
        {
            "category":"Health Services",
            "subcategory":"Nursing And Care Facility",
            "type":"Services"
        }
    ],
    "sg:phone":"+1 479 674 2174",
    "sg:postcode":"72941",
    "sg:province":"AR",
    "sg:tags":[
        "intermediate"
    ],
    "wof:name":"Billings Fairchild",
    "wof:placetype":"venue"
},
  "geometry": {"coordinates":[-94.227096,35.350163],"type":"Point"}
}