{
  "type": "Feature",
  "properties": {
    "iso:country":"US",
    "sg:address":"1029 S College St",
    "sg:city":"Mountain Home",
    "sg:classifiers":[
        {
            "category":"Personal",
            "subcategory":"Beauty Salon",
            "type":"Services"
        }
    ],
    "sg:phone":"+1 870 425 6240",
    "sg:postcode":"72653",
    "sg:province":"AR",
    "sg:tags":[
        "shop"
    ],
    "wof:name":"Design's By Diane",
    "wof:placetype":"venue"
},
  "geometry": {"coordinates":[-92.380737,36.330746],"type":"Point"}
}