{
  "type": "Feature",
  "properties": {
    "iso:country":"US",
    "sg:address":"805 S Air Base Hwy",
    "sg:city":"Blytheville",
    "sg:classifiers":[
        {
            "category":"Personal",
            "subcategory":"Beauty Salon",
            "type":"Services"
        }
    ],
    "sg:phone":"+1 870 532 5516",
    "sg:postcode":"72315",
    "sg:province":"AR",
    "sg:tags":[
        "shop"
    ],
    "wof:name":"Deloras Hair Styling Center",
    "wof:placetype":"venue"
},
  "geometry": {"coordinates":[-89.96514500000001,35.950464],"type":"Point"}
}