{
  "type": "Feature",
  "properties": {
    "iso:country":"US",
    "sg:address":"106 S Rodney Parham Rd",
    "sg:city":"Little Rock",
    "sg:classifiers":[
        {
            "category":"Shopping",
            "subcategory":"Pharmacy",
            "type":"Retail Goods"
        }
    ],
    "sg:phone":"+1 501 225 2322",
    "sg:postcode":"72205",
    "sg:province":"AR",
    "wof:name":"Darnell Drug Company Inc",
    "wof:placetype":"venue"
},
  "geometry": {"coordinates":[-92.36687,34.752756],"type":"Point"}
}