{
  "type": "Feature",
  "properties": {
    "addr:full":"2115 Louisiana St Little Rock AR 72206",
    "addr:housenumber":"2115",
    "addr:postcode":"72206",
    "addr:street":"Louisiana St",
    "iso:country":"US",
    "sg:address":"2115 Louisiana St",
    "sg:city":"Little Rock",
    "sg:classifiers":[
        {
            "category":"Professional",
            "subcategory":"Engineering",
            "type":"Services"
        }
    ],
    "sg:phone":"+1 501 372 4881",
    "sg:postcode":"72206",
    "sg:province":"AR",
    "wof:name":"Oswald Engineering Inc",
    "wof:placetype":"venue"
},
  "geometry": {"coordinates":[-92.274956,34.727889],"type":"Point"}
}