{
  "type": "Feature",
  "properties": {
    "iso:country":"US",
    "sg:address":"15 E Chestnut St",
    "sg:city":"Marianna",
    "sg:classifiers":[
        {
            "category":"Government",
            "subcategory":"Police Station",
            "type":"Public Place"
        }
    ],
    "sg:phone":"+1 870 295 7777",
    "sg:postcode":"72360",
    "sg:province":"AR",
    "sg:tags":[
        "sheriff"
    ],
    "wof:name":"Lee County Sheriff",
    "wof:placetype":"venue"
},
  "geometry": {"coordinates":[-90.757492,34.7746],"type":"Point"}
}