{
  "type": "Feature",
  "properties": {
    "iso:country":"US",
    "sg:address":"2448 Hwy 62 W",
    "sg:city":"Mountain Home",
    "sg:classifiers":[
        {
            "category":"Autos & Motor Vehicles",
            "subcategory":"Automobile Sales",
            "type":"Retail Goods"
        }
    ],
    "sg:phone":"+1 870 425 6996",
    "sg:postcode":"72653",
    "sg:province":"AR",
    "sg:tags":[
        "car",
        "dealership",
        "dealer"
    ],
    "sg:website":"www.ultimateautogroup.com",
    "wof:name":"Ultimate Auto Group Inc",
    "wof:placetype":"venue"
},
  "geometry": {"coordinates":[-92.393342,36.320504],"type":"Point"}
}