{
  "type": "Feature",
  "properties": {
    "addr:full":"1101 Spring St Mountain Home AR 72653",
    "addr:housenumber":"1101",
    "addr:postcode":"72653",
    "addr:street":"Spring St",
    "iso:country":"US",
    "sg:address":"1101 Spring St",
    "sg:city":"Mountain Home",
    "sg:classifiers":[
        {
            "category":"Health Services",
            "subcategory":"Clinic",
            "type":"Services"
        }
    ],
    "sg:phone":"+1 870 425 9811",
    "sg:postcode":"72653",
    "sg:province":"AR",
    "sg:tags":[
        "home"
    ],
    "wof:name":"Area Agency On Aging",
    "wof:placetype":"venue"
},
  "geometry": {"coordinates":[-92.368664,36.34352],"type":"Point"}
}