{
  "type": "Feature",
  "properties": {
    "addr:full":"253 Greyland Rd Lockesburg AR 71846",
    "addr:housenumber":"253",
    "addr:postcode":"71846",
    "addr:street":"Greyland Rd",
    "iso:country":"US",
    "sg:address":"253 Greyland Rd",
    "sg:city":"Lockesburg",
    "sg:classifiers":[
        {
            "category":"Wholesale",
            "subcategory":"Farm Supplies",
            "type":"Manufacturing & Wholesale Goods"
        }
    ],
    "sg:phone":"+1 870 286 5610",
    "sg:postcode":"71846",
    "sg:province":"AR",
    "sg:tags":[
        "auction",
        "livestock",
        "market"
    ],
    "wof:name":"John N Hendrix Corp",
    "wof:placetype":"venue"
},
  "geometry": {"coordinates":[-94.10232999999999,34.020394],"type":"Point"}
}