{
  "type": "Feature",
  "properties": {
    "iso:country":"US",
    "sg:address":"500 W Broadway",
    "sg:city":"West Memphis",
    "sg:classifiers":[
        {
            "category":"Shopping",
            "subcategory":"Tobacco",
            "type":"Retail Goods"
        }
    ],
    "sg:phone":"+1 870 735 6915",
    "sg:postcode":"72301",
    "sg:province":"AR",
    "sg:tags":[
        "cigarette",
        "cigar",
        "dealer"
    ],
    "wof:name":"Tobacco Superstore",
    "wof:placetype":"venue"
},
  "geometry": {"coordinates":[-90.195836,35.146262],"type":"Point"}
}