{
  "type": "Feature",
  "properties": {
    "addr:full":"508 Foster Chapel Rd Searcy AR 72143",
    "addr:housenumber":"508",
    "addr:postcode":"72143",
    "addr:street":"Foster Chapel Rd",
    "iso:country":"US",
    "sg:address":"508 Foster Chapel Rd",
    "sg:city":"Searcy",
    "sg:classifiers":[
        {
            "category":"Manufacturing",
            "subcategory":"Chemicals & Compounds",
            "type":"Manufacturing & Wholesale Goods"
        }
    ],
    "sg:phone":"+1 501 279 2729",
    "sg:postcode":"72143",
    "sg:province":"AR",
    "sg:tags":[
        "chemicals-wholesale",
        "manufacturer"
    ],
    "wof:name":"Protective Coatings Inc",
    "wof:placetype":"venue"
},
  "geometry": {"coordinates":[-91.79997,35.284016],"type":"Point"}
}