{
  "type": "Feature",
  "properties": {
    "iso:country":"US",
    "sg:address":"16781 Hwy 5 S",
    "sg:city":"Norfork",
    "sg:classifiers":[
        {
            "category":"Building & Trades",
            "subcategory":"Construction",
            "type":"Services"
        }
    ],
    "sg:phone":"+1 870 499 7269",
    "sg:postcode":"72658",
    "sg:province":"AR",
    "sg:tags":[
        "hanging",
        "contractor"
    ],
    "wof:name":"Fuller Paint Service",
    "wof:placetype":"venue"
},
  "geometry": {"coordinates":[-92.240029,36.18417],"type":"Point"}
}