{
  "type": "Feature",
  "properties": {
    "iso:country":"US",
    "sg:address":"12029 Marche Rd",
    "sg:city":"Maumelle",
    "sg:classifiers":[
        {
            "category":"Education",
            "subcategory":"School",
            "type":"Public Place"
        }
    ],
    "sg:phone":"+1 501 551 6646",
    "sg:postcode":"72118",
    "sg:province":"AR",
    "wof:name":"Cox Consulting",
    "wof:placetype":"venue"
},
  "geometry": {"coordinates":[-92.361909,34.862828],"type":"Point"}
}