{
  "type": "Feature",
  "properties": {
    "iso:country":"US",
    "sg:address":"708 Towne Oaks Dr",
    "sg:city":"Little Rock",
    "sg:classifiers":[
        {
            "category":"Building & Trades",
            "subcategory":"Equipment Rental",
            "type":"Services"
        }
    ],
    "sg:phone":"+1 501 224 3133",
    "sg:postcode":"72227",
    "sg:province":"AR",
    "sg:tags":[
        "party",
        "supply"
    ],
    "wof:name":"Party Time Rental Inc",
    "wof:placetype":"venue"
},
  "geometry": {"coordinates":[-92.377982,34.761018],"type":"Point"}
}