{
  "type": "Feature",
  "properties": {
    "iso:country":"US",
    "sg:address":"222 W 6th St",
    "sg:city":"Mountain Home",
    "sg:classifiers":[
        {
            "category":"Manufacturing",
            "subcategory":"Metals",
            "type":"Manufacturing & Wholesale Goods"
        }
    ],
    "sg:phone":"+1 870 425 7214",
    "sg:postcode":"72653",
    "sg:province":"AR",
    "sg:tags":[
        "product",
        "fabricated",
        "mfg"
    ],
    "wof:name":"Moark Award Co",
    "wof:placetype":"venue"
},
  "geometry": {"coordinates":[-92.38883800000001,36.336239],"type":"Point"}
}