{
  "type": "Feature",
  "properties": {
    "iso:country":"US",
    "sg:address":"3215 Coats Rd",
    "sg:city":"Benton",
    "sg:classifiers":[
        {
            "category":"Organizations",
            "subcategory":"Religious Organization",
            "type":"Services"
        }
    ],
    "sg:phone":"+1 501 860 6909",
    "sg:postcode":"72015",
    "sg:province":"AR",
    "sg:tags":[
        "church"
    ],
    "wof:name":"Temple Baptist Church",
    "wof:placetype":"venue"
},
  "geometry": {"coordinates":[-92.547843,34.57414],"type":"Point"}
}