{
  "type": "Feature",
  "properties": {
    "iso:country":"US",
    "sg:address":"9444 US Hwy 65",
    "sg:city":"Bee Branch",
    "sg:classifiers":[
        {
            "category":"Building & Trades",
            "subcategory":"Construction",
            "type":"Services"
        }
    ],
    "sg:phone":"+1 501 745 4366",
    "sg:postcode":"72013",
    "sg:province":"AR",
    "sg:tags":[
        "hanging",
        "contractor"
    ],
    "wof:name":"John Bull Painting",
    "wof:placetype":"venue"
},
  "geometry": {"coordinates":[-92.414932,35.469561],"type":"Point"}
}