{
  "type": "Feature",
  "properties": {
    "addr:full":"8703 Geyer Springs Rd Little Rock AR 72209",
    "addr:housenumber":"8703",
    "addr:postcode":"72209",
    "addr:street":"Geyer Springs Rd",
    "iso:country":"US",
    "sg:address":"8703 Geyer Springs Rd",
    "sg:city":"Little Rock",
    "sg:classifiers":[
        {
            "category":"Restaurant",
            "type":"Food & Drink"
        }
    ],
    "sg:menulink":"http://www.allmenus.com/ar/little-rock/173977-wendys/menu/",
    "sg:phone":"+1 501 562 7506",
    "sg:postcode":"72209",
    "sg:province":"AR",
    "sg:tags":[
        "burger",
        "american",
        "soup"
    ],
    "wof:name":"Wendy's",
    "wof:placetype":"venue"
},
  "geometry": {"coordinates":[-92.34425299999999,34.670977],"type":"Point"}
}