{
  "type": "Feature",
  "properties": {
    "iso:country":"US",
    "sg:address":"15116 State Rte 333",
    "sg:city":"Dover",
    "sg:classifiers":[
        {
            "category":"Organizations",
            "subcategory":"Religious Organization",
            "type":"Services"
        }
    ],
    "sg:phone":"+1 479 331 2652",
    "sg:postcode":"72837",
    "sg:province":"AR",
    "sg:tags":[
        "church"
    ],
    "wof:name":"North New Hope Assembly Of God",
    "wof:placetype":"venue"
},
  "geometry": {"coordinates":[-93.167858,35.409062],"type":"Point"}
}