{
  "type": "Feature",
  "properties": {
    "iso:country":"US",
    "sg:address":"313 N 3rd St",
    "sg:city":"Augusta",
    "sg:classifiers":[
        {
            "category":"Retail",
            "subcategory":"Auto Repair",
            "type":"Services"
        }
    ],
    "sg:phone":"+1 870 347 2139",
    "sg:postcode":"72006",
    "sg:province":"AR",
    "sg:tags":[
        "body"
    ],
    "wof:name":"Youngmans Collision Center LLC",
    "wof:placetype":"venue"
},
  "geometry": {"coordinates":[-91.365251,35.286212],"type":"Point"}
}