{
  "type": "Feature",
  "properties": {
    "addr:full":"3490 State Hwy 301 Delight AR 71940",
    "addr:housenumber":"3490",
    "addr:postcode":"71940",
    "addr:street":"State Hwy 301",
    "iso:country":"US",
    "sg:address":"3490 State Hwy 301",
    "sg:city":"Delight",
    "sg:classifiers":[
        {
            "category":"Manufacturing",
            "subcategory":"Lumber",
            "type":"Manufacturing & Wholesale Goods"
        }
    ],
    "sg:phone":"+1 870 379 3013",
    "sg:postcode":"71940",
    "sg:province":"AR",
    "sg:tags":[
        "logging"
    ],
    "wof:name":"Hills Logging",
    "wof:placetype":"venue"
},
  "geometry": {"coordinates":[-93.596158,33.988234],"type":"Point"}
}