{
  "type": "Feature",
  "properties": {
    "iso:country":"US",
    "sg:address":"906 Hwy 62 E",
    "sg:city":"Mountain Home",
    "sg:classifiers":[
        {
            "category":"Shopping",
            "subcategory":"Books",
            "type":"Retail Goods"
        }
    ],
    "sg:phone":"+1 870 425 7505",
    "sg:postcode":"72653",
    "sg:province":"AR",
    "sg:tags":[
        "dealer"
    ],
    "wof:name":"Bearly Used Book & Etc",
    "wof:placetype":"venue"
},
  "geometry": {"coordinates":[-92.375092,36.347438],"type":"Point"}
}