{
  "type": "Feature",
  "properties": {
    "addr:full":"909 Charles St El Dorado AR 71730",
    "addr:housenumber":"909",
    "addr:postcode":"71730",
    "addr:street":"Charles St",
    "iso:country":"US",
    "sg:address":"909 Charles St",
    "sg:city":"El Dorado",
    "sg:classifiers":[
        {
            "category":"Utilities",
            "subcategory":"Mobile Phone",
            "type":"Services"
        }
    ],
    "sg:phone":"+1 870 863 9144",
    "sg:postcode":"71730",
    "sg:province":"AR",
    "sg:tags":[
        "telephone",
        "cellular"
    ],
    "wof:name":"Alltel Communications",
    "wof:placetype":"venue"
},
  "geometry": {"coordinates":[-92.63513500000001,33.200021],"type":"Point"}
}