{
  "type": "Feature",
  "properties": {
    "iso:country":"US",
    "sg:address":"850 US Hwy 65 Bus",
    "sg:city":"Clinton",
    "sg:classifiers":[
        {
            "category":"Insurance",
            "subcategory":"Insurance Agent",
            "type":"Services"
        }
    ],
    "sg:phone":"+1 501 745 7900",
    "sg:postcode":"72031",
    "sg:province":"AR",
    "wof:name":"Kimbrell's Insurance",
    "wof:placetype":"venue"
},
  "geometry": {"coordinates":[-92.463042,35.597275],"type":"Point"}
}