{
  "type": "Feature",
  "properties": {
    "iso:country":"US",
    "sg:address":"14023 Fortson Rd",
    "sg:city":"Jacksonville",
    "sg:classifiers":[
        {
            "category":"Health Services",
            "subcategory":"Medical Lab",
            "type":"Services"
        }
    ],
    "sg:phone":"+1 501 988 2264",
    "sg:postcode":"72076",
    "sg:province":"AR",
    "sg:tags":[
        "laboratory",
        "dental"
    ],
    "wof:name":"Mitchell Dental Laboratories",
    "wof:placetype":"venue"
},
  "geometry": {"coordinates":[-92.210246,34.994758],"type":"Point"}
}