{
  "type": "Feature",
  "properties": {
    "iso:country":"US",
    "sg:address":"515 Oak Cir",
    "sg:city":"Little Rock",
    "sg:classifiers":[
        {
            "category":"Real Estate",
            "subcategory":"Real Estate Agent",
            "type":"Services"
        }
    ],
    "sg:phone":"+1 501 376 6731",
    "sg:postcode":"72206",
    "sg:province":"AR",
    "wof:name":"Henley-Longing Real Estate",
    "wof:placetype":"venue"
},
  "geometry": {"coordinates":[-92.27373299999999,34.666429],"type":"Point"}
}