{
  "type": "Feature",
  "properties": {
    "iso:country":"US",
    "sg:address":"2371 Green Acres",
    "sg:city":"Fayetteville",
    "sg:classifiers":[
        {
            "category":"Education",
            "subcategory":"Dance Studio",
            "type":"Public Place"
        }
    ],
    "sg:phone":"+1 479 444 7779",
    "sg:postcode":"72703",
    "sg:province":"AR",
    "sg:tags":[
        "instruction",
        "dancing"
    ],
    "wof:name":"Art Of Motion",
    "wof:placetype":"venue"
},
  "geometry": {"coordinates":[-94.157373,36.094753],"type":"Point"}
}