{
  "type": "Feature",
  "properties": {
    "iso:country":"US",
    "sg:address":"1604 W Main St",
    "sg:city":"Walnut Ridge",
    "sg:classifiers":[
        {
            "category":"Restaurant",
            "type":"Food & Drink"
        }
    ],
    "sg:phone":"+1 870 886 9808",
    "sg:postcode":"72476",
    "sg:province":"AR",
    "wof:name":"Don's Steakhouse",
    "wof:placetype":"venue"
},
  "geometry": {"coordinates":[-90.97173600000001,36.074966],"type":"Point"}
}