{
  "type": "Feature",
  "properties": {
    "iso:country":"US",
    "sg:address":"4323 W 29th St",
    "sg:city":"Little Rock",
    "sg:classifiers":[
        {
            "category":"Retail",
            "subcategory":"Funeral Services",
            "type":"Services"
        }
    ],
    "sg:phone":"+1 501 660 4323",
    "sg:postcode":"72204",
    "sg:province":"AR",
    "sg:tags":[
        "director"
    ],
    "wof:name":"Gunn Funeral Home",
    "wof:placetype":"venue"
},
  "geometry": {"coordinates":[-92.322625,34.725129],"type":"Point"}
}