{
  "type": "Feature",
  "properties": {
    "iso:country":"US",
    "sg:address":"1021 W Sypert St",
    "sg:city":"Nashville",
    "sg:classifiers":[
        {
            "category":"Manufacturing",
            "subcategory":"Tools & Machinery",
            "type":"Manufacturing & Wholesale Goods"
        },
        {
            "category":"Wholesale",
            "subcategory":"Home Furnishings",
            "type":"Manufacturing & Wholesale Goods"
        }
    ],
    "sg:phone":"+1 870 845 3155",
    "sg:postcode":"71852",
    "sg:province":"AR",
    "sg:tags":[
        "electric",
        "fixture",
        "equipment",
        "part",
        "plumbing",
        "supplies-wholesale",
        "manufacturer"
    ],
    "wof:name":"R & J Supply Inc",
    "wof:placetype":"venue"
},
  "geometry": {"coordinates":[-93.860387,33.941788],"type":"Point"}
}