{
  "type": "Feature",
  "properties": {
    "iso:country":"US",
    "sg:address":"13325 E 1st St",
    "sg:city":"Alexander",
    "sg:classifiers":[
        {
            "category":"Food & Beverages",
            "subcategory":"Groceries & Convenience Stores",
            "type":"Retail Goods"
        }
    ],
    "sg:phone":"+1 501 455 0345",
    "sg:postcode":"72002",
    "sg:province":"AR",
    "wof:name":"Economy Grocery",
    "wof:placetype":"venue"
},
  "geometry": {"coordinates":[-92.44311,34.630875],"type":"Point"}
}