{
  "type": "Feature",
  "properties": {
    "iso:country":"US",
    "sg:address":"1007 Martin Luther King Jr Dr",
    "sg:city":"Helena",
    "sg:classifiers":[
        {
            "category":"Building & Trades",
            "subcategory":"Construction",
            "type":"Services"
        }
    ],
    "sg:phone":"+1 870 338 8472",
    "sg:postcode":"72342",
    "sg:province":"AR",
    "sg:tags":[
        "residential",
        "contractor"
    ],
    "wof:name":"Champion Builders Inc",
    "wof:placetype":"venue"
},
  "geometry": {"coordinates":[-90.609654,34.501741],"type":"Point"}
}