{
  "type": "Feature",
  "properties": {
    "iso:country":"US",
    "sg:address":"11025 Anderson Dr",
    "sg:city":"Little Rock",
    "sg:classifiers":[
        {
            "category":"Professional",
            "subcategory":"Lawyer & Legal Services",
            "type":"Services"
        }
    ],
    "sg:phone":"+1 501 219 0077",
    "sg:postcode":"72212",
    "sg:province":"AR",
    "wof:name":"Hare Wynn Newell & Newton LLP",
    "wof:placetype":"venue"
},
  "geometry": {"coordinates":[-92.39471500000001,34.789843],"type":"Point"}
}