{
  "type": "Feature",
  "properties": {
    "iso:country":"US",
    "sg:address":"231 Phillips Rd",
    "sg:city":"Pottsville",
    "sg:classifiers":[
        {
            "category":"Building & Trades",
            "subcategory":"Construction",
            "type":"Services"
        }
    ],
    "sg:phone":"+1 479 968 5360",
    "sg:postcode":"72858",
    "sg:province":"AR",
    "sg:tags":[
        "painter"
    ],
    "wof:name":"Steve Ferguson's Painting",
    "wof:placetype":"venue"
},
  "geometry": {"coordinates":[-93.02262500000001,35.256163],"type":"Point"}
}