{
  "type": "Feature",
  "properties": {
    "addr:full":"107 N Reynolds Rd Bryant AR 72022",
    "addr:housenumber":"107",
    "addr:postcode":"72022",
    "addr:street":"N Reynolds Rd",
    "iso:country":"US",
    "sg:address":"107 N Reynolds Rd",
    "sg:city":"Bryant",
    "sg:classifiers":[
        {
            "category":"Personal",
            "subcategory":"Beauty Salon",
            "type":"Services"
        }
    ],
    "sg:phone":"+1 501 847 8382",
    "sg:postcode":"72022",
    "sg:province":"AR",
    "sg:tags":[
        "shop"
    ],
    "wof:name":"Smitty's Hair Styles",
    "wof:placetype":"venue"
},
  "geometry": {"coordinates":[-92.489104,34.595786],"type":"Point"}
}