{
  "type": "Feature",
  "properties": {
    "iso:country":"US",
    "sg:address":"3604 Jefferson Ave",
    "sg:city":"Texarkana",
    "sg:classifiers":[
        {
            "category":"Shopping",
            "subcategory":"Gifts & Souvenirs",
            "type":"Retail Goods"
        },
        {
            "category":"Shopping",
            "subcategory":"Clothing, Apparel, & Fashions",
            "type":"Retail Goods"
        }
    ],
    "sg:phone":"+1 870 774 7744",
    "sg:postcode":"71854",
    "sg:province":"AR",
    "wof:name":"Carolyn's Closet",
    "wof:placetype":"venue"
},
  "geometry": {"coordinates":[-94.029139,33.458151],"type":"Point"}
}