{
  "type": "Feature",
  "properties": {
    "iso:country":"US",
    "sg:address":"410 Hwy 371 S",
    "sg:city":"Magnolia",
    "sg:classifiers":[
        {
            "category":"Building & Trades",
            "subcategory":"Landscaping Services",
            "type":"Services"
        }
    ],
    "sg:phone":"+1 870 234 1173",
    "sg:postcode":"71753",
    "sg:province":"AR",
    "sg:tags":[
        "fence"
    ],
    "wof:name":"Emerson Fence Co",
    "wof:placetype":"venue"
},
  "geometry": {"coordinates":[-93.270872,33.269128],"type":"Point"}
}