{
  "type": "Feature",
  "properties": {
    "iso:country":"US",
    "sg:address":"3002 E 19th St",
    "sg:city":"Texarkana",
    "sg:classifiers":[
        {
            "category":"Professional",
            "subcategory":"Art Services",
            "type":"Services"
        }
    ],
    "sg:phone":"+1 870 773 0029",
    "sg:postcode":"71854",
    "sg:province":"AR",
    "sg:tags":[
        "arts",
        "graphic",
        "design"
    ],
    "wof:name":"American Screen Printing",
    "wof:placetype":"venue"
},
  "geometry": {"coordinates":[-94.008252,33.440477],"type":"Point"}
}