{
  "type": "Feature",
  "properties": {
    "iso:country":"US",
    "sg:address":"300 S Church St",
    "sg:city":"Jonesboro",
    "sg:classifiers":[
        {
            "category":"Banks & Credit Unions",
            "subcategory":"Bank",
            "type":"Services"
        }
    ],
    "sg:phone":"+1 870 935 5521",
    "sg:postcode":"72401",
    "sg:province":"AR",
    "wof:name":"Regions",
    "wof:placetype":"venue"
},
  "geometry": {"coordinates":[-90.70394400000001,35.840549],"type":"Point"}
}