{
  "type": "Feature",
  "properties": {
    "iso:country":"US",
    "sg:address":"1108 Vine St",
    "sg:city":"Batesville",
    "sg:classifiers":[
        {
            "category":"Personal",
            "subcategory":"Beauty Salon",
            "type":"Services"
        }
    ],
    "sg:phone":"+1 870 793 8173",
    "sg:postcode":"72501",
    "sg:province":"AR",
    "wof:name":"Jim's Beauty Supply",
    "wof:placetype":"venue"
},
  "geometry": {"coordinates":[-91.641694,35.773602],"type":"Point"}
}