{
  "type": "Feature",
  "properties": {
    "addr:full":"24 Hunters Cove Cabot AR 72023",
    "addr:housenumber":"24",
    "addr:postcode":"72023",
    "addr:street":"Hunters Cove",
    "iso:country":"US",
    "sg:address":"24 Hunters Cove",
    "sg:city":"Cabot",
    "sg:classifiers":[
        {
            "category":"Professional",
            "type":"Services"
        }
    ],
    "sg:phone":"+1 501 843 2482",
    "sg:postcode":"72023",
    "sg:province":"AR",
    "wof:name":"Randall Ostrander",
    "wof:placetype":"venue"
},
  "geometry": {"coordinates":[-92.018478,34.956559],"type":"Point"}
}