{
  "type": "Feature",
  "properties": {
    "iso:country":"US",
    "sg:address":"4940 E Nettleton Ave",
    "sg:city":"Jonesboro",
    "sg:classifiers":[
        {
            "category":"Health Services",
            "subcategory":"Doctor",
            "type":"Services"
        }
    ],
    "sg:phone":"+1 870 932 2145",
    "sg:postcode":"72401",
    "sg:province":"AR",
    "sg:tags":[
        "clinic"
    ],
    "wof:name":"Haley Chiropractic Clinic",
    "wof:placetype":"venue"
},
  "geometry": {"coordinates":[-90.64986500000001,35.818081],"type":"Point"}
}