{
  "type": "Feature",
  "properties": {
    "iso:country":"US",
    "sg:address":"1203 Park Dr",
    "sg:city":"Hope",
    "sg:classifiers":[
        {
            "category":"Building & Trades",
            "subcategory":"Equipment Rental",
            "type":"Services"
        }
    ],
    "sg:phone":"+1 870 777 2400",
    "sg:postcode":"71801",
    "sg:province":"AR",
    "sg:tags":[
        "yard"
    ],
    "wof:name":"Good Home Ctr",
    "wof:placetype":"venue"
},
  "geometry": {"coordinates":[-93.604567,33.660432],"type":"Point"}
}