{
  "type": "Feature",
  "properties": {
    "iso:country":"US",
    "sg:address":"138 S Gosnell St",
    "sg:city":"Blytheville",
    "sg:classifiers":[
        {
            "category":"Building & Trades",
            "subcategory":"Construction",
            "type":"Services"
        }
    ],
    "sg:phone":"+1 870 532 9725",
    "sg:postcode":"72315",
    "sg:province":"AR",
    "sg:tags":[
        "contractor"
    ],
    "wof:name":"Jacks Fence Co",
    "wof:placetype":"venue"
},
  "geometry": {"coordinates":[-89.971177,35.972001],"type":"Point"}
}