{
  "type": "Feature",
  "properties": {
    "addr:full":"5905 Forest Pl Little Rock AR 72207",
    "addr:housenumber":"5905",
    "addr:postcode":"72207",
    "addr:street":"Forest Pl",
    "iso:country":"US",
    "sg:address":"5905 Forest Pl",
    "sg:city":"Little Rock",
    "sg:classifiers":[
        {
            "category":"Social Services",
            "type":"Services"
        }
    ],
    "sg:phone":"+1 501 666 8686",
    "sg:postcode":"72207",
    "sg:province":"AR",
    "sg:tags":[
        "guidance",
        "child"
    ],
    "sg:website":"www.youthandfamilies.org",
    "wof:name":"Centers For Youth & Families",
    "wof:placetype":"venue"
},
  "geometry": {"coordinates":[-92.33994,34.76506],"type":"Point"}
}