{
  "type": "Feature",
  "properties": {
    "iso:country":"US",
    "sg:address":"1700 Rannoch Trce",
    "sg:city":"Fort Smith",
    "sg:classifiers":[
        {
            "category":"Manufacturing",
            "subcategory":"Motor Vehicles & Parts",
            "type":"Manufacturing & Wholesale Goods"
        }
    ],
    "sg:phone":"+1 479 646 1882",
    "sg:postcode":"72908",
    "sg:province":"AR",
    "sg:tags":[
        "mfg",
        "trimming"
    ],
    "wof:name":"Bows By Buzz",
    "wof:placetype":"venue"
},
  "geometry": {"coordinates":[-94.41855,35.286726],"type":"Point"}
}