{
  "type": "Feature",
  "properties": {
    "iso:country":"US",
    "sg:address":"1112 Garrison Ave",
    "sg:city":"Fort Smith",
    "sg:classifiers":[
        {
            "category":"Shopping",
            "subcategory":"Musical Instruments",
            "type":"Retail Goods"
        }
    ],
    "sg:phone":"+1 479 783 1131",
    "sg:postcode":"72901",
    "sg:province":"AR",
    "sg:website":"www.siglermusic.com",
    "wof:name":"Sigler Music Ctr",
    "wof:placetype":"venue"
},
  "geometry": {"coordinates":[-94.41994,35.38361],"type":"Point"}
}