{
  "type": "Feature",
  "properties": {
    "iso:country":"US",
    "sg:address":"32 Southshore Ln",
    "sg:city":"Conway",
    "sg:classifiers":[
        {
            "category":"Restaurant",
            "type":"Food & Drink"
        }
    ],
    "sg:phone":"+1 501 450 3954",
    "sg:postcode":"72032",
    "sg:province":"AR",
    "sg:tags":[
        "eating"
    ],
    "wof:name":"Smokehouse Bar B Que LLC",
    "wof:placetype":"venue"
},
  "geometry": {"coordinates":[-92.438461,35.130077],"type":"Point"}
}