{
  "type": "Feature",
  "properties": {
    "addr:full":"3440 I- 55 Marion AR 72364",
    "addr:housenumber":"3440;55",
    "addr:postcode":"72364",
    "addr:street":"I",
    "iso:country":"US",
    "sg:address":"3440 I- 55",
    "sg:city":"Marion",
    "sg:classifiers":[
        {
            "category":"Food & Beverages",
            "subcategory":"Groceries & Convenience Stores",
            "type":"Retail Goods"
        }
    ],
    "sg:phone":"+1 870 739 2857",
    "sg:postcode":"72364",
    "sg:province":"AR",
    "wof:name":"Flash Markets Inc",
    "wof:placetype":"venue"
},
  "geometry": {"coordinates":[-90.207511,35.213295],"type":"Point"}
}