{
  "type": "Feature",
  "properties": {
    "iso:country":"US",
    "sg:address":"506 Little Creek Cut Off Rd Cut Off",
    "sg:city":"Sheridan",
    "sg:classifiers":[
        {
            "category":"Restaurant",
            "type":"Food & Drink"
        }
    ],
    "sg:phone":"+1 870 942 7827",
    "sg:postcode":"72150",
    "sg:province":"AR",
    "sg:tags":[
        "style",
        "family"
    ],
    "wof:name":"C M J Restaurants Of Ar Inc",
    "wof:placetype":"venue"
},
  "geometry": {"coordinates":[-92.39538899999999,34.321089],"type":"Point"}
}