{
  "type": "Feature",
  "properties": {
    "addr:full":"357 S Main St Monticello AR 71655",
    "addr:housenumber":"357",
    "addr:postcode":"71655",
    "addr:street":"S Main St",
    "iso:country":"US",
    "sg:address":"357 S Main St",
    "sg:city":"Monticello",
    "sg:classifiers":[
        {
            "category":"Professional",
            "subcategory":"Computer Services",
            "type":"Services"
        }
    ],
    "sg:phone":"+1 870 367 2267",
    "sg:postcode":"71655",
    "sg:province":"AR",
    "sg:tags":[
        "repair"
    ],
    "wof:name":"Monticello Computer Svc",
    "wof:placetype":"venue"
},
  "geometry": {"coordinates":[-91.791501,33.624392],"type":"Point"}
}