{
  "type": "Feature",
  "properties": {
    "addr:full":"426 Sturgis Rd Conway AR 72034",
    "addr:housenumber":"426",
    "addr:postcode":"72034",
    "addr:street":"Sturgis Rd",
    "iso:country":"US",
    "sg:address":"426 Sturgis Rd",
    "sg:city":"Conway",
    "sg:classifiers":[
        {
            "category":"Social Services",
            "subcategory":"Child Care",
            "type":"Services"
        }
    ],
    "sg:phone":"+1 501 470 3563",
    "sg:postcode":"72034",
    "sg:province":"AR",
    "sg:tags":[
        "day"
    ],
    "wof:name":"Mrs Jeanies At Home Day Care",
    "wof:placetype":"venue"
},
  "geometry": {"coordinates":[-92.41833800000001,34.996988],"type":"Point"}
}