{
  "type": "Feature",
  "properties": {
    "iso:country":"US",
    "sg:address":"8200 Flint Ridge Rd",
    "sg:city":"Little Rock",
    "sg:classifiers":[
        {
            "category":"Organizations",
            "subcategory":"Religious Organization",
            "type":"Services"
        }
    ],
    "sg:phone":"+1 501 455 3995",
    "sg:postcode":"72210",
    "sg:province":"AR",
    "wof:name":"Oak Park Baptist Church",
    "wof:placetype":"venue"
},
  "geometry": {"coordinates":[-92.409115,34.677932],"type":"Point"}
}