{
  "type": "Feature",
  "properties": {
    "iso:country":"US",
    "sg:address":"905 NW 10th St",
    "sg:city":"Bentonville",
    "sg:classifiers":[
        {
            "category":"Freight",
            "type":"Transportation"
        }
    ],
    "sg:phone":"+1 479 271 8739",
    "sg:postcode":"72712",
    "sg:province":"AR",
    "sg:tags":[
        "operator",
        "trucking"
    ],
    "wof:name":"David L Dalton",
    "wof:placetype":"venue"
},
  "geometry": {"coordinates":[-94.225835,36.383011],"type":"Point"}
}