{
  "type": "Feature",
  "properties": {
    "addr:full":"1201 S 8th Ave Paragould AR 72450",
    "addr:housenumber":"1201",
    "addr:postcode":"72450",
    "addr:street":"S 8Th Ave",
    "iso:country":"US",
    "sg:address":"1201 S 8th Ave",
    "sg:city":"Paragould",
    "sg:classifiers":[
        {
            "category":"Retail",
            "subcategory":"Animal Services",
            "type":"Services"
        }
    ],
    "sg:phone":"+1 870 236 2489",
    "sg:postcode":"72450",
    "sg:province":"AR",
    "sg:tags":[
        "horse",
        "training"
    ],
    "wof:name":"Dowdy Stables",
    "wof:placetype":"venue"
},
  "geometry": {"coordinates":[-90.47658199999999,36.043167],"type":"Point"}
}