{
  "type": "Feature",
  "properties": {
    "iso:country":"US",
    "sg:address":"601 W Walnut St",
    "sg:city":"Rogers",
    "sg:classifiers":[
        {
            "category":"Transit Center",
            "subcategory":"Freight",
            "type":"Transportation"
        },
        {
            "category":"Freight",
            "type":"Transportation"
        }
    ],
    "sg:phone":"+1 479 936 2185",
    "sg:postcode":"72756",
    "sg:province":"AR",
    "sg:tags":[
        "trucking-motor",
        "broker",
        "trucking"
    ],
    "wof:name":"California Freight Sales",
    "wof:placetype":"venue"
},
  "geometry": {"coordinates":[-94.12252,36.333431],"type":"Point"}
}