{
  "type": "Feature",
  "properties": {
    "iso:country":"US",
    "sg:address":"704 McCauley St",
    "sg:city":"Warren",
    "sg:classifiers":[
        {
            "category":"Organizations",
            "subcategory":"Religious Organization",
            "type":"Services"
        }
    ],
    "sg:phone":"+1 870 226 7176",
    "sg:postcode":"71671",
    "sg:province":"AR",
    "sg:tags":[
        "church"
    ],
    "wof:name":"Living Testament COGIC",
    "wof:placetype":"venue"
},
  "geometry": {"coordinates":[-92.07451500000001,33.605838],"type":"Point"}
}