{
  "type": "Feature",
  "properties": {
    "iso:country":"US",
    "sg:address":"2210 S Walton Blvd",
    "sg:city":"Bentonville",
    "sg:classifiers":[
        {
            "category":"Food & Beverages",
            "subcategory":"Bakery",
            "type":"Retail Goods"
        }
    ],
    "sg:phone":"+1 479 254 0731",
    "sg:postcode":"72712",
    "sg:province":"AR",
    "wof:name":"Gonzales Panaderia",
    "wof:placetype":"venue"
},
  "geometry": {"coordinates":[-94.210635,36.347948],"type":"Point"}
}