{
  "type": "Feature",
  "properties": {
    "iso:country":"US",
    "sg:address":"1550 83rd St NW",
    "sg:city":"Grove",
    "sg:classifiers":[
        {
            "category":"Recreation",
            "type":"Entertainment"
        },
        {
            "category":"Retail",
            "subcategory":"Storage",
            "type":"Services"
        },
        {
            "category":"Recreation",
            "subcategory":"Campground",
            "type":"Entertainment"
        }
    ],
    "sg:phone":"+1 800 880 8884",
    "sg:postcode":"74344",
    "sg:province":"OK",
    "sg:tags":[
        "camps-recreational",
        "park",
        "household",
        "recreational",
        "commercial",
        "campers-storage",
        "vehicle",
        "boat"
    ],
    "sg:website":"http://www.cedaroaksrv.com",
    "wof:name":"Cedar Oaks RV Resort & Mini Storage",
    "wof:placetype":"venue"
},
  "geometry": {"coordinates":[-94.813625,36.620073],"type":"Point"}
}