{
  "type": "Feature",
  "properties": {
    "addr:full":"232 Glenview Ln N Little Rock AR 72117",
    "addr:housenumber":"232",
    "addr:postcode":"72117",
    "addr:street":"Glenview Ln N",
    "iso:country":"US",
    "sg:address":"232 Glenview Ln",
    "sg:city":"N Little Rock",
    "sg:classifiers":[
        {
            "category":"Freight",
            "type":"Transportation"
        }
    ],
    "sg:phone":"+1 501 945 4574",
    "sg:postcode":"72117",
    "sg:province":"AR",
    "sg:tags":[
        "dry",
        "bulk",
        "trucking"
    ],
    "sg:website":"www.millert.com",
    "wof:name":"Miller Transporters Inc",
    "wof:placetype":"venue"
},
  "geometry": {"coordinates":[-92.210587,34.763616],"type":"Point"}
}