{
  "type": "Feature",
  "properties": {
    "addr:full":"2315 Alma Hwy Van Buren AR 72956",
    "addr:housenumber":"2315",
    "addr:postcode":"72956",
    "addr:street":"Alma Hwy",
    "iso:country":"US",
    "sg:address":"2315 Alma Hwy",
    "sg:city":"Van Buren",
    "sg:classifiers":[
        {
            "category":"Professional",
            "subcategory":"Testing Lab",
            "type":"Services"
        }
    ],
    "sg:phone":"+1 479 474 2354",
    "sg:postcode":"72956",
    "sg:province":"AR",
    "sg:tags":[
        "laboratory"
    ],
    "sg:website":"www.standardlabs.com",
    "wof:name":"Standard Laboratories Inc",
    "wof:placetype":"venue"
},
  "geometry": {"coordinates":[-94.337102,35.4367],"type":"Point"}
}