{
  "type": "Feature",
  "properties": {
    "iso:country":"US",
    "sg:address":"221 W 2nd St",
    "sg:city":"Little Rock",
    "sg:classifiers":[
        {
            "category":"Travel",
            "subcategory":"Travel Agent",
            "type":"Entertainment"
        }
    ],
    "sg:phone":"+1 501 868 7287",
    "sg:postcode":"72201",
    "sg:province":"AR",
    "sg:tags":[
        "tours",
        "promoter"
    ],
    "sg:website":"www.littlerocktours.com",
    "wof:name":"Little Rock Tours",
    "wof:placetype":"venue"
},
  "geometry": {"coordinates":[-92.272123,34.747255],"type":"Point"}
}