{
  "type": "Feature",
  "properties": {
    "iso:country":"US",
    "sg:address":"1600 Newport Rd",
    "sg:city":"Batesville",
    "sg:classifiers":[
        {
            "category":"Professional",
            "subcategory":"Business Services",
            "type":"Services"
        }
    ],
    "sg:phone":"+1 870 251 0300",
    "sg:postcode":"72501",
    "sg:province":"AR",
    "wof:name":"Jett Enterprises",
    "wof:placetype":"venue"
},
  "geometry": {"coordinates":[-91.559848,35.690466],"type":"Point"}
}