{
  "type": "Feature",
  "properties": {
    "iso:country":"US",
    "sg:address":"501 E Centerton Blvd",
    "sg:city":"Centerton",
    "sg:classifiers":[
        {
            "category":"Real Estate",
            "subcategory":"Real Estate Services",
            "type":"Services"
        }
    ],
    "sg:phone":"+1 877 829 7094",
    "sg:postcode":"72719",
    "sg:province":"AR",
    "sg:tags":[
        "apartment",
        "rental",
        "finder"
    ],
    "wof:name":"Stoneleigh Centerton",
    "wof:placetype":"venue"
},
  "geometry": {"coordinates":[-94.276663,36.358322],"type":"Point"}
}