{
  "type": "Feature",
  "properties": {
    "iso:country":"US",
    "sg:address":"2217 S Adams Ave",
    "sg:city":"Camden",
    "sg:classifiers":[
        {
            "category":"Home & Garden",
            "subcategory":"Furniture",
            "type":"Retail Goods"
        }
    ],
    "sg:phone":"+1 870 231 5511",
    "sg:postcode":"71701",
    "sg:province":"AR",
    "wof:name":"Ivan Smith Furniture 23",
    "wof:placetype":"venue"
},
  "geometry": {"coordinates":[-92.825175,33.542487],"type":"Point"}
}