{
  "type": "Feature",
  "properties": {
    "iso:country":"US",
    "sg:address":"150 W Main St",
    "sg:city":"Clarksville",
    "sg:classifiers":[
        {
            "category":"Shopping",
            "subcategory":"Books",
            "type":"Retail Goods"
        }
    ],
    "sg:phone":"+1 479 754 2295",
    "sg:postcode":"72830",
    "sg:province":"AR",
    "wof:name":"Christian Book Store",
    "wof:placetype":"venue"
},
  "geometry": {"coordinates":[-93.462548,35.471255],"type":"Point"}
}