{
  "type": "Feature",
  "properties": {
    "iso:country":"US",
    "sg:address":"1226 Ferguson Dr",
    "sg:city":"Benton",
    "sg:classifiers":[
        {
            "category":"Health Services",
            "subcategory":"Doctor",
            "type":"Services"
        },
        {
            "category":"Health Services",
            "subcategory":"Dentist",
            "type":"Services"
        }
    ],
    "sg:phone":"+1 501 778 6510",
    "sg:postcode":"72015",
    "sg:province":"AR",
    "sg:tags":[
        "dentists-oral",
        "physician",
        "maxillofacial",
        "surgeons",
        "dentists-periodontists",
        "surgery",
        "oral"
    ],
    "wof:name":"Peder Jensen",
    "wof:placetype":"venue"
},
  "geometry": {"coordinates":[-92.580043,34.574134],"type":"Point"}
}