{
  "type": "Feature",
  "properties": {
    "addr:full":"107 W Arch Ave Searcy AR 72143",
    "addr:housenumber":"107",
    "addr:postcode":"72143",
    "addr:street":"W Arch Ave",
    "iso:country":"US",
    "sg:address":"107 W Arch Ave",
    "sg:city":"Searcy",
    "sg:classifiers":[
        {
            "category":"Retail",
            "subcategory":"Portrait Studio",
            "type":"Services"
        }
    ],
    "sg:phone":"+1 501 268 3298",
    "sg:postcode":"72143",
    "sg:province":"AR",
    "sg:tags":[
        "photographer",
        "photography",
        "commercial",
        "photo"
    ],
    "wof:name":"Baker John Photography",
    "wof:placetype":"venue"
},
  "geometry": {"coordinates":[-91.73767100000001,35.250057],"type":"Point"}
}