{
  "type": "Feature",
  "properties": {
    "iso:country":"US",
    "sg:address":"325 W Van Buren",
    "sg:city":"Eureka Springs",
    "sg:classifiers":[
        {
            "category":"Travel",
            "subcategory":"Hotels & Motels",
            "type":"Entertainment"
        }
    ],
    "sg:phone":"+1 479 253 8128",
    "sg:postcode":"72632",
    "sg:province":"AR",
    "wof:name":"Rustic Manor Motel",
    "wof:placetype":"venue"
},
  "geometry": {"coordinates":[-93.770016,36.421148],"type":"Point"}
}