{
  "type": "Feature",
  "properties": {
    "iso:country":"US",
    "sg:address":"201 N 37th St",
    "sg:city":"Rogers",
    "sg:classifiers":[
        {
            "category":"Arts & Performance",
            "subcategory":"Arts Center",
            "type":"Entertainment"
        },
        {
            "category":"Personal",
            "type":"Services"
        }
    ],
    "sg:phone":"+1 479 246 9941",
    "sg:postcode":"72756",
    "sg:province":"AR",
    "sg:tags":[
        "planning",
        "party",
        "performing",
        "event"
    ],
    "sg:website":"www.regionalrec.com",
    "wof:name":"Regional Rec Dance Gymnastics & Cheer",
    "wof:placetype":"venue"
},
  "geometry": {"coordinates":[-94.169801,36.336223],"type":"Point"}
}