{
  "type": "Feature",
  "properties": {
    "iso:country":"US",
    "sg:address":"408 State Hwy 149",
    "sg:city":"Earle",
    "sg:classifiers":[
        {
            "category":"Autos & Motor Vehicles",
            "subcategory":"Fuel & Gas Station",
            "type":"Retail Goods"
        }
    ],
    "sg:phone":"+1 870 657 2105",
    "sg:postcode":"72331",
    "sg:province":"AR",
    "sg:tags":[
        "plaza",
        "truck",
        "stops"
    ],
    "wof:name":"Truckstops Of America",
    "wof:placetype":"venue"
},
  "geometry": {"coordinates":[-90.46109,35.269199],"type":"Point"}
}