{
  "type": "Feature",
  "properties": {
    "iso:country":"US",
    "sg:address":"606 N Betty Jo Dr",
    "sg:city":"Fayetteville",
    "sg:classifiers":[
        {
            "category":"Real Estate",
            "subcategory":"Real Estate Agent",
            "type":"Services"
        }
    ],
    "sg:phone":"+1 479 571 3839",
    "sg:postcode":"72701",
    "sg:province":"AR",
    "wof:name":"B & R Property",
    "wof:placetype":"venue"
},
  "geometry": {"coordinates":[-94.206228,36.072512],"type":"Point"}
}