{
  "type": "Feature",
  "properties": {
    "iso:country":"US",
    "sg:address":"224 Rebecca Ln",
    "sg:city":"Walnut Ridge",
    "sg:classifiers":[
        {
            "category":"Professional",
            "subcategory":"Business Services",
            "type":"Services"
        }
    ],
    "sg:phone":"+1 870 886 3351",
    "sg:postcode":"72476",
    "sg:province":"AR",
    "wof:name":"JW Technology Inc",
    "wof:placetype":"venue"
},
  "geometry": {"coordinates":[-90.956956,36.080263],"type":"Point"}
}