{
  "type": "Feature",
  "properties": {
    "iso:country":"US",
    "sg:address":"4801 Somers Ave",
    "sg:city":"N Little Rock",
    "sg:classifiers":[
        {
            "category":"Organizations",
            "subcategory":"Religious Organization",
            "type":"Services"
        }
    ],
    "sg:phone":"+1 501 758 5256",
    "sg:postcode":"72116",
    "sg:province":"AR",
    "sg:tags":[
        "church"
    ],
    "wof:name":"Church Of Christ",
    "wof:placetype":"venue"
},
  "geometry": {"coordinates":[-92.21884,34.801736],"type":"Point"}
}