{
  "type": "Feature",
  "properties": {
    "addr:full":"601 Scott St Little Rock AR 72201",
    "addr:housenumber":"601",
    "addr:postcode":"72201",
    "addr:street":"Scott St",
    "iso:country":"US",
    "sg:address":"601 Scott St",
    "sg:city":"Little Rock",
    "sg:classifiers":[
        {
            "category":"Wholesale",
            "subcategory":"Groceries",
            "type":"Manufacturing & Wholesale Goods"
        }
    ],
    "sg:phone":"+1 501 372 2321",
    "sg:postcode":"72201",
    "sg:province":"AR",
    "sg:tags":[
        "confectionery",
        "candy"
    ],
    "sg:website":"www.mitchco1.com",
    "wof:name":"Mitchell & Co",
    "wof:placetype":"venue"
},
  "geometry": {"coordinates":[-92.27026600000001,34.742014],"type":"Point"}
}