{
  "type": "Feature",
  "properties": {
    "iso:country":"US",
    "sg:address":"100 W Boone St",
    "sg:city":"Redfield",
    "sg:classifiers":[
        {
            "category":"Science Facility",
            "type":"Public Place"
        }
    ],
    "sg:phone":"+1 734 355 8044",
    "sg:postcode":"72132",
    "sg:province":"AR",
    "sg:tags":[
        "development",
        "laboratories-research"
    ],
    "wof:name":"Consensus Biolabs",
    "wof:placetype":"venue"
},
  "geometry": {"coordinates":[-92.181229,34.444279],"type":"Point"}
}