{
  "type": "Feature",
  "properties": {
    "iso:country":"US",
    "sg:address":"1407 Winchester Dr",
    "sg:city":"Jonesboro",
    "sg:classifiers":[
        {
            "category":"Building & Trades",
            "subcategory":"Construction",
            "type":"Services"
        }
    ],
    "sg:phone":"+1 870 930 0670",
    "sg:postcode":"72401",
    "sg:province":"AR",
    "sg:tags":[
        "concrete",
        "contractor"
    ],
    "wof:name":"Bradley Construction",
    "wof:placetype":"venue"
},
  "geometry": {"coordinates":[-90.721165,35.864906],"type":"Point"}
}