{
  "type": "Feature",
  "properties": {
    "addr:full":"502 S 4th Ave Paragould AR 72450",
    "addr:housenumber":"502",
    "addr:postcode":"72450",
    "addr:street":"S 4Th Ave",
    "iso:country":"US",
    "sg:address":"502 S 4th Ave",
    "sg:city":"Paragould",
    "sg:classifiers":[
        {
            "category":"Taxi",
            "type":"Transportation"
        }
    ],
    "sg:phone":"+1 870 236 1153",
    "sg:postcode":"72450",
    "sg:province":"AR",
    "sg:tags":[
        "taxicab"
    ],
    "wof:name":"Number One Paragould Cab Co",
    "wof:placetype":"venue"
},
  "geometry": {"coordinates":[-90.48265600000001,36.052146],"type":"Point"}
}