{
  "type": "Feature",
  "properties": {
    "addr:full":"4424 Frazier Pike Little Rock AR 72206",
    "addr:housenumber":"4424",
    "addr:postcode":"72206",
    "addr:street":"Frazier Pike",
    "iso:country":"US",
    "sg:address":"4424 Frazier Pike",
    "sg:city":"Little Rock",
    "sg:classifiers":[
        {
            "category":"Retail",
            "subcategory":"Self-service Laundry",
            "type":"Services"
        }
    ],
    "sg:phone":"+1 501 490 0101",
    "sg:postcode":"72206",
    "sg:province":"AR",
    "wof:name":"Fantastic Wash Coin Laundry",
    "wof:placetype":"venue"
},
  "geometry": {"coordinates":[-92.223439,34.707754],"type":"Point"}
}