{
  "type": "Feature",
  "properties": {
    "addr:full":"27 Paxos St Eureka Springs AR 72632",
    "addr:housenumber":"27",
    "addr:postcode":"72632",
    "addr:street":"Paxos St",
    "iso:country":"US",
    "sg:address":"27 Paxos St",
    "sg:city":"Eureka Springs",
    "sg:classifiers":[
        {
            "category":"Travel",
            "subcategory":"Hotels & Motels",
            "type":"Entertainment"
        }
    ],
    "sg:phone":"+1 479 253 6555",
    "sg:postcode":"72632",
    "sg:province":"AR",
    "sg:tags":[
        "breakfast",
        "accommodation",
        "bed"
    ],
    "wof:name":"Edgewood Manor Deluxe Lodging",
    "wof:placetype":"venue"
},
  "geometry": {"coordinates":[-93.745873,36.400309],"type":"Point"}
}