{
  "type": "Feature",
  "properties": {
    "iso:country":"US",
    "sg:address":"2427 E Sweetbriar Dr",
    "sg:city":"Fayetteville",
    "sg:classifiers":[
        {
            "category":"Shopping",
            "subcategory":"Books",
            "type":"Retail Goods"
        }
    ],
    "sg:phone":"+1 479 443 4201",
    "sg:postcode":"72703",
    "sg:province":"AR",
    "sg:tags":[
        "educational",
        "material"
    ],
    "wof:name":"Misall",
    "wof:placetype":"venue"
},
  "geometry": {"coordinates":[-94.127292,36.113071],"type":"Point"}
}