{
  "type": "Feature",
  "properties": {
    "iso:country":"US",
    "sg:address":"1014 Malcolm Ave",
    "sg:city":"Newport",
    "sg:classifiers":[
        {
            "category":"Autos & Motor Vehicles",
            "subcategory":"Auto Supplies",
            "type":"Retail Goods"
        }
    ],
    "sg:phone":"+1 870 217 0595",
    "sg:postcode":"72112",
    "sg:province":"AR",
    "wof:name":"OReilly Automotive Inc",
    "wof:placetype":"venue"
},
  "geometry": {"coordinates":[-91.267658,35.606195],"type":"Point"}
}