{
  "type": "Feature",
  "properties": {
    "iso:country":"US",
    "sg:address":"5820 E Huntsville Rd",
    "sg:city":"Fayetteville",
    "sg:classifiers":[
        {
            "category":"Shopping",
            "subcategory":"Bicycles & Sporting Goods",
            "type":"Retail Goods"
        }
    ],
    "sg:phone":"+1 479 443 2038",
    "sg:postcode":"72701",
    "sg:province":"AR",
    "wof:name":"Three River Gun Shop",
    "wof:placetype":"venue"
},
  "geometry": {"coordinates":[-94.07878,36.046534],"type":"Point"}
}