{
  "type": "Feature",
  "properties": {
    "iso:country":"US",
    "sg:address":"5231 Watkins Ave",
    "sg:city":"Springdale",
    "sg:classifiers":[
        {
            "category":"Building & Trades",
            "subcategory":"Landscaping Services",
            "type":"Services"
        }
    ],
    "sg:phone":"+1 479 502 2192",
    "sg:postcode":"72762",
    "sg:province":"AR",
    "sg:tags":[
        "lawn",
        "maintenance"
    ],
    "wof:name":"Nichols Reliable Lawn Care",
    "wof:placetype":"venue"
},
  "geometry": {"coordinates":[-94.187411,36.160948],"type":"Point"}
}