{
  "type": "Feature",
  "properties": {
    "iso:country":"US",
    "sg:address":"12009 Geyer Springs Rd",
    "sg:city":"Little Rock",
    "sg:classifiers":[
        {
            "category":"Manufacturing",
            "subcategory":"Apparel",
            "type":"Manufacturing & Wholesale Goods"
        }
    ],
    "sg:phone":"+1 501 568 2300",
    "sg:postcode":"72206",
    "sg:province":"AR",
    "wof:name":"Lasting Impressions EMB Co",
    "wof:placetype":"venue"
},
  "geometry": {"coordinates":[-92.34567300000001,34.6427],"type":"Point"}
}