{
  "type": "Feature",
  "properties": {
    "iso:country":"US",
    "sg:address":"1810 E Walnut St",
    "sg:city":"Paris",
    "sg:classifiers":[
        {
            "category":"Real Estate",
            "subcategory":"Developer",
            "type":"Services"
        }
    ],
    "sg:phone":"+1 479 963 8419",
    "sg:postcode":"72855",
    "sg:province":"AR",
    "sg:tags":[
        "cemetery"
    ],
    "wof:name":"Oakwood Cemetery",
    "wof:placetype":"venue"
},
  "geometry": {"coordinates":[-93.706536,35.292014],"type":"Point"}
}