{
  "type": "Feature",
  "properties": {
    "iso:country":"US",
    "sg:address":"19999 Y City Rd",
    "sg:city":"Gentry",
    "sg:classifiers":[
        {
            "category":"Farming",
            "subcategory":"Livestock Farm",
            "type":"Manufacturing & Wholesale Goods"
        }
    ],
    "sg:phone":"+1 479 736 2504",
    "sg:postcode":"72734",
    "sg:province":"AR",
    "sg:tags":[
        "animal",
        "general"
    ],
    "wof:name":"Nsf Farm",
    "wof:placetype":"venue"
},
  "geometry": {"coordinates":[-94.473218,36.303402],"type":"Point"}
}