{
  "type": "Feature",
  "properties": {
    "iso:country":"US",
    "sg:address":"302 S 20th St",
    "sg:city":"Rogers",
    "sg:classifiers":[
        {
            "category":"Professional",
            "subcategory":"Computer Services",
            "type":"Services"
        },
        {
            "category":"Shopping",
            "subcategory":"Computers & Home Electronics",
            "type":"Retail Goods"
        }
    ],
    "sg:phone":"+1 479 925 7799",
    "sg:postcode":"72758",
    "sg:province":"AR",
    "sg:tags":[
        "development",
        "application",
        "software"
    ],
    "wof:name":"Decisions Made Easy Inc",
    "wof:placetype":"venue"
},
  "geometry": {"coordinates":[-94.146222,36.33217],"type":"Point"}
}