{
  "type": "Feature",
  "properties": {
    "iso:country":"US",
    "sg:address":"1309 Robinhood Rd",
    "sg:city":"Bentonville",
    "sg:classifiers":[
        {
            "category":"Retail",
            "subcategory":"Auto Repair",
            "type":"Services"
        }
    ],
    "sg:phone":"+1 479 273 2227",
    "sg:postcode":"72712",
    "sg:province":"AR",
    "sg:tags":[
        "general"
    ],
    "wof:name":"Prince Automotive Service",
    "wof:placetype":"venue"
},
  "geometry": {"coordinates":[-94.228156,36.383391],"type":"Point"}
}