{
  "type": "Feature",
  "properties": {
    "addr:full":"12182 Walnut Hill Rd Garfield AR 72732",
    "addr:housenumber":"12182",
    "addr:postcode":"72732",
    "addr:street":"Walnut Hill Rd",
    "iso:country":"US",
    "sg:address":"12182 Walnut Hill Rd",
    "sg:city":"Garfield",
    "sg:classifiers":[
        {
            "category":"Home & Garden",
            "subcategory":"Furniture",
            "type":"Retail Goods"
        },
        {
            "category":"Wholesale",
            "subcategory":"Home Furnishings",
            "type":"Manufacturing & Wholesale Goods"
        }
    ],
    "sg:phone":"+1 479 359 3347",
    "sg:postcode":"72732",
    "sg:province":"AR",
    "sg:tags":[
        "equipment-wholesale",
        "kitchen",
        "equipment-household",
        "manufacturer",
        "cabinet"
    ],
    "wof:name":"Pro Line Cabinets Inc",
    "wof:placetype":"venue"
},
  "geometry": {"coordinates":[-93.995756,36.39782],"type":"Point"}
}