{
  "type": "Feature",
  "properties": {
    "iso:country":"US",
    "sg:address":"7 Mabelvale Dr",
    "sg:city":"Little Rock",
    "sg:classifiers":[
        {
            "category":"Building & Trades",
            "subcategory":"Construction",
            "type":"Services"
        }
    ],
    "sg:phone":"+1 501 562 3176",
    "sg:postcode":"72209",
    "sg:province":"AR",
    "sg:tags":[
        "roofing",
        "contractor"
    ],
    "wof:name":"Mid-Ark Roofing Inc",
    "wof:placetype":"venue"
},
  "geometry": {"coordinates":[-92.377617,34.6744],"type":"Point"}
}