{
  "type": "Feature",
  "properties": {
    "addr:full":"216 White Blossom Cir Bryant AR 72022",
    "addr:housenumber":"216",
    "addr:postcode":"72022",
    "addr:street":"White Blossom Cir",
    "iso:country":"US",
    "sg:address":"216 White Blossom Cir",
    "sg:city":"Bryant",
    "sg:classifiers":[
        {
            "category":"Utilities",
            "subcategory":"Telephone",
            "type":"Services"
        }
    ],
    "sg:phone":"+1 501 847 4782",
    "sg:postcode":"72022",
    "sg:province":"AR",
    "sg:tags":[
        "web",
        "design",
        "site",
        "communication"
    ],
    "wof:name":"Scaife Technology Services",
    "wof:placetype":"venue"
},
  "geometry": {"coordinates":[-92.489394,34.604636],"type":"Point"}
}