{
  "type": "Feature",
  "properties": {
    "iso:country":"US",
    "sg:address":"1714 Dill St",
    "sg:city":"Newport",
    "sg:classifiers":[
        {
            "category":"Professional",
            "subcategory":"Business Services",
            "type":"Services"
        }
    ],
    "sg:phone":"+1 870 523 5503",
    "sg:postcode":"72112",
    "sg:province":"AR",
    "sg:tags":[
        "not",
        "classified",
        "elsewhere"
    ],
    "wof:name":"Charles D Turner",
    "wof:placetype":"venue"
},
  "geometry": {"coordinates":[-91.258742,35.604686],"type":"Point"}
}