{
  "type": "Feature",
  "properties": {
    "iso:country":"US",
    "sg:address":"115 Lecta Ave",
    "sg:city":"Fort Smith",
    "sg:classifiers":[
        {
            "category":"Shopping",
            "subcategory":"Gifts & Souvenirs",
            "type":"Retail Goods"
        }
    ],
    "sg:phone":"+1 479 783 8022",
    "sg:postcode":"72901",
    "sg:province":"AR",
    "sg:tags":[
        "antique"
    ],
    "wof:name":"Now & Then Shoppe Inc",
    "wof:placetype":"venue"
},
  "geometry": {"coordinates":[-94.401097,35.376558],"type":"Point"}
}