{
  "type": "Feature",
  "properties": {
    "iso:country":"US",
    "sg:address":"1901 S Caraway Rd",
    "sg:city":"Jonesboro",
    "sg:classifiers":[
        {
            "category":"Shopping",
            "subcategory":"Computers & Home Electronics",
            "type":"Retail Goods"
        }
    ],
    "sg:phone":"+1 870 972 6280",
    "sg:postcode":"72404",
    "sg:province":"AR",
    "sg:tags":[
        "equipment",
        "electronic",
        "supply"
    ],
    "wof:name":"Radio Shack",
    "wof:placetype":"venue"
},
  "geometry": {"coordinates":[-90.67789399999999,35.822527],"type":"Point"}
}