{
  "type": "Feature",
  "properties": {
    "addr:full":"1717 E Susan Dr Fayetteville AR 72703",
    "addr:housenumber":"1717",
    "addr:postcode":"72703",
    "addr:street":"E Susan Dr",
    "iso:country":"US",
    "sg:address":"1717 E Susan Dr",
    "sg:city":"Fayetteville",
    "sg:classifiers":[
        {
            "category":"Professional",
            "subcategory":"Advertising",
            "type":"Services"
        }
    ],
    "sg:phone":"+1 479 587 8265",
    "sg:postcode":"72703",
    "sg:province":"AR",
    "sg:tags":[
        "mail",
        "direct"
    ],
    "wof:name":"Val-Pak",
    "wof:placetype":"venue"
},
  "geometry": {"coordinates":[-94.135775,36.092347],"type":"Point"}
}