{
  "type": "Feature",
  "properties": {
    "iso:country":"US",
    "sg:address":"421 Greening St NW",
    "sg:city":"Camden",
    "sg:classifiers":[
        {
            "category":"Professional",
            "subcategory":"Business Services",
            "type":"Services"
        }
    ],
    "sg:phone":"+1 870 836 7532",
    "sg:postcode":"71701",
    "sg:province":"AR",
    "sg:tags":[
        "painter",
        "sign"
    ],
    "wof:name":"Art & Sign",
    "wof:placetype":"venue"
},
  "geometry": {"coordinates":[-92.835053,33.586171],"type":"Point"}
}