{
  "type": "Feature",
  "properties": {
    "iso:country":"US",
    "sg:address":"612 E 22nd St",
    "sg:city":"Stuttgart",
    "sg:classifiers":[
        {
            "category":"Building & Trades",
            "subcategory":"Construction",
            "type":"Services"
        }
    ],
    "sg:phone":"+1 870 673 6112",
    "sg:postcode":"72160",
    "sg:province":"AR",
    "sg:tags":[
        "clearing",
        "land",
        "leveling"
    ],
    "wof:name":"Hoskyn Enterprises Inc",
    "wof:placetype":"venue"
},
  "geometry": {"coordinates":[-91.546009,34.47917],"type":"Point"}
}