{
  "type": "Feature",
  "properties": {
    "iso:country":"US",
    "sg:address":"3701 Alcoa Rd",
    "sg:city":"Benton",
    "sg:classifiers":[
        {
            "category":"Building & Trades",
            "subcategory":"Construction",
            "type":"Services"
        }
    ],
    "sg:phone":"+1 501 315 0358",
    "sg:postcode":"72015",
    "sg:province":"AR",
    "sg:tags":[
        "excavating",
        "contractor"
    ],
    "wof:name":"Sam Johnson Construction Inc",
    "wof:placetype":"venue"
},
  "geometry": {"coordinates":[-92.53522,34.58199],"type":"Point"}
}