{
  "type": "Feature",
  "properties": {
    "iso:country":"US",
    "sg:address":"435 W Washington St",
    "sg:city":"Camden",
    "sg:classifiers":[
        {
            "category":"Government",
            "subcategory":"Office",
            "type":"Public Place"
        }
    ],
    "sg:phone":"+1 800 772 1213",
    "sg:postcode":"71701",
    "sg:province":"AR",
    "sg:tags":[
        "program",
        "administrative"
    ],
    "wof:name":"Social Security Administration",
    "wof:placetype":"venue"
},
  "geometry": {"coordinates":[-92.834969,33.584749],"type":"Point"}
}