{
  "type": "Feature",
  "properties": {
    "addr:full":"7005 S Hazel St Pine Bluff AR 71603",
    "addr:housenumber":"7005",
    "addr:postcode":"71603",
    "addr:street":"S Hazel St",
    "iso:country":"US",
    "sg:address":"7005 S Hazel St",
    "sg:city":"Pine Bluff",
    "sg:classifiers":[
        {
            "category":"Health Services",
            "subcategory":"Doctor",
            "type":"Services"
        }
    ],
    "sg:phone":"+1 870 536 3070",
    "sg:postcode":"71603",
    "sg:province":"AR",
    "sg:tags":[
        "clinic"
    ],
    "wof:name":"Digestive Disease Ctr",
    "wof:placetype":"venue"
},
  "geometry": {"coordinates":[-92.023978,34.15621],"type":"Point"}
}