{
  "type": "Feature",
  "properties": {
    "iso:country":"US",
    "sg:address":"3300 Commonwealth Dr",
    "sg:city":"Bryant",
    "sg:classifiers":[
        {
            "category":"Insurance",
            "subcategory":"Hazard Insurance",
            "type":"Services"
        },
        {
            "category":"Banks & Credit Unions",
            "subcategory":"Bank",
            "type":"Services"
        }
    ],
    "sg:phone":"+1 501 847 4199",
    "sg:postcode":"72022",
    "sg:province":"AR",
    "sg:tags":[
        "commercial",
        "saving",
        "business"
    ],
    "sg:website":"http://statefarm.com",
    "wof:name":"Reginelli Matthew",
    "wof:placetype":"venue"
},
  "geometry": {"coordinates":[-92.499527,34.624611],"type":"Point"}
}