{
  "type": "Feature",
  "properties": {
    "addr:full":"4 E 7th St Mountain Home AR 72653",
    "addr:housenumber":"4",
    "addr:postcode":"72653",
    "addr:street":"E 7Th St",
    "iso:country":"US",
    "sg:address":"4 E 7th St",
    "sg:city":"Mountain Home",
    "sg:classifiers":[
        {
            "category":"Personal",
            "subcategory":"Beauty Salon",
            "type":"Services"
        }
    ],
    "sg:phone":"+1 870 425 7514",
    "sg:postcode":"72653",
    "sg:province":"AR",
    "sg:tags":[
        "shop"
    ],
    "wof:name":"Spa Salon",
    "wof:placetype":"venue"
},
  "geometry": {"coordinates":[-92.385304,36.334645],"type":"Point"}
}