{
  "type": "Feature",
  "properties": {
    "iso:country":"US",
    "sg:address":"225 Barner St",
    "sg:city":"Fordyce",
    "sg:classifiers":[
        {
            "category":"Real Estate",
            "subcategory":"Real Estate Operator",
            "type":"Services"
        }
    ],
    "sg:phone":"+1 870 352 5171",
    "sg:postcode":"71742",
    "sg:province":"AR",
    "sg:tags":[
        "building",
        "apartment"
    ],
    "wof:name":"Higher Heights Apartments",
    "wof:placetype":"venue"
},
  "geometry": {"coordinates":[-92.3994,33.81404],"type":"Point"}
}