{
  "type": "Feature",
  "properties": {
    "addr:full":"17484 Highway 5 Lonsdale AR 72087",
    "addr:housenumber":"17484",
    "addr:postcode":"72087",
    "addr:street":"Highway 5",
    "iso:country":"US",
    "sg:address":"17484 Highway 5",
    "sg:city":"Lonsdale",
    "sg:classifiers":[
        {
            "category":"Government",
            "subcategory":"Fire Station",
            "type":"Public Place"
        },
        {
            "category":"Government",
            "subcategory":"Office",
            "type":"Public Place"
        }
    ],
    "sg:phone":"+1 501 794 1720",
    "sg:postcode":"72087",
    "sg:province":"AR",
    "sg:tags":[
        "department",
        "township",
        "protection",
        "government-city",
        "village"
    ],
    "wof:name":"Crows Station Fire Protection Association",
    "wof:placetype":"venue"
},
  "geometry": {"coordinates":[-92.79243099999999,34.613738],"type":"Point"}
}