{
  "type": "Feature",
  "properties": {
    "iso:country":"US",
    "sg:address":"924 Goblin Dr",
    "sg:city":"Harrison",
    "sg:classifiers":[
        {
            "category":"Health Services",
            "subcategory":"Chiropractor",
            "type":"Services"
        },
        {
            "category":"Health Services",
            "subcategory":"Doctor",
            "type":"Services"
        }
    ],
    "sg:phone":"+1 870 743 3311",
    "sg:postcode":"72601",
    "sg:province":"AR",
    "sg:tags":[
        "clinic"
    ],
    "wof:name":"Coats Chiropractic Clinic P A",
    "wof:placetype":"venue"
},
  "geometry": {"coordinates":[-93.134638,36.247172],"type":"Point"}
}