{
  "type": "Feature",
  "properties": {
    "addr:full":"409 W Cypress St Brinkley AR 72021",
    "addr:housenumber":"409",
    "addr:postcode":"72021",
    "addr:street":"W Cypress St",
    "iso:country":"US",
    "sg:address":"409 W Cypress St",
    "sg:city":"Brinkley",
    "sg:classifiers":[
        {
            "category":"Building & Trades",
            "subcategory":"Construction",
            "type":"Services"
        }
    ],
    "sg:phone":"+1 870 734 1221",
    "sg:postcode":"72021",
    "sg:province":"AR",
    "sg:tags":[
        "excavating",
        "contractor"
    ],
    "wof:name":"Belcher Dirt & Gravel",
    "wof:placetype":"venue"
},
  "geometry": {"coordinates":[-91.197789,34.887305],"type":"Point"}
}