{
  "type": "Feature",
  "properties": {
    "iso:country":"US",
    "sg:address":"2505 W Main St",
    "sg:city":"Clarksville",
    "sg:classifiers":[
        {
            "category":"Shopping",
            "subcategory":"Bicycles & Sporting Goods",
            "type":"Retail Goods"
        }
    ],
    "sg:phone":"+1 479 754 6354",
    "sg:postcode":"72830",
    "sg:province":"AR",
    "sg:tags":[
        "bait",
        "fishing"
    ],
    "wof:name":"Bill's Bait & Tackle",
    "wof:placetype":"venue"
},
  "geometry": {"coordinates":[-93.51906,35.466698],"type":"Point"}
}