{
  "type": "Feature",
  "properties": {
    "iso:country":"US",
    "sg:address":"1222 Edison Ave",
    "sg:city":"Benton",
    "sg:classifiers":[
        {
            "category":"Autos & Motor Vehicles",
            "subcategory":"Automobile Sales",
            "type":"Retail Goods"
        }
    ],
    "sg:phone":"+1 501 776 4008",
    "sg:postcode":"72015",
    "sg:province":"AR",
    "sg:tags":[
        "car",
        "used"
    ],
    "wof:name":"Wholesale Motors",
    "wof:placetype":"venue"
},
  "geometry": {"coordinates":[-92.573415,34.557279],"type":"Point"}
}