{
  "type": "Feature",
  "properties": {
    "iso:country":"US",
    "sg:address":"409 W Centerton Blvd",
    "sg:city":"Centerton",
    "sg:classifiers":[
        {
            "category":"Place Of Worship",
            "subcategory":"Church",
            "type":"Public Place"
        },
        {
            "category":"Place Of Worship",
            "type":"Public Place"
        }
    ],
    "sg:phone":"+1 479 224 6446",
    "sg:postcode":"72719",
    "sg:province":"AR",
    "sg:tags":[
        "churches-interdenominational",
        "churches-various",
        "denomination"
    ],
    "wof:name":"Iglesia Mas Que Vencedores",
    "wof:placetype":"venue"
},
  "geometry": {"coordinates":[-94.288241,36.358509],"type":"Point"}
}