{
  "type": "Feature",
  "properties": {
    "iso:country":"US",
    "sg:address":"330 Beach Rd",
    "sg:city":"Russellville",
    "sg:classifiers":[
        {
            "category":"Recreation",
            "subcategory":"Marina",
            "type":"Entertainment"
        }
    ],
    "sg:phone":"+1 479 967 1543",
    "sg:postcode":"72802",
    "sg:province":"AR",
    "wof:name":"Russellville Marina",
    "wof:placetype":"venue"
},
  "geometry": {"coordinates":[-93.20223300000001,35.292127],"type":"Point"}
}