{
  "type": "Feature",
  "properties": {
    "iso:country":"US",
    "sg:address":"420 Wells Rd",
    "sg:city":"Bald Knob",
    "sg:classifiers":[
        {
            "category":"Building & Trades",
            "subcategory":"Construction",
            "type":"Services"
        }
    ],
    "sg:phone":"+1 501 724 5446",
    "sg:postcode":"72010",
    "sg:province":"AR",
    "sg:tags":[
        "house"
    ],
    "wof:name":"Brock Construction",
    "wof:placetype":"venue"
},
  "geometry": {"coordinates":[-91.59902099999999,35.405622],"type":"Point"}
}