{
  "type": "Feature",
  "properties": {
    "iso:country":"US",
    "sg:address":"781 E Randall Wobbe Ln",
    "sg:city":"Springdale",
    "sg:classifiers":[
        {
            "category":"Transit Center",
            "subcategory":"Freight",
            "type":"Transportation"
        },
        {
            "category":"Building & Trades",
            "subcategory":"Equipment Rental",
            "type":"Services"
        },
        {
            "category":"Building & Trades",
            "subcategory":"Construction",
            "type":"Services"
        }
    ],
    "sg:phone":"+1 479 927 1672",
    "sg:postcode":"72764",
    "sg:province":"AR",
    "sg:tags":[
        "yard",
        "supply",
        "forklift",
        "contractor",
        "truck",
        "crane",
        "store"
    ],
    "sg:website":"http://www.he-equipment.com",
    "wof:name":"H& E Equipment Services",
    "wof:placetype":"venue"
},
  "geometry": {"coordinates":[-94.119003,36.2029],"type":"Point"}
}