{
  "type": "Feature",
  "properties": {
    "iso:country":"US",
    "sg:address":"108 Chad St",
    "sg:city":"Hot Springs",
    "sg:classifiers":[
        {
            "category":"Shopping",
            "subcategory":"Computers & Home Electronics",
            "type":"Retail Goods"
        }
    ],
    "sg:phone":"+1 501 262 5200",
    "sg:postcode":"71901",
    "sg:province":"AR",
    "sg:tags":[
        "software"
    ],
    "wof:name":"Prosystems Inc",
    "wof:placetype":"venue"
},
  "geometry": {"coordinates":[-92.95277,34.459573],"type":"Point"}
}