{
  "type": "Feature",
  "properties": {
    "iso:country":"US",
    "sg:address":"509 N Main St",
    "sg:city":"Mulberry",
    "sg:classifiers":[
        {
            "category":"Professional",
            "subcategory":"Accounting & Tax Preparation",
            "type":"Services"
        }
    ],
    "sg:phone":"+1 479 997 8282",
    "sg:postcode":"72947",
    "sg:province":"AR",
    "sg:tags":[
        "accountant"
    ],
    "wof:name":"Herman Luper CPA",
    "wof:placetype":"venue"
},
  "geometry": {"coordinates":[-94.051911,35.501479],"type":"Point"}
}