{
  "type": "Feature",
  "properties": {
    "addr:full":"302 Madison 2500 Huntsville AR 72740",
    "addr:housenumber":"302",
    "addr:postcode":"2500;72740",
    "iso:country":"US",
    "sg:address":"302 Madison 2500",
    "sg:city":"Huntsville",
    "sg:classifiers":[
        {
            "category":"Restaurant",
            "type":"Food & Drink"
        }
    ],
    "sg:phone":"+1 479 665 2205",
    "sg:postcode":"72740",
    "sg:province":"AR",
    "sg:tags":[
        "eating"
    ],
    "wof:name":"Charlebois Inc",
    "wof:placetype":"venue"
},
  "geometry": {"coordinates":[-93.593695,36.067617],"type":"Point"}
}