{
  "type": "Feature",
  "properties": {
    "addr:full":"914 N Vine St Magnolia AR 71753",
    "addr:housenumber":"914",
    "addr:postcode":"71753",
    "addr:street":"N Vine St",
    "iso:country":"US",
    "sg:address":"914 N Vine St",
    "sg:city":"Magnolia",
    "sg:classifiers":[
        {
            "category":"Organizations",
            "subcategory":"Membership Organization",
            "type":"Services"
        }
    ],
    "sg:phone":"+1 870 234 7770",
    "sg:postcode":"71753",
    "sg:province":"AR",
    "sg:website":"www.aa.org",
    "wof:name":"Alcoholics Anonymous",
    "wof:placetype":"venue"
},
  "geometry": {"coordinates":[-93.243584,33.275372],"type":"Point"}
}