{
  "type": "Feature",
  "properties": {
    "iso:country":"US",
    "sg:address":"1000 Mc Henry St",
    "sg:city":"El Dorado",
    "sg:classifiers":[
        {
            "category":"Professional",
            "type":"Services"
        }
    ],
    "sg:phone":"+1 870 863 9822",
    "sg:postcode":"71730",
    "sg:province":"AR",
    "sg:tags":[
        "establishment"
    ],
    "wof:name":"Dresser Rand",
    "wof:placetype":"venue"
},
  "geometry": {"coordinates":[-92.673594,33.201518],"type":"Point"}
}