{
  "type": "Feature",
  "properties": {
    "iso:country":"US",
    "sg:address":"18701 US Hwy 62",
    "sg:city":"Garfield",
    "sg:classifiers":[
        {
            "category":"Professional",
            "subcategory":"Business Services",
            "type":"Services"
        }
    ],
    "sg:phone":"+1 479 359 3607",
    "sg:postcode":"72732",
    "sg:province":"AR",
    "wof:name":"Ashmore Creek Flea Mkt Gallery",
    "wof:placetype":"venue"
},
  "geometry": {"coordinates":[-93.96472199999999,36.450717],"type":"Point"}
}