{
  "type": "Feature",
  "properties": {
    "iso:country":"US",
    "sg:address":"3408 S University Ave",
    "sg:city":"Little Rock",
    "sg:classifiers":[
        {
            "category":"Personal",
            "subcategory":"Beauty Salon",
            "type":"Services"
        }
    ],
    "sg:phone":"+1 501 562 7221",
    "sg:postcode":"72204",
    "sg:province":"AR",
    "wof:name":"Y J'Nai's",
    "wof:placetype":"venue"
},
  "geometry": {"coordinates":[-92.34218199999999,34.722095],"type":"Point"}
}