{
  "type": "Feature",
  "properties": {
    "addr:full":"102 Davis Ln Russellville AR 72802",
    "addr:housenumber":"102",
    "addr:postcode":"72802",
    "addr:street":"Davis Ln",
    "iso:country":"US",
    "sg:address":"102 Davis Ln",
    "sg:city":"Russellville",
    "sg:classifiers":[
        {
            "category":"Building & Trades",
            "subcategory":"Cleaning & Sanitation",
            "type":"Services"
        }
    ],
    "sg:phone":"+1 479 967 0609",
    "sg:postcode":"72802",
    "sg:province":"AR",
    "sg:tags":[
        "commercial",
        "janitorial"
    ],
    "wof:name":"Davis Janitorial",
    "wof:placetype":"venue"
},
  "geometry": {"coordinates":[-92.976952,35.337637],"type":"Point"}
}