{
  "type": "Feature",
  "properties": {
    "iso:country":"US",
    "sg:address":"316 S Main St",
    "sg:city":"Okolona",
    "sg:classifiers":[
        {
            "category":"Government",
            "subcategory":"Post Office",
            "type":"Public Place"
        }
    ],
    "sg:phone":"+1 870 274 3494",
    "sg:postcode":"71962",
    "sg:province":"AR",
    "wof:name":"US Post Office",
    "wof:placetype":"venue"
},
  "geometry": {"coordinates":[-93.337694,34.002001],"type":"Point"}
}