{
  "type": "Feature",
  "properties": {
    "iso:country":"US",
    "sg:address":"324 W Broadway Ave",
    "sg:city":"Forrest City",
    "sg:classifiers":[
        {
            "category":"Professional",
            "subcategory":"Accounting & Tax Preparation",
            "type":"Services"
        }
    ],
    "sg:phone":"+1 870 630 9797",
    "sg:postcode":"72335",
    "sg:province":"AR",
    "sg:tags":[
        "return",
        "filing"
    ],
    "wof:name":"Jackson Hewitt Tax Svc",
    "wof:placetype":"venue"
},
  "geometry": {"coordinates":[-90.789985,35.007977],"type":"Point"}
}