{
  "type": "Feature",
  "properties": {
    "addr:full":"465 S Main St Waldron AR 72958",
    "addr:housenumber":"465",
    "addr:postcode":"72958",
    "addr:street":"S Main St",
    "iso:country":"US",
    "sg:address":"465 S Main St",
    "sg:city":"Waldron",
    "sg:classifiers":[
        {
            "category":"Autos & Motor Vehicles",
            "subcategory":"Motorcycle Sales",
            "type":"Retail Goods"
        }
    ],
    "sg:phone":"+1 479 637 2177",
    "sg:postcode":"72958",
    "sg:province":"AR",
    "sg:tags":[
        "scooter"
    ],
    "wof:name":"America's Best Motorcycle Spls",
    "wof:placetype":"venue"
},
  "geometry": {"coordinates":[-94.091185,34.897841],"type":"Point"}
}