{
  "type": "Feature",
  "properties": {
    "iso:country":"US",
    "sg:address":"1818 N Taylor St",
    "sg:city":"Little Rock",
    "sg:classifiers":[
        {
            "category":"Shopping",
            "type":"Retail Goods"
        }
    ],
    "sg:phone":"+1 501 666 4210",
    "sg:postcode":"72207",
    "sg:province":"AR",
    "sg:tags":[
        "merchandise"
    ],
    "wof:name":"Wild Birds Unlimited",
    "wof:placetype":"venue"
},
  "geometry": {"coordinates":[-92.33596799999999,34.769031],"type":"Point"}
}