{
  "type": "Feature",
  "properties": {
    "iso:country":"US",
    "sg:address":"501 Elsinger Blvd",
    "sg:city":"Conway",
    "sg:classifiers":[
        {
            "category":"Coffee & Tea",
            "type":"Food & Drink"
        }
    ],
    "sg:menulink":"http://www.allmenus.com/ar/cadron/115337-starbucks-coffee/menu/",
    "sg:phone":"+1 501 328 5739",
    "sg:postcode":"72032",
    "sg:province":"AR",
    "sg:tags":[
        "american"
    ],
    "wof:name":"Starbucks Coffee",
    "wof:placetype":"venue"
},
  "geometry": {"coordinates":[-92.414315,35.090608],"type":"Point"}
}