{
  "type": "Feature",
  "properties": {
    "iso:country":"US",
    "sg:address":"3508 N 13th St",
    "sg:city":"Rogers",
    "sg:classifiers":[
        {
            "category":"Utilities",
            "subcategory":"Fuel Oil & Lpg",
            "type":"Services"
        }
    ],
    "sg:phone":"+1 479 903 6514",
    "sg:postcode":"72756",
    "sg:province":"AR",
    "sg:tags":[
        "dealer"
    ],
    "wof:name":"JC Oil Company Inc",
    "wof:placetype":"venue"
},
  "geometry": {"coordinates":[-94.13385599999999,36.368077],"type":"Point"}
}