{
  "type": "Feature",
  "properties": {
    "iso:country":"US",
    "sg:address":"120 Madison 2120",
    "sg:city":"Huntsville",
    "sg:classifiers":[
        {
            "category":"Farming",
            "subcategory":"Farm",
            "type":"Manufacturing & Wholesale Goods"
        }
    ],
    "sg:phone":"+1 479 665 2148",
    "sg:postcode":"72740",
    "sg:province":"AR",
    "sg:tags":[
        "crop",
        "general"
    ],
    "wof:name":"Hawthorn Farms",
    "wof:placetype":"venue"
},
  "geometry": {"coordinates":[-93.556512,36.123219],"type":"Point"}
}