{
  "type": "Feature",
  "properties": {
    "iso:country":"US",
    "sg:address":"318 W Monroe Ave",
    "sg:city":"Jonesboro",
    "sg:classifiers":[
        {
            "category":"Retail",
            "subcategory":"Laundry & Dry Cleaning",
            "type":"Services"
        }
    ],
    "sg:phone":"+1 870 972 0700",
    "sg:postcode":"72401",
    "sg:province":"AR",
    "sg:tags":[
        "building",
        "maintenance"
    ],
    "wof:name":"Huddleston Carpet Care",
    "wof:placetype":"venue"
},
  "geometry": {"coordinates":[-90.710325,35.839264],"type":"Point"}
}