{
  "type": "Feature",
  "properties": {
    "iso:country":"US",
    "sg:address":"84 Walnut St",
    "sg:city":"Marianna",
    "sg:classifiers":[
        {
            "category":"Building & Trades",
            "subcategory":"Equipment Rental",
            "type":"Services"
        }
    ],
    "sg:phone":"+1 870 295 3338",
    "sg:postcode":"72360",
    "sg:province":"AR",
    "wof:name":"Edwards Rentals LLC",
    "wof:placetype":"venue"
},
  "geometry": {"coordinates":[-90.759607,34.777405],"type":"Point"}
}