{
  "type": "Feature",
  "properties": {
    "iso:country":"US",
    "sg:address":"2108 Breckenridge Ter",
    "sg:city":"Greenwood",
    "sg:classifiers":[
        {
            "category":"Building & Trades",
            "subcategory":"Construction",
            "type":"Services"
        }
    ],
    "sg:phone":"+1 479 996 0197",
    "sg:postcode":"72936",
    "sg:province":"AR",
    "sg:tags":[
        "wallcoverings-installation",
        "wallpaper",
        "painting",
        "contractor"
    ],
    "wof:name":"Jim's Painting And Remodeling Inc",
    "wof:placetype":"venue"
},
  "geometry": {"coordinates":[-94.291481,35.22159],"type":"Point"}
}