{
  "type": "Feature",
  "properties": {
    "addr:full":"404 Main St Horatio AR 71842",
    "addr:housenumber":"404",
    "addr:postcode":"71842",
    "addr:street":"Main St",
    "iso:country":"US",
    "sg:address":"404 Main St",
    "sg:city":"Horatio",
    "sg:classifiers":[
        {
            "category":"Personal",
            "subcategory":"Beauty Salon",
            "type":"Services"
        }
    ],
    "sg:phone":"+1 870 832 4878",
    "sg:postcode":"71842",
    "sg:province":"AR",
    "wof:name":"Cutting Up",
    "wof:placetype":"venue"
},
  "geometry": {"coordinates":[-94.35498800000001,33.938326],"type":"Point"}
}