{
  "type": "Feature",
  "properties": {
    "iso:country":"US",
    "sg:address":"3958 O St N",
    "sg:city":"Fort Smith",
    "sg:classifiers":[
        {
            "category":"Shopping",
            "subcategory":"Beauty & Cosmetics",
            "type":"Retail Goods"
        },
        {
            "category":"Shopping",
            "subcategory":"Clothing, Apparel, & Fashions",
            "type":"Retail Goods"
        }
    ],
    "sg:phone":"+1 479 785 2711",
    "sg:postcode":"72904",
    "sg:province":"AR",
    "sg:tags":[
        "wig",
        "toupee",
        "hairpiece",
        "merchandise"
    ],
    "wof:name":"Young's Beauty Mart",
    "wof:placetype":"venue"
},
  "geometry": {"coordinates":[-94.388207,35.392923],"type":"Point"}
}