{
  "type": "Feature",
  "properties": {
    "iso:country":"US",
    "sg:address":"10798 Shell Rd",
    "sg:city":"Bentonville",
    "sg:classifiers":[
        {
            "category":"Building & Trades",
            "subcategory":"Construction",
            "type":"Services"
        }
    ],
    "sg:phone":"+1 479 273 3547",
    "sg:postcode":"72712",
    "sg:province":"AR",
    "sg:tags":[
        "excavation",
        "contractor"
    ],
    "wof:name":"Bonds Excavating Enterprises",
    "wof:placetype":"venue"
},
  "geometry": {"coordinates":[-94.262194,36.336452],"type":"Point"}
}