{
  "type": "Feature",
  "properties": {
    "iso:country":"US",
    "sg:address":"7209 Greers Ferry Rd",
    "sg:city":"Greers Ferry",
    "sg:classifiers":[
        {
            "category":"Restaurant",
            "type":"Food & Drink"
        }
    ],
    "sg:phone":"+1 501 723 4480",
    "sg:postcode":"72067",
    "sg:province":"AR",
    "wof:name":"Janssens Lake Front Restaurant",
    "wof:placetype":"venue"
},
  "geometry": {"coordinates":[-92.174896,35.578044],"type":"Point"}
}