{
  "type": "Feature",
  "properties": {
    "iso:country":"US",
    "sg:address":"816 Ferry St",
    "sg:city":"Little Rock",
    "sg:classifiers":[
        {
            "category":"Education",
            "subcategory":"School",
            "type":"Public Place"
        }
    ],
    "sg:phone":"+1 501 374 9166",
    "sg:postcode":"72202",
    "sg:province":"AR",
    "sg:tags":[
        "organization",
        "religious"
    ],
    "wof:name":"St Edward's School",
    "wof:placetype":"venue"
},
  "geometry": {"coordinates":[-92.26436,34.739702],"type":"Point"}
}