{
  "type": "Feature",
  "properties": {
    "iso:country":"US",
    "sg:address":"3710 NW Creekstone Blvd",
    "sg:city":"Bentonville",
    "sg:classifiers":[
        {
            "category":"Utilities",
            "subcategory":"Water",
            "type":"Services"
        }
    ],
    "sg:phone":"+1 479 254 0180",
    "sg:postcode":"72712",
    "sg:province":"AR",
    "sg:tags":[
        "umbrella"
    ],
    "wof:name":"Essex Mfg",
    "wof:placetype":"venue"
},
  "geometry": {"coordinates":[-94.217453,36.420537],"type":"Point"}
}