{
  "type": "Feature",
  "properties": {
    "iso:country":"US",
    "sg:address":"105 Central Ave",
    "sg:city":"Searcy",
    "sg:classifiers":[
        {
            "category":"Health Services",
            "subcategory":"Doctor",
            "type":"Services"
        }
    ],
    "sg:phone":"+1 501 268 7154",
    "sg:postcode":"72143",
    "sg:province":"AR",
    "sg:tags":[
        "clinic"
    ],
    "sg:website":"www.loweryeye.medem.com",
    "wof:name":"Lowery Eye Clinic & Surgery",
    "wof:placetype":"venue"
},
  "geometry": {"coordinates":[-91.73544099999999,35.236301],"type":"Point"}
}