{
  "type": "Feature",
  "properties": {
    "iso:country":"US",
    "sg:address":"3 Co Rd 247",
    "sg:city":"Wynne",
    "sg:classifiers":[
        {
            "category":"Organizations",
            "subcategory":"Religious Organization",
            "type":"Services"
        }
    ],
    "sg:phone":"+1 870 238 3659",
    "sg:postcode":"72396",
    "sg:province":"AR",
    "sg:tags":[
        "church"
    ],
    "wof:name":"Mt Omah Baptist Church",
    "wof:placetype":"venue"
},
  "geometry": {"coordinates":[-90.811802,35.259017],"type":"Point"}
}