{
  "type": "Feature",
  "properties": {
    "iso:country":"US",
    "sg:address":"660 S Thompson St",
    "sg:city":"Springdale",
    "sg:classifiers":[
        {
            "category":"Travel",
            "subcategory":"Hotels & Motels",
            "type":"Entertainment"
        }
    ],
    "sg:phone":"+1 479 751 4878",
    "sg:postcode":"72764",
    "sg:province":"AR",
    "sg:tags":[
        "operation"
    ],
    "wof:name":"Springdale Motel",
    "wof:placetype":"venue"
},
  "geometry": {"coordinates":[-94.138987,36.177752],"type":"Point"}
}