{
  "type": "Feature",
  "properties": {
    "iso:country":"US",
    "sg:address":"517 W Keiser Ave",
    "sg:city":"Osceola",
    "sg:classifiers":[
        {
            "category":"Shopping",
            "subcategory":"Discount & Variety Stores",
            "type":"Retail Goods"
        }
    ],
    "sg:phone":"+1 870 563 5402",
    "sg:postcode":"72370",
    "sg:province":"AR",
    "wof:name":"Dollar General",
    "wof:placetype":"venue"
},
  "geometry": {"coordinates":[-89.974465,35.697551],"type":"Point"}
}