{
  "type": "Feature",
  "properties": {
    "iso:country":"US",
    "sg:address":"1225 Renfroe St",
    "sg:city":"Magnolia",
    "sg:classifiers":[
        {
            "category":"Organizations",
            "subcategory":"Religious Organization",
            "type":"Services"
        }
    ],
    "sg:phone":"+1 870 234 2306",
    "sg:postcode":"71753",
    "sg:province":"AR",
    "sg:tags":[
        "church"
    ],
    "wof:name":"House Of Prayer",
    "wof:placetype":"venue"
},
  "geometry": {"coordinates":[-93.22667300000001,33.256719],"type":"Point"}
}