{
  "type": "Feature",
  "properties": {
    "addr:full":"1750 S Constitution Ave Ashdown AR 71822",
    "addr:housenumber":"1750",
    "addr:postcode":"71822",
    "addr:street":"S Constitution Ave",
    "iso:country":"US",
    "sg:address":"1750 S Constitution Ave",
    "sg:city":"Ashdown",
    "sg:classifiers":[
        {
            "category":"Restaurant",
            "type":"Food & Drink"
        }
    ],
    "sg:phone":"+1 870 898 9777",
    "sg:postcode":"71822",
    "sg:province":"AR",
    "sg:tags":[
        "eating"
    ],
    "wof:name":"Hong Kwong Chinese Restaurant",
    "wof:placetype":"venue"
},
  "geometry": {"coordinates":[-94.111311,33.653685],"type":"Point"}
}