{
  "type": "Feature",
  "properties": {
    "iso:country":"US",
    "sg:address":"108 Alma Ln",
    "sg:city":"Clarksville",
    "sg:classifiers":[
        {
            "category":"Professional",
            "subcategory":"Business Services",
            "type":"Services"
        }
    ],
    "sg:phone":"+1 479 754 7518",
    "sg:postcode":"72830",
    "sg:province":"AR",
    "sg:tags":[
        "painter",
        "sign"
    ],
    "wof:name":"Finishing Touch Vinyl Letter",
    "wof:placetype":"venue"
},
  "geometry": {"coordinates":[-93.447087,35.444483],"type":"Point"}
}