{
  "type": "Feature",
  "properties": {
    "addr:full":"1123 S University Ave Little Rock AR 72204",
    "addr:housenumber":"1123",
    "addr:postcode":"72204",
    "addr:street":"S University Ave",
    "iso:country":"US",
    "sg:address":"1123 S University Ave",
    "sg:city":"Little Rock",
    "sg:classifiers":[
        {
            "category":"Professional",
            "subcategory":"Research",
            "type":"Services"
        }
    ],
    "sg:phone":"+1 501 686 8715",
    "sg:postcode":"72204",
    "sg:province":"AR",
    "sg:tags":[
        "commercial",
        "physical"
    ],
    "wof:name":"Department Information Tech",
    "wof:placetype":"venue"
},
  "geometry": {"coordinates":[-92.341335,34.742513],"type":"Point"}
}