{
  "type": "Feature",
  "properties": {
    "addr:full":"5814 Brown Ln Ozark AR 72949",
    "addr:housenumber":"5814",
    "addr:postcode":"72949",
    "addr:street":"Brown Ln",
    "iso:country":"US",
    "sg:address":"5814 Brown Ln",
    "sg:city":"Ozark",
    "sg:classifiers":[
        {
            "category":"Home & Garden",
            "subcategory":"Garden Supply",
            "type":"Retail Goods"
        }
    ],
    "sg:phone":"+1 479 667 2405",
    "sg:postcode":"72949",
    "sg:province":"AR",
    "sg:tags":[
        "nurseryman"
    ],
    "wof:name":"Southaven Nursery",
    "wof:placetype":"venue"
},
  "geometry": {"coordinates":[-93.83479699999999,35.3977],"type":"Point"}
}