{
  "type": "Feature",
  "properties": {
    "iso:country":"US",
    "sg:address":"8915 Edgemont Rd",
    "sg:city":"Higden",
    "sg:classifiers":[
        {
            "category":"Retail",
            "subcategory":"Repair Shop",
            "type":"Services"
        }
    ],
    "sg:phone":"+1 501 825 7059",
    "sg:postcode":"72067",
    "sg:province":"AR",
    "wof:name":"Louise Frye",
    "wof:placetype":"venue"
},
  "geometry": {"coordinates":[-92.177044,35.577148],"type":"Point"}
}