{
  "type": "Feature",
  "properties": {
    "iso:country":"US",
    "sg:address":"130 Grant 74",
    "sg:city":"Sheridan",
    "sg:classifiers":[
        {
            "category":"Government",
            "subcategory":"Office",
            "type":"Public Place"
        }
    ],
    "sg:phone":"+1 870 942 3333",
    "sg:postcode":"72150",
    "sg:province":"AR",
    "sg:tags":[
        "county",
        "safety",
        "order"
    ],
    "wof:name":"Grant County Emergency Mgmt",
    "wof:placetype":"venue"
},
  "geometry": {"coordinates":[-92.378123,34.30926],"type":"Point"}
}