{
  "type": "Feature",
  "properties": {
    "iso:country":"US",
    "sg:address":"13 Blackberry Rd",
    "sg:city":"Searcy",
    "sg:classifiers":[
        {
            "category":"Professional",
            "subcategory":"Lawyer & Legal Services",
            "type":"Services"
        }
    ],
    "sg:phone":"+1 501 268 0631",
    "sg:postcode":"72143",
    "sg:province":"AR",
    "sg:tags":[
        "attorney"
    ],
    "wof:name":"Charles Michael Wise",
    "wof:placetype":"venue"
},
  "geometry": {"coordinates":[-91.790617,35.230812],"type":"Point"}
}