{
  "type": "Feature",
  "properties": {
    "addr:full":"4801 W Commercial Dr N Little Rock AR 72116",
    "addr:housenumber":"4801",
    "addr:postcode":"72116",
    "addr:street":"W Commercial Dr N",
    "iso:country":"US",
    "sg:address":"4801 W Commercial Dr",
    "sg:city":"N Little Rock",
    "sg:classifiers":[
        {
            "category":"Travel",
            "subcategory":"Hotels & Motels",
            "type":"Entertainment"
        }
    ],
    "sg:phone":"+1 501 753 8660",
    "sg:postcode":"72116",
    "sg:province":"AR",
    "sg:tags":[
        "operation"
    ],
    "wof:name":"Hampton Inn",
    "wof:placetype":"venue"
},
  "geometry": {"coordinates":[-92.220167,34.797674],"type":"Point"}
}