{
  "type": "Feature",
  "properties": {
    "iso:country":"US",
    "sg:address":"5228 R St",
    "sg:city":"Little Rock",
    "sg:phone":"+1 501 664 4666",
    "sg:postcode":"72207",
    "sg:province":"AR",
    "sg:tags":[
        "farm",
        "rice",
        "wheat",
        "soybean",
        "cotton"
    ],
    "wof:name":"PCI Farms",
    "wof:placetype":"venue"
},
  "geometry": {"coordinates":[-92.330698,34.76911],"type":"Point"}
}