{
  "type": "Feature",
  "properties": {
    "iso:country":"US",
    "sg:address":"1607 US Hwy 71",
    "sg:city":"Mena",
    "sg:classifiers":[
        {
            "category":"Banks & Credit Unions",
            "subcategory":"Bank",
            "type":"Services"
        }
    ],
    "sg:phone":"+1 479 394 1027",
    "sg:postcode":"71953",
    "sg:province":"AR",
    "sg:tags":[
        "loan"
    ],
    "wof:name":"Farm Credit Svc",
    "wof:placetype":"venue"
},
  "geometry": {"coordinates":[-94.243635,34.572944],"type":"Point"}
}