{
  "type": "Feature",
  "properties": {
    "iso:country":"US",
    "sg:address":"210 W 2nd St",
    "sg:city":"Lewisville",
    "sg:classifiers":[
        {
            "category":"Food & Beverages",
            "subcategory":"Groceries & Convenience Stores",
            "type":"Retail Goods"
        }
    ],
    "sg:phone":"+1 870 921 4544",
    "sg:postcode":"71845",
    "sg:province":"AR",
    "wof:name":"Barton Grocery & Market",
    "wof:placetype":"venue"
},
  "geometry": {"coordinates":[-93.576318,33.356229],"type":"Point"}
}