{
  "type": "Feature",
  "properties": {
    "iso:country":"US",
    "sg:address":"314 Main St",
    "sg:city":"Little Rock",
    "sg:classifiers":[
        {
            "category":"Retail",
            "subcategory":"Repair Shop",
            "type":"Services"
        }
    ],
    "sg:phone":"+1 501 612 7322",
    "sg:postcode":"72201",
    "sg:province":"AR",
    "sg:tags":[
        "instrument",
        "musical"
    ],
    "wof:name":"FIXAUDIO.COM",
    "wof:placetype":"venue"
},
  "geometry": {"coordinates":[-92.270826,34.745905],"type":"Point"}
}