{
  "type": "Feature",
  "properties": {
    "iso:country":"US",
    "sg:address":"76 Wakerobin Rd",
    "sg:city":"Russellville",
    "sg:classifiers":[
        {
            "category":"Building & Trades",
            "subcategory":"Pest Control",
            "type":"Services"
        }
    ],
    "sg:phone":"+1 479 968 9177",
    "sg:postcode":"72802",
    "sg:province":"AR",
    "wof:name":"River Valley Pest Control",
    "wof:placetype":"venue"
},
  "geometry": {"coordinates":[-93.104891,35.349113],"type":"Point"}
}