{
  "type": "Feature",
  "properties": {
    "addr:full":"2051 Harkrider St Conway AR 72032",
    "addr:housenumber":"2051",
    "addr:postcode":"72032",
    "addr:street":"Harkrider St",
    "iso:country":"US",
    "sg:address":"2051 Harkrider St",
    "sg:city":"Conway",
    "sg:classifiers":[
        {
            "category":"Retail",
            "subcategory":"Car Wash",
            "type":"Services"
        }
    ],
    "sg:phone":"+1 501 764 1557",
    "sg:postcode":"72032",
    "sg:province":"AR",
    "sg:tags":[
        "automobile",
        "detail",
        "clean"
    ],
    "wof:name":"Travel Senter Auto Detailing",
    "wof:placetype":"venue"
},
  "geometry": {"coordinates":[-92.44084100000001,35.104787],"type":"Point"}
}