{
  "type": "Feature",
  "properties": {
    "iso:country":"US",
    "sg:address":"107 NW 2nd St",
    "sg:city":"Bentonville",
    "sg:classifiers":[
        {
            "category":"Sports & Exercise",
            "subcategory":"Gym",
            "type":"Entertainment"
        },
        {
            "category":"Arts & Performance",
            "subcategory":"Dance",
            "type":"Entertainment"
        }
    ],
    "sg:phone":"+1 479 464 5977",
    "sg:postcode":"72712",
    "sg:province":"AR",
    "sg:tags":[
        "instruction",
        "yoga",
        "dancing"
    ],
    "wof:name":"Kaleidoscope Dance",
    "wof:placetype":"venue"
},
  "geometry": {"coordinates":[-94.20889099999999,36.372941],"type":"Point"}
}