{
  "type": "Feature",
  "properties": {
    "addr:full":"1303 Hillcrest Dr Conway AR 72034",
    "addr:housenumber":"1303",
    "addr:postcode":"72034",
    "addr:street":"Hillcrest Dr",
    "iso:country":"US",
    "sg:address":"1303 Hillcrest Dr",
    "sg:city":"Conway",
    "sg:classifiers":[
        {
            "category":"Government",
            "subcategory":"Court House",
            "type":"Public Place"
        }
    ],
    "sg:phone":"+1 501 339 8925",
    "sg:postcode":"72034",
    "sg:province":"AR",
    "sg:tags":[
        "justice"
    ],
    "wof:name":"Pulaski County District Court",
    "wof:placetype":"venue"
},
  "geometry": {"coordinates":[-92.45977000000001,35.096214],"type":"Point"}
}