{
  "type": "Feature",
  "properties": {
    "iso:country":"US",
    "sg:address":"3570 Cutter Ridge Rd",
    "sg:city":"Conway",
    "sg:classifiers":[
        {
            "category":"Building & Trades",
            "subcategory":"Construction",
            "type":"Services"
        }
    ],
    "sg:phone":"+1 501 327 5442",
    "sg:postcode":"72034",
    "sg:province":"AR",
    "sg:tags":[
        "house"
    ],
    "wof:name":"E Massey Construction Inc",
    "wof:placetype":"venue"
},
  "geometry": {"coordinates":[-92.488609,35.081454],"type":"Point"}
}