{
  "type": "Feature",
  "properties": {
    "iso:country":"US",
    "sg:address":"601 E 8th Ave",
    "sg:city":"Pine Bluff",
    "sg:classifiers":[
        {
            "category":"Professional",
            "subcategory":"Employment Agencies",
            "type":"Services"
        }
    ],
    "sg:phone":"+1 870 535 5507",
    "sg:postcode":"71601",
    "sg:province":"AR",
    "sg:tags":[
        "help",
        "contractor"
    ],
    "wof:name":"A Team Temporary Svc",
    "wof:placetype":"venue"
},
  "geometry": {"coordinates":[-91.997718,34.22171],"type":"Point"}
}