{
  "type": "Feature",
  "properties": {
    "iso:country":"US",
    "sg:address":"19251 US Hwy 62",
    "sg:city":"Garfield",
    "sg:classifiers":[
        {
            "category":"Shopping",
            "type":"Retail Goods"
        },
        {
            "category":"Professional",
            "subcategory":"Management & Consulting",
            "type":"Services"
        }
    ],
    "sg:phone":"+1 479 359 2111",
    "sg:postcode":"72732",
    "sg:province":"AR",
    "sg:tags":[
        "equipment",
        "hearing",
        "impaired",
        "supply"
    ],
    "wof:name":"Key Audiometrics Inc",
    "wof:placetype":"venue"
},
  "geometry": {"coordinates":[-93.953553,36.466271],"type":"Point"}
}