{
  "type": "Feature",
  "properties": {
    "addr:full":"2806 E Race Ave Searcy AR 72143",
    "addr:housenumber":"2806",
    "addr:postcode":"72143",
    "addr:street":"E Race Ave",
    "iso:country":"US",
    "sg:address":"2806 E Race Ave",
    "sg:city":"Searcy",
    "sg:classifiers":[
        {
            "category":"Autos & Motor Vehicles",
            "subcategory":"Auto Supplies",
            "type":"Retail Goods"
        }
    ],
    "sg:phone":"+1 501 305 2928",
    "sg:postcode":"72143",
    "sg:province":"AR",
    "sg:tags":[
        "automobile",
        "parts"
    ],
    "wof:name":"Advance Auto Parts Inc",
    "wof:placetype":"venue"
},
  "geometry": {"coordinates":[-91.70381999999999,35.250597],"type":"Point"}
}