{
  "type": "Feature",
  "properties": {
    "iso:country":"US",
    "sg:address":"70 Hwy 319 E",
    "sg:city":"Vilonia",
    "sg:classifiers":[
        {
            "category":"Building & Trades",
            "subcategory":"Landscaping Services",
            "type":"Services"
        }
    ],
    "sg:phone":"+1 501 796 2090",
    "sg:postcode":"72173",
    "sg:province":"AR",
    "wof:name":"Quality Tree Service LLC",
    "wof:placetype":"venue"
},
  "geometry": {"coordinates":[-92.175697,35.057675],"type":"Point"}
}