{
  "type": "Feature",
  "properties": {
    "addr:full":"6534 Tyro Rd Hackett AR 72937",
    "addr:housenumber":"6534",
    "addr:postcode":"72937",
    "addr:street":"Tyro Rd",
    "iso:country":"US",
    "sg:address":"6534 Tyro Rd",
    "sg:city":"Hackett",
    "sg:classifiers":[
        {
            "category":"Retail",
            "subcategory":"Auto Repair",
            "type":"Services"
        }
    ],
    "sg:phone":"+1 501 638 8191",
    "sg:postcode":"72937",
    "sg:province":"AR",
    "sg:tags":[
        "glass",
        "replacement"
    ],
    "wof:name":"Professional Auto Glass LLC",
    "wof:placetype":"venue"
},
  "geometry": {"coordinates":[-94.39126,35.12575],"type":"Point"}
}