{
  "type": "Feature",
  "properties": {
    "addr:full":"1570 Ione Pl Springdale AR 72764",
    "addr:housenumber":"1570",
    "addr:postcode":"72764",
    "addr:street":"Ione Pl",
    "iso:country":"US",
    "sg:address":"1570 Ione Pl",
    "sg:city":"Springdale",
    "sg:classifiers":[
        {
            "category":"Real Estate",
            "subcategory":"Real Estate Operator",
            "type":"Services"
        }
    ],
    "sg:phone":"+1 479 750 3030",
    "sg:postcode":"72764",
    "sg:province":"AR",
    "sg:tags":[
        "apartment"
    ],
    "wof:name":"Pleasant Point Apartments",
    "wof:placetype":"venue"
},
  "geometry": {"coordinates":[-94.14734199999999,36.169281],"type":"Point"}
}