{
  "type": "Feature",
  "properties": {
    "addr:full":"8012 Sheridan Rd White Hall AR 71602",
    "addr:housenumber":"8012",
    "addr:postcode":"71602",
    "addr:street":"Sheridan Rd",
    "iso:country":"US",
    "sg:address":"8012 Sheridan Rd",
    "sg:city":"White Hall",
    "sg:classifiers":[
        {
            "category":"Restaurant",
            "type":"Food & Drink"
        }
    ],
    "sg:menulink":"http://www.allmenus.com/ar/washington/190466-mcdonalds/menu/",
    "sg:postcode":"71602",
    "sg:province":"AR",
    "sg:tags":[
        "burger",
        "american"
    ],
    "wof:name":"McDonald's",
    "wof:placetype":"venue"
},
  "geometry": {"coordinates":[-92.100819,34.260001],"type":"Point"}
}