{
  "type": "Feature",
  "properties": {
    "iso:country":"US",
    "sg:address":"10569 Terpening Rd",
    "sg:city":"Prairie Grove",
    "sg:classifiers":[
        {
            "category":"Home & Garden",
            "subcategory":"Building Materials",
            "type":"Retail Goods"
        },
        {
            "category":"Manufacturing",
            "subcategory":"Tools & Machinery",
            "type":"Manufacturing & Wholesale Goods"
        }
    ],
    "sg:phone":"+1 479 846 5572",
    "sg:postcode":"72753",
    "sg:province":"AR",
    "sg:tags":[
        "supply",
        "energy",
        "system",
        "equipment",
        "conservation",
        "prod"
    ],
    "wof:name":"Northwest Energy Systems",
    "wof:placetype":"venue"
},
  "geometry": {"coordinates":[-94.272915,35.99614],"type":"Point"}
}