{
  "type": "Feature",
  "properties": {
    "iso:country":"US",
    "sg:address":"11167 State Hwy 336",
    "sg:city":"Clinton",
    "sg:classifiers":[
        {
            "category":"Building & Trades",
            "subcategory":"Construction",
            "type":"Services"
        }
    ],
    "sg:phone":"+1 501 745 4770",
    "sg:postcode":"72031",
    "sg:province":"AR",
    "sg:tags":[
        "general",
        "contractor"
    ],
    "wof:name":"Appleby Home Improvements",
    "wof:placetype":"venue"
},
  "geometry": {"coordinates":[-92.509795,35.466987],"type":"Point"}
}