{
  "type": "Feature",
  "properties": {
    "addr:full":"5604 Ellsworth Rd Fort Smith AR 72903",
    "addr:housenumber":"5604",
    "addr:postcode":"72903",
    "addr:street":"Ellsworth Rd",
    "iso:country":"US",
    "sg:address":"5604 Ellsworth Rd",
    "sg:city":"Fort Smith",
    "sg:classifiers":[
        {
            "category":"Health Services",
            "subcategory":"Doctor",
            "type":"Services"
        }
    ],
    "sg:phone":"+1 479 484 7336",
    "sg:postcode":"72903",
    "sg:province":"AR",
    "sg:tags":[
        "dentist"
    ],
    "wof:name":"Dr Mark A Willis DDS",
    "wof:placetype":"venue"
},
  "geometry": {"coordinates":[-94.36785,35.365959],"type":"Point"}
}