{
  "type": "Feature",
  "properties": {
    "iso:country":"US",
    "sg:address":"287 W Locke Ave",
    "sg:city":"De Queen",
    "sg:classifiers":[
        {
            "category":"Real Estate",
            "subcategory":"Real Estate Operator",
            "type":"Services"
        }
    ],
    "sg:phone":"+1 870 642 6555",
    "sg:postcode":"71832",
    "sg:province":"AR",
    "sg:tags":[
        "building",
        "apartment"
    ],
    "wof:name":"Kings Gate Apts",
    "wof:placetype":"venue"
},
  "geometry": {"coordinates":[-94.359289,34.038119],"type":"Point"}
}