{
  "type": "Feature",
  "properties": {
    "iso:country":"US",
    "sg:address":"31 Heritage Park Cir",
    "sg:city":"Sherwood",
    "sg:classifiers":[
        {
            "category":"Shopping",
            "subcategory":"Jewelry",
            "type":"Retail Goods"
        }
    ],
    "sg:phone":"+1 501 758 1357",
    "sg:postcode":"72116",
    "sg:province":"AR",
    "sg:tags":[
        "jeweler"
    ],
    "wof:name":"Chudy Associates Inc-With Love",
    "wof:placetype":"venue"
},
  "geometry": {"coordinates":[-92.236807,34.794028],"type":"Point"}
}