{
  "type": "Feature",
  "properties": {
    "addr:full":"24 Co Rd 2230 Cherry Valley AR 72324",
    "addr:housenumber":"24;2230",
    "addr:postcode":"72324",
    "addr:street":"Co Rd",
    "iso:country":"US",
    "sg:address":"24 Co Rd 2230",
    "sg:city":"Cherry Valley",
    "sg:classifiers":[
        {
            "category":"Retail",
            "subcategory":"Repair Shop",
            "type":"Services"
        }
    ],
    "sg:phone":"+1 870 588 4322",
    "sg:postcode":"72324",
    "sg:province":"AR",
    "sg:tags":[
        "farm",
        "equipment",
        "parts"
    ],
    "wof:name":"Johnny Mc Farland Shop",
    "wof:placetype":"venue"
},
  "geometry": {"coordinates":[-90.84319000000001,35.344629],"type":"Point"}
}