{
  "type": "Feature",
  "properties": {
    "addr:full":"111 S Main St Nashville AR 71852",
    "addr:housenumber":"111",
    "addr:postcode":"71852",
    "addr:street":"S Main St",
    "iso:country":"US",
    "sg:address":"111 S Main St",
    "sg:city":"Nashville",
    "sg:classifiers":[
        {
            "category":"Shopping",
            "subcategory":"Books",
            "type":"Retail Goods"
        }
    ],
    "sg:phone":"+1 870 845 3447",
    "sg:postcode":"71852",
    "sg:province":"AR",
    "wof:name":"Literacy Book Store",
    "wof:placetype":"venue"
},
  "geometry": {"coordinates":[-93.847041,33.943326],"type":"Point"}
}