{
  "type": "Feature",
  "properties": {
    "addr:full":"805 Gipson Rd Harrison AR 72601",
    "addr:housenumber":"805",
    "addr:postcode":"72601",
    "addr:street":"Gipson Rd",
    "iso:country":"US",
    "sg:address":"805 Gipson Rd",
    "sg:city":"Harrison",
    "sg:classifiers":[
        {
            "category":"Building & Trades",
            "subcategory":"Construction",
            "type":"Services"
        }
    ],
    "sg:phone":"+1 870 741 5318",
    "sg:postcode":"72601",
    "sg:province":"AR",
    "sg:tags":[
        "house"
    ],
    "wof:name":"Rowbothum Construction LLC",
    "wof:placetype":"venue"
},
  "geometry": {"coordinates":[-93.14008200000001,36.259495],"type":"Point"}
}