{
  "type": "Feature",
  "properties": {
    "addr:full":"400 W Barraque St Pine Bluff AR 71601",
    "addr:housenumber":"400",
    "addr:postcode":"71601",
    "addr:street":"W Barraque St",
    "iso:country":"US",
    "sg:address":"400 W Barraque St",
    "sg:city":"Pine Bluff",
    "sg:classifiers":[
        {
            "category":"Retail",
            "subcategory":"Auto Repair",
            "type":"Services"
        }
    ],
    "sg:phone":"+1 870 536 2620",
    "sg:postcode":"71601",
    "sg:province":"AR",
    "sg:tags":[
        "repairing",
        "automobile"
    ],
    "wof:name":"United Auto Repair",
    "wof:placetype":"venue"
},
  "geometry": {"coordinates":[-92.00753899999999,34.229485],"type":"Point"}
}