{
  "type": "Feature",
  "properties": {
    "iso:country":"US",
    "sg:address":"22009 Indian Bluff Rd",
    "sg:city":"Garfield",
    "sg:classifiers":[
        {
            "category":"Professional",
            "type":"Services"
        }
    ],
    "sg:phone":"+1 479 656 3990",
    "sg:postcode":"72732",
    "sg:province":"AR",
    "wof:name":"Dagne E Phillips",
    "wof:placetype":"venue"
},
  "geometry": {"coordinates":[-93.888773,36.432019],"type":"Point"}
}