{
  "type": "Feature",
  "properties": {
    "addr:full":"806 Hendrix St Altus AR 72821",
    "addr:housenumber":"806",
    "addr:postcode":"72821",
    "addr:street":"Hendrix St",
    "iso:country":"US",
    "sg:address":"806 Hendrix St",
    "sg:city":"Altus",
    "sg:classifiers":[
        {
            "category":"Organizations",
            "subcategory":"Religious Organization",
            "type":"Services"
        }
    ],
    "sg:phone":"+1 479 468 4120",
    "sg:postcode":"72821",
    "sg:province":"AR",
    "wof:name":"Altus United Methodist Church",
    "wof:placetype":"venue"
},
  "geometry": {"coordinates":[-93.763515,35.440203],"type":"Point"}
}