{
  "type": "Feature",
  "properties": {
    "addr:full":"2609 Daulong Dr North Little Rock AR 72117",
    "addr:housenumber":"2609",
    "addr:postcode":"72117",
    "addr:street":"Daulong Dr",
    "iso:country":"US",
    "sg:address":"2609 Daulong Dr",
    "sg:city":"North Little Rock",
    "sg:classifiers":[
        {
            "category":"Shopping",
            "type":"Retail Goods"
        }
    ],
    "sg:phone":"+1 501 945 6969",
    "sg:postcode":"72117",
    "sg:province":"AR",
    "sg:tags":[
        "merchandise"
    ],
    "wof:name":"Caribbean Clear Purification",
    "wof:placetype":"venue"
},
  "geometry": {"coordinates":[-92.190754,34.779018],"type":"Point"}
}