{
  "type": "Feature",
  "properties": {
    "iso:country":"US",
    "sg:address":"265 Dave Creek Pkwy",
    "sg:city":"Fairfield Bay",
    "sg:classifiers":[
        {
            "category":"Health Services",
            "subcategory":"Nursing And Care Facility",
            "type":"Services"
        }
    ],
    "sg:phone":"+1 501 884 3210",
    "sg:postcode":"72088",
    "sg:province":"AR",
    "sg:tags":[
        "skilled"
    ],
    "sg:website":"www.good-sam.com",
    "wof:name":"Good Samaritan Indian Rock Vlg",
    "wof:placetype":"venue"
},
  "geometry": {"coordinates":[-92.262244,35.616051],"type":"Point"}
}