{
  "type": "Feature",
  "properties": {
    "addr:full":"2810 W Walnut St Rogers AR 72756",
    "addr:housenumber":"2810",
    "addr:postcode":"72756",
    "addr:street":"W Walnut St",
    "iso:country":"US",
    "sg:address":"2810 W Walnut St",
    "sg:city":"Rogers",
    "sg:classifiers":[
        {
            "category":"Cinema",
            "subcategory":"Movie Rental",
            "type":"Entertainment"
        }
    ],
    "sg:phone":"+1 479 246 9070",
    "sg:postcode":"72756",
    "sg:province":"AR",
    "sg:tags":[
        "game",
        "video"
    ],
    "wof:name":"Replay Entertainment Exchange",
    "wof:placetype":"venue"
},
  "geometry": {"coordinates":[-94.16172899999999,36.334288],"type":"Point"}
}