{
  "type": "Feature",
  "properties": {
    "iso:country":"US",
    "sg:address":"1900 Malvern Ave",
    "sg:city":"Hot Springs National",
    "sg:classifiers":[
        {
            "category":"Health Services",
            "subcategory":"Doctor",
            "type":"Services"
        }
    ],
    "sg:phone":"+1 501 623 6455",
    "sg:postcode":"71901",
    "sg:province":"AR",
    "sg:tags":[
        "medical"
    ],
    "wof:name":"Brenda N Powell MD Facog",
    "wof:placetype":"venue"
},
  "geometry": {"coordinates":[-93.033909,34.486804],"type":"Point"}
}