{
  "type": "Feature",
  "properties": {
    "addr:full":"605 W Lakeview Dr Springdale AR 72764",
    "addr:housenumber":"605",
    "addr:postcode":"72764",
    "addr:street":"W Lakeview Dr",
    "iso:country":"US",
    "sg:address":"605 W Lakeview Dr",
    "sg:city":"Springdale",
    "sg:classifiers":[
        {
            "category":"Professional",
            "subcategory":"Management & Consulting",
            "type":"Services"
        }
    ],
    "sg:phone":"+1 479 271 6900",
    "sg:postcode":"72764",
    "sg:province":"AR",
    "sg:tags":[
        "marketing",
        "consultant"
    ],
    "wof:name":"Quick Turn",
    "wof:placetype":"venue"
},
  "geometry": {"coordinates":[-94.141459,36.140029],"type":"Point"}
}