{
  "type": "Feature",
  "properties": {
    "addr:full":"140 Newark Cir Hot Springs AR 71901",
    "addr:housenumber":"140",
    "addr:postcode":"71901",
    "addr:street":"Newark Cir",
    "iso:country":"US",
    "sg:address":"140 Newark Cir",
    "sg:city":"Hot Springs",
    "sg:classifiers":[
        {
            "category":"Retail",
            "subcategory":"Repair Shop",
            "type":"Services"
        }
    ],
    "sg:phone":"+1 501 262 5190",
    "sg:postcode":"71901",
    "sg:province":"AR",
    "sg:tags":[
        "appliance"
    ],
    "wof:name":"George's Appliance Svc",
    "wof:placetype":"venue"
},
  "geometry": {"coordinates":[-92.94842,34.531213],"type":"Point"}
}