{
  "type": "Feature",
  "properties": {
    "addr:full":"16013 W Sardis Rd Bauxite AR 72011",
    "addr:housenumber":"16013",
    "addr:postcode":"72011",
    "addr:street":"W Sardis Rd",
    "iso:country":"US",
    "sg:address":"16013 W Sardis Rd",
    "sg:city":"Bauxite",
    "sg:classifiers":[
        {
            "category":"Retail",
            "subcategory":"Repair Shop",
            "type":"Services"
        }
    ],
    "sg:phone":"+1 501 557 5800",
    "sg:postcode":"72011",
    "sg:province":"AR",
    "sg:tags":[
        "crane"
    ],
    "sg:website":"www.manitowoccranes.com",
    "wof:name":"Manitowoc Re-Manufacturing Inc",
    "wof:placetype":"venue"
},
  "geometry": {"coordinates":[-92.455742,34.561235],"type":"Point"}
}