{
  "type": "Feature",
  "properties": {
    "addr:full":"1518 S Battery St Little Rock AR 72202",
    "addr:housenumber":"1518",
    "addr:postcode":"72202",
    "addr:street":"S Battery St",
    "iso:country":"US",
    "sg:address":"1518 S Battery St",
    "sg:city":"Little Rock",
    "sg:classifiers":[
        {
            "category":"Retail",
            "subcategory":"Funeral Services",
            "type":"Services"
        }
    ],
    "sg:phone":"+1 501 376 4800",
    "sg:postcode":"72202",
    "sg:province":"AR",
    "wof:name":"Premier Funeral Home",
    "wof:placetype":"venue"
},
  "geometry": {"coordinates":[-92.294296,34.735835],"type":"Point"}
}