{
  "type": "Feature",
  "properties": {
    "addr:full":"3112 US Hwy 82 W Crossett AR 71635",
    "addr:housenumber":"3112",
    "addr:postcode":"71635",
    "addr:street":"Us Hwy 82 W Crossett",
    "iso:country":"US",
    "sg:address":"3112 US Hwy 82 W",
    "sg:city":"Crossett",
    "sg:classifiers":[
        {
            "category":"Food & Beverages",
            "subcategory":"Meat & Fish",
            "type":"Retail Goods"
        }
    ],
    "sg:phone":"+1 870 364 8431",
    "sg:postcode":"71635",
    "sg:province":"AR",
    "sg:tags":[
        "seafood"
    ],
    "wof:name":"Don's Fish Market",
    "wof:placetype":"venue"
},
  "geometry": {"coordinates":[-92.04816599999999,33.142567],"type":"Point"}
}