{
  "type": "Feature",
  "properties": {
    "addr:full":"309 N Dillard St Monticello AR 71655",
    "addr:housenumber":"309",
    "addr:postcode":"71655",
    "addr:street":"N Dillard St",
    "iso:country":"US",
    "sg:address":"309 N Dillard St",
    "sg:city":"Monticello",
    "sg:classifiers":[
        {
            "category":"Retail",
            "subcategory":"Funeral Services",
            "type":"Services"
        }
    ],
    "sg:phone":"+1 870 367 3551",
    "sg:postcode":"71655",
    "sg:province":"AR",
    "sg:tags":[
        "life",
        "carrier",
        "insurance"
    ],
    "wof:name":"Henderson Funeral Home Inc",
    "wof:placetype":"venue"
},
  "geometry": {"coordinates":[-91.78136000000001,33.630672],"type":"Point"}
}