{
  "type": "Feature",
  "properties": {
    "iso:country":"US",
    "sg:address":"129 Locust Ave",
    "sg:city":"Trumann",
    "sg:classifiers":[
        {
            "category":"Organizations",
            "subcategory":"Religious Organization",
            "type":"Services"
        }
    ],
    "sg:phone":"+1 870 483 0107",
    "sg:postcode":"72472",
    "sg:province":"AR",
    "sg:tags":[
        "church"
    ],
    "wof:name":"Church Of Lord Jesus Christ",
    "wof:placetype":"venue"
},
  "geometry": {"coordinates":[-90.50926200000001,35.672078],"type":"Point"}
}