{
  "type": "Feature",
  "properties": {
    "addr:full":"1415 W 41st St N Little Rock AR 72118",
    "addr:housenumber":"1415",
    "addr:postcode":"72118",
    "addr:street":"W 41St St N",
    "iso:country":"US",
    "sg:address":"1415 W 41st St",
    "sg:city":"N Little Rock",
    "sg:classifiers":[
        {
            "category":"Organizations",
            "subcategory":"Religious Organization",
            "type":"Services"
        }
    ],
    "sg:phone":"+1 501 753 6684",
    "sg:postcode":"72118",
    "sg:province":"AR",
    "sg:tags":[
        "church"
    ],
    "wof:name":"Church Of God Of Central Ar",
    "wof:placetype":"venue"
},
  "geometry": {"coordinates":[-92.28185000000001,34.792996],"type":"Point"}
}