{
  "type": "Feature",
  "properties": {
    "iso:country":"US",
    "sg:address":"700 Normandy St",
    "sg:city":"Marked Tree",
    "sg:classifiers":[
        {
            "category":"Education",
            "subcategory":"School",
            "type":"Public Place"
        }
    ],
    "sg:phone":"+1 870 358 2214",
    "sg:postcode":"72365",
    "sg:province":"AR",
    "wof:name":"Marked Tree Elementary School",
    "wof:placetype":"venue"
},
  "geometry": {"coordinates":[-90.41515800000001,35.522873],"type":"Point"}
}