{
  "type": "Feature",
  "properties": {
    "iso:country":"US",
    "sg:address":"306 N Forrest St",
    "sg:city":"Forrest City",
    "sg:classifiers":[
        {
            "category":"Professional",
            "subcategory":"Lawyer & Legal Services",
            "type":"Services"
        }
    ],
    "sg:phone":"+1 870 633 2538",
    "sg:postcode":"72335",
    "sg:province":"AR",
    "sg:tags":[
        "attorney"
    ],
    "wof:name":"Bland Law Offices",
    "wof:placetype":"venue"
},
  "geometry": {"coordinates":[-90.78413999999999,35.01245],"type":"Point"}
}