{
  "type": "Feature",
  "properties": {
    "addr:full":"102 Freeman Ct Berryville AR 72616",
    "addr:housenumber":"102",
    "addr:postcode":"72616",
    "addr:street":"Freeman Ct",
    "iso:country":"US",
    "sg:address":"102 Freeman Ct",
    "sg:city":"Berryville",
    "sg:classifiers":[
        {
            "category":"Autos & Motor Vehicles",
            "subcategory":"Automobile Sales",
            "type":"Retail Goods"
        }
    ],
    "sg:phone":"+1 870 423 4900",
    "sg:postcode":"72616",
    "sg:province":"AR",
    "sg:tags":[
        "used"
    ],
    "wof:name":"Main Street Motor Co",
    "wof:placetype":"venue"
},
  "geometry": {"coordinates":[-93.570153,36.369472],"type":"Point"}
}