{
  "type": "Feature",
  "properties": {
    "iso:country":"US",
    "sg:address":"211 N 23rd St",
    "sg:city":"Paragould",
    "sg:classifiers":[
        {
            "category":"Health Services",
            "subcategory":"Hospital",
            "type":"Services"
        }
    ],
    "sg:phone":"+1 870 335 9483",
    "sg:postcode":"72450",
    "sg:province":"AR",
    "sg:tags":[
        "mental"
    ],
    "sg:website":"www.familiesinc.net",
    "wof:name":"Families Inc",
    "wof:placetype":"venue"
},
  "geometry": {"coordinates":[-90.515014,36.060646],"type":"Point"}
}