{
  "type": "Feature",
  "properties": {
    "addr:full":"1445 Coon Creek Ln Batesville AR 72501",
    "addr:housenumber":"1445",
    "addr:postcode":"72501",
    "addr:street":"Coon Creek Ln",
    "iso:country":"US",
    "sg:address":"1445 Coon Creek Ln",
    "sg:city":"Batesville",
    "sg:classifiers":[
        {
            "category":"Building & Trades",
            "subcategory":"Construction",
            "type":"Services"
        }
    ],
    "sg:phone":"+1 870 793 2994",
    "sg:postcode":"72501",
    "sg:province":"AR",
    "sg:tags":[
        "house"
    ],
    "wof:name":"Dale Barnett Construction",
    "wof:placetype":"venue"
},
  "geometry": {"coordinates":[-91.635036,35.881368],"type":"Point"}
}