{
  "type": "Feature",
  "properties": {
    "addr:full":"21400 Chicot Rd Mabelvale AR 72103",
    "addr:housenumber":"21400",
    "addr:postcode":"72103",
    "addr:street":"Chicot Rd",
    "iso:country":"US",
    "sg:address":"21400 Chicot Rd",
    "sg:city":"Mabelvale",
    "sg:classifiers":[
        {
            "category":"Manufacturing",
            "subcategory":"Buildings",
            "type":"Manufacturing & Wholesale Goods"
        },
        {
            "category":"Home & Garden",
            "subcategory":"Building Materials",
            "type":"Retail Goods"
        },
        {
            "category":"Professional",
            "subcategory":"Printing & Photocopies",
            "type":"Services"
        },
        {
            "category":"Building & Trades",
            "subcategory":"Locksmith",
            "type":"Services"
        }
    ],
    "sg:phone":"+1 501 261 7765",
    "sg:postcode":"72103",
    "sg:province":"AR",
    "sg:tags":[
        "repairing",
        "repair",
        "door",
        "garage",
        "opener",
        "door-overhead",
        "type",
        "garages-building"
    ],
    "sg:website":"http://www.affordablegaragedoorservice.net",
    "wof:name":"Affordable Garage Door Service",
    "wof:placetype":"venue"
},
  "geometry": {"coordinates":[-92.369652,34.554642],"type":"Point"}
}