{
  "type": "Feature",
  "properties": {
    "iso:country":"US",
    "sg:address":"709 SW A St",
    "sg:city":"Bentonville",
    "sg:classifiers":[
        {
            "category":"Shopping",
            "subcategory":"Used Merchandise",
            "type":"Retail Goods"
        }
    ],
    "sg:phone":"+1 479 464 8492",
    "sg:postcode":"72712",
    "sg:province":"AR",
    "wof:name":"Little Darlings",
    "wof:placetype":"venue"
},
  "geometry": {"coordinates":[-94.210258,36.364291],"type":"Point"}
}