{
  "type": "Feature",
  "properties": {
    "iso:country":"US",
    "sg:address":"1440 Hwy 62-412",
    "sg:city":"Highland",
    "sg:classifiers":[
        {
            "category":"Real Estate",
            "subcategory":"Real Estate Agent",
            "type":"Services"
        }
    ],
    "sg:phone":"+1 870 856 2212",
    "sg:postcode":"72542",
    "sg:province":"AR",
    "wof:name":"Century 21",
    "wof:placetype":"venue"
},
  "geometry": {"coordinates":[-91.54868999999999,36.26004],"type":"Point"}
}