{
  "type": "Feature",
  "properties": {
    "iso:country":"US",
    "sg:address":"18020 Cantrell Rd",
    "sg:city":"Little Rock",
    "sg:classifiers":[
        {
            "category":"Organizations",
            "subcategory":"Religious Organization",
            "type":"Services"
        }
    ],
    "sg:phone":"+1 501 868 4719",
    "sg:postcode":"72223",
    "sg:province":"AR",
    "wof:name":"Immanuel Baptist West",
    "wof:placetype":"venue"
},
  "geometry": {"coordinates":[-92.471341,34.808927],"type":"Point"}
}