{
  "type": "Feature",
  "properties": {
    "addr:full":"11712 Arch St Little Rock AR 72206",
    "addr:housenumber":"11712",
    "addr:postcode":"72206",
    "addr:street":"Arch St",
    "iso:country":"US",
    "sg:address":"11712 Arch St",
    "sg:city":"Little Rock",
    "sg:classifiers":[
        {
            "category":"Building & Trades",
            "subcategory":"Construction",
            "type":"Services"
        }
    ],
    "sg:phone":"+1 501 888 2132",
    "sg:postcode":"72206",
    "sg:province":"AR",
    "sg:tags":[
        "specializing",
        "residential",
        "contractor",
        "commercial",
        "rem"
    ],
    "wof:name":"Bradford Construction Entps",
    "wof:placetype":"venue"
},
  "geometry": {"coordinates":[-92.309915,34.639815],"type":"Point"}
}