{
  "type": "Feature",
  "properties": {
    "addr:full":"2 Sonata Trl Little Rock AR 72205",
    "addr:housenumber":"2",
    "addr:postcode":"72205",
    "addr:street":"Sonata Trl",
    "iso:country":"US",
    "sg:address":"2 Sonata Trl",
    "sg:city":"Little Rock",
    "sg:classifiers":[
        {
            "category":"Shopping",
            "subcategory":"Pharmacy",
            "type":"Retail Goods"
        }
    ],
    "sg:phone":"+1 501 562 6657",
    "sg:postcode":"72205",
    "sg:province":"AR",
    "wof:name":"Pharmerica Inc",
    "wof:placetype":"venue"
},
  "geometry": {"coordinates":[-92.366884,34.760264],"type":"Point"}
}