{
  "type": "Feature",
  "properties": {
    "iso:country":"US",
    "sg:address":"1100 E Roosevelt Rd",
    "sg:city":"Little Rock",
    "sg:classifiers":[
        {
            "category":"Professional",
            "subcategory":"Accounting & Tax Preparation",
            "type":"Services"
        }
    ],
    "sg:phone":"+1 501 375 2121",
    "sg:postcode":"72206",
    "sg:province":"AR",
    "sg:tags":[
        "return",
        "filing"
    ],
    "wof:name":"Jackson Hewitt Tax Svc",
    "wof:placetype":"venue"
},
  "geometry": {"coordinates":[-92.258922,34.723028],"type":"Point"}
}