{
  "type": "Feature",
  "properties": {
    "iso:country":"US",
    "sg:address":"259 Carmichael Rd",
    "sg:city":"Searcy",
    "sg:classifiers":[
        {
            "category":"Building & Trades",
            "subcategory":"Construction",
            "type":"Services"
        }
    ],
    "sg:phone":"+1 501 230 5732",
    "sg:postcode":"72143",
    "sg:province":"AR",
    "sg:tags":[
        "residential"
    ],
    "wof:name":"Joseph Bradford",
    "wof:placetype":"venue"
},
  "geometry": {"coordinates":[-91.918137,35.282039],"type":"Point"}
}