{
  "type": "Feature",
  "properties": {
    "addr:full":"10001 Lile Dr Little Rock AR 72205",
    "addr:housenumber":"10001",
    "addr:postcode":"72205",
    "addr:street":"Lile Dr",
    "iso:country":"US",
    "sg:address":"10001 Lile Dr",
    "sg:city":"Little Rock",
    "sg:classifiers":[
        {
            "category":"Health Services",
            "subcategory":"Doctor",
            "type":"Services"
        }
    ],
    "sg:phone":"+1 501 227 8000",
    "sg:postcode":"72205",
    "sg:province":"AR",
    "sg:tags":[
        "clinic"
    ],
    "sg:website":"www.lrdc.com",
    "wof:name":"Little Rock Diagnostic Clinic",
    "wof:placetype":"venue"
},
  "geometry": {"coordinates":[-92.384877,34.746218],"type":"Point"}
}