{
  "type": "Feature",
  "properties": {
    "iso:country":"US",
    "sg:address":"408 W Central Ave",
    "sg:city":"Harrison",
    "sg:classifiers":[
        {
            "category":"Health Services",
            "subcategory":"Health Practitioner",
            "type":"Services"
        }
    ],
    "sg:phone":"+1 870 743 4438",
    "sg:postcode":"72601",
    "sg:province":"AR",
    "wof:name":"Harrison Physical Therapy Inc",
    "wof:placetype":"venue"
},
  "geometry": {"coordinates":[-93.111623,36.228569],"type":"Point"}
}