{
  "type": "Feature",
  "properties": {
    "addr:full":"1800 S Division St Blytheville AR 72315",
    "addr:housenumber":"1800",
    "addr:postcode":"72315",
    "addr:street":"S Division St",
    "iso:country":"US",
    "sg:address":"1800 S Division St",
    "sg:city":"Blytheville",
    "sg:classifiers":[
        {
            "category":"Autos & Motor Vehicles",
            "subcategory":"Automobile Sales",
            "type":"Retail Goods"
        },
        {
            "category":"Retail",
            "subcategory":"Auto Repair",
            "type":"Services"
        }
    ],
    "sg:phone":"+1 870 763 2560",
    "sg:postcode":"72315",
    "sg:province":"AR",
    "sg:tags":[
        "dealers-used",
        "car",
        "used",
        "cars-wholesale",
        "diagnostic"
    ],
    "sg:website":"http://tristatemotorcompany.net",
    "wof:name":"Tri State Motors Co",
    "wof:placetype":"venue"
},
  "geometry": {"coordinates":[-89.918671,35.905239],"type":"Point"}
}