{
  "type": "Feature",
  "properties": {
    "addr:full":"2898 Hwy 46 S Sheridan AR 72150",
    "addr:housenumber":"2898",
    "addr:postcode":"72150",
    "addr:street":"Hwy 46 S",
    "iso:country":"US",
    "sg:address":"2898 Hwy 46 S",
    "sg:city":"Sheridan",
    "sg:classifiers":[
        {
            "category":"Farming",
            "subcategory":"Fish & Marine Products",
            "type":"Manufacturing & Wholesale Goods"
        }
    ],
    "sg:phone":"+1 870 917 2085",
    "sg:postcode":"72150",
    "sg:province":"AR",
    "sg:tags":[
        "management"
    ],
    "wof:name":"Knighten Pat AR Game Fish Comm",
    "wof:placetype":"venue"
},
  "geometry": {"coordinates":[-92.43931499999999,34.277458],"type":"Point"}
}