{
  "type": "Feature",
  "properties": {
    "iso:country":"US",
    "sg:address":"2898 Hwy 46 S",
    "sg:city":"Sheridan",
    "sg:classifiers":[
        {
            "category":"Farming",
            "subcategory":"Fish & Marine Products",
            "type":"Manufacturing & Wholesale Goods"
        }
    ],
    "sg:phone":"+1 870 917 2085",
    "sg:postcode":"72150",
    "sg:province":"AR",
    "sg:tags":[
        "management"
    ],
    "wof:name":"Knighten Pat AR Game Fish Comm",
    "wof:placetype":"venue"
},
  "geometry": {"coordinates":[-92.439315,34.277458],"type":"Point"}
}