{
  "type": "Feature",
  "properties": {
    "iso:country":"US",
    "sg:address":"350 Beavers Rd",
    "sg:city":"Lake Village",
    "sg:classifiers":[
        {
            "category":"Building & Trades",
            "subcategory":"Plumbing",
            "type":"Services"
        }
    ],
    "sg:phone":"+1 870 265 5875",
    "sg:postcode":"71653",
    "sg:province":"AR",
    "sg:tags":[
        "plumbing",
        "contractor"
    ],
    "wof:name":"DMK Plumbing & Electrical",
    "wof:placetype":"venue"
},
  "geometry": {"coordinates":[-91.390795,33.303407],"type":"Point"}
}