{
  "type": "Feature",
  "properties": {
    "iso:country":"US",
    "sg:address":"1100 S 28th St",
    "sg:city":"Van Buren",
    "sg:classifiers":[
        {
            "category":"Freight",
            "type":"Transportation"
        }
    ],
    "sg:phone":"+1 479 471 9900",
    "sg:postcode":"72956",
    "sg:province":"AR",
    "sg:tags":[
        "trucking"
    ],
    "wof:name":"G T Transportation Svc",
    "wof:placetype":"venue"
},
  "geometry": {"coordinates":[-94.329635,35.423076],"type":"Point"}
}