{
  "type": "Feature",
  "properties": {
    "iso:country":"US",
    "sg:address":"204 Mississippi St S",
    "sg:city":"Wynne",
    "sg:classifiers":[
        {
            "category":"Health Services",
            "subcategory":"Doctor",
            "type":"Services"
        }
    ],
    "sg:phone":"+1 870 238 3133",
    "sg:postcode":"72396",
    "sg:province":"AR",
    "sg:tags":[
        "dentist"
    ],
    "wof:name":"W Sneed Shaw DDS",
    "wof:placetype":"venue"
},
  "geometry": {"coordinates":[-90.785427,35.222515],"type":"Point"}
}