{
  "type": "Feature",
  "properties": {
    "iso:country":"US",
    "sg:address":"189 Idlewood Dr",
    "sg:city":"Lakeview",
    "sg:classifiers":[
        {
            "category":"Shopping",
            "subcategory":"Bicycles & Sporting Goods",
            "type":"Retail Goods"
        }
    ],
    "sg:phone":"+1 870 425 5340",
    "sg:postcode":"72642",
    "sg:province":"AR",
    "wof:name":"Performance Tennis",
    "wof:placetype":"venue"
},
  "geometry": {"coordinates":[-92.533666,36.38552],"type":"Point"}
}