{
  "type": "Feature",
  "properties": {
    "iso:country":"US",
    "sg:address":"620 E Parkway Dr",
    "sg:city":"Russellville",
    "sg:classifiers":[
        {
            "category":"Personal",
            "type":"Services"
        }
    ],
    "sg:phone":"+1 479 968 5683",
    "sg:postcode":"72801",
    "sg:province":"AR",
    "sg:tags":[
        "consultant",
        "planning",
        "wedding"
    ],
    "wof:name":"Celebrations Of Love",
    "wof:placetype":"venue"
},
  "geometry": {"coordinates":[-93.13677,35.28162],"type":"Point"}
}