{
  "type": "Feature",
  "properties": {
    "addr:full":"623 N Walnut St Harrison AR 72601",
    "addr:housenumber":"623",
    "addr:postcode":"72601",
    "addr:street":"N Walnut St",
    "iso:country":"US",
    "sg:address":"623 N Walnut St",
    "sg:city":"Harrison",
    "sg:classifiers":[
        {
            "category":"Social Services",
            "type":"Services"
        }
    ],
    "sg:phone":"+1 870 743 6225",
    "sg:postcode":"72601",
    "sg:province":"AR",
    "sg:tags":[
        "counselor",
        "marriage",
        "family"
    ],
    "wof:name":"Family Psychological Ctr Inc",
    "wof:placetype":"venue"
},
  "geometry": {"coordinates":[-93.105778,36.236381],"type":"Point"}
}