{
  "type": "Feature",
  "properties": {
    "iso:country":"US",
    "sg:address":"7 Belair",
    "sg:city":"N Little Rock",
    "sg:classifiers":[
        {
            "category":"Professional",
            "subcategory":"Business Services",
            "type":"Services"
        }
    ],
    "sg:phone":"+1 501 753 4252",
    "sg:postcode":"72116",
    "sg:province":"AR",
    "sg:tags":[
        "inventory"
    ],
    "wof:name":"Midwest Inventory Svc",
    "wof:placetype":"venue"
},
  "geometry": {"coordinates":[-92.238865,34.784475],"type":"Point"}
}