{
  "type": "Feature",
  "properties": {
    "iso:country":"US",
    "sg:address":"40 Sugar Creek Center",
    "sg:city":"Bella Vista",
    "sg:classifiers":[
        {
            "category":"Sports & Exercise",
            "subcategory":"Gym",
            "type":"Entertainment"
        }
    ],
    "sg:phone":"+1 479 855 9800",
    "sg:postcode":"72714",
    "sg:province":"AR",
    "sg:tags":[
        "fitness",
        "physical",
        "facility"
    ],
    "wof:name":"Curves For Women",
    "wof:placetype":"venue"
},
  "geometry": {"coordinates":[-94.237027,36.439478],"type":"Point"}
}