{
  "type": "Feature",
  "properties": {
    "iso:country":"US",
    "sg:address":"14910 Arch St",
    "sg:city":"Little Rock",
    "sg:classifiers":[
        {
            "category":"Banks & Credit Unions",
            "subcategory":"Bank",
            "type":"Services"
        }
    ],
    "sg:phone":"+1 501 888 6700",
    "sg:postcode":"72206",
    "sg:province":"AR",
    "sg:tags":[
        "loan"
    ],
    "wof:name":"All Season's Pawn & Loan",
    "wof:placetype":"venue"
},
  "geometry": {"coordinates":[-92.317441,34.613922],"type":"Point"}
}