{
  "type": "Feature",
  "properties": {
    "addr:full":"400 S Mock St Prairie Grove AR 72753",
    "addr:housenumber":"400",
    "addr:postcode":"72753",
    "addr:street":"S Mock St",
    "iso:country":"US",
    "sg:address":"400 S Mock St",
    "sg:city":"Prairie Grove",
    "sg:phone":"+1 479 267 5656",
    "sg:postcode":"72753",
    "sg:province":"AR",
    "sg:tags":[
        "food",
        "equipment",
        "processing"
    ],
    "wof:name":"Batchmaster",
    "wof:placetype":"venue"
},
  "geometry": {"coordinates":[-94.31840200000001,35.971548],"type":"Point"}
}