{
  "type": "Feature",
  "properties": {
    "iso:country":"US",
    "sg:address":"1904 Hickory Dr",
    "sg:city":"Bryant",
    "sg:classifiers":[
        {
            "category":"Organizations",
            "subcategory":"Non-profit Organization",
            "type":"Services"
        }
    ],
    "sg:phone":"+1 501 847 3269",
    "sg:postcode":"72019",
    "sg:province":"AR",
    "sg:tags":[
        "fund",
        "raising"
    ],
    "wof:name":"Jbt Marketing, Inc",
    "wof:placetype":"venue"
},
  "geometry": {"coordinates":[-92.506314,34.638193],"type":"Point"}
}