{
  "type": "Feature",
  "properties": {
    "iso:country":"US",
    "sg:address":"260 Lake Hamilton Dr",
    "sg:city":"Hot Springs",
    "sg:classifiers":[
        {
            "category":"Travel",
            "subcategory":"Hotels & Motels",
            "type":"Entertainment"
        }
    ],
    "sg:phone":"+1 501 525 1362",
    "sg:postcode":"71913",
    "sg:province":"AR",
    "sg:tags":[
        "resort"
    ],
    "wof:name":"Willow Beach Motel & Cottages",
    "wof:placetype":"venue"
},
  "geometry": {"coordinates":[-93.081733,34.446131],"type":"Point"}
}