{
  "type": "Feature",
  "properties": {
    "iso:country":"US",
    "sg:address":"201 1/2 Oak St",
    "sg:city":"Crossett",
    "sg:classifiers":[
        {
            "category":"Personal",
            "subcategory":"Beauty Salon",
            "type":"Services"
        }
    ],
    "sg:phone":"+1 870 364 2020",
    "sg:postcode":"71635",
    "sg:province":"AR",
    "wof:name":"Battaglia Sara",
    "wof:placetype":"venue"
},
  "geometry": {"coordinates":[-91.95880099999999,33.13393],"type":"Point"}
}