{
  "type": "Feature",
  "properties": {
    "addr:full":"617 Walnut St Helena AR 72342",
    "addr:housenumber":"617",
    "addr:postcode":"72342",
    "addr:street":"Walnut St",
    "iso:country":"US",
    "sg:address":"617 Walnut St",
    "sg:city":"Helena",
    "sg:classifiers":[
        {
            "category":"Government",
            "subcategory":"Office",
            "type":"Public Place"
        }
    ],
    "sg:phone":"+1 870 338 6651",
    "sg:postcode":"72342",
    "sg:province":"AR",
    "sg:tags":[
        "federal"
    ],
    "wof:name":"US Consolidated Farm Svc Agcy",
    "wof:placetype":"venue"
},
  "geometry": {"coordinates":[-90.587436,34.528968],"type":"Point"}
}