{
  "type": "Feature",
  "properties": {
    "iso:country":"US",
    "sg:address":"477 N Monitor Rd",
    "sg:city":"Springdale",
    "sg:classifiers":[
        {
            "category":"Freight",
            "type":"Transportation"
        }
    ],
    "sg:phone":"+1 479 872 0639",
    "sg:postcode":"72764",
    "sg:province":"AR",
    "sg:tags":[
        "operator",
        "trucking"
    ],
    "wof:name":"Smith Iron Inc",
    "wof:placetype":"venue"
},
  "geometry": {"coordinates":[-94.102688,36.190254],"type":"Point"}
}