{
  "type": "Feature",
  "properties": {
    "iso:country":"US",
    "sg:address":"720 S Beech St",
    "sg:city":"Pine Bluff",
    "sg:classifiers":[
        {
            "category":"Insurance",
            "subcategory":"Insurance Agent",
            "type":"Services"
        }
    ],
    "sg:phone":"+1 870 534 0223",
    "sg:postcode":"71601",
    "sg:province":"AR",
    "wof:name":"Met Life",
    "wof:placetype":"venue"
},
  "geometry": {"coordinates":[-92.009619,34.221807],"type":"Point"}
}