{
  "type": "Feature",
  "properties": {
    "iso:country":"US",
    "sg:address":"140 Ashley Road 909",
    "sg:city":"Montrose",
    "sg:classifiers":[
        {
            "category":"Autos & Motor Vehicles",
            "subcategory":"Motorcycle Sales",
            "type":"Retail Goods"
        }
    ],
    "sg:phone":"+1 870 853 4874",
    "sg:postcode":"71658",
    "sg:province":"AR",
    "sg:tags":[
        "scooter"
    ],
    "wof:name":"Southern Iron Cycles",
    "wof:placetype":"venue"
},
  "geometry": {"coordinates":[-91.62172200000001,33.292268],"type":"Point"}
}