{
  "type": "Feature",
  "properties": {
    "iso:country":"US",
    "sg:address":"300 W Main St",
    "sg:city":"El Dorado",
    "sg:classifiers":[
        {
            "category":"Organizations",
            "subcategory":"Religious Organization",
            "type":"Services"
        }
    ],
    "sg:phone":"+1 870 863 4330",
    "sg:postcode":"71730",
    "sg:province":"AR",
    "sg:tags":[
        "church",
        "baptist",
        "care",
        "center",
        "child"
    ],
    "wof:name":"First Baptist Day Care Center",
    "wof:placetype":"venue"
},
  "geometry": {"coordinates":[-92.667921,33.211875],"type":"Point"}
}