{
  "type": "Feature",
  "properties": {
    "iso:country":"US",
    "sg:address":"301 W 7th St",
    "sg:city":"North Little Rock",
    "sg:classifiers":[
        {
            "category":"Health Services",
            "subcategory":"Clinic",
            "type":"Services"
        }
    ],
    "sg:phone":"+1 501 812 0077",
    "sg:postcode":"72114",
    "sg:province":"AR",
    "sg:tags":[
        "home",
        "care"
    ],
    "wof:name":"Arkansas HM Care For Snors LLC",
    "wof:placetype":"venue"
},
  "geometry": {"coordinates":[-92.27112099999999,34.760089],"type":"Point"}
}