{
  "type": "Feature",
  "properties": {
    "iso:country":"US",
    "sg:address":"615 S Cedar St",
    "sg:city":"Pine Bluff",
    "sg:classifiers":[
        {
            "category":"Organizations",
            "subcategory":"Religious Organization",
            "type":"Services"
        }
    ],
    "sg:phone":"+1 870 536 2036",
    "sg:postcode":"71603",
    "sg:province":"AR",
    "sg:tags":[
        "church"
    ],
    "wof:name":"Redeemed Temple Chr-God In",
    "wof:placetype":"venue"
},
  "geometry": {"coordinates":[-92.019571,34.222855],"type":"Point"}
}