{
  "type": "Feature",
  "properties": {
    "iso:country":"US",
    "sg:address":"685 Hwy 65 N",
    "sg:city":"Greenbrier",
    "sg:classifiers":[
        {
            "category":"Building & Trades",
            "subcategory":"Electrical",
            "type":"Services"
        }
    ],
    "sg:phone":"+1 501 679 7410",
    "sg:postcode":"72058",
    "sg:province":"AR",
    "sg:tags":[
        "electrical",
        "contractor"
    ],
    "wof:name":"H & H Electric Arkansas LLC",
    "wof:placetype":"venue"
},
  "geometry": {"coordinates":[-92.392105,35.190528],"type":"Point"}
}