{
  "type": "Feature",
  "properties": {
    "iso:country":"US",
    "sg:address":"1673 N College Ave",
    "sg:city":"Fayetteville",
    "sg:classifiers":[
        {
            "category":"Bars & Pubs",
            "type":"Food & Drink"
        },
        {
            "category":"Restaurant",
            "type":"Food & Drink"
        },
        {
            "category":"Bars & Pubs",
            "subcategory":"Lounge",
            "type":"Food & Drink"
        }
    ],
    "sg:phone":"+1 479 935 4445",
    "sg:postcode":"72703",
    "sg:province":"AR",
    "sg:tags":[
        "grill",
        "cocktail"
    ],
    "wof:name":"Cheers",
    "wof:placetype":"venue"
},
  "geometry": {"coordinates":[-94.15568,36.083973],"type":"Point"}
}