{
  "type": "Feature",
  "properties": {
    "addr:full":"830 E Robinson Ave Springdale AR 72764",
    "addr:housenumber":"830",
    "addr:postcode":"72764",
    "addr:street":"E Robinson Ave",
    "iso:country":"US",
    "sg:address":"830 E Robinson Ave",
    "sg:city":"Springdale",
    "sg:classifiers":[
        {
            "category":"Shopping",
            "subcategory":"Computers & Home Electronics",
            "type":"Retail Goods"
        }
    ],
    "sg:phone":"+1 479 756 9600",
    "sg:postcode":"72764",
    "sg:province":"AR",
    "sg:tags":[
        "equipment",
        "dealer"
    ],
    "wof:name":"Corporate Express",
    "wof:placetype":"venue"
},
  "geometry": {"coordinates":[-94.11994199999999,36.167026],"type":"Point"}
}