{
  "type": "Feature",
  "properties": {
    "addr:full":"500 Main Higginson AR 72068",
    "addr:housenumber":"500",
    "addr:postcode":"72068",
    "addr:street":"Main Higginson",
    "iso:country":"US",
    "sg:address":"500 Main",
    "sg:city":"Higginson",
    "sg:classifiers":[
        {
            "category":"Organizations",
            "subcategory":"Religious Organization",
            "type":"Services"
        }
    ],
    "sg:phone":"+1 501 742 5269",
    "sg:postcode":"72068",
    "sg:province":"AR",
    "sg:tags":[
        "church"
    ],
    "wof:name":"Higginson Assembly Of God",
    "wof:placetype":"venue"
},
  "geometry": {"coordinates":[-91.71032,35.199677],"type":"Point"}
}