{
  "type": "Feature",
  "properties": {
    "iso:country":"US",
    "sg:address":"1301 S West Ave",
    "sg:city":"Fayetteville",
    "sg:classifiers":[
        {
            "category":"Social Services",
            "type":"Services"
        }
    ],
    "sg:phone":"+1 479 444 7047",
    "sg:postcode":"72701",
    "sg:province":"AR",
    "sg:tags":[
        "counseling"
    ],
    "wof:name":"Paula Ellington Counseling",
    "wof:placetype":"venue"
},
  "geometry": {"coordinates":[-94.16586599999999,36.048361],"type":"Point"}
}