{
  "type": "Feature",
  "properties": {
    "iso:country":"US",
    "sg:address":"51 N Grandfield Rd",
    "sg:city":"Newhope",
    "sg:classifiers":[
        {
            "category":"Building & Trades",
            "subcategory":"Cleaning & Sanitation",
            "type":"Services"
        }
    ],
    "sg:phone":"+1 870 398 5355",
    "sg:postcode":"71959",
    "sg:province":"AR",
    "sg:tags":[
        "janitorial"
    ],
    "wof:name":"Debbie Whisenhunt",
    "wof:placetype":"venue"
},
  "geometry": {"coordinates":[-93.913296,34.221939],"type":"Point"}
}