{
  "type": "Feature",
  "properties": {
    "iso:country":"US",
    "sg:address":"1111 Mallard Pl",
    "sg:city":"Bentonville",
    "sg:classifiers":[
        {
            "category":"Building & Trades",
            "subcategory":"Landscaping Services",
            "type":"Services"
        }
    ],
    "sg:phone":"+1 479 271 0867",
    "sg:postcode":"72712",
    "sg:province":"AR",
    "sg:tags":[
        "landscape"
    ],
    "wof:name":"Rodden Inc",
    "wof:placetype":"venue"
},
  "geometry": {"coordinates":[-94.19558000000001,36.353974],"type":"Point"}
}