{
  "type": "Feature",
  "properties": {
    "addr:full":"123 N Pine St Magnolia AR 71753",
    "addr:housenumber":"123",
    "addr:postcode":"71753",
    "addr:street":"N Pine St",
    "iso:country":"US",
    "sg:address":"123 N Pine St",
    "sg:city":"Magnolia",
    "sg:classifiers":[
        {
            "category":"Retail",
            "subcategory":"Laundry & Dry Cleaning",
            "type":"Services"
        }
    ],
    "sg:phone":"+1 870 234 2566",
    "sg:postcode":"71753",
    "sg:province":"AR",
    "wof:name":"Sno-White Laundry & Cleaners",
    "wof:placetype":"venue"
},
  "geometry": {"coordinates":[-93.238302,33.267985],"type":"Point"}
}