{
  "type": "Feature",
  "properties": {
    "iso:country":"US",
    "sg:address":"11015 Arcade Dr",
    "sg:city":"Little Rock",
    "sg:classifiers":[
        {
            "category":"Professional",
            "subcategory":"Accounting & Tax Preparation",
            "type":"Services"
        }
    ],
    "sg:phone":"+1 501 217 0141",
    "sg:postcode":"72212",
    "sg:province":"AR",
    "sg:tags":[
        "accountant"
    ],
    "wof:name":"David Crain CPA LTD",
    "wof:placetype":"venue"
},
  "geometry": {"coordinates":[-92.395992,34.769312],"type":"Point"}
}