{
  "type": "Feature",
  "properties": {
    "iso:country":"US",
    "sg:address":"6140 Moro Bay Hwy",
    "sg:city":"El Dorado",
    "sg:classifiers":[
        {
            "category":"Food & Beverages",
            "subcategory":"Groceries & Convenience Stores",
            "type":"Retail Goods"
        }
    ],
    "sg:phone":"+1 870 862 9495",
    "sg:postcode":"71730",
    "sg:province":"AR",
    "sg:tags":[
        "grocer"
    ],
    "wof:name":"Brenda's One Stop",
    "wof:placetype":"venue"
},
  "geometry": {"coordinates":[-92.531124,33.23437],"type":"Point"}
}