{
  "type": "Feature",
  "properties": {
    "iso:country":"US",
    "sg:address":"501 Fairway Cir",
    "sg:city":"Springdale",
    "sg:classifiers":[
        {
            "category":"Shopping",
            "type":"Retail Goods"
        },
        {
            "category":"Manufacturing",
            "subcategory":"Paper Products",
            "type":"Manufacturing & Wholesale Goods"
        }
    ],
    "sg:phone":"+1 479 872 2445",
    "sg:postcode":"72764",
    "sg:province":"AR",
    "sg:tags":[
        "packaging",
        "materials-wholesale",
        "material",
        "manufacturer"
    ],
    "wof:name":"Cunningham Tape & Packaging Inc",
    "wof:placetype":"venue"
},
  "geometry": {"coordinates":[-94.140637,36.146893],"type":"Point"}
}