{
  "type": "Feature",
  "properties": {
    "iso:country":"US",
    "sg:address":"101 Country Club Dr",
    "sg:city":"Hot Springs National",
    "sg:classifiers":[
        {
            "category":"Recreation",
            "type":"Entertainment"
        }
    ],
    "sg:phone":"+1 501 623 4981",
    "sg:postcode":"71901",
    "sg:province":"AR",
    "sg:tags":[
        "club",
        "membership",
        "eating",
        "drinking"
    ],
    "wof:name":"Hot Springs Country Club Inc",
    "wof:placetype":"venue"
},
  "geometry": {"coordinates":[-93.02958599999999,34.480767],"type":"Point"}
}