{
  "type": "Feature",
  "properties": {
    "iso:country":"US",
    "sg:address":"201 E Broadway St",
    "sg:city":"Morrilton",
    "sg:classifiers":[
        {
            "category":"Shopping",
            "subcategory":"Pharmacy",
            "type":"Retail Goods"
        }
    ],
    "sg:phone":"+1 501 354 3505",
    "sg:postcode":"72110",
    "sg:province":"AR",
    "sg:tags":[
        "drug",
        "store"
    ],
    "wof:name":"Bill's Pharmacy",
    "wof:placetype":"venue"
},
  "geometry": {"coordinates":[-92.74372099999999,35.152631],"type":"Point"}
}