{
  "type": "Feature",
  "properties": {
    "addr:full":"1313 N Hwy 62 65 Harrison AR 72601",
    "addr:housenumber":"1313;65",
    "addr:postcode":"72601",
    "addr:street":"N Hwy 62;Harrison",
    "iso:country":"US",
    "sg:address":"1313 N Hwy 62 65",
    "sg:city":"Harrison",
    "sg:classifiers":[
        {
            "category":"Cinema",
            "subcategory":"Movie Rental",
            "type":"Entertainment"
        }
    ],
    "sg:phone":"+1 870 743 6442",
    "sg:postcode":"72601",
    "sg:province":"AR",
    "sg:tags":[
        "leasing",
        "video",
        "disc",
        "tape"
    ],
    "sg:website":"www.moviegallery.com",
    "wof:name":"Movie Gallery",
    "wof:placetype":"venue"
},
  "geometry": {"coordinates":[-93.13224599999999,36.261956],"type":"Point"}
}