{
  "type": "Feature",
  "properties": {
    "iso:country":"US",
    "sg:address":"1625 Albert Pike Rd",
    "sg:city":"Hot Springs National Park",
    "sg:classifiers":[
        {
            "category":"Insurance",
            "subcategory":"Hazard Insurance",
            "type":"Services"
        }
    ],
    "sg:phone":"+1 501 624 7183",
    "sg:postcode":"71913",
    "sg:province":"AR",
    "sg:tags":[
        "property",
        "casualty"
    ],
    "wof:name":"Allstate",
    "wof:placetype":"venue"
},
  "geometry": {"coordinates":[-93.091897,34.493511],"type":"Point"}
}