{
  "type": "Feature",
  "properties": {
    "iso:country":"US",
    "sg:address":"364 Military Rd",
    "sg:city":"Marion",
    "sg:classifiers":[
        {
            "category":"Government",
            "subcategory":"Fire Station",
            "type":"Public Place"
        },
        {
            "category":"Government",
            "subcategory":"Office",
            "type":"Public Place"
        }
    ],
    "sg:phone":"+1 870 739 4127",
    "sg:postcode":"72364",
    "sg:province":"AR",
    "sg:tags":[
        "department",
        "township",
        "protection",
        "government-city",
        "village"
    ],
    "sg:website":"http://www.marionarkansas.org",
    "wof:name":"Marion Fire Department",
    "wof:placetype":"venue"
},
  "geometry": {"coordinates":[-90.203765,35.213004],"type":"Point"}
}