{
  "type": "Feature",
  "properties": {
    "iso:country":"US",
    "sg:address":"601 Shamburger Ln",
    "sg:city":"Little Rock",
    "sg:classifiers":[
        {
            "category":"Freight",
            "type":"Transportation"
        }
    ],
    "sg:phone":"+1 501 490 0044",
    "sg:postcode":"72206",
    "sg:province":"AR",
    "sg:tags":[
        "dry",
        "bulk",
        "trucking"
    ],
    "wof:name":"Asphalt Transport Inc",
    "wof:placetype":"venue"
},
  "geometry": {"coordinates":[-92.25620000000001,34.679542],"type":"Point"}
}