{
  "type": "Feature",
  "properties": {
    "addr:full":"2506 W Washington Ave Jonesboro AR 72401",
    "addr:housenumber":"2506",
    "addr:postcode":"72401",
    "addr:street":"W Washington Ave",
    "iso:country":"US",
    "sg:address":"2506 W Washington Ave",
    "sg:city":"Jonesboro",
    "sg:classifiers":[
        {
            "category":"Real Estate",
            "subcategory":"Real Estate Services",
            "type":"Services"
        }
    ],
    "sg:phone":"+1 870 933 7076",
    "sg:postcode":"72401",
    "sg:province":"AR",
    "sg:tags":[
        "management"
    ],
    "wof:name":"Corporate Real Estate Services",
    "wof:placetype":"venue"
},
  "geometry": {"coordinates":[-90.74352399999999,35.838479],"type":"Point"}
}