{
  "type": "Feature",
  "properties": {
    "iso:country":"US",
    "sg:address":"55 Brierwood Dr",
    "sg:city":"Higden",
    "sg:classifiers":[
        {
            "category":"Retail",
            "subcategory":"Repair Shop",
            "type":"Services"
        }
    ],
    "sg:phone":"+1 501 825 6540",
    "sg:postcode":"72067",
    "sg:province":"AR",
    "sg:tags":[
        "appliance"
    ],
    "wof:name":"A-1 Appliance",
    "wof:placetype":"venue"
},
  "geometry": {"coordinates":[-92.206375,35.568951],"type":"Point"}
}