{
  "type": "Feature",
  "properties": {
    "iso:country":"US",
    "sg:address":"10413 Highway 62 E",
    "sg:city":"Flippin",
    "sg:classifiers":[
        {
            "category":"Shopping",
            "subcategory":"Gifts & Souvenirs",
            "type":"Retail Goods"
        },
        {
            "category":"Shopping",
            "subcategory":"Antiques",
            "type":"Retail Goods"
        }
    ],
    "sg:phone":"+1 870 453 4438",
    "sg:postcode":"72634",
    "sg:province":"AR",
    "sg:tags":[
        "shop"
    ],
    "wof:name":"Gift-Tiques",
    "wof:placetype":"venue"
},
  "geometry": {"coordinates":[-92.547745,36.267882],"type":"Point"}
}